; Auto-generated by icon_emit_jvm.c — Tiny-ICON Byrd Box JVM
.bytecode 45.0
.class public rung36_jcon_fncs1
.super java/lang/Object

.field public static icn_failed B
.field public static icn_suspended B
.field public static icn_suspend_id I
.field public static icn_retval_obj Ljava/lang/Object;
.field public static icn_retval J
.field public static icn_retval_str Ljava/lang/String;
.field public static icn_arg_str_0 Ljava/lang/String;
.field public static icn_pv_wf_v Ljava/lang/String;
.field public static icn_gvar_T Ljava/util/HashMap;
.field public static icn_gvar_L Ljava/util/ArrayList;
.field public static icn_gvar_v D
.field public static icn_7_alt_gate I
.field public static icn_pv_q1_F J
.field public static icn_14_alt_gate I
.field public static icn_20_alt_gate I
.field public static icn_26_bang_str Ljava/lang/String;
.field public static icn_26_bang_pos I
.field public static icn_30_alt_gate I
.field public static icn_37_alt_gate I
.field public static icn_43_alt_gate I
.field public static icn_49_bang_str Ljava/lang/String;
.field public static icn_49_bang_pos I
.field public static icn_53_alt_gate I
.field public static icn_61_alt_gate I
.field public static icn_67_alt_gate I
.field public static icn_pv_q1_f J
.field public static icn_75_alt_gate I
.field public static icn_82_alt_gate I
.field public static icn_87_alt_gate I
.field public static icn_pv_q2_f J
.field public static icn_94_alt_gate I
.field public static icn_101_alt_gate I
.field public static icn_108_alt_gate I
.field public static icn_114_alt_gate I
.field public static icn_121_alt_gate I
.field public static icn_128_alt_gate I
.field public static icn_134_alt_gate I
.field public static icn_140_bang_str Ljava/lang/String;
.field public static icn_140_bang_pos I
.field public static icn_pv_q2_F J
.field public static icn_142_lc Ljava/lang/String;
.field public static icn_142_rc Ljava/lang/String;
.field public static icn_145_lc Ljava/lang/String;
.field public static icn_145_rc Ljava/lang/String;
.field public static icn_150_alt_gate I
.field public static icn_157_alt_gate I
.field public static icn_163_alt_gate I
.field public static icn_169_bang_str Ljava/lang/String;
.field public static icn_169_bang_pos I
.field public static icn_171_lc Ljava/lang/String;
.field public static icn_171_rc Ljava/lang/String;
.field public static icn_174_lc Ljava/lang/String;
.field public static icn_174_rc Ljava/lang/String;
.field public static icn_179_alt_gate I
.field public static icn_185_alt_gate I
.field public static icn_pv_q4_T Ljava/util/HashMap;
.field public static icn_pv_q4_T_dflt Ljava/lang/Object;
.field public static icn_pv_q4_L Ljava/util/ArrayList;
.field public static icn_193_bang_list Ljava/util/ArrayList;
.field public static icn_193_bang_idx I
.field public static icn_194_sort_list Ljava/util/ArrayList;
.field public static icn_197_pushval Ljava/lang/Object;
.field public static icn_197_pushlist Ljava/util/ArrayList;
.field public static icn_199_ktbl Ljava/util/HashMap;
.field public static icn_199_karr [Ljava/lang/Object;
.field public static icn_199_kidx I
.field public static icn_199_kinit I
.field public static icn_202_tsa_vl J
.field public static icn_202_tsa_vo Ljava/lang/Object;
.field public static icn_202_tsa_ks Ljava/lang/String;
.field public static icn_204_I J
.field public static icn_204_bound J
.field public static icn_204_e1cur J
.field public static icn_204_e2seen I
.field public static icn_204_e1val J
.field public static icn_204_e2val J
.field public static icn_pv_q5_v D
.field public static icn_214_binop_lc D
.field public static icn_214_binop_rc D
.field public static icn_214_binop_bf I
.field public static icn_pv_q5_i J
.field public static icn_arg_0 J
.field public static icn_225_alt_gate I
.field public static icn_228_relop_lc D
.field public static icn_228_relop_rc D
.field public static icn_233_alt_gate I
.field public static icn_233_alt_val J
.field public static icn_246_I J
.field public static icn_246_bound J
.field public static icn_246_e1cur J
.field public static icn_246_e2seen I
.field public static icn_246_e1val J
.field public static icn_246_e2val J

.method public static main([Ljava/lang/String;)V
    .limit stack 4
    .limit locals 1
    invokestatic rung36_jcon_fncs1/icn_main()V
    return
.end method

.method public static icn_builtin_left(Ljava/lang/String;ILjava/lang/String;)Ljava/lang/String;
    .limit stack 4
    .limit locals 5
    aload_0
    invokevirtual java/lang/String/length()I
    iload_1
    if_icmplt icn_left_pad
    aload_0
    iconst_0
    iload_1
    invokevirtual java/lang/String/substring(II)Ljava/lang/String;
    areturn
icn_left_pad:
    new java/lang/StringBuilder
    dup
    aload_0
    invokespecial java/lang/StringBuilder/<init>(Ljava/lang/String;)V
    astore_3
icn_left_loop:
    aload_3
    invokevirtual java/lang/StringBuilder/length()I
    iload_1
    if_icmpge icn_left_done
    aload_3
    aload_2
    iconst_0
    invokevirtual java/lang/String/charAt(I)C
    invokevirtual java/lang/StringBuilder/append(C)Ljava/lang/StringBuilder;
    pop
    goto icn_left_loop
icn_left_done:
    aload_3
    invokevirtual java/lang/StringBuilder/toString()Ljava/lang/String;
    areturn
.end method

.method public static icn_builtin_right(Ljava/lang/String;ILjava/lang/String;)Ljava/lang/String;
    .limit stack 4
    .limit locals 5
    aload_0
    invokevirtual java/lang/String/length()I
    iload_1
    if_icmplt icn_right_pad
    aload_0
    invokevirtual java/lang/String/length()I
    iload_1
    isub
    aload_0
    swap
    invokevirtual java/lang/String/substring(I)Ljava/lang/String;
    areturn
icn_right_pad:
    new java/lang/StringBuilder
    dup
    invokespecial java/lang/StringBuilder/<init>()V
    astore_3
    iload_1
    aload_0
    invokevirtual java/lang/String/length()I
    isub
    istore 4
    iconst_0
icn_right_loop:
    dup
    iload 4
    if_icmpge icn_right_append
    aload_3
    aload_2
    iconst_0
    invokevirtual java/lang/String/charAt(I)C
    invokevirtual java/lang/StringBuilder/append(C)Ljava/lang/StringBuilder;
    pop
    iconst_1
    iadd
    goto icn_right_loop
icn_right_append:
    pop
    aload_3
    aload_0
    invokevirtual java/lang/StringBuilder/append(Ljava/lang/String;)Ljava/lang/StringBuilder;
    pop
    aload_3
    invokevirtual java/lang/StringBuilder/toString()Ljava/lang/String;
    areturn
.end method

.method public static icn_builtin_center(Ljava/lang/String;ILjava/lang/String;)Ljava/lang/String;
    .limit stack 5
    .limit locals 7
    aload_0
    invokevirtual java/lang/String/length()I
    iload_1
    if_icmplt icn_ctr_pad
    aload_0
    iconst_0
    iload_1
    invokevirtual java/lang/String/substring(II)Ljava/lang/String;
    areturn
icn_ctr_pad:
    iload_1
    aload_0
    invokevirtual java/lang/String/length()I
    isub
    istore_3
    iload_3
    iconst_2
    idiv
    istore 4
    iload_3
    iload 4
    isub
    istore 5
    new java/lang/StringBuilder
    dup
    invokespecial java/lang/StringBuilder/<init>()V
    astore 6
    iconst_0
icn_ctr_lloop:
    dup
    iload 4
    if_icmpge icn_ctr_mid
    aload 6
    aload_2
    iconst_0
    invokevirtual java/lang/String/charAt(I)C
    invokevirtual java/lang/StringBuilder/append(C)Ljava/lang/StringBuilder;
    pop
    iconst_1
    iadd
    goto icn_ctr_lloop
icn_ctr_mid:
    pop
    aload 6
    aload_0
    invokevirtual java/lang/StringBuilder/append(Ljava/lang/String;)Ljava/lang/StringBuilder;
    pop
    iconst_0
icn_ctr_rloop:
    dup
    iload 5
    if_icmpge icn_ctr_done
    aload 6
    aload_2
    iconst_0
    invokevirtual java/lang/String/charAt(I)C
    invokevirtual java/lang/StringBuilder/append(C)Ljava/lang/StringBuilder;
    pop
    iconst_1
    iadd
    goto icn_ctr_rloop
icn_ctr_done:
    pop
    aload 6
    invokevirtual java/lang/StringBuilder/toString()Ljava/lang/String;
    areturn
.end method

.method public static icn_builtin_trim(Ljava/lang/String;Ljava/lang/String;)Ljava/lang/String;
    .limit stack 4
    .limit locals 3
    aload_0
    invokevirtual java/lang/String/length()I
    istore_2
icn_trim_loop:
    iload_2
    ifle icn_trim_done
    aload_1
    aload_0
    iload_2
    iconst_1
    isub
    invokevirtual java/lang/String/charAt(I)C
    invokevirtual java/lang/String/indexOf(I)I
    iflt icn_trim_done
    iinc 2 -1
    goto icn_trim_loop
icn_trim_done:
    aload_0
    iconst_0
    iload_2
    invokevirtual java/lang/String/substring(II)Ljava/lang/String;
    areturn
.end method

.method public static icn_builtin_map(Ljava/lang/String;Ljava/lang/String;Ljava/lang/String;)Ljava/lang/String;
    .limit stack 5
    .limit locals 7
    new java/lang/StringBuilder
    dup
    invokespecial java/lang/StringBuilder/<init>()V
    astore_3
    iconst_0
    istore 4
icn_map_loop:
    iload 4
    aload_0
    invokevirtual java/lang/String/length()I
    if_icmpge icn_map_done
    aload_0
    iload 4
    invokevirtual java/lang/String/charAt(I)C
    istore 5
    aload_1
    iload 5
    invokevirtual java/lang/String/indexOf(I)I
    istore 6
    iload 6
    iflt icn_map_notfound
    iload 6
    aload_2
    invokevirtual java/lang/String/length()I
    if_icmpge icn_map_notfound
    aload_3
    aload_2
    iload 6
    invokevirtual java/lang/String/charAt(I)C
    invokevirtual java/lang/StringBuilder/append(C)Ljava/lang/StringBuilder;
    pop
    goto icn_map_next
icn_map_notfound:
    aload_3
    iload 5
    invokevirtual java/lang/StringBuilder/append(C)Ljava/lang/StringBuilder;
    pop
icn_map_next:
    iinc 4 1
    goto icn_map_loop
icn_map_done:
    aload_3
    invokevirtual java/lang/StringBuilder/toString()Ljava/lang/String;
    areturn
.end method

.method public static icn_builtin_parse_long(Ljava/lang/String;)J
    .limit stack 4
    .limit locals 4
    .catch java/lang/Exception from icn_plong_L0 to icn_plong_L1 using icn_plong_catch
icn_plong_L0:
    aload_0
    invokevirtual java/lang/String/trim()Ljava/lang/String;
    astore_1
    aload_1
    ldc "r"
    invokevirtual java/lang/String/contains(Ljava/lang/CharSequence;)Z
    ifeq icn_plong_plain
    aload_1
    ldc "r"
    iconst_2
    invokevirtual java/lang/String/split(Ljava/lang/String;I)[Ljava/lang/String;
    astore_2
    aload_2
    iconst_0
    aaload
    invokestatic java/lang/Integer/parseInt(Ljava/lang/String;)I
    istore_3
    aload_2
    iconst_1
    aaload
    iload_3
    invokestatic java/lang/Long/parseLong(Ljava/lang/String;I)J
    goto icn_plong_L1
icn_plong_plain:
    aload_1
    invokestatic java/lang/Long/parseLong(Ljava/lang/String;)J
icn_plong_L1:
    lreturn
icn_plong_catch:
    pop
    ldc2_w -9223372036854775808
    lreturn
.end method

.method public static icn_builtin_numeric(Ljava/lang/String;)J
    .limit stack 2
    .limit locals 2
    aload_0
    invokestatic rung36_jcon_fncs1/icn_builtin_parse_long(Ljava/lang/String;)J
    lreturn
.end method

.method public static icn_builtin_sort(Ljava/util/ArrayList;)Ljava/util/ArrayList;
    .limit stack 6
    .limit locals 8
    new java/util/ArrayList
    dup
    aload_0
    invokespecial java/util/ArrayList/<init>(Ljava/util/Collection;)V
    astore_1
    iconst_1
    istore_2
icn_sort_outer:
    aload_1
    invokevirtual java/util/ArrayList/size()I
    iload_2
    if_icmple icn_sort_done
    aload_1
    iload_2
    invokevirtual java/util/ArrayList/get(I)Ljava/lang/Object;
    checkcast java/lang/Long
    invokevirtual java/lang/Long/longValue()J
    lstore 4
    iload_2
    iconst_1
    isub
    istore_3
icn_sort_inner:
    iload_3
    iflt icn_sort_insert
    aload_1
    iload_3
    invokevirtual java/util/ArrayList/get(I)Ljava/lang/Object;
    checkcast java/lang/Long
    invokevirtual java/lang/Long/longValue()J
    lload 4
    lcmp
    ifle icn_sort_insert
    aload_1
    iload_3
    iconst_1
    iadd
    aload_1
    iload_3
    invokevirtual java/util/ArrayList/get(I)Ljava/lang/Object;
    invokevirtual java/util/ArrayList/set(ILjava/lang/Object;)Ljava/lang/Object;
    pop
    iinc 3 -1
    goto icn_sort_inner
icn_sort_insert:
    aload_1
    iload_3
    iconst_1
    iadd
    lload 4
    invokestatic java/lang/Long/valueOf(J)Ljava/lang/Long;
    invokevirtual java/util/ArrayList/set(ILjava/lang/Object;)Ljava/lang/Object;
    pop
    iinc 2 1
    goto icn_sort_outer
icn_sort_done:
    aload_1
    areturn
.end method

.method public static icn_builtin_sortf(Ljava/util/ArrayList;I)Ljava/util/ArrayList;
    .limit stack 8
    .limit locals 10
    new java/util/ArrayList
    dup
    aload_0
    invokespecial java/util/ArrayList/<init>(Ljava/util/Collection;)V
    astore_2
    iconst_1
    istore_3
icn_sortf_outer:
    aload_2
    invokevirtual java/util/ArrayList/size()I
    iload_3
    if_icmple icn_sortf_done
    aload_2
    iload_3
    invokevirtual java/util/ArrayList/get(I)Ljava/lang/Object;
    astore 5
    iload_3
    iconst_1
    isub
    istore 4
icn_sortf_inner:
    iload 4
    iflt icn_sortf_insert
    aload_2
    iload 4
    invokevirtual java/util/ArrayList/get(I)Ljava/lang/Object;
    astore 6
    aload 6
    invokevirtual java/lang/Object/getClass()Ljava/lang/Class;
    invokevirtual java/lang/Class/getDeclaredFields()[Ljava/lang/reflect/Field;
    iload_1
    iconst_1
    isub
    aaload
    aload 6
    invokevirtual java/lang/reflect/Field/get(Ljava/lang/Object;)Ljava/lang/Object;
    astore 7
    aload 5
    invokevirtual java/lang/Object/getClass()Ljava/lang/Class;
    invokevirtual java/lang/Class/getDeclaredFields()[Ljava/lang/reflect/Field;
    iload_1
    iconst_1
    isub
    aaload
    aload 5
    invokevirtual java/lang/reflect/Field/get(Ljava/lang/Object;)Ljava/lang/Object;
    astore 8
    aload 7
    checkcast java/lang/Long
    aload 8
    checkcast java/lang/Long
    invokevirtual java/lang/Long/compareTo(Ljava/lang/Long;)I
    ifle icn_sortf_insert
    aload_2
    iload 4
    iconst_1
    iadd
    aload_2
    iload 4
    invokevirtual java/util/ArrayList/get(I)Ljava/lang/Object;
    invokevirtual java/util/ArrayList/set(ILjava/lang/Object;)Ljava/lang/Object;
    pop
    iinc 4 -1
    goto icn_sortf_inner
icn_sortf_insert:
    aload_2
    iload 4
    iconst_1
    iadd
    aload 5
    invokevirtual java/util/ArrayList/set(ILjava/lang/Object;)Ljava/lang/Object;
    pop
    iinc 3 1
    goto icn_sortf_outer
icn_sortf_done:
    aload_2
    areturn
.end method

.method public static icn_main()V
    .limit stack 16
    .limit locals 172
    lconst_0
    lstore 0
    lconst_0
    lstore 2
    lconst_0
    lstore 4
    lconst_0
    lstore 6
    lconst_0
    lstore 8
    lconst_0
    lstore 10
    lconst_0
    lstore 12
    lconst_0
    lstore 14
    lconst_0
    lstore 16
    lconst_0
    lstore 18
    lconst_0
    lstore 20
    lconst_0
    lstore 22
    lconst_0
    lstore 24
    lconst_0
    lstore 26
    lconst_0
    lstore 28
    lconst_0
    lstore 30
    lconst_0
    lstore 32
    lconst_0
    lstore 34
    lconst_0
    lstore 36
    lconst_0
    lstore 38
    lconst_0
    lstore 40
    lconst_0
    lstore 42
    lconst_0
    lstore 44
    lconst_0
    lstore 46
    lconst_0
    lstore 48
    lconst_0
    lstore 50
    lconst_0
    lstore 52
    lconst_0
    lstore 54
    lconst_0
    lstore 56
    lconst_0
    lstore 58
    lconst_0
    lstore 60
    lconst_0
    lstore 62
    iconst_0
    istore 84
    iconst_0
    istore 85
    iconst_0
    istore 86
    iconst_0
    istore 87
    aconst_null
    astore 148
    aconst_null
    astore 149
    aconst_null
    astore 150
    aconst_null
    astore 151
    goto icn_4_α
icn_0_α:
    goto icn_0_docall
icn_0_β:
    goto icn_main_done
icn_0_docall:
    invokestatic rung36_jcon_fncs1/icn_q5()V
    getstatic rung36_jcon_fncs1/icn_failed B
    ifne icn_0_after_call
    getstatic rung36_jcon_fncs1/icn_retval J
    goto icn_main_s4_sdrain
icn_0_after_call:
    goto icn_main_done
icn_main_s4_sdrain:
    pop2
    goto icn_main_done
icn_1_α:
    goto icn_1_docall
icn_1_β:
    goto icn_0_α
icn_1_docall:
    invokestatic rung36_jcon_fncs1/icn_q4()V
    getstatic rung36_jcon_fncs1/icn_failed B
    ifne icn_1_after_call
    getstatic rung36_jcon_fncs1/icn_retval J
    goto icn_main_s3_sdrain
icn_1_after_call:
    goto icn_0_α
icn_main_s3_sdrain:
    pop2
    goto icn_0_α
icn_2_α:
    goto icn_2_docall
icn_2_β:
    goto icn_1_α
icn_2_docall:
    invokestatic rung36_jcon_fncs1/icn_q3()V
    getstatic rung36_jcon_fncs1/icn_failed B
    ifne icn_2_after_call
    getstatic rung36_jcon_fncs1/icn_retval J
    goto icn_main_s2_sdrain
icn_2_after_call:
    goto icn_1_α
icn_main_s2_sdrain:
    pop2
    goto icn_1_α
icn_3_α:
    goto icn_3_docall
icn_3_β:
    goto icn_2_α
icn_3_docall:
    invokestatic rung36_jcon_fncs1/icn_q2()V
    getstatic rung36_jcon_fncs1/icn_failed B
    ifne icn_3_after_call
    getstatic rung36_jcon_fncs1/icn_retval J
    goto icn_main_s1_sdrain
icn_3_after_call:
    goto icn_2_α
icn_main_s1_sdrain:
    pop2
    goto icn_2_α
icn_4_α:
    goto icn_4_docall
icn_4_β:
    goto icn_3_α
icn_4_docall:
    invokestatic rung36_jcon_fncs1/icn_q1()V
    getstatic rung36_jcon_fncs1/icn_failed B
    ifne icn_4_after_call
    getstatic rung36_jcon_fncs1/icn_retval J
    goto icn_main_s0_sdrain
icn_4_after_call:
    goto icn_3_α
icn_main_s0_sdrain:
    pop2
    goto icn_3_α
icn_main_done:
    return
.end method

.method public static icn_q1()V
    .limit stack 16
    .limit locals 253
    lconst_0
    lstore 0
    lconst_0
    lstore 2
    lconst_0
    lstore 4
    lconst_0
    lstore 6
    lconst_0
    lstore 8
    lconst_0
    lstore 10
    lconst_0
    lstore 12
    lconst_0
    lstore 14
    lconst_0
    lstore 16
    lconst_0
    lstore 18
    lconst_0
    lstore 20
    lconst_0
    lstore 22
    lconst_0
    lstore 24
    lconst_0
    lstore 26
    lconst_0
    lstore 28
    lconst_0
    lstore 30
    lconst_0
    lstore 32
    lconst_0
    lstore 34
    lconst_0
    lstore 36
    lconst_0
    lstore 38
    lconst_0
    lstore 40
    lconst_0
    lstore 42
    lconst_0
    lstore 44
    lconst_0
    lstore 46
    lconst_0
    lstore 48
    lconst_0
    lstore 50
    lconst_0
    lstore 52
    lconst_0
    lstore 54
    lconst_0
    lstore 56
    lconst_0
    lstore 58
    lconst_0
    lstore 60
    lconst_0
    lstore 62
    iconst_0
    istore 84
    iconst_0
    istore 85
    iconst_0
    istore 86
    iconst_0
    istore 87
    aconst_null
    astore 148
    aconst_null
    astore 149
    aconst_null
    astore 150
    aconst_null
    astore 151
    aconst_null
    astore 152
    aconst_null
    astore 153
    aconst_null
    astore 154
    aconst_null
    astore 155
    aconst_null
    astore 156
    aconst_null
    astore 157
    aconst_null
    astore 158
    aconst_null
    astore 159
    aconst_null
    astore 160
    aconst_null
    astore 161
    aconst_null
    astore 162
    aconst_null
    astore 163
    aconst_null
    astore 164
    aconst_null
    astore 165
    aconst_null
    astore 166
    aconst_null
    astore 167
    aconst_null
    astore 168
    aconst_null
    astore 169
    aconst_null
    astore 170
    aconst_null
    astore 171
    aconst_null
    astore 172
    aconst_null
    astore 173
    aconst_null
    astore 174
    aconst_null
    astore 175
    aconst_null
    astore 176
    aconst_null
    astore 177
    aconst_null
    astore 178
    aconst_null
    astore 179
    aconst_null
    astore 180
    aconst_null
    astore 181
    aconst_null
    astore 182
    aconst_null
    astore 183
    aconst_null
    astore 184
    aconst_null
    astore 185
    aconst_null
    astore 186
    aconst_null
    astore 187
    aconst_null
    astore 188
    aconst_null
    astore 189
    aconst_null
    astore 190
    aconst_null
    astore 191
    aconst_null
    astore 192
    aconst_null
    astore 193
    aconst_null
    astore 194
    aconst_null
    astore 195
    aconst_null
    astore 196
    aconst_null
    astore 197
    aconst_null
    astore 198
    goto icn_80_α
;  STR
icn_6_α:
    ldc "F := open(\"fncs1.dat\") ----> "
    goto icn_5_waft_0
icn_6_β:
    goto icn_q1_done
;  STR
icn_8_α:
    ldc "none"
    goto icn_7_alt_g1
icn_8_β:
    goto icn_q1_done
icn_11_α:
    goto icn_8_α
icn_11_β:
    goto icn_8_α
icn_10_α:
    goto icn_11_α
icn_10_β:
    goto icn_11_β
icn_10_store:
    putstatic rung36_jcon_fncs1/icn_pv_q1_F J
    getstatic rung36_jcon_fncs1/icn_pv_q1_F J
    goto icn_9_image_after
icn_9_α:
    goto icn_10_α
icn_9_β:
    goto icn_10_β
icn_9_image_after:
    invokestatic java/lang/Long/toString(J)Ljava/lang/String;
    goto icn_7_alt_g0
icn_7_alt_g0:
    astore 148
    sipush 1
    putstatic rung36_jcon_fncs1/icn_7_alt_gate I
    aload 148
    goto icn_5_waft_1
icn_7_alt_g1:
    astore 149
    sipush 2
    putstatic rung36_jcon_fncs1/icn_7_alt_gate I
    aload 149
    goto icn_5_waft_1
icn_7_α:
    iconst_0
    putstatic rung36_jcon_fncs1/icn_7_alt_gate I
    goto icn_9_α
icn_7_β:
    getstatic rung36_jcon_fncs1/icn_7_alt_gate I
    tableswitch 1 2
        icn_9_β
        icn_8_β
        default: icn_q1_done
icn_5_α:
    goto icn_6_α
icn_5_β:
    goto icn_6_β
    goto icn_5_wentry
icn_5_waft_0:
    astore 150
    getstatic java/lang/System/out Ljava/io/PrintStream;
    aload 150
    invokevirtual java/io/PrintStream/print(Ljava/lang/String;)V
    goto icn_7_α
icn_5_waft_1:
    astore 151
    getstatic java/lang/System/out Ljava/io/PrintStream;
    aload 151
    invokevirtual java/io/PrintStream/print(Ljava/lang/String;)V
    getstatic java/lang/System/out Ljava/io/PrintStream;
    ldc ""
    invokevirtual java/io/PrintStream/println(Ljava/lang/String;)V
    aload 151
    goto icn_q1_s11_sdrain
icn_5_wentry:
    goto icn_6_α
icn_q1_s11_sdrain:
    pop
    goto icn_q1_done
;  STR
icn_13_α:
    ldc "close(F) ----> "
    goto icn_12_waft_0
icn_13_β:
    goto icn_5_α
;  STR
icn_15_α:
    ldc "none"
    goto icn_14_alt_g1
icn_15_β:
    goto icn_5_α
icn_17_α:
    goto icn_15_α
icn_17_β:
    goto icn_15_α
icn_16_α:
    goto icn_17_α
icn_16_β:
    goto icn_17_β
icn_16_image_after:
    invokestatic java/lang/Long/toString(J)Ljava/lang/String;
    goto icn_14_alt_g0
icn_14_alt_g0:
    astore 152
    sipush 1
    putstatic rung36_jcon_fncs1/icn_14_alt_gate I
    aload 152
    goto icn_12_waft_1
icn_14_alt_g1:
    astore 153
    sipush 2
    putstatic rung36_jcon_fncs1/icn_14_alt_gate I
    aload 153
    goto icn_12_waft_1
icn_14_α:
    iconst_0
    putstatic rung36_jcon_fncs1/icn_14_alt_gate I
    goto icn_16_α
icn_14_β:
    getstatic rung36_jcon_fncs1/icn_14_alt_gate I
    tableswitch 1 2
        icn_16_β
        icn_15_β
        default: icn_5_α
icn_12_α:
    goto icn_13_α
icn_12_β:
    goto icn_13_β
    goto icn_12_wentry
icn_12_waft_0:
    astore 154
    getstatic java/lang/System/out Ljava/io/PrintStream;
    aload 154
    invokevirtual java/io/PrintStream/print(Ljava/lang/String;)V
    goto icn_14_α
icn_12_waft_1:
    astore 155
    getstatic java/lang/System/out Ljava/io/PrintStream;
    aload 155
    invokevirtual java/io/PrintStream/print(Ljava/lang/String;)V
    getstatic java/lang/System/out Ljava/io/PrintStream;
    ldc ""
    invokevirtual java/io/PrintStream/println(Ljava/lang/String;)V
    aload 155
    goto icn_q1_s10_sdrain
icn_12_wentry:
    goto icn_13_α
icn_q1_s10_sdrain:
    pop
    goto icn_5_α
;  STR
icn_19_α:
    ldc "every write(map(!F)) ----> "
    goto icn_18_waft_0
icn_19_β:
    goto icn_12_α
;  STR
icn_21_α:
    ldc "none"
    goto icn_20_alt_g1
icn_21_β:
    goto icn_12_α
;  VAR
icn_27_α:
    getstatic rung36_jcon_fncs1/icn_pv_q1_F J
    goto icn_26_bang_adv
icn_27_β:
    goto icn_21_α
icn_26_α:
    goto icn_27_α
icn_26_β:
    goto icn_26_bang_chk
icn_26_bang_adv:
    putstatic rung36_jcon_fncs1/icn_26_bang_str Ljava/lang/String;
    iconst_0
    putstatic rung36_jcon_fncs1/icn_26_bang_pos I
icn_26_bang_chk:
    getstatic rung36_jcon_fncs1/icn_26_bang_str Ljava/lang/String;
    invokevirtual java/lang/String/length()I
    getstatic rung36_jcon_fncs1/icn_26_bang_pos I
    if_icmple icn_21_α
    getstatic rung36_jcon_fncs1/icn_26_bang_str Ljava/lang/String;
    getstatic rung36_jcon_fncs1/icn_26_bang_pos I
    getstatic rung36_jcon_fncs1/icn_26_bang_pos I
    iconst_1
    iadd
    invokevirtual java/lang/String/substring(II)Ljava/lang/String;
    getstatic rung36_jcon_fncs1/icn_26_bang_pos I
    iconst_1
    iadd
    putstatic rung36_jcon_fncs1/icn_26_bang_pos I
    goto icn_25_map1_after
icn_25_α:
    goto icn_26_α
icn_25_β:
    goto icn_26_β
icn_25_map1_after:
    ldc "ABCDEFGHIJKLMNOPQRSTUVWXYZ"
    ldc "abcdefghijklmnopqrstuvwxyz"
    invokestatic rung36_jcon_fncs1/icn_builtin_map(Ljava/lang/String;Ljava/lang/String;Ljava/lang/String;)Ljava/lang/String;
    goto icn_24_waft_0
icn_24_α:
    goto icn_25_α
icn_24_β:
    goto icn_25_β
    goto icn_24_wentry
icn_24_waft_0:
    astore 156
    getstatic java/lang/System/out Ljava/io/PrintStream;
    aload 156
    invokevirtual java/io/PrintStream/print(Ljava/lang/String;)V
    getstatic java/lang/System/out Ljava/io/PrintStream;
    ldc ""
    invokevirtual java/io/PrintStream/println(Ljava/lang/String;)V
    aload 156
    goto icn_23_gdrain
icn_24_wentry:
    goto icn_25_α
icn_23_gdrain:
    pop
icn_23_pump:
    goto icn_24_β
icn_23_α:
    goto icn_24_α
icn_23_β:
    goto icn_21_α
icn_22_α:
    goto icn_23_α
icn_22_β:
    goto icn_23_β
icn_22_image_after:
    invokestatic java/lang/Long/toString(J)Ljava/lang/String;
    goto icn_20_alt_g0
icn_20_alt_g0:
    astore 157
    sipush 1
    putstatic rung36_jcon_fncs1/icn_20_alt_gate I
    aload 157
    goto icn_18_waft_1
icn_20_alt_g1:
    astore 158
    sipush 2
    putstatic rung36_jcon_fncs1/icn_20_alt_gate I
    aload 158
    goto icn_18_waft_1
icn_20_α:
    iconst_0
    putstatic rung36_jcon_fncs1/icn_20_alt_gate I
    goto icn_22_α
icn_20_β:
    getstatic rung36_jcon_fncs1/icn_20_alt_gate I
    tableswitch 1 2
        icn_22_β
        icn_21_β
        default: icn_12_α
icn_18_α:
    goto icn_19_α
icn_18_β:
    goto icn_19_β
    goto icn_18_wentry
icn_18_waft_0:
    astore 159
    getstatic java/lang/System/out Ljava/io/PrintStream;
    aload 159
    invokevirtual java/io/PrintStream/print(Ljava/lang/String;)V
    goto icn_20_α
icn_18_waft_1:
    astore 160
    getstatic java/lang/System/out Ljava/io/PrintStream;
    aload 160
    invokevirtual java/io/PrintStream/print(Ljava/lang/String;)V
    getstatic java/lang/System/out Ljava/io/PrintStream;
    ldc ""
    invokevirtual java/io/PrintStream/println(Ljava/lang/String;)V
    aload 160
    goto icn_q1_s9_sdrain
icn_18_wentry:
    goto icn_19_α
icn_q1_s9_sdrain:
    pop
    goto icn_12_α
;  STR
icn_29_α:
    ldc "F := open(\"fncs1.dat\") ----> "
    goto icn_28_waft_0
icn_29_β:
    goto icn_18_α
;  STR
icn_31_α:
    ldc "none"
    goto icn_30_alt_g1
icn_31_β:
    goto icn_18_α
icn_34_α:
    goto icn_31_α
icn_34_β:
    goto icn_31_α
icn_33_α:
    goto icn_34_α
icn_33_β:
    goto icn_34_β
icn_33_store:
    putstatic rung36_jcon_fncs1/icn_pv_q1_F J
    getstatic rung36_jcon_fncs1/icn_pv_q1_F J
    goto icn_32_image_after
icn_32_α:
    goto icn_33_α
icn_32_β:
    goto icn_33_β
icn_32_image_after:
    invokestatic java/lang/Long/toString(J)Ljava/lang/String;
    goto icn_30_alt_g0
icn_30_alt_g0:
    astore 161
    sipush 1
    putstatic rung36_jcon_fncs1/icn_30_alt_gate I
    aload 161
    goto icn_28_waft_1
icn_30_alt_g1:
    astore 162
    sipush 2
    putstatic rung36_jcon_fncs1/icn_30_alt_gate I
    aload 162
    goto icn_28_waft_1
icn_30_α:
    iconst_0
    putstatic rung36_jcon_fncs1/icn_30_alt_gate I
    goto icn_32_α
icn_30_β:
    getstatic rung36_jcon_fncs1/icn_30_alt_gate I
    tableswitch 1 2
        icn_32_β
        icn_31_β
        default: icn_18_α
icn_28_α:
    goto icn_29_α
icn_28_β:
    goto icn_29_β
    goto icn_28_wentry
icn_28_waft_0:
    astore 163
    getstatic java/lang/System/out Ljava/io/PrintStream;
    aload 163
    invokevirtual java/io/PrintStream/print(Ljava/lang/String;)V
    goto icn_30_α
icn_28_waft_1:
    astore 164
    getstatic java/lang/System/out Ljava/io/PrintStream;
    aload 164
    invokevirtual java/io/PrintStream/print(Ljava/lang/String;)V
    getstatic java/lang/System/out Ljava/io/PrintStream;
    ldc ""
    invokevirtual java/io/PrintStream/println(Ljava/lang/String;)V
    aload 164
    goto icn_q1_s8_sdrain
icn_28_wentry:
    goto icn_29_α
icn_q1_s8_sdrain:
    pop
    goto icn_18_α
;  STR
icn_36_α:
    ldc "close(F) ----> "
    goto icn_35_waft_0
icn_36_β:
    goto icn_28_α
;  STR
icn_38_α:
    ldc "none"
    goto icn_37_alt_g1
icn_38_β:
    goto icn_28_α
icn_40_α:
    goto icn_38_α
icn_40_β:
    goto icn_38_α
icn_39_α:
    goto icn_40_α
icn_39_β:
    goto icn_40_β
icn_39_image_after:
    invokestatic java/lang/Long/toString(J)Ljava/lang/String;
    goto icn_37_alt_g0
icn_37_alt_g0:
    astore 165
    sipush 1
    putstatic rung36_jcon_fncs1/icn_37_alt_gate I
    aload 165
    goto icn_35_waft_1
icn_37_alt_g1:
    astore 166
    sipush 2
    putstatic rung36_jcon_fncs1/icn_37_alt_gate I
    aload 166
    goto icn_35_waft_1
icn_37_α:
    iconst_0
    putstatic rung36_jcon_fncs1/icn_37_alt_gate I
    goto icn_39_α
icn_37_β:
    getstatic rung36_jcon_fncs1/icn_37_alt_gate I
    tableswitch 1 2
        icn_39_β
        icn_38_β
        default: icn_28_α
icn_35_α:
    goto icn_36_α
icn_35_β:
    goto icn_36_β
    goto icn_35_wentry
icn_35_waft_0:
    astore 167
    getstatic java/lang/System/out Ljava/io/PrintStream;
    aload 167
    invokevirtual java/io/PrintStream/print(Ljava/lang/String;)V
    goto icn_37_α
icn_35_waft_1:
    astore 168
    getstatic java/lang/System/out Ljava/io/PrintStream;
    aload 168
    invokevirtual java/io/PrintStream/print(Ljava/lang/String;)V
    getstatic java/lang/System/out Ljava/io/PrintStream;
    ldc ""
    invokevirtual java/io/PrintStream/println(Ljava/lang/String;)V
    aload 168
    goto icn_q1_s7_sdrain
icn_35_wentry:
    goto icn_36_α
icn_q1_s7_sdrain:
    pop
    goto icn_28_α
;  STR
icn_42_α:
    ldc "every write(reverse(!F)) ----> "
    goto icn_41_waft_0
icn_42_β:
    goto icn_35_α
;  STR
icn_44_α:
    ldc "none"
    goto icn_43_alt_g1
icn_44_β:
    goto icn_35_α
;  VAR
icn_50_α:
    getstatic rung36_jcon_fncs1/icn_pv_q1_F J
    goto icn_49_bang_adv
icn_50_β:
    goto icn_44_α
icn_49_α:
    goto icn_50_α
icn_49_β:
    goto icn_49_bang_chk
icn_49_bang_adv:
    putstatic rung36_jcon_fncs1/icn_49_bang_str Ljava/lang/String;
    iconst_0
    putstatic rung36_jcon_fncs1/icn_49_bang_pos I
icn_49_bang_chk:
    getstatic rung36_jcon_fncs1/icn_49_bang_str Ljava/lang/String;
    invokevirtual java/lang/String/length()I
    getstatic rung36_jcon_fncs1/icn_49_bang_pos I
    if_icmple icn_44_α
    getstatic rung36_jcon_fncs1/icn_49_bang_str Ljava/lang/String;
    getstatic rung36_jcon_fncs1/icn_49_bang_pos I
    getstatic rung36_jcon_fncs1/icn_49_bang_pos I
    iconst_1
    iadd
    invokevirtual java/lang/String/substring(II)Ljava/lang/String;
    getstatic rung36_jcon_fncs1/icn_49_bang_pos I
    iconst_1
    iadd
    putstatic rung36_jcon_fncs1/icn_49_bang_pos I
    goto icn_48_rev_after
icn_48_α:
    goto icn_49_α
icn_48_β:
    goto icn_49_β
icn_48_rev_after:
    new java/lang/StringBuilder
    dup_x1
    swap
    invokespecial java/lang/StringBuilder/<init>(Ljava/lang/String;)V
    invokevirtual java/lang/StringBuilder/reverse()Ljava/lang/StringBuilder;
    invokevirtual java/lang/StringBuilder/toString()Ljava/lang/String;
    goto icn_47_waft_0
icn_47_α:
    goto icn_48_α
icn_47_β:
    goto icn_48_β
    goto icn_47_wentry
icn_47_waft_0:
    astore 169
    getstatic java/lang/System/out Ljava/io/PrintStream;
    aload 169
    invokevirtual java/io/PrintStream/print(Ljava/lang/String;)V
    getstatic java/lang/System/out Ljava/io/PrintStream;
    ldc ""
    invokevirtual java/io/PrintStream/println(Ljava/lang/String;)V
    aload 169
    goto icn_46_gdrain
icn_47_wentry:
    goto icn_48_α
icn_46_gdrain:
    pop
icn_46_pump:
    goto icn_47_β
icn_46_α:
    goto icn_47_α
icn_46_β:
    goto icn_44_α
icn_45_α:
    goto icn_46_α
icn_45_β:
    goto icn_46_β
icn_45_image_after:
    invokestatic java/lang/Long/toString(J)Ljava/lang/String;
    goto icn_43_alt_g0
icn_43_alt_g0:
    astore 170
    sipush 1
    putstatic rung36_jcon_fncs1/icn_43_alt_gate I
    aload 170
    goto icn_41_waft_1
icn_43_alt_g1:
    astore 171
    sipush 2
    putstatic rung36_jcon_fncs1/icn_43_alt_gate I
    aload 171
    goto icn_41_waft_1
icn_43_α:
    iconst_0
    putstatic rung36_jcon_fncs1/icn_43_alt_gate I
    goto icn_45_α
icn_43_β:
    getstatic rung36_jcon_fncs1/icn_43_alt_gate I
    tableswitch 1 2
        icn_45_β
        icn_44_β
        default: icn_35_α
icn_41_α:
    goto icn_42_α
icn_41_β:
    goto icn_42_β
    goto icn_41_wentry
icn_41_waft_0:
    astore 172
    getstatic java/lang/System/out Ljava/io/PrintStream;
    aload 172
    invokevirtual java/io/PrintStream/print(Ljava/lang/String;)V
    goto icn_43_α
icn_41_waft_1:
    astore 173
    getstatic java/lang/System/out Ljava/io/PrintStream;
    aload 173
    invokevirtual java/io/PrintStream/print(Ljava/lang/String;)V
    getstatic java/lang/System/out Ljava/io/PrintStream;
    ldc ""
    invokevirtual java/io/PrintStream/println(Ljava/lang/String;)V
    aload 173
    goto icn_q1_s6_sdrain
icn_41_wentry:
    goto icn_42_α
icn_q1_s6_sdrain:
    pop
    goto icn_35_α
;  STR
icn_52_α:
    ldc "F := open(\"fncs1.dat\") ----> "
    goto icn_51_waft_0
icn_52_β:
    goto icn_41_α
;  STR
icn_54_α:
    ldc "none"
    goto icn_53_alt_g1
icn_54_β:
    goto icn_41_α
icn_57_α:
    goto icn_54_α
icn_57_β:
    goto icn_54_α
icn_56_α:
    goto icn_57_α
icn_56_β:
    goto icn_57_β
icn_56_store:
    putstatic rung36_jcon_fncs1/icn_pv_q1_F J
    getstatic rung36_jcon_fncs1/icn_pv_q1_F J
    goto icn_55_image_after
icn_55_α:
    goto icn_56_α
icn_55_β:
    goto icn_56_β
icn_55_image_after:
    invokestatic java/lang/Long/toString(J)Ljava/lang/String;
    goto icn_53_alt_g0
icn_53_alt_g0:
    astore 174
    sipush 1
    putstatic rung36_jcon_fncs1/icn_53_alt_gate I
    aload 174
    goto icn_51_waft_1
icn_53_alt_g1:
    astore 175
    sipush 2
    putstatic rung36_jcon_fncs1/icn_53_alt_gate I
    aload 175
    goto icn_51_waft_1
icn_53_α:
    iconst_0
    putstatic rung36_jcon_fncs1/icn_53_alt_gate I
    goto icn_55_α
icn_53_β:
    getstatic rung36_jcon_fncs1/icn_53_alt_gate I
    tableswitch 1 2
        icn_55_β
        icn_54_β
        default: icn_41_α
icn_51_α:
    goto icn_52_α
icn_51_β:
    goto icn_52_β
    goto icn_51_wentry
icn_51_waft_0:
    astore 176
    getstatic java/lang/System/out Ljava/io/PrintStream;
    aload 176
    invokevirtual java/io/PrintStream/print(Ljava/lang/String;)V
    goto icn_53_α
icn_51_waft_1:
    astore 177
    getstatic java/lang/System/out Ljava/io/PrintStream;
    aload 177
    invokevirtual java/io/PrintStream/print(Ljava/lang/String;)V
    getstatic java/lang/System/out Ljava/io/PrintStream;
    ldc ""
    invokevirtual java/io/PrintStream/println(Ljava/lang/String;)V
    aload 177
    goto icn_q1_s5_sdrain
icn_51_wentry:
    goto icn_52_α
icn_q1_s5_sdrain:
    pop
    goto icn_41_α
icn_58_α:
    goto icn_51_α
icn_58_β:
    goto icn_51_α
icn_q1_s4_sdrain:
    pop2
    goto icn_51_α
;  STR
icn_60_α:
    ldc "close(f) ----> "
    goto icn_59_waft_0
icn_60_β:
    goto icn_58_α
;  STR
icn_62_α:
    ldc "none"
    goto icn_61_alt_g1
icn_62_β:
    goto icn_58_α
icn_64_α:
    goto icn_62_α
icn_64_β:
    goto icn_62_α
icn_63_α:
    goto icn_64_α
icn_63_β:
    goto icn_64_β
icn_63_image_after:
    invokestatic java/lang/Long/toString(J)Ljava/lang/String;
    goto icn_61_alt_g0
icn_61_alt_g0:
    astore 178
    sipush 1
    putstatic rung36_jcon_fncs1/icn_61_alt_gate I
    aload 178
    goto icn_59_waft_1
icn_61_alt_g1:
    astore 179
    sipush 2
    putstatic rung36_jcon_fncs1/icn_61_alt_gate I
    aload 179
    goto icn_59_waft_1
icn_61_α:
    iconst_0
    putstatic rung36_jcon_fncs1/icn_61_alt_gate I
    goto icn_63_α
icn_61_β:
    getstatic rung36_jcon_fncs1/icn_61_alt_gate I
    tableswitch 1 2
        icn_63_β
        icn_62_β
        default: icn_58_α
icn_59_α:
    goto icn_60_α
icn_59_β:
    goto icn_60_β
    goto icn_59_wentry
icn_59_waft_0:
    astore 180
    getstatic java/lang/System/out Ljava/io/PrintStream;
    aload 180
    invokevirtual java/io/PrintStream/print(Ljava/lang/String;)V
    goto icn_61_α
icn_59_waft_1:
    astore 181
    getstatic java/lang/System/out Ljava/io/PrintStream;
    aload 181
    invokevirtual java/io/PrintStream/print(Ljava/lang/String;)V
    getstatic java/lang/System/out Ljava/io/PrintStream;
    ldc ""
    invokevirtual java/io/PrintStream/println(Ljava/lang/String;)V
    aload 181
    goto icn_q1_s3_sdrain
icn_59_wentry:
    goto icn_60_α
icn_q1_s3_sdrain:
    pop
    goto icn_58_α
;  STR
icn_66_α:
    ldc "write(f,\"hello world\") ----> "
    goto icn_65_waft_0
icn_66_β:
    goto icn_59_α
;  STR
icn_68_α:
    ldc "none"
    goto icn_67_alt_g1
icn_68_β:
    goto icn_59_α
;  VAR
icn_71_α:
    getstatic rung36_jcon_fncs1/icn_pv_q1_f J
    goto icn_70_waft_0
icn_71_β:
    goto icn_68_α
;  STR
icn_72_α:
    ldc "hello world"
    goto icn_70_waft_1
icn_72_β:
    goto icn_68_α
icn_70_α:
    goto icn_71_α
icn_70_β:
    goto icn_71_β
    goto icn_70_wentry
icn_70_waft_0:
    lstore 4
    getstatic java/lang/System/out Ljava/io/PrintStream;
    lload 4
    invokevirtual java/io/PrintStream/print(J)V
    goto icn_72_α
icn_70_waft_1:
    astore 182
    getstatic java/lang/System/out Ljava/io/PrintStream;
    aload 182
    invokevirtual java/io/PrintStream/print(Ljava/lang/String;)V
    getstatic java/lang/System/out Ljava/io/PrintStream;
    ldc ""
    invokevirtual java/io/PrintStream/println(Ljava/lang/String;)V
    aload 182
    goto icn_69_image_after
icn_70_wentry:
    goto icn_71_α
icn_69_α:
    goto icn_70_α
icn_69_β:
    goto icn_70_β
icn_69_image_after:
    goto icn_67_alt_g0
icn_67_alt_g0:
    astore 183
    sipush 1
    putstatic rung36_jcon_fncs1/icn_67_alt_gate I
    aload 183
    goto icn_65_waft_1
icn_67_alt_g1:
    astore 184
    sipush 2
    putstatic rung36_jcon_fncs1/icn_67_alt_gate I
    aload 184
    goto icn_65_waft_1
icn_67_α:
    iconst_0
    putstatic rung36_jcon_fncs1/icn_67_alt_gate I
    goto icn_69_α
icn_67_β:
    getstatic rung36_jcon_fncs1/icn_67_alt_gate I
    tableswitch 1 2
        icn_69_β
        icn_68_β
        default: icn_59_α
icn_65_α:
    goto icn_66_α
icn_65_β:
    goto icn_66_β
    goto icn_65_wentry
icn_65_waft_0:
    astore 185
    getstatic java/lang/System/out Ljava/io/PrintStream;
    aload 185
    invokevirtual java/io/PrintStream/print(Ljava/lang/String;)V
    goto icn_67_α
icn_65_waft_1:
    astore 186
    getstatic java/lang/System/out Ljava/io/PrintStream;
    aload 186
    invokevirtual java/io/PrintStream/print(Ljava/lang/String;)V
    getstatic java/lang/System/out Ljava/io/PrintStream;
    ldc ""
    invokevirtual java/io/PrintStream/println(Ljava/lang/String;)V
    aload 186
    goto icn_q1_s2_sdrain
icn_65_wentry:
    goto icn_66_α
icn_q1_s2_sdrain:
    pop
    goto icn_59_α
;  STR
icn_74_α:
    ldc "f := open(\"foo.baz\",\"w\") ----> "
    goto icn_73_waft_0
icn_74_β:
    goto icn_65_α
;  STR
icn_76_α:
    ldc "none"
    goto icn_75_alt_g1
icn_76_β:
    goto icn_65_α
icn_79_α:
    goto icn_76_α
icn_79_β:
    goto icn_76_α
icn_78_α:
    goto icn_79_α
icn_78_β:
    goto icn_79_β
icn_78_store:
    putstatic rung36_jcon_fncs1/icn_pv_q1_f J
    getstatic rung36_jcon_fncs1/icn_pv_q1_f J
    goto icn_77_image_after
icn_77_α:
    goto icn_78_α
icn_77_β:
    goto icn_78_β
icn_77_image_after:
    invokestatic java/lang/Long/toString(J)Ljava/lang/String;
    goto icn_75_alt_g0
icn_75_alt_g0:
    astore 187
    sipush 1
    putstatic rung36_jcon_fncs1/icn_75_alt_gate I
    aload 187
    goto icn_73_waft_1
icn_75_alt_g1:
    astore 188
    sipush 2
    putstatic rung36_jcon_fncs1/icn_75_alt_gate I
    aload 188
    goto icn_73_waft_1
icn_75_α:
    iconst_0
    putstatic rung36_jcon_fncs1/icn_75_alt_gate I
    goto icn_77_α
icn_75_β:
    getstatic rung36_jcon_fncs1/icn_75_alt_gate I
    tableswitch 1 2
        icn_77_β
        icn_76_β
        default: icn_65_α
icn_73_α:
    goto icn_74_α
icn_73_β:
    goto icn_74_β
    goto icn_73_wentry
icn_73_waft_0:
    astore 189
    getstatic java/lang/System/out Ljava/io/PrintStream;
    aload 189
    invokevirtual java/io/PrintStream/print(Ljava/lang/String;)V
    goto icn_75_α
icn_73_waft_1:
    astore 190
    getstatic java/lang/System/out Ljava/io/PrintStream;
    aload 190
    invokevirtual java/io/PrintStream/print(Ljava/lang/String;)V
    getstatic java/lang/System/out Ljava/io/PrintStream;
    ldc ""
    invokevirtual java/io/PrintStream/println(Ljava/lang/String;)V
    aload 190
    goto icn_q1_s1_sdrain
icn_73_wentry:
    goto icn_74_α
icn_q1_s1_sdrain:
    pop
    goto icn_65_α
;  STR
icn_81_α:
    ldc " ----> "
    goto icn_80_waft_0
icn_81_β:
    goto icn_73_α
;  STR
icn_83_α:
    ldc "none"
    goto icn_82_alt_g1
icn_83_β:
    goto icn_73_α
icn_84_α:
    goto icn_83_α
icn_84_β:
    goto icn_83_α
icn_82_alt_g0:
    astore 191
    sipush 1
    putstatic rung36_jcon_fncs1/icn_82_alt_gate I
    aload 191
    goto icn_80_waft_1
icn_82_alt_g1:
    astore 192
    sipush 2
    putstatic rung36_jcon_fncs1/icn_82_alt_gate I
    aload 192
    goto icn_80_waft_1
icn_82_α:
    iconst_0
    putstatic rung36_jcon_fncs1/icn_82_alt_gate I
    goto icn_84_α
icn_82_β:
    getstatic rung36_jcon_fncs1/icn_82_alt_gate I
    tableswitch 1 2
        icn_84_β
        icn_83_β
        default: icn_73_α
icn_80_α:
    goto icn_81_α
icn_80_β:
    goto icn_81_β
    goto icn_80_wentry
icn_80_waft_0:
    astore 193
    getstatic java/lang/System/out Ljava/io/PrintStream;
    aload 193
    invokevirtual java/io/PrintStream/print(Ljava/lang/String;)V
    goto icn_82_α
icn_80_waft_1:
    astore 194
    getstatic java/lang/System/out Ljava/io/PrintStream;
    aload 194
    invokevirtual java/io/PrintStream/print(Ljava/lang/String;)V
    getstatic java/lang/System/out Ljava/io/PrintStream;
    ldc ""
    invokevirtual java/io/PrintStream/println(Ljava/lang/String;)V
    aload 194
    goto icn_q1_s0_sdrain
icn_80_wentry:
    goto icn_81_α
icn_q1_s0_sdrain:
    pop
    goto icn_73_α
icn_q1_done:
    iconst_0
    putstatic rung36_jcon_fncs1/icn_suspended B
    iconst_0
    putstatic rung36_jcon_fncs1/icn_suspend_id I
    iconst_1
    putstatic rung36_jcon_fncs1/icn_failed B
    return
icn_q1_ret:
    iconst_0
    putstatic rung36_jcon_fncs1/icn_failed B
    return
icn_q1_sret:
    return
.end method

.method public static icn_q2()V
    .limit stack 16
    .limit locals 308
    lconst_0
    lstore 0
    lconst_0
    lstore 2
    lconst_0
    lstore 4
    lconst_0
    lstore 6
    lconst_0
    lstore 8
    lconst_0
    lstore 10
    lconst_0
    lstore 12
    lconst_0
    lstore 14
    lconst_0
    lstore 16
    lconst_0
    lstore 18
    lconst_0
    lstore 20
    lconst_0
    lstore 22
    lconst_0
    lstore 24
    lconst_0
    lstore 26
    lconst_0
    lstore 28
    lconst_0
    lstore 30
    lconst_0
    lstore 32
    lconst_0
    lstore 34
    lconst_0
    lstore 36
    lconst_0
    lstore 38
    lconst_0
    lstore 40
    lconst_0
    lstore 42
    lconst_0
    lstore 44
    lconst_0
    lstore 46
    lconst_0
    lstore 48
    lconst_0
    lstore 50
    lconst_0
    lstore 52
    lconst_0
    lstore 54
    lconst_0
    lstore 56
    lconst_0
    lstore 58
    lconst_0
    lstore 60
    lconst_0
    lstore 62
    iconst_0
    istore 84
    iconst_0
    istore 85
    iconst_0
    istore 86
    iconst_0
    istore 87
    iconst_0
    istore 88
    iconst_0
    istore 89
    iconst_0
    istore 90
    iconst_0
    istore 91
    aconst_null
    astore 148
    aconst_null
    astore 149
    aconst_null
    astore 150
    aconst_null
    astore 151
    aconst_null
    astore 152
    aconst_null
    astore 153
    aconst_null
    astore 154
    aconst_null
    astore 155
    aconst_null
    astore 156
    aconst_null
    astore 157
    aconst_null
    astore 158
    aconst_null
    astore 159
    aconst_null
    astore 160
    aconst_null
    astore 161
    aconst_null
    astore 162
    aconst_null
    astore 163
    aconst_null
    astore 164
    aconst_null
    astore 165
    aconst_null
    astore 166
    aconst_null
    astore 167
    aconst_null
    astore 168
    aconst_null
    astore 169
    aconst_null
    astore 170
    aconst_null
    astore 171
    aconst_null
    astore 172
    aconst_null
    astore 173
    aconst_null
    astore 174
    aconst_null
    astore 175
    aconst_null
    astore 176
    aconst_null
    astore 177
    aconst_null
    astore 178
    aconst_null
    astore 179
    aconst_null
    astore 180
    aconst_null
    astore 181
    aconst_null
    astore 182
    aconst_null
    astore 183
    aconst_null
    astore 184
    aconst_null
    astore 185
    aconst_null
    astore 186
    aconst_null
    astore 187
    aconst_null
    astore 188
    aconst_null
    astore 189
    aconst_null
    astore 190
    aconst_null
    astore 191
    aconst_null
    astore 192
    aconst_null
    astore 193
    aconst_null
    astore 194
    aconst_null
    astore 195
    aconst_null
    astore 196
    aconst_null
    astore 197
    aconst_null
    astore 198
    aconst_null
    astore 199
    aconst_null
    astore 200
    aconst_null
    astore 201
    aconst_null
    astore 202
    aconst_null
    astore 203
    goto icn_161_α
;  STR
icn_86_α:
    ldc "f := open(\"fncs1.dat\") ----> "
    goto icn_85_waft_0
icn_86_β:
    goto icn_q2_done
;  STR
icn_88_α:
    ldc "none"
    goto icn_87_alt_g1
icn_88_β:
    goto icn_q2_done
icn_91_α:
    goto icn_88_α
icn_91_β:
    goto icn_88_α
icn_90_α:
    goto icn_91_α
icn_90_β:
    goto icn_91_β
icn_90_store:
    putstatic rung36_jcon_fncs1/icn_pv_q2_f J
    getstatic rung36_jcon_fncs1/icn_pv_q2_f J
    goto icn_89_image_after
icn_89_α:
    goto icn_90_α
icn_89_β:
    goto icn_90_β
icn_89_image_after:
    invokestatic java/lang/Long/toString(J)Ljava/lang/String;
    goto icn_87_alt_g0
icn_87_alt_g0:
    astore 148
    sipush 1
    putstatic rung36_jcon_fncs1/icn_87_alt_gate I
    aload 148
    goto icn_85_waft_1
icn_87_alt_g1:
    astore 149
    sipush 2
    putstatic rung36_jcon_fncs1/icn_87_alt_gate I
    aload 149
    goto icn_85_waft_1
icn_87_α:
    iconst_0
    putstatic rung36_jcon_fncs1/icn_87_alt_gate I
    goto icn_89_α
icn_87_β:
    getstatic rung36_jcon_fncs1/icn_87_alt_gate I
    tableswitch 1 2
        icn_89_β
        icn_88_β
        default: icn_q2_done
icn_85_α:
    goto icn_86_α
icn_85_β:
    goto icn_86_β
    goto icn_85_wentry
icn_85_waft_0:
    astore 150
    getstatic java/lang/System/out Ljava/io/PrintStream;
    aload 150
    invokevirtual java/io/PrintStream/print(Ljava/lang/String;)V
    goto icn_87_α
icn_85_waft_1:
    astore 151
    getstatic java/lang/System/out Ljava/io/PrintStream;
    aload 151
    invokevirtual java/io/PrintStream/print(Ljava/lang/String;)V
    getstatic java/lang/System/out Ljava/io/PrintStream;
    ldc ""
    invokevirtual java/io/PrintStream/println(Ljava/lang/String;)V
    aload 151
    goto icn_q2_s10_sdrain
icn_85_wentry:
    goto icn_86_α
icn_q2_s10_sdrain:
    pop
    goto icn_q2_done
;  STR
icn_93_α:
    ldc "while writes(reads(f,10)) ----> "
    goto icn_92_waft_0
icn_93_β:
    goto icn_85_α
;  STR
icn_95_α:
    ldc "none"
    goto icn_94_alt_g1
icn_95_β:
    goto icn_85_α
icn_98_α:
    goto icn_95_α
icn_98_β:
    goto icn_95_α
icn_97_condok:
    pop2
    goto icn_98_α
icn_97_α:
    goto icn_98_α
icn_97_β:
    goto icn_95_α
icn_96_α:
    goto icn_97_α
icn_96_β:
    goto icn_97_β
icn_96_image_after:
    invokestatic java/lang/Long/toString(J)Ljava/lang/String;
    goto icn_94_alt_g0
icn_94_alt_g0:
    astore 152
    sipush 1
    putstatic rung36_jcon_fncs1/icn_94_alt_gate I
    aload 152
    goto icn_92_waft_1
icn_94_alt_g1:
    astore 153
    sipush 2
    putstatic rung36_jcon_fncs1/icn_94_alt_gate I
    aload 153
    goto icn_92_waft_1
icn_94_α:
    iconst_0
    putstatic rung36_jcon_fncs1/icn_94_alt_gate I
    goto icn_96_α
icn_94_β:
    getstatic rung36_jcon_fncs1/icn_94_alt_gate I
    tableswitch 1 2
        icn_96_β
        icn_95_β
        default: icn_85_α
icn_92_α:
    goto icn_93_α
icn_92_β:
    goto icn_93_β
    goto icn_92_wentry
icn_92_waft_0:
    astore 154
    getstatic java/lang/System/out Ljava/io/PrintStream;
    aload 154
    invokevirtual java/io/PrintStream/print(Ljava/lang/String;)V
    goto icn_94_α
icn_92_waft_1:
    astore 155
    getstatic java/lang/System/out Ljava/io/PrintStream;
    aload 155
    invokevirtual java/io/PrintStream/print(Ljava/lang/String;)V
    getstatic java/lang/System/out Ljava/io/PrintStream;
    ldc ""
    invokevirtual java/io/PrintStream/println(Ljava/lang/String;)V
    aload 155
    goto icn_q2_s9_sdrain
icn_92_wentry:
    goto icn_93_α
icn_q2_s9_sdrain:
    pop
    goto icn_85_α
;  STR
icn_100_α:
    ldc "f := open(\"fncs1.dat\") ----> "
    goto icn_99_waft_0
icn_100_β:
    goto icn_92_α
;  STR
icn_102_α:
    ldc "none"
    goto icn_101_alt_g1
icn_102_β:
    goto icn_92_α
icn_105_α:
    goto icn_102_α
icn_105_β:
    goto icn_102_α
icn_104_α:
    goto icn_105_α
icn_104_β:
    goto icn_105_β
icn_104_store:
    putstatic rung36_jcon_fncs1/icn_pv_q2_f J
    getstatic rung36_jcon_fncs1/icn_pv_q2_f J
    goto icn_103_image_after
icn_103_α:
    goto icn_104_α
icn_103_β:
    goto icn_104_β
icn_103_image_after:
    invokestatic java/lang/Long/toString(J)Ljava/lang/String;
    goto icn_101_alt_g0
icn_101_alt_g0:
    astore 156
    sipush 1
    putstatic rung36_jcon_fncs1/icn_101_alt_gate I
    aload 156
    goto icn_99_waft_1
icn_101_alt_g1:
    astore 157
    sipush 2
    putstatic rung36_jcon_fncs1/icn_101_alt_gate I
    aload 157
    goto icn_99_waft_1
icn_101_α:
    iconst_0
    putstatic rung36_jcon_fncs1/icn_101_alt_gate I
    goto icn_103_α
icn_101_β:
    getstatic rung36_jcon_fncs1/icn_101_alt_gate I
    tableswitch 1 2
        icn_103_β
        icn_102_β
        default: icn_92_α
icn_99_α:
    goto icn_100_α
icn_99_β:
    goto icn_100_β
    goto icn_99_wentry
icn_99_waft_0:
    astore 158
    getstatic java/lang/System/out Ljava/io/PrintStream;
    aload 158
    invokevirtual java/io/PrintStream/print(Ljava/lang/String;)V
    goto icn_101_α
icn_99_waft_1:
    astore 159
    getstatic java/lang/System/out Ljava/io/PrintStream;
    aload 159
    invokevirtual java/io/PrintStream/print(Ljava/lang/String;)V
    getstatic java/lang/System/out Ljava/io/PrintStream;
    ldc ""
    invokevirtual java/io/PrintStream/println(Ljava/lang/String;)V
    aload 159
    goto icn_q2_s8_sdrain
icn_99_wentry:
    goto icn_100_α
icn_q2_s8_sdrain:
    pop
    goto icn_92_α
;  STR
icn_107_α:
    ldc "close(f) ----> "
    goto icn_106_waft_0
icn_107_β:
    goto icn_99_α
;  STR
icn_109_α:
    ldc "none"
    goto icn_108_alt_g1
icn_109_β:
    goto icn_99_α
icn_111_α:
    goto icn_109_α
icn_111_β:
    goto icn_109_α
icn_110_α:
    goto icn_111_α
icn_110_β:
    goto icn_111_β
icn_110_image_after:
    invokestatic java/lang/Long/toString(J)Ljava/lang/String;
    goto icn_108_alt_g0
icn_108_alt_g0:
    astore 160
    sipush 1
    putstatic rung36_jcon_fncs1/icn_108_alt_gate I
    aload 160
    goto icn_106_waft_1
icn_108_alt_g1:
    astore 161
    sipush 2
    putstatic rung36_jcon_fncs1/icn_108_alt_gate I
    aload 161
    goto icn_106_waft_1
icn_108_α:
    iconst_0
    putstatic rung36_jcon_fncs1/icn_108_alt_gate I
    goto icn_110_α
icn_108_β:
    getstatic rung36_jcon_fncs1/icn_108_alt_gate I
    tableswitch 1 2
        icn_110_β
        icn_109_β
        default: icn_99_α
icn_106_α:
    goto icn_107_α
icn_106_β:
    goto icn_107_β
    goto icn_106_wentry
icn_106_waft_0:
    astore 162
    getstatic java/lang/System/out Ljava/io/PrintStream;
    aload 162
    invokevirtual java/io/PrintStream/print(Ljava/lang/String;)V
    goto icn_108_α
icn_106_waft_1:
    astore 163
    getstatic java/lang/System/out Ljava/io/PrintStream;
    aload 163
    invokevirtual java/io/PrintStream/print(Ljava/lang/String;)V
    getstatic java/lang/System/out Ljava/io/PrintStream;
    ldc ""
    invokevirtual java/io/PrintStream/println(Ljava/lang/String;)V
    aload 163
    goto icn_q2_s7_sdrain
icn_106_wentry:
    goto icn_107_α
icn_q2_s7_sdrain:
    pop
    goto icn_99_α
;  STR
icn_113_α:
    ldc "while writes(reads(f)) ----> "
    goto icn_112_waft_0
icn_113_β:
    goto icn_106_α
;  STR
icn_115_α:
    ldc "none"
    goto icn_114_alt_g1
icn_115_β:
    goto icn_106_α
icn_118_α:
    goto icn_115_α
icn_118_β:
    goto icn_115_α
icn_117_condok:
    pop2
    goto icn_118_α
icn_117_α:
    goto icn_118_α
icn_117_β:
    goto icn_115_α
icn_116_α:
    goto icn_117_α
icn_116_β:
    goto icn_117_β
icn_116_image_after:
    invokestatic java/lang/Long/toString(J)Ljava/lang/String;
    goto icn_114_alt_g0
icn_114_alt_g0:
    astore 164
    sipush 1
    putstatic rung36_jcon_fncs1/icn_114_alt_gate I
    aload 164
    goto icn_112_waft_1
icn_114_alt_g1:
    astore 165
    sipush 2
    putstatic rung36_jcon_fncs1/icn_114_alt_gate I
    aload 165
    goto icn_112_waft_1
icn_114_α:
    iconst_0
    putstatic rung36_jcon_fncs1/icn_114_alt_gate I
    goto icn_116_α
icn_114_β:
    getstatic rung36_jcon_fncs1/icn_114_alt_gate I
    tableswitch 1 2
        icn_116_β
        icn_115_β
        default: icn_106_α
icn_112_α:
    goto icn_113_α
icn_112_β:
    goto icn_113_β
    goto icn_112_wentry
icn_112_waft_0:
    astore 166
    getstatic java/lang/System/out Ljava/io/PrintStream;
    aload 166
    invokevirtual java/io/PrintStream/print(Ljava/lang/String;)V
    goto icn_114_α
icn_112_waft_1:
    astore 167
    getstatic java/lang/System/out Ljava/io/PrintStream;
    aload 167
    invokevirtual java/io/PrintStream/print(Ljava/lang/String;)V
    getstatic java/lang/System/out Ljava/io/PrintStream;
    ldc ""
    invokevirtual java/io/PrintStream/println(Ljava/lang/String;)V
    aload 167
    goto icn_q2_s6_sdrain
icn_112_wentry:
    goto icn_113_α
icn_q2_s6_sdrain:
    pop
    goto icn_106_α
;  STR
icn_120_α:
    ldc "f := open(\"fncs1.dat\") ----> "
    goto icn_119_waft_0
icn_120_β:
    goto icn_112_α
;  STR
icn_122_α:
    ldc "none"
    goto icn_121_alt_g1
icn_122_β:
    goto icn_112_α
icn_125_α:
    goto icn_122_α
icn_125_β:
    goto icn_122_α
icn_124_α:
    goto icn_125_α
icn_124_β:
    goto icn_125_β
icn_124_store:
    putstatic rung36_jcon_fncs1/icn_pv_q2_f J
    getstatic rung36_jcon_fncs1/icn_pv_q2_f J
    goto icn_123_image_after
icn_123_α:
    goto icn_124_α
icn_123_β:
    goto icn_124_β
icn_123_image_after:
    invokestatic java/lang/Long/toString(J)Ljava/lang/String;
    goto icn_121_alt_g0
icn_121_alt_g0:
    astore 168
    sipush 1
    putstatic rung36_jcon_fncs1/icn_121_alt_gate I
    aload 168
    goto icn_119_waft_1
icn_121_alt_g1:
    astore 169
    sipush 2
    putstatic rung36_jcon_fncs1/icn_121_alt_gate I
    aload 169
    goto icn_119_waft_1
icn_121_α:
    iconst_0
    putstatic rung36_jcon_fncs1/icn_121_alt_gate I
    goto icn_123_α
icn_121_β:
    getstatic rung36_jcon_fncs1/icn_121_alt_gate I
    tableswitch 1 2
        icn_123_β
        icn_122_β
        default: icn_112_α
icn_119_α:
    goto icn_120_α
icn_119_β:
    goto icn_120_β
    goto icn_119_wentry
icn_119_waft_0:
    astore 170
    getstatic java/lang/System/out Ljava/io/PrintStream;
    aload 170
    invokevirtual java/io/PrintStream/print(Ljava/lang/String;)V
    goto icn_121_α
icn_119_waft_1:
    astore 171
    getstatic java/lang/System/out Ljava/io/PrintStream;
    aload 171
    invokevirtual java/io/PrintStream/print(Ljava/lang/String;)V
    getstatic java/lang/System/out Ljava/io/PrintStream;
    ldc ""
    invokevirtual java/io/PrintStream/println(Ljava/lang/String;)V
    aload 171
    goto icn_q2_s5_sdrain
icn_119_wentry:
    goto icn_120_α
icn_q2_s5_sdrain:
    pop
    goto icn_112_α
;  STR
icn_127_α:
    ldc "close(F) ----> "
    goto icn_126_waft_0
icn_127_β:
    goto icn_119_α
;  STR
icn_129_α:
    ldc "none"
    goto icn_128_alt_g1
icn_129_β:
    goto icn_119_α
icn_131_α:
    goto icn_129_α
icn_131_β:
    goto icn_129_α
icn_130_α:
    goto icn_131_α
icn_130_β:
    goto icn_131_β
icn_130_image_after:
    invokestatic java/lang/Long/toString(J)Ljava/lang/String;
    goto icn_128_alt_g0
icn_128_alt_g0:
    astore 172
    sipush 1
    putstatic rung36_jcon_fncs1/icn_128_alt_gate I
    aload 172
    goto icn_126_waft_1
icn_128_alt_g1:
    astore 173
    sipush 2
    putstatic rung36_jcon_fncs1/icn_128_alt_gate I
    aload 173
    goto icn_126_waft_1
icn_128_α:
    iconst_0
    putstatic rung36_jcon_fncs1/icn_128_alt_gate I
    goto icn_130_α
icn_128_β:
    getstatic rung36_jcon_fncs1/icn_128_alt_gate I
    tableswitch 1 2
        icn_130_β
        icn_129_β
        default: icn_119_α
icn_126_α:
    goto icn_127_α
icn_126_β:
    goto icn_127_β
    goto icn_126_wentry
icn_126_waft_0:
    astore 174
    getstatic java/lang/System/out Ljava/io/PrintStream;
    aload 174
    invokevirtual java/io/PrintStream/print(Ljava/lang/String;)V
    goto icn_128_α
icn_126_waft_1:
    astore 175
    getstatic java/lang/System/out Ljava/io/PrintStream;
    aload 175
    invokevirtual java/io/PrintStream/print(Ljava/lang/String;)V
    getstatic java/lang/System/out Ljava/io/PrintStream;
    ldc ""
    invokevirtual java/io/PrintStream/println(Ljava/lang/String;)V
    aload 175
    goto icn_q2_s4_sdrain
icn_126_wentry:
    goto icn_127_α
icn_q2_s4_sdrain:
    pop
    goto icn_119_α
;  STR
icn_133_α:
    ldc "every write(map(!F,&cset || \"     \",&cset || \"aeiou\")) ----> "
    goto icn_132_waft_0
icn_133_β:
    goto icn_126_α
;  STR
icn_135_α:
    ldc "none"
    goto icn_134_alt_g1
icn_135_β:
    goto icn_126_α
;  VAR
icn_141_α:
    getstatic rung36_jcon_fncs1/icn_pv_q2_F J
    goto icn_140_bang_adv
icn_141_β:
    goto icn_135_α
icn_140_α:
    goto icn_141_α
icn_140_β:
    goto icn_140_bang_chk
icn_140_bang_adv:
    putstatic rung36_jcon_fncs1/icn_140_bang_str Ljava/lang/String;
    iconst_0
    putstatic rung36_jcon_fncs1/icn_140_bang_pos I
icn_140_bang_chk:
    getstatic rung36_jcon_fncs1/icn_140_bang_str Ljava/lang/String;
    invokevirtual java/lang/String/length()I
    getstatic rung36_jcon_fncs1/icn_140_bang_pos I
    if_icmple icn_135_α
    getstatic rung36_jcon_fncs1/icn_140_bang_str Ljava/lang/String;
    getstatic rung36_jcon_fncs1/icn_140_bang_pos I
    getstatic rung36_jcon_fncs1/icn_140_bang_pos I
    iconst_1
    iadd
    invokevirtual java/lang/String/substring(II)Ljava/lang/String;
    getstatic rung36_jcon_fncs1/icn_140_bang_pos I
    iconst_1
    iadd
    putstatic rung36_jcon_fncs1/icn_140_bang_pos I
    goto icn_139_map_mid1
;  STR
icn_143_α:
    ldc "     "
    goto icn_142_rrelay
icn_143_β:
    goto icn_142_lb
;  VAR
icn_144_α:
    ldc "\u0000\u0001\u0002\u0003\u0004\u0005\u0006\u0007\u0008\u0009\u000a\u000b\u000c\u000d\u000e\u000f\u0010\u0011\u0012\u0013\u0014\u0015\u0016\u0017\u0018\u0019\u001a\u001b\u001c\u001d\u001e\u001f !\"#$%&'()*+,-./0123456789:;<=>?@ABCDEFGHIJKLMNOPQRSTUVWXYZ[\\]^_`abcdefghijklmnopqrstuvwxyz{|}~\u007f"
    goto icn_142_lrelay
icn_144_β:
    goto icn_135_α
icn_142_lrelay:
    putstatic rung36_jcon_fncs1/icn_142_lc Ljava/lang/String;
    goto icn_142_lstore
icn_142_rrelay:
    putstatic rung36_jcon_fncs1/icn_142_rc Ljava/lang/String;
    goto icn_142_compute
icn_142_lb:
    goto icn_144_β
icn_142_α:
    iconst_0
    istore 84
    goto icn_144_α
icn_142_β:
    goto icn_143_β
icn_142_lstore:
    iload 84
    ifeq icn_143_α
    goto icn_143_β
icn_142_compute:
    getstatic rung36_jcon_fncs1/icn_142_lc Ljava/lang/String;
    getstatic rung36_jcon_fncs1/icn_142_rc Ljava/lang/String;
    invokevirtual java/lang/String/concat(Ljava/lang/String;)Ljava/lang/String;
    goto icn_139_map_mid2
;  STR
icn_146_α:
    ldc "aeiou"
    goto icn_145_rrelay
icn_146_β:
    goto icn_145_lb
;  VAR
icn_147_α:
    ldc "\u0000\u0001\u0002\u0003\u0004\u0005\u0006\u0007\u0008\u0009\u000a\u000b\u000c\u000d\u000e\u000f\u0010\u0011\u0012\u0013\u0014\u0015\u0016\u0017\u0018\u0019\u001a\u001b\u001c\u001d\u001e\u001f !\"#$%&'()*+,-./0123456789:;<=>?@ABCDEFGHIJKLMNOPQRSTUVWXYZ[\\]^_`abcdefghijklmnopqrstuvwxyz{|}~\u007f"
    goto icn_145_lrelay
icn_147_β:
    goto icn_135_α
icn_145_lrelay:
    putstatic rung36_jcon_fncs1/icn_145_lc Ljava/lang/String;
    goto icn_145_lstore
icn_145_rrelay:
    putstatic rung36_jcon_fncs1/icn_145_rc Ljava/lang/String;
    goto icn_145_compute
icn_145_lb:
    goto icn_147_β
icn_145_α:
    iconst_0
    istore 85
    goto icn_147_α
icn_145_β:
    goto icn_146_β
icn_145_lstore:
    iload 85
    ifeq icn_146_α
    goto icn_146_β
icn_145_compute:
    getstatic rung36_jcon_fncs1/icn_145_lc Ljava/lang/String;
    getstatic rung36_jcon_fncs1/icn_145_rc Ljava/lang/String;
    invokevirtual java/lang/String/concat(Ljava/lang/String;)Ljava/lang/String;
    goto icn_139_map_after
icn_139_α:
    goto icn_140_α
icn_139_β:
    goto icn_140_β
icn_139_map_mid1:
    astore 176
    goto icn_142_α
icn_139_map_mid2:
    astore 177
    goto icn_145_α
icn_139_map_after:
    astore 178
    aload 176
    aload 177
    aload 178
    invokestatic rung36_jcon_fncs1/icn_builtin_map(Ljava/lang/String;Ljava/lang/String;Ljava/lang/String;)Ljava/lang/String;
    goto icn_138_waft_0
icn_138_α:
    goto icn_139_α
icn_138_β:
    goto icn_139_β
    goto icn_138_wentry
icn_138_waft_0:
    astore 179
    getstatic java/lang/System/out Ljava/io/PrintStream;
    aload 179
    invokevirtual java/io/PrintStream/print(Ljava/lang/String;)V
    getstatic java/lang/System/out Ljava/io/PrintStream;
    ldc ""
    invokevirtual java/io/PrintStream/println(Ljava/lang/String;)V
    aload 179
    goto icn_137_gdrain
icn_138_wentry:
    goto icn_139_α
icn_137_gdrain:
    pop
icn_137_pump:
    goto icn_138_β
icn_137_α:
    goto icn_138_α
icn_137_β:
    goto icn_135_α
icn_136_α:
    goto icn_137_α
icn_136_β:
    goto icn_137_β
icn_136_image_after:
    invokestatic java/lang/Long/toString(J)Ljava/lang/String;
    goto icn_134_alt_g0
icn_134_alt_g0:
    astore 180
    sipush 1
    putstatic rung36_jcon_fncs1/icn_134_alt_gate I
    aload 180
    goto icn_132_waft_1
icn_134_alt_g1:
    astore 181
    sipush 2
    putstatic rung36_jcon_fncs1/icn_134_alt_gate I
    aload 181
    goto icn_132_waft_1
icn_134_α:
    iconst_0
    putstatic rung36_jcon_fncs1/icn_134_alt_gate I
    goto icn_136_α
icn_134_β:
    getstatic rung36_jcon_fncs1/icn_134_alt_gate I
    tableswitch 1 2
        icn_136_β
        icn_135_β
        default: icn_126_α
icn_132_α:
    goto icn_133_α
icn_132_β:
    goto icn_133_β
    goto icn_132_wentry
icn_132_waft_0:
    astore 182
    getstatic java/lang/System/out Ljava/io/PrintStream;
    aload 182
    invokevirtual java/io/PrintStream/print(Ljava/lang/String;)V
    goto icn_134_α
icn_132_waft_1:
    astore 183
    getstatic java/lang/System/out Ljava/io/PrintStream;
    aload 183
    invokevirtual java/io/PrintStream/print(Ljava/lang/String;)V
    getstatic java/lang/System/out Ljava/io/PrintStream;
    ldc ""
    invokevirtual java/io/PrintStream/println(Ljava/lang/String;)V
    aload 183
    goto icn_q2_s3_sdrain
icn_132_wentry:
    goto icn_133_α
icn_q2_s3_sdrain:
    pop
    goto icn_126_α
;  STR
icn_149_α:
    ldc "F := open(\"fncs1.dat\") ----> "
    goto icn_148_waft_0
icn_149_β:
    goto icn_132_α
;  STR
icn_151_α:
    ldc "none"
    goto icn_150_alt_g1
icn_151_β:
    goto icn_132_α
icn_154_α:
    goto icn_151_α
icn_154_β:
    goto icn_151_α
icn_153_α:
    goto icn_154_α
icn_153_β:
    goto icn_154_β
icn_153_store:
    putstatic rung36_jcon_fncs1/icn_pv_q2_F J
    getstatic rung36_jcon_fncs1/icn_pv_q2_F J
    goto icn_152_image_after
icn_152_α:
    goto icn_153_α
icn_152_β:
    goto icn_153_β
icn_152_image_after:
    invokestatic java/lang/Long/toString(J)Ljava/lang/String;
    goto icn_150_alt_g0
icn_150_alt_g0:
    astore 184
    sipush 1
    putstatic rung36_jcon_fncs1/icn_150_alt_gate I
    aload 184
    goto icn_148_waft_1
icn_150_alt_g1:
    astore 185
    sipush 2
    putstatic rung36_jcon_fncs1/icn_150_alt_gate I
    aload 185
    goto icn_148_waft_1
icn_150_α:
    iconst_0
    putstatic rung36_jcon_fncs1/icn_150_alt_gate I
    goto icn_152_α
icn_150_β:
    getstatic rung36_jcon_fncs1/icn_150_alt_gate I
    tableswitch 1 2
        icn_152_β
        icn_151_β
        default: icn_132_α
icn_148_α:
    goto icn_149_α
icn_148_β:
    goto icn_149_β
    goto icn_148_wentry
icn_148_waft_0:
    astore 186
    getstatic java/lang/System/out Ljava/io/PrintStream;
    aload 186
    invokevirtual java/io/PrintStream/print(Ljava/lang/String;)V
    goto icn_150_α
icn_148_waft_1:
    astore 187
    getstatic java/lang/System/out Ljava/io/PrintStream;
    aload 187
    invokevirtual java/io/PrintStream/print(Ljava/lang/String;)V
    getstatic java/lang/System/out Ljava/io/PrintStream;
    ldc ""
    invokevirtual java/io/PrintStream/println(Ljava/lang/String;)V
    aload 187
    goto icn_q2_s2_sdrain
icn_148_wentry:
    goto icn_149_α
icn_q2_s2_sdrain:
    pop
    goto icn_132_α
;  STR
icn_156_α:
    ldc "close(F) ----> "
    goto icn_155_waft_0
icn_156_β:
    goto icn_148_α
;  STR
icn_158_α:
    ldc "none"
    goto icn_157_alt_g1
icn_158_β:
    goto icn_148_α
icn_160_α:
    goto icn_158_α
icn_160_β:
    goto icn_158_α
icn_159_α:
    goto icn_160_α
icn_159_β:
    goto icn_160_β
icn_159_image_after:
    invokestatic java/lang/Long/toString(J)Ljava/lang/String;
    goto icn_157_alt_g0
icn_157_alt_g0:
    astore 188
    sipush 1
    putstatic rung36_jcon_fncs1/icn_157_alt_gate I
    aload 188
    goto icn_155_waft_1
icn_157_alt_g1:
    astore 189
    sipush 2
    putstatic rung36_jcon_fncs1/icn_157_alt_gate I
    aload 189
    goto icn_155_waft_1
icn_157_α:
    iconst_0
    putstatic rung36_jcon_fncs1/icn_157_alt_gate I
    goto icn_159_α
icn_157_β:
    getstatic rung36_jcon_fncs1/icn_157_alt_gate I
    tableswitch 1 2
        icn_159_β
        icn_158_β
        default: icn_148_α
icn_155_α:
    goto icn_156_α
icn_155_β:
    goto icn_156_β
    goto icn_155_wentry
icn_155_waft_0:
    astore 190
    getstatic java/lang/System/out Ljava/io/PrintStream;
    aload 190
    invokevirtual java/io/PrintStream/print(Ljava/lang/String;)V
    goto icn_157_α
icn_155_waft_1:
    astore 191
    getstatic java/lang/System/out Ljava/io/PrintStream;
    aload 191
    invokevirtual java/io/PrintStream/print(Ljava/lang/String;)V
    getstatic java/lang/System/out Ljava/io/PrintStream;
    ldc ""
    invokevirtual java/io/PrintStream/println(Ljava/lang/String;)V
    aload 191
    goto icn_q2_s1_sdrain
icn_155_wentry:
    goto icn_156_α
icn_q2_s1_sdrain:
    pop
    goto icn_148_α
;  STR
icn_162_α:
    ldc "every write(map(!F,&cset || \"aeiou\",&cset || \"-----\")) ----> "
    goto icn_161_waft_0
icn_162_β:
    goto icn_155_α
;  STR
icn_164_α:
    ldc "none"
    goto icn_163_alt_g1
icn_164_β:
    goto icn_155_α
;  VAR
icn_170_α:
    getstatic rung36_jcon_fncs1/icn_pv_q2_F J
    goto icn_169_bang_adv
icn_170_β:
    goto icn_164_α
icn_169_α:
    goto icn_170_α
icn_169_β:
    goto icn_169_bang_chk
icn_169_bang_adv:
    putstatic rung36_jcon_fncs1/icn_169_bang_str Ljava/lang/String;
    iconst_0
    putstatic rung36_jcon_fncs1/icn_169_bang_pos I
icn_169_bang_chk:
    getstatic rung36_jcon_fncs1/icn_169_bang_str Ljava/lang/String;
    invokevirtual java/lang/String/length()I
    getstatic rung36_jcon_fncs1/icn_169_bang_pos I
    if_icmple icn_164_α
    getstatic rung36_jcon_fncs1/icn_169_bang_str Ljava/lang/String;
    getstatic rung36_jcon_fncs1/icn_169_bang_pos I
    getstatic rung36_jcon_fncs1/icn_169_bang_pos I
    iconst_1
    iadd
    invokevirtual java/lang/String/substring(II)Ljava/lang/String;
    getstatic rung36_jcon_fncs1/icn_169_bang_pos I
    iconst_1
    iadd
    putstatic rung36_jcon_fncs1/icn_169_bang_pos I
    goto icn_168_map_mid1
;  STR
icn_172_α:
    ldc "aeiou"
    goto icn_171_rrelay
icn_172_β:
    goto icn_171_lb
;  VAR
icn_173_α:
    ldc "\u0000\u0001\u0002\u0003\u0004\u0005\u0006\u0007\u0008\u0009\u000a\u000b\u000c\u000d\u000e\u000f\u0010\u0011\u0012\u0013\u0014\u0015\u0016\u0017\u0018\u0019\u001a\u001b\u001c\u001d\u001e\u001f !\"#$%&'()*+,-./0123456789:;<=>?@ABCDEFGHIJKLMNOPQRSTUVWXYZ[\\]^_`abcdefghijklmnopqrstuvwxyz{|}~\u007f"
    goto icn_171_lrelay
icn_173_β:
    goto icn_164_α
icn_171_lrelay:
    putstatic rung36_jcon_fncs1/icn_171_lc Ljava/lang/String;
    goto icn_171_lstore
icn_171_rrelay:
    putstatic rung36_jcon_fncs1/icn_171_rc Ljava/lang/String;
    goto icn_171_compute
icn_171_lb:
    goto icn_173_β
icn_171_α:
    iconst_0
    istore 86
    goto icn_173_α
icn_171_β:
    goto icn_172_β
icn_171_lstore:
    iload 86
    ifeq icn_172_α
    goto icn_172_β
icn_171_compute:
    getstatic rung36_jcon_fncs1/icn_171_lc Ljava/lang/String;
    getstatic rung36_jcon_fncs1/icn_171_rc Ljava/lang/String;
    invokevirtual java/lang/String/concat(Ljava/lang/String;)Ljava/lang/String;
    goto icn_168_map_mid2
;  STR
icn_175_α:
    ldc "-----"
    goto icn_174_rrelay
icn_175_β:
    goto icn_174_lb
;  VAR
icn_176_α:
    ldc "\u0000\u0001\u0002\u0003\u0004\u0005\u0006\u0007\u0008\u0009\u000a\u000b\u000c\u000d\u000e\u000f\u0010\u0011\u0012\u0013\u0014\u0015\u0016\u0017\u0018\u0019\u001a\u001b\u001c\u001d\u001e\u001f !\"#$%&'()*+,-./0123456789:;<=>?@ABCDEFGHIJKLMNOPQRSTUVWXYZ[\\]^_`abcdefghijklmnopqrstuvwxyz{|}~\u007f"
    goto icn_174_lrelay
icn_176_β:
    goto icn_164_α
icn_174_lrelay:
    putstatic rung36_jcon_fncs1/icn_174_lc Ljava/lang/String;
    goto icn_174_lstore
icn_174_rrelay:
    putstatic rung36_jcon_fncs1/icn_174_rc Ljava/lang/String;
    goto icn_174_compute
icn_174_lb:
    goto icn_176_β
icn_174_α:
    iconst_0
    istore 87
    goto icn_176_α
icn_174_β:
    goto icn_175_β
icn_174_lstore:
    iload 87
    ifeq icn_175_α
    goto icn_175_β
icn_174_compute:
    getstatic rung36_jcon_fncs1/icn_174_lc Ljava/lang/String;
    getstatic rung36_jcon_fncs1/icn_174_rc Ljava/lang/String;
    invokevirtual java/lang/String/concat(Ljava/lang/String;)Ljava/lang/String;
    goto icn_168_map_after
icn_168_α:
    goto icn_169_α
icn_168_β:
    goto icn_169_β
icn_168_map_mid1:
    astore 192
    goto icn_171_α
icn_168_map_mid2:
    astore 193
    goto icn_174_α
icn_168_map_after:
    astore 194
    aload 192
    aload 193
    aload 194
    invokestatic rung36_jcon_fncs1/icn_builtin_map(Ljava/lang/String;Ljava/lang/String;Ljava/lang/String;)Ljava/lang/String;
    goto icn_167_waft_0
icn_167_α:
    goto icn_168_α
icn_167_β:
    goto icn_168_β
    goto icn_167_wentry
icn_167_waft_0:
    astore 195
    getstatic java/lang/System/out Ljava/io/PrintStream;
    aload 195
    invokevirtual java/io/PrintStream/print(Ljava/lang/String;)V
    getstatic java/lang/System/out Ljava/io/PrintStream;
    ldc ""
    invokevirtual java/io/PrintStream/println(Ljava/lang/String;)V
    aload 195
    goto icn_166_gdrain
icn_167_wentry:
    goto icn_168_α
icn_166_gdrain:
    pop
icn_166_pump:
    goto icn_167_β
icn_166_α:
    goto icn_167_α
icn_166_β:
    goto icn_164_α
icn_165_α:
    goto icn_166_α
icn_165_β:
    goto icn_166_β
icn_165_image_after:
    invokestatic java/lang/Long/toString(J)Ljava/lang/String;
    goto icn_163_alt_g0
icn_163_alt_g0:
    astore 196
    sipush 1
    putstatic rung36_jcon_fncs1/icn_163_alt_gate I
    aload 196
    goto icn_161_waft_1
icn_163_alt_g1:
    astore 197
    sipush 2
    putstatic rung36_jcon_fncs1/icn_163_alt_gate I
    aload 197
    goto icn_161_waft_1
icn_163_α:
    iconst_0
    putstatic rung36_jcon_fncs1/icn_163_alt_gate I
    goto icn_165_α
icn_163_β:
    getstatic rung36_jcon_fncs1/icn_163_alt_gate I
    tableswitch 1 2
        icn_165_β
        icn_164_β
        default: icn_155_α
icn_161_α:
    goto icn_162_α
icn_161_β:
    goto icn_162_β
    goto icn_161_wentry
icn_161_waft_0:
    astore 198
    getstatic java/lang/System/out Ljava/io/PrintStream;
    aload 198
    invokevirtual java/io/PrintStream/print(Ljava/lang/String;)V
    goto icn_163_α
icn_161_waft_1:
    astore 199
    getstatic java/lang/System/out Ljava/io/PrintStream;
    aload 199
    invokevirtual java/io/PrintStream/print(Ljava/lang/String;)V
    getstatic java/lang/System/out Ljava/io/PrintStream;
    ldc ""
    invokevirtual java/io/PrintStream/println(Ljava/lang/String;)V
    aload 199
    goto icn_q2_s0_sdrain
icn_161_wentry:
    goto icn_162_α
icn_q2_s0_sdrain:
    pop
    goto icn_155_α
icn_q2_done:
    iconst_0
    putstatic rung36_jcon_fncs1/icn_suspended B
    iconst_0
    putstatic rung36_jcon_fncs1/icn_suspend_id I
    iconst_1
    putstatic rung36_jcon_fncs1/icn_failed B
    return
icn_q2_ret:
    iconst_0
    putstatic rung36_jcon_fncs1/icn_failed B
    return
icn_q2_sret:
    return
.end method

.method public static icn_q3()V
    .limit stack 16
    .limit locals 269
    lconst_0
    lstore 0
    lconst_0
    lstore 2
    lconst_0
    lstore 4
    lconst_0
    lstore 6
    lconst_0
    lstore 8
    lconst_0
    lstore 10
    lconst_0
    lstore 12
    lconst_0
    lstore 14
    lconst_0
    lstore 16
    lconst_0
    lstore 18
    lconst_0
    lstore 20
    lconst_0
    lstore 22
    lconst_0
    lstore 24
    lconst_0
    lstore 26
    lconst_0
    lstore 28
    lconst_0
    lstore 30
    lconst_0
    lstore 32
    lconst_0
    lstore 34
    lconst_0
    lstore 36
    lconst_0
    lstore 38
    lconst_0
    lstore 40
    lconst_0
    lstore 42
    lconst_0
    lstore 44
    lconst_0
    lstore 46
    lconst_0
    lstore 48
    lconst_0
    lstore 50
    lconst_0
    lstore 52
    lconst_0
    lstore 54
    lconst_0
    lstore 56
    lconst_0
    lstore 58
    lconst_0
    lstore 60
    lconst_0
    lstore 62
    iconst_0
    istore 84
    iconst_0
    istore 85
    iconst_0
    istore 86
    iconst_0
    istore 87
    aconst_null
    astore 148
    aconst_null
    astore 149
    aconst_null
    astore 150
    aconst_null
    astore 151
    aconst_null
    astore 152
    aconst_null
    astore 153
    aconst_null
    astore 154
    aconst_null
    astore 155
    aconst_null
    astore 156
    aconst_null
    astore 157
    aconst_null
    astore 158
    aconst_null
    astore 159
    aconst_null
    astore 160
    goto icn_183_α
;  STR
icn_178_α:
    ldc "close(f) ----> "
    goto icn_177_waft_0
icn_178_β:
    goto icn_q3_done
;  STR
icn_180_α:
    ldc "none"
    goto icn_179_alt_g1
icn_180_β:
    goto icn_q3_done
icn_182_α:
    goto icn_180_α
icn_182_β:
    goto icn_180_α
icn_181_α:
    goto icn_182_α
icn_181_β:
    goto icn_182_β
icn_181_image_after:
    invokestatic java/lang/Long/toString(J)Ljava/lang/String;
    goto icn_179_alt_g0
icn_179_alt_g0:
    astore 148
    sipush 1
    putstatic rung36_jcon_fncs1/icn_179_alt_gate I
    aload 148
    goto icn_177_waft_1
icn_179_alt_g1:
    astore 149
    sipush 2
    putstatic rung36_jcon_fncs1/icn_179_alt_gate I
    aload 149
    goto icn_177_waft_1
icn_179_α:
    iconst_0
    putstatic rung36_jcon_fncs1/icn_179_alt_gate I
    goto icn_181_α
icn_179_β:
    getstatic rung36_jcon_fncs1/icn_179_alt_gate I
    tableswitch 1 2
        icn_181_β
        icn_180_β
        default: icn_q3_done
icn_177_α:
    goto icn_178_α
icn_177_β:
    goto icn_178_β
    goto icn_177_wentry
icn_177_waft_0:
    astore 150
    getstatic java/lang/System/out Ljava/io/PrintStream;
    aload 150
    invokevirtual java/io/PrintStream/print(Ljava/lang/String;)V
    goto icn_179_α
icn_177_waft_1:
    astore 151
    getstatic java/lang/System/out Ljava/io/PrintStream;
    aload 151
    invokevirtual java/io/PrintStream/print(Ljava/lang/String;)V
    getstatic java/lang/System/out Ljava/io/PrintStream;
    ldc ""
    invokevirtual java/io/PrintStream/println(Ljava/lang/String;)V
    aload 151
    goto icn_q3_s1_sdrain
icn_177_wentry:
    goto icn_178_α
icn_q3_s1_sdrain:
    pop
    goto icn_q3_done
;  STR
icn_184_α:
    ldc "while write(read(f)) ----> "
    goto icn_183_waft_0
icn_184_β:
    goto icn_177_α
;  STR
icn_186_α:
    ldc "none"
    goto icn_185_alt_g1
icn_186_β:
    goto icn_177_α
icn_190_α:
    goto icn_186_α
icn_190_β:
    goto icn_186_α
icn_189_α:
    goto icn_190_α
icn_189_β:
    goto icn_190_β
    goto icn_189_wentry
icn_189_waft_0:
    astore 152
    getstatic java/lang/System/out Ljava/io/PrintStream;
    aload 152
    invokevirtual java/io/PrintStream/print(Ljava/lang/String;)V
    getstatic java/lang/System/out Ljava/io/PrintStream;
    ldc ""
    invokevirtual java/io/PrintStream/println(Ljava/lang/String;)V
    aload 152
    goto icn_188_condok
icn_189_wentry:
    goto icn_190_α
icn_188_condok:
    pop
    goto icn_189_α
icn_188_α:
    goto icn_189_α
icn_188_β:
    goto icn_186_α
icn_187_α:
    goto icn_188_α
icn_187_β:
    goto icn_188_β
icn_187_image_after:
    invokestatic java/lang/Long/toString(J)Ljava/lang/String;
    goto icn_185_alt_g0
icn_185_alt_g0:
    astore 153
    sipush 1
    putstatic rung36_jcon_fncs1/icn_185_alt_gate I
    aload 153
    goto icn_183_waft_1
icn_185_alt_g1:
    astore 154
    sipush 2
    putstatic rung36_jcon_fncs1/icn_185_alt_gate I
    aload 154
    goto icn_183_waft_1
icn_185_α:
    iconst_0
    putstatic rung36_jcon_fncs1/icn_185_alt_gate I
    goto icn_187_α
icn_185_β:
    getstatic rung36_jcon_fncs1/icn_185_alt_gate I
    tableswitch 1 2
        icn_187_β
        icn_186_β
        default: icn_177_α
icn_183_α:
    goto icn_184_α
icn_183_β:
    goto icn_184_β
    goto icn_183_wentry
icn_183_waft_0:
    astore 155
    getstatic java/lang/System/out Ljava/io/PrintStream;
    aload 155
    invokevirtual java/io/PrintStream/print(Ljava/lang/String;)V
    goto icn_185_α
icn_183_waft_1:
    astore 156
    getstatic java/lang/System/out Ljava/io/PrintStream;
    aload 156
    invokevirtual java/io/PrintStream/print(Ljava/lang/String;)V
    getstatic java/lang/System/out Ljava/io/PrintStream;
    ldc ""
    invokevirtual java/io/PrintStream/println(Ljava/lang/String;)V
    aload 156
    goto icn_q3_s0_sdrain
icn_183_wentry:
    goto icn_184_α
icn_q3_s0_sdrain:
    pop
    goto icn_177_α
icn_q3_done:
    iconst_0
    putstatic rung36_jcon_fncs1/icn_suspended B
    iconst_0
    putstatic rung36_jcon_fncs1/icn_suspend_id I
    iconst_1
    putstatic rung36_jcon_fncs1/icn_failed B
    return
icn_q3_ret:
    iconst_0
    putstatic rung36_jcon_fncs1/icn_failed B
    return
icn_q3_sret:
    return
.end method

.method public static icn_q4()V
    .limit stack 16
    .limit locals 302
    lconst_0
    lstore 0
    lconst_0
    lstore 2
    lconst_0
    lstore 4
    lconst_0
    lstore 6
    lconst_0
    lstore 8
    lconst_0
    lstore 10
    lconst_0
    lstore 12
    lconst_0
    lstore 14
    lconst_0
    lstore 16
    lconst_0
    lstore 18
    lconst_0
    lstore 20
    lconst_0
    lstore 22
    lconst_0
    lstore 24
    lconst_0
    lstore 26
    lconst_0
    lstore 28
    lconst_0
    lstore 30
    lconst_0
    lstore 32
    lconst_0
    lstore 34
    lconst_0
    lstore 36
    lconst_0
    lstore 38
    lconst_0
    lstore 40
    lconst_0
    lstore 42
    lconst_0
    lstore 44
    lconst_0
    lstore 46
    lconst_0
    lstore 48
    lconst_0
    lstore 50
    lconst_0
    lstore 52
    lconst_0
    lstore 54
    lconst_0
    lstore 56
    lconst_0
    lstore 58
    lconst_0
    lstore 60
    lconst_0
    lstore 62
    iconst_0
    istore 84
    iconst_0
    istore 85
    iconst_0
    istore 86
    iconst_0
    istore 87
    aconst_null
    astore 148
    aconst_null
    astore 149
    aconst_null
    astore 150
    aconst_null
    astore 151
    goto icn_209_α
;  VAR
icn_195_α:
    getstatic rung36_jcon_fncs1/icn_pv_q4_L Ljava/util/ArrayList;
    goto icn_194_sort_rel
icn_195_β:
    goto icn_q4_done
icn_194_α:
    goto icn_195_α
icn_194_β:
    goto icn_q4_done
icn_194_sort_rel:
    putstatic rung36_jcon_fncs1/icn_194_sort_list Ljava/util/ArrayList;
    getstatic rung36_jcon_fncs1/icn_194_sort_list Ljava/util/ArrayList;
    invokestatic rung36_jcon_fncs1/icn_builtin_sort(Ljava/util/ArrayList;)Ljava/util/ArrayList;
    goto icn_193_bang_st
icn_193_α:
    goto icn_194_α
icn_193_β:
    goto icn_193_bang_chk
icn_193_bang_st:
    putstatic rung36_jcon_fncs1/icn_193_bang_list Ljava/util/ArrayList;
    iconst_0
    putstatic rung36_jcon_fncs1/icn_193_bang_idx I
icn_193_bang_chk:
    getstatic rung36_jcon_fncs1/icn_193_bang_list Ljava/util/ArrayList;
    invokevirtual java/util/ArrayList/size()I
    getstatic rung36_jcon_fncs1/icn_193_bang_idx I
    if_icmple icn_q4_done
    getstatic rung36_jcon_fncs1/icn_193_bang_list Ljava/util/ArrayList;
    getstatic rung36_jcon_fncs1/icn_193_bang_idx I
    invokevirtual java/util/ArrayList/get(I)Ljava/lang/Object;
icn_193_bang_ok:
    checkcast java/lang/Long
    invokevirtual java/lang/Long/longValue()J
    getstatic rung36_jcon_fncs1/icn_193_bang_idx I
    iconst_1
    iadd
    putstatic rung36_jcon_fncs1/icn_193_bang_idx I
    goto icn_192_waft_0
icn_192_α:
    goto icn_193_α
icn_192_β:
    goto icn_193_β
    goto icn_192_wentry
icn_192_waft_0:
    lstore 4
    getstatic java/lang/System/out Ljava/io/PrintStream;
    lload 4
    invokevirtual java/io/PrintStream/print(J)V
    getstatic java/lang/System/out Ljava/io/PrintStream;
    ldc ""
    invokevirtual java/io/PrintStream/println(Ljava/lang/String;)V
    lload 4
    goto icn_191_gdrain
icn_192_wentry:
    goto icn_193_α
icn_191_gdrain:
    pop2
icn_191_pump:
    goto icn_192_β
icn_191_α:
    goto icn_192_α
icn_191_β:
    goto icn_q4_done
;  VAR
icn_198_α:
    getstatic rung36_jcon_fncs1/icn_pv_q4_L Ljava/util/ArrayList;
    goto icn_197_lr
icn_198_β:
    goto icn_191_α
;  VAR
icn_200_α:
    getstatic rung36_jcon_fncs1/icn_pv_q4_T Ljava/util/HashMap;
    goto icn_199_ktr
icn_200_β:
    goto icn_191_α
icn_199_α:
    getstatic rung36_jcon_fncs1/icn_199_kinit I
    ifne icn_199_kchk
    goto icn_200_α
icn_199_ktr:
    putstatic rung36_jcon_fncs1/icn_199_ktbl Ljava/util/HashMap;
    getstatic rung36_jcon_fncs1/icn_199_ktbl Ljava/util/HashMap;
    invokevirtual java/util/HashMap/keySet()Ljava/util/Set;
    invokeinterface java/util/Set/toArray()[Ljava/lang/Object; 1
    putstatic rung36_jcon_fncs1/icn_199_karr [Ljava/lang/Object;
    iconst_0
    putstatic rung36_jcon_fncs1/icn_199_kidx I
    iconst_1
    putstatic rung36_jcon_fncs1/icn_199_kinit I
    goto icn_199_kchk
icn_199_β:
    getstatic rung36_jcon_fncs1/icn_199_kidx I
    iconst_1
    iadd
    putstatic rung36_jcon_fncs1/icn_199_kidx I
icn_199_kchk:
    getstatic rung36_jcon_fncs1/icn_199_karr [Ljava/lang/Object;
    checkcast [Ljava/lang/Object;
    arraylength
    getstatic rung36_jcon_fncs1/icn_199_kidx I
    if_icmple icn_191_α
    getstatic rung36_jcon_fncs1/icn_199_karr [Ljava/lang/Object;
    checkcast [Ljava/lang/Object;
    getstatic rung36_jcon_fncs1/icn_199_kidx I
    aaload
    checkcast java/lang/String
    invokestatic java/lang/Long/parseLong(Ljava/lang/String;)J
    goto icn_197_vr
icn_197_α:
    goto icn_198_α
icn_197_β:
    goto icn_191_α
icn_197_lr:
    putstatic rung36_jcon_fncs1/icn_197_pushlist Ljava/util/ArrayList;
    goto icn_199_α
icn_197_vr:
    invokestatic java/lang/Long/valueOf(J)Ljava/lang/Long;
    putstatic rung36_jcon_fncs1/icn_197_pushval Ljava/lang/Object;
    getstatic rung36_jcon_fncs1/icn_197_pushlist Ljava/util/ArrayList;
    getstatic rung36_jcon_fncs1/icn_197_pushval Ljava/lang/Object;
    invokevirtual java/util/ArrayList/add(Ljava/lang/Object;)Z
    pop
    getstatic rung36_jcon_fncs1/icn_197_pushlist Ljava/util/ArrayList;
    goto icn_196_gdrain
icn_196_gdrain:
    pop
icn_196_pump:
    goto icn_197_β
icn_196_α:
    goto icn_197_α
icn_196_β:
    goto icn_191_α
;  INT
icn_203_α:
    ldc2_w 1
    goto icn_202_tsa_vr
icn_203_β:
    goto icn_196_α
;  INT
icn_205_α:
    ldc2_w 20
    goto icn_204_e2relay
icn_205_β:
    goto icn_204_e1b
;  INT
icn_206_α:
    ldc2_w 1
    goto icn_204_e1relay
icn_206_β:
    goto icn_196_α
icn_204_e1relay:
    putstatic rung36_jcon_fncs1/icn_204_e1val J
    goto icn_205_α
icn_204_e2relay:
    putstatic rung36_jcon_fncs1/icn_204_e2val J
    goto icn_204_init
icn_204_e1b:
    iconst_0
    putstatic rung36_jcon_fncs1/icn_204_e2seen I
    goto icn_206_β
icn_204_e2b:
    goto icn_205_β
icn_204_α:
    iconst_0
    putstatic rung36_jcon_fncs1/icn_204_e2seen I
    goto icn_206_α
icn_204_β:
    getstatic rung36_jcon_fncs1/icn_204_I J
    lconst_1
    ladd
    putstatic rung36_jcon_fncs1/icn_204_I J
    goto icn_204_code
icn_204_init:
    getstatic rung36_jcon_fncs1/icn_204_e2val J
    putstatic rung36_jcon_fncs1/icn_204_bound J
    getstatic rung36_jcon_fncs1/icn_204_e2seen I
    ifne icn_204_init_e2adv
    getstatic rung36_jcon_fncs1/icn_204_e1val J
    putstatic rung36_jcon_fncs1/icn_204_e1cur J
    getstatic rung36_jcon_fncs1/icn_204_e1cur J
    putstatic rung36_jcon_fncs1/icn_204_I J
    iconst_1
    putstatic rung36_jcon_fncs1/icn_204_e2seen I
    goto icn_204_code
icn_204_init_e2adv:
    getstatic rung36_jcon_fncs1/icn_204_e1cur J
    putstatic rung36_jcon_fncs1/icn_204_I J
    goto icn_204_code
icn_204_code:
    getstatic rung36_jcon_fncs1/icn_204_I J
    getstatic rung36_jcon_fncs1/icn_204_bound J
    lcmp
    ifgt icn_204_e2b
    getstatic rung36_jcon_fncs1/icn_204_I J
    goto icn_202_tsa_kr
icn_202_α:
    goto icn_203_α
icn_202_β:
    goto icn_196_α
icn_202_tsa_vr:
    dup2
    putstatic rung36_jcon_fncs1/icn_202_tsa_vl J
    invokestatic java/lang/Long/valueOf(J)Ljava/lang/Long;
    putstatic rung36_jcon_fncs1/icn_202_tsa_vo Ljava/lang/Object;
    goto icn_204_α
icn_202_tsa_kr:
    invokestatic java/lang/Long/toString(J)Ljava/lang/String;
    putstatic rung36_jcon_fncs1/icn_202_tsa_ks Ljava/lang/String;
    goto icn_202_tsa_put
icn_202_tsa_put:
    getstatic rung36_jcon_fncs1/icn_pv_q4_T Ljava/util/HashMap;
    getstatic rung36_jcon_fncs1/icn_202_tsa_ks Ljava/lang/String;
    getstatic rung36_jcon_fncs1/icn_202_tsa_vo Ljava/lang/Object;
    invokevirtual java/util/HashMap/put(Ljava/lang/Object;Ljava/lang/Object;)Ljava/lang/Object;
    pop
    getstatic rung36_jcon_fncs1/icn_202_tsa_vl J
    goto icn_201_gdrain
icn_201_gdrain:
    pop2
icn_201_pump:
    goto icn_202_β
icn_201_α:
    goto icn_202_α
icn_201_β:
    goto icn_196_α
icn_208_α:
    goto icn_201_α
icn_208_β:
    goto icn_201_α
icn_207_α:
    goto icn_208_α
icn_207_β:
    goto icn_208_β
icn_207_store:
    putstatic rung36_jcon_fncs1/icn_pv_q4_L Ljava/util/ArrayList;
    getstatic rung36_jcon_fncs1/icn_pv_q4_L Ljava/util/ArrayList;
    goto icn_q4_s1_sdrain
icn_q4_s1_sdrain:
    pop
    goto icn_201_α
icn_210_α:
    goto icn_207_α
icn_210_β:
    goto icn_207_α
icn_209_α:
    goto icn_210_α
icn_209_β:
    goto icn_210_β
icn_209_store:
    putstatic rung36_jcon_fncs1/icn_pv_q4_T Ljava/util/HashMap;
    getstatic rung36_jcon_fncs1/icn_pv_q4_T Ljava/util/HashMap;
    goto icn_q4_s0_sdrain
icn_q4_s0_sdrain:
    pop
    goto icn_207_α
icn_q4_done:
    iconst_0
    putstatic rung36_jcon_fncs1/icn_suspended B
    iconst_0
    putstatic rung36_jcon_fncs1/icn_suspend_id I
    iconst_1
    putstatic rung36_jcon_fncs1/icn_failed B
    return
icn_q4_ret:
    iconst_0
    putstatic rung36_jcon_fncs1/icn_failed B
    return
icn_q4_sret:
    return
.end method

.method public static icn_q5()V
    .limit stack 16
    .limit locals 338
    lconst_0
    lstore 0
    lconst_0
    lstore 2
    lconst_0
    lstore 4
    lconst_0
    lstore 6
    lconst_0
    lstore 8
    lconst_0
    lstore 10
    lconst_0
    lstore 12
    lconst_0
    lstore 14
    lconst_0
    lstore 16
    lconst_0
    lstore 18
    lconst_0
    lstore 20
    lconst_0
    lstore 22
    lconst_0
    lstore 24
    lconst_0
    lstore 26
    lconst_0
    lstore 28
    lconst_0
    lstore 30
    lconst_0
    lstore 32
    lconst_0
    lstore 34
    lconst_0
    lstore 36
    lconst_0
    lstore 38
    lconst_0
    lstore 40
    lconst_0
    lstore 42
    lconst_0
    lstore 44
    lconst_0
    lstore 46
    lconst_0
    lstore 48
    lconst_0
    lstore 50
    lconst_0
    lstore 52
    lconst_0
    lstore 54
    lconst_0
    lstore 56
    lconst_0
    lstore 58
    lconst_0
    lstore 60
    lconst_0
    lstore 62
    iconst_0
    istore 84
    iconst_0
    istore 85
    iconst_0
    istore 86
    iconst_0
    istore 87
    aconst_null
    astore 148
    aconst_null
    astore 149
    aconst_null
    astore 150
    aconst_null
    astore 151
    aconst_null
    astore 152
    aconst_null
    astore 153
    goto icn_211_α
;  VAR
icn_215_α:
    getstatic rung36_jcon_fncs1/icn_pv_q5_i J
    goto icn_214_rrelay
icn_215_β:
    goto icn_214_lb
;  REAL
icn_216_α:
    ldc2_w 0.25d
    goto icn_214_lrelay
icn_216_β:
    goto icn_212_seq_rf_0
icn_214_lrelay:
    putstatic rung36_jcon_fncs1/icn_214_binop_lc D
    goto icn_214_lstore
icn_214_rrelay:
    l2d
    putstatic rung36_jcon_fncs1/icn_214_binop_rc D
    goto icn_214_compute
icn_214_lb:
    goto icn_216_β
icn_214_α:
    iconst_0
    putstatic rung36_jcon_fncs1/icn_214_binop_bf I
    goto icn_216_α
icn_214_β:
    iconst_1
    putstatic rung36_jcon_fncs1/icn_214_binop_bf I
    goto icn_216_α
icn_214_lstore:
    getstatic rung36_jcon_fncs1/icn_214_binop_bf I
    ifeq icn_215_α
    goto icn_215_β
icn_214_compute:
    getstatic rung36_jcon_fncs1/icn_214_binop_lc D
    getstatic rung36_jcon_fncs1/icn_214_binop_rc D
    dmul
    goto icn_213_store
icn_213_α:
    goto icn_214_α
icn_213_β:
    goto icn_214_β
icn_213_store:
    putstatic rung36_jcon_fncs1/icn_pv_q5_v D
    getstatic rung36_jcon_fncs1/icn_pv_q5_v D
    goto icn_212_seq_rg_0
;  VAR
icn_218_α:
    getstatic rung36_jcon_fncs1/icn_pv_q5_v D
    goto icn_217_arg0
icn_218_β:
    goto icn_212_seq_rf_1
icn_217_arg0:
    putstatic rung36_jcon_fncs1/icn_arg_0 J
    goto icn_217_docall
icn_217_α:
    goto icn_218_α
icn_217_β:
    goto icn_218_β
icn_217_docall:
    getstatic rung36_jcon_fncs1/icn_202_tsa_vl J
    lstore 152
    getstatic rung36_jcon_fncs1/icn_204_I J
    lstore 154
    getstatic rung36_jcon_fncs1/icn_204_bound J
    lstore 156
    getstatic rung36_jcon_fncs1/icn_204_e1cur J
    lstore 158
    getstatic rung36_jcon_fncs1/icn_204_e1val J
    lstore 160
    getstatic rung36_jcon_fncs1/icn_204_e2val J
    lstore 162
    getstatic rung36_jcon_fncs1/icn_pv_q5_i J
    lstore 164
    invokestatic rung36_jcon_fncs1/icn_wf()V
    lload 152
    putstatic rung36_jcon_fncs1/icn_202_tsa_vl J
    lload 154
    putstatic rung36_jcon_fncs1/icn_204_I J
    lload 156
    putstatic rung36_jcon_fncs1/icn_204_bound J
    lload 158
    putstatic rung36_jcon_fncs1/icn_204_e1cur J
    lload 160
    putstatic rung36_jcon_fncs1/icn_204_e1val J
    lload 162
    putstatic rung36_jcon_fncs1/icn_204_e2val J
    lload 164
    putstatic rung36_jcon_fncs1/icn_pv_q5_i J
    getstatic rung36_jcon_fncs1/icn_failed B
    ifne icn_217_after_call
    getstatic rung36_jcon_fncs1/icn_retval J
    goto icn_212_seq_rg_1
icn_217_after_call:
    goto icn_212_seq_rf_1
icn_222_α:
    goto icn_212_seq_rf_2
icn_222_β:
    goto icn_212_seq_rf_2
icn_221_arg0:
    putstatic rung36_jcon_fncs1/icn_arg_0 J
    goto icn_221_docall
icn_221_α:
    goto icn_222_α
icn_221_β:
    goto icn_222_β
icn_221_docall:
    getstatic rung36_jcon_fncs1/icn_202_tsa_vl J
    lstore 152
    getstatic rung36_jcon_fncs1/icn_204_I J
    lstore 154
    getstatic rung36_jcon_fncs1/icn_204_bound J
    lstore 156
    getstatic rung36_jcon_fncs1/icn_204_e1cur J
    lstore 158
    getstatic rung36_jcon_fncs1/icn_204_e1val J
    lstore 160
    getstatic rung36_jcon_fncs1/icn_204_e2val J
    lstore 162
    getstatic rung36_jcon_fncs1/icn_pv_q5_i J
    lstore 164
    invokestatic rung36_jcon_fncs1/icn_wf()V
    lload 152
    putstatic rung36_jcon_fncs1/icn_202_tsa_vl J
    lload 154
    putstatic rung36_jcon_fncs1/icn_204_I J
    lload 156
    putstatic rung36_jcon_fncs1/icn_204_bound J
    lload 158
    putstatic rung36_jcon_fncs1/icn_204_e1cur J
    lload 160
    putstatic rung36_jcon_fncs1/icn_204_e1val J
    lload 162
    putstatic rung36_jcon_fncs1/icn_204_e2val J
    lload 164
    putstatic rung36_jcon_fncs1/icn_pv_q5_i J
    getstatic rung36_jcon_fncs1/icn_failed B
    ifne icn_221_after_call
    getstatic rung36_jcon_fncs1/icn_retval J
    goto icn_220_gdrain
icn_221_after_call:
    goto icn_212_seq_rf_2
icn_220_gdrain:
    pop2
icn_220_pump:
    goto icn_221_β
icn_220_α:
    goto icn_221_α
icn_220_β:
    goto icn_212_seq_rf_2
;  STR
icn_226_α:
    ldc ""
    goto icn_225_alt_g1
icn_226_β:
    goto icn_212_seq_rf_2
;  STR
icn_227_α:
    ldc ""
    goto icn_225_alt_g0
icn_227_β:
    goto icn_226_α
icn_225_alt_g0:
    astore 148
    sipush 1
    putstatic rung36_jcon_fncs1/icn_225_alt_gate I
    aload 148
    goto icn_224_arg0
icn_225_alt_g1:
    astore 149
    sipush 2
    putstatic rung36_jcon_fncs1/icn_225_alt_gate I
    aload 149
    goto icn_224_arg0
icn_225_α:
    iconst_0
    putstatic rung36_jcon_fncs1/icn_225_alt_gate I
    goto icn_227_α
icn_225_β:
    getstatic rung36_jcon_fncs1/icn_225_alt_gate I
    tableswitch 1 2
        icn_227_β
        icn_226_β
        default: icn_212_seq_rf_2
icn_224_arg0:
    putstatic rung36_jcon_fncs1/icn_arg_str_0 Ljava/lang/String;
    lconst_0
    putstatic rung36_jcon_fncs1/icn_arg_0 J
    goto icn_224_docall
icn_224_α:
    goto icn_225_α
icn_224_β:
    goto icn_225_β
icn_224_docall:
    getstatic rung36_jcon_fncs1/icn_202_tsa_vl J
    lstore 154
    getstatic rung36_jcon_fncs1/icn_204_I J
    lstore 156
    getstatic rung36_jcon_fncs1/icn_204_bound J
    lstore 158
    getstatic rung36_jcon_fncs1/icn_204_e1cur J
    lstore 160
    getstatic rung36_jcon_fncs1/icn_204_e1val J
    lstore 162
    getstatic rung36_jcon_fncs1/icn_204_e2val J
    lstore 164
    getstatic rung36_jcon_fncs1/icn_pv_q5_i J
    lstore 166
    invokestatic rung36_jcon_fncs1/icn_wf()V
    lload 154
    putstatic rung36_jcon_fncs1/icn_202_tsa_vl J
    lload 156
    putstatic rung36_jcon_fncs1/icn_204_I J
    lload 158
    putstatic rung36_jcon_fncs1/icn_204_bound J
    lload 160
    putstatic rung36_jcon_fncs1/icn_204_e1cur J
    lload 162
    putstatic rung36_jcon_fncs1/icn_204_e1val J
    lload 164
    putstatic rung36_jcon_fncs1/icn_204_e2val J
    lload 166
    putstatic rung36_jcon_fncs1/icn_pv_q5_i J
    getstatic rung36_jcon_fncs1/icn_failed B
    ifne icn_224_after_call
    getstatic rung36_jcon_fncs1/icn_retval J
    goto icn_223_gdrain
icn_224_after_call:
    goto icn_212_seq_rf_2
icn_223_gdrain:
    pop2
icn_223_pump:
    goto icn_224_β
icn_223_α:
    goto icn_224_α
icn_223_β:
    goto icn_212_seq_rf_2
;  REAL
icn_229_α:
    ldc2_w 1.0d
    goto icn_228_rrelay
icn_229_β:
    goto icn_228_lb
;  VAR
icn_230_α:
    getstatic rung36_jcon_fncs1/icn_pv_q5_v D
    goto icn_228_lrelay
icn_230_β:
    goto icn_219_else
icn_228_lrelay:
    putstatic rung36_jcon_fncs1/icn_228_relop_lc D
    goto icn_228_lstore
icn_228_rrelay:
    putstatic rung36_jcon_fncs1/icn_228_relop_rc D
    goto icn_228_check
icn_228_lb:
    goto icn_230_β
icn_228_α:
    goto icn_230_α
icn_228_β:
    goto icn_229_β
icn_228_lstore:
    goto icn_229_α
icn_228_check:
    getstatic rung36_jcon_fncs1/icn_228_relop_lc D
    getstatic rung36_jcon_fncs1/icn_228_relop_rc D
    dcmpl
    ifgt icn_229_β
    getstatic rung36_jcon_fncs1/icn_228_relop_rc D
    goto icn_219_then
icn_219_then:
    pop2
    goto icn_220_α
icn_219_else:
    goto icn_223_α
icn_219_α:
    goto icn_228_α
icn_219_β:
    goto icn_228_β
icn_234_α:
    goto icn_212_seq_rf_3
icn_234_β:
    goto icn_212_seq_rf_3
icn_235_α:
    goto icn_234_α
icn_235_β:
    goto icn_234_α
icn_233_alt_g0:
    putstatic rung36_jcon_fncs1/icn_233_alt_val J
    sipush 1
    putstatic rung36_jcon_fncs1/icn_233_alt_gate I
    getstatic rung36_jcon_fncs1/icn_233_alt_val J
    goto icn_232_arg0
icn_233_alt_g1:
    putstatic rung36_jcon_fncs1/icn_233_alt_val J
    sipush 2
    putstatic rung36_jcon_fncs1/icn_233_alt_gate I
    getstatic rung36_jcon_fncs1/icn_233_alt_val J
    goto icn_232_arg0
icn_233_α:
    iconst_0
    putstatic rung36_jcon_fncs1/icn_233_alt_gate I
    goto icn_235_α
icn_233_β:
    getstatic rung36_jcon_fncs1/icn_233_alt_gate I
    tableswitch 1 2
        icn_235_β
        icn_234_β
        default: icn_212_seq_rf_3
icn_232_arg0:
    putstatic rung36_jcon_fncs1/icn_arg_0 J
    goto icn_232_docall
icn_232_α:
    goto icn_233_α
icn_232_β:
    goto icn_233_β
icn_232_docall:
    getstatic rung36_jcon_fncs1/icn_202_tsa_vl J
    lstore 154
    getstatic rung36_jcon_fncs1/icn_204_I J
    lstore 156
    getstatic rung36_jcon_fncs1/icn_204_bound J
    lstore 158
    getstatic rung36_jcon_fncs1/icn_204_e1cur J
    lstore 160
    getstatic rung36_jcon_fncs1/icn_204_e1val J
    lstore 162
    getstatic rung36_jcon_fncs1/icn_204_e2val J
    lstore 164
    getstatic rung36_jcon_fncs1/icn_pv_q5_i J
    lstore 166
    getstatic rung36_jcon_fncs1/icn_233_alt_val J
    lstore 168
    invokestatic rung36_jcon_fncs1/icn_wf()V
    lload 154
    putstatic rung36_jcon_fncs1/icn_202_tsa_vl J
    lload 156
    putstatic rung36_jcon_fncs1/icn_204_I J
    lload 158
    putstatic rung36_jcon_fncs1/icn_204_bound J
    lload 160
    putstatic rung36_jcon_fncs1/icn_204_e1cur J
    lload 162
    putstatic rung36_jcon_fncs1/icn_204_e1val J
    lload 164
    putstatic rung36_jcon_fncs1/icn_204_e2val J
    lload 166
    putstatic rung36_jcon_fncs1/icn_pv_q5_i J
    lload 168
    putstatic rung36_jcon_fncs1/icn_233_alt_val J
    getstatic rung36_jcon_fncs1/icn_failed B
    ifne icn_232_after_call
    getstatic rung36_jcon_fncs1/icn_retval J
    goto icn_231_gdrain
icn_232_after_call:
    goto icn_212_seq_rf_3
icn_231_gdrain:
    pop2
icn_231_pump:
    goto icn_232_β
icn_231_α:
    goto icn_232_α
icn_231_β:
    goto icn_212_seq_rf_3
icn_238_α:
    goto icn_212_seq_rf_4
icn_238_β:
    goto icn_212_seq_rf_4
icn_237_arg0:
    putstatic rung36_jcon_fncs1/icn_arg_0 J
    goto icn_237_docall
icn_237_α:
    goto icn_238_α
icn_237_β:
    goto icn_238_β
icn_237_docall:
    getstatic rung36_jcon_fncs1/icn_202_tsa_vl J
    lstore 154
    getstatic rung36_jcon_fncs1/icn_204_I J
    lstore 156
    getstatic rung36_jcon_fncs1/icn_204_bound J
    lstore 158
    getstatic rung36_jcon_fncs1/icn_204_e1cur J
    lstore 160
    getstatic rung36_jcon_fncs1/icn_204_e1val J
    lstore 162
    getstatic rung36_jcon_fncs1/icn_204_e2val J
    lstore 164
    getstatic rung36_jcon_fncs1/icn_pv_q5_i J
    lstore 166
    getstatic rung36_jcon_fncs1/icn_233_alt_val J
    lstore 168
    invokestatic rung36_jcon_fncs1/icn_wf()V
    lload 154
    putstatic rung36_jcon_fncs1/icn_202_tsa_vl J
    lload 156
    putstatic rung36_jcon_fncs1/icn_204_I J
    lload 158
    putstatic rung36_jcon_fncs1/icn_204_bound J
    lload 160
    putstatic rung36_jcon_fncs1/icn_204_e1cur J
    lload 162
    putstatic rung36_jcon_fncs1/icn_204_e1val J
    lload 164
    putstatic rung36_jcon_fncs1/icn_204_e2val J
    lload 166
    putstatic rung36_jcon_fncs1/icn_pv_q5_i J
    lload 168
    putstatic rung36_jcon_fncs1/icn_233_alt_val J
    getstatic rung36_jcon_fncs1/icn_failed B
    ifne icn_237_after_call
    getstatic rung36_jcon_fncs1/icn_retval J
    goto icn_236_gdrain
icn_237_after_call:
    goto icn_212_seq_rf_4
icn_236_gdrain:
    pop2
icn_236_pump:
    goto icn_237_β
icn_236_α:
    goto icn_237_α
icn_236_β:
    goto icn_212_seq_rf_4
icn_241_α:
    goto icn_212_seq_rf_5
icn_241_β:
    goto icn_212_seq_rf_5
icn_240_arg0:
    putstatic rung36_jcon_fncs1/icn_arg_0 J
    goto icn_240_docall
icn_240_α:
    goto icn_241_α
icn_240_β:
    goto icn_241_β
icn_240_docall:
    getstatic rung36_jcon_fncs1/icn_202_tsa_vl J
    lstore 154
    getstatic rung36_jcon_fncs1/icn_204_I J
    lstore 156
    getstatic rung36_jcon_fncs1/icn_204_bound J
    lstore 158
    getstatic rung36_jcon_fncs1/icn_204_e1cur J
    lstore 160
    getstatic rung36_jcon_fncs1/icn_204_e1val J
    lstore 162
    getstatic rung36_jcon_fncs1/icn_204_e2val J
    lstore 164
    getstatic rung36_jcon_fncs1/icn_pv_q5_i J
    lstore 166
    getstatic rung36_jcon_fncs1/icn_233_alt_val J
    lstore 168
    invokestatic rung36_jcon_fncs1/icn_wf()V
    lload 154
    putstatic rung36_jcon_fncs1/icn_202_tsa_vl J
    lload 156
    putstatic rung36_jcon_fncs1/icn_204_I J
    lload 158
    putstatic rung36_jcon_fncs1/icn_204_bound J
    lload 160
    putstatic rung36_jcon_fncs1/icn_204_e1cur J
    lload 162
    putstatic rung36_jcon_fncs1/icn_204_e1val J
    lload 164
    putstatic rung36_jcon_fncs1/icn_204_e2val J
    lload 166
    putstatic rung36_jcon_fncs1/icn_pv_q5_i J
    lload 168
    putstatic rung36_jcon_fncs1/icn_233_alt_val J
    getstatic rung36_jcon_fncs1/icn_failed B
    ifne icn_240_after_call
    getstatic rung36_jcon_fncs1/icn_retval J
    goto icn_239_gdrain
icn_240_after_call:
    goto icn_212_seq_rf_5
icn_239_gdrain:
    pop2
icn_239_pump:
    goto icn_240_β
icn_239_α:
    goto icn_240_α
icn_239_β:
    goto icn_212_seq_rf_5
icn_243_α:
    goto icn_212_seq_rf_6
icn_243_β:
    goto icn_212_seq_rf_6
icn_242_arg0:
    putstatic rung36_jcon_fncs1/icn_arg_0 J
    goto icn_242_docall
icn_242_α:
    goto icn_243_α
icn_242_β:
    goto icn_243_β
icn_242_docall:
    getstatic rung36_jcon_fncs1/icn_202_tsa_vl J
    lstore 154
    getstatic rung36_jcon_fncs1/icn_204_I J
    lstore 156
    getstatic rung36_jcon_fncs1/icn_204_bound J
    lstore 158
    getstatic rung36_jcon_fncs1/icn_204_e1cur J
    lstore 160
    getstatic rung36_jcon_fncs1/icn_204_e1val J
    lstore 162
    getstatic rung36_jcon_fncs1/icn_204_e2val J
    lstore 164
    getstatic rung36_jcon_fncs1/icn_pv_q5_i J
    lstore 166
    getstatic rung36_jcon_fncs1/icn_233_alt_val J
    lstore 168
    invokestatic rung36_jcon_fncs1/icn_wf()V
    lload 154
    putstatic rung36_jcon_fncs1/icn_202_tsa_vl J
    lload 156
    putstatic rung36_jcon_fncs1/icn_204_I J
    lload 158
    putstatic rung36_jcon_fncs1/icn_204_bound J
    lload 160
    putstatic rung36_jcon_fncs1/icn_204_e1cur J
    lload 162
    putstatic rung36_jcon_fncs1/icn_204_e1val J
    lload 164
    putstatic rung36_jcon_fncs1/icn_204_e2val J
    lload 166
    putstatic rung36_jcon_fncs1/icn_pv_q5_i J
    lload 168
    putstatic rung36_jcon_fncs1/icn_233_alt_val J
    getstatic rung36_jcon_fncs1/icn_failed B
    ifne icn_242_after_call
    getstatic rung36_jcon_fncs1/icn_retval J
    goto icn_212_seq_rg_6
icn_242_after_call:
    goto icn_212_seq_rf_6
icn_244_α:
    getstatic java/lang/System/out Ljava/io/PrintStream;
    ldc ""
    invokevirtual java/io/PrintStream/println(Ljava/lang/String;)V
    goto icn_211_bdrain
icn_244_β:
    goto icn_211_pump
    goto icn_212_α
icn_212_seq_rg_0:
    pop2
    goto icn_217_α
icn_212_seq_rg_1:
    pop2
    goto icn_219_α
icn_212_seq_rg_2:
    pop2
    goto icn_231_α
icn_212_seq_rg_3:
    pop2
    goto icn_236_α
icn_212_seq_rg_4:
    pop2
    goto icn_239_α
icn_212_seq_rg_5:
    pop2
    goto icn_242_α
icn_212_seq_rg_6:
    pop2
    goto icn_244_α
icn_212_seq_rf_0:
    goto icn_217_α
icn_212_seq_rf_1:
    goto icn_219_α
icn_212_seq_rf_2:
    goto icn_231_α
icn_212_seq_rf_3:
    goto icn_236_α
icn_212_seq_rf_4:
    goto icn_239_α
icn_212_seq_rf_5:
    goto icn_242_α
icn_212_seq_rf_6:
    goto icn_244_α
icn_212_α:
    goto icn_213_α
icn_212_β:
    goto icn_244_β
;  INT
icn_247_α:
    ldc2_w 25
    goto icn_246_e2relay
icn_247_β:
    goto icn_246_e1b
;  INT
icn_248_α:
    ldc2_w 1
    goto icn_246_e1relay
icn_248_β:
    goto icn_q5_done
icn_246_e1relay:
    putstatic rung36_jcon_fncs1/icn_246_e1val J
    goto icn_247_α
icn_246_e2relay:
    putstatic rung36_jcon_fncs1/icn_246_e2val J
    goto icn_246_init
icn_246_e1b:
    iconst_0
    putstatic rung36_jcon_fncs1/icn_246_e2seen I
    goto icn_248_β
icn_246_e2b:
    goto icn_247_β
icn_246_α:
    iconst_0
    putstatic rung36_jcon_fncs1/icn_246_e2seen I
    goto icn_248_α
icn_246_β:
    getstatic rung36_jcon_fncs1/icn_246_I J
    lconst_1
    ladd
    putstatic rung36_jcon_fncs1/icn_246_I J
    goto icn_246_code
icn_246_init:
    getstatic rung36_jcon_fncs1/icn_246_e2val J
    putstatic rung36_jcon_fncs1/icn_246_bound J
    getstatic rung36_jcon_fncs1/icn_246_e2seen I
    ifne icn_246_init_e2adv
    getstatic rung36_jcon_fncs1/icn_246_e1val J
    putstatic rung36_jcon_fncs1/icn_246_e1cur J
    getstatic rung36_jcon_fncs1/icn_246_e1cur J
    putstatic rung36_jcon_fncs1/icn_246_I J
    iconst_1
    putstatic rung36_jcon_fncs1/icn_246_e2seen I
    goto icn_246_code
icn_246_init_e2adv:
    getstatic rung36_jcon_fncs1/icn_246_e1cur J
    putstatic rung36_jcon_fncs1/icn_246_I J
    goto icn_246_code
icn_246_code:
    getstatic rung36_jcon_fncs1/icn_246_I J
    getstatic rung36_jcon_fncs1/icn_246_bound J
    lcmp
    ifgt icn_246_e2b
    getstatic rung36_jcon_fncs1/icn_246_I J
    goto icn_245_store
icn_245_α:
    goto icn_246_α
icn_245_β:
    goto icn_246_β
icn_245_store:
    putstatic rung36_jcon_fncs1/icn_pv_q5_i J
    getstatic rung36_jcon_fncs1/icn_pv_q5_i J
    goto icn_211_gdrain
icn_211_gdrain:
    pop2
    goto icn_212_α
icn_211_bdrain:
    pop2
icn_211_pump:
    goto icn_245_β
icn_211_α:
    goto icn_245_α
icn_211_β:
    goto icn_q5_done
icn_q5_done:
    iconst_0
    putstatic rung36_jcon_fncs1/icn_suspended B
    iconst_0
    putstatic rung36_jcon_fncs1/icn_suspend_id I
    iconst_1
    putstatic rung36_jcon_fncs1/icn_failed B
    return
icn_q5_ret:
    iconst_0
    putstatic rung36_jcon_fncs1/icn_failed B
    return
icn_q5_sret:
    return
.end method

.method public static icn_wf()V
    .limit stack 16
    .limit locals 336
    lconst_0
    lstore 0
    lconst_0
    lstore 2
    lconst_0
    lstore 4
    lconst_0
    lstore 6
    lconst_0
    lstore 8
    lconst_0
    lstore 10
    lconst_0
    lstore 12
    lconst_0
    lstore 14
    lconst_0
    lstore 16
    lconst_0
    lstore 18
    lconst_0
    lstore 20
    lconst_0
    lstore 22
    lconst_0
    lstore 24
    lconst_0
    lstore 26
    lconst_0
    lstore 28
    lconst_0
    lstore 30
    lconst_0
    lstore 32
    lconst_0
    lstore 34
    lconst_0
    lstore 36
    lconst_0
    lstore 38
    lconst_0
    lstore 40
    lconst_0
    lstore 42
    lconst_0
    lstore 44
    lconst_0
    lstore 46
    lconst_0
    lstore 48
    lconst_0
    lstore 50
    lconst_0
    lstore 52
    lconst_0
    lstore 54
    lconst_0
    lstore 56
    lconst_0
    lstore 58
    lconst_0
    lstore 60
    lconst_0
    lstore 62
    iconst_0
    istore 84
    iconst_0
    istore 85
    iconst_0
    istore 86
    iconst_0
    istore 87
    aconst_null
    astore 148
    aconst_null
    astore 149
    aconst_null
    astore 150
    aconst_null
    astore 151
    getstatic rung36_jcon_fncs1/icn_arg_str_0 Ljava/lang/String;
    putstatic rung36_jcon_fncs1/icn_pv_wf_v Ljava/lang/String;
    goto icn_249_α
icn_249_α:
    goto icn_wf_done
icn_249_β:
    goto icn_wf_done
icn_wf_s0_sdrain:
    pop2
    goto icn_wf_done
icn_wf_done:
    iconst_0
    putstatic rung36_jcon_fncs1/icn_suspended B
    iconst_0
    putstatic rung36_jcon_fncs1/icn_suspend_id I
    iconst_1
    putstatic rung36_jcon_fncs1/icn_failed B
    return
icn_wf_ret:
    iconst_0
    putstatic rung36_jcon_fncs1/icn_failed B
    return
icn_wf_sret:
    return
.end method

; --- record array ---
.class public rung36_jcon_fncs1$array
.super java/lang/Object

.method public <init>()V
    .limit stack 1
    .limit locals 1
    aload_0
    invokespecial java/lang/Object/<init>()V
    return
.end method

