; Auto-generated by icon_emit_jvm.c — Tiny-ICON Byrd Box JVM
.bytecode 45.0
.class public rung36_jcon_scan
.super java/lang/Object

.field public static icn_failed B
.field public static icn_suspended B
.field public static icn_suspend_id I
.field public static icn_retval_obj Ljava/lang/Object;
.field public static icn_retval J
.field public static icn_retval_str Ljava/lang/String;
.field public static icn_gvar_&subject Ljava/lang/String;
.field public static icn_pv_p2__kw_subject Ljava/lang/String;
.field public static icn_pv_p3__kw_subject Ljava/lang/String;
.field public static icn_gvar_s Ljava/lang/String;
.field public static icn_pv_p3_s Ljava/lang/String;
.field public static icn_pv_p4_s Ljava/lang/String;
.field public static icn_2_alt_gate I
.field public static icn_9_alt_gate I
.field public static icn_15_alt_gate I
.field public static icn_subject Ljava/lang/String;
.field public static icn_21_alt_gate I
.field public static icn_gvar_&pos J
.field public static icn_27_alt_gate I
.field public static icn_30_swap_t1 J
.field public static icn_30_swap_t2 J
.field public static icn_33_alt_gate I
.field public static icn_pv_p1__kw_subject J
.field public static icn_40_alt_gate I
.field public static icn_scan_oldsubj_45 Ljava/lang/String;
.field public static icn_scan_oldpos_45 I
.field public static icn_pos I
.field public static icn_46_I J
.field public static icn_46_bound J
.field public static icn_46_e1cur J
.field public static icn_46_e2seen I
.field public static icn_46_e1val J
.field public static icn_46_e2val J
.field public static icn_53_alt_gate I
.field public static icn_scan_oldsubj_58 Ljava/lang/String;
.field public static icn_scan_oldpos_58 I
.field public static icn_scan_oldsubj_59 Ljava/lang/String;
.field public static icn_scan_oldpos_59 I
.field public static icn_60_alt_gate I
.field public static icn_upto_cs_63 Ljava/lang/String;
.field public static icn_66_I J
.field public static icn_66_bound J
.field public static icn_66_e1cur J
.field public static icn_66_e2seen I
.field public static icn_66_e1val J
.field public static icn_66_e2val J
.field public static icn_71_alt_gate I
.field public static icn_scan_oldsubj_76 Ljava/lang/String;
.field public static icn_scan_oldpos_76 I
.field public static icn_77_alt_gate I
.field public static icn_upto_cs_82 Ljava/lang/String;
.field public static icn_83_bang_str Ljava/lang/String;
.field public static icn_83_bang_pos I
.field public static icn_87_alt_gate I
.field public static icn_92_alt_gate I
.field public static icn_100_alt_gate I
.field public static icn_107_alt_gate I
.field public static icn_114_alt_gate I
.field public static icn_121_alt_gate I
.field public static icn_129_alt_gate I
.field public static icn_136_alt_gate I
.field public static icn_143_alt_gate I
.field public static icn_150_alt_gate I
.field public static icn_157_alt_gate I
.field public static icn_164_alt_gate I
.field public static icn_167_augtemp J
.field public static icn_172_alt_gate I
.field public static icn_179_alt_gate I
.field public static icn_scan_oldsubj_184 Ljava/lang/String;
.field public static icn_scan_oldpos_184 I
.field public static icn_scan_oldsubj_187 Ljava/lang/String;
.field public static icn_scan_oldpos_187 I
.field public static icn_194_alt_gate I
.field public static icn_scan_oldsubj_199 Ljava/lang/String;
.field public static icn_scan_oldpos_199 I
.field public static icn_202_I J
.field public static icn_202_bound J
.field public static icn_202_e1cur J
.field public static icn_202_e2seen I
.field public static icn_202_e1val J
.field public static icn_202_e2val J
.field public static icn_207_alt_gate I
.field public static icn_213_alt_gate I
.field public static icn_221_alt_gate I
.field public static icn_227_alt_gate I
.field public static icn_233_alt_gate I
.field public static icn_239_I J
.field public static icn_239_bound J
.field public static icn_239_e1cur J
.field public static icn_239_e2seen I
.field public static icn_239_e1val J
.field public static icn_239_e2val J
.field public static icn_244_alt_gate I
.field public static icn_252_alt_gate I
.field public static icn_261_alt_gate I
.field public static icn_scan_oldsubj_264 Ljava/lang/String;
.field public static icn_scan_oldpos_264 I
.field public static icn_266_and_drain_0 Ljava/lang/String;
.field public static icn_276_alt_gate I
.field public static icn_scan_oldsubj_280 Ljava/lang/String;
.field public static icn_scan_oldpos_280 I
.field public static icn_284_alt_gate I
.field public static icn_289_alt_gate I
.field public static icn_296_alt_gate I
.field public static icn_scan_oldsubj_301 Ljava/lang/String;
.field public static icn_scan_oldpos_301 I
.field public static icn_307_alt_gate I
.field public static icn_314_alt_gate I
.field public static icn_upto_cs_320 Ljava/lang/String;
.field public static icn_319_augtemp J
.field public static icn_324_alt_gate I

.method static <clinit>()V
    .limit stack 2
    .limit locals 0
    ldc ""
    putstatic rung36_jcon_scan/icn_subject Ljava/lang/String;
    iconst_0
    putstatic rung36_jcon_scan/icn_pos I
    return
.end method

.method public static main([Ljava/lang/String;)V
    .limit stack 4
    .limit locals 1
    invokestatic rung36_jcon_scan/icn_main()V
    return
.end method

.method public static icn_builtin_any(Ljava/lang/String;Ljava/lang/String;I)J
    .limit stack 4
    .limit locals 3
    ; if pos >= subj.length() → return -1
    aload_1
    invokevirtual java/lang/String/length()I
    iload_2
    if_icmpgt icn_any_inbounds
    ldc2_w -1
    lreturn
icn_any_inbounds:
    ; cs.indexOf(subj.charAt(pos)) >= 0?
    aload_0
    aload_1
    iload_2
    invokevirtual java/lang/String/charAt(I)C
    invokevirtual java/lang/String/indexOf(I)I
    ifge icn_any_match
    ldc2_w -1
    lreturn
icn_any_match:
    ; return pos+2 (new 1-based pos after consuming one char)
    iload_2
    iconst_2
    iadd
    i2l
    lreturn
.end method

.method public static icn_builtin_many(Ljava/lang/String;Ljava/lang/String;I)J
    .limit stack 4
    .limit locals 4
    ; check first char in cs — must match at least one
    aload_1
    invokevirtual java/lang/String/length()I
    iload_2
    if_icmpgt icn_many_first_ok
    ldc2_w -1
    lreturn
icn_many_first_ok:
    aload_0
    aload_1
    iload_2
    invokevirtual java/lang/String/charAt(I)C
    invokevirtual java/lang/String/indexOf(I)I
    ifge icn_many_loop_init
    ldc2_w -1
    lreturn
icn_many_loop_init:
    ; local 3 = pos (working)
    iload_2
    istore_3
icn_many_loop:
    iinc 3 1
    ; if pos3 >= length → done
    aload_1
    invokevirtual java/lang/String/length()I
    iload_3
    if_icmpgt icn_many_cont
    iload_3
    i2l
    lconst_1
    ladd
    lreturn
icn_many_cont:
    aload_0
    aload_1
    iload_3
    invokevirtual java/lang/String/charAt(I)C
    invokevirtual java/lang/String/indexOf(I)I
    ifge icn_many_loop
    ; stopped — return pos3+1 (1-based)
    iload_3
    iconst_1
    iadd
    i2l
    lreturn
.end method

.method public static icn_builtin_upto_step(Ljava/lang/String;Ljava/lang/String;I)J
    .limit stack 4
    .limit locals 4
    iload_2
    istore_3
icn_upto_scan:
    ; if pos3 >= length → -1
    aload_1
    invokevirtual java/lang/String/length()I
    iload_3
    if_icmpgt icn_upto_inbounds
    ldc2_w -1
    lreturn
icn_upto_inbounds:
    aload_0
    aload_1
    iload_3
    invokevirtual java/lang/String/charAt(I)C
    invokevirtual java/lang/String/indexOf(I)I
    ifge icn_upto_found
    iinc 3 1
    goto icn_upto_scan
icn_upto_found:
    ; return pos3+1 (1-based); caller sets icn_pos=result for next resume
    iload_3
    iconst_1
    iadd
    i2l
    lreturn
.end method

.method public static icn_builtin_find(Ljava/lang/String;Ljava/lang/String;I)J
    .limit stack 4
    .limit locals 3
    aload_1
    aload_0
    iload_2
    invokevirtual java/lang/String/indexOf(Ljava/lang/String;I)I
    dup
    ifge icn_find_ok
    pop
    ldc2_w -1
    lreturn
icn_find_ok:
    iconst_1
    iadd
    i2l
    lreturn
.end method

.method public static icn_builtin_match(Ljava/lang/String;Ljava/lang/String;I)J
    .limit stack 4
    .limit locals 3
    aload_1
    aload_0
    iload_2
    invokevirtual java/lang/String/startsWith(Ljava/lang/String;I)Z
    ifne icn_match_ok
    ldc2_w -1
    lreturn
icn_match_ok:
    iload_2
    aload_0
    invokevirtual java/lang/String/length()I
    iadd
    iconst_1
    iadd
    i2l
    lreturn
.end method

.method public static icn_builtin_tab_str(ILjava/lang/String;I)Ljava/lang/String;
    .limit stack 4
    .limit locals 4
    ; end = n-1 (0-based)
    iload_0
    iconst_1
    isub
    istore_3
    ; fail if end < pos
    iload_3
    iload_2
    if_icmpge icn_tab_posok
    aconst_null
    areturn
icn_tab_posok:
    ; fail if end > subj.length()
    aload_1
    invokevirtual java/lang/String/length()I
    iload_3
    if_icmpge icn_tab_lenok
    aconst_null
    areturn
icn_tab_lenok:
    ; update icn_pos = end (static field)
    iload_3
    putstatic rung36_jcon_scan/icn_pos I
    ; return subj.substring(pos, end)
    aload_1
    iload_2
    iload_3
    invokevirtual java/lang/String/substring(II)Ljava/lang/String;
    areturn
.end method

.method public static icn_builtin_move_str(ILjava/lang/String;I)Ljava/lang/String;
    .limit stack 4
    .limit locals 4
    ; end = pos+n
    iload_2
    iload_0
    iadd
    istore_3
    ; fail if end > subj.length()
    aload_1
    invokevirtual java/lang/String/length()I
    iload_3
    if_icmpge icn_move_ok
    aconst_null
    areturn
icn_move_ok:
    ; update icn_pos = end
    iload_3
    putstatic rung36_jcon_scan/icn_pos I
    ; return subj.substring(pos, end)
    aload_1
    iload_2
    iload_3
    invokevirtual java/lang/String/substring(II)Ljava/lang/String;
    areturn
.end method

.method public static icn_builtin_left(Ljava/lang/String;ILjava/lang/String;)Ljava/lang/String;
    .limit stack 4
    .limit locals 5
    aload_0
    invokevirtual java/lang/String/length()I
    iload_1
    if_icmplt icn_left_pad
    aload_0
    iconst_0
    iload_1
    invokevirtual java/lang/String/substring(II)Ljava/lang/String;
    areturn
icn_left_pad:
    new java/lang/StringBuilder
    dup
    aload_0
    invokespecial java/lang/StringBuilder/<init>(Ljava/lang/String;)V
    astore_3
icn_left_loop:
    aload_3
    invokevirtual java/lang/StringBuilder/length()I
    iload_1
    if_icmpge icn_left_done
    aload_3
    aload_2
    iconst_0
    invokevirtual java/lang/String/charAt(I)C
    invokevirtual java/lang/StringBuilder/append(C)Ljava/lang/StringBuilder;
    pop
    goto icn_left_loop
icn_left_done:
    aload_3
    invokevirtual java/lang/StringBuilder/toString()Ljava/lang/String;
    areturn
.end method

.method public static icn_builtin_right(Ljava/lang/String;ILjava/lang/String;)Ljava/lang/String;
    .limit stack 4
    .limit locals 5
    aload_0
    invokevirtual java/lang/String/length()I
    iload_1
    if_icmplt icn_right_pad
    aload_0
    invokevirtual java/lang/String/length()I
    iload_1
    isub
    aload_0
    swap
    invokevirtual java/lang/String/substring(I)Ljava/lang/String;
    areturn
icn_right_pad:
    new java/lang/StringBuilder
    dup
    invokespecial java/lang/StringBuilder/<init>()V
    astore_3
    iload_1
    aload_0
    invokevirtual java/lang/String/length()I
    isub
    istore 4
    iconst_0
icn_right_loop:
    dup
    iload 4
    if_icmpge icn_right_append
    aload_3
    aload_2
    iconst_0
    invokevirtual java/lang/String/charAt(I)C
    invokevirtual java/lang/StringBuilder/append(C)Ljava/lang/StringBuilder;
    pop
    iconst_1
    iadd
    goto icn_right_loop
icn_right_append:
    pop
    aload_3
    aload_0
    invokevirtual java/lang/StringBuilder/append(Ljava/lang/String;)Ljava/lang/StringBuilder;
    pop
    aload_3
    invokevirtual java/lang/StringBuilder/toString()Ljava/lang/String;
    areturn
.end method

.method public static icn_builtin_center(Ljava/lang/String;ILjava/lang/String;)Ljava/lang/String;
    .limit stack 5
    .limit locals 7
    aload_0
    invokevirtual java/lang/String/length()I
    iload_1
    if_icmplt icn_ctr_pad
    aload_0
    iconst_0
    iload_1
    invokevirtual java/lang/String/substring(II)Ljava/lang/String;
    areturn
icn_ctr_pad:
    iload_1
    aload_0
    invokevirtual java/lang/String/length()I
    isub
    istore_3
    iload_3
    iconst_2
    idiv
    istore 4
    iload_3
    iload 4
    isub
    istore 5
    new java/lang/StringBuilder
    dup
    invokespecial java/lang/StringBuilder/<init>()V
    astore 6
    iconst_0
icn_ctr_lloop:
    dup
    iload 4
    if_icmpge icn_ctr_mid
    aload 6
    aload_2
    iconst_0
    invokevirtual java/lang/String/charAt(I)C
    invokevirtual java/lang/StringBuilder/append(C)Ljava/lang/StringBuilder;
    pop
    iconst_1
    iadd
    goto icn_ctr_lloop
icn_ctr_mid:
    pop
    aload 6
    aload_0
    invokevirtual java/lang/StringBuilder/append(Ljava/lang/String;)Ljava/lang/StringBuilder;
    pop
    iconst_0
icn_ctr_rloop:
    dup
    iload 5
    if_icmpge icn_ctr_done
    aload 6
    aload_2
    iconst_0
    invokevirtual java/lang/String/charAt(I)C
    invokevirtual java/lang/StringBuilder/append(C)Ljava/lang/StringBuilder;
    pop
    iconst_1
    iadd
    goto icn_ctr_rloop
icn_ctr_done:
    pop
    aload 6
    invokevirtual java/lang/StringBuilder/toString()Ljava/lang/String;
    areturn
.end method

.method public static icn_builtin_trim(Ljava/lang/String;Ljava/lang/String;)Ljava/lang/String;
    .limit stack 4
    .limit locals 3
    aload_0
    invokevirtual java/lang/String/length()I
    istore_2
icn_trim_loop:
    iload_2
    ifle icn_trim_done
    aload_1
    aload_0
    iload_2
    iconst_1
    isub
    invokevirtual java/lang/String/charAt(I)C
    invokevirtual java/lang/String/indexOf(I)I
    iflt icn_trim_done
    iinc 2 -1
    goto icn_trim_loop
icn_trim_done:
    aload_0
    iconst_0
    iload_2
    invokevirtual java/lang/String/substring(II)Ljava/lang/String;
    areturn
.end method

.method public static icn_builtin_map(Ljava/lang/String;Ljava/lang/String;Ljava/lang/String;)Ljava/lang/String;
    .limit stack 5
    .limit locals 7
    new java/lang/StringBuilder
    dup
    invokespecial java/lang/StringBuilder/<init>()V
    astore_3
    iconst_0
    istore 4
icn_map_loop:
    iload 4
    aload_0
    invokevirtual java/lang/String/length()I
    if_icmpge icn_map_done
    aload_0
    iload 4
    invokevirtual java/lang/String/charAt(I)C
    istore 5
    aload_1
    iload 5
    invokevirtual java/lang/String/indexOf(I)I
    istore 6
    iload 6
    iflt icn_map_notfound
    iload 6
    aload_2
    invokevirtual java/lang/String/length()I
    if_icmpge icn_map_notfound
    aload_3
    aload_2
    iload 6
    invokevirtual java/lang/String/charAt(I)C
    invokevirtual java/lang/StringBuilder/append(C)Ljava/lang/StringBuilder;
    pop
    goto icn_map_next
icn_map_notfound:
    aload_3
    iload 5
    invokevirtual java/lang/StringBuilder/append(C)Ljava/lang/StringBuilder;
    pop
icn_map_next:
    iinc 4 1
    goto icn_map_loop
icn_map_done:
    aload_3
    invokevirtual java/lang/StringBuilder/toString()Ljava/lang/String;
    areturn
.end method

.method public static icn_builtin_parse_long(Ljava/lang/String;)J
    .limit stack 4
    .limit locals 4
    .catch java/lang/Exception from icn_plong_L0 to icn_plong_L1 using icn_plong_catch
icn_plong_L0:
    aload_0
    invokevirtual java/lang/String/trim()Ljava/lang/String;
    astore_1
    aload_1
    ldc "r"
    invokevirtual java/lang/String/contains(Ljava/lang/CharSequence;)Z
    ifeq icn_plong_plain
    aload_1
    ldc "r"
    iconst_2
    invokevirtual java/lang/String/split(Ljava/lang/String;I)[Ljava/lang/String;
    astore_2
    aload_2
    iconst_0
    aaload
    invokestatic java/lang/Integer/parseInt(Ljava/lang/String;)I
    istore_3
    aload_2
    iconst_1
    aaload
    iload_3
    invokestatic java/lang/Long/parseLong(Ljava/lang/String;I)J
    goto icn_plong_L1
icn_plong_plain:
    aload_1
    invokestatic java/lang/Long/parseLong(Ljava/lang/String;)J
icn_plong_L1:
    lreturn
icn_plong_catch:
    pop
    ldc2_w -9223372036854775808
    lreturn
.end method

.method public static icn_builtin_numeric(Ljava/lang/String;)J
    .limit stack 2
    .limit locals 2
    aload_0
    invokestatic rung36_jcon_scan/icn_builtin_parse_long(Ljava/lang/String;)J
    lreturn
.end method

.method public static icn_builtin_sort(Ljava/util/ArrayList;)Ljava/util/ArrayList;
    .limit stack 6
    .limit locals 8
    new java/util/ArrayList
    dup
    aload_0
    invokespecial java/util/ArrayList/<init>(Ljava/util/Collection;)V
    astore_1
    iconst_1
    istore_2
icn_sort_outer:
    aload_1
    invokevirtual java/util/ArrayList/size()I
    iload_2
    if_icmple icn_sort_done
    aload_1
    iload_2
    invokevirtual java/util/ArrayList/get(I)Ljava/lang/Object;
    checkcast java/lang/Long
    invokevirtual java/lang/Long/longValue()J
    lstore 4
    iload_2
    iconst_1
    isub
    istore_3
icn_sort_inner:
    iload_3
    iflt icn_sort_insert
    aload_1
    iload_3
    invokevirtual java/util/ArrayList/get(I)Ljava/lang/Object;
    checkcast java/lang/Long
    invokevirtual java/lang/Long/longValue()J
    lload 4
    lcmp
    ifle icn_sort_insert
    aload_1
    iload_3
    iconst_1
    iadd
    aload_1
    iload_3
    invokevirtual java/util/ArrayList/get(I)Ljava/lang/Object;
    invokevirtual java/util/ArrayList/set(ILjava/lang/Object;)Ljava/lang/Object;
    pop
    iinc 3 -1
    goto icn_sort_inner
icn_sort_insert:
    aload_1
    iload_3
    iconst_1
    iadd
    lload 4
    invokestatic java/lang/Long/valueOf(J)Ljava/lang/Long;
    invokevirtual java/util/ArrayList/set(ILjava/lang/Object;)Ljava/lang/Object;
    pop
    iinc 2 1
    goto icn_sort_outer
icn_sort_done:
    aload_1
    areturn
.end method

.method public static icn_builtin_sortf(Ljava/util/ArrayList;I)Ljava/util/ArrayList;
    .limit stack 8
    .limit locals 10
    new java/util/ArrayList
    dup
    aload_0
    invokespecial java/util/ArrayList/<init>(Ljava/util/Collection;)V
    astore_2
    iconst_1
    istore_3
icn_sortf_outer:
    aload_2
    invokevirtual java/util/ArrayList/size()I
    iload_3
    if_icmple icn_sortf_done
    aload_2
    iload_3
    invokevirtual java/util/ArrayList/get(I)Ljava/lang/Object;
    astore 5
    iload_3
    iconst_1
    isub
    istore 4
icn_sortf_inner:
    iload 4
    iflt icn_sortf_insert
    aload_2
    iload 4
    invokevirtual java/util/ArrayList/get(I)Ljava/lang/Object;
    astore 6
    aload 6
    invokevirtual java/lang/Object/getClass()Ljava/lang/Class;
    invokevirtual java/lang/Class/getDeclaredFields()[Ljava/lang/reflect/Field;
    iload_1
    iconst_1
    isub
    aaload
    aload 6
    invokevirtual java/lang/reflect/Field/get(Ljava/lang/Object;)Ljava/lang/Object;
    astore 7
    aload 5
    invokevirtual java/lang/Object/getClass()Ljava/lang/Class;
    invokevirtual java/lang/Class/getDeclaredFields()[Ljava/lang/reflect/Field;
    iload_1
    iconst_1
    isub
    aaload
    aload 5
    invokevirtual java/lang/reflect/Field/get(Ljava/lang/Object;)Ljava/lang/Object;
    astore 8
    aload 7
    checkcast java/lang/Long
    aload 8
    checkcast java/lang/Long
    invokevirtual java/lang/Long/compareTo(Ljava/lang/Long;)I
    ifle icn_sortf_insert
    aload_2
    iload 4
    iconst_1
    iadd
    aload_2
    iload 4
    invokevirtual java/util/ArrayList/get(I)Ljava/lang/Object;
    invokevirtual java/util/ArrayList/set(ILjava/lang/Object;)Ljava/lang/Object;
    pop
    iinc 4 -1
    goto icn_sortf_inner
icn_sortf_insert:
    aload_2
    iload 4
    iconst_1
    iadd
    aload 5
    invokevirtual java/util/ArrayList/set(ILjava/lang/Object;)Ljava/lang/Object;
    pop
    iinc 3 1
    goto icn_sortf_outer
icn_sortf_done:
    aload_2
    areturn
.end method

.method public static icn_builtin_random(J)J
    .limit stack 4
    .limit locals 4
    ; if n <= 0 return 0
    lload_0
    lconst_0
    lcmp
    ifgt icn_rand_pos
    lconst_0
    lreturn
icn_rand_pos:
    invokestatic java/lang/System/nanoTime()J
    lload_0
    lrem
    lconst_1
    ladd
    lreturn
.end method

.method public static icn_builtin_cset_complement(Ljava/lang/String;)Ljava/lang/String;
    .limit stack 4
    .limit locals 4
    ; StringBuilder result
    new java/lang/StringBuilder
    dup
    invokespecial java/lang/StringBuilder/<init>()V
    astore_1
    ; loop c = 1..127
    iconst_1
    istore_2
icn_csc_loop:
    iload_2
    bipush 127
    if_icmpgt icn_csc_done
    ; cs.indexOf(c) < 0 → append
    aload_0
    iload_2
    invokevirtual java/lang/String/indexOf(I)I
    ifge icn_csc_skip
    aload_1
    iload_2
    invokevirtual java/lang/StringBuilder/append(C)Ljava/lang/StringBuilder;
    pop
icn_csc_skip:
    iinc 2 1
    goto icn_csc_loop
icn_csc_done:
    aload_1
    invokevirtual java/lang/StringBuilder/toString()Ljava/lang/String;
    areturn
.end method

.method public static icn_builtin_cset_union(Ljava/lang/String;Ljava/lang/String;)Ljava/lang/String;
    .limit stack 4
    .limit locals 4
    ; start with copy of a
    new java/lang/StringBuilder
    dup
    aload_0
    invokespecial java/lang/StringBuilder/<init>(Ljava/lang/String;)V
    astore_2
    ; for each char in b: if a.indexOf(c)<0 append
    iconst_0
    istore_3
icn_csu_loop:
    iload_3
    aload_1
    invokevirtual java/lang/String/length()I
    if_icmpge icn_csu_done
    aload_1
    iload_3
    invokevirtual java/lang/String/charAt(I)C
    istore 0
    aload_0
    iload 0
    invokevirtual java/lang/String/indexOf(I)I
    ifge icn_csu_skip
    aload_2
    iload 0
    invokevirtual java/lang/StringBuilder/append(C)Ljava/lang/StringBuilder;
    pop
icn_csu_skip:
    iinc 3 1
    goto icn_csu_loop
icn_csu_done:
    aload_2
    invokevirtual java/lang/StringBuilder/toString()Ljava/lang/String;
    areturn
.end method

.method public static icn_builtin_cset_diff(Ljava/lang/String;Ljava/lang/String;)Ljava/lang/String;
    .limit stack 4
    .limit locals 4
    new java/lang/StringBuilder
    dup
    invokespecial java/lang/StringBuilder/<init>()V
    astore_2
    iconst_0
    istore_3
icn_csd_loop:
    iload_3
    aload_0
    invokevirtual java/lang/String/length()I
    if_icmpge icn_csd_done
    aload_0
    iload_3
    invokevirtual java/lang/String/charAt(I)C
    istore 0
    aload_1
    iload 0
    invokevirtual java/lang/String/indexOf(I)I
    ifge icn_csd_skip
    aload_2
    iload 0
    invokevirtual java/lang/StringBuilder/append(C)Ljava/lang/StringBuilder;
    pop
icn_csd_skip:
    iinc 3 1
    goto icn_csd_loop
icn_csd_done:
    aload_2
    invokevirtual java/lang/StringBuilder/toString()Ljava/lang/String;
    areturn
.end method

.method public static icn_builtin_cset_inter(Ljava/lang/String;Ljava/lang/String;)Ljava/lang/String;
    .limit stack 4
    .limit locals 4
    new java/lang/StringBuilder
    dup
    invokespecial java/lang/StringBuilder/<init>()V
    astore_2
    iconst_0
    istore_3
icn_csi_loop:
    iload_3
    aload_0
    invokevirtual java/lang/String/length()I
    if_icmpge icn_csi_done
    aload_0
    iload_3
    invokevirtual java/lang/String/charAt(I)C
    istore 0
    aload_1
    iload 0
    invokevirtual java/lang/String/indexOf(I)I
    iflt icn_csi_skip
    aload_2
    iload 0
    invokevirtual java/lang/StringBuilder/append(C)Ljava/lang/StringBuilder;
    pop
icn_csi_skip:
    iinc 3 1
    goto icn_csi_loop
icn_csi_done:
    aload_2
    invokevirtual java/lang/StringBuilder/toString()Ljava/lang/String;
    areturn
.end method

.method public static icn_p1()V
    .limit stack 16
    .limit locals 306
    lconst_0
    lstore 0
    lconst_0
    lstore 2
    lconst_0
    lstore 4
    lconst_0
    lstore 6
    lconst_0
    lstore 8
    lconst_0
    lstore 10
    lconst_0
    lstore 12
    lconst_0
    lstore 14
    lconst_0
    lstore 16
    lconst_0
    lstore 18
    lconst_0
    lstore 20
    lconst_0
    lstore 22
    lconst_0
    lstore 24
    lconst_0
    lstore 26
    lconst_0
    lstore 28
    lconst_0
    lstore 30
    lconst_0
    lstore 32
    lconst_0
    lstore 34
    lconst_0
    lstore 36
    lconst_0
    lstore 38
    lconst_0
    lstore 40
    lconst_0
    lstore 42
    lconst_0
    lstore 44
    lconst_0
    lstore 46
    lconst_0
    lstore 48
    lconst_0
    lstore 50
    lconst_0
    lstore 52
    lconst_0
    lstore 54
    lconst_0
    lstore 56
    lconst_0
    lstore 58
    lconst_0
    lstore 60
    lconst_0
    lstore 62
    iconst_0
    istore 84
    iconst_0
    istore 85
    iconst_0
    istore 86
    iconst_0
    istore 87
    aconst_null
    astore 148
    aconst_null
    astore 149
    aconst_null
    astore 150
    aconst_null
    astore 151
    aconst_null
    astore 152
    aconst_null
    astore 153
    aconst_null
    astore 154
    aconst_null
    astore 155
    aconst_null
    astore 156
    aconst_null
    astore 157
    aconst_null
    astore 158
    aconst_null
    astore 159
    aconst_null
    astore 160
    aconst_null
    astore 161
    aconst_null
    astore 162
    aconst_null
    astore 163
    aconst_null
    astore 164
    aconst_null
    astore 165
    aconst_null
    astore 166
    aconst_null
    astore 167
    aconst_null
    astore 168
    aconst_null
    astore 169
    aconst_null
    astore 170
    aconst_null
    astore 171
    aconst_null
    astore 172
    aconst_null
    astore 173
    aconst_null
    astore 174
    aconst_null
    astore 175
    aconst_null
    astore 176
    aconst_null
    astore 177
    aconst_null
    astore 178
    aconst_null
    astore 179
    aconst_null
    astore 180
    aconst_null
    astore 181
    aconst_null
    astore 182
    aconst_null
    astore 183
    aconst_null
    astore 184
    aconst_null
    astore 185
    aconst_null
    astore 186
    aconst_null
    astore 187
    aconst_null
    astore 188
    aconst_null
    astore 189
    aconst_null
    astore 190
    aconst_null
    astore 191
    aconst_null
    astore 192
    aconst_null
    astore 193
    aconst_null
    astore 194
    aconst_null
    astore 195
    aconst_null
    astore 196
    aconst_null
    astore 197
    aconst_null
    astore 198
    aconst_null
    astore 199
    goto icn_85_α
;  STR
icn_1_α:
    ldc "-1 ----> "
    goto icn_0_waft_0
icn_1_β:
    goto icn_p1_done
;  STR
icn_3_α:
    ldc "none"
    goto icn_2_alt_g1
icn_3_β:
    goto icn_p1_done
;  INT
icn_6_α:
    ldc2_w 1
    goto icn_5_neg
icn_6_β:
    goto icn_3_α
;  NEG
icn_5_α:
    goto icn_6_α
icn_5_β:
    goto icn_6_β
icn_5_neg:
    lneg
    goto icn_4_image_after
icn_4_α:
    goto icn_5_α
icn_4_β:
    goto icn_5_β
icn_4_image_after:
    invokestatic java/lang/Long/toString(J)Ljava/lang/String;
    goto icn_2_alt_g0
icn_2_alt_g0:
    astore 148
    sipush 1
    putstatic rung36_jcon_scan/icn_2_alt_gate I
    aload 148
    goto icn_0_waft_1
icn_2_alt_g1:
    astore 149
    sipush 2
    putstatic rung36_jcon_scan/icn_2_alt_gate I
    aload 149
    goto icn_0_waft_1
icn_2_α:
    iconst_0
    putstatic rung36_jcon_scan/icn_2_alt_gate I
    goto icn_4_α
icn_2_β:
    getstatic rung36_jcon_scan/icn_2_alt_gate I
    tableswitch 1 2
        icn_4_β
        icn_3_β
        default: icn_p1_done
icn_0_α:
    goto icn_1_α
icn_0_β:
    goto icn_1_β
    goto icn_0_wentry
icn_0_waft_0:
    astore 150
    getstatic java/lang/System/out Ljava/io/PrintStream;
    aload 150
    invokevirtual java/io/PrintStream/print(Ljava/lang/String;)V
    goto icn_2_α
icn_0_waft_1:
    astore 151
    getstatic java/lang/System/out Ljava/io/PrintStream;
    aload 151
    invokevirtual java/io/PrintStream/print(Ljava/lang/String;)V
    getstatic java/lang/System/out Ljava/io/PrintStream;
    ldc ""
    invokevirtual java/io/PrintStream/println(Ljava/lang/String;)V
    aload 151
    goto icn_p1_s9_sdrain
icn_0_wentry:
    goto icn_1_α
icn_p1_s9_sdrain:
    pop
    goto icn_p1_done
;  STR
icn_8_α:
    ldc "+1 ----> "
    goto icn_7_waft_0
icn_8_β:
    goto icn_0_α
;  STR
icn_10_α:
    ldc "none"
    goto icn_9_alt_g1
icn_10_β:
    goto icn_0_α
;  INT
icn_12_α:
    ldc2_w 1
    goto icn_11_image_after
icn_12_β:
    goto icn_10_α
icn_11_α:
    goto icn_12_α
icn_11_β:
    goto icn_12_β
icn_11_image_after:
    invokestatic java/lang/Long/toString(J)Ljava/lang/String;
    goto icn_9_alt_g0
icn_9_alt_g0:
    astore 152
    sipush 1
    putstatic rung36_jcon_scan/icn_9_alt_gate I
    aload 152
    goto icn_7_waft_1
icn_9_alt_g1:
    astore 153
    sipush 2
    putstatic rung36_jcon_scan/icn_9_alt_gate I
    aload 153
    goto icn_7_waft_1
icn_9_α:
    iconst_0
    putstatic rung36_jcon_scan/icn_9_alt_gate I
    goto icn_11_α
icn_9_β:
    getstatic rung36_jcon_scan/icn_9_alt_gate I
    tableswitch 1 2
        icn_11_β
        icn_10_β
        default: icn_0_α
icn_7_α:
    goto icn_8_α
icn_7_β:
    goto icn_8_β
    goto icn_7_wentry
icn_7_waft_0:
    astore 154
    getstatic java/lang/System/out Ljava/io/PrintStream;
    aload 154
    invokevirtual java/io/PrintStream/print(Ljava/lang/String;)V
    goto icn_9_α
icn_7_waft_1:
    astore 155
    getstatic java/lang/System/out Ljava/io/PrintStream;
    aload 155
    invokevirtual java/io/PrintStream/print(Ljava/lang/String;)V
    getstatic java/lang/System/out Ljava/io/PrintStream;
    ldc ""
    invokevirtual java/io/PrintStream/println(Ljava/lang/String;)V
    aload 155
    goto icn_p1_s8_sdrain
icn_7_wentry:
    goto icn_8_α
icn_p1_s8_sdrain:
    pop
    goto icn_0_α
;  STR
icn_14_α:
    ldc "&subject ----> "
    goto icn_13_waft_0
icn_14_β:
    goto icn_7_α
;  STR
icn_16_α:
    ldc "none"
    goto icn_15_alt_g1
icn_16_β:
    goto icn_7_α
;  VAR
icn_18_α:
    getstatic rung36_jcon_scan/icn_subject Ljava/lang/String;
    goto icn_17_image_after
icn_18_β:
    goto icn_16_α
icn_17_α:
    goto icn_18_α
icn_17_β:
    goto icn_18_β
icn_17_image_after:
    goto icn_15_alt_g0
icn_15_alt_g0:
    astore 156
    sipush 1
    putstatic rung36_jcon_scan/icn_15_alt_gate I
    aload 156
    goto icn_13_waft_1
icn_15_alt_g1:
    astore 157
    sipush 2
    putstatic rung36_jcon_scan/icn_15_alt_gate I
    aload 157
    goto icn_13_waft_1
icn_15_α:
    iconst_0
    putstatic rung36_jcon_scan/icn_15_alt_gate I
    goto icn_17_α
icn_15_β:
    getstatic rung36_jcon_scan/icn_15_alt_gate I
    tableswitch 1 2
        icn_17_β
        icn_16_β
        default: icn_7_α
icn_13_α:
    goto icn_14_α
icn_13_β:
    goto icn_14_β
    goto icn_13_wentry
icn_13_waft_0:
    astore 158
    getstatic java/lang/System/out Ljava/io/PrintStream;
    aload 158
    invokevirtual java/io/PrintStream/print(Ljava/lang/String;)V
    goto icn_15_α
icn_13_waft_1:
    astore 159
    getstatic java/lang/System/out Ljava/io/PrintStream;
    aload 159
    invokevirtual java/io/PrintStream/print(Ljava/lang/String;)V
    getstatic java/lang/System/out Ljava/io/PrintStream;
    ldc ""
    invokevirtual java/io/PrintStream/println(Ljava/lang/String;)V
    aload 159
    goto icn_p1_s7_sdrain
icn_13_wentry:
    goto icn_14_α
icn_p1_s7_sdrain:
    pop
    goto icn_7_α
;  STR
icn_20_α:
    ldc "&pos ----> "
    goto icn_19_waft_0
icn_20_β:
    goto icn_13_α
;  STR
icn_22_α:
    ldc "none"
    goto icn_21_alt_g1
icn_22_β:
    goto icn_13_α
;  VAR
icn_24_α:
    getstatic rung36_jcon_scan/icn_gvar_&pos J
    goto icn_23_image_after
icn_24_β:
    goto icn_22_α
icn_23_α:
    goto icn_24_α
icn_23_β:
    goto icn_24_β
icn_23_image_after:
    invokestatic java/lang/Long/toString(J)Ljava/lang/String;
    goto icn_21_alt_g0
icn_21_alt_g0:
    astore 160
    sipush 1
    putstatic rung36_jcon_scan/icn_21_alt_gate I
    aload 160
    goto icn_19_waft_1
icn_21_alt_g1:
    astore 161
    sipush 2
    putstatic rung36_jcon_scan/icn_21_alt_gate I
    aload 161
    goto icn_19_waft_1
icn_21_α:
    iconst_0
    putstatic rung36_jcon_scan/icn_21_alt_gate I
    goto icn_23_α
icn_21_β:
    getstatic rung36_jcon_scan/icn_21_alt_gate I
    tableswitch 1 2
        icn_23_β
        icn_22_β
        default: icn_13_α
icn_19_α:
    goto icn_20_α
icn_19_β:
    goto icn_20_β
    goto icn_19_wentry
icn_19_waft_0:
    astore 162
    getstatic java/lang/System/out Ljava/io/PrintStream;
    aload 162
    invokevirtual java/io/PrintStream/print(Ljava/lang/String;)V
    goto icn_21_α
icn_19_waft_1:
    astore 163
    getstatic java/lang/System/out Ljava/io/PrintStream;
    aload 163
    invokevirtual java/io/PrintStream/print(Ljava/lang/String;)V
    getstatic java/lang/System/out Ljava/io/PrintStream;
    ldc ""
    invokevirtual java/io/PrintStream/println(Ljava/lang/String;)V
    aload 163
    goto icn_p1_s6_sdrain
icn_19_wentry:
    goto icn_20_α
icn_p1_s6_sdrain:
    pop
    goto icn_13_α
;  STR
icn_26_α:
    ldc "&pos :=: &subject ----> "
    goto icn_25_waft_0
icn_26_β:
    goto icn_19_α
;  STR
icn_28_α:
    ldc "none"
    goto icn_27_alt_g1
icn_28_β:
    goto icn_19_α
icn_30_α:
    getstatic rung36_jcon_scan/icn_gvar_&pos J
    putstatic rung36_jcon_scan/icn_30_swap_t1 J
    getstatic rung36_jcon_scan/icn_pv_p1__kw_subject J
    putstatic rung36_jcon_scan/icn_30_swap_t2 J
    getstatic rung36_jcon_scan/icn_30_swap_t2 J
    putstatic rung36_jcon_scan/icn_gvar_&pos J
    getstatic rung36_jcon_scan/icn_30_swap_t1 J
    putstatic rung36_jcon_scan/icn_pv_p1__kw_subject J
    getstatic rung36_jcon_scan/icn_gvar_&pos J
    goto icn_29_image_after
icn_30_β:
    goto icn_28_α
icn_29_α:
    goto icn_30_α
icn_29_β:
    goto icn_30_β
icn_29_image_after:
    invokestatic java/lang/Long/toString(J)Ljava/lang/String;
    goto icn_27_alt_g0
icn_27_alt_g0:
    astore 164
    sipush 1
    putstatic rung36_jcon_scan/icn_27_alt_gate I
    aload 164
    goto icn_25_waft_1
icn_27_alt_g1:
    astore 165
    sipush 2
    putstatic rung36_jcon_scan/icn_27_alt_gate I
    aload 165
    goto icn_25_waft_1
icn_27_α:
    iconst_0
    putstatic rung36_jcon_scan/icn_27_alt_gate I
    goto icn_29_α
icn_27_β:
    getstatic rung36_jcon_scan/icn_27_alt_gate I
    tableswitch 1 2
        icn_29_β
        icn_28_β
        default: icn_19_α
icn_25_α:
    goto icn_26_α
icn_25_β:
    goto icn_26_β
    goto icn_25_wentry
icn_25_waft_0:
    astore 166
    getstatic java/lang/System/out Ljava/io/PrintStream;
    aload 166
    invokevirtual java/io/PrintStream/print(Ljava/lang/String;)V
    goto icn_27_α
icn_25_waft_1:
    astore 167
    getstatic java/lang/System/out Ljava/io/PrintStream;
    aload 167
    invokevirtual java/io/PrintStream/print(Ljava/lang/String;)V
    getstatic java/lang/System/out Ljava/io/PrintStream;
    ldc ""
    invokevirtual java/io/PrintStream/println(Ljava/lang/String;)V
    aload 167
    goto icn_p1_s5_sdrain
icn_25_wentry:
    goto icn_26_α
icn_p1_s5_sdrain:
    pop
    goto icn_19_α
;  STR
icn_32_α:
    ldc "&subject := &pos ----> "
    goto icn_31_waft_0
icn_32_β:
    goto icn_25_α
;  STR
icn_34_α:
    ldc "none"
    goto icn_33_alt_g1
icn_34_β:
    goto icn_25_α
;  VAR
icn_37_α:
    getstatic rung36_jcon_scan/icn_gvar_&pos J
    goto icn_36_store
icn_37_β:
    goto icn_34_α
icn_36_α:
    goto icn_37_α
icn_36_β:
    goto icn_37_β
icn_36_store:
    putstatic rung36_jcon_scan/icn_pv_p1__kw_subject J
    getstatic rung36_jcon_scan/icn_pv_p1__kw_subject J
    goto icn_35_image_after
icn_35_α:
    goto icn_36_α
icn_35_β:
    goto icn_36_β
icn_35_image_after:
    invokestatic java/lang/Long/toString(J)Ljava/lang/String;
    goto icn_33_alt_g0
icn_33_alt_g0:
    astore 168
    sipush 1
    putstatic rung36_jcon_scan/icn_33_alt_gate I
    aload 168
    goto icn_31_waft_1
icn_33_alt_g1:
    astore 169
    sipush 2
    putstatic rung36_jcon_scan/icn_33_alt_gate I
    aload 169
    goto icn_31_waft_1
icn_33_α:
    iconst_0
    putstatic rung36_jcon_scan/icn_33_alt_gate I
    goto icn_35_α
icn_33_β:
    getstatic rung36_jcon_scan/icn_33_alt_gate I
    tableswitch 1 2
        icn_35_β
        icn_34_β
        default: icn_25_α
icn_31_α:
    goto icn_32_α
icn_31_β:
    goto icn_32_β
    goto icn_31_wentry
icn_31_waft_0:
    astore 170
    getstatic java/lang/System/out Ljava/io/PrintStream;
    aload 170
    invokevirtual java/io/PrintStream/print(Ljava/lang/String;)V
    goto icn_33_α
icn_31_waft_1:
    astore 171
    getstatic java/lang/System/out Ljava/io/PrintStream;
    aload 171
    invokevirtual java/io/PrintStream/print(Ljava/lang/String;)V
    getstatic java/lang/System/out Ljava/io/PrintStream;
    ldc ""
    invokevirtual java/io/PrintStream/println(Ljava/lang/String;)V
    aload 171
    goto icn_p1_s4_sdrain
icn_31_wentry:
    goto icn_32_α
icn_p1_s4_sdrain:
    pop
    goto icn_25_α
;  STR
icn_39_α:
    ldc "every write((1 to 10) ? move(1)) ----> "
    goto icn_38_waft_0
icn_39_β:
    goto icn_31_α
;  STR
icn_41_α:
    ldc "none"
    goto icn_40_alt_g1
icn_41_β:
    goto icn_31_α
;  INT
icn_47_α:
    ldc2_w 10
    goto icn_46_e2relay
icn_47_β:
    goto icn_46_e1b
;  INT
icn_48_α:
    ldc2_w 1
    goto icn_46_e1relay
icn_48_β:
    goto icn_41_α
icn_46_e1relay:
    putstatic rung36_jcon_scan/icn_46_e1val J
    goto icn_47_α
icn_46_e2relay:
    putstatic rung36_jcon_scan/icn_46_e2val J
    goto icn_46_init
icn_46_e1b:
    iconst_0
    putstatic rung36_jcon_scan/icn_46_e2seen I
    goto icn_48_β
icn_46_e2b:
    goto icn_47_β
icn_46_α:
    iconst_0
    putstatic rung36_jcon_scan/icn_46_e2seen I
    goto icn_48_α
icn_46_β:
    getstatic rung36_jcon_scan/icn_46_I J
    lconst_1
    ladd
    putstatic rung36_jcon_scan/icn_46_I J
    goto icn_46_code
icn_46_init:
    getstatic rung36_jcon_scan/icn_46_e2val J
    putstatic rung36_jcon_scan/icn_46_bound J
    getstatic rung36_jcon_scan/icn_46_e2seen I
    ifne icn_46_init_e2adv
    getstatic rung36_jcon_scan/icn_46_e1val J
    putstatic rung36_jcon_scan/icn_46_e1cur J
    getstatic rung36_jcon_scan/icn_46_e1cur J
    putstatic rung36_jcon_scan/icn_46_I J
    iconst_1
    putstatic rung36_jcon_scan/icn_46_e2seen I
    goto icn_46_code
icn_46_init_e2adv:
    getstatic rung36_jcon_scan/icn_46_e1cur J
    putstatic rung36_jcon_scan/icn_46_I J
    goto icn_46_code
icn_46_code:
    getstatic rung36_jcon_scan/icn_46_I J
    getstatic rung36_jcon_scan/icn_46_bound J
    lcmp
    ifgt icn_46_e2b
    getstatic rung36_jcon_scan/icn_46_I J
    goto icn_45_scan_setup
;  INT
icn_50_α:
    ldc2_w 1
    goto icn_49_mva
icn_50_β:
    goto icn_45_scan_bfail
icn_49_α:
    goto icn_50_α
icn_49_β:
    goto icn_45_scan_bfail
icn_49_mva:
;  move: n (long) on stack
    l2i
    getstatic rung36_jcon_scan/icn_subject Ljava/lang/String;
    getstatic rung36_jcon_scan/icn_pos I
    invokestatic rung36_jcon_scan/icn_builtin_move_str(ILjava/lang/String;I)Ljava/lang/String;
    dup
    ifnonnull icn_49_mvo
    pop
    goto icn_45_scan_bfail
icn_49_mvo:
;  move ok: icn_pos advanced by helper, push String → γ
    goto icn_45_scan_bok
;  SCAN
icn_45_α:
    goto icn_46_α
icn_45_β:
    goto icn_45_scan_beta
icn_45_scan_setup:
;  SCAN save+install
    getstatic rung36_jcon_scan/icn_subject Ljava/lang/String;
    putstatic rung36_jcon_scan/icn_scan_oldsubj_45 Ljava/lang/String;
    getstatic rung36_jcon_scan/icn_pos I
    putstatic rung36_jcon_scan/icn_scan_oldpos_45 I
    putstatic rung36_jcon_scan/icn_subject Ljava/lang/String;
    iconst_0
    putstatic rung36_jcon_scan/icn_pos I
    goto icn_49_α
icn_45_scan_bok:
;  SCAN restore (body ok)
    getstatic rung36_jcon_scan/icn_scan_oldsubj_45 Ljava/lang/String;
    putstatic rung36_jcon_scan/icn_subject Ljava/lang/String;
    getstatic rung36_jcon_scan/icn_scan_oldpos_45 I
    putstatic rung36_jcon_scan/icn_pos I
    goto icn_44_waft_0
icn_45_scan_bfail:
;  SCAN restore (body fail)
    getstatic rung36_jcon_scan/icn_scan_oldsubj_45 Ljava/lang/String;
    putstatic rung36_jcon_scan/icn_subject Ljava/lang/String;
    getstatic rung36_jcon_scan/icn_scan_oldpos_45 I
    putstatic rung36_jcon_scan/icn_pos I
    goto icn_46_β
icn_45_scan_beta:
;  SCAN restore (outer β)
    getstatic rung36_jcon_scan/icn_scan_oldsubj_45 Ljava/lang/String;
    putstatic rung36_jcon_scan/icn_subject Ljava/lang/String;
    getstatic rung36_jcon_scan/icn_scan_oldpos_45 I
    putstatic rung36_jcon_scan/icn_pos I
    goto icn_49_β
icn_44_α:
    goto icn_45_α
icn_44_β:
    goto icn_45_β
    goto icn_44_wentry
icn_44_waft_0:
    astore 172
    getstatic java/lang/System/out Ljava/io/PrintStream;
    aload 172
    invokevirtual java/io/PrintStream/print(Ljava/lang/String;)V
    getstatic java/lang/System/out Ljava/io/PrintStream;
    ldc ""
    invokevirtual java/io/PrintStream/println(Ljava/lang/String;)V
    aload 172
    goto icn_43_gdrain
icn_44_wentry:
    goto icn_45_α
icn_43_gdrain:
    pop
icn_43_pump:
    goto icn_44_β
icn_43_α:
    goto icn_44_α
icn_43_β:
    goto icn_41_α
icn_42_α:
    goto icn_43_α
icn_42_β:
    goto icn_43_β
icn_42_image_after:
    invokestatic java/lang/Long/toString(J)Ljava/lang/String;
    goto icn_40_alt_g0
icn_40_alt_g0:
    astore 173
    sipush 1
    putstatic rung36_jcon_scan/icn_40_alt_gate I
    aload 173
    goto icn_38_waft_1
icn_40_alt_g1:
    astore 174
    sipush 2
    putstatic rung36_jcon_scan/icn_40_alt_gate I
    aload 174
    goto icn_38_waft_1
icn_40_α:
    iconst_0
    putstatic rung36_jcon_scan/icn_40_alt_gate I
    goto icn_42_α
icn_40_β:
    getstatic rung36_jcon_scan/icn_40_alt_gate I
    tableswitch 1 2
        icn_42_β
        icn_41_β
        default: icn_31_α
icn_38_α:
    goto icn_39_α
icn_38_β:
    goto icn_39_β
    goto icn_38_wentry
icn_38_waft_0:
    astore 175
    getstatic java/lang/System/out Ljava/io/PrintStream;
    aload 175
    invokevirtual java/io/PrintStream/print(Ljava/lang/String;)V
    goto icn_40_α
icn_38_waft_1:
    astore 176
    getstatic java/lang/System/out Ljava/io/PrintStream;
    aload 176
    invokevirtual java/io/PrintStream/print(Ljava/lang/String;)V
    getstatic java/lang/System/out Ljava/io/PrintStream;
    ldc ""
    invokevirtual java/io/PrintStream/println(Ljava/lang/String;)V
    aload 176
    goto icn_p1_s3_sdrain
icn_38_wentry:
    goto icn_39_α
icn_p1_s3_sdrain:
    pop
    goto icn_31_α
;  STR
icn_52_α:
    ldc "every write(((\"aeiou\" | \"foobaz\") ? upto('dracula')) ? =(1 to 10)) ----> "
    goto icn_51_waft_0
icn_52_β:
    goto icn_38_α
;  STR
icn_54_α:
    ldc "none"
    goto icn_53_alt_g1
icn_54_β:
    goto icn_38_α
;  STR
icn_61_α:
    ldc "foobaz"
    goto icn_60_alt_g1
icn_61_β:
    goto icn_54_α
;  STR
icn_62_α:
    ldc "aeiou"
    goto icn_60_alt_g0
icn_62_β:
    goto icn_61_α
icn_60_alt_g0:
    astore 177
    sipush 1
    putstatic rung36_jcon_scan/icn_60_alt_gate I
    aload 177
    goto icn_59_scan_setup
icn_60_alt_g1:
    astore 178
    sipush 2
    putstatic rung36_jcon_scan/icn_60_alt_gate I
    aload 178
    goto icn_59_scan_setup
icn_60_α:
    iconst_0
    putstatic rung36_jcon_scan/icn_60_alt_gate I
    goto icn_62_α
icn_60_β:
    getstatic rung36_jcon_scan/icn_60_alt_gate I
    tableswitch 1 2
        icn_62_β
        icn_61_β
        default: icn_54_α
;  STR
icn_64_α:
    ldc "dracula"
    goto icn_63_after
icn_64_β:
    goto icn_59_scan_bfail
icn_63_α:
    goto icn_64_α
icn_63_after:
;  upto α: save cs, enter step
    putstatic rung36_jcon_scan/icn_upto_cs_63 Ljava/lang/String;
    goto icn_63_step
icn_63_β:
    goto icn_63_step
icn_63_step:
;  upto step
    getstatic rung36_jcon_scan/icn_upto_cs_63 Ljava/lang/String;
    getstatic rung36_jcon_scan/icn_subject Ljava/lang/String;
    getstatic rung36_jcon_scan/icn_pos I
    invokestatic rung36_jcon_scan/icn_builtin_upto_step(Ljava/lang/String;Ljava/lang/String;I)J
    dup2
    lconst_1
    lneg
    lcmp
    ifne icn_63_chk
    pop2
    goto icn_59_scan_bfail
icn_63_chk:
;  upto: yield 1-based pos (tab advances icn_pos)
    goto icn_59_scan_bok
;  SCAN
icn_59_α:
    goto icn_60_α
icn_59_β:
    goto icn_59_scan_beta
icn_59_scan_setup:
;  SCAN save+install
    getstatic rung36_jcon_scan/icn_subject Ljava/lang/String;
    putstatic rung36_jcon_scan/icn_scan_oldsubj_59 Ljava/lang/String;
    getstatic rung36_jcon_scan/icn_pos I
    putstatic rung36_jcon_scan/icn_scan_oldpos_59 I
    putstatic rung36_jcon_scan/icn_subject Ljava/lang/String;
    iconst_0
    putstatic rung36_jcon_scan/icn_pos I
    goto icn_63_α
icn_59_scan_bok:
;  SCAN restore (body ok)
    getstatic rung36_jcon_scan/icn_scan_oldsubj_59 Ljava/lang/String;
    putstatic rung36_jcon_scan/icn_subject Ljava/lang/String;
    getstatic rung36_jcon_scan/icn_scan_oldpos_59 I
    putstatic rung36_jcon_scan/icn_pos I
    goto icn_58_scan_setup
icn_59_scan_bfail:
;  SCAN restore (body fail)
    getstatic rung36_jcon_scan/icn_scan_oldsubj_59 Ljava/lang/String;
    putstatic rung36_jcon_scan/icn_subject Ljava/lang/String;
    getstatic rung36_jcon_scan/icn_scan_oldpos_59 I
    putstatic rung36_jcon_scan/icn_pos I
    goto icn_60_β
icn_59_scan_beta:
;  SCAN restore (outer β)
    getstatic rung36_jcon_scan/icn_scan_oldsubj_59 Ljava/lang/String;
    putstatic rung36_jcon_scan/icn_subject Ljava/lang/String;
    getstatic rung36_jcon_scan/icn_scan_oldpos_59 I
    putstatic rung36_jcon_scan/icn_pos I
    goto icn_63_β
;  INT
icn_67_α:
    ldc2_w 10
    goto icn_66_e2relay
icn_67_β:
    goto icn_66_e1b
;  INT
icn_68_α:
    ldc2_w 1
    goto icn_66_e1relay
icn_68_β:
    goto icn_58_scan_bfail
icn_66_e1relay:
    putstatic rung36_jcon_scan/icn_66_e1val J
    goto icn_67_α
icn_66_e2relay:
    putstatic rung36_jcon_scan/icn_66_e2val J
    goto icn_66_init
icn_66_e1b:
    iconst_0
    putstatic rung36_jcon_scan/icn_66_e2seen I
    goto icn_68_β
icn_66_e2b:
    goto icn_67_β
icn_66_α:
    iconst_0
    putstatic rung36_jcon_scan/icn_66_e2seen I
    goto icn_68_α
icn_66_β:
    getstatic rung36_jcon_scan/icn_66_I J
    lconst_1
    ladd
    putstatic rung36_jcon_scan/icn_66_I J
    goto icn_66_code
icn_66_init:
    getstatic rung36_jcon_scan/icn_66_e2val J
    putstatic rung36_jcon_scan/icn_66_bound J
    getstatic rung36_jcon_scan/icn_66_e2seen I
    ifne icn_66_init_e2adv
    getstatic rung36_jcon_scan/icn_66_e1val J
    putstatic rung36_jcon_scan/icn_66_e1cur J
    getstatic rung36_jcon_scan/icn_66_e1cur J
    putstatic rung36_jcon_scan/icn_66_I J
    iconst_1
    putstatic rung36_jcon_scan/icn_66_e2seen I
    goto icn_66_code
icn_66_init_e2adv:
    getstatic rung36_jcon_scan/icn_66_e1cur J
    putstatic rung36_jcon_scan/icn_66_I J
    goto icn_66_code
icn_66_code:
    getstatic rung36_jcon_scan/icn_66_I J
    getstatic rung36_jcon_scan/icn_66_bound J
    lcmp
    ifgt icn_66_e2b
    getstatic rung36_jcon_scan/icn_66_I J
    goto icn_65_ma
icn_65_α:
    goto icn_66_α
icn_65_β:
    goto icn_58_scan_bfail
icn_65_ma:
;  match: s String on stack
    getstatic rung36_jcon_scan/icn_subject Ljava/lang/String;
    getstatic rung36_jcon_scan/icn_pos I
    invokestatic rung36_jcon_scan/icn_builtin_match(Ljava/lang/String;Ljava/lang/String;I)J
    dup2
    lconst_1
    lneg
    lcmp
    ifne icn_65_mo
    pop2
    goto icn_58_scan_bfail
icn_65_mo:
;  match ok: icn_pos = result-1 (0-based), push result → γ
    dup2
    l2i
    iconst_1
    isub
    putstatic rung36_jcon_scan/icn_pos I
    goto icn_58_scan_bok
;  SCAN
icn_58_α:
    goto icn_59_α
icn_58_β:
    goto icn_58_scan_beta
icn_58_scan_setup:
;  SCAN save+install
    getstatic rung36_jcon_scan/icn_subject Ljava/lang/String;
    putstatic rung36_jcon_scan/icn_scan_oldsubj_58 Ljava/lang/String;
    getstatic rung36_jcon_scan/icn_pos I
    putstatic rung36_jcon_scan/icn_scan_oldpos_58 I
    putstatic rung36_jcon_scan/icn_subject Ljava/lang/String;
    iconst_0
    putstatic rung36_jcon_scan/icn_pos I
    goto icn_65_α
icn_58_scan_bok:
;  SCAN restore (body ok)
    getstatic rung36_jcon_scan/icn_scan_oldsubj_58 Ljava/lang/String;
    putstatic rung36_jcon_scan/icn_subject Ljava/lang/String;
    getstatic rung36_jcon_scan/icn_scan_oldpos_58 I
    putstatic rung36_jcon_scan/icn_pos I
    goto icn_57_waft_0
icn_58_scan_bfail:
;  SCAN restore (body fail)
    getstatic rung36_jcon_scan/icn_scan_oldsubj_58 Ljava/lang/String;
    putstatic rung36_jcon_scan/icn_subject Ljava/lang/String;
    getstatic rung36_jcon_scan/icn_scan_oldpos_58 I
    putstatic rung36_jcon_scan/icn_pos I
    goto icn_59_β
icn_58_scan_beta:
;  SCAN restore (outer β)
    getstatic rung36_jcon_scan/icn_scan_oldsubj_58 Ljava/lang/String;
    putstatic rung36_jcon_scan/icn_subject Ljava/lang/String;
    getstatic rung36_jcon_scan/icn_scan_oldpos_58 I
    putstatic rung36_jcon_scan/icn_pos I
    goto icn_65_β
icn_57_α:
    goto icn_58_α
icn_57_β:
    goto icn_58_β
    goto icn_57_wentry
icn_57_waft_0:
    astore 179
    getstatic java/lang/System/out Ljava/io/PrintStream;
    aload 179
    invokevirtual java/io/PrintStream/print(Ljava/lang/String;)V
    getstatic java/lang/System/out Ljava/io/PrintStream;
    ldc ""
    invokevirtual java/io/PrintStream/println(Ljava/lang/String;)V
    aload 179
    goto icn_56_gdrain
icn_57_wentry:
    goto icn_58_α
icn_56_gdrain:
    pop
icn_56_pump:
    goto icn_57_β
icn_56_α:
    goto icn_57_α
icn_56_β:
    goto icn_54_α
icn_55_α:
    goto icn_56_α
icn_55_β:
    goto icn_56_β
icn_55_image_after:
    invokestatic java/lang/Long/toString(J)Ljava/lang/String;
    goto icn_53_alt_g0
icn_53_alt_g0:
    astore 180
    sipush 1
    putstatic rung36_jcon_scan/icn_53_alt_gate I
    aload 180
    goto icn_51_waft_1
icn_53_alt_g1:
    astore 181
    sipush 2
    putstatic rung36_jcon_scan/icn_53_alt_gate I
    aload 181
    goto icn_51_waft_1
icn_53_α:
    iconst_0
    putstatic rung36_jcon_scan/icn_53_alt_gate I
    goto icn_55_α
icn_53_β:
    getstatic rung36_jcon_scan/icn_53_alt_gate I
    tableswitch 1 2
        icn_55_β
        icn_54_β
        default: icn_38_α
icn_51_α:
    goto icn_52_α
icn_51_β:
    goto icn_52_β
    goto icn_51_wentry
icn_51_waft_0:
    astore 182
    getstatic java/lang/System/out Ljava/io/PrintStream;
    aload 182
    invokevirtual java/io/PrintStream/print(Ljava/lang/String;)V
    goto icn_53_α
icn_51_waft_1:
    astore 183
    getstatic java/lang/System/out Ljava/io/PrintStream;
    aload 183
    invokevirtual java/io/PrintStream/print(Ljava/lang/String;)V
    getstatic java/lang/System/out Ljava/io/PrintStream;
    ldc ""
    invokevirtual java/io/PrintStream/println(Ljava/lang/String;)V
    aload 183
    goto icn_p1_s2_sdrain
icn_51_wentry:
    goto icn_52_α
icn_p1_s2_sdrain:
    pop
    goto icn_38_α
;  STR
icn_70_α:
    ldc "every write((\"badc\" | \"edgf\" | \"x\") ? write(upto(!&lcase))) ----> "
    goto icn_69_waft_0
icn_70_β:
    goto icn_51_α
;  STR
icn_72_α:
    ldc "none"
    goto icn_71_alt_g1
icn_72_β:
    goto icn_51_α
;  STR
icn_78_α:
    ldc "x"
    goto icn_77_alt_g2
icn_78_β:
    goto icn_72_α
;  STR
icn_79_α:
    ldc "edgf"
    goto icn_77_alt_g1
icn_79_β:
    goto icn_78_α
;  STR
icn_80_α:
    ldc "badc"
    goto icn_77_alt_g0
icn_80_β:
    goto icn_79_α
icn_77_alt_g0:
    astore 184
    sipush 1
    putstatic rung36_jcon_scan/icn_77_alt_gate I
    aload 184
    goto icn_76_scan_setup
icn_77_alt_g1:
    astore 185
    sipush 2
    putstatic rung36_jcon_scan/icn_77_alt_gate I
    aload 185
    goto icn_76_scan_setup
icn_77_alt_g2:
    astore 186
    sipush 3
    putstatic rung36_jcon_scan/icn_77_alt_gate I
    aload 186
    goto icn_76_scan_setup
icn_77_α:
    iconst_0
    putstatic rung36_jcon_scan/icn_77_alt_gate I
    goto icn_80_α
icn_77_β:
    getstatic rung36_jcon_scan/icn_77_alt_gate I
    tableswitch 1 3
        icn_80_β
        icn_79_β
        icn_78_β
        default: icn_72_α
;  VAR
icn_84_α:
    ldc "abcdefghijklmnopqrstuvwxyz"
    goto icn_83_bang_adv
icn_84_β:
    goto icn_76_scan_bfail
icn_83_α:
    goto icn_84_α
icn_83_β:
    goto icn_83_bang_chk
icn_83_bang_adv:
    putstatic rung36_jcon_scan/icn_83_bang_str Ljava/lang/String;
    iconst_0
    putstatic rung36_jcon_scan/icn_83_bang_pos I
icn_83_bang_chk:
    getstatic rung36_jcon_scan/icn_83_bang_str Ljava/lang/String;
    invokevirtual java/lang/String/length()I
    getstatic rung36_jcon_scan/icn_83_bang_pos I
    if_icmple icn_76_scan_bfail
    getstatic rung36_jcon_scan/icn_83_bang_str Ljava/lang/String;
    getstatic rung36_jcon_scan/icn_83_bang_pos I
    getstatic rung36_jcon_scan/icn_83_bang_pos I
    iconst_1
    iadd
    invokevirtual java/lang/String/substring(II)Ljava/lang/String;
    getstatic rung36_jcon_scan/icn_83_bang_pos I
    iconst_1
    iadd
    putstatic rung36_jcon_scan/icn_83_bang_pos I
    goto icn_82_after
icn_82_α:
    goto icn_83_α
icn_82_after:
;  upto α: save cs, enter step
    putstatic rung36_jcon_scan/icn_upto_cs_82 Ljava/lang/String;
    goto icn_82_step
icn_82_β:
    goto icn_82_step
icn_82_step:
;  upto step
    getstatic rung36_jcon_scan/icn_upto_cs_82 Ljava/lang/String;
    getstatic rung36_jcon_scan/icn_subject Ljava/lang/String;
    getstatic rung36_jcon_scan/icn_pos I
    invokestatic rung36_jcon_scan/icn_builtin_upto_step(Ljava/lang/String;Ljava/lang/String;I)J
    dup2
    lconst_1
    lneg
    lcmp
    ifne icn_82_chk
    pop2
    goto icn_76_scan_bfail
icn_82_chk:
;  upto: yield 1-based pos (tab advances icn_pos)
    goto icn_81_waft_0
icn_81_α:
    goto icn_82_α
icn_81_β:
    goto icn_82_β
    goto icn_81_wentry
icn_81_waft_0:
    lstore 2
    getstatic java/lang/System/out Ljava/io/PrintStream;
    lload 2
    invokevirtual java/io/PrintStream/print(J)V
    getstatic java/lang/System/out Ljava/io/PrintStream;
    ldc ""
    invokevirtual java/io/PrintStream/println(Ljava/lang/String;)V
    lload 2
    goto icn_76_scan_bok
icn_81_wentry:
    goto icn_82_α
;  SCAN
icn_76_α:
    goto icn_77_α
icn_76_β:
    goto icn_76_scan_beta
icn_76_scan_setup:
;  SCAN save+install
    getstatic rung36_jcon_scan/icn_subject Ljava/lang/String;
    putstatic rung36_jcon_scan/icn_scan_oldsubj_76 Ljava/lang/String;
    getstatic rung36_jcon_scan/icn_pos I
    putstatic rung36_jcon_scan/icn_scan_oldpos_76 I
    putstatic rung36_jcon_scan/icn_subject Ljava/lang/String;
    iconst_0
    putstatic rung36_jcon_scan/icn_pos I
    goto icn_81_α
icn_76_scan_bok:
;  SCAN restore (body ok)
    getstatic rung36_jcon_scan/icn_scan_oldsubj_76 Ljava/lang/String;
    putstatic rung36_jcon_scan/icn_subject Ljava/lang/String;
    getstatic rung36_jcon_scan/icn_scan_oldpos_76 I
    putstatic rung36_jcon_scan/icn_pos I
    goto icn_75_waft_0
icn_76_scan_bfail:
;  SCAN restore (body fail)
    getstatic rung36_jcon_scan/icn_scan_oldsubj_76 Ljava/lang/String;
    putstatic rung36_jcon_scan/icn_subject Ljava/lang/String;
    getstatic rung36_jcon_scan/icn_scan_oldpos_76 I
    putstatic rung36_jcon_scan/icn_pos I
    goto icn_77_β
icn_76_scan_beta:
;  SCAN restore (outer β)
    getstatic rung36_jcon_scan/icn_scan_oldsubj_76 Ljava/lang/String;
    putstatic rung36_jcon_scan/icn_subject Ljava/lang/String;
    getstatic rung36_jcon_scan/icn_scan_oldpos_76 I
    putstatic rung36_jcon_scan/icn_pos I
    goto icn_81_β
icn_75_α:
    goto icn_76_α
icn_75_β:
    goto icn_76_β
    goto icn_75_wentry
icn_75_waft_0:
    astore 187
    getstatic java/lang/System/out Ljava/io/PrintStream;
    aload 187
    invokevirtual java/io/PrintStream/print(Ljava/lang/String;)V
    getstatic java/lang/System/out Ljava/io/PrintStream;
    ldc ""
    invokevirtual java/io/PrintStream/println(Ljava/lang/String;)V
    aload 187
    goto icn_74_gdrain
icn_75_wentry:
    goto icn_76_α
icn_74_gdrain:
    pop
icn_74_pump:
    goto icn_75_β
icn_74_α:
    goto icn_75_α
icn_74_β:
    goto icn_72_α
icn_73_α:
    goto icn_74_α
icn_73_β:
    goto icn_74_β
icn_73_image_after:
    invokestatic java/lang/Long/toString(J)Ljava/lang/String;
    goto icn_71_alt_g0
icn_71_alt_g0:
    astore 188
    sipush 1
    putstatic rung36_jcon_scan/icn_71_alt_gate I
    aload 188
    goto icn_69_waft_1
icn_71_alt_g1:
    astore 189
    sipush 2
    putstatic rung36_jcon_scan/icn_71_alt_gate I
    aload 189
    goto icn_69_waft_1
icn_71_α:
    iconst_0
    putstatic rung36_jcon_scan/icn_71_alt_gate I
    goto icn_73_α
icn_71_β:
    getstatic rung36_jcon_scan/icn_71_alt_gate I
    tableswitch 1 2
        icn_73_β
        icn_72_β
        default: icn_51_α
icn_69_α:
    goto icn_70_α
icn_69_β:
    goto icn_70_β
    goto icn_69_wentry
icn_69_waft_0:
    astore 190
    getstatic java/lang/System/out Ljava/io/PrintStream;
    aload 190
    invokevirtual java/io/PrintStream/print(Ljava/lang/String;)V
    goto icn_71_α
icn_69_waft_1:
    astore 191
    getstatic java/lang/System/out Ljava/io/PrintStream;
    aload 191
    invokevirtual java/io/PrintStream/print(Ljava/lang/String;)V
    getstatic java/lang/System/out Ljava/io/PrintStream;
    ldc ""
    invokevirtual java/io/PrintStream/println(Ljava/lang/String;)V
    aload 191
    goto icn_p1_s1_sdrain
icn_69_wentry:
    goto icn_70_α
icn_p1_s1_sdrain:
    pop
    goto icn_51_α
;  STR
icn_86_α:
    ldc " ----> "
    goto icn_85_waft_0
icn_86_β:
    goto icn_69_α
;  STR
icn_88_α:
    ldc "none"
    goto icn_87_alt_g1
icn_88_β:
    goto icn_69_α
icn_89_α:
    goto icn_88_α
icn_89_β:
    goto icn_88_α
icn_87_alt_g0:
    astore 192
    sipush 1
    putstatic rung36_jcon_scan/icn_87_alt_gate I
    aload 192
    goto icn_85_waft_1
icn_87_alt_g1:
    astore 193
    sipush 2
    putstatic rung36_jcon_scan/icn_87_alt_gate I
    aload 193
    goto icn_85_waft_1
icn_87_α:
    iconst_0
    putstatic rung36_jcon_scan/icn_87_alt_gate I
    goto icn_89_α
icn_87_β:
    getstatic rung36_jcon_scan/icn_87_alt_gate I
    tableswitch 1 2
        icn_89_β
        icn_88_β
        default: icn_69_α
icn_85_α:
    goto icn_86_α
icn_85_β:
    goto icn_86_β
    goto icn_85_wentry
icn_85_waft_0:
    astore 194
    getstatic java/lang/System/out Ljava/io/PrintStream;
    aload 194
    invokevirtual java/io/PrintStream/print(Ljava/lang/String;)V
    goto icn_87_α
icn_85_waft_1:
    astore 195
    getstatic java/lang/System/out Ljava/io/PrintStream;
    aload 195
    invokevirtual java/io/PrintStream/print(Ljava/lang/String;)V
    getstatic java/lang/System/out Ljava/io/PrintStream;
    ldc ""
    invokevirtual java/io/PrintStream/println(Ljava/lang/String;)V
    aload 195
    goto icn_p1_s0_sdrain
icn_85_wentry:
    goto icn_86_α
icn_p1_s0_sdrain:
    pop
    goto icn_69_α
icn_p1_done:
    iconst_0
    putstatic rung36_jcon_scan/icn_suspended B
    iconst_0
    putstatic rung36_jcon_scan/icn_suspend_id I
    iconst_1
    putstatic rung36_jcon_scan/icn_failed B
    return
icn_p1_ret:
    iconst_0
    putstatic rung36_jcon_scan/icn_failed B
    return
icn_p1_sret:
    return
.end method

.method public static icn_p2()V
    .limit stack 16
    .limit locals 318
    lconst_0
    lstore 0
    lconst_0
    lstore 2
    lconst_0
    lstore 4
    lconst_0
    lstore 6
    lconst_0
    lstore 8
    lconst_0
    lstore 10
    lconst_0
    lstore 12
    lconst_0
    lstore 14
    lconst_0
    lstore 16
    lconst_0
    lstore 18
    lconst_0
    lstore 20
    lconst_0
    lstore 22
    lconst_0
    lstore 24
    lconst_0
    lstore 26
    lconst_0
    lstore 28
    lconst_0
    lstore 30
    lconst_0
    lstore 32
    lconst_0
    lstore 34
    lconst_0
    lstore 36
    lconst_0
    lstore 38
    lconst_0
    lstore 40
    lconst_0
    lstore 42
    lconst_0
    lstore 44
    lconst_0
    lstore 46
    lconst_0
    lstore 48
    lconst_0
    lstore 50
    lconst_0
    lstore 52
    lconst_0
    lstore 54
    lconst_0
    lstore 56
    lconst_0
    lstore 58
    lconst_0
    lstore 60
    lconst_0
    lstore 62
    iconst_0
    istore 84
    iconst_0
    istore 85
    iconst_0
    istore 86
    iconst_0
    istore 87
    aconst_null
    astore 148
    aconst_null
    astore 149
    aconst_null
    astore 150
    aconst_null
    astore 151
    aconst_null
    astore 152
    aconst_null
    astore 153
    aconst_null
    astore 154
    aconst_null
    astore 155
    aconst_null
    astore 156
    aconst_null
    astore 157
    aconst_null
    astore 158
    aconst_null
    astore 159
    aconst_null
    astore 160
    aconst_null
    astore 161
    aconst_null
    astore 162
    aconst_null
    astore 163
    aconst_null
    astore 164
    aconst_null
    astore 165
    aconst_null
    astore 166
    aconst_null
    astore 167
    aconst_null
    astore 168
    aconst_null
    astore 169
    aconst_null
    astore 170
    aconst_null
    astore 171
    aconst_null
    astore 172
    aconst_null
    astore 173
    aconst_null
    astore 174
    aconst_null
    astore 175
    aconst_null
    astore 176
    aconst_null
    astore 177
    aconst_null
    astore 178
    aconst_null
    astore 179
    aconst_null
    astore 180
    aconst_null
    astore 181
    aconst_null
    astore 182
    aconst_null
    astore 183
    aconst_null
    astore 184
    aconst_null
    astore 185
    aconst_null
    astore 186
    aconst_null
    astore 187
    aconst_null
    astore 188
    aconst_null
    astore 189
    aconst_null
    astore 190
    aconst_null
    astore 191
    goto icn_155_α
;  STR
icn_91_α:
    ldc "&subject := string(&lcase) ----> "
    goto icn_90_waft_0
icn_91_β:
    goto icn_p2_done
;  STR
icn_93_α:
    ldc "none"
    goto icn_92_alt_g1
icn_93_β:
    goto icn_p2_done
;  VAR
icn_97_α:
    ldc "abcdefghijklmnopqrstuvwxyz"
    goto icn_96_str_after
icn_97_β:
    goto icn_93_α
icn_96_α:
    goto icn_97_α
icn_96_β:
    goto icn_97_β
icn_96_str_after:
    invokestatic java/lang/Long/toString(J)Ljava/lang/String;
    goto icn_95_store
icn_95_α:
    goto icn_96_α
icn_95_β:
    goto icn_96_β
icn_95_store:
    putstatic rung36_jcon_scan/icn_pv_p2__kw_subject Ljava/lang/String;
    getstatic rung36_jcon_scan/icn_pv_p2__kw_subject Ljava/lang/String;
    goto icn_94_image_after
icn_94_α:
    goto icn_95_α
icn_94_β:
    goto icn_95_β
icn_94_image_after:
    goto icn_92_alt_g0
icn_92_alt_g0:
    astore 148
    sipush 1
    putstatic rung36_jcon_scan/icn_92_alt_gate I
    aload 148
    goto icn_90_waft_1
icn_92_alt_g1:
    astore 149
    sipush 2
    putstatic rung36_jcon_scan/icn_92_alt_gate I
    aload 149
    goto icn_90_waft_1
icn_92_α:
    iconst_0
    putstatic rung36_jcon_scan/icn_92_alt_gate I
    goto icn_94_α
icn_92_β:
    getstatic rung36_jcon_scan/icn_92_alt_gate I
    tableswitch 1 2
        icn_94_β
        icn_93_β
        default: icn_p2_done
icn_90_α:
    goto icn_91_α
icn_90_β:
    goto icn_91_β
    goto icn_90_wentry
icn_90_waft_0:
    astore 150
    getstatic java/lang/System/out Ljava/io/PrintStream;
    aload 150
    invokevirtual java/io/PrintStream/print(Ljava/lang/String;)V
    goto icn_92_α
icn_90_waft_1:
    astore 151
    getstatic java/lang/System/out Ljava/io/PrintStream;
    aload 151
    invokevirtual java/io/PrintStream/print(Ljava/lang/String;)V
    getstatic java/lang/System/out Ljava/io/PrintStream;
    ldc ""
    invokevirtual java/io/PrintStream/println(Ljava/lang/String;)V
    aload 151
    goto icn_p2_s9_sdrain
icn_90_wentry:
    goto icn_91_α
icn_p2_s9_sdrain:
    pop
    goto icn_p2_done
;  STR
icn_99_α:
    ldc "=\"d\" ----> "
    goto icn_98_waft_0
icn_99_β:
    goto icn_90_α
;  STR
icn_101_α:
    ldc "none"
    goto icn_100_alt_g1
icn_101_β:
    goto icn_90_α
;  STR
icn_104_α:
    ldc "d"
    goto icn_103_ma
icn_104_β:
    goto icn_101_α
icn_103_α:
    goto icn_104_α
icn_103_β:
    goto icn_101_α
icn_103_ma:
;  match: s String on stack
    getstatic rung36_jcon_scan/icn_subject Ljava/lang/String;
    getstatic rung36_jcon_scan/icn_pos I
    invokestatic rung36_jcon_scan/icn_builtin_match(Ljava/lang/String;Ljava/lang/String;I)J
    dup2
    lconst_1
    lneg
    lcmp
    ifne icn_103_mo
    pop2
    goto icn_101_α
icn_103_mo:
;  match ok: icn_pos = result-1 (0-based), push result → γ
    dup2
    l2i
    iconst_1
    isub
    putstatic rung36_jcon_scan/icn_pos I
    goto icn_102_image_after
icn_102_α:
    goto icn_103_α
icn_102_β:
    goto icn_103_β
icn_102_image_after:
    invokestatic java/lang/Long/toString(J)Ljava/lang/String;
    goto icn_100_alt_g0
icn_100_alt_g0:
    astore 152
    sipush 1
    putstatic rung36_jcon_scan/icn_100_alt_gate I
    aload 152
    goto icn_98_waft_1
icn_100_alt_g1:
    astore 153
    sipush 2
    putstatic rung36_jcon_scan/icn_100_alt_gate I
    aload 153
    goto icn_98_waft_1
icn_100_α:
    iconst_0
    putstatic rung36_jcon_scan/icn_100_alt_gate I
    goto icn_102_α
icn_100_β:
    getstatic rung36_jcon_scan/icn_100_alt_gate I
    tableswitch 1 2
        icn_102_β
        icn_101_β
        default: icn_90_α
icn_98_α:
    goto icn_99_α
icn_98_β:
    goto icn_99_β
    goto icn_98_wentry
icn_98_waft_0:
    astore 154
    getstatic java/lang/System/out Ljava/io/PrintStream;
    aload 154
    invokevirtual java/io/PrintStream/print(Ljava/lang/String;)V
    goto icn_100_α
icn_98_waft_1:
    astore 155
    getstatic java/lang/System/out Ljava/io/PrintStream;
    aload 155
    invokevirtual java/io/PrintStream/print(Ljava/lang/String;)V
    getstatic java/lang/System/out Ljava/io/PrintStream;
    ldc ""
    invokevirtual java/io/PrintStream/println(Ljava/lang/String;)V
    aload 155
    goto icn_p2_s8_sdrain
icn_98_wentry:
    goto icn_99_α
icn_p2_s8_sdrain:
    pop
    goto icn_90_α
;  STR
icn_106_α:
    ldc "=\"b\" ----> "
    goto icn_105_waft_0
icn_106_β:
    goto icn_98_α
;  STR
icn_108_α:
    ldc "none"
    goto icn_107_alt_g1
icn_108_β:
    goto icn_98_α
;  STR
icn_111_α:
    ldc "b"
    goto icn_110_ma
icn_111_β:
    goto icn_108_α
icn_110_α:
    goto icn_111_α
icn_110_β:
    goto icn_108_α
icn_110_ma:
;  match: s String on stack
    getstatic rung36_jcon_scan/icn_subject Ljava/lang/String;
    getstatic rung36_jcon_scan/icn_pos I
    invokestatic rung36_jcon_scan/icn_builtin_match(Ljava/lang/String;Ljava/lang/String;I)J
    dup2
    lconst_1
    lneg
    lcmp
    ifne icn_110_mo
    pop2
    goto icn_108_α
icn_110_mo:
;  match ok: icn_pos = result-1 (0-based), push result → γ
    dup2
    l2i
    iconst_1
    isub
    putstatic rung36_jcon_scan/icn_pos I
    goto icn_109_image_after
icn_109_α:
    goto icn_110_α
icn_109_β:
    goto icn_110_β
icn_109_image_after:
    invokestatic java/lang/Long/toString(J)Ljava/lang/String;
    goto icn_107_alt_g0
icn_107_alt_g0:
    astore 156
    sipush 1
    putstatic rung36_jcon_scan/icn_107_alt_gate I
    aload 156
    goto icn_105_waft_1
icn_107_alt_g1:
    astore 157
    sipush 2
    putstatic rung36_jcon_scan/icn_107_alt_gate I
    aload 157
    goto icn_105_waft_1
icn_107_α:
    iconst_0
    putstatic rung36_jcon_scan/icn_107_alt_gate I
    goto icn_109_α
icn_107_β:
    getstatic rung36_jcon_scan/icn_107_alt_gate I
    tableswitch 1 2
        icn_109_β
        icn_108_β
        default: icn_98_α
icn_105_α:
    goto icn_106_α
icn_105_β:
    goto icn_106_β
    goto icn_105_wentry
icn_105_waft_0:
    astore 158
    getstatic java/lang/System/out Ljava/io/PrintStream;
    aload 158
    invokevirtual java/io/PrintStream/print(Ljava/lang/String;)V
    goto icn_107_α
icn_105_waft_1:
    astore 159
    getstatic java/lang/System/out Ljava/io/PrintStream;
    aload 159
    invokevirtual java/io/PrintStream/print(Ljava/lang/String;)V
    getstatic java/lang/System/out Ljava/io/PrintStream;
    ldc ""
    invokevirtual java/io/PrintStream/println(Ljava/lang/String;)V
    aload 159
    goto icn_p2_s7_sdrain
icn_105_wentry:
    goto icn_106_α
icn_p2_s7_sdrain:
    pop
    goto icn_98_α
;  STR
icn_113_α:
    ldc "=\"a\" ----> "
    goto icn_112_waft_0
icn_113_β:
    goto icn_105_α
;  STR
icn_115_α:
    ldc "none"
    goto icn_114_alt_g1
icn_115_β:
    goto icn_105_α
;  STR
icn_118_α:
    ldc "a"
    goto icn_117_ma
icn_118_β:
    goto icn_115_α
icn_117_α:
    goto icn_118_α
icn_117_β:
    goto icn_115_α
icn_117_ma:
;  match: s String on stack
    getstatic rung36_jcon_scan/icn_subject Ljava/lang/String;
    getstatic rung36_jcon_scan/icn_pos I
    invokestatic rung36_jcon_scan/icn_builtin_match(Ljava/lang/String;Ljava/lang/String;I)J
    dup2
    lconst_1
    lneg
    lcmp
    ifne icn_117_mo
    pop2
    goto icn_115_α
icn_117_mo:
;  match ok: icn_pos = result-1 (0-based), push result → γ
    dup2
    l2i
    iconst_1
    isub
    putstatic rung36_jcon_scan/icn_pos I
    goto icn_116_image_after
icn_116_α:
    goto icn_117_α
icn_116_β:
    goto icn_117_β
icn_116_image_after:
    invokestatic java/lang/Long/toString(J)Ljava/lang/String;
    goto icn_114_alt_g0
icn_114_alt_g0:
    astore 160
    sipush 1
    putstatic rung36_jcon_scan/icn_114_alt_gate I
    aload 160
    goto icn_112_waft_1
icn_114_alt_g1:
    astore 161
    sipush 2
    putstatic rung36_jcon_scan/icn_114_alt_gate I
    aload 161
    goto icn_112_waft_1
icn_114_α:
    iconst_0
    putstatic rung36_jcon_scan/icn_114_alt_gate I
    goto icn_116_α
icn_114_β:
    getstatic rung36_jcon_scan/icn_114_alt_gate I
    tableswitch 1 2
        icn_116_β
        icn_115_β
        default: icn_105_α
icn_112_α:
    goto icn_113_α
icn_112_β:
    goto icn_113_β
    goto icn_112_wentry
icn_112_waft_0:
    astore 162
    getstatic java/lang/System/out Ljava/io/PrintStream;
    aload 162
    invokevirtual java/io/PrintStream/print(Ljava/lang/String;)V
    goto icn_114_α
icn_112_waft_1:
    astore 163
    getstatic java/lang/System/out Ljava/io/PrintStream;
    aload 163
    invokevirtual java/io/PrintStream/print(Ljava/lang/String;)V
    getstatic java/lang/System/out Ljava/io/PrintStream;
    ldc ""
    invokevirtual java/io/PrintStream/println(Ljava/lang/String;)V
    aload 163
    goto icn_p2_s6_sdrain
icn_112_wentry:
    goto icn_113_α
icn_p2_s6_sdrain:
    pop
    goto icn_105_α
;  STR
icn_120_α:
    ldc "&subject := string(&lcase) ----> "
    goto icn_119_waft_0
icn_120_β:
    goto icn_112_α
;  STR
icn_122_α:
    ldc "none"
    goto icn_121_alt_g1
icn_122_β:
    goto icn_112_α
;  VAR
icn_126_α:
    ldc "abcdefghijklmnopqrstuvwxyz"
    goto icn_125_str_after
icn_126_β:
    goto icn_122_α
icn_125_α:
    goto icn_126_α
icn_125_β:
    goto icn_126_β
icn_125_str_after:
    invokestatic java/lang/Long/toString(J)Ljava/lang/String;
    goto icn_124_store
icn_124_α:
    goto icn_125_α
icn_124_β:
    goto icn_125_β
icn_124_store:
    putstatic rung36_jcon_scan/icn_pv_p2__kw_subject Ljava/lang/String;
    getstatic rung36_jcon_scan/icn_pv_p2__kw_subject Ljava/lang/String;
    goto icn_123_image_after
icn_123_α:
    goto icn_124_α
icn_123_β:
    goto icn_124_β
icn_123_image_after:
    goto icn_121_alt_g0
icn_121_alt_g0:
    astore 164
    sipush 1
    putstatic rung36_jcon_scan/icn_121_alt_gate I
    aload 164
    goto icn_119_waft_1
icn_121_alt_g1:
    astore 165
    sipush 2
    putstatic rung36_jcon_scan/icn_121_alt_gate I
    aload 165
    goto icn_119_waft_1
icn_121_α:
    iconst_0
    putstatic rung36_jcon_scan/icn_121_alt_gate I
    goto icn_123_α
icn_121_β:
    getstatic rung36_jcon_scan/icn_121_alt_gate I
    tableswitch 1 2
        icn_123_β
        icn_122_β
        default: icn_112_α
icn_119_α:
    goto icn_120_α
icn_119_β:
    goto icn_120_β
    goto icn_119_wentry
icn_119_waft_0:
    astore 166
    getstatic java/lang/System/out Ljava/io/PrintStream;
    aload 166
    invokevirtual java/io/PrintStream/print(Ljava/lang/String;)V
    goto icn_121_α
icn_119_waft_1:
    astore 167
    getstatic java/lang/System/out Ljava/io/PrintStream;
    aload 167
    invokevirtual java/io/PrintStream/print(Ljava/lang/String;)V
    getstatic java/lang/System/out Ljava/io/PrintStream;
    ldc ""
    invokevirtual java/io/PrintStream/println(Ljava/lang/String;)V
    aload 167
    goto icn_p2_s5_sdrain
icn_119_wentry:
    goto icn_120_α
icn_p2_s5_sdrain:
    pop
    goto icn_112_α
;  STR
icn_128_α:
    ldc "~&ascii ----> "
    goto icn_127_waft_0
icn_128_β:
    goto icn_119_α
;  STR
icn_130_α:
    ldc "none"
    goto icn_129_alt_g1
icn_130_β:
    goto icn_119_α
;  VAR
icn_133_α:
    ldc "\u0000\u0001\u0002\u0003\u0004\u0005\u0006\u0007\u0008\u0009\u000a\u000b\u000c\u000d\u000e\u000f\u0010\u0011\u0012\u0013\u0014\u0015\u0016\u0017\u0018\u0019\u001a\u001b\u001c\u001d\u001e\u001f !\"#$%&'()*+,-./0123456789:;<=>?@ABCDEFGHIJKLMNOPQRSTUVWXYZ[\\]^_`abcdefghijklmnopqrstuvwxyz{|}~\u007f"
    goto icn_132_csc_relay
icn_133_β:
    goto icn_130_α
icn_132_α:
    goto icn_133_α
icn_132_β:
    goto icn_133_β
icn_132_csc_relay:
    invokestatic rung36_jcon_scan/icn_builtin_cset_complement(Ljava/lang/String;)Ljava/lang/String;
    goto icn_131_image_after
icn_131_α:
    goto icn_132_α
icn_131_β:
    goto icn_132_β
icn_131_image_after:
    invokestatic java/lang/Long/toString(J)Ljava/lang/String;
    goto icn_129_alt_g0
icn_129_alt_g0:
    astore 168
    sipush 1
    putstatic rung36_jcon_scan/icn_129_alt_gate I
    aload 168
    goto icn_127_waft_1
icn_129_alt_g1:
    astore 169
    sipush 2
    putstatic rung36_jcon_scan/icn_129_alt_gate I
    aload 169
    goto icn_127_waft_1
icn_129_α:
    iconst_0
    putstatic rung36_jcon_scan/icn_129_alt_gate I
    goto icn_131_α
icn_129_β:
    getstatic rung36_jcon_scan/icn_129_alt_gate I
    tableswitch 1 2
        icn_131_β
        icn_130_β
        default: icn_119_α
icn_127_α:
    goto icn_128_α
icn_127_β:
    goto icn_128_β
    goto icn_127_wentry
icn_127_waft_0:
    astore 170
    getstatic java/lang/System/out Ljava/io/PrintStream;
    aload 170
    invokevirtual java/io/PrintStream/print(Ljava/lang/String;)V
    goto icn_129_α
icn_127_waft_1:
    astore 171
    getstatic java/lang/System/out Ljava/io/PrintStream;
    aload 171
    invokevirtual java/io/PrintStream/print(Ljava/lang/String;)V
    getstatic java/lang/System/out Ljava/io/PrintStream;
    ldc ""
    invokevirtual java/io/PrintStream/println(Ljava/lang/String;)V
    aload 171
    goto icn_p2_s4_sdrain
icn_127_wentry:
    goto icn_128_α
icn_p2_s4_sdrain:
    pop
    goto icn_119_α
;  STR
icn_135_α:
    ldc "~&cset ----> "
    goto icn_134_waft_0
icn_135_β:
    goto icn_127_α
;  STR
icn_137_α:
    ldc "none"
    goto icn_136_alt_g1
icn_137_β:
    goto icn_127_α
;  VAR
icn_140_α:
    ldc "\u0000\u0001\u0002\u0003\u0004\u0005\u0006\u0007\u0008\u0009\u000a\u000b\u000c\u000d\u000e\u000f\u0010\u0011\u0012\u0013\u0014\u0015\u0016\u0017\u0018\u0019\u001a\u001b\u001c\u001d\u001e\u001f !\"#$%&'()*+,-./0123456789:;<=>?@ABCDEFGHIJKLMNOPQRSTUVWXYZ[\\]^_`abcdefghijklmnopqrstuvwxyz{|}~\u007f"
    goto icn_139_csc_relay
icn_140_β:
    goto icn_137_α
icn_139_α:
    goto icn_140_α
icn_139_β:
    goto icn_140_β
icn_139_csc_relay:
    invokestatic rung36_jcon_scan/icn_builtin_cset_complement(Ljava/lang/String;)Ljava/lang/String;
    goto icn_138_image_after
icn_138_α:
    goto icn_139_α
icn_138_β:
    goto icn_139_β
icn_138_image_after:
    invokestatic java/lang/Long/toString(J)Ljava/lang/String;
    goto icn_136_alt_g0
icn_136_alt_g0:
    astore 172
    sipush 1
    putstatic rung36_jcon_scan/icn_136_alt_gate I
    aload 172
    goto icn_134_waft_1
icn_136_alt_g1:
    astore 173
    sipush 2
    putstatic rung36_jcon_scan/icn_136_alt_gate I
    aload 173
    goto icn_134_waft_1
icn_136_α:
    iconst_0
    putstatic rung36_jcon_scan/icn_136_alt_gate I
    goto icn_138_α
icn_136_β:
    getstatic rung36_jcon_scan/icn_136_alt_gate I
    tableswitch 1 2
        icn_138_β
        icn_137_β
        default: icn_127_α
icn_134_α:
    goto icn_135_α
icn_134_β:
    goto icn_135_β
    goto icn_134_wentry
icn_134_waft_0:
    astore 174
    getstatic java/lang/System/out Ljava/io/PrintStream;
    aload 174
    invokevirtual java/io/PrintStream/print(Ljava/lang/String;)V
    goto icn_136_α
icn_134_waft_1:
    astore 175
    getstatic java/lang/System/out Ljava/io/PrintStream;
    aload 175
    invokevirtual java/io/PrintStream/print(Ljava/lang/String;)V
    getstatic java/lang/System/out Ljava/io/PrintStream;
    ldc ""
    invokevirtual java/io/PrintStream/println(Ljava/lang/String;)V
    aload 175
    goto icn_p2_s3_sdrain
icn_134_wentry:
    goto icn_135_α
icn_p2_s3_sdrain:
    pop
    goto icn_127_α
;  STR
icn_142_α:
    ldc "?10 ----> "
    goto icn_141_waft_0
icn_142_β:
    goto icn_134_α
;  STR
icn_144_α:
    ldc "none"
    goto icn_143_alt_g1
icn_144_β:
    goto icn_134_α
;  INT
icn_147_α:
    ldc2_w 10
    goto icn_146_rand
icn_147_β:
    goto icn_144_α
icn_146_α:
    goto icn_147_α
icn_146_β:
    goto icn_147_β
icn_146_rand:
    invokestatic rung36_jcon_scan/icn_builtin_random(J)J
    goto icn_145_image_after
icn_145_α:
    goto icn_146_α
icn_145_β:
    goto icn_146_β
icn_145_image_after:
    invokestatic java/lang/Long/toString(J)Ljava/lang/String;
    goto icn_143_alt_g0
icn_143_alt_g0:
    astore 176
    sipush 1
    putstatic rung36_jcon_scan/icn_143_alt_gate I
    aload 176
    goto icn_141_waft_1
icn_143_alt_g1:
    astore 177
    sipush 2
    putstatic rung36_jcon_scan/icn_143_alt_gate I
    aload 177
    goto icn_141_waft_1
icn_143_α:
    iconst_0
    putstatic rung36_jcon_scan/icn_143_alt_gate I
    goto icn_145_α
icn_143_β:
    getstatic rung36_jcon_scan/icn_143_alt_gate I
    tableswitch 1 2
        icn_145_β
        icn_144_β
        default: icn_134_α
icn_141_α:
    goto icn_142_α
icn_141_β:
    goto icn_142_β
    goto icn_141_wentry
icn_141_waft_0:
    astore 178
    getstatic java/lang/System/out Ljava/io/PrintStream;
    aload 178
    invokevirtual java/io/PrintStream/print(Ljava/lang/String;)V
    goto icn_143_α
icn_141_waft_1:
    astore 179
    getstatic java/lang/System/out Ljava/io/PrintStream;
    aload 179
    invokevirtual java/io/PrintStream/print(Ljava/lang/String;)V
    getstatic java/lang/System/out Ljava/io/PrintStream;
    ldc ""
    invokevirtual java/io/PrintStream/println(Ljava/lang/String;)V
    aload 179
    goto icn_p2_s2_sdrain
icn_141_wentry:
    goto icn_142_α
icn_p2_s2_sdrain:
    pop
    goto icn_134_α
;  STR
icn_149_α:
    ldc "?10 ----> "
    goto icn_148_waft_0
icn_149_β:
    goto icn_141_α
;  STR
icn_151_α:
    ldc "none"
    goto icn_150_alt_g1
icn_151_β:
    goto icn_141_α
;  INT
icn_154_α:
    ldc2_w 10
    goto icn_153_rand
icn_154_β:
    goto icn_151_α
icn_153_α:
    goto icn_154_α
icn_153_β:
    goto icn_154_β
icn_153_rand:
    invokestatic rung36_jcon_scan/icn_builtin_random(J)J
    goto icn_152_image_after
icn_152_α:
    goto icn_153_α
icn_152_β:
    goto icn_153_β
icn_152_image_after:
    invokestatic java/lang/Long/toString(J)Ljava/lang/String;
    goto icn_150_alt_g0
icn_150_alt_g0:
    astore 180
    sipush 1
    putstatic rung36_jcon_scan/icn_150_alt_gate I
    aload 180
    goto icn_148_waft_1
icn_150_alt_g1:
    astore 181
    sipush 2
    putstatic rung36_jcon_scan/icn_150_alt_gate I
    aload 181
    goto icn_148_waft_1
icn_150_α:
    iconst_0
    putstatic rung36_jcon_scan/icn_150_alt_gate I
    goto icn_152_α
icn_150_β:
    getstatic rung36_jcon_scan/icn_150_alt_gate I
    tableswitch 1 2
        icn_152_β
        icn_151_β
        default: icn_141_α
icn_148_α:
    goto icn_149_α
icn_148_β:
    goto icn_149_β
    goto icn_148_wentry
icn_148_waft_0:
    astore 182
    getstatic java/lang/System/out Ljava/io/PrintStream;
    aload 182
    invokevirtual java/io/PrintStream/print(Ljava/lang/String;)V
    goto icn_150_α
icn_148_waft_1:
    astore 183
    getstatic java/lang/System/out Ljava/io/PrintStream;
    aload 183
    invokevirtual java/io/PrintStream/print(Ljava/lang/String;)V
    getstatic java/lang/System/out Ljava/io/PrintStream;
    ldc ""
    invokevirtual java/io/PrintStream/println(Ljava/lang/String;)V
    aload 183
    goto icn_p2_s1_sdrain
icn_148_wentry:
    goto icn_149_α
icn_p2_s1_sdrain:
    pop
    goto icn_141_α
;  STR
icn_156_α:
    ldc "?10 ----> "
    goto icn_155_waft_0
icn_156_β:
    goto icn_148_α
;  STR
icn_158_α:
    ldc "none"
    goto icn_157_alt_g1
icn_158_β:
    goto icn_148_α
;  INT
icn_161_α:
    ldc2_w 10
    goto icn_160_rand
icn_161_β:
    goto icn_158_α
icn_160_α:
    goto icn_161_α
icn_160_β:
    goto icn_161_β
icn_160_rand:
    invokestatic rung36_jcon_scan/icn_builtin_random(J)J
    goto icn_159_image_after
icn_159_α:
    goto icn_160_α
icn_159_β:
    goto icn_160_β
icn_159_image_after:
    invokestatic java/lang/Long/toString(J)Ljava/lang/String;
    goto icn_157_alt_g0
icn_157_alt_g0:
    astore 184
    sipush 1
    putstatic rung36_jcon_scan/icn_157_alt_gate I
    aload 184
    goto icn_155_waft_1
icn_157_alt_g1:
    astore 185
    sipush 2
    putstatic rung36_jcon_scan/icn_157_alt_gate I
    aload 185
    goto icn_155_waft_1
icn_157_α:
    iconst_0
    putstatic rung36_jcon_scan/icn_157_alt_gate I
    goto icn_159_α
icn_157_β:
    getstatic rung36_jcon_scan/icn_157_alt_gate I
    tableswitch 1 2
        icn_159_β
        icn_158_β
        default: icn_148_α
icn_155_α:
    goto icn_156_α
icn_155_β:
    goto icn_156_β
    goto icn_155_wentry
icn_155_waft_0:
    astore 186
    getstatic java/lang/System/out Ljava/io/PrintStream;
    aload 186
    invokevirtual java/io/PrintStream/print(Ljava/lang/String;)V
    goto icn_157_α
icn_155_waft_1:
    astore 187
    getstatic java/lang/System/out Ljava/io/PrintStream;
    aload 187
    invokevirtual java/io/PrintStream/print(Ljava/lang/String;)V
    getstatic java/lang/System/out Ljava/io/PrintStream;
    ldc ""
    invokevirtual java/io/PrintStream/println(Ljava/lang/String;)V
    aload 187
    goto icn_p2_s0_sdrain
icn_155_wentry:
    goto icn_156_α
icn_p2_s0_sdrain:
    pop
    goto icn_148_α
icn_p2_done:
    iconst_0
    putstatic rung36_jcon_scan/icn_suspended B
    iconst_0
    putstatic rung36_jcon_scan/icn_suspend_id I
    iconst_1
    putstatic rung36_jcon_scan/icn_failed B
    return
icn_p2_ret:
    iconst_0
    putstatic rung36_jcon_scan/icn_failed B
    return
icn_p2_sret:
    return
.end method

.method public static icn_p3()V
    .limit stack 16
    .limit locals 386
    lconst_0
    lstore 0
    lconst_0
    lstore 2
    lconst_0
    lstore 4
    lconst_0
    lstore 6
    lconst_0
    lstore 8
    lconst_0
    lstore 10
    lconst_0
    lstore 12
    lconst_0
    lstore 14
    lconst_0
    lstore 16
    lconst_0
    lstore 18
    lconst_0
    lstore 20
    lconst_0
    lstore 22
    lconst_0
    lstore 24
    lconst_0
    lstore 26
    lconst_0
    lstore 28
    lconst_0
    lstore 30
    lconst_0
    lstore 32
    lconst_0
    lstore 34
    lconst_0
    lstore 36
    lconst_0
    lstore 38
    lconst_0
    lstore 40
    lconst_0
    lstore 42
    lconst_0
    lstore 44
    lconst_0
    lstore 46
    lconst_0
    lstore 48
    lconst_0
    lstore 50
    lconst_0
    lstore 52
    lconst_0
    lstore 54
    lconst_0
    lstore 56
    lconst_0
    lstore 58
    lconst_0
    lstore 60
    lconst_0
    lstore 62
    iconst_0
    istore 84
    iconst_0
    istore 85
    iconst_0
    istore 86
    iconst_0
    istore 87
    aconst_null
    astore 148
    aconst_null
    astore 149
    aconst_null
    astore 150
    aconst_null
    astore 151
    aconst_null
    astore 152
    aconst_null
    astore 153
    aconst_null
    astore 154
    aconst_null
    astore 155
    aconst_null
    astore 156
    aconst_null
    astore 157
    aconst_null
    astore 158
    aconst_null
    astore 159
    aconst_null
    astore 160
    aconst_null
    astore 161
    aconst_null
    astore 162
    aconst_null
    astore 163
    aconst_null
    astore 164
    aconst_null
    astore 165
    aconst_null
    astore 166
    aconst_null
    astore 167
    aconst_null
    astore 168
    aconst_null
    astore 169
    aconst_null
    astore 170
    aconst_null
    astore 171
    aconst_null
    astore 172
    aconst_null
    astore 173
    aconst_null
    astore 174
    aconst_null
    astore 175
    aconst_null
    astore 176
    aconst_null
    astore 177
    aconst_null
    astore 178
    aconst_null
    astore 179
    aconst_null
    astore 180
    aconst_null
    astore 181
    aconst_null
    astore 182
    aconst_null
    astore 183
    aconst_null
    astore 184
    aconst_null
    astore 185
    aconst_null
    astore 186
    aconst_null
    astore 187
    aconst_null
    astore 188
    aconst_null
    astore 189
    aconst_null
    astore 190
    aconst_null
    astore 191
    aconst_null
    astore 192
    aconst_null
    astore 193
    aconst_null
    astore 194
    aconst_null
    astore 195
    aconst_null
    astore 196
    aconst_null
    astore 197
    aconst_null
    astore 198
    aconst_null
    astore 199
    goto icn_250_α
;  STR
icn_163_α:
    ldc "s ?:= move(3) ----> "
    goto icn_162_waft_0
icn_163_β:
    goto icn_p3_done
;  STR
icn_165_α:
    ldc "none"
    goto icn_164_alt_g1
icn_165_β:
    goto icn_p3_done
;  INT
icn_169_α:
    ldc2_w 3
    goto icn_168_mva
icn_169_β:
    goto icn_165_α
icn_168_α:
    goto icn_169_α
icn_168_β:
    goto icn_165_α
icn_168_mva:
;  move: n (long) on stack
    l2i
    getstatic rung36_jcon_scan/icn_subject Ljava/lang/String;
    getstatic rung36_jcon_scan/icn_pos I
    invokestatic rung36_jcon_scan/icn_builtin_move_str(ILjava/lang/String;I)Ljava/lang/String;
    dup
    ifnonnull icn_168_mvo
    pop
    goto icn_165_α
icn_168_mvo:
;  move ok: icn_pos advanced by helper, push String → γ
    goto icn_167_rhsok
icn_167_α:
    goto icn_168_α
icn_167_β:
    goto icn_168_β
icn_167_rhsok:
    putstatic rung36_jcon_scan/icn_167_augtemp J
    getstatic rung36_jcon_scan/icn_pv_p3_s J
    getstatic rung36_jcon_scan/icn_167_augtemp J
    ladd
    dup2
    putstatic rung36_jcon_scan/icn_pv_p3_s J
    goto icn_166_image_after
icn_166_α:
    goto icn_167_α
icn_166_β:
    goto icn_167_β
icn_166_image_after:
    invokestatic java/lang/Long/toString(J)Ljava/lang/String;
    goto icn_164_alt_g0
icn_164_alt_g0:
    astore 148
    sipush 1
    putstatic rung36_jcon_scan/icn_164_alt_gate I
    aload 148
    goto icn_162_waft_1
icn_164_alt_g1:
    astore 149
    sipush 2
    putstatic rung36_jcon_scan/icn_164_alt_gate I
    aload 149
    goto icn_162_waft_1
icn_164_α:
    iconst_0
    putstatic rung36_jcon_scan/icn_164_alt_gate I
    goto icn_166_α
icn_164_β:
    getstatic rung36_jcon_scan/icn_164_alt_gate I
    tableswitch 1 2
        icn_166_β
        icn_165_β
        default: icn_p3_done
icn_162_α:
    goto icn_163_α
icn_162_β:
    goto icn_163_β
    goto icn_162_wentry
icn_162_waft_0:
    astore 150
    getstatic java/lang/System/out Ljava/io/PrintStream;
    aload 150
    invokevirtual java/io/PrintStream/print(Ljava/lang/String;)V
    goto icn_164_α
icn_162_waft_1:
    astore 151
    getstatic java/lang/System/out Ljava/io/PrintStream;
    aload 151
    invokevirtual java/io/PrintStream/print(Ljava/lang/String;)V
    getstatic java/lang/System/out Ljava/io/PrintStream;
    ldc ""
    invokevirtual java/io/PrintStream/println(Ljava/lang/String;)V
    aload 151
    goto icn_p3_s10_sdrain
icn_162_wentry:
    goto icn_163_α
icn_p3_s10_sdrain:
    pop
    goto icn_p3_done
;  STR
icn_171_α:
    ldc "s := \"abcdef\" ----> "
    goto icn_170_waft_0
icn_171_β:
    goto icn_162_α
;  STR
icn_173_α:
    ldc "none"
    goto icn_172_alt_g1
icn_173_β:
    goto icn_162_α
;  STR
icn_176_α:
    ldc "abcdef"
    goto icn_175_store
icn_176_β:
    goto icn_173_α
icn_175_α:
    goto icn_176_α
icn_175_β:
    goto icn_176_β
icn_175_store:
    putstatic rung36_jcon_scan/icn_pv_p3_s Ljava/lang/String;
    getstatic rung36_jcon_scan/icn_pv_p3_s Ljava/lang/String;
    goto icn_174_image_after
icn_174_α:
    goto icn_175_α
icn_174_β:
    goto icn_175_β
icn_174_image_after:
    goto icn_172_alt_g0
icn_172_alt_g0:
    astore 152
    sipush 1
    putstatic rung36_jcon_scan/icn_172_alt_gate I
    aload 152
    goto icn_170_waft_1
icn_172_alt_g1:
    astore 153
    sipush 2
    putstatic rung36_jcon_scan/icn_172_alt_gate I
    aload 153
    goto icn_170_waft_1
icn_172_α:
    iconst_0
    putstatic rung36_jcon_scan/icn_172_alt_gate I
    goto icn_174_α
icn_172_β:
    getstatic rung36_jcon_scan/icn_172_alt_gate I
    tableswitch 1 2
        icn_174_β
        icn_173_β
        default: icn_162_α
icn_170_α:
    goto icn_171_α
icn_170_β:
    goto icn_171_β
    goto icn_170_wentry
icn_170_waft_0:
    astore 154
    getstatic java/lang/System/out Ljava/io/PrintStream;
    aload 154
    invokevirtual java/io/PrintStream/print(Ljava/lang/String;)V
    goto icn_172_α
icn_170_waft_1:
    astore 155
    getstatic java/lang/System/out Ljava/io/PrintStream;
    aload 155
    invokevirtual java/io/PrintStream/print(Ljava/lang/String;)V
    getstatic java/lang/System/out Ljava/io/PrintStream;
    ldc ""
    invokevirtual java/io/PrintStream/println(Ljava/lang/String;)V
    aload 155
    goto icn_p3_s9_sdrain
icn_170_wentry:
    goto icn_171_α
icn_p3_s9_sdrain:
    pop
    goto icn_162_α
;  STR
icn_178_α:
    ldc "every write(\"abcde\" ? while move(2) ? move(1)) ----> "
    goto icn_177_waft_0
icn_178_β:
    goto icn_170_α
;  STR
icn_180_α:
    ldc "none"
    goto icn_179_alt_g1
icn_180_β:
    goto icn_170_α
;  STR
icn_185_α:
    ldc "abcde"
    goto icn_184_scan_setup
icn_185_β:
    goto icn_180_α
;  INT
icn_189_α:
    ldc2_w 2
    goto icn_188_mva
icn_189_β:
    goto icn_184_scan_bfail
icn_188_α:
    goto icn_189_α
icn_188_β:
    goto icn_184_scan_bfail
icn_188_mva:
;  move: n (long) on stack
    l2i
    getstatic rung36_jcon_scan/icn_subject Ljava/lang/String;
    getstatic rung36_jcon_scan/icn_pos I
    invokestatic rung36_jcon_scan/icn_builtin_move_str(ILjava/lang/String;I)Ljava/lang/String;
    dup
    ifnonnull icn_188_mvo
    pop
    goto icn_184_scan_bfail
icn_188_mvo:
;  move ok: icn_pos advanced by helper, push String → γ
    goto icn_187_scan_setup
;  INT
icn_191_α:
    ldc2_w 1
    goto icn_190_mva
icn_191_β:
    goto icn_187_scan_bfail
icn_190_α:
    goto icn_191_α
icn_190_β:
    goto icn_187_scan_bfail
icn_190_mva:
;  move: n (long) on stack
    l2i
    getstatic rung36_jcon_scan/icn_subject Ljava/lang/String;
    getstatic rung36_jcon_scan/icn_pos I
    invokestatic rung36_jcon_scan/icn_builtin_move_str(ILjava/lang/String;I)Ljava/lang/String;
    dup
    ifnonnull icn_190_mvo
    pop
    goto icn_187_scan_bfail
icn_190_mvo:
;  move ok: icn_pos advanced by helper, push String → γ
    goto icn_187_scan_bok
;  SCAN
icn_187_α:
    goto icn_188_α
icn_187_β:
    goto icn_187_scan_beta
icn_187_scan_setup:
;  SCAN save+install
    getstatic rung36_jcon_scan/icn_subject Ljava/lang/String;
    putstatic rung36_jcon_scan/icn_scan_oldsubj_187 Ljava/lang/String;
    getstatic rung36_jcon_scan/icn_pos I
    putstatic rung36_jcon_scan/icn_scan_oldpos_187 I
    putstatic rung36_jcon_scan/icn_subject Ljava/lang/String;
    iconst_0
    putstatic rung36_jcon_scan/icn_pos I
    goto icn_190_α
icn_187_scan_bok:
;  SCAN restore (body ok)
    getstatic rung36_jcon_scan/icn_scan_oldsubj_187 Ljava/lang/String;
    putstatic rung36_jcon_scan/icn_subject Ljava/lang/String;
    getstatic rung36_jcon_scan/icn_scan_oldpos_187 I
    putstatic rung36_jcon_scan/icn_pos I
    goto icn_186_condok
icn_187_scan_bfail:
;  SCAN restore (body fail)
    getstatic rung36_jcon_scan/icn_scan_oldsubj_187 Ljava/lang/String;
    putstatic rung36_jcon_scan/icn_subject Ljava/lang/String;
    getstatic rung36_jcon_scan/icn_scan_oldpos_187 I
    putstatic rung36_jcon_scan/icn_pos I
    goto icn_188_β
icn_187_scan_beta:
;  SCAN restore (outer β)
    getstatic rung36_jcon_scan/icn_scan_oldsubj_187 Ljava/lang/String;
    putstatic rung36_jcon_scan/icn_subject Ljava/lang/String;
    getstatic rung36_jcon_scan/icn_scan_oldpos_187 I
    putstatic rung36_jcon_scan/icn_pos I
    goto icn_190_β
icn_186_condok:
    pop
    goto icn_187_α
icn_186_α:
    goto icn_187_α
icn_186_β:
    goto icn_184_scan_bfail
;  SCAN
icn_184_α:
    goto icn_185_α
icn_184_β:
    goto icn_184_scan_beta
icn_184_scan_setup:
;  SCAN save+install
    getstatic rung36_jcon_scan/icn_subject Ljava/lang/String;
    putstatic rung36_jcon_scan/icn_scan_oldsubj_184 Ljava/lang/String;
    getstatic rung36_jcon_scan/icn_pos I
    putstatic rung36_jcon_scan/icn_scan_oldpos_184 I
    putstatic rung36_jcon_scan/icn_subject Ljava/lang/String;
    iconst_0
    putstatic rung36_jcon_scan/icn_pos I
    goto icn_186_α
icn_184_scan_bok:
;  SCAN restore (body ok)
    getstatic rung36_jcon_scan/icn_scan_oldsubj_184 Ljava/lang/String;
    putstatic rung36_jcon_scan/icn_subject Ljava/lang/String;
    getstatic rung36_jcon_scan/icn_scan_oldpos_184 I
    putstatic rung36_jcon_scan/icn_pos I
    goto icn_183_waft_0
icn_184_scan_bfail:
;  SCAN restore (body fail)
    getstatic rung36_jcon_scan/icn_scan_oldsubj_184 Ljava/lang/String;
    putstatic rung36_jcon_scan/icn_subject Ljava/lang/String;
    getstatic rung36_jcon_scan/icn_scan_oldpos_184 I
    putstatic rung36_jcon_scan/icn_pos I
    goto icn_185_β
icn_184_scan_beta:
;  SCAN restore (outer β)
    getstatic rung36_jcon_scan/icn_scan_oldsubj_184 Ljava/lang/String;
    putstatic rung36_jcon_scan/icn_subject Ljava/lang/String;
    getstatic rung36_jcon_scan/icn_scan_oldpos_184 I
    putstatic rung36_jcon_scan/icn_pos I
    goto icn_186_β
icn_183_α:
    goto icn_184_α
icn_183_β:
    goto icn_184_β
    goto icn_183_wentry
icn_183_waft_0:
    astore 156
    getstatic java/lang/System/out Ljava/io/PrintStream;
    aload 156
    invokevirtual java/io/PrintStream/print(Ljava/lang/String;)V
    getstatic java/lang/System/out Ljava/io/PrintStream;
    ldc ""
    invokevirtual java/io/PrintStream/println(Ljava/lang/String;)V
    aload 156
    goto icn_182_gdrain
icn_183_wentry:
    goto icn_184_α
icn_182_gdrain:
    pop
icn_182_pump:
    goto icn_183_β
icn_182_α:
    goto icn_183_α
icn_182_β:
    goto icn_180_α
icn_181_α:
    goto icn_182_α
icn_181_β:
    goto icn_182_β
icn_181_image_after:
    invokestatic java/lang/Long/toString(J)Ljava/lang/String;
    goto icn_179_alt_g0
icn_179_alt_g0:
    astore 157
    sipush 1
    putstatic rung36_jcon_scan/icn_179_alt_gate I
    aload 157
    goto icn_177_waft_1
icn_179_alt_g1:
    astore 158
    sipush 2
    putstatic rung36_jcon_scan/icn_179_alt_gate I
    aload 158
    goto icn_177_waft_1
icn_179_α:
    iconst_0
    putstatic rung36_jcon_scan/icn_179_alt_gate I
    goto icn_181_α
icn_179_β:
    getstatic rung36_jcon_scan/icn_179_alt_gate I
    tableswitch 1 2
        icn_181_β
        icn_180_β
        default: icn_170_α
icn_177_α:
    goto icn_178_α
icn_177_β:
    goto icn_178_β
    goto icn_177_wentry
icn_177_waft_0:
    astore 159
    getstatic java/lang/System/out Ljava/io/PrintStream;
    aload 159
    invokevirtual java/io/PrintStream/print(Ljava/lang/String;)V
    goto icn_179_α
icn_177_waft_1:
    astore 160
    getstatic java/lang/System/out Ljava/io/PrintStream;
    aload 160
    invokevirtual java/io/PrintStream/print(Ljava/lang/String;)V
    getstatic java/lang/System/out Ljava/io/PrintStream;
    ldc ""
    invokevirtual java/io/PrintStream/println(Ljava/lang/String;)V
    aload 160
    goto icn_p3_s8_sdrain
icn_177_wentry:
    goto icn_178_α
icn_p3_s8_sdrain:
    pop
    goto icn_170_α
;  STR
icn_193_α:
    ldc "every write(\"abcdef\" ? tab(1 to 10)) ----> "
    goto icn_192_waft_0
icn_193_β:
    goto icn_177_α
;  STR
icn_195_α:
    ldc "none"
    goto icn_194_alt_g1
icn_195_β:
    goto icn_177_α
;  STR
icn_200_α:
    ldc "abcdef"
    goto icn_199_scan_setup
icn_200_β:
    goto icn_195_α
;  INT
icn_203_α:
    ldc2_w 10
    goto icn_202_e2relay
icn_203_β:
    goto icn_202_e1b
;  INT
icn_204_α:
    ldc2_w 1
    goto icn_202_e1relay
icn_204_β:
    goto icn_199_scan_bfail
icn_202_e1relay:
    putstatic rung36_jcon_scan/icn_202_e1val J
    goto icn_203_α
icn_202_e2relay:
    putstatic rung36_jcon_scan/icn_202_e2val J
    goto icn_202_init
icn_202_e1b:
    iconst_0
    putstatic rung36_jcon_scan/icn_202_e2seen I
    goto icn_204_β
icn_202_e2b:
    goto icn_203_β
icn_202_α:
    iconst_0
    putstatic rung36_jcon_scan/icn_202_e2seen I
    goto icn_204_α
icn_202_β:
    getstatic rung36_jcon_scan/icn_202_I J
    lconst_1
    ladd
    putstatic rung36_jcon_scan/icn_202_I J
    goto icn_202_code
icn_202_init:
    getstatic rung36_jcon_scan/icn_202_e2val J
    putstatic rung36_jcon_scan/icn_202_bound J
    getstatic rung36_jcon_scan/icn_202_e2seen I
    ifne icn_202_init_e2adv
    getstatic rung36_jcon_scan/icn_202_e1val J
    putstatic rung36_jcon_scan/icn_202_e1cur J
    getstatic rung36_jcon_scan/icn_202_e1cur J
    putstatic rung36_jcon_scan/icn_202_I J
    iconst_1
    putstatic rung36_jcon_scan/icn_202_e2seen I
    goto icn_202_code
icn_202_init_e2adv:
    getstatic rung36_jcon_scan/icn_202_e1cur J
    putstatic rung36_jcon_scan/icn_202_I J
    goto icn_202_code
icn_202_code:
    getstatic rung36_jcon_scan/icn_202_I J
    getstatic rung36_jcon_scan/icn_202_bound J
    lcmp
    ifgt icn_202_e2b
    getstatic rung36_jcon_scan/icn_202_I J
    goto icn_201_ta
icn_201_α:
    goto icn_202_α
icn_201_β:
    goto icn_199_scan_bfail
icn_201_ta:
;  tab: n (long) on stack
    l2i
    getstatic rung36_jcon_scan/icn_subject Ljava/lang/String;
    getstatic rung36_jcon_scan/icn_pos I
    invokestatic rung36_jcon_scan/icn_builtin_tab_str(ILjava/lang/String;I)Ljava/lang/String;
    dup
    ifnonnull icn_201_to
    pop
    goto icn_199_scan_bfail
icn_201_to:
;  tab ok: advance icn_pos = n-1, push String → γ
    goto icn_199_scan_bok
;  SCAN
icn_199_α:
    goto icn_200_α
icn_199_β:
    goto icn_199_scan_beta
icn_199_scan_setup:
;  SCAN save+install
    getstatic rung36_jcon_scan/icn_subject Ljava/lang/String;
    putstatic rung36_jcon_scan/icn_scan_oldsubj_199 Ljava/lang/String;
    getstatic rung36_jcon_scan/icn_pos I
    putstatic rung36_jcon_scan/icn_scan_oldpos_199 I
    putstatic rung36_jcon_scan/icn_subject Ljava/lang/String;
    iconst_0
    putstatic rung36_jcon_scan/icn_pos I
    goto icn_201_α
icn_199_scan_bok:
;  SCAN restore (body ok)
    getstatic rung36_jcon_scan/icn_scan_oldsubj_199 Ljava/lang/String;
    putstatic rung36_jcon_scan/icn_subject Ljava/lang/String;
    getstatic rung36_jcon_scan/icn_scan_oldpos_199 I
    putstatic rung36_jcon_scan/icn_pos I
    goto icn_198_waft_0
icn_199_scan_bfail:
;  SCAN restore (body fail)
    getstatic rung36_jcon_scan/icn_scan_oldsubj_199 Ljava/lang/String;
    putstatic rung36_jcon_scan/icn_subject Ljava/lang/String;
    getstatic rung36_jcon_scan/icn_scan_oldpos_199 I
    putstatic rung36_jcon_scan/icn_pos I
    goto icn_200_β
icn_199_scan_beta:
;  SCAN restore (outer β)
    getstatic rung36_jcon_scan/icn_scan_oldsubj_199 Ljava/lang/String;
    putstatic rung36_jcon_scan/icn_subject Ljava/lang/String;
    getstatic rung36_jcon_scan/icn_scan_oldpos_199 I
    putstatic rung36_jcon_scan/icn_pos I
    goto icn_201_β
icn_198_α:
    goto icn_199_α
icn_198_β:
    goto icn_199_β
    goto icn_198_wentry
icn_198_waft_0:
    astore 161
    getstatic java/lang/System/out Ljava/io/PrintStream;
    aload 161
    invokevirtual java/io/PrintStream/print(Ljava/lang/String;)V
    getstatic java/lang/System/out Ljava/io/PrintStream;
    ldc ""
    invokevirtual java/io/PrintStream/println(Ljava/lang/String;)V
    aload 161
    goto icn_197_gdrain
icn_198_wentry:
    goto icn_199_α
icn_197_gdrain:
    pop
icn_197_pump:
    goto icn_198_β
icn_197_α:
    goto icn_198_α
icn_197_β:
    goto icn_195_α
icn_196_α:
    goto icn_197_α
icn_196_β:
    goto icn_197_β
icn_196_image_after:
    invokestatic java/lang/Long/toString(J)Ljava/lang/String;
    goto icn_194_alt_g0
icn_194_alt_g0:
    astore 162
    sipush 1
    putstatic rung36_jcon_scan/icn_194_alt_gate I
    aload 162
    goto icn_192_waft_1
icn_194_alt_g1:
    astore 163
    sipush 2
    putstatic rung36_jcon_scan/icn_194_alt_gate I
    aload 163
    goto icn_192_waft_1
icn_194_α:
    iconst_0
    putstatic rung36_jcon_scan/icn_194_alt_gate I
    goto icn_196_α
icn_194_β:
    getstatic rung36_jcon_scan/icn_194_alt_gate I
    tableswitch 1 2
        icn_196_β
        icn_195_β
        default: icn_177_α
icn_192_α:
    goto icn_193_α
icn_192_β:
    goto icn_193_β
    goto icn_192_wentry
icn_192_waft_0:
    astore 164
    getstatic java/lang/System/out Ljava/io/PrintStream;
    aload 164
    invokevirtual java/io/PrintStream/print(Ljava/lang/String;)V
    goto icn_194_α
icn_192_waft_1:
    astore 165
    getstatic java/lang/System/out Ljava/io/PrintStream;
    aload 165
    invokevirtual java/io/PrintStream/print(Ljava/lang/String;)V
    getstatic java/lang/System/out Ljava/io/PrintStream;
    ldc ""
    invokevirtual java/io/PrintStream/println(Ljava/lang/String;)V
    aload 165
    goto icn_p3_s7_sdrain
icn_192_wentry:
    goto icn_193_α
icn_p3_s7_sdrain:
    pop
    goto icn_177_α
;  STR
icn_206_α:
    ldc "pos(1) ----> "
    goto icn_205_waft_0
icn_206_β:
    goto icn_192_α
;  STR
icn_208_α:
    ldc "none"
    goto icn_207_alt_g1
icn_208_β:
    goto icn_192_α
icn_210_α:
    goto icn_208_α
icn_210_β:
    goto icn_208_α
icn_209_α:
    goto icn_210_α
icn_209_β:
    goto icn_210_β
icn_209_image_after:
    invokestatic java/lang/Long/toString(J)Ljava/lang/String;
    goto icn_207_alt_g0
icn_207_alt_g0:
    astore 166
    sipush 1
    putstatic rung36_jcon_scan/icn_207_alt_gate I
    aload 166
    goto icn_205_waft_1
icn_207_alt_g1:
    astore 167
    sipush 2
    putstatic rung36_jcon_scan/icn_207_alt_gate I
    aload 167
    goto icn_205_waft_1
icn_207_α:
    iconst_0
    putstatic rung36_jcon_scan/icn_207_alt_gate I
    goto icn_209_α
icn_207_β:
    getstatic rung36_jcon_scan/icn_207_alt_gate I
    tableswitch 1 2
        icn_209_β
        icn_208_β
        default: icn_192_α
icn_205_α:
    goto icn_206_α
icn_205_β:
    goto icn_206_β
    goto icn_205_wentry
icn_205_waft_0:
    astore 168
    getstatic java/lang/System/out Ljava/io/PrintStream;
    aload 168
    invokevirtual java/io/PrintStream/print(Ljava/lang/String;)V
    goto icn_207_α
icn_205_waft_1:
    astore 169
    getstatic java/lang/System/out Ljava/io/PrintStream;
    aload 169
    invokevirtual java/io/PrintStream/print(Ljava/lang/String;)V
    getstatic java/lang/System/out Ljava/io/PrintStream;
    ldc ""
    invokevirtual java/io/PrintStream/println(Ljava/lang/String;)V
    aload 169
    goto icn_p3_s6_sdrain
icn_205_wentry:
    goto icn_206_α
icn_p3_s6_sdrain:
    pop
    goto icn_192_α
;  STR
icn_212_α:
    ldc "&subject := string(&lcase) ----> "
    goto icn_211_waft_0
icn_212_β:
    goto icn_205_α
;  STR
icn_214_α:
    ldc "none"
    goto icn_213_alt_g1
icn_214_β:
    goto icn_205_α
;  VAR
icn_218_α:
    ldc "abcdefghijklmnopqrstuvwxyz"
    goto icn_217_str_after
icn_218_β:
    goto icn_214_α
icn_217_α:
    goto icn_218_α
icn_217_β:
    goto icn_218_β
icn_217_str_after:
    invokestatic java/lang/Long/toString(J)Ljava/lang/String;
    goto icn_216_store
icn_216_α:
    goto icn_217_α
icn_216_β:
    goto icn_217_β
icn_216_store:
    putstatic rung36_jcon_scan/icn_pv_p3__kw_subject Ljava/lang/String;
    getstatic rung36_jcon_scan/icn_pv_p3__kw_subject Ljava/lang/String;
    goto icn_215_image_after
icn_215_α:
    goto icn_216_α
icn_215_β:
    goto icn_216_β
icn_215_image_after:
    goto icn_213_alt_g0
icn_213_alt_g0:
    astore 170
    sipush 1
    putstatic rung36_jcon_scan/icn_213_alt_gate I
    aload 170
    goto icn_211_waft_1
icn_213_alt_g1:
    astore 171
    sipush 2
    putstatic rung36_jcon_scan/icn_213_alt_gate I
    aload 171
    goto icn_211_waft_1
icn_213_α:
    iconst_0
    putstatic rung36_jcon_scan/icn_213_alt_gate I
    goto icn_215_α
icn_213_β:
    getstatic rung36_jcon_scan/icn_213_alt_gate I
    tableswitch 1 2
        icn_215_β
        icn_214_β
        default: icn_205_α
icn_211_α:
    goto icn_212_α
icn_211_β:
    goto icn_212_β
    goto icn_211_wentry
icn_211_waft_0:
    astore 172
    getstatic java/lang/System/out Ljava/io/PrintStream;
    aload 172
    invokevirtual java/io/PrintStream/print(Ljava/lang/String;)V
    goto icn_213_α
icn_211_waft_1:
    astore 173
    getstatic java/lang/System/out Ljava/io/PrintStream;
    aload 173
    invokevirtual java/io/PrintStream/print(Ljava/lang/String;)V
    getstatic java/lang/System/out Ljava/io/PrintStream;
    ldc ""
    invokevirtual java/io/PrintStream/println(Ljava/lang/String;)V
    aload 173
    goto icn_p3_s5_sdrain
icn_211_wentry:
    goto icn_212_α
icn_p3_s5_sdrain:
    pop
    goto icn_205_α
;  STR
icn_220_α:
    ldc "pos(15) ----> "
    goto icn_219_waft_0
icn_220_β:
    goto icn_211_α
;  STR
icn_222_α:
    ldc "none"
    goto icn_221_alt_g1
icn_222_β:
    goto icn_211_α
icn_224_α:
    goto icn_222_α
icn_224_β:
    goto icn_222_α
icn_223_α:
    goto icn_224_α
icn_223_β:
    goto icn_224_β
icn_223_image_after:
    invokestatic java/lang/Long/toString(J)Ljava/lang/String;
    goto icn_221_alt_g0
icn_221_alt_g0:
    astore 174
    sipush 1
    putstatic rung36_jcon_scan/icn_221_alt_gate I
    aload 174
    goto icn_219_waft_1
icn_221_alt_g1:
    astore 175
    sipush 2
    putstatic rung36_jcon_scan/icn_221_alt_gate I
    aload 175
    goto icn_219_waft_1
icn_221_α:
    iconst_0
    putstatic rung36_jcon_scan/icn_221_alt_gate I
    goto icn_223_α
icn_221_β:
    getstatic rung36_jcon_scan/icn_221_alt_gate I
    tableswitch 1 2
        icn_223_β
        icn_222_β
        default: icn_211_α
icn_219_α:
    goto icn_220_α
icn_219_β:
    goto icn_220_β
    goto icn_219_wentry
icn_219_waft_0:
    astore 176
    getstatic java/lang/System/out Ljava/io/PrintStream;
    aload 176
    invokevirtual java/io/PrintStream/print(Ljava/lang/String;)V
    goto icn_221_α
icn_219_waft_1:
    astore 177
    getstatic java/lang/System/out Ljava/io/PrintStream;
    aload 177
    invokevirtual java/io/PrintStream/print(Ljava/lang/String;)V
    getstatic java/lang/System/out Ljava/io/PrintStream;
    ldc ""
    invokevirtual java/io/PrintStream/println(Ljava/lang/String;)V
    aload 177
    goto icn_p3_s4_sdrain
icn_219_wentry:
    goto icn_220_α
icn_p3_s4_sdrain:
    pop
    goto icn_211_α
;  STR
icn_226_α:
    ldc "pos(0) ----> "
    goto icn_225_waft_0
icn_226_β:
    goto icn_219_α
;  STR
icn_228_α:
    ldc "none"
    goto icn_227_alt_g1
icn_228_β:
    goto icn_219_α
icn_230_α:
    goto icn_228_α
icn_230_β:
    goto icn_228_α
icn_229_α:
    goto icn_230_α
icn_229_β:
    goto icn_230_β
icn_229_image_after:
    invokestatic java/lang/Long/toString(J)Ljava/lang/String;
    goto icn_227_alt_g0
icn_227_alt_g0:
    astore 178
    sipush 1
    putstatic rung36_jcon_scan/icn_227_alt_gate I
    aload 178
    goto icn_225_waft_1
icn_227_alt_g1:
    astore 179
    sipush 2
    putstatic rung36_jcon_scan/icn_227_alt_gate I
    aload 179
    goto icn_225_waft_1
icn_227_α:
    iconst_0
    putstatic rung36_jcon_scan/icn_227_alt_gate I
    goto icn_229_α
icn_227_β:
    getstatic rung36_jcon_scan/icn_227_alt_gate I
    tableswitch 1 2
        icn_229_β
        icn_228_β
        default: icn_219_α
icn_225_α:
    goto icn_226_α
icn_225_β:
    goto icn_226_β
    goto icn_225_wentry
icn_225_waft_0:
    astore 180
    getstatic java/lang/System/out Ljava/io/PrintStream;
    aload 180
    invokevirtual java/io/PrintStream/print(Ljava/lang/String;)V
    goto icn_227_α
icn_225_waft_1:
    astore 181
    getstatic java/lang/System/out Ljava/io/PrintStream;
    aload 181
    invokevirtual java/io/PrintStream/print(Ljava/lang/String;)V
    getstatic java/lang/System/out Ljava/io/PrintStream;
    ldc ""
    invokevirtual java/io/PrintStream/println(Ljava/lang/String;)V
    aload 181
    goto icn_p3_s3_sdrain
icn_225_wentry:
    goto icn_226_α
icn_p3_s3_sdrain:
    pop
    goto icn_219_α
;  STR
icn_232_α:
    ldc "every write(tab(1 to 10)) ----> "
    goto icn_231_waft_0
icn_232_β:
    goto icn_225_α
;  STR
icn_234_α:
    ldc "none"
    goto icn_233_alt_g1
icn_234_β:
    goto icn_225_α
;  INT
icn_240_α:
    ldc2_w 10
    goto icn_239_e2relay
icn_240_β:
    goto icn_239_e1b
;  INT
icn_241_α:
    ldc2_w 1
    goto icn_239_e1relay
icn_241_β:
    goto icn_234_α
icn_239_e1relay:
    putstatic rung36_jcon_scan/icn_239_e1val J
    goto icn_240_α
icn_239_e2relay:
    putstatic rung36_jcon_scan/icn_239_e2val J
    goto icn_239_init
icn_239_e1b:
    iconst_0
    putstatic rung36_jcon_scan/icn_239_e2seen I
    goto icn_241_β
icn_239_e2b:
    goto icn_240_β
icn_239_α:
    iconst_0
    putstatic rung36_jcon_scan/icn_239_e2seen I
    goto icn_241_α
icn_239_β:
    getstatic rung36_jcon_scan/icn_239_I J
    lconst_1
    ladd
    putstatic rung36_jcon_scan/icn_239_I J
    goto icn_239_code
icn_239_init:
    getstatic rung36_jcon_scan/icn_239_e2val J
    putstatic rung36_jcon_scan/icn_239_bound J
    getstatic rung36_jcon_scan/icn_239_e2seen I
    ifne icn_239_init_e2adv
    getstatic rung36_jcon_scan/icn_239_e1val J
    putstatic rung36_jcon_scan/icn_239_e1cur J
    getstatic rung36_jcon_scan/icn_239_e1cur J
    putstatic rung36_jcon_scan/icn_239_I J
    iconst_1
    putstatic rung36_jcon_scan/icn_239_e2seen I
    goto icn_239_code
icn_239_init_e2adv:
    getstatic rung36_jcon_scan/icn_239_e1cur J
    putstatic rung36_jcon_scan/icn_239_I J
    goto icn_239_code
icn_239_code:
    getstatic rung36_jcon_scan/icn_239_I J
    getstatic rung36_jcon_scan/icn_239_bound J
    lcmp
    ifgt icn_239_e2b
    getstatic rung36_jcon_scan/icn_239_I J
    goto icn_238_ta
icn_238_α:
    goto icn_239_α
icn_238_β:
    goto icn_234_α
icn_238_ta:
;  tab: n (long) on stack
    l2i
    getstatic rung36_jcon_scan/icn_subject Ljava/lang/String;
    getstatic rung36_jcon_scan/icn_pos I
    invokestatic rung36_jcon_scan/icn_builtin_tab_str(ILjava/lang/String;I)Ljava/lang/String;
    dup
    ifnonnull icn_238_to
    pop
    goto icn_234_α
icn_238_to:
;  tab ok: advance icn_pos = n-1, push String → γ
    goto icn_237_waft_0
icn_237_α:
    goto icn_238_α
icn_237_β:
    goto icn_238_β
    goto icn_237_wentry
icn_237_waft_0:
    astore 182
    getstatic java/lang/System/out Ljava/io/PrintStream;
    aload 182
    invokevirtual java/io/PrintStream/print(Ljava/lang/String;)V
    getstatic java/lang/System/out Ljava/io/PrintStream;
    ldc ""
    invokevirtual java/io/PrintStream/println(Ljava/lang/String;)V
    aload 182
    goto icn_236_gdrain
icn_237_wentry:
    goto icn_238_α
icn_236_gdrain:
    pop
icn_236_pump:
    goto icn_237_β
icn_236_α:
    goto icn_237_α
icn_236_β:
    goto icn_234_α
icn_235_α:
    goto icn_236_α
icn_235_β:
    goto icn_236_β
icn_235_image_after:
    invokestatic java/lang/Long/toString(J)Ljava/lang/String;
    goto icn_233_alt_g0
icn_233_alt_g0:
    astore 183
    sipush 1
    putstatic rung36_jcon_scan/icn_233_alt_gate I
    aload 183
    goto icn_231_waft_1
icn_233_alt_g1:
    astore 184
    sipush 2
    putstatic rung36_jcon_scan/icn_233_alt_gate I
    aload 184
    goto icn_231_waft_1
icn_233_α:
    iconst_0
    putstatic rung36_jcon_scan/icn_233_alt_gate I
    goto icn_235_α
icn_233_β:
    getstatic rung36_jcon_scan/icn_233_alt_gate I
    tableswitch 1 2
        icn_235_β
        icn_234_β
        default: icn_225_α
icn_231_α:
    goto icn_232_α
icn_231_β:
    goto icn_232_β
    goto icn_231_wentry
icn_231_waft_0:
    astore 185
    getstatic java/lang/System/out Ljava/io/PrintStream;
    aload 185
    invokevirtual java/io/PrintStream/print(Ljava/lang/String;)V
    goto icn_233_α
icn_231_waft_1:
    astore 186
    getstatic java/lang/System/out Ljava/io/PrintStream;
    aload 186
    invokevirtual java/io/PrintStream/print(Ljava/lang/String;)V
    getstatic java/lang/System/out Ljava/io/PrintStream;
    ldc ""
    invokevirtual java/io/PrintStream/println(Ljava/lang/String;)V
    aload 186
    goto icn_p3_s2_sdrain
icn_231_wentry:
    goto icn_232_α
icn_p3_s2_sdrain:
    pop
    goto icn_225_α
;  STR
icn_243_α:
    ldc "&subject := string(&lcase) ----> "
    goto icn_242_waft_0
icn_243_β:
    goto icn_231_α
;  STR
icn_245_α:
    ldc "none"
    goto icn_244_alt_g1
icn_245_β:
    goto icn_231_α
;  VAR
icn_249_α:
    ldc "abcdefghijklmnopqrstuvwxyz"
    goto icn_248_str_after
icn_249_β:
    goto icn_245_α
icn_248_α:
    goto icn_249_α
icn_248_β:
    goto icn_249_β
icn_248_str_after:
    invokestatic java/lang/Long/toString(J)Ljava/lang/String;
    goto icn_247_store
icn_247_α:
    goto icn_248_α
icn_247_β:
    goto icn_248_β
icn_247_store:
    putstatic rung36_jcon_scan/icn_pv_p3__kw_subject Ljava/lang/String;
    getstatic rung36_jcon_scan/icn_pv_p3__kw_subject Ljava/lang/String;
    goto icn_246_image_after
icn_246_α:
    goto icn_247_α
icn_246_β:
    goto icn_247_β
icn_246_image_after:
    goto icn_244_alt_g0
icn_244_alt_g0:
    astore 187
    sipush 1
    putstatic rung36_jcon_scan/icn_244_alt_gate I
    aload 187
    goto icn_242_waft_1
icn_244_alt_g1:
    astore 188
    sipush 2
    putstatic rung36_jcon_scan/icn_244_alt_gate I
    aload 188
    goto icn_242_waft_1
icn_244_α:
    iconst_0
    putstatic rung36_jcon_scan/icn_244_alt_gate I
    goto icn_246_α
icn_244_β:
    getstatic rung36_jcon_scan/icn_244_alt_gate I
    tableswitch 1 2
        icn_246_β
        icn_245_β
        default: icn_231_α
icn_242_α:
    goto icn_243_α
icn_242_β:
    goto icn_243_β
    goto icn_242_wentry
icn_242_waft_0:
    astore 189
    getstatic java/lang/System/out Ljava/io/PrintStream;
    aload 189
    invokevirtual java/io/PrintStream/print(Ljava/lang/String;)V
    goto icn_244_α
icn_242_waft_1:
    astore 190
    getstatic java/lang/System/out Ljava/io/PrintStream;
    aload 190
    invokevirtual java/io/PrintStream/print(Ljava/lang/String;)V
    getstatic java/lang/System/out Ljava/io/PrintStream;
    ldc ""
    invokevirtual java/io/PrintStream/println(Ljava/lang/String;)V
    aload 190
    goto icn_p3_s1_sdrain
icn_242_wentry:
    goto icn_243_α
icn_p3_s1_sdrain:
    pop
    goto icn_231_α
;  STR
icn_251_α:
    ldc "while write(move(1)) ----> "
    goto icn_250_waft_0
icn_251_β:
    goto icn_242_α
;  STR
icn_253_α:
    ldc "none"
    goto icn_252_alt_g1
icn_253_β:
    goto icn_242_α
;  INT
icn_258_α:
    ldc2_w 1
    goto icn_257_mva
icn_258_β:
    goto icn_253_α
icn_257_α:
    goto icn_258_α
icn_257_β:
    goto icn_253_α
icn_257_mva:
;  move: n (long) on stack
    l2i
    getstatic rung36_jcon_scan/icn_subject Ljava/lang/String;
    getstatic rung36_jcon_scan/icn_pos I
    invokestatic rung36_jcon_scan/icn_builtin_move_str(ILjava/lang/String;I)Ljava/lang/String;
    dup
    ifnonnull icn_257_mvo
    pop
    goto icn_253_α
icn_257_mvo:
;  move ok: icn_pos advanced by helper, push String → γ
    goto icn_256_waft_0
icn_256_α:
    goto icn_257_α
icn_256_β:
    goto icn_257_β
    goto icn_256_wentry
icn_256_waft_0:
    astore 191
    getstatic java/lang/System/out Ljava/io/PrintStream;
    aload 191
    invokevirtual java/io/PrintStream/print(Ljava/lang/String;)V
    getstatic java/lang/System/out Ljava/io/PrintStream;
    ldc ""
    invokevirtual java/io/PrintStream/println(Ljava/lang/String;)V
    aload 191
    goto icn_255_condok
icn_256_wentry:
    goto icn_257_α
icn_255_condok:
    pop
    goto icn_256_α
icn_255_α:
    goto icn_256_α
icn_255_β:
    goto icn_253_α
icn_254_α:
    goto icn_255_α
icn_254_β:
    goto icn_255_β
icn_254_image_after:
    invokestatic java/lang/Long/toString(J)Ljava/lang/String;
    goto icn_252_alt_g0
icn_252_alt_g0:
    astore 192
    sipush 1
    putstatic rung36_jcon_scan/icn_252_alt_gate I
    aload 192
    goto icn_250_waft_1
icn_252_alt_g1:
    astore 193
    sipush 2
    putstatic rung36_jcon_scan/icn_252_alt_gate I
    aload 193
    goto icn_250_waft_1
icn_252_α:
    iconst_0
    putstatic rung36_jcon_scan/icn_252_alt_gate I
    goto icn_254_α
icn_252_β:
    getstatic rung36_jcon_scan/icn_252_alt_gate I
    tableswitch 1 2
        icn_254_β
        icn_253_β
        default: icn_242_α
icn_250_α:
    goto icn_251_α
icn_250_β:
    goto icn_251_β
    goto icn_250_wentry
icn_250_waft_0:
    astore 194
    getstatic java/lang/System/out Ljava/io/PrintStream;
    aload 194
    invokevirtual java/io/PrintStream/print(Ljava/lang/String;)V
    goto icn_252_α
icn_250_waft_1:
    astore 195
    getstatic java/lang/System/out Ljava/io/PrintStream;
    aload 195
    invokevirtual java/io/PrintStream/print(Ljava/lang/String;)V
    getstatic java/lang/System/out Ljava/io/PrintStream;
    ldc ""
    invokevirtual java/io/PrintStream/println(Ljava/lang/String;)V
    aload 195
    goto icn_p3_s0_sdrain
icn_250_wentry:
    goto icn_251_α
icn_p3_s0_sdrain:
    pop
    goto icn_242_α
icn_p3_done:
    iconst_0
    putstatic rung36_jcon_scan/icn_suspended B
    iconst_0
    putstatic rung36_jcon_scan/icn_suspend_id I
    iconst_1
    putstatic rung36_jcon_scan/icn_failed B
    return
icn_p3_ret:
    iconst_0
    putstatic rung36_jcon_scan/icn_failed B
    return
icn_p3_sret:
    return
.end method

.method public static icn_p4()V
    .limit stack 16
    .limit locals 404
    lconst_0
    lstore 0
    lconst_0
    lstore 2
    lconst_0
    lstore 4
    lconst_0
    lstore 6
    lconst_0
    lstore 8
    lconst_0
    lstore 10
    lconst_0
    lstore 12
    lconst_0
    lstore 14
    lconst_0
    lstore 16
    lconst_0
    lstore 18
    lconst_0
    lstore 20
    lconst_0
    lstore 22
    lconst_0
    lstore 24
    lconst_0
    lstore 26
    lconst_0
    lstore 28
    lconst_0
    lstore 30
    lconst_0
    lstore 32
    lconst_0
    lstore 34
    lconst_0
    lstore 36
    lconst_0
    lstore 38
    lconst_0
    lstore 40
    lconst_0
    lstore 42
    lconst_0
    lstore 44
    lconst_0
    lstore 46
    lconst_0
    lstore 48
    lconst_0
    lstore 50
    lconst_0
    lstore 52
    lconst_0
    lstore 54
    lconst_0
    lstore 56
    lconst_0
    lstore 58
    lconst_0
    lstore 60
    lconst_0
    lstore 62
    iconst_0
    istore 84
    iconst_0
    istore 85
    iconst_0
    istore 86
    iconst_0
    istore 87
    aconst_null
    astore 148
    aconst_null
    astore 149
    aconst_null
    astore 150
    aconst_null
    astore 151
    aconst_null
    astore 152
    aconst_null
    astore 153
    aconst_null
    astore 154
    aconst_null
    astore 155
    aconst_null
    astore 156
    aconst_null
    astore 157
    aconst_null
    astore 158
    aconst_null
    astore 159
    aconst_null
    astore 160
    aconst_null
    astore 161
    aconst_null
    astore 162
    aconst_null
    astore 163
    aconst_null
    astore 164
    aconst_null
    astore 165
    aconst_null
    astore 166
    aconst_null
    astore 167
    aconst_null
    astore 168
    aconst_null
    astore 169
    aconst_null
    astore 170
    aconst_null
    astore 171
    aconst_null
    astore 172
    aconst_null
    astore 173
    aconst_null
    astore 174
    aconst_null
    astore 175
    aconst_null
    astore 176
    aconst_null
    astore 177
    aconst_null
    astore 178
    aconst_null
    astore 179
    aconst_null
    astore 180
    aconst_null
    astore 181
    aconst_null
    astore 182
    aconst_null
    astore 183
    goto icn_322_α
;  STR
icn_260_α:
    ldc "\"abcdef\" ? (tab(0) & (while write(move(-1)))) ----> "
    goto icn_259_waft_0
icn_260_β:
    goto icn_p4_done
;  STR
icn_262_α:
    ldc "none"
    goto icn_261_alt_g1
icn_262_β:
    goto icn_p4_done
;  STR
icn_265_α:
    ldc "abcdef"
    goto icn_264_scan_setup
icn_265_β:
    goto icn_262_α
;  INT
icn_268_α:
    ldc2_w 0
    goto icn_267_ta
icn_268_β:
    goto icn_264_scan_bfail
icn_267_α:
    goto icn_268_α
icn_267_β:
    goto icn_264_scan_bfail
icn_267_ta:
;  tab: n (long) on stack
    l2i
    getstatic rung36_jcon_scan/icn_subject Ljava/lang/String;
    getstatic rung36_jcon_scan/icn_pos I
    invokestatic rung36_jcon_scan/icn_builtin_tab_str(ILjava/lang/String;I)Ljava/lang/String;
    dup
    ifnonnull icn_267_to
    pop
    goto icn_264_scan_bfail
icn_267_to:
;  tab ok: advance icn_pos = n-1, push String → γ
    goto icn_266_and_rg_0
;  INT
icn_273_α:
    ldc2_w 1
    goto icn_272_neg
icn_273_β:
    goto icn_267_β
;  NEG
icn_272_α:
    goto icn_273_α
icn_272_β:
    goto icn_273_β
icn_272_neg:
    lneg
    goto icn_271_mva
icn_271_α:
    goto icn_272_α
icn_271_β:
    goto icn_267_β
icn_271_mva:
;  move: n (long) on stack
    l2i
    getstatic rung36_jcon_scan/icn_subject Ljava/lang/String;
    getstatic rung36_jcon_scan/icn_pos I
    invokestatic rung36_jcon_scan/icn_builtin_move_str(ILjava/lang/String;I)Ljava/lang/String;
    dup
    ifnonnull icn_271_mvo
    pop
    goto icn_267_β
icn_271_mvo:
;  move ok: icn_pos advanced by helper, push String → γ
    goto icn_270_waft_0
icn_270_α:
    goto icn_271_α
icn_270_β:
    goto icn_271_β
    goto icn_270_wentry
icn_270_waft_0:
    astore 148
    getstatic java/lang/System/out Ljava/io/PrintStream;
    aload 148
    invokevirtual java/io/PrintStream/print(Ljava/lang/String;)V
    getstatic java/lang/System/out Ljava/io/PrintStream;
    ldc ""
    invokevirtual java/io/PrintStream/println(Ljava/lang/String;)V
    aload 148
    goto icn_269_condok
icn_270_wentry:
    goto icn_271_α
icn_269_condok:
    pop
    goto icn_270_α
icn_269_α:
    goto icn_270_α
icn_269_β:
    goto icn_267_β
    goto icn_266_α
icn_266_and_rg_0:
    putstatic rung36_jcon_scan/icn_266_and_drain_0 Ljava/lang/String;
    goto icn_269_α
icn_266_α:
    goto icn_267_α
icn_266_β:
    goto icn_269_β
;  SCAN
icn_264_α:
    goto icn_265_α
icn_264_β:
    goto icn_264_scan_beta
icn_264_scan_setup:
;  SCAN save+install
    getstatic rung36_jcon_scan/icn_subject Ljava/lang/String;
    putstatic rung36_jcon_scan/icn_scan_oldsubj_264 Ljava/lang/String;
    getstatic rung36_jcon_scan/icn_pos I
    putstatic rung36_jcon_scan/icn_scan_oldpos_264 I
    putstatic rung36_jcon_scan/icn_subject Ljava/lang/String;
    iconst_0
    putstatic rung36_jcon_scan/icn_pos I
    goto icn_266_α
icn_264_scan_bok:
;  SCAN restore (body ok)
    getstatic rung36_jcon_scan/icn_scan_oldsubj_264 Ljava/lang/String;
    putstatic rung36_jcon_scan/icn_subject Ljava/lang/String;
    getstatic rung36_jcon_scan/icn_scan_oldpos_264 I
    putstatic rung36_jcon_scan/icn_pos I
    goto icn_263_image_after
icn_264_scan_bfail:
;  SCAN restore (body fail)
    getstatic rung36_jcon_scan/icn_scan_oldsubj_264 Ljava/lang/String;
    putstatic rung36_jcon_scan/icn_subject Ljava/lang/String;
    getstatic rung36_jcon_scan/icn_scan_oldpos_264 I
    putstatic rung36_jcon_scan/icn_pos I
    goto icn_265_β
icn_264_scan_beta:
;  SCAN restore (outer β)
    getstatic rung36_jcon_scan/icn_scan_oldsubj_264 Ljava/lang/String;
    putstatic rung36_jcon_scan/icn_subject Ljava/lang/String;
    getstatic rung36_jcon_scan/icn_scan_oldpos_264 I
    putstatic rung36_jcon_scan/icn_pos I
    goto icn_266_β
icn_263_α:
    goto icn_264_α
icn_263_β:
    goto icn_264_β
icn_263_image_after:
    goto icn_261_alt_g0
icn_261_alt_g0:
    astore 149
    sipush 1
    putstatic rung36_jcon_scan/icn_261_alt_gate I
    aload 149
    goto icn_259_waft_1
icn_261_alt_g1:
    astore 150
    sipush 2
    putstatic rung36_jcon_scan/icn_261_alt_gate I
    aload 150
    goto icn_259_waft_1
icn_261_α:
    iconst_0
    putstatic rung36_jcon_scan/icn_261_alt_gate I
    goto icn_263_α
icn_261_β:
    getstatic rung36_jcon_scan/icn_261_alt_gate I
    tableswitch 1 2
        icn_263_β
        icn_262_β
        default: icn_p4_done
icn_259_α:
    goto icn_260_α
icn_259_β:
    goto icn_260_β
    goto icn_259_wentry
icn_259_waft_0:
    astore 151
    getstatic java/lang/System/out Ljava/io/PrintStream;
    aload 151
    invokevirtual java/io/PrintStream/print(Ljava/lang/String;)V
    goto icn_261_α
icn_259_waft_1:
    astore 152
    getstatic java/lang/System/out Ljava/io/PrintStream;
    aload 152
    invokevirtual java/io/PrintStream/print(Ljava/lang/String;)V
    getstatic java/lang/System/out Ljava/io/PrintStream;
    ldc ""
    invokevirtual java/io/PrintStream/println(Ljava/lang/String;)V
    aload 152
    goto icn_p4_s6_sdrain
icn_259_wentry:
    goto icn_260_α
icn_p4_s6_sdrain:
    pop
    goto icn_p4_done
;  STR
icn_275_α:
    ldc "every s ? write(=(\"a\" | \"x\")) ----> "
    goto icn_274_waft_0
icn_275_β:
    goto icn_259_α
;  STR
icn_277_α:
    ldc "none"
    goto icn_276_alt_g1
icn_277_β:
    goto icn_259_α
;  VAR
icn_281_α:
    getstatic rung36_jcon_scan/icn_pv_p4_s Ljava/lang/String;
    goto icn_280_scan_setup
icn_281_β:
    goto icn_277_α
;  STR
icn_285_α:
    ldc "x"
    goto icn_284_alt_g1
icn_285_β:
    goto icn_280_scan_bfail
;  STR
icn_286_α:
    ldc "a"
    goto icn_284_alt_g0
icn_286_β:
    goto icn_285_α
icn_284_alt_g0:
    astore 153
    sipush 1
    putstatic rung36_jcon_scan/icn_284_alt_gate I
    aload 153
    goto icn_283_ma
icn_284_alt_g1:
    astore 154
    sipush 2
    putstatic rung36_jcon_scan/icn_284_alt_gate I
    aload 154
    goto icn_283_ma
icn_284_α:
    iconst_0
    putstatic rung36_jcon_scan/icn_284_alt_gate I
    goto icn_286_α
icn_284_β:
    getstatic rung36_jcon_scan/icn_284_alt_gate I
    tableswitch 1 2
        icn_286_β
        icn_285_β
        default: icn_280_scan_bfail
icn_283_α:
    goto icn_284_α
icn_283_β:
    goto icn_280_scan_bfail
icn_283_ma:
;  match: s String on stack
    getstatic rung36_jcon_scan/icn_subject Ljava/lang/String;
    getstatic rung36_jcon_scan/icn_pos I
    invokestatic rung36_jcon_scan/icn_builtin_match(Ljava/lang/String;Ljava/lang/String;I)J
    dup2
    lconst_1
    lneg
    lcmp
    ifne icn_283_mo
    pop2
    goto icn_280_scan_bfail
icn_283_mo:
;  match ok: icn_pos = result-1 (0-based), push result → γ
    dup2
    l2i
    iconst_1
    isub
    putstatic rung36_jcon_scan/icn_pos I
    goto icn_282_waft_0
icn_282_α:
    goto icn_283_α
icn_282_β:
    goto icn_283_β
    goto icn_282_wentry
icn_282_waft_0:
    lstore 2
    getstatic java/lang/System/out Ljava/io/PrintStream;
    lload 2
    invokevirtual java/io/PrintStream/print(J)V
    getstatic java/lang/System/out Ljava/io/PrintStream;
    ldc ""
    invokevirtual java/io/PrintStream/println(Ljava/lang/String;)V
    lload 2
    goto icn_280_scan_bok
icn_282_wentry:
    goto icn_283_α
;  SCAN
icn_280_α:
    goto icn_281_α
icn_280_β:
    goto icn_280_scan_beta
icn_280_scan_setup:
;  SCAN save+install
    getstatic rung36_jcon_scan/icn_subject Ljava/lang/String;
    putstatic rung36_jcon_scan/icn_scan_oldsubj_280 Ljava/lang/String;
    getstatic rung36_jcon_scan/icn_pos I
    putstatic rung36_jcon_scan/icn_scan_oldpos_280 I
    putstatic rung36_jcon_scan/icn_subject Ljava/lang/String;
    iconst_0
    putstatic rung36_jcon_scan/icn_pos I
    goto icn_282_α
icn_280_scan_bok:
;  SCAN restore (body ok)
    getstatic rung36_jcon_scan/icn_scan_oldsubj_280 Ljava/lang/String;
    putstatic rung36_jcon_scan/icn_subject Ljava/lang/String;
    getstatic rung36_jcon_scan/icn_scan_oldpos_280 I
    putstatic rung36_jcon_scan/icn_pos I
    goto icn_279_gdrain
icn_280_scan_bfail:
;  SCAN restore (body fail)
    getstatic rung36_jcon_scan/icn_scan_oldsubj_280 Ljava/lang/String;
    putstatic rung36_jcon_scan/icn_subject Ljava/lang/String;
    getstatic rung36_jcon_scan/icn_scan_oldpos_280 I
    putstatic rung36_jcon_scan/icn_pos I
    goto icn_281_β
icn_280_scan_beta:
;  SCAN restore (outer β)
    getstatic rung36_jcon_scan/icn_scan_oldsubj_280 Ljava/lang/String;
    putstatic rung36_jcon_scan/icn_subject Ljava/lang/String;
    getstatic rung36_jcon_scan/icn_scan_oldpos_280 I
    putstatic rung36_jcon_scan/icn_pos I
    goto icn_282_β
icn_279_gdrain:
    pop
icn_279_pump:
    goto icn_280_β
icn_279_α:
    goto icn_280_α
icn_279_β:
    goto icn_277_α
icn_278_α:
    goto icn_279_α
icn_278_β:
    goto icn_279_β
icn_278_image_after:
    invokestatic java/lang/Long/toString(J)Ljava/lang/String;
    goto icn_276_alt_g0
icn_276_alt_g0:
    astore 155
    sipush 1
    putstatic rung36_jcon_scan/icn_276_alt_gate I
    aload 155
    goto icn_274_waft_1
icn_276_alt_g1:
    astore 156
    sipush 2
    putstatic rung36_jcon_scan/icn_276_alt_gate I
    aload 156
    goto icn_274_waft_1
icn_276_α:
    iconst_0
    putstatic rung36_jcon_scan/icn_276_alt_gate I
    goto icn_278_α
icn_276_β:
    getstatic rung36_jcon_scan/icn_276_alt_gate I
    tableswitch 1 2
        icn_278_β
        icn_277_β
        default: icn_259_α
icn_274_α:
    goto icn_275_α
icn_274_β:
    goto icn_275_β
    goto icn_274_wentry
icn_274_waft_0:
    astore 157
    getstatic java/lang/System/out Ljava/io/PrintStream;
    aload 157
    invokevirtual java/io/PrintStream/print(Ljava/lang/String;)V
    goto icn_276_α
icn_274_waft_1:
    astore 158
    getstatic java/lang/System/out Ljava/io/PrintStream;
    aload 158
    invokevirtual java/io/PrintStream/print(Ljava/lang/String;)V
    getstatic java/lang/System/out Ljava/io/PrintStream;
    ldc ""
    invokevirtual java/io/PrintStream/println(Ljava/lang/String;)V
    aload 158
    goto icn_p4_s5_sdrain
icn_274_wentry:
    goto icn_275_α
icn_p4_s5_sdrain:
    pop
    goto icn_259_α
;  STR
icn_288_α:
    ldc "s := \"xxxxxx\" ----> "
    goto icn_287_waft_0
icn_288_β:
    goto icn_274_α
;  STR
icn_290_α:
    ldc "none"
    goto icn_289_alt_g1
icn_290_β:
    goto icn_274_α
;  STR
icn_293_α:
    ldc "xxxxxx"
    goto icn_292_store
icn_293_β:
    goto icn_290_α
icn_292_α:
    goto icn_293_α
icn_292_β:
    goto icn_293_β
icn_292_store:
    putstatic rung36_jcon_scan/icn_pv_p4_s Ljava/lang/String;
    getstatic rung36_jcon_scan/icn_pv_p4_s Ljava/lang/String;
    goto icn_291_image_after
icn_291_α:
    goto icn_292_α
icn_291_β:
    goto icn_292_β
icn_291_image_after:
    goto icn_289_alt_g0
icn_289_alt_g0:
    astore 159
    sipush 1
    putstatic rung36_jcon_scan/icn_289_alt_gate I
    aload 159
    goto icn_287_waft_1
icn_289_alt_g1:
    astore 160
    sipush 2
    putstatic rung36_jcon_scan/icn_289_alt_gate I
    aload 160
    goto icn_287_waft_1
icn_289_α:
    iconst_0
    putstatic rung36_jcon_scan/icn_289_alt_gate I
    goto icn_291_α
icn_289_β:
    getstatic rung36_jcon_scan/icn_289_alt_gate I
    tableswitch 1 2
        icn_291_β
        icn_290_β
        default: icn_274_α
icn_287_α:
    goto icn_288_α
icn_287_β:
    goto icn_288_β
    goto icn_287_wentry
icn_287_waft_0:
    astore 161
    getstatic java/lang/System/out Ljava/io/PrintStream;
    aload 161
    invokevirtual java/io/PrintStream/print(Ljava/lang/String;)V
    goto icn_289_α
icn_287_waft_1:
    astore 162
    getstatic java/lang/System/out Ljava/io/PrintStream;
    aload 162
    invokevirtual java/io/PrintStream/print(Ljava/lang/String;)V
    getstatic java/lang/System/out Ljava/io/PrintStream;
    ldc ""
    invokevirtual java/io/PrintStream/println(Ljava/lang/String;)V
    aload 162
    goto icn_p4_s4_sdrain
icn_287_wentry:
    goto icn_288_α
icn_p4_s4_sdrain:
    pop
    goto icn_274_α
;  STR
icn_295_α:
    ldc "every write(s ? tab(find(\" \"))) ----> "
    goto icn_294_waft_0
icn_295_β:
    goto icn_287_α
;  STR
icn_297_α:
    ldc "none"
    goto icn_296_alt_g1
icn_297_β:
    goto icn_287_α
;  VAR
icn_302_α:
    getstatic rung36_jcon_scan/icn_pv_p4_s Ljava/lang/String;
    goto icn_301_scan_setup
icn_302_β:
    goto icn_297_α
icn_304_α:
    goto icn_301_scan_bfail
icn_304_β:
    goto icn_301_scan_bfail
icn_303_α:
    goto icn_304_α
icn_303_β:
    goto icn_301_scan_bfail
icn_303_ta:
;  tab: n (long) on stack
    l2i
    getstatic rung36_jcon_scan/icn_subject Ljava/lang/String;
    getstatic rung36_jcon_scan/icn_pos I
    invokestatic rung36_jcon_scan/icn_builtin_tab_str(ILjava/lang/String;I)Ljava/lang/String;
    dup
    ifnonnull icn_303_to
    pop
    goto icn_301_scan_bfail
icn_303_to:
;  tab ok: advance icn_pos = n-1, push String → γ
    goto icn_301_scan_bok
;  SCAN
icn_301_α:
    goto icn_302_α
icn_301_β:
    goto icn_301_scan_beta
icn_301_scan_setup:
;  SCAN save+install
    getstatic rung36_jcon_scan/icn_subject Ljava/lang/String;
    putstatic rung36_jcon_scan/icn_scan_oldsubj_301 Ljava/lang/String;
    getstatic rung36_jcon_scan/icn_pos I
    putstatic rung36_jcon_scan/icn_scan_oldpos_301 I
    putstatic rung36_jcon_scan/icn_subject Ljava/lang/String;
    iconst_0
    putstatic rung36_jcon_scan/icn_pos I
    goto icn_303_α
icn_301_scan_bok:
;  SCAN restore (body ok)
    getstatic rung36_jcon_scan/icn_scan_oldsubj_301 Ljava/lang/String;
    putstatic rung36_jcon_scan/icn_subject Ljava/lang/String;
    getstatic rung36_jcon_scan/icn_scan_oldpos_301 I
    putstatic rung36_jcon_scan/icn_pos I
    goto icn_300_waft_0
icn_301_scan_bfail:
;  SCAN restore (body fail)
    getstatic rung36_jcon_scan/icn_scan_oldsubj_301 Ljava/lang/String;
    putstatic rung36_jcon_scan/icn_subject Ljava/lang/String;
    getstatic rung36_jcon_scan/icn_scan_oldpos_301 I
    putstatic rung36_jcon_scan/icn_pos I
    goto icn_302_β
icn_301_scan_beta:
;  SCAN restore (outer β)
    getstatic rung36_jcon_scan/icn_scan_oldsubj_301 Ljava/lang/String;
    putstatic rung36_jcon_scan/icn_subject Ljava/lang/String;
    getstatic rung36_jcon_scan/icn_scan_oldpos_301 I
    putstatic rung36_jcon_scan/icn_pos I
    goto icn_303_β
icn_300_α:
    goto icn_301_α
icn_300_β:
    goto icn_301_β
    goto icn_300_wentry
icn_300_waft_0:
    astore 163
    getstatic java/lang/System/out Ljava/io/PrintStream;
    aload 163
    invokevirtual java/io/PrintStream/print(Ljava/lang/String;)V
    getstatic java/lang/System/out Ljava/io/PrintStream;
    ldc ""
    invokevirtual java/io/PrintStream/println(Ljava/lang/String;)V
    aload 163
    goto icn_299_gdrain
icn_300_wentry:
    goto icn_301_α
icn_299_gdrain:
    pop
icn_299_pump:
    goto icn_300_β
icn_299_α:
    goto icn_300_α
icn_299_β:
    goto icn_297_α
icn_298_α:
    goto icn_299_α
icn_298_β:
    goto icn_299_β
icn_298_image_after:
    invokestatic java/lang/Long/toString(J)Ljava/lang/String;
    goto icn_296_alt_g0
icn_296_alt_g0:
    astore 164
    sipush 1
    putstatic rung36_jcon_scan/icn_296_alt_gate I
    aload 164
    goto icn_294_waft_1
icn_296_alt_g1:
    astore 165
    sipush 2
    putstatic rung36_jcon_scan/icn_296_alt_gate I
    aload 165
    goto icn_294_waft_1
icn_296_α:
    iconst_0
    putstatic rung36_jcon_scan/icn_296_alt_gate I
    goto icn_298_α
icn_296_β:
    getstatic rung36_jcon_scan/icn_296_alt_gate I
    tableswitch 1 2
        icn_298_β
        icn_297_β
        default: icn_287_α
icn_294_α:
    goto icn_295_α
icn_294_β:
    goto icn_295_β
    goto icn_294_wentry
icn_294_waft_0:
    astore 166
    getstatic java/lang/System/out Ljava/io/PrintStream;
    aload 166
    invokevirtual java/io/PrintStream/print(Ljava/lang/String;)V
    goto icn_296_α
icn_294_waft_1:
    astore 167
    getstatic java/lang/System/out Ljava/io/PrintStream;
    aload 167
    invokevirtual java/io/PrintStream/print(Ljava/lang/String;)V
    getstatic java/lang/System/out Ljava/io/PrintStream;
    ldc ""
    invokevirtual java/io/PrintStream/println(Ljava/lang/String;)V
    aload 167
    goto icn_p4_s3_sdrain
icn_294_wentry:
    goto icn_295_α
icn_p4_s3_sdrain:
    pop
    goto icn_287_α
;  STR
icn_306_α:
    ldc "s := \"this is the time to work it all out\" ----> "
    goto icn_305_waft_0
icn_306_β:
    goto icn_294_α
;  STR
icn_308_α:
    ldc "none"
    goto icn_307_alt_g1
icn_308_β:
    goto icn_294_α
;  STR
icn_311_α:
    ldc "this is the time to work it all out"
    goto icn_310_store
icn_311_β:
    goto icn_308_α
icn_310_α:
    goto icn_311_α
icn_310_β:
    goto icn_311_β
icn_310_store:
    putstatic rung36_jcon_scan/icn_pv_p4_s Ljava/lang/String;
    getstatic rung36_jcon_scan/icn_pv_p4_s Ljava/lang/String;
    goto icn_309_image_after
icn_309_α:
    goto icn_310_α
icn_309_β:
    goto icn_310_β
icn_309_image_after:
    goto icn_307_alt_g0
icn_307_alt_g0:
    astore 168
    sipush 1
    putstatic rung36_jcon_scan/icn_307_alt_gate I
    aload 168
    goto icn_305_waft_1
icn_307_alt_g1:
    astore 169
    sipush 2
    putstatic rung36_jcon_scan/icn_307_alt_gate I
    aload 169
    goto icn_305_waft_1
icn_307_α:
    iconst_0
    putstatic rung36_jcon_scan/icn_307_alt_gate I
    goto icn_309_α
icn_307_β:
    getstatic rung36_jcon_scan/icn_307_alt_gate I
    tableswitch 1 2
        icn_309_β
        icn_308_β
        default: icn_294_α
icn_305_α:
    goto icn_306_α
icn_305_β:
    goto icn_306_β
    goto icn_305_wentry
icn_305_waft_0:
    astore 170
    getstatic java/lang/System/out Ljava/io/PrintStream;
    aload 170
    invokevirtual java/io/PrintStream/print(Ljava/lang/String;)V
    goto icn_307_α
icn_305_waft_1:
    astore 171
    getstatic java/lang/System/out Ljava/io/PrintStream;
    aload 171
    invokevirtual java/io/PrintStream/print(Ljava/lang/String;)V
    getstatic java/lang/System/out Ljava/io/PrintStream;
    ldc ""
    invokevirtual java/io/PrintStream/println(Ljava/lang/String;)V
    aload 171
    goto icn_p4_s2_sdrain
icn_305_wentry:
    goto icn_306_α
icn_p4_s2_sdrain:
    pop
    goto icn_294_α
;  STR
icn_313_α:
    ldc "every write(s ?:= upto(&lcase)) ----> "
    goto icn_312_waft_0
icn_313_β:
    goto icn_305_α
;  STR
icn_315_α:
    ldc "none"
    goto icn_314_alt_g1
icn_315_β:
    goto icn_305_α
;  VAR
icn_321_α:
    ldc "abcdefghijklmnopqrstuvwxyz"
    goto icn_320_after
icn_321_β:
    goto icn_315_α
icn_320_α:
    goto icn_321_α
icn_320_after:
;  upto α: save cs, enter step
    putstatic rung36_jcon_scan/icn_upto_cs_320 Ljava/lang/String;
    goto icn_320_step
icn_320_β:
    goto icn_320_step
icn_320_step:
;  upto step
    getstatic rung36_jcon_scan/icn_upto_cs_320 Ljava/lang/String;
    getstatic rung36_jcon_scan/icn_subject Ljava/lang/String;
    getstatic rung36_jcon_scan/icn_pos I
    invokestatic rung36_jcon_scan/icn_builtin_upto_step(Ljava/lang/String;Ljava/lang/String;I)J
    dup2
    lconst_1
    lneg
    lcmp
    ifne icn_320_chk
    pop2
    goto icn_315_α
icn_320_chk:
;  upto: yield 1-based pos (tab advances icn_pos)
    goto icn_319_rhsok
icn_319_α:
    goto icn_320_α
icn_319_β:
    goto icn_320_β
icn_319_rhsok:
    putstatic rung36_jcon_scan/icn_319_augtemp J
    getstatic rung36_jcon_scan/icn_pv_p4_s J
    getstatic rung36_jcon_scan/icn_319_augtemp J
    ladd
    dup2
    putstatic rung36_jcon_scan/icn_pv_p4_s J
    goto icn_318_waft_0
icn_318_α:
    goto icn_319_α
icn_318_β:
    goto icn_319_β
    goto icn_318_wentry
icn_318_waft_0:
    lstore 4
    getstatic java/lang/System/out Ljava/io/PrintStream;
    lload 4
    invokevirtual java/io/PrintStream/print(J)V
    getstatic java/lang/System/out Ljava/io/PrintStream;
    ldc ""
    invokevirtual java/io/PrintStream/println(Ljava/lang/String;)V
    lload 4
    goto icn_317_gdrain
icn_318_wentry:
    goto icn_319_α
icn_317_gdrain:
    pop2
icn_317_pump:
    goto icn_318_β
icn_317_α:
    goto icn_318_α
icn_317_β:
    goto icn_315_α
icn_316_α:
    goto icn_317_α
icn_316_β:
    goto icn_317_β
icn_316_image_after:
    invokestatic java/lang/Long/toString(J)Ljava/lang/String;
    goto icn_314_alt_g0
icn_314_alt_g0:
    astore 172
    sipush 1
    putstatic rung36_jcon_scan/icn_314_alt_gate I
    aload 172
    goto icn_312_waft_1
icn_314_alt_g1:
    astore 173
    sipush 2
    putstatic rung36_jcon_scan/icn_314_alt_gate I
    aload 173
    goto icn_312_waft_1
icn_314_α:
    iconst_0
    putstatic rung36_jcon_scan/icn_314_alt_gate I
    goto icn_316_α
icn_314_β:
    getstatic rung36_jcon_scan/icn_314_alt_gate I
    tableswitch 1 2
        icn_316_β
        icn_315_β
        default: icn_305_α
icn_312_α:
    goto icn_313_α
icn_312_β:
    goto icn_313_β
    goto icn_312_wentry
icn_312_waft_0:
    astore 174
    getstatic java/lang/System/out Ljava/io/PrintStream;
    aload 174
    invokevirtual java/io/PrintStream/print(Ljava/lang/String;)V
    goto icn_314_α
icn_312_waft_1:
    astore 175
    getstatic java/lang/System/out Ljava/io/PrintStream;
    aload 175
    invokevirtual java/io/PrintStream/print(Ljava/lang/String;)V
    getstatic java/lang/System/out Ljava/io/PrintStream;
    ldc ""
    invokevirtual java/io/PrintStream/println(Ljava/lang/String;)V
    aload 175
    goto icn_p4_s1_sdrain
icn_312_wentry:
    goto icn_313_α
icn_p4_s1_sdrain:
    pop
    goto icn_305_α
;  STR
icn_323_α:
    ldc "s := \"abcdef\" ----> "
    goto icn_322_waft_0
icn_323_β:
    goto icn_312_α
;  STR
icn_325_α:
    ldc "none"
    goto icn_324_alt_g1
icn_325_β:
    goto icn_312_α
;  STR
icn_328_α:
    ldc "abcdef"
    goto icn_327_store
icn_328_β:
    goto icn_325_α
icn_327_α:
    goto icn_328_α
icn_327_β:
    goto icn_328_β
icn_327_store:
    putstatic rung36_jcon_scan/icn_pv_p4_s Ljava/lang/String;
    getstatic rung36_jcon_scan/icn_pv_p4_s Ljava/lang/String;
    goto icn_326_image_after
icn_326_α:
    goto icn_327_α
icn_326_β:
    goto icn_327_β
icn_326_image_after:
    goto icn_324_alt_g0
icn_324_alt_g0:
    astore 176
    sipush 1
    putstatic rung36_jcon_scan/icn_324_alt_gate I
    aload 176
    goto icn_322_waft_1
icn_324_alt_g1:
    astore 177
    sipush 2
    putstatic rung36_jcon_scan/icn_324_alt_gate I
    aload 177
    goto icn_322_waft_1
icn_324_α:
    iconst_0
    putstatic rung36_jcon_scan/icn_324_alt_gate I
    goto icn_326_α
icn_324_β:
    getstatic rung36_jcon_scan/icn_324_alt_gate I
    tableswitch 1 2
        icn_326_β
        icn_325_β
        default: icn_312_α
icn_322_α:
    goto icn_323_α
icn_322_β:
    goto icn_323_β
    goto icn_322_wentry
icn_322_waft_0:
    astore 178
    getstatic java/lang/System/out Ljava/io/PrintStream;
    aload 178
    invokevirtual java/io/PrintStream/print(Ljava/lang/String;)V
    goto icn_324_α
icn_322_waft_1:
    astore 179
    getstatic java/lang/System/out Ljava/io/PrintStream;
    aload 179
    invokevirtual java/io/PrintStream/print(Ljava/lang/String;)V
    getstatic java/lang/System/out Ljava/io/PrintStream;
    ldc ""
    invokevirtual java/io/PrintStream/println(Ljava/lang/String;)V
    aload 179
    goto icn_p4_s0_sdrain
icn_322_wentry:
    goto icn_323_α
icn_p4_s0_sdrain:
    pop
    goto icn_312_α
icn_p4_done:
    iconst_0
    putstatic rung36_jcon_scan/icn_suspended B
    iconst_0
    putstatic rung36_jcon_scan/icn_suspend_id I
    iconst_1
    putstatic rung36_jcon_scan/icn_failed B
    return
icn_p4_ret:
    iconst_0
    putstatic rung36_jcon_scan/icn_failed B
    return
icn_p4_sret:
    return
.end method

.method public static icn_main()V
    .limit stack 16
    .limit locals 372
    lconst_0
    lstore 0
    lconst_0
    lstore 2
    lconst_0
    lstore 4
    lconst_0
    lstore 6
    lconst_0
    lstore 8
    lconst_0
    lstore 10
    lconst_0
    lstore 12
    lconst_0
    lstore 14
    lconst_0
    lstore 16
    lconst_0
    lstore 18
    lconst_0
    lstore 20
    lconst_0
    lstore 22
    lconst_0
    lstore 24
    lconst_0
    lstore 26
    lconst_0
    lstore 28
    lconst_0
    lstore 30
    lconst_0
    lstore 32
    lconst_0
    lstore 34
    lconst_0
    lstore 36
    lconst_0
    lstore 38
    lconst_0
    lstore 40
    lconst_0
    lstore 42
    lconst_0
    lstore 44
    lconst_0
    lstore 46
    lconst_0
    lstore 48
    lconst_0
    lstore 50
    lconst_0
    lstore 52
    lconst_0
    lstore 54
    lconst_0
    lstore 56
    lconst_0
    lstore 58
    lconst_0
    lstore 60
    lconst_0
    lstore 62
    iconst_0
    istore 84
    iconst_0
    istore 85
    iconst_0
    istore 86
    iconst_0
    istore 87
    aconst_null
    astore 148
    aconst_null
    astore 149
    aconst_null
    astore 150
    aconst_null
    astore 151
    goto icn_332_α
icn_329_α:
    goto icn_329_docall
icn_329_β:
    goto icn_main_done
icn_329_docall:
    getstatic rung36_jcon_scan/icn_30_swap_t1 J
    lstore 152
    getstatic rung36_jcon_scan/icn_30_swap_t2 J
    lstore 154
    getstatic rung36_jcon_scan/icn_46_I J
    lstore 156
    getstatic rung36_jcon_scan/icn_46_bound J
    lstore 158
    getstatic rung36_jcon_scan/icn_46_e1cur J
    lstore 160
    getstatic rung36_jcon_scan/icn_46_e1val J
    lstore 162
    getstatic rung36_jcon_scan/icn_46_e2val J
    lstore 164
    getstatic rung36_jcon_scan/icn_66_I J
    lstore 166
    getstatic rung36_jcon_scan/icn_66_bound J
    lstore 168
    getstatic rung36_jcon_scan/icn_66_e1cur J
    lstore 170
    getstatic rung36_jcon_scan/icn_66_e1val J
    lstore 172
    getstatic rung36_jcon_scan/icn_66_e2val J
    lstore 174
    getstatic rung36_jcon_scan/icn_167_augtemp J
    lstore 176
    getstatic rung36_jcon_scan/icn_202_I J
    lstore 178
    getstatic rung36_jcon_scan/icn_202_bound J
    lstore 180
    getstatic rung36_jcon_scan/icn_202_e1cur J
    lstore 182
    getstatic rung36_jcon_scan/icn_202_e1val J
    lstore 184
    getstatic rung36_jcon_scan/icn_202_e2val J
    lstore 186
    getstatic rung36_jcon_scan/icn_239_I J
    lstore 188
    getstatic rung36_jcon_scan/icn_239_bound J
    lstore 190
    getstatic rung36_jcon_scan/icn_239_e1cur J
    lstore 192
    getstatic rung36_jcon_scan/icn_239_e1val J
    lstore 194
    getstatic rung36_jcon_scan/icn_239_e2val J
    lstore 196
    getstatic rung36_jcon_scan/icn_319_augtemp J
    lstore 198
    invokestatic rung36_jcon_scan/icn_p4()V
    lload 152
    putstatic rung36_jcon_scan/icn_30_swap_t1 J
    lload 154
    putstatic rung36_jcon_scan/icn_30_swap_t2 J
    lload 156
    putstatic rung36_jcon_scan/icn_46_I J
    lload 158
    putstatic rung36_jcon_scan/icn_46_bound J
    lload 160
    putstatic rung36_jcon_scan/icn_46_e1cur J
    lload 162
    putstatic rung36_jcon_scan/icn_46_e1val J
    lload 164
    putstatic rung36_jcon_scan/icn_46_e2val J
    lload 166
    putstatic rung36_jcon_scan/icn_66_I J
    lload 168
    putstatic rung36_jcon_scan/icn_66_bound J
    lload 170
    putstatic rung36_jcon_scan/icn_66_e1cur J
    lload 172
    putstatic rung36_jcon_scan/icn_66_e1val J
    lload 174
    putstatic rung36_jcon_scan/icn_66_e2val J
    lload 176
    putstatic rung36_jcon_scan/icn_167_augtemp J
    lload 178
    putstatic rung36_jcon_scan/icn_202_I J
    lload 180
    putstatic rung36_jcon_scan/icn_202_bound J
    lload 182
    putstatic rung36_jcon_scan/icn_202_e1cur J
    lload 184
    putstatic rung36_jcon_scan/icn_202_e1val J
    lload 186
    putstatic rung36_jcon_scan/icn_202_e2val J
    lload 188
    putstatic rung36_jcon_scan/icn_239_I J
    lload 190
    putstatic rung36_jcon_scan/icn_239_bound J
    lload 192
    putstatic rung36_jcon_scan/icn_239_e1cur J
    lload 194
    putstatic rung36_jcon_scan/icn_239_e1val J
    lload 196
    putstatic rung36_jcon_scan/icn_239_e2val J
    lload 198
    putstatic rung36_jcon_scan/icn_319_augtemp J
    getstatic rung36_jcon_scan/icn_failed B
    ifne icn_329_after_call
    getstatic rung36_jcon_scan/icn_retval J
    goto icn_main_s3_sdrain
icn_329_after_call:
    goto icn_main_done
icn_main_s3_sdrain:
    pop2
    goto icn_main_done
icn_330_α:
    goto icn_330_docall
icn_330_β:
    goto icn_329_α
icn_330_docall:
    getstatic rung36_jcon_scan/icn_30_swap_t1 J
    lstore 152
    getstatic rung36_jcon_scan/icn_30_swap_t2 J
    lstore 154
    getstatic rung36_jcon_scan/icn_46_I J
    lstore 156
    getstatic rung36_jcon_scan/icn_46_bound J
    lstore 158
    getstatic rung36_jcon_scan/icn_46_e1cur J
    lstore 160
    getstatic rung36_jcon_scan/icn_46_e1val J
    lstore 162
    getstatic rung36_jcon_scan/icn_46_e2val J
    lstore 164
    getstatic rung36_jcon_scan/icn_66_I J
    lstore 166
    getstatic rung36_jcon_scan/icn_66_bound J
    lstore 168
    getstatic rung36_jcon_scan/icn_66_e1cur J
    lstore 170
    getstatic rung36_jcon_scan/icn_66_e1val J
    lstore 172
    getstatic rung36_jcon_scan/icn_66_e2val J
    lstore 174
    getstatic rung36_jcon_scan/icn_167_augtemp J
    lstore 176
    getstatic rung36_jcon_scan/icn_202_I J
    lstore 178
    getstatic rung36_jcon_scan/icn_202_bound J
    lstore 180
    getstatic rung36_jcon_scan/icn_202_e1cur J
    lstore 182
    getstatic rung36_jcon_scan/icn_202_e1val J
    lstore 184
    getstatic rung36_jcon_scan/icn_202_e2val J
    lstore 186
    getstatic rung36_jcon_scan/icn_239_I J
    lstore 188
    getstatic rung36_jcon_scan/icn_239_bound J
    lstore 190
    getstatic rung36_jcon_scan/icn_239_e1cur J
    lstore 192
    getstatic rung36_jcon_scan/icn_239_e1val J
    lstore 194
    getstatic rung36_jcon_scan/icn_239_e2val J
    lstore 196
    getstatic rung36_jcon_scan/icn_319_augtemp J
    lstore 198
    invokestatic rung36_jcon_scan/icn_p3()V
    lload 152
    putstatic rung36_jcon_scan/icn_30_swap_t1 J
    lload 154
    putstatic rung36_jcon_scan/icn_30_swap_t2 J
    lload 156
    putstatic rung36_jcon_scan/icn_46_I J
    lload 158
    putstatic rung36_jcon_scan/icn_46_bound J
    lload 160
    putstatic rung36_jcon_scan/icn_46_e1cur J
    lload 162
    putstatic rung36_jcon_scan/icn_46_e1val J
    lload 164
    putstatic rung36_jcon_scan/icn_46_e2val J
    lload 166
    putstatic rung36_jcon_scan/icn_66_I J
    lload 168
    putstatic rung36_jcon_scan/icn_66_bound J
    lload 170
    putstatic rung36_jcon_scan/icn_66_e1cur J
    lload 172
    putstatic rung36_jcon_scan/icn_66_e1val J
    lload 174
    putstatic rung36_jcon_scan/icn_66_e2val J
    lload 176
    putstatic rung36_jcon_scan/icn_167_augtemp J
    lload 178
    putstatic rung36_jcon_scan/icn_202_I J
    lload 180
    putstatic rung36_jcon_scan/icn_202_bound J
    lload 182
    putstatic rung36_jcon_scan/icn_202_e1cur J
    lload 184
    putstatic rung36_jcon_scan/icn_202_e1val J
    lload 186
    putstatic rung36_jcon_scan/icn_202_e2val J
    lload 188
    putstatic rung36_jcon_scan/icn_239_I J
    lload 190
    putstatic rung36_jcon_scan/icn_239_bound J
    lload 192
    putstatic rung36_jcon_scan/icn_239_e1cur J
    lload 194
    putstatic rung36_jcon_scan/icn_239_e1val J
    lload 196
    putstatic rung36_jcon_scan/icn_239_e2val J
    lload 198
    putstatic rung36_jcon_scan/icn_319_augtemp J
    getstatic rung36_jcon_scan/icn_failed B
    ifne icn_330_after_call
    getstatic rung36_jcon_scan/icn_retval J
    goto icn_main_s2_sdrain
icn_330_after_call:
    goto icn_329_α
icn_main_s2_sdrain:
    pop2
    goto icn_329_α
icn_331_α:
    goto icn_331_docall
icn_331_β:
    goto icn_330_α
icn_331_docall:
    getstatic rung36_jcon_scan/icn_30_swap_t1 J
    lstore 152
    getstatic rung36_jcon_scan/icn_30_swap_t2 J
    lstore 154
    getstatic rung36_jcon_scan/icn_46_I J
    lstore 156
    getstatic rung36_jcon_scan/icn_46_bound J
    lstore 158
    getstatic rung36_jcon_scan/icn_46_e1cur J
    lstore 160
    getstatic rung36_jcon_scan/icn_46_e1val J
    lstore 162
    getstatic rung36_jcon_scan/icn_46_e2val J
    lstore 164
    getstatic rung36_jcon_scan/icn_66_I J
    lstore 166
    getstatic rung36_jcon_scan/icn_66_bound J
    lstore 168
    getstatic rung36_jcon_scan/icn_66_e1cur J
    lstore 170
    getstatic rung36_jcon_scan/icn_66_e1val J
    lstore 172
    getstatic rung36_jcon_scan/icn_66_e2val J
    lstore 174
    getstatic rung36_jcon_scan/icn_167_augtemp J
    lstore 176
    getstatic rung36_jcon_scan/icn_202_I J
    lstore 178
    getstatic rung36_jcon_scan/icn_202_bound J
    lstore 180
    getstatic rung36_jcon_scan/icn_202_e1cur J
    lstore 182
    getstatic rung36_jcon_scan/icn_202_e1val J
    lstore 184
    getstatic rung36_jcon_scan/icn_202_e2val J
    lstore 186
    getstatic rung36_jcon_scan/icn_239_I J
    lstore 188
    getstatic rung36_jcon_scan/icn_239_bound J
    lstore 190
    getstatic rung36_jcon_scan/icn_239_e1cur J
    lstore 192
    getstatic rung36_jcon_scan/icn_239_e1val J
    lstore 194
    getstatic rung36_jcon_scan/icn_239_e2val J
    lstore 196
    getstatic rung36_jcon_scan/icn_319_augtemp J
    lstore 198
    invokestatic rung36_jcon_scan/icn_p2()V
    lload 152
    putstatic rung36_jcon_scan/icn_30_swap_t1 J
    lload 154
    putstatic rung36_jcon_scan/icn_30_swap_t2 J
    lload 156
    putstatic rung36_jcon_scan/icn_46_I J
    lload 158
    putstatic rung36_jcon_scan/icn_46_bound J
    lload 160
    putstatic rung36_jcon_scan/icn_46_e1cur J
    lload 162
    putstatic rung36_jcon_scan/icn_46_e1val J
    lload 164
    putstatic rung36_jcon_scan/icn_46_e2val J
    lload 166
    putstatic rung36_jcon_scan/icn_66_I J
    lload 168
    putstatic rung36_jcon_scan/icn_66_bound J
    lload 170
    putstatic rung36_jcon_scan/icn_66_e1cur J
    lload 172
    putstatic rung36_jcon_scan/icn_66_e1val J
    lload 174
    putstatic rung36_jcon_scan/icn_66_e2val J
    lload 176
    putstatic rung36_jcon_scan/icn_167_augtemp J
    lload 178
    putstatic rung36_jcon_scan/icn_202_I J
    lload 180
    putstatic rung36_jcon_scan/icn_202_bound J
    lload 182
    putstatic rung36_jcon_scan/icn_202_e1cur J
    lload 184
    putstatic rung36_jcon_scan/icn_202_e1val J
    lload 186
    putstatic rung36_jcon_scan/icn_202_e2val J
    lload 188
    putstatic rung36_jcon_scan/icn_239_I J
    lload 190
    putstatic rung36_jcon_scan/icn_239_bound J
    lload 192
    putstatic rung36_jcon_scan/icn_239_e1cur J
    lload 194
    putstatic rung36_jcon_scan/icn_239_e1val J
    lload 196
    putstatic rung36_jcon_scan/icn_239_e2val J
    lload 198
    putstatic rung36_jcon_scan/icn_319_augtemp J
    getstatic rung36_jcon_scan/icn_failed B
    ifne icn_331_after_call
    getstatic rung36_jcon_scan/icn_retval J
    goto icn_main_s1_sdrain
icn_331_after_call:
    goto icn_330_α
icn_main_s1_sdrain:
    pop2
    goto icn_330_α
icn_332_α:
    goto icn_332_docall
icn_332_β:
    goto icn_331_α
icn_332_docall:
    getstatic rung36_jcon_scan/icn_30_swap_t1 J
    lstore 152
    getstatic rung36_jcon_scan/icn_30_swap_t2 J
    lstore 154
    getstatic rung36_jcon_scan/icn_46_I J
    lstore 156
    getstatic rung36_jcon_scan/icn_46_bound J
    lstore 158
    getstatic rung36_jcon_scan/icn_46_e1cur J
    lstore 160
    getstatic rung36_jcon_scan/icn_46_e1val J
    lstore 162
    getstatic rung36_jcon_scan/icn_46_e2val J
    lstore 164
    getstatic rung36_jcon_scan/icn_66_I J
    lstore 166
    getstatic rung36_jcon_scan/icn_66_bound J
    lstore 168
    getstatic rung36_jcon_scan/icn_66_e1cur J
    lstore 170
    getstatic rung36_jcon_scan/icn_66_e1val J
    lstore 172
    getstatic rung36_jcon_scan/icn_66_e2val J
    lstore 174
    getstatic rung36_jcon_scan/icn_167_augtemp J
    lstore 176
    getstatic rung36_jcon_scan/icn_202_I J
    lstore 178
    getstatic rung36_jcon_scan/icn_202_bound J
    lstore 180
    getstatic rung36_jcon_scan/icn_202_e1cur J
    lstore 182
    getstatic rung36_jcon_scan/icn_202_e1val J
    lstore 184
    getstatic rung36_jcon_scan/icn_202_e2val J
    lstore 186
    getstatic rung36_jcon_scan/icn_239_I J
    lstore 188
    getstatic rung36_jcon_scan/icn_239_bound J
    lstore 190
    getstatic rung36_jcon_scan/icn_239_e1cur J
    lstore 192
    getstatic rung36_jcon_scan/icn_239_e1val J
    lstore 194
    getstatic rung36_jcon_scan/icn_239_e2val J
    lstore 196
    getstatic rung36_jcon_scan/icn_319_augtemp J
    lstore 198
    invokestatic rung36_jcon_scan/icn_p1()V
    lload 152
    putstatic rung36_jcon_scan/icn_30_swap_t1 J
    lload 154
    putstatic rung36_jcon_scan/icn_30_swap_t2 J
    lload 156
    putstatic rung36_jcon_scan/icn_46_I J
    lload 158
    putstatic rung36_jcon_scan/icn_46_bound J
    lload 160
    putstatic rung36_jcon_scan/icn_46_e1cur J
    lload 162
    putstatic rung36_jcon_scan/icn_46_e1val J
    lload 164
    putstatic rung36_jcon_scan/icn_46_e2val J
    lload 166
    putstatic rung36_jcon_scan/icn_66_I J
    lload 168
    putstatic rung36_jcon_scan/icn_66_bound J
    lload 170
    putstatic rung36_jcon_scan/icn_66_e1cur J
    lload 172
    putstatic rung36_jcon_scan/icn_66_e1val J
    lload 174
    putstatic rung36_jcon_scan/icn_66_e2val J
    lload 176
    putstatic rung36_jcon_scan/icn_167_augtemp J
    lload 178
    putstatic rung36_jcon_scan/icn_202_I J
    lload 180
    putstatic rung36_jcon_scan/icn_202_bound J
    lload 182
    putstatic rung36_jcon_scan/icn_202_e1cur J
    lload 184
    putstatic rung36_jcon_scan/icn_202_e1val J
    lload 186
    putstatic rung36_jcon_scan/icn_202_e2val J
    lload 188
    putstatic rung36_jcon_scan/icn_239_I J
    lload 190
    putstatic rung36_jcon_scan/icn_239_bound J
    lload 192
    putstatic rung36_jcon_scan/icn_239_e1cur J
    lload 194
    putstatic rung36_jcon_scan/icn_239_e1val J
    lload 196
    putstatic rung36_jcon_scan/icn_239_e2val J
    lload 198
    putstatic rung36_jcon_scan/icn_319_augtemp J
    getstatic rung36_jcon_scan/icn_failed B
    ifne icn_332_after_call
    getstatic rung36_jcon_scan/icn_retval J
    goto icn_main_s0_sdrain
icn_332_after_call:
    goto icn_331_α
icn_main_s0_sdrain:
    pop2
    goto icn_331_α
icn_main_done:
    return
.end method

; --- record array ---
.class public rung36_jcon_scan$array
.super java/lang/Object

.method public <init>()V
    .limit stack 1
    .limit locals 1
    aload_0
    invokespecial java/lang/Object/<init>()V
    return
.end method

