; Auto-generated by icon_emit_jvm.c — Tiny-ICON Byrd Box JVM
.bytecode 45.0
.class public rung36_jcon_io
.super java/lang/Object

.field public static icn_failed B
.field public static icn_suspended B
.field public static icn_suspend_id I
.field public static icn_retval_obj Ljava/lang/Object;
.field public static icn_retval J
.field public static icn_retval_str Ljava/lang/String;
.field public static icn_arg_str_0 Ljava/lang/String;
.field public static icn_pv_tsys_s Ljava/lang/String;
.field public static icn_pv_rfile_name Ljava/lang/String;
.field public static icn_pv_wfile_name Ljava/lang/String;
.field public static icn_arg_str_1 Ljava/lang/String;
.field public static icn_pv_wfile_mode Ljava/lang/String;
.field public static icn_arg_str_2 Ljava/lang/String;
.field public static icn_pv_wfile_s Ljava/lang/String;
.field public static icn_pv_main_L Ljava/util/ArrayList;
.field public static icn_arg_0 J
.field public static icn_pv_main_t2 J
.field public static icn_pv_main_t1 J
.field public static icn_36_alt_gate I
.field public static icn_36_alt_val J
.field public static icn_gvar_&output J
.field public static icn_58_alt_gate I
.field public static icn_64_alt_gate I
.field public static icn_arg_2 J
.field public static icn_arg_1 J
.field public static icn_121_alt_gate I
.field public static icn_127_alt_gate I
.field public static icn_133_alt_gate I
.field public static icn_139_alt_gate I
.field public static icn_146_alt_gate I
.field public static icn_152_alt_gate I
.field public static icn_158_alt_gate I
.field public static icn_164_alt_gate I
.field public static icn_170_limit_count J
.field public static icn_170_limit_max J
.field public static icn_173_bang_str Ljava/lang/String;
.field public static icn_173_bang_pos I
.field public static icn_gvar_&input J
.field public static icn_170_limit_val Ljava/lang/String;
.field public static icn_177_bang_str Ljava/lang/String;
.field public static icn_177_bang_pos I
.field public static icn_178_limit_count J
.field public static icn_178_limit_max J
.field public static icn_178_limit_val J
.field public static icn_182_bang_str Ljava/lang/String;
.field public static icn_182_bang_pos I
.field public static icn_stdin_reader Ljava/lang/Object;
.field public static icn_stdin_init I
.field public static icn_pv_main_f J
.field public static icn_201_bang_list Ljava/util/ArrayList;
.field public static icn_201_bang_idx I
.field public static icn_204_sort_list Ljava/util/ArrayList;
.field public static icn_207_mklist Ljava/util/ArrayList;
.field public static icn_207_elem_0 Ljava/lang/Object;
.field public static icn_207_elem_1 Ljava/lang/Object;
.field public static icn_207_elem_2 Ljava/lang/Object;
.field public static icn_gvar_&errout J
.field public static icn_207_elem_3 Ljava/lang/Object;
.field public static icn_212_alt_gate I
.field public static icn_212_alt_val J
.field public static icn_pv_main_m J
.field public static icn_207_elem_4 Ljava/lang/Object;
.field public static icn_pv_main_n J
.field public static icn_scan_oldsubj_219 Ljava/lang/String;
.field public static icn_scan_oldpos_219 I
.field public static icn_subject Ljava/lang/String;
.field public static icn_pos I
.field public static icn_pv_wfile_f J
.field public static icn_232_alt_gate I
.field public static icn_upto_cs_234 Ljava/lang/String;
.field public static icn_232_alt_val J
.field public static icn_259_toby_i J
.field public static icn_259_toby_end J
.field public static icn_259_toby_stp J
.field public static icn_pv_rfile_i J
.field public static icn_pv_rfile_f J
.field public static icn_pv_tpipe_p J
.field public static icn_317_alt_gate I
.field public static icn_317_alt_val J
.field public static icn_325_bang_str Ljava/lang/String;
.field public static icn_325_bang_pos I
.field public static icn_331_alt_gate I
.field public static icn_331_alt_val J
.field public static icn_339_I J
.field public static icn_339_bound J
.field public static icn_339_e1cur J
.field public static icn_339_e2seen I
.field public static icn_339_e1val J
.field public static icn_339_e2val J
.field public static icn_346_alt_gate I
.field public static icn_346_alt_val J
.field public static icn_359_alt_gate I
.field public static icn_359_alt_val J

.method static <clinit>()V
    .limit stack 2
    .limit locals 0
    ldc ""
    putstatic rung36_jcon_io/icn_subject Ljava/lang/String;
    iconst_0
    putstatic rung36_jcon_io/icn_pos I
    return
.end method

.method public static main([Ljava/lang/String;)V
    .limit stack 4
    .limit locals 1
    invokestatic rung36_jcon_io/icn_main()V
    return
.end method

.method public static icn_builtin_any(Ljava/lang/String;Ljava/lang/String;I)J
    .limit stack 4
    .limit locals 3
    ; if pos >= subj.length() → return -1
    aload_1
    invokevirtual java/lang/String/length()I
    iload_2
    if_icmpgt icn_any_inbounds
    ldc2_w -1
    lreturn
icn_any_inbounds:
    ; cs.indexOf(subj.charAt(pos)) >= 0?
    aload_0
    aload_1
    iload_2
    invokevirtual java/lang/String/charAt(I)C
    invokevirtual java/lang/String/indexOf(I)I
    ifge icn_any_match
    ldc2_w -1
    lreturn
icn_any_match:
    ; return pos+2 (new 1-based pos after consuming one char)
    iload_2
    iconst_2
    iadd
    i2l
    lreturn
.end method

.method public static icn_builtin_many(Ljava/lang/String;Ljava/lang/String;I)J
    .limit stack 4
    .limit locals 4
    ; check first char in cs — must match at least one
    aload_1
    invokevirtual java/lang/String/length()I
    iload_2
    if_icmpgt icn_many_first_ok
    ldc2_w -1
    lreturn
icn_many_first_ok:
    aload_0
    aload_1
    iload_2
    invokevirtual java/lang/String/charAt(I)C
    invokevirtual java/lang/String/indexOf(I)I
    ifge icn_many_loop_init
    ldc2_w -1
    lreturn
icn_many_loop_init:
    ; local 3 = pos (working)
    iload_2
    istore_3
icn_many_loop:
    iinc 3 1
    ; if pos3 >= length → done
    aload_1
    invokevirtual java/lang/String/length()I
    iload_3
    if_icmpgt icn_many_cont
    iload_3
    i2l
    lconst_1
    ladd
    lreturn
icn_many_cont:
    aload_0
    aload_1
    iload_3
    invokevirtual java/lang/String/charAt(I)C
    invokevirtual java/lang/String/indexOf(I)I
    ifge icn_many_loop
    ; stopped — return pos3+1 (1-based)
    iload_3
    iconst_1
    iadd
    i2l
    lreturn
.end method

.method public static icn_builtin_upto_step(Ljava/lang/String;Ljava/lang/String;I)J
    .limit stack 4
    .limit locals 4
    iload_2
    istore_3
icn_upto_scan:
    ; if pos3 >= length → -1
    aload_1
    invokevirtual java/lang/String/length()I
    iload_3
    if_icmpgt icn_upto_inbounds
    ldc2_w -1
    lreturn
icn_upto_inbounds:
    aload_0
    aload_1
    iload_3
    invokevirtual java/lang/String/charAt(I)C
    invokevirtual java/lang/String/indexOf(I)I
    ifge icn_upto_found
    iinc 3 1
    goto icn_upto_scan
icn_upto_found:
    ; return pos3+1 (1-based); caller sets icn_pos=result for next resume
    iload_3
    iconst_1
    iadd
    i2l
    lreturn
.end method

.method public static icn_builtin_find(Ljava/lang/String;Ljava/lang/String;I)J
    .limit stack 4
    .limit locals 3
    aload_1
    aload_0
    iload_2
    invokevirtual java/lang/String/indexOf(Ljava/lang/String;I)I
    dup
    ifge icn_find_ok
    pop
    ldc2_w -1
    lreturn
icn_find_ok:
    iconst_1
    iadd
    i2l
    lreturn
.end method

.method public static icn_builtin_match(Ljava/lang/String;Ljava/lang/String;I)J
    .limit stack 4
    .limit locals 3
    aload_1
    aload_0
    iload_2
    invokevirtual java/lang/String/startsWith(Ljava/lang/String;I)Z
    ifne icn_match_ok
    ldc2_w -1
    lreturn
icn_match_ok:
    iload_2
    aload_0
    invokevirtual java/lang/String/length()I
    iadd
    iconst_1
    iadd
    i2l
    lreturn
.end method

.method public static icn_builtin_tab_str(ILjava/lang/String;I)Ljava/lang/String;
    .limit stack 4
    .limit locals 4
    ; end = n-1 (0-based)
    iload_0
    iconst_1
    isub
    istore_3
    ; fail if end < pos
    iload_3
    iload_2
    if_icmpge icn_tab_posok
    aconst_null
    areturn
icn_tab_posok:
    ; fail if end > subj.length()
    aload_1
    invokevirtual java/lang/String/length()I
    iload_3
    if_icmpge icn_tab_lenok
    aconst_null
    areturn
icn_tab_lenok:
    ; update icn_pos = end (static field)
    iload_3
    putstatic rung36_jcon_io/icn_pos I
    ; return subj.substring(pos, end)
    aload_1
    iload_2
    iload_3
    invokevirtual java/lang/String/substring(II)Ljava/lang/String;
    areturn
.end method

.method public static icn_builtin_move_str(ILjava/lang/String;I)Ljava/lang/String;
    .limit stack 4
    .limit locals 4
    ; end = pos+n
    iload_2
    iload_0
    iadd
    istore_3
    ; fail if end > subj.length()
    aload_1
    invokevirtual java/lang/String/length()I
    iload_3
    if_icmpge icn_move_ok
    aconst_null
    areturn
icn_move_ok:
    ; update icn_pos = end
    iload_3
    putstatic rung36_jcon_io/icn_pos I
    ; return subj.substring(pos, end)
    aload_1
    iload_2
    iload_3
    invokevirtual java/lang/String/substring(II)Ljava/lang/String;
    areturn
.end method

.method public static icn_builtin_left(Ljava/lang/String;ILjava/lang/String;)Ljava/lang/String;
    .limit stack 4
    .limit locals 5
    aload_0
    invokevirtual java/lang/String/length()I
    iload_1
    if_icmplt icn_left_pad
    aload_0
    iconst_0
    iload_1
    invokevirtual java/lang/String/substring(II)Ljava/lang/String;
    areturn
icn_left_pad:
    new java/lang/StringBuilder
    dup
    aload_0
    invokespecial java/lang/StringBuilder/<init>(Ljava/lang/String;)V
    astore_3
icn_left_loop:
    aload_3
    invokevirtual java/lang/StringBuilder/length()I
    iload_1
    if_icmpge icn_left_done
    aload_3
    aload_2
    iconst_0
    invokevirtual java/lang/String/charAt(I)C
    invokevirtual java/lang/StringBuilder/append(C)Ljava/lang/StringBuilder;
    pop
    goto icn_left_loop
icn_left_done:
    aload_3
    invokevirtual java/lang/StringBuilder/toString()Ljava/lang/String;
    areturn
.end method

.method public static icn_builtin_right(Ljava/lang/String;ILjava/lang/String;)Ljava/lang/String;
    .limit stack 4
    .limit locals 5
    aload_0
    invokevirtual java/lang/String/length()I
    iload_1
    if_icmplt icn_right_pad
    aload_0
    invokevirtual java/lang/String/length()I
    iload_1
    isub
    aload_0
    swap
    invokevirtual java/lang/String/substring(I)Ljava/lang/String;
    areturn
icn_right_pad:
    new java/lang/StringBuilder
    dup
    invokespecial java/lang/StringBuilder/<init>()V
    astore_3
    iload_1
    aload_0
    invokevirtual java/lang/String/length()I
    isub
    istore 4
    iconst_0
icn_right_loop:
    dup
    iload 4
    if_icmpge icn_right_append
    aload_3
    aload_2
    iconst_0
    invokevirtual java/lang/String/charAt(I)C
    invokevirtual java/lang/StringBuilder/append(C)Ljava/lang/StringBuilder;
    pop
    iconst_1
    iadd
    goto icn_right_loop
icn_right_append:
    pop
    aload_3
    aload_0
    invokevirtual java/lang/StringBuilder/append(Ljava/lang/String;)Ljava/lang/StringBuilder;
    pop
    aload_3
    invokevirtual java/lang/StringBuilder/toString()Ljava/lang/String;
    areturn
.end method

.method public static icn_builtin_center(Ljava/lang/String;ILjava/lang/String;)Ljava/lang/String;
    .limit stack 5
    .limit locals 7
    aload_0
    invokevirtual java/lang/String/length()I
    iload_1
    if_icmplt icn_ctr_pad
    aload_0
    iconst_0
    iload_1
    invokevirtual java/lang/String/substring(II)Ljava/lang/String;
    areturn
icn_ctr_pad:
    iload_1
    aload_0
    invokevirtual java/lang/String/length()I
    isub
    istore_3
    iload_3
    iconst_2
    idiv
    istore 4
    iload_3
    iload 4
    isub
    istore 5
    new java/lang/StringBuilder
    dup
    invokespecial java/lang/StringBuilder/<init>()V
    astore 6
    iconst_0
icn_ctr_lloop:
    dup
    iload 4
    if_icmpge icn_ctr_mid
    aload 6
    aload_2
    iconst_0
    invokevirtual java/lang/String/charAt(I)C
    invokevirtual java/lang/StringBuilder/append(C)Ljava/lang/StringBuilder;
    pop
    iconst_1
    iadd
    goto icn_ctr_lloop
icn_ctr_mid:
    pop
    aload 6
    aload_0
    invokevirtual java/lang/StringBuilder/append(Ljava/lang/String;)Ljava/lang/StringBuilder;
    pop
    iconst_0
icn_ctr_rloop:
    dup
    iload 5
    if_icmpge icn_ctr_done
    aload 6
    aload_2
    iconst_0
    invokevirtual java/lang/String/charAt(I)C
    invokevirtual java/lang/StringBuilder/append(C)Ljava/lang/StringBuilder;
    pop
    iconst_1
    iadd
    goto icn_ctr_rloop
icn_ctr_done:
    pop
    aload 6
    invokevirtual java/lang/StringBuilder/toString()Ljava/lang/String;
    areturn
.end method

.method public static icn_builtin_trim(Ljava/lang/String;Ljava/lang/String;)Ljava/lang/String;
    .limit stack 4
    .limit locals 3
    aload_0
    invokevirtual java/lang/String/length()I
    istore_2
icn_trim_loop:
    iload_2
    ifle icn_trim_done
    aload_1
    aload_0
    iload_2
    iconst_1
    isub
    invokevirtual java/lang/String/charAt(I)C
    invokevirtual java/lang/String/indexOf(I)I
    iflt icn_trim_done
    iinc 2 -1
    goto icn_trim_loop
icn_trim_done:
    aload_0
    iconst_0
    iload_2
    invokevirtual java/lang/String/substring(II)Ljava/lang/String;
    areturn
.end method

.method public static icn_builtin_map(Ljava/lang/String;Ljava/lang/String;Ljava/lang/String;)Ljava/lang/String;
    .limit stack 5
    .limit locals 7
    new java/lang/StringBuilder
    dup
    invokespecial java/lang/StringBuilder/<init>()V
    astore_3
    iconst_0
    istore 4
icn_map_loop:
    iload 4
    aload_0
    invokevirtual java/lang/String/length()I
    if_icmpge icn_map_done
    aload_0
    iload 4
    invokevirtual java/lang/String/charAt(I)C
    istore 5
    aload_1
    iload 5
    invokevirtual java/lang/String/indexOf(I)I
    istore 6
    iload 6
    iflt icn_map_notfound
    iload 6
    aload_2
    invokevirtual java/lang/String/length()I
    if_icmpge icn_map_notfound
    aload_3
    aload_2
    iload 6
    invokevirtual java/lang/String/charAt(I)C
    invokevirtual java/lang/StringBuilder/append(C)Ljava/lang/StringBuilder;
    pop
    goto icn_map_next
icn_map_notfound:
    aload_3
    iload 5
    invokevirtual java/lang/StringBuilder/append(C)Ljava/lang/StringBuilder;
    pop
icn_map_next:
    iinc 4 1
    goto icn_map_loop
icn_map_done:
    aload_3
    invokevirtual java/lang/StringBuilder/toString()Ljava/lang/String;
    areturn
.end method

.method public static icn_builtin_parse_long(Ljava/lang/String;)J
    .limit stack 4
    .limit locals 4
    .catch java/lang/Exception from icn_plong_L0 to icn_plong_L1 using icn_plong_catch
icn_plong_L0:
    aload_0
    invokevirtual java/lang/String/trim()Ljava/lang/String;
    astore_1
    aload_1
    ldc "r"
    invokevirtual java/lang/String/contains(Ljava/lang/CharSequence;)Z
    ifeq icn_plong_plain
    aload_1
    ldc "r"
    iconst_2
    invokevirtual java/lang/String/split(Ljava/lang/String;I)[Ljava/lang/String;
    astore_2
    aload_2
    iconst_0
    aaload
    invokestatic java/lang/Integer/parseInt(Ljava/lang/String;)I
    istore_3
    aload_2
    iconst_1
    aaload
    iload_3
    invokestatic java/lang/Long/parseLong(Ljava/lang/String;I)J
    goto icn_plong_L1
icn_plong_plain:
    aload_1
    invokestatic java/lang/Long/parseLong(Ljava/lang/String;)J
icn_plong_L1:
    lreturn
icn_plong_catch:
    pop
    ldc2_w -9223372036854775808
    lreturn
.end method

.method public static icn_builtin_numeric(Ljava/lang/String;)J
    .limit stack 2
    .limit locals 2
    aload_0
    invokestatic rung36_jcon_io/icn_builtin_parse_long(Ljava/lang/String;)J
    lreturn
.end method

.method public static icn_builtin_sort(Ljava/util/ArrayList;)Ljava/util/ArrayList;
    .limit stack 6
    .limit locals 8
    new java/util/ArrayList
    dup
    aload_0
    invokespecial java/util/ArrayList/<init>(Ljava/util/Collection;)V
    astore_1
    iconst_1
    istore_2
icn_sort_outer:
    aload_1
    invokevirtual java/util/ArrayList/size()I
    iload_2
    if_icmple icn_sort_done
    aload_1
    iload_2
    invokevirtual java/util/ArrayList/get(I)Ljava/lang/Object;
    checkcast java/lang/Long
    invokevirtual java/lang/Long/longValue()J
    lstore 4
    iload_2
    iconst_1
    isub
    istore_3
icn_sort_inner:
    iload_3
    iflt icn_sort_insert
    aload_1
    iload_3
    invokevirtual java/util/ArrayList/get(I)Ljava/lang/Object;
    checkcast java/lang/Long
    invokevirtual java/lang/Long/longValue()J
    lload 4
    lcmp
    ifle icn_sort_insert
    aload_1
    iload_3
    iconst_1
    iadd
    aload_1
    iload_3
    invokevirtual java/util/ArrayList/get(I)Ljava/lang/Object;
    invokevirtual java/util/ArrayList/set(ILjava/lang/Object;)Ljava/lang/Object;
    pop
    iinc 3 -1
    goto icn_sort_inner
icn_sort_insert:
    aload_1
    iload_3
    iconst_1
    iadd
    lload 4
    invokestatic java/lang/Long/valueOf(J)Ljava/lang/Long;
    invokevirtual java/util/ArrayList/set(ILjava/lang/Object;)Ljava/lang/Object;
    pop
    iinc 2 1
    goto icn_sort_outer
icn_sort_done:
    aload_1
    areturn
.end method

.method public static icn_builtin_sortf(Ljava/util/ArrayList;I)Ljava/util/ArrayList;
    .limit stack 8
    .limit locals 10
    new java/util/ArrayList
    dup
    aload_0
    invokespecial java/util/ArrayList/<init>(Ljava/util/Collection;)V
    astore_2
    iconst_1
    istore_3
icn_sortf_outer:
    aload_2
    invokevirtual java/util/ArrayList/size()I
    iload_3
    if_icmple icn_sortf_done
    aload_2
    iload_3
    invokevirtual java/util/ArrayList/get(I)Ljava/lang/Object;
    astore 5
    iload_3
    iconst_1
    isub
    istore 4
icn_sortf_inner:
    iload 4
    iflt icn_sortf_insert
    aload_2
    iload 4
    invokevirtual java/util/ArrayList/get(I)Ljava/lang/Object;
    astore 6
    aload 6
    invokevirtual java/lang/Object/getClass()Ljava/lang/Class;
    invokevirtual java/lang/Class/getDeclaredFields()[Ljava/lang/reflect/Field;
    iload_1
    iconst_1
    isub
    aaload
    aload 6
    invokevirtual java/lang/reflect/Field/get(Ljava/lang/Object;)Ljava/lang/Object;
    astore 7
    aload 5
    invokevirtual java/lang/Object/getClass()Ljava/lang/Class;
    invokevirtual java/lang/Class/getDeclaredFields()[Ljava/lang/reflect/Field;
    iload_1
    iconst_1
    isub
    aaload
    aload 5
    invokevirtual java/lang/reflect/Field/get(Ljava/lang/Object;)Ljava/lang/Object;
    astore 8
    aload 7
    checkcast java/lang/Long
    aload 8
    checkcast java/lang/Long
    invokevirtual java/lang/Long/compareTo(Ljava/lang/Long;)I
    ifle icn_sortf_insert
    aload_2
    iload 4
    iconst_1
    iadd
    aload_2
    iload 4
    invokevirtual java/util/ArrayList/get(I)Ljava/lang/Object;
    invokevirtual java/util/ArrayList/set(ILjava/lang/Object;)Ljava/lang/Object;
    pop
    iinc 4 -1
    goto icn_sortf_inner
icn_sortf_insert:
    aload_2
    iload 4
    iconst_1
    iadd
    aload 5
    invokevirtual java/util/ArrayList/set(ILjava/lang/Object;)Ljava/lang/Object;
    pop
    iinc 3 1
    goto icn_sortf_outer
icn_sortf_done:
    aload_2
    areturn
.end method

.method public static icn_main()V
    .limit stack 16
    .limit locals 333
    lconst_0
    lstore 0
    lconst_0
    lstore 2
    lconst_0
    lstore 4
    lconst_0
    lstore 6
    lconst_0
    lstore 8
    lconst_0
    lstore 10
    lconst_0
    lstore 12
    lconst_0
    lstore 14
    lconst_0
    lstore 16
    lconst_0
    lstore 18
    lconst_0
    lstore 20
    lconst_0
    lstore 22
    lconst_0
    lstore 24
    lconst_0
    lstore 26
    lconst_0
    lstore 28
    lconst_0
    lstore 30
    lconst_0
    lstore 32
    lconst_0
    lstore 34
    lconst_0
    lstore 36
    lconst_0
    lstore 38
    lconst_0
    lstore 40
    lconst_0
    lstore 42
    lconst_0
    lstore 44
    lconst_0
    lstore 46
    lconst_0
    lstore 48
    lconst_0
    lstore 50
    lconst_0
    lstore 52
    lconst_0
    lstore 54
    lconst_0
    lstore 56
    lconst_0
    lstore 58
    lconst_0
    lstore 60
    lconst_0
    lstore 62
    iconst_0
    istore 84
    iconst_0
    istore 85
    iconst_0
    istore 86
    iconst_0
    istore 87
    aconst_null
    astore 148
    aconst_null
    astore 149
    aconst_null
    astore 150
    aconst_null
    astore 151
    aconst_null
    astore 152
    aconst_null
    astore 153
    aconst_null
    astore 154
    aconst_null
    astore 155
    aconst_null
    astore 156
    aconst_null
    astore 157
    aconst_null
    astore 158
    aconst_null
    astore 159
    aconst_null
    astore 160
    aconst_null
    astore 161
    aconst_null
    astore 162
    aconst_null
    astore 163
    aconst_null
    astore 164
    aconst_null
    astore 165
    aconst_null
    astore 166
    aconst_null
    astore 167
    aconst_null
    astore 168
    aconst_null
    astore 169
    aconst_null
    astore 170
    aconst_null
    astore 171
    aconst_null
    astore 172
    aconst_null
    astore 173
    aconst_null
    astore 174
    aconst_null
    astore 175
    aconst_null
    astore 176
    aconst_null
    astore 177
    aconst_null
    astore 178
    aconst_null
    astore 179
    aconst_null
    astore 180
    aconst_null
    astore 181
    aconst_null
    astore 182
    aconst_null
    astore 183
    aconst_null
    astore 184
    aconst_null
    astore 185
    aconst_null
    astore 186
    aconst_null
    astore 187
    aconst_null
    astore 188
    aconst_null
    astore 189
    aconst_null
    astore 190
    aconst_null
    astore 191
    aconst_null
    astore 192
    aconst_null
    astore 193
    aconst_null
    astore 194
    aconst_null
    astore 195
    aconst_null
    astore 196
    aconst_null
    astore 197
    aconst_null
    astore 198
    aconst_null
    astore 199
    aconst_null
    astore 200
    aconst_null
    astore 201
    aconst_null
    astore 202
    aconst_null
    astore 203
    aconst_null
    astore 204
    aconst_null
    astore 205
    aconst_null
    astore 206
    aconst_null
    astore 207
    aconst_null
    astore 208
    goto icn_206_α
icn_0_α:
    goto icn_0_docall
icn_0_β:
    goto icn_main_done
icn_0_docall:
    invokestatic rung36_jcon_io/icn_tpipe()V
    getstatic rung36_jcon_io/icn_failed B
    ifne icn_0_after_call
    getstatic rung36_jcon_io/icn_retval J
    goto icn_main_s69_sdrain
icn_0_after_call:
    goto icn_main_done
icn_main_s69_sdrain:
    pop2
    goto icn_main_done
;  STR
icn_2_α:
    ldc "ls io.[ids][tca][dnt]"
    goto icn_1_arg0
icn_2_β:
    goto icn_0_α
icn_1_arg0:
    putstatic rung36_jcon_io/icn_arg_str_0 Ljava/lang/String;
    lconst_0
    putstatic rung36_jcon_io/icn_arg_0 J
    goto icn_1_docall
icn_1_α:
    goto icn_2_α
icn_1_β:
    goto icn_2_β
icn_1_docall:
    invokestatic rung36_jcon_io/icn_tsys()V
    getstatic rung36_jcon_io/icn_failed B
    ifne icn_1_after_call
    getstatic rung36_jcon_io/icn_retval J
    goto icn_main_s68_sdrain
icn_1_after_call:
    goto icn_0_α
icn_main_s68_sdrain:
    pop2
    goto icn_0_α
;  STR
icn_4_α:
    ldc "echo hello world"
    goto icn_3_arg0
icn_4_β:
    goto icn_1_α
icn_3_arg0:
    putstatic rung36_jcon_io/icn_arg_str_0 Ljava/lang/String;
    lconst_0
    putstatic rung36_jcon_io/icn_arg_0 J
    goto icn_3_docall
icn_3_α:
    goto icn_4_α
icn_3_β:
    goto icn_4_β
icn_3_docall:
    invokestatic rung36_jcon_io/icn_tsys()V
    getstatic rung36_jcon_io/icn_failed B
    ifne icn_3_after_call
    getstatic rung36_jcon_io/icn_retval J
    goto icn_main_s67_sdrain
icn_3_after_call:
    goto icn_1_α
icn_main_s67_sdrain:
    pop2
    goto icn_1_α
icn_5_α:
    getstatic java/lang/System/out Ljava/io/PrintStream;
    ldc ""
    invokevirtual java/io/PrintStream/println(Ljava/lang/String;)V
    goto icn_main_s66_sdrain
icn_5_β:
    goto icn_3_α
icn_main_s66_sdrain:
    pop2
    goto icn_3_α
icn_6_α:
    goto icn_5_α
icn_6_β:
    goto icn_5_α
icn_main_s65_sdrain:
    pop2
    goto icn_5_α
icn_7_α:
    goto icn_6_α
icn_7_β:
    goto icn_6_α
icn_main_s64_sdrain:
    pop2
    goto icn_6_α
icn_8_α:
    goto icn_7_α
icn_8_β:
    goto icn_7_α
icn_main_s63_sdrain:
    pop2
    goto icn_7_α
icn_9_α:
    goto icn_8_α
icn_9_β:
    goto icn_8_α
icn_main_s62_sdrain:
    pop2
    goto icn_8_α
;  STR
icn_11_α:
    ldc "pqr\nstu"
    goto icn_10_waft_0
icn_11_β:
    goto icn_9_α
icn_10_α:
    goto icn_11_α
icn_10_β:
    goto icn_11_β
    goto icn_10_wentry
icn_10_waft_0:
    astore 148
    getstatic java/lang/System/out Ljava/io/PrintStream;
    aload 148
    invokevirtual java/io/PrintStream/print(Ljava/lang/String;)V
    getstatic java/lang/System/out Ljava/io/PrintStream;
    ldc ""
    invokevirtual java/io/PrintStream/println(Ljava/lang/String;)V
    aload 148
    goto icn_main_s61_sdrain
icn_10_wentry:
    goto icn_11_α
icn_main_s61_sdrain:
    pop
    goto icn_9_α
icn_12_α:
    goto icn_10_α
icn_12_β:
    goto icn_10_α
icn_main_s60_sdrain:
    pop2
    goto icn_10_α
icn_13_α:
    goto icn_12_α
icn_13_β:
    goto icn_12_α
icn_main_s59_sdrain:
    pop2
    goto icn_12_α
icn_14_α:
    goto icn_13_α
icn_14_β:
    goto icn_13_α
icn_main_s58_sdrain:
    pop2
    goto icn_13_α
icn_15_α:
    getstatic java/lang/System/out Ljava/io/PrintStream;
    ldc ""
    invokevirtual java/io/PrintStream/println(Ljava/lang/String;)V
    goto icn_main_s57_sdrain
icn_15_β:
    goto icn_14_α
icn_main_s57_sdrain:
    pop2
    goto icn_14_α
icn_17_α:
    goto icn_15_α
icn_17_β:
    goto icn_15_α
icn_16_gdrain:
    pop2
icn_16_pump:
    goto icn_17_β
icn_16_α:
    goto icn_17_α
icn_16_β:
    goto icn_15_α
icn_19_α:
    goto icn_16_α
icn_19_β:
    goto icn_16_α
icn_18_gdrain:
    pop2
icn_18_pump:
    goto icn_19_β
icn_18_α:
    goto icn_19_α
icn_18_β:
    goto icn_16_α
;  STR
icn_21_α:
    ldc "tmp2"
    goto icn_20_arg0
icn_21_β:
    goto icn_18_α
icn_20_arg0:
    putstatic rung36_jcon_io/icn_arg_str_0 Ljava/lang/String;
    lconst_0
    putstatic rung36_jcon_io/icn_arg_0 J
    goto icn_20_docall
icn_20_α:
    goto icn_21_α
icn_20_β:
    goto icn_21_β
icn_20_docall:
    invokestatic rung36_jcon_io/icn_rfile()V
    getstatic rung36_jcon_io/icn_failed B
    ifne icn_20_after_call
    getstatic rung36_jcon_io/icn_retval J
    goto icn_main_s54_sdrain
icn_20_after_call:
    goto icn_18_α
icn_main_s54_sdrain:
    pop2
    goto icn_18_α
;  STR
icn_23_α:
    ldc "tmp1"
    goto icn_22_arg0
icn_23_β:
    goto icn_20_α
icn_22_arg0:
    putstatic rung36_jcon_io/icn_arg_str_0 Ljava/lang/String;
    lconst_0
    putstatic rung36_jcon_io/icn_arg_0 J
    goto icn_22_docall
icn_22_α:
    goto icn_23_α
icn_22_β:
    goto icn_23_β
icn_22_docall:
    invokestatic rung36_jcon_io/icn_rfile()V
    getstatic rung36_jcon_io/icn_failed B
    ifne icn_22_after_call
    getstatic rung36_jcon_io/icn_retval J
    goto icn_main_s53_sdrain
icn_22_after_call:
    goto icn_20_α
icn_main_s53_sdrain:
    pop2
    goto icn_20_α
icn_25_α:
    goto icn_22_α
icn_25_β:
    goto icn_22_α
icn_24_gdrain:
    pop2
icn_24_pump:
    goto icn_25_β
icn_24_α:
    goto icn_25_α
icn_24_β:
    goto icn_22_α
;  VAR
icn_27_α:
    getstatic rung36_jcon_io/icn_pv_main_t2 J
    goto icn_26_waft_0
icn_27_β:
    goto icn_24_α
;  STR
icn_28_α:
    ldc ">2f"
    goto icn_26_waft_1
icn_28_β:
    goto icn_24_α
icn_26_α:
    goto icn_27_α
icn_26_β:
    goto icn_27_β
    goto icn_26_wentry
icn_26_waft_0:
    lstore 12
    getstatic java/lang/System/out Ljava/io/PrintStream;
    lload 12
    invokevirtual java/io/PrintStream/print(J)V
    goto icn_28_α
icn_26_waft_1:
    astore 149
    getstatic java/lang/System/out Ljava/io/PrintStream;
    aload 149
    invokevirtual java/io/PrintStream/print(Ljava/lang/String;)V
    getstatic java/lang/System/out Ljava/io/PrintStream;
    ldc ""
    invokevirtual java/io/PrintStream/println(Ljava/lang/String;)V
    aload 149
    goto icn_main_s51_sdrain
icn_26_wentry:
    goto icn_27_α
icn_main_s51_sdrain:
    pop
    goto icn_24_α
;  VAR
icn_30_α:
    getstatic rung36_jcon_io/icn_pv_main_t1 J
    goto icn_29_waft_0
icn_30_β:
    goto icn_26_α
;  STR
icn_31_α:
    ldc ">1f"
    goto icn_29_waft_1
icn_31_β:
    goto icn_26_α
icn_29_α:
    goto icn_30_α
icn_29_β:
    goto icn_30_β
    goto icn_29_wentry
icn_29_waft_0:
    lstore 14
    getstatic java/lang/System/out Ljava/io/PrintStream;
    lload 14
    invokevirtual java/io/PrintStream/print(J)V
    goto icn_31_α
icn_29_waft_1:
    astore 150
    getstatic java/lang/System/out Ljava/io/PrintStream;
    aload 150
    invokevirtual java/io/PrintStream/print(Ljava/lang/String;)V
    getstatic java/lang/System/out Ljava/io/PrintStream;
    ldc ""
    invokevirtual java/io/PrintStream/println(Ljava/lang/String;)V
    aload 150
    goto icn_main_s50_sdrain
icn_29_wentry:
    goto icn_30_α
icn_main_s50_sdrain:
    pop
    goto icn_26_α
icn_32_α:
    goto icn_29_α
icn_32_β:
    goto icn_29_α
icn_main_s49_sdrain:
    pop2
    goto icn_29_α
icn_33_α:
    goto icn_32_α
icn_33_β:
    goto icn_32_α
icn_main_s48_sdrain:
    pop2
    goto icn_32_α
;  VAR
icn_37_α:
    getstatic rung36_jcon_io/icn_pv_main_t2 J
    goto icn_36_alt_g1
icn_37_β:
    goto icn_33_α
;  VAR
icn_38_α:
    getstatic rung36_jcon_io/icn_pv_main_t1 J
    goto icn_36_alt_g0
icn_38_β:
    goto icn_37_α
icn_36_alt_g0:
    putstatic rung36_jcon_io/icn_36_alt_val J
    sipush 1
    putstatic rung36_jcon_io/icn_36_alt_gate I
    getstatic rung36_jcon_io/icn_36_alt_val J
    goto icn_35_waft_0
icn_36_alt_g1:
    putstatic rung36_jcon_io/icn_36_alt_val J
    sipush 2
    putstatic rung36_jcon_io/icn_36_alt_gate I
    getstatic rung36_jcon_io/icn_36_alt_val J
    goto icn_35_waft_0
icn_36_α:
    iconst_0
    putstatic rung36_jcon_io/icn_36_alt_gate I
    goto icn_38_α
icn_36_β:
    getstatic rung36_jcon_io/icn_36_alt_gate I
    tableswitch 1 2
        icn_38_β
        icn_37_β
        default: icn_33_α
icn_35_α:
    goto icn_36_α
icn_35_β:
    goto icn_36_β
    goto icn_35_wentry
icn_35_waft_0:
    lstore 16
    getstatic java/lang/System/out Ljava/io/PrintStream;
    lload 16
    invokevirtual java/io/PrintStream/print(J)V
    getstatic java/lang/System/out Ljava/io/PrintStream;
    ldc ""
    invokevirtual java/io/PrintStream/println(Ljava/lang/String;)V
    lload 16
    goto icn_34_gdrain
icn_35_wentry:
    goto icn_36_α
icn_34_gdrain:
    pop2
icn_34_pump:
    goto icn_35_β
icn_34_α:
    goto icn_35_α
icn_34_β:
    goto icn_33_α
;  STR
icn_40_α:
    ldc ">stdout"
    goto icn_39_waft_0
icn_40_β:
    goto icn_34_α
;  VAR
icn_41_α:
    getstatic rung36_jcon_io/icn_pv_main_t2 J
    goto icn_39_waft_1
icn_41_β:
    goto icn_34_α
;  STR
icn_42_α:
    ldc ">2d"
    goto icn_39_waft_2
icn_42_β:
    goto icn_34_α
;  VAR
icn_43_α:
    getstatic rung36_jcon_io/icn_pv_main_t1 J
    goto icn_39_waft_3
icn_43_β:
    goto icn_34_α
;  VAR
icn_44_α:
    getstatic rung36_jcon_io/icn_pv_main_t1 J
    goto icn_39_waft_4
icn_44_β:
    goto icn_34_α
;  STR
icn_45_α:
    ldc ">1d"
    goto icn_39_waft_5
icn_45_β:
    goto icn_34_α
;  VAR
icn_46_α:
    getstatic rung36_jcon_io/icn_gvar_&output J
    goto icn_39_waft_6
icn_46_β:
    goto icn_34_α
icn_39_α:
    goto icn_40_α
icn_39_β:
    goto icn_40_β
    goto icn_39_wentry
icn_39_waft_0:
    astore 151
    getstatic java/lang/System/out Ljava/io/PrintStream;
    aload 151
    invokevirtual java/io/PrintStream/print(Ljava/lang/String;)V
    goto icn_41_α
icn_39_waft_1:
    lstore 18
    getstatic java/lang/System/out Ljava/io/PrintStream;
    lload 18
    invokevirtual java/io/PrintStream/print(J)V
    goto icn_42_α
icn_39_waft_2:
    astore 152
    getstatic java/lang/System/out Ljava/io/PrintStream;
    aload 152
    invokevirtual java/io/PrintStream/print(Ljava/lang/String;)V
    goto icn_43_α
icn_39_waft_3:
    lstore 20
    getstatic java/lang/System/out Ljava/io/PrintStream;
    lload 20
    invokevirtual java/io/PrintStream/print(J)V
    goto icn_44_α
icn_39_waft_4:
    lstore 22
    getstatic java/lang/System/out Ljava/io/PrintStream;
    lload 22
    invokevirtual java/io/PrintStream/print(J)V
    goto icn_45_α
icn_39_waft_5:
    astore 153
    getstatic java/lang/System/out Ljava/io/PrintStream;
    aload 153
    invokevirtual java/io/PrintStream/print(Ljava/lang/String;)V
    goto icn_46_α
icn_39_waft_6:
    lstore 24
    getstatic java/lang/System/out Ljava/io/PrintStream;
    lload 24
    invokevirtual java/io/PrintStream/print(J)V
    getstatic java/lang/System/out Ljava/io/PrintStream;
    ldc ""
    invokevirtual java/io/PrintStream/println(Ljava/lang/String;)V
    lload 24
    goto icn_main_s46_sdrain
icn_39_wentry:
    goto icn_40_α
icn_main_s46_sdrain:
    pop2
    goto icn_34_α
;  STR
icn_48_α:
    ldc ">stdout"
    goto icn_47_waft_0
icn_48_β:
    goto icn_39_α
;  VAR
icn_49_α:
    getstatic rung36_jcon_io/icn_pv_main_t1 J
    goto icn_47_waft_1
icn_49_β:
    goto icn_39_α
;  STR
icn_50_α:
    ldc ">1c"
    goto icn_47_waft_2
icn_50_β:
    goto icn_39_α
;  VAR
icn_51_α:
    getstatic rung36_jcon_io/icn_pv_main_t2 J
    goto icn_47_waft_3
icn_51_β:
    goto icn_39_α
;  VAR
icn_52_α:
    getstatic rung36_jcon_io/icn_pv_main_t2 J
    goto icn_47_waft_4
icn_52_β:
    goto icn_39_α
;  STR
icn_53_α:
    ldc ">2c"
    goto icn_47_waft_5
icn_53_β:
    goto icn_39_α
;  VAR
icn_54_α:
    getstatic rung36_jcon_io/icn_gvar_&output J
    goto icn_47_waft_6
icn_54_β:
    goto icn_39_α
icn_47_α:
    goto icn_48_α
icn_47_β:
    goto icn_48_β
    goto icn_47_wentry
icn_47_waft_0:
    astore 154
    getstatic java/lang/System/out Ljava/io/PrintStream;
    aload 154
    invokevirtual java/io/PrintStream/print(Ljava/lang/String;)V
    goto icn_49_α
icn_47_waft_1:
    lstore 26
    getstatic java/lang/System/out Ljava/io/PrintStream;
    lload 26
    invokevirtual java/io/PrintStream/print(J)V
    goto icn_50_α
icn_47_waft_2:
    astore 155
    getstatic java/lang/System/out Ljava/io/PrintStream;
    aload 155
    invokevirtual java/io/PrintStream/print(Ljava/lang/String;)V
    goto icn_51_α
icn_47_waft_3:
    lstore 28
    getstatic java/lang/System/out Ljava/io/PrintStream;
    lload 28
    invokevirtual java/io/PrintStream/print(J)V
    goto icn_52_α
icn_47_waft_4:
    lstore 30
    getstatic java/lang/System/out Ljava/io/PrintStream;
    lload 30
    invokevirtual java/io/PrintStream/print(J)V
    goto icn_53_α
icn_47_waft_5:
    astore 156
    getstatic java/lang/System/out Ljava/io/PrintStream;
    aload 156
    invokevirtual java/io/PrintStream/print(Ljava/lang/String;)V
    goto icn_54_α
icn_47_waft_6:
    lstore 32
    getstatic java/lang/System/out Ljava/io/PrintStream;
    lload 32
    invokevirtual java/io/PrintStream/print(J)V
    getstatic java/lang/System/out Ljava/io/PrintStream;
    ldc ""
    invokevirtual java/io/PrintStream/println(Ljava/lang/String;)V
    lload 32
    goto icn_main_s45_sdrain
icn_47_wentry:
    goto icn_48_α
icn_main_s45_sdrain:
    pop2
    goto icn_39_α
icn_55_α:
    goto icn_47_α
icn_55_β:
    goto icn_47_α
icn_main_s44_sdrain:
    pop2
    goto icn_47_α
icn_56_α:
    goto icn_55_α
icn_56_β:
    goto icn_55_α
icn_main_s43_sdrain:
    pop2
    goto icn_55_α
;  STR
icn_59_α:
    ldc "can't open tmp2"
    goto icn_58_alt_g1
icn_59_β:
    goto icn_56_α
icn_62_α:
    goto icn_59_α
icn_62_β:
    goto icn_59_α
icn_61_α:
    goto icn_62_α
icn_61_β:
    goto icn_62_β
icn_61_store:
    putstatic rung36_jcon_io/icn_pv_main_t2 J
    getstatic rung36_jcon_io/icn_pv_main_t2 J
    goto icn_60_image_after
icn_60_α:
    goto icn_61_α
icn_60_β:
    goto icn_61_β
icn_60_image_after:
    invokestatic java/lang/Long/toString(J)Ljava/lang/String;
    goto icn_58_alt_g0
icn_58_alt_g0:
    astore 157
    sipush 1
    putstatic rung36_jcon_io/icn_58_alt_gate I
    aload 157
    goto icn_57_waft_0
icn_58_alt_g1:
    astore 158
    sipush 2
    putstatic rung36_jcon_io/icn_58_alt_gate I
    aload 158
    goto icn_57_waft_0
icn_58_α:
    iconst_0
    putstatic rung36_jcon_io/icn_58_alt_gate I
    goto icn_60_α
icn_58_β:
    getstatic rung36_jcon_io/icn_58_alt_gate I
    tableswitch 1 2
        icn_60_β
        icn_59_β
        default: icn_56_α
icn_57_α:
    goto icn_58_α
icn_57_β:
    goto icn_58_β
    goto icn_57_wentry
icn_57_waft_0:
    astore 159
    getstatic java/lang/System/out Ljava/io/PrintStream;
    aload 159
    invokevirtual java/io/PrintStream/print(Ljava/lang/String;)V
    getstatic java/lang/System/out Ljava/io/PrintStream;
    ldc ""
    invokevirtual java/io/PrintStream/println(Ljava/lang/String;)V
    aload 159
    goto icn_main_s42_sdrain
icn_57_wentry:
    goto icn_58_α
icn_main_s42_sdrain:
    pop
    goto icn_56_α
;  STR
icn_65_α:
    ldc "can't open tmp1"
    goto icn_64_alt_g1
icn_65_β:
    goto icn_57_α
icn_68_α:
    goto icn_65_α
icn_68_β:
    goto icn_65_α
icn_67_α:
    goto icn_68_α
icn_67_β:
    goto icn_68_β
icn_67_store:
    putstatic rung36_jcon_io/icn_pv_main_t1 J
    getstatic rung36_jcon_io/icn_pv_main_t1 J
    goto icn_66_image_after
icn_66_α:
    goto icn_67_α
icn_66_β:
    goto icn_67_β
icn_66_image_after:
    invokestatic java/lang/Long/toString(J)Ljava/lang/String;
    goto icn_64_alt_g0
icn_64_alt_g0:
    astore 160
    sipush 1
    putstatic rung36_jcon_io/icn_64_alt_gate I
    aload 160
    goto icn_63_waft_0
icn_64_alt_g1:
    astore 161
    sipush 2
    putstatic rung36_jcon_io/icn_64_alt_gate I
    aload 161
    goto icn_63_waft_0
icn_64_α:
    iconst_0
    putstatic rung36_jcon_io/icn_64_alt_gate I
    goto icn_66_α
icn_64_β:
    getstatic rung36_jcon_io/icn_64_alt_gate I
    tableswitch 1 2
        icn_66_β
        icn_65_β
        default: icn_57_α
icn_63_α:
    goto icn_64_α
icn_63_β:
    goto icn_64_β
    goto icn_63_wentry
icn_63_waft_0:
    astore 162
    getstatic java/lang/System/out Ljava/io/PrintStream;
    aload 162
    invokevirtual java/io/PrintStream/print(Ljava/lang/String;)V
    getstatic java/lang/System/out Ljava/io/PrintStream;
    ldc ""
    invokevirtual java/io/PrintStream/println(Ljava/lang/String;)V
    aload 162
    goto icn_main_s41_sdrain
icn_63_wentry:
    goto icn_64_α
icn_main_s41_sdrain:
    pop
    goto icn_57_α
icn_69_α:
    getstatic java/lang/System/out Ljava/io/PrintStream;
    ldc ""
    invokevirtual java/io/PrintStream/println(Ljava/lang/String;)V
    goto icn_main_s40_sdrain
icn_69_β:
    goto icn_63_α
icn_main_s40_sdrain:
    pop2
    goto icn_63_α
;  STR
icn_71_α:
    ldc "tmp2"
    goto icn_70_arg0
icn_71_β:
    goto icn_69_α
icn_70_arg0:
    putstatic rung36_jcon_io/icn_arg_str_0 Ljava/lang/String;
    lconst_0
    putstatic rung36_jcon_io/icn_arg_0 J
    goto icn_70_docall
icn_70_α:
    goto icn_71_α
icn_70_β:
    goto icn_71_β
icn_70_docall:
    getstatic rung36_jcon_io/icn_pv_main_t2 J
    lstore 167
    getstatic rung36_jcon_io/icn_pv_main_t1 J
    lstore 169
    getstatic rung36_jcon_io/icn_36_alt_val J
    lstore 171
    invokestatic rung36_jcon_io/icn_rfile()V
    lload 167
    putstatic rung36_jcon_io/icn_pv_main_t2 J
    lload 169
    putstatic rung36_jcon_io/icn_pv_main_t1 J
    lload 171
    putstatic rung36_jcon_io/icn_36_alt_val J
    getstatic rung36_jcon_io/icn_failed B
    ifne icn_70_after_call
    getstatic rung36_jcon_io/icn_retval J
    goto icn_main_s39_sdrain
icn_70_after_call:
    goto icn_69_α
icn_main_s39_sdrain:
    pop2
    goto icn_69_α
icn_72_α:
    goto icn_70_α
icn_72_β:
    goto icn_70_α
icn_main_s38_sdrain:
    pop2
    goto icn_70_α
;  STR
icn_74_α:
    ldc "tmp1"
    goto icn_73_arg0
icn_74_β:
    goto icn_72_α
icn_73_arg0:
    putstatic rung36_jcon_io/icn_arg_str_0 Ljava/lang/String;
    lconst_0
    putstatic rung36_jcon_io/icn_arg_0 J
    goto icn_73_docall
icn_73_α:
    goto icn_74_α
icn_73_β:
    goto icn_74_β
icn_73_docall:
    getstatic rung36_jcon_io/icn_pv_main_t2 J
    lstore 167
    getstatic rung36_jcon_io/icn_pv_main_t1 J
    lstore 169
    getstatic rung36_jcon_io/icn_36_alt_val J
    lstore 171
    invokestatic rung36_jcon_io/icn_rfile()V
    lload 167
    putstatic rung36_jcon_io/icn_pv_main_t2 J
    lload 169
    putstatic rung36_jcon_io/icn_pv_main_t1 J
    lload 171
    putstatic rung36_jcon_io/icn_36_alt_val J
    getstatic rung36_jcon_io/icn_failed B
    ifne icn_73_after_call
    getstatic rung36_jcon_io/icn_retval J
    goto icn_main_s37_sdrain
icn_73_after_call:
    goto icn_72_α
icn_main_s37_sdrain:
    pop2
    goto icn_72_α
;  STR
icn_76_α:
    ldc "cleared anew"
    goto icn_75_arg2
icn_76_β:
    goto icn_73_α
icn_75_arg2:
    putstatic rung36_jcon_io/icn_arg_str_2 Ljava/lang/String;
    lconst_0
    putstatic rung36_jcon_io/icn_arg_2 J
    goto icn_75_docall
;  STR
icn_77_α:
    ldc "crw"
    goto icn_75_arg1
icn_77_β:
    goto icn_73_α
icn_75_arg1:
    putstatic rung36_jcon_io/icn_arg_str_1 Ljava/lang/String;
    lconst_0
    putstatic rung36_jcon_io/icn_arg_1 J
    goto icn_76_α
;  STR
icn_78_α:
    ldc "tmp1"
    goto icn_75_arg0
icn_78_β:
    goto icn_73_α
icn_75_arg0:
    putstatic rung36_jcon_io/icn_arg_str_0 Ljava/lang/String;
    lconst_0
    putstatic rung36_jcon_io/icn_arg_0 J
    goto icn_77_α
icn_75_α:
    goto icn_78_α
icn_75_β:
    goto icn_76_β
icn_75_docall:
    getstatic rung36_jcon_io/icn_pv_main_t2 J
    lstore 167
    getstatic rung36_jcon_io/icn_pv_main_t1 J
    lstore 169
    getstatic rung36_jcon_io/icn_36_alt_val J
    lstore 171
    invokestatic rung36_jcon_io/icn_wfile()V
    lload 167
    putstatic rung36_jcon_io/icn_pv_main_t2 J
    lload 169
    putstatic rung36_jcon_io/icn_pv_main_t1 J
    lload 171
    putstatic rung36_jcon_io/icn_36_alt_val J
    getstatic rung36_jcon_io/icn_failed B
    ifne icn_75_after_call
    getstatic rung36_jcon_io/icn_retval J
    goto icn_main_s36_sdrain
icn_75_after_call:
    goto icn_73_α
icn_main_s36_sdrain:
    pop2
    goto icn_73_α
;  STR
icn_80_α:
    ldc "tmp1"
    goto icn_79_arg0
icn_80_β:
    goto icn_75_α
icn_79_arg0:
    putstatic rung36_jcon_io/icn_arg_str_0 Ljava/lang/String;
    lconst_0
    putstatic rung36_jcon_io/icn_arg_0 J
    goto icn_79_docall
icn_79_α:
    goto icn_80_α
icn_79_β:
    goto icn_80_β
icn_79_docall:
    getstatic rung36_jcon_io/icn_pv_main_t2 J
    lstore 167
    getstatic rung36_jcon_io/icn_pv_main_t1 J
    lstore 169
    getstatic rung36_jcon_io/icn_36_alt_val J
    lstore 171
    invokestatic rung36_jcon_io/icn_rfile()V
    lload 167
    putstatic rung36_jcon_io/icn_pv_main_t2 J
    lload 169
    putstatic rung36_jcon_io/icn_pv_main_t1 J
    lload 171
    putstatic rung36_jcon_io/icn_36_alt_val J
    getstatic rung36_jcon_io/icn_failed B
    ifne icn_79_after_call
    getstatic rung36_jcon_io/icn_retval J
    goto icn_main_s35_sdrain
icn_79_after_call:
    goto icn_75_α
icn_main_s35_sdrain:
    pop2
    goto icn_75_α
;  STR
icn_82_α:
    ldc "mode b "
    goto icn_81_arg2
icn_82_β:
    goto icn_79_α
icn_81_arg2:
    putstatic rung36_jcon_io/icn_arg_str_2 Ljava/lang/String;
    lconst_0
    putstatic rung36_jcon_io/icn_arg_2 J
    goto icn_81_docall
;  STR
icn_83_α:
    ldc "b"
    goto icn_81_arg1
icn_83_β:
    goto icn_79_α
icn_81_arg1:
    putstatic rung36_jcon_io/icn_arg_str_1 Ljava/lang/String;
    lconst_0
    putstatic rung36_jcon_io/icn_arg_1 J
    goto icn_82_α
;  STR
icn_84_α:
    ldc "tmp1"
    goto icn_81_arg0
icn_84_β:
    goto icn_79_α
icn_81_arg0:
    putstatic rung36_jcon_io/icn_arg_str_0 Ljava/lang/String;
    lconst_0
    putstatic rung36_jcon_io/icn_arg_0 J
    goto icn_83_α
icn_81_α:
    goto icn_84_α
icn_81_β:
    goto icn_82_β
icn_81_docall:
    getstatic rung36_jcon_io/icn_pv_main_t2 J
    lstore 167
    getstatic rung36_jcon_io/icn_pv_main_t1 J
    lstore 169
    getstatic rung36_jcon_io/icn_36_alt_val J
    lstore 171
    invokestatic rung36_jcon_io/icn_wfile()V
    lload 167
    putstatic rung36_jcon_io/icn_pv_main_t2 J
    lload 169
    putstatic rung36_jcon_io/icn_pv_main_t1 J
    lload 171
    putstatic rung36_jcon_io/icn_36_alt_val J
    getstatic rung36_jcon_io/icn_failed B
    ifne icn_81_after_call
    getstatic rung36_jcon_io/icn_retval J
    goto icn_main_s34_sdrain
icn_81_after_call:
    goto icn_79_α
icn_main_s34_sdrain:
    pop2
    goto icn_79_α
;  STR
icn_86_α:
    ldc "tmp1"
    goto icn_85_arg0
icn_86_β:
    goto icn_81_α
icn_85_arg0:
    putstatic rung36_jcon_io/icn_arg_str_0 Ljava/lang/String;
    lconst_0
    putstatic rung36_jcon_io/icn_arg_0 J
    goto icn_85_docall
icn_85_α:
    goto icn_86_α
icn_85_β:
    goto icn_86_β
icn_85_docall:
    getstatic rung36_jcon_io/icn_pv_main_t2 J
    lstore 167
    getstatic rung36_jcon_io/icn_pv_main_t1 J
    lstore 169
    getstatic rung36_jcon_io/icn_36_alt_val J
    lstore 171
    invokestatic rung36_jcon_io/icn_rfile()V
    lload 167
    putstatic rung36_jcon_io/icn_pv_main_t2 J
    lload 169
    putstatic rung36_jcon_io/icn_pv_main_t1 J
    lload 171
    putstatic rung36_jcon_io/icn_36_alt_val J
    getstatic rung36_jcon_io/icn_failed B
    ifne icn_85_after_call
    getstatic rung36_jcon_io/icn_retval J
    goto icn_main_s33_sdrain
icn_85_after_call:
    goto icn_81_α
icn_main_s33_sdrain:
    pop2
    goto icn_81_α
;  STR
icn_88_α:
    ldc "changed"
    goto icn_87_arg2
icn_88_β:
    goto icn_85_α
icn_87_arg2:
    putstatic rung36_jcon_io/icn_arg_str_2 Ljava/lang/String;
    lconst_0
    putstatic rung36_jcon_io/icn_arg_2 J
    goto icn_87_docall
;  STR
icn_89_α:
    ldc "rw"
    goto icn_87_arg1
icn_89_β:
    goto icn_85_α
icn_87_arg1:
    putstatic rung36_jcon_io/icn_arg_str_1 Ljava/lang/String;
    lconst_0
    putstatic rung36_jcon_io/icn_arg_1 J
    goto icn_88_α
;  STR
icn_90_α:
    ldc "tmp1"
    goto icn_87_arg0
icn_90_β:
    goto icn_85_α
icn_87_arg0:
    putstatic rung36_jcon_io/icn_arg_str_0 Ljava/lang/String;
    lconst_0
    putstatic rung36_jcon_io/icn_arg_0 J
    goto icn_89_α
icn_87_α:
    goto icn_90_α
icn_87_β:
    goto icn_88_β
icn_87_docall:
    getstatic rung36_jcon_io/icn_pv_main_t2 J
    lstore 167
    getstatic rung36_jcon_io/icn_pv_main_t1 J
    lstore 169
    getstatic rung36_jcon_io/icn_36_alt_val J
    lstore 171
    invokestatic rung36_jcon_io/icn_wfile()V
    lload 167
    putstatic rung36_jcon_io/icn_pv_main_t2 J
    lload 169
    putstatic rung36_jcon_io/icn_pv_main_t1 J
    lload 171
    putstatic rung36_jcon_io/icn_36_alt_val J
    getstatic rung36_jcon_io/icn_failed B
    ifne icn_87_after_call
    getstatic rung36_jcon_io/icn_retval J
    goto icn_main_s32_sdrain
icn_87_after_call:
    goto icn_85_α
icn_main_s32_sdrain:
    pop2
    goto icn_85_α
;  STR
icn_92_α:
    ldc "tmp1"
    goto icn_91_arg0
icn_92_β:
    goto icn_87_α
icn_91_arg0:
    putstatic rung36_jcon_io/icn_arg_str_0 Ljava/lang/String;
    lconst_0
    putstatic rung36_jcon_io/icn_arg_0 J
    goto icn_91_docall
icn_91_α:
    goto icn_92_α
icn_91_β:
    goto icn_92_β
icn_91_docall:
    getstatic rung36_jcon_io/icn_pv_main_t2 J
    lstore 167
    getstatic rung36_jcon_io/icn_pv_main_t1 J
    lstore 169
    getstatic rung36_jcon_io/icn_36_alt_val J
    lstore 171
    invokestatic rung36_jcon_io/icn_rfile()V
    lload 167
    putstatic rung36_jcon_io/icn_pv_main_t2 J
    lload 169
    putstatic rung36_jcon_io/icn_pv_main_t1 J
    lload 171
    putstatic rung36_jcon_io/icn_36_alt_val J
    getstatic rung36_jcon_io/icn_failed B
    ifne icn_91_after_call
    getstatic rung36_jcon_io/icn_retval J
    goto icn_main_s31_sdrain
icn_91_after_call:
    goto icn_87_α
icn_main_s31_sdrain:
    pop2
    goto icn_87_α
;  STR
icn_94_α:
    ldc "gets extended"
    goto icn_93_arg2
icn_94_β:
    goto icn_91_α
icn_93_arg2:
    putstatic rung36_jcon_io/icn_arg_str_2 Ljava/lang/String;
    lconst_0
    putstatic rung36_jcon_io/icn_arg_2 J
    goto icn_93_docall
;  STR
icn_95_α:
    ldc "a"
    goto icn_93_arg1
icn_95_β:
    goto icn_91_α
icn_93_arg1:
    putstatic rung36_jcon_io/icn_arg_str_1 Ljava/lang/String;
    lconst_0
    putstatic rung36_jcon_io/icn_arg_1 J
    goto icn_94_α
;  STR
icn_96_α:
    ldc "tmp1"
    goto icn_93_arg0
icn_96_β:
    goto icn_91_α
icn_93_arg0:
    putstatic rung36_jcon_io/icn_arg_str_0 Ljava/lang/String;
    lconst_0
    putstatic rung36_jcon_io/icn_arg_0 J
    goto icn_95_α
icn_93_α:
    goto icn_96_α
icn_93_β:
    goto icn_94_β
icn_93_docall:
    getstatic rung36_jcon_io/icn_pv_main_t2 J
    lstore 167
    getstatic rung36_jcon_io/icn_pv_main_t1 J
    lstore 169
    getstatic rung36_jcon_io/icn_36_alt_val J
    lstore 171
    invokestatic rung36_jcon_io/icn_wfile()V
    lload 167
    putstatic rung36_jcon_io/icn_pv_main_t2 J
    lload 169
    putstatic rung36_jcon_io/icn_pv_main_t1 J
    lload 171
    putstatic rung36_jcon_io/icn_36_alt_val J
    getstatic rung36_jcon_io/icn_failed B
    ifne icn_93_after_call
    getstatic rung36_jcon_io/icn_retval J
    goto icn_main_s30_sdrain
icn_93_after_call:
    goto icn_91_α
icn_main_s30_sdrain:
    pop2
    goto icn_91_α
;  STR
icn_98_α:
    ldc "tmp1"
    goto icn_97_arg0
icn_98_β:
    goto icn_93_α
icn_97_arg0:
    putstatic rung36_jcon_io/icn_arg_str_0 Ljava/lang/String;
    lconst_0
    putstatic rung36_jcon_io/icn_arg_0 J
    goto icn_97_docall
icn_97_α:
    goto icn_98_α
icn_97_β:
    goto icn_98_β
icn_97_docall:
    getstatic rung36_jcon_io/icn_pv_main_t2 J
    lstore 167
    getstatic rung36_jcon_io/icn_pv_main_t1 J
    lstore 169
    getstatic rung36_jcon_io/icn_36_alt_val J
    lstore 171
    invokestatic rung36_jcon_io/icn_rfile()V
    lload 167
    putstatic rung36_jcon_io/icn_pv_main_t2 J
    lload 169
    putstatic rung36_jcon_io/icn_pv_main_t1 J
    lload 171
    putstatic rung36_jcon_io/icn_36_alt_val J
    getstatic rung36_jcon_io/icn_failed B
    ifne icn_97_after_call
    getstatic rung36_jcon_io/icn_retval J
    goto icn_main_s29_sdrain
icn_97_after_call:
    goto icn_93_α
icn_main_s29_sdrain:
    pop2
    goto icn_93_α
;  STR
icn_100_α:
    ldc "shorter file"
    goto icn_99_arg2
icn_100_β:
    goto icn_97_α
icn_99_arg2:
    putstatic rung36_jcon_io/icn_arg_str_2 Ljava/lang/String;
    lconst_0
    putstatic rung36_jcon_io/icn_arg_2 J
    goto icn_99_docall
;  STR
icn_101_α:
    ldc "w"
    goto icn_99_arg1
icn_101_β:
    goto icn_97_α
icn_99_arg1:
    putstatic rung36_jcon_io/icn_arg_str_1 Ljava/lang/String;
    lconst_0
    putstatic rung36_jcon_io/icn_arg_1 J
    goto icn_100_α
;  STR
icn_102_α:
    ldc "tmp1"
    goto icn_99_arg0
icn_102_β:
    goto icn_97_α
icn_99_arg0:
    putstatic rung36_jcon_io/icn_arg_str_0 Ljava/lang/String;
    lconst_0
    putstatic rung36_jcon_io/icn_arg_0 J
    goto icn_101_α
icn_99_α:
    goto icn_102_α
icn_99_β:
    goto icn_100_β
icn_99_docall:
    getstatic rung36_jcon_io/icn_pv_main_t2 J
    lstore 167
    getstatic rung36_jcon_io/icn_pv_main_t1 J
    lstore 169
    getstatic rung36_jcon_io/icn_36_alt_val J
    lstore 171
    invokestatic rung36_jcon_io/icn_wfile()V
    lload 167
    putstatic rung36_jcon_io/icn_pv_main_t2 J
    lload 169
    putstatic rung36_jcon_io/icn_pv_main_t1 J
    lload 171
    putstatic rung36_jcon_io/icn_36_alt_val J
    getstatic rung36_jcon_io/icn_failed B
    ifne icn_99_after_call
    getstatic rung36_jcon_io/icn_retval J
    goto icn_main_s28_sdrain
icn_99_after_call:
    goto icn_97_α
icn_main_s28_sdrain:
    pop2
    goto icn_97_α
;  STR
icn_104_α:
    ldc "tmp1"
    goto icn_103_arg0
icn_104_β:
    goto icn_99_α
icn_103_arg0:
    putstatic rung36_jcon_io/icn_arg_str_0 Ljava/lang/String;
    lconst_0
    putstatic rung36_jcon_io/icn_arg_0 J
    goto icn_103_docall
icn_103_α:
    goto icn_104_α
icn_103_β:
    goto icn_104_β
icn_103_docall:
    getstatic rung36_jcon_io/icn_pv_main_t2 J
    lstore 167
    getstatic rung36_jcon_io/icn_pv_main_t1 J
    lstore 169
    getstatic rung36_jcon_io/icn_36_alt_val J
    lstore 171
    invokestatic rung36_jcon_io/icn_rfile()V
    lload 167
    putstatic rung36_jcon_io/icn_pv_main_t2 J
    lload 169
    putstatic rung36_jcon_io/icn_pv_main_t1 J
    lload 171
    putstatic rung36_jcon_io/icn_36_alt_val J
    getstatic rung36_jcon_io/icn_failed B
    ifne icn_103_after_call
    getstatic rung36_jcon_io/icn_retval J
    goto icn_main_s27_sdrain
icn_103_after_call:
    goto icn_99_α
icn_main_s27_sdrain:
    pop2
    goto icn_99_α
;  STR
icn_106_α:
    ldc "follow the yellow brick road"
    goto icn_105_arg2
icn_106_β:
    goto icn_103_α
icn_105_arg2:
    putstatic rung36_jcon_io/icn_arg_str_2 Ljava/lang/String;
    lconst_0
    putstatic rung36_jcon_io/icn_arg_2 J
    goto icn_105_docall
;  STR
icn_107_α:
    ldc "w"
    goto icn_105_arg1
icn_107_β:
    goto icn_103_α
icn_105_arg1:
    putstatic rung36_jcon_io/icn_arg_str_1 Ljava/lang/String;
    lconst_0
    putstatic rung36_jcon_io/icn_arg_1 J
    goto icn_106_α
;  STR
icn_108_α:
    ldc "tmp1"
    goto icn_105_arg0
icn_108_β:
    goto icn_103_α
icn_105_arg0:
    putstatic rung36_jcon_io/icn_arg_str_0 Ljava/lang/String;
    lconst_0
    putstatic rung36_jcon_io/icn_arg_0 J
    goto icn_107_α
icn_105_α:
    goto icn_108_α
icn_105_β:
    goto icn_106_β
icn_105_docall:
    getstatic rung36_jcon_io/icn_pv_main_t2 J
    lstore 167
    getstatic rung36_jcon_io/icn_pv_main_t1 J
    lstore 169
    getstatic rung36_jcon_io/icn_36_alt_val J
    lstore 171
    invokestatic rung36_jcon_io/icn_wfile()V
    lload 167
    putstatic rung36_jcon_io/icn_pv_main_t2 J
    lload 169
    putstatic rung36_jcon_io/icn_pv_main_t1 J
    lload 171
    putstatic rung36_jcon_io/icn_36_alt_val J
    getstatic rung36_jcon_io/icn_failed B
    ifne icn_105_after_call
    getstatic rung36_jcon_io/icn_retval J
    goto icn_main_s26_sdrain
icn_105_after_call:
    goto icn_103_α
icn_main_s26_sdrain:
    pop2
    goto icn_103_α
;  STR
icn_110_α:
    ldc "/dev/null"
    goto icn_109_arg0
icn_110_β:
    goto icn_105_α
icn_109_arg0:
    putstatic rung36_jcon_io/icn_arg_str_0 Ljava/lang/String;
    lconst_0
    putstatic rung36_jcon_io/icn_arg_0 J
    goto icn_109_docall
icn_109_α:
    goto icn_110_α
icn_109_β:
    goto icn_110_β
icn_109_docall:
    getstatic rung36_jcon_io/icn_pv_main_t2 J
    lstore 167
    getstatic rung36_jcon_io/icn_pv_main_t1 J
    lstore 169
    getstatic rung36_jcon_io/icn_36_alt_val J
    lstore 171
    invokestatic rung36_jcon_io/icn_rfile()V
    lload 167
    putstatic rung36_jcon_io/icn_pv_main_t2 J
    lload 169
    putstatic rung36_jcon_io/icn_pv_main_t1 J
    lload 171
    putstatic rung36_jcon_io/icn_36_alt_val J
    getstatic rung36_jcon_io/icn_failed B
    ifne icn_109_after_call
    getstatic rung36_jcon_io/icn_retval J
    goto icn_main_s25_sdrain
icn_109_after_call:
    goto icn_105_α
icn_main_s25_sdrain:
    pop2
    goto icn_105_α
icn_111_α:
    getstatic java/lang/System/out Ljava/io/PrintStream;
    ldc ""
    invokevirtual java/io/PrintStream/println(Ljava/lang/String;)V
    goto icn_main_s24_sdrain
icn_111_β:
    goto icn_109_α
icn_main_s24_sdrain:
    pop2
    goto icn_109_α
icn_114_α:
    goto icn_111_α
icn_114_β:
    goto icn_111_α
icn_113_α:
    goto icn_114_α
icn_113_β:
    goto icn_114_β
icn_113_image_after:
    invokestatic java/lang/Long/toString(J)Ljava/lang/String;
    goto icn_112_waft_0
icn_112_α:
    goto icn_113_α
icn_112_β:
    goto icn_113_β
    goto icn_112_wentry
icn_112_waft_0:
    astore 163
    getstatic java/lang/System/out Ljava/io/PrintStream;
    aload 163
    invokevirtual java/io/PrintStream/print(Ljava/lang/String;)V
    getstatic java/lang/System/out Ljava/io/PrintStream;
    ldc ""
    invokevirtual java/io/PrintStream/println(Ljava/lang/String;)V
    aload 163
    goto icn_main_s23_sdrain
icn_112_wentry:
    goto icn_113_α
icn_main_s23_sdrain:
    pop
    goto icn_111_α
icn_116_α:
    goto icn_112_α
icn_116_β:
    goto icn_112_α
icn_115_gdrain:
    pop2
icn_115_pump:
    goto icn_116_β
icn_115_α:
    goto icn_116_α
icn_115_β:
    goto icn_112_α
icn_118_α:
    goto icn_115_α
icn_118_β:
    goto icn_115_α
icn_117_gdrain:
    pop2
icn_117_pump:
    goto icn_118_β
icn_117_α:
    goto icn_118_α
icn_117_β:
    goto icn_115_α
;  STR
icn_120_α:
    ldc "flush /dev/null: "
    goto icn_119_waft_0
icn_120_β:
    goto icn_117_α
;  STR
icn_122_α:
    ldc "FAILED"
    goto icn_121_alt_g1
icn_122_β:
    goto icn_117_α
icn_124_α:
    goto icn_122_α
icn_124_β:
    goto icn_122_α
icn_123_α:
    goto icn_124_α
icn_123_β:
    goto icn_124_β
icn_123_image_after:
    invokestatic java/lang/Long/toString(J)Ljava/lang/String;
    goto icn_121_alt_g0
icn_121_alt_g0:
    astore 164
    sipush 1
    putstatic rung36_jcon_io/icn_121_alt_gate I
    aload 164
    goto icn_119_waft_1
icn_121_alt_g1:
    astore 165
    sipush 2
    putstatic rung36_jcon_io/icn_121_alt_gate I
    aload 165
    goto icn_119_waft_1
icn_121_α:
    iconst_0
    putstatic rung36_jcon_io/icn_121_alt_gate I
    goto icn_123_α
icn_121_β:
    getstatic rung36_jcon_io/icn_121_alt_gate I
    tableswitch 1 2
        icn_123_β
        icn_122_β
        default: icn_117_α
icn_119_α:
    goto icn_120_α
icn_119_β:
    goto icn_120_β
    goto icn_119_wentry
icn_119_waft_0:
    astore 166
    getstatic java/lang/System/out Ljava/io/PrintStream;
    aload 166
    invokevirtual java/io/PrintStream/print(Ljava/lang/String;)V
    goto icn_121_α
icn_119_waft_1:
    astore 167
    getstatic java/lang/System/out Ljava/io/PrintStream;
    aload 167
    invokevirtual java/io/PrintStream/print(Ljava/lang/String;)V
    getstatic java/lang/System/out Ljava/io/PrintStream;
    ldc ""
    invokevirtual java/io/PrintStream/println(Ljava/lang/String;)V
    aload 167
    goto icn_main_s20_sdrain
icn_119_wentry:
    goto icn_120_α
icn_main_s20_sdrain:
    pop
    goto icn_117_α
;  STR
icn_126_α:
    ldc "close /dev/null: "
    goto icn_125_waft_0
icn_126_β:
    goto icn_119_α
;  STR
icn_128_α:
    ldc "FAILED"
    goto icn_127_alt_g1
icn_128_β:
    goto icn_119_α
icn_130_α:
    goto icn_128_α
icn_130_β:
    goto icn_128_α
icn_129_α:
    goto icn_130_α
icn_129_β:
    goto icn_130_β
icn_129_image_after:
    invokestatic java/lang/Long/toString(J)Ljava/lang/String;
    goto icn_127_alt_g0
icn_127_alt_g0:
    astore 168
    sipush 1
    putstatic rung36_jcon_io/icn_127_alt_gate I
    aload 168
    goto icn_125_waft_1
icn_127_alt_g1:
    astore 169
    sipush 2
    putstatic rung36_jcon_io/icn_127_alt_gate I
    aload 169
    goto icn_125_waft_1
icn_127_α:
    iconst_0
    putstatic rung36_jcon_io/icn_127_alt_gate I
    goto icn_129_α
icn_127_β:
    getstatic rung36_jcon_io/icn_127_alt_gate I
    tableswitch 1 2
        icn_129_β
        icn_128_β
        default: icn_119_α
icn_125_α:
    goto icn_126_α
icn_125_β:
    goto icn_126_β
    goto icn_125_wentry
icn_125_waft_0:
    astore 170
    getstatic java/lang/System/out Ljava/io/PrintStream;
    aload 170
    invokevirtual java/io/PrintStream/print(Ljava/lang/String;)V
    goto icn_127_α
icn_125_waft_1:
    astore 171
    getstatic java/lang/System/out Ljava/io/PrintStream;
    aload 171
    invokevirtual java/io/PrintStream/print(Ljava/lang/String;)V
    getstatic java/lang/System/out Ljava/io/PrintStream;
    ldc ""
    invokevirtual java/io/PrintStream/println(Ljava/lang/String;)V
    aload 171
    goto icn_main_s19_sdrain
icn_125_wentry:
    goto icn_126_α
icn_main_s19_sdrain:
    pop
    goto icn_119_α
;  STR
icn_132_α:
    ldc "close /dev/null: "
    goto icn_131_waft_0
icn_132_β:
    goto icn_125_α
;  STR
icn_134_α:
    ldc "FAILED"
    goto icn_133_alt_g1
icn_134_β:
    goto icn_125_α
icn_136_α:
    goto icn_134_α
icn_136_β:
    goto icn_134_α
icn_135_α:
    goto icn_136_α
icn_135_β:
    goto icn_136_β
icn_135_image_after:
    invokestatic java/lang/Long/toString(J)Ljava/lang/String;
    goto icn_133_alt_g0
icn_133_alt_g0:
    astore 172
    sipush 1
    putstatic rung36_jcon_io/icn_133_alt_gate I
    aload 172
    goto icn_131_waft_1
icn_133_alt_g1:
    astore 173
    sipush 2
    putstatic rung36_jcon_io/icn_133_alt_gate I
    aload 173
    goto icn_131_waft_1
icn_133_α:
    iconst_0
    putstatic rung36_jcon_io/icn_133_alt_gate I
    goto icn_135_α
icn_133_β:
    getstatic rung36_jcon_io/icn_133_alt_gate I
    tableswitch 1 2
        icn_135_β
        icn_134_β
        default: icn_125_α
icn_131_α:
    goto icn_132_α
icn_131_β:
    goto icn_132_β
    goto icn_131_wentry
icn_131_waft_0:
    astore 174
    getstatic java/lang/System/out Ljava/io/PrintStream;
    aload 174
    invokevirtual java/io/PrintStream/print(Ljava/lang/String;)V
    goto icn_133_α
icn_131_waft_1:
    astore 175
    getstatic java/lang/System/out Ljava/io/PrintStream;
    aload 175
    invokevirtual java/io/PrintStream/print(Ljava/lang/String;)V
    getstatic java/lang/System/out Ljava/io/PrintStream;
    ldc ""
    invokevirtual java/io/PrintStream/println(Ljava/lang/String;)V
    aload 175
    goto icn_main_s18_sdrain
icn_131_wentry:
    goto icn_132_α
icn_main_s18_sdrain:
    pop
    goto icn_125_α
;  STR
icn_138_α:
    ldc "flush /dev/null: "
    goto icn_137_waft_0
icn_138_β:
    goto icn_131_α
;  STR
icn_140_α:
    ldc "FAILED"
    goto icn_139_alt_g1
icn_140_β:
    goto icn_131_α
icn_142_α:
    goto icn_140_α
icn_142_β:
    goto icn_140_α
icn_141_α:
    goto icn_142_α
icn_141_β:
    goto icn_142_β
icn_141_image_after:
    invokestatic java/lang/Long/toString(J)Ljava/lang/String;
    goto icn_139_alt_g0
icn_139_alt_g0:
    astore 176
    sipush 1
    putstatic rung36_jcon_io/icn_139_alt_gate I
    aload 176
    goto icn_137_waft_1
icn_139_alt_g1:
    astore 177
    sipush 2
    putstatic rung36_jcon_io/icn_139_alt_gate I
    aload 177
    goto icn_137_waft_1
icn_139_α:
    iconst_0
    putstatic rung36_jcon_io/icn_139_alt_gate I
    goto icn_141_α
icn_139_β:
    getstatic rung36_jcon_io/icn_139_alt_gate I
    tableswitch 1 2
        icn_141_β
        icn_140_β
        default: icn_131_α
icn_137_α:
    goto icn_138_α
icn_137_β:
    goto icn_138_β
    goto icn_137_wentry
icn_137_waft_0:
    astore 178
    getstatic java/lang/System/out Ljava/io/PrintStream;
    aload 178
    invokevirtual java/io/PrintStream/print(Ljava/lang/String;)V
    goto icn_139_α
icn_137_waft_1:
    astore 179
    getstatic java/lang/System/out Ljava/io/PrintStream;
    aload 179
    invokevirtual java/io/PrintStream/print(Ljava/lang/String;)V
    getstatic java/lang/System/out Ljava/io/PrintStream;
    ldc ""
    invokevirtual java/io/PrintStream/println(Ljava/lang/String;)V
    aload 179
    goto icn_main_s17_sdrain
icn_137_wentry:
    goto icn_138_α
icn_main_s17_sdrain:
    pop
    goto icn_131_α
icn_143_α:
    getstatic java/lang/System/out Ljava/io/PrintStream;
    ldc ""
    invokevirtual java/io/PrintStream/println(Ljava/lang/String;)V
    goto icn_main_s16_sdrain
icn_143_β:
    goto icn_137_α
icn_main_s16_sdrain:
    pop2
    goto icn_137_α
;  STR
icn_145_α:
    ldc "flush /etc/passwd: "
    goto icn_144_waft_0
icn_145_β:
    goto icn_143_α
;  STR
icn_147_α:
    ldc "FAILED"
    goto icn_146_alt_g1
icn_147_β:
    goto icn_143_α
icn_149_α:
    goto icn_147_α
icn_149_β:
    goto icn_147_α
icn_148_α:
    goto icn_149_α
icn_148_β:
    goto icn_149_β
icn_148_image_after:
    invokestatic java/lang/Long/toString(J)Ljava/lang/String;
    goto icn_146_alt_g0
icn_146_alt_g0:
    astore 180
    sipush 1
    putstatic rung36_jcon_io/icn_146_alt_gate I
    aload 180
    goto icn_144_waft_1
icn_146_alt_g1:
    astore 181
    sipush 2
    putstatic rung36_jcon_io/icn_146_alt_gate I
    aload 181
    goto icn_144_waft_1
icn_146_α:
    iconst_0
    putstatic rung36_jcon_io/icn_146_alt_gate I
    goto icn_148_α
icn_146_β:
    getstatic rung36_jcon_io/icn_146_alt_gate I
    tableswitch 1 2
        icn_148_β
        icn_147_β
        default: icn_143_α
icn_144_α:
    goto icn_145_α
icn_144_β:
    goto icn_145_β
    goto icn_144_wentry
icn_144_waft_0:
    astore 182
    getstatic java/lang/System/out Ljava/io/PrintStream;
    aload 182
    invokevirtual java/io/PrintStream/print(Ljava/lang/String;)V
    goto icn_146_α
icn_144_waft_1:
    astore 183
    getstatic java/lang/System/out Ljava/io/PrintStream;
    aload 183
    invokevirtual java/io/PrintStream/print(Ljava/lang/String;)V
    getstatic java/lang/System/out Ljava/io/PrintStream;
    ldc ""
    invokevirtual java/io/PrintStream/println(Ljava/lang/String;)V
    aload 183
    goto icn_main_s15_sdrain
icn_144_wentry:
    goto icn_145_α
icn_main_s15_sdrain:
    pop
    goto icn_143_α
;  STR
icn_151_α:
    ldc "close /etc/passwd: "
    goto icn_150_waft_0
icn_151_β:
    goto icn_144_α
;  STR
icn_153_α:
    ldc "FAILED"
    goto icn_152_alt_g1
icn_153_β:
    goto icn_144_α
icn_155_α:
    goto icn_153_α
icn_155_β:
    goto icn_153_α
icn_154_α:
    goto icn_155_α
icn_154_β:
    goto icn_155_β
icn_154_image_after:
    invokestatic java/lang/Long/toString(J)Ljava/lang/String;
    goto icn_152_alt_g0
icn_152_alt_g0:
    astore 184
    sipush 1
    putstatic rung36_jcon_io/icn_152_alt_gate I
    aload 184
    goto icn_150_waft_1
icn_152_alt_g1:
    astore 185
    sipush 2
    putstatic rung36_jcon_io/icn_152_alt_gate I
    aload 185
    goto icn_150_waft_1
icn_152_α:
    iconst_0
    putstatic rung36_jcon_io/icn_152_alt_gate I
    goto icn_154_α
icn_152_β:
    getstatic rung36_jcon_io/icn_152_alt_gate I
    tableswitch 1 2
        icn_154_β
        icn_153_β
        default: icn_144_α
icn_150_α:
    goto icn_151_α
icn_150_β:
    goto icn_151_β
    goto icn_150_wentry
icn_150_waft_0:
    astore 186
    getstatic java/lang/System/out Ljava/io/PrintStream;
    aload 186
    invokevirtual java/io/PrintStream/print(Ljava/lang/String;)V
    goto icn_152_α
icn_150_waft_1:
    astore 187
    getstatic java/lang/System/out Ljava/io/PrintStream;
    aload 187
    invokevirtual java/io/PrintStream/print(Ljava/lang/String;)V
    getstatic java/lang/System/out Ljava/io/PrintStream;
    ldc ""
    invokevirtual java/io/PrintStream/println(Ljava/lang/String;)V
    aload 187
    goto icn_main_s14_sdrain
icn_150_wentry:
    goto icn_151_α
icn_main_s14_sdrain:
    pop
    goto icn_144_α
;  STR
icn_157_α:
    ldc "close /etc/passwd: "
    goto icn_156_waft_0
icn_157_β:
    goto icn_150_α
;  STR
icn_159_α:
    ldc "FAILED"
    goto icn_158_alt_g1
icn_159_β:
    goto icn_150_α
icn_161_α:
    goto icn_159_α
icn_161_β:
    goto icn_159_α
icn_160_α:
    goto icn_161_α
icn_160_β:
    goto icn_161_β
icn_160_image_after:
    invokestatic java/lang/Long/toString(J)Ljava/lang/String;
    goto icn_158_alt_g0
icn_158_alt_g0:
    astore 188
    sipush 1
    putstatic rung36_jcon_io/icn_158_alt_gate I
    aload 188
    goto icn_156_waft_1
icn_158_alt_g1:
    astore 189
    sipush 2
    putstatic rung36_jcon_io/icn_158_alt_gate I
    aload 189
    goto icn_156_waft_1
icn_158_α:
    iconst_0
    putstatic rung36_jcon_io/icn_158_alt_gate I
    goto icn_160_α
icn_158_β:
    getstatic rung36_jcon_io/icn_158_alt_gate I
    tableswitch 1 2
        icn_160_β
        icn_159_β
        default: icn_150_α
icn_156_α:
    goto icn_157_α
icn_156_β:
    goto icn_157_β
    goto icn_156_wentry
icn_156_waft_0:
    astore 190
    getstatic java/lang/System/out Ljava/io/PrintStream;
    aload 190
    invokevirtual java/io/PrintStream/print(Ljava/lang/String;)V
    goto icn_158_α
icn_156_waft_1:
    astore 191
    getstatic java/lang/System/out Ljava/io/PrintStream;
    aload 191
    invokevirtual java/io/PrintStream/print(Ljava/lang/String;)V
    getstatic java/lang/System/out Ljava/io/PrintStream;
    ldc ""
    invokevirtual java/io/PrintStream/println(Ljava/lang/String;)V
    aload 191
    goto icn_main_s13_sdrain
icn_156_wentry:
    goto icn_157_α
icn_main_s13_sdrain:
    pop
    goto icn_150_α
;  STR
icn_163_α:
    ldc "flush /etc/passwd: "
    goto icn_162_waft_0
icn_163_β:
    goto icn_156_α
;  STR
icn_165_α:
    ldc "FAILED"
    goto icn_164_alt_g1
icn_165_β:
    goto icn_156_α
icn_167_α:
    goto icn_165_α
icn_167_β:
    goto icn_165_α
icn_166_α:
    goto icn_167_α
icn_166_β:
    goto icn_167_β
icn_166_image_after:
    invokestatic java/lang/Long/toString(J)Ljava/lang/String;
    goto icn_164_alt_g0
icn_164_alt_g0:
    astore 192
    sipush 1
    putstatic rung36_jcon_io/icn_164_alt_gate I
    aload 192
    goto icn_162_waft_1
icn_164_alt_g1:
    astore 193
    sipush 2
    putstatic rung36_jcon_io/icn_164_alt_gate I
    aload 193
    goto icn_162_waft_1
icn_164_α:
    iconst_0
    putstatic rung36_jcon_io/icn_164_alt_gate I
    goto icn_166_α
icn_164_β:
    getstatic rung36_jcon_io/icn_164_alt_gate I
    tableswitch 1 2
        icn_166_β
        icn_165_β
        default: icn_156_α
icn_162_α:
    goto icn_163_α
icn_162_β:
    goto icn_163_β
    goto icn_162_wentry
icn_162_waft_0:
    astore 194
    getstatic java/lang/System/out Ljava/io/PrintStream;
    aload 194
    invokevirtual java/io/PrintStream/print(Ljava/lang/String;)V
    goto icn_164_α
icn_162_waft_1:
    astore 195
    getstatic java/lang/System/out Ljava/io/PrintStream;
    aload 195
    invokevirtual java/io/PrintStream/print(Ljava/lang/String;)V
    getstatic java/lang/System/out Ljava/io/PrintStream;
    ldc ""
    invokevirtual java/io/PrintStream/println(Ljava/lang/String;)V
    aload 195
    goto icn_main_s12_sdrain
icn_162_wentry:
    goto icn_163_α
icn_main_s12_sdrain:
    pop
    goto icn_156_α
icn_168_α:
    getstatic java/lang/System/out Ljava/io/PrintStream;
    ldc ""
    invokevirtual java/io/PrintStream/println(Ljava/lang/String;)V
    goto icn_main_s11_sdrain
icn_168_β:
    goto icn_162_α
icn_main_s11_sdrain:
    pop2
    goto icn_162_α
;  INT
icn_171_α:
    ldc2_w 2
    goto icn_170_limit_nrelay
icn_171_β:
    goto icn_168_α
;  VAR
icn_174_α:
    getstatic rung36_jcon_io/icn_gvar_&input J
    goto icn_173_bang_adv
icn_174_β:
    goto icn_168_α
icn_173_α:
    goto icn_174_α
icn_173_β:
    goto icn_173_bang_chk
icn_173_bang_adv:
    putstatic rung36_jcon_io/icn_173_bang_str Ljava/lang/String;
    iconst_0
    putstatic rung36_jcon_io/icn_173_bang_pos I
icn_173_bang_chk:
    getstatic rung36_jcon_io/icn_173_bang_str Ljava/lang/String;
    invokevirtual java/lang/String/length()I
    getstatic rung36_jcon_io/icn_173_bang_pos I
    if_icmple icn_168_α
    getstatic rung36_jcon_io/icn_173_bang_str Ljava/lang/String;
    getstatic rung36_jcon_io/icn_173_bang_pos I
    getstatic rung36_jcon_io/icn_173_bang_pos I
    iconst_1
    iadd
    invokevirtual java/lang/String/substring(II)Ljava/lang/String;
    getstatic rung36_jcon_io/icn_173_bang_pos I
    iconst_1
    iadd
    putstatic rung36_jcon_io/icn_173_bang_pos I
    goto icn_172_waft_0
icn_172_α:
    goto icn_173_α
icn_172_β:
    goto icn_173_β
    goto icn_172_wentry
icn_172_waft_0:
    astore 196
    getstatic java/lang/System/out Ljava/io/PrintStream;
    aload 196
    invokevirtual java/io/PrintStream/print(Ljava/lang/String;)V
    getstatic java/lang/System/out Ljava/io/PrintStream;
    ldc ""
    invokevirtual java/io/PrintStream/println(Ljava/lang/String;)V
    aload 196
    goto icn_170_limit_egamma
icn_172_wentry:
    goto icn_173_α
icn_170_limit_nrelay:
    putstatic rung36_jcon_io/icn_170_limit_max J
    lconst_0
    putstatic rung36_jcon_io/icn_170_limit_count J
    goto icn_172_α
icn_170_limit_egamma:
    putstatic rung36_jcon_io/icn_170_limit_val Ljava/lang/String;
icn_170_limit_chkex:
    getstatic rung36_jcon_io/icn_170_limit_count J
    getstatic rung36_jcon_io/icn_170_limit_max J
    lcmp
    ifge icn_172_β
    getstatic rung36_jcon_io/icn_170_limit_count J
    lconst_1
    ladd
    putstatic rung36_jcon_io/icn_170_limit_count J
    getstatic rung36_jcon_io/icn_170_limit_val Ljava/lang/String;
    goto icn_169_gdrain
icn_170_α:
    goto icn_171_α
icn_170_β:
    getstatic rung36_jcon_io/icn_170_limit_count J
    getstatic rung36_jcon_io/icn_170_limit_max J
    lcmp
    ifge icn_168_α
    goto icn_172_β
icn_169_gdrain:
    pop
icn_169_pump:
    goto icn_170_β
icn_169_α:
    goto icn_170_α
icn_169_β:
    goto icn_168_α
;  INT
icn_179_α:
    ldc2_w 2
    goto icn_178_limit_nrelay
icn_179_β:
    goto icn_169_α
;  VAR
icn_180_α:
    getstatic rung36_jcon_io/icn_gvar_&input J
    goto icn_178_limit_egamma
icn_180_β:
    goto icn_169_α
icn_178_limit_nrelay:
    putstatic rung36_jcon_io/icn_178_limit_max J
    lconst_0
    putstatic rung36_jcon_io/icn_178_limit_count J
    goto icn_180_α
icn_178_limit_egamma:
    putstatic rung36_jcon_io/icn_178_limit_val J
icn_178_limit_chkex:
    getstatic rung36_jcon_io/icn_178_limit_count J
    getstatic rung36_jcon_io/icn_178_limit_max J
    lcmp
    ifge icn_180_β
    getstatic rung36_jcon_io/icn_178_limit_count J
    lconst_1
    ladd
    putstatic rung36_jcon_io/icn_178_limit_count J
    getstatic rung36_jcon_io/icn_178_limit_val J
    goto icn_177_bang_adv
icn_178_α:
    goto icn_179_α
icn_178_β:
    getstatic rung36_jcon_io/icn_178_limit_count J
    getstatic rung36_jcon_io/icn_178_limit_max J
    lcmp
    ifge icn_169_α
    goto icn_180_β
icn_177_α:
    goto icn_178_α
icn_177_β:
    goto icn_177_bang_chk
icn_177_bang_adv:
    putstatic rung36_jcon_io/icn_177_bang_str Ljava/lang/String;
    iconst_0
    putstatic rung36_jcon_io/icn_177_bang_pos I
icn_177_bang_chk:
    getstatic rung36_jcon_io/icn_177_bang_str Ljava/lang/String;
    invokevirtual java/lang/String/length()I
    getstatic rung36_jcon_io/icn_177_bang_pos I
    if_icmple icn_169_α
    getstatic rung36_jcon_io/icn_177_bang_str Ljava/lang/String;
    getstatic rung36_jcon_io/icn_177_bang_pos I
    getstatic rung36_jcon_io/icn_177_bang_pos I
    iconst_1
    iadd
    invokevirtual java/lang/String/substring(II)Ljava/lang/String;
    getstatic rung36_jcon_io/icn_177_bang_pos I
    iconst_1
    iadd
    putstatic rung36_jcon_io/icn_177_bang_pos I
    goto icn_176_waft_0
icn_176_α:
    goto icn_177_α
icn_176_β:
    goto icn_177_β
    goto icn_176_wentry
icn_176_waft_0:
    astore 197
    getstatic java/lang/System/out Ljava/io/PrintStream;
    aload 197
    invokevirtual java/io/PrintStream/print(Ljava/lang/String;)V
    getstatic java/lang/System/out Ljava/io/PrintStream;
    ldc ""
    invokevirtual java/io/PrintStream/println(Ljava/lang/String;)V
    aload 197
    goto icn_175_gdrain
icn_176_wentry:
    goto icn_177_α
icn_175_gdrain:
    pop
icn_175_pump:
    goto icn_176_β
icn_175_α:
    goto icn_176_α
icn_175_β:
    goto icn_169_α
;  VAR
icn_183_α:
    getstatic rung36_jcon_io/icn_gvar_&input J
    goto icn_182_bang_adv
icn_183_β:
    goto icn_175_α
icn_182_α:
    goto icn_183_α
icn_182_β:
    goto icn_182_bang_chk
icn_182_bang_adv:
    putstatic rung36_jcon_io/icn_182_bang_str Ljava/lang/String;
    iconst_0
    putstatic rung36_jcon_io/icn_182_bang_pos I
icn_182_bang_chk:
    getstatic rung36_jcon_io/icn_182_bang_str Ljava/lang/String;
    invokevirtual java/lang/String/length()I
    getstatic rung36_jcon_io/icn_182_bang_pos I
    if_icmple icn_175_α
    getstatic rung36_jcon_io/icn_182_bang_str Ljava/lang/String;
    getstatic rung36_jcon_io/icn_182_bang_pos I
    getstatic rung36_jcon_io/icn_182_bang_pos I
    iconst_1
    iadd
    invokevirtual java/lang/String/substring(II)Ljava/lang/String;
    getstatic rung36_jcon_io/icn_182_bang_pos I
    iconst_1
    iadd
    putstatic rung36_jcon_io/icn_182_bang_pos I
    goto icn_181_waft_0
icn_181_α:
    goto icn_182_α
icn_181_β:
    goto icn_182_β
    goto icn_181_wentry
icn_181_waft_0:
    astore 198
    getstatic java/lang/System/out Ljava/io/PrintStream;
    aload 198
    invokevirtual java/io/PrintStream/print(Ljava/lang/String;)V
    getstatic java/lang/System/out Ljava/io/PrintStream;
    ldc ""
    invokevirtual java/io/PrintStream/println(Ljava/lang/String;)V
    aload 198
    goto icn_main_s8_sdrain
icn_181_wentry:
    goto icn_182_α
icn_main_s8_sdrain:
    pop
    goto icn_175_α
icn_186_α:
    getstatic rung36_jcon_io/icn_stdin_init I
    ifne icn_186_rd_call
    new java/io/BufferedReader
    dup
    new java/io/InputStreamReader
    dup
    getstatic java/lang/System/in Ljava/io/InputStream;
    invokespecial java/io/InputStreamReader/<init>(Ljava/io/InputStream;)V
    invokespecial java/io/BufferedReader/<init>(Ljava/io/Reader;)V
    putstatic rung36_jcon_io/icn_stdin_reader Ljava/lang/Object;
    iconst_1
    putstatic rung36_jcon_io/icn_stdin_init I
icn_186_rd_call:
    getstatic rung36_jcon_io/icn_stdin_reader Ljava/lang/Object;
    checkcast java/io/BufferedReader
    invokevirtual java/io/BufferedReader/readLine()Ljava/lang/String;
    dup
    ifnull icn_186_rd_null
    goto icn_185_waft_0
icn_186_rd_null:
    pop
    goto icn_181_α
icn_186_β:
    goto icn_181_α
icn_185_α:
    goto icn_186_α
icn_185_β:
    goto icn_186_β
    goto icn_185_wentry
icn_185_waft_0:
    astore 199
    getstatic java/lang/System/out Ljava/io/PrintStream;
    aload 199
    invokevirtual java/io/PrintStream/print(Ljava/lang/String;)V
    getstatic java/lang/System/out Ljava/io/PrintStream;
    ldc ""
    invokevirtual java/io/PrintStream/println(Ljava/lang/String;)V
    aload 199
    goto icn_184_condok
icn_185_wentry:
    goto icn_186_α
icn_184_condok:
    pop
    goto icn_184_wbstart
icn_187_α:
    goto icn_181_α
icn_187_β:
    goto icn_181_α
icn_184_wbstart:
    goto icn_187_α
icn_184_wbdrain:
    pop2
icn_184_top:
    goto icn_185_α
icn_184_α:
    goto icn_185_α
icn_184_β:
    goto icn_181_α
icn_189_α:
    goto icn_184_α
icn_189_β:
    goto icn_184_α
icn_188_α:
    goto icn_189_α
icn_188_β:
    goto icn_189_β
    goto icn_188_wentry
icn_188_waft_0:
    astore 200
    getstatic java/lang/System/out Ljava/io/PrintStream;
    aload 200
    invokevirtual java/io/PrintStream/print(Ljava/lang/String;)V
    getstatic java/lang/System/out Ljava/io/PrintStream;
    ldc ""
    invokevirtual java/io/PrintStream/println(Ljava/lang/String;)V
    aload 200
    goto icn_main_s6_sdrain
icn_188_wentry:
    goto icn_189_α
icn_main_s6_sdrain:
    pop
    goto icn_184_α
icn_191_α:
    getstatic rung36_jcon_io/icn_stdin_init I
    ifne icn_191_rd_call
    new java/io/BufferedReader
    dup
    new java/io/InputStreamReader
    dup
    getstatic java/lang/System/in Ljava/io/InputStream;
    invokespecial java/io/InputStreamReader/<init>(Ljava/io/InputStream;)V
    invokespecial java/io/BufferedReader/<init>(Ljava/io/Reader;)V
    putstatic rung36_jcon_io/icn_stdin_reader Ljava/lang/Object;
    iconst_1
    putstatic rung36_jcon_io/icn_stdin_init I
icn_191_rd_call:
    getstatic rung36_jcon_io/icn_stdin_reader Ljava/lang/Object;
    checkcast java/io/BufferedReader
    invokevirtual java/io/BufferedReader/readLine()Ljava/lang/String;
    dup
    ifnull icn_191_rd_null
    goto icn_190_waft_0
icn_191_rd_null:
    pop
    goto icn_188_α
icn_191_β:
    goto icn_188_α
icn_190_α:
    goto icn_191_α
icn_190_β:
    goto icn_191_β
    goto icn_190_wentry
icn_190_waft_0:
    astore 201
    getstatic java/lang/System/out Ljava/io/PrintStream;
    aload 201
    invokevirtual java/io/PrintStream/print(Ljava/lang/String;)V
    getstatic java/lang/System/out Ljava/io/PrintStream;
    ldc ""
    invokevirtual java/io/PrintStream/println(Ljava/lang/String;)V
    aload 201
    goto icn_main_s5_sdrain
icn_190_wentry:
    goto icn_191_α
icn_main_s5_sdrain:
    pop
    goto icn_188_α
icn_192_α:
    getstatic java/lang/System/out Ljava/io/PrintStream;
    ldc ""
    invokevirtual java/io/PrintStream/println(Ljava/lang/String;)V
    goto icn_main_s4_sdrain
icn_192_β:
    goto icn_190_α
icn_main_s4_sdrain:
    pop2
    goto icn_190_α
;  VAR
icn_196_α:
    getstatic rung36_jcon_io/icn_pv_main_f J
    goto icn_195_type_after
icn_196_β:
    goto icn_193_pump
icn_195_α:
    goto icn_196_α
icn_195_β:
    goto icn_196_β
icn_195_type_after:
    pop2
    ldc "integer"
    goto icn_194_waft_0
;  STR
icn_197_α:
    ldc ": "
    goto icn_194_waft_1
icn_197_β:
    goto icn_193_pump
;  VAR
icn_199_α:
    getstatic rung36_jcon_io/icn_pv_main_f J
    goto icn_198_image_after
icn_199_β:
    goto icn_193_pump
icn_198_α:
    goto icn_199_α
icn_198_β:
    goto icn_199_β
icn_198_image_after:
    invokestatic java/lang/Long/toString(J)Ljava/lang/String;
    goto icn_194_waft_2
icn_194_α:
    goto icn_195_α
icn_194_β:
    goto icn_195_β
    goto icn_194_wentry
icn_194_waft_0:
    astore 202
    getstatic java/lang/System/out Ljava/io/PrintStream;
    aload 202
    invokevirtual java/io/PrintStream/print(Ljava/lang/String;)V
    goto icn_197_α
icn_194_waft_1:
    astore 203
    getstatic java/lang/System/out Ljava/io/PrintStream;
    aload 203
    invokevirtual java/io/PrintStream/print(Ljava/lang/String;)V
    goto icn_198_α
icn_194_waft_2:
    astore 204
    getstatic java/lang/System/out Ljava/io/PrintStream;
    aload 204
    invokevirtual java/io/PrintStream/print(Ljava/lang/String;)V
    getstatic java/lang/System/out Ljava/io/PrintStream;
    ldc ""
    invokevirtual java/io/PrintStream/println(Ljava/lang/String;)V
    aload 204
    goto icn_193_bdrain
icn_194_wentry:
    goto icn_195_α
;  VAR
icn_202_α:
    getstatic rung36_jcon_io/icn_pv_main_L Ljava/util/ArrayList;
    goto icn_201_bang_st
icn_202_β:
    goto icn_192_α
icn_201_α:
    goto icn_202_α
icn_201_β:
    goto icn_201_bang_chk
icn_201_bang_st:
    putstatic rung36_jcon_io/icn_201_bang_list Ljava/util/ArrayList;
    iconst_0
    putstatic rung36_jcon_io/icn_201_bang_idx I
icn_201_bang_chk:
    getstatic rung36_jcon_io/icn_201_bang_list Ljava/util/ArrayList;
    invokevirtual java/util/ArrayList/size()I
    getstatic rung36_jcon_io/icn_201_bang_idx I
    if_icmple icn_192_α
    getstatic rung36_jcon_io/icn_201_bang_list Ljava/util/ArrayList;
    getstatic rung36_jcon_io/icn_201_bang_idx I
    invokevirtual java/util/ArrayList/get(I)Ljava/lang/Object;
icn_201_bang_ok:
    checkcast java/lang/Long
    invokevirtual java/lang/Long/longValue()J
    getstatic rung36_jcon_io/icn_201_bang_idx I
    iconst_1
    iadd
    putstatic rung36_jcon_io/icn_201_bang_idx I
    goto icn_200_store
icn_200_α:
    goto icn_201_α
icn_200_β:
    goto icn_201_β
icn_200_store:
    putstatic rung36_jcon_io/icn_pv_main_f J
    getstatic rung36_jcon_io/icn_pv_main_f J
    goto icn_193_gdrain
icn_193_gdrain:
    pop2
    goto icn_194_α
icn_193_bdrain:
    pop
icn_193_pump:
    goto icn_200_β
icn_193_α:
    goto icn_200_α
icn_193_β:
    goto icn_192_α
;  VAR
icn_205_α:
    getstatic rung36_jcon_io/icn_pv_main_L Ljava/util/ArrayList;
    goto icn_204_sort_rel
icn_205_β:
    goto icn_193_α
icn_204_α:
    goto icn_205_α
icn_204_β:
    goto icn_193_α
icn_204_sort_rel:
    putstatic rung36_jcon_io/icn_204_sort_list Ljava/util/ArrayList;
    getstatic rung36_jcon_io/icn_204_sort_list Ljava/util/ArrayList;
    invokestatic rung36_jcon_io/icn_builtin_sort(Ljava/util/ArrayList;)Ljava/util/ArrayList;
    goto icn_203_store
icn_203_α:
    goto icn_204_α
icn_203_β:
    goto icn_204_β
icn_203_store:
    putstatic rung36_jcon_io/icn_pv_main_L Ljava/util/ArrayList;
    getstatic rung36_jcon_io/icn_pv_main_L Ljava/util/ArrayList;
    goto icn_main_s2_sdrain
icn_main_s2_sdrain:
    pop
    goto icn_193_α
icn_207_α:
    new java/util/ArrayList
    dup
    invokespecial java/util/ArrayList/<init>()V
    putstatic rung36_jcon_io/icn_207_mklist Ljava/util/ArrayList;
;  VAR
icn_208_α:
    getstatic rung36_jcon_io/icn_gvar_&input J
    goto icn_207_mke_0
icn_208_β:
    goto icn_203_α
    goto icn_208_α
icn_207_mke_0:
    invokestatic java/lang/Long/valueOf(J)Ljava/lang/Long;
    putstatic rung36_jcon_io/icn_207_elem_0 Ljava/lang/Object;
    getstatic rung36_jcon_io/icn_207_mklist Ljava/util/ArrayList;
    getstatic rung36_jcon_io/icn_207_elem_0 Ljava/lang/Object;
    invokevirtual java/util/ArrayList/add(Ljava/lang/Object;)Z
    pop
;  VAR
icn_209_α:
    getstatic rung36_jcon_io/icn_gvar_&output J
    goto icn_207_mke_1
icn_209_β:
    goto icn_203_α
    goto icn_209_α
icn_207_mke_1:
    invokestatic java/lang/Long/valueOf(J)Ljava/lang/Long;
    putstatic rung36_jcon_io/icn_207_elem_1 Ljava/lang/Object;
    getstatic rung36_jcon_io/icn_207_mklist Ljava/util/ArrayList;
    getstatic rung36_jcon_io/icn_207_elem_1 Ljava/lang/Object;
    invokevirtual java/util/ArrayList/add(Ljava/lang/Object;)Z
    pop
;  VAR
icn_210_α:
    getstatic rung36_jcon_io/icn_gvar_&errout J
    goto icn_207_mke_2
icn_210_β:
    goto icn_203_α
    goto icn_210_α
icn_207_mke_2:
    invokestatic java/lang/Long/valueOf(J)Ljava/lang/Long;
    putstatic rung36_jcon_io/icn_207_elem_2 Ljava/lang/Object;
    getstatic rung36_jcon_io/icn_207_mklist Ljava/util/ArrayList;
    getstatic rung36_jcon_io/icn_207_elem_2 Ljava/lang/Object;
    invokevirtual java/util/ArrayList/add(Ljava/lang/Object;)Z
    pop
icn_213_α:
    goto icn_203_α
icn_213_β:
    goto icn_203_α
icn_214_α:
    goto icn_213_α
icn_214_β:
    goto icn_213_α
icn_212_alt_g0:
    pop
    lconst_0
    putstatic rung36_jcon_io/icn_212_alt_val J
    sipush 1
    putstatic rung36_jcon_io/icn_212_alt_gate I
    getstatic rung36_jcon_io/icn_212_alt_val J
    goto icn_211_store
icn_212_alt_g1:
    putstatic rung36_jcon_io/icn_212_alt_val J
    sipush 2
    putstatic rung36_jcon_io/icn_212_alt_gate I
    getstatic rung36_jcon_io/icn_212_alt_val J
    goto icn_211_store
icn_212_α:
    iconst_0
    putstatic rung36_jcon_io/icn_212_alt_gate I
    goto icn_214_α
icn_212_β:
    getstatic rung36_jcon_io/icn_212_alt_gate I
    tableswitch 1 2
        icn_214_β
        icn_213_β
        default: icn_203_α
icn_211_α:
    goto icn_212_α
icn_211_β:
    goto icn_212_β
icn_211_store:
    putstatic rung36_jcon_io/icn_pv_main_m J
    getstatic rung36_jcon_io/icn_pv_main_m J
    goto icn_207_mke_3
    goto icn_211_α
icn_207_mke_3:
    invokestatic java/lang/Long/valueOf(J)Ljava/lang/Long;
    putstatic rung36_jcon_io/icn_207_elem_3 Ljava/lang/Object;
    getstatic rung36_jcon_io/icn_207_mklist Ljava/util/ArrayList;
    getstatic rung36_jcon_io/icn_207_elem_3 Ljava/lang/Object;
    invokevirtual java/util/ArrayList/add(Ljava/lang/Object;)Z
    pop
icn_216_α:
    goto icn_203_α
icn_216_β:
    goto icn_203_α
icn_215_α:
    goto icn_216_α
icn_215_β:
    goto icn_216_β
icn_215_store:
    putstatic rung36_jcon_io/icn_pv_main_n J
    getstatic rung36_jcon_io/icn_pv_main_n J
    goto icn_207_mke_4
    goto icn_215_α
icn_207_mke_4:
    invokestatic java/lang/Long/valueOf(J)Ljava/lang/Long;
    putstatic rung36_jcon_io/icn_207_elem_4 Ljava/lang/Object;
    getstatic rung36_jcon_io/icn_207_mklist Ljava/util/ArrayList;
    getstatic rung36_jcon_io/icn_207_elem_4 Ljava/lang/Object;
    invokevirtual java/util/ArrayList/add(Ljava/lang/Object;)Z
    pop
    getstatic rung36_jcon_io/icn_207_mklist Ljava/util/ArrayList;
    goto icn_206_store
icn_207_β:
    goto icn_203_α
icn_206_α:
    goto icn_207_α
icn_206_β:
    goto icn_207_β
icn_206_store:
    putstatic rung36_jcon_io/icn_pv_main_L Ljava/util/ArrayList;
    getstatic rung36_jcon_io/icn_pv_main_L Ljava/util/ArrayList;
    goto icn_main_s1_sdrain
icn_main_s1_sdrain:
    pop
    goto icn_203_α
icn_main_done:
    return
.end method

.method public static icn_wfile()V
    .limit stack 16
    .limit locals 295
    lconst_0
    lstore 0
    lconst_0
    lstore 2
    lconst_0
    lstore 4
    lconst_0
    lstore 6
    lconst_0
    lstore 8
    lconst_0
    lstore 10
    lconst_0
    lstore 12
    lconst_0
    lstore 14
    lconst_0
    lstore 16
    lconst_0
    lstore 18
    lconst_0
    lstore 20
    lconst_0
    lstore 22
    lconst_0
    lstore 24
    lconst_0
    lstore 26
    lconst_0
    lstore 28
    lconst_0
    lstore 30
    lconst_0
    lstore 32
    lconst_0
    lstore 34
    lconst_0
    lstore 36
    lconst_0
    lstore 38
    lconst_0
    lstore 40
    lconst_0
    lstore 42
    lconst_0
    lstore 44
    lconst_0
    lstore 46
    lconst_0
    lstore 48
    lconst_0
    lstore 50
    lconst_0
    lstore 52
    lconst_0
    lstore 54
    lconst_0
    lstore 56
    lconst_0
    lstore 58
    lconst_0
    lstore 60
    lconst_0
    lstore 62
    iconst_0
    istore 84
    iconst_0
    istore 85
    iconst_0
    istore 86
    iconst_0
    istore 87
    aconst_null
    astore 148
    aconst_null
    astore 149
    aconst_null
    astore 150
    aconst_null
    astore 151
    aconst_null
    astore 152
    aconst_null
    astore 153
    aconst_null
    astore 154
    getstatic rung36_jcon_io/icn_arg_str_0 Ljava/lang/String;
    putstatic rung36_jcon_io/icn_pv_wfile_name Ljava/lang/String;
    getstatic rung36_jcon_io/icn_arg_str_1 Ljava/lang/String;
    putstatic rung36_jcon_io/icn_pv_wfile_mode Ljava/lang/String;
    getstatic rung36_jcon_io/icn_arg_str_2 Ljava/lang/String;
    putstatic rung36_jcon_io/icn_pv_wfile_s Ljava/lang/String;
    goto icn_249_α
icn_217_α:
    lconst_0
    putstatic rung36_jcon_io/icn_retval J
    iconst_0
    putstatic rung36_jcon_io/icn_failed B
    goto icn_wfile_ret
icn_217_β:
    goto icn_wfile_ret
;  VAR
icn_220_α:
    getstatic rung36_jcon_io/icn_pv_wfile_s Ljava/lang/String;
    goto icn_219_scan_setup
icn_220_β:
    goto icn_217_α
icn_222_α:
    goto icn_221_seq_rf_0
icn_222_β:
    goto icn_221_seq_rf_0
;  STR
icn_225_α:
    ldc " "
    goto icn_224_after
icn_225_β:
    goto icn_221_seq_rf_1
icn_224_α:
    goto icn_225_α
icn_224_β:
    goto icn_225_β
icn_224_after:
;  many: cs String on stack
    getstatic rung36_jcon_io/icn_subject Ljava/lang/String;
    getstatic rung36_jcon_io/icn_pos I
    invokestatic rung36_jcon_io/icn_builtin_many(Ljava/lang/String;Ljava/lang/String;I)J
    dup2
    lconst_1
    lneg
    lcmp
    ifne icn_224_chk
    pop2
    goto icn_221_seq_rf_1
icn_224_chk:
;  many ok: advance icn_pos
    dup2
    lconst_1
    lsub
    l2i
    putstatic rung36_jcon_io/icn_pos I
    goto icn_223_ta
icn_223_α:
    goto icn_224_α
icn_223_β:
    goto icn_221_seq_rf_1
icn_223_ta:
;  tab: n (long) on stack
    l2i
    getstatic rung36_jcon_io/icn_subject Ljava/lang/String;
    getstatic rung36_jcon_io/icn_pos I
    invokestatic rung36_jcon_io/icn_builtin_tab_str(ILjava/lang/String;I)Ljava/lang/String;
    dup
    ifnonnull icn_223_to
    pop
    goto icn_221_seq_rf_1
icn_223_to:
;  tab ok: advance icn_pos = n-1, push String → γ
    goto icn_221_seq_rg_1
icn_228_α:
    goto icn_227_succ
icn_228_β:
    goto icn_227_succ
;  NOT
icn_227_α:
    goto icn_228_α
icn_227_β:
    goto icn_228_β
icn_227_cok:
    pop2
    goto icn_221_seq_rf_2
icn_227_succ:
    lconst_0
    goto icn_226_condok
icn_226_condok:
    pop2
    goto icn_226_wbstart
;  VAR
icn_230_α:
    getstatic rung36_jcon_io/icn_pv_wfile_f J
    goto icn_229_waft_0
icn_230_β:
    goto icn_226_wb_rf_0
;  INT
icn_233_α:
    ldc2_w 0
    goto icn_232_alt_g1
icn_233_β:
    goto icn_226_wb_rf_0
;  STR
icn_235_α:
    ldc " "
    goto icn_234_after
icn_235_β:
    goto icn_233_α
icn_234_α:
    goto icn_235_α
icn_234_after:
;  upto α: save cs, enter step
    putstatic rung36_jcon_io/icn_upto_cs_234 Ljava/lang/String;
    goto icn_234_step
icn_234_β:
    goto icn_234_step
icn_234_step:
;  upto step
    getstatic rung36_jcon_io/icn_upto_cs_234 Ljava/lang/String;
    getstatic rung36_jcon_io/icn_subject Ljava/lang/String;
    getstatic rung36_jcon_io/icn_pos I
    invokestatic rung36_jcon_io/icn_builtin_upto_step(Ljava/lang/String;Ljava/lang/String;I)J
    dup2
    lconst_1
    lneg
    lcmp
    ifne icn_234_chk
    pop2
    goto icn_233_α
icn_234_chk:
;  upto: yield 1-based pos (tab advances icn_pos)
    goto icn_232_alt_g0
icn_232_alt_g0:
    putstatic rung36_jcon_io/icn_232_alt_val J
    sipush 1
    putstatic rung36_jcon_io/icn_232_alt_gate I
    getstatic rung36_jcon_io/icn_232_alt_val J
    goto icn_231_ta
icn_232_alt_g1:
    putstatic rung36_jcon_io/icn_232_alt_val J
    sipush 2
    putstatic rung36_jcon_io/icn_232_alt_gate I
    getstatic rung36_jcon_io/icn_232_alt_val J
    goto icn_231_ta
icn_232_α:
    iconst_0
    putstatic rung36_jcon_io/icn_232_alt_gate I
    goto icn_234_α
icn_232_β:
    getstatic rung36_jcon_io/icn_232_alt_gate I
    tableswitch 1 2
        icn_234_β
        icn_233_β
        default: icn_226_wb_rf_0
icn_231_α:
    goto icn_232_α
icn_231_β:
    goto icn_226_wb_rf_0
icn_231_ta:
;  tab: n (long) on stack
    l2i
    getstatic rung36_jcon_io/icn_subject Ljava/lang/String;
    getstatic rung36_jcon_io/icn_pos I
    invokestatic rung36_jcon_io/icn_builtin_tab_str(ILjava/lang/String;I)Ljava/lang/String;
    dup
    ifnonnull icn_231_to
    pop
    goto icn_226_wb_rf_0
icn_231_to:
;  tab ok: advance icn_pos = n-1, push String → γ
    goto icn_229_waft_1
icn_229_α:
    goto icn_230_α
icn_229_β:
    goto icn_230_β
    goto icn_229_wentry
icn_229_waft_0:
    lstore 8
    getstatic java/lang/System/out Ljava/io/PrintStream;
    lload 8
    invokevirtual java/io/PrintStream/print(J)V
    goto icn_231_α
icn_229_waft_1:
    astore 148
    getstatic java/lang/System/out Ljava/io/PrintStream;
    aload 148
    invokevirtual java/io/PrintStream/print(Ljava/lang/String;)V
    getstatic java/lang/System/out Ljava/io/PrintStream;
    ldc ""
    invokevirtual java/io/PrintStream/println(Ljava/lang/String;)V
    aload 148
    goto icn_226_wb_rg_0
icn_229_wentry:
    goto icn_230_α
;  STR
icn_238_α:
    ldc " "
    goto icn_237_after
icn_238_β:
    goto icn_226_top
icn_237_α:
    goto icn_238_α
icn_237_β:
    goto icn_238_β
icn_237_after:
;  many: cs String on stack
    getstatic rung36_jcon_io/icn_subject Ljava/lang/String;
    getstatic rung36_jcon_io/icn_pos I
    invokestatic rung36_jcon_io/icn_builtin_many(Ljava/lang/String;Ljava/lang/String;I)J
    dup2
    lconst_1
    lneg
    lcmp
    ifne icn_237_chk
    pop2
    goto icn_226_top
icn_237_chk:
;  many ok: advance icn_pos
    dup2
    lconst_1
    lsub
    l2i
    putstatic rung36_jcon_io/icn_pos I
    goto icn_236_ta
icn_236_α:
    goto icn_237_α
icn_236_β:
    goto icn_226_top
icn_236_ta:
;  tab: n (long) on stack
    l2i
    getstatic rung36_jcon_io/icn_subject Ljava/lang/String;
    getstatic rung36_jcon_io/icn_pos I
    invokestatic rung36_jcon_io/icn_builtin_tab_str(ILjava/lang/String;I)Ljava/lang/String;
    dup
    ifnonnull icn_236_to
    pop
    goto icn_226_top
icn_236_to:
;  tab ok: advance icn_pos = n-1, push String → γ
    goto icn_226_wbdrain
    goto icn_226_wbstart
icn_226_wb_rg_0:
    pop
    goto icn_236_α
icn_226_wb_rf_0:
    goto icn_236_α
icn_226_wbstart:
    goto icn_229_α
icn_226_wbdrain:
    pop
icn_226_top:
    goto icn_227_α
icn_226_α:
    goto icn_227_α
icn_226_β:
    goto icn_221_seq_rf_2
;  STR
icn_240_α:
    ldc " : "
    goto icn_239_waft_0
icn_240_β:
    goto icn_221_seq_rf_3
icn_241_α:
    goto icn_221_seq_rf_3
icn_241_β:
    goto icn_221_seq_rf_3
icn_239_α:
    goto icn_240_α
icn_239_β:
    goto icn_240_β
    goto icn_239_wentry
icn_239_waft_0:
    astore 149
    getstatic java/lang/System/out Ljava/io/PrintStream;
    aload 149
    invokevirtual java/io/PrintStream/print(Ljava/lang/String;)V
    goto icn_241_α
icn_239_waft_1:
    lstore 10
    getstatic java/lang/System/out Ljava/io/PrintStream;
    lload 10
    invokevirtual java/io/PrintStream/print(J)V
    getstatic java/lang/System/out Ljava/io/PrintStream;
    ldc ""
    invokevirtual java/io/PrintStream/println(Ljava/lang/String;)V
    lload 10
    goto icn_221_seq_rg_3
icn_239_wentry:
    goto icn_240_α
icn_242_α:
    goto icn_221_seq_rf_4
icn_242_β:
    goto icn_221_seq_rf_4
icn_243_α:
    goto icn_219_scan_bfail
icn_243_β:
    goto icn_219_scan_bfail
    goto icn_221_α
icn_221_seq_rg_0:
    pop2
    goto icn_223_α
icn_221_seq_rg_1:
    pop
    goto icn_226_α
icn_221_seq_rg_2:
    pop2
    goto icn_239_α
icn_221_seq_rg_3:
    pop2
    goto icn_242_α
icn_221_seq_rg_4:
    pop2
    goto icn_243_α
icn_221_seq_rf_0:
    goto icn_223_α
icn_221_seq_rf_1:
    goto icn_226_α
icn_221_seq_rf_2:
    goto icn_239_α
icn_221_seq_rf_3:
    goto icn_242_α
icn_221_seq_rf_4:
    goto icn_243_α
icn_221_α:
    goto icn_222_α
icn_221_β:
    goto icn_243_β
;  SCAN
icn_219_α:
    goto icn_220_α
icn_219_β:
    goto icn_219_scan_beta
icn_219_scan_setup:
;  SCAN save+install
    getstatic rung36_jcon_io/icn_subject Ljava/lang/String;
    putstatic rung36_jcon_io/icn_scan_oldsubj_219 Ljava/lang/String;
    getstatic rung36_jcon_io/icn_pos I
    putstatic rung36_jcon_io/icn_scan_oldpos_219 I
    putstatic rung36_jcon_io/icn_subject Ljava/lang/String;
    iconst_0
    putstatic rung36_jcon_io/icn_pos I
    goto icn_221_α
icn_219_scan_bok:
;  SCAN restore (body ok)
    getstatic rung36_jcon_io/icn_scan_oldsubj_219 Ljava/lang/String;
    putstatic rung36_jcon_io/icn_subject Ljava/lang/String;
    getstatic rung36_jcon_io/icn_scan_oldpos_219 I
    putstatic rung36_jcon_io/icn_pos I
    goto icn_wfile_s3_sdrain
icn_219_scan_bfail:
;  SCAN restore (body fail)
    getstatic rung36_jcon_io/icn_scan_oldsubj_219 Ljava/lang/String;
    putstatic rung36_jcon_io/icn_subject Ljava/lang/String;
    getstatic rung36_jcon_io/icn_scan_oldpos_219 I
    putstatic rung36_jcon_io/icn_pos I
    goto icn_220_β
icn_219_scan_beta:
;  SCAN restore (outer β)
    getstatic rung36_jcon_io/icn_scan_oldsubj_219 Ljava/lang/String;
    putstatic rung36_jcon_io/icn_subject Ljava/lang/String;
    getstatic rung36_jcon_io/icn_scan_oldpos_219 I
    putstatic rung36_jcon_io/icn_pos I
    goto icn_221_β
;  STR
icn_245_α:
    ldc "can't open"
    goto icn_244_waft_0
icn_245_β:
    goto icn_217_α
icn_244_α:
    goto icn_245_α
icn_244_β:
    goto icn_245_β
    goto icn_244_wentry
icn_244_waft_0:
    astore 150
    getstatic java/lang/System/out Ljava/io/PrintStream;
    aload 150
    invokevirtual java/io/PrintStream/print(Ljava/lang/String;)V
    getstatic java/lang/System/out Ljava/io/PrintStream;
    ldc ""
    invokevirtual java/io/PrintStream/println(Ljava/lang/String;)V
    aload 150
    goto icn_wfile_s3_sdrain
icn_244_wentry:
    goto icn_245_α
icn_247_α:
    goto icn_218_else
icn_247_β:
    goto icn_218_else
icn_246_α:
    goto icn_247_α
icn_246_β:
    goto icn_247_β
icn_246_store:
    putstatic rung36_jcon_io/icn_pv_wfile_f J
    getstatic rung36_jcon_io/icn_pv_wfile_f J
    goto icn_218_then
icn_218_then:
    pop2
    goto icn_219_α
icn_218_else:
    goto icn_244_α
icn_218_α:
    goto icn_246_α
icn_218_β:
    goto icn_246_β
icn_wfile_s3_sdrain:
    pop
    goto icn_217_α
icn_248_α:
    goto icn_218_α
icn_248_β:
    goto icn_218_α
icn_wfile_s2_sdrain:
    pop2
    goto icn_218_α
icn_249_α:
    getstatic java/lang/System/out Ljava/io/PrintStream;
    ldc ""
    invokevirtual java/io/PrintStream/println(Ljava/lang/String;)V
    goto icn_wfile_s1_sdrain
icn_249_β:
    goto icn_248_α
icn_wfile_s1_sdrain:
    pop2
    goto icn_248_α
icn_wfile_done:
    iconst_0
    putstatic rung36_jcon_io/icn_suspended B
    iconst_0
    putstatic rung36_jcon_io/icn_suspend_id I
    iconst_1
    putstatic rung36_jcon_io/icn_failed B
    return
icn_wfile_ret:
    iconst_0
    putstatic rung36_jcon_io/icn_failed B
    return
icn_wfile_sret:
    return
.end method

.method public static icn_rfile()V
    .limit stack 16
    .limit locals 303
    lconst_0
    lstore 0
    lconst_0
    lstore 2
    lconst_0
    lstore 4
    lconst_0
    lstore 6
    lconst_0
    lstore 8
    lconst_0
    lstore 10
    lconst_0
    lstore 12
    lconst_0
    lstore 14
    lconst_0
    lstore 16
    lconst_0
    lstore 18
    lconst_0
    lstore 20
    lconst_0
    lstore 22
    lconst_0
    lstore 24
    lconst_0
    lstore 26
    lconst_0
    lstore 28
    lconst_0
    lstore 30
    lconst_0
    lstore 32
    lconst_0
    lstore 34
    lconst_0
    lstore 36
    lconst_0
    lstore 38
    lconst_0
    lstore 40
    lconst_0
    lstore 42
    lconst_0
    lstore 44
    lconst_0
    lstore 46
    lconst_0
    lstore 48
    lconst_0
    lstore 50
    lconst_0
    lstore 52
    lconst_0
    lstore 54
    lconst_0
    lstore 56
    lconst_0
    lstore 58
    lconst_0
    lstore 60
    lconst_0
    lstore 62
    iconst_0
    istore 84
    iconst_0
    istore 85
    iconst_0
    istore 86
    iconst_0
    istore 87
    aconst_null
    astore 148
    aconst_null
    astore 149
    aconst_null
    astore 150
    aconst_null
    astore 151
    aconst_null
    astore 152
    getstatic rung36_jcon_io/icn_arg_str_0 Ljava/lang/String;
    putstatic rung36_jcon_io/icn_pv_rfile_name Ljava/lang/String;
    goto icn_291_α
icn_250_α:
    lconst_0
    putstatic rung36_jcon_io/icn_retval J
    iconst_0
    putstatic rung36_jcon_io/icn_failed B
    goto icn_rfile_ret
icn_250_β:
    goto icn_rfile_ret
icn_251_α:
    goto icn_250_α
icn_251_β:
    goto icn_250_α
icn_rfile_s18_sdrain:
    pop2
    goto icn_250_α
icn_252_α:
    getstatic java/lang/System/out Ljava/io/PrintStream;
    ldc ""
    invokevirtual java/io/PrintStream/println(Ljava/lang/String;)V
    goto icn_rfile_s17_sdrain
icn_252_β:
    goto icn_251_α
icn_rfile_s17_sdrain:
    pop2
    goto icn_251_α
icn_255_α:
    goto icn_253_pump
icn_255_β:
    goto icn_253_pump
icn_256_α:
    goto icn_253_pump
icn_256_β:
    goto icn_253_pump
icn_257_α:
    goto icn_254_else
icn_257_β:
    goto icn_254_else
icn_254_then:
    pop2
    goto icn_255_α
icn_254_else:
    goto icn_256_α
icn_254_α:
    goto icn_257_α
icn_254_β:
    goto icn_257_β
;  INT
icn_260_α:
    ldc2_w 30
    goto icn_259_tb_r1
icn_260_β:
    goto icn_252_α
;  INT
icn_262_α:
    ldc2_w 30
    goto icn_261_neg
icn_262_β:
    goto icn_252_α
;  NEG
icn_261_α:
    goto icn_262_α
icn_261_β:
    goto icn_262_β
icn_261_neg:
    lneg
    goto icn_259_tb_r2
;  INT
icn_264_α:
    ldc2_w 1
    goto icn_263_neg
icn_264_β:
    goto icn_252_α
;  NEG
icn_263_α:
    goto icn_264_α
icn_263_β:
    goto icn_264_β
icn_263_neg:
    lneg
    goto icn_259_tb_r3
;  TO_BY -- forward-only, supports integer and real
icn_259_α:
    goto icn_260_α
icn_259_tb_r1:
    putstatic rung36_jcon_io/icn_259_toby_i J
    goto icn_261_α
icn_259_tb_r2:
    putstatic rung36_jcon_io/icn_259_toby_end J
    goto icn_263_α
icn_259_tb_r3:
    putstatic rung36_jcon_io/icn_259_toby_stp J
    goto icn_259_tb_check
icn_259_β:
    getstatic rung36_jcon_io/icn_259_toby_i J
    getstatic rung36_jcon_io/icn_259_toby_stp J
    ladd
    putstatic rung36_jcon_io/icn_259_toby_i J
    goto icn_259_tb_check
icn_259_tb_check:
    getstatic rung36_jcon_io/icn_259_toby_stp J
    lconst_0
    lcmp
    ifgt icn_259_tb_ckp
    getstatic rung36_jcon_io/icn_259_toby_stp J
    lconst_0
    lcmp
    iflt icn_259_tb_ckn
    goto icn_252_α
icn_259_tb_ckp:
    getstatic rung36_jcon_io/icn_259_toby_i J
    getstatic rung36_jcon_io/icn_259_toby_end J
    lcmp
    ifgt icn_252_α
    getstatic rung36_jcon_io/icn_259_toby_i J
    goto icn_258_store
icn_259_tb_ckn:
    getstatic rung36_jcon_io/icn_259_toby_i J
    getstatic rung36_jcon_io/icn_259_toby_end J
    lcmp
    iflt icn_252_α
    getstatic rung36_jcon_io/icn_259_toby_i J
    goto icn_258_store
icn_258_α:
    goto icn_259_α
icn_258_β:
    goto icn_259_β
icn_258_store:
    putstatic rung36_jcon_io/icn_pv_rfile_i J
    getstatic rung36_jcon_io/icn_pv_rfile_i J
    goto icn_253_gdrain
icn_253_gdrain:
    pop2
    goto icn_254_α
icn_253_bdrain:
    pop2
icn_253_pump:
    goto icn_258_β
icn_253_α:
    goto icn_258_α
icn_253_β:
    goto icn_252_α
icn_265_α:
    goto icn_253_α
icn_265_β:
    goto icn_253_α
icn_rfile_s15_sdrain:
    pop2
    goto icn_253_α
icn_266_α:
    getstatic java/lang/System/out Ljava/io/PrintStream;
    ldc ""
    invokevirtual java/io/PrintStream/println(Ljava/lang/String;)V
    goto icn_rfile_s14_sdrain
icn_266_β:
    goto icn_265_α
icn_rfile_s14_sdrain:
    pop2
    goto icn_265_α
icn_268_α:
    goto icn_266_α
icn_268_β:
    goto icn_266_α
icn_267_condok:
    pop2
    goto icn_268_α
icn_267_α:
    goto icn_268_α
icn_267_β:
    goto icn_266_α
icn_269_α:
    goto icn_267_α
icn_269_β:
    goto icn_267_α
icn_rfile_s12_sdrain:
    pop2
    goto icn_267_α
icn_270_α:
    goto icn_269_α
icn_270_β:
    goto icn_269_α
icn_rfile_s11_sdrain:
    pop2
    goto icn_269_α
icn_271_α:
    getstatic java/lang/System/out Ljava/io/PrintStream;
    ldc ""
    invokevirtual java/io/PrintStream/println(Ljava/lang/String;)V
    goto icn_rfile_s10_sdrain
icn_271_β:
    goto icn_270_α
icn_rfile_s10_sdrain:
    pop2
    goto icn_270_α
icn_273_α:
    goto icn_271_α
icn_273_β:
    goto icn_271_α
icn_272_condok:
    pop2
    goto icn_272_wbstart
icn_274_α:
    goto icn_272_top
icn_274_β:
    goto icn_272_top
icn_272_wbstart:
    goto icn_274_α
icn_272_wbdrain:
    pop2
icn_272_top:
    goto icn_273_α
icn_272_α:
    goto icn_273_α
icn_272_β:
    goto icn_271_α
icn_275_α:
    goto icn_272_α
icn_275_β:
    goto icn_272_α
icn_rfile_s8_sdrain:
    pop2
    goto icn_272_α
icn_276_α:
    goto icn_275_α
icn_276_β:
    goto icn_275_α
icn_rfile_s7_sdrain:
    pop2
    goto icn_275_α
icn_278_α:
    goto icn_276_α
icn_278_β:
    goto icn_276_α
icn_277_gdrain:
    pop2
icn_277_pump:
    goto icn_278_β
icn_277_α:
    goto icn_278_α
icn_277_β:
    goto icn_276_α
icn_279_α:
    goto icn_277_α
icn_279_β:
    goto icn_277_α
icn_rfile_s5_sdrain:
    pop2
    goto icn_277_α
icn_280_α:
    getstatic java/lang/System/out Ljava/io/PrintStream;
    ldc ""
    invokevirtual java/io/PrintStream/println(Ljava/lang/String;)V
    goto icn_rfile_s4_sdrain
icn_280_β:
    goto icn_279_α
icn_rfile_s4_sdrain:
    pop2
    goto icn_279_α
icn_282_α:
    goto icn_280_α
icn_282_β:
    goto icn_280_α
icn_281_condok:
    pop2
    goto icn_282_α
icn_281_α:
    goto icn_282_α
icn_281_β:
    goto icn_280_α
;  STR
icn_286_α:
    ldc " can't open"
    goto icn_285_waft_0
icn_286_β:
    goto icn_284_seq_rf_0
icn_285_α:
    goto icn_286_α
icn_285_β:
    goto icn_286_β
    goto icn_285_wentry
icn_285_waft_0:
    astore 148
    getstatic java/lang/System/out Ljava/io/PrintStream;
    aload 148
    invokevirtual java/io/PrintStream/print(Ljava/lang/String;)V
    getstatic java/lang/System/out Ljava/io/PrintStream;
    ldc ""
    invokevirtual java/io/PrintStream/println(Ljava/lang/String;)V
    aload 148
    goto icn_284_seq_rg_0
icn_285_wentry:
    goto icn_286_α
icn_287_α:
    iconst_1
    putstatic rung36_jcon_io/icn_failed B
    goto icn_rfile_done
icn_287_β:
    goto icn_281_α
    goto icn_284_α
icn_284_seq_rg_0:
    pop
    goto icn_287_α
icn_284_seq_rf_0:
    goto icn_287_α
icn_284_α:
    goto icn_285_α
icn_284_β:
    goto icn_287_β
icn_290_α:
    goto icn_288_succ
icn_290_β:
    goto icn_288_succ
icn_289_α:
    goto icn_290_α
icn_289_β:
    goto icn_290_β
icn_289_store:
    putstatic rung36_jcon_io/icn_pv_rfile_f J
    getstatic rung36_jcon_io/icn_pv_rfile_f J
    goto icn_288_cok
;  NOT
icn_288_α:
    goto icn_289_α
icn_288_β:
    goto icn_289_β
icn_288_cok:
    pop2
    goto icn_283_else
icn_288_succ:
    lconst_0
    goto icn_283_then
icn_283_then:
    pop2
    goto icn_284_α
icn_283_else:
    goto icn_281_α
icn_283_α:
    goto icn_288_α
icn_283_β:
    goto icn_288_β
icn_rfile_s2_sdrain:
    pop2
    goto icn_281_α
icn_291_α:
    goto icn_283_α
icn_291_β:
    goto icn_283_α
icn_rfile_s1_sdrain:
    pop2
    goto icn_283_α
icn_rfile_done:
    iconst_0
    putstatic rung36_jcon_io/icn_suspended B
    iconst_0
    putstatic rung36_jcon_io/icn_suspend_id I
    iconst_1
    putstatic rung36_jcon_io/icn_failed B
    return
icn_rfile_ret:
    iconst_0
    putstatic rung36_jcon_io/icn_failed B
    return
icn_rfile_sret:
    return
.end method

.method public static icn_tsys()V
    .limit stack 16
    .limit locals 304
    lconst_0
    lstore 0
    lconst_0
    lstore 2
    lconst_0
    lstore 4
    lconst_0
    lstore 6
    lconst_0
    lstore 8
    lconst_0
    lstore 10
    lconst_0
    lstore 12
    lconst_0
    lstore 14
    lconst_0
    lstore 16
    lconst_0
    lstore 18
    lconst_0
    lstore 20
    lconst_0
    lstore 22
    lconst_0
    lstore 24
    lconst_0
    lstore 26
    lconst_0
    lstore 28
    lconst_0
    lstore 30
    lconst_0
    lstore 32
    lconst_0
    lstore 34
    lconst_0
    lstore 36
    lconst_0
    lstore 38
    lconst_0
    lstore 40
    lconst_0
    lstore 42
    lconst_0
    lstore 44
    lconst_0
    lstore 46
    lconst_0
    lstore 48
    lconst_0
    lstore 50
    lconst_0
    lstore 52
    lconst_0
    lstore 54
    lconst_0
    lstore 56
    lconst_0
    lstore 58
    lconst_0
    lstore 60
    lconst_0
    lstore 62
    iconst_0
    istore 84
    iconst_0
    istore 85
    iconst_0
    istore 86
    iconst_0
    istore 87
    aconst_null
    astore 148
    aconst_null
    astore 149
    aconst_null
    astore 150
    aconst_null
    astore 151
    aconst_null
    astore 152
    aconst_null
    astore 153
    getstatic rung36_jcon_io/icn_arg_str_0 Ljava/lang/String;
    putstatic rung36_jcon_io/icn_pv_tsys_s Ljava/lang/String;
    goto icn_294_α
icn_292_α:
    lconst_0
    putstatic rung36_jcon_io/icn_retval J
    iconst_0
    putstatic rung36_jcon_io/icn_failed B
    goto icn_tsys_ret
icn_292_β:
    goto icn_tsys_ret
icn_293_α:
    goto icn_292_α
icn_293_β:
    goto icn_292_α
icn_tsys_s1_sdrain:
    pop2
    goto icn_292_α
;  STR
icn_295_α:
    ldc "$ "
    goto icn_294_waft_0
icn_295_β:
    goto icn_293_α
;  VAR
icn_296_α:
    getstatic rung36_jcon_io/icn_pv_tsys_s Ljava/lang/String;
    goto icn_294_waft_1
icn_296_β:
    goto icn_293_α
icn_294_α:
    goto icn_295_α
icn_294_β:
    goto icn_295_β
    goto icn_294_wentry
icn_294_waft_0:
    astore 148
    getstatic java/lang/System/out Ljava/io/PrintStream;
    aload 148
    invokevirtual java/io/PrintStream/print(Ljava/lang/String;)V
    goto icn_296_α
icn_294_waft_1:
    astore 149
    getstatic java/lang/System/out Ljava/io/PrintStream;
    aload 149
    invokevirtual java/io/PrintStream/print(Ljava/lang/String;)V
    getstatic java/lang/System/out Ljava/io/PrintStream;
    ldc ""
    invokevirtual java/io/PrintStream/println(Ljava/lang/String;)V
    aload 149
    goto icn_tsys_s0_sdrain
icn_294_wentry:
    goto icn_295_α
icn_tsys_s0_sdrain:
    pop
    goto icn_293_α
icn_tsys_done:
    iconst_0
    putstatic rung36_jcon_io/icn_suspended B
    iconst_0
    putstatic rung36_jcon_io/icn_suspend_id I
    iconst_1
    putstatic rung36_jcon_io/icn_failed B
    return
icn_tsys_ret:
    iconst_0
    putstatic rung36_jcon_io/icn_failed B
    return
icn_tsys_sret:
    return
.end method

.method public static icn_tpipe()V
    .limit stack 16
    .limit locals 351
    lconst_0
    lstore 0
    lconst_0
    lstore 2
    lconst_0
    lstore 4
    lconst_0
    lstore 6
    lconst_0
    lstore 8
    lconst_0
    lstore 10
    lconst_0
    lstore 12
    lconst_0
    lstore 14
    lconst_0
    lstore 16
    lconst_0
    lstore 18
    lconst_0
    lstore 20
    lconst_0
    lstore 22
    lconst_0
    lstore 24
    lconst_0
    lstore 26
    lconst_0
    lstore 28
    lconst_0
    lstore 30
    lconst_0
    lstore 32
    lconst_0
    lstore 34
    lconst_0
    lstore 36
    lconst_0
    lstore 38
    lconst_0
    lstore 40
    lconst_0
    lstore 42
    lconst_0
    lstore 44
    lconst_0
    lstore 46
    lconst_0
    lstore 48
    lconst_0
    lstore 50
    lconst_0
    lstore 52
    lconst_0
    lstore 54
    lconst_0
    lstore 56
    lconst_0
    lstore 58
    lconst_0
    lstore 60
    lconst_0
    lstore 62
    iconst_0
    istore 84
    iconst_0
    istore 85
    iconst_0
    istore 86
    iconst_0
    istore 87
    aconst_null
    astore 148
    aconst_null
    astore 149
    aconst_null
    astore 150
    aconst_null
    astore 151
    aconst_null
    astore 152
    aconst_null
    astore 153
    aconst_null
    astore 154
    aconst_null
    astore 155
    aconst_null
    astore 156
    aconst_null
    astore 157
    aconst_null
    astore 158
    aconst_null
    astore 159
    aconst_null
    astore 160
    aconst_null
    astore 161
    aconst_null
    astore 162
    aconst_null
    astore 163
    aconst_null
    astore 164
    aconst_null
    astore 165
    aconst_null
    astore 166
    goto icn_362_α
icn_297_α:
    lconst_0
    putstatic rung36_jcon_io/icn_retval J
    iconst_0
    putstatic rung36_jcon_io/icn_failed B
    goto icn_tpipe_ret
icn_297_β:
    goto icn_tpipe_ret
icn_298_α:
    goto icn_297_α
icn_298_β:
    goto icn_297_α
icn_tpipe_s24_sdrain:
    pop2
    goto icn_297_α
;  STR
icn_300_α:
    ldc "--- done closing output pipe"
    goto icn_299_waft_0
icn_300_β:
    goto icn_298_α
icn_299_α:
    goto icn_300_α
icn_299_β:
    goto icn_300_β
    goto icn_299_wentry
icn_299_waft_0:
    astore 148
    getstatic java/lang/System/out Ljava/io/PrintStream;
    aload 148
    invokevirtual java/io/PrintStream/print(Ljava/lang/String;)V
    getstatic java/lang/System/out Ljava/io/PrintStream;
    ldc ""
    invokevirtual java/io/PrintStream/println(Ljava/lang/String;)V
    aload 148
    goto icn_tpipe_s23_sdrain
icn_299_wentry:
    goto icn_300_α
icn_tpipe_s23_sdrain:
    pop
    goto icn_298_α
icn_301_α:
    goto icn_299_α
icn_301_β:
    goto icn_299_α
icn_tpipe_s22_sdrain:
    pop2
    goto icn_299_α
;  STR
icn_303_α:
    ldc "--- closing output pipe"
    goto icn_302_waft_0
icn_303_β:
    goto icn_301_α
icn_302_α:
    goto icn_303_α
icn_302_β:
    goto icn_303_β
    goto icn_302_wentry
icn_302_waft_0:
    astore 149
    getstatic java/lang/System/out Ljava/io/PrintStream;
    aload 149
    invokevirtual java/io/PrintStream/print(Ljava/lang/String;)V
    getstatic java/lang/System/out Ljava/io/PrintStream;
    ldc ""
    invokevirtual java/io/PrintStream/println(Ljava/lang/String;)V
    aload 149
    goto icn_tpipe_s21_sdrain
icn_302_wentry:
    goto icn_303_α
icn_tpipe_s21_sdrain:
    pop
    goto icn_301_α
;  VAR
icn_305_α:
    getstatic rung36_jcon_io/icn_pv_tpipe_p J
    goto icn_304_waft_0
icn_305_β:
    goto icn_302_α
;  STR
icn_306_α:
    ldc "and the mome raths outgrabe"
    goto icn_304_waft_1
icn_306_β:
    goto icn_302_α
icn_304_α:
    goto icn_305_α
icn_304_β:
    goto icn_305_β
    goto icn_304_wentry
icn_304_waft_0:
    lstore 2
    getstatic java/lang/System/out Ljava/io/PrintStream;
    lload 2
    invokevirtual java/io/PrintStream/print(J)V
    goto icn_306_α
icn_304_waft_1:
    astore 150
    getstatic java/lang/System/out Ljava/io/PrintStream;
    aload 150
    invokevirtual java/io/PrintStream/print(Ljava/lang/String;)V
    getstatic java/lang/System/out Ljava/io/PrintStream;
    ldc ""
    invokevirtual java/io/PrintStream/println(Ljava/lang/String;)V
    aload 150
    goto icn_tpipe_s20_sdrain
icn_304_wentry:
    goto icn_305_α
icn_tpipe_s20_sdrain:
    pop
    goto icn_302_α
;  VAR
icn_308_α:
    getstatic rung36_jcon_io/icn_pv_tpipe_p J
    goto icn_307_waft_0
icn_308_β:
    goto icn_304_α
;  STR
icn_309_α:
    ldc "two roads diverged in a yellow wood"
    goto icn_307_waft_1
icn_309_β:
    goto icn_304_α
icn_307_α:
    goto icn_308_α
icn_307_β:
    goto icn_308_β
    goto icn_307_wentry
icn_307_waft_0:
    lstore 4
    getstatic java/lang/System/out Ljava/io/PrintStream;
    lload 4
    invokevirtual java/io/PrintStream/print(J)V
    goto icn_309_α
icn_307_waft_1:
    astore 151
    getstatic java/lang/System/out Ljava/io/PrintStream;
    aload 151
    invokevirtual java/io/PrintStream/print(Ljava/lang/String;)V
    getstatic java/lang/System/out Ljava/io/PrintStream;
    ldc ""
    invokevirtual java/io/PrintStream/println(Ljava/lang/String;)V
    aload 151
    goto icn_tpipe_s19_sdrain
icn_307_wentry:
    goto icn_308_α
icn_tpipe_s19_sdrain:
    pop
    goto icn_304_α
;  VAR
icn_311_α:
    getstatic rung36_jcon_io/icn_pv_tpipe_p J
    goto icn_310_waft_0
icn_311_β:
    goto icn_307_α
;  STR
icn_312_α:
    ldc "once upon a midnight dreary"
    goto icn_310_waft_1
icn_312_β:
    goto icn_307_α
icn_310_α:
    goto icn_311_α
icn_310_β:
    goto icn_311_β
    goto icn_310_wentry
icn_310_waft_0:
    lstore 6
    getstatic java/lang/System/out Ljava/io/PrintStream;
    lload 6
    invokevirtual java/io/PrintStream/print(J)V
    goto icn_312_α
icn_310_waft_1:
    astore 152
    getstatic java/lang/System/out Ljava/io/PrintStream;
    aload 152
    invokevirtual java/io/PrintStream/print(Ljava/lang/String;)V
    getstatic java/lang/System/out Ljava/io/PrintStream;
    ldc ""
    invokevirtual java/io/PrintStream/println(Ljava/lang/String;)V
    aload 152
    goto icn_tpipe_s18_sdrain
icn_310_wentry:
    goto icn_311_α
icn_tpipe_s18_sdrain:
    pop
    goto icn_307_α
;  VAR
icn_315_α:
    getstatic rung36_jcon_io/icn_pv_tpipe_p J
    goto icn_314_image_after
icn_315_β:
    goto icn_310_α
icn_314_α:
    goto icn_315_α
icn_314_β:
    goto icn_315_β
icn_314_image_after:
    invokestatic java/lang/Long/toString(J)Ljava/lang/String;
    goto icn_313_waft_0
icn_313_α:
    goto icn_314_α
icn_313_β:
    goto icn_314_β
    goto icn_313_wentry
icn_313_waft_0:
    astore 153
    getstatic java/lang/System/out Ljava/io/PrintStream;
    aload 153
    invokevirtual java/io/PrintStream/print(Ljava/lang/String;)V
    getstatic java/lang/System/out Ljava/io/PrintStream;
    ldc ""
    invokevirtual java/io/PrintStream/println(Ljava/lang/String;)V
    aload 153
    goto icn_tpipe_s17_sdrain
icn_313_wentry:
    goto icn_314_α
icn_tpipe_s17_sdrain:
    pop
    goto icn_310_α
icn_318_α:
    goto icn_313_α
icn_318_β:
    goto icn_313_α
icn_319_α:
    goto icn_318_α
icn_319_β:
    goto icn_318_α
icn_317_alt_g0:
    pop
    lconst_0
    putstatic rung36_jcon_io/icn_317_alt_val J
    sipush 1
    putstatic rung36_jcon_io/icn_317_alt_gate I
    getstatic rung36_jcon_io/icn_317_alt_val J
    goto icn_316_store
icn_317_alt_g1:
    putstatic rung36_jcon_io/icn_317_alt_val J
    sipush 2
    putstatic rung36_jcon_io/icn_317_alt_gate I
    getstatic rung36_jcon_io/icn_317_alt_val J
    goto icn_316_store
icn_317_α:
    iconst_0
    putstatic rung36_jcon_io/icn_317_alt_gate I
    goto icn_319_α
icn_317_β:
    getstatic rung36_jcon_io/icn_317_alt_gate I
    tableswitch 1 2
        icn_319_β
        icn_318_β
        default: icn_313_α
icn_316_α:
    goto icn_317_α
icn_316_β:
    goto icn_317_β
icn_316_store:
    putstatic rung36_jcon_io/icn_pv_tpipe_p J
    getstatic rung36_jcon_io/icn_pv_tpipe_p J
    goto icn_tpipe_s16_sdrain
icn_tpipe_s16_sdrain:
    pop2
    goto icn_313_α
icn_320_α:
    getstatic java/lang/System/out Ljava/io/PrintStream;
    ldc ""
    invokevirtual java/io/PrintStream/println(Ljava/lang/String;)V
    goto icn_tpipe_s15_sdrain
icn_320_β:
    goto icn_316_α
icn_tpipe_s15_sdrain:
    pop2
    goto icn_316_α
icn_321_α:
    goto icn_320_α
icn_321_β:
    goto icn_320_α
icn_tpipe_s14_sdrain:
    pop2
    goto icn_320_α
;  STR
icn_324_α:
    ldc "> "
    goto icn_323_waft_0
icn_324_β:
    goto icn_321_α
;  VAR
icn_326_α:
    getstatic rung36_jcon_io/icn_pv_tpipe_p J
    goto icn_325_bang_adv
icn_326_β:
    goto icn_321_α
icn_325_α:
    goto icn_326_α
icn_325_β:
    goto icn_325_bang_chk
icn_325_bang_adv:
    putstatic rung36_jcon_io/icn_325_bang_str Ljava/lang/String;
    iconst_0
    putstatic rung36_jcon_io/icn_325_bang_pos I
icn_325_bang_chk:
    getstatic rung36_jcon_io/icn_325_bang_str Ljava/lang/String;
    invokevirtual java/lang/String/length()I
    getstatic rung36_jcon_io/icn_325_bang_pos I
    if_icmple icn_321_α
    getstatic rung36_jcon_io/icn_325_bang_str Ljava/lang/String;
    getstatic rung36_jcon_io/icn_325_bang_pos I
    getstatic rung36_jcon_io/icn_325_bang_pos I
    iconst_1
    iadd
    invokevirtual java/lang/String/substring(II)Ljava/lang/String;
    getstatic rung36_jcon_io/icn_325_bang_pos I
    iconst_1
    iadd
    putstatic rung36_jcon_io/icn_325_bang_pos I
    goto icn_323_waft_1
icn_323_α:
    goto icn_324_α
icn_323_β:
    goto icn_324_β
    goto icn_323_wentry
icn_323_waft_0:
    astore 154
    getstatic java/lang/System/out Ljava/io/PrintStream;
    aload 154
    invokevirtual java/io/PrintStream/print(Ljava/lang/String;)V
    goto icn_325_α
icn_323_waft_1:
    astore 155
    getstatic java/lang/System/out Ljava/io/PrintStream;
    aload 155
    invokevirtual java/io/PrintStream/print(Ljava/lang/String;)V
    getstatic java/lang/System/out Ljava/io/PrintStream;
    ldc ""
    invokevirtual java/io/PrintStream/println(Ljava/lang/String;)V
    aload 155
    goto icn_322_gdrain
icn_323_wentry:
    goto icn_324_α
icn_322_gdrain:
    pop
icn_322_pump:
    goto icn_323_β
icn_322_α:
    goto icn_323_α
icn_322_β:
    goto icn_321_α
;  VAR
icn_329_α:
    getstatic rung36_jcon_io/icn_pv_tpipe_p J
    goto icn_328_image_after
icn_329_β:
    goto icn_322_α
icn_328_α:
    goto icn_329_α
icn_328_β:
    goto icn_329_β
icn_328_image_after:
    invokestatic java/lang/Long/toString(J)Ljava/lang/String;
    goto icn_327_waft_0
icn_327_α:
    goto icn_328_α
icn_327_β:
    goto icn_328_β
    goto icn_327_wentry
icn_327_waft_0:
    astore 156
    getstatic java/lang/System/out Ljava/io/PrintStream;
    aload 156
    invokevirtual java/io/PrintStream/print(Ljava/lang/String;)V
    getstatic java/lang/System/out Ljava/io/PrintStream;
    ldc ""
    invokevirtual java/io/PrintStream/println(Ljava/lang/String;)V
    aload 156
    goto icn_tpipe_s12_sdrain
icn_327_wentry:
    goto icn_328_α
icn_tpipe_s12_sdrain:
    pop
    goto icn_322_α
icn_332_α:
    goto icn_327_α
icn_332_β:
    goto icn_327_α
icn_333_α:
    goto icn_332_α
icn_333_β:
    goto icn_332_α
icn_331_alt_g0:
    pop
    lconst_0
    putstatic rung36_jcon_io/icn_331_alt_val J
    sipush 1
    putstatic rung36_jcon_io/icn_331_alt_gate I
    getstatic rung36_jcon_io/icn_331_alt_val J
    goto icn_330_store
icn_331_alt_g1:
    putstatic rung36_jcon_io/icn_331_alt_val J
    sipush 2
    putstatic rung36_jcon_io/icn_331_alt_gate I
    getstatic rung36_jcon_io/icn_331_alt_val J
    goto icn_330_store
icn_331_α:
    iconst_0
    putstatic rung36_jcon_io/icn_331_alt_gate I
    goto icn_333_α
icn_331_β:
    getstatic rung36_jcon_io/icn_331_alt_gate I
    tableswitch 1 2
        icn_333_β
        icn_332_β
        default: icn_327_α
icn_330_α:
    goto icn_331_α
icn_330_β:
    goto icn_331_β
icn_330_store:
    putstatic rung36_jcon_io/icn_pv_tpipe_p J
    getstatic rung36_jcon_io/icn_pv_tpipe_p J
    goto icn_tpipe_s11_sdrain
icn_tpipe_s11_sdrain:
    pop2
    goto icn_327_α
icn_334_α:
    getstatic java/lang/System/out Ljava/io/PrintStream;
    ldc ""
    invokevirtual java/io/PrintStream/println(Ljava/lang/String;)V
    goto icn_tpipe_s10_sdrain
icn_334_β:
    goto icn_330_α
icn_tpipe_s10_sdrain:
    pop2
    goto icn_330_α
;  STR
icn_337_α:
    ldc "> "
    goto icn_336_waft_0
icn_337_β:
    goto icn_335_pump
icn_338_α:
    goto icn_335_pump
icn_338_β:
    goto icn_335_pump
icn_336_α:
    goto icn_337_α
icn_336_β:
    goto icn_337_β
    goto icn_336_wentry
icn_336_waft_0:
    astore 157
    getstatic java/lang/System/out Ljava/io/PrintStream;
    aload 157
    invokevirtual java/io/PrintStream/print(Ljava/lang/String;)V
    goto icn_338_α
icn_336_waft_1:
    astore 158
    getstatic java/lang/System/out Ljava/io/PrintStream;
    aload 158
    invokevirtual java/io/PrintStream/print(Ljava/lang/String;)V
    getstatic java/lang/System/out Ljava/io/PrintStream;
    ldc ""
    invokevirtual java/io/PrintStream/println(Ljava/lang/String;)V
    aload 158
    goto icn_335_bdrain
icn_336_wentry:
    goto icn_337_α
;  INT
icn_340_α:
    ldc2_w 10
    goto icn_339_e2relay
icn_340_β:
    goto icn_339_e1b
;  INT
icn_341_α:
    ldc2_w 1
    goto icn_339_e1relay
icn_341_β:
    goto icn_334_α
icn_339_e1relay:
    putstatic rung36_jcon_io/icn_339_e1val J
    goto icn_340_α
icn_339_e2relay:
    putstatic rung36_jcon_io/icn_339_e2val J
    goto icn_339_init
icn_339_e1b:
    iconst_0
    putstatic rung36_jcon_io/icn_339_e2seen I
    goto icn_341_β
icn_339_e2b:
    goto icn_340_β
icn_339_α:
    iconst_0
    putstatic rung36_jcon_io/icn_339_e2seen I
    goto icn_341_α
icn_339_β:
    getstatic rung36_jcon_io/icn_339_I J
    lconst_1
    ladd
    putstatic rung36_jcon_io/icn_339_I J
    goto icn_339_code
icn_339_init:
    getstatic rung36_jcon_io/icn_339_e2val J
    putstatic rung36_jcon_io/icn_339_bound J
    getstatic rung36_jcon_io/icn_339_e2seen I
    ifne icn_339_init_e2adv
    getstatic rung36_jcon_io/icn_339_e1val J
    putstatic rung36_jcon_io/icn_339_e1cur J
    getstatic rung36_jcon_io/icn_339_e1cur J
    putstatic rung36_jcon_io/icn_339_I J
    iconst_1
    putstatic rung36_jcon_io/icn_339_e2seen I
    goto icn_339_code
icn_339_init_e2adv:
    getstatic rung36_jcon_io/icn_339_e1cur J
    putstatic rung36_jcon_io/icn_339_I J
    goto icn_339_code
icn_339_code:
    getstatic rung36_jcon_io/icn_339_I J
    getstatic rung36_jcon_io/icn_339_bound J
    lcmp
    ifgt icn_339_e2b
    getstatic rung36_jcon_io/icn_339_I J
    goto icn_335_gdrain
icn_335_gdrain:
    pop2
    goto icn_336_α
icn_335_bdrain:
    pop
icn_335_pump:
    goto icn_339_β
icn_335_α:
    goto icn_339_α
icn_335_β:
    goto icn_334_α
;  VAR
icn_344_α:
    getstatic rung36_jcon_io/icn_pv_tpipe_p J
    goto icn_343_image_after
icn_344_β:
    goto icn_335_α
icn_343_α:
    goto icn_344_α
icn_343_β:
    goto icn_344_β
icn_343_image_after:
    invokestatic java/lang/Long/toString(J)Ljava/lang/String;
    goto icn_342_waft_0
icn_342_α:
    goto icn_343_α
icn_342_β:
    goto icn_343_β
    goto icn_342_wentry
icn_342_waft_0:
    astore 159
    getstatic java/lang/System/out Ljava/io/PrintStream;
    aload 159
    invokevirtual java/io/PrintStream/print(Ljava/lang/String;)V
    getstatic java/lang/System/out Ljava/io/PrintStream;
    ldc ""
    invokevirtual java/io/PrintStream/println(Ljava/lang/String;)V
    aload 159
    goto icn_tpipe_s8_sdrain
icn_342_wentry:
    goto icn_343_α
icn_tpipe_s8_sdrain:
    pop
    goto icn_335_α
icn_347_α:
    goto icn_342_α
icn_347_β:
    goto icn_342_α
icn_348_α:
    goto icn_347_α
icn_348_β:
    goto icn_347_α
icn_346_alt_g0:
    pop
    lconst_0
    putstatic rung36_jcon_io/icn_346_alt_val J
    sipush 1
    putstatic rung36_jcon_io/icn_346_alt_gate I
    getstatic rung36_jcon_io/icn_346_alt_val J
    goto icn_345_store
icn_346_alt_g1:
    putstatic rung36_jcon_io/icn_346_alt_val J
    sipush 2
    putstatic rung36_jcon_io/icn_346_alt_gate I
    getstatic rung36_jcon_io/icn_346_alt_val J
    goto icn_345_store
icn_346_α:
    iconst_0
    putstatic rung36_jcon_io/icn_346_alt_gate I
    goto icn_348_α
icn_346_β:
    getstatic rung36_jcon_io/icn_346_alt_gate I
    tableswitch 1 2
        icn_348_β
        icn_347_β
        default: icn_342_α
icn_345_α:
    goto icn_346_α
icn_345_β:
    goto icn_346_β
icn_345_store:
    putstatic rung36_jcon_io/icn_pv_tpipe_p J
    getstatic rung36_jcon_io/icn_pv_tpipe_p J
    goto icn_tpipe_s7_sdrain
icn_tpipe_s7_sdrain:
    pop2
    goto icn_342_α
icn_349_α:
    getstatic java/lang/System/out Ljava/io/PrintStream;
    ldc ""
    invokevirtual java/io/PrintStream/println(Ljava/lang/String;)V
    goto icn_tpipe_s6_sdrain
icn_349_β:
    goto icn_345_α
icn_tpipe_s6_sdrain:
    pop2
    goto icn_345_α
icn_350_α:
    goto icn_349_α
icn_350_β:
    goto icn_349_α
icn_tpipe_s5_sdrain:
    pop2
    goto icn_349_α
;  STR
icn_353_α:
    ldc "> "
    goto icn_352_waft_0
icn_353_β:
    goto icn_350_α
icn_354_α:
    goto icn_350_α
icn_354_β:
    goto icn_350_α
icn_352_α:
    goto icn_353_α
icn_352_β:
    goto icn_353_β
    goto icn_352_wentry
icn_352_waft_0:
    astore 160
    getstatic java/lang/System/out Ljava/io/PrintStream;
    aload 160
    invokevirtual java/io/PrintStream/print(Ljava/lang/String;)V
    goto icn_354_α
icn_352_waft_1:
    astore 161
    getstatic java/lang/System/out Ljava/io/PrintStream;
    aload 161
    invokevirtual java/io/PrintStream/print(Ljava/lang/String;)V
    getstatic java/lang/System/out Ljava/io/PrintStream;
    ldc ""
    invokevirtual java/io/PrintStream/println(Ljava/lang/String;)V
    aload 161
    goto icn_351_condok
icn_352_wentry:
    goto icn_353_α
icn_351_condok:
    pop
    goto icn_352_α
icn_351_α:
    goto icn_352_α
icn_351_β:
    goto icn_350_α
;  VAR
icn_357_α:
    getstatic rung36_jcon_io/icn_pv_tpipe_p J
    goto icn_356_image_after
icn_357_β:
    goto icn_351_α
icn_356_α:
    goto icn_357_α
icn_356_β:
    goto icn_357_β
icn_356_image_after:
    invokestatic java/lang/Long/toString(J)Ljava/lang/String;
    goto icn_355_waft_0
icn_355_α:
    goto icn_356_α
icn_355_β:
    goto icn_356_β
    goto icn_355_wentry
icn_355_waft_0:
    astore 162
    getstatic java/lang/System/out Ljava/io/PrintStream;
    aload 162
    invokevirtual java/io/PrintStream/print(Ljava/lang/String;)V
    getstatic java/lang/System/out Ljava/io/PrintStream;
    ldc ""
    invokevirtual java/io/PrintStream/println(Ljava/lang/String;)V
    aload 162
    goto icn_tpipe_s3_sdrain
icn_355_wentry:
    goto icn_356_α
icn_tpipe_s3_sdrain:
    pop
    goto icn_351_α
icn_360_α:
    goto icn_355_α
icn_360_β:
    goto icn_355_α
icn_361_α:
    goto icn_360_α
icn_361_β:
    goto icn_360_α
icn_359_alt_g0:
    pop
    lconst_0
    putstatic rung36_jcon_io/icn_359_alt_val J
    sipush 1
    putstatic rung36_jcon_io/icn_359_alt_gate I
    getstatic rung36_jcon_io/icn_359_alt_val J
    goto icn_358_store
icn_359_alt_g1:
    putstatic rung36_jcon_io/icn_359_alt_val J
    sipush 2
    putstatic rung36_jcon_io/icn_359_alt_gate I
    getstatic rung36_jcon_io/icn_359_alt_val J
    goto icn_358_store
icn_359_α:
    iconst_0
    putstatic rung36_jcon_io/icn_359_alt_gate I
    goto icn_361_α
icn_359_β:
    getstatic rung36_jcon_io/icn_359_alt_gate I
    tableswitch 1 2
        icn_361_β
        icn_360_β
        default: icn_355_α
icn_358_α:
    goto icn_359_α
icn_358_β:
    goto icn_359_β
icn_358_store:
    putstatic rung36_jcon_io/icn_pv_tpipe_p J
    getstatic rung36_jcon_io/icn_pv_tpipe_p J
    goto icn_tpipe_s2_sdrain
icn_tpipe_s2_sdrain:
    pop2
    goto icn_355_α
icn_362_α:
    getstatic java/lang/System/out Ljava/io/PrintStream;
    ldc ""
    invokevirtual java/io/PrintStream/println(Ljava/lang/String;)V
    goto icn_tpipe_s1_sdrain
icn_362_β:
    goto icn_358_α
icn_tpipe_s1_sdrain:
    pop2
    goto icn_358_α
icn_tpipe_done:
    iconst_0
    putstatic rung36_jcon_io/icn_suspended B
    iconst_0
    putstatic rung36_jcon_io/icn_suspend_id I
    iconst_1
    putstatic rung36_jcon_io/icn_failed B
    return
icn_tpipe_ret:
    iconst_0
    putstatic rung36_jcon_io/icn_failed B
    return
icn_tpipe_sret:
    return
.end method

