; Auto-generated by icon_emit_jvm.c — Tiny-ICON Byrd Box JVM
.bytecode 45.0
.class public rung36_jcon_collate
.super java/lang/Object

.field public static icn_failed B
.field public static icn_suspended B
.field public static icn_suspend_id I
.field public static icn_retval_obj Ljava/lang/Object;
.field public static icn_retval J
.field public static icn_retval_str Ljava/lang/String;
.field public static icn_arg_str_0 Ljava/lang/String;
.field public static icn_pv_collate_s1 Ljava/lang/String;
.field public static icn_arg_str_1 Ljava/lang/String;
.field public static icn_pv_collate_s2 Ljava/lang/String;
.field public static icn_pv_decollate_s Ljava/lang/String;
.field public static icn_pv_permute_s Ljava/lang/String;
.field public static icn_gvar_llabels Ljava/lang/String;
.field public static icn_pv_collate_llabels Ljava/lang/String;
.field public static icn_gvar_rlabels Ljava/lang/String;
.field public static icn_pv_collate_rlabels Ljava/lang/String;
.field public static icn_gvar_blabels Ljava/lang/String;
.field public static icn_pv_collate_blabels Ljava/lang/String;
.field public static icn_gvar_clabels Ljava/lang/String;
.field public static icn_pv_collate_clabels Ljava/lang/String;
.field public static icn_gvar_ltemp Ljava/lang/String;
.field public static icn_pv_collate_ltemp Ljava/lang/String;
.field public static icn_gvar_rtemp Ljava/lang/String;
.field public static icn_pv_collate_rtemp Ljava/lang/String;
.field public static icn_gvar_t Ljava/lang/String;
.field public static icn_pv_collate_t Ljava/lang/String;
.field public static icn_gvar_s1 Ljava/lang/String;
.field public static icn_gvar_s2 Ljava/lang/String;
.field public static icn_gvar_object Ljava/lang/String;
.field public static icn_pv_decollate_object Ljava/lang/String;
.field public static icn_gvar_x Ljava/lang/String;
.field public static icn_pv_permute_x Ljava/lang/String;
.field public static icn_pv_permute_t Ljava/lang/String;
.field public static icn_arg_1 J
.field public static icn_pv_main_s2 J
.field public static icn_arg_0 J
.field public static icn_pv_main_s1 J
.field public static icn_33_lc Ljava/lang/String;
.field public static icn_33_rc Ljava/lang/String;
.field public static icn_36_left_s Ljava/lang/String;
.field public static icn_38_binop_lc J
.field public static icn_38_binop_rc J
.field public static icn_38_binop_bf I
.field public static icn_pv_collate_length J
.field public static icn_41_lc Ljava/lang/String;
.field public static icn_41_rc Ljava/lang/String;
.field public static icn_42_left_s Ljava/lang/String;
.field public static icn_45_left_s Ljava/lang/String;
.field public static icn_48_lc Ljava/lang/String;
.field public static icn_48_rc Ljava/lang/String;
.field public static icn_52_lc Ljava/lang/String;
.field public static icn_52_rc Ljava/lang/String;
.field public static icn_54_lc Ljava/lang/String;
.field public static icn_54_rc Ljava/lang/String;
.field public static icn_56_right_s Ljava/lang/String;
.field public static icn_58_binop_lc J
.field public static icn_58_binop_rc J
.field public static icn_58_binop_bf I
.field public static icn_pv_collate_half J
.field public static icn_61_right_s Ljava/lang/String;
.field public static icn_63_binop_lc J
.field public static icn_63_binop_rc J
.field public static icn_63_binop_bf I
.field public static icn_69_lc Ljava/lang/String;
.field public static icn_69_rc Ljava/lang/String;
.field public static icn_70_left_s Ljava/lang/String;
.field public static icn_73_left_s Ljava/lang/String;
.field public static icn_76_relop_lc J
.field public static icn_76_relop_rc J
.field public static icn_85_sec_s Ljava/lang/String;
.field public static icn_85_sec_lo I
.field public static icn_85_sec_hi I
.field public static icn_87_binop_lc J
.field public static icn_87_binop_rc J
.field public static icn_87_binop_bf I
.field public static icn_93_sec_s Ljava/lang/String;
.field public static icn_93_sec_lo I
.field public static icn_93_sec_hi I
.field public static icn_96_binop_lc J
.field public static icn_96_binop_rc J
.field public static icn_96_binop_bf I
.field public static icn_103_sec_s Ljava/lang/String;
.field public static icn_103_sec_lo I
.field public static icn_103_sec_hi I
.field public static icn_105_binop_lc J
.field public static icn_105_binop_rc J
.field public static icn_105_binop_bf I
.field public static icn_111_sec_s Ljava/lang/String;
.field public static icn_111_sec_lo I
.field public static icn_111_sec_hi I
.field public static icn_114_binop_lc J
.field public static icn_114_binop_rc J
.field public static icn_114_binop_bf I
.field public static icn_120_relop_lc J
.field public static icn_120_relop_rc J
.field public static icn_125_relop_lc J
.field public static icn_125_relop_rc J
.field public static icn_init_collate I
.field public static icn_137_lc Ljava/lang/String;
.field public static icn_137_rc Ljava/lang/String;
.field public static icn_145_left_s Ljava/lang/String;
.field public static icn_147_binop_lc J
.field public static icn_147_binop_rc J
.field public static icn_147_binop_bf I
.field public static icn_152_right_s Ljava/lang/String;
.field public static icn_154_binop_lc J
.field public static icn_154_binop_rc J
.field public static icn_154_binop_bf I
.field public static icn_175_sec_s Ljava/lang/String;
.field public static icn_175_sec_lo I
.field public static icn_175_sec_hi I
.field public static icn_178_binop_lc J
.field public static icn_178_binop_rc J
.field public static icn_178_binop_bf I
.field public static icn_180_binop_lc J
.field public static icn_180_binop_rc J
.field public static icn_180_binop_bf I
.field public static icn_pv_decollate_n Ljava/lang/String;
.field public static icn_pv_decollate_ssize J
.field public static icn_183_sec_s Ljava/lang/String;
.field public static icn_183_sec_lo I
.field public static icn_183_sec_hi I
.field public static icn_pv_decollate_image J
.field public static icn_185_binop_lc J
.field public static icn_185_binop_rc J
.field public static icn_185_binop_bf I
.field public static icn_191_lc Ljava/lang/String;
.field public static icn_191_rc Ljava/lang/String;
.field public static icn_194_sec_s Ljava/lang/String;
.field public static icn_194_sec_lo I
.field public static icn_194_sec_hi I
.field public static icn_196_binop_lc J
.field public static icn_196_binop_rc J
.field public static icn_196_binop_bf I
.field public static icn_pv_decollate_dsize J
.field public static icn_201_sec_s Ljava/lang/String;
.field public static icn_201_sec_lo I
.field public static icn_201_sec_hi I
.field public static icn_204_binop_lc J
.field public static icn_204_binop_rc J
.field public static icn_204_binop_bf I
.field public static icn_206_binop_lc J
.field public static icn_206_binop_rc J
.field public static icn_206_binop_bf I
.field public static icn_209_sec_s Ljava/lang/String;
.field public static icn_209_sec_lo I
.field public static icn_209_sec_hi I
.field public static icn_211_binop_lc J
.field public static icn_211_binop_rc J
.field public static icn_211_binop_bf I
.field public static icn_214_binop_lc J
.field public static icn_214_binop_rc J
.field public static icn_214_binop_bf I
.field public static icn_217_sec_s Ljava/lang/String;
.field public static icn_217_sec_lo I
.field public static icn_217_sec_hi I
.field public static icn_220_binop_lc J
.field public static icn_220_binop_rc J
.field public static icn_220_binop_bf I
.field public static icn_223_relop_lc J
.field public static icn_223_relop_rc J
.field public static icn_225_binop_lc J
.field public static icn_225_binop_rc J
.field public static icn_225_binop_bf I
.field public static icn_231_augtemp J
.field public static icn_init_decollate I
.field public static icn_238_sub_s Ljava/lang/String;
.field public static icn_238_sub_i I
.field public static icn_241_binop_lc J
.field public static icn_241_binop_rc J
.field public static icn_241_binop_bf I
.field public static icn_245_sec_s Ljava/lang/String;
.field public static icn_245_sec_lo I
.field public static icn_245_sec_hi I
.field public static icn_257_bang_list Ljava/util/ArrayList;
.field public static icn_257_bang_idx I
.field public static icn_258_sort_list Ljava/util/ArrayList;
.field public static icn_pv_perm_output J
.field public static icn_263_I J
.field public static icn_263_bound J
.field public static icn_263_e1cur J
.field public static icn_263_e2seen I
.field public static icn_263_e1val J
.field public static icn_263_e2val J
.field public static icn_271_sub_s Ljava/lang/String;
.field public static icn_271_sub_i I
.field public static icn_pv_permute_i J
.field public static icn_278_lsa_l Ljava/util/ArrayList;
.field public static icn_278_lsa_i J
.field public static icn_278_lsa_v Ljava/lang/String;
.field public static icn_281_lc Ljava/lang/String;
.field public static icn_281_rc Ljava/lang/String;
.field public static icn_286_I J
.field public static icn_286_bound J
.field public static icn_286_e1cur J
.field public static icn_286_e2seen I
.field public static icn_286_e1val J
.field public static icn_286_e2val J

.method public static main([Ljava/lang/String;)V
    .limit stack 4
    .limit locals 1
    invokestatic rung36_jcon_collate/icn_main()V
    return
.end method

.method public static icn_builtin_left(Ljava/lang/String;ILjava/lang/String;)Ljava/lang/String;
    .limit stack 4
    .limit locals 5
    aload_0
    invokevirtual java/lang/String/length()I
    iload_1
    if_icmplt icn_left_pad
    aload_0
    iconst_0
    iload_1
    invokevirtual java/lang/String/substring(II)Ljava/lang/String;
    areturn
icn_left_pad:
    new java/lang/StringBuilder
    dup
    aload_0
    invokespecial java/lang/StringBuilder/<init>(Ljava/lang/String;)V
    astore_3
icn_left_loop:
    aload_3
    invokevirtual java/lang/StringBuilder/length()I
    iload_1
    if_icmpge icn_left_done
    aload_3
    aload_2
    iconst_0
    invokevirtual java/lang/String/charAt(I)C
    invokevirtual java/lang/StringBuilder/append(C)Ljava/lang/StringBuilder;
    pop
    goto icn_left_loop
icn_left_done:
    aload_3
    invokevirtual java/lang/StringBuilder/toString()Ljava/lang/String;
    areturn
.end method

.method public static icn_builtin_right(Ljava/lang/String;ILjava/lang/String;)Ljava/lang/String;
    .limit stack 4
    .limit locals 5
    aload_0
    invokevirtual java/lang/String/length()I
    iload_1
    if_icmplt icn_right_pad
    aload_0
    invokevirtual java/lang/String/length()I
    iload_1
    isub
    aload_0
    swap
    invokevirtual java/lang/String/substring(I)Ljava/lang/String;
    areturn
icn_right_pad:
    new java/lang/StringBuilder
    dup
    invokespecial java/lang/StringBuilder/<init>()V
    astore_3
    iload_1
    aload_0
    invokevirtual java/lang/String/length()I
    isub
    istore 4
    iconst_0
icn_right_loop:
    dup
    iload 4
    if_icmpge icn_right_append
    aload_3
    aload_2
    iconst_0
    invokevirtual java/lang/String/charAt(I)C
    invokevirtual java/lang/StringBuilder/append(C)Ljava/lang/StringBuilder;
    pop
    iconst_1
    iadd
    goto icn_right_loop
icn_right_append:
    pop
    aload_3
    aload_0
    invokevirtual java/lang/StringBuilder/append(Ljava/lang/String;)Ljava/lang/StringBuilder;
    pop
    aload_3
    invokevirtual java/lang/StringBuilder/toString()Ljava/lang/String;
    areturn
.end method

.method public static icn_builtin_center(Ljava/lang/String;ILjava/lang/String;)Ljava/lang/String;
    .limit stack 5
    .limit locals 7
    aload_0
    invokevirtual java/lang/String/length()I
    iload_1
    if_icmplt icn_ctr_pad
    aload_0
    iconst_0
    iload_1
    invokevirtual java/lang/String/substring(II)Ljava/lang/String;
    areturn
icn_ctr_pad:
    iload_1
    aload_0
    invokevirtual java/lang/String/length()I
    isub
    istore_3
    iload_3
    iconst_2
    idiv
    istore 4
    iload_3
    iload 4
    isub
    istore 5
    new java/lang/StringBuilder
    dup
    invokespecial java/lang/StringBuilder/<init>()V
    astore 6
    iconst_0
icn_ctr_lloop:
    dup
    iload 4
    if_icmpge icn_ctr_mid
    aload 6
    aload_2
    iconst_0
    invokevirtual java/lang/String/charAt(I)C
    invokevirtual java/lang/StringBuilder/append(C)Ljava/lang/StringBuilder;
    pop
    iconst_1
    iadd
    goto icn_ctr_lloop
icn_ctr_mid:
    pop
    aload 6
    aload_0
    invokevirtual java/lang/StringBuilder/append(Ljava/lang/String;)Ljava/lang/StringBuilder;
    pop
    iconst_0
icn_ctr_rloop:
    dup
    iload 5
    if_icmpge icn_ctr_done
    aload 6
    aload_2
    iconst_0
    invokevirtual java/lang/String/charAt(I)C
    invokevirtual java/lang/StringBuilder/append(C)Ljava/lang/StringBuilder;
    pop
    iconst_1
    iadd
    goto icn_ctr_rloop
icn_ctr_done:
    pop
    aload 6
    invokevirtual java/lang/StringBuilder/toString()Ljava/lang/String;
    areturn
.end method

.method public static icn_builtin_trim(Ljava/lang/String;Ljava/lang/String;)Ljava/lang/String;
    .limit stack 4
    .limit locals 3
    aload_0
    invokevirtual java/lang/String/length()I
    istore_2
icn_trim_loop:
    iload_2
    ifle icn_trim_done
    aload_1
    aload_0
    iload_2
    iconst_1
    isub
    invokevirtual java/lang/String/charAt(I)C
    invokevirtual java/lang/String/indexOf(I)I
    iflt icn_trim_done
    iinc 2 -1
    goto icn_trim_loop
icn_trim_done:
    aload_0
    iconst_0
    iload_2
    invokevirtual java/lang/String/substring(II)Ljava/lang/String;
    areturn
.end method

.method public static icn_builtin_map(Ljava/lang/String;Ljava/lang/String;Ljava/lang/String;)Ljava/lang/String;
    .limit stack 5
    .limit locals 7
    new java/lang/StringBuilder
    dup
    invokespecial java/lang/StringBuilder/<init>()V
    astore_3
    iconst_0
    istore 4
icn_map_loop:
    iload 4
    aload_0
    invokevirtual java/lang/String/length()I
    if_icmpge icn_map_done
    aload_0
    iload 4
    invokevirtual java/lang/String/charAt(I)C
    istore 5
    aload_1
    iload 5
    invokevirtual java/lang/String/indexOf(I)I
    istore 6
    iload 6
    iflt icn_map_notfound
    iload 6
    aload_2
    invokevirtual java/lang/String/length()I
    if_icmpge icn_map_notfound
    aload_3
    aload_2
    iload 6
    invokevirtual java/lang/String/charAt(I)C
    invokevirtual java/lang/StringBuilder/append(C)Ljava/lang/StringBuilder;
    pop
    goto icn_map_next
icn_map_notfound:
    aload_3
    iload 5
    invokevirtual java/lang/StringBuilder/append(C)Ljava/lang/StringBuilder;
    pop
icn_map_next:
    iinc 4 1
    goto icn_map_loop
icn_map_done:
    aload_3
    invokevirtual java/lang/StringBuilder/toString()Ljava/lang/String;
    areturn
.end method

.method public static icn_builtin_parse_long(Ljava/lang/String;)J
    .limit stack 4
    .limit locals 4
    .catch java/lang/Exception from icn_plong_L0 to icn_plong_L1 using icn_plong_catch
icn_plong_L0:
    aload_0
    invokevirtual java/lang/String/trim()Ljava/lang/String;
    astore_1
    aload_1
    ldc "r"
    invokevirtual java/lang/String/contains(Ljava/lang/CharSequence;)Z
    ifeq icn_plong_plain
    aload_1
    ldc "r"
    iconst_2
    invokevirtual java/lang/String/split(Ljava/lang/String;I)[Ljava/lang/String;
    astore_2
    aload_2
    iconst_0
    aaload
    invokestatic java/lang/Integer/parseInt(Ljava/lang/String;)I
    istore_3
    aload_2
    iconst_1
    aaload
    iload_3
    invokestatic java/lang/Long/parseLong(Ljava/lang/String;I)J
    goto icn_plong_L1
icn_plong_plain:
    aload_1
    invokestatic java/lang/Long/parseLong(Ljava/lang/String;)J
icn_plong_L1:
    lreturn
icn_plong_catch:
    pop
    ldc2_w -9223372036854775808
    lreturn
.end method

.method public static icn_builtin_numeric(Ljava/lang/String;)J
    .limit stack 2
    .limit locals 2
    aload_0
    invokestatic rung36_jcon_collate/icn_builtin_parse_long(Ljava/lang/String;)J
    lreturn
.end method

.method public static icn_builtin_sort(Ljava/util/ArrayList;)Ljava/util/ArrayList;
    .limit stack 6
    .limit locals 8
    new java/util/ArrayList
    dup
    aload_0
    invokespecial java/util/ArrayList/<init>(Ljava/util/Collection;)V
    astore_1
    iconst_1
    istore_2
icn_sort_outer:
    aload_1
    invokevirtual java/util/ArrayList/size()I
    iload_2
    if_icmple icn_sort_done
    aload_1
    iload_2
    invokevirtual java/util/ArrayList/get(I)Ljava/lang/Object;
    checkcast java/lang/Long
    invokevirtual java/lang/Long/longValue()J
    lstore 4
    iload_2
    iconst_1
    isub
    istore_3
icn_sort_inner:
    iload_3
    iflt icn_sort_insert
    aload_1
    iload_3
    invokevirtual java/util/ArrayList/get(I)Ljava/lang/Object;
    checkcast java/lang/Long
    invokevirtual java/lang/Long/longValue()J
    lload 4
    lcmp
    ifle icn_sort_insert
    aload_1
    iload_3
    iconst_1
    iadd
    aload_1
    iload_3
    invokevirtual java/util/ArrayList/get(I)Ljava/lang/Object;
    invokevirtual java/util/ArrayList/set(ILjava/lang/Object;)Ljava/lang/Object;
    pop
    iinc 3 -1
    goto icn_sort_inner
icn_sort_insert:
    aload_1
    iload_3
    iconst_1
    iadd
    lload 4
    invokestatic java/lang/Long/valueOf(J)Ljava/lang/Long;
    invokevirtual java/util/ArrayList/set(ILjava/lang/Object;)Ljava/lang/Object;
    pop
    iinc 2 1
    goto icn_sort_outer
icn_sort_done:
    aload_1
    areturn
.end method

.method public static icn_builtin_sortf(Ljava/util/ArrayList;I)Ljava/util/ArrayList;
    .limit stack 8
    .limit locals 10
    new java/util/ArrayList
    dup
    aload_0
    invokespecial java/util/ArrayList/<init>(Ljava/util/Collection;)V
    astore_2
    iconst_1
    istore_3
icn_sortf_outer:
    aload_2
    invokevirtual java/util/ArrayList/size()I
    iload_3
    if_icmple icn_sortf_done
    aload_2
    iload_3
    invokevirtual java/util/ArrayList/get(I)Ljava/lang/Object;
    astore 5
    iload_3
    iconst_1
    isub
    istore 4
icn_sortf_inner:
    iload 4
    iflt icn_sortf_insert
    aload_2
    iload 4
    invokevirtual java/util/ArrayList/get(I)Ljava/lang/Object;
    astore 6
    aload 6
    invokevirtual java/lang/Object/getClass()Ljava/lang/Class;
    invokevirtual java/lang/Class/getDeclaredFields()[Ljava/lang/reflect/Field;
    iload_1
    iconst_1
    isub
    aaload
    aload 6
    invokevirtual java/lang/reflect/Field/get(Ljava/lang/Object;)Ljava/lang/Object;
    astore 7
    aload 5
    invokevirtual java/lang/Object/getClass()Ljava/lang/Class;
    invokevirtual java/lang/Class/getDeclaredFields()[Ljava/lang/reflect/Field;
    iload_1
    iconst_1
    isub
    aaload
    aload 5
    invokevirtual java/lang/reflect/Field/get(Ljava/lang/Object;)Ljava/lang/Object;
    astore 8
    aload 7
    checkcast java/lang/Long
    aload 8
    checkcast java/lang/Long
    invokevirtual java/lang/Long/compareTo(Ljava/lang/Long;)I
    ifle icn_sortf_insert
    aload_2
    iload 4
    iconst_1
    iadd
    aload_2
    iload 4
    invokevirtual java/util/ArrayList/get(I)Ljava/lang/Object;
    invokevirtual java/util/ArrayList/set(ILjava/lang/Object;)Ljava/lang/Object;
    pop
    iinc 4 -1
    goto icn_sortf_inner
icn_sortf_insert:
    aload_2
    iload 4
    iconst_1
    iadd
    aload 5
    invokevirtual java/util/ArrayList/set(ILjava/lang/Object;)Ljava/lang/Object;
    pop
    iinc 3 1
    goto icn_sortf_outer
icn_sortf_done:
    aload_2
    areturn
.end method

.method public static icn_main()V
    .limit stack 16
    .limit locals 228
    lconst_0
    lstore 0
    lconst_0
    lstore 2
    lconst_0
    lstore 4
    lconst_0
    lstore 6
    lconst_0
    lstore 8
    lconst_0
    lstore 10
    lconst_0
    lstore 12
    lconst_0
    lstore 14
    lconst_0
    lstore 16
    lconst_0
    lstore 18
    lconst_0
    lstore 20
    lconst_0
    lstore 22
    lconst_0
    lstore 24
    lconst_0
    lstore 26
    lconst_0
    lstore 28
    lconst_0
    lstore 30
    lconst_0
    lstore 32
    lconst_0
    lstore 34
    lconst_0
    lstore 36
    lconst_0
    lstore 38
    lconst_0
    lstore 40
    lconst_0
    lstore 42
    lconst_0
    lstore 44
    lconst_0
    lstore 46
    lconst_0
    lstore 48
    lconst_0
    lstore 50
    lconst_0
    lstore 52
    lconst_0
    lstore 54
    lconst_0
    lstore 56
    lconst_0
    lstore 58
    lconst_0
    lstore 60
    lconst_0
    lstore 62
    iconst_0
    istore 84
    iconst_0
    istore 85
    iconst_0
    istore 86
    iconst_0
    istore 87
    aconst_null
    astore 148
    aconst_null
    astore 149
    aconst_null
    astore 150
    aconst_null
    astore 151
    aconst_null
    astore 152
    aconst_null
    astore 153
    aconst_null
    astore 154
    aconst_null
    astore 155
    goto icn_27_α
icn_0_α:
    goto icn_0_docall
icn_0_β:
    goto icn_main_done
icn_0_docall:
    invokestatic rung36_jcon_collate/icn_perm()V
    getstatic rung36_jcon_collate/icn_failed B
    ifne icn_0_after_call
    getstatic rung36_jcon_collate/icn_retval J
    goto icn_main_s6_sdrain
icn_0_after_call:
    goto icn_main_done
icn_main_s6_sdrain:
    pop2
    goto icn_main_done
;  INT
icn_4_α:
    ldc2_w 0
    goto icn_3_arg1
icn_4_β:
    goto icn_0_α
icn_3_arg1:
    putstatic rung36_jcon_collate/icn_arg_1 J
    goto icn_3_docall
;  VAR
icn_5_α:
    getstatic rung36_jcon_collate/icn_pv_main_s2 J
    goto icn_3_arg0
icn_5_β:
    goto icn_0_α
icn_3_arg0:
    putstatic rung36_jcon_collate/icn_arg_str_0 Ljava/lang/String;
    lconst_0
    putstatic rung36_jcon_collate/icn_arg_0 J
    goto icn_4_α
icn_3_α:
    goto icn_5_α
icn_3_β:
    goto icn_4_β
icn_3_docall:
    getstatic rung36_jcon_collate/icn_pv_main_s2 J
    lstore 152
    invokestatic rung36_jcon_collate/icn_decollate()V
    lload 152
    putstatic rung36_jcon_collate/icn_pv_main_s2 J
    getstatic rung36_jcon_collate/icn_failed B
    ifne icn_3_after_call
    getstatic rung36_jcon_collate/icn_retval J
    goto icn_2_image_after
icn_3_after_call:
    goto icn_0_α
icn_2_α:
    goto icn_3_α
icn_2_β:
    goto icn_3_β
icn_2_image_after:
    invokestatic java/lang/Long/toString(J)Ljava/lang/String;
    goto icn_1_waft_0
icn_1_α:
    goto icn_2_α
icn_1_β:
    goto icn_2_β
    goto icn_1_wentry
icn_1_waft_0:
    astore 148
    getstatic java/lang/System/out Ljava/io/PrintStream;
    aload 148
    invokevirtual java/io/PrintStream/print(Ljava/lang/String;)V
    getstatic java/lang/System/out Ljava/io/PrintStream;
    ldc ""
    invokevirtual java/io/PrintStream/println(Ljava/lang/String;)V
    aload 148
    goto icn_main_s5_sdrain
icn_1_wentry:
    goto icn_2_α
icn_main_s5_sdrain:
    pop
    goto icn_0_α
;  INT
icn_9_α:
    ldc2_w 1
    goto icn_8_arg1
icn_9_β:
    goto icn_1_α
icn_8_arg1:
    putstatic rung36_jcon_collate/icn_arg_1 J
    goto icn_8_docall
;  VAR
icn_10_α:
    getstatic rung36_jcon_collate/icn_pv_main_s2 J
    goto icn_8_arg0
icn_10_β:
    goto icn_1_α
icn_8_arg0:
    putstatic rung36_jcon_collate/icn_arg_str_0 Ljava/lang/String;
    lconst_0
    putstatic rung36_jcon_collate/icn_arg_0 J
    goto icn_9_α
icn_8_α:
    goto icn_10_α
icn_8_β:
    goto icn_9_β
icn_8_docall:
    getstatic rung36_jcon_collate/icn_pv_main_s2 J
    lstore 153
    invokestatic rung36_jcon_collate/icn_decollate()V
    lload 153
    putstatic rung36_jcon_collate/icn_pv_main_s2 J
    getstatic rung36_jcon_collate/icn_failed B
    ifne icn_8_after_call
    getstatic rung36_jcon_collate/icn_retval J
    goto icn_7_image_after
icn_8_after_call:
    goto icn_1_α
icn_7_α:
    goto icn_8_α
icn_7_β:
    goto icn_8_β
icn_7_image_after:
    invokestatic java/lang/Long/toString(J)Ljava/lang/String;
    goto icn_6_waft_0
icn_6_α:
    goto icn_7_α
icn_6_β:
    goto icn_7_β
    goto icn_6_wentry
icn_6_waft_0:
    astore 149
    getstatic java/lang/System/out Ljava/io/PrintStream;
    aload 149
    invokevirtual java/io/PrintStream/print(Ljava/lang/String;)V
    getstatic java/lang/System/out Ljava/io/PrintStream;
    ldc ""
    invokevirtual java/io/PrintStream/println(Ljava/lang/String;)V
    aload 149
    goto icn_main_s4_sdrain
icn_6_wentry:
    goto icn_7_α
icn_main_s4_sdrain:
    pop
    goto icn_1_α
;  INT
icn_14_α:
    ldc2_w 1
    goto icn_13_arg1
icn_14_β:
    goto icn_6_α
icn_13_arg1:
    putstatic rung36_jcon_collate/icn_arg_1 J
    goto icn_13_docall
;  VAR
icn_15_α:
    getstatic rung36_jcon_collate/icn_pv_main_s1 J
    goto icn_13_arg0
icn_15_β:
    goto icn_6_α
icn_13_arg0:
    putstatic rung36_jcon_collate/icn_arg_str_0 Ljava/lang/String;
    lconst_0
    putstatic rung36_jcon_collate/icn_arg_0 J
    goto icn_14_α
icn_13_α:
    goto icn_15_α
icn_13_β:
    goto icn_14_β
icn_13_docall:
    getstatic rung36_jcon_collate/icn_pv_main_s2 J
    lstore 154
    getstatic rung36_jcon_collate/icn_pv_main_s1 J
    lstore 156
    invokestatic rung36_jcon_collate/icn_decollate()V
    lload 154
    putstatic rung36_jcon_collate/icn_pv_main_s2 J
    lload 156
    putstatic rung36_jcon_collate/icn_pv_main_s1 J
    getstatic rung36_jcon_collate/icn_failed B
    ifne icn_13_after_call
    getstatic rung36_jcon_collate/icn_retval J
    goto icn_12_image_after
icn_13_after_call:
    goto icn_6_α
icn_12_α:
    goto icn_13_α
icn_12_β:
    goto icn_13_β
icn_12_image_after:
    invokestatic java/lang/Long/toString(J)Ljava/lang/String;
    goto icn_11_waft_0
icn_11_α:
    goto icn_12_α
icn_11_β:
    goto icn_12_β
    goto icn_11_wentry
icn_11_waft_0:
    astore 150
    getstatic java/lang/System/out Ljava/io/PrintStream;
    aload 150
    invokevirtual java/io/PrintStream/print(Ljava/lang/String;)V
    getstatic java/lang/System/out Ljava/io/PrintStream;
    ldc ""
    invokevirtual java/io/PrintStream/println(Ljava/lang/String;)V
    aload 150
    goto icn_main_s3_sdrain
icn_11_wentry:
    goto icn_12_α
icn_main_s3_sdrain:
    pop
    goto icn_6_α
;  INT
icn_19_α:
    ldc2_w 0
    goto icn_18_arg1
icn_19_β:
    goto icn_11_α
icn_18_arg1:
    putstatic rung36_jcon_collate/icn_arg_1 J
    goto icn_18_docall
;  VAR
icn_20_α:
    getstatic rung36_jcon_collate/icn_pv_main_s1 J
    goto icn_18_arg0
icn_20_β:
    goto icn_11_α
icn_18_arg0:
    putstatic rung36_jcon_collate/icn_arg_str_0 Ljava/lang/String;
    lconst_0
    putstatic rung36_jcon_collate/icn_arg_0 J
    goto icn_19_α
icn_18_α:
    goto icn_20_α
icn_18_β:
    goto icn_19_β
icn_18_docall:
    getstatic rung36_jcon_collate/icn_pv_main_s2 J
    lstore 155
    getstatic rung36_jcon_collate/icn_pv_main_s1 J
    lstore 157
    invokestatic rung36_jcon_collate/icn_decollate()V
    lload 155
    putstatic rung36_jcon_collate/icn_pv_main_s2 J
    lload 157
    putstatic rung36_jcon_collate/icn_pv_main_s1 J
    getstatic rung36_jcon_collate/icn_failed B
    ifne icn_18_after_call
    getstatic rung36_jcon_collate/icn_retval J
    goto icn_17_image_after
icn_18_after_call:
    goto icn_11_α
icn_17_α:
    goto icn_18_α
icn_17_β:
    goto icn_18_β
icn_17_image_after:
    invokestatic java/lang/Long/toString(J)Ljava/lang/String;
    goto icn_16_waft_0
icn_16_α:
    goto icn_17_α
icn_16_β:
    goto icn_17_β
    goto icn_16_wentry
icn_16_waft_0:
    astore 151
    getstatic java/lang/System/out Ljava/io/PrintStream;
    aload 151
    invokevirtual java/io/PrintStream/print(Ljava/lang/String;)V
    getstatic java/lang/System/out Ljava/io/PrintStream;
    ldc ""
    invokevirtual java/io/PrintStream/println(Ljava/lang/String;)V
    aload 151
    goto icn_main_s2_sdrain
icn_16_wentry:
    goto icn_17_α
icn_main_s2_sdrain:
    pop
    goto icn_11_α
;  VAR
icn_24_α:
    ldc "\u0000\u0001\u0002\u0003\u0004\u0005\u0006\u0007\u0008\u0009\u000a\u000b\u000c\u000d\u000e\u000f\u0010\u0011\u0012\u0013\u0014\u0015\u0016\u0017\u0018\u0019\u001a\u001b\u001c\u001d\u001e\u001f !\"#$%&'()*+,-./0123456789:;<=>?@ABCDEFGHIJKLMNOPQRSTUVWXYZ[\\]^_`abcdefghijklmnopqrstuvwxyz{|}~\u007f"
    goto icn_23_rev_after
icn_24_β:
    goto icn_16_α
icn_23_α:
    goto icn_24_α
icn_23_β:
    goto icn_24_β
icn_23_rev_after:
    new java/lang/StringBuilder
    dup_x1
    swap
    invokespecial java/lang/StringBuilder/<init>(Ljava/lang/String;)V
    invokevirtual java/lang/StringBuilder/reverse()Ljava/lang/StringBuilder;
    invokevirtual java/lang/StringBuilder/toString()Ljava/lang/String;
    goto icn_22_arg1
icn_22_arg1:
    putstatic rung36_jcon_collate/icn_arg_str_1 Ljava/lang/String;
    lconst_0
    putstatic rung36_jcon_collate/icn_arg_1 J
    goto icn_22_docall
;  VAR
icn_26_α:
    ldc "\u0000\u0001\u0002\u0003\u0004\u0005\u0006\u0007\u0008\u0009\u000a\u000b\u000c\u000d\u000e\u000f\u0010\u0011\u0012\u0013\u0014\u0015\u0016\u0017\u0018\u0019\u001a\u001b\u001c\u001d\u001e\u001f !\"#$%&'()*+,-./0123456789:;<=>?@ABCDEFGHIJKLMNOPQRSTUVWXYZ[\\]^_`abcdefghijklmnopqrstuvwxyz{|}~\u007f"
    goto icn_25_rev_after
icn_26_β:
    goto icn_16_α
icn_25_α:
    goto icn_26_α
icn_25_β:
    goto icn_26_β
icn_25_rev_after:
    new java/lang/StringBuilder
    dup_x1
    swap
    invokespecial java/lang/StringBuilder/<init>(Ljava/lang/String;)V
    invokevirtual java/lang/StringBuilder/reverse()Ljava/lang/StringBuilder;
    invokevirtual java/lang/StringBuilder/toString()Ljava/lang/String;
    goto icn_22_arg0
icn_22_arg0:
    putstatic rung36_jcon_collate/icn_arg_str_0 Ljava/lang/String;
    lconst_0
    putstatic rung36_jcon_collate/icn_arg_0 J
    goto icn_23_α
icn_22_α:
    goto icn_25_α
icn_22_β:
    goto icn_23_β
icn_22_docall:
    getstatic rung36_jcon_collate/icn_pv_main_s2 J
    lstore 156
    getstatic rung36_jcon_collate/icn_pv_main_s1 J
    lstore 158
    invokestatic rung36_jcon_collate/icn_collate()V
    lload 156
    putstatic rung36_jcon_collate/icn_pv_main_s2 J
    lload 158
    putstatic rung36_jcon_collate/icn_pv_main_s1 J
    getstatic rung36_jcon_collate/icn_failed B
    ifne icn_22_after_call
    getstatic rung36_jcon_collate/icn_retval J
    goto icn_21_store
icn_22_after_call:
    goto icn_16_α
icn_21_α:
    goto icn_22_α
icn_21_β:
    goto icn_22_β
icn_21_store:
    putstatic rung36_jcon_collate/icn_pv_main_s2 J
    getstatic rung36_jcon_collate/icn_pv_main_s2 J
    goto icn_main_s1_sdrain
icn_main_s1_sdrain:
    pop2
    goto icn_16_α
;  VAR
icn_29_α:
    ldc "\u0000\u0001\u0002\u0003\u0004\u0005\u0006\u0007\u0008\u0009\u000a\u000b\u000c\u000d\u000e\u000f\u0010\u0011\u0012\u0013\u0014\u0015\u0016\u0017\u0018\u0019\u001a\u001b\u001c\u001d\u001e\u001f !\"#$%&'()*+,-./0123456789:;<=>?@ABCDEFGHIJKLMNOPQRSTUVWXYZ[\\]^_`abcdefghijklmnopqrstuvwxyz{|}~\u007f"
    goto icn_28_arg1
icn_29_β:
    goto icn_21_α
icn_28_arg1:
    putstatic rung36_jcon_collate/icn_arg_1 J
    goto icn_28_docall
;  VAR
icn_30_α:
    ldc "\u0000\u0001\u0002\u0003\u0004\u0005\u0006\u0007\u0008\u0009\u000a\u000b\u000c\u000d\u000e\u000f\u0010\u0011\u0012\u0013\u0014\u0015\u0016\u0017\u0018\u0019\u001a\u001b\u001c\u001d\u001e\u001f !\"#$%&'()*+,-./0123456789:;<=>?@ABCDEFGHIJKLMNOPQRSTUVWXYZ[\\]^_`abcdefghijklmnopqrstuvwxyz{|}~\u007f"
    goto icn_28_arg0
icn_30_β:
    goto icn_21_α
icn_28_arg0:
    putstatic rung36_jcon_collate/icn_arg_0 J
    goto icn_29_α
icn_28_α:
    goto icn_30_α
icn_28_β:
    goto icn_29_β
icn_28_docall:
    getstatic rung36_jcon_collate/icn_pv_main_s2 J
    lstore 156
    getstatic rung36_jcon_collate/icn_pv_main_s1 J
    lstore 158
    invokestatic rung36_jcon_collate/icn_collate()V
    lload 156
    putstatic rung36_jcon_collate/icn_pv_main_s2 J
    lload 158
    putstatic rung36_jcon_collate/icn_pv_main_s1 J
    getstatic rung36_jcon_collate/icn_failed B
    ifne icn_28_after_call
    getstatic rung36_jcon_collate/icn_retval J
    goto icn_27_store
icn_28_after_call:
    goto icn_21_α
icn_27_α:
    goto icn_28_α
icn_27_β:
    goto icn_28_β
icn_27_store:
    putstatic rung36_jcon_collate/icn_pv_main_s1 J
    getstatic rung36_jcon_collate/icn_pv_main_s1 J
    goto icn_main_s0_sdrain
icn_main_s0_sdrain:
    pop2
    goto icn_21_α
icn_main_done:
    return
.end method

.method public static icn_collate()V
    .limit stack 16
    .limit locals 372
    lconst_0
    lstore 0
    lconst_0
    lstore 2
    lconst_0
    lstore 4
    lconst_0
    lstore 6
    lconst_0
    lstore 8
    lconst_0
    lstore 10
    lconst_0
    lstore 12
    lconst_0
    lstore 14
    lconst_0
    lstore 16
    lconst_0
    lstore 18
    lconst_0
    lstore 20
    lconst_0
    lstore 22
    lconst_0
    lstore 24
    lconst_0
    lstore 26
    lconst_0
    lstore 28
    lconst_0
    lstore 30
    lconst_0
    lstore 32
    lconst_0
    lstore 34
    lconst_0
    lstore 36
    lconst_0
    lstore 38
    lconst_0
    lstore 40
    lconst_0
    lstore 42
    lconst_0
    lstore 44
    lconst_0
    lstore 46
    lconst_0
    lstore 48
    lconst_0
    lstore 50
    lconst_0
    lstore 52
    lconst_0
    lstore 54
    lconst_0
    lstore 56
    lconst_0
    lstore 58
    lconst_0
    lstore 60
    lconst_0
    lstore 62
    iconst_0
    istore 84
    iconst_0
    istore 85
    iconst_0
    istore 86
    iconst_0
    istore 87
    iconst_0
    istore 88
    iconst_0
    istore 89
    iconst_0
    istore 90
    iconst_0
    istore 91
    iconst_0
    istore 92
    iconst_0
    istore 93
    iconst_0
    istore 94
    iconst_0
    istore 95
    iconst_0
    istore 96
    iconst_0
    istore 97
    iconst_0
    istore 98
    iconst_0
    istore 99
    iconst_0
    istore 100
    iconst_0
    istore 101
    iconst_0
    istore 102
    iconst_0
    istore 103
    iconst_0
    istore 104
    iconst_0
    istore 105
    iconst_0
    istore 106
    iconst_0
    istore 107
    iconst_0
    istore 108
    iconst_0
    istore 109
    iconst_0
    istore 110
    iconst_0
    istore 111
    iconst_0
    istore 112
    iconst_0
    istore 113
    iconst_0
    istore 114
    iconst_0
    istore 115
    aconst_null
    astore 148
    aconst_null
    astore 149
    aconst_null
    astore 150
    aconst_null
    astore 151
    aconst_null
    astore 152
    aconst_null
    astore 153
    aconst_null
    astore 154
    aconst_null
    astore 155
    aconst_null
    astore 156
    aconst_null
    astore 157
    getstatic rung36_jcon_collate/icn_arg_str_0 Ljava/lang/String;
    putstatic rung36_jcon_collate/icn_pv_collate_s1 Ljava/lang/String;
    getstatic rung36_jcon_collate/icn_arg_str_1 Ljava/lang/String;
    putstatic rung36_jcon_collate/icn_pv_collate_s2 Ljava/lang/String;
    goto icn_130_α
;  VAR
icn_34_α:
    getstatic rung36_jcon_collate/icn_pv_collate_t Ljava/lang/String;
    goto icn_33_rrelay
icn_34_β:
    goto icn_33_lb
;  VAR
icn_37_α:
    getstatic rung36_jcon_collate/icn_pv_collate_clabels Ljava/lang/String;
    goto icn_36_left_mid
icn_37_β:
    goto icn_32_ret_fail
;  VAR
icn_39_α:
    getstatic rung36_jcon_collate/icn_pv_collate_length J
    goto icn_38_rrelay
icn_39_β:
    goto icn_38_lb
;  INT
icn_40_α:
    ldc2_w 2
    goto icn_38_lrelay
icn_40_β:
    goto icn_32_ret_fail
icn_38_lrelay:
    putstatic rung36_jcon_collate/icn_38_binop_lc J
    goto icn_38_lstore
icn_38_rrelay:
    putstatic rung36_jcon_collate/icn_38_binop_rc J
    goto icn_38_compute
icn_38_lb:
    goto icn_40_β
icn_38_α:
    iconst_0
    putstatic rung36_jcon_collate/icn_38_binop_bf I
    goto icn_40_α
icn_38_β:
    iconst_1
    putstatic rung36_jcon_collate/icn_38_binop_bf I
    goto icn_40_α
icn_38_lstore:
    getstatic rung36_jcon_collate/icn_38_binop_bf I
    ifeq icn_39_α
    goto icn_39_β
icn_38_compute:
    getstatic rung36_jcon_collate/icn_38_binop_lc J
    getstatic rung36_jcon_collate/icn_38_binop_rc J
    lmul
    goto icn_36_left_after
icn_36_α:
    goto icn_37_α
icn_36_β:
    goto icn_37_β
icn_36_left_mid:
    putstatic rung36_jcon_collate/icn_36_left_s Ljava/lang/String;
    goto icn_38_α
icn_36_left_after:
    l2i
    istore 85
    getstatic rung36_jcon_collate/icn_36_left_s Ljava/lang/String;
    iload 85
    ldc " "
    invokestatic rung36_jcon_collate/icn_builtin_left(Ljava/lang/String;ILjava/lang/String;)Ljava/lang/String;
    goto icn_35_map_mid1
;  VAR
icn_43_α:
    getstatic rung36_jcon_collate/icn_pv_collate_rlabels Ljava/lang/String;
    goto icn_42_left_mid
icn_43_β:
    goto icn_41_lb
;  VAR
icn_44_α:
    getstatic rung36_jcon_collate/icn_pv_collate_length J
    goto icn_42_left_after
icn_44_β:
    goto icn_41_lb
icn_42_α:
    goto icn_43_α
icn_42_β:
    goto icn_43_β
icn_42_left_mid:
    putstatic rung36_jcon_collate/icn_42_left_s Ljava/lang/String;
    goto icn_44_α
icn_42_left_after:
    l2i
    istore 87
    getstatic rung36_jcon_collate/icn_42_left_s Ljava/lang/String;
    iload 87
    ldc " "
    invokestatic rung36_jcon_collate/icn_builtin_left(Ljava/lang/String;ILjava/lang/String;)Ljava/lang/String;
    goto icn_41_rrelay
;  VAR
icn_46_α:
    getstatic rung36_jcon_collate/icn_pv_collate_llabels Ljava/lang/String;
    goto icn_45_left_mid
icn_46_β:
    goto icn_32_ret_fail
;  VAR
icn_47_α:
    getstatic rung36_jcon_collate/icn_pv_collate_length J
    goto icn_45_left_after
icn_47_β:
    goto icn_32_ret_fail
icn_45_α:
    goto icn_46_α
icn_45_β:
    goto icn_46_β
icn_45_left_mid:
    putstatic rung36_jcon_collate/icn_45_left_s Ljava/lang/String;
    goto icn_47_α
icn_45_left_after:
    l2i
    istore 88
    getstatic rung36_jcon_collate/icn_45_left_s Ljava/lang/String;
    iload 88
    ldc " "
    invokestatic rung36_jcon_collate/icn_builtin_left(Ljava/lang/String;ILjava/lang/String;)Ljava/lang/String;
    goto icn_41_lrelay
icn_41_lrelay:
    putstatic rung36_jcon_collate/icn_41_lc Ljava/lang/String;
    goto icn_41_lstore
icn_41_rrelay:
    putstatic rung36_jcon_collate/icn_41_rc Ljava/lang/String;
    goto icn_41_compute
icn_41_lb:
    goto icn_45_β
icn_41_α:
    iconst_0
    istore 86
    goto icn_45_α
icn_41_β:
    iconst_1
    istore 86
    goto icn_45_α
icn_41_lstore:
    iload 86
    ifeq icn_42_α
    goto icn_42_β
icn_41_compute:
    getstatic rung36_jcon_collate/icn_41_lc Ljava/lang/String;
    getstatic rung36_jcon_collate/icn_41_rc Ljava/lang/String;
    invokevirtual java/lang/String/concat(Ljava/lang/String;)Ljava/lang/String;
    goto icn_35_map_mid2
;  VAR
icn_49_α:
    getstatic rung36_jcon_collate/icn_pv_collate_s2 Ljava/lang/String;
    goto icn_48_rrelay
icn_49_β:
    goto icn_48_lb
;  VAR
icn_50_α:
    getstatic rung36_jcon_collate/icn_pv_collate_s1 Ljava/lang/String;
    goto icn_48_lrelay
icn_50_β:
    goto icn_32_ret_fail
icn_48_lrelay:
    putstatic rung36_jcon_collate/icn_48_lc Ljava/lang/String;
    goto icn_48_lstore
icn_48_rrelay:
    putstatic rung36_jcon_collate/icn_48_rc Ljava/lang/String;
    goto icn_48_compute
icn_48_lb:
    goto icn_50_β
icn_48_α:
    iconst_0
    istore 89
    goto icn_50_α
icn_48_β:
    iconst_1
    istore 89
    goto icn_50_α
icn_48_lstore:
    iload 89
    ifeq icn_49_α
    goto icn_49_β
icn_48_compute:
    getstatic rung36_jcon_collate/icn_48_lc Ljava/lang/String;
    getstatic rung36_jcon_collate/icn_48_rc Ljava/lang/String;
    invokevirtual java/lang/String/concat(Ljava/lang/String;)Ljava/lang/String;
    goto icn_35_map_after
icn_35_α:
    goto icn_36_α
icn_35_β:
    goto icn_36_β
icn_35_map_mid1:
    astore 148
    goto icn_41_α
icn_35_map_mid2:
    astore 149
    goto icn_48_α
icn_35_map_after:
    astore 150
    aload 148
    aload 149
    aload 150
    invokestatic rung36_jcon_collate/icn_builtin_map(Ljava/lang/String;Ljava/lang/String;Ljava/lang/String;)Ljava/lang/String;
    goto icn_33_lrelay
icn_33_lrelay:
    putstatic rung36_jcon_collate/icn_33_lc Ljava/lang/String;
    goto icn_33_lstore
icn_33_rrelay:
    putstatic rung36_jcon_collate/icn_33_rc Ljava/lang/String;
    goto icn_33_compute
icn_33_lb:
    goto icn_35_β
icn_33_α:
    iconst_0
    istore 84
    goto icn_35_α
icn_33_β:
    iconst_1
    istore 84
    goto icn_35_α
icn_33_lstore:
    iload 84
    ifeq icn_34_α
    goto icn_34_β
icn_33_compute:
    getstatic rung36_jcon_collate/icn_33_lc Ljava/lang/String;
    getstatic rung36_jcon_collate/icn_33_rc Ljava/lang/String;
    invokevirtual java/lang/String/concat(Ljava/lang/String;)Ljava/lang/String;
    goto icn_32_ret_store
icn_32_α:
    goto icn_33_α
icn_32_β:
    goto icn_collate_ret
icn_32_ret_fail:
    iconst_1
    putstatic rung36_jcon_collate/icn_failed B
    goto icn_collate_done
icn_32_ret_store:
    putstatic rung36_jcon_collate/icn_retval_str Ljava/lang/String;
    lconst_0
    putstatic rung36_jcon_collate/icn_retval J
    iconst_0
    putstatic rung36_jcon_collate/icn_failed B
    goto icn_collate_ret
;  VAR
icn_53_α:
    getstatic rung36_jcon_collate/icn_pv_collate_t Ljava/lang/String;
    goto icn_52_rrelay
icn_53_β:
    goto icn_52_lb
;  VAR
icn_57_α:
    getstatic rung36_jcon_collate/icn_pv_collate_s2 Ljava/lang/String;
    goto icn_56_right_mid
icn_57_β:
    goto icn_54_lb
;  VAR
icn_59_α:
    getstatic rung36_jcon_collate/icn_pv_collate_half J
    goto icn_58_rrelay
icn_59_β:
    goto icn_58_lb
;  VAR
icn_60_α:
    getstatic rung36_jcon_collate/icn_pv_collate_length J
    goto icn_58_lrelay
icn_60_β:
    goto icn_54_lb
icn_58_lrelay:
    putstatic rung36_jcon_collate/icn_58_binop_lc J
    goto icn_58_lstore
icn_58_rrelay:
    putstatic rung36_jcon_collate/icn_58_binop_rc J
    goto icn_58_compute
icn_58_lb:
    goto icn_60_β
icn_58_α:
    iconst_0
    putstatic rung36_jcon_collate/icn_58_binop_bf I
    goto icn_60_α
icn_58_β:
    iconst_1
    putstatic rung36_jcon_collate/icn_58_binop_bf I
    goto icn_60_α
icn_58_lstore:
    getstatic rung36_jcon_collate/icn_58_binop_bf I
    ifeq icn_59_α
    goto icn_59_β
icn_58_compute:
    getstatic rung36_jcon_collate/icn_58_binop_lc J
    getstatic rung36_jcon_collate/icn_58_binop_rc J
    lsub
    goto icn_56_right_after
icn_56_α:
    goto icn_57_α
icn_56_β:
    goto icn_57_β
icn_56_right_mid:
    putstatic rung36_jcon_collate/icn_56_right_s Ljava/lang/String;
    goto icn_58_α
icn_56_right_after:
    l2i
    istore 92
    getstatic rung36_jcon_collate/icn_56_right_s Ljava/lang/String;
    iload 92
    ldc " "
    invokestatic rung36_jcon_collate/icn_builtin_right(Ljava/lang/String;ILjava/lang/String;)Ljava/lang/String;
    goto icn_55_arg1
icn_55_arg1:
    putstatic rung36_jcon_collate/icn_arg_str_1 Ljava/lang/String;
    lconst_0
    putstatic rung36_jcon_collate/icn_arg_1 J
    goto icn_55_docall
;  VAR
icn_62_α:
    getstatic rung36_jcon_collate/icn_pv_collate_s1 Ljava/lang/String;
    goto icn_61_right_mid
icn_62_β:
    goto icn_54_lb
;  VAR
icn_64_α:
    getstatic rung36_jcon_collate/icn_pv_collate_half J
    goto icn_63_rrelay
icn_64_β:
    goto icn_63_lb
;  VAR
icn_65_α:
    getstatic rung36_jcon_collate/icn_pv_collate_length J
    goto icn_63_lrelay
icn_65_β:
    goto icn_54_lb
icn_63_lrelay:
    putstatic rung36_jcon_collate/icn_63_binop_lc J
    goto icn_63_lstore
icn_63_rrelay:
    putstatic rung36_jcon_collate/icn_63_binop_rc J
    goto icn_63_compute
icn_63_lb:
    goto icn_65_β
icn_63_α:
    iconst_0
    putstatic rung36_jcon_collate/icn_63_binop_bf I
    goto icn_65_α
icn_63_β:
    iconst_1
    putstatic rung36_jcon_collate/icn_63_binop_bf I
    goto icn_65_α
icn_63_lstore:
    getstatic rung36_jcon_collate/icn_63_binop_bf I
    ifeq icn_64_α
    goto icn_64_β
icn_63_compute:
    getstatic rung36_jcon_collate/icn_63_binop_lc J
    getstatic rung36_jcon_collate/icn_63_binop_rc J
    lsub
    goto icn_61_right_after
icn_61_α:
    goto icn_62_α
icn_61_β:
    goto icn_62_β
icn_61_right_mid:
    putstatic rung36_jcon_collate/icn_61_right_s Ljava/lang/String;
    goto icn_63_α
icn_61_right_after:
    l2i
    istore 93
    getstatic rung36_jcon_collate/icn_61_right_s Ljava/lang/String;
    iload 93
    ldc " "
    invokestatic rung36_jcon_collate/icn_builtin_right(Ljava/lang/String;ILjava/lang/String;)Ljava/lang/String;
    goto icn_55_arg0
icn_55_arg0:
    putstatic rung36_jcon_collate/icn_arg_str_0 Ljava/lang/String;
    lconst_0
    putstatic rung36_jcon_collate/icn_arg_0 J
    goto icn_56_α
icn_55_α:
    goto icn_61_α
icn_55_β:
    goto icn_56_β
icn_55_docall:
    getstatic rung36_jcon_collate/icn_38_binop_lc J
    lstore 155
    getstatic rung36_jcon_collate/icn_38_binop_rc J
    lstore 157
    getstatic rung36_jcon_collate/icn_pv_collate_length J
    lstore 159
    getstatic rung36_jcon_collate/icn_58_binop_lc J
    lstore 161
    getstatic rung36_jcon_collate/icn_58_binop_rc J
    lstore 163
    getstatic rung36_jcon_collate/icn_pv_collate_half J
    lstore 165
    getstatic rung36_jcon_collate/icn_63_binop_lc J
    lstore 167
    getstatic rung36_jcon_collate/icn_63_binop_rc J
    lstore 169
    invokestatic rung36_jcon_collate/icn_collate()V
    lload 155
    putstatic rung36_jcon_collate/icn_38_binop_lc J
    lload 157
    putstatic rung36_jcon_collate/icn_38_binop_rc J
    lload 159
    putstatic rung36_jcon_collate/icn_pv_collate_length J
    lload 161
    putstatic rung36_jcon_collate/icn_58_binop_lc J
    lload 163
    putstatic rung36_jcon_collate/icn_58_binop_rc J
    lload 165
    putstatic rung36_jcon_collate/icn_pv_collate_half J
    lload 167
    putstatic rung36_jcon_collate/icn_63_binop_lc J
    lload 169
    putstatic rung36_jcon_collate/icn_63_binop_rc J
    getstatic rung36_jcon_collate/icn_failed B
    ifne icn_55_after_call
    getstatic rung36_jcon_collate/icn_retval J
    goto icn_54_rrelay
icn_55_after_call:
    goto icn_54_lb
;  VAR
icn_67_α:
    getstatic rung36_jcon_collate/icn_pv_collate_clabels Ljava/lang/String;
    goto icn_66_map_mid1
icn_67_β:
    goto icn_51_ret_fail
;  VAR
icn_68_α:
    getstatic rung36_jcon_collate/icn_pv_collate_blabels Ljava/lang/String;
    goto icn_66_map_mid2
icn_68_β:
    goto icn_51_ret_fail
;  VAR
icn_71_α:
    getstatic rung36_jcon_collate/icn_pv_collate_s2 Ljava/lang/String;
    goto icn_70_left_mid
icn_71_β:
    goto icn_69_lb
;  VAR
icn_72_α:
    getstatic rung36_jcon_collate/icn_pv_collate_half J
    goto icn_70_left_after
icn_72_β:
    goto icn_69_lb
icn_70_α:
    goto icn_71_α
icn_70_β:
    goto icn_71_β
icn_70_left_mid:
    putstatic rung36_jcon_collate/icn_70_left_s Ljava/lang/String;
    goto icn_72_α
icn_70_left_after:
    l2i
    istore 95
    getstatic rung36_jcon_collate/icn_70_left_s Ljava/lang/String;
    iload 95
    ldc " "
    invokestatic rung36_jcon_collate/icn_builtin_left(Ljava/lang/String;ILjava/lang/String;)Ljava/lang/String;
    goto icn_69_rrelay
;  VAR
icn_74_α:
    getstatic rung36_jcon_collate/icn_pv_collate_s1 Ljava/lang/String;
    goto icn_73_left_mid
icn_74_β:
    goto icn_51_ret_fail
;  VAR
icn_75_α:
    getstatic rung36_jcon_collate/icn_pv_collate_half J
    goto icn_73_left_after
icn_75_β:
    goto icn_51_ret_fail
icn_73_α:
    goto icn_74_α
icn_73_β:
    goto icn_74_β
icn_73_left_mid:
    putstatic rung36_jcon_collate/icn_73_left_s Ljava/lang/String;
    goto icn_75_α
icn_73_left_after:
    l2i
    istore 96
    getstatic rung36_jcon_collate/icn_73_left_s Ljava/lang/String;
    iload 96
    ldc " "
    invokestatic rung36_jcon_collate/icn_builtin_left(Ljava/lang/String;ILjava/lang/String;)Ljava/lang/String;
    goto icn_69_lrelay
icn_69_lrelay:
    putstatic rung36_jcon_collate/icn_69_lc Ljava/lang/String;
    goto icn_69_lstore
icn_69_rrelay:
    putstatic rung36_jcon_collate/icn_69_rc Ljava/lang/String;
    goto icn_69_compute
icn_69_lb:
    goto icn_73_β
icn_69_α:
    iconst_0
    istore 94
    goto icn_73_α
icn_69_β:
    iconst_1
    istore 94
    goto icn_73_α
icn_69_lstore:
    iload 94
    ifeq icn_70_α
    goto icn_70_β
icn_69_compute:
    getstatic rung36_jcon_collate/icn_69_lc Ljava/lang/String;
    getstatic rung36_jcon_collate/icn_69_rc Ljava/lang/String;
    invokevirtual java/lang/String/concat(Ljava/lang/String;)Ljava/lang/String;
    goto icn_66_map_after
icn_66_α:
    goto icn_67_α
icn_66_β:
    goto icn_67_β
icn_66_map_mid1:
    astore 151
    goto icn_68_α
icn_66_map_mid2:
    astore 152
    goto icn_69_α
icn_66_map_after:
    astore 153
    aload 151
    aload 152
    aload 153
    invokestatic rung36_jcon_collate/icn_builtin_map(Ljava/lang/String;Ljava/lang/String;Ljava/lang/String;)Ljava/lang/String;
    goto icn_54_lrelay
icn_54_lrelay:
    putstatic rung36_jcon_collate/icn_54_lc Ljava/lang/String;
    goto icn_54_lstore
icn_54_rrelay:
    putstatic rung36_jcon_collate/icn_54_rc Ljava/lang/String;
    goto icn_54_compute
icn_54_lb:
    goto icn_66_β
icn_54_α:
    iconst_0
    istore 91
    goto icn_66_α
icn_54_β:
    iconst_1
    istore 91
    goto icn_66_α
icn_54_lstore:
    iload 91
    ifeq icn_55_α
    goto icn_55_β
icn_54_compute:
    getstatic rung36_jcon_collate/icn_54_lc Ljava/lang/String;
    getstatic rung36_jcon_collate/icn_54_rc Ljava/lang/String;
    invokevirtual java/lang/String/concat(Ljava/lang/String;)Ljava/lang/String;
    goto icn_52_lrelay
icn_52_lrelay:
    putstatic rung36_jcon_collate/icn_52_lc Ljava/lang/String;
    goto icn_52_lstore
icn_52_rrelay:
    putstatic rung36_jcon_collate/icn_52_rc Ljava/lang/String;
    goto icn_52_compute
icn_52_lb:
    goto icn_54_β
icn_52_α:
    iconst_0
    istore 90
    goto icn_54_α
icn_52_β:
    iconst_1
    istore 90
    goto icn_54_α
icn_52_lstore:
    iload 90
    ifeq icn_53_α
    goto icn_53_β
icn_52_compute:
    getstatic rung36_jcon_collate/icn_52_lc Ljava/lang/String;
    getstatic rung36_jcon_collate/icn_52_rc Ljava/lang/String;
    invokevirtual java/lang/String/concat(Ljava/lang/String;)Ljava/lang/String;
    goto icn_51_ret_store
icn_51_α:
    goto icn_52_α
icn_51_β:
    goto icn_collate_ret
icn_51_ret_fail:
    iconst_1
    putstatic rung36_jcon_collate/icn_failed B
    goto icn_collate_done
icn_51_ret_store:
    putstatic rung36_jcon_collate/icn_retval_str Ljava/lang/String;
    lconst_0
    putstatic rung36_jcon_collate/icn_retval J
    iconst_0
    putstatic rung36_jcon_collate/icn_failed B
    goto icn_collate_ret
;  VAR
icn_77_α:
    getstatic rung36_jcon_collate/icn_pv_collate_half J
    goto icn_76_rrelay
icn_77_β:
    goto icn_76_lb
;  VAR
icn_78_α:
    getstatic rung36_jcon_collate/icn_pv_collate_length J
    goto icn_76_lrelay
icn_78_β:
    goto icn_31_else
icn_76_lrelay:
    putstatic rung36_jcon_collate/icn_76_relop_lc J
    goto icn_76_lstore
icn_76_rrelay:
    putstatic rung36_jcon_collate/icn_76_relop_rc J
    goto icn_76_check
icn_76_lb:
    goto icn_78_β
icn_76_α:
    goto icn_78_α
icn_76_β:
    goto icn_77_β
icn_76_lstore:
    goto icn_77_α
icn_76_check:
    getstatic rung36_jcon_collate/icn_76_relop_lc J
    getstatic rung36_jcon_collate/icn_76_relop_rc J
    lcmp
    ifgt icn_77_β
    getstatic rung36_jcon_collate/icn_76_relop_rc J
    goto icn_31_then
icn_31_then:
    pop2
    goto icn_32_α
icn_31_else:
    goto icn_51_α
icn_31_α:
    goto icn_76_α
icn_31_β:
    goto icn_76_β
;  VAR
icn_81_α:
    getstatic rung36_jcon_collate/icn_pv_collate_s1 Ljava/lang/String;
    goto icn_80_relay
icn_81_β:
    goto icn_31_α
icn_80_α:
    goto icn_81_α
icn_80_β:
    goto icn_81_β
icn_80_relay:
    invokevirtual java/lang/String/length()I
    i2l
    goto icn_79_store
icn_79_α:
    goto icn_80_α
icn_79_β:
    goto icn_80_β
icn_79_store:
    putstatic rung36_jcon_collate/icn_pv_collate_length J
    getstatic rung36_jcon_collate/icn_pv_collate_length J
    goto icn_collate_s4_sdrain
icn_collate_s4_sdrain:
    pop2
    goto icn_31_α
;  VAR
icn_86_α:
    getstatic rung36_jcon_collate/icn_pv_collate_s1 Ljava/lang/String;
    goto icn_85_sec_sr
icn_86_β:
    goto icn_83_seq_rf_0
;  INT
icn_88_α:
    ldc2_w 1
    goto icn_87_rrelay
icn_88_β:
    goto icn_87_lb
;  VAR
icn_90_α:
    getstatic rung36_jcon_collate/icn_pv_collate_s2 Ljava/lang/String;
    goto icn_89_relay
icn_90_β:
    goto icn_83_seq_rf_0
icn_89_α:
    goto icn_90_α
icn_89_β:
    goto icn_90_β
icn_89_relay:
    invokevirtual java/lang/String/length()I
    i2l
    goto icn_87_lrelay
icn_87_lrelay:
    putstatic rung36_jcon_collate/icn_87_binop_lc J
    goto icn_87_lstore
icn_87_rrelay:
    putstatic rung36_jcon_collate/icn_87_binop_rc J
    goto icn_87_compute
icn_87_lb:
    goto icn_89_β
icn_87_α:
    iconst_0
    putstatic rung36_jcon_collate/icn_87_binop_bf I
    goto icn_89_α
icn_87_β:
    goto icn_88_β
icn_87_lstore:
    getstatic rung36_jcon_collate/icn_87_binop_bf I
    ifeq icn_88_α
    goto icn_88_β
icn_87_compute:
    getstatic rung36_jcon_collate/icn_87_binop_lc J
    getstatic rung36_jcon_collate/icn_87_binop_rc J
    ladd
    goto icn_85_sec_lor
;  INT
icn_91_α:
    ldc2_w 0
    goto icn_85_sec_hir
icn_91_β:
    goto icn_83_seq_rf_0
icn_85_sec_lor:
    l2i
    istore 97
    iload 97
    ifgt icn_85_sec_lop
    iload 97
    iflt icn_85_sec_lon
icn_85_sec_loz:
    goto icn_83_seq_rf_0
icn_85_sec_lop:
    iload 97
    iconst_1
    isub
    putstatic rung36_jcon_collate/icn_85_sec_lo I
    goto icn_91_α
icn_85_sec_lon:
    getstatic rung36_jcon_collate/icn_85_sec_s Ljava/lang/String;
    invokevirtual java/lang/String/length()I
    iload 97
    iadd
    putstatic rung36_jcon_collate/icn_85_sec_lo I
    goto icn_91_α
icn_85_sec_hir:
    l2i
    istore 98
    iload 98
    ifgt icn_85_sec_hip
    iload 98
    iflt icn_85_sec_hin
icn_85_sec_hiz:
    goto icn_83_seq_rf_0
icn_85_sec_hip:
    iload 98
    iconst_1
    isub
    putstatic rung36_jcon_collate/icn_85_sec_hi I
    goto icn_85_sec_cmp
icn_85_sec_hin:
    getstatic rung36_jcon_collate/icn_85_sec_s Ljava/lang/String;
    invokevirtual java/lang/String/length()I
    iload 98
    iadd
    putstatic rung36_jcon_collate/icn_85_sec_hi I
    goto icn_85_sec_cmp
icn_85_sec_cmp:
    getstatic rung36_jcon_collate/icn_85_sec_lo I
    iflt icn_83_seq_rf_0
    getstatic rung36_jcon_collate/icn_85_sec_hi I
    iflt icn_83_seq_rf_0
    getstatic rung36_jcon_collate/icn_85_sec_s Ljava/lang/String;
    invokevirtual java/lang/String/length()I
    getstatic rung36_jcon_collate/icn_85_sec_lo I
    if_icmplt icn_83_seq_rf_0
    getstatic rung36_jcon_collate/icn_85_sec_s Ljava/lang/String;
    invokevirtual java/lang/String/length()I
    istore 99
    getstatic rung36_jcon_collate/icn_85_sec_hi I
    iload 99
    if_icmple icn_85_sec_hiok
    iload 99
    putstatic rung36_jcon_collate/icn_85_sec_hi I
icn_85_sec_hiok:
    getstatic rung36_jcon_collate/icn_85_sec_s Ljava/lang/String;
    getstatic rung36_jcon_collate/icn_85_sec_lo I
    getstatic rung36_jcon_collate/icn_85_sec_hi I
    invokevirtual java/lang/String/substring(II)Ljava/lang/String;
    goto icn_84_store
icn_85_α:
    goto icn_86_α
icn_85_sec_sr:
    putstatic rung36_jcon_collate/icn_85_sec_s Ljava/lang/String;
    goto icn_87_α
icn_85_β:
    goto icn_83_seq_rf_0
icn_84_α:
    goto icn_85_α
icn_84_β:
    goto icn_85_β
icn_84_store:
    putstatic rung36_jcon_collate/icn_pv_collate_t Ljava/lang/String;
    getstatic rung36_jcon_collate/icn_pv_collate_t Ljava/lang/String;
    goto icn_83_seq_rg_0
;  VAR
icn_94_α:
    getstatic rung36_jcon_collate/icn_pv_collate_s1 Ljava/lang/String;
    goto icn_93_sec_sr
icn_94_β:
    goto icn_79_α
;  INT
icn_95_α:
    ldc2_w 1
    goto icn_93_sec_lor
icn_95_β:
    goto icn_79_α
;  INT
icn_97_α:
    ldc2_w 1
    goto icn_96_rrelay
icn_97_β:
    goto icn_96_lb
;  VAR
icn_99_α:
    getstatic rung36_jcon_collate/icn_pv_collate_s2 Ljava/lang/String;
    goto icn_98_relay
icn_99_β:
    goto icn_79_α
icn_98_α:
    goto icn_99_α
icn_98_β:
    goto icn_99_β
icn_98_relay:
    invokevirtual java/lang/String/length()I
    i2l
    goto icn_96_lrelay
icn_96_lrelay:
    putstatic rung36_jcon_collate/icn_96_binop_lc J
    goto icn_96_lstore
icn_96_rrelay:
    putstatic rung36_jcon_collate/icn_96_binop_rc J
    goto icn_96_compute
icn_96_lb:
    goto icn_98_β
icn_96_α:
    iconst_0
    putstatic rung36_jcon_collate/icn_96_binop_bf I
    goto icn_98_α
icn_96_β:
    goto icn_97_β
icn_96_lstore:
    getstatic rung36_jcon_collate/icn_96_binop_bf I
    ifeq icn_97_α
    goto icn_97_β
icn_96_compute:
    getstatic rung36_jcon_collate/icn_96_binop_lc J
    getstatic rung36_jcon_collate/icn_96_binop_rc J
    ladd
    goto icn_93_sec_hir
icn_93_sec_lor:
    l2i
    istore 100
    iload 100
    ifgt icn_93_sec_lop
    iload 100
    iflt icn_93_sec_lon
icn_93_sec_loz:
    goto icn_79_α
icn_93_sec_lop:
    iload 100
    iconst_1
    isub
    putstatic rung36_jcon_collate/icn_93_sec_lo I
    goto icn_96_α
icn_93_sec_lon:
    getstatic rung36_jcon_collate/icn_93_sec_s Ljava/lang/String;
    invokevirtual java/lang/String/length()I
    iload 100
    iadd
    putstatic rung36_jcon_collate/icn_93_sec_lo I
    goto icn_96_α
icn_93_sec_hir:
    l2i
    istore 101
    iload 101
    ifgt icn_93_sec_hip
    iload 101
    iflt icn_93_sec_hin
icn_93_sec_hiz:
    goto icn_79_α
icn_93_sec_hip:
    iload 101
    iconst_1
    isub
    putstatic rung36_jcon_collate/icn_93_sec_hi I
    goto icn_93_sec_cmp
icn_93_sec_hin:
    getstatic rung36_jcon_collate/icn_93_sec_s Ljava/lang/String;
    invokevirtual java/lang/String/length()I
    iload 101
    iadd
    putstatic rung36_jcon_collate/icn_93_sec_hi I
    goto icn_93_sec_cmp
icn_93_sec_cmp:
    getstatic rung36_jcon_collate/icn_93_sec_lo I
    iflt icn_79_α
    getstatic rung36_jcon_collate/icn_93_sec_hi I
    iflt icn_79_α
    getstatic rung36_jcon_collate/icn_93_sec_s Ljava/lang/String;
    invokevirtual java/lang/String/length()I
    getstatic rung36_jcon_collate/icn_93_sec_lo I
    if_icmplt icn_79_α
    getstatic rung36_jcon_collate/icn_93_sec_s Ljava/lang/String;
    invokevirtual java/lang/String/length()I
    istore 102
    getstatic rung36_jcon_collate/icn_93_sec_hi I
    iload 102
    if_icmple icn_93_sec_hiok
    iload 102
    putstatic rung36_jcon_collate/icn_93_sec_hi I
icn_93_sec_hiok:
    getstatic rung36_jcon_collate/icn_93_sec_s Ljava/lang/String;
    getstatic rung36_jcon_collate/icn_93_sec_lo I
    getstatic rung36_jcon_collate/icn_93_sec_hi I
    invokevirtual java/lang/String/substring(II)Ljava/lang/String;
    goto icn_92_store
icn_93_α:
    goto icn_94_α
icn_93_sec_sr:
    putstatic rung36_jcon_collate/icn_93_sec_s Ljava/lang/String;
    goto icn_95_α
icn_93_β:
    goto icn_79_α
icn_92_α:
    goto icn_93_α
icn_92_β:
    goto icn_93_β
icn_92_store:
    putstatic rung36_jcon_collate/icn_pv_collate_s1 Ljava/lang/String;
    getstatic rung36_jcon_collate/icn_pv_collate_s1 Ljava/lang/String;
    goto icn_collate_s3_sdrain
    goto icn_83_α
icn_83_seq_rg_0:
    pop
    goto icn_92_α
icn_83_seq_rf_0:
    goto icn_92_α
icn_83_α:
    goto icn_84_α
icn_83_β:
    goto icn_92_β
;  VAR
icn_104_α:
    getstatic rung36_jcon_collate/icn_pv_collate_s2 Ljava/lang/String;
    goto icn_103_sec_sr
icn_104_β:
    goto icn_101_seq_rf_0
;  INT
icn_106_α:
    ldc2_w 1
    goto icn_105_rrelay
icn_106_β:
    goto icn_105_lb
;  VAR
icn_108_α:
    getstatic rung36_jcon_collate/icn_pv_collate_s1 Ljava/lang/String;
    goto icn_107_relay
icn_108_β:
    goto icn_101_seq_rf_0
icn_107_α:
    goto icn_108_α
icn_107_β:
    goto icn_108_β
icn_107_relay:
    invokevirtual java/lang/String/length()I
    i2l
    goto icn_105_lrelay
icn_105_lrelay:
    putstatic rung36_jcon_collate/icn_105_binop_lc J
    goto icn_105_lstore
icn_105_rrelay:
    putstatic rung36_jcon_collate/icn_105_binop_rc J
    goto icn_105_compute
icn_105_lb:
    goto icn_107_β
icn_105_α:
    iconst_0
    putstatic rung36_jcon_collate/icn_105_binop_bf I
    goto icn_107_α
icn_105_β:
    goto icn_106_β
icn_105_lstore:
    getstatic rung36_jcon_collate/icn_105_binop_bf I
    ifeq icn_106_α
    goto icn_106_β
icn_105_compute:
    getstatic rung36_jcon_collate/icn_105_binop_lc J
    getstatic rung36_jcon_collate/icn_105_binop_rc J
    ladd
    goto icn_103_sec_lor
;  INT
icn_109_α:
    ldc2_w 0
    goto icn_103_sec_hir
icn_109_β:
    goto icn_101_seq_rf_0
icn_103_sec_lor:
    l2i
    istore 103
    iload 103
    ifgt icn_103_sec_lop
    iload 103
    iflt icn_103_sec_lon
icn_103_sec_loz:
    goto icn_101_seq_rf_0
icn_103_sec_lop:
    iload 103
    iconst_1
    isub
    putstatic rung36_jcon_collate/icn_103_sec_lo I
    goto icn_109_α
icn_103_sec_lon:
    getstatic rung36_jcon_collate/icn_103_sec_s Ljava/lang/String;
    invokevirtual java/lang/String/length()I
    iload 103
    iadd
    putstatic rung36_jcon_collate/icn_103_sec_lo I
    goto icn_109_α
icn_103_sec_hir:
    l2i
    istore 104
    iload 104
    ifgt icn_103_sec_hip
    iload 104
    iflt icn_103_sec_hin
icn_103_sec_hiz:
    goto icn_101_seq_rf_0
icn_103_sec_hip:
    iload 104
    iconst_1
    isub
    putstatic rung36_jcon_collate/icn_103_sec_hi I
    goto icn_103_sec_cmp
icn_103_sec_hin:
    getstatic rung36_jcon_collate/icn_103_sec_s Ljava/lang/String;
    invokevirtual java/lang/String/length()I
    iload 104
    iadd
    putstatic rung36_jcon_collate/icn_103_sec_hi I
    goto icn_103_sec_cmp
icn_103_sec_cmp:
    getstatic rung36_jcon_collate/icn_103_sec_lo I
    iflt icn_101_seq_rf_0
    getstatic rung36_jcon_collate/icn_103_sec_hi I
    iflt icn_101_seq_rf_0
    getstatic rung36_jcon_collate/icn_103_sec_s Ljava/lang/String;
    invokevirtual java/lang/String/length()I
    getstatic rung36_jcon_collate/icn_103_sec_lo I
    if_icmplt icn_101_seq_rf_0
    getstatic rung36_jcon_collate/icn_103_sec_s Ljava/lang/String;
    invokevirtual java/lang/String/length()I
    istore 105
    getstatic rung36_jcon_collate/icn_103_sec_hi I
    iload 105
    if_icmple icn_103_sec_hiok
    iload 105
    putstatic rung36_jcon_collate/icn_103_sec_hi I
icn_103_sec_hiok:
    getstatic rung36_jcon_collate/icn_103_sec_s Ljava/lang/String;
    getstatic rung36_jcon_collate/icn_103_sec_lo I
    getstatic rung36_jcon_collate/icn_103_sec_hi I
    invokevirtual java/lang/String/substring(II)Ljava/lang/String;
    goto icn_102_store
icn_103_α:
    goto icn_104_α
icn_103_sec_sr:
    putstatic rung36_jcon_collate/icn_103_sec_s Ljava/lang/String;
    goto icn_105_α
icn_103_β:
    goto icn_101_seq_rf_0
icn_102_α:
    goto icn_103_α
icn_102_β:
    goto icn_103_β
icn_102_store:
    putstatic rung36_jcon_collate/icn_pv_collate_t Ljava/lang/String;
    getstatic rung36_jcon_collate/icn_pv_collate_t Ljava/lang/String;
    goto icn_101_seq_rg_0
;  VAR
icn_112_α:
    getstatic rung36_jcon_collate/icn_pv_collate_s2 Ljava/lang/String;
    goto icn_111_sec_sr
icn_112_β:
    goto icn_79_α
;  INT
icn_113_α:
    ldc2_w 1
    goto icn_111_sec_lor
icn_113_β:
    goto icn_79_α
;  INT
icn_115_α:
    ldc2_w 1
    goto icn_114_rrelay
icn_115_β:
    goto icn_114_lb
;  VAR
icn_117_α:
    getstatic rung36_jcon_collate/icn_pv_collate_s1 Ljava/lang/String;
    goto icn_116_relay
icn_117_β:
    goto icn_79_α
icn_116_α:
    goto icn_117_α
icn_116_β:
    goto icn_117_β
icn_116_relay:
    invokevirtual java/lang/String/length()I
    i2l
    goto icn_114_lrelay
icn_114_lrelay:
    putstatic rung36_jcon_collate/icn_114_binop_lc J
    goto icn_114_lstore
icn_114_rrelay:
    putstatic rung36_jcon_collate/icn_114_binop_rc J
    goto icn_114_compute
icn_114_lb:
    goto icn_116_β
icn_114_α:
    iconst_0
    putstatic rung36_jcon_collate/icn_114_binop_bf I
    goto icn_116_α
icn_114_β:
    goto icn_115_β
icn_114_lstore:
    getstatic rung36_jcon_collate/icn_114_binop_bf I
    ifeq icn_115_α
    goto icn_115_β
icn_114_compute:
    getstatic rung36_jcon_collate/icn_114_binop_lc J
    getstatic rung36_jcon_collate/icn_114_binop_rc J
    ladd
    goto icn_111_sec_hir
icn_111_sec_lor:
    l2i
    istore 106
    iload 106
    ifgt icn_111_sec_lop
    iload 106
    iflt icn_111_sec_lon
icn_111_sec_loz:
    goto icn_79_α
icn_111_sec_lop:
    iload 106
    iconst_1
    isub
    putstatic rung36_jcon_collate/icn_111_sec_lo I
    goto icn_114_α
icn_111_sec_lon:
    getstatic rung36_jcon_collate/icn_111_sec_s Ljava/lang/String;
    invokevirtual java/lang/String/length()I
    iload 106
    iadd
    putstatic rung36_jcon_collate/icn_111_sec_lo I
    goto icn_114_α
icn_111_sec_hir:
    l2i
    istore 107
    iload 107
    ifgt icn_111_sec_hip
    iload 107
    iflt icn_111_sec_hin
icn_111_sec_hiz:
    goto icn_79_α
icn_111_sec_hip:
    iload 107
    iconst_1
    isub
    putstatic rung36_jcon_collate/icn_111_sec_hi I
    goto icn_111_sec_cmp
icn_111_sec_hin:
    getstatic rung36_jcon_collate/icn_111_sec_s Ljava/lang/String;
    invokevirtual java/lang/String/length()I
    iload 107
    iadd
    putstatic rung36_jcon_collate/icn_111_sec_hi I
    goto icn_111_sec_cmp
icn_111_sec_cmp:
    getstatic rung36_jcon_collate/icn_111_sec_lo I
    iflt icn_79_α
    getstatic rung36_jcon_collate/icn_111_sec_hi I
    iflt icn_79_α
    getstatic rung36_jcon_collate/icn_111_sec_s Ljava/lang/String;
    invokevirtual java/lang/String/length()I
    getstatic rung36_jcon_collate/icn_111_sec_lo I
    if_icmplt icn_79_α
    getstatic rung36_jcon_collate/icn_111_sec_s Ljava/lang/String;
    invokevirtual java/lang/String/length()I
    istore 108
    getstatic rung36_jcon_collate/icn_111_sec_hi I
    iload 108
    if_icmple icn_111_sec_hiok
    iload 108
    putstatic rung36_jcon_collate/icn_111_sec_hi I
icn_111_sec_hiok:
    getstatic rung36_jcon_collate/icn_111_sec_s Ljava/lang/String;
    getstatic rung36_jcon_collate/icn_111_sec_lo I
    getstatic rung36_jcon_collate/icn_111_sec_hi I
    invokevirtual java/lang/String/substring(II)Ljava/lang/String;
    goto icn_110_store
icn_111_α:
    goto icn_112_α
icn_111_sec_sr:
    putstatic rung36_jcon_collate/icn_111_sec_s Ljava/lang/String;
    goto icn_113_α
icn_111_β:
    goto icn_79_α
icn_110_α:
    goto icn_111_α
icn_110_β:
    goto icn_111_β
icn_110_store:
    putstatic rung36_jcon_collate/icn_pv_collate_s2 Ljava/lang/String;
    getstatic rung36_jcon_collate/icn_pv_collate_s2 Ljava/lang/String;
    goto icn_collate_s3_sdrain
    goto icn_101_α
icn_101_seq_rg_0:
    pop
    goto icn_110_α
icn_101_seq_rf_0:
    goto icn_110_α
icn_101_α:
    goto icn_102_α
icn_101_β:
    goto icn_110_β
;  STR
icn_119_α:
    ldc ""
    goto icn_118_store
icn_119_β:
    goto icn_79_α
icn_118_α:
    goto icn_119_α
icn_118_β:
    goto icn_119_β
icn_118_store:
    putstatic rung36_jcon_collate/icn_pv_collate_t Ljava/lang/String;
    getstatic rung36_jcon_collate/icn_pv_collate_t Ljava/lang/String;
    goto icn_collate_s3_sdrain
;  VAR
icn_122_α:
    getstatic rung36_jcon_collate/icn_pv_collate_s1 Ljava/lang/String;
    goto icn_121_relay
icn_122_β:
    goto icn_120_lb
icn_121_α:
    goto icn_122_α
icn_121_β:
    goto icn_122_β
icn_121_relay:
    invokevirtual java/lang/String/length()I
    i2l
    goto icn_120_rrelay
;  VAR
icn_124_α:
    getstatic rung36_jcon_collate/icn_pv_collate_s2 Ljava/lang/String;
    goto icn_123_relay
icn_124_β:
    goto icn_100_else
icn_123_α:
    goto icn_124_α
icn_123_β:
    goto icn_124_β
icn_123_relay:
    invokevirtual java/lang/String/length()I
    i2l
    goto icn_120_lrelay
icn_120_lrelay:
    putstatic rung36_jcon_collate/icn_120_relop_lc J
    goto icn_120_lstore
icn_120_rrelay:
    putstatic rung36_jcon_collate/icn_120_relop_rc J
    goto icn_120_check
icn_120_lb:
    goto icn_123_β
icn_120_α:
    goto icn_123_α
icn_120_β:
    goto icn_121_β
icn_120_lstore:
    goto icn_121_α
icn_120_check:
    getstatic rung36_jcon_collate/icn_120_relop_lc J
    getstatic rung36_jcon_collate/icn_120_relop_rc J
    lcmp
    ifle icn_121_β
    getstatic rung36_jcon_collate/icn_120_relop_rc J
    goto icn_100_then
icn_100_then:
    pop2
    goto icn_101_α
icn_100_else:
    goto icn_118_α
icn_100_α:
    goto icn_120_α
icn_100_β:
    goto icn_120_β
;  VAR
icn_127_α:
    getstatic rung36_jcon_collate/icn_pv_collate_s2 Ljava/lang/String;
    goto icn_126_relay
icn_127_β:
    goto icn_125_lb
icn_126_α:
    goto icn_127_α
icn_126_β:
    goto icn_127_β
icn_126_relay:
    invokevirtual java/lang/String/length()I
    i2l
    goto icn_125_rrelay
;  VAR
icn_129_α:
    getstatic rung36_jcon_collate/icn_pv_collate_s1 Ljava/lang/String;
    goto icn_128_relay
icn_129_β:
    goto icn_82_else
icn_128_α:
    goto icn_129_α
icn_128_β:
    goto icn_129_β
icn_128_relay:
    invokevirtual java/lang/String/length()I
    i2l
    goto icn_125_lrelay
icn_125_lrelay:
    putstatic rung36_jcon_collate/icn_125_relop_lc J
    goto icn_125_lstore
icn_125_rrelay:
    putstatic rung36_jcon_collate/icn_125_relop_rc J
    goto icn_125_check
icn_125_lb:
    goto icn_128_β
icn_125_α:
    goto icn_128_α
icn_125_β:
    goto icn_126_β
icn_125_lstore:
    goto icn_126_α
icn_125_check:
    getstatic rung36_jcon_collate/icn_125_relop_lc J
    getstatic rung36_jcon_collate/icn_125_relop_rc J
    lcmp
    ifle icn_126_β
    getstatic rung36_jcon_collate/icn_125_relop_rc J
    goto icn_82_then
icn_82_then:
    pop2
    goto icn_83_α
icn_82_else:
    goto icn_100_α
icn_82_α:
    goto icn_125_α
icn_82_β:
    goto icn_125_β
icn_collate_s3_sdrain:
    pop
    goto icn_79_α
icn_130_α:
    getstatic rung36_jcon_collate/icn_init_collate I
    ifne icn_130_init_skip
    iconst_1
    putstatic rung36_jcon_collate/icn_init_collate I
;  STR
icn_133_α:
    ldc "abxy"
    goto icn_132_store
icn_133_β:
    goto icn_131_seq_rf_0
icn_132_α:
    goto icn_133_α
icn_132_β:
    goto icn_133_β
icn_132_store:
    putstatic rung36_jcon_collate/icn_pv_collate_llabels Ljava/lang/String;
    getstatic rung36_jcon_collate/icn_pv_collate_llabels Ljava/lang/String;
    goto icn_131_seq_rg_0
;  STR
icn_135_α:
    ldc "cduv"
    goto icn_134_store
icn_135_β:
    goto icn_131_seq_rf_1
icn_134_α:
    goto icn_135_α
icn_134_β:
    goto icn_135_β
icn_134_store:
    putstatic rung36_jcon_collate/icn_pv_collate_rlabels Ljava/lang/String;
    getstatic rung36_jcon_collate/icn_pv_collate_rlabels Ljava/lang/String;
    goto icn_131_seq_rg_1
;  VAR
icn_138_α:
    getstatic rung36_jcon_collate/icn_pv_collate_rlabels Ljava/lang/String;
    goto icn_137_rrelay
icn_138_β:
    goto icn_137_lb
;  VAR
icn_139_α:
    getstatic rung36_jcon_collate/icn_pv_collate_llabels Ljava/lang/String;
    goto icn_137_lrelay
icn_139_β:
    goto icn_131_seq_rf_2
icn_137_lrelay:
    putstatic rung36_jcon_collate/icn_137_lc Ljava/lang/String;
    goto icn_137_lstore
icn_137_rrelay:
    putstatic rung36_jcon_collate/icn_137_rc Ljava/lang/String;
    goto icn_137_compute
icn_137_lb:
    goto icn_139_β
icn_137_α:
    iconst_0
    istore 109
    goto icn_139_α
icn_137_β:
    iconst_1
    istore 109
    goto icn_139_α
icn_137_lstore:
    iload 109
    ifeq icn_138_α
    goto icn_138_β
icn_137_compute:
    getstatic rung36_jcon_collate/icn_137_lc Ljava/lang/String;
    getstatic rung36_jcon_collate/icn_137_rc Ljava/lang/String;
    invokevirtual java/lang/String/concat(Ljava/lang/String;)Ljava/lang/String;
    goto icn_136_store
icn_136_α:
    goto icn_137_α
icn_136_β:
    goto icn_137_β
icn_136_store:
    putstatic rung36_jcon_collate/icn_pv_collate_blabels Ljava/lang/String;
    getstatic rung36_jcon_collate/icn_pv_collate_blabels Ljava/lang/String;
    goto icn_131_seq_rg_2
;  STR
icn_141_α:
    ldc "acbdxuyv"
    goto icn_140_store
icn_141_β:
    goto icn_131_seq_rf_3
icn_140_α:
    goto icn_141_α
icn_140_β:
    goto icn_141_β
icn_140_store:
    putstatic rung36_jcon_collate/icn_pv_collate_clabels Ljava/lang/String;
    getstatic rung36_jcon_collate/icn_pv_collate_clabels Ljava/lang/String;
    goto icn_131_seq_rg_3
;  INT
icn_143_α:
    ldc2_w 4
    goto icn_142_store
icn_143_β:
    goto icn_131_seq_rf_4
icn_142_α:
    goto icn_143_α
icn_142_β:
    goto icn_143_β
icn_142_store:
    putstatic rung36_jcon_collate/icn_pv_collate_half J
    getstatic rung36_jcon_collate/icn_pv_collate_half J
    goto icn_131_seq_rg_4
;  VAR
icn_146_α:
    ldc "\u0000\u0001\u0002\u0003\u0004\u0005\u0006\u0007\u0008\u0009\u000a\u000b\u000c\u000d\u000e\u000f\u0010\u0011\u0012\u0013\u0014\u0015\u0016\u0017\u0018\u0019\u001a\u001b\u001c\u001d\u001e\u001f !\"#$%&'()*+,-./0123456789:;<=>?@ABCDEFGHIJKLMNOPQRSTUVWXYZ[\\]^_`abcdefghijklmnopqrstuvwxyz{|}~\u007f"
    goto icn_145_left_mid
icn_146_β:
    goto icn_131_seq_rf_5
;  INT
icn_148_α:
    ldc2_w 2
    goto icn_147_rrelay
icn_148_β:
    goto icn_147_lb
;  VAR
icn_150_α:
    ldc "\u0000\u0001\u0002\u0003\u0004\u0005\u0006\u0007\u0008\u0009\u000a\u000b\u000c\u000d\u000e\u000f\u0010\u0011\u0012\u0013\u0014\u0015\u0016\u0017\u0018\u0019\u001a\u001b\u001c\u001d\u001e\u001f !\"#$%&'()*+,-./0123456789:;<=>?@ABCDEFGHIJKLMNOPQRSTUVWXYZ[\\]^_`abcdefghijklmnopqrstuvwxyz{|}~\u007f"
    goto icn_149_relay
icn_150_β:
    goto icn_131_seq_rf_5
icn_149_α:
    goto icn_150_α
icn_149_β:
    goto icn_150_β
icn_149_relay:
    invokevirtual java/lang/String/length()I
    i2l
    goto icn_147_lrelay
icn_147_lrelay:
    putstatic rung36_jcon_collate/icn_147_binop_lc J
    goto icn_147_lstore
icn_147_rrelay:
    putstatic rung36_jcon_collate/icn_147_binop_rc J
    goto icn_147_compute
icn_147_lb:
    goto icn_149_β
icn_147_α:
    iconst_0
    putstatic rung36_jcon_collate/icn_147_binop_bf I
    goto icn_149_α
icn_147_β:
    goto icn_148_β
icn_147_lstore:
    getstatic rung36_jcon_collate/icn_147_binop_bf I
    ifeq icn_148_α
    goto icn_148_β
icn_147_compute:
    getstatic rung36_jcon_collate/icn_147_binop_lc J
    getstatic rung36_jcon_collate/icn_147_binop_rc J
    ldiv
    goto icn_145_left_after
icn_145_α:
    goto icn_146_α
icn_145_β:
    goto icn_146_β
icn_145_left_mid:
    invokestatic java/lang/Long/toString(J)Ljava/lang/String;
    putstatic rung36_jcon_collate/icn_145_left_s Ljava/lang/String;
    goto icn_147_α
icn_145_left_after:
    l2i
    istore 110
    getstatic rung36_jcon_collate/icn_145_left_s Ljava/lang/String;
    iload 110
    ldc " "
    invokestatic rung36_jcon_collate/icn_builtin_left(Ljava/lang/String;ILjava/lang/String;)Ljava/lang/String;
    goto icn_144_store
icn_144_α:
    goto icn_145_α
icn_144_β:
    goto icn_145_β
icn_144_store:
    putstatic rung36_jcon_collate/icn_pv_collate_ltemp Ljava/lang/String;
    getstatic rung36_jcon_collate/icn_pv_collate_ltemp Ljava/lang/String;
    goto icn_131_seq_rg_5
;  VAR
icn_153_α:
    ldc "\u0000\u0001\u0002\u0003\u0004\u0005\u0006\u0007\u0008\u0009\u000a\u000b\u000c\u000d\u000e\u000f\u0010\u0011\u0012\u0013\u0014\u0015\u0016\u0017\u0018\u0019\u001a\u001b\u001c\u001d\u001e\u001f !\"#$%&'()*+,-./0123456789:;<=>?@ABCDEFGHIJKLMNOPQRSTUVWXYZ[\\]^_`abcdefghijklmnopqrstuvwxyz{|}~\u007f"
    goto icn_152_right_mid
icn_153_β:
    goto icn_131_seq_rf_6
;  INT
icn_155_α:
    ldc2_w 2
    goto icn_154_rrelay
icn_155_β:
    goto icn_154_lb
;  VAR
icn_157_α:
    ldc "\u0000\u0001\u0002\u0003\u0004\u0005\u0006\u0007\u0008\u0009\u000a\u000b\u000c\u000d\u000e\u000f\u0010\u0011\u0012\u0013\u0014\u0015\u0016\u0017\u0018\u0019\u001a\u001b\u001c\u001d\u001e\u001f !\"#$%&'()*+,-./0123456789:;<=>?@ABCDEFGHIJKLMNOPQRSTUVWXYZ[\\]^_`abcdefghijklmnopqrstuvwxyz{|}~\u007f"
    goto icn_156_relay
icn_157_β:
    goto icn_131_seq_rf_6
icn_156_α:
    goto icn_157_α
icn_156_β:
    goto icn_157_β
icn_156_relay:
    invokevirtual java/lang/String/length()I
    i2l
    goto icn_154_lrelay
icn_154_lrelay:
    putstatic rung36_jcon_collate/icn_154_binop_lc J
    goto icn_154_lstore
icn_154_rrelay:
    putstatic rung36_jcon_collate/icn_154_binop_rc J
    goto icn_154_compute
icn_154_lb:
    goto icn_156_β
icn_154_α:
    iconst_0
    putstatic rung36_jcon_collate/icn_154_binop_bf I
    goto icn_156_α
icn_154_β:
    goto icn_155_β
icn_154_lstore:
    getstatic rung36_jcon_collate/icn_154_binop_bf I
    ifeq icn_155_α
    goto icn_155_β
icn_154_compute:
    getstatic rung36_jcon_collate/icn_154_binop_lc J
    getstatic rung36_jcon_collate/icn_154_binop_rc J
    ldiv
    goto icn_152_right_after
icn_152_α:
    goto icn_153_α
icn_152_β:
    goto icn_153_β
icn_152_right_mid:
    invokestatic java/lang/Long/toString(J)Ljava/lang/String;
    putstatic rung36_jcon_collate/icn_152_right_s Ljava/lang/String;
    goto icn_154_α
icn_152_right_after:
    l2i
    istore 111
    getstatic rung36_jcon_collate/icn_152_right_s Ljava/lang/String;
    iload 111
    ldc " "
    invokestatic rung36_jcon_collate/icn_builtin_right(Ljava/lang/String;ILjava/lang/String;)Ljava/lang/String;
    goto icn_151_store
icn_151_α:
    goto icn_152_α
icn_151_β:
    goto icn_152_β
icn_151_store:
    putstatic rung36_jcon_collate/icn_pv_collate_rtemp Ljava/lang/String;
    getstatic rung36_jcon_collate/icn_pv_collate_rtemp Ljava/lang/String;
    goto icn_131_seq_rg_6
;  VAR
icn_160_α:
    getstatic rung36_jcon_collate/icn_pv_collate_rtemp Ljava/lang/String;
    goto icn_159_arg1
icn_160_β:
    goto icn_131_seq_rf_7
icn_159_arg1:
    putstatic rung36_jcon_collate/icn_arg_str_1 Ljava/lang/String;
    lconst_0
    putstatic rung36_jcon_collate/icn_arg_1 J
    goto icn_159_docall
;  VAR
icn_161_α:
    getstatic rung36_jcon_collate/icn_pv_collate_ltemp Ljava/lang/String;
    goto icn_159_arg0
icn_161_β:
    goto icn_131_seq_rf_7
icn_159_arg0:
    putstatic rung36_jcon_collate/icn_arg_str_0 Ljava/lang/String;
    lconst_0
    putstatic rung36_jcon_collate/icn_arg_0 J
    goto icn_160_α
icn_159_α:
    goto icn_161_α
icn_159_β:
    goto icn_160_β
icn_159_docall:
    getstatic rung36_jcon_collate/icn_38_binop_lc J
    lstore 158
    getstatic rung36_jcon_collate/icn_38_binop_rc J
    lstore 160
    getstatic rung36_jcon_collate/icn_pv_collate_length J
    lstore 162
    getstatic rung36_jcon_collate/icn_58_binop_lc J
    lstore 164
    getstatic rung36_jcon_collate/icn_58_binop_rc J
    lstore 166
    getstatic rung36_jcon_collate/icn_pv_collate_half J
    lstore 168
    getstatic rung36_jcon_collate/icn_63_binop_lc J
    lstore 170
    getstatic rung36_jcon_collate/icn_63_binop_rc J
    lstore 172
    getstatic rung36_jcon_collate/icn_76_relop_lc J
    lstore 174
    getstatic rung36_jcon_collate/icn_76_relop_rc J
    lstore 176
    getstatic rung36_jcon_collate/icn_87_binop_lc J
    lstore 178
    getstatic rung36_jcon_collate/icn_87_binop_rc J
    lstore 180
    getstatic rung36_jcon_collate/icn_96_binop_lc J
    lstore 182
    getstatic rung36_jcon_collate/icn_96_binop_rc J
    lstore 184
    getstatic rung36_jcon_collate/icn_105_binop_lc J
    lstore 186
    getstatic rung36_jcon_collate/icn_105_binop_rc J
    lstore 188
    getstatic rung36_jcon_collate/icn_114_binop_lc J
    lstore 190
    getstatic rung36_jcon_collate/icn_114_binop_rc J
    lstore 192
    getstatic rung36_jcon_collate/icn_120_relop_lc J
    lstore 194
    getstatic rung36_jcon_collate/icn_120_relop_rc J
    lstore 196
    getstatic rung36_jcon_collate/icn_125_relop_lc J
    lstore 198
    getstatic rung36_jcon_collate/icn_125_relop_rc J
    lstore 200
    getstatic rung36_jcon_collate/icn_147_binop_lc J
    lstore 202
    getstatic rung36_jcon_collate/icn_147_binop_rc J
    lstore 204
    getstatic rung36_jcon_collate/icn_154_binop_lc J
    lstore 206
    getstatic rung36_jcon_collate/icn_154_binop_rc J
    lstore 208
    invokestatic rung36_jcon_collate/icn_collate()V
    lload 158
    putstatic rung36_jcon_collate/icn_38_binop_lc J
    lload 160
    putstatic rung36_jcon_collate/icn_38_binop_rc J
    lload 162
    putstatic rung36_jcon_collate/icn_pv_collate_length J
    lload 164
    putstatic rung36_jcon_collate/icn_58_binop_lc J
    lload 166
    putstatic rung36_jcon_collate/icn_58_binop_rc J
    lload 168
    putstatic rung36_jcon_collate/icn_pv_collate_half J
    lload 170
    putstatic rung36_jcon_collate/icn_63_binop_lc J
    lload 172
    putstatic rung36_jcon_collate/icn_63_binop_rc J
    lload 174
    putstatic rung36_jcon_collate/icn_76_relop_lc J
    lload 176
    putstatic rung36_jcon_collate/icn_76_relop_rc J
    lload 178
    putstatic rung36_jcon_collate/icn_87_binop_lc J
    lload 180
    putstatic rung36_jcon_collate/icn_87_binop_rc J
    lload 182
    putstatic rung36_jcon_collate/icn_96_binop_lc J
    lload 184
    putstatic rung36_jcon_collate/icn_96_binop_rc J
    lload 186
    putstatic rung36_jcon_collate/icn_105_binop_lc J
    lload 188
    putstatic rung36_jcon_collate/icn_105_binop_rc J
    lload 190
    putstatic rung36_jcon_collate/icn_114_binop_lc J
    lload 192
    putstatic rung36_jcon_collate/icn_114_binop_rc J
    lload 194
    putstatic rung36_jcon_collate/icn_120_relop_lc J
    lload 196
    putstatic rung36_jcon_collate/icn_120_relop_rc J
    lload 198
    putstatic rung36_jcon_collate/icn_125_relop_lc J
    lload 200
    putstatic rung36_jcon_collate/icn_125_relop_rc J
    lload 202
    putstatic rung36_jcon_collate/icn_147_binop_lc J
    lload 204
    putstatic rung36_jcon_collate/icn_147_binop_rc J
    lload 206
    putstatic rung36_jcon_collate/icn_154_binop_lc J
    lload 208
    putstatic rung36_jcon_collate/icn_154_binop_rc J
    getstatic rung36_jcon_collate/icn_failed B
    ifne icn_159_after_call
    getstatic rung36_jcon_collate/icn_retval J
    goto icn_158_store
icn_159_after_call:
    goto icn_131_seq_rf_7
icn_158_α:
    goto icn_159_α
icn_158_β:
    goto icn_159_β
icn_158_store:
    putstatic rung36_jcon_collate/icn_pv_collate_clabels J
    getstatic rung36_jcon_collate/icn_pv_collate_clabels J
    goto icn_131_seq_rg_7
;  VAR
icn_163_α:
    getstatic rung36_jcon_collate/icn_pv_collate_ltemp Ljava/lang/String;
    goto icn_162_store
icn_163_β:
    goto icn_131_seq_rf_8
icn_162_α:
    goto icn_163_α
icn_162_β:
    goto icn_163_β
icn_162_store:
    putstatic rung36_jcon_collate/icn_pv_collate_llabels Ljava/lang/String;
    getstatic rung36_jcon_collate/icn_pv_collate_llabels Ljava/lang/String;
    goto icn_131_seq_rg_8
;  VAR
icn_165_α:
    getstatic rung36_jcon_collate/icn_pv_collate_rtemp Ljava/lang/String;
    goto icn_164_store
icn_165_β:
    goto icn_131_seq_rf_9
icn_164_α:
    goto icn_165_α
icn_164_β:
    goto icn_165_β
icn_164_store:
    putstatic rung36_jcon_collate/icn_pv_collate_rlabels Ljava/lang/String;
    getstatic rung36_jcon_collate/icn_pv_collate_rlabels Ljava/lang/String;
    goto icn_131_seq_rg_9
;  VAR
icn_168_α:
    ldc "\u0000\u0001\u0002\u0003\u0004\u0005\u0006\u0007\u0008\u0009\u000a\u000b\u000c\u000d\u000e\u000f\u0010\u0011\u0012\u0013\u0014\u0015\u0016\u0017\u0018\u0019\u001a\u001b\u001c\u001d\u001e\u001f !\"#$%&'()*+,-./0123456789:;<=>?@ABCDEFGHIJKLMNOPQRSTUVWXYZ[\\]^_`abcdefghijklmnopqrstuvwxyz{|}~\u007f"
    goto icn_167_str_after
icn_168_β:
    goto icn_131_seq_rf_10
icn_167_α:
    goto icn_168_α
icn_167_β:
    goto icn_168_β
icn_167_str_after:
    invokestatic java/lang/Long/toString(J)Ljava/lang/String;
    goto icn_166_store
icn_166_α:
    goto icn_167_α
icn_166_β:
    goto icn_167_β
icn_166_store:
    putstatic rung36_jcon_collate/icn_pv_collate_blabels Ljava/lang/String;
    getstatic rung36_jcon_collate/icn_pv_collate_blabels Ljava/lang/String;
    goto icn_131_seq_rg_10
;  VAR
icn_171_α:
    getstatic rung36_jcon_collate/icn_pv_collate_llabels Ljava/lang/String;
    goto icn_170_relay
icn_171_β:
    goto icn_130_init_run
icn_170_α:
    goto icn_171_α
icn_170_β:
    goto icn_171_β
icn_170_relay:
    invokevirtual java/lang/String/length()I
    i2l
    goto icn_169_store
icn_169_α:
    goto icn_170_α
icn_169_β:
    goto icn_170_β
icn_169_store:
    putstatic rung36_jcon_collate/icn_pv_collate_half J
    getstatic rung36_jcon_collate/icn_pv_collate_half J
    goto icn_130_init_drain
    goto icn_131_α
icn_131_seq_rg_0:
    pop
    goto icn_134_α
icn_131_seq_rg_1:
    pop
    goto icn_136_α
icn_131_seq_rg_2:
    pop
    goto icn_140_α
icn_131_seq_rg_3:
    pop
    goto icn_142_α
icn_131_seq_rg_4:
    pop2
    goto icn_144_α
icn_131_seq_rg_5:
    pop
    goto icn_151_α
icn_131_seq_rg_6:
    pop
    goto icn_158_α
icn_131_seq_rg_7:
    pop2
    goto icn_162_α
icn_131_seq_rg_8:
    pop
    goto icn_164_α
icn_131_seq_rg_9:
    pop
    goto icn_166_α
icn_131_seq_rg_10:
    pop
    goto icn_169_α
icn_131_seq_rf_0:
    goto icn_134_α
icn_131_seq_rf_1:
    goto icn_136_α
icn_131_seq_rf_2:
    goto icn_140_α
icn_131_seq_rf_3:
    goto icn_142_α
icn_131_seq_rf_4:
    goto icn_144_α
icn_131_seq_rf_5:
    goto icn_151_α
icn_131_seq_rf_6:
    goto icn_158_α
icn_131_seq_rf_7:
    goto icn_162_α
icn_131_seq_rf_8:
    goto icn_164_α
icn_131_seq_rf_9:
    goto icn_166_α
icn_131_seq_rf_10:
    goto icn_169_α
icn_131_α:
    goto icn_132_α
icn_131_β:
    goto icn_169_β
    goto icn_131_α
icn_130_init_drain:
    pop2
icn_130_init_run:
    lconst_0
    goto icn_collate_s2_sdrain
icn_130_init_skip:
    lconst_0
    goto icn_collate_s2_sdrain
icn_130_β:
    goto icn_82_α
icn_collate_s2_sdrain:
    pop2
    goto icn_82_α
icn_collate_done:
    iconst_0
    putstatic rung36_jcon_collate/icn_suspended B
    iconst_0
    putstatic rung36_jcon_collate/icn_suspend_id I
    iconst_1
    putstatic rung36_jcon_collate/icn_failed B
    return
icn_collate_ret:
    iconst_0
    putstatic rung36_jcon_collate/icn_failed B
    return
icn_collate_sret:
    return
.end method

.method public static icn_decollate()V
    .limit stack 16
    .limit locals 506
    lconst_0
    lstore 0
    lconst_0
    lstore 2
    lconst_0
    lstore 4
    lconst_0
    lstore 6
    lconst_0
    lstore 8
    lconst_0
    lstore 10
    lconst_0
    lstore 12
    lconst_0
    lstore 14
    lconst_0
    lstore 16
    lconst_0
    lstore 18
    lconst_0
    lstore 20
    lconst_0
    lstore 22
    lconst_0
    lstore 24
    lconst_0
    lstore 26
    lconst_0
    lstore 28
    lconst_0
    lstore 30
    lconst_0
    lstore 32
    lconst_0
    lstore 34
    lconst_0
    lstore 36
    lconst_0
    lstore 38
    lconst_0
    lstore 40
    lconst_0
    lstore 42
    lconst_0
    lstore 44
    lconst_0
    lstore 46
    lconst_0
    lstore 48
    lconst_0
    lstore 50
    lconst_0
    lstore 52
    lconst_0
    lstore 54
    lconst_0
    lstore 56
    lconst_0
    lstore 58
    lconst_0
    lstore 60
    lconst_0
    lstore 62
    iconst_0
    istore 84
    iconst_0
    istore 85
    iconst_0
    istore 86
    iconst_0
    istore 87
    iconst_0
    istore 88
    iconst_0
    istore 89
    iconst_0
    istore 90
    iconst_0
    istore 91
    iconst_0
    istore 92
    iconst_0
    istore 93
    iconst_0
    istore 94
    iconst_0
    istore 95
    iconst_0
    istore 96
    iconst_0
    istore 97
    iconst_0
    istore 98
    iconst_0
    istore 99
    iconst_0
    istore 100
    iconst_0
    istore 101
    iconst_0
    istore 102
    iconst_0
    istore 103
    iconst_0
    istore 104
    iconst_0
    istore 105
    iconst_0
    istore 106
    iconst_0
    istore 107
    iconst_0
    istore 108
    iconst_0
    istore 109
    iconst_0
    istore 110
    iconst_0
    istore 111
    aconst_null
    astore 148
    aconst_null
    astore 149
    aconst_null
    astore 150
    aconst_null
    astore 151
    aconst_null
    astore 152
    aconst_null
    astore 153
    aconst_null
    astore 154
    aconst_null
    astore 155
    aconst_null
    astore 156
    aconst_null
    astore 157
    aconst_null
    astore 158
    aconst_null
    astore 159
    getstatic rung36_jcon_collate/icn_arg_str_0 Ljava/lang/String;
    putstatic rung36_jcon_collate/icn_pv_decollate_s Ljava/lang/String;
    getstatic rung36_jcon_collate/icn_arg_str_1 Ljava/lang/String;
    putstatic rung36_jcon_collate/icn_pv_decollate_n Ljava/lang/String;
    goto icn_233_α
;  VAR
icn_176_α:
    getstatic rung36_jcon_collate/icn_pv_decollate_object Ljava/lang/String;
    goto icn_175_sec_sr
icn_176_β:
    goto icn_173_ret_fail
;  INT
icn_177_α:
    ldc2_w 1
    goto icn_175_sec_lor
icn_177_β:
    goto icn_173_ret_fail
;  INT
icn_179_α:
    ldc2_w 2
    goto icn_178_rrelay
icn_179_β:
    goto icn_178_lb
;  VAR
icn_181_α:
    getstatic rung36_jcon_collate/icn_pv_decollate_n J
    goto icn_180_rrelay
icn_181_β:
    goto icn_180_lb
;  VAR
icn_182_α:
    getstatic rung36_jcon_collate/icn_pv_decollate_ssize J
    goto icn_180_lrelay
icn_182_β:
    goto icn_173_ret_fail
icn_180_lrelay:
    putstatic rung36_jcon_collate/icn_180_binop_lc J
    goto icn_180_lstore
icn_180_rrelay:
    putstatic rung36_jcon_collate/icn_180_binop_rc J
    goto icn_180_compute
icn_180_lb:
    goto icn_182_β
icn_180_α:
    iconst_0
    putstatic rung36_jcon_collate/icn_180_binop_bf I
    goto icn_182_α
icn_180_β:
    iconst_1
    putstatic rung36_jcon_collate/icn_180_binop_bf I
    goto icn_182_α
icn_180_lstore:
    getstatic rung36_jcon_collate/icn_180_binop_bf I
    ifeq icn_181_α
    goto icn_181_β
icn_180_compute:
    getstatic rung36_jcon_collate/icn_180_binop_lc J
    getstatic rung36_jcon_collate/icn_180_binop_rc J
    ladd
    goto icn_178_lrelay
icn_178_lrelay:
    putstatic rung36_jcon_collate/icn_178_binop_lc J
    goto icn_178_lstore
icn_178_rrelay:
    putstatic rung36_jcon_collate/icn_178_binop_rc J
    goto icn_178_compute
icn_178_lb:
    goto icn_180_β
icn_178_α:
    iconst_0
    putstatic rung36_jcon_collate/icn_178_binop_bf I
    goto icn_180_α
icn_178_β:
    goto icn_179_β
icn_178_lstore:
    getstatic rung36_jcon_collate/icn_178_binop_bf I
    ifeq icn_179_α
    goto icn_179_β
icn_178_compute:
    getstatic rung36_jcon_collate/icn_178_binop_lc J
    getstatic rung36_jcon_collate/icn_178_binop_rc J
    ldiv
    goto icn_175_sec_hir
icn_175_sec_lor:
    l2i
    istore 84
    iload 84
    ifgt icn_175_sec_lop
    iload 84
    iflt icn_175_sec_lon
icn_175_sec_loz:
    goto icn_173_ret_fail
icn_175_sec_lop:
    iload 84
    iconst_1
    isub
    putstatic rung36_jcon_collate/icn_175_sec_lo I
    goto icn_178_α
icn_175_sec_lon:
    getstatic rung36_jcon_collate/icn_175_sec_s Ljava/lang/String;
    invokevirtual java/lang/String/length()I
    iload 84
    iadd
    putstatic rung36_jcon_collate/icn_175_sec_lo I
    goto icn_178_α
icn_175_sec_hir:
    l2i
    istore 85
    iload 85
    ifgt icn_175_sec_hip
    iload 85
    iflt icn_175_sec_hin
icn_175_sec_hiz:
    goto icn_173_ret_fail
icn_175_sec_hip:
    iload 85
    iconst_1
    isub
    putstatic rung36_jcon_collate/icn_175_sec_hi I
    goto icn_175_sec_cmp
icn_175_sec_hin:
    getstatic rung36_jcon_collate/icn_175_sec_s Ljava/lang/String;
    invokevirtual java/lang/String/length()I
    iload 85
    iadd
    putstatic rung36_jcon_collate/icn_175_sec_hi I
    goto icn_175_sec_cmp
icn_175_sec_cmp:
    getstatic rung36_jcon_collate/icn_175_sec_lo I
    iflt icn_173_ret_fail
    getstatic rung36_jcon_collate/icn_175_sec_hi I
    iflt icn_173_ret_fail
    getstatic rung36_jcon_collate/icn_175_sec_s Ljava/lang/String;
    invokevirtual java/lang/String/length()I
    getstatic rung36_jcon_collate/icn_175_sec_lo I
    if_icmplt icn_173_ret_fail
    getstatic rung36_jcon_collate/icn_175_sec_s Ljava/lang/String;
    invokevirtual java/lang/String/length()I
    istore 86
    getstatic rung36_jcon_collate/icn_175_sec_hi I
    iload 86
    if_icmple icn_175_sec_hiok
    iload 86
    putstatic rung36_jcon_collate/icn_175_sec_hi I
icn_175_sec_hiok:
    getstatic rung36_jcon_collate/icn_175_sec_s Ljava/lang/String;
    getstatic rung36_jcon_collate/icn_175_sec_lo I
    getstatic rung36_jcon_collate/icn_175_sec_hi I
    invokevirtual java/lang/String/substring(II)Ljava/lang/String;
    goto icn_174_map_mid1
icn_175_α:
    goto icn_176_α
icn_175_sec_sr:
    putstatic rung36_jcon_collate/icn_175_sec_s Ljava/lang/String;
    goto icn_177_α
icn_175_β:
    goto icn_173_ret_fail
;  VAR
icn_184_α:
    getstatic rung36_jcon_collate/icn_pv_decollate_image J
    goto icn_183_sec_sr
icn_184_β:
    goto icn_173_ret_fail
;  INT
icn_186_α:
    ldc2_w 1
    goto icn_185_rrelay
icn_186_β:
    goto icn_185_lb
;  VAR
icn_187_α:
    getstatic rung36_jcon_collate/icn_pv_decollate_n J
    goto icn_185_lrelay
icn_187_β:
    goto icn_173_ret_fail
icn_185_lrelay:
    putstatic rung36_jcon_collate/icn_185_binop_lc J
    goto icn_185_lstore
icn_185_rrelay:
    putstatic rung36_jcon_collate/icn_185_binop_rc J
    goto icn_185_compute
icn_185_lb:
    goto icn_187_β
icn_185_α:
    iconst_0
    putstatic rung36_jcon_collate/icn_185_binop_bf I
    goto icn_187_α
icn_185_β:
    iconst_1
    putstatic rung36_jcon_collate/icn_185_binop_bf I
    goto icn_187_α
icn_185_lstore:
    getstatic rung36_jcon_collate/icn_185_binop_bf I
    ifeq icn_186_α
    goto icn_186_β
icn_185_compute:
    getstatic rung36_jcon_collate/icn_185_binop_lc J
    getstatic rung36_jcon_collate/icn_185_binop_rc J
    ladd
    goto icn_183_sec_lor
;  VAR
icn_188_α:
    getstatic rung36_jcon_collate/icn_pv_decollate_ssize J
    goto icn_183_sec_hir
icn_188_β:
    goto icn_173_ret_fail
icn_183_sec_lor:
    l2i
    istore 87
    iload 87
    ifgt icn_183_sec_lop
    iload 87
    iflt icn_183_sec_lon
icn_183_sec_loz:
    goto icn_173_ret_fail
icn_183_sec_lop:
    iload 87
    iconst_1
    isub
    putstatic rung36_jcon_collate/icn_183_sec_lo I
    goto icn_188_α
icn_183_sec_lon:
    getstatic rung36_jcon_collate/icn_183_sec_s Ljava/lang/String;
    invokevirtual java/lang/String/length()I
    iload 87
    iadd
    putstatic rung36_jcon_collate/icn_183_sec_lo I
    goto icn_188_α
icn_183_sec_hir:
    l2i
    istore 88
    iload 88
    ifgt icn_183_sec_hip
    iload 88
    iflt icn_183_sec_hin
icn_183_sec_hiz:
    goto icn_173_ret_fail
icn_183_sec_hip:
    iload 88
    iconst_1
    isub
    putstatic rung36_jcon_collate/icn_183_sec_hi I
    goto icn_183_sec_cmp
icn_183_sec_hin:
    getstatic rung36_jcon_collate/icn_183_sec_s Ljava/lang/String;
    invokevirtual java/lang/String/length()I
    iload 88
    iadd
    putstatic rung36_jcon_collate/icn_183_sec_hi I
    goto icn_183_sec_cmp
icn_183_sec_cmp:
    getstatic rung36_jcon_collate/icn_183_sec_lo I
    iflt icn_173_ret_fail
    getstatic rung36_jcon_collate/icn_183_sec_hi I
    iflt icn_173_ret_fail
    getstatic rung36_jcon_collate/icn_183_sec_s Ljava/lang/String;
    invokevirtual java/lang/String/length()I
    getstatic rung36_jcon_collate/icn_183_sec_lo I
    if_icmplt icn_173_ret_fail
    getstatic rung36_jcon_collate/icn_183_sec_s Ljava/lang/String;
    invokevirtual java/lang/String/length()I
    istore 89
    getstatic rung36_jcon_collate/icn_183_sec_hi I
    iload 89
    if_icmple icn_183_sec_hiok
    iload 89
    putstatic rung36_jcon_collate/icn_183_sec_hi I
icn_183_sec_hiok:
    getstatic rung36_jcon_collate/icn_183_sec_s Ljava/lang/String;
    getstatic rung36_jcon_collate/icn_183_sec_lo I
    getstatic rung36_jcon_collate/icn_183_sec_hi I
    invokevirtual java/lang/String/substring(II)Ljava/lang/String;
    goto icn_174_map_mid2
icn_183_α:
    goto icn_184_α
icn_183_sec_sr:
    putstatic rung36_jcon_collate/icn_183_sec_s Ljava/lang/String;
    goto icn_185_α
icn_183_β:
    goto icn_173_ret_fail
;  VAR
icn_189_α:
    getstatic rung36_jcon_collate/icn_pv_decollate_s Ljava/lang/String;
    goto icn_174_map_after
icn_189_β:
    goto icn_173_ret_fail
icn_174_α:
    goto icn_175_α
icn_174_β:
    goto icn_175_β
icn_174_map_mid1:
    astore 148
    goto icn_183_α
icn_174_map_mid2:
    astore 149
    goto icn_189_α
icn_174_map_after:
    astore 150
    aload 148
    aload 149
    aload 150
    invokestatic rung36_jcon_collate/icn_builtin_map(Ljava/lang/String;Ljava/lang/String;Ljava/lang/String;)Ljava/lang/String;
    goto icn_173_ret_store
icn_173_α:
    goto icn_174_α
icn_173_β:
    goto icn_decollate_ret
icn_173_ret_fail:
    iconst_1
    putstatic rung36_jcon_collate/icn_failed B
    goto icn_decollate_done
icn_173_ret_store:
    putstatic rung36_jcon_collate/icn_retval_str Ljava/lang/String;
    lconst_0
    putstatic rung36_jcon_collate/icn_retval J
    iconst_0
    putstatic rung36_jcon_collate/icn_failed B
    goto icn_decollate_ret
;  VAR
icn_193_α:
    getstatic rung36_jcon_collate/icn_pv_decollate_n J
    goto icn_192_arg1
icn_193_β:
    goto icn_191_lb
icn_192_arg1:
    putstatic rung36_jcon_collate/icn_arg_1 J
    goto icn_192_docall
;  VAR
icn_195_α:
    getstatic rung36_jcon_collate/icn_pv_decollate_s Ljava/lang/String;
    goto icn_194_sec_sr
icn_195_β:
    goto icn_191_lb
;  INT
icn_197_α:
    ldc2_w 1
    goto icn_196_rrelay
icn_197_β:
    goto icn_196_lb
;  VAR
icn_198_α:
    getstatic rung36_jcon_collate/icn_pv_decollate_dsize J
    goto icn_196_lrelay
icn_198_β:
    goto icn_191_lb
icn_196_lrelay:
    putstatic rung36_jcon_collate/icn_196_binop_lc J
    goto icn_196_lstore
icn_196_rrelay:
    putstatic rung36_jcon_collate/icn_196_binop_rc J
    goto icn_196_compute
icn_196_lb:
    goto icn_198_β
icn_196_α:
    iconst_0
    putstatic rung36_jcon_collate/icn_196_binop_bf I
    goto icn_198_α
icn_196_β:
    iconst_1
    putstatic rung36_jcon_collate/icn_196_binop_bf I
    goto icn_198_α
icn_196_lstore:
    getstatic rung36_jcon_collate/icn_196_binop_bf I
    ifeq icn_197_α
    goto icn_197_β
icn_196_compute:
    getstatic rung36_jcon_collate/icn_196_binop_lc J
    getstatic rung36_jcon_collate/icn_196_binop_rc J
    lsub
    goto icn_194_sec_lor
;  INT
icn_199_α:
    ldc2_w 0
    goto icn_194_sec_hir
icn_199_β:
    goto icn_191_lb
icn_194_sec_lor:
    l2i
    istore 91
    iload 91
    ifgt icn_194_sec_lop
    iload 91
    iflt icn_194_sec_lon
icn_194_sec_loz:
    goto icn_191_lb
icn_194_sec_lop:
    iload 91
    iconst_1
    isub
    putstatic rung36_jcon_collate/icn_194_sec_lo I
    goto icn_199_α
icn_194_sec_lon:
    getstatic rung36_jcon_collate/icn_194_sec_s Ljava/lang/String;
    invokevirtual java/lang/String/length()I
    iload 91
    iadd
    putstatic rung36_jcon_collate/icn_194_sec_lo I
    goto icn_199_α
icn_194_sec_hir:
    l2i
    istore 92
    iload 92
    ifgt icn_194_sec_hip
    iload 92
    iflt icn_194_sec_hin
icn_194_sec_hiz:
    goto icn_191_lb
icn_194_sec_hip:
    iload 92
    iconst_1
    isub
    putstatic rung36_jcon_collate/icn_194_sec_hi I
    goto icn_194_sec_cmp
icn_194_sec_hin:
    getstatic rung36_jcon_collate/icn_194_sec_s Ljava/lang/String;
    invokevirtual java/lang/String/length()I
    iload 92
    iadd
    putstatic rung36_jcon_collate/icn_194_sec_hi I
    goto icn_194_sec_cmp
icn_194_sec_cmp:
    getstatic rung36_jcon_collate/icn_194_sec_lo I
    iflt icn_191_lb
    getstatic rung36_jcon_collate/icn_194_sec_hi I
    iflt icn_191_lb
    getstatic rung36_jcon_collate/icn_194_sec_s Ljava/lang/String;
    invokevirtual java/lang/String/length()I
    getstatic rung36_jcon_collate/icn_194_sec_lo I
    if_icmplt icn_191_lb
    getstatic rung36_jcon_collate/icn_194_sec_s Ljava/lang/String;
    invokevirtual java/lang/String/length()I
    istore 93
    getstatic rung36_jcon_collate/icn_194_sec_hi I
    iload 93
    if_icmple icn_194_sec_hiok
    iload 93
    putstatic rung36_jcon_collate/icn_194_sec_hi I
icn_194_sec_hiok:
    getstatic rung36_jcon_collate/icn_194_sec_s Ljava/lang/String;
    getstatic rung36_jcon_collate/icn_194_sec_lo I
    getstatic rung36_jcon_collate/icn_194_sec_hi I
    invokevirtual java/lang/String/substring(II)Ljava/lang/String;
    goto icn_192_arg0
icn_194_α:
    goto icn_195_α
icn_194_sec_sr:
    putstatic rung36_jcon_collate/icn_194_sec_s Ljava/lang/String;
    goto icn_196_α
icn_194_β:
    goto icn_191_lb
icn_192_arg0:
    putstatic rung36_jcon_collate/icn_arg_str_0 Ljava/lang/String;
    lconst_0
    putstatic rung36_jcon_collate/icn_arg_0 J
    goto icn_193_α
icn_192_α:
    goto icn_194_α
icn_192_β:
    goto icn_193_β
icn_192_docall:
    getstatic rung36_jcon_collate/icn_38_binop_lc J
    lstore 155
    getstatic rung36_jcon_collate/icn_38_binop_rc J
    lstore 157
    getstatic rung36_jcon_collate/icn_58_binop_lc J
    lstore 159
    getstatic rung36_jcon_collate/icn_58_binop_rc J
    lstore 161
    getstatic rung36_jcon_collate/icn_63_binop_lc J
    lstore 163
    getstatic rung36_jcon_collate/icn_63_binop_rc J
    lstore 165
    getstatic rung36_jcon_collate/icn_76_relop_lc J
    lstore 167
    getstatic rung36_jcon_collate/icn_76_relop_rc J
    lstore 169
    getstatic rung36_jcon_collate/icn_87_binop_lc J
    lstore 171
    getstatic rung36_jcon_collate/icn_87_binop_rc J
    lstore 173
    getstatic rung36_jcon_collate/icn_96_binop_lc J
    lstore 175
    getstatic rung36_jcon_collate/icn_96_binop_rc J
    lstore 177
    getstatic rung36_jcon_collate/icn_105_binop_lc J
    lstore 179
    getstatic rung36_jcon_collate/icn_105_binop_rc J
    lstore 181
    getstatic rung36_jcon_collate/icn_114_binop_lc J
    lstore 183
    getstatic rung36_jcon_collate/icn_114_binop_rc J
    lstore 185
    getstatic rung36_jcon_collate/icn_120_relop_lc J
    lstore 187
    getstatic rung36_jcon_collate/icn_120_relop_rc J
    lstore 189
    getstatic rung36_jcon_collate/icn_125_relop_lc J
    lstore 191
    getstatic rung36_jcon_collate/icn_125_relop_rc J
    lstore 193
    getstatic rung36_jcon_collate/icn_147_binop_lc J
    lstore 195
    getstatic rung36_jcon_collate/icn_147_binop_rc J
    lstore 197
    getstatic rung36_jcon_collate/icn_154_binop_lc J
    lstore 199
    getstatic rung36_jcon_collate/icn_154_binop_rc J
    lstore 201
    getstatic rung36_jcon_collate/icn_178_binop_lc J
    lstore 203
    getstatic rung36_jcon_collate/icn_178_binop_rc J
    lstore 205
    getstatic rung36_jcon_collate/icn_180_binop_lc J
    lstore 207
    getstatic rung36_jcon_collate/icn_180_binop_rc J
    lstore 209
    getstatic rung36_jcon_collate/icn_pv_decollate_n J
    lstore 211
    getstatic rung36_jcon_collate/icn_pv_decollate_ssize J
    lstore 213
    getstatic rung36_jcon_collate/icn_pv_decollate_image J
    lstore 215
    getstatic rung36_jcon_collate/icn_185_binop_lc J
    lstore 217
    getstatic rung36_jcon_collate/icn_185_binop_rc J
    lstore 219
    getstatic rung36_jcon_collate/icn_196_binop_lc J
    lstore 221
    getstatic rung36_jcon_collate/icn_196_binop_rc J
    lstore 223
    getstatic rung36_jcon_collate/icn_pv_decollate_dsize J
    lstore 225
    invokestatic rung36_jcon_collate/icn_decollate()V
    lload 155
    putstatic rung36_jcon_collate/icn_38_binop_lc J
    lload 157
    putstatic rung36_jcon_collate/icn_38_binop_rc J
    lload 159
    putstatic rung36_jcon_collate/icn_58_binop_lc J
    lload 161
    putstatic rung36_jcon_collate/icn_58_binop_rc J
    lload 163
    putstatic rung36_jcon_collate/icn_63_binop_lc J
    lload 165
    putstatic rung36_jcon_collate/icn_63_binop_rc J
    lload 167
    putstatic rung36_jcon_collate/icn_76_relop_lc J
    lload 169
    putstatic rung36_jcon_collate/icn_76_relop_rc J
    lload 171
    putstatic rung36_jcon_collate/icn_87_binop_lc J
    lload 173
    putstatic rung36_jcon_collate/icn_87_binop_rc J
    lload 175
    putstatic rung36_jcon_collate/icn_96_binop_lc J
    lload 177
    putstatic rung36_jcon_collate/icn_96_binop_rc J
    lload 179
    putstatic rung36_jcon_collate/icn_105_binop_lc J
    lload 181
    putstatic rung36_jcon_collate/icn_105_binop_rc J
    lload 183
    putstatic rung36_jcon_collate/icn_114_binop_lc J
    lload 185
    putstatic rung36_jcon_collate/icn_114_binop_rc J
    lload 187
    putstatic rung36_jcon_collate/icn_120_relop_lc J
    lload 189
    putstatic rung36_jcon_collate/icn_120_relop_rc J
    lload 191
    putstatic rung36_jcon_collate/icn_125_relop_lc J
    lload 193
    putstatic rung36_jcon_collate/icn_125_relop_rc J
    lload 195
    putstatic rung36_jcon_collate/icn_147_binop_lc J
    lload 197
    putstatic rung36_jcon_collate/icn_147_binop_rc J
    lload 199
    putstatic rung36_jcon_collate/icn_154_binop_lc J
    lload 201
    putstatic rung36_jcon_collate/icn_154_binop_rc J
    lload 203
    putstatic rung36_jcon_collate/icn_178_binop_lc J
    lload 205
    putstatic rung36_jcon_collate/icn_178_binop_rc J
    lload 207
    putstatic rung36_jcon_collate/icn_180_binop_lc J
    lload 209
    putstatic rung36_jcon_collate/icn_180_binop_rc J
    lload 211
    putstatic rung36_jcon_collate/icn_pv_decollate_n J
    lload 213
    putstatic rung36_jcon_collate/icn_pv_decollate_ssize J
    lload 215
    putstatic rung36_jcon_collate/icn_pv_decollate_image J
    lload 217
    putstatic rung36_jcon_collate/icn_185_binop_lc J
    lload 219
    putstatic rung36_jcon_collate/icn_185_binop_rc J
    lload 221
    putstatic rung36_jcon_collate/icn_196_binop_lc J
    lload 223
    putstatic rung36_jcon_collate/icn_196_binop_rc J
    lload 225
    putstatic rung36_jcon_collate/icn_pv_decollate_dsize J
    getstatic rung36_jcon_collate/icn_failed B
    ifne icn_192_after_call
    getstatic rung36_jcon_collate/icn_retval J
    goto icn_191_rrelay
icn_192_after_call:
    goto icn_191_lb
;  VAR
icn_202_α:
    getstatic rung36_jcon_collate/icn_pv_decollate_object Ljava/lang/String;
    goto icn_201_sec_sr
icn_202_β:
    goto icn_190_ret_fail
;  INT
icn_203_α:
    ldc2_w 1
    goto icn_201_sec_lor
icn_203_β:
    goto icn_190_ret_fail
;  INT
icn_205_α:
    ldc2_w 2
    goto icn_204_rrelay
icn_205_β:
    goto icn_204_lb
;  INT
icn_207_α:
    ldc2_w 2
    goto icn_206_rrelay
icn_207_β:
    goto icn_206_lb
;  VAR
icn_208_α:
    getstatic rung36_jcon_collate/icn_pv_decollate_dsize J
    goto icn_206_lrelay
icn_208_β:
    goto icn_190_ret_fail
icn_206_lrelay:
    putstatic rung36_jcon_collate/icn_206_binop_lc J
    goto icn_206_lstore
icn_206_rrelay:
    putstatic rung36_jcon_collate/icn_206_binop_rc J
    goto icn_206_compute
icn_206_lb:
    goto icn_208_β
icn_206_α:
    iconst_0
    putstatic rung36_jcon_collate/icn_206_binop_bf I
    goto icn_208_α
icn_206_β:
    iconst_1
    putstatic rung36_jcon_collate/icn_206_binop_bf I
    goto icn_208_α
icn_206_lstore:
    getstatic rung36_jcon_collate/icn_206_binop_bf I
    ifeq icn_207_α
    goto icn_207_β
icn_206_compute:
    getstatic rung36_jcon_collate/icn_206_binop_lc J
    getstatic rung36_jcon_collate/icn_206_binop_rc J
    lsub
    goto icn_204_lrelay
icn_204_lrelay:
    putstatic rung36_jcon_collate/icn_204_binop_lc J
    goto icn_204_lstore
icn_204_rrelay:
    putstatic rung36_jcon_collate/icn_204_binop_rc J
    goto icn_204_compute
icn_204_lb:
    goto icn_206_β
icn_204_α:
    iconst_0
    putstatic rung36_jcon_collate/icn_204_binop_bf I
    goto icn_206_α
icn_204_β:
    goto icn_205_β
icn_204_lstore:
    getstatic rung36_jcon_collate/icn_204_binop_bf I
    ifeq icn_205_α
    goto icn_205_β
icn_204_compute:
    getstatic rung36_jcon_collate/icn_204_binop_lc J
    getstatic rung36_jcon_collate/icn_204_binop_rc J
    ldiv
    goto icn_201_sec_hir
icn_201_sec_lor:
    l2i
    istore 94
    iload 94
    ifgt icn_201_sec_lop
    iload 94
    iflt icn_201_sec_lon
icn_201_sec_loz:
    goto icn_190_ret_fail
icn_201_sec_lop:
    iload 94
    iconst_1
    isub
    putstatic rung36_jcon_collate/icn_201_sec_lo I
    goto icn_204_α
icn_201_sec_lon:
    getstatic rung36_jcon_collate/icn_201_sec_s Ljava/lang/String;
    invokevirtual java/lang/String/length()I
    iload 94
    iadd
    putstatic rung36_jcon_collate/icn_201_sec_lo I
    goto icn_204_α
icn_201_sec_hir:
    l2i
    istore 95
    iload 95
    ifgt icn_201_sec_hip
    iload 95
    iflt icn_201_sec_hin
icn_201_sec_hiz:
    goto icn_190_ret_fail
icn_201_sec_hip:
    iload 95
    iconst_1
    isub
    putstatic rung36_jcon_collate/icn_201_sec_hi I
    goto icn_201_sec_cmp
icn_201_sec_hin:
    getstatic rung36_jcon_collate/icn_201_sec_s Ljava/lang/String;
    invokevirtual java/lang/String/length()I
    iload 95
    iadd
    putstatic rung36_jcon_collate/icn_201_sec_hi I
    goto icn_201_sec_cmp
icn_201_sec_cmp:
    getstatic rung36_jcon_collate/icn_201_sec_lo I
    iflt icn_190_ret_fail
    getstatic rung36_jcon_collate/icn_201_sec_hi I
    iflt icn_190_ret_fail
    getstatic rung36_jcon_collate/icn_201_sec_s Ljava/lang/String;
    invokevirtual java/lang/String/length()I
    getstatic rung36_jcon_collate/icn_201_sec_lo I
    if_icmplt icn_190_ret_fail
    getstatic rung36_jcon_collate/icn_201_sec_s Ljava/lang/String;
    invokevirtual java/lang/String/length()I
    istore 96
    getstatic rung36_jcon_collate/icn_201_sec_hi I
    iload 96
    if_icmple icn_201_sec_hiok
    iload 96
    putstatic rung36_jcon_collate/icn_201_sec_hi I
icn_201_sec_hiok:
    getstatic rung36_jcon_collate/icn_201_sec_s Ljava/lang/String;
    getstatic rung36_jcon_collate/icn_201_sec_lo I
    getstatic rung36_jcon_collate/icn_201_sec_hi I
    invokevirtual java/lang/String/substring(II)Ljava/lang/String;
    goto icn_200_map_mid1
icn_201_α:
    goto icn_202_α
icn_201_sec_sr:
    putstatic rung36_jcon_collate/icn_201_sec_s Ljava/lang/String;
    goto icn_203_α
icn_201_β:
    goto icn_190_ret_fail
;  VAR
icn_210_α:
    getstatic rung36_jcon_collate/icn_pv_decollate_image J
    goto icn_209_sec_sr
icn_210_β:
    goto icn_190_ret_fail
;  INT
icn_212_α:
    ldc2_w 1
    goto icn_211_rrelay
icn_212_β:
    goto icn_211_lb
;  VAR
icn_213_α:
    getstatic rung36_jcon_collate/icn_pv_decollate_n J
    goto icn_211_lrelay
icn_213_β:
    goto icn_190_ret_fail
icn_211_lrelay:
    putstatic rung36_jcon_collate/icn_211_binop_lc J
    goto icn_211_lstore
icn_211_rrelay:
    putstatic rung36_jcon_collate/icn_211_binop_rc J
    goto icn_211_compute
icn_211_lb:
    goto icn_213_β
icn_211_α:
    iconst_0
    putstatic rung36_jcon_collate/icn_211_binop_bf I
    goto icn_213_α
icn_211_β:
    iconst_1
    putstatic rung36_jcon_collate/icn_211_binop_bf I
    goto icn_213_α
icn_211_lstore:
    getstatic rung36_jcon_collate/icn_211_binop_bf I
    ifeq icn_212_α
    goto icn_212_β
icn_211_compute:
    getstatic rung36_jcon_collate/icn_211_binop_lc J
    getstatic rung36_jcon_collate/icn_211_binop_rc J
    ladd
    goto icn_209_sec_lor
;  INT
icn_215_α:
    ldc2_w 2
    goto icn_214_rrelay
icn_215_β:
    goto icn_214_lb
;  VAR
icn_216_α:
    getstatic rung36_jcon_collate/icn_pv_decollate_dsize J
    goto icn_214_lrelay
icn_216_β:
    goto icn_190_ret_fail
icn_214_lrelay:
    putstatic rung36_jcon_collate/icn_214_binop_lc J
    goto icn_214_lstore
icn_214_rrelay:
    putstatic rung36_jcon_collate/icn_214_binop_rc J
    goto icn_214_compute
icn_214_lb:
    goto icn_216_β
icn_214_α:
    iconst_0
    putstatic rung36_jcon_collate/icn_214_binop_bf I
    goto icn_216_α
icn_214_β:
    iconst_1
    putstatic rung36_jcon_collate/icn_214_binop_bf I
    goto icn_216_α
icn_214_lstore:
    getstatic rung36_jcon_collate/icn_214_binop_bf I
    ifeq icn_215_α
    goto icn_215_β
icn_214_compute:
    getstatic rung36_jcon_collate/icn_214_binop_lc J
    getstatic rung36_jcon_collate/icn_214_binop_rc J
    lsub
    goto icn_209_sec_hir
icn_209_sec_lor:
    l2i
    istore 97
    iload 97
    ifgt icn_209_sec_lop
    iload 97
    iflt icn_209_sec_lon
icn_209_sec_loz:
    goto icn_190_ret_fail
icn_209_sec_lop:
    iload 97
    iconst_1
    isub
    putstatic rung36_jcon_collate/icn_209_sec_lo I
    goto icn_214_α
icn_209_sec_lon:
    getstatic rung36_jcon_collate/icn_209_sec_s Ljava/lang/String;
    invokevirtual java/lang/String/length()I
    iload 97
    iadd
    putstatic rung36_jcon_collate/icn_209_sec_lo I
    goto icn_214_α
icn_209_sec_hir:
    l2i
    istore 98
    iload 98
    ifgt icn_209_sec_hip
    iload 98
    iflt icn_209_sec_hin
icn_209_sec_hiz:
    goto icn_190_ret_fail
icn_209_sec_hip:
    iload 98
    iconst_1
    isub
    putstatic rung36_jcon_collate/icn_209_sec_hi I
    goto icn_209_sec_cmp
icn_209_sec_hin:
    getstatic rung36_jcon_collate/icn_209_sec_s Ljava/lang/String;
    invokevirtual java/lang/String/length()I
    iload 98
    iadd
    putstatic rung36_jcon_collate/icn_209_sec_hi I
    goto icn_209_sec_cmp
icn_209_sec_cmp:
    getstatic rung36_jcon_collate/icn_209_sec_lo I
    iflt icn_190_ret_fail
    getstatic rung36_jcon_collate/icn_209_sec_hi I
    iflt icn_190_ret_fail
    getstatic rung36_jcon_collate/icn_209_sec_s Ljava/lang/String;
    invokevirtual java/lang/String/length()I
    getstatic rung36_jcon_collate/icn_209_sec_lo I
    if_icmplt icn_190_ret_fail
    getstatic rung36_jcon_collate/icn_209_sec_s Ljava/lang/String;
    invokevirtual java/lang/String/length()I
    istore 99
    getstatic rung36_jcon_collate/icn_209_sec_hi I
    iload 99
    if_icmple icn_209_sec_hiok
    iload 99
    putstatic rung36_jcon_collate/icn_209_sec_hi I
icn_209_sec_hiok:
    getstatic rung36_jcon_collate/icn_209_sec_s Ljava/lang/String;
    getstatic rung36_jcon_collate/icn_209_sec_lo I
    getstatic rung36_jcon_collate/icn_209_sec_hi I
    invokevirtual java/lang/String/substring(II)Ljava/lang/String;
    goto icn_200_map_mid2
icn_209_α:
    goto icn_210_α
icn_209_sec_sr:
    putstatic rung36_jcon_collate/icn_209_sec_s Ljava/lang/String;
    goto icn_211_α
icn_209_β:
    goto icn_190_ret_fail
;  VAR
icn_218_α:
    getstatic rung36_jcon_collate/icn_pv_decollate_s Ljava/lang/String;
    goto icn_217_sec_sr
icn_218_β:
    goto icn_190_ret_fail
;  INT
icn_219_α:
    ldc2_w 1
    goto icn_217_sec_lor
icn_219_β:
    goto icn_190_ret_fail
;  INT
icn_221_α:
    ldc2_w 2
    goto icn_220_rrelay
icn_221_β:
    goto icn_220_lb
;  VAR
icn_222_α:
    getstatic rung36_jcon_collate/icn_pv_decollate_dsize J
    goto icn_220_lrelay
icn_222_β:
    goto icn_190_ret_fail
icn_220_lrelay:
    putstatic rung36_jcon_collate/icn_220_binop_lc J
    goto icn_220_lstore
icn_220_rrelay:
    putstatic rung36_jcon_collate/icn_220_binop_rc J
    goto icn_220_compute
icn_220_lb:
    goto icn_222_β
icn_220_α:
    iconst_0
    putstatic rung36_jcon_collate/icn_220_binop_bf I
    goto icn_222_α
icn_220_β:
    iconst_1
    putstatic rung36_jcon_collate/icn_220_binop_bf I
    goto icn_222_α
icn_220_lstore:
    getstatic rung36_jcon_collate/icn_220_binop_bf I
    ifeq icn_221_α
    goto icn_221_β
icn_220_compute:
    getstatic rung36_jcon_collate/icn_220_binop_lc J
    getstatic rung36_jcon_collate/icn_220_binop_rc J
    lsub
    goto icn_217_sec_hir
icn_217_sec_lor:
    l2i
    istore 100
    iload 100
    ifgt icn_217_sec_lop
    iload 100
    iflt icn_217_sec_lon
icn_217_sec_loz:
    goto icn_190_ret_fail
icn_217_sec_lop:
    iload 100
    iconst_1
    isub
    putstatic rung36_jcon_collate/icn_217_sec_lo I
    goto icn_220_α
icn_217_sec_lon:
    getstatic rung36_jcon_collate/icn_217_sec_s Ljava/lang/String;
    invokevirtual java/lang/String/length()I
    iload 100
    iadd
    putstatic rung36_jcon_collate/icn_217_sec_lo I
    goto icn_220_α
icn_217_sec_hir:
    l2i
    istore 101
    iload 101
    ifgt icn_217_sec_hip
    iload 101
    iflt icn_217_sec_hin
icn_217_sec_hiz:
    goto icn_190_ret_fail
icn_217_sec_hip:
    iload 101
    iconst_1
    isub
    putstatic rung36_jcon_collate/icn_217_sec_hi I
    goto icn_217_sec_cmp
icn_217_sec_hin:
    getstatic rung36_jcon_collate/icn_217_sec_s Ljava/lang/String;
    invokevirtual java/lang/String/length()I
    iload 101
    iadd
    putstatic rung36_jcon_collate/icn_217_sec_hi I
    goto icn_217_sec_cmp
icn_217_sec_cmp:
    getstatic rung36_jcon_collate/icn_217_sec_lo I
    iflt icn_190_ret_fail
    getstatic rung36_jcon_collate/icn_217_sec_hi I
    iflt icn_190_ret_fail
    getstatic rung36_jcon_collate/icn_217_sec_s Ljava/lang/String;
    invokevirtual java/lang/String/length()I
    getstatic rung36_jcon_collate/icn_217_sec_lo I
    if_icmplt icn_190_ret_fail
    getstatic rung36_jcon_collate/icn_217_sec_s Ljava/lang/String;
    invokevirtual java/lang/String/length()I
    istore 102
    getstatic rung36_jcon_collate/icn_217_sec_hi I
    iload 102
    if_icmple icn_217_sec_hiok
    iload 102
    putstatic rung36_jcon_collate/icn_217_sec_hi I
icn_217_sec_hiok:
    getstatic rung36_jcon_collate/icn_217_sec_s Ljava/lang/String;
    getstatic rung36_jcon_collate/icn_217_sec_lo I
    getstatic rung36_jcon_collate/icn_217_sec_hi I
    invokevirtual java/lang/String/substring(II)Ljava/lang/String;
    goto icn_200_map_after
icn_217_α:
    goto icn_218_α
icn_217_sec_sr:
    putstatic rung36_jcon_collate/icn_217_sec_s Ljava/lang/String;
    goto icn_219_α
icn_217_β:
    goto icn_190_ret_fail
icn_200_α:
    goto icn_201_α
icn_200_β:
    goto icn_201_β
icn_200_map_mid1:
    astore 151
    goto icn_209_α
icn_200_map_mid2:
    astore 152
    goto icn_217_α
icn_200_map_after:
    astore 153
    aload 151
    aload 152
    aload 153
    invokestatic rung36_jcon_collate/icn_builtin_map(Ljava/lang/String;Ljava/lang/String;Ljava/lang/String;)Ljava/lang/String;
    goto icn_191_lrelay
icn_191_lrelay:
    putstatic rung36_jcon_collate/icn_191_lc Ljava/lang/String;
    goto icn_191_lstore
icn_191_rrelay:
    putstatic rung36_jcon_collate/icn_191_rc Ljava/lang/String;
    goto icn_191_compute
icn_191_lb:
    goto icn_200_β
icn_191_α:
    iconst_0
    istore 90
    goto icn_200_α
icn_191_β:
    iconst_1
    istore 90
    goto icn_200_α
icn_191_lstore:
    iload 90
    ifeq icn_192_α
    goto icn_192_β
icn_191_compute:
    getstatic rung36_jcon_collate/icn_191_lc Ljava/lang/String;
    getstatic rung36_jcon_collate/icn_191_rc Ljava/lang/String;
    invokevirtual java/lang/String/concat(Ljava/lang/String;)Ljava/lang/String;
    goto icn_190_ret_store
icn_190_α:
    goto icn_191_α
icn_190_β:
    goto icn_decollate_ret
icn_190_ret_fail:
    iconst_1
    putstatic rung36_jcon_collate/icn_failed B
    goto icn_decollate_done
icn_190_ret_store:
    putstatic rung36_jcon_collate/icn_retval_str Ljava/lang/String;
    lconst_0
    putstatic rung36_jcon_collate/icn_retval J
    iconst_0
    putstatic rung36_jcon_collate/icn_failed B
    goto icn_decollate_ret
;  VAR
icn_224_α:
    getstatic rung36_jcon_collate/icn_pv_decollate_dsize J
    goto icn_223_rrelay
icn_224_β:
    goto icn_223_lb
;  VAR
icn_226_α:
    getstatic rung36_jcon_collate/icn_pv_decollate_n J
    goto icn_225_rrelay
icn_226_β:
    goto icn_225_lb
;  VAR
icn_227_α:
    getstatic rung36_jcon_collate/icn_pv_decollate_ssize J
    goto icn_225_lrelay
icn_227_β:
    goto icn_172_else
icn_225_lrelay:
    putstatic rung36_jcon_collate/icn_225_binop_lc J
    goto icn_225_lstore
icn_225_rrelay:
    putstatic rung36_jcon_collate/icn_225_binop_rc J
    goto icn_225_compute
icn_225_lb:
    goto icn_227_β
icn_225_α:
    iconst_0
    putstatic rung36_jcon_collate/icn_225_binop_bf I
    goto icn_227_α
icn_225_β:
    iconst_1
    putstatic rung36_jcon_collate/icn_225_binop_bf I
    goto icn_227_α
icn_225_lstore:
    getstatic rung36_jcon_collate/icn_225_binop_bf I
    ifeq icn_226_α
    goto icn_226_β
icn_225_compute:
    getstatic rung36_jcon_collate/icn_225_binop_lc J
    getstatic rung36_jcon_collate/icn_225_binop_rc J
    ladd
    goto icn_223_lrelay
icn_223_lrelay:
    putstatic rung36_jcon_collate/icn_223_relop_lc J
    goto icn_223_lstore
icn_223_rrelay:
    putstatic rung36_jcon_collate/icn_223_relop_rc J
    goto icn_223_check
icn_223_lb:
    goto icn_225_β
icn_223_α:
    goto icn_225_α
icn_223_β:
    goto icn_224_β
icn_223_lstore:
    goto icn_224_α
icn_223_check:
    getstatic rung36_jcon_collate/icn_223_relop_lc J
    getstatic rung36_jcon_collate/icn_223_relop_rc J
    lcmp
    ifgt icn_224_β
    getstatic rung36_jcon_collate/icn_223_relop_rc J
    goto icn_172_then
icn_172_then:
    pop2
    goto icn_173_α
icn_172_else:
    goto icn_190_α
icn_172_α:
    goto icn_223_α
icn_172_β:
    goto icn_223_β
;  VAR
icn_230_α:
    getstatic rung36_jcon_collate/icn_pv_decollate_s Ljava/lang/String;
    goto icn_229_relay
icn_230_β:
    goto icn_172_α
icn_229_α:
    goto icn_230_α
icn_229_β:
    goto icn_230_β
icn_229_relay:
    invokevirtual java/lang/String/length()I
    i2l
    goto icn_228_store
icn_228_α:
    goto icn_229_α
icn_228_β:
    goto icn_229_β
icn_228_store:
    putstatic rung36_jcon_collate/icn_pv_decollate_ssize J
    getstatic rung36_jcon_collate/icn_pv_decollate_ssize J
    goto icn_decollate_s4_sdrain
icn_decollate_s4_sdrain:
    pop2
    goto icn_172_α
;  INT
icn_232_α:
    ldc2_w 2
    goto icn_231_rhsok
icn_232_β:
    goto icn_228_α
icn_231_α:
    goto icn_232_α
icn_231_β:
    goto icn_232_β
icn_231_rhsok:
    putstatic rung36_jcon_collate/icn_231_augtemp J
    getstatic rung36_jcon_collate/icn_pv_decollate_n J
    getstatic rung36_jcon_collate/icn_231_augtemp J
    lrem
    dup2
    putstatic rung36_jcon_collate/icn_pv_decollate_n J
    goto icn_decollate_s3_sdrain
icn_decollate_s3_sdrain:
    pop2
    goto icn_228_α
icn_233_α:
    getstatic rung36_jcon_collate/icn_init_decollate I
    ifne icn_233_init_skip
    iconst_1
    putstatic rung36_jcon_collate/icn_init_decollate I
;  INT
icn_239_α:
    ldc2_w 1
    goto icn_238_sub_irelay
icn_239_β:
    goto icn_234_seq_rf_0
;  VAR
icn_240_α:
    ldc "\u0000\u0001\u0002\u0003\u0004\u0005\u0006\u0007\u0008\u0009\u000a\u000b\u000c\u000d\u000e\u000f\u0010\u0011\u0012\u0013\u0014\u0015\u0016\u0017\u0018\u0019\u001a\u001b\u001c\u001d\u001e\u001f !\"#$%&'()*+,-./0123456789:;<=>?@ABCDEFGHIJKLMNOPQRSTUVWXYZ[\\]^_`abcdefghijklmnopqrstuvwxyz{|}~\u007f"
    goto icn_238_sub_srelay
icn_240_β:
    goto icn_234_seq_rf_0
icn_238_sub_srelay:
    putstatic rung36_jcon_collate/icn_238_sub_s Ljava/lang/String;
    goto icn_239_α
icn_238_sub_irelay:
    l2i
    istore 103
    iload 103
    ifgt icn_238_sub_pos
    iload 103
    iflt icn_238_sub_neg
icn_238_sub_z:
    goto icn_234_seq_rf_0
icn_238_sub_pos:
    iload 103
    iconst_1
    isub
    putstatic rung36_jcon_collate/icn_238_sub_i I
    goto icn_238_sub_check
icn_238_sub_neg:
    getstatic rung36_jcon_collate/icn_238_sub_s Ljava/lang/String;
    invokevirtual java/lang/String/length()I
    iload 103
    iadd
    putstatic rung36_jcon_collate/icn_238_sub_i I
    goto icn_238_sub_check
icn_238_sub_check:
    getstatic rung36_jcon_collate/icn_238_sub_i I
    iflt icn_234_seq_rf_0
    getstatic rung36_jcon_collate/icn_238_sub_s Ljava/lang/String;
    invokevirtual java/lang/String/length()I
    getstatic rung36_jcon_collate/icn_238_sub_i I
    if_icmple icn_234_seq_rf_0
    getstatic rung36_jcon_collate/icn_238_sub_s Ljava/lang/String;
    getstatic rung36_jcon_collate/icn_238_sub_i I
    getstatic rung36_jcon_collate/icn_238_sub_i I
    iconst_1
    iadd
    invokevirtual java/lang/String/substring(II)Ljava/lang/String;
    goto icn_237_repl_mid
icn_238_α:
    goto icn_240_α
icn_238_β:
    goto icn_239_β
;  INT
icn_242_α:
    ldc2_w 1
    goto icn_241_rrelay
icn_242_β:
    goto icn_241_lb
;  VAR
icn_244_α:
    ldc "\u0000\u0001\u0002\u0003\u0004\u0005\u0006\u0007\u0008\u0009\u000a\u000b\u000c\u000d\u000e\u000f\u0010\u0011\u0012\u0013\u0014\u0015\u0016\u0017\u0018\u0019\u001a\u001b\u001c\u001d\u001e\u001f !\"#$%&'()*+,-./0123456789:;<=>?@ABCDEFGHIJKLMNOPQRSTUVWXYZ[\\]^_`abcdefghijklmnopqrstuvwxyz{|}~\u007f"
    goto icn_243_relay
icn_244_β:
    goto icn_234_seq_rf_0
icn_243_α:
    goto icn_244_α
icn_243_β:
    goto icn_244_β
icn_243_relay:
    invokevirtual java/lang/String/length()I
    i2l
    goto icn_241_lrelay
icn_241_lrelay:
    putstatic rung36_jcon_collate/icn_241_binop_lc J
    goto icn_241_lstore
icn_241_rrelay:
    putstatic rung36_jcon_collate/icn_241_binop_rc J
    goto icn_241_compute
icn_241_lb:
    goto icn_243_β
icn_241_α:
    iconst_0
    putstatic rung36_jcon_collate/icn_241_binop_bf I
    goto icn_243_α
icn_241_β:
    goto icn_242_β
icn_241_lstore:
    getstatic rung36_jcon_collate/icn_241_binop_bf I
    ifeq icn_242_α
    goto icn_242_β
icn_241_compute:
    getstatic rung36_jcon_collate/icn_241_binop_lc J
    getstatic rung36_jcon_collate/icn_241_binop_rc J
    lsub
    goto icn_237_repl_after
icn_237_α:
    goto icn_238_α
icn_237_β:
    goto icn_238_β
icn_237_repl_mid:
    astore 154
    goto icn_241_α
icn_237_repl_after:
    l2i
    istore 104
    new java/lang/StringBuilder
    dup
    invokespecial java/lang/StringBuilder/<init>()V
    astore 155
    iconst_0
    istore 12
icn_237_repl_loop:
    iload 12
    iload 104
    if_icmpge icn_237_repl_done
    aload 155
    aload 154
    invokevirtual java/lang/StringBuilder/append(Ljava/lang/String;)Ljava/lang/StringBuilder;
    pop
    iinc 12 1
    goto icn_237_repl_loop
icn_237_repl_done:
    aload 155
    invokevirtual java/lang/StringBuilder/toString()Ljava/lang/String;
    goto icn_236_arg1
icn_236_arg1:
    putstatic rung36_jcon_collate/icn_arg_str_1 Ljava/lang/String;
    lconst_0
    putstatic rung36_jcon_collate/icn_arg_1 J
    goto icn_236_docall
;  VAR
icn_246_α:
    ldc "\u0000\u0001\u0002\u0003\u0004\u0005\u0006\u0007\u0008\u0009\u000a\u000b\u000c\u000d\u000e\u000f\u0010\u0011\u0012\u0013\u0014\u0015\u0016\u0017\u0018\u0019\u001a\u001b\u001c\u001d\u001e\u001f !\"#$%&'()*+,-./0123456789:;<=>?@ABCDEFGHIJKLMNOPQRSTUVWXYZ[\\]^_`abcdefghijklmnopqrstuvwxyz{|}~\u007f"
    goto icn_245_sec_sr
icn_246_β:
    goto icn_234_seq_rf_0
;  INT
icn_247_α:
    ldc2_w 2
    goto icn_245_sec_lor
icn_247_β:
    goto icn_234_seq_rf_0
;  INT
icn_248_α:
    ldc2_w 0
    goto icn_245_sec_hir
icn_248_β:
    goto icn_234_seq_rf_0
icn_245_sec_lor:
    l2i
    istore 105
    iload 105
    ifgt icn_245_sec_lop
    iload 105
    iflt icn_245_sec_lon
icn_245_sec_loz:
    goto icn_234_seq_rf_0
icn_245_sec_lop:
    iload 105
    iconst_1
    isub
    putstatic rung36_jcon_collate/icn_245_sec_lo I
    goto icn_248_α
icn_245_sec_lon:
    getstatic rung36_jcon_collate/icn_245_sec_s Ljava/lang/String;
    invokevirtual java/lang/String/length()I
    iload 105
    iadd
    putstatic rung36_jcon_collate/icn_245_sec_lo I
    goto icn_248_α
icn_245_sec_hir:
    l2i
    istore 106
    iload 106
    ifgt icn_245_sec_hip
    iload 106
    iflt icn_245_sec_hin
icn_245_sec_hiz:
    goto icn_234_seq_rf_0
icn_245_sec_hip:
    iload 106
    iconst_1
    isub
    putstatic rung36_jcon_collate/icn_245_sec_hi I
    goto icn_245_sec_cmp
icn_245_sec_hin:
    getstatic rung36_jcon_collate/icn_245_sec_s Ljava/lang/String;
    invokevirtual java/lang/String/length()I
    iload 106
    iadd
    putstatic rung36_jcon_collate/icn_245_sec_hi I
    goto icn_245_sec_cmp
icn_245_sec_cmp:
    getstatic rung36_jcon_collate/icn_245_sec_lo I
    iflt icn_234_seq_rf_0
    getstatic rung36_jcon_collate/icn_245_sec_hi I
    iflt icn_234_seq_rf_0
    getstatic rung36_jcon_collate/icn_245_sec_s Ljava/lang/String;
    invokevirtual java/lang/String/length()I
    getstatic rung36_jcon_collate/icn_245_sec_lo I
    if_icmplt icn_234_seq_rf_0
    getstatic rung36_jcon_collate/icn_245_sec_s Ljava/lang/String;
    invokevirtual java/lang/String/length()I
    istore 107
    getstatic rung36_jcon_collate/icn_245_sec_hi I
    iload 107
    if_icmple icn_245_sec_hiok
    iload 107
    putstatic rung36_jcon_collate/icn_245_sec_hi I
icn_245_sec_hiok:
    getstatic rung36_jcon_collate/icn_245_sec_s Ljava/lang/String;
    getstatic rung36_jcon_collate/icn_245_sec_lo I
    getstatic rung36_jcon_collate/icn_245_sec_hi I
    invokevirtual java/lang/String/substring(II)Ljava/lang/String;
    goto icn_236_arg0
icn_245_α:
    goto icn_246_α
icn_245_sec_sr:
    putstatic rung36_jcon_collate/icn_245_sec_s Ljava/lang/String;
    goto icn_247_α
icn_245_β:
    goto icn_234_seq_rf_0
icn_236_arg0:
    putstatic rung36_jcon_collate/icn_arg_str_0 Ljava/lang/String;
    lconst_0
    putstatic rung36_jcon_collate/icn_arg_0 J
    goto icn_237_α
icn_236_α:
    goto icn_245_α
icn_236_β:
    goto icn_237_β
icn_236_docall:
    getstatic rung36_jcon_collate/icn_38_binop_lc J
    lstore 160
    getstatic rung36_jcon_collate/icn_38_binop_rc J
    lstore 162
    getstatic rung36_jcon_collate/icn_58_binop_lc J
    lstore 164
    getstatic rung36_jcon_collate/icn_58_binop_rc J
    lstore 166
    getstatic rung36_jcon_collate/icn_63_binop_lc J
    lstore 168
    getstatic rung36_jcon_collate/icn_63_binop_rc J
    lstore 170
    getstatic rung36_jcon_collate/icn_76_relop_lc J
    lstore 172
    getstatic rung36_jcon_collate/icn_76_relop_rc J
    lstore 174
    getstatic rung36_jcon_collate/icn_87_binop_lc J
    lstore 176
    getstatic rung36_jcon_collate/icn_87_binop_rc J
    lstore 178
    getstatic rung36_jcon_collate/icn_96_binop_lc J
    lstore 180
    getstatic rung36_jcon_collate/icn_96_binop_rc J
    lstore 182
    getstatic rung36_jcon_collate/icn_105_binop_lc J
    lstore 184
    getstatic rung36_jcon_collate/icn_105_binop_rc J
    lstore 186
    getstatic rung36_jcon_collate/icn_114_binop_lc J
    lstore 188
    getstatic rung36_jcon_collate/icn_114_binop_rc J
    lstore 190
    getstatic rung36_jcon_collate/icn_120_relop_lc J
    lstore 192
    getstatic rung36_jcon_collate/icn_120_relop_rc J
    lstore 194
    getstatic rung36_jcon_collate/icn_125_relop_lc J
    lstore 196
    getstatic rung36_jcon_collate/icn_125_relop_rc J
    lstore 198
    getstatic rung36_jcon_collate/icn_147_binop_lc J
    lstore 200
    getstatic rung36_jcon_collate/icn_147_binop_rc J
    lstore 202
    getstatic rung36_jcon_collate/icn_154_binop_lc J
    lstore 204
    getstatic rung36_jcon_collate/icn_154_binop_rc J
    lstore 206
    getstatic rung36_jcon_collate/icn_178_binop_lc J
    lstore 208
    getstatic rung36_jcon_collate/icn_178_binop_rc J
    lstore 210
    getstatic rung36_jcon_collate/icn_180_binop_lc J
    lstore 212
    getstatic rung36_jcon_collate/icn_180_binop_rc J
    lstore 214
    getstatic rung36_jcon_collate/icn_pv_decollate_n J
    lstore 216
    getstatic rung36_jcon_collate/icn_pv_decollate_ssize J
    lstore 218
    getstatic rung36_jcon_collate/icn_pv_decollate_image J
    lstore 220
    getstatic rung36_jcon_collate/icn_185_binop_lc J
    lstore 222
    getstatic rung36_jcon_collate/icn_185_binop_rc J
    lstore 224
    getstatic rung36_jcon_collate/icn_196_binop_lc J
    lstore 226
    getstatic rung36_jcon_collate/icn_196_binop_rc J
    lstore 228
    getstatic rung36_jcon_collate/icn_pv_decollate_dsize J
    lstore 230
    getstatic rung36_jcon_collate/icn_204_binop_lc J
    lstore 232
    getstatic rung36_jcon_collate/icn_204_binop_rc J
    lstore 234
    getstatic rung36_jcon_collate/icn_206_binop_lc J
    lstore 236
    getstatic rung36_jcon_collate/icn_206_binop_rc J
    lstore 238
    getstatic rung36_jcon_collate/icn_211_binop_lc J
    lstore 240
    getstatic rung36_jcon_collate/icn_211_binop_rc J
    lstore 242
    getstatic rung36_jcon_collate/icn_214_binop_lc J
    lstore 244
    getstatic rung36_jcon_collate/icn_214_binop_rc J
    lstore 246
    getstatic rung36_jcon_collate/icn_220_binop_lc J
    lstore 248
    getstatic rung36_jcon_collate/icn_220_binop_rc J
    lstore 250
    getstatic rung36_jcon_collate/icn_223_relop_lc J
    lstore 252
    getstatic rung36_jcon_collate/icn_223_relop_rc J
    lstore 254
    getstatic rung36_jcon_collate/icn_225_binop_lc J
    lstore 256
    getstatic rung36_jcon_collate/icn_225_binop_rc J
    lstore 258
    getstatic rung36_jcon_collate/icn_231_augtemp J
    lstore 260
    getstatic rung36_jcon_collate/icn_241_binop_lc J
    lstore 262
    getstatic rung36_jcon_collate/icn_241_binop_rc J
    lstore 264
    invokestatic rung36_jcon_collate/icn_collate()V
    lload 160
    putstatic rung36_jcon_collate/icn_38_binop_lc J
    lload 162
    putstatic rung36_jcon_collate/icn_38_binop_rc J
    lload 164
    putstatic rung36_jcon_collate/icn_58_binop_lc J
    lload 166
    putstatic rung36_jcon_collate/icn_58_binop_rc J
    lload 168
    putstatic rung36_jcon_collate/icn_63_binop_lc J
    lload 170
    putstatic rung36_jcon_collate/icn_63_binop_rc J
    lload 172
    putstatic rung36_jcon_collate/icn_76_relop_lc J
    lload 174
    putstatic rung36_jcon_collate/icn_76_relop_rc J
    lload 176
    putstatic rung36_jcon_collate/icn_87_binop_lc J
    lload 178
    putstatic rung36_jcon_collate/icn_87_binop_rc J
    lload 180
    putstatic rung36_jcon_collate/icn_96_binop_lc J
    lload 182
    putstatic rung36_jcon_collate/icn_96_binop_rc J
    lload 184
    putstatic rung36_jcon_collate/icn_105_binop_lc J
    lload 186
    putstatic rung36_jcon_collate/icn_105_binop_rc J
    lload 188
    putstatic rung36_jcon_collate/icn_114_binop_lc J
    lload 190
    putstatic rung36_jcon_collate/icn_114_binop_rc J
    lload 192
    putstatic rung36_jcon_collate/icn_120_relop_lc J
    lload 194
    putstatic rung36_jcon_collate/icn_120_relop_rc J
    lload 196
    putstatic rung36_jcon_collate/icn_125_relop_lc J
    lload 198
    putstatic rung36_jcon_collate/icn_125_relop_rc J
    lload 200
    putstatic rung36_jcon_collate/icn_147_binop_lc J
    lload 202
    putstatic rung36_jcon_collate/icn_147_binop_rc J
    lload 204
    putstatic rung36_jcon_collate/icn_154_binop_lc J
    lload 206
    putstatic rung36_jcon_collate/icn_154_binop_rc J
    lload 208
    putstatic rung36_jcon_collate/icn_178_binop_lc J
    lload 210
    putstatic rung36_jcon_collate/icn_178_binop_rc J
    lload 212
    putstatic rung36_jcon_collate/icn_180_binop_lc J
    lload 214
    putstatic rung36_jcon_collate/icn_180_binop_rc J
    lload 216
    putstatic rung36_jcon_collate/icn_pv_decollate_n J
    lload 218
    putstatic rung36_jcon_collate/icn_pv_decollate_ssize J
    lload 220
    putstatic rung36_jcon_collate/icn_pv_decollate_image J
    lload 222
    putstatic rung36_jcon_collate/icn_185_binop_lc J
    lload 224
    putstatic rung36_jcon_collate/icn_185_binop_rc J
    lload 226
    putstatic rung36_jcon_collate/icn_196_binop_lc J
    lload 228
    putstatic rung36_jcon_collate/icn_196_binop_rc J
    lload 230
    putstatic rung36_jcon_collate/icn_pv_decollate_dsize J
    lload 232
    putstatic rung36_jcon_collate/icn_204_binop_lc J
    lload 234
    putstatic rung36_jcon_collate/icn_204_binop_rc J
    lload 236
    putstatic rung36_jcon_collate/icn_206_binop_lc J
    lload 238
    putstatic rung36_jcon_collate/icn_206_binop_rc J
    lload 240
    putstatic rung36_jcon_collate/icn_211_binop_lc J
    lload 242
    putstatic rung36_jcon_collate/icn_211_binop_rc J
    lload 244
    putstatic rung36_jcon_collate/icn_214_binop_lc J
    lload 246
    putstatic rung36_jcon_collate/icn_214_binop_rc J
    lload 248
    putstatic rung36_jcon_collate/icn_220_binop_lc J
    lload 250
    putstatic rung36_jcon_collate/icn_220_binop_rc J
    lload 252
    putstatic rung36_jcon_collate/icn_223_relop_lc J
    lload 254
    putstatic rung36_jcon_collate/icn_223_relop_rc J
    lload 256
    putstatic rung36_jcon_collate/icn_225_binop_lc J
    lload 258
    putstatic rung36_jcon_collate/icn_225_binop_rc J
    lload 260
    putstatic rung36_jcon_collate/icn_231_augtemp J
    lload 262
    putstatic rung36_jcon_collate/icn_241_binop_lc J
    lload 264
    putstatic rung36_jcon_collate/icn_241_binop_rc J
    getstatic rung36_jcon_collate/icn_failed B
    ifne icn_236_after_call
    getstatic rung36_jcon_collate/icn_retval J
    goto icn_235_store
icn_236_after_call:
    goto icn_234_seq_rf_0
icn_235_α:
    goto icn_236_α
icn_235_β:
    goto icn_236_β
icn_235_store:
    putstatic rung36_jcon_collate/icn_pv_decollate_image J
    getstatic rung36_jcon_collate/icn_pv_decollate_image J
    goto icn_234_seq_rg_0
;  VAR
icn_251_α:
    ldc "\u0000\u0001\u0002\u0003\u0004\u0005\u0006\u0007\u0008\u0009\u000a\u000b\u000c\u000d\u000e\u000f\u0010\u0011\u0012\u0013\u0014\u0015\u0016\u0017\u0018\u0019\u001a\u001b\u001c\u001d\u001e\u001f !\"#$%&'()*+,-./0123456789:;<=>?@ABCDEFGHIJKLMNOPQRSTUVWXYZ[\\]^_`abcdefghijklmnopqrstuvwxyz{|}~\u007f"
    goto icn_250_str_after
icn_251_β:
    goto icn_234_seq_rf_1
icn_250_α:
    goto icn_251_α
icn_250_β:
    goto icn_251_β
icn_250_str_after:
    invokestatic java/lang/Long/toString(J)Ljava/lang/String;
    goto icn_249_store
icn_249_α:
    goto icn_250_α
icn_249_β:
    goto icn_250_β
icn_249_store:
    putstatic rung36_jcon_collate/icn_pv_decollate_object Ljava/lang/String;
    getstatic rung36_jcon_collate/icn_pv_decollate_object Ljava/lang/String;
    goto icn_234_seq_rg_1
;  VAR
icn_254_α:
    getstatic rung36_jcon_collate/icn_pv_decollate_image J
    goto icn_253_relay
icn_254_β:
    goto icn_233_init_run
icn_253_α:
    goto icn_254_α
icn_253_β:
    goto icn_254_β
icn_253_relay:
    invokevirtual java/lang/String/length()I
    i2l
    goto icn_252_store
icn_252_α:
    goto icn_253_α
icn_252_β:
    goto icn_253_β
icn_252_store:
    putstatic rung36_jcon_collate/icn_pv_decollate_dsize J
    getstatic rung36_jcon_collate/icn_pv_decollate_dsize J
    goto icn_233_init_drain
    goto icn_234_α
icn_234_seq_rg_0:
    pop2
    goto icn_249_α
icn_234_seq_rg_1:
    pop
    goto icn_252_α
icn_234_seq_rf_0:
    goto icn_249_α
icn_234_seq_rf_1:
    goto icn_252_α
icn_234_α:
    goto icn_235_α
icn_234_β:
    goto icn_252_β
    goto icn_234_α
icn_233_init_drain:
    pop2
icn_233_init_run:
    lconst_0
    goto icn_decollate_s2_sdrain
icn_233_init_skip:
    lconst_0
    goto icn_decollate_s2_sdrain
icn_233_β:
    goto icn_231_α
icn_decollate_s2_sdrain:
    pop2
    goto icn_231_α
icn_decollate_done:
    iconst_0
    putstatic rung36_jcon_collate/icn_suspended B
    iconst_0
    putstatic rung36_jcon_collate/icn_suspend_id I
    iconst_1
    putstatic rung36_jcon_collate/icn_failed B
    return
icn_decollate_ret:
    iconst_0
    putstatic rung36_jcon_collate/icn_failed B
    return
icn_decollate_sret:
    return
.end method

.method public static icn_perm()V
    .limit stack 16
    .limit locals 518
    lconst_0
    lstore 0
    lconst_0
    lstore 2
    lconst_0
    lstore 4
    lconst_0
    lstore 6
    lconst_0
    lstore 8
    lconst_0
    lstore 10
    lconst_0
    lstore 12
    lconst_0
    lstore 14
    lconst_0
    lstore 16
    lconst_0
    lstore 18
    lconst_0
    lstore 20
    lconst_0
    lstore 22
    lconst_0
    lstore 24
    lconst_0
    lstore 26
    lconst_0
    lstore 28
    lconst_0
    lstore 30
    lconst_0
    lstore 32
    lconst_0
    lstore 34
    lconst_0
    lstore 36
    lconst_0
    lstore 38
    lconst_0
    lstore 40
    lconst_0
    lstore 42
    lconst_0
    lstore 44
    lconst_0
    lstore 46
    lconst_0
    lstore 48
    lconst_0
    lstore 50
    lconst_0
    lstore 52
    lconst_0
    lstore 54
    lconst_0
    lstore 56
    lconst_0
    lstore 58
    lconst_0
    lstore 60
    lconst_0
    lstore 62
    iconst_0
    istore 84
    iconst_0
    istore 85
    iconst_0
    istore 86
    iconst_0
    istore 87
    aconst_null
    astore 148
    aconst_null
    astore 149
    aconst_null
    astore 150
    aconst_null
    astore 151
    goto icn_266_α
;  VAR
icn_259_α:
    getstatic rung36_jcon_collate/icn_pv_perm_output J
    goto icn_258_sort_rel
icn_259_β:
    goto icn_perm_done
icn_258_α:
    goto icn_259_α
icn_258_β:
    goto icn_perm_done
icn_258_sort_rel:
    putstatic rung36_jcon_collate/icn_258_sort_list Ljava/util/ArrayList;
    getstatic rung36_jcon_collate/icn_258_sort_list Ljava/util/ArrayList;
    invokestatic rung36_jcon_collate/icn_builtin_sort(Ljava/util/ArrayList;)Ljava/util/ArrayList;
    goto icn_257_bang_st
icn_257_α:
    goto icn_258_α
icn_257_β:
    goto icn_257_bang_chk
icn_257_bang_st:
    putstatic rung36_jcon_collate/icn_257_bang_list Ljava/util/ArrayList;
    iconst_0
    putstatic rung36_jcon_collate/icn_257_bang_idx I
icn_257_bang_chk:
    getstatic rung36_jcon_collate/icn_257_bang_list Ljava/util/ArrayList;
    invokevirtual java/util/ArrayList/size()I
    getstatic rung36_jcon_collate/icn_257_bang_idx I
    if_icmple icn_perm_done
    getstatic rung36_jcon_collate/icn_257_bang_list Ljava/util/ArrayList;
    getstatic rung36_jcon_collate/icn_257_bang_idx I
    invokevirtual java/util/ArrayList/get(I)Ljava/lang/Object;
icn_257_bang_ok:
    checkcast java/lang/Long
    invokevirtual java/lang/Long/longValue()J
    getstatic rung36_jcon_collate/icn_257_bang_idx I
    iconst_1
    iadd
    putstatic rung36_jcon_collate/icn_257_bang_idx I
    goto icn_256_waft_0
icn_256_α:
    goto icn_257_α
icn_256_β:
    goto icn_257_β
    goto icn_256_wentry
icn_256_waft_0:
    lstore 2
    getstatic java/lang/System/out Ljava/io/PrintStream;
    lload 2
    invokevirtual java/io/PrintStream/print(J)V
    getstatic java/lang/System/out Ljava/io/PrintStream;
    ldc ""
    invokevirtual java/io/PrintStream/println(Ljava/lang/String;)V
    lload 2
    goto icn_255_gdrain
icn_256_wentry:
    goto icn_257_α
icn_255_gdrain:
    pop2
icn_255_pump:
    goto icn_256_β
icn_255_α:
    goto icn_256_α
icn_255_β:
    goto icn_perm_done
icn_262_α:
    goto icn_260_pump
icn_262_β:
    goto icn_260_pump
icn_261_gdrain:
    pop
icn_261_pump:
    goto icn_262_β
icn_261_α:
    goto icn_262_α
icn_261_β:
    goto icn_260_pump
;  INT
icn_264_α:
    ldc2_w 2
    goto icn_263_e2relay
icn_264_β:
    goto icn_263_e1b
;  INT
icn_265_α:
    ldc2_w 1
    goto icn_263_e1relay
icn_265_β:
    goto icn_255_α
icn_263_e1relay:
    putstatic rung36_jcon_collate/icn_263_e1val J
    goto icn_264_α
icn_263_e2relay:
    putstatic rung36_jcon_collate/icn_263_e2val J
    goto icn_263_init
icn_263_e1b:
    iconst_0
    putstatic rung36_jcon_collate/icn_263_e2seen I
    goto icn_265_β
icn_263_e2b:
    goto icn_264_β
icn_263_α:
    iconst_0
    putstatic rung36_jcon_collate/icn_263_e2seen I
    goto icn_265_α
icn_263_β:
    getstatic rung36_jcon_collate/icn_263_I J
    lconst_1
    ladd
    putstatic rung36_jcon_collate/icn_263_I J
    goto icn_263_code
icn_263_init:
    getstatic rung36_jcon_collate/icn_263_e2val J
    putstatic rung36_jcon_collate/icn_263_bound J
    getstatic rung36_jcon_collate/icn_263_e2seen I
    ifne icn_263_init_e2adv
    getstatic rung36_jcon_collate/icn_263_e1val J
    putstatic rung36_jcon_collate/icn_263_e1cur J
    getstatic rung36_jcon_collate/icn_263_e1cur J
    putstatic rung36_jcon_collate/icn_263_I J
    iconst_1
    putstatic rung36_jcon_collate/icn_263_e2seen I
    goto icn_263_code
icn_263_init_e2adv:
    getstatic rung36_jcon_collate/icn_263_e1cur J
    putstatic rung36_jcon_collate/icn_263_I J
    goto icn_263_code
icn_263_code:
    getstatic rung36_jcon_collate/icn_263_I J
    getstatic rung36_jcon_collate/icn_263_bound J
    lcmp
    ifgt icn_263_e2b
    getstatic rung36_jcon_collate/icn_263_I J
    goto icn_260_gdrain
icn_260_gdrain:
    pop2
    goto icn_261_α
icn_260_bdrain:
    pop2
icn_260_pump:
    goto icn_263_β
icn_260_α:
    goto icn_263_α
icn_260_β:
    goto icn_255_α
icn_267_α:
    goto icn_260_α
icn_267_β:
    goto icn_260_α
icn_266_α:
    goto icn_267_α
icn_266_β:
    goto icn_267_β
icn_266_store:
    putstatic rung36_jcon_collate/icn_pv_perm_output J
    getstatic rung36_jcon_collate/icn_pv_perm_output J
    goto icn_perm_s0_sdrain
icn_perm_s0_sdrain:
    pop2
    goto icn_260_α
icn_perm_done:
    iconst_0
    putstatic rung36_jcon_collate/icn_suspended B
    iconst_0
    putstatic rung36_jcon_collate/icn_suspend_id I
    iconst_1
    putstatic rung36_jcon_collate/icn_failed B
    return
icn_perm_ret:
    iconst_0
    putstatic rung36_jcon_collate/icn_failed B
    return
icn_perm_sret:
    return
.end method

.method public static icn_permute()V
    .limit stack 16
    .limit locals 546
    lconst_0
    lstore 0
    lconst_0
    lstore 2
    lconst_0
    lstore 4
    lconst_0
    lstore 6
    lconst_0
    lstore 8
    lconst_0
    lstore 10
    lconst_0
    lstore 12
    lconst_0
    lstore 14
    lconst_0
    lstore 16
    lconst_0
    lstore 18
    lconst_0
    lstore 20
    lconst_0
    lstore 22
    lconst_0
    lstore 24
    lconst_0
    lstore 26
    lconst_0
    lstore 28
    lconst_0
    lstore 30
    lconst_0
    lstore 32
    lconst_0
    lstore 34
    lconst_0
    lstore 36
    lconst_0
    lstore 38
    lconst_0
    lstore 40
    lconst_0
    lstore 42
    lconst_0
    lstore 44
    lconst_0
    lstore 46
    lconst_0
    lstore 48
    lconst_0
    lstore 50
    lconst_0
    lstore 52
    lconst_0
    lstore 54
    lconst_0
    lstore 56
    lconst_0
    lstore 58
    lconst_0
    lstore 60
    lconst_0
    lstore 62
    iconst_0
    istore 84
    iconst_0
    istore 85
    iconst_0
    istore 86
    iconst_0
    istore 87
    iconst_0
    istore 88
    iconst_0
    istore 89
    iconst_0
    istore 90
    iconst_0
    istore 91
    aconst_null
    astore 148
    aconst_null
    astore 149
    aconst_null
    astore 150
    aconst_null
    astore 151
    lconst_0
    lstore 0
    lconst_0
    lstore 2
    lconst_0
    lstore 4
    lconst_0
    lstore 6
    getstatic rung36_jcon_collate/icn_suspend_id I
    ifne icn_permute_beta
icn_permute_fresh:
    getstatic rung36_jcon_collate/icn_arg_str_0 Ljava/lang/String;
    putstatic rung36_jcon_collate/icn_pv_permute_s Ljava/lang/String;
    goto icn_290_α
;  VAR
icn_272_α:
    getstatic rung36_jcon_collate/icn_pv_permute_i J
    goto icn_271_sub_irelay
icn_272_β:
    goto icn_269_seq_rf_0
;  VAR
icn_273_α:
    getstatic rung36_jcon_collate/icn_pv_permute_s Ljava/lang/String;
    goto icn_271_sub_srelay
icn_273_β:
    goto icn_269_seq_rf_0
icn_271_sub_srelay:
    putstatic rung36_jcon_collate/icn_271_sub_s Ljava/lang/String;
    goto icn_272_α
icn_271_sub_irelay:
    l2i
    istore 84
    iload 84
    ifgt icn_271_sub_pos
    iload 84
    iflt icn_271_sub_neg
icn_271_sub_z:
    goto icn_269_seq_rf_0
icn_271_sub_pos:
    iload 84
    iconst_1
    isub
    putstatic rung36_jcon_collate/icn_271_sub_i I
    goto icn_271_sub_check
icn_271_sub_neg:
    getstatic rung36_jcon_collate/icn_271_sub_s Ljava/lang/String;
    invokevirtual java/lang/String/length()I
    iload 84
    iadd
    putstatic rung36_jcon_collate/icn_271_sub_i I
    goto icn_271_sub_check
icn_271_sub_check:
    getstatic rung36_jcon_collate/icn_271_sub_i I
    iflt icn_269_seq_rf_0
    getstatic rung36_jcon_collate/icn_271_sub_s Ljava/lang/String;
    invokevirtual java/lang/String/length()I
    getstatic rung36_jcon_collate/icn_271_sub_i I
    if_icmple icn_269_seq_rf_0
    getstatic rung36_jcon_collate/icn_271_sub_s Ljava/lang/String;
    getstatic rung36_jcon_collate/icn_271_sub_i I
    getstatic rung36_jcon_collate/icn_271_sub_i I
    iconst_1
    iadd
    invokevirtual java/lang/String/substring(II)Ljava/lang/String;
    goto icn_270_store
icn_271_α:
    goto icn_273_α
icn_271_β:
    goto icn_272_β
icn_270_α:
    goto icn_271_α
icn_270_β:
    goto icn_271_β
icn_270_store:
    putstatic rung36_jcon_collate/icn_pv_permute_x Ljava/lang/String;
    getstatic rung36_jcon_collate/icn_pv_permute_x Ljava/lang/String;
    goto icn_269_seq_rg_0
;  VAR
icn_275_α:
    getstatic rung36_jcon_collate/icn_pv_permute_s Ljava/lang/String;
    goto icn_274_store
icn_275_β:
    goto icn_269_seq_rf_1
icn_274_α:
    goto icn_275_α
icn_274_β:
    goto icn_275_β
icn_274_store:
    putstatic rung36_jcon_collate/icn_pv_permute_t Ljava/lang/String;
    getstatic rung36_jcon_collate/icn_pv_permute_t Ljava/lang/String;
    goto icn_269_seq_rg_1
;  STR
icn_277_α:
    ldc ""
    goto icn_276_store
icn_277_β:
    goto icn_269_seq_rf_2
icn_276_α:
    goto icn_277_α
icn_276_β:
    goto icn_277_β
icn_276_store:
    putstatic rung36_jcon_collate/icn_278_lsa_v Ljava/lang/String;
    getstatic rung36_jcon_collate/icn_pv_permute_t Ljava/util/ArrayList;
    putstatic rung36_jcon_collate/icn_278_lsa_l Ljava/util/ArrayList;
;  VAR
icn_279_α:
    getstatic rung36_jcon_collate/icn_pv_permute_i J
    goto icn_278_lsa_ir
icn_279_β:
    goto icn_269_seq_rf_2
    goto icn_279_α
icn_278_lsa_ir:
    lconst_1
    lsub
    putstatic rung36_jcon_collate/icn_278_lsa_i J
    goto icn_278_lsa_do
icn_278_lsa_do:
    getstatic rung36_jcon_collate/icn_278_lsa_l Ljava/util/ArrayList;
    getstatic rung36_jcon_collate/icn_278_lsa_i J
    l2i
    getstatic rung36_jcon_collate/icn_278_lsa_v Ljava/lang/String;
    invokevirtual java/util/ArrayList/set(ILjava/lang/Object;)Ljava/lang/Object;
    pop
    getstatic rung36_jcon_collate/icn_278_lsa_v Ljava/lang/String;
    goto icn_269_seq_rg_2
;  VAR
icn_283_α:
    getstatic rung36_jcon_collate/icn_pv_permute_t Ljava/lang/String;
    goto icn_282_arg0
icn_283_β:
    goto icn_281_lb
icn_282_arg0:
    putstatic rung36_jcon_collate/icn_arg_str_0 Ljava/lang/String;
    lconst_0
    putstatic rung36_jcon_collate/icn_arg_0 J
    goto icn_282_docall
icn_282_α:
    goto icn_283_α
icn_282_β:
    getstatic rung36_jcon_collate/icn_suspended B
    ifeq icn_282_b_fail
    getstatic rung36_jcon_collate/icn_38_binop_lc J
    lstore 152
    getstatic rung36_jcon_collate/icn_38_binop_rc J
    lstore 154
    getstatic rung36_jcon_collate/icn_58_binop_lc J
    lstore 156
    getstatic rung36_jcon_collate/icn_58_binop_rc J
    lstore 158
    getstatic rung36_jcon_collate/icn_63_binop_lc J
    lstore 160
    getstatic rung36_jcon_collate/icn_63_binop_rc J
    lstore 162
    getstatic rung36_jcon_collate/icn_76_relop_lc J
    lstore 164
    getstatic rung36_jcon_collate/icn_76_relop_rc J
    lstore 166
    getstatic rung36_jcon_collate/icn_87_binop_lc J
    lstore 168
    getstatic rung36_jcon_collate/icn_87_binop_rc J
    lstore 170
    getstatic rung36_jcon_collate/icn_96_binop_lc J
    lstore 172
    getstatic rung36_jcon_collate/icn_96_binop_rc J
    lstore 174
    getstatic rung36_jcon_collate/icn_105_binop_lc J
    lstore 176
    getstatic rung36_jcon_collate/icn_105_binop_rc J
    lstore 178
    getstatic rung36_jcon_collate/icn_114_binop_lc J
    lstore 180
    getstatic rung36_jcon_collate/icn_114_binop_rc J
    lstore 182
    getstatic rung36_jcon_collate/icn_120_relop_lc J
    lstore 184
    getstatic rung36_jcon_collate/icn_120_relop_rc J
    lstore 186
    getstatic rung36_jcon_collate/icn_125_relop_lc J
    lstore 188
    getstatic rung36_jcon_collate/icn_125_relop_rc J
    lstore 190
    getstatic rung36_jcon_collate/icn_147_binop_lc J
    lstore 192
    getstatic rung36_jcon_collate/icn_147_binop_rc J
    lstore 194
    getstatic rung36_jcon_collate/icn_154_binop_lc J
    lstore 196
    getstatic rung36_jcon_collate/icn_154_binop_rc J
    lstore 198
    getstatic rung36_jcon_collate/icn_178_binop_lc J
    lstore 200
    getstatic rung36_jcon_collate/icn_178_binop_rc J
    lstore 202
    getstatic rung36_jcon_collate/icn_180_binop_lc J
    lstore 204
    getstatic rung36_jcon_collate/icn_180_binop_rc J
    lstore 206
    getstatic rung36_jcon_collate/icn_185_binop_lc J
    lstore 208
    getstatic rung36_jcon_collate/icn_185_binop_rc J
    lstore 210
    getstatic rung36_jcon_collate/icn_196_binop_lc J
    lstore 212
    getstatic rung36_jcon_collate/icn_196_binop_rc J
    lstore 214
    getstatic rung36_jcon_collate/icn_204_binop_lc J
    lstore 216
    getstatic rung36_jcon_collate/icn_204_binop_rc J
    lstore 218
    getstatic rung36_jcon_collate/icn_206_binop_lc J
    lstore 220
    getstatic rung36_jcon_collate/icn_206_binop_rc J
    lstore 222
    getstatic rung36_jcon_collate/icn_211_binop_lc J
    lstore 224
    getstatic rung36_jcon_collate/icn_211_binop_rc J
    lstore 226
    getstatic rung36_jcon_collate/icn_214_binop_lc J
    lstore 228
    getstatic rung36_jcon_collate/icn_214_binop_rc J
    lstore 230
    getstatic rung36_jcon_collate/icn_220_binop_lc J
    lstore 232
    getstatic rung36_jcon_collate/icn_220_binop_rc J
    lstore 234
    getstatic rung36_jcon_collate/icn_223_relop_lc J
    lstore 236
    getstatic rung36_jcon_collate/icn_223_relop_rc J
    lstore 238
    getstatic rung36_jcon_collate/icn_225_binop_lc J
    lstore 240
    getstatic rung36_jcon_collate/icn_225_binop_rc J
    lstore 242
    getstatic rung36_jcon_collate/icn_231_augtemp J
    lstore 244
    getstatic rung36_jcon_collate/icn_241_binop_lc J
    lstore 246
    getstatic rung36_jcon_collate/icn_241_binop_rc J
    lstore 248
    getstatic rung36_jcon_collate/icn_263_I J
    lstore 250
    getstatic rung36_jcon_collate/icn_263_bound J
    lstore 252
    getstatic rung36_jcon_collate/icn_263_e1cur J
    lstore 254
    getstatic rung36_jcon_collate/icn_263_e1val J
    lstore 256
    getstatic rung36_jcon_collate/icn_263_e2val J
    lstore 258
    getstatic rung36_jcon_collate/icn_pv_permute_i J
    lstore 260
    getstatic rung36_jcon_collate/icn_278_lsa_i J
    lstore 262
    invokestatic rung36_jcon_collate/icn_permute()V
    lload 152
    putstatic rung36_jcon_collate/icn_38_binop_lc J
    lload 154
    putstatic rung36_jcon_collate/icn_38_binop_rc J
    lload 156
    putstatic rung36_jcon_collate/icn_58_binop_lc J
    lload 158
    putstatic rung36_jcon_collate/icn_58_binop_rc J
    lload 160
    putstatic rung36_jcon_collate/icn_63_binop_lc J
    lload 162
    putstatic rung36_jcon_collate/icn_63_binop_rc J
    lload 164
    putstatic rung36_jcon_collate/icn_76_relop_lc J
    lload 166
    putstatic rung36_jcon_collate/icn_76_relop_rc J
    lload 168
    putstatic rung36_jcon_collate/icn_87_binop_lc J
    lload 170
    putstatic rung36_jcon_collate/icn_87_binop_rc J
    lload 172
    putstatic rung36_jcon_collate/icn_96_binop_lc J
    lload 174
    putstatic rung36_jcon_collate/icn_96_binop_rc J
    lload 176
    putstatic rung36_jcon_collate/icn_105_binop_lc J
    lload 178
    putstatic rung36_jcon_collate/icn_105_binop_rc J
    lload 180
    putstatic rung36_jcon_collate/icn_114_binop_lc J
    lload 182
    putstatic rung36_jcon_collate/icn_114_binop_rc J
    lload 184
    putstatic rung36_jcon_collate/icn_120_relop_lc J
    lload 186
    putstatic rung36_jcon_collate/icn_120_relop_rc J
    lload 188
    putstatic rung36_jcon_collate/icn_125_relop_lc J
    lload 190
    putstatic rung36_jcon_collate/icn_125_relop_rc J
    lload 192
    putstatic rung36_jcon_collate/icn_147_binop_lc J
    lload 194
    putstatic rung36_jcon_collate/icn_147_binop_rc J
    lload 196
    putstatic rung36_jcon_collate/icn_154_binop_lc J
    lload 198
    putstatic rung36_jcon_collate/icn_154_binop_rc J
    lload 200
    putstatic rung36_jcon_collate/icn_178_binop_lc J
    lload 202
    putstatic rung36_jcon_collate/icn_178_binop_rc J
    lload 204
    putstatic rung36_jcon_collate/icn_180_binop_lc J
    lload 206
    putstatic rung36_jcon_collate/icn_180_binop_rc J
    lload 208
    putstatic rung36_jcon_collate/icn_185_binop_lc J
    lload 210
    putstatic rung36_jcon_collate/icn_185_binop_rc J
    lload 212
    putstatic rung36_jcon_collate/icn_196_binop_lc J
    lload 214
    putstatic rung36_jcon_collate/icn_196_binop_rc J
    lload 216
    putstatic rung36_jcon_collate/icn_204_binop_lc J
    lload 218
    putstatic rung36_jcon_collate/icn_204_binop_rc J
    lload 220
    putstatic rung36_jcon_collate/icn_206_binop_lc J
    lload 222
    putstatic rung36_jcon_collate/icn_206_binop_rc J
    lload 224
    putstatic rung36_jcon_collate/icn_211_binop_lc J
    lload 226
    putstatic rung36_jcon_collate/icn_211_binop_rc J
    lload 228
    putstatic rung36_jcon_collate/icn_214_binop_lc J
    lload 230
    putstatic rung36_jcon_collate/icn_214_binop_rc J
    lload 232
    putstatic rung36_jcon_collate/icn_220_binop_lc J
    lload 234
    putstatic rung36_jcon_collate/icn_220_binop_rc J
    lload 236
    putstatic rung36_jcon_collate/icn_223_relop_lc J
    lload 238
    putstatic rung36_jcon_collate/icn_223_relop_rc J
    lload 240
    putstatic rung36_jcon_collate/icn_225_binop_lc J
    lload 242
    putstatic rung36_jcon_collate/icn_225_binop_rc J
    lload 244
    putstatic rung36_jcon_collate/icn_231_augtemp J
    lload 246
    putstatic rung36_jcon_collate/icn_241_binop_lc J
    lload 248
    putstatic rung36_jcon_collate/icn_241_binop_rc J
    lload 250
    putstatic rung36_jcon_collate/icn_263_I J
    lload 252
    putstatic rung36_jcon_collate/icn_263_bound J
    lload 254
    putstatic rung36_jcon_collate/icn_263_e1cur J
    lload 256
    putstatic rung36_jcon_collate/icn_263_e1val J
    lload 258
    putstatic rung36_jcon_collate/icn_263_e2val J
    lload 260
    putstatic rung36_jcon_collate/icn_pv_permute_i J
    lload 262
    putstatic rung36_jcon_collate/icn_278_lsa_i J
    getstatic rung36_jcon_collate/icn_failed B
    ifne icn_282_after_resume
    getstatic rung36_jcon_collate/icn_retval J
    goto icn_281_rrelay
icn_282_after_resume:
    goto icn_281_lb
icn_282_b_fail:
    goto icn_281_lb
icn_282_docall:
    getstatic rung36_jcon_collate/icn_38_binop_lc J
    lstore 152
    getstatic rung36_jcon_collate/icn_38_binop_rc J
    lstore 154
    getstatic rung36_jcon_collate/icn_58_binop_lc J
    lstore 156
    getstatic rung36_jcon_collate/icn_58_binop_rc J
    lstore 158
    getstatic rung36_jcon_collate/icn_63_binop_lc J
    lstore 160
    getstatic rung36_jcon_collate/icn_63_binop_rc J
    lstore 162
    getstatic rung36_jcon_collate/icn_76_relop_lc J
    lstore 164
    getstatic rung36_jcon_collate/icn_76_relop_rc J
    lstore 166
    getstatic rung36_jcon_collate/icn_87_binop_lc J
    lstore 168
    getstatic rung36_jcon_collate/icn_87_binop_rc J
    lstore 170
    getstatic rung36_jcon_collate/icn_96_binop_lc J
    lstore 172
    getstatic rung36_jcon_collate/icn_96_binop_rc J
    lstore 174
    getstatic rung36_jcon_collate/icn_105_binop_lc J
    lstore 176
    getstatic rung36_jcon_collate/icn_105_binop_rc J
    lstore 178
    getstatic rung36_jcon_collate/icn_114_binop_lc J
    lstore 180
    getstatic rung36_jcon_collate/icn_114_binop_rc J
    lstore 182
    getstatic rung36_jcon_collate/icn_120_relop_lc J
    lstore 184
    getstatic rung36_jcon_collate/icn_120_relop_rc J
    lstore 186
    getstatic rung36_jcon_collate/icn_125_relop_lc J
    lstore 188
    getstatic rung36_jcon_collate/icn_125_relop_rc J
    lstore 190
    getstatic rung36_jcon_collate/icn_147_binop_lc J
    lstore 192
    getstatic rung36_jcon_collate/icn_147_binop_rc J
    lstore 194
    getstatic rung36_jcon_collate/icn_154_binop_lc J
    lstore 196
    getstatic rung36_jcon_collate/icn_154_binop_rc J
    lstore 198
    getstatic rung36_jcon_collate/icn_178_binop_lc J
    lstore 200
    getstatic rung36_jcon_collate/icn_178_binop_rc J
    lstore 202
    getstatic rung36_jcon_collate/icn_180_binop_lc J
    lstore 204
    getstatic rung36_jcon_collate/icn_180_binop_rc J
    lstore 206
    getstatic rung36_jcon_collate/icn_185_binop_lc J
    lstore 208
    getstatic rung36_jcon_collate/icn_185_binop_rc J
    lstore 210
    getstatic rung36_jcon_collate/icn_196_binop_lc J
    lstore 212
    getstatic rung36_jcon_collate/icn_196_binop_rc J
    lstore 214
    getstatic rung36_jcon_collate/icn_204_binop_lc J
    lstore 216
    getstatic rung36_jcon_collate/icn_204_binop_rc J
    lstore 218
    getstatic rung36_jcon_collate/icn_206_binop_lc J
    lstore 220
    getstatic rung36_jcon_collate/icn_206_binop_rc J
    lstore 222
    getstatic rung36_jcon_collate/icn_211_binop_lc J
    lstore 224
    getstatic rung36_jcon_collate/icn_211_binop_rc J
    lstore 226
    getstatic rung36_jcon_collate/icn_214_binop_lc J
    lstore 228
    getstatic rung36_jcon_collate/icn_214_binop_rc J
    lstore 230
    getstatic rung36_jcon_collate/icn_220_binop_lc J
    lstore 232
    getstatic rung36_jcon_collate/icn_220_binop_rc J
    lstore 234
    getstatic rung36_jcon_collate/icn_223_relop_lc J
    lstore 236
    getstatic rung36_jcon_collate/icn_223_relop_rc J
    lstore 238
    getstatic rung36_jcon_collate/icn_225_binop_lc J
    lstore 240
    getstatic rung36_jcon_collate/icn_225_binop_rc J
    lstore 242
    getstatic rung36_jcon_collate/icn_231_augtemp J
    lstore 244
    getstatic rung36_jcon_collate/icn_241_binop_lc J
    lstore 246
    getstatic rung36_jcon_collate/icn_241_binop_rc J
    lstore 248
    getstatic rung36_jcon_collate/icn_263_I J
    lstore 250
    getstatic rung36_jcon_collate/icn_263_bound J
    lstore 252
    getstatic rung36_jcon_collate/icn_263_e1cur J
    lstore 254
    getstatic rung36_jcon_collate/icn_263_e1val J
    lstore 256
    getstatic rung36_jcon_collate/icn_263_e2val J
    lstore 258
    getstatic rung36_jcon_collate/icn_pv_permute_i J
    lstore 260
    getstatic rung36_jcon_collate/icn_278_lsa_i J
    lstore 262
    invokestatic rung36_jcon_collate/icn_permute()V
    lload 152
    putstatic rung36_jcon_collate/icn_38_binop_lc J
    lload 154
    putstatic rung36_jcon_collate/icn_38_binop_rc J
    lload 156
    putstatic rung36_jcon_collate/icn_58_binop_lc J
    lload 158
    putstatic rung36_jcon_collate/icn_58_binop_rc J
    lload 160
    putstatic rung36_jcon_collate/icn_63_binop_lc J
    lload 162
    putstatic rung36_jcon_collate/icn_63_binop_rc J
    lload 164
    putstatic rung36_jcon_collate/icn_76_relop_lc J
    lload 166
    putstatic rung36_jcon_collate/icn_76_relop_rc J
    lload 168
    putstatic rung36_jcon_collate/icn_87_binop_lc J
    lload 170
    putstatic rung36_jcon_collate/icn_87_binop_rc J
    lload 172
    putstatic rung36_jcon_collate/icn_96_binop_lc J
    lload 174
    putstatic rung36_jcon_collate/icn_96_binop_rc J
    lload 176
    putstatic rung36_jcon_collate/icn_105_binop_lc J
    lload 178
    putstatic rung36_jcon_collate/icn_105_binop_rc J
    lload 180
    putstatic rung36_jcon_collate/icn_114_binop_lc J
    lload 182
    putstatic rung36_jcon_collate/icn_114_binop_rc J
    lload 184
    putstatic rung36_jcon_collate/icn_120_relop_lc J
    lload 186
    putstatic rung36_jcon_collate/icn_120_relop_rc J
    lload 188
    putstatic rung36_jcon_collate/icn_125_relop_lc J
    lload 190
    putstatic rung36_jcon_collate/icn_125_relop_rc J
    lload 192
    putstatic rung36_jcon_collate/icn_147_binop_lc J
    lload 194
    putstatic rung36_jcon_collate/icn_147_binop_rc J
    lload 196
    putstatic rung36_jcon_collate/icn_154_binop_lc J
    lload 198
    putstatic rung36_jcon_collate/icn_154_binop_rc J
    lload 200
    putstatic rung36_jcon_collate/icn_178_binop_lc J
    lload 202
    putstatic rung36_jcon_collate/icn_178_binop_rc J
    lload 204
    putstatic rung36_jcon_collate/icn_180_binop_lc J
    lload 206
    putstatic rung36_jcon_collate/icn_180_binop_rc J
    lload 208
    putstatic rung36_jcon_collate/icn_185_binop_lc J
    lload 210
    putstatic rung36_jcon_collate/icn_185_binop_rc J
    lload 212
    putstatic rung36_jcon_collate/icn_196_binop_lc J
    lload 214
    putstatic rung36_jcon_collate/icn_196_binop_rc J
    lload 216
    putstatic rung36_jcon_collate/icn_204_binop_lc J
    lload 218
    putstatic rung36_jcon_collate/icn_204_binop_rc J
    lload 220
    putstatic rung36_jcon_collate/icn_206_binop_lc J
    lload 222
    putstatic rung36_jcon_collate/icn_206_binop_rc J
    lload 224
    putstatic rung36_jcon_collate/icn_211_binop_lc J
    lload 226
    putstatic rung36_jcon_collate/icn_211_binop_rc J
    lload 228
    putstatic rung36_jcon_collate/icn_214_binop_lc J
    lload 230
    putstatic rung36_jcon_collate/icn_214_binop_rc J
    lload 232
    putstatic rung36_jcon_collate/icn_220_binop_lc J
    lload 234
    putstatic rung36_jcon_collate/icn_220_binop_rc J
    lload 236
    putstatic rung36_jcon_collate/icn_223_relop_lc J
    lload 238
    putstatic rung36_jcon_collate/icn_223_relop_rc J
    lload 240
    putstatic rung36_jcon_collate/icn_225_binop_lc J
    lload 242
    putstatic rung36_jcon_collate/icn_225_binop_rc J
    lload 244
    putstatic rung36_jcon_collate/icn_231_augtemp J
    lload 246
    putstatic rung36_jcon_collate/icn_241_binop_lc J
    lload 248
    putstatic rung36_jcon_collate/icn_241_binop_rc J
    lload 250
    putstatic rung36_jcon_collate/icn_263_I J
    lload 252
    putstatic rung36_jcon_collate/icn_263_bound J
    lload 254
    putstatic rung36_jcon_collate/icn_263_e1cur J
    lload 256
    putstatic rung36_jcon_collate/icn_263_e1val J
    lload 258
    putstatic rung36_jcon_collate/icn_263_e2val J
    lload 260
    putstatic rung36_jcon_collate/icn_pv_permute_i J
    lload 262
    putstatic rung36_jcon_collate/icn_278_lsa_i J
    getstatic rung36_jcon_collate/icn_failed B
    ifne icn_282_after_call
    getstatic rung36_jcon_collate/icn_retval J
    goto icn_281_rrelay
icn_282_after_call:
    goto icn_281_lb
;  VAR
icn_284_α:
    getstatic rung36_jcon_collate/icn_pv_permute_x Ljava/lang/String;
    goto icn_281_lrelay
icn_284_β:
    goto icn_permute_done
icn_281_lrelay:
    putstatic rung36_jcon_collate/icn_281_lc Ljava/lang/String;
    goto icn_281_lstore
icn_281_rrelay:
    putstatic rung36_jcon_collate/icn_281_rc Ljava/lang/String;
    goto icn_281_compute
icn_281_lb:
    goto icn_284_β
icn_281_α:
    iconst_0
    istore 85
    goto icn_284_α
icn_281_β:
    iconst_1
    istore 85
    goto icn_284_α
icn_281_lstore:
    iload 85
    ifeq icn_282_α
    goto icn_282_β
icn_281_compute:
    getstatic rung36_jcon_collate/icn_281_lc Ljava/lang/String;
    getstatic rung36_jcon_collate/icn_281_rc Ljava/lang/String;
    invokevirtual java/lang/String/concat(Ljava/lang/String;)Ljava/lang/String;
    goto icn_280_yield
icn_280_α:
    goto icn_281_α
icn_280_β:
    goto icn_280_resume
icn_280_yield:
    putstatic rung36_jcon_collate/icn_retval J
    iconst_0
    putstatic rung36_jcon_collate/icn_failed B
    iconst_1
    putstatic rung36_jcon_collate/icn_suspended B
    sipush 1
    putstatic rung36_jcon_collate/icn_suspend_id I
    goto icn_permute_sret
icn_280_resume:
    goto icn_268_pump
    goto icn_269_α
icn_269_seq_rg_0:
    pop
    goto icn_274_α
icn_269_seq_rg_1:
    pop
    goto icn_276_α
icn_269_seq_rg_2:
    pop
    goto icn_280_α
icn_269_seq_rf_0:
    goto icn_274_α
icn_269_seq_rf_1:
    goto icn_276_α
icn_269_seq_rf_2:
    goto icn_280_α
icn_269_α:
    goto icn_270_α
icn_269_β:
    goto icn_280_β
;  VAR
icn_288_α:
    getstatic rung36_jcon_collate/icn_pv_permute_s Ljava/lang/String;
    goto icn_287_relay
icn_288_β:
    goto icn_286_e1b
icn_287_α:
    goto icn_288_α
icn_287_β:
    goto icn_288_β
icn_287_relay:
    invokevirtual java/lang/String/length()I
    i2l
    goto icn_286_e2relay
;  INT
icn_289_α:
    ldc2_w 1
    goto icn_286_e1relay
icn_289_β:
    goto icn_permute_done
icn_286_e1relay:
    putstatic rung36_jcon_collate/icn_286_e1val J
    goto icn_287_α
icn_286_e2relay:
    putstatic rung36_jcon_collate/icn_286_e2val J
    goto icn_286_init
icn_286_e1b:
    iconst_0
    putstatic rung36_jcon_collate/icn_286_e2seen I
    goto icn_289_β
icn_286_e2b:
    goto icn_287_β
icn_286_α:
    iconst_0
    putstatic rung36_jcon_collate/icn_286_e2seen I
    goto icn_289_α
icn_286_β:
    getstatic rung36_jcon_collate/icn_286_I J
    lconst_1
    ladd
    putstatic rung36_jcon_collate/icn_286_I J
    goto icn_286_code
icn_286_init:
    getstatic rung36_jcon_collate/icn_286_e2val J
    putstatic rung36_jcon_collate/icn_286_bound J
    getstatic rung36_jcon_collate/icn_286_e2seen I
    ifne icn_286_init_e2adv
    getstatic rung36_jcon_collate/icn_286_e1val J
    putstatic rung36_jcon_collate/icn_286_e1cur J
    getstatic rung36_jcon_collate/icn_286_e1cur J
    putstatic rung36_jcon_collate/icn_286_I J
    iconst_1
    putstatic rung36_jcon_collate/icn_286_e2seen I
    goto icn_286_code
icn_286_init_e2adv:
    getstatic rung36_jcon_collate/icn_286_e1cur J
    putstatic rung36_jcon_collate/icn_286_I J
    goto icn_286_code
icn_286_code:
    getstatic rung36_jcon_collate/icn_286_I J
    getstatic rung36_jcon_collate/icn_286_bound J
    lcmp
    ifgt icn_286_e2b
    getstatic rung36_jcon_collate/icn_286_I J
    goto icn_285_store
icn_285_α:
    goto icn_286_α
icn_285_β:
    goto icn_286_β
icn_285_store:
    putstatic rung36_jcon_collate/icn_pv_permute_i J
    getstatic rung36_jcon_collate/icn_pv_permute_i J
    goto icn_268_gdrain
icn_268_gdrain:
    pop2
    goto icn_269_α
icn_268_bdrain:
    pop2
icn_268_pump:
    goto icn_285_β
icn_268_α:
    goto icn_285_α
icn_268_β:
    goto icn_permute_done
;  STR
icn_292_α:
    ldc ""
    goto icn_291_ret_store
icn_292_β:
    goto icn_291_ret_fail
icn_291_α:
    goto icn_292_α
icn_291_β:
    goto icn_permute_ret
icn_291_ret_fail:
    iconst_1
    putstatic rung36_jcon_collate/icn_failed B
    goto icn_permute_done
icn_291_ret_store:
    putstatic rung36_jcon_collate/icn_retval_str Ljava/lang/String;
    lconst_0
    putstatic rung36_jcon_collate/icn_retval J
    iconst_0
    putstatic rung36_jcon_collate/icn_failed B
    goto icn_permute_ret
;  VAR
icn_294_α:
    getstatic rung36_jcon_collate/icn_pv_permute_s Ljava/lang/String;
    goto icn_293_lrelay
icn_294_β:
    goto icn_290_else
;  STR
icn_295_α:
    ldc ""
    goto icn_293_rrelay
icn_295_β:
    goto icn_290_else
;  STRRELOP
icn_293_α:
    goto icn_294_α
icn_293_β:
    goto icn_294_β
icn_293_lrelay:
    astore 86
    goto icn_293_lstore
icn_293_lstore:
    goto icn_295_α
icn_293_rrelay:
    astore 87
    goto icn_293_chk
icn_293_chk:
    aload 86
    aload 87
    invokevirtual java/lang/String/compareTo(Ljava/lang/String;)I
    ifne icn_295_β
    lconst_0
    goto icn_290_then
icn_290_then:
    pop2
    goto icn_291_α
icn_290_else:
    goto icn_268_α
icn_290_α:
    goto icn_293_α
icn_290_β:
    goto icn_293_β
icn_permute_beta:
    getstatic rung36_jcon_collate/icn_suspend_id I
    tableswitch 1 1
        icn_280_resume
        default: icn_permute_done
icn_permute_done:
    iconst_0
    putstatic rung36_jcon_collate/icn_suspended B
    iconst_0
    putstatic rung36_jcon_collate/icn_suspend_id I
    iconst_1
    putstatic rung36_jcon_collate/icn_failed B
    return
icn_permute_ret:
    iconst_0
    putstatic rung36_jcon_collate/icn_failed B
    return
icn_permute_sret:
    return
.end method

