; Auto-generated by icon_emit_jvm.c — Tiny-ICON Byrd Box JVM
.bytecode 45.0
.class public rung36_jcon_lists
.super java/lang/Object

.field public static icn_failed B
.field public static icn_suspended B
.field public static icn_suspend_id I
.field public static icn_retval_obj Ljava/lang/Object;
.field public static icn_retval J
.field public static icn_retval_str Ljava/lang/String;
.field public static icn_arg_str_0 Ljava/lang/String;
.field public static icn_pv_limage_label Ljava/lang/String;
.field public static icn_arg_str_1 Ljava/lang/String;
.field public static icn_pv_limage_lst Ljava/lang/String;
.field public static icn_pv_main_x Ljava/util/ArrayList;
.field public static icn_pv_main_z Ljava/lang/String;
.field public static icn_gvar_z Ljava/lang/String;
.field public static icn_arg_1 J
.field public static icn_arg_0 J
.field public static icn_pv_main_y J
.field public static icn_22_lc Ljava/lang/String;
.field public static icn_22_rc Ljava/lang/String;
.field public static icn_41_alt_gate I
.field public static icn_45_sec_s Ljava/lang/String;
.field public static icn_45_sec_lo I
.field public static icn_45_sec_hi I
.field public static icn_41_alt_val J
.field public static icn_50_alt_gate I
.field public static icn_54_sec_s Ljava/lang/String;
.field public static icn_54_sec_lo I
.field public static icn_54_sec_hi I
.field public static icn_50_alt_val J
.field public static icn_61_sec_s Ljava/lang/String;
.field public static icn_61_sec_lo I
.field public static icn_61_sec_hi I
.field public static icn_69_sec_s Ljava/lang/String;
.field public static icn_69_sec_lo I
.field public static icn_69_sec_hi I
.field public static icn_76_sec_s Ljava/lang/String;
.field public static icn_76_sec_lo I
.field public static icn_76_sec_hi I
.field public static icn_82_sec_s Ljava/lang/String;
.field public static icn_82_sec_lo I
.field public static icn_82_sec_hi I
.field public static icn_91_mklist Ljava/util/ArrayList;
.field public static icn_91_elem_0 Ljava/lang/Object;
.field public static icn_91_elem_1 Ljava/lang/Object;
.field public static icn_91_elem_2 Ljava/lang/Object;
.field public static icn_91_elem_3 Ljava/lang/Object;
.field public static icn_91_elem_4 Ljava/lang/Object;
.field public static icn_91_elem_5 Ljava/lang/Object;
.field public static icn_91_elem_6 Ljava/lang/Object;
.field public static icn_91_elem_7 Ljava/lang/Object;
.field public static icn_91_elem_8 Ljava/lang/Object;
.field public static icn_102_alt_gate I
.field public static icn_104_plist Ljava/util/ArrayList;
.field public static icn_104_psz I
.field public static icn_102_alt_val J
.field public static icn_107_alt_gate I
.field public static icn_109_glist Ljava/util/ArrayList;
.field public static icn_107_alt_val J
.field public static icn_112_alt_gate I
.field public static icn_114_glist Ljava/util/ArrayList;
.field public static icn_112_alt_val J
.field public static icn_116_glist Ljava/util/ArrayList;
.field public static icn_119_alt_gate I
.field public static icn_121_lsub_l Ljava/util/ArrayList;
.field public static icn_121_lsub_i I
.field public static icn_119_alt_val J
.field public static icn_126_alt_gate I
.field public static icn_128_lsub_l Ljava/util/ArrayList;
.field public static icn_128_lsub_i I
.field public static icn_126_alt_val J
.field public static icn_132_alt_gate I
.field public static icn_134_lsub_l Ljava/util/ArrayList;
.field public static icn_134_lsub_i I
.field public static icn_132_alt_val J
.field public static icn_147_mklist Ljava/util/ArrayList;
.field public static icn_147_elem_0 Ljava/lang/Object;
.field public static icn_pv_main_i J
.field public static icn_155_lsa_l Ljava/util/ArrayList;
.field public static icn_155_lsa_i J
.field public static icn_155_lsa_v J
.field public static icn_158_I J
.field public static icn_158_bound J
.field public static icn_158_e1cur J
.field public static icn_158_e2seen I
.field public static icn_158_e1val J
.field public static icn_158_e2val J
.field public static icn_160_binop_lc J
.field public static icn_160_binop_rc J
.field public static icn_160_binop_bf I
.field public static icn_171_lsa_l Ljava/util/ArrayList;
.field public static icn_171_lsa_i J
.field public static icn_171_lsa_v J
.field public static icn_174_I J
.field public static icn_174_bound J
.field public static icn_174_e1cur J
.field public static icn_174_e2seen I
.field public static icn_174_e1val J
.field public static icn_174_e2val J
.field public static icn_175_binop_lc J
.field public static icn_175_binop_rc J
.field public static icn_175_binop_bf I
.field public static icn_181_mklist Ljava/util/ArrayList;
.field public static icn_181_elem_0 Ljava/lang/Object;
.field public static icn_181_elem_1 Ljava/lang/Object;
.field public static icn_181_elem_2 Ljava/lang/Object;
.field public static icn_181_elem_3 Ljava/lang/Object;
.field public static icn_181_elem_4 Ljava/lang/Object;
.field public static icn_196_pushval Ljava/lang/Object;
.field public static icn_196_pushlist Ljava/util/ArrayList;
.field public static icn_197_pushval Ljava/lang/Object;
.field public static icn_197_pushlist Ljava/util/ArrayList;
.field public static icn_204_pushval Ljava/lang/Object;
.field public static icn_204_pushlist Ljava/util/ArrayList;
.field public static icn_205_pushval Ljava/lang/Object;
.field public static icn_205_pushlist Ljava/util/ArrayList;
.field public static icn_212_pushval Ljava/lang/Object;
.field public static icn_212_pushlist Ljava/util/ArrayList;
.field public static icn_218_pushval Ljava/lang/Object;
.field public static icn_218_pushlist Ljava/util/ArrayList;
.field public static icn_224_pushval Ljava/lang/Object;
.field public static icn_224_pushlist Ljava/util/ArrayList;
.field public static icn_225_pushval Ljava/lang/Object;
.field public static icn_225_pushlist Ljava/util/ArrayList;
.field public static icn_232_pushval Ljava/lang/Object;
.field public static icn_232_pushlist Ljava/util/ArrayList;
.field public static icn_238_pushval Ljava/lang/Object;
.field public static icn_238_pushlist Ljava/util/ArrayList;
.field public static icn_247_plist Ljava/util/ArrayList;
.field public static icn_247_psz I
.field public static icn_255_glist Ljava/util/ArrayList;
.field public static icn_263_glist Ljava/util/ArrayList;
.field public static icn_274_mklist Ljava/util/ArrayList;
.field public static icn_274_elem_0 Ljava/lang/Object;
.field public static icn_274_elem_1 Ljava/lang/Object;
.field public static icn_274_elem_2 Ljava/lang/Object;
.field public static icn_279_lc Ljava/lang/String;
.field public static icn_279_rc Ljava/lang/String;
.field public static icn_280_mklist Ljava/util/ArrayList;
.field public static icn_280_elem_0 Ljava/lang/Object;
.field public static icn_280_elem_1 Ljava/lang/Object;
.field public static icn_280_elem_2 Ljava/lang/Object;
.field public static icn_280_elem_3 Ljava/lang/Object;
.field public static icn_280_elem_4 Ljava/lang/Object;
.field public static icn_286_mklist Ljava/util/ArrayList;
.field public static icn_286_elem_0 Ljava/lang/Object;
.field public static icn_286_elem_1 Ljava/lang/Object;
.field public static icn_286_elem_2 Ljava/lang/Object;
.field public static icn_292_mklist Ljava/util/ArrayList;
.field public static icn_292_elem_0 Ljava/lang/Object;
.field public static icn_292_elem_1 Ljava/lang/Object;
.field public static icn_292_elem_2 Ljava/lang/Object;
.field public static icn_292_elem_3 Ljava/lang/Object;
.field public static icn_299_mklist Ljava/util/ArrayList;
.field public static icn_299_elem_0 Ljava/lang/Object;
.field public static icn_303_mklist Ljava/util/ArrayList;
.field public static icn_303_elem_0 Ljava/lang/Object;
.field public static icn_307_mklist Ljava/util/ArrayList;
.field public static icn_310_ln J
.field public static icn_310_lx Ljava/lang/Object;
.field public static icn_310_ll Ljava/util/ArrayList;
.field public static icn_310_lc I
.field public static icn_315_ln J
.field public static icn_315_lx Ljava/lang/Object;
.field public static icn_315_ll Ljava/util/ArrayList;
.field public static icn_315_lc I
.field public static icn_320_ln J
.field public static icn_320_lx Ljava/lang/Object;
.field public static icn_320_ll Ljava/util/ArrayList;
.field public static icn_320_lc I

.method public static main([Ljava/lang/String;)V
    .limit stack 4
    .limit locals 1
    invokestatic rung36_jcon_lists/icn_main()V
    return
.end method

.method public static icn_builtin_left(Ljava/lang/String;ILjava/lang/String;)Ljava/lang/String;
    .limit stack 4
    .limit locals 5
    aload_0
    invokevirtual java/lang/String/length()I
    iload_1
    if_icmplt icn_left_pad
    aload_0
    iconst_0
    iload_1
    invokevirtual java/lang/String/substring(II)Ljava/lang/String;
    areturn
icn_left_pad:
    new java/lang/StringBuilder
    dup
    aload_0
    invokespecial java/lang/StringBuilder/<init>(Ljava/lang/String;)V
    astore_3
icn_left_loop:
    aload_3
    invokevirtual java/lang/StringBuilder/length()I
    iload_1
    if_icmpge icn_left_done
    aload_3
    aload_2
    iconst_0
    invokevirtual java/lang/String/charAt(I)C
    invokevirtual java/lang/StringBuilder/append(C)Ljava/lang/StringBuilder;
    pop
    goto icn_left_loop
icn_left_done:
    aload_3
    invokevirtual java/lang/StringBuilder/toString()Ljava/lang/String;
    areturn
.end method

.method public static icn_builtin_right(Ljava/lang/String;ILjava/lang/String;)Ljava/lang/String;
    .limit stack 4
    .limit locals 5
    aload_0
    invokevirtual java/lang/String/length()I
    iload_1
    if_icmplt icn_right_pad
    aload_0
    invokevirtual java/lang/String/length()I
    iload_1
    isub
    aload_0
    swap
    invokevirtual java/lang/String/substring(I)Ljava/lang/String;
    areturn
icn_right_pad:
    new java/lang/StringBuilder
    dup
    invokespecial java/lang/StringBuilder/<init>()V
    astore_3
    iload_1
    aload_0
    invokevirtual java/lang/String/length()I
    isub
    istore 4
    iconst_0
icn_right_loop:
    dup
    iload 4
    if_icmpge icn_right_append
    aload_3
    aload_2
    iconst_0
    invokevirtual java/lang/String/charAt(I)C
    invokevirtual java/lang/StringBuilder/append(C)Ljava/lang/StringBuilder;
    pop
    iconst_1
    iadd
    goto icn_right_loop
icn_right_append:
    pop
    aload_3
    aload_0
    invokevirtual java/lang/StringBuilder/append(Ljava/lang/String;)Ljava/lang/StringBuilder;
    pop
    aload_3
    invokevirtual java/lang/StringBuilder/toString()Ljava/lang/String;
    areturn
.end method

.method public static icn_builtin_center(Ljava/lang/String;ILjava/lang/String;)Ljava/lang/String;
    .limit stack 5
    .limit locals 7
    aload_0
    invokevirtual java/lang/String/length()I
    iload_1
    if_icmplt icn_ctr_pad
    aload_0
    iconst_0
    iload_1
    invokevirtual java/lang/String/substring(II)Ljava/lang/String;
    areturn
icn_ctr_pad:
    iload_1
    aload_0
    invokevirtual java/lang/String/length()I
    isub
    istore_3
    iload_3
    iconst_2
    idiv
    istore 4
    iload_3
    iload 4
    isub
    istore 5
    new java/lang/StringBuilder
    dup
    invokespecial java/lang/StringBuilder/<init>()V
    astore 6
    iconst_0
icn_ctr_lloop:
    dup
    iload 4
    if_icmpge icn_ctr_mid
    aload 6
    aload_2
    iconst_0
    invokevirtual java/lang/String/charAt(I)C
    invokevirtual java/lang/StringBuilder/append(C)Ljava/lang/StringBuilder;
    pop
    iconst_1
    iadd
    goto icn_ctr_lloop
icn_ctr_mid:
    pop
    aload 6
    aload_0
    invokevirtual java/lang/StringBuilder/append(Ljava/lang/String;)Ljava/lang/StringBuilder;
    pop
    iconst_0
icn_ctr_rloop:
    dup
    iload 5
    if_icmpge icn_ctr_done
    aload 6
    aload_2
    iconst_0
    invokevirtual java/lang/String/charAt(I)C
    invokevirtual java/lang/StringBuilder/append(C)Ljava/lang/StringBuilder;
    pop
    iconst_1
    iadd
    goto icn_ctr_rloop
icn_ctr_done:
    pop
    aload 6
    invokevirtual java/lang/StringBuilder/toString()Ljava/lang/String;
    areturn
.end method

.method public static icn_builtin_trim(Ljava/lang/String;Ljava/lang/String;)Ljava/lang/String;
    .limit stack 4
    .limit locals 3
    aload_0
    invokevirtual java/lang/String/length()I
    istore_2
icn_trim_loop:
    iload_2
    ifle icn_trim_done
    aload_1
    aload_0
    iload_2
    iconst_1
    isub
    invokevirtual java/lang/String/charAt(I)C
    invokevirtual java/lang/String/indexOf(I)I
    iflt icn_trim_done
    iinc 2 -1
    goto icn_trim_loop
icn_trim_done:
    aload_0
    iconst_0
    iload_2
    invokevirtual java/lang/String/substring(II)Ljava/lang/String;
    areturn
.end method

.method public static icn_builtin_map(Ljava/lang/String;Ljava/lang/String;Ljava/lang/String;)Ljava/lang/String;
    .limit stack 5
    .limit locals 7
    new java/lang/StringBuilder
    dup
    invokespecial java/lang/StringBuilder/<init>()V
    astore_3
    iconst_0
    istore 4
icn_map_loop:
    iload 4
    aload_0
    invokevirtual java/lang/String/length()I
    if_icmpge icn_map_done
    aload_0
    iload 4
    invokevirtual java/lang/String/charAt(I)C
    istore 5
    aload_1
    iload 5
    invokevirtual java/lang/String/indexOf(I)I
    istore 6
    iload 6
    iflt icn_map_notfound
    iload 6
    aload_2
    invokevirtual java/lang/String/length()I
    if_icmpge icn_map_notfound
    aload_3
    aload_2
    iload 6
    invokevirtual java/lang/String/charAt(I)C
    invokevirtual java/lang/StringBuilder/append(C)Ljava/lang/StringBuilder;
    pop
    goto icn_map_next
icn_map_notfound:
    aload_3
    iload 5
    invokevirtual java/lang/StringBuilder/append(C)Ljava/lang/StringBuilder;
    pop
icn_map_next:
    iinc 4 1
    goto icn_map_loop
icn_map_done:
    aload_3
    invokevirtual java/lang/StringBuilder/toString()Ljava/lang/String;
    areturn
.end method

.method public static icn_builtin_parse_long(Ljava/lang/String;)J
    .limit stack 4
    .limit locals 4
    .catch java/lang/Exception from icn_plong_L0 to icn_plong_L1 using icn_plong_catch
icn_plong_L0:
    aload_0
    invokevirtual java/lang/String/trim()Ljava/lang/String;
    astore_1
    aload_1
    ldc "r"
    invokevirtual java/lang/String/contains(Ljava/lang/CharSequence;)Z
    ifeq icn_plong_plain
    aload_1
    ldc "r"
    iconst_2
    invokevirtual java/lang/String/split(Ljava/lang/String;I)[Ljava/lang/String;
    astore_2
    aload_2
    iconst_0
    aaload
    invokestatic java/lang/Integer/parseInt(Ljava/lang/String;)I
    istore_3
    aload_2
    iconst_1
    aaload
    iload_3
    invokestatic java/lang/Long/parseLong(Ljava/lang/String;I)J
    goto icn_plong_L1
icn_plong_plain:
    aload_1
    invokestatic java/lang/Long/parseLong(Ljava/lang/String;)J
icn_plong_L1:
    lreturn
icn_plong_catch:
    pop
    ldc2_w -9223372036854775808
    lreturn
.end method

.method public static icn_builtin_numeric(Ljava/lang/String;)J
    .limit stack 2
    .limit locals 2
    aload_0
    invokestatic rung36_jcon_lists/icn_builtin_parse_long(Ljava/lang/String;)J
    lreturn
.end method

.method public static icn_builtin_sort(Ljava/util/ArrayList;)Ljava/util/ArrayList;
    .limit stack 6
    .limit locals 8
    new java/util/ArrayList
    dup
    aload_0
    invokespecial java/util/ArrayList/<init>(Ljava/util/Collection;)V
    astore_1
    iconst_1
    istore_2
icn_sort_outer:
    aload_1
    invokevirtual java/util/ArrayList/size()I
    iload_2
    if_icmple icn_sort_done
    aload_1
    iload_2
    invokevirtual java/util/ArrayList/get(I)Ljava/lang/Object;
    checkcast java/lang/Long
    invokevirtual java/lang/Long/longValue()J
    lstore 4
    iload_2
    iconst_1
    isub
    istore_3
icn_sort_inner:
    iload_3
    iflt icn_sort_insert
    aload_1
    iload_3
    invokevirtual java/util/ArrayList/get(I)Ljava/lang/Object;
    checkcast java/lang/Long
    invokevirtual java/lang/Long/longValue()J
    lload 4
    lcmp
    ifle icn_sort_insert
    aload_1
    iload_3
    iconst_1
    iadd
    aload_1
    iload_3
    invokevirtual java/util/ArrayList/get(I)Ljava/lang/Object;
    invokevirtual java/util/ArrayList/set(ILjava/lang/Object;)Ljava/lang/Object;
    pop
    iinc 3 -1
    goto icn_sort_inner
icn_sort_insert:
    aload_1
    iload_3
    iconst_1
    iadd
    lload 4
    invokestatic java/lang/Long/valueOf(J)Ljava/lang/Long;
    invokevirtual java/util/ArrayList/set(ILjava/lang/Object;)Ljava/lang/Object;
    pop
    iinc 2 1
    goto icn_sort_outer
icn_sort_done:
    aload_1
    areturn
.end method

.method public static icn_builtin_sortf(Ljava/util/ArrayList;I)Ljava/util/ArrayList;
    .limit stack 8
    .limit locals 10
    new java/util/ArrayList
    dup
    aload_0
    invokespecial java/util/ArrayList/<init>(Ljava/util/Collection;)V
    astore_2
    iconst_1
    istore_3
icn_sortf_outer:
    aload_2
    invokevirtual java/util/ArrayList/size()I
    iload_3
    if_icmple icn_sortf_done
    aload_2
    iload_3
    invokevirtual java/util/ArrayList/get(I)Ljava/lang/Object;
    astore 5
    iload_3
    iconst_1
    isub
    istore 4
icn_sortf_inner:
    iload 4
    iflt icn_sortf_insert
    aload_2
    iload 4
    invokevirtual java/util/ArrayList/get(I)Ljava/lang/Object;
    astore 6
    aload 6
    invokevirtual java/lang/Object/getClass()Ljava/lang/Class;
    invokevirtual java/lang/Class/getDeclaredFields()[Ljava/lang/reflect/Field;
    iload_1
    iconst_1
    isub
    aaload
    aload 6
    invokevirtual java/lang/reflect/Field/get(Ljava/lang/Object;)Ljava/lang/Object;
    astore 7
    aload 5
    invokevirtual java/lang/Object/getClass()Ljava/lang/Class;
    invokevirtual java/lang/Class/getDeclaredFields()[Ljava/lang/reflect/Field;
    iload_1
    iconst_1
    isub
    aaload
    aload 5
    invokevirtual java/lang/reflect/Field/get(Ljava/lang/Object;)Ljava/lang/Object;
    astore 8
    aload 7
    checkcast java/lang/Long
    aload 8
    checkcast java/lang/Long
    invokevirtual java/lang/Long/compareTo(Ljava/lang/Long;)I
    ifle icn_sortf_insert
    aload_2
    iload 4
    iconst_1
    iadd
    aload_2
    iload 4
    invokevirtual java/util/ArrayList/get(I)Ljava/lang/Object;
    invokevirtual java/util/ArrayList/set(ILjava/lang/Object;)Ljava/lang/Object;
    pop
    iinc 4 -1
    goto icn_sortf_inner
icn_sortf_insert:
    aload_2
    iload 4
    iconst_1
    iadd
    aload 5
    invokevirtual java/util/ArrayList/set(ILjava/lang/Object;)Ljava/lang/Object;
    pop
    iinc 3 1
    goto icn_sortf_outer
icn_sortf_done:
    aload_2
    areturn
.end method

.method public static icn_builtin_random(J)J
    .limit stack 4
    .limit locals 4
    ; if n <= 0 return 0
    lload_0
    lconst_0
    lcmp
    ifgt icn_rand_pos
    lconst_0
    lreturn
icn_rand_pos:
    invokestatic java/lang/System/nanoTime()J
    lload_0
    lrem
    lconst_1
    ladd
    lreturn
.end method

.method public static icn_main()V
    .limit stack 16
    .limit locals 495
    lconst_0
    lstore 0
    lconst_0
    lstore 2
    lconst_0
    lstore 4
    lconst_0
    lstore 6
    lconst_0
    lstore 8
    lconst_0
    lstore 10
    lconst_0
    lstore 12
    lconst_0
    lstore 14
    lconst_0
    lstore 16
    lconst_0
    lstore 18
    lconst_0
    lstore 20
    lconst_0
    lstore 22
    lconst_0
    lstore 24
    lconst_0
    lstore 26
    lconst_0
    lstore 28
    lconst_0
    lstore 30
    lconst_0
    lstore 32
    lconst_0
    lstore 34
    lconst_0
    lstore 36
    lconst_0
    lstore 38
    lconst_0
    lstore 40
    lconst_0
    lstore 42
    lconst_0
    lstore 44
    lconst_0
    lstore 46
    lconst_0
    lstore 48
    lconst_0
    lstore 50
    lconst_0
    lstore 52
    lconst_0
    lstore 54
    lconst_0
    lstore 56
    lconst_0
    lstore 58
    lconst_0
    lstore 60
    lconst_0
    lstore 62
    iconst_0
    istore 84
    iconst_0
    istore 85
    iconst_0
    istore 86
    iconst_0
    istore 87
    iconst_0
    istore 88
    iconst_0
    istore 89
    iconst_0
    istore 90
    iconst_0
    istore 91
    iconst_0
    istore 92
    iconst_0
    istore 93
    iconst_0
    istore 94
    iconst_0
    istore 95
    iconst_0
    istore 96
    iconst_0
    istore 97
    iconst_0
    istore 98
    iconst_0
    istore 99
    iconst_0
    istore 100
    iconst_0
    istore 101
    iconst_0
    istore 102
    iconst_0
    istore 103
    iconst_0
    istore 104
    iconst_0
    istore 105
    iconst_0
    istore 106
    iconst_0
    istore 107
    iconst_0
    istore 108
    iconst_0
    istore 109
    iconst_0
    istore 110
    aconst_null
    astore 148
    aconst_null
    astore 149
    aconst_null
    astore 150
    aconst_null
    astore 151
    aconst_null
    astore 152
    aconst_null
    astore 153
    aconst_null
    astore 154
    aconst_null
    astore 155
    aconst_null
    astore 156
    aconst_null
    astore 157
    aconst_null
    astore 158
    aconst_null
    astore 159
    aconst_null
    astore 160
    goto icn_332_α
;  VAR
icn_1_α:
    getstatic rung36_jcon_lists/icn_pv_main_z Ljava/lang/String;
    goto icn_0_arg1
icn_1_β:
    goto icn_main_done
icn_0_arg1:
    putstatic rung36_jcon_lists/icn_arg_str_1 Ljava/lang/String;
    lconst_0
    putstatic rung36_jcon_lists/icn_arg_1 J
    goto icn_0_docall
;  STR
icn_2_α:
    ldc "z"
    goto icn_0_arg0
icn_2_β:
    goto icn_main_done
icn_0_arg0:
    putstatic rung36_jcon_lists/icn_arg_str_0 Ljava/lang/String;
    lconst_0
    putstatic rung36_jcon_lists/icn_arg_0 J
    goto icn_1_α
icn_0_α:
    goto icn_2_α
icn_0_β:
    goto icn_1_β
icn_0_docall:
    invokestatic rung36_jcon_lists/icn_limage()V
    getstatic rung36_jcon_lists/icn_failed B
    ifne icn_0_after_call
    getstatic rung36_jcon_lists/icn_retval J
    goto icn_main_s77_sdrain
icn_0_after_call:
    goto icn_main_done
icn_main_s77_sdrain:
    pop2
    goto icn_main_done
;  VAR
icn_4_α:
    getstatic rung36_jcon_lists/icn_pv_main_y J
    goto icn_3_arg1
icn_4_β:
    goto icn_0_α
icn_3_arg1:
    putstatic rung36_jcon_lists/icn_arg_1 J
    goto icn_3_docall
;  STR
icn_5_α:
    ldc "y"
    goto icn_3_arg0
icn_5_β:
    goto icn_0_α
icn_3_arg0:
    putstatic rung36_jcon_lists/icn_arg_str_0 Ljava/lang/String;
    lconst_0
    putstatic rung36_jcon_lists/icn_arg_0 J
    goto icn_4_α
icn_3_α:
    goto icn_5_α
icn_3_β:
    goto icn_4_β
icn_3_docall:
    getstatic rung36_jcon_lists/icn_pv_main_y J
    lstore 152
    invokestatic rung36_jcon_lists/icn_limage()V
    lload 152
    putstatic rung36_jcon_lists/icn_pv_main_y J
    getstatic rung36_jcon_lists/icn_failed B
    ifne icn_3_after_call
    getstatic rung36_jcon_lists/icn_retval J
    goto icn_main_s76_sdrain
icn_3_after_call:
    goto icn_0_α
icn_main_s76_sdrain:
    pop2
    goto icn_0_α
;  VAR
icn_7_α:
    getstatic rung36_jcon_lists/icn_pv_main_x Ljava/util/ArrayList;
    goto icn_6_arg1
icn_7_β:
    goto icn_3_α
icn_6_arg1:
    putstatic rung36_jcon_lists/icn_arg_1 J
    goto icn_6_docall
;  STR
icn_8_α:
    ldc "x"
    goto icn_6_arg0
icn_8_β:
    goto icn_3_α
icn_6_arg0:
    putstatic rung36_jcon_lists/icn_arg_str_0 Ljava/lang/String;
    lconst_0
    putstatic rung36_jcon_lists/icn_arg_0 J
    goto icn_7_α
icn_6_α:
    goto icn_8_α
icn_6_β:
    goto icn_7_β
icn_6_docall:
    getstatic rung36_jcon_lists/icn_pv_main_y J
    lstore 152
    invokestatic rung36_jcon_lists/icn_limage()V
    lload 152
    putstatic rung36_jcon_lists/icn_pv_main_y J
    getstatic rung36_jcon_lists/icn_failed B
    ifne icn_6_after_call
    getstatic rung36_jcon_lists/icn_retval J
    goto icn_main_s75_sdrain
icn_6_after_call:
    goto icn_3_α
icn_main_s75_sdrain:
    pop2
    goto icn_3_α
;  INT
icn_11_α:
    ldc2_w 50
    goto icn_10_rhsok
icn_11_β:
    goto icn_6_α
icn_10_α:
    goto icn_11_α
icn_10_β:
    goto icn_11_β
icn_10_rhsok:
    goto icn_9_gdrain
icn_9_gdrain:
    pop2
icn_9_pump:
    goto icn_10_β
icn_9_α:
    goto icn_10_α
icn_9_β:
    goto icn_6_α
;  INT
icn_14_α:
    ldc2_w 20
    goto icn_13_rhsok
icn_14_β:
    goto icn_9_α
icn_13_α:
    goto icn_14_α
icn_13_β:
    goto icn_14_β
icn_13_rhsok:
    goto icn_12_gdrain
icn_12_gdrain:
    pop2
icn_12_pump:
    goto icn_13_β
icn_12_α:
    goto icn_13_α
icn_12_β:
    goto icn_9_α
;  INT
icn_17_α:
    ldc2_w 10
    goto icn_16_rhsok
icn_17_β:
    goto icn_12_α
icn_16_α:
    goto icn_17_α
icn_16_β:
    goto icn_17_β
icn_16_rhsok:
    goto icn_15_gdrain
icn_15_gdrain:
    pop2
icn_15_pump:
    goto icn_16_β
icn_15_α:
    goto icn_16_α
icn_15_β:
    goto icn_12_α
;  VAR
icn_19_α:
    getstatic rung36_jcon_lists/icn_pv_main_z Ljava/lang/String;
    goto icn_18_arg1
icn_19_β:
    goto icn_15_α
icn_18_arg1:
    putstatic rung36_jcon_lists/icn_arg_str_1 Ljava/lang/String;
    lconst_0
    putstatic rung36_jcon_lists/icn_arg_1 J
    goto icn_18_docall
;  STR
icn_20_α:
    ldc "z"
    goto icn_18_arg0
icn_20_β:
    goto icn_15_α
icn_18_arg0:
    putstatic rung36_jcon_lists/icn_arg_str_0 Ljava/lang/String;
    lconst_0
    putstatic rung36_jcon_lists/icn_arg_0 J
    goto icn_19_α
icn_18_α:
    goto icn_20_α
icn_18_β:
    goto icn_19_β
icn_18_docall:
    getstatic rung36_jcon_lists/icn_pv_main_y J
    lstore 152
    invokestatic rung36_jcon_lists/icn_limage()V
    lload 152
    putstatic rung36_jcon_lists/icn_pv_main_y J
    getstatic rung36_jcon_lists/icn_failed B
    ifne icn_18_after_call
    getstatic rung36_jcon_lists/icn_retval J
    goto icn_main_s71_sdrain
icn_18_after_call:
    goto icn_15_α
icn_main_s71_sdrain:
    pop2
    goto icn_15_α
;  VAR
icn_23_α:
    getstatic rung36_jcon_lists/icn_pv_main_y J
    goto icn_22_rrelay
icn_23_β:
    goto icn_22_lb
;  VAR
icn_24_α:
    getstatic rung36_jcon_lists/icn_pv_main_x Ljava/util/ArrayList;
    goto icn_22_lrelay
icn_24_β:
    goto icn_18_α
icn_22_lrelay:
    putstatic rung36_jcon_lists/icn_22_lc Ljava/lang/String;
    goto icn_22_lstore
icn_22_rrelay:
    putstatic rung36_jcon_lists/icn_22_rc Ljava/lang/String;
    goto icn_22_compute
icn_22_lb:
    goto icn_24_β
icn_22_α:
    iconst_0
    istore 84
    goto icn_24_α
icn_22_β:
    goto icn_23_β
icn_22_lstore:
    iload 84
    ifeq icn_23_α
    goto icn_23_β
icn_22_compute:
    getstatic rung36_jcon_lists/icn_22_lc Ljava/lang/String;
    getstatic rung36_jcon_lists/icn_22_rc Ljava/lang/String;
    invokevirtual java/lang/String/concat(Ljava/lang/String;)Ljava/lang/String;
    goto icn_21_store
icn_21_α:
    goto icn_22_α
icn_21_β:
    goto icn_22_β
icn_21_store:
    putstatic rung36_jcon_lists/icn_pv_main_z Ljava/lang/String;
    getstatic rung36_jcon_lists/icn_pv_main_z Ljava/lang/String;
    goto icn_main_s70_sdrain
icn_main_s70_sdrain:
    pop
    goto icn_18_α
;  VAR
icn_26_α:
    getstatic rung36_jcon_lists/icn_pv_main_y J
    goto icn_25_arg1
icn_26_β:
    goto icn_21_α
icn_25_arg1:
    putstatic rung36_jcon_lists/icn_arg_1 J
    goto icn_25_docall
;  STR
icn_27_α:
    ldc "y"
    goto icn_25_arg0
icn_27_β:
    goto icn_21_α
icn_25_arg0:
    putstatic rung36_jcon_lists/icn_arg_str_0 Ljava/lang/String;
    lconst_0
    putstatic rung36_jcon_lists/icn_arg_0 J
    goto icn_26_α
icn_25_α:
    goto icn_27_α
icn_25_β:
    goto icn_26_β
icn_25_docall:
    getstatic rung36_jcon_lists/icn_pv_main_y J
    lstore 152
    invokestatic rung36_jcon_lists/icn_limage()V
    lload 152
    putstatic rung36_jcon_lists/icn_pv_main_y J
    getstatic rung36_jcon_lists/icn_failed B
    ifne icn_25_after_call
    getstatic rung36_jcon_lists/icn_retval J
    goto icn_main_s69_sdrain
icn_25_after_call:
    goto icn_21_α
icn_main_s69_sdrain:
    pop2
    goto icn_21_α
;  VAR
icn_29_α:
    getstatic rung36_jcon_lists/icn_pv_main_x Ljava/util/ArrayList;
    goto icn_28_arg1
icn_29_β:
    goto icn_25_α
icn_28_arg1:
    putstatic rung36_jcon_lists/icn_arg_1 J
    goto icn_28_docall
;  STR
icn_30_α:
    ldc "x"
    goto icn_28_arg0
icn_30_β:
    goto icn_25_α
icn_28_arg0:
    putstatic rung36_jcon_lists/icn_arg_str_0 Ljava/lang/String;
    lconst_0
    putstatic rung36_jcon_lists/icn_arg_0 J
    goto icn_29_α
icn_28_α:
    goto icn_30_α
icn_28_β:
    goto icn_29_β
icn_28_docall:
    getstatic rung36_jcon_lists/icn_pv_main_y J
    lstore 152
    invokestatic rung36_jcon_lists/icn_limage()V
    lload 152
    putstatic rung36_jcon_lists/icn_pv_main_y J
    getstatic rung36_jcon_lists/icn_failed B
    ifne icn_28_after_call
    getstatic rung36_jcon_lists/icn_retval J
    goto icn_main_s68_sdrain
icn_28_after_call:
    goto icn_25_α
icn_main_s68_sdrain:
    pop2
    goto icn_25_α
;  INT
icn_33_α:
    ldc2_w 20
    goto icn_32_rhsok
icn_33_β:
    goto icn_28_α
icn_32_α:
    goto icn_33_α
icn_32_β:
    goto icn_33_β
icn_32_rhsok:
    goto icn_31_gdrain
icn_31_gdrain:
    pop2
icn_31_pump:
    goto icn_32_β
icn_31_α:
    goto icn_32_α
icn_31_β:
    goto icn_28_α
;  INT
icn_36_α:
    ldc2_w 10
    goto icn_35_rhsok
icn_36_β:
    goto icn_31_α
icn_35_α:
    goto icn_36_α
icn_35_β:
    goto icn_36_β
icn_35_rhsok:
    goto icn_34_gdrain
icn_34_gdrain:
    pop2
icn_34_pump:
    goto icn_35_β
icn_34_α:
    goto icn_35_α
icn_34_β:
    goto icn_31_α
;  VAR
icn_39_α:
    getstatic rung36_jcon_lists/icn_pv_main_x Ljava/util/ArrayList;
    goto icn_38_copy_after
icn_39_β:
    goto icn_34_α
icn_38_α:
    goto icn_39_α
icn_38_β:
    goto icn_39_β
icn_38_copy_after:
    goto icn_37_store
icn_37_α:
    goto icn_38_α
icn_37_β:
    goto icn_38_β
icn_37_store:
    putstatic rung36_jcon_lists/icn_pv_main_y J
    getstatic rung36_jcon_lists/icn_pv_main_y J
    goto icn_main_s65_sdrain
icn_main_s65_sdrain:
    pop2
    goto icn_34_α
icn_40_α:
    getstatic java/lang/System/out Ljava/io/PrintStream;
    ldc ""
    invokevirtual java/io/PrintStream/println(Ljava/lang/String;)V
    goto icn_main_s64_sdrain
icn_40_β:
    goto icn_37_α
icn_main_s64_sdrain:
    pop2
    goto icn_37_α
;  STR
icn_43_α:
    ldc "v. wraparound failed"
    goto icn_42_waft_0
icn_43_β:
    goto icn_40_α
icn_42_α:
    goto icn_43_α
icn_42_β:
    goto icn_43_β
    goto icn_42_wentry
icn_42_waft_0:
    astore 148
    getstatic java/lang/System/out Ljava/io/PrintStream;
    aload 148
    invokevirtual java/io/PrintStream/print(Ljava/lang/String;)V
    getstatic java/lang/System/out Ljava/io/PrintStream;
    ldc ""
    invokevirtual java/io/PrintStream/println(Ljava/lang/String;)V
    aload 148
    goto icn_41_alt_g1
icn_42_wentry:
    goto icn_43_α
;  VAR
icn_46_α:
    getstatic rung36_jcon_lists/icn_pv_main_x Ljava/util/ArrayList;
    goto icn_45_sec_sr
icn_46_β:
    goto icn_42_α
;  INT
icn_47_α:
    ldc2_w 3
    goto icn_45_sec_lor
icn_47_β:
    goto icn_42_α
;  INT
icn_48_α:
    ldc2_w 6
    goto icn_45_sec_hir
icn_48_β:
    goto icn_42_α
icn_45_sec_lor:
    l2i
    istore 85
    iload 85
    ifgt icn_45_sec_lop
    iload 85
    iflt icn_45_sec_lon
icn_45_sec_loz:
    goto icn_42_α
icn_45_sec_lop:
    iload 85
    iconst_1
    isub
    putstatic rung36_jcon_lists/icn_45_sec_lo I
    goto icn_48_α
icn_45_sec_lon:
    getstatic rung36_jcon_lists/icn_45_sec_s Ljava/lang/String;
    invokevirtual java/lang/String/length()I
    iload 85
    iadd
    putstatic rung36_jcon_lists/icn_45_sec_lo I
    goto icn_48_α
icn_45_sec_hir:
    l2i
    istore 86
    iload 86
    ifgt icn_45_sec_hip
    iload 86
    iflt icn_45_sec_hin
icn_45_sec_hiz:
    goto icn_42_α
icn_45_sec_hip:
    iload 86
    iconst_1
    isub
    putstatic rung36_jcon_lists/icn_45_sec_hi I
    goto icn_45_sec_cmp
icn_45_sec_hin:
    getstatic rung36_jcon_lists/icn_45_sec_s Ljava/lang/String;
    invokevirtual java/lang/String/length()I
    iload 86
    iadd
    putstatic rung36_jcon_lists/icn_45_sec_hi I
    goto icn_45_sec_cmp
icn_45_sec_cmp:
    getstatic rung36_jcon_lists/icn_45_sec_lo I
    iflt icn_42_α
    getstatic rung36_jcon_lists/icn_45_sec_hi I
    iflt icn_42_α
    getstatic rung36_jcon_lists/icn_45_sec_s Ljava/lang/String;
    invokevirtual java/lang/String/length()I
    getstatic rung36_jcon_lists/icn_45_sec_lo I
    if_icmplt icn_42_α
    getstatic rung36_jcon_lists/icn_45_sec_s Ljava/lang/String;
    invokevirtual java/lang/String/length()I
    istore 87
    getstatic rung36_jcon_lists/icn_45_sec_hi I
    iload 87
    if_icmple icn_45_sec_hiok
    iload 87
    putstatic rung36_jcon_lists/icn_45_sec_hi I
icn_45_sec_hiok:
    getstatic rung36_jcon_lists/icn_45_sec_s Ljava/lang/String;
    getstatic rung36_jcon_lists/icn_45_sec_lo I
    getstatic rung36_jcon_lists/icn_45_sec_hi I
    invokevirtual java/lang/String/substring(II)Ljava/lang/String;
    goto icn_44_arg1
icn_45_α:
    goto icn_46_α
icn_45_sec_sr:
    putstatic rung36_jcon_lists/icn_45_sec_s Ljava/lang/String;
    goto icn_47_α
icn_45_β:
    goto icn_42_α
icn_44_arg1:
    putstatic rung36_jcon_lists/icn_arg_str_1 Ljava/lang/String;
    lconst_0
    putstatic rung36_jcon_lists/icn_arg_1 J
    goto icn_44_docall
;  STR
icn_49_α:
    ldc "v"
    goto icn_44_arg0
icn_49_β:
    goto icn_42_α
icn_44_arg0:
    putstatic rung36_jcon_lists/icn_arg_str_0 Ljava/lang/String;
    lconst_0
    putstatic rung36_jcon_lists/icn_arg_0 J
    goto icn_45_α
icn_44_α:
    goto icn_49_α
icn_44_β:
    goto icn_45_β
icn_44_docall:
    getstatic rung36_jcon_lists/icn_pv_main_y J
    lstore 153
    invokestatic rung36_jcon_lists/icn_limage()V
    lload 153
    putstatic rung36_jcon_lists/icn_pv_main_y J
    getstatic rung36_jcon_lists/icn_failed B
    ifne icn_44_after_call
    getstatic rung36_jcon_lists/icn_retval J
    goto icn_41_alt_g0
icn_44_after_call:
    goto icn_42_α
icn_41_alt_g0:
    putstatic rung36_jcon_lists/icn_41_alt_val J
    sipush 1
    putstatic rung36_jcon_lists/icn_41_alt_gate I
    getstatic rung36_jcon_lists/icn_41_alt_val J
    goto icn_main_s63_sdrain
icn_41_alt_g1:
    pop
    lconst_0
    putstatic rung36_jcon_lists/icn_41_alt_val J
    sipush 2
    putstatic rung36_jcon_lists/icn_41_alt_gate I
    getstatic rung36_jcon_lists/icn_41_alt_val J
    goto icn_main_s63_sdrain
icn_41_α:
    iconst_0
    putstatic rung36_jcon_lists/icn_41_alt_gate I
    goto icn_44_α
icn_41_β:
    getstatic rung36_jcon_lists/icn_41_alt_gate I
    tableswitch 1 2
        icn_44_β
        icn_42_β
        default: icn_40_α
icn_main_s63_sdrain:
    pop2
    goto icn_40_α
;  STR
icn_52_α:
    ldc "u. wraparound failed"
    goto icn_51_waft_0
icn_52_β:
    goto icn_41_α
icn_51_α:
    goto icn_52_α
icn_51_β:
    goto icn_52_β
    goto icn_51_wentry
icn_51_waft_0:
    astore 149
    getstatic java/lang/System/out Ljava/io/PrintStream;
    aload 149
    invokevirtual java/io/PrintStream/print(Ljava/lang/String;)V
    getstatic java/lang/System/out Ljava/io/PrintStream;
    ldc ""
    invokevirtual java/io/PrintStream/println(Ljava/lang/String;)V
    aload 149
    goto icn_50_alt_g1
icn_51_wentry:
    goto icn_52_α
;  VAR
icn_55_α:
    getstatic rung36_jcon_lists/icn_pv_main_x Ljava/util/ArrayList;
    goto icn_54_sec_sr
icn_55_β:
    goto icn_51_α
;  INT
icn_57_α:
    ldc2_w 3
    goto icn_56_neg
icn_57_β:
    goto icn_51_α
;  NEG
icn_56_α:
    goto icn_57_α
icn_56_β:
    goto icn_57_β
icn_56_neg:
    lneg
    goto icn_54_sec_lor
;  INT
icn_58_α:
    ldc2_w 6
    goto icn_54_sec_hir
icn_58_β:
    goto icn_51_α
icn_54_sec_lor:
    l2i
    istore 88
    iload 88
    ifgt icn_54_sec_lop
    iload 88
    iflt icn_54_sec_lon
icn_54_sec_loz:
    goto icn_51_α
icn_54_sec_lop:
    iload 88
    iconst_1
    isub
    putstatic rung36_jcon_lists/icn_54_sec_lo I
    goto icn_58_α
icn_54_sec_lon:
    getstatic rung36_jcon_lists/icn_54_sec_s Ljava/lang/String;
    invokevirtual java/lang/String/length()I
    iload 88
    iadd
    putstatic rung36_jcon_lists/icn_54_sec_lo I
    goto icn_58_α
icn_54_sec_hir:
    l2i
    istore 89
    iload 89
    ifgt icn_54_sec_hip
    iload 89
    iflt icn_54_sec_hin
icn_54_sec_hiz:
    goto icn_51_α
icn_54_sec_hip:
    iload 89
    iconst_1
    isub
    putstatic rung36_jcon_lists/icn_54_sec_hi I
    goto icn_54_sec_cmp
icn_54_sec_hin:
    getstatic rung36_jcon_lists/icn_54_sec_s Ljava/lang/String;
    invokevirtual java/lang/String/length()I
    iload 89
    iadd
    putstatic rung36_jcon_lists/icn_54_sec_hi I
    goto icn_54_sec_cmp
icn_54_sec_cmp:
    getstatic rung36_jcon_lists/icn_54_sec_lo I
    iflt icn_51_α
    getstatic rung36_jcon_lists/icn_54_sec_hi I
    iflt icn_51_α
    getstatic rung36_jcon_lists/icn_54_sec_s Ljava/lang/String;
    invokevirtual java/lang/String/length()I
    getstatic rung36_jcon_lists/icn_54_sec_lo I
    if_icmplt icn_51_α
    getstatic rung36_jcon_lists/icn_54_sec_s Ljava/lang/String;
    invokevirtual java/lang/String/length()I
    istore 90
    getstatic rung36_jcon_lists/icn_54_sec_hi I
    iload 90
    if_icmple icn_54_sec_hiok
    iload 90
    putstatic rung36_jcon_lists/icn_54_sec_hi I
icn_54_sec_hiok:
    getstatic rung36_jcon_lists/icn_54_sec_s Ljava/lang/String;
    getstatic rung36_jcon_lists/icn_54_sec_lo I
    getstatic rung36_jcon_lists/icn_54_sec_hi I
    invokevirtual java/lang/String/substring(II)Ljava/lang/String;
    goto icn_53_arg1
icn_54_α:
    goto icn_55_α
icn_54_sec_sr:
    putstatic rung36_jcon_lists/icn_54_sec_s Ljava/lang/String;
    goto icn_56_α
icn_54_β:
    goto icn_51_α
icn_53_arg1:
    putstatic rung36_jcon_lists/icn_arg_str_1 Ljava/lang/String;
    lconst_0
    putstatic rung36_jcon_lists/icn_arg_1 J
    goto icn_53_docall
;  STR
icn_59_α:
    ldc "u"
    goto icn_53_arg0
icn_59_β:
    goto icn_51_α
icn_53_arg0:
    putstatic rung36_jcon_lists/icn_arg_str_0 Ljava/lang/String;
    lconst_0
    putstatic rung36_jcon_lists/icn_arg_0 J
    goto icn_54_α
icn_53_α:
    goto icn_59_α
icn_53_β:
    goto icn_54_β
icn_53_docall:
    getstatic rung36_jcon_lists/icn_pv_main_y J
    lstore 154
    getstatic rung36_jcon_lists/icn_41_alt_val J
    lstore 156
    invokestatic rung36_jcon_lists/icn_limage()V
    lload 154
    putstatic rung36_jcon_lists/icn_pv_main_y J
    lload 156
    putstatic rung36_jcon_lists/icn_41_alt_val J
    getstatic rung36_jcon_lists/icn_failed B
    ifne icn_53_after_call
    getstatic rung36_jcon_lists/icn_retval J
    goto icn_50_alt_g0
icn_53_after_call:
    goto icn_51_α
icn_50_alt_g0:
    putstatic rung36_jcon_lists/icn_50_alt_val J
    sipush 1
    putstatic rung36_jcon_lists/icn_50_alt_gate I
    getstatic rung36_jcon_lists/icn_50_alt_val J
    goto icn_main_s62_sdrain
icn_50_alt_g1:
    pop
    lconst_0
    putstatic rung36_jcon_lists/icn_50_alt_val J
    sipush 2
    putstatic rung36_jcon_lists/icn_50_alt_gate I
    getstatic rung36_jcon_lists/icn_50_alt_val J
    goto icn_main_s62_sdrain
icn_50_α:
    iconst_0
    putstatic rung36_jcon_lists/icn_50_alt_gate I
    goto icn_53_α
icn_50_β:
    getstatic rung36_jcon_lists/icn_50_alt_gate I
    tableswitch 1 2
        icn_53_β
        icn_51_β
        default: icn_41_α
icn_main_s62_sdrain:
    pop2
    goto icn_41_α
;  VAR
icn_62_α:
    getstatic rung36_jcon_lists/icn_pv_main_x Ljava/util/ArrayList;
    goto icn_61_sec_sr
icn_62_β:
    goto icn_50_α
;  INT
icn_64_α:
    ldc2_w 5
    goto icn_63_neg
icn_64_β:
    goto icn_50_α
;  NEG
icn_63_α:
    goto icn_64_α
icn_63_β:
    goto icn_64_β
icn_63_neg:
    lneg
    goto icn_61_sec_lor
;  INT
icn_66_α:
    ldc2_w 1
    goto icn_65_neg
icn_66_β:
    goto icn_50_α
;  NEG
icn_65_α:
    goto icn_66_α
icn_65_β:
    goto icn_66_β
icn_65_neg:
    lneg
    goto icn_61_sec_hir
icn_61_sec_lor:
    l2i
    istore 91
    iload 91
    ifgt icn_61_sec_lop
    iload 91
    iflt icn_61_sec_lon
icn_61_sec_loz:
    goto icn_50_α
icn_61_sec_lop:
    iload 91
    iconst_1
    isub
    putstatic rung36_jcon_lists/icn_61_sec_lo I
    goto icn_65_α
icn_61_sec_lon:
    getstatic rung36_jcon_lists/icn_61_sec_s Ljava/lang/String;
    invokevirtual java/lang/String/length()I
    iload 91
    iadd
    putstatic rung36_jcon_lists/icn_61_sec_lo I
    goto icn_65_α
icn_61_sec_hir:
    l2i
    istore 92
    iload 92
    ifgt icn_61_sec_hip
    iload 92
    iflt icn_61_sec_hin
icn_61_sec_hiz:
    goto icn_50_α
icn_61_sec_hip:
    iload 92
    iconst_1
    isub
    putstatic rung36_jcon_lists/icn_61_sec_hi I
    goto icn_61_sec_cmp
icn_61_sec_hin:
    getstatic rung36_jcon_lists/icn_61_sec_s Ljava/lang/String;
    invokevirtual java/lang/String/length()I
    iload 92
    iadd
    putstatic rung36_jcon_lists/icn_61_sec_hi I
    goto icn_61_sec_cmp
icn_61_sec_cmp:
    getstatic rung36_jcon_lists/icn_61_sec_lo I
    iflt icn_50_α
    getstatic rung36_jcon_lists/icn_61_sec_hi I
    iflt icn_50_α
    getstatic rung36_jcon_lists/icn_61_sec_s Ljava/lang/String;
    invokevirtual java/lang/String/length()I
    getstatic rung36_jcon_lists/icn_61_sec_lo I
    if_icmplt icn_50_α
    getstatic rung36_jcon_lists/icn_61_sec_s Ljava/lang/String;
    invokevirtual java/lang/String/length()I
    istore 93
    getstatic rung36_jcon_lists/icn_61_sec_hi I
    iload 93
    if_icmple icn_61_sec_hiok
    iload 93
    putstatic rung36_jcon_lists/icn_61_sec_hi I
icn_61_sec_hiok:
    getstatic rung36_jcon_lists/icn_61_sec_s Ljava/lang/String;
    getstatic rung36_jcon_lists/icn_61_sec_lo I
    getstatic rung36_jcon_lists/icn_61_sec_hi I
    invokevirtual java/lang/String/substring(II)Ljava/lang/String;
    goto icn_60_arg1
icn_61_α:
    goto icn_62_α
icn_61_sec_sr:
    putstatic rung36_jcon_lists/icn_61_sec_s Ljava/lang/String;
    goto icn_63_α
icn_61_β:
    goto icn_50_α
icn_60_arg1:
    putstatic rung36_jcon_lists/icn_arg_str_1 Ljava/lang/String;
    lconst_0
    putstatic rung36_jcon_lists/icn_arg_1 J
    goto icn_60_docall
;  STR
icn_67_α:
    ldc "t"
    goto icn_60_arg0
icn_67_β:
    goto icn_50_α
icn_60_arg0:
    putstatic rung36_jcon_lists/icn_arg_str_0 Ljava/lang/String;
    lconst_0
    putstatic rung36_jcon_lists/icn_arg_0 J
    goto icn_61_α
icn_60_α:
    goto icn_67_α
icn_60_β:
    goto icn_61_β
icn_60_docall:
    getstatic rung36_jcon_lists/icn_pv_main_y J
    lstore 154
    getstatic rung36_jcon_lists/icn_41_alt_val J
    lstore 156
    getstatic rung36_jcon_lists/icn_50_alt_val J
    lstore 158
    invokestatic rung36_jcon_lists/icn_limage()V
    lload 154
    putstatic rung36_jcon_lists/icn_pv_main_y J
    lload 156
    putstatic rung36_jcon_lists/icn_41_alt_val J
    lload 158
    putstatic rung36_jcon_lists/icn_50_alt_val J
    getstatic rung36_jcon_lists/icn_failed B
    ifne icn_60_after_call
    getstatic rung36_jcon_lists/icn_retval J
    goto icn_main_s61_sdrain
icn_60_after_call:
    goto icn_50_α
icn_main_s61_sdrain:
    pop2
    goto icn_50_α
;  VAR
icn_70_α:
    getstatic rung36_jcon_lists/icn_pv_main_x Ljava/util/ArrayList;
    goto icn_69_sec_sr
icn_70_β:
    goto icn_60_α
;  INT
icn_72_α:
    ldc2_w 3
    goto icn_71_neg
icn_72_β:
    goto icn_60_α
;  NEG
icn_71_α:
    goto icn_72_α
icn_71_β:
    goto icn_72_β
icn_71_neg:
    lneg
    goto icn_69_sec_lor
;  INT
icn_73_α:
    ldc2_w 5
    goto icn_69_sec_hir
icn_73_β:
    goto icn_60_α
icn_69_sec_lor:
    l2i
    istore 94
    iload 94
    ifgt icn_69_sec_lop
    iload 94
    iflt icn_69_sec_lon
icn_69_sec_loz:
    goto icn_60_α
icn_69_sec_lop:
    iload 94
    iconst_1
    isub
    putstatic rung36_jcon_lists/icn_69_sec_lo I
    goto icn_73_α
icn_69_sec_lon:
    getstatic rung36_jcon_lists/icn_69_sec_s Ljava/lang/String;
    invokevirtual java/lang/String/length()I
    iload 94
    iadd
    putstatic rung36_jcon_lists/icn_69_sec_lo I
    goto icn_73_α
icn_69_sec_hir:
    l2i
    istore 95
    iload 95
    ifgt icn_69_sec_hip
    iload 95
    iflt icn_69_sec_hin
icn_69_sec_hiz:
    goto icn_60_α
icn_69_sec_hip:
    iload 95
    iconst_1
    isub
    putstatic rung36_jcon_lists/icn_69_sec_hi I
    goto icn_69_sec_cmp
icn_69_sec_hin:
    getstatic rung36_jcon_lists/icn_69_sec_s Ljava/lang/String;
    invokevirtual java/lang/String/length()I
    iload 95
    iadd
    putstatic rung36_jcon_lists/icn_69_sec_hi I
    goto icn_69_sec_cmp
icn_69_sec_cmp:
    getstatic rung36_jcon_lists/icn_69_sec_lo I
    iflt icn_60_α
    getstatic rung36_jcon_lists/icn_69_sec_hi I
    iflt icn_60_α
    getstatic rung36_jcon_lists/icn_69_sec_s Ljava/lang/String;
    invokevirtual java/lang/String/length()I
    getstatic rung36_jcon_lists/icn_69_sec_lo I
    if_icmplt icn_60_α
    getstatic rung36_jcon_lists/icn_69_sec_s Ljava/lang/String;
    invokevirtual java/lang/String/length()I
    istore 96
    getstatic rung36_jcon_lists/icn_69_sec_hi I
    iload 96
    if_icmple icn_69_sec_hiok
    iload 96
    putstatic rung36_jcon_lists/icn_69_sec_hi I
icn_69_sec_hiok:
    getstatic rung36_jcon_lists/icn_69_sec_s Ljava/lang/String;
    getstatic rung36_jcon_lists/icn_69_sec_lo I
    getstatic rung36_jcon_lists/icn_69_sec_hi I
    invokevirtual java/lang/String/substring(II)Ljava/lang/String;
    goto icn_68_arg1
icn_69_α:
    goto icn_70_α
icn_69_sec_sr:
    putstatic rung36_jcon_lists/icn_69_sec_s Ljava/lang/String;
    goto icn_71_α
icn_69_β:
    goto icn_60_α
icn_68_arg1:
    putstatic rung36_jcon_lists/icn_arg_str_1 Ljava/lang/String;
    lconst_0
    putstatic rung36_jcon_lists/icn_arg_1 J
    goto icn_68_docall
;  STR
icn_74_α:
    ldc "s"
    goto icn_68_arg0
icn_74_β:
    goto icn_60_α
icn_68_arg0:
    putstatic rung36_jcon_lists/icn_arg_str_0 Ljava/lang/String;
    lconst_0
    putstatic rung36_jcon_lists/icn_arg_0 J
    goto icn_69_α
icn_68_α:
    goto icn_74_α
icn_68_β:
    goto icn_69_β
icn_68_docall:
    getstatic rung36_jcon_lists/icn_pv_main_y J
    lstore 154
    getstatic rung36_jcon_lists/icn_41_alt_val J
    lstore 156
    getstatic rung36_jcon_lists/icn_50_alt_val J
    lstore 158
    invokestatic rung36_jcon_lists/icn_limage()V
    lload 154
    putstatic rung36_jcon_lists/icn_pv_main_y J
    lload 156
    putstatic rung36_jcon_lists/icn_41_alt_val J
    lload 158
    putstatic rung36_jcon_lists/icn_50_alt_val J
    getstatic rung36_jcon_lists/icn_failed B
    ifne icn_68_after_call
    getstatic rung36_jcon_lists/icn_retval J
    goto icn_main_s60_sdrain
icn_68_after_call:
    goto icn_60_α
icn_main_s60_sdrain:
    pop2
    goto icn_60_α
;  VAR
icn_77_α:
    getstatic rung36_jcon_lists/icn_pv_main_x Ljava/util/ArrayList;
    goto icn_76_sec_sr
icn_77_β:
    goto icn_68_α
;  INT
icn_78_α:
    ldc2_w 2
    goto icn_76_sec_lor
icn_78_β:
    goto icn_68_α
;  INT
icn_79_α:
    ldc2_w 5
    goto icn_76_sec_hir
icn_79_β:
    goto icn_68_α
icn_76_sec_lor:
    l2i
    istore 97
    iload 97
    ifgt icn_76_sec_lop
    iload 97
    iflt icn_76_sec_lon
icn_76_sec_loz:
    goto icn_68_α
icn_76_sec_lop:
    iload 97
    iconst_1
    isub
    putstatic rung36_jcon_lists/icn_76_sec_lo I
    goto icn_79_α
icn_76_sec_lon:
    getstatic rung36_jcon_lists/icn_76_sec_s Ljava/lang/String;
    invokevirtual java/lang/String/length()I
    iload 97
    iadd
    putstatic rung36_jcon_lists/icn_76_sec_lo I
    goto icn_79_α
icn_76_sec_hir:
    l2i
    istore 98
    iload 98
    ifgt icn_76_sec_hip
    iload 98
    iflt icn_76_sec_hin
icn_76_sec_hiz:
    goto icn_68_α
icn_76_sec_hip:
    iload 98
    iconst_1
    isub
    putstatic rung36_jcon_lists/icn_76_sec_hi I
    goto icn_76_sec_cmp
icn_76_sec_hin:
    getstatic rung36_jcon_lists/icn_76_sec_s Ljava/lang/String;
    invokevirtual java/lang/String/length()I
    iload 98
    iadd
    putstatic rung36_jcon_lists/icn_76_sec_hi I
    goto icn_76_sec_cmp
icn_76_sec_cmp:
    getstatic rung36_jcon_lists/icn_76_sec_lo I
    iflt icn_68_α
    getstatic rung36_jcon_lists/icn_76_sec_hi I
    iflt icn_68_α
    getstatic rung36_jcon_lists/icn_76_sec_s Ljava/lang/String;
    invokevirtual java/lang/String/length()I
    getstatic rung36_jcon_lists/icn_76_sec_lo I
    if_icmplt icn_68_α
    getstatic rung36_jcon_lists/icn_76_sec_s Ljava/lang/String;
    invokevirtual java/lang/String/length()I
    istore 99
    getstatic rung36_jcon_lists/icn_76_sec_hi I
    iload 99
    if_icmple icn_76_sec_hiok
    iload 99
    putstatic rung36_jcon_lists/icn_76_sec_hi I
icn_76_sec_hiok:
    getstatic rung36_jcon_lists/icn_76_sec_s Ljava/lang/String;
    getstatic rung36_jcon_lists/icn_76_sec_lo I
    getstatic rung36_jcon_lists/icn_76_sec_hi I
    invokevirtual java/lang/String/substring(II)Ljava/lang/String;
    goto icn_75_arg1
icn_76_α:
    goto icn_77_α
icn_76_sec_sr:
    putstatic rung36_jcon_lists/icn_76_sec_s Ljava/lang/String;
    goto icn_78_α
icn_76_β:
    goto icn_68_α
icn_75_arg1:
    putstatic rung36_jcon_lists/icn_arg_str_1 Ljava/lang/String;
    lconst_0
    putstatic rung36_jcon_lists/icn_arg_1 J
    goto icn_75_docall
;  STR
icn_80_α:
    ldc "r"
    goto icn_75_arg0
icn_80_β:
    goto icn_68_α
icn_75_arg0:
    putstatic rung36_jcon_lists/icn_arg_str_0 Ljava/lang/String;
    lconst_0
    putstatic rung36_jcon_lists/icn_arg_0 J
    goto icn_76_α
icn_75_α:
    goto icn_80_α
icn_75_β:
    goto icn_76_β
icn_75_docall:
    getstatic rung36_jcon_lists/icn_pv_main_y J
    lstore 154
    getstatic rung36_jcon_lists/icn_41_alt_val J
    lstore 156
    getstatic rung36_jcon_lists/icn_50_alt_val J
    lstore 158
    invokestatic rung36_jcon_lists/icn_limage()V
    lload 154
    putstatic rung36_jcon_lists/icn_pv_main_y J
    lload 156
    putstatic rung36_jcon_lists/icn_41_alt_val J
    lload 158
    putstatic rung36_jcon_lists/icn_50_alt_val J
    getstatic rung36_jcon_lists/icn_failed B
    ifne icn_75_after_call
    getstatic rung36_jcon_lists/icn_retval J
    goto icn_main_s59_sdrain
icn_75_after_call:
    goto icn_68_α
icn_main_s59_sdrain:
    pop2
    goto icn_68_α
;  VAR
icn_83_α:
    getstatic rung36_jcon_lists/icn_pv_main_x Ljava/util/ArrayList;
    goto icn_82_sec_sr
icn_83_β:
    goto icn_75_α
;  INT
icn_84_α:
    ldc2_w 1
    goto icn_82_sec_lor
icn_84_β:
    goto icn_75_α
;  INT
icn_85_α:
    ldc2_w 0
    goto icn_82_sec_hir
icn_85_β:
    goto icn_75_α
icn_82_sec_lor:
    l2i
    istore 100
    iload 100
    ifgt icn_82_sec_lop
    iload 100
    iflt icn_82_sec_lon
icn_82_sec_loz:
    goto icn_75_α
icn_82_sec_lop:
    iload 100
    iconst_1
    isub
    putstatic rung36_jcon_lists/icn_82_sec_lo I
    goto icn_85_α
icn_82_sec_lon:
    getstatic rung36_jcon_lists/icn_82_sec_s Ljava/lang/String;
    invokevirtual java/lang/String/length()I
    iload 100
    iadd
    putstatic rung36_jcon_lists/icn_82_sec_lo I
    goto icn_85_α
icn_82_sec_hir:
    l2i
    istore 101
    iload 101
    ifgt icn_82_sec_hip
    iload 101
    iflt icn_82_sec_hin
icn_82_sec_hiz:
    goto icn_75_α
icn_82_sec_hip:
    iload 101
    iconst_1
    isub
    putstatic rung36_jcon_lists/icn_82_sec_hi I
    goto icn_82_sec_cmp
icn_82_sec_hin:
    getstatic rung36_jcon_lists/icn_82_sec_s Ljava/lang/String;
    invokevirtual java/lang/String/length()I
    iload 101
    iadd
    putstatic rung36_jcon_lists/icn_82_sec_hi I
    goto icn_82_sec_cmp
icn_82_sec_cmp:
    getstatic rung36_jcon_lists/icn_82_sec_lo I
    iflt icn_75_α
    getstatic rung36_jcon_lists/icn_82_sec_hi I
    iflt icn_75_α
    getstatic rung36_jcon_lists/icn_82_sec_s Ljava/lang/String;
    invokevirtual java/lang/String/length()I
    getstatic rung36_jcon_lists/icn_82_sec_lo I
    if_icmplt icn_75_α
    getstatic rung36_jcon_lists/icn_82_sec_s Ljava/lang/String;
    invokevirtual java/lang/String/length()I
    istore 102
    getstatic rung36_jcon_lists/icn_82_sec_hi I
    iload 102
    if_icmple icn_82_sec_hiok
    iload 102
    putstatic rung36_jcon_lists/icn_82_sec_hi I
icn_82_sec_hiok:
    getstatic rung36_jcon_lists/icn_82_sec_s Ljava/lang/String;
    getstatic rung36_jcon_lists/icn_82_sec_lo I
    getstatic rung36_jcon_lists/icn_82_sec_hi I
    invokevirtual java/lang/String/substring(II)Ljava/lang/String;
    goto icn_81_arg1
icn_82_α:
    goto icn_83_α
icn_82_sec_sr:
    putstatic rung36_jcon_lists/icn_82_sec_s Ljava/lang/String;
    goto icn_84_α
icn_82_β:
    goto icn_75_α
icn_81_arg1:
    putstatic rung36_jcon_lists/icn_arg_str_1 Ljava/lang/String;
    lconst_0
    putstatic rung36_jcon_lists/icn_arg_1 J
    goto icn_81_docall
;  STR
icn_86_α:
    ldc "q"
    goto icn_81_arg0
icn_86_β:
    goto icn_75_α
icn_81_arg0:
    putstatic rung36_jcon_lists/icn_arg_str_0 Ljava/lang/String;
    lconst_0
    putstatic rung36_jcon_lists/icn_arg_0 J
    goto icn_82_α
icn_81_α:
    goto icn_86_α
icn_81_β:
    goto icn_82_β
icn_81_docall:
    getstatic rung36_jcon_lists/icn_pv_main_y J
    lstore 154
    getstatic rung36_jcon_lists/icn_41_alt_val J
    lstore 156
    getstatic rung36_jcon_lists/icn_50_alt_val J
    lstore 158
    invokestatic rung36_jcon_lists/icn_limage()V
    lload 154
    putstatic rung36_jcon_lists/icn_pv_main_y J
    lload 156
    putstatic rung36_jcon_lists/icn_41_alt_val J
    lload 158
    putstatic rung36_jcon_lists/icn_50_alt_val J
    getstatic rung36_jcon_lists/icn_failed B
    ifne icn_81_after_call
    getstatic rung36_jcon_lists/icn_retval J
    goto icn_main_s58_sdrain
icn_81_after_call:
    goto icn_75_α
icn_main_s58_sdrain:
    pop2
    goto icn_75_α
;  VAR
icn_88_α:
    getstatic rung36_jcon_lists/icn_pv_main_x Ljava/util/ArrayList;
    goto icn_87_arg1
icn_88_β:
    goto icn_81_α
icn_87_arg1:
    putstatic rung36_jcon_lists/icn_arg_1 J
    goto icn_87_docall
;  STR
icn_89_α:
    ldc "p"
    goto icn_87_arg0
icn_89_β:
    goto icn_81_α
icn_87_arg0:
    putstatic rung36_jcon_lists/icn_arg_str_0 Ljava/lang/String;
    lconst_0
    putstatic rung36_jcon_lists/icn_arg_0 J
    goto icn_88_α
icn_87_α:
    goto icn_89_α
icn_87_β:
    goto icn_88_β
icn_87_docall:
    getstatic rung36_jcon_lists/icn_pv_main_y J
    lstore 154
    getstatic rung36_jcon_lists/icn_41_alt_val J
    lstore 156
    getstatic rung36_jcon_lists/icn_50_alt_val J
    lstore 158
    invokestatic rung36_jcon_lists/icn_limage()V
    lload 154
    putstatic rung36_jcon_lists/icn_pv_main_y J
    lload 156
    putstatic rung36_jcon_lists/icn_41_alt_val J
    lload 158
    putstatic rung36_jcon_lists/icn_50_alt_val J
    getstatic rung36_jcon_lists/icn_failed B
    ifne icn_87_after_call
    getstatic rung36_jcon_lists/icn_retval J
    goto icn_main_s57_sdrain
icn_87_after_call:
    goto icn_81_α
icn_main_s57_sdrain:
    pop2
    goto icn_81_α
icn_91_α:
    new java/util/ArrayList
    dup
    invokespecial java/util/ArrayList/<init>()V
    putstatic rung36_jcon_lists/icn_91_mklist Ljava/util/ArrayList;
;  INT
icn_92_α:
    ldc2_w 1
    goto icn_91_mke_0
icn_92_β:
    goto icn_87_α
    goto icn_92_α
icn_91_mke_0:
    invokestatic java/lang/Long/valueOf(J)Ljava/lang/Long;
    putstatic rung36_jcon_lists/icn_91_elem_0 Ljava/lang/Object;
    getstatic rung36_jcon_lists/icn_91_mklist Ljava/util/ArrayList;
    getstatic rung36_jcon_lists/icn_91_elem_0 Ljava/lang/Object;
    invokevirtual java/util/ArrayList/add(Ljava/lang/Object;)Z
    pop
;  INT
icn_93_α:
    ldc2_w 2
    goto icn_91_mke_1
icn_93_β:
    goto icn_87_α
    goto icn_93_α
icn_91_mke_1:
    invokestatic java/lang/Long/valueOf(J)Ljava/lang/Long;
    putstatic rung36_jcon_lists/icn_91_elem_1 Ljava/lang/Object;
    getstatic rung36_jcon_lists/icn_91_mklist Ljava/util/ArrayList;
    getstatic rung36_jcon_lists/icn_91_elem_1 Ljava/lang/Object;
    invokevirtual java/util/ArrayList/add(Ljava/lang/Object;)Z
    pop
;  INT
icn_94_α:
    ldc2_w 3
    goto icn_91_mke_2
icn_94_β:
    goto icn_87_α
    goto icn_94_α
icn_91_mke_2:
    invokestatic java/lang/Long/valueOf(J)Ljava/lang/Long;
    putstatic rung36_jcon_lists/icn_91_elem_2 Ljava/lang/Object;
    getstatic rung36_jcon_lists/icn_91_mklist Ljava/util/ArrayList;
    getstatic rung36_jcon_lists/icn_91_elem_2 Ljava/lang/Object;
    invokevirtual java/util/ArrayList/add(Ljava/lang/Object;)Z
    pop
;  INT
icn_95_α:
    ldc2_w 4
    goto icn_91_mke_3
icn_95_β:
    goto icn_87_α
    goto icn_95_α
icn_91_mke_3:
    invokestatic java/lang/Long/valueOf(J)Ljava/lang/Long;
    putstatic rung36_jcon_lists/icn_91_elem_3 Ljava/lang/Object;
    getstatic rung36_jcon_lists/icn_91_mklist Ljava/util/ArrayList;
    getstatic rung36_jcon_lists/icn_91_elem_3 Ljava/lang/Object;
    invokevirtual java/util/ArrayList/add(Ljava/lang/Object;)Z
    pop
;  INT
icn_96_α:
    ldc2_w 5
    goto icn_91_mke_4
icn_96_β:
    goto icn_87_α
    goto icn_96_α
icn_91_mke_4:
    invokestatic java/lang/Long/valueOf(J)Ljava/lang/Long;
    putstatic rung36_jcon_lists/icn_91_elem_4 Ljava/lang/Object;
    getstatic rung36_jcon_lists/icn_91_mklist Ljava/util/ArrayList;
    getstatic rung36_jcon_lists/icn_91_elem_4 Ljava/lang/Object;
    invokevirtual java/util/ArrayList/add(Ljava/lang/Object;)Z
    pop
;  INT
icn_97_α:
    ldc2_w 6
    goto icn_91_mke_5
icn_97_β:
    goto icn_87_α
    goto icn_97_α
icn_91_mke_5:
    invokestatic java/lang/Long/valueOf(J)Ljava/lang/Long;
    putstatic rung36_jcon_lists/icn_91_elem_5 Ljava/lang/Object;
    getstatic rung36_jcon_lists/icn_91_mklist Ljava/util/ArrayList;
    getstatic rung36_jcon_lists/icn_91_elem_5 Ljava/lang/Object;
    invokevirtual java/util/ArrayList/add(Ljava/lang/Object;)Z
    pop
;  INT
icn_98_α:
    ldc2_w 7
    goto icn_91_mke_6
icn_98_β:
    goto icn_87_α
    goto icn_98_α
icn_91_mke_6:
    invokestatic java/lang/Long/valueOf(J)Ljava/lang/Long;
    putstatic rung36_jcon_lists/icn_91_elem_6 Ljava/lang/Object;
    getstatic rung36_jcon_lists/icn_91_mklist Ljava/util/ArrayList;
    getstatic rung36_jcon_lists/icn_91_elem_6 Ljava/lang/Object;
    invokevirtual java/util/ArrayList/add(Ljava/lang/Object;)Z
    pop
;  INT
icn_99_α:
    ldc2_w 8
    goto icn_91_mke_7
icn_99_β:
    goto icn_87_α
    goto icn_99_α
icn_91_mke_7:
    invokestatic java/lang/Long/valueOf(J)Ljava/lang/Long;
    putstatic rung36_jcon_lists/icn_91_elem_7 Ljava/lang/Object;
    getstatic rung36_jcon_lists/icn_91_mklist Ljava/util/ArrayList;
    getstatic rung36_jcon_lists/icn_91_elem_7 Ljava/lang/Object;
    invokevirtual java/util/ArrayList/add(Ljava/lang/Object;)Z
    pop
;  INT
icn_100_α:
    ldc2_w 9
    goto icn_91_mke_8
icn_100_β:
    goto icn_87_α
    goto icn_100_α
icn_91_mke_8:
    invokestatic java/lang/Long/valueOf(J)Ljava/lang/Long;
    putstatic rung36_jcon_lists/icn_91_elem_8 Ljava/lang/Object;
    getstatic rung36_jcon_lists/icn_91_mklist Ljava/util/ArrayList;
    getstatic rung36_jcon_lists/icn_91_elem_8 Ljava/lang/Object;
    invokevirtual java/util/ArrayList/add(Ljava/lang/Object;)Z
    pop
    getstatic rung36_jcon_lists/icn_91_mklist Ljava/util/ArrayList;
    goto icn_90_store
icn_91_β:
    goto icn_87_α
icn_90_α:
    goto icn_91_α
icn_90_β:
    goto icn_91_β
icn_90_store:
    putstatic rung36_jcon_lists/icn_pv_main_x Ljava/util/ArrayList;
    getstatic rung36_jcon_lists/icn_pv_main_x Ljava/util/ArrayList;
    goto icn_main_s56_sdrain
icn_main_s56_sdrain:
    pop
    goto icn_87_α
;  STR
icn_103_α:
    ldc "ok failure on pull"
    goto icn_102_alt_g1
icn_103_β:
    goto icn_90_α
;  VAR
icn_105_α:
    getstatic rung36_jcon_lists/icn_pv_main_x Ljava/util/ArrayList;
    goto icn_104_lr
icn_105_β:
    goto icn_103_α
icn_104_α:
    goto icn_105_α
icn_104_β:
    goto icn_103_α
icn_104_lr:
    putstatic rung36_jcon_lists/icn_104_plist Ljava/util/ArrayList;
    getstatic rung36_jcon_lists/icn_104_plist Ljava/util/ArrayList;
    invokevirtual java/util/ArrayList/size()I
    dup
    ifeq icn_104_pfail
    iconst_1
    isub
    putstatic rung36_jcon_lists/icn_104_psz I
    getstatic rung36_jcon_lists/icn_104_plist Ljava/util/ArrayList;
    getstatic rung36_jcon_lists/icn_104_psz I
    invokevirtual java/util/ArrayList/remove(I)Ljava/lang/Object;
    dup
    ifnonnull icn_104_pok
    pop
    goto icn_103_α
icn_104_pok:
    checkcast java/lang/Long
    invokevirtual java/lang/Long/longValue()J
    goto icn_102_alt_g0
icn_104_pfail:
    pop
    goto icn_103_α
icn_102_alt_g0:
    pop
    lconst_0
    putstatic rung36_jcon_lists/icn_102_alt_val J
    sipush 1
    putstatic rung36_jcon_lists/icn_102_alt_gate I
    getstatic rung36_jcon_lists/icn_102_alt_val J
    goto icn_101_waft_0
icn_102_alt_g1:
    pop
    lconst_0
    putstatic rung36_jcon_lists/icn_102_alt_val J
    sipush 2
    putstatic rung36_jcon_lists/icn_102_alt_gate I
    getstatic rung36_jcon_lists/icn_102_alt_val J
    goto icn_101_waft_0
icn_102_α:
    iconst_0
    putstatic rung36_jcon_lists/icn_102_alt_gate I
    goto icn_104_α
icn_102_β:
    getstatic rung36_jcon_lists/icn_102_alt_gate I
    tableswitch 1 2
        icn_104_β
        icn_103_β
        default: icn_90_α
icn_101_α:
    goto icn_102_α
icn_101_β:
    goto icn_102_β
    goto icn_101_wentry
icn_101_waft_0:
    lstore 8
    getstatic java/lang/System/out Ljava/io/PrintStream;
    lload 8
    invokevirtual java/io/PrintStream/print(J)V
    getstatic java/lang/System/out Ljava/io/PrintStream;
    ldc ""
    invokevirtual java/io/PrintStream/println(Ljava/lang/String;)V
    lload 8
    goto icn_main_s55_sdrain
icn_101_wentry:
    goto icn_102_α
icn_main_s55_sdrain:
    pop2
    goto icn_90_α
;  STR
icn_108_α:
    ldc "ok failure on pop"
    goto icn_107_alt_g1
icn_108_β:
    goto icn_101_α
;  VAR
icn_110_α:
    getstatic rung36_jcon_lists/icn_pv_main_x Ljava/util/ArrayList;
    goto icn_109_lr
icn_110_β:
    goto icn_108_α
icn_109_α:
    goto icn_110_α
icn_109_β:
    goto icn_108_α
icn_109_lr:
    putstatic rung36_jcon_lists/icn_109_glist Ljava/util/ArrayList;
    getstatic rung36_jcon_lists/icn_109_glist Ljava/util/ArrayList;
    invokevirtual java/util/ArrayList/size()I
    ifeq icn_108_α
    getstatic rung36_jcon_lists/icn_109_glist Ljava/util/ArrayList;
    iconst_0
    invokevirtual java/util/ArrayList/remove(I)Ljava/lang/Object;
    dup
    ifnonnull icn_109_gok
    pop
    goto icn_108_α
icn_109_gok:
    checkcast java/lang/Long
    invokevirtual java/lang/Long/longValue()J
    goto icn_107_alt_g0
icn_107_alt_g0:
    pop
    lconst_0
    putstatic rung36_jcon_lists/icn_107_alt_val J
    sipush 1
    putstatic rung36_jcon_lists/icn_107_alt_gate I
    getstatic rung36_jcon_lists/icn_107_alt_val J
    goto icn_106_waft_0
icn_107_alt_g1:
    pop
    lconst_0
    putstatic rung36_jcon_lists/icn_107_alt_val J
    sipush 2
    putstatic rung36_jcon_lists/icn_107_alt_gate I
    getstatic rung36_jcon_lists/icn_107_alt_val J
    goto icn_106_waft_0
icn_107_α:
    iconst_0
    putstatic rung36_jcon_lists/icn_107_alt_gate I
    goto icn_109_α
icn_107_β:
    getstatic rung36_jcon_lists/icn_107_alt_gate I
    tableswitch 1 2
        icn_109_β
        icn_108_β
        default: icn_101_α
icn_106_α:
    goto icn_107_α
icn_106_β:
    goto icn_107_β
    goto icn_106_wentry
icn_106_waft_0:
    lstore 10
    getstatic java/lang/System/out Ljava/io/PrintStream;
    lload 10
    invokevirtual java/io/PrintStream/print(J)V
    getstatic java/lang/System/out Ljava/io/PrintStream;
    ldc ""
    invokevirtual java/io/PrintStream/println(Ljava/lang/String;)V
    lload 10
    goto icn_main_s54_sdrain
icn_106_wentry:
    goto icn_107_α
icn_main_s54_sdrain:
    pop2
    goto icn_101_α
;  STR
icn_113_α:
    ldc "ok failure on get"
    goto icn_112_alt_g1
icn_113_β:
    goto icn_106_α
;  VAR
icn_115_α:
    getstatic rung36_jcon_lists/icn_pv_main_x Ljava/util/ArrayList;
    goto icn_114_lr
icn_115_β:
    goto icn_113_α
icn_114_α:
    goto icn_115_α
icn_114_β:
    goto icn_113_α
icn_114_lr:
    putstatic rung36_jcon_lists/icn_114_glist Ljava/util/ArrayList;
    getstatic rung36_jcon_lists/icn_114_glist Ljava/util/ArrayList;
    invokevirtual java/util/ArrayList/size()I
    ifeq icn_113_α
    getstatic rung36_jcon_lists/icn_114_glist Ljava/util/ArrayList;
    iconst_0
    invokevirtual java/util/ArrayList/remove(I)Ljava/lang/Object;
    dup
    ifnonnull icn_114_gok
    pop
    goto icn_113_α
icn_114_gok:
    checkcast java/lang/Long
    invokevirtual java/lang/Long/longValue()J
    goto icn_112_alt_g0
icn_112_alt_g0:
    putstatic rung36_jcon_lists/icn_112_alt_val J
    sipush 1
    putstatic rung36_jcon_lists/icn_112_alt_gate I
    getstatic rung36_jcon_lists/icn_112_alt_val J
    goto icn_111_waft_0
icn_112_alt_g1:
    pop
    lconst_0
    putstatic rung36_jcon_lists/icn_112_alt_val J
    sipush 2
    putstatic rung36_jcon_lists/icn_112_alt_gate I
    getstatic rung36_jcon_lists/icn_112_alt_val J
    goto icn_111_waft_0
icn_112_α:
    iconst_0
    putstatic rung36_jcon_lists/icn_112_alt_gate I
    goto icn_114_α
icn_112_β:
    getstatic rung36_jcon_lists/icn_112_alt_gate I
    tableswitch 1 2
        icn_114_β
        icn_113_β
        default: icn_106_α
icn_111_α:
    goto icn_112_α
icn_111_β:
    goto icn_112_β
    goto icn_111_wentry
icn_111_waft_0:
    lstore 12
    getstatic java/lang/System/out Ljava/io/PrintStream;
    lload 12
    invokevirtual java/io/PrintStream/print(J)V
    getstatic java/lang/System/out Ljava/io/PrintStream;
    ldc ""
    invokevirtual java/io/PrintStream/println(Ljava/lang/String;)V
    lload 12
    goto icn_main_s53_sdrain
icn_111_wentry:
    goto icn_112_α
icn_main_s53_sdrain:
    pop2
    goto icn_106_α
;  VAR
icn_117_α:
    getstatic rung36_jcon_lists/icn_pv_main_x Ljava/util/ArrayList;
    goto icn_116_lr
icn_117_β:
    goto icn_111_α
icn_116_α:
    goto icn_117_α
icn_116_β:
    goto icn_111_α
icn_116_lr:
    putstatic rung36_jcon_lists/icn_116_glist Ljava/util/ArrayList;
    getstatic rung36_jcon_lists/icn_116_glist Ljava/util/ArrayList;
    invokevirtual java/util/ArrayList/size()I
    ifeq icn_111_α
    getstatic rung36_jcon_lists/icn_116_glist Ljava/util/ArrayList;
    iconst_0
    invokevirtual java/util/ArrayList/remove(I)Ljava/lang/Object;
    dup
    ifnonnull icn_116_gok
    pop
    goto icn_111_α
icn_116_gok:
    checkcast java/lang/Long
    invokevirtual java/lang/Long/longValue()J
    goto icn_main_s52_sdrain
icn_main_s52_sdrain:
    pop2
    goto icn_111_α
;  STR
icn_120_α:
    ldc "ok failure -2"
    goto icn_119_alt_g1
icn_120_β:
    goto icn_116_α
;  VAR
icn_122_α:
    getstatic rung36_jcon_lists/icn_pv_main_x Ljava/util/ArrayList;
    goto icn_121_lsub_lr
icn_122_β:
    goto icn_120_α
;  INT
icn_124_α:
    ldc2_w 2
    goto icn_123_neg
icn_124_β:
    goto icn_120_α
;  NEG
icn_123_α:
    goto icn_124_α
icn_123_β:
    goto icn_124_β
icn_123_neg:
    lneg
    goto icn_121_lsub_ir
icn_121_α:
    goto icn_122_α
icn_121_β:
    goto icn_123_β
icn_121_lsub_lr:
    putstatic rung36_jcon_lists/icn_121_lsub_l Ljava/util/ArrayList;
    goto icn_123_α
icn_121_lsub_ir:
    l2i
    istore 103
    iload 103
    ifgt icn_121_lsub_pos
    iload 103
    iflt icn_121_lsub_neg
icn_121_lsub_z:
    goto icn_120_α
icn_121_lsub_pos:
    iload 103
    iconst_1
    isub
    putstatic rung36_jcon_lists/icn_121_lsub_i I
    goto icn_121_lsub_chk
icn_121_lsub_neg:
    getstatic rung36_jcon_lists/icn_121_lsub_l Ljava/util/ArrayList;
    invokevirtual java/util/ArrayList/size()I
    iload 103
    iadd
    putstatic rung36_jcon_lists/icn_121_lsub_i I
    goto icn_121_lsub_chk
icn_121_lsub_chk:
    getstatic rung36_jcon_lists/icn_121_lsub_i I
    iflt icn_120_α
    getstatic rung36_jcon_lists/icn_121_lsub_l Ljava/util/ArrayList;
    invokevirtual java/util/ArrayList/size()I
    getstatic rung36_jcon_lists/icn_121_lsub_i I
    if_icmple icn_120_α
    getstatic rung36_jcon_lists/icn_121_lsub_l Ljava/util/ArrayList;
    getstatic rung36_jcon_lists/icn_121_lsub_i I
    invokevirtual java/util/ArrayList/get(I)Ljava/lang/Object;
    checkcast java/lang/Long
    invokevirtual java/lang/Long/longValue()J
    goto icn_119_alt_g0
icn_119_alt_g0:
    putstatic rung36_jcon_lists/icn_119_alt_val J
    sipush 1
    putstatic rung36_jcon_lists/icn_119_alt_gate I
    getstatic rung36_jcon_lists/icn_119_alt_val J
    goto icn_118_waft_0
icn_119_alt_g1:
    pop
    lconst_0
    putstatic rung36_jcon_lists/icn_119_alt_val J
    sipush 2
    putstatic rung36_jcon_lists/icn_119_alt_gate I
    getstatic rung36_jcon_lists/icn_119_alt_val J
    goto icn_118_waft_0
icn_119_α:
    iconst_0
    putstatic rung36_jcon_lists/icn_119_alt_gate I
    goto icn_121_α
icn_119_β:
    getstatic rung36_jcon_lists/icn_119_alt_gate I
    tableswitch 1 2
        icn_121_β
        icn_120_β
        default: icn_116_α
icn_118_α:
    goto icn_119_α
icn_118_β:
    goto icn_119_β
    goto icn_118_wentry
icn_118_waft_0:
    lstore 14
    getstatic java/lang/System/out Ljava/io/PrintStream;
    lload 14
    invokevirtual java/io/PrintStream/print(J)V
    getstatic java/lang/System/out Ljava/io/PrintStream;
    ldc ""
    invokevirtual java/io/PrintStream/println(Ljava/lang/String;)V
    lload 14
    goto icn_main_s51_sdrain
icn_118_wentry:
    goto icn_119_α
icn_main_s51_sdrain:
    pop2
    goto icn_116_α
;  STR
icn_127_α:
    ldc "ok failure 2"
    goto icn_126_alt_g1
icn_127_β:
    goto icn_118_α
;  VAR
icn_129_α:
    getstatic rung36_jcon_lists/icn_pv_main_x Ljava/util/ArrayList;
    goto icn_128_lsub_lr
icn_129_β:
    goto icn_127_α
;  INT
icn_130_α:
    ldc2_w 2
    goto icn_128_lsub_ir
icn_130_β:
    goto icn_127_α
icn_128_α:
    goto icn_129_α
icn_128_β:
    goto icn_130_β
icn_128_lsub_lr:
    putstatic rung36_jcon_lists/icn_128_lsub_l Ljava/util/ArrayList;
    goto icn_130_α
icn_128_lsub_ir:
    l2i
    istore 104
    iload 104
    ifgt icn_128_lsub_pos
    iload 104
    iflt icn_128_lsub_neg
icn_128_lsub_z:
    goto icn_127_α
icn_128_lsub_pos:
    iload 104
    iconst_1
    isub
    putstatic rung36_jcon_lists/icn_128_lsub_i I
    goto icn_128_lsub_chk
icn_128_lsub_neg:
    getstatic rung36_jcon_lists/icn_128_lsub_l Ljava/util/ArrayList;
    invokevirtual java/util/ArrayList/size()I
    iload 104
    iadd
    putstatic rung36_jcon_lists/icn_128_lsub_i I
    goto icn_128_lsub_chk
icn_128_lsub_chk:
    getstatic rung36_jcon_lists/icn_128_lsub_i I
    iflt icn_127_α
    getstatic rung36_jcon_lists/icn_128_lsub_l Ljava/util/ArrayList;
    invokevirtual java/util/ArrayList/size()I
    getstatic rung36_jcon_lists/icn_128_lsub_i I
    if_icmple icn_127_α
    getstatic rung36_jcon_lists/icn_128_lsub_l Ljava/util/ArrayList;
    getstatic rung36_jcon_lists/icn_128_lsub_i I
    invokevirtual java/util/ArrayList/get(I)Ljava/lang/Object;
    checkcast java/lang/Long
    invokevirtual java/lang/Long/longValue()J
    goto icn_126_alt_g0
icn_126_alt_g0:
    putstatic rung36_jcon_lists/icn_126_alt_val J
    sipush 1
    putstatic rung36_jcon_lists/icn_126_alt_gate I
    getstatic rung36_jcon_lists/icn_126_alt_val J
    goto icn_125_waft_0
icn_126_alt_g1:
    pop
    lconst_0
    putstatic rung36_jcon_lists/icn_126_alt_val J
    sipush 2
    putstatic rung36_jcon_lists/icn_126_alt_gate I
    getstatic rung36_jcon_lists/icn_126_alt_val J
    goto icn_125_waft_0
icn_126_α:
    iconst_0
    putstatic rung36_jcon_lists/icn_126_alt_gate I
    goto icn_128_α
icn_126_β:
    getstatic rung36_jcon_lists/icn_126_alt_gate I
    tableswitch 1 2
        icn_128_β
        icn_127_β
        default: icn_118_α
icn_125_α:
    goto icn_126_α
icn_125_β:
    goto icn_126_β
    goto icn_125_wentry
icn_125_waft_0:
    lstore 16
    getstatic java/lang/System/out Ljava/io/PrintStream;
    lload 16
    invokevirtual java/io/PrintStream/print(J)V
    getstatic java/lang/System/out Ljava/io/PrintStream;
    ldc ""
    invokevirtual java/io/PrintStream/println(Ljava/lang/String;)V
    lload 16
    goto icn_main_s50_sdrain
icn_125_wentry:
    goto icn_126_α
icn_main_s50_sdrain:
    pop2
    goto icn_118_α
;  STR
icn_133_α:
    ldc "ok failure 0"
    goto icn_132_alt_g1
icn_133_β:
    goto icn_125_α
;  VAR
icn_135_α:
    getstatic rung36_jcon_lists/icn_pv_main_x Ljava/util/ArrayList;
    goto icn_134_lsub_lr
icn_135_β:
    goto icn_133_α
;  INT
icn_136_α:
    ldc2_w 0
    goto icn_134_lsub_ir
icn_136_β:
    goto icn_133_α
icn_134_α:
    goto icn_135_α
icn_134_β:
    goto icn_136_β
icn_134_lsub_lr:
    putstatic rung36_jcon_lists/icn_134_lsub_l Ljava/util/ArrayList;
    goto icn_136_α
icn_134_lsub_ir:
    l2i
    istore 105
    iload 105
    ifgt icn_134_lsub_pos
    iload 105
    iflt icn_134_lsub_neg
icn_134_lsub_z:
    goto icn_133_α
icn_134_lsub_pos:
    iload 105
    iconst_1
    isub
    putstatic rung36_jcon_lists/icn_134_lsub_i I
    goto icn_134_lsub_chk
icn_134_lsub_neg:
    getstatic rung36_jcon_lists/icn_134_lsub_l Ljava/util/ArrayList;
    invokevirtual java/util/ArrayList/size()I
    iload 105
    iadd
    putstatic rung36_jcon_lists/icn_134_lsub_i I
    goto icn_134_lsub_chk
icn_134_lsub_chk:
    getstatic rung36_jcon_lists/icn_134_lsub_i I
    iflt icn_133_α
    getstatic rung36_jcon_lists/icn_134_lsub_l Ljava/util/ArrayList;
    invokevirtual java/util/ArrayList/size()I
    getstatic rung36_jcon_lists/icn_134_lsub_i I
    if_icmple icn_133_α
    getstatic rung36_jcon_lists/icn_134_lsub_l Ljava/util/ArrayList;
    getstatic rung36_jcon_lists/icn_134_lsub_i I
    invokevirtual java/util/ArrayList/get(I)Ljava/lang/Object;
    checkcast java/lang/Long
    invokevirtual java/lang/Long/longValue()J
    goto icn_132_alt_g0
icn_132_alt_g0:
    putstatic rung36_jcon_lists/icn_132_alt_val J
    sipush 1
    putstatic rung36_jcon_lists/icn_132_alt_gate I
    getstatic rung36_jcon_lists/icn_132_alt_val J
    goto icn_131_waft_0
icn_132_alt_g1:
    pop
    lconst_0
    putstatic rung36_jcon_lists/icn_132_alt_val J
    sipush 2
    putstatic rung36_jcon_lists/icn_132_alt_gate I
    getstatic rung36_jcon_lists/icn_132_alt_val J
    goto icn_131_waft_0
icn_132_α:
    iconst_0
    putstatic rung36_jcon_lists/icn_132_alt_gate I
    goto icn_134_α
icn_132_β:
    getstatic rung36_jcon_lists/icn_132_alt_gate I
    tableswitch 1 2
        icn_134_β
        icn_133_β
        default: icn_125_α
icn_131_α:
    goto icn_132_α
icn_131_β:
    goto icn_132_β
    goto icn_131_wentry
icn_131_waft_0:
    lstore 18
    getstatic java/lang/System/out Ljava/io/PrintStream;
    lload 18
    invokevirtual java/io/PrintStream/print(J)V
    getstatic java/lang/System/out Ljava/io/PrintStream;
    ldc ""
    invokevirtual java/io/PrintStream/println(Ljava/lang/String;)V
    lload 18
    goto icn_main_s49_sdrain
icn_131_wentry:
    goto icn_132_α
icn_main_s49_sdrain:
    pop2
    goto icn_125_α
;  VAR
icn_138_α:
    getstatic rung36_jcon_lists/icn_pv_main_x Ljava/util/ArrayList;
    goto icn_137_arg1
icn_138_β:
    goto icn_131_α
icn_137_arg1:
    putstatic rung36_jcon_lists/icn_arg_1 J
    goto icn_137_docall
;  STR
icn_139_α:
    ldc "P"
    goto icn_137_arg0
icn_139_β:
    goto icn_131_α
icn_137_arg0:
    putstatic rung36_jcon_lists/icn_arg_str_0 Ljava/lang/String;
    lconst_0
    putstatic rung36_jcon_lists/icn_arg_0 J
    goto icn_138_α
icn_137_α:
    goto icn_139_α
icn_137_β:
    goto icn_138_β
icn_137_docall:
    getstatic rung36_jcon_lists/icn_pv_main_y J
    lstore 154
    getstatic rung36_jcon_lists/icn_41_alt_val J
    lstore 156
    getstatic rung36_jcon_lists/icn_50_alt_val J
    lstore 158
    getstatic rung36_jcon_lists/icn_102_alt_val J
    lstore 160
    getstatic rung36_jcon_lists/icn_107_alt_val J
    lstore 162
    getstatic rung36_jcon_lists/icn_112_alt_val J
    lstore 164
    getstatic rung36_jcon_lists/icn_119_alt_val J
    lstore 166
    getstatic rung36_jcon_lists/icn_126_alt_val J
    lstore 168
    getstatic rung36_jcon_lists/icn_132_alt_val J
    lstore 170
    invokestatic rung36_jcon_lists/icn_limage()V
    lload 154
    putstatic rung36_jcon_lists/icn_pv_main_y J
    lload 156
    putstatic rung36_jcon_lists/icn_41_alt_val J
    lload 158
    putstatic rung36_jcon_lists/icn_50_alt_val J
    lload 160
    putstatic rung36_jcon_lists/icn_102_alt_val J
    lload 162
    putstatic rung36_jcon_lists/icn_107_alt_val J
    lload 164
    putstatic rung36_jcon_lists/icn_112_alt_val J
    lload 166
    putstatic rung36_jcon_lists/icn_119_alt_val J
    lload 168
    putstatic rung36_jcon_lists/icn_126_alt_val J
    lload 170
    putstatic rung36_jcon_lists/icn_132_alt_val J
    getstatic rung36_jcon_lists/icn_failed B
    ifne icn_137_after_call
    getstatic rung36_jcon_lists/icn_retval J
    goto icn_main_s48_sdrain
icn_137_after_call:
    goto icn_131_α
icn_main_s48_sdrain:
    pop2
    goto icn_131_α
;  INT
icn_141_α:
    ldc2_w 2
    goto icn_140_store
icn_141_β:
    goto icn_137_α
icn_140_α:
    goto icn_141_α
icn_140_β:
    goto icn_141_β
icn_140_store:
    pop2
    lconst_0
    goto icn_main_s47_sdrain
icn_main_s47_sdrain:
    pop2
    goto icn_137_α
;  STR
icn_143_α:
    ldc "\t"
    goto icn_142_waft_0
icn_143_β:
    goto icn_140_α
;  VAR
icn_145_α:
    getstatic rung36_jcon_lists/icn_pv_main_x Ljava/util/ArrayList;
    goto icn_144_rand
icn_145_β:
    goto icn_140_α
icn_144_α:
    goto icn_145_α
icn_144_β:
    goto icn_145_β
icn_144_rand:
    invokestatic rung36_jcon_lists/icn_builtin_random(J)J
    goto icn_142_waft_1
icn_142_α:
    goto icn_143_α
icn_142_β:
    goto icn_143_β
    goto icn_142_wentry
icn_142_waft_0:
    astore 150
    getstatic java/lang/System/out Ljava/io/PrintStream;
    aload 150
    invokevirtual java/io/PrintStream/print(Ljava/lang/String;)V
    goto icn_144_α
icn_142_waft_1:
    lstore 20
    getstatic java/lang/System/out Ljava/io/PrintStream;
    lload 20
    invokevirtual java/io/PrintStream/print(J)V
    getstatic java/lang/System/out Ljava/io/PrintStream;
    ldc ""
    invokevirtual java/io/PrintStream/println(Ljava/lang/String;)V
    lload 20
    goto icn_main_s46_sdrain
icn_142_wentry:
    goto icn_143_α
icn_main_s46_sdrain:
    pop2
    goto icn_140_α
icn_147_α:
    new java/util/ArrayList
    dup
    invokespecial java/util/ArrayList/<init>()V
    putstatic rung36_jcon_lists/icn_147_mklist Ljava/util/ArrayList;
;  INT
icn_148_α:
    ldc2_w 1
    goto icn_147_mke_0
icn_148_β:
    goto icn_142_α
    goto icn_148_α
icn_147_mke_0:
    invokestatic java/lang/Long/valueOf(J)Ljava/lang/Long;
    putstatic rung36_jcon_lists/icn_147_elem_0 Ljava/lang/Object;
    getstatic rung36_jcon_lists/icn_147_mklist Ljava/util/ArrayList;
    getstatic rung36_jcon_lists/icn_147_elem_0 Ljava/lang/Object;
    invokevirtual java/util/ArrayList/add(Ljava/lang/Object;)Z
    pop
    getstatic rung36_jcon_lists/icn_147_mklist Ljava/util/ArrayList;
    goto icn_146_store
icn_147_β:
    goto icn_142_α
icn_146_α:
    goto icn_147_α
icn_146_β:
    goto icn_147_β
icn_146_store:
    putstatic rung36_jcon_lists/icn_pv_main_x Ljava/util/ArrayList;
    getstatic rung36_jcon_lists/icn_pv_main_x Ljava/util/ArrayList;
    goto icn_main_s45_sdrain
icn_main_s45_sdrain:
    pop
    goto icn_142_α
;  VAR
icn_150_α:
    getstatic rung36_jcon_lists/icn_pv_main_x Ljava/util/ArrayList;
    goto icn_149_arg1
icn_150_β:
    goto icn_146_α
icn_149_arg1:
    putstatic rung36_jcon_lists/icn_arg_1 J
    goto icn_149_docall
;  STR
icn_151_α:
    ldc "O"
    goto icn_149_arg0
icn_151_β:
    goto icn_146_α
icn_149_arg0:
    putstatic rung36_jcon_lists/icn_arg_str_0 Ljava/lang/String;
    lconst_0
    putstatic rung36_jcon_lists/icn_arg_0 J
    goto icn_150_α
icn_149_α:
    goto icn_151_α
icn_149_β:
    goto icn_150_β
icn_149_docall:
    getstatic rung36_jcon_lists/icn_pv_main_y J
    lstore 155
    getstatic rung36_jcon_lists/icn_41_alt_val J
    lstore 157
    getstatic rung36_jcon_lists/icn_50_alt_val J
    lstore 159
    getstatic rung36_jcon_lists/icn_102_alt_val J
    lstore 161
    getstatic rung36_jcon_lists/icn_107_alt_val J
    lstore 163
    getstatic rung36_jcon_lists/icn_112_alt_val J
    lstore 165
    getstatic rung36_jcon_lists/icn_119_alt_val J
    lstore 167
    getstatic rung36_jcon_lists/icn_126_alt_val J
    lstore 169
    getstatic rung36_jcon_lists/icn_132_alt_val J
    lstore 171
    invokestatic rung36_jcon_lists/icn_limage()V
    lload 155
    putstatic rung36_jcon_lists/icn_pv_main_y J
    lload 157
    putstatic rung36_jcon_lists/icn_41_alt_val J
    lload 159
    putstatic rung36_jcon_lists/icn_50_alt_val J
    lload 161
    putstatic rung36_jcon_lists/icn_102_alt_val J
    lload 163
    putstatic rung36_jcon_lists/icn_107_alt_val J
    lload 165
    putstatic rung36_jcon_lists/icn_112_alt_val J
    lload 167
    putstatic rung36_jcon_lists/icn_119_alt_val J
    lload 169
    putstatic rung36_jcon_lists/icn_126_alt_val J
    lload 171
    putstatic rung36_jcon_lists/icn_132_alt_val J
    getstatic rung36_jcon_lists/icn_failed B
    ifne icn_149_after_call
    getstatic rung36_jcon_lists/icn_retval J
    goto icn_main_s44_sdrain
icn_149_after_call:
    goto icn_146_α
icn_main_s44_sdrain:
    pop2
    goto icn_146_α
;  VAR
icn_154_α:
    getstatic rung36_jcon_lists/icn_pv_main_i J
    goto icn_153_store
icn_154_β:
    goto icn_152_pump
icn_153_α:
    goto icn_154_α
icn_153_β:
    goto icn_154_β
icn_153_store:
    putstatic rung36_jcon_lists/icn_155_lsa_v J
    getstatic rung36_jcon_lists/icn_pv_main_x Ljava/util/ArrayList;
    putstatic rung36_jcon_lists/icn_155_lsa_l Ljava/util/ArrayList;
;  VAR
icn_156_α:
    getstatic rung36_jcon_lists/icn_pv_main_i J
    goto icn_155_lsa_ir
icn_156_β:
    goto icn_152_pump
    goto icn_156_α
icn_155_lsa_ir:
    lconst_1
    lsub
    putstatic rung36_jcon_lists/icn_155_lsa_i J
    goto icn_155_lsa_do
icn_155_lsa_do:
    getstatic rung36_jcon_lists/icn_155_lsa_l Ljava/util/ArrayList;
    getstatic rung36_jcon_lists/icn_155_lsa_i J
    l2i
    getstatic rung36_jcon_lists/icn_155_lsa_v J
    invokestatic java/lang/Long/valueOf(J)Ljava/lang/Long;
    invokevirtual java/util/ArrayList/set(ILjava/lang/Object;)Ljava/lang/Object;
    pop
    getstatic rung36_jcon_lists/icn_155_lsa_v J
    goto icn_152_bdrain
;  INT
icn_159_α:
    ldc2_w 0
    goto icn_158_e2relay
icn_159_β:
    goto icn_158_e1b
;  INT
icn_161_α:
    ldc2_w 3
    goto icn_160_rrelay
icn_161_β:
    goto icn_160_lb
;  VAR
icn_164_α:
    getstatic rung36_jcon_lists/icn_pv_main_x Ljava/util/ArrayList;
    goto icn_163_relay
icn_164_β:
    goto icn_149_α
icn_163_α:
    goto icn_164_α
icn_163_β:
    goto icn_164_β
icn_163_relay:
    invokevirtual java/util/ArrayList/size()I
    i2l
    goto icn_162_neg
;  NEG
icn_162_α:
    goto icn_163_α
icn_162_β:
    goto icn_163_β
icn_162_neg:
    lneg
    goto icn_160_lrelay
icn_160_lrelay:
    putstatic rung36_jcon_lists/icn_160_binop_lc J
    goto icn_160_lstore
icn_160_rrelay:
    putstatic rung36_jcon_lists/icn_160_binop_rc J
    goto icn_160_compute
icn_160_lb:
    goto icn_162_β
icn_160_α:
    iconst_0
    putstatic rung36_jcon_lists/icn_160_binop_bf I
    goto icn_162_α
icn_160_β:
    goto icn_161_β
icn_160_lstore:
    getstatic rung36_jcon_lists/icn_160_binop_bf I
    ifeq icn_161_α
    goto icn_161_β
icn_160_compute:
    getstatic rung36_jcon_lists/icn_160_binop_lc J
    getstatic rung36_jcon_lists/icn_160_binop_rc J
    lsub
    goto icn_158_e1relay
icn_158_e1relay:
    putstatic rung36_jcon_lists/icn_158_e1val J
    goto icn_159_α
icn_158_e2relay:
    putstatic rung36_jcon_lists/icn_158_e2val J
    goto icn_158_init
icn_158_e1b:
    iconst_0
    putstatic rung36_jcon_lists/icn_158_e2seen I
    goto icn_160_β
icn_158_e2b:
    goto icn_159_β
icn_158_α:
    iconst_0
    putstatic rung36_jcon_lists/icn_158_e2seen I
    goto icn_160_α
icn_158_β:
    getstatic rung36_jcon_lists/icn_158_I J
    lconst_1
    ladd
    putstatic rung36_jcon_lists/icn_158_I J
    goto icn_158_code
icn_158_init:
    getstatic rung36_jcon_lists/icn_158_e2val J
    putstatic rung36_jcon_lists/icn_158_bound J
    getstatic rung36_jcon_lists/icn_158_e2seen I
    ifne icn_158_init_e2adv
    getstatic rung36_jcon_lists/icn_158_e1val J
    putstatic rung36_jcon_lists/icn_158_e1cur J
    getstatic rung36_jcon_lists/icn_158_e1cur J
    putstatic rung36_jcon_lists/icn_158_I J
    iconst_1
    putstatic rung36_jcon_lists/icn_158_e2seen I
    goto icn_158_code
icn_158_init_e2adv:
    getstatic rung36_jcon_lists/icn_158_e1cur J
    putstatic rung36_jcon_lists/icn_158_I J
    goto icn_158_code
icn_158_code:
    getstatic rung36_jcon_lists/icn_158_I J
    getstatic rung36_jcon_lists/icn_158_bound J
    lcmp
    ifgt icn_158_e2b
    getstatic rung36_jcon_lists/icn_158_I J
    goto icn_157_store
icn_157_α:
    goto icn_158_α
icn_157_β:
    goto icn_158_β
icn_157_store:
    putstatic rung36_jcon_lists/icn_pv_main_i J
    getstatic rung36_jcon_lists/icn_pv_main_i J
    goto icn_152_gdrain
icn_152_gdrain:
    pop2
    goto icn_153_α
icn_152_bdrain:
    pop2
icn_152_pump:
    goto icn_157_β
icn_152_α:
    goto icn_157_α
icn_152_β:
    goto icn_149_α
;  VAR
icn_166_α:
    getstatic rung36_jcon_lists/icn_pv_main_x Ljava/util/ArrayList;
    goto icn_165_arg1
icn_166_β:
    goto icn_152_α
icn_165_arg1:
    putstatic rung36_jcon_lists/icn_arg_1 J
    goto icn_165_docall
;  STR
icn_167_α:
    ldc "N"
    goto icn_165_arg0
icn_167_β:
    goto icn_152_α
icn_165_arg0:
    putstatic rung36_jcon_lists/icn_arg_str_0 Ljava/lang/String;
    lconst_0
    putstatic rung36_jcon_lists/icn_arg_0 J
    goto icn_166_α
icn_165_α:
    goto icn_167_α
icn_165_β:
    goto icn_166_β
icn_165_docall:
    getstatic rung36_jcon_lists/icn_pv_main_y J
    lstore 155
    getstatic rung36_jcon_lists/icn_41_alt_val J
    lstore 157
    getstatic rung36_jcon_lists/icn_50_alt_val J
    lstore 159
    getstatic rung36_jcon_lists/icn_102_alt_val J
    lstore 161
    getstatic rung36_jcon_lists/icn_107_alt_val J
    lstore 163
    getstatic rung36_jcon_lists/icn_112_alt_val J
    lstore 165
    getstatic rung36_jcon_lists/icn_119_alt_val J
    lstore 167
    getstatic rung36_jcon_lists/icn_126_alt_val J
    lstore 169
    getstatic rung36_jcon_lists/icn_132_alt_val J
    lstore 171
    getstatic rung36_jcon_lists/icn_pv_main_i J
    lstore 173
    getstatic rung36_jcon_lists/icn_155_lsa_i J
    lstore 175
    getstatic rung36_jcon_lists/icn_155_lsa_v J
    lstore 177
    getstatic rung36_jcon_lists/icn_158_I J
    lstore 179
    getstatic rung36_jcon_lists/icn_158_bound J
    lstore 181
    getstatic rung36_jcon_lists/icn_158_e1cur J
    lstore 183
    getstatic rung36_jcon_lists/icn_158_e1val J
    lstore 185
    getstatic rung36_jcon_lists/icn_158_e2val J
    lstore 187
    getstatic rung36_jcon_lists/icn_160_binop_lc J
    lstore 189
    getstatic rung36_jcon_lists/icn_160_binop_rc J
    lstore 191
    invokestatic rung36_jcon_lists/icn_limage()V
    lload 155
    putstatic rung36_jcon_lists/icn_pv_main_y J
    lload 157
    putstatic rung36_jcon_lists/icn_41_alt_val J
    lload 159
    putstatic rung36_jcon_lists/icn_50_alt_val J
    lload 161
    putstatic rung36_jcon_lists/icn_102_alt_val J
    lload 163
    putstatic rung36_jcon_lists/icn_107_alt_val J
    lload 165
    putstatic rung36_jcon_lists/icn_112_alt_val J
    lload 167
    putstatic rung36_jcon_lists/icn_119_alt_val J
    lload 169
    putstatic rung36_jcon_lists/icn_126_alt_val J
    lload 171
    putstatic rung36_jcon_lists/icn_132_alt_val J
    lload 173
    putstatic rung36_jcon_lists/icn_pv_main_i J
    lload 175
    putstatic rung36_jcon_lists/icn_155_lsa_i J
    lload 177
    putstatic rung36_jcon_lists/icn_155_lsa_v J
    lload 179
    putstatic rung36_jcon_lists/icn_158_I J
    lload 181
    putstatic rung36_jcon_lists/icn_158_bound J
    lload 183
    putstatic rung36_jcon_lists/icn_158_e1cur J
    lload 185
    putstatic rung36_jcon_lists/icn_158_e1val J
    lload 187
    putstatic rung36_jcon_lists/icn_158_e2val J
    lload 189
    putstatic rung36_jcon_lists/icn_160_binop_lc J
    lload 191
    putstatic rung36_jcon_lists/icn_160_binop_rc J
    getstatic rung36_jcon_lists/icn_failed B
    ifne icn_165_after_call
    getstatic rung36_jcon_lists/icn_retval J
    goto icn_main_s42_sdrain
icn_165_after_call:
    goto icn_152_α
icn_main_s42_sdrain:
    pop2
    goto icn_152_α
;  VAR
icn_170_α:
    getstatic rung36_jcon_lists/icn_pv_main_i J
    goto icn_169_store
icn_170_β:
    goto icn_168_pump
icn_169_α:
    goto icn_170_α
icn_169_β:
    goto icn_170_β
icn_169_store:
    putstatic rung36_jcon_lists/icn_171_lsa_v J
    getstatic rung36_jcon_lists/icn_pv_main_x Ljava/util/ArrayList;
    putstatic rung36_jcon_lists/icn_171_lsa_l Ljava/util/ArrayList;
;  VAR
icn_172_α:
    getstatic rung36_jcon_lists/icn_pv_main_i J
    goto icn_171_lsa_ir
icn_172_β:
    goto icn_168_pump
    goto icn_172_α
icn_171_lsa_ir:
    lconst_1
    lsub
    putstatic rung36_jcon_lists/icn_171_lsa_i J
    goto icn_171_lsa_do
icn_171_lsa_do:
    getstatic rung36_jcon_lists/icn_171_lsa_l Ljava/util/ArrayList;
    getstatic rung36_jcon_lists/icn_171_lsa_i J
    l2i
    getstatic rung36_jcon_lists/icn_171_lsa_v J
    invokestatic java/lang/Long/valueOf(J)Ljava/lang/Long;
    invokevirtual java/util/ArrayList/set(ILjava/lang/Object;)Ljava/lang/Object;
    pop
    getstatic rung36_jcon_lists/icn_171_lsa_v J
    goto icn_168_bdrain
;  INT
icn_176_α:
    ldc2_w 3
    goto icn_175_rrelay
icn_176_β:
    goto icn_175_lb
;  VAR
icn_178_α:
    getstatic rung36_jcon_lists/icn_pv_main_x Ljava/util/ArrayList;
    goto icn_177_relay
icn_178_β:
    goto icn_174_e1b
icn_177_α:
    goto icn_178_α
icn_177_β:
    goto icn_178_β
icn_177_relay:
    invokevirtual java/util/ArrayList/size()I
    i2l
    goto icn_175_lrelay
icn_175_lrelay:
    putstatic rung36_jcon_lists/icn_175_binop_lc J
    goto icn_175_lstore
icn_175_rrelay:
    putstatic rung36_jcon_lists/icn_175_binop_rc J
    goto icn_175_compute
icn_175_lb:
    goto icn_177_β
icn_175_α:
    iconst_0
    putstatic rung36_jcon_lists/icn_175_binop_bf I
    goto icn_177_α
icn_175_β:
    goto icn_176_β
icn_175_lstore:
    getstatic rung36_jcon_lists/icn_175_binop_bf I
    ifeq icn_176_α
    goto icn_176_β
icn_175_compute:
    getstatic rung36_jcon_lists/icn_175_binop_lc J
    getstatic rung36_jcon_lists/icn_175_binop_rc J
    ladd
    goto icn_174_e2relay
;  INT
icn_179_α:
    ldc2_w 0
    goto icn_174_e1relay
icn_179_β:
    goto icn_165_α
icn_174_e1relay:
    putstatic rung36_jcon_lists/icn_174_e1val J
    goto icn_175_α
icn_174_e2relay:
    putstatic rung36_jcon_lists/icn_174_e2val J
    goto icn_174_init
icn_174_e1b:
    iconst_0
    putstatic rung36_jcon_lists/icn_174_e2seen I
    goto icn_179_β
icn_174_e2b:
    goto icn_175_β
icn_174_α:
    iconst_0
    putstatic rung36_jcon_lists/icn_174_e2seen I
    goto icn_179_α
icn_174_β:
    getstatic rung36_jcon_lists/icn_174_I J
    lconst_1
    ladd
    putstatic rung36_jcon_lists/icn_174_I J
    goto icn_174_code
icn_174_init:
    getstatic rung36_jcon_lists/icn_174_e2val J
    putstatic rung36_jcon_lists/icn_174_bound J
    getstatic rung36_jcon_lists/icn_174_e2seen I
    ifne icn_174_init_e2adv
    getstatic rung36_jcon_lists/icn_174_e1val J
    putstatic rung36_jcon_lists/icn_174_e1cur J
    getstatic rung36_jcon_lists/icn_174_e1cur J
    putstatic rung36_jcon_lists/icn_174_I J
    iconst_1
    putstatic rung36_jcon_lists/icn_174_e2seen I
    goto icn_174_code
icn_174_init_e2adv:
    getstatic rung36_jcon_lists/icn_174_e1cur J
    putstatic rung36_jcon_lists/icn_174_I J
    goto icn_174_code
icn_174_code:
    getstatic rung36_jcon_lists/icn_174_I J
    getstatic rung36_jcon_lists/icn_174_bound J
    lcmp
    ifgt icn_174_e2b
    getstatic rung36_jcon_lists/icn_174_I J
    goto icn_173_store
icn_173_α:
    goto icn_174_α
icn_173_β:
    goto icn_174_β
icn_173_store:
    putstatic rung36_jcon_lists/icn_pv_main_i J
    getstatic rung36_jcon_lists/icn_pv_main_i J
    goto icn_168_gdrain
icn_168_gdrain:
    pop2
    goto icn_169_α
icn_168_bdrain:
    pop2
icn_168_pump:
    goto icn_173_β
icn_168_α:
    goto icn_173_α
icn_168_β:
    goto icn_165_α
icn_181_α:
    new java/util/ArrayList
    dup
    invokespecial java/util/ArrayList/<init>()V
    putstatic rung36_jcon_lists/icn_181_mklist Ljava/util/ArrayList;
;  INT
icn_182_α:
    ldc2_w 1
    goto icn_181_mke_0
icn_182_β:
    goto icn_168_α
    goto icn_182_α
icn_181_mke_0:
    invokestatic java/lang/Long/valueOf(J)Ljava/lang/Long;
    putstatic rung36_jcon_lists/icn_181_elem_0 Ljava/lang/Object;
    getstatic rung36_jcon_lists/icn_181_mklist Ljava/util/ArrayList;
    getstatic rung36_jcon_lists/icn_181_elem_0 Ljava/lang/Object;
    invokevirtual java/util/ArrayList/add(Ljava/lang/Object;)Z
    pop
;  INT
icn_183_α:
    ldc2_w 2
    goto icn_181_mke_1
icn_183_β:
    goto icn_168_α
    goto icn_183_α
icn_181_mke_1:
    invokestatic java/lang/Long/valueOf(J)Ljava/lang/Long;
    putstatic rung36_jcon_lists/icn_181_elem_1 Ljava/lang/Object;
    getstatic rung36_jcon_lists/icn_181_mklist Ljava/util/ArrayList;
    getstatic rung36_jcon_lists/icn_181_elem_1 Ljava/lang/Object;
    invokevirtual java/util/ArrayList/add(Ljava/lang/Object;)Z
    pop
;  INT
icn_184_α:
    ldc2_w 3
    goto icn_181_mke_2
icn_184_β:
    goto icn_168_α
    goto icn_184_α
icn_181_mke_2:
    invokestatic java/lang/Long/valueOf(J)Ljava/lang/Long;
    putstatic rung36_jcon_lists/icn_181_elem_2 Ljava/lang/Object;
    getstatic rung36_jcon_lists/icn_181_mklist Ljava/util/ArrayList;
    getstatic rung36_jcon_lists/icn_181_elem_2 Ljava/lang/Object;
    invokevirtual java/util/ArrayList/add(Ljava/lang/Object;)Z
    pop
;  INT
icn_185_α:
    ldc2_w 4
    goto icn_181_mke_3
icn_185_β:
    goto icn_168_α
    goto icn_185_α
icn_181_mke_3:
    invokestatic java/lang/Long/valueOf(J)Ljava/lang/Long;
    putstatic rung36_jcon_lists/icn_181_elem_3 Ljava/lang/Object;
    getstatic rung36_jcon_lists/icn_181_mklist Ljava/util/ArrayList;
    getstatic rung36_jcon_lists/icn_181_elem_3 Ljava/lang/Object;
    invokevirtual java/util/ArrayList/add(Ljava/lang/Object;)Z
    pop
;  INT
icn_186_α:
    ldc2_w 5
    goto icn_181_mke_4
icn_186_β:
    goto icn_168_α
    goto icn_186_α
icn_181_mke_4:
    invokestatic java/lang/Long/valueOf(J)Ljava/lang/Long;
    putstatic rung36_jcon_lists/icn_181_elem_4 Ljava/lang/Object;
    getstatic rung36_jcon_lists/icn_181_mklist Ljava/util/ArrayList;
    getstatic rung36_jcon_lists/icn_181_elem_4 Ljava/lang/Object;
    invokevirtual java/util/ArrayList/add(Ljava/lang/Object;)Z
    pop
    getstatic rung36_jcon_lists/icn_181_mklist Ljava/util/ArrayList;
    goto icn_180_store
icn_181_β:
    goto icn_168_α
icn_180_α:
    goto icn_181_α
icn_180_β:
    goto icn_181_β
icn_180_store:
    putstatic rung36_jcon_lists/icn_pv_main_x Ljava/util/ArrayList;
    getstatic rung36_jcon_lists/icn_pv_main_x Ljava/util/ArrayList;
    goto icn_main_s40_sdrain
icn_main_s40_sdrain:
    pop
    goto icn_168_α
;  VAR
icn_188_α:
    getstatic rung36_jcon_lists/icn_pv_main_x Ljava/util/ArrayList;
    goto icn_187_arg1
icn_188_β:
    goto icn_180_α
icn_187_arg1:
    putstatic rung36_jcon_lists/icn_arg_1 J
    goto icn_187_docall
;  STR
icn_189_α:
    ldc "M"
    goto icn_187_arg0
icn_189_β:
    goto icn_180_α
icn_187_arg0:
    putstatic rung36_jcon_lists/icn_arg_str_0 Ljava/lang/String;
    lconst_0
    putstatic rung36_jcon_lists/icn_arg_0 J
    goto icn_188_α
icn_187_α:
    goto icn_189_α
icn_187_β:
    goto icn_188_β
icn_187_docall:
    getstatic rung36_jcon_lists/icn_pv_main_y J
    lstore 155
    getstatic rung36_jcon_lists/icn_41_alt_val J
    lstore 157
    getstatic rung36_jcon_lists/icn_50_alt_val J
    lstore 159
    getstatic rung36_jcon_lists/icn_102_alt_val J
    lstore 161
    getstatic rung36_jcon_lists/icn_107_alt_val J
    lstore 163
    getstatic rung36_jcon_lists/icn_112_alt_val J
    lstore 165
    getstatic rung36_jcon_lists/icn_119_alt_val J
    lstore 167
    getstatic rung36_jcon_lists/icn_126_alt_val J
    lstore 169
    getstatic rung36_jcon_lists/icn_132_alt_val J
    lstore 171
    getstatic rung36_jcon_lists/icn_pv_main_i J
    lstore 173
    getstatic rung36_jcon_lists/icn_155_lsa_i J
    lstore 175
    getstatic rung36_jcon_lists/icn_155_lsa_v J
    lstore 177
    getstatic rung36_jcon_lists/icn_158_I J
    lstore 179
    getstatic rung36_jcon_lists/icn_158_bound J
    lstore 181
    getstatic rung36_jcon_lists/icn_158_e1cur J
    lstore 183
    getstatic rung36_jcon_lists/icn_158_e1val J
    lstore 185
    getstatic rung36_jcon_lists/icn_158_e2val J
    lstore 187
    getstatic rung36_jcon_lists/icn_160_binop_lc J
    lstore 189
    getstatic rung36_jcon_lists/icn_160_binop_rc J
    lstore 191
    getstatic rung36_jcon_lists/icn_171_lsa_i J
    lstore 193
    getstatic rung36_jcon_lists/icn_171_lsa_v J
    lstore 195
    getstatic rung36_jcon_lists/icn_174_I J
    lstore 197
    getstatic rung36_jcon_lists/icn_174_bound J
    lstore 199
    getstatic rung36_jcon_lists/icn_174_e1cur J
    lstore 201
    getstatic rung36_jcon_lists/icn_174_e1val J
    lstore 203
    getstatic rung36_jcon_lists/icn_174_e2val J
    lstore 205
    getstatic rung36_jcon_lists/icn_175_binop_lc J
    lstore 207
    getstatic rung36_jcon_lists/icn_175_binop_rc J
    lstore 209
    invokestatic rung36_jcon_lists/icn_limage()V
    lload 155
    putstatic rung36_jcon_lists/icn_pv_main_y J
    lload 157
    putstatic rung36_jcon_lists/icn_41_alt_val J
    lload 159
    putstatic rung36_jcon_lists/icn_50_alt_val J
    lload 161
    putstatic rung36_jcon_lists/icn_102_alt_val J
    lload 163
    putstatic rung36_jcon_lists/icn_107_alt_val J
    lload 165
    putstatic rung36_jcon_lists/icn_112_alt_val J
    lload 167
    putstatic rung36_jcon_lists/icn_119_alt_val J
    lload 169
    putstatic rung36_jcon_lists/icn_126_alt_val J
    lload 171
    putstatic rung36_jcon_lists/icn_132_alt_val J
    lload 173
    putstatic rung36_jcon_lists/icn_pv_main_i J
    lload 175
    putstatic rung36_jcon_lists/icn_155_lsa_i J
    lload 177
    putstatic rung36_jcon_lists/icn_155_lsa_v J
    lload 179
    putstatic rung36_jcon_lists/icn_158_I J
    lload 181
    putstatic rung36_jcon_lists/icn_158_bound J
    lload 183
    putstatic rung36_jcon_lists/icn_158_e1cur J
    lload 185
    putstatic rung36_jcon_lists/icn_158_e1val J
    lload 187
    putstatic rung36_jcon_lists/icn_158_e2val J
    lload 189
    putstatic rung36_jcon_lists/icn_160_binop_lc J
    lload 191
    putstatic rung36_jcon_lists/icn_160_binop_rc J
    lload 193
    putstatic rung36_jcon_lists/icn_171_lsa_i J
    lload 195
    putstatic rung36_jcon_lists/icn_171_lsa_v J
    lload 197
    putstatic rung36_jcon_lists/icn_174_I J
    lload 199
    putstatic rung36_jcon_lists/icn_174_bound J
    lload 201
    putstatic rung36_jcon_lists/icn_174_e1cur J
    lload 203
    putstatic rung36_jcon_lists/icn_174_e1val J
    lload 205
    putstatic rung36_jcon_lists/icn_174_e2val J
    lload 207
    putstatic rung36_jcon_lists/icn_175_binop_lc J
    lload 209
    putstatic rung36_jcon_lists/icn_175_binop_rc J
    getstatic rung36_jcon_lists/icn_failed B
    ifne icn_187_after_call
    getstatic rung36_jcon_lists/icn_retval J
    goto icn_main_s39_sdrain
icn_187_after_call:
    goto icn_180_α
icn_main_s39_sdrain:
    pop2
    goto icn_180_α
;  INT
icn_192_α:
    ldc2_w 7
    goto icn_191_store
icn_192_β:
    goto icn_187_α
icn_191_α:
    goto icn_192_α
icn_191_β:
    goto icn_192_β
icn_191_store:
    pop2
    lconst_0
    goto icn_190_gdrain
icn_190_gdrain:
    pop2
icn_190_pump:
    goto icn_191_β
icn_190_α:
    goto icn_191_α
icn_190_β:
    goto icn_187_α
;  VAR
icn_194_α:
    getstatic rung36_jcon_lists/icn_pv_main_x Ljava/util/ArrayList;
    goto icn_193_arg1
icn_194_β:
    goto icn_190_α
icn_193_arg1:
    putstatic rung36_jcon_lists/icn_arg_1 J
    goto icn_193_docall
;  STR
icn_195_α:
    ldc "L"
    goto icn_193_arg0
icn_195_β:
    goto icn_190_α
icn_193_arg0:
    putstatic rung36_jcon_lists/icn_arg_str_0 Ljava/lang/String;
    lconst_0
    putstatic rung36_jcon_lists/icn_arg_0 J
    goto icn_194_α
icn_193_α:
    goto icn_195_α
icn_193_β:
    goto icn_194_β
icn_193_docall:
    getstatic rung36_jcon_lists/icn_pv_main_y J
    lstore 155
    getstatic rung36_jcon_lists/icn_41_alt_val J
    lstore 157
    getstatic rung36_jcon_lists/icn_50_alt_val J
    lstore 159
    getstatic rung36_jcon_lists/icn_102_alt_val J
    lstore 161
    getstatic rung36_jcon_lists/icn_107_alt_val J
    lstore 163
    getstatic rung36_jcon_lists/icn_112_alt_val J
    lstore 165
    getstatic rung36_jcon_lists/icn_119_alt_val J
    lstore 167
    getstatic rung36_jcon_lists/icn_126_alt_val J
    lstore 169
    getstatic rung36_jcon_lists/icn_132_alt_val J
    lstore 171
    getstatic rung36_jcon_lists/icn_pv_main_i J
    lstore 173
    getstatic rung36_jcon_lists/icn_155_lsa_i J
    lstore 175
    getstatic rung36_jcon_lists/icn_155_lsa_v J
    lstore 177
    getstatic rung36_jcon_lists/icn_158_I J
    lstore 179
    getstatic rung36_jcon_lists/icn_158_bound J
    lstore 181
    getstatic rung36_jcon_lists/icn_158_e1cur J
    lstore 183
    getstatic rung36_jcon_lists/icn_158_e1val J
    lstore 185
    getstatic rung36_jcon_lists/icn_158_e2val J
    lstore 187
    getstatic rung36_jcon_lists/icn_160_binop_lc J
    lstore 189
    getstatic rung36_jcon_lists/icn_160_binop_rc J
    lstore 191
    getstatic rung36_jcon_lists/icn_171_lsa_i J
    lstore 193
    getstatic rung36_jcon_lists/icn_171_lsa_v J
    lstore 195
    getstatic rung36_jcon_lists/icn_174_I J
    lstore 197
    getstatic rung36_jcon_lists/icn_174_bound J
    lstore 199
    getstatic rung36_jcon_lists/icn_174_e1cur J
    lstore 201
    getstatic rung36_jcon_lists/icn_174_e1val J
    lstore 203
    getstatic rung36_jcon_lists/icn_174_e2val J
    lstore 205
    getstatic rung36_jcon_lists/icn_175_binop_lc J
    lstore 207
    getstatic rung36_jcon_lists/icn_175_binop_rc J
    lstore 209
    invokestatic rung36_jcon_lists/icn_limage()V
    lload 155
    putstatic rung36_jcon_lists/icn_pv_main_y J
    lload 157
    putstatic rung36_jcon_lists/icn_41_alt_val J
    lload 159
    putstatic rung36_jcon_lists/icn_50_alt_val J
    lload 161
    putstatic rung36_jcon_lists/icn_102_alt_val J
    lload 163
    putstatic rung36_jcon_lists/icn_107_alt_val J
    lload 165
    putstatic rung36_jcon_lists/icn_112_alt_val J
    lload 167
    putstatic rung36_jcon_lists/icn_119_alt_val J
    lload 169
    putstatic rung36_jcon_lists/icn_126_alt_val J
    lload 171
    putstatic rung36_jcon_lists/icn_132_alt_val J
    lload 173
    putstatic rung36_jcon_lists/icn_pv_main_i J
    lload 175
    putstatic rung36_jcon_lists/icn_155_lsa_i J
    lload 177
    putstatic rung36_jcon_lists/icn_155_lsa_v J
    lload 179
    putstatic rung36_jcon_lists/icn_158_I J
    lload 181
    putstatic rung36_jcon_lists/icn_158_bound J
    lload 183
    putstatic rung36_jcon_lists/icn_158_e1cur J
    lload 185
    putstatic rung36_jcon_lists/icn_158_e1val J
    lload 187
    putstatic rung36_jcon_lists/icn_158_e2val J
    lload 189
    putstatic rung36_jcon_lists/icn_160_binop_lc J
    lload 191
    putstatic rung36_jcon_lists/icn_160_binop_rc J
    lload 193
    putstatic rung36_jcon_lists/icn_171_lsa_i J
    lload 195
    putstatic rung36_jcon_lists/icn_171_lsa_v J
    lload 197
    putstatic rung36_jcon_lists/icn_174_I J
    lload 199
    putstatic rung36_jcon_lists/icn_174_bound J
    lload 201
    putstatic rung36_jcon_lists/icn_174_e1cur J
    lload 203
    putstatic rung36_jcon_lists/icn_174_e1val J
    lload 205
    putstatic rung36_jcon_lists/icn_174_e2val J
    lload 207
    putstatic rung36_jcon_lists/icn_175_binop_lc J
    lload 209
    putstatic rung36_jcon_lists/icn_175_binop_rc J
    getstatic rung36_jcon_lists/icn_failed B
    ifne icn_193_after_call
    getstatic rung36_jcon_lists/icn_retval J
    goto icn_main_s37_sdrain
icn_193_after_call:
    goto icn_190_α
icn_main_s37_sdrain:
    pop2
    goto icn_190_α
;  VAR
icn_198_α:
    getstatic rung36_jcon_lists/icn_pv_main_x Ljava/util/ArrayList;
    goto icn_197_lr
icn_198_β:
    goto icn_193_α
;  INT
icn_199_α:
    ldc2_w 20
    goto icn_197_vr
icn_199_β:
    goto icn_193_α
icn_197_α:
    goto icn_198_α
icn_197_β:
    goto icn_193_α
icn_197_lr:
    putstatic rung36_jcon_lists/icn_197_pushlist Ljava/util/ArrayList;
    goto icn_199_α
icn_197_vr:
    invokestatic java/lang/Long/valueOf(J)Ljava/lang/Long;
    putstatic rung36_jcon_lists/icn_197_pushval Ljava/lang/Object;
    getstatic rung36_jcon_lists/icn_197_pushlist Ljava/util/ArrayList;
    iconst_0
    getstatic rung36_jcon_lists/icn_197_pushval Ljava/lang/Object;
    invokevirtual java/util/ArrayList/add(ILjava/lang/Object;)V
    getstatic rung36_jcon_lists/icn_197_pushlist Ljava/util/ArrayList;
    goto icn_196_lr
;  INT
icn_200_α:
    ldc2_w 22
    goto icn_196_vr
icn_200_β:
    goto icn_193_α
icn_196_α:
    goto icn_197_α
icn_196_β:
    goto icn_193_α
icn_196_lr:
    putstatic rung36_jcon_lists/icn_196_pushlist Ljava/util/ArrayList;
    goto icn_200_α
icn_196_vr:
    invokestatic java/lang/Long/valueOf(J)Ljava/lang/Long;
    putstatic rung36_jcon_lists/icn_196_pushval Ljava/lang/Object;
    getstatic rung36_jcon_lists/icn_196_pushlist Ljava/util/ArrayList;
    getstatic rung36_jcon_lists/icn_196_pushval Ljava/lang/Object;
    invokevirtual java/util/ArrayList/add(Ljava/lang/Object;)Z
    pop
    getstatic rung36_jcon_lists/icn_196_pushlist Ljava/util/ArrayList;
    goto icn_main_s36_sdrain
icn_main_s36_sdrain:
    pop
    goto icn_193_α
;  VAR
icn_202_α:
    getstatic rung36_jcon_lists/icn_pv_main_x Ljava/util/ArrayList;
    goto icn_201_arg1
icn_202_β:
    goto icn_196_α
icn_201_arg1:
    putstatic rung36_jcon_lists/icn_arg_1 J
    goto icn_201_docall
;  STR
icn_203_α:
    ldc "K"
    goto icn_201_arg0
icn_203_β:
    goto icn_196_α
icn_201_arg0:
    putstatic rung36_jcon_lists/icn_arg_str_0 Ljava/lang/String;
    lconst_0
    putstatic rung36_jcon_lists/icn_arg_0 J
    goto icn_202_α
icn_201_α:
    goto icn_203_α
icn_201_β:
    goto icn_202_β
icn_201_docall:
    getstatic rung36_jcon_lists/icn_pv_main_y J
    lstore 155
    getstatic rung36_jcon_lists/icn_41_alt_val J
    lstore 157
    getstatic rung36_jcon_lists/icn_50_alt_val J
    lstore 159
    getstatic rung36_jcon_lists/icn_102_alt_val J
    lstore 161
    getstatic rung36_jcon_lists/icn_107_alt_val J
    lstore 163
    getstatic rung36_jcon_lists/icn_112_alt_val J
    lstore 165
    getstatic rung36_jcon_lists/icn_119_alt_val J
    lstore 167
    getstatic rung36_jcon_lists/icn_126_alt_val J
    lstore 169
    getstatic rung36_jcon_lists/icn_132_alt_val J
    lstore 171
    getstatic rung36_jcon_lists/icn_pv_main_i J
    lstore 173
    getstatic rung36_jcon_lists/icn_155_lsa_i J
    lstore 175
    getstatic rung36_jcon_lists/icn_155_lsa_v J
    lstore 177
    getstatic rung36_jcon_lists/icn_158_I J
    lstore 179
    getstatic rung36_jcon_lists/icn_158_bound J
    lstore 181
    getstatic rung36_jcon_lists/icn_158_e1cur J
    lstore 183
    getstatic rung36_jcon_lists/icn_158_e1val J
    lstore 185
    getstatic rung36_jcon_lists/icn_158_e2val J
    lstore 187
    getstatic rung36_jcon_lists/icn_160_binop_lc J
    lstore 189
    getstatic rung36_jcon_lists/icn_160_binop_rc J
    lstore 191
    getstatic rung36_jcon_lists/icn_171_lsa_i J
    lstore 193
    getstatic rung36_jcon_lists/icn_171_lsa_v J
    lstore 195
    getstatic rung36_jcon_lists/icn_174_I J
    lstore 197
    getstatic rung36_jcon_lists/icn_174_bound J
    lstore 199
    getstatic rung36_jcon_lists/icn_174_e1cur J
    lstore 201
    getstatic rung36_jcon_lists/icn_174_e1val J
    lstore 203
    getstatic rung36_jcon_lists/icn_174_e2val J
    lstore 205
    getstatic rung36_jcon_lists/icn_175_binop_lc J
    lstore 207
    getstatic rung36_jcon_lists/icn_175_binop_rc J
    lstore 209
    invokestatic rung36_jcon_lists/icn_limage()V
    lload 155
    putstatic rung36_jcon_lists/icn_pv_main_y J
    lload 157
    putstatic rung36_jcon_lists/icn_41_alt_val J
    lload 159
    putstatic rung36_jcon_lists/icn_50_alt_val J
    lload 161
    putstatic rung36_jcon_lists/icn_102_alt_val J
    lload 163
    putstatic rung36_jcon_lists/icn_107_alt_val J
    lload 165
    putstatic rung36_jcon_lists/icn_112_alt_val J
    lload 167
    putstatic rung36_jcon_lists/icn_119_alt_val J
    lload 169
    putstatic rung36_jcon_lists/icn_126_alt_val J
    lload 171
    putstatic rung36_jcon_lists/icn_132_alt_val J
    lload 173
    putstatic rung36_jcon_lists/icn_pv_main_i J
    lload 175
    putstatic rung36_jcon_lists/icn_155_lsa_i J
    lload 177
    putstatic rung36_jcon_lists/icn_155_lsa_v J
    lload 179
    putstatic rung36_jcon_lists/icn_158_I J
    lload 181
    putstatic rung36_jcon_lists/icn_158_bound J
    lload 183
    putstatic rung36_jcon_lists/icn_158_e1cur J
    lload 185
    putstatic rung36_jcon_lists/icn_158_e1val J
    lload 187
    putstatic rung36_jcon_lists/icn_158_e2val J
    lload 189
    putstatic rung36_jcon_lists/icn_160_binop_lc J
    lload 191
    putstatic rung36_jcon_lists/icn_160_binop_rc J
    lload 193
    putstatic rung36_jcon_lists/icn_171_lsa_i J
    lload 195
    putstatic rung36_jcon_lists/icn_171_lsa_v J
    lload 197
    putstatic rung36_jcon_lists/icn_174_I J
    lload 199
    putstatic rung36_jcon_lists/icn_174_bound J
    lload 201
    putstatic rung36_jcon_lists/icn_174_e1cur J
    lload 203
    putstatic rung36_jcon_lists/icn_174_e1val J
    lload 205
    putstatic rung36_jcon_lists/icn_174_e2val J
    lload 207
    putstatic rung36_jcon_lists/icn_175_binop_lc J
    lload 209
    putstatic rung36_jcon_lists/icn_175_binop_rc J
    getstatic rung36_jcon_lists/icn_failed B
    ifne icn_201_after_call
    getstatic rung36_jcon_lists/icn_retval J
    goto icn_main_s35_sdrain
icn_201_after_call:
    goto icn_196_α
icn_main_s35_sdrain:
    pop2
    goto icn_196_α
;  VAR
icn_206_α:
    getstatic rung36_jcon_lists/icn_pv_main_x Ljava/util/ArrayList;
    goto icn_205_lr
icn_206_β:
    goto icn_201_α
;  INT
icn_207_α:
    ldc2_w 16
    goto icn_205_vr
icn_207_β:
    goto icn_201_α
icn_205_α:
    goto icn_206_α
icn_205_β:
    goto icn_201_α
icn_205_lr:
    putstatic rung36_jcon_lists/icn_205_pushlist Ljava/util/ArrayList;
    goto icn_207_α
icn_205_vr:
    invokestatic java/lang/Long/valueOf(J)Ljava/lang/Long;
    putstatic rung36_jcon_lists/icn_205_pushval Ljava/lang/Object;
    getstatic rung36_jcon_lists/icn_205_pushlist Ljava/util/ArrayList;
    getstatic rung36_jcon_lists/icn_205_pushval Ljava/lang/Object;
    invokevirtual java/util/ArrayList/add(Ljava/lang/Object;)Z
    pop
    getstatic rung36_jcon_lists/icn_205_pushlist Ljava/util/ArrayList;
    goto icn_204_lr
;  INT
icn_208_α:
    ldc2_w 18
    goto icn_204_vr
icn_208_β:
    goto icn_201_α
icn_204_α:
    goto icn_205_α
icn_204_β:
    goto icn_201_α
icn_204_lr:
    putstatic rung36_jcon_lists/icn_204_pushlist Ljava/util/ArrayList;
    goto icn_208_α
icn_204_vr:
    invokestatic java/lang/Long/valueOf(J)Ljava/lang/Long;
    putstatic rung36_jcon_lists/icn_204_pushval Ljava/lang/Object;
    getstatic rung36_jcon_lists/icn_204_pushlist Ljava/util/ArrayList;
    getstatic rung36_jcon_lists/icn_204_pushval Ljava/lang/Object;
    invokevirtual java/util/ArrayList/add(Ljava/lang/Object;)Z
    pop
    getstatic rung36_jcon_lists/icn_204_pushlist Ljava/util/ArrayList;
    goto icn_main_s34_sdrain
icn_main_s34_sdrain:
    pop
    goto icn_201_α
;  VAR
icn_210_α:
    getstatic rung36_jcon_lists/icn_pv_main_x Ljava/util/ArrayList;
    goto icn_209_arg1
icn_210_β:
    goto icn_204_α
icn_209_arg1:
    putstatic rung36_jcon_lists/icn_arg_1 J
    goto icn_209_docall
;  STR
icn_211_α:
    ldc "J"
    goto icn_209_arg0
icn_211_β:
    goto icn_204_α
icn_209_arg0:
    putstatic rung36_jcon_lists/icn_arg_str_0 Ljava/lang/String;
    lconst_0
    putstatic rung36_jcon_lists/icn_arg_0 J
    goto icn_210_α
icn_209_α:
    goto icn_211_α
icn_209_β:
    goto icn_210_β
icn_209_docall:
    getstatic rung36_jcon_lists/icn_pv_main_y J
    lstore 155
    getstatic rung36_jcon_lists/icn_41_alt_val J
    lstore 157
    getstatic rung36_jcon_lists/icn_50_alt_val J
    lstore 159
    getstatic rung36_jcon_lists/icn_102_alt_val J
    lstore 161
    getstatic rung36_jcon_lists/icn_107_alt_val J
    lstore 163
    getstatic rung36_jcon_lists/icn_112_alt_val J
    lstore 165
    getstatic rung36_jcon_lists/icn_119_alt_val J
    lstore 167
    getstatic rung36_jcon_lists/icn_126_alt_val J
    lstore 169
    getstatic rung36_jcon_lists/icn_132_alt_val J
    lstore 171
    getstatic rung36_jcon_lists/icn_pv_main_i J
    lstore 173
    getstatic rung36_jcon_lists/icn_155_lsa_i J
    lstore 175
    getstatic rung36_jcon_lists/icn_155_lsa_v J
    lstore 177
    getstatic rung36_jcon_lists/icn_158_I J
    lstore 179
    getstatic rung36_jcon_lists/icn_158_bound J
    lstore 181
    getstatic rung36_jcon_lists/icn_158_e1cur J
    lstore 183
    getstatic rung36_jcon_lists/icn_158_e1val J
    lstore 185
    getstatic rung36_jcon_lists/icn_158_e2val J
    lstore 187
    getstatic rung36_jcon_lists/icn_160_binop_lc J
    lstore 189
    getstatic rung36_jcon_lists/icn_160_binop_rc J
    lstore 191
    getstatic rung36_jcon_lists/icn_171_lsa_i J
    lstore 193
    getstatic rung36_jcon_lists/icn_171_lsa_v J
    lstore 195
    getstatic rung36_jcon_lists/icn_174_I J
    lstore 197
    getstatic rung36_jcon_lists/icn_174_bound J
    lstore 199
    getstatic rung36_jcon_lists/icn_174_e1cur J
    lstore 201
    getstatic rung36_jcon_lists/icn_174_e1val J
    lstore 203
    getstatic rung36_jcon_lists/icn_174_e2val J
    lstore 205
    getstatic rung36_jcon_lists/icn_175_binop_lc J
    lstore 207
    getstatic rung36_jcon_lists/icn_175_binop_rc J
    lstore 209
    invokestatic rung36_jcon_lists/icn_limage()V
    lload 155
    putstatic rung36_jcon_lists/icn_pv_main_y J
    lload 157
    putstatic rung36_jcon_lists/icn_41_alt_val J
    lload 159
    putstatic rung36_jcon_lists/icn_50_alt_val J
    lload 161
    putstatic rung36_jcon_lists/icn_102_alt_val J
    lload 163
    putstatic rung36_jcon_lists/icn_107_alt_val J
    lload 165
    putstatic rung36_jcon_lists/icn_112_alt_val J
    lload 167
    putstatic rung36_jcon_lists/icn_119_alt_val J
    lload 169
    putstatic rung36_jcon_lists/icn_126_alt_val J
    lload 171
    putstatic rung36_jcon_lists/icn_132_alt_val J
    lload 173
    putstatic rung36_jcon_lists/icn_pv_main_i J
    lload 175
    putstatic rung36_jcon_lists/icn_155_lsa_i J
    lload 177
    putstatic rung36_jcon_lists/icn_155_lsa_v J
    lload 179
    putstatic rung36_jcon_lists/icn_158_I J
    lload 181
    putstatic rung36_jcon_lists/icn_158_bound J
    lload 183
    putstatic rung36_jcon_lists/icn_158_e1cur J
    lload 185
    putstatic rung36_jcon_lists/icn_158_e1val J
    lload 187
    putstatic rung36_jcon_lists/icn_158_e2val J
    lload 189
    putstatic rung36_jcon_lists/icn_160_binop_lc J
    lload 191
    putstatic rung36_jcon_lists/icn_160_binop_rc J
    lload 193
    putstatic rung36_jcon_lists/icn_171_lsa_i J
    lload 195
    putstatic rung36_jcon_lists/icn_171_lsa_v J
    lload 197
    putstatic rung36_jcon_lists/icn_174_I J
    lload 199
    putstatic rung36_jcon_lists/icn_174_bound J
    lload 201
    putstatic rung36_jcon_lists/icn_174_e1cur J
    lload 203
    putstatic rung36_jcon_lists/icn_174_e1val J
    lload 205
    putstatic rung36_jcon_lists/icn_174_e2val J
    lload 207
    putstatic rung36_jcon_lists/icn_175_binop_lc J
    lload 209
    putstatic rung36_jcon_lists/icn_175_binop_rc J
    getstatic rung36_jcon_lists/icn_failed B
    ifne icn_209_after_call
    getstatic rung36_jcon_lists/icn_retval J
    goto icn_main_s33_sdrain
icn_209_after_call:
    goto icn_204_α
icn_main_s33_sdrain:
    pop2
    goto icn_204_α
;  VAR
icn_213_α:
    getstatic rung36_jcon_lists/icn_pv_main_x Ljava/util/ArrayList;
    goto icn_212_lr
icn_213_β:
    goto icn_209_α
;  INT
icn_214_α:
    ldc2_w 13
    goto icn_212_vr
icn_214_β:
    goto icn_209_α
icn_212_α:
    goto icn_213_α
icn_212_β:
    goto icn_209_α
icn_212_lr:
    putstatic rung36_jcon_lists/icn_212_pushlist Ljava/util/ArrayList;
    goto icn_214_α
icn_212_vr:
    invokestatic java/lang/Long/valueOf(J)Ljava/lang/Long;
    putstatic rung36_jcon_lists/icn_212_pushval Ljava/lang/Object;
    getstatic rung36_jcon_lists/icn_212_pushlist Ljava/util/ArrayList;
    getstatic rung36_jcon_lists/icn_212_pushval Ljava/lang/Object;
    invokevirtual java/util/ArrayList/add(Ljava/lang/Object;)Z
    pop
    getstatic rung36_jcon_lists/icn_212_pushlist Ljava/util/ArrayList;
    goto icn_main_s32_sdrain
icn_main_s32_sdrain:
    pop
    goto icn_209_α
;  VAR
icn_216_α:
    getstatic rung36_jcon_lists/icn_pv_main_x Ljava/util/ArrayList;
    goto icn_215_arg1
icn_216_β:
    goto icn_212_α
icn_215_arg1:
    putstatic rung36_jcon_lists/icn_arg_1 J
    goto icn_215_docall
;  STR
icn_217_α:
    ldc "I"
    goto icn_215_arg0
icn_217_β:
    goto icn_212_α
icn_215_arg0:
    putstatic rung36_jcon_lists/icn_arg_str_0 Ljava/lang/String;
    lconst_0
    putstatic rung36_jcon_lists/icn_arg_0 J
    goto icn_216_α
icn_215_α:
    goto icn_217_α
icn_215_β:
    goto icn_216_β
icn_215_docall:
    getstatic rung36_jcon_lists/icn_pv_main_y J
    lstore 155
    getstatic rung36_jcon_lists/icn_41_alt_val J
    lstore 157
    getstatic rung36_jcon_lists/icn_50_alt_val J
    lstore 159
    getstatic rung36_jcon_lists/icn_102_alt_val J
    lstore 161
    getstatic rung36_jcon_lists/icn_107_alt_val J
    lstore 163
    getstatic rung36_jcon_lists/icn_112_alt_val J
    lstore 165
    getstatic rung36_jcon_lists/icn_119_alt_val J
    lstore 167
    getstatic rung36_jcon_lists/icn_126_alt_val J
    lstore 169
    getstatic rung36_jcon_lists/icn_132_alt_val J
    lstore 171
    getstatic rung36_jcon_lists/icn_pv_main_i J
    lstore 173
    getstatic rung36_jcon_lists/icn_155_lsa_i J
    lstore 175
    getstatic rung36_jcon_lists/icn_155_lsa_v J
    lstore 177
    getstatic rung36_jcon_lists/icn_158_I J
    lstore 179
    getstatic rung36_jcon_lists/icn_158_bound J
    lstore 181
    getstatic rung36_jcon_lists/icn_158_e1cur J
    lstore 183
    getstatic rung36_jcon_lists/icn_158_e1val J
    lstore 185
    getstatic rung36_jcon_lists/icn_158_e2val J
    lstore 187
    getstatic rung36_jcon_lists/icn_160_binop_lc J
    lstore 189
    getstatic rung36_jcon_lists/icn_160_binop_rc J
    lstore 191
    getstatic rung36_jcon_lists/icn_171_lsa_i J
    lstore 193
    getstatic rung36_jcon_lists/icn_171_lsa_v J
    lstore 195
    getstatic rung36_jcon_lists/icn_174_I J
    lstore 197
    getstatic rung36_jcon_lists/icn_174_bound J
    lstore 199
    getstatic rung36_jcon_lists/icn_174_e1cur J
    lstore 201
    getstatic rung36_jcon_lists/icn_174_e1val J
    lstore 203
    getstatic rung36_jcon_lists/icn_174_e2val J
    lstore 205
    getstatic rung36_jcon_lists/icn_175_binop_lc J
    lstore 207
    getstatic rung36_jcon_lists/icn_175_binop_rc J
    lstore 209
    invokestatic rung36_jcon_lists/icn_limage()V
    lload 155
    putstatic rung36_jcon_lists/icn_pv_main_y J
    lload 157
    putstatic rung36_jcon_lists/icn_41_alt_val J
    lload 159
    putstatic rung36_jcon_lists/icn_50_alt_val J
    lload 161
    putstatic rung36_jcon_lists/icn_102_alt_val J
    lload 163
    putstatic rung36_jcon_lists/icn_107_alt_val J
    lload 165
    putstatic rung36_jcon_lists/icn_112_alt_val J
    lload 167
    putstatic rung36_jcon_lists/icn_119_alt_val J
    lload 169
    putstatic rung36_jcon_lists/icn_126_alt_val J
    lload 171
    putstatic rung36_jcon_lists/icn_132_alt_val J
    lload 173
    putstatic rung36_jcon_lists/icn_pv_main_i J
    lload 175
    putstatic rung36_jcon_lists/icn_155_lsa_i J
    lload 177
    putstatic rung36_jcon_lists/icn_155_lsa_v J
    lload 179
    putstatic rung36_jcon_lists/icn_158_I J
    lload 181
    putstatic rung36_jcon_lists/icn_158_bound J
    lload 183
    putstatic rung36_jcon_lists/icn_158_e1cur J
    lload 185
    putstatic rung36_jcon_lists/icn_158_e1val J
    lload 187
    putstatic rung36_jcon_lists/icn_158_e2val J
    lload 189
    putstatic rung36_jcon_lists/icn_160_binop_lc J
    lload 191
    putstatic rung36_jcon_lists/icn_160_binop_rc J
    lload 193
    putstatic rung36_jcon_lists/icn_171_lsa_i J
    lload 195
    putstatic rung36_jcon_lists/icn_171_lsa_v J
    lload 197
    putstatic rung36_jcon_lists/icn_174_I J
    lload 199
    putstatic rung36_jcon_lists/icn_174_bound J
    lload 201
    putstatic rung36_jcon_lists/icn_174_e1cur J
    lload 203
    putstatic rung36_jcon_lists/icn_174_e1val J
    lload 205
    putstatic rung36_jcon_lists/icn_174_e2val J
    lload 207
    putstatic rung36_jcon_lists/icn_175_binop_lc J
    lload 209
    putstatic rung36_jcon_lists/icn_175_binop_rc J
    getstatic rung36_jcon_lists/icn_failed B
    ifne icn_215_after_call
    getstatic rung36_jcon_lists/icn_retval J
    goto icn_main_s31_sdrain
icn_215_after_call:
    goto icn_212_α
icn_main_s31_sdrain:
    pop2
    goto icn_212_α
;  VAR
icn_219_α:
    getstatic rung36_jcon_lists/icn_pv_main_x Ljava/util/ArrayList;
    goto icn_218_lr
icn_219_β:
    goto icn_215_α
;  INT
icn_220_α:
    ldc2_w 12
    goto icn_218_vr
icn_220_β:
    goto icn_215_α
icn_218_α:
    goto icn_219_α
icn_218_β:
    goto icn_215_α
icn_218_lr:
    putstatic rung36_jcon_lists/icn_218_pushlist Ljava/util/ArrayList;
    goto icn_220_α
icn_218_vr:
    invokestatic java/lang/Long/valueOf(J)Ljava/lang/Long;
    putstatic rung36_jcon_lists/icn_218_pushval Ljava/lang/Object;
    getstatic rung36_jcon_lists/icn_218_pushlist Ljava/util/ArrayList;
    getstatic rung36_jcon_lists/icn_218_pushval Ljava/lang/Object;
    invokevirtual java/util/ArrayList/add(Ljava/lang/Object;)Z
    pop
    getstatic rung36_jcon_lists/icn_218_pushlist Ljava/util/ArrayList;
    goto icn_main_s30_sdrain
icn_main_s30_sdrain:
    pop
    goto icn_215_α
;  VAR
icn_222_α:
    getstatic rung36_jcon_lists/icn_pv_main_x Ljava/util/ArrayList;
    goto icn_221_arg1
icn_222_β:
    goto icn_218_α
icn_221_arg1:
    putstatic rung36_jcon_lists/icn_arg_1 J
    goto icn_221_docall
;  STR
icn_223_α:
    ldc "H"
    goto icn_221_arg0
icn_223_β:
    goto icn_218_α
icn_221_arg0:
    putstatic rung36_jcon_lists/icn_arg_str_0 Ljava/lang/String;
    lconst_0
    putstatic rung36_jcon_lists/icn_arg_0 J
    goto icn_222_α
icn_221_α:
    goto icn_223_α
icn_221_β:
    goto icn_222_β
icn_221_docall:
    getstatic rung36_jcon_lists/icn_pv_main_y J
    lstore 155
    getstatic rung36_jcon_lists/icn_41_alt_val J
    lstore 157
    getstatic rung36_jcon_lists/icn_50_alt_val J
    lstore 159
    getstatic rung36_jcon_lists/icn_102_alt_val J
    lstore 161
    getstatic rung36_jcon_lists/icn_107_alt_val J
    lstore 163
    getstatic rung36_jcon_lists/icn_112_alt_val J
    lstore 165
    getstatic rung36_jcon_lists/icn_119_alt_val J
    lstore 167
    getstatic rung36_jcon_lists/icn_126_alt_val J
    lstore 169
    getstatic rung36_jcon_lists/icn_132_alt_val J
    lstore 171
    getstatic rung36_jcon_lists/icn_pv_main_i J
    lstore 173
    getstatic rung36_jcon_lists/icn_155_lsa_i J
    lstore 175
    getstatic rung36_jcon_lists/icn_155_lsa_v J
    lstore 177
    getstatic rung36_jcon_lists/icn_158_I J
    lstore 179
    getstatic rung36_jcon_lists/icn_158_bound J
    lstore 181
    getstatic rung36_jcon_lists/icn_158_e1cur J
    lstore 183
    getstatic rung36_jcon_lists/icn_158_e1val J
    lstore 185
    getstatic rung36_jcon_lists/icn_158_e2val J
    lstore 187
    getstatic rung36_jcon_lists/icn_160_binop_lc J
    lstore 189
    getstatic rung36_jcon_lists/icn_160_binop_rc J
    lstore 191
    getstatic rung36_jcon_lists/icn_171_lsa_i J
    lstore 193
    getstatic rung36_jcon_lists/icn_171_lsa_v J
    lstore 195
    getstatic rung36_jcon_lists/icn_174_I J
    lstore 197
    getstatic rung36_jcon_lists/icn_174_bound J
    lstore 199
    getstatic rung36_jcon_lists/icn_174_e1cur J
    lstore 201
    getstatic rung36_jcon_lists/icn_174_e1val J
    lstore 203
    getstatic rung36_jcon_lists/icn_174_e2val J
    lstore 205
    getstatic rung36_jcon_lists/icn_175_binop_lc J
    lstore 207
    getstatic rung36_jcon_lists/icn_175_binop_rc J
    lstore 209
    invokestatic rung36_jcon_lists/icn_limage()V
    lload 155
    putstatic rung36_jcon_lists/icn_pv_main_y J
    lload 157
    putstatic rung36_jcon_lists/icn_41_alt_val J
    lload 159
    putstatic rung36_jcon_lists/icn_50_alt_val J
    lload 161
    putstatic rung36_jcon_lists/icn_102_alt_val J
    lload 163
    putstatic rung36_jcon_lists/icn_107_alt_val J
    lload 165
    putstatic rung36_jcon_lists/icn_112_alt_val J
    lload 167
    putstatic rung36_jcon_lists/icn_119_alt_val J
    lload 169
    putstatic rung36_jcon_lists/icn_126_alt_val J
    lload 171
    putstatic rung36_jcon_lists/icn_132_alt_val J
    lload 173
    putstatic rung36_jcon_lists/icn_pv_main_i J
    lload 175
    putstatic rung36_jcon_lists/icn_155_lsa_i J
    lload 177
    putstatic rung36_jcon_lists/icn_155_lsa_v J
    lload 179
    putstatic rung36_jcon_lists/icn_158_I J
    lload 181
    putstatic rung36_jcon_lists/icn_158_bound J
    lload 183
    putstatic rung36_jcon_lists/icn_158_e1cur J
    lload 185
    putstatic rung36_jcon_lists/icn_158_e1val J
    lload 187
    putstatic rung36_jcon_lists/icn_158_e2val J
    lload 189
    putstatic rung36_jcon_lists/icn_160_binop_lc J
    lload 191
    putstatic rung36_jcon_lists/icn_160_binop_rc J
    lload 193
    putstatic rung36_jcon_lists/icn_171_lsa_i J
    lload 195
    putstatic rung36_jcon_lists/icn_171_lsa_v J
    lload 197
    putstatic rung36_jcon_lists/icn_174_I J
    lload 199
    putstatic rung36_jcon_lists/icn_174_bound J
    lload 201
    putstatic rung36_jcon_lists/icn_174_e1cur J
    lload 203
    putstatic rung36_jcon_lists/icn_174_e1val J
    lload 205
    putstatic rung36_jcon_lists/icn_174_e2val J
    lload 207
    putstatic rung36_jcon_lists/icn_175_binop_lc J
    lload 209
    putstatic rung36_jcon_lists/icn_175_binop_rc J
    getstatic rung36_jcon_lists/icn_failed B
    ifne icn_221_after_call
    getstatic rung36_jcon_lists/icn_retval J
    goto icn_main_s29_sdrain
icn_221_after_call:
    goto icn_218_α
icn_main_s29_sdrain:
    pop2
    goto icn_218_α
;  VAR
icn_226_α:
    getstatic rung36_jcon_lists/icn_pv_main_x Ljava/util/ArrayList;
    goto icn_225_lr
icn_226_β:
    goto icn_221_α
;  INT
icn_227_α:
    ldc2_w 8
    goto icn_225_vr
icn_227_β:
    goto icn_221_α
icn_225_α:
    goto icn_226_α
icn_225_β:
    goto icn_221_α
icn_225_lr:
    putstatic rung36_jcon_lists/icn_225_pushlist Ljava/util/ArrayList;
    goto icn_227_α
icn_225_vr:
    invokestatic java/lang/Long/valueOf(J)Ljava/lang/Long;
    putstatic rung36_jcon_lists/icn_225_pushval Ljava/lang/Object;
    getstatic rung36_jcon_lists/icn_225_pushlist Ljava/util/ArrayList;
    iconst_0
    getstatic rung36_jcon_lists/icn_225_pushval Ljava/lang/Object;
    invokevirtual java/util/ArrayList/add(ILjava/lang/Object;)V
    getstatic rung36_jcon_lists/icn_225_pushlist Ljava/util/ArrayList;
    goto icn_224_lr
;  INT
icn_228_α:
    ldc2_w 10
    goto icn_224_vr
icn_228_β:
    goto icn_221_α
icn_224_α:
    goto icn_225_α
icn_224_β:
    goto icn_221_α
icn_224_lr:
    putstatic rung36_jcon_lists/icn_224_pushlist Ljava/util/ArrayList;
    goto icn_228_α
icn_224_vr:
    invokestatic java/lang/Long/valueOf(J)Ljava/lang/Long;
    putstatic rung36_jcon_lists/icn_224_pushval Ljava/lang/Object;
    getstatic rung36_jcon_lists/icn_224_pushlist Ljava/util/ArrayList;
    iconst_0
    getstatic rung36_jcon_lists/icn_224_pushval Ljava/lang/Object;
    invokevirtual java/util/ArrayList/add(ILjava/lang/Object;)V
    getstatic rung36_jcon_lists/icn_224_pushlist Ljava/util/ArrayList;
    goto icn_main_s28_sdrain
icn_main_s28_sdrain:
    pop
    goto icn_221_α
;  VAR
icn_230_α:
    getstatic rung36_jcon_lists/icn_pv_main_x Ljava/util/ArrayList;
    goto icn_229_arg1
icn_230_β:
    goto icn_224_α
icn_229_arg1:
    putstatic rung36_jcon_lists/icn_arg_1 J
    goto icn_229_docall
;  STR
icn_231_α:
    ldc "G"
    goto icn_229_arg0
icn_231_β:
    goto icn_224_α
icn_229_arg0:
    putstatic rung36_jcon_lists/icn_arg_str_0 Ljava/lang/String;
    lconst_0
    putstatic rung36_jcon_lists/icn_arg_0 J
    goto icn_230_α
icn_229_α:
    goto icn_231_α
icn_229_β:
    goto icn_230_β
icn_229_docall:
    getstatic rung36_jcon_lists/icn_pv_main_y J
    lstore 155
    getstatic rung36_jcon_lists/icn_41_alt_val J
    lstore 157
    getstatic rung36_jcon_lists/icn_50_alt_val J
    lstore 159
    getstatic rung36_jcon_lists/icn_102_alt_val J
    lstore 161
    getstatic rung36_jcon_lists/icn_107_alt_val J
    lstore 163
    getstatic rung36_jcon_lists/icn_112_alt_val J
    lstore 165
    getstatic rung36_jcon_lists/icn_119_alt_val J
    lstore 167
    getstatic rung36_jcon_lists/icn_126_alt_val J
    lstore 169
    getstatic rung36_jcon_lists/icn_132_alt_val J
    lstore 171
    getstatic rung36_jcon_lists/icn_pv_main_i J
    lstore 173
    getstatic rung36_jcon_lists/icn_155_lsa_i J
    lstore 175
    getstatic rung36_jcon_lists/icn_155_lsa_v J
    lstore 177
    getstatic rung36_jcon_lists/icn_158_I J
    lstore 179
    getstatic rung36_jcon_lists/icn_158_bound J
    lstore 181
    getstatic rung36_jcon_lists/icn_158_e1cur J
    lstore 183
    getstatic rung36_jcon_lists/icn_158_e1val J
    lstore 185
    getstatic rung36_jcon_lists/icn_158_e2val J
    lstore 187
    getstatic rung36_jcon_lists/icn_160_binop_lc J
    lstore 189
    getstatic rung36_jcon_lists/icn_160_binop_rc J
    lstore 191
    getstatic rung36_jcon_lists/icn_171_lsa_i J
    lstore 193
    getstatic rung36_jcon_lists/icn_171_lsa_v J
    lstore 195
    getstatic rung36_jcon_lists/icn_174_I J
    lstore 197
    getstatic rung36_jcon_lists/icn_174_bound J
    lstore 199
    getstatic rung36_jcon_lists/icn_174_e1cur J
    lstore 201
    getstatic rung36_jcon_lists/icn_174_e1val J
    lstore 203
    getstatic rung36_jcon_lists/icn_174_e2val J
    lstore 205
    getstatic rung36_jcon_lists/icn_175_binop_lc J
    lstore 207
    getstatic rung36_jcon_lists/icn_175_binop_rc J
    lstore 209
    invokestatic rung36_jcon_lists/icn_limage()V
    lload 155
    putstatic rung36_jcon_lists/icn_pv_main_y J
    lload 157
    putstatic rung36_jcon_lists/icn_41_alt_val J
    lload 159
    putstatic rung36_jcon_lists/icn_50_alt_val J
    lload 161
    putstatic rung36_jcon_lists/icn_102_alt_val J
    lload 163
    putstatic rung36_jcon_lists/icn_107_alt_val J
    lload 165
    putstatic rung36_jcon_lists/icn_112_alt_val J
    lload 167
    putstatic rung36_jcon_lists/icn_119_alt_val J
    lload 169
    putstatic rung36_jcon_lists/icn_126_alt_val J
    lload 171
    putstatic rung36_jcon_lists/icn_132_alt_val J
    lload 173
    putstatic rung36_jcon_lists/icn_pv_main_i J
    lload 175
    putstatic rung36_jcon_lists/icn_155_lsa_i J
    lload 177
    putstatic rung36_jcon_lists/icn_155_lsa_v J
    lload 179
    putstatic rung36_jcon_lists/icn_158_I J
    lload 181
    putstatic rung36_jcon_lists/icn_158_bound J
    lload 183
    putstatic rung36_jcon_lists/icn_158_e1cur J
    lload 185
    putstatic rung36_jcon_lists/icn_158_e1val J
    lload 187
    putstatic rung36_jcon_lists/icn_158_e2val J
    lload 189
    putstatic rung36_jcon_lists/icn_160_binop_lc J
    lload 191
    putstatic rung36_jcon_lists/icn_160_binop_rc J
    lload 193
    putstatic rung36_jcon_lists/icn_171_lsa_i J
    lload 195
    putstatic rung36_jcon_lists/icn_171_lsa_v J
    lload 197
    putstatic rung36_jcon_lists/icn_174_I J
    lload 199
    putstatic rung36_jcon_lists/icn_174_bound J
    lload 201
    putstatic rung36_jcon_lists/icn_174_e1cur J
    lload 203
    putstatic rung36_jcon_lists/icn_174_e1val J
    lload 205
    putstatic rung36_jcon_lists/icn_174_e2val J
    lload 207
    putstatic rung36_jcon_lists/icn_175_binop_lc J
    lload 209
    putstatic rung36_jcon_lists/icn_175_binop_rc J
    getstatic rung36_jcon_lists/icn_failed B
    ifne icn_229_after_call
    getstatic rung36_jcon_lists/icn_retval J
    goto icn_main_s27_sdrain
icn_229_after_call:
    goto icn_224_α
icn_main_s27_sdrain:
    pop2
    goto icn_224_α
;  VAR
icn_233_α:
    getstatic rung36_jcon_lists/icn_pv_main_x Ljava/util/ArrayList;
    goto icn_232_lr
icn_233_β:
    goto icn_229_α
;  INT
icn_234_α:
    ldc2_w 5
    goto icn_232_vr
icn_234_β:
    goto icn_229_α
icn_232_α:
    goto icn_233_α
icn_232_β:
    goto icn_229_α
icn_232_lr:
    putstatic rung36_jcon_lists/icn_232_pushlist Ljava/util/ArrayList;
    goto icn_234_α
icn_232_vr:
    invokestatic java/lang/Long/valueOf(J)Ljava/lang/Long;
    putstatic rung36_jcon_lists/icn_232_pushval Ljava/lang/Object;
    getstatic rung36_jcon_lists/icn_232_pushlist Ljava/util/ArrayList;
    iconst_0
    getstatic rung36_jcon_lists/icn_232_pushval Ljava/lang/Object;
    invokevirtual java/util/ArrayList/add(ILjava/lang/Object;)V
    getstatic rung36_jcon_lists/icn_232_pushlist Ljava/util/ArrayList;
    goto icn_main_s26_sdrain
icn_main_s26_sdrain:
    pop
    goto icn_229_α
;  VAR
icn_236_α:
    getstatic rung36_jcon_lists/icn_pv_main_x Ljava/util/ArrayList;
    goto icn_235_arg1
icn_236_β:
    goto icn_232_α
icn_235_arg1:
    putstatic rung36_jcon_lists/icn_arg_1 J
    goto icn_235_docall
;  STR
icn_237_α:
    ldc "F"
    goto icn_235_arg0
icn_237_β:
    goto icn_232_α
icn_235_arg0:
    putstatic rung36_jcon_lists/icn_arg_str_0 Ljava/lang/String;
    lconst_0
    putstatic rung36_jcon_lists/icn_arg_0 J
    goto icn_236_α
icn_235_α:
    goto icn_237_α
icn_235_β:
    goto icn_236_β
icn_235_docall:
    getstatic rung36_jcon_lists/icn_pv_main_y J
    lstore 155
    getstatic rung36_jcon_lists/icn_41_alt_val J
    lstore 157
    getstatic rung36_jcon_lists/icn_50_alt_val J
    lstore 159
    getstatic rung36_jcon_lists/icn_102_alt_val J
    lstore 161
    getstatic rung36_jcon_lists/icn_107_alt_val J
    lstore 163
    getstatic rung36_jcon_lists/icn_112_alt_val J
    lstore 165
    getstatic rung36_jcon_lists/icn_119_alt_val J
    lstore 167
    getstatic rung36_jcon_lists/icn_126_alt_val J
    lstore 169
    getstatic rung36_jcon_lists/icn_132_alt_val J
    lstore 171
    getstatic rung36_jcon_lists/icn_pv_main_i J
    lstore 173
    getstatic rung36_jcon_lists/icn_155_lsa_i J
    lstore 175
    getstatic rung36_jcon_lists/icn_155_lsa_v J
    lstore 177
    getstatic rung36_jcon_lists/icn_158_I J
    lstore 179
    getstatic rung36_jcon_lists/icn_158_bound J
    lstore 181
    getstatic rung36_jcon_lists/icn_158_e1cur J
    lstore 183
    getstatic rung36_jcon_lists/icn_158_e1val J
    lstore 185
    getstatic rung36_jcon_lists/icn_158_e2val J
    lstore 187
    getstatic rung36_jcon_lists/icn_160_binop_lc J
    lstore 189
    getstatic rung36_jcon_lists/icn_160_binop_rc J
    lstore 191
    getstatic rung36_jcon_lists/icn_171_lsa_i J
    lstore 193
    getstatic rung36_jcon_lists/icn_171_lsa_v J
    lstore 195
    getstatic rung36_jcon_lists/icn_174_I J
    lstore 197
    getstatic rung36_jcon_lists/icn_174_bound J
    lstore 199
    getstatic rung36_jcon_lists/icn_174_e1cur J
    lstore 201
    getstatic rung36_jcon_lists/icn_174_e1val J
    lstore 203
    getstatic rung36_jcon_lists/icn_174_e2val J
    lstore 205
    getstatic rung36_jcon_lists/icn_175_binop_lc J
    lstore 207
    getstatic rung36_jcon_lists/icn_175_binop_rc J
    lstore 209
    invokestatic rung36_jcon_lists/icn_limage()V
    lload 155
    putstatic rung36_jcon_lists/icn_pv_main_y J
    lload 157
    putstatic rung36_jcon_lists/icn_41_alt_val J
    lload 159
    putstatic rung36_jcon_lists/icn_50_alt_val J
    lload 161
    putstatic rung36_jcon_lists/icn_102_alt_val J
    lload 163
    putstatic rung36_jcon_lists/icn_107_alt_val J
    lload 165
    putstatic rung36_jcon_lists/icn_112_alt_val J
    lload 167
    putstatic rung36_jcon_lists/icn_119_alt_val J
    lload 169
    putstatic rung36_jcon_lists/icn_126_alt_val J
    lload 171
    putstatic rung36_jcon_lists/icn_132_alt_val J
    lload 173
    putstatic rung36_jcon_lists/icn_pv_main_i J
    lload 175
    putstatic rung36_jcon_lists/icn_155_lsa_i J
    lload 177
    putstatic rung36_jcon_lists/icn_155_lsa_v J
    lload 179
    putstatic rung36_jcon_lists/icn_158_I J
    lload 181
    putstatic rung36_jcon_lists/icn_158_bound J
    lload 183
    putstatic rung36_jcon_lists/icn_158_e1cur J
    lload 185
    putstatic rung36_jcon_lists/icn_158_e1val J
    lload 187
    putstatic rung36_jcon_lists/icn_158_e2val J
    lload 189
    putstatic rung36_jcon_lists/icn_160_binop_lc J
    lload 191
    putstatic rung36_jcon_lists/icn_160_binop_rc J
    lload 193
    putstatic rung36_jcon_lists/icn_171_lsa_i J
    lload 195
    putstatic rung36_jcon_lists/icn_171_lsa_v J
    lload 197
    putstatic rung36_jcon_lists/icn_174_I J
    lload 199
    putstatic rung36_jcon_lists/icn_174_bound J
    lload 201
    putstatic rung36_jcon_lists/icn_174_e1cur J
    lload 203
    putstatic rung36_jcon_lists/icn_174_e1val J
    lload 205
    putstatic rung36_jcon_lists/icn_174_e2val J
    lload 207
    putstatic rung36_jcon_lists/icn_175_binop_lc J
    lload 209
    putstatic rung36_jcon_lists/icn_175_binop_rc J
    getstatic rung36_jcon_lists/icn_failed B
    ifne icn_235_after_call
    getstatic rung36_jcon_lists/icn_retval J
    goto icn_main_s25_sdrain
icn_235_after_call:
    goto icn_232_α
icn_main_s25_sdrain:
    pop2
    goto icn_232_α
;  VAR
icn_239_α:
    getstatic rung36_jcon_lists/icn_pv_main_x Ljava/util/ArrayList;
    goto icn_238_lr
icn_239_β:
    goto icn_235_α
;  INT
icn_240_α:
    ldc2_w 4
    goto icn_238_vr
icn_240_β:
    goto icn_235_α
icn_238_α:
    goto icn_239_α
icn_238_β:
    goto icn_235_α
icn_238_lr:
    putstatic rung36_jcon_lists/icn_238_pushlist Ljava/util/ArrayList;
    goto icn_240_α
icn_238_vr:
    invokestatic java/lang/Long/valueOf(J)Ljava/lang/Long;
    putstatic rung36_jcon_lists/icn_238_pushval Ljava/lang/Object;
    getstatic rung36_jcon_lists/icn_238_pushlist Ljava/util/ArrayList;
    iconst_0
    getstatic rung36_jcon_lists/icn_238_pushval Ljava/lang/Object;
    invokevirtual java/util/ArrayList/add(ILjava/lang/Object;)V
    getstatic rung36_jcon_lists/icn_238_pushlist Ljava/util/ArrayList;
    goto icn_main_s24_sdrain
icn_main_s24_sdrain:
    pop
    goto icn_235_α
;  VAR
icn_242_α:
    getstatic rung36_jcon_lists/icn_pv_main_x Ljava/util/ArrayList;
    goto icn_241_arg1
icn_242_β:
    goto icn_238_α
icn_241_arg1:
    putstatic rung36_jcon_lists/icn_arg_1 J
    goto icn_241_docall
;  STR
icn_243_α:
    ldc "E"
    goto icn_241_arg0
icn_243_β:
    goto icn_238_α
icn_241_arg0:
    putstatic rung36_jcon_lists/icn_arg_str_0 Ljava/lang/String;
    lconst_0
    putstatic rung36_jcon_lists/icn_arg_0 J
    goto icn_242_α
icn_241_α:
    goto icn_243_α
icn_241_β:
    goto icn_242_β
icn_241_docall:
    getstatic rung36_jcon_lists/icn_pv_main_y J
    lstore 155
    getstatic rung36_jcon_lists/icn_41_alt_val J
    lstore 157
    getstatic rung36_jcon_lists/icn_50_alt_val J
    lstore 159
    getstatic rung36_jcon_lists/icn_102_alt_val J
    lstore 161
    getstatic rung36_jcon_lists/icn_107_alt_val J
    lstore 163
    getstatic rung36_jcon_lists/icn_112_alt_val J
    lstore 165
    getstatic rung36_jcon_lists/icn_119_alt_val J
    lstore 167
    getstatic rung36_jcon_lists/icn_126_alt_val J
    lstore 169
    getstatic rung36_jcon_lists/icn_132_alt_val J
    lstore 171
    getstatic rung36_jcon_lists/icn_pv_main_i J
    lstore 173
    getstatic rung36_jcon_lists/icn_155_lsa_i J
    lstore 175
    getstatic rung36_jcon_lists/icn_155_lsa_v J
    lstore 177
    getstatic rung36_jcon_lists/icn_158_I J
    lstore 179
    getstatic rung36_jcon_lists/icn_158_bound J
    lstore 181
    getstatic rung36_jcon_lists/icn_158_e1cur J
    lstore 183
    getstatic rung36_jcon_lists/icn_158_e1val J
    lstore 185
    getstatic rung36_jcon_lists/icn_158_e2val J
    lstore 187
    getstatic rung36_jcon_lists/icn_160_binop_lc J
    lstore 189
    getstatic rung36_jcon_lists/icn_160_binop_rc J
    lstore 191
    getstatic rung36_jcon_lists/icn_171_lsa_i J
    lstore 193
    getstatic rung36_jcon_lists/icn_171_lsa_v J
    lstore 195
    getstatic rung36_jcon_lists/icn_174_I J
    lstore 197
    getstatic rung36_jcon_lists/icn_174_bound J
    lstore 199
    getstatic rung36_jcon_lists/icn_174_e1cur J
    lstore 201
    getstatic rung36_jcon_lists/icn_174_e1val J
    lstore 203
    getstatic rung36_jcon_lists/icn_174_e2val J
    lstore 205
    getstatic rung36_jcon_lists/icn_175_binop_lc J
    lstore 207
    getstatic rung36_jcon_lists/icn_175_binop_rc J
    lstore 209
    invokestatic rung36_jcon_lists/icn_limage()V
    lload 155
    putstatic rung36_jcon_lists/icn_pv_main_y J
    lload 157
    putstatic rung36_jcon_lists/icn_41_alt_val J
    lload 159
    putstatic rung36_jcon_lists/icn_50_alt_val J
    lload 161
    putstatic rung36_jcon_lists/icn_102_alt_val J
    lload 163
    putstatic rung36_jcon_lists/icn_107_alt_val J
    lload 165
    putstatic rung36_jcon_lists/icn_112_alt_val J
    lload 167
    putstatic rung36_jcon_lists/icn_119_alt_val J
    lload 169
    putstatic rung36_jcon_lists/icn_126_alt_val J
    lload 171
    putstatic rung36_jcon_lists/icn_132_alt_val J
    lload 173
    putstatic rung36_jcon_lists/icn_pv_main_i J
    lload 175
    putstatic rung36_jcon_lists/icn_155_lsa_i J
    lload 177
    putstatic rung36_jcon_lists/icn_155_lsa_v J
    lload 179
    putstatic rung36_jcon_lists/icn_158_I J
    lload 181
    putstatic rung36_jcon_lists/icn_158_bound J
    lload 183
    putstatic rung36_jcon_lists/icn_158_e1cur J
    lload 185
    putstatic rung36_jcon_lists/icn_158_e1val J
    lload 187
    putstatic rung36_jcon_lists/icn_158_e2val J
    lload 189
    putstatic rung36_jcon_lists/icn_160_binop_lc J
    lload 191
    putstatic rung36_jcon_lists/icn_160_binop_rc J
    lload 193
    putstatic rung36_jcon_lists/icn_171_lsa_i J
    lload 195
    putstatic rung36_jcon_lists/icn_171_lsa_v J
    lload 197
    putstatic rung36_jcon_lists/icn_174_I J
    lload 199
    putstatic rung36_jcon_lists/icn_174_bound J
    lload 201
    putstatic rung36_jcon_lists/icn_174_e1cur J
    lload 203
    putstatic rung36_jcon_lists/icn_174_e1val J
    lload 205
    putstatic rung36_jcon_lists/icn_174_e2val J
    lload 207
    putstatic rung36_jcon_lists/icn_175_binop_lc J
    lload 209
    putstatic rung36_jcon_lists/icn_175_binop_rc J
    getstatic rung36_jcon_lists/icn_failed B
    ifne icn_241_after_call
    getstatic rung36_jcon_lists/icn_retval J
    goto icn_main_s23_sdrain
icn_241_after_call:
    goto icn_238_α
icn_main_s23_sdrain:
    pop2
    goto icn_238_α
;  STR
icn_245_α:
    ldc "\t"
    goto icn_244_waft_0
icn_245_β:
    goto icn_241_α
;  VAR
icn_248_α:
    getstatic rung36_jcon_lists/icn_pv_main_x Ljava/util/ArrayList;
    goto icn_247_lr
icn_248_β:
    goto icn_241_α
icn_247_α:
    goto icn_248_α
icn_247_β:
    goto icn_241_α
icn_247_lr:
    putstatic rung36_jcon_lists/icn_247_plist Ljava/util/ArrayList;
    getstatic rung36_jcon_lists/icn_247_plist Ljava/util/ArrayList;
    invokevirtual java/util/ArrayList/size()I
    dup
    ifeq icn_247_pfail
    iconst_1
    isub
    putstatic rung36_jcon_lists/icn_247_psz I
    getstatic rung36_jcon_lists/icn_247_plist Ljava/util/ArrayList;
    getstatic rung36_jcon_lists/icn_247_psz I
    invokevirtual java/util/ArrayList/remove(I)Ljava/lang/Object;
    dup
    ifnonnull icn_247_pok
    pop
    goto icn_241_α
icn_247_pok:
    checkcast java/lang/Long
    invokevirtual java/lang/Long/longValue()J
    goto icn_246_image_after
icn_247_pfail:
    pop
    goto icn_241_α
icn_246_α:
    goto icn_247_α
icn_246_β:
    goto icn_247_β
icn_246_image_after:
    invokestatic java/lang/Long/toString(J)Ljava/lang/String;
    goto icn_244_waft_1
icn_244_α:
    goto icn_245_α
icn_244_β:
    goto icn_245_β
    goto icn_244_wentry
icn_244_waft_0:
    astore 151
    getstatic java/lang/System/out Ljava/io/PrintStream;
    aload 151
    invokevirtual java/io/PrintStream/print(Ljava/lang/String;)V
    goto icn_246_α
icn_244_waft_1:
    astore 152
    getstatic java/lang/System/out Ljava/io/PrintStream;
    aload 152
    invokevirtual java/io/PrintStream/print(Ljava/lang/String;)V
    getstatic java/lang/System/out Ljava/io/PrintStream;
    ldc ""
    invokevirtual java/io/PrintStream/println(Ljava/lang/String;)V
    aload 152
    goto icn_main_s22_sdrain
icn_244_wentry:
    goto icn_245_α
icn_main_s22_sdrain:
    pop
    goto icn_241_α
;  VAR
icn_250_α:
    getstatic rung36_jcon_lists/icn_pv_main_x Ljava/util/ArrayList;
    goto icn_249_arg1
icn_250_β:
    goto icn_244_α
icn_249_arg1:
    putstatic rung36_jcon_lists/icn_arg_1 J
    goto icn_249_docall
;  STR
icn_251_α:
    ldc "D"
    goto icn_249_arg0
icn_251_β:
    goto icn_244_α
icn_249_arg0:
    putstatic rung36_jcon_lists/icn_arg_str_0 Ljava/lang/String;
    lconst_0
    putstatic rung36_jcon_lists/icn_arg_0 J
    goto icn_250_α
icn_249_α:
    goto icn_251_α
icn_249_β:
    goto icn_250_β
icn_249_docall:
    getstatic rung36_jcon_lists/icn_pv_main_y J
    lstore 157
    getstatic rung36_jcon_lists/icn_41_alt_val J
    lstore 159
    getstatic rung36_jcon_lists/icn_50_alt_val J
    lstore 161
    getstatic rung36_jcon_lists/icn_102_alt_val J
    lstore 163
    getstatic rung36_jcon_lists/icn_107_alt_val J
    lstore 165
    getstatic rung36_jcon_lists/icn_112_alt_val J
    lstore 167
    getstatic rung36_jcon_lists/icn_119_alt_val J
    lstore 169
    getstatic rung36_jcon_lists/icn_126_alt_val J
    lstore 171
    getstatic rung36_jcon_lists/icn_132_alt_val J
    lstore 173
    getstatic rung36_jcon_lists/icn_pv_main_i J
    lstore 175
    getstatic rung36_jcon_lists/icn_155_lsa_i J
    lstore 177
    getstatic rung36_jcon_lists/icn_155_lsa_v J
    lstore 179
    getstatic rung36_jcon_lists/icn_158_I J
    lstore 181
    getstatic rung36_jcon_lists/icn_158_bound J
    lstore 183
    getstatic rung36_jcon_lists/icn_158_e1cur J
    lstore 185
    getstatic rung36_jcon_lists/icn_158_e1val J
    lstore 187
    getstatic rung36_jcon_lists/icn_158_e2val J
    lstore 189
    getstatic rung36_jcon_lists/icn_160_binop_lc J
    lstore 191
    getstatic rung36_jcon_lists/icn_160_binop_rc J
    lstore 193
    getstatic rung36_jcon_lists/icn_171_lsa_i J
    lstore 195
    getstatic rung36_jcon_lists/icn_171_lsa_v J
    lstore 197
    getstatic rung36_jcon_lists/icn_174_I J
    lstore 199
    getstatic rung36_jcon_lists/icn_174_bound J
    lstore 201
    getstatic rung36_jcon_lists/icn_174_e1cur J
    lstore 203
    getstatic rung36_jcon_lists/icn_174_e1val J
    lstore 205
    getstatic rung36_jcon_lists/icn_174_e2val J
    lstore 207
    getstatic rung36_jcon_lists/icn_175_binop_lc J
    lstore 209
    getstatic rung36_jcon_lists/icn_175_binop_rc J
    lstore 211
    invokestatic rung36_jcon_lists/icn_limage()V
    lload 157
    putstatic rung36_jcon_lists/icn_pv_main_y J
    lload 159
    putstatic rung36_jcon_lists/icn_41_alt_val J
    lload 161
    putstatic rung36_jcon_lists/icn_50_alt_val J
    lload 163
    putstatic rung36_jcon_lists/icn_102_alt_val J
    lload 165
    putstatic rung36_jcon_lists/icn_107_alt_val J
    lload 167
    putstatic rung36_jcon_lists/icn_112_alt_val J
    lload 169
    putstatic rung36_jcon_lists/icn_119_alt_val J
    lload 171
    putstatic rung36_jcon_lists/icn_126_alt_val J
    lload 173
    putstatic rung36_jcon_lists/icn_132_alt_val J
    lload 175
    putstatic rung36_jcon_lists/icn_pv_main_i J
    lload 177
    putstatic rung36_jcon_lists/icn_155_lsa_i J
    lload 179
    putstatic rung36_jcon_lists/icn_155_lsa_v J
    lload 181
    putstatic rung36_jcon_lists/icn_158_I J
    lload 183
    putstatic rung36_jcon_lists/icn_158_bound J
    lload 185
    putstatic rung36_jcon_lists/icn_158_e1cur J
    lload 187
    putstatic rung36_jcon_lists/icn_158_e1val J
    lload 189
    putstatic rung36_jcon_lists/icn_158_e2val J
    lload 191
    putstatic rung36_jcon_lists/icn_160_binop_lc J
    lload 193
    putstatic rung36_jcon_lists/icn_160_binop_rc J
    lload 195
    putstatic rung36_jcon_lists/icn_171_lsa_i J
    lload 197
    putstatic rung36_jcon_lists/icn_171_lsa_v J
    lload 199
    putstatic rung36_jcon_lists/icn_174_I J
    lload 201
    putstatic rung36_jcon_lists/icn_174_bound J
    lload 203
    putstatic rung36_jcon_lists/icn_174_e1cur J
    lload 205
    putstatic rung36_jcon_lists/icn_174_e1val J
    lload 207
    putstatic rung36_jcon_lists/icn_174_e2val J
    lload 209
    putstatic rung36_jcon_lists/icn_175_binop_lc J
    lload 211
    putstatic rung36_jcon_lists/icn_175_binop_rc J
    getstatic rung36_jcon_lists/icn_failed B
    ifne icn_249_after_call
    getstatic rung36_jcon_lists/icn_retval J
    goto icn_main_s21_sdrain
icn_249_after_call:
    goto icn_244_α
icn_main_s21_sdrain:
    pop2
    goto icn_244_α
;  STR
icn_253_α:
    ldc "\t"
    goto icn_252_waft_0
icn_253_β:
    goto icn_249_α
;  VAR
icn_256_α:
    getstatic rung36_jcon_lists/icn_pv_main_x Ljava/util/ArrayList;
    goto icn_255_lr
icn_256_β:
    goto icn_249_α
icn_255_α:
    goto icn_256_α
icn_255_β:
    goto icn_249_α
icn_255_lr:
    putstatic rung36_jcon_lists/icn_255_glist Ljava/util/ArrayList;
    getstatic rung36_jcon_lists/icn_255_glist Ljava/util/ArrayList;
    invokevirtual java/util/ArrayList/size()I
    ifeq icn_249_α
    getstatic rung36_jcon_lists/icn_255_glist Ljava/util/ArrayList;
    iconst_0
    invokevirtual java/util/ArrayList/remove(I)Ljava/lang/Object;
    dup
    ifnonnull icn_255_gok
    pop
    goto icn_249_α
icn_255_gok:
    checkcast java/lang/Long
    invokevirtual java/lang/Long/longValue()J
    goto icn_254_image_after
icn_254_α:
    goto icn_255_α
icn_254_β:
    goto icn_255_β
icn_254_image_after:
    invokestatic java/lang/Long/toString(J)Ljava/lang/String;
    goto icn_252_waft_1
icn_252_α:
    goto icn_253_α
icn_252_β:
    goto icn_253_β
    goto icn_252_wentry
icn_252_waft_0:
    astore 153
    getstatic java/lang/System/out Ljava/io/PrintStream;
    aload 153
    invokevirtual java/io/PrintStream/print(Ljava/lang/String;)V
    goto icn_254_α
icn_252_waft_1:
    astore 154
    getstatic java/lang/System/out Ljava/io/PrintStream;
    aload 154
    invokevirtual java/io/PrintStream/print(Ljava/lang/String;)V
    getstatic java/lang/System/out Ljava/io/PrintStream;
    ldc ""
    invokevirtual java/io/PrintStream/println(Ljava/lang/String;)V
    aload 154
    goto icn_main_s20_sdrain
icn_252_wentry:
    goto icn_253_α
icn_main_s20_sdrain:
    pop
    goto icn_249_α
;  VAR
icn_258_α:
    getstatic rung36_jcon_lists/icn_pv_main_x Ljava/util/ArrayList;
    goto icn_257_arg1
icn_258_β:
    goto icn_252_α
icn_257_arg1:
    putstatic rung36_jcon_lists/icn_arg_1 J
    goto icn_257_docall
;  STR
icn_259_α:
    ldc "C"
    goto icn_257_arg0
icn_259_β:
    goto icn_252_α
icn_257_arg0:
    putstatic rung36_jcon_lists/icn_arg_str_0 Ljava/lang/String;
    lconst_0
    putstatic rung36_jcon_lists/icn_arg_0 J
    goto icn_258_α
icn_257_α:
    goto icn_259_α
icn_257_β:
    goto icn_258_β
icn_257_docall:
    getstatic rung36_jcon_lists/icn_pv_main_y J
    lstore 159
    getstatic rung36_jcon_lists/icn_41_alt_val J
    lstore 161
    getstatic rung36_jcon_lists/icn_50_alt_val J
    lstore 163
    getstatic rung36_jcon_lists/icn_102_alt_val J
    lstore 165
    getstatic rung36_jcon_lists/icn_107_alt_val J
    lstore 167
    getstatic rung36_jcon_lists/icn_112_alt_val J
    lstore 169
    getstatic rung36_jcon_lists/icn_119_alt_val J
    lstore 171
    getstatic rung36_jcon_lists/icn_126_alt_val J
    lstore 173
    getstatic rung36_jcon_lists/icn_132_alt_val J
    lstore 175
    getstatic rung36_jcon_lists/icn_pv_main_i J
    lstore 177
    getstatic rung36_jcon_lists/icn_155_lsa_i J
    lstore 179
    getstatic rung36_jcon_lists/icn_155_lsa_v J
    lstore 181
    getstatic rung36_jcon_lists/icn_158_I J
    lstore 183
    getstatic rung36_jcon_lists/icn_158_bound J
    lstore 185
    getstatic rung36_jcon_lists/icn_158_e1cur J
    lstore 187
    getstatic rung36_jcon_lists/icn_158_e1val J
    lstore 189
    getstatic rung36_jcon_lists/icn_158_e2val J
    lstore 191
    getstatic rung36_jcon_lists/icn_160_binop_lc J
    lstore 193
    getstatic rung36_jcon_lists/icn_160_binop_rc J
    lstore 195
    getstatic rung36_jcon_lists/icn_171_lsa_i J
    lstore 197
    getstatic rung36_jcon_lists/icn_171_lsa_v J
    lstore 199
    getstatic rung36_jcon_lists/icn_174_I J
    lstore 201
    getstatic rung36_jcon_lists/icn_174_bound J
    lstore 203
    getstatic rung36_jcon_lists/icn_174_e1cur J
    lstore 205
    getstatic rung36_jcon_lists/icn_174_e1val J
    lstore 207
    getstatic rung36_jcon_lists/icn_174_e2val J
    lstore 209
    getstatic rung36_jcon_lists/icn_175_binop_lc J
    lstore 211
    getstatic rung36_jcon_lists/icn_175_binop_rc J
    lstore 213
    invokestatic rung36_jcon_lists/icn_limage()V
    lload 159
    putstatic rung36_jcon_lists/icn_pv_main_y J
    lload 161
    putstatic rung36_jcon_lists/icn_41_alt_val J
    lload 163
    putstatic rung36_jcon_lists/icn_50_alt_val J
    lload 165
    putstatic rung36_jcon_lists/icn_102_alt_val J
    lload 167
    putstatic rung36_jcon_lists/icn_107_alt_val J
    lload 169
    putstatic rung36_jcon_lists/icn_112_alt_val J
    lload 171
    putstatic rung36_jcon_lists/icn_119_alt_val J
    lload 173
    putstatic rung36_jcon_lists/icn_126_alt_val J
    lload 175
    putstatic rung36_jcon_lists/icn_132_alt_val J
    lload 177
    putstatic rung36_jcon_lists/icn_pv_main_i J
    lload 179
    putstatic rung36_jcon_lists/icn_155_lsa_i J
    lload 181
    putstatic rung36_jcon_lists/icn_155_lsa_v J
    lload 183
    putstatic rung36_jcon_lists/icn_158_I J
    lload 185
    putstatic rung36_jcon_lists/icn_158_bound J
    lload 187
    putstatic rung36_jcon_lists/icn_158_e1cur J
    lload 189
    putstatic rung36_jcon_lists/icn_158_e1val J
    lload 191
    putstatic rung36_jcon_lists/icn_158_e2val J
    lload 193
    putstatic rung36_jcon_lists/icn_160_binop_lc J
    lload 195
    putstatic rung36_jcon_lists/icn_160_binop_rc J
    lload 197
    putstatic rung36_jcon_lists/icn_171_lsa_i J
    lload 199
    putstatic rung36_jcon_lists/icn_171_lsa_v J
    lload 201
    putstatic rung36_jcon_lists/icn_174_I J
    lload 203
    putstatic rung36_jcon_lists/icn_174_bound J
    lload 205
    putstatic rung36_jcon_lists/icn_174_e1cur J
    lload 207
    putstatic rung36_jcon_lists/icn_174_e1val J
    lload 209
    putstatic rung36_jcon_lists/icn_174_e2val J
    lload 211
    putstatic rung36_jcon_lists/icn_175_binop_lc J
    lload 213
    putstatic rung36_jcon_lists/icn_175_binop_rc J
    getstatic rung36_jcon_lists/icn_failed B
    ifne icn_257_after_call
    getstatic rung36_jcon_lists/icn_retval J
    goto icn_main_s19_sdrain
icn_257_after_call:
    goto icn_252_α
icn_main_s19_sdrain:
    pop2
    goto icn_252_α
;  STR
icn_261_α:
    ldc "\t"
    goto icn_260_waft_0
icn_261_β:
    goto icn_257_α
;  VAR
icn_264_α:
    getstatic rung36_jcon_lists/icn_pv_main_x Ljava/util/ArrayList;
    goto icn_263_lr
icn_264_β:
    goto icn_257_α
icn_263_α:
    goto icn_264_α
icn_263_β:
    goto icn_257_α
icn_263_lr:
    putstatic rung36_jcon_lists/icn_263_glist Ljava/util/ArrayList;
    getstatic rung36_jcon_lists/icn_263_glist Ljava/util/ArrayList;
    invokevirtual java/util/ArrayList/size()I
    ifeq icn_257_α
    getstatic rung36_jcon_lists/icn_263_glist Ljava/util/ArrayList;
    iconst_0
    invokevirtual java/util/ArrayList/remove(I)Ljava/lang/Object;
    dup
    ifnonnull icn_263_gok
    pop
    goto icn_257_α
icn_263_gok:
    checkcast java/lang/Long
    invokevirtual java/lang/Long/longValue()J
    goto icn_262_image_after
icn_262_α:
    goto icn_263_α
icn_262_β:
    goto icn_263_β
icn_262_image_after:
    invokestatic java/lang/Long/toString(J)Ljava/lang/String;
    goto icn_260_waft_1
icn_260_α:
    goto icn_261_α
icn_260_β:
    goto icn_261_β
    goto icn_260_wentry
icn_260_waft_0:
    astore 155
    getstatic java/lang/System/out Ljava/io/PrintStream;
    aload 155
    invokevirtual java/io/PrintStream/print(Ljava/lang/String;)V
    goto icn_262_α
icn_260_waft_1:
    astore 156
    getstatic java/lang/System/out Ljava/io/PrintStream;
    aload 156
    invokevirtual java/io/PrintStream/print(Ljava/lang/String;)V
    getstatic java/lang/System/out Ljava/io/PrintStream;
    ldc ""
    invokevirtual java/io/PrintStream/println(Ljava/lang/String;)V
    aload 156
    goto icn_main_s18_sdrain
icn_260_wentry:
    goto icn_261_α
icn_main_s18_sdrain:
    pop
    goto icn_257_α
;  VAR
icn_266_α:
    getstatic rung36_jcon_lists/icn_pv_main_x Ljava/util/ArrayList;
    goto icn_265_arg1
icn_266_β:
    goto icn_260_α
icn_265_arg1:
    putstatic rung36_jcon_lists/icn_arg_1 J
    goto icn_265_docall
;  STR
icn_267_α:
    ldc "B"
    goto icn_265_arg0
icn_267_β:
    goto icn_260_α
icn_265_arg0:
    putstatic rung36_jcon_lists/icn_arg_str_0 Ljava/lang/String;
    lconst_0
    putstatic rung36_jcon_lists/icn_arg_0 J
    goto icn_266_α
icn_265_α:
    goto icn_267_α
icn_265_β:
    goto icn_266_β
icn_265_docall:
    getstatic rung36_jcon_lists/icn_pv_main_y J
    lstore 161
    getstatic rung36_jcon_lists/icn_41_alt_val J
    lstore 163
    getstatic rung36_jcon_lists/icn_50_alt_val J
    lstore 165
    getstatic rung36_jcon_lists/icn_102_alt_val J
    lstore 167
    getstatic rung36_jcon_lists/icn_107_alt_val J
    lstore 169
    getstatic rung36_jcon_lists/icn_112_alt_val J
    lstore 171
    getstatic rung36_jcon_lists/icn_119_alt_val J
    lstore 173
    getstatic rung36_jcon_lists/icn_126_alt_val J
    lstore 175
    getstatic rung36_jcon_lists/icn_132_alt_val J
    lstore 177
    getstatic rung36_jcon_lists/icn_pv_main_i J
    lstore 179
    getstatic rung36_jcon_lists/icn_155_lsa_i J
    lstore 181
    getstatic rung36_jcon_lists/icn_155_lsa_v J
    lstore 183
    getstatic rung36_jcon_lists/icn_158_I J
    lstore 185
    getstatic rung36_jcon_lists/icn_158_bound J
    lstore 187
    getstatic rung36_jcon_lists/icn_158_e1cur J
    lstore 189
    getstatic rung36_jcon_lists/icn_158_e1val J
    lstore 191
    getstatic rung36_jcon_lists/icn_158_e2val J
    lstore 193
    getstatic rung36_jcon_lists/icn_160_binop_lc J
    lstore 195
    getstatic rung36_jcon_lists/icn_160_binop_rc J
    lstore 197
    getstatic rung36_jcon_lists/icn_171_lsa_i J
    lstore 199
    getstatic rung36_jcon_lists/icn_171_lsa_v J
    lstore 201
    getstatic rung36_jcon_lists/icn_174_I J
    lstore 203
    getstatic rung36_jcon_lists/icn_174_bound J
    lstore 205
    getstatic rung36_jcon_lists/icn_174_e1cur J
    lstore 207
    getstatic rung36_jcon_lists/icn_174_e1val J
    lstore 209
    getstatic rung36_jcon_lists/icn_174_e2val J
    lstore 211
    getstatic rung36_jcon_lists/icn_175_binop_lc J
    lstore 213
    getstatic rung36_jcon_lists/icn_175_binop_rc J
    lstore 215
    invokestatic rung36_jcon_lists/icn_limage()V
    lload 161
    putstatic rung36_jcon_lists/icn_pv_main_y J
    lload 163
    putstatic rung36_jcon_lists/icn_41_alt_val J
    lload 165
    putstatic rung36_jcon_lists/icn_50_alt_val J
    lload 167
    putstatic rung36_jcon_lists/icn_102_alt_val J
    lload 169
    putstatic rung36_jcon_lists/icn_107_alt_val J
    lload 171
    putstatic rung36_jcon_lists/icn_112_alt_val J
    lload 173
    putstatic rung36_jcon_lists/icn_119_alt_val J
    lload 175
    putstatic rung36_jcon_lists/icn_126_alt_val J
    lload 177
    putstatic rung36_jcon_lists/icn_132_alt_val J
    lload 179
    putstatic rung36_jcon_lists/icn_pv_main_i J
    lload 181
    putstatic rung36_jcon_lists/icn_155_lsa_i J
    lload 183
    putstatic rung36_jcon_lists/icn_155_lsa_v J
    lload 185
    putstatic rung36_jcon_lists/icn_158_I J
    lload 187
    putstatic rung36_jcon_lists/icn_158_bound J
    lload 189
    putstatic rung36_jcon_lists/icn_158_e1cur J
    lload 191
    putstatic rung36_jcon_lists/icn_158_e1val J
    lload 193
    putstatic rung36_jcon_lists/icn_158_e2val J
    lload 195
    putstatic rung36_jcon_lists/icn_160_binop_lc J
    lload 197
    putstatic rung36_jcon_lists/icn_160_binop_rc J
    lload 199
    putstatic rung36_jcon_lists/icn_171_lsa_i J
    lload 201
    putstatic rung36_jcon_lists/icn_171_lsa_v J
    lload 203
    putstatic rung36_jcon_lists/icn_174_I J
    lload 205
    putstatic rung36_jcon_lists/icn_174_bound J
    lload 207
    putstatic rung36_jcon_lists/icn_174_e1cur J
    lload 209
    putstatic rung36_jcon_lists/icn_174_e1val J
    lload 211
    putstatic rung36_jcon_lists/icn_174_e2val J
    lload 213
    putstatic rung36_jcon_lists/icn_175_binop_lc J
    lload 215
    putstatic rung36_jcon_lists/icn_175_binop_rc J
    getstatic rung36_jcon_lists/icn_failed B
    ifne icn_265_after_call
    getstatic rung36_jcon_lists/icn_retval J
    goto icn_main_s17_sdrain
icn_265_after_call:
    goto icn_260_α
icn_main_s17_sdrain:
    pop2
    goto icn_260_α
icn_268_α:
    goto icn_265_α
icn_268_β:
    goto icn_265_α
icn_main_s16_sdrain:
    pop
    goto icn_265_α
;  VAR
icn_270_α:
    getstatic rung36_jcon_lists/icn_pv_main_x Ljava/util/ArrayList;
    goto icn_269_arg1
icn_270_β:
    goto icn_268_α
icn_269_arg1:
    putstatic rung36_jcon_lists/icn_arg_1 J
    goto icn_269_docall
;  STR
icn_271_α:
    ldc "A"
    goto icn_269_arg0
icn_271_β:
    goto icn_268_α
icn_269_arg0:
    putstatic rung36_jcon_lists/icn_arg_str_0 Ljava/lang/String;
    lconst_0
    putstatic rung36_jcon_lists/icn_arg_0 J
    goto icn_270_α
icn_269_α:
    goto icn_271_α
icn_269_β:
    goto icn_270_β
icn_269_docall:
    getstatic rung36_jcon_lists/icn_pv_main_y J
    lstore 161
    getstatic rung36_jcon_lists/icn_41_alt_val J
    lstore 163
    getstatic rung36_jcon_lists/icn_50_alt_val J
    lstore 165
    getstatic rung36_jcon_lists/icn_102_alt_val J
    lstore 167
    getstatic rung36_jcon_lists/icn_107_alt_val J
    lstore 169
    getstatic rung36_jcon_lists/icn_112_alt_val J
    lstore 171
    getstatic rung36_jcon_lists/icn_119_alt_val J
    lstore 173
    getstatic rung36_jcon_lists/icn_126_alt_val J
    lstore 175
    getstatic rung36_jcon_lists/icn_132_alt_val J
    lstore 177
    getstatic rung36_jcon_lists/icn_pv_main_i J
    lstore 179
    getstatic rung36_jcon_lists/icn_155_lsa_i J
    lstore 181
    getstatic rung36_jcon_lists/icn_155_lsa_v J
    lstore 183
    getstatic rung36_jcon_lists/icn_158_I J
    lstore 185
    getstatic rung36_jcon_lists/icn_158_bound J
    lstore 187
    getstatic rung36_jcon_lists/icn_158_e1cur J
    lstore 189
    getstatic rung36_jcon_lists/icn_158_e1val J
    lstore 191
    getstatic rung36_jcon_lists/icn_158_e2val J
    lstore 193
    getstatic rung36_jcon_lists/icn_160_binop_lc J
    lstore 195
    getstatic rung36_jcon_lists/icn_160_binop_rc J
    lstore 197
    getstatic rung36_jcon_lists/icn_171_lsa_i J
    lstore 199
    getstatic rung36_jcon_lists/icn_171_lsa_v J
    lstore 201
    getstatic rung36_jcon_lists/icn_174_I J
    lstore 203
    getstatic rung36_jcon_lists/icn_174_bound J
    lstore 205
    getstatic rung36_jcon_lists/icn_174_e1cur J
    lstore 207
    getstatic rung36_jcon_lists/icn_174_e1val J
    lstore 209
    getstatic rung36_jcon_lists/icn_174_e2val J
    lstore 211
    getstatic rung36_jcon_lists/icn_175_binop_lc J
    lstore 213
    getstatic rung36_jcon_lists/icn_175_binop_rc J
    lstore 215
    invokestatic rung36_jcon_lists/icn_limage()V
    lload 161
    putstatic rung36_jcon_lists/icn_pv_main_y J
    lload 163
    putstatic rung36_jcon_lists/icn_41_alt_val J
    lload 165
    putstatic rung36_jcon_lists/icn_50_alt_val J
    lload 167
    putstatic rung36_jcon_lists/icn_102_alt_val J
    lload 169
    putstatic rung36_jcon_lists/icn_107_alt_val J
    lload 171
    putstatic rung36_jcon_lists/icn_112_alt_val J
    lload 173
    putstatic rung36_jcon_lists/icn_119_alt_val J
    lload 175
    putstatic rung36_jcon_lists/icn_126_alt_val J
    lload 177
    putstatic rung36_jcon_lists/icn_132_alt_val J
    lload 179
    putstatic rung36_jcon_lists/icn_pv_main_i J
    lload 181
    putstatic rung36_jcon_lists/icn_155_lsa_i J
    lload 183
    putstatic rung36_jcon_lists/icn_155_lsa_v J
    lload 185
    putstatic rung36_jcon_lists/icn_158_I J
    lload 187
    putstatic rung36_jcon_lists/icn_158_bound J
    lload 189
    putstatic rung36_jcon_lists/icn_158_e1cur J
    lload 191
    putstatic rung36_jcon_lists/icn_158_e1val J
    lload 193
    putstatic rung36_jcon_lists/icn_158_e2val J
    lload 195
    putstatic rung36_jcon_lists/icn_160_binop_lc J
    lload 197
    putstatic rung36_jcon_lists/icn_160_binop_rc J
    lload 199
    putstatic rung36_jcon_lists/icn_171_lsa_i J
    lload 201
    putstatic rung36_jcon_lists/icn_171_lsa_v J
    lload 203
    putstatic rung36_jcon_lists/icn_174_I J
    lload 205
    putstatic rung36_jcon_lists/icn_174_bound J
    lload 207
    putstatic rung36_jcon_lists/icn_174_e1cur J
    lload 209
    putstatic rung36_jcon_lists/icn_174_e1val J
    lload 211
    putstatic rung36_jcon_lists/icn_174_e2val J
    lload 213
    putstatic rung36_jcon_lists/icn_175_binop_lc J
    lload 215
    putstatic rung36_jcon_lists/icn_175_binop_rc J
    getstatic rung36_jcon_lists/icn_failed B
    ifne icn_269_after_call
    getstatic rung36_jcon_lists/icn_retval J
    goto icn_main_s15_sdrain
icn_269_after_call:
    goto icn_268_α
icn_main_s15_sdrain:
    pop2
    goto icn_268_α
icn_272_α:
    goto icn_269_α
icn_272_β:
    goto icn_269_α
icn_main_s14_sdrain:
    pop
    goto icn_269_α
icn_274_α:
    new java/util/ArrayList
    dup
    invokespecial java/util/ArrayList/<init>()V
    putstatic rung36_jcon_lists/icn_274_mklist Ljava/util/ArrayList;
;  INT
icn_275_α:
    ldc2_w 1
    goto icn_274_mke_0
icn_275_β:
    goto icn_272_α
    goto icn_275_α
icn_274_mke_0:
    invokestatic java/lang/Long/valueOf(J)Ljava/lang/Long;
    putstatic rung36_jcon_lists/icn_274_elem_0 Ljava/lang/Object;
    getstatic rung36_jcon_lists/icn_274_mklist Ljava/util/ArrayList;
    getstatic rung36_jcon_lists/icn_274_elem_0 Ljava/lang/Object;
    invokevirtual java/util/ArrayList/add(Ljava/lang/Object;)Z
    pop
;  INT
icn_276_α:
    ldc2_w 2
    goto icn_274_mke_1
icn_276_β:
    goto icn_272_α
    goto icn_276_α
icn_274_mke_1:
    invokestatic java/lang/Long/valueOf(J)Ljava/lang/Long;
    putstatic rung36_jcon_lists/icn_274_elem_1 Ljava/lang/Object;
    getstatic rung36_jcon_lists/icn_274_mklist Ljava/util/ArrayList;
    getstatic rung36_jcon_lists/icn_274_elem_1 Ljava/lang/Object;
    invokevirtual java/util/ArrayList/add(Ljava/lang/Object;)Z
    pop
;  INT
icn_277_α:
    ldc2_w 3
    goto icn_274_mke_2
icn_277_β:
    goto icn_272_α
    goto icn_277_α
icn_274_mke_2:
    invokestatic java/lang/Long/valueOf(J)Ljava/lang/Long;
    putstatic rung36_jcon_lists/icn_274_elem_2 Ljava/lang/Object;
    getstatic rung36_jcon_lists/icn_274_mklist Ljava/util/ArrayList;
    getstatic rung36_jcon_lists/icn_274_elem_2 Ljava/lang/Object;
    invokevirtual java/util/ArrayList/add(Ljava/lang/Object;)Z
    pop
    getstatic rung36_jcon_lists/icn_274_mklist Ljava/util/ArrayList;
    goto icn_273_store
icn_274_β:
    goto icn_272_α
icn_273_α:
    goto icn_274_α
icn_273_β:
    goto icn_274_β
icn_273_store:
    putstatic rung36_jcon_lists/icn_pv_main_x Ljava/util/ArrayList;
    getstatic rung36_jcon_lists/icn_pv_main_x Ljava/util/ArrayList;
    goto icn_main_s13_sdrain
icn_main_s13_sdrain:
    pop
    goto icn_272_α
icn_280_α:
    new java/util/ArrayList
    dup
    invokespecial java/util/ArrayList/<init>()V
    putstatic rung36_jcon_lists/icn_280_mklist Ljava/util/ArrayList;
;  INT
icn_281_α:
    ldc2_w 4
    goto icn_280_mke_0
icn_281_β:
    goto icn_279_lb
    goto icn_281_α
icn_280_mke_0:
    invokestatic java/lang/Long/valueOf(J)Ljava/lang/Long;
    putstatic rung36_jcon_lists/icn_280_elem_0 Ljava/lang/Object;
    getstatic rung36_jcon_lists/icn_280_mklist Ljava/util/ArrayList;
    getstatic rung36_jcon_lists/icn_280_elem_0 Ljava/lang/Object;
    invokevirtual java/util/ArrayList/add(Ljava/lang/Object;)Z
    pop
;  INT
icn_282_α:
    ldc2_w 5
    goto icn_280_mke_1
icn_282_β:
    goto icn_279_lb
    goto icn_282_α
icn_280_mke_1:
    invokestatic java/lang/Long/valueOf(J)Ljava/lang/Long;
    putstatic rung36_jcon_lists/icn_280_elem_1 Ljava/lang/Object;
    getstatic rung36_jcon_lists/icn_280_mklist Ljava/util/ArrayList;
    getstatic rung36_jcon_lists/icn_280_elem_1 Ljava/lang/Object;
    invokevirtual java/util/ArrayList/add(Ljava/lang/Object;)Z
    pop
;  INT
icn_283_α:
    ldc2_w 6
    goto icn_280_mke_2
icn_283_β:
    goto icn_279_lb
    goto icn_283_α
icn_280_mke_2:
    invokestatic java/lang/Long/valueOf(J)Ljava/lang/Long;
    putstatic rung36_jcon_lists/icn_280_elem_2 Ljava/lang/Object;
    getstatic rung36_jcon_lists/icn_280_mklist Ljava/util/ArrayList;
    getstatic rung36_jcon_lists/icn_280_elem_2 Ljava/lang/Object;
    invokevirtual java/util/ArrayList/add(Ljava/lang/Object;)Z
    pop
;  INT
icn_284_α:
    ldc2_w 7
    goto icn_280_mke_3
icn_284_β:
    goto icn_279_lb
    goto icn_284_α
icn_280_mke_3:
    invokestatic java/lang/Long/valueOf(J)Ljava/lang/Long;
    putstatic rung36_jcon_lists/icn_280_elem_3 Ljava/lang/Object;
    getstatic rung36_jcon_lists/icn_280_mklist Ljava/util/ArrayList;
    getstatic rung36_jcon_lists/icn_280_elem_3 Ljava/lang/Object;
    invokevirtual java/util/ArrayList/add(Ljava/lang/Object;)Z
    pop
;  INT
icn_285_α:
    ldc2_w 8
    goto icn_280_mke_4
icn_285_β:
    goto icn_279_lb
    goto icn_285_α
icn_280_mke_4:
    invokestatic java/lang/Long/valueOf(J)Ljava/lang/Long;
    putstatic rung36_jcon_lists/icn_280_elem_4 Ljava/lang/Object;
    getstatic rung36_jcon_lists/icn_280_mklist Ljava/util/ArrayList;
    getstatic rung36_jcon_lists/icn_280_elem_4 Ljava/lang/Object;
    invokevirtual java/util/ArrayList/add(Ljava/lang/Object;)Z
    pop
    getstatic rung36_jcon_lists/icn_280_mklist Ljava/util/ArrayList;
    goto icn_279_rrelay
icn_280_β:
    goto icn_279_lb
icn_286_α:
    new java/util/ArrayList
    dup
    invokespecial java/util/ArrayList/<init>()V
    putstatic rung36_jcon_lists/icn_286_mklist Ljava/util/ArrayList;
;  INT
icn_287_α:
    ldc2_w 1
    goto icn_286_mke_0
icn_287_β:
    goto icn_273_α
    goto icn_287_α
icn_286_mke_0:
    invokestatic java/lang/Long/valueOf(J)Ljava/lang/Long;
    putstatic rung36_jcon_lists/icn_286_elem_0 Ljava/lang/Object;
    getstatic rung36_jcon_lists/icn_286_mklist Ljava/util/ArrayList;
    getstatic rung36_jcon_lists/icn_286_elem_0 Ljava/lang/Object;
    invokevirtual java/util/ArrayList/add(Ljava/lang/Object;)Z
    pop
;  INT
icn_288_α:
    ldc2_w 2
    goto icn_286_mke_1
icn_288_β:
    goto icn_273_α
    goto icn_288_α
icn_286_mke_1:
    invokestatic java/lang/Long/valueOf(J)Ljava/lang/Long;
    putstatic rung36_jcon_lists/icn_286_elem_1 Ljava/lang/Object;
    getstatic rung36_jcon_lists/icn_286_mklist Ljava/util/ArrayList;
    getstatic rung36_jcon_lists/icn_286_elem_1 Ljava/lang/Object;
    invokevirtual java/util/ArrayList/add(Ljava/lang/Object;)Z
    pop
;  INT
icn_289_α:
    ldc2_w 3
    goto icn_286_mke_2
icn_289_β:
    goto icn_273_α
    goto icn_289_α
icn_286_mke_2:
    invokestatic java/lang/Long/valueOf(J)Ljava/lang/Long;
    putstatic rung36_jcon_lists/icn_286_elem_2 Ljava/lang/Object;
    getstatic rung36_jcon_lists/icn_286_mklist Ljava/util/ArrayList;
    getstatic rung36_jcon_lists/icn_286_elem_2 Ljava/lang/Object;
    invokevirtual java/util/ArrayList/add(Ljava/lang/Object;)Z
    pop
    getstatic rung36_jcon_lists/icn_286_mklist Ljava/util/ArrayList;
    goto icn_279_lrelay
icn_286_β:
    goto icn_273_α
icn_279_lrelay:
    putstatic rung36_jcon_lists/icn_279_lc Ljava/lang/String;
    goto icn_279_lstore
icn_279_rrelay:
    putstatic rung36_jcon_lists/icn_279_rc Ljava/lang/String;
    goto icn_279_compute
icn_279_lb:
    goto icn_286_β
icn_279_α:
    iconst_0
    istore 106
    goto icn_286_α
icn_279_β:
    goto icn_280_β
icn_279_lstore:
    iload 106
    ifeq icn_280_α
    goto icn_280_β
icn_279_compute:
    getstatic rung36_jcon_lists/icn_279_lc Ljava/lang/String;
    getstatic rung36_jcon_lists/icn_279_rc Ljava/lang/String;
    invokevirtual java/lang/String/concat(Ljava/lang/String;)Ljava/lang/String;
    goto icn_278_arg1
icn_278_arg1:
    putstatic rung36_jcon_lists/icn_arg_str_1 Ljava/lang/String;
    lconst_0
    putstatic rung36_jcon_lists/icn_arg_1 J
    goto icn_278_docall
;  STR
icn_290_α:
    ldc "i"
    goto icn_278_arg0
icn_290_β:
    goto icn_273_α
icn_278_arg0:
    putstatic rung36_jcon_lists/icn_arg_str_0 Ljava/lang/String;
    lconst_0
    putstatic rung36_jcon_lists/icn_arg_0 J
    goto icn_279_α
icn_278_α:
    goto icn_290_α
icn_278_β:
    goto icn_279_β
icn_278_docall:
    getstatic rung36_jcon_lists/icn_pv_main_y J
    lstore 161
    getstatic rung36_jcon_lists/icn_41_alt_val J
    lstore 163
    getstatic rung36_jcon_lists/icn_50_alt_val J
    lstore 165
    getstatic rung36_jcon_lists/icn_102_alt_val J
    lstore 167
    getstatic rung36_jcon_lists/icn_107_alt_val J
    lstore 169
    getstatic rung36_jcon_lists/icn_112_alt_val J
    lstore 171
    getstatic rung36_jcon_lists/icn_119_alt_val J
    lstore 173
    getstatic rung36_jcon_lists/icn_126_alt_val J
    lstore 175
    getstatic rung36_jcon_lists/icn_132_alt_val J
    lstore 177
    getstatic rung36_jcon_lists/icn_pv_main_i J
    lstore 179
    getstatic rung36_jcon_lists/icn_155_lsa_i J
    lstore 181
    getstatic rung36_jcon_lists/icn_155_lsa_v J
    lstore 183
    getstatic rung36_jcon_lists/icn_158_I J
    lstore 185
    getstatic rung36_jcon_lists/icn_158_bound J
    lstore 187
    getstatic rung36_jcon_lists/icn_158_e1cur J
    lstore 189
    getstatic rung36_jcon_lists/icn_158_e1val J
    lstore 191
    getstatic rung36_jcon_lists/icn_158_e2val J
    lstore 193
    getstatic rung36_jcon_lists/icn_160_binop_lc J
    lstore 195
    getstatic rung36_jcon_lists/icn_160_binop_rc J
    lstore 197
    getstatic rung36_jcon_lists/icn_171_lsa_i J
    lstore 199
    getstatic rung36_jcon_lists/icn_171_lsa_v J
    lstore 201
    getstatic rung36_jcon_lists/icn_174_I J
    lstore 203
    getstatic rung36_jcon_lists/icn_174_bound J
    lstore 205
    getstatic rung36_jcon_lists/icn_174_e1cur J
    lstore 207
    getstatic rung36_jcon_lists/icn_174_e1val J
    lstore 209
    getstatic rung36_jcon_lists/icn_174_e2val J
    lstore 211
    getstatic rung36_jcon_lists/icn_175_binop_lc J
    lstore 213
    getstatic rung36_jcon_lists/icn_175_binop_rc J
    lstore 215
    invokestatic rung36_jcon_lists/icn_limage()V
    lload 161
    putstatic rung36_jcon_lists/icn_pv_main_y J
    lload 163
    putstatic rung36_jcon_lists/icn_41_alt_val J
    lload 165
    putstatic rung36_jcon_lists/icn_50_alt_val J
    lload 167
    putstatic rung36_jcon_lists/icn_102_alt_val J
    lload 169
    putstatic rung36_jcon_lists/icn_107_alt_val J
    lload 171
    putstatic rung36_jcon_lists/icn_112_alt_val J
    lload 173
    putstatic rung36_jcon_lists/icn_119_alt_val J
    lload 175
    putstatic rung36_jcon_lists/icn_126_alt_val J
    lload 177
    putstatic rung36_jcon_lists/icn_132_alt_val J
    lload 179
    putstatic rung36_jcon_lists/icn_pv_main_i J
    lload 181
    putstatic rung36_jcon_lists/icn_155_lsa_i J
    lload 183
    putstatic rung36_jcon_lists/icn_155_lsa_v J
    lload 185
    putstatic rung36_jcon_lists/icn_158_I J
    lload 187
    putstatic rung36_jcon_lists/icn_158_bound J
    lload 189
    putstatic rung36_jcon_lists/icn_158_e1cur J
    lload 191
    putstatic rung36_jcon_lists/icn_158_e1val J
    lload 193
    putstatic rung36_jcon_lists/icn_158_e2val J
    lload 195
    putstatic rung36_jcon_lists/icn_160_binop_lc J
    lload 197
    putstatic rung36_jcon_lists/icn_160_binop_rc J
    lload 199
    putstatic rung36_jcon_lists/icn_171_lsa_i J
    lload 201
    putstatic rung36_jcon_lists/icn_171_lsa_v J
    lload 203
    putstatic rung36_jcon_lists/icn_174_I J
    lload 205
    putstatic rung36_jcon_lists/icn_174_bound J
    lload 207
    putstatic rung36_jcon_lists/icn_174_e1cur J
    lload 209
    putstatic rung36_jcon_lists/icn_174_e1val J
    lload 211
    putstatic rung36_jcon_lists/icn_174_e2val J
    lload 213
    putstatic rung36_jcon_lists/icn_175_binop_lc J
    lload 215
    putstatic rung36_jcon_lists/icn_175_binop_rc J
    getstatic rung36_jcon_lists/icn_failed B
    ifne icn_278_after_call
    getstatic rung36_jcon_lists/icn_retval J
    goto icn_main_s12_sdrain
icn_278_after_call:
    goto icn_273_α
icn_main_s12_sdrain:
    pop2
    goto icn_273_α
icn_292_α:
    new java/util/ArrayList
    dup
    invokespecial java/util/ArrayList/<init>()V
    putstatic rung36_jcon_lists/icn_292_mklist Ljava/util/ArrayList;
;  INT
icn_293_α:
    ldc2_w 2
    goto icn_292_mke_0
icn_293_β:
    goto icn_278_α
    goto icn_293_α
icn_292_mke_0:
    invokestatic java/lang/Long/valueOf(J)Ljava/lang/Long;
    putstatic rung36_jcon_lists/icn_292_elem_0 Ljava/lang/Object;
    getstatic rung36_jcon_lists/icn_292_mklist Ljava/util/ArrayList;
    getstatic rung36_jcon_lists/icn_292_elem_0 Ljava/lang/Object;
    invokevirtual java/util/ArrayList/add(Ljava/lang/Object;)Z
    pop
;  INT
icn_294_α:
    ldc2_w 3
    goto icn_292_mke_1
icn_294_β:
    goto icn_278_α
    goto icn_294_α
icn_292_mke_1:
    invokestatic java/lang/Long/valueOf(J)Ljava/lang/Long;
    putstatic rung36_jcon_lists/icn_292_elem_1 Ljava/lang/Object;
    getstatic rung36_jcon_lists/icn_292_mklist Ljava/util/ArrayList;
    getstatic rung36_jcon_lists/icn_292_elem_1 Ljava/lang/Object;
    invokevirtual java/util/ArrayList/add(Ljava/lang/Object;)Z
    pop
;  INT
icn_295_α:
    ldc2_w 4
    goto icn_292_mke_2
icn_295_β:
    goto icn_278_α
    goto icn_295_α
icn_292_mke_2:
    invokestatic java/lang/Long/valueOf(J)Ljava/lang/Long;
    putstatic rung36_jcon_lists/icn_292_elem_2 Ljava/lang/Object;
    getstatic rung36_jcon_lists/icn_292_mklist Ljava/util/ArrayList;
    getstatic rung36_jcon_lists/icn_292_elem_2 Ljava/lang/Object;
    invokevirtual java/util/ArrayList/add(Ljava/lang/Object;)Z
    pop
;  INT
icn_296_α:
    ldc2_w 5
    goto icn_292_mke_3
icn_296_β:
    goto icn_278_α
    goto icn_296_α
icn_292_mke_3:
    invokestatic java/lang/Long/valueOf(J)Ljava/lang/Long;
    putstatic rung36_jcon_lists/icn_292_elem_3 Ljava/lang/Object;
    getstatic rung36_jcon_lists/icn_292_mklist Ljava/util/ArrayList;
    getstatic rung36_jcon_lists/icn_292_elem_3 Ljava/lang/Object;
    invokevirtual java/util/ArrayList/add(Ljava/lang/Object;)Z
    pop
    getstatic rung36_jcon_lists/icn_292_mklist Ljava/util/ArrayList;
    goto icn_291_arg1
icn_292_β:
    goto icn_278_α
icn_291_arg1:
    putstatic rung36_jcon_lists/icn_arg_1 J
    goto icn_291_docall
;  STR
icn_297_α:
    ldc "h"
    goto icn_291_arg0
icn_297_β:
    goto icn_278_α
icn_291_arg0:
    putstatic rung36_jcon_lists/icn_arg_str_0 Ljava/lang/String;
    lconst_0
    putstatic rung36_jcon_lists/icn_arg_0 J
    goto icn_292_α
icn_291_α:
    goto icn_297_α
icn_291_β:
    goto icn_292_β
icn_291_docall:
    getstatic rung36_jcon_lists/icn_pv_main_y J
    lstore 161
    getstatic rung36_jcon_lists/icn_41_alt_val J
    lstore 163
    getstatic rung36_jcon_lists/icn_50_alt_val J
    lstore 165
    getstatic rung36_jcon_lists/icn_102_alt_val J
    lstore 167
    getstatic rung36_jcon_lists/icn_107_alt_val J
    lstore 169
    getstatic rung36_jcon_lists/icn_112_alt_val J
    lstore 171
    getstatic rung36_jcon_lists/icn_119_alt_val J
    lstore 173
    getstatic rung36_jcon_lists/icn_126_alt_val J
    lstore 175
    getstatic rung36_jcon_lists/icn_132_alt_val J
    lstore 177
    getstatic rung36_jcon_lists/icn_pv_main_i J
    lstore 179
    getstatic rung36_jcon_lists/icn_155_lsa_i J
    lstore 181
    getstatic rung36_jcon_lists/icn_155_lsa_v J
    lstore 183
    getstatic rung36_jcon_lists/icn_158_I J
    lstore 185
    getstatic rung36_jcon_lists/icn_158_bound J
    lstore 187
    getstatic rung36_jcon_lists/icn_158_e1cur J
    lstore 189
    getstatic rung36_jcon_lists/icn_158_e1val J
    lstore 191
    getstatic rung36_jcon_lists/icn_158_e2val J
    lstore 193
    getstatic rung36_jcon_lists/icn_160_binop_lc J
    lstore 195
    getstatic rung36_jcon_lists/icn_160_binop_rc J
    lstore 197
    getstatic rung36_jcon_lists/icn_171_lsa_i J
    lstore 199
    getstatic rung36_jcon_lists/icn_171_lsa_v J
    lstore 201
    getstatic rung36_jcon_lists/icn_174_I J
    lstore 203
    getstatic rung36_jcon_lists/icn_174_bound J
    lstore 205
    getstatic rung36_jcon_lists/icn_174_e1cur J
    lstore 207
    getstatic rung36_jcon_lists/icn_174_e1val J
    lstore 209
    getstatic rung36_jcon_lists/icn_174_e2val J
    lstore 211
    getstatic rung36_jcon_lists/icn_175_binop_lc J
    lstore 213
    getstatic rung36_jcon_lists/icn_175_binop_rc J
    lstore 215
    invokestatic rung36_jcon_lists/icn_limage()V
    lload 161
    putstatic rung36_jcon_lists/icn_pv_main_y J
    lload 163
    putstatic rung36_jcon_lists/icn_41_alt_val J
    lload 165
    putstatic rung36_jcon_lists/icn_50_alt_val J
    lload 167
    putstatic rung36_jcon_lists/icn_102_alt_val J
    lload 169
    putstatic rung36_jcon_lists/icn_107_alt_val J
    lload 171
    putstatic rung36_jcon_lists/icn_112_alt_val J
    lload 173
    putstatic rung36_jcon_lists/icn_119_alt_val J
    lload 175
    putstatic rung36_jcon_lists/icn_126_alt_val J
    lload 177
    putstatic rung36_jcon_lists/icn_132_alt_val J
    lload 179
    putstatic rung36_jcon_lists/icn_pv_main_i J
    lload 181
    putstatic rung36_jcon_lists/icn_155_lsa_i J
    lload 183
    putstatic rung36_jcon_lists/icn_155_lsa_v J
    lload 185
    putstatic rung36_jcon_lists/icn_158_I J
    lload 187
    putstatic rung36_jcon_lists/icn_158_bound J
    lload 189
    putstatic rung36_jcon_lists/icn_158_e1cur J
    lload 191
    putstatic rung36_jcon_lists/icn_158_e1val J
    lload 193
    putstatic rung36_jcon_lists/icn_158_e2val J
    lload 195
    putstatic rung36_jcon_lists/icn_160_binop_lc J
    lload 197
    putstatic rung36_jcon_lists/icn_160_binop_rc J
    lload 199
    putstatic rung36_jcon_lists/icn_171_lsa_i J
    lload 201
    putstatic rung36_jcon_lists/icn_171_lsa_v J
    lload 203
    putstatic rung36_jcon_lists/icn_174_I J
    lload 205
    putstatic rung36_jcon_lists/icn_174_bound J
    lload 207
    putstatic rung36_jcon_lists/icn_174_e1cur J
    lload 209
    putstatic rung36_jcon_lists/icn_174_e1val J
    lload 211
    putstatic rung36_jcon_lists/icn_174_e2val J
    lload 213
    putstatic rung36_jcon_lists/icn_175_binop_lc J
    lload 215
    putstatic rung36_jcon_lists/icn_175_binop_rc J
    getstatic rung36_jcon_lists/icn_failed B
    ifne icn_291_after_call
    getstatic rung36_jcon_lists/icn_retval J
    goto icn_main_s11_sdrain
icn_291_after_call:
    goto icn_278_α
icn_main_s11_sdrain:
    pop2
    goto icn_278_α
icn_299_α:
    new java/util/ArrayList
    dup
    invokespecial java/util/ArrayList/<init>()V
    putstatic rung36_jcon_lists/icn_299_mklist Ljava/util/ArrayList;
;  INT
icn_300_α:
    ldc2_w 1
    goto icn_299_mke_0
icn_300_β:
    goto icn_291_α
    goto icn_300_α
icn_299_mke_0:
    invokestatic java/lang/Long/valueOf(J)Ljava/lang/Long;
    putstatic rung36_jcon_lists/icn_299_elem_0 Ljava/lang/Object;
    getstatic rung36_jcon_lists/icn_299_mklist Ljava/util/ArrayList;
    getstatic rung36_jcon_lists/icn_299_elem_0 Ljava/lang/Object;
    invokevirtual java/util/ArrayList/add(Ljava/lang/Object;)Z
    pop
    getstatic rung36_jcon_lists/icn_299_mklist Ljava/util/ArrayList;
    goto icn_298_arg1
icn_299_β:
    goto icn_291_α
icn_298_arg1:
    putstatic rung36_jcon_lists/icn_arg_1 J
    goto icn_298_docall
;  STR
icn_301_α:
    ldc "g"
    goto icn_298_arg0
icn_301_β:
    goto icn_291_α
icn_298_arg0:
    putstatic rung36_jcon_lists/icn_arg_str_0 Ljava/lang/String;
    lconst_0
    putstatic rung36_jcon_lists/icn_arg_0 J
    goto icn_299_α
icn_298_α:
    goto icn_301_α
icn_298_β:
    goto icn_299_β
icn_298_docall:
    getstatic rung36_jcon_lists/icn_pv_main_y J
    lstore 161
    getstatic rung36_jcon_lists/icn_41_alt_val J
    lstore 163
    getstatic rung36_jcon_lists/icn_50_alt_val J
    lstore 165
    getstatic rung36_jcon_lists/icn_102_alt_val J
    lstore 167
    getstatic rung36_jcon_lists/icn_107_alt_val J
    lstore 169
    getstatic rung36_jcon_lists/icn_112_alt_val J
    lstore 171
    getstatic rung36_jcon_lists/icn_119_alt_val J
    lstore 173
    getstatic rung36_jcon_lists/icn_126_alt_val J
    lstore 175
    getstatic rung36_jcon_lists/icn_132_alt_val J
    lstore 177
    getstatic rung36_jcon_lists/icn_pv_main_i J
    lstore 179
    getstatic rung36_jcon_lists/icn_155_lsa_i J
    lstore 181
    getstatic rung36_jcon_lists/icn_155_lsa_v J
    lstore 183
    getstatic rung36_jcon_lists/icn_158_I J
    lstore 185
    getstatic rung36_jcon_lists/icn_158_bound J
    lstore 187
    getstatic rung36_jcon_lists/icn_158_e1cur J
    lstore 189
    getstatic rung36_jcon_lists/icn_158_e1val J
    lstore 191
    getstatic rung36_jcon_lists/icn_158_e2val J
    lstore 193
    getstatic rung36_jcon_lists/icn_160_binop_lc J
    lstore 195
    getstatic rung36_jcon_lists/icn_160_binop_rc J
    lstore 197
    getstatic rung36_jcon_lists/icn_171_lsa_i J
    lstore 199
    getstatic rung36_jcon_lists/icn_171_lsa_v J
    lstore 201
    getstatic rung36_jcon_lists/icn_174_I J
    lstore 203
    getstatic rung36_jcon_lists/icn_174_bound J
    lstore 205
    getstatic rung36_jcon_lists/icn_174_e1cur J
    lstore 207
    getstatic rung36_jcon_lists/icn_174_e1val J
    lstore 209
    getstatic rung36_jcon_lists/icn_174_e2val J
    lstore 211
    getstatic rung36_jcon_lists/icn_175_binop_lc J
    lstore 213
    getstatic rung36_jcon_lists/icn_175_binop_rc J
    lstore 215
    invokestatic rung36_jcon_lists/icn_limage()V
    lload 161
    putstatic rung36_jcon_lists/icn_pv_main_y J
    lload 163
    putstatic rung36_jcon_lists/icn_41_alt_val J
    lload 165
    putstatic rung36_jcon_lists/icn_50_alt_val J
    lload 167
    putstatic rung36_jcon_lists/icn_102_alt_val J
    lload 169
    putstatic rung36_jcon_lists/icn_107_alt_val J
    lload 171
    putstatic rung36_jcon_lists/icn_112_alt_val J
    lload 173
    putstatic rung36_jcon_lists/icn_119_alt_val J
    lload 175
    putstatic rung36_jcon_lists/icn_126_alt_val J
    lload 177
    putstatic rung36_jcon_lists/icn_132_alt_val J
    lload 179
    putstatic rung36_jcon_lists/icn_pv_main_i J
    lload 181
    putstatic rung36_jcon_lists/icn_155_lsa_i J
    lload 183
    putstatic rung36_jcon_lists/icn_155_lsa_v J
    lload 185
    putstatic rung36_jcon_lists/icn_158_I J
    lload 187
    putstatic rung36_jcon_lists/icn_158_bound J
    lload 189
    putstatic rung36_jcon_lists/icn_158_e1cur J
    lload 191
    putstatic rung36_jcon_lists/icn_158_e1val J
    lload 193
    putstatic rung36_jcon_lists/icn_158_e2val J
    lload 195
    putstatic rung36_jcon_lists/icn_160_binop_lc J
    lload 197
    putstatic rung36_jcon_lists/icn_160_binop_rc J
    lload 199
    putstatic rung36_jcon_lists/icn_171_lsa_i J
    lload 201
    putstatic rung36_jcon_lists/icn_171_lsa_v J
    lload 203
    putstatic rung36_jcon_lists/icn_174_I J
    lload 205
    putstatic rung36_jcon_lists/icn_174_bound J
    lload 207
    putstatic rung36_jcon_lists/icn_174_e1cur J
    lload 209
    putstatic rung36_jcon_lists/icn_174_e1val J
    lload 211
    putstatic rung36_jcon_lists/icn_174_e2val J
    lload 213
    putstatic rung36_jcon_lists/icn_175_binop_lc J
    lload 215
    putstatic rung36_jcon_lists/icn_175_binop_rc J
    getstatic rung36_jcon_lists/icn_failed B
    ifne icn_298_after_call
    getstatic rung36_jcon_lists/icn_retval J
    goto icn_main_s10_sdrain
icn_298_after_call:
    goto icn_291_α
icn_main_s10_sdrain:
    pop2
    goto icn_291_α
icn_303_α:
    new java/util/ArrayList
    dup
    invokespecial java/util/ArrayList/<init>()V
    putstatic rung36_jcon_lists/icn_303_mklist Ljava/util/ArrayList;
;  VAR
icn_304_α:
    lconst_0
    goto icn_303_mke_0
icn_304_β:
    goto icn_298_α
    goto icn_304_α
icn_303_mke_0:
    invokestatic java/lang/Long/valueOf(J)Ljava/lang/Long;
    putstatic rung36_jcon_lists/icn_303_elem_0 Ljava/lang/Object;
    getstatic rung36_jcon_lists/icn_303_mklist Ljava/util/ArrayList;
    getstatic rung36_jcon_lists/icn_303_elem_0 Ljava/lang/Object;
    invokevirtual java/util/ArrayList/add(Ljava/lang/Object;)Z
    pop
    getstatic rung36_jcon_lists/icn_303_mklist Ljava/util/ArrayList;
    goto icn_302_arg1
icn_303_β:
    goto icn_298_α
icn_302_arg1:
    putstatic rung36_jcon_lists/icn_arg_1 J
    goto icn_302_docall
;  STR
icn_305_α:
    ldc "f"
    goto icn_302_arg0
icn_305_β:
    goto icn_298_α
icn_302_arg0:
    putstatic rung36_jcon_lists/icn_arg_str_0 Ljava/lang/String;
    lconst_0
    putstatic rung36_jcon_lists/icn_arg_0 J
    goto icn_303_α
icn_302_α:
    goto icn_305_α
icn_302_β:
    goto icn_303_β
icn_302_docall:
    getstatic rung36_jcon_lists/icn_pv_main_y J
    lstore 161
    getstatic rung36_jcon_lists/icn_41_alt_val J
    lstore 163
    getstatic rung36_jcon_lists/icn_50_alt_val J
    lstore 165
    getstatic rung36_jcon_lists/icn_102_alt_val J
    lstore 167
    getstatic rung36_jcon_lists/icn_107_alt_val J
    lstore 169
    getstatic rung36_jcon_lists/icn_112_alt_val J
    lstore 171
    getstatic rung36_jcon_lists/icn_119_alt_val J
    lstore 173
    getstatic rung36_jcon_lists/icn_126_alt_val J
    lstore 175
    getstatic rung36_jcon_lists/icn_132_alt_val J
    lstore 177
    getstatic rung36_jcon_lists/icn_pv_main_i J
    lstore 179
    getstatic rung36_jcon_lists/icn_155_lsa_i J
    lstore 181
    getstatic rung36_jcon_lists/icn_155_lsa_v J
    lstore 183
    getstatic rung36_jcon_lists/icn_158_I J
    lstore 185
    getstatic rung36_jcon_lists/icn_158_bound J
    lstore 187
    getstatic rung36_jcon_lists/icn_158_e1cur J
    lstore 189
    getstatic rung36_jcon_lists/icn_158_e1val J
    lstore 191
    getstatic rung36_jcon_lists/icn_158_e2val J
    lstore 193
    getstatic rung36_jcon_lists/icn_160_binop_lc J
    lstore 195
    getstatic rung36_jcon_lists/icn_160_binop_rc J
    lstore 197
    getstatic rung36_jcon_lists/icn_171_lsa_i J
    lstore 199
    getstatic rung36_jcon_lists/icn_171_lsa_v J
    lstore 201
    getstatic rung36_jcon_lists/icn_174_I J
    lstore 203
    getstatic rung36_jcon_lists/icn_174_bound J
    lstore 205
    getstatic rung36_jcon_lists/icn_174_e1cur J
    lstore 207
    getstatic rung36_jcon_lists/icn_174_e1val J
    lstore 209
    getstatic rung36_jcon_lists/icn_174_e2val J
    lstore 211
    getstatic rung36_jcon_lists/icn_175_binop_lc J
    lstore 213
    getstatic rung36_jcon_lists/icn_175_binop_rc J
    lstore 215
    invokestatic rung36_jcon_lists/icn_limage()V
    lload 161
    putstatic rung36_jcon_lists/icn_pv_main_y J
    lload 163
    putstatic rung36_jcon_lists/icn_41_alt_val J
    lload 165
    putstatic rung36_jcon_lists/icn_50_alt_val J
    lload 167
    putstatic rung36_jcon_lists/icn_102_alt_val J
    lload 169
    putstatic rung36_jcon_lists/icn_107_alt_val J
    lload 171
    putstatic rung36_jcon_lists/icn_112_alt_val J
    lload 173
    putstatic rung36_jcon_lists/icn_119_alt_val J
    lload 175
    putstatic rung36_jcon_lists/icn_126_alt_val J
    lload 177
    putstatic rung36_jcon_lists/icn_132_alt_val J
    lload 179
    putstatic rung36_jcon_lists/icn_pv_main_i J
    lload 181
    putstatic rung36_jcon_lists/icn_155_lsa_i J
    lload 183
    putstatic rung36_jcon_lists/icn_155_lsa_v J
    lload 185
    putstatic rung36_jcon_lists/icn_158_I J
    lload 187
    putstatic rung36_jcon_lists/icn_158_bound J
    lload 189
    putstatic rung36_jcon_lists/icn_158_e1cur J
    lload 191
    putstatic rung36_jcon_lists/icn_158_e1val J
    lload 193
    putstatic rung36_jcon_lists/icn_158_e2val J
    lload 195
    putstatic rung36_jcon_lists/icn_160_binop_lc J
    lload 197
    putstatic rung36_jcon_lists/icn_160_binop_rc J
    lload 199
    putstatic rung36_jcon_lists/icn_171_lsa_i J
    lload 201
    putstatic rung36_jcon_lists/icn_171_lsa_v J
    lload 203
    putstatic rung36_jcon_lists/icn_174_I J
    lload 205
    putstatic rung36_jcon_lists/icn_174_bound J
    lload 207
    putstatic rung36_jcon_lists/icn_174_e1cur J
    lload 209
    putstatic rung36_jcon_lists/icn_174_e1val J
    lload 211
    putstatic rung36_jcon_lists/icn_174_e2val J
    lload 213
    putstatic rung36_jcon_lists/icn_175_binop_lc J
    lload 215
    putstatic rung36_jcon_lists/icn_175_binop_rc J
    getstatic rung36_jcon_lists/icn_failed B
    ifne icn_302_after_call
    getstatic rung36_jcon_lists/icn_retval J
    goto icn_main_s9_sdrain
icn_302_after_call:
    goto icn_298_α
icn_main_s9_sdrain:
    pop2
    goto icn_298_α
icn_307_α:
    new java/util/ArrayList
    dup
    invokespecial java/util/ArrayList/<init>()V
    putstatic rung36_jcon_lists/icn_307_mklist Ljava/util/ArrayList;
    getstatic rung36_jcon_lists/icn_307_mklist Ljava/util/ArrayList;
    goto icn_306_arg1
icn_307_β:
    goto icn_302_α
icn_306_arg1:
    putstatic rung36_jcon_lists/icn_arg_1 J
    goto icn_306_docall
;  STR
icn_308_α:
    ldc "e"
    goto icn_306_arg0
icn_308_β:
    goto icn_302_α
icn_306_arg0:
    putstatic rung36_jcon_lists/icn_arg_str_0 Ljava/lang/String;
    lconst_0
    putstatic rung36_jcon_lists/icn_arg_0 J
    goto icn_307_α
icn_306_α:
    goto icn_308_α
icn_306_β:
    goto icn_307_β
icn_306_docall:
    getstatic rung36_jcon_lists/icn_pv_main_y J
    lstore 161
    getstatic rung36_jcon_lists/icn_41_alt_val J
    lstore 163
    getstatic rung36_jcon_lists/icn_50_alt_val J
    lstore 165
    getstatic rung36_jcon_lists/icn_102_alt_val J
    lstore 167
    getstatic rung36_jcon_lists/icn_107_alt_val J
    lstore 169
    getstatic rung36_jcon_lists/icn_112_alt_val J
    lstore 171
    getstatic rung36_jcon_lists/icn_119_alt_val J
    lstore 173
    getstatic rung36_jcon_lists/icn_126_alt_val J
    lstore 175
    getstatic rung36_jcon_lists/icn_132_alt_val J
    lstore 177
    getstatic rung36_jcon_lists/icn_pv_main_i J
    lstore 179
    getstatic rung36_jcon_lists/icn_155_lsa_i J
    lstore 181
    getstatic rung36_jcon_lists/icn_155_lsa_v J
    lstore 183
    getstatic rung36_jcon_lists/icn_158_I J
    lstore 185
    getstatic rung36_jcon_lists/icn_158_bound J
    lstore 187
    getstatic rung36_jcon_lists/icn_158_e1cur J
    lstore 189
    getstatic rung36_jcon_lists/icn_158_e1val J
    lstore 191
    getstatic rung36_jcon_lists/icn_158_e2val J
    lstore 193
    getstatic rung36_jcon_lists/icn_160_binop_lc J
    lstore 195
    getstatic rung36_jcon_lists/icn_160_binop_rc J
    lstore 197
    getstatic rung36_jcon_lists/icn_171_lsa_i J
    lstore 199
    getstatic rung36_jcon_lists/icn_171_lsa_v J
    lstore 201
    getstatic rung36_jcon_lists/icn_174_I J
    lstore 203
    getstatic rung36_jcon_lists/icn_174_bound J
    lstore 205
    getstatic rung36_jcon_lists/icn_174_e1cur J
    lstore 207
    getstatic rung36_jcon_lists/icn_174_e1val J
    lstore 209
    getstatic rung36_jcon_lists/icn_174_e2val J
    lstore 211
    getstatic rung36_jcon_lists/icn_175_binop_lc J
    lstore 213
    getstatic rung36_jcon_lists/icn_175_binop_rc J
    lstore 215
    invokestatic rung36_jcon_lists/icn_limage()V
    lload 161
    putstatic rung36_jcon_lists/icn_pv_main_y J
    lload 163
    putstatic rung36_jcon_lists/icn_41_alt_val J
    lload 165
    putstatic rung36_jcon_lists/icn_50_alt_val J
    lload 167
    putstatic rung36_jcon_lists/icn_102_alt_val J
    lload 169
    putstatic rung36_jcon_lists/icn_107_alt_val J
    lload 171
    putstatic rung36_jcon_lists/icn_112_alt_val J
    lload 173
    putstatic rung36_jcon_lists/icn_119_alt_val J
    lload 175
    putstatic rung36_jcon_lists/icn_126_alt_val J
    lload 177
    putstatic rung36_jcon_lists/icn_132_alt_val J
    lload 179
    putstatic rung36_jcon_lists/icn_pv_main_i J
    lload 181
    putstatic rung36_jcon_lists/icn_155_lsa_i J
    lload 183
    putstatic rung36_jcon_lists/icn_155_lsa_v J
    lload 185
    putstatic rung36_jcon_lists/icn_158_I J
    lload 187
    putstatic rung36_jcon_lists/icn_158_bound J
    lload 189
    putstatic rung36_jcon_lists/icn_158_e1cur J
    lload 191
    putstatic rung36_jcon_lists/icn_158_e1val J
    lload 193
    putstatic rung36_jcon_lists/icn_158_e2val J
    lload 195
    putstatic rung36_jcon_lists/icn_160_binop_lc J
    lload 197
    putstatic rung36_jcon_lists/icn_160_binop_rc J
    lload 199
    putstatic rung36_jcon_lists/icn_171_lsa_i J
    lload 201
    putstatic rung36_jcon_lists/icn_171_lsa_v J
    lload 203
    putstatic rung36_jcon_lists/icn_174_I J
    lload 205
    putstatic rung36_jcon_lists/icn_174_bound J
    lload 207
    putstatic rung36_jcon_lists/icn_174_e1cur J
    lload 209
    putstatic rung36_jcon_lists/icn_174_e1val J
    lload 211
    putstatic rung36_jcon_lists/icn_174_e2val J
    lload 213
    putstatic rung36_jcon_lists/icn_175_binop_lc J
    lload 215
    putstatic rung36_jcon_lists/icn_175_binop_rc J
    getstatic rung36_jcon_lists/icn_failed B
    ifne icn_306_after_call
    getstatic rung36_jcon_lists/icn_retval J
    goto icn_main_s8_sdrain
icn_306_after_call:
    goto icn_302_α
icn_main_s8_sdrain:
    pop2
    goto icn_302_α
;  INT
icn_311_α:
    ldc2_w 6
    goto icn_310_nlr
icn_311_β:
    goto icn_306_α
;  INT
icn_312_α:
    ldc2_w 7
    goto icn_310_xlr
icn_312_β:
    goto icn_306_α
icn_310_α:
    goto icn_311_α
icn_310_β:
    goto icn_306_α
icn_310_nlr:
    putstatic rung36_jcon_lists/icn_310_ln J
    goto icn_312_α
icn_310_xlr:
    invokestatic java/lang/Long/valueOf(J)Ljava/lang/Long;
    putstatic rung36_jcon_lists/icn_310_lx Ljava/lang/Object;
    new java/util/ArrayList
    dup
    invokespecial java/util/ArrayList/<init>()V
    putstatic rung36_jcon_lists/icn_310_ll Ljava/util/ArrayList;
    getstatic rung36_jcon_lists/icn_310_ln J
    l2i
    putstatic rung36_jcon_lists/icn_310_lc I
icn_310_llp:
    getstatic rung36_jcon_lists/icn_310_lc I
    ifeq icn_310_lld
    getstatic rung36_jcon_lists/icn_310_ll Ljava/util/ArrayList;
    getstatic rung36_jcon_lists/icn_310_lx Ljava/lang/Object;
    invokevirtual java/util/ArrayList/add(Ljava/lang/Object;)Z
    pop
    getstatic rung36_jcon_lists/icn_310_lc I
    iconst_1
    isub
    putstatic rung36_jcon_lists/icn_310_lc I
    goto icn_310_llp
icn_310_lld:
    getstatic rung36_jcon_lists/icn_310_ll Ljava/util/ArrayList;
    goto icn_309_arg1
icn_309_arg1:
    putstatic rung36_jcon_lists/icn_arg_1 J
    goto icn_309_docall
;  STR
icn_313_α:
    ldc "d"
    goto icn_309_arg0
icn_313_β:
    goto icn_306_α
icn_309_arg0:
    putstatic rung36_jcon_lists/icn_arg_str_0 Ljava/lang/String;
    lconst_0
    putstatic rung36_jcon_lists/icn_arg_0 J
    goto icn_310_α
icn_309_α:
    goto icn_313_α
icn_309_β:
    goto icn_310_β
icn_309_docall:
    getstatic rung36_jcon_lists/icn_pv_main_y J
    lstore 161
    getstatic rung36_jcon_lists/icn_41_alt_val J
    lstore 163
    getstatic rung36_jcon_lists/icn_50_alt_val J
    lstore 165
    getstatic rung36_jcon_lists/icn_102_alt_val J
    lstore 167
    getstatic rung36_jcon_lists/icn_107_alt_val J
    lstore 169
    getstatic rung36_jcon_lists/icn_112_alt_val J
    lstore 171
    getstatic rung36_jcon_lists/icn_119_alt_val J
    lstore 173
    getstatic rung36_jcon_lists/icn_126_alt_val J
    lstore 175
    getstatic rung36_jcon_lists/icn_132_alt_val J
    lstore 177
    getstatic rung36_jcon_lists/icn_pv_main_i J
    lstore 179
    getstatic rung36_jcon_lists/icn_155_lsa_i J
    lstore 181
    getstatic rung36_jcon_lists/icn_155_lsa_v J
    lstore 183
    getstatic rung36_jcon_lists/icn_158_I J
    lstore 185
    getstatic rung36_jcon_lists/icn_158_bound J
    lstore 187
    getstatic rung36_jcon_lists/icn_158_e1cur J
    lstore 189
    getstatic rung36_jcon_lists/icn_158_e1val J
    lstore 191
    getstatic rung36_jcon_lists/icn_158_e2val J
    lstore 193
    getstatic rung36_jcon_lists/icn_160_binop_lc J
    lstore 195
    getstatic rung36_jcon_lists/icn_160_binop_rc J
    lstore 197
    getstatic rung36_jcon_lists/icn_171_lsa_i J
    lstore 199
    getstatic rung36_jcon_lists/icn_171_lsa_v J
    lstore 201
    getstatic rung36_jcon_lists/icn_174_I J
    lstore 203
    getstatic rung36_jcon_lists/icn_174_bound J
    lstore 205
    getstatic rung36_jcon_lists/icn_174_e1cur J
    lstore 207
    getstatic rung36_jcon_lists/icn_174_e1val J
    lstore 209
    getstatic rung36_jcon_lists/icn_174_e2val J
    lstore 211
    getstatic rung36_jcon_lists/icn_175_binop_lc J
    lstore 213
    getstatic rung36_jcon_lists/icn_175_binop_rc J
    lstore 215
    getstatic rung36_jcon_lists/icn_310_ln J
    lstore 217
    invokestatic rung36_jcon_lists/icn_limage()V
    lload 161
    putstatic rung36_jcon_lists/icn_pv_main_y J
    lload 163
    putstatic rung36_jcon_lists/icn_41_alt_val J
    lload 165
    putstatic rung36_jcon_lists/icn_50_alt_val J
    lload 167
    putstatic rung36_jcon_lists/icn_102_alt_val J
    lload 169
    putstatic rung36_jcon_lists/icn_107_alt_val J
    lload 171
    putstatic rung36_jcon_lists/icn_112_alt_val J
    lload 173
    putstatic rung36_jcon_lists/icn_119_alt_val J
    lload 175
    putstatic rung36_jcon_lists/icn_126_alt_val J
    lload 177
    putstatic rung36_jcon_lists/icn_132_alt_val J
    lload 179
    putstatic rung36_jcon_lists/icn_pv_main_i J
    lload 181
    putstatic rung36_jcon_lists/icn_155_lsa_i J
    lload 183
    putstatic rung36_jcon_lists/icn_155_lsa_v J
    lload 185
    putstatic rung36_jcon_lists/icn_158_I J
    lload 187
    putstatic rung36_jcon_lists/icn_158_bound J
    lload 189
    putstatic rung36_jcon_lists/icn_158_e1cur J
    lload 191
    putstatic rung36_jcon_lists/icn_158_e1val J
    lload 193
    putstatic rung36_jcon_lists/icn_158_e2val J
    lload 195
    putstatic rung36_jcon_lists/icn_160_binop_lc J
    lload 197
    putstatic rung36_jcon_lists/icn_160_binop_rc J
    lload 199
    putstatic rung36_jcon_lists/icn_171_lsa_i J
    lload 201
    putstatic rung36_jcon_lists/icn_171_lsa_v J
    lload 203
    putstatic rung36_jcon_lists/icn_174_I J
    lload 205
    putstatic rung36_jcon_lists/icn_174_bound J
    lload 207
    putstatic rung36_jcon_lists/icn_174_e1cur J
    lload 209
    putstatic rung36_jcon_lists/icn_174_e1val J
    lload 211
    putstatic rung36_jcon_lists/icn_174_e2val J
    lload 213
    putstatic rung36_jcon_lists/icn_175_binop_lc J
    lload 215
    putstatic rung36_jcon_lists/icn_175_binop_rc J
    lload 217
    putstatic rung36_jcon_lists/icn_310_ln J
    getstatic rung36_jcon_lists/icn_failed B
    ifne icn_309_after_call
    getstatic rung36_jcon_lists/icn_retval J
    goto icn_main_s7_sdrain
icn_309_after_call:
    goto icn_306_α
icn_main_s7_sdrain:
    pop2
    goto icn_306_α
;  INT
icn_316_α:
    ldc2_w 4
    goto icn_315_nlr
icn_316_β:
    goto icn_309_α
;  INT
icn_317_α:
    ldc2_w 5
    goto icn_315_xlr
icn_317_β:
    goto icn_309_α
icn_315_α:
    goto icn_316_α
icn_315_β:
    goto icn_309_α
icn_315_nlr:
    putstatic rung36_jcon_lists/icn_315_ln J
    goto icn_317_α
icn_315_xlr:
    invokestatic java/lang/Long/valueOf(J)Ljava/lang/Long;
    putstatic rung36_jcon_lists/icn_315_lx Ljava/lang/Object;
    new java/util/ArrayList
    dup
    invokespecial java/util/ArrayList/<init>()V
    putstatic rung36_jcon_lists/icn_315_ll Ljava/util/ArrayList;
    getstatic rung36_jcon_lists/icn_315_ln J
    l2i
    putstatic rung36_jcon_lists/icn_315_lc I
icn_315_llp:
    getstatic rung36_jcon_lists/icn_315_lc I
    ifeq icn_315_lld
    getstatic rung36_jcon_lists/icn_315_ll Ljava/util/ArrayList;
    getstatic rung36_jcon_lists/icn_315_lx Ljava/lang/Object;
    invokevirtual java/util/ArrayList/add(Ljava/lang/Object;)Z
    pop
    getstatic rung36_jcon_lists/icn_315_lc I
    iconst_1
    isub
    putstatic rung36_jcon_lists/icn_315_lc I
    goto icn_315_llp
icn_315_lld:
    getstatic rung36_jcon_lists/icn_315_ll Ljava/util/ArrayList;
    goto icn_314_arg1
icn_314_arg1:
    putstatic rung36_jcon_lists/icn_arg_1 J
    goto icn_314_docall
;  STR
icn_318_α:
    ldc "d"
    goto icn_314_arg0
icn_318_β:
    goto icn_309_α
icn_314_arg0:
    putstatic rung36_jcon_lists/icn_arg_str_0 Ljava/lang/String;
    lconst_0
    putstatic rung36_jcon_lists/icn_arg_0 J
    goto icn_315_α
icn_314_α:
    goto icn_318_α
icn_314_β:
    goto icn_315_β
icn_314_docall:
    getstatic rung36_jcon_lists/icn_pv_main_y J
    lstore 161
    getstatic rung36_jcon_lists/icn_41_alt_val J
    lstore 163
    getstatic rung36_jcon_lists/icn_50_alt_val J
    lstore 165
    getstatic rung36_jcon_lists/icn_102_alt_val J
    lstore 167
    getstatic rung36_jcon_lists/icn_107_alt_val J
    lstore 169
    getstatic rung36_jcon_lists/icn_112_alt_val J
    lstore 171
    getstatic rung36_jcon_lists/icn_119_alt_val J
    lstore 173
    getstatic rung36_jcon_lists/icn_126_alt_val J
    lstore 175
    getstatic rung36_jcon_lists/icn_132_alt_val J
    lstore 177
    getstatic rung36_jcon_lists/icn_pv_main_i J
    lstore 179
    getstatic rung36_jcon_lists/icn_155_lsa_i J
    lstore 181
    getstatic rung36_jcon_lists/icn_155_lsa_v J
    lstore 183
    getstatic rung36_jcon_lists/icn_158_I J
    lstore 185
    getstatic rung36_jcon_lists/icn_158_bound J
    lstore 187
    getstatic rung36_jcon_lists/icn_158_e1cur J
    lstore 189
    getstatic rung36_jcon_lists/icn_158_e1val J
    lstore 191
    getstatic rung36_jcon_lists/icn_158_e2val J
    lstore 193
    getstatic rung36_jcon_lists/icn_160_binop_lc J
    lstore 195
    getstatic rung36_jcon_lists/icn_160_binop_rc J
    lstore 197
    getstatic rung36_jcon_lists/icn_171_lsa_i J
    lstore 199
    getstatic rung36_jcon_lists/icn_171_lsa_v J
    lstore 201
    getstatic rung36_jcon_lists/icn_174_I J
    lstore 203
    getstatic rung36_jcon_lists/icn_174_bound J
    lstore 205
    getstatic rung36_jcon_lists/icn_174_e1cur J
    lstore 207
    getstatic rung36_jcon_lists/icn_174_e1val J
    lstore 209
    getstatic rung36_jcon_lists/icn_174_e2val J
    lstore 211
    getstatic rung36_jcon_lists/icn_175_binop_lc J
    lstore 213
    getstatic rung36_jcon_lists/icn_175_binop_rc J
    lstore 215
    getstatic rung36_jcon_lists/icn_310_ln J
    lstore 217
    getstatic rung36_jcon_lists/icn_315_ln J
    lstore 219
    invokestatic rung36_jcon_lists/icn_limage()V
    lload 161
    putstatic rung36_jcon_lists/icn_pv_main_y J
    lload 163
    putstatic rung36_jcon_lists/icn_41_alt_val J
    lload 165
    putstatic rung36_jcon_lists/icn_50_alt_val J
    lload 167
    putstatic rung36_jcon_lists/icn_102_alt_val J
    lload 169
    putstatic rung36_jcon_lists/icn_107_alt_val J
    lload 171
    putstatic rung36_jcon_lists/icn_112_alt_val J
    lload 173
    putstatic rung36_jcon_lists/icn_119_alt_val J
    lload 175
    putstatic rung36_jcon_lists/icn_126_alt_val J
    lload 177
    putstatic rung36_jcon_lists/icn_132_alt_val J
    lload 179
    putstatic rung36_jcon_lists/icn_pv_main_i J
    lload 181
    putstatic rung36_jcon_lists/icn_155_lsa_i J
    lload 183
    putstatic rung36_jcon_lists/icn_155_lsa_v J
    lload 185
    putstatic rung36_jcon_lists/icn_158_I J
    lload 187
    putstatic rung36_jcon_lists/icn_158_bound J
    lload 189
    putstatic rung36_jcon_lists/icn_158_e1cur J
    lload 191
    putstatic rung36_jcon_lists/icn_158_e1val J
    lload 193
    putstatic rung36_jcon_lists/icn_158_e2val J
    lload 195
    putstatic rung36_jcon_lists/icn_160_binop_lc J
    lload 197
    putstatic rung36_jcon_lists/icn_160_binop_rc J
    lload 199
    putstatic rung36_jcon_lists/icn_171_lsa_i J
    lload 201
    putstatic rung36_jcon_lists/icn_171_lsa_v J
    lload 203
    putstatic rung36_jcon_lists/icn_174_I J
    lload 205
    putstatic rung36_jcon_lists/icn_174_bound J
    lload 207
    putstatic rung36_jcon_lists/icn_174_e1cur J
    lload 209
    putstatic rung36_jcon_lists/icn_174_e1val J
    lload 211
    putstatic rung36_jcon_lists/icn_174_e2val J
    lload 213
    putstatic rung36_jcon_lists/icn_175_binop_lc J
    lload 215
    putstatic rung36_jcon_lists/icn_175_binop_rc J
    lload 217
    putstatic rung36_jcon_lists/icn_310_ln J
    lload 219
    putstatic rung36_jcon_lists/icn_315_ln J
    getstatic rung36_jcon_lists/icn_failed B
    ifne icn_314_after_call
    getstatic rung36_jcon_lists/icn_retval J
    goto icn_main_s6_sdrain
icn_314_after_call:
    goto icn_309_α
icn_main_s6_sdrain:
    pop2
    goto icn_309_α
;  VAR
icn_321_α:
    lconst_0
    goto icn_320_nlr
icn_321_β:
    goto icn_314_α
;  INT
icn_322_α:
    ldc2_w 3
    goto icn_320_xlr
icn_322_β:
    goto icn_314_α
icn_320_α:
    goto icn_321_α
icn_320_β:
    goto icn_314_α
icn_320_nlr:
    putstatic rung36_jcon_lists/icn_320_ln J
    goto icn_322_α
icn_320_xlr:
    invokestatic java/lang/Long/valueOf(J)Ljava/lang/Long;
    putstatic rung36_jcon_lists/icn_320_lx Ljava/lang/Object;
    new java/util/ArrayList
    dup
    invokespecial java/util/ArrayList/<init>()V
    putstatic rung36_jcon_lists/icn_320_ll Ljava/util/ArrayList;
    getstatic rung36_jcon_lists/icn_320_ln J
    l2i
    putstatic rung36_jcon_lists/icn_320_lc I
icn_320_llp:
    getstatic rung36_jcon_lists/icn_320_lc I
    ifeq icn_320_lld
    getstatic rung36_jcon_lists/icn_320_ll Ljava/util/ArrayList;
    getstatic rung36_jcon_lists/icn_320_lx Ljava/lang/Object;
    invokevirtual java/util/ArrayList/add(Ljava/lang/Object;)Z
    pop
    getstatic rung36_jcon_lists/icn_320_lc I
    iconst_1
    isub
    putstatic rung36_jcon_lists/icn_320_lc I
    goto icn_320_llp
icn_320_lld:
    getstatic rung36_jcon_lists/icn_320_ll Ljava/util/ArrayList;
    goto icn_319_arg1
icn_319_arg1:
    putstatic rung36_jcon_lists/icn_arg_1 J
    goto icn_319_docall
;  STR
icn_323_α:
    ldc "c"
    goto icn_319_arg0
icn_323_β:
    goto icn_314_α
icn_319_arg0:
    putstatic rung36_jcon_lists/icn_arg_str_0 Ljava/lang/String;
    lconst_0
    putstatic rung36_jcon_lists/icn_arg_0 J
    goto icn_320_α
icn_319_α:
    goto icn_323_α
icn_319_β:
    goto icn_320_β
icn_319_docall:
    getstatic rung36_jcon_lists/icn_pv_main_y J
    lstore 161
    getstatic rung36_jcon_lists/icn_41_alt_val J
    lstore 163
    getstatic rung36_jcon_lists/icn_50_alt_val J
    lstore 165
    getstatic rung36_jcon_lists/icn_102_alt_val J
    lstore 167
    getstatic rung36_jcon_lists/icn_107_alt_val J
    lstore 169
    getstatic rung36_jcon_lists/icn_112_alt_val J
    lstore 171
    getstatic rung36_jcon_lists/icn_119_alt_val J
    lstore 173
    getstatic rung36_jcon_lists/icn_126_alt_val J
    lstore 175
    getstatic rung36_jcon_lists/icn_132_alt_val J
    lstore 177
    getstatic rung36_jcon_lists/icn_pv_main_i J
    lstore 179
    getstatic rung36_jcon_lists/icn_155_lsa_i J
    lstore 181
    getstatic rung36_jcon_lists/icn_155_lsa_v J
    lstore 183
    getstatic rung36_jcon_lists/icn_158_I J
    lstore 185
    getstatic rung36_jcon_lists/icn_158_bound J
    lstore 187
    getstatic rung36_jcon_lists/icn_158_e1cur J
    lstore 189
    getstatic rung36_jcon_lists/icn_158_e1val J
    lstore 191
    getstatic rung36_jcon_lists/icn_158_e2val J
    lstore 193
    getstatic rung36_jcon_lists/icn_160_binop_lc J
    lstore 195
    getstatic rung36_jcon_lists/icn_160_binop_rc J
    lstore 197
    getstatic rung36_jcon_lists/icn_171_lsa_i J
    lstore 199
    getstatic rung36_jcon_lists/icn_171_lsa_v J
    lstore 201
    getstatic rung36_jcon_lists/icn_174_I J
    lstore 203
    getstatic rung36_jcon_lists/icn_174_bound J
    lstore 205
    getstatic rung36_jcon_lists/icn_174_e1cur J
    lstore 207
    getstatic rung36_jcon_lists/icn_174_e1val J
    lstore 209
    getstatic rung36_jcon_lists/icn_174_e2val J
    lstore 211
    getstatic rung36_jcon_lists/icn_175_binop_lc J
    lstore 213
    getstatic rung36_jcon_lists/icn_175_binop_rc J
    lstore 215
    getstatic rung36_jcon_lists/icn_310_ln J
    lstore 217
    getstatic rung36_jcon_lists/icn_315_ln J
    lstore 219
    getstatic rung36_jcon_lists/icn_320_ln J
    lstore 221
    invokestatic rung36_jcon_lists/icn_limage()V
    lload 161
    putstatic rung36_jcon_lists/icn_pv_main_y J
    lload 163
    putstatic rung36_jcon_lists/icn_41_alt_val J
    lload 165
    putstatic rung36_jcon_lists/icn_50_alt_val J
    lload 167
    putstatic rung36_jcon_lists/icn_102_alt_val J
    lload 169
    putstatic rung36_jcon_lists/icn_107_alt_val J
    lload 171
    putstatic rung36_jcon_lists/icn_112_alt_val J
    lload 173
    putstatic rung36_jcon_lists/icn_119_alt_val J
    lload 175
    putstatic rung36_jcon_lists/icn_126_alt_val J
    lload 177
    putstatic rung36_jcon_lists/icn_132_alt_val J
    lload 179
    putstatic rung36_jcon_lists/icn_pv_main_i J
    lload 181
    putstatic rung36_jcon_lists/icn_155_lsa_i J
    lload 183
    putstatic rung36_jcon_lists/icn_155_lsa_v J
    lload 185
    putstatic rung36_jcon_lists/icn_158_I J
    lload 187
    putstatic rung36_jcon_lists/icn_158_bound J
    lload 189
    putstatic rung36_jcon_lists/icn_158_e1cur J
    lload 191
    putstatic rung36_jcon_lists/icn_158_e1val J
    lload 193
    putstatic rung36_jcon_lists/icn_158_e2val J
    lload 195
    putstatic rung36_jcon_lists/icn_160_binop_lc J
    lload 197
    putstatic rung36_jcon_lists/icn_160_binop_rc J
    lload 199
    putstatic rung36_jcon_lists/icn_171_lsa_i J
    lload 201
    putstatic rung36_jcon_lists/icn_171_lsa_v J
    lload 203
    putstatic rung36_jcon_lists/icn_174_I J
    lload 205
    putstatic rung36_jcon_lists/icn_174_bound J
    lload 207
    putstatic rung36_jcon_lists/icn_174_e1cur J
    lload 209
    putstatic rung36_jcon_lists/icn_174_e1val J
    lload 211
    putstatic rung36_jcon_lists/icn_174_e2val J
    lload 213
    putstatic rung36_jcon_lists/icn_175_binop_lc J
    lload 215
    putstatic rung36_jcon_lists/icn_175_binop_rc J
    lload 217
    putstatic rung36_jcon_lists/icn_310_ln J
    lload 219
    putstatic rung36_jcon_lists/icn_315_ln J
    lload 221
    putstatic rung36_jcon_lists/icn_320_ln J
    getstatic rung36_jcon_lists/icn_failed B
    ifne icn_319_after_call
    getstatic rung36_jcon_lists/icn_retval J
    goto icn_main_s5_sdrain
icn_319_after_call:
    goto icn_314_α
icn_main_s5_sdrain:
    pop2
    goto icn_314_α
icn_325_α:
    goto icn_319_α
icn_325_β:
    goto icn_319_α
icn_324_arg1:
    putstatic rung36_jcon_lists/icn_arg_1 J
    goto icn_324_docall
;  STR
icn_326_α:
    ldc "b"
    goto icn_324_arg0
icn_326_β:
    goto icn_319_α
icn_324_arg0:
    putstatic rung36_jcon_lists/icn_arg_str_0 Ljava/lang/String;
    lconst_0
    putstatic rung36_jcon_lists/icn_arg_0 J
    goto icn_325_α
icn_324_α:
    goto icn_326_α
icn_324_β:
    goto icn_325_β
icn_324_docall:
    getstatic rung36_jcon_lists/icn_pv_main_y J
    lstore 161
    getstatic rung36_jcon_lists/icn_41_alt_val J
    lstore 163
    getstatic rung36_jcon_lists/icn_50_alt_val J
    lstore 165
    getstatic rung36_jcon_lists/icn_102_alt_val J
    lstore 167
    getstatic rung36_jcon_lists/icn_107_alt_val J
    lstore 169
    getstatic rung36_jcon_lists/icn_112_alt_val J
    lstore 171
    getstatic rung36_jcon_lists/icn_119_alt_val J
    lstore 173
    getstatic rung36_jcon_lists/icn_126_alt_val J
    lstore 175
    getstatic rung36_jcon_lists/icn_132_alt_val J
    lstore 177
    getstatic rung36_jcon_lists/icn_pv_main_i J
    lstore 179
    getstatic rung36_jcon_lists/icn_155_lsa_i J
    lstore 181
    getstatic rung36_jcon_lists/icn_155_lsa_v J
    lstore 183
    getstatic rung36_jcon_lists/icn_158_I J
    lstore 185
    getstatic rung36_jcon_lists/icn_158_bound J
    lstore 187
    getstatic rung36_jcon_lists/icn_158_e1cur J
    lstore 189
    getstatic rung36_jcon_lists/icn_158_e1val J
    lstore 191
    getstatic rung36_jcon_lists/icn_158_e2val J
    lstore 193
    getstatic rung36_jcon_lists/icn_160_binop_lc J
    lstore 195
    getstatic rung36_jcon_lists/icn_160_binop_rc J
    lstore 197
    getstatic rung36_jcon_lists/icn_171_lsa_i J
    lstore 199
    getstatic rung36_jcon_lists/icn_171_lsa_v J
    lstore 201
    getstatic rung36_jcon_lists/icn_174_I J
    lstore 203
    getstatic rung36_jcon_lists/icn_174_bound J
    lstore 205
    getstatic rung36_jcon_lists/icn_174_e1cur J
    lstore 207
    getstatic rung36_jcon_lists/icn_174_e1val J
    lstore 209
    getstatic rung36_jcon_lists/icn_174_e2val J
    lstore 211
    getstatic rung36_jcon_lists/icn_175_binop_lc J
    lstore 213
    getstatic rung36_jcon_lists/icn_175_binop_rc J
    lstore 215
    getstatic rung36_jcon_lists/icn_310_ln J
    lstore 217
    getstatic rung36_jcon_lists/icn_315_ln J
    lstore 219
    getstatic rung36_jcon_lists/icn_320_ln J
    lstore 221
    invokestatic rung36_jcon_lists/icn_limage()V
    lload 161
    putstatic rung36_jcon_lists/icn_pv_main_y J
    lload 163
    putstatic rung36_jcon_lists/icn_41_alt_val J
    lload 165
    putstatic rung36_jcon_lists/icn_50_alt_val J
    lload 167
    putstatic rung36_jcon_lists/icn_102_alt_val J
    lload 169
    putstatic rung36_jcon_lists/icn_107_alt_val J
    lload 171
    putstatic rung36_jcon_lists/icn_112_alt_val J
    lload 173
    putstatic rung36_jcon_lists/icn_119_alt_val J
    lload 175
    putstatic rung36_jcon_lists/icn_126_alt_val J
    lload 177
    putstatic rung36_jcon_lists/icn_132_alt_val J
    lload 179
    putstatic rung36_jcon_lists/icn_pv_main_i J
    lload 181
    putstatic rung36_jcon_lists/icn_155_lsa_i J
    lload 183
    putstatic rung36_jcon_lists/icn_155_lsa_v J
    lload 185
    putstatic rung36_jcon_lists/icn_158_I J
    lload 187
    putstatic rung36_jcon_lists/icn_158_bound J
    lload 189
    putstatic rung36_jcon_lists/icn_158_e1cur J
    lload 191
    putstatic rung36_jcon_lists/icn_158_e1val J
    lload 193
    putstatic rung36_jcon_lists/icn_158_e2val J
    lload 195
    putstatic rung36_jcon_lists/icn_160_binop_lc J
    lload 197
    putstatic rung36_jcon_lists/icn_160_binop_rc J
    lload 199
    putstatic rung36_jcon_lists/icn_171_lsa_i J
    lload 201
    putstatic rung36_jcon_lists/icn_171_lsa_v J
    lload 203
    putstatic rung36_jcon_lists/icn_174_I J
    lload 205
    putstatic rung36_jcon_lists/icn_174_bound J
    lload 207
    putstatic rung36_jcon_lists/icn_174_e1cur J
    lload 209
    putstatic rung36_jcon_lists/icn_174_e1val J
    lload 211
    putstatic rung36_jcon_lists/icn_174_e2val J
    lload 213
    putstatic rung36_jcon_lists/icn_175_binop_lc J
    lload 215
    putstatic rung36_jcon_lists/icn_175_binop_rc J
    lload 217
    putstatic rung36_jcon_lists/icn_310_ln J
    lload 219
    putstatic rung36_jcon_lists/icn_315_ln J
    lload 221
    putstatic rung36_jcon_lists/icn_320_ln J
    getstatic rung36_jcon_lists/icn_failed B
    ifne icn_324_after_call
    getstatic rung36_jcon_lists/icn_retval J
    goto icn_main_s4_sdrain
icn_324_after_call:
    goto icn_319_α
icn_main_s4_sdrain:
    pop2
    goto icn_319_α
icn_328_α:
    goto icn_324_α
icn_328_β:
    goto icn_324_α
icn_327_arg1:
    putstatic rung36_jcon_lists/icn_arg_1 J
    goto icn_327_docall
;  STR
icn_329_α:
    ldc "a"
    goto icn_327_arg0
icn_329_β:
    goto icn_324_α
icn_327_arg0:
    putstatic rung36_jcon_lists/icn_arg_str_0 Ljava/lang/String;
    lconst_0
    putstatic rung36_jcon_lists/icn_arg_0 J
    goto icn_328_α
icn_327_α:
    goto icn_329_α
icn_327_β:
    goto icn_328_β
icn_327_docall:
    getstatic rung36_jcon_lists/icn_pv_main_y J
    lstore 161
    getstatic rung36_jcon_lists/icn_41_alt_val J
    lstore 163
    getstatic rung36_jcon_lists/icn_50_alt_val J
    lstore 165
    getstatic rung36_jcon_lists/icn_102_alt_val J
    lstore 167
    getstatic rung36_jcon_lists/icn_107_alt_val J
    lstore 169
    getstatic rung36_jcon_lists/icn_112_alt_val J
    lstore 171
    getstatic rung36_jcon_lists/icn_119_alt_val J
    lstore 173
    getstatic rung36_jcon_lists/icn_126_alt_val J
    lstore 175
    getstatic rung36_jcon_lists/icn_132_alt_val J
    lstore 177
    getstatic rung36_jcon_lists/icn_pv_main_i J
    lstore 179
    getstatic rung36_jcon_lists/icn_155_lsa_i J
    lstore 181
    getstatic rung36_jcon_lists/icn_155_lsa_v J
    lstore 183
    getstatic rung36_jcon_lists/icn_158_I J
    lstore 185
    getstatic rung36_jcon_lists/icn_158_bound J
    lstore 187
    getstatic rung36_jcon_lists/icn_158_e1cur J
    lstore 189
    getstatic rung36_jcon_lists/icn_158_e1val J
    lstore 191
    getstatic rung36_jcon_lists/icn_158_e2val J
    lstore 193
    getstatic rung36_jcon_lists/icn_160_binop_lc J
    lstore 195
    getstatic rung36_jcon_lists/icn_160_binop_rc J
    lstore 197
    getstatic rung36_jcon_lists/icn_171_lsa_i J
    lstore 199
    getstatic rung36_jcon_lists/icn_171_lsa_v J
    lstore 201
    getstatic rung36_jcon_lists/icn_174_I J
    lstore 203
    getstatic rung36_jcon_lists/icn_174_bound J
    lstore 205
    getstatic rung36_jcon_lists/icn_174_e1cur J
    lstore 207
    getstatic rung36_jcon_lists/icn_174_e1val J
    lstore 209
    getstatic rung36_jcon_lists/icn_174_e2val J
    lstore 211
    getstatic rung36_jcon_lists/icn_175_binop_lc J
    lstore 213
    getstatic rung36_jcon_lists/icn_175_binop_rc J
    lstore 215
    getstatic rung36_jcon_lists/icn_310_ln J
    lstore 217
    getstatic rung36_jcon_lists/icn_315_ln J
    lstore 219
    getstatic rung36_jcon_lists/icn_320_ln J
    lstore 221
    invokestatic rung36_jcon_lists/icn_limage()V
    lload 161
    putstatic rung36_jcon_lists/icn_pv_main_y J
    lload 163
    putstatic rung36_jcon_lists/icn_41_alt_val J
    lload 165
    putstatic rung36_jcon_lists/icn_50_alt_val J
    lload 167
    putstatic rung36_jcon_lists/icn_102_alt_val J
    lload 169
    putstatic rung36_jcon_lists/icn_107_alt_val J
    lload 171
    putstatic rung36_jcon_lists/icn_112_alt_val J
    lload 173
    putstatic rung36_jcon_lists/icn_119_alt_val J
    lload 175
    putstatic rung36_jcon_lists/icn_126_alt_val J
    lload 177
    putstatic rung36_jcon_lists/icn_132_alt_val J
    lload 179
    putstatic rung36_jcon_lists/icn_pv_main_i J
    lload 181
    putstatic rung36_jcon_lists/icn_155_lsa_i J
    lload 183
    putstatic rung36_jcon_lists/icn_155_lsa_v J
    lload 185
    putstatic rung36_jcon_lists/icn_158_I J
    lload 187
    putstatic rung36_jcon_lists/icn_158_bound J
    lload 189
    putstatic rung36_jcon_lists/icn_158_e1cur J
    lload 191
    putstatic rung36_jcon_lists/icn_158_e1val J
    lload 193
    putstatic rung36_jcon_lists/icn_158_e2val J
    lload 195
    putstatic rung36_jcon_lists/icn_160_binop_lc J
    lload 197
    putstatic rung36_jcon_lists/icn_160_binop_rc J
    lload 199
    putstatic rung36_jcon_lists/icn_171_lsa_i J
    lload 201
    putstatic rung36_jcon_lists/icn_171_lsa_v J
    lload 203
    putstatic rung36_jcon_lists/icn_174_I J
    lload 205
    putstatic rung36_jcon_lists/icn_174_bound J
    lload 207
    putstatic rung36_jcon_lists/icn_174_e1cur J
    lload 209
    putstatic rung36_jcon_lists/icn_174_e1val J
    lload 211
    putstatic rung36_jcon_lists/icn_174_e2val J
    lload 213
    putstatic rung36_jcon_lists/icn_175_binop_lc J
    lload 215
    putstatic rung36_jcon_lists/icn_175_binop_rc J
    lload 217
    putstatic rung36_jcon_lists/icn_310_ln J
    lload 219
    putstatic rung36_jcon_lists/icn_315_ln J
    lload 221
    putstatic rung36_jcon_lists/icn_320_ln J
    getstatic rung36_jcon_lists/icn_failed B
    ifne icn_327_after_call
    getstatic rung36_jcon_lists/icn_retval J
    goto icn_main_s3_sdrain
icn_327_after_call:
    goto icn_324_α
icn_main_s3_sdrain:
    pop2
    goto icn_324_α
icn_331_α:
    goto icn_327_α
icn_331_β:
    goto icn_327_α
icn_330_α:
    goto icn_331_α
icn_330_β:
    goto icn_331_β
    goto icn_330_wentry
icn_330_waft_0:
    lstore 22
    getstatic java/lang/System/out Ljava/io/PrintStream;
    lload 22
    invokevirtual java/io/PrintStream/print(J)V
    getstatic java/lang/System/out Ljava/io/PrintStream;
    ldc ""
    invokevirtual java/io/PrintStream/println(Ljava/lang/String;)V
    lload 22
    goto icn_main_s2_sdrain
icn_330_wentry:
    goto icn_331_α
icn_main_s2_sdrain:
    pop2
    goto icn_327_α
icn_333_α:
    goto icn_330_α
icn_333_β:
    goto icn_330_α
icn_332_α:
    goto icn_333_α
icn_332_β:
    goto icn_333_β
    goto icn_332_wentry
icn_332_waft_0:
    lstore 24
    getstatic java/lang/System/out Ljava/io/PrintStream;
    lload 24
    invokevirtual java/io/PrintStream/print(J)V
    getstatic java/lang/System/out Ljava/io/PrintStream;
    ldc ""
    invokevirtual java/io/PrintStream/println(Ljava/lang/String;)V
    lload 24
    goto icn_main_s1_sdrain
icn_332_wentry:
    goto icn_333_α
icn_main_s1_sdrain:
    pop2
    goto icn_330_α
icn_main_done:
    return
.end method

.method public static icn_limage()V
    .limit stack 16
    .limit locals 486
    lconst_0
    lstore 0
    lconst_0
    lstore 2
    lconst_0
    lstore 4
    lconst_0
    lstore 6
    lconst_0
    lstore 8
    lconst_0
    lstore 10
    lconst_0
    lstore 12
    lconst_0
    lstore 14
    lconst_0
    lstore 16
    lconst_0
    lstore 18
    lconst_0
    lstore 20
    lconst_0
    lstore 22
    lconst_0
    lstore 24
    lconst_0
    lstore 26
    lconst_0
    lstore 28
    lconst_0
    lstore 30
    lconst_0
    lstore 32
    lconst_0
    lstore 34
    lconst_0
    lstore 36
    lconst_0
    lstore 38
    lconst_0
    lstore 40
    lconst_0
    lstore 42
    lconst_0
    lstore 44
    lconst_0
    lstore 46
    lconst_0
    lstore 48
    lconst_0
    lstore 50
    lconst_0
    lstore 52
    lconst_0
    lstore 54
    lconst_0
    lstore 56
    lconst_0
    lstore 58
    lconst_0
    lstore 60
    lconst_0
    lstore 62
    iconst_0
    istore 84
    iconst_0
    istore 85
    iconst_0
    istore 86
    iconst_0
    istore 87
    aconst_null
    astore 148
    aconst_null
    astore 149
    aconst_null
    astore 150
    aconst_null
    astore 151
    getstatic rung36_jcon_lists/icn_arg_str_0 Ljava/lang/String;
    putstatic rung36_jcon_lists/icn_pv_limage_label Ljava/lang/String;
    getstatic rung36_jcon_lists/icn_arg_str_1 Ljava/lang/String;
    putstatic rung36_jcon_lists/icn_pv_limage_lst Ljava/lang/String;
    goto icn_338_α
icn_334_α:
    lconst_0
    putstatic rung36_jcon_lists/icn_retval J
    iconst_0
    putstatic rung36_jcon_lists/icn_failed B
    goto icn_limage_ret
icn_334_β:
    goto icn_limage_ret
icn_335_α:
    getstatic java/lang/System/out Ljava/io/PrintStream;
    ldc ""
    invokevirtual java/io/PrintStream/println(Ljava/lang/String;)V
    goto icn_limage_s2_sdrain
icn_335_β:
    goto icn_334_α
icn_limage_s2_sdrain:
    pop2
    goto icn_334_α
icn_337_α:
    goto icn_335_α
icn_337_β:
    goto icn_335_α
icn_336_gdrain:
    pop2
icn_336_pump:
    goto icn_337_β
icn_336_α:
    goto icn_337_α
icn_336_β:
    goto icn_335_α
icn_338_α:
    goto icn_336_α
icn_338_β:
    goto icn_336_α
icn_limage_s0_sdrain:
    pop2
    goto icn_336_α
icn_limage_done:
    iconst_0
    putstatic rung36_jcon_lists/icn_suspended B
    iconst_0
    putstatic rung36_jcon_lists/icn_suspend_id I
    iconst_1
    putstatic rung36_jcon_lists/icn_failed B
    return
icn_limage_ret:
    iconst_0
    putstatic rung36_jcon_lists/icn_failed B
    return
icn_limage_sret:
    return
.end method

