; Auto-generated by icon_emit_jvm.c — Tiny-ICON Byrd Box JVM
.bytecode 45.0
.class public rung36_jcon_mindfa
.super java/lang/Object

.field public static icn_failed B
.field public static icn_suspended B
.field public static icn_suspend_id I
.field public static icn_retval_obj Ljava/lang/Object;
.field public static icn_retval J
.field public static icn_retval_str Ljava/lang/String;
.field public static icn_arg_str_0 Ljava/lang/String;
.field public static icn_pv_showdfa_msg Ljava/lang/String;
.field public static icn_pv_readset_s Ljava/lang/String;
.field public static icn_pv_writeset_msg Ljava/lang/String;
.field public static icn_pv_marklists_l Ljava/lang/String;
.field public static icn_gvar_q0 Ljava/lang/String;
.field public static icn_pv_getdfa_q0 Ljava/lang/String;
.field public static icn_gvar_d Ljava/util/HashMap;
.field public static icn_gvar_q Ljava/lang/String;
.field public static icn_pv_getdfa_q Ljava/lang/String;
.field public static icn_gvar_t1 Ljava/util/ArrayList;
.field public static icn_pv_showdfa_q Ljava/lang/String;
.field public static icn_gvar_a Ljava/lang/String;
.field public static icn_pv_showdfa_a Ljava/lang/String;
.field public static icn_gvar_tmp Ljava/lang/String;
.field public static icn_pv_writeset_tmp Ljava/lang/String;
.field public static icn_gvar_distab Ljava/util/HashMap;
.field public static icn_gvar_dlists Ljava/util/HashMap;
.field public static icn_gvar_p Ljava/lang/String;
.field public static icn_pv_minimize_p Ljava/lang/String;
.field public static icn_pv_minimize_a Ljava/lang/String;
.field public static icn_gvar_e Ljava/lang/String;
.field public static icn_pv_marklists_e Ljava/lang/String;
.field public static icn_gvar_qset Ljava/lang/String;
.field public static icn_pv_makemdfa_qset Ljava/lang/String;
.field public static icn_gvar_etab Ljava/util/HashMap;
.field public static icn_pv_makemdfa_p Ljava/lang/String;
.field public static icn_gvar_tlist Ljava/util/ArrayList;
.field public static icn_gvar_elist Ljava/util/ArrayList;
.field public static icn_gvar_Delta Ljava/util/HashMap;
.field public static icn_gvar_echeck Ljava/util/HashMap;
.field public static icn_pv_makemdfa_a Ljava/lang/String;
.field public static icn_pv_equiv_p Ljava/lang/String;
.field public static icn_pv_equivdelta_q Ljava/lang/String;
.field public static icn_gvar_r Ljava/lang/String;
.field public static icn_pv_equivdelta_r Ljava/lang/String;
.field public static icn_gvar_ftab Ljava/util/HashMap;
.field public static icn_pv_finalstates_p Ljava/lang/String;
.field public static icn_gvar_flist Ljava/util/ArrayList;
.field public static icn_pv_diff_t1 Ljava/lang/String;
.field public static icn_gvar_t2 Ljava/lang/String;
.field public static icn_pv_diff_t2 Ljava/lang/String;
.field public static icn_gvar_l Ljava/util/ArrayList;
.field public static icn_pv_main_x J
.field public static icn_arg_1 J
.field public static icn_arg_0 J
.field public static icn_7_I J
.field public static icn_7_bound J
.field public static icn_7_e1cur J
.field public static icn_7_e2seen I
.field public static icn_7_e1val J
.field public static icn_7_e2val J
.field public static icn_pv_getdfa_d Ljava/util/HashMap;
.field public static icn_pv_getdfa_d_dflt Ljava/lang/Object;
.field public static icn_13_rc_a0 Ljava/lang/Object;
.field public static icn_13_rc_a1 Ljava/lang/Object;
.field public static icn_13_rc_a2 Ljava/lang/Object;
.field public static icn_13_rc_a3 Ljava/lang/Object;
.field public static icn_13_rc_a4 Ljava/lang/Object;
.field public static icn_13_rc_obj Ljava/lang/Object;
.field public static icn_pv_getdfa_Q J
.field public static icn_pv_getdfa_S J
.field public static icn_pv_getdfa_F J
.field public static icn_22_tsa_vl Ljava/lang/String;
.field public static icn_22_tsa_vo Ljava/lang/Object;
.field public static icn_22_tsa_ks Ljava/lang/String;
.field public static icn_stdin_reader Ljava/lang/Object;
.field public static icn_stdin_init I
.field public static icn_24_lc Ljava/lang/String;
.field public static icn_24_rc Ljava/lang/String;
.field public static icn_26_lc Ljava/lang/String;
.field public static icn_26_rc Ljava/lang/String;
.field public static icn_31_bang_str Ljava/lang/String;
.field public static icn_31_bang_pos I
.field public static icn_pv_readset_t1 Ljava/util/ArrayList;
.field public static icn_50_pushval Ljava/lang/Object;
.field public static icn_50_pushlist Ljava/util/ArrayList;
.field public static icn_52_bang_str Ljava/lang/String;
.field public static icn_52_bang_pos I
.field public static icn_55_mklist Ljava/util/ArrayList;
.field public static icn_pv_showdfa_D J
.field public static icn_65_bang_str Ljava/lang/String;
.field public static icn_65_bang_pos I
.field public static icn_93_I J
.field public static icn_93_bound J
.field public static icn_93_e1cur J
.field public static icn_93_e2seen I
.field public static icn_93_e1val J
.field public static icn_93_e2val J
.field public static icn_101_sec_s Ljava/lang/String;
.field public static icn_101_sec_lo I
.field public static icn_101_sec_hi I
.field public static icn_109_lc Ljava/lang/String;
.field public static icn_109_rc Ljava/lang/String;
.field public static icn_111_bang_str Ljava/lang/String;
.field public static icn_111_bang_pos I
.field public static icn_pv_writeset_s J
.field public static icn_108_augtemp_s Ljava/lang/String;
.field public static icn_pv_minimize_distab Ljava/util/HashMap;
.field public static icn_pv_minimize_distab_dflt Ljava/lang/Object;
.field public static icn_pv_minimize_dlists Ljava/util/HashMap;
.field public static icn_pv_minimize_dlists_dflt Ljava/lang/Object;
.field public static icn_pv_minimize_D Ljava/lang/String;
.field public static icn_122_tsa_vl Ljava/lang/String;
.field public static icn_122_tsa_vo Ljava/lang/Object;
.field public static icn_122_tsa_ks Ljava/lang/String;
.field public static icn_126_ts_tbl Ljava/util/HashMap;
.field public static icn_126_ts_key Ljava/lang/String;
.field public static icn_126_ts_kval J
.field public static icn_pv_minimize_cs J
.field public static icn_140_mklist Ljava/util/ArrayList;
.field public static icn_141_pushval Ljava/lang/Object;
.field public static icn_141_pushlist Ljava/util/ArrayList;
.field public static icn_142_ts_tbl Ljava/util/HashMap;
.field public static icn_142_ts_key Ljava/lang/String;
.field public static icn_142_ts_kval J
.field public static icn_147_sub_s Ljava/lang/String;
.field public static icn_147_sub_i I
.field public static icn_148_lc Ljava/lang/String;
.field public static icn_148_rc Ljava/lang/String;
.field public static icn_150_lc Ljava/lang/String;
.field public static icn_150_rc Ljava/lang/String;
.field public static icn_154_sub_s Ljava/lang/String;
.field public static icn_154_sub_i I
.field public static icn_155_lc Ljava/lang/String;
.field public static icn_155_rc Ljava/lang/String;
.field public static icn_157_lc Ljava/lang/String;
.field public static icn_157_rc Ljava/lang/String;
.field public static icn_162_bang_str Ljava/lang/String;
.field public static icn_162_bang_pos I
.field public static icn_165_ts_tbl Ljava/util/HashMap;
.field public static icn_165_ts_key Ljava/lang/String;
.field public static icn_165_ts_kval J
.field public static icn_169_alt_gate I
.field public static icn_172_bang_str Ljava/lang/String;
.field public static icn_172_bang_pos I
.field public static icn_pv_minimize_QF J
.field public static icn_176_bang_str Ljava/lang/String;
.field public static icn_176_bang_pos I
.field public static icn_pv_minimize_F J
.field public static icn_168_and_drain_0 Ljava/lang/String;
.field public static icn_182_tsa_vl Ljava/lang/String;
.field public static icn_182_tsa_vo Ljava/lang/Object;
.field public static icn_182_tsa_ks Ljava/lang/String;
.field public static icn_187_bang_str Ljava/lang/String;
.field public static icn_187_bang_pos I
.field public static icn_202_tsa_vl Ljava/lang/String;
.field public static icn_202_tsa_vo Ljava/lang/Object;
.field public static icn_202_tsa_ks Ljava/lang/String;
.field public static icn_206_ts_tbl Ljava/util/HashMap;
.field public static icn_206_ts_key Ljava/lang/String;
.field public static icn_206_ts_kval J
.field public static icn_210_bang_list Ljava/util/ArrayList;
.field public static icn_210_bang_idx I
.field public static icn_pv_makemdfa_etab Ljava/util/HashMap;
.field public static icn_pv_makemdfa_etab_dflt Ljava/lang/Object;
.field public static icn_pv_makemdfa_tlist Ljava/util/ArrayList;
.field public static icn_pv_makemdfa_elist Ljava/util/ArrayList;
.field public static icn_pv_makemdfa_Delta Ljava/util/HashMap;
.field public static icn_pv_makemdfa_Delta_dflt Ljava/lang/Object;
.field public static icn_pv_makemdfa_echeck Ljava/util/HashMap;
.field public static icn_pv_makemdfa_echeck_dflt Ljava/lang/Object;
.field public static icn_217_rc_a0 Ljava/lang/Object;
.field public static icn_217_rc_a1 Ljava/lang/Object;
.field public static icn_217_rc_a2 Ljava/lang/Object;
.field public static icn_217_rc_a3 Ljava/lang/Object;
.field public static icn_217_rc_a4 Ljava/lang/Object;
.field public static icn_217_rc_obj Ljava/lang/Object;
.field public static icn_pv_makemdfa_q0 J
.field public static icn_pv_makemdfa_D Ljava/lang/String;
.field public static icn_227_glist Ljava/util/ArrayList;
.field public static icn_pv_makemdfa_q J
.field public static icn_231_tsa_vl J
.field public static icn_231_tsa_vo Ljava/lang/Object;
.field public static icn_231_tsa_ks Ljava/lang/String;
.field public static icn_arg_3 J
.field public static icn_arg_2 J
.field public static icn_arg_str_1 Ljava/lang/String;
.field public static icn_237_lc Ljava/lang/String;
.field public static icn_237_rc Ljava/lang/String;
.field public static icn_239_lc Ljava/lang/String;
.field public static icn_239_rc Ljava/lang/String;
.field public static icn_244_tsa_vl J
.field public static icn_244_tsa_vo Ljava/lang/Object;
.field public static icn_244_tsa_ks Ljava/lang/String;
.field public static icn_245_ts_tbl Ljava/util/HashMap;
.field public static icn_245_ts_key Ljava/lang/String;
.field public static icn_245_ts_kval J
.field public static icn_247_lc Ljava/lang/String;
.field public static icn_247_rc Ljava/lang/String;
.field public static icn_249_lc Ljava/lang/String;
.field public static icn_249_rc Ljava/lang/String;
.field public static icn_252_ts_tbl Ljava/util/HashMap;
.field public static icn_252_ts_key Ljava/lang/String;
.field public static icn_252_ts_kval J
.field public static icn_254_lc Ljava/lang/String;
.field public static icn_254_rc Ljava/lang/String;
.field public static icn_256_lc Ljava/lang/String;
.field public static icn_256_rc Ljava/lang/String;
.field public static icn_259_pushval Ljava/lang/Object;
.field public static icn_259_pushlist Ljava/util/ArrayList;
.field public static icn_261_ts_tbl Ljava/util/HashMap;
.field public static icn_261_ts_key Ljava/lang/String;
.field public static icn_261_ts_kval J
.field public static icn_263_lc Ljava/lang/String;
.field public static icn_263_rc Ljava/lang/String;
.field public static icn_265_lc Ljava/lang/String;
.field public static icn_265_rc Ljava/lang/String;
.field public static icn_268_pushval Ljava/lang/Object;
.field public static icn_268_pushlist Ljava/util/ArrayList;
.field public static icn_270_ts_tbl Ljava/util/HashMap;
.field public static icn_270_ts_key Ljava/lang/String;
.field public static icn_270_ts_kval J
.field public static icn_272_lc Ljava/lang/String;
.field public static icn_272_rc Ljava/lang/String;
.field public static icn_274_lc Ljava/lang/String;
.field public static icn_274_rc Ljava/lang/String;
.field public static icn_278_ts_tbl Ljava/util/HashMap;
.field public static icn_278_ts_key Ljava/lang/String;
.field public static icn_278_ts_kval J
.field public static icn_280_ts_tbl Ljava/util/HashMap;
.field public static icn_280_ts_key Ljava/lang/String;
.field public static icn_280_ts_kval J
.field public static icn_282_lc Ljava/lang/String;
.field public static icn_282_rc Ljava/lang/String;
.field public static icn_284_lc Ljava/lang/String;
.field public static icn_284_rc Ljava/lang/String;
.field public static icn_288_bang_str Ljava/lang/String;
.field public static icn_288_bang_pos I
.field public static icn_290_tsa_vl Ljava/lang/String;
.field public static icn_290_tsa_vo Ljava/lang/Object;
.field public static icn_290_tsa_ks Ljava/lang/String;
.field public static icn_295_pushval Ljava/lang/Object;
.field public static icn_295_pushlist Ljava/util/ArrayList;
.field public static icn_298_pushval Ljava/lang/Object;
.field public static icn_298_pushlist Ljava/util/ArrayList;
.field public static icn_308_mklist Ljava/util/ArrayList;
.field public static icn_310_mklist Ljava/util/ArrayList;
.field public static icn_313_augtemp J
.field public static icn_316_alt_gate I
.field public static icn_316_alt_val J
.field public static icn_pv_makemdfa_plike J
.field public static icn_324_alt_gate I
.field public static icn_324_alt_val J
.field public static icn_323_augtemp J
.field public static icn_330_ts_tbl Ljava/util/HashMap;
.field public static icn_330_ts_key Ljava/lang/String;
.field public static icn_330_ts_kval J
.field public static icn_335_bang_str Ljava/lang/String;
.field public static icn_335_bang_pos I
.field public static icn_334_and_drain_0 Ljava/lang/String;
.field public static icn_342_tsa_vl J
.field public static icn_342_tsa_vo Ljava/lang/Object;
.field public static icn_342_tsa_ks Ljava/lang/String;
.field public static icn_346_bang_str Ljava/lang/String;
.field public static icn_346_bang_pos I
.field public static icn_pv_makemdfa_DT Ljava/lang/String;
.field public static icn_cbo357_lcs Ljava/lang/String;
.field public static icn_cbo357_rcs Ljava/lang/String;
.field public static icn_pv_equiv_q Ljava/lang/String;
.field public static icn_362_bang_str Ljava/lang/String;
.field public static icn_362_bang_pos I
.field public static icn_pv_equiv_el Ljava/lang/String;
.field public static icn_pv_equivdelta_el J
.field public static icn_369_sub_s Ljava/lang/String;
.field public static icn_369_sub_i I
.field public static icn_370_lc Ljava/lang/String;
.field public static icn_370_rc Ljava/lang/String;
.field public static icn_pv_equivdelta_a Ljava/lang/String;
.field public static icn_372_lc Ljava/lang/String;
.field public static icn_372_rc Ljava/lang/String;
.field public static icn_377_bang_str Ljava/lang/String;
.field public static icn_377_bang_pos I
.field public static icn_pv_equivdelta_p Ljava/lang/String;
.field public static icn_pv_equivdelta_D J
.field public static icn_pv_finalstates_ftab Ljava/util/HashMap;
.field public static icn_pv_finalstates_ftab_dflt Ljava/lang/Object;
.field public static icn_pv_finalstates_flist Ljava/util/ArrayList;
.field public static icn_382_pushval Ljava/lang/Object;
.field public static icn_382_pushlist Ljava/util/ArrayList;
.field public static icn_384_sub_s Ljava/lang/String;
.field public static icn_384_sub_i I
.field public static icn_386_bang_list Ljava/util/ArrayList;
.field public static icn_386_bang_idx I
.field public static icn_387_sort_list Ljava/util/ArrayList;
.field public static icn_390_mklist Ljava/util/ArrayList;
.field public static icn_392_tsa_vl Ljava/lang/String;
.field public static icn_392_tsa_vo Ljava/lang/Object;
.field public static icn_392_tsa_ks Ljava/lang/String;
.field public static icn_pv_finalstates_q J
.field public static icn_pv_finalstates_el Ljava/lang/String;
.field public static icn_399_bang_str Ljava/lang/String;
.field public static icn_399_bang_pos I
.field public static icn_pv_finalstates_D Ljava/lang/String;
.field public static icn_pv_diff_l Ljava/util/ArrayList;
.field public static icn_407_relop_lc J
.field public static icn_407_relop_rc J
.field public static icn_412_pushval Ljava/lang/Object;
.field public static icn_412_pushlist Ljava/util/ArrayList;
.field public static icn_414_bang_str Ljava/lang/String;
.field public static icn_414_bang_pos I
.field public static icn_cbo415_lcs Ljava/lang/String;
.field public static icn_cbo415_rcs Ljava/lang/String;
.field public static icn_419_mklist Ljava/util/ArrayList;
.field public static icn_422_bang_str Ljava/lang/String;
.field public static icn_422_bang_pos I
.field public static icn_pv_diff_l2 Ljava/lang/String;
.field public static icn_421_augtemp J
.field public static icn_428_bang_str Ljava/lang/String;
.field public static icn_428_bang_pos I
.field public static icn_pv_diff_l1 Ljava/lang/String;
.field public static icn_427_augtemp J

.method public static main([Ljava/lang/String;)V
    .limit stack 4
    .limit locals 1
    invokestatic rung36_jcon_mindfa/icn_main()V
    return
.end method

.method public static icn_builtin_left(Ljava/lang/String;ILjava/lang/String;)Ljava/lang/String;
    .limit stack 4
    .limit locals 5
    aload_0
    invokevirtual java/lang/String/length()I
    iload_1
    if_icmplt icn_left_pad
    aload_0
    iconst_0
    iload_1
    invokevirtual java/lang/String/substring(II)Ljava/lang/String;
    areturn
icn_left_pad:
    new java/lang/StringBuilder
    dup
    aload_0
    invokespecial java/lang/StringBuilder/<init>(Ljava/lang/String;)V
    astore_3
icn_left_loop:
    aload_3
    invokevirtual java/lang/StringBuilder/length()I
    iload_1
    if_icmpge icn_left_done
    aload_3
    aload_2
    iconst_0
    invokevirtual java/lang/String/charAt(I)C
    invokevirtual java/lang/StringBuilder/append(C)Ljava/lang/StringBuilder;
    pop
    goto icn_left_loop
icn_left_done:
    aload_3
    invokevirtual java/lang/StringBuilder/toString()Ljava/lang/String;
    areturn
.end method

.method public static icn_builtin_right(Ljava/lang/String;ILjava/lang/String;)Ljava/lang/String;
    .limit stack 4
    .limit locals 5
    aload_0
    invokevirtual java/lang/String/length()I
    iload_1
    if_icmplt icn_right_pad
    aload_0
    invokevirtual java/lang/String/length()I
    iload_1
    isub
    aload_0
    swap
    invokevirtual java/lang/String/substring(I)Ljava/lang/String;
    areturn
icn_right_pad:
    new java/lang/StringBuilder
    dup
    invokespecial java/lang/StringBuilder/<init>()V
    astore_3
    iload_1
    aload_0
    invokevirtual java/lang/String/length()I
    isub
    istore 4
    iconst_0
icn_right_loop:
    dup
    iload 4
    if_icmpge icn_right_append
    aload_3
    aload_2
    iconst_0
    invokevirtual java/lang/String/charAt(I)C
    invokevirtual java/lang/StringBuilder/append(C)Ljava/lang/StringBuilder;
    pop
    iconst_1
    iadd
    goto icn_right_loop
icn_right_append:
    pop
    aload_3
    aload_0
    invokevirtual java/lang/StringBuilder/append(Ljava/lang/String;)Ljava/lang/StringBuilder;
    pop
    aload_3
    invokevirtual java/lang/StringBuilder/toString()Ljava/lang/String;
    areturn
.end method

.method public static icn_builtin_center(Ljava/lang/String;ILjava/lang/String;)Ljava/lang/String;
    .limit stack 5
    .limit locals 7
    aload_0
    invokevirtual java/lang/String/length()I
    iload_1
    if_icmplt icn_ctr_pad
    aload_0
    iconst_0
    iload_1
    invokevirtual java/lang/String/substring(II)Ljava/lang/String;
    areturn
icn_ctr_pad:
    iload_1
    aload_0
    invokevirtual java/lang/String/length()I
    isub
    istore_3
    iload_3
    iconst_2
    idiv
    istore 4
    iload_3
    iload 4
    isub
    istore 5
    new java/lang/StringBuilder
    dup
    invokespecial java/lang/StringBuilder/<init>()V
    astore 6
    iconst_0
icn_ctr_lloop:
    dup
    iload 4
    if_icmpge icn_ctr_mid
    aload 6
    aload_2
    iconst_0
    invokevirtual java/lang/String/charAt(I)C
    invokevirtual java/lang/StringBuilder/append(C)Ljava/lang/StringBuilder;
    pop
    iconst_1
    iadd
    goto icn_ctr_lloop
icn_ctr_mid:
    pop
    aload 6
    aload_0
    invokevirtual java/lang/StringBuilder/append(Ljava/lang/String;)Ljava/lang/StringBuilder;
    pop
    iconst_0
icn_ctr_rloop:
    dup
    iload 5
    if_icmpge icn_ctr_done
    aload 6
    aload_2
    iconst_0
    invokevirtual java/lang/String/charAt(I)C
    invokevirtual java/lang/StringBuilder/append(C)Ljava/lang/StringBuilder;
    pop
    iconst_1
    iadd
    goto icn_ctr_rloop
icn_ctr_done:
    pop
    aload 6
    invokevirtual java/lang/StringBuilder/toString()Ljava/lang/String;
    areturn
.end method

.method public static icn_builtin_trim(Ljava/lang/String;Ljava/lang/String;)Ljava/lang/String;
    .limit stack 4
    .limit locals 3
    aload_0
    invokevirtual java/lang/String/length()I
    istore_2
icn_trim_loop:
    iload_2
    ifle icn_trim_done
    aload_1
    aload_0
    iload_2
    iconst_1
    isub
    invokevirtual java/lang/String/charAt(I)C
    invokevirtual java/lang/String/indexOf(I)I
    iflt icn_trim_done
    iinc 2 -1
    goto icn_trim_loop
icn_trim_done:
    aload_0
    iconst_0
    iload_2
    invokevirtual java/lang/String/substring(II)Ljava/lang/String;
    areturn
.end method

.method public static icn_builtin_map(Ljava/lang/String;Ljava/lang/String;Ljava/lang/String;)Ljava/lang/String;
    .limit stack 5
    .limit locals 7
    new java/lang/StringBuilder
    dup
    invokespecial java/lang/StringBuilder/<init>()V
    astore_3
    iconst_0
    istore 4
icn_map_loop:
    iload 4
    aload_0
    invokevirtual java/lang/String/length()I
    if_icmpge icn_map_done
    aload_0
    iload 4
    invokevirtual java/lang/String/charAt(I)C
    istore 5
    aload_1
    iload 5
    invokevirtual java/lang/String/indexOf(I)I
    istore 6
    iload 6
    iflt icn_map_notfound
    iload 6
    aload_2
    invokevirtual java/lang/String/length()I
    if_icmpge icn_map_notfound
    aload_3
    aload_2
    iload 6
    invokevirtual java/lang/String/charAt(I)C
    invokevirtual java/lang/StringBuilder/append(C)Ljava/lang/StringBuilder;
    pop
    goto icn_map_next
icn_map_notfound:
    aload_3
    iload 5
    invokevirtual java/lang/StringBuilder/append(C)Ljava/lang/StringBuilder;
    pop
icn_map_next:
    iinc 4 1
    goto icn_map_loop
icn_map_done:
    aload_3
    invokevirtual java/lang/StringBuilder/toString()Ljava/lang/String;
    areturn
.end method

.method public static icn_builtin_parse_long(Ljava/lang/String;)J
    .limit stack 4
    .limit locals 4
    .catch java/lang/Exception from icn_plong_L0 to icn_plong_L1 using icn_plong_catch
icn_plong_L0:
    aload_0
    invokevirtual java/lang/String/trim()Ljava/lang/String;
    astore_1
    aload_1
    ldc "r"
    invokevirtual java/lang/String/contains(Ljava/lang/CharSequence;)Z
    ifeq icn_plong_plain
    aload_1
    ldc "r"
    iconst_2
    invokevirtual java/lang/String/split(Ljava/lang/String;I)[Ljava/lang/String;
    astore_2
    aload_2
    iconst_0
    aaload
    invokestatic java/lang/Integer/parseInt(Ljava/lang/String;)I
    istore_3
    aload_2
    iconst_1
    aaload
    iload_3
    invokestatic java/lang/Long/parseLong(Ljava/lang/String;I)J
    goto icn_plong_L1
icn_plong_plain:
    aload_1
    invokestatic java/lang/Long/parseLong(Ljava/lang/String;)J
icn_plong_L1:
    lreturn
icn_plong_catch:
    pop
    ldc2_w -9223372036854775808
    lreturn
.end method

.method public static icn_builtin_numeric(Ljava/lang/String;)J
    .limit stack 2
    .limit locals 2
    aload_0
    invokestatic rung36_jcon_mindfa/icn_builtin_parse_long(Ljava/lang/String;)J
    lreturn
.end method

.method public static icn_builtin_sort(Ljava/util/ArrayList;)Ljava/util/ArrayList;
    .limit stack 6
    .limit locals 8
    new java/util/ArrayList
    dup
    aload_0
    invokespecial java/util/ArrayList/<init>(Ljava/util/Collection;)V
    astore_1
    iconst_1
    istore_2
icn_sort_outer:
    aload_1
    invokevirtual java/util/ArrayList/size()I
    iload_2
    if_icmple icn_sort_done
    aload_1
    iload_2
    invokevirtual java/util/ArrayList/get(I)Ljava/lang/Object;
    checkcast java/lang/Long
    invokevirtual java/lang/Long/longValue()J
    lstore 4
    iload_2
    iconst_1
    isub
    istore_3
icn_sort_inner:
    iload_3
    iflt icn_sort_insert
    aload_1
    iload_3
    invokevirtual java/util/ArrayList/get(I)Ljava/lang/Object;
    checkcast java/lang/Long
    invokevirtual java/lang/Long/longValue()J
    lload 4
    lcmp
    ifle icn_sort_insert
    aload_1
    iload_3
    iconst_1
    iadd
    aload_1
    iload_3
    invokevirtual java/util/ArrayList/get(I)Ljava/lang/Object;
    invokevirtual java/util/ArrayList/set(ILjava/lang/Object;)Ljava/lang/Object;
    pop
    iinc 3 -1
    goto icn_sort_inner
icn_sort_insert:
    aload_1
    iload_3
    iconst_1
    iadd
    lload 4
    invokestatic java/lang/Long/valueOf(J)Ljava/lang/Long;
    invokevirtual java/util/ArrayList/set(ILjava/lang/Object;)Ljava/lang/Object;
    pop
    iinc 2 1
    goto icn_sort_outer
icn_sort_done:
    aload_1
    areturn
.end method

.method public static icn_builtin_sortf(Ljava/util/ArrayList;I)Ljava/util/ArrayList;
    .limit stack 8
    .limit locals 10
    new java/util/ArrayList
    dup
    aload_0
    invokespecial java/util/ArrayList/<init>(Ljava/util/Collection;)V
    astore_2
    iconst_1
    istore_3
icn_sortf_outer:
    aload_2
    invokevirtual java/util/ArrayList/size()I
    iload_3
    if_icmple icn_sortf_done
    aload_2
    iload_3
    invokevirtual java/util/ArrayList/get(I)Ljava/lang/Object;
    astore 5
    iload_3
    iconst_1
    isub
    istore 4
icn_sortf_inner:
    iload 4
    iflt icn_sortf_insert
    aload_2
    iload 4
    invokevirtual java/util/ArrayList/get(I)Ljava/lang/Object;
    astore 6
    aload 6
    invokevirtual java/lang/Object/getClass()Ljava/lang/Class;
    invokevirtual java/lang/Class/getDeclaredFields()[Ljava/lang/reflect/Field;
    iload_1
    iconst_1
    isub
    aaload
    aload 6
    invokevirtual java/lang/reflect/Field/get(Ljava/lang/Object;)Ljava/lang/Object;
    astore 7
    aload 5
    invokevirtual java/lang/Object/getClass()Ljava/lang/Class;
    invokevirtual java/lang/Class/getDeclaredFields()[Ljava/lang/reflect/Field;
    iload_1
    iconst_1
    isub
    aaload
    aload 5
    invokevirtual java/lang/reflect/Field/get(Ljava/lang/Object;)Ljava/lang/Object;
    astore 8
    aload 7
    checkcast java/lang/Long
    aload 8
    checkcast java/lang/Long
    invokevirtual java/lang/Long/compareTo(Ljava/lang/Long;)I
    ifle icn_sortf_insert
    aload_2
    iload 4
    iconst_1
    iadd
    aload_2
    iload 4
    invokevirtual java/util/ArrayList/get(I)Ljava/lang/Object;
    invokevirtual java/util/ArrayList/set(ILjava/lang/Object;)Ljava/lang/Object;
    pop
    iinc 4 -1
    goto icn_sortf_inner
icn_sortf_insert:
    aload_2
    iload 4
    iconst_1
    iadd
    aload 5
    invokevirtual java/util/ArrayList/set(ILjava/lang/Object;)Ljava/lang/Object;
    pop
    iinc 3 1
    goto icn_sortf_outer
icn_sortf_done:
    aload_2
    areturn
.end method

.method public static icn_builtin_cset_complement(Ljava/lang/String;)Ljava/lang/String;
    .limit stack 4
    .limit locals 4
    ; StringBuilder result
    new java/lang/StringBuilder
    dup
    invokespecial java/lang/StringBuilder/<init>()V
    astore_1
    ; loop c = 1..127
    iconst_1
    istore_2
icn_csc_loop:
    iload_2
    bipush 127
    if_icmpgt icn_csc_done
    ; cs.indexOf(c) < 0 → append
    aload_0
    iload_2
    invokevirtual java/lang/String/indexOf(I)I
    ifge icn_csc_skip
    aload_1
    iload_2
    invokevirtual java/lang/StringBuilder/append(C)Ljava/lang/StringBuilder;
    pop
icn_csc_skip:
    iinc 2 1
    goto icn_csc_loop
icn_csc_done:
    aload_1
    invokevirtual java/lang/StringBuilder/toString()Ljava/lang/String;
    areturn
.end method

.method public static icn_builtin_cset_union(Ljava/lang/String;Ljava/lang/String;)Ljava/lang/String;
    .limit stack 4
    .limit locals 4
    ; start with copy of a
    new java/lang/StringBuilder
    dup
    aload_0
    invokespecial java/lang/StringBuilder/<init>(Ljava/lang/String;)V
    astore_2
    ; for each char in b: if a.indexOf(c)<0 append
    iconst_0
    istore_3
icn_csu_loop:
    iload_3
    aload_1
    invokevirtual java/lang/String/length()I
    if_icmpge icn_csu_done
    aload_1
    iload_3
    invokevirtual java/lang/String/charAt(I)C
    istore 0
    aload_0
    iload 0
    invokevirtual java/lang/String/indexOf(I)I
    ifge icn_csu_skip
    aload_2
    iload 0
    invokevirtual java/lang/StringBuilder/append(C)Ljava/lang/StringBuilder;
    pop
icn_csu_skip:
    iinc 3 1
    goto icn_csu_loop
icn_csu_done:
    aload_2
    invokevirtual java/lang/StringBuilder/toString()Ljava/lang/String;
    areturn
.end method

.method public static icn_builtin_cset_diff(Ljava/lang/String;Ljava/lang/String;)Ljava/lang/String;
    .limit stack 4
    .limit locals 4
    new java/lang/StringBuilder
    dup
    invokespecial java/lang/StringBuilder/<init>()V
    astore_2
    iconst_0
    istore_3
icn_csd_loop:
    iload_3
    aload_0
    invokevirtual java/lang/String/length()I
    if_icmpge icn_csd_done
    aload_0
    iload_3
    invokevirtual java/lang/String/charAt(I)C
    istore 0
    aload_1
    iload 0
    invokevirtual java/lang/String/indexOf(I)I
    ifge icn_csd_skip
    aload_2
    iload 0
    invokevirtual java/lang/StringBuilder/append(C)Ljava/lang/StringBuilder;
    pop
icn_csd_skip:
    iinc 3 1
    goto icn_csd_loop
icn_csd_done:
    aload_2
    invokevirtual java/lang/StringBuilder/toString()Ljava/lang/String;
    areturn
.end method

.method public static icn_builtin_cset_inter(Ljava/lang/String;Ljava/lang/String;)Ljava/lang/String;
    .limit stack 4
    .limit locals 4
    new java/lang/StringBuilder
    dup
    invokespecial java/lang/StringBuilder/<init>()V
    astore_2
    iconst_0
    istore_3
icn_csi_loop:
    iload_3
    aload_0
    invokevirtual java/lang/String/length()I
    if_icmpge icn_csi_done
    aload_0
    iload_3
    invokevirtual java/lang/String/charAt(I)C
    istore 0
    aload_1
    iload 0
    invokevirtual java/lang/String/indexOf(I)I
    iflt icn_csi_skip
    aload_2
    iload 0
    invokevirtual java/lang/StringBuilder/append(C)Ljava/lang/StringBuilder;
    pop
icn_csi_skip:
    iinc 3 1
    goto icn_csi_loop
icn_csi_done:
    aload_2
    invokevirtual java/lang/StringBuilder/toString()Ljava/lang/String;
    areturn
.end method

.method public static icn_main()V
    .limit stack 16
    .limit locals 266
    lconst_0
    lstore 0
    lconst_0
    lstore 2
    lconst_0
    lstore 4
    lconst_0
    lstore 6
    lconst_0
    lstore 8
    lconst_0
    lstore 10
    lconst_0
    lstore 12
    lconst_0
    lstore 14
    lconst_0
    lstore 16
    lconst_0
    lstore 18
    lconst_0
    lstore 20
    lconst_0
    lstore 22
    lconst_0
    lstore 24
    lconst_0
    lstore 26
    lconst_0
    lstore 28
    lconst_0
    lstore 30
    lconst_0
    lstore 32
    lconst_0
    lstore 34
    lconst_0
    lstore 36
    lconst_0
    lstore 38
    lconst_0
    lstore 40
    lconst_0
    lstore 42
    lconst_0
    lstore 44
    lconst_0
    lstore 46
    lconst_0
    lstore 48
    lconst_0
    lstore 50
    lconst_0
    lstore 52
    lconst_0
    lstore 54
    lconst_0
    lstore 56
    lconst_0
    lstore 58
    lconst_0
    lstore 60
    lconst_0
    lstore 62
    iconst_0
    istore 84
    iconst_0
    istore 85
    iconst_0
    istore 86
    iconst_0
    istore 87
    aconst_null
    astore 148
    aconst_null
    astore 149
    aconst_null
    astore 150
    aconst_null
    astore 151
    goto icn_10_α
;  VAR
icn_4_α:
    getstatic rung36_jcon_mindfa/icn_pv_main_x J
    goto icn_3_arg1
icn_4_β:
    goto icn_0_pump
icn_3_arg1:
    putstatic rung36_jcon_mindfa/icn_arg_1 J
    goto icn_3_docall
;  STR
icn_5_α:
    ldc "Original"
    goto icn_3_arg0
icn_5_β:
    goto icn_0_pump
icn_3_arg0:
    putstatic rung36_jcon_mindfa/icn_arg_str_0 Ljava/lang/String;
    lconst_0
    putstatic rung36_jcon_mindfa/icn_arg_0 J
    goto icn_4_α
icn_3_α:
    goto icn_5_α
icn_3_β:
    goto icn_4_β
icn_3_docall:
    getstatic rung36_jcon_mindfa/icn_pv_main_x J
    lstore 152
    invokestatic rung36_jcon_mindfa/icn_showdfa()V
    lload 152
    putstatic rung36_jcon_mindfa/icn_pv_main_x J
    getstatic rung36_jcon_mindfa/icn_failed B
    ifne icn_3_after_call
    getstatic rung36_jcon_mindfa/icn_retval J
    goto icn_2_arg0
icn_3_after_call:
    goto icn_0_pump
icn_2_arg0:
    putstatic rung36_jcon_mindfa/icn_arg_0 J
    goto icn_2_docall
icn_2_α:
    goto icn_3_α
icn_2_β:
    goto icn_3_β
icn_2_docall:
    getstatic rung36_jcon_mindfa/icn_pv_main_x J
    lstore 152
    invokestatic rung36_jcon_mindfa/icn_minimize()V
    lload 152
    putstatic rung36_jcon_mindfa/icn_pv_main_x J
    getstatic rung36_jcon_mindfa/icn_failed B
    ifne icn_2_after_call
    getstatic rung36_jcon_mindfa/icn_retval J
    goto icn_1_arg1
icn_2_after_call:
    goto icn_0_pump
icn_1_arg1:
    putstatic rung36_jcon_mindfa/icn_arg_1 J
    goto icn_1_docall
;  STR
icn_6_α:
    ldc "Reduced"
    goto icn_1_arg0
icn_6_β:
    goto icn_0_pump
icn_1_arg0:
    putstatic rung36_jcon_mindfa/icn_arg_str_0 Ljava/lang/String;
    lconst_0
    putstatic rung36_jcon_mindfa/icn_arg_0 J
    goto icn_2_α
icn_1_α:
    goto icn_6_α
icn_1_β:
    goto icn_2_β
icn_1_docall:
    getstatic rung36_jcon_mindfa/icn_pv_main_x J
    lstore 152
    invokestatic rung36_jcon_mindfa/icn_showdfa()V
    lload 152
    putstatic rung36_jcon_mindfa/icn_pv_main_x J
    getstatic rung36_jcon_mindfa/icn_failed B
    ifne icn_1_after_call
    getstatic rung36_jcon_mindfa/icn_retval J
    goto icn_0_bdrain
icn_1_after_call:
    goto icn_0_pump
;  INT
icn_8_α:
    ldc2_w 10
    goto icn_7_e2relay
icn_8_β:
    goto icn_7_e1b
;  INT
icn_9_α:
    ldc2_w 1
    goto icn_7_e1relay
icn_9_β:
    goto icn_main_done
icn_7_e1relay:
    putstatic rung36_jcon_mindfa/icn_7_e1val J
    goto icn_8_α
icn_7_e2relay:
    putstatic rung36_jcon_mindfa/icn_7_e2val J
    goto icn_7_init
icn_7_e1b:
    iconst_0
    putstatic rung36_jcon_mindfa/icn_7_e2seen I
    goto icn_9_β
icn_7_e2b:
    goto icn_8_β
icn_7_α:
    iconst_0
    putstatic rung36_jcon_mindfa/icn_7_e2seen I
    goto icn_9_α
icn_7_β:
    getstatic rung36_jcon_mindfa/icn_7_I J
    lconst_1
    ladd
    putstatic rung36_jcon_mindfa/icn_7_I J
    goto icn_7_code
icn_7_init:
    getstatic rung36_jcon_mindfa/icn_7_e2val J
    putstatic rung36_jcon_mindfa/icn_7_bound J
    getstatic rung36_jcon_mindfa/icn_7_e2seen I
    ifne icn_7_init_e2adv
    getstatic rung36_jcon_mindfa/icn_7_e1val J
    putstatic rung36_jcon_mindfa/icn_7_e1cur J
    getstatic rung36_jcon_mindfa/icn_7_e1cur J
    putstatic rung36_jcon_mindfa/icn_7_I J
    iconst_1
    putstatic rung36_jcon_mindfa/icn_7_e2seen I
    goto icn_7_code
icn_7_init_e2adv:
    getstatic rung36_jcon_mindfa/icn_7_e1cur J
    putstatic rung36_jcon_mindfa/icn_7_I J
    goto icn_7_code
icn_7_code:
    getstatic rung36_jcon_mindfa/icn_7_I J
    getstatic rung36_jcon_mindfa/icn_7_bound J
    lcmp
    ifgt icn_7_e2b
    getstatic rung36_jcon_mindfa/icn_7_I J
    goto icn_0_gdrain
icn_0_gdrain:
    pop2
    goto icn_1_α
icn_0_bdrain:
    pop2
icn_0_pump:
    goto icn_7_β
icn_0_α:
    goto icn_7_α
icn_0_β:
    goto icn_main_done
icn_11_α:
    goto icn_11_docall
icn_11_β:
    goto icn_0_α
icn_11_docall:
    getstatic rung36_jcon_mindfa/icn_pv_main_x J
    lstore 152
    getstatic rung36_jcon_mindfa/icn_7_I J
    lstore 154
    getstatic rung36_jcon_mindfa/icn_7_bound J
    lstore 156
    getstatic rung36_jcon_mindfa/icn_7_e1cur J
    lstore 158
    getstatic rung36_jcon_mindfa/icn_7_e1val J
    lstore 160
    getstatic rung36_jcon_mindfa/icn_7_e2val J
    lstore 162
    invokestatic rung36_jcon_mindfa/icn_getdfa()V
    lload 152
    putstatic rung36_jcon_mindfa/icn_pv_main_x J
    lload 154
    putstatic rung36_jcon_mindfa/icn_7_I J
    lload 156
    putstatic rung36_jcon_mindfa/icn_7_bound J
    lload 158
    putstatic rung36_jcon_mindfa/icn_7_e1cur J
    lload 160
    putstatic rung36_jcon_mindfa/icn_7_e1val J
    lload 162
    putstatic rung36_jcon_mindfa/icn_7_e2val J
    getstatic rung36_jcon_mindfa/icn_failed B
    ifne icn_11_after_call
    getstatic rung36_jcon_mindfa/icn_retval J
    goto icn_10_store
icn_11_after_call:
    goto icn_0_α
icn_10_α:
    goto icn_11_α
icn_10_β:
    goto icn_11_β
icn_10_store:
    putstatic rung36_jcon_mindfa/icn_pv_main_x J
    getstatic rung36_jcon_mindfa/icn_pv_main_x J
    goto icn_main_s0_sdrain
icn_main_s0_sdrain:
    pop2
    goto icn_0_α
icn_main_done:
    return
.end method

.method public static icn_getdfa()V
    .limit stack 16
    .limit locals 310
    lconst_0
    lstore 0
    lconst_0
    lstore 2
    lconst_0
    lstore 4
    lconst_0
    lstore 6
    lconst_0
    lstore 8
    lconst_0
    lstore 10
    lconst_0
    lstore 12
    lconst_0
    lstore 14
    lconst_0
    lstore 16
    lconst_0
    lstore 18
    lconst_0
    lstore 20
    lconst_0
    lstore 22
    lconst_0
    lstore 24
    lconst_0
    lstore 26
    lconst_0
    lstore 28
    lconst_0
    lstore 30
    lconst_0
    lstore 32
    lconst_0
    lstore 34
    lconst_0
    lstore 36
    lconst_0
    lstore 38
    lconst_0
    lstore 40
    lconst_0
    lstore 42
    lconst_0
    lstore 44
    lconst_0
    lstore 46
    lconst_0
    lstore 48
    lconst_0
    lstore 50
    lconst_0
    lstore 52
    lconst_0
    lstore 54
    lconst_0
    lstore 56
    lconst_0
    lstore 58
    lconst_0
    lstore 60
    lconst_0
    lstore 62
    iconst_0
    istore 84
    iconst_0
    istore 85
    iconst_0
    istore 86
    iconst_0
    istore 87
    iconst_0
    istore 88
    iconst_0
    istore 89
    aconst_null
    astore 148
    aconst_null
    astore 149
    aconst_null
    astore 150
    aconst_null
    astore 151
    goto icn_44_α
;  VAR
icn_14_α:
    getstatic rung36_jcon_mindfa/icn_pv_getdfa_Q J
    goto icn_13_rc_r1
icn_14_β:
    goto icn_12_ret_fail
;  VAR
icn_15_α:
    getstatic rung36_jcon_mindfa/icn_pv_getdfa_S J
    goto icn_13_rc_r2
icn_15_β:
    goto icn_12_ret_fail
;  VAR
icn_16_α:
    getstatic rung36_jcon_mindfa/icn_pv_getdfa_d Ljava/util/HashMap;
    goto icn_13_rc_r3
icn_16_β:
    goto icn_12_ret_fail
;  VAR
icn_17_α:
    getstatic rung36_jcon_mindfa/icn_pv_getdfa_q0 Ljava/lang/String;
    goto icn_13_rc_r4
icn_17_β:
    goto icn_12_ret_fail
;  VAR
icn_18_α:
    getstatic rung36_jcon_mindfa/icn_pv_getdfa_F J
    goto icn_13_rc_r5
icn_18_β:
    goto icn_12_ret_fail
icn_13_α:
    goto icn_14_α
icn_13_β:
    goto icn_12_ret_fail
icn_13_rc_r1:
    invokestatic java/lang/Long/valueOf(J)Ljava/lang/Long;
    putstatic rung36_jcon_mindfa/icn_13_rc_a0 Ljava/lang/Object;
    goto icn_15_α
icn_13_rc_r2:
    invokestatic java/lang/Long/valueOf(J)Ljava/lang/Long;
    putstatic rung36_jcon_mindfa/icn_13_rc_a1 Ljava/lang/Object;
    goto icn_16_α
icn_13_rc_r3:
    invokestatic java/lang/Long/valueOf(J)Ljava/lang/Long;
    putstatic rung36_jcon_mindfa/icn_13_rc_a2 Ljava/lang/Object;
    goto icn_17_α
icn_13_rc_r4:
    invokestatic java/lang/Long/valueOf(J)Ljava/lang/Long;
    putstatic rung36_jcon_mindfa/icn_13_rc_a3 Ljava/lang/Object;
    goto icn_18_α
icn_13_rc_r5:
    invokestatic java/lang/Long/valueOf(J)Ljava/lang/Long;
    putstatic rung36_jcon_mindfa/icn_13_rc_a4 Ljava/lang/Object;
    goto icn_13_rc_build
icn_13_rc_build:
    new rung36_jcon_mindfa$dfa
    dup
    invokespecial rung36_jcon_mindfa$dfa/<init>()V
    putstatic rung36_jcon_mindfa/icn_13_rc_obj Ljava/lang/Object;
    getstatic rung36_jcon_mindfa/icn_13_rc_obj Ljava/lang/Object;
    putstatic rung36_jcon_mindfa/icn_retval_obj Ljava/lang/Object;
    lconst_0
    goto icn_12_ret_store
icn_12_α:
    goto icn_13_α
icn_12_β:
    goto icn_getdfa_ret
icn_12_ret_fail:
    iconst_1
    putstatic rung36_jcon_mindfa/icn_failed B
    goto icn_getdfa_done
icn_12_ret_store:
    putstatic rung36_jcon_mindfa/icn_retval J
    iconst_0
    putstatic rung36_jcon_mindfa/icn_failed B
    goto icn_getdfa_ret
icn_21_α:
    goto icn_20_seq_rf_0
icn_21_β:
    goto icn_20_seq_rf_0
icn_23_α:
    getstatic rung36_jcon_mindfa/icn_stdin_init I
    ifne icn_23_rd_call
    new java/io/BufferedReader
    dup
    new java/io/InputStreamReader
    dup
    getstatic java/lang/System/in Ljava/io/InputStream;
    invokespecial java/io/InputStreamReader/<init>(Ljava/io/InputStream;)V
    invokespecial java/io/BufferedReader/<init>(Ljava/io/Reader;)V
    putstatic rung36_jcon_mindfa/icn_stdin_reader Ljava/lang/Object;
    iconst_1
    putstatic rung36_jcon_mindfa/icn_stdin_init I
icn_23_rd_call:
    getstatic rung36_jcon_mindfa/icn_stdin_reader Ljava/lang/Object;
    checkcast java/io/BufferedReader
    invokevirtual java/io/BufferedReader/readLine()Ljava/lang/String;
    dup
    ifnull icn_23_rd_null
    goto icn_22_tsa_vr
icn_23_rd_null:
    pop
    goto icn_19_pump
icn_23_β:
    goto icn_19_pump
;  VAR
icn_25_α:
    getstatic rung36_jcon_mindfa/icn_gvar_a Ljava/lang/String;
    goto icn_24_rrelay
icn_25_β:
    goto icn_24_lb
;  STR
icn_27_α:
    ldc ":"
    goto icn_26_rrelay
icn_27_β:
    goto icn_26_lb
;  VAR
icn_28_α:
    getstatic rung36_jcon_mindfa/icn_pv_getdfa_q Ljava/lang/String;
    goto icn_26_lrelay
icn_28_β:
    goto icn_19_pump
icn_26_lrelay:
    putstatic rung36_jcon_mindfa/icn_26_lc Ljava/lang/String;
    goto icn_26_lstore
icn_26_rrelay:
    putstatic rung36_jcon_mindfa/icn_26_rc Ljava/lang/String;
    goto icn_26_compute
icn_26_lb:
    goto icn_28_β
icn_26_α:
    iconst_0
    istore 85
    goto icn_28_α
icn_26_β:
    iconst_1
    istore 85
    goto icn_28_α
icn_26_lstore:
    iload 85
    ifeq icn_27_α
    goto icn_27_β
icn_26_compute:
    getstatic rung36_jcon_mindfa/icn_26_lc Ljava/lang/String;
    getstatic rung36_jcon_mindfa/icn_26_rc Ljava/lang/String;
    invokevirtual java/lang/String/concat(Ljava/lang/String;)Ljava/lang/String;
    goto icn_24_lrelay
icn_24_lrelay:
    putstatic rung36_jcon_mindfa/icn_24_lc Ljava/lang/String;
    goto icn_24_lstore
icn_24_rrelay:
    putstatic rung36_jcon_mindfa/icn_24_rc Ljava/lang/String;
    goto icn_24_compute
icn_24_lb:
    goto icn_26_β
icn_24_α:
    iconst_0
    istore 84
    goto icn_26_α
icn_24_β:
    iconst_1
    istore 84
    goto icn_26_α
icn_24_lstore:
    iload 84
    ifeq icn_25_α
    goto icn_25_β
icn_24_compute:
    getstatic rung36_jcon_mindfa/icn_24_lc Ljava/lang/String;
    getstatic rung36_jcon_mindfa/icn_24_rc Ljava/lang/String;
    invokevirtual java/lang/String/concat(Ljava/lang/String;)Ljava/lang/String;
    goto icn_22_tsa_kr
icn_22_α:
    goto icn_23_α
icn_22_β:
    goto icn_19_pump
icn_22_tsa_vr:
    dup
    putstatic rung36_jcon_mindfa/icn_22_tsa_vl Ljava/lang/String;
    goto icn_24_α
icn_22_tsa_kr:
    putstatic rung36_jcon_mindfa/icn_22_tsa_ks Ljava/lang/String;
    goto icn_22_tsa_put
icn_22_tsa_put:
    getstatic rung36_jcon_mindfa/icn_pv_getdfa_d Ljava/util/HashMap;
    getstatic rung36_jcon_mindfa/icn_22_tsa_ks Ljava/lang/String;
    getstatic rung36_jcon_mindfa/icn_22_tsa_vl Ljava/lang/String;
    invokevirtual java/util/HashMap/put(Ljava/lang/Object;Ljava/lang/Object;)Ljava/lang/Object;
    pop
    getstatic rung36_jcon_mindfa/icn_22_tsa_vl Ljava/lang/String;
    goto icn_19_bdrain
    goto icn_20_α
icn_20_seq_rg_0:
    pop2
    goto icn_22_α
icn_20_seq_rf_0:
    goto icn_22_α
icn_20_α:
    goto icn_21_α
icn_20_β:
    goto icn_22_β
;  VAR
icn_32_α:
    getstatic rung36_jcon_mindfa/icn_pv_getdfa_S J
    goto icn_31_bang_adv
icn_32_β:
    goto icn_12_α
icn_31_α:
    goto icn_32_α
icn_31_β:
    goto icn_31_bang_chk
icn_31_bang_adv:
    putstatic rung36_jcon_mindfa/icn_31_bang_str Ljava/lang/String;
    iconst_0
    putstatic rung36_jcon_mindfa/icn_31_bang_pos I
icn_31_bang_chk:
    getstatic rung36_jcon_mindfa/icn_31_bang_str Ljava/lang/String;
    invokevirtual java/lang/String/length()I
    getstatic rung36_jcon_mindfa/icn_31_bang_pos I
    if_icmple icn_12_α
    getstatic rung36_jcon_mindfa/icn_31_bang_str Ljava/lang/String;
    getstatic rung36_jcon_mindfa/icn_31_bang_pos I
    getstatic rung36_jcon_mindfa/icn_31_bang_pos I
    iconst_1
    iadd
    invokevirtual java/lang/String/substring(II)Ljava/lang/String;
    getstatic rung36_jcon_mindfa/icn_31_bang_pos I
    iconst_1
    iadd
    putstatic rung36_jcon_mindfa/icn_31_bang_pos I
    goto icn_30_store
icn_30_α:
    goto icn_31_α
icn_30_β:
    goto icn_31_β
icn_30_store:
    pop
    aconst_null
    goto icn_29_store
icn_29_α:
    goto icn_30_α
icn_29_β:
    goto icn_30_β
icn_29_store:
    putstatic rung36_jcon_mindfa/icn_pv_getdfa_q Ljava/lang/String;
    getstatic rung36_jcon_mindfa/icn_pv_getdfa_q Ljava/lang/String;
    goto icn_19_gdrain
icn_19_gdrain:
    pop
    goto icn_20_α
icn_19_bdrain:
    pop
icn_19_pump:
    goto icn_29_β
icn_19_α:
    goto icn_29_α
icn_19_β:
    goto icn_12_α
icn_34_α:
    goto icn_19_α
icn_34_β:
    goto icn_19_α
icn_33_α:
    goto icn_34_α
icn_33_β:
    goto icn_34_β
icn_33_store:
    putstatic rung36_jcon_mindfa/icn_pv_getdfa_d Ljava/util/HashMap;
    getstatic rung36_jcon_mindfa/icn_pv_getdfa_d Ljava/util/HashMap;
    goto icn_getdfa_s7_sdrain
icn_getdfa_s7_sdrain:
    pop
    goto icn_19_α
icn_36_α:
    getstatic rung36_jcon_mindfa/icn_stdin_init I
    ifne icn_36_rd_call
    new java/io/BufferedReader
    dup
    new java/io/InputStreamReader
    dup
    getstatic java/lang/System/in Ljava/io/InputStream;
    invokespecial java/io/InputStreamReader/<init>(Ljava/io/InputStream;)V
    invokespecial java/io/BufferedReader/<init>(Ljava/io/Reader;)V
    putstatic rung36_jcon_mindfa/icn_stdin_reader Ljava/lang/Object;
    iconst_1
    putstatic rung36_jcon_mindfa/icn_stdin_init I
icn_36_rd_call:
    getstatic rung36_jcon_mindfa/icn_stdin_reader Ljava/lang/Object;
    checkcast java/io/BufferedReader
    invokevirtual java/io/BufferedReader/readLine()Ljava/lang/String;
    dup
    ifnull icn_36_rd_null
    goto icn_35_store
icn_36_rd_null:
    pop
    goto icn_33_α
icn_36_β:
    goto icn_33_α
icn_35_α:
    goto icn_36_α
icn_35_β:
    goto icn_36_β
icn_35_store:
    putstatic rung36_jcon_mindfa/icn_pv_getdfa_q0 Ljava/lang/String;
    getstatic rung36_jcon_mindfa/icn_pv_getdfa_q0 Ljava/lang/String;
    goto icn_getdfa_s6_sdrain
icn_getdfa_s6_sdrain:
    pop
    goto icn_33_α
icn_37_α:
    goto icn_35_α
icn_37_β:
    goto icn_35_α
icn_getdfa_s5_sdrain:
    pop2
    goto icn_35_α
;  STR
icn_40_α:
    ldc "Enter Final states (subset of states): "
    goto icn_39_arg0
icn_40_β:
    goto icn_37_α
icn_39_arg0:
    putstatic rung36_jcon_mindfa/icn_arg_str_0 Ljava/lang/String;
    lconst_0
    putstatic rung36_jcon_mindfa/icn_arg_0 J
    goto icn_39_docall
icn_39_α:
    goto icn_40_α
icn_39_β:
    goto icn_40_β
icn_39_docall:
    getstatic rung36_jcon_mindfa/icn_7_I J
    lstore 152
    getstatic rung36_jcon_mindfa/icn_7_bound J
    lstore 154
    getstatic rung36_jcon_mindfa/icn_7_e1cur J
    lstore 156
    getstatic rung36_jcon_mindfa/icn_7_e1val J
    lstore 158
    getstatic rung36_jcon_mindfa/icn_7_e2val J
    lstore 160
    getstatic rung36_jcon_mindfa/icn_pv_getdfa_Q J
    lstore 162
    getstatic rung36_jcon_mindfa/icn_pv_getdfa_S J
    lstore 164
    getstatic rung36_jcon_mindfa/icn_pv_getdfa_F J
    lstore 166
    invokestatic rung36_jcon_mindfa/icn_readset()V
    lload 152
    putstatic rung36_jcon_mindfa/icn_7_I J
    lload 154
    putstatic rung36_jcon_mindfa/icn_7_bound J
    lload 156
    putstatic rung36_jcon_mindfa/icn_7_e1cur J
    lload 158
    putstatic rung36_jcon_mindfa/icn_7_e1val J
    lload 160
    putstatic rung36_jcon_mindfa/icn_7_e2val J
    lload 162
    putstatic rung36_jcon_mindfa/icn_pv_getdfa_Q J
    lload 164
    putstatic rung36_jcon_mindfa/icn_pv_getdfa_S J
    lload 166
    putstatic rung36_jcon_mindfa/icn_pv_getdfa_F J
    getstatic rung36_jcon_mindfa/icn_failed B
    ifne icn_39_after_call
    getstatic rung36_jcon_mindfa/icn_retval J
    goto icn_38_store
icn_39_after_call:
    goto icn_37_α
icn_38_α:
    goto icn_39_α
icn_38_β:
    goto icn_39_β
icn_38_store:
    putstatic rung36_jcon_mindfa/icn_pv_getdfa_F J
    getstatic rung36_jcon_mindfa/icn_pv_getdfa_F J
    goto icn_getdfa_s4_sdrain
icn_getdfa_s4_sdrain:
    pop2
    goto icn_37_α
;  STR
icn_43_α:
    ldc "Enter input alphabet: "
    goto icn_42_arg0
icn_43_β:
    goto icn_38_α
icn_42_arg0:
    putstatic rung36_jcon_mindfa/icn_arg_str_0 Ljava/lang/String;
    lconst_0
    putstatic rung36_jcon_mindfa/icn_arg_0 J
    goto icn_42_docall
icn_42_α:
    goto icn_43_α
icn_42_β:
    goto icn_43_β
icn_42_docall:
    getstatic rung36_jcon_mindfa/icn_7_I J
    lstore 152
    getstatic rung36_jcon_mindfa/icn_7_bound J
    lstore 154
    getstatic rung36_jcon_mindfa/icn_7_e1cur J
    lstore 156
    getstatic rung36_jcon_mindfa/icn_7_e1val J
    lstore 158
    getstatic rung36_jcon_mindfa/icn_7_e2val J
    lstore 160
    getstatic rung36_jcon_mindfa/icn_pv_getdfa_Q J
    lstore 162
    getstatic rung36_jcon_mindfa/icn_pv_getdfa_S J
    lstore 164
    getstatic rung36_jcon_mindfa/icn_pv_getdfa_F J
    lstore 166
    invokestatic rung36_jcon_mindfa/icn_readset()V
    lload 152
    putstatic rung36_jcon_mindfa/icn_7_I J
    lload 154
    putstatic rung36_jcon_mindfa/icn_7_bound J
    lload 156
    putstatic rung36_jcon_mindfa/icn_7_e1cur J
    lload 158
    putstatic rung36_jcon_mindfa/icn_7_e1val J
    lload 160
    putstatic rung36_jcon_mindfa/icn_7_e2val J
    lload 162
    putstatic rung36_jcon_mindfa/icn_pv_getdfa_Q J
    lload 164
    putstatic rung36_jcon_mindfa/icn_pv_getdfa_S J
    lload 166
    putstatic rung36_jcon_mindfa/icn_pv_getdfa_F J
    getstatic rung36_jcon_mindfa/icn_failed B
    ifne icn_42_after_call
    getstatic rung36_jcon_mindfa/icn_retval J
    goto icn_41_store
icn_42_after_call:
    goto icn_38_α
icn_41_α:
    goto icn_42_α
icn_41_β:
    goto icn_42_β
icn_41_store:
    putstatic rung36_jcon_mindfa/icn_pv_getdfa_S J
    getstatic rung36_jcon_mindfa/icn_pv_getdfa_S J
    goto icn_getdfa_s3_sdrain
icn_getdfa_s3_sdrain:
    pop2
    goto icn_38_α
;  STR
icn_46_α:
    ldc "Enter states (1 character names): "
    goto icn_45_arg0
icn_46_β:
    goto icn_41_α
icn_45_arg0:
    putstatic rung36_jcon_mindfa/icn_arg_str_0 Ljava/lang/String;
    lconst_0
    putstatic rung36_jcon_mindfa/icn_arg_0 J
    goto icn_45_docall
icn_45_α:
    goto icn_46_α
icn_45_β:
    goto icn_46_β
icn_45_docall:
    getstatic rung36_jcon_mindfa/icn_7_I J
    lstore 152
    getstatic rung36_jcon_mindfa/icn_7_bound J
    lstore 154
    getstatic rung36_jcon_mindfa/icn_7_e1cur J
    lstore 156
    getstatic rung36_jcon_mindfa/icn_7_e1val J
    lstore 158
    getstatic rung36_jcon_mindfa/icn_7_e2val J
    lstore 160
    getstatic rung36_jcon_mindfa/icn_pv_getdfa_Q J
    lstore 162
    getstatic rung36_jcon_mindfa/icn_pv_getdfa_S J
    lstore 164
    getstatic rung36_jcon_mindfa/icn_pv_getdfa_F J
    lstore 166
    invokestatic rung36_jcon_mindfa/icn_readset()V
    lload 152
    putstatic rung36_jcon_mindfa/icn_7_I J
    lload 154
    putstatic rung36_jcon_mindfa/icn_7_bound J
    lload 156
    putstatic rung36_jcon_mindfa/icn_7_e1cur J
    lload 158
    putstatic rung36_jcon_mindfa/icn_7_e1val J
    lload 160
    putstatic rung36_jcon_mindfa/icn_7_e2val J
    lload 162
    putstatic rung36_jcon_mindfa/icn_pv_getdfa_Q J
    lload 164
    putstatic rung36_jcon_mindfa/icn_pv_getdfa_S J
    lload 166
    putstatic rung36_jcon_mindfa/icn_pv_getdfa_F J
    getstatic rung36_jcon_mindfa/icn_failed B
    ifne icn_45_after_call
    getstatic rung36_jcon_mindfa/icn_retval J
    goto icn_44_store
icn_45_after_call:
    goto icn_41_α
icn_44_α:
    goto icn_45_α
icn_44_β:
    goto icn_45_β
icn_44_store:
    putstatic rung36_jcon_mindfa/icn_pv_getdfa_Q J
    getstatic rung36_jcon_mindfa/icn_pv_getdfa_Q J
    goto icn_getdfa_s2_sdrain
icn_getdfa_s2_sdrain:
    pop2
    goto icn_41_α
icn_getdfa_done:
    iconst_0
    putstatic rung36_jcon_mindfa/icn_suspended B
    iconst_0
    putstatic rung36_jcon_mindfa/icn_suspend_id I
    iconst_1
    putstatic rung36_jcon_mindfa/icn_failed B
    return
icn_getdfa_ret:
    iconst_0
    putstatic rung36_jcon_mindfa/icn_failed B
    return
icn_getdfa_sret:
    return
.end method

.method public static icn_readset()V
    .limit stack 16
    .limit locals 322
    lconst_0
    lstore 0
    lconst_0
    lstore 2
    lconst_0
    lstore 4
    lconst_0
    lstore 6
    lconst_0
    lstore 8
    lconst_0
    lstore 10
    lconst_0
    lstore 12
    lconst_0
    lstore 14
    lconst_0
    lstore 16
    lconst_0
    lstore 18
    lconst_0
    lstore 20
    lconst_0
    lstore 22
    lconst_0
    lstore 24
    lconst_0
    lstore 26
    lconst_0
    lstore 28
    lconst_0
    lstore 30
    lconst_0
    lstore 32
    lconst_0
    lstore 34
    lconst_0
    lstore 36
    lconst_0
    lstore 38
    lconst_0
    lstore 40
    lconst_0
    lstore 42
    lconst_0
    lstore 44
    lconst_0
    lstore 46
    lconst_0
    lstore 48
    lconst_0
    lstore 50
    lconst_0
    lstore 52
    lconst_0
    lstore 54
    lconst_0
    lstore 56
    lconst_0
    lstore 58
    lconst_0
    lstore 60
    lconst_0
    lstore 62
    iconst_0
    istore 84
    iconst_0
    istore 85
    iconst_0
    istore 86
    iconst_0
    istore 87
    aconst_null
    astore 148
    aconst_null
    astore 149
    aconst_null
    astore 150
    aconst_null
    astore 151
    getstatic rung36_jcon_mindfa/icn_arg_str_0 Ljava/lang/String;
    putstatic rung36_jcon_mindfa/icn_pv_readset_s Ljava/lang/String;
    goto icn_56_α
;  VAR
icn_48_α:
    getstatic rung36_jcon_mindfa/icn_pv_readset_t1 Ljava/util/ArrayList;
    goto icn_47_ret_store
icn_48_β:
    goto icn_47_ret_fail
icn_47_α:
    goto icn_48_α
icn_47_β:
    goto icn_readset_ret
icn_47_ret_fail:
    iconst_1
    putstatic rung36_jcon_mindfa/icn_failed B
    goto icn_readset_done
icn_47_ret_store:
    putstatic rung36_jcon_mindfa/icn_retval J
    iconst_0
    putstatic rung36_jcon_mindfa/icn_failed B
    goto icn_readset_ret
;  VAR
icn_51_α:
    getstatic rung36_jcon_mindfa/icn_pv_readset_t1 Ljava/util/ArrayList;
    goto icn_50_lr
icn_51_β:
    goto icn_47_α
icn_53_α:
    goto icn_47_α
icn_53_β:
    goto icn_47_α
icn_52_α:
    goto icn_53_α
icn_52_β:
    goto icn_52_bang_chk
icn_52_bang_adv:
    putstatic rung36_jcon_mindfa/icn_52_bang_str Ljava/lang/String;
    iconst_0
    putstatic rung36_jcon_mindfa/icn_52_bang_pos I
icn_52_bang_chk:
    getstatic rung36_jcon_mindfa/icn_52_bang_str Ljava/lang/String;
    invokevirtual java/lang/String/length()I
    getstatic rung36_jcon_mindfa/icn_52_bang_pos I
    if_icmple icn_47_α
    getstatic rung36_jcon_mindfa/icn_52_bang_str Ljava/lang/String;
    getstatic rung36_jcon_mindfa/icn_52_bang_pos I
    getstatic rung36_jcon_mindfa/icn_52_bang_pos I
    iconst_1
    iadd
    invokevirtual java/lang/String/substring(II)Ljava/lang/String;
    getstatic rung36_jcon_mindfa/icn_52_bang_pos I
    iconst_1
    iadd
    putstatic rung36_jcon_mindfa/icn_52_bang_pos I
    goto icn_50_vr
icn_50_α:
    goto icn_51_α
icn_50_β:
    goto icn_47_α
icn_50_lr:
    putstatic rung36_jcon_mindfa/icn_50_pushlist Ljava/util/ArrayList;
    goto icn_52_α
icn_50_vr:
    putstatic rung36_jcon_mindfa/icn_50_pushval Ljava/lang/Object;
    getstatic rung36_jcon_mindfa/icn_50_pushlist Ljava/util/ArrayList;
    getstatic rung36_jcon_mindfa/icn_50_pushval Ljava/lang/Object;
    invokevirtual java/util/ArrayList/add(Ljava/lang/Object;)Z
    pop
    getstatic rung36_jcon_mindfa/icn_50_pushlist Ljava/util/ArrayList;
    goto icn_49_gdrain
icn_49_gdrain:
    pop
icn_49_pump:
    goto icn_50_β
icn_49_α:
    goto icn_50_α
icn_49_β:
    goto icn_47_α
icn_55_α:
    new java/util/ArrayList
    dup
    invokespecial java/util/ArrayList/<init>()V
    putstatic rung36_jcon_mindfa/icn_55_mklist Ljava/util/ArrayList;
    getstatic rung36_jcon_mindfa/icn_55_mklist Ljava/util/ArrayList;
    goto icn_54_store
icn_55_β:
    goto icn_49_α
icn_54_α:
    goto icn_55_α
icn_54_β:
    goto icn_55_β
icn_54_store:
    putstatic rung36_jcon_mindfa/icn_pv_readset_t1 Ljava/util/ArrayList;
    getstatic rung36_jcon_mindfa/icn_pv_readset_t1 Ljava/util/ArrayList;
    goto icn_readset_s2_sdrain
icn_readset_s2_sdrain:
    pop
    goto icn_49_α
icn_56_α:
    goto icn_54_α
icn_56_β:
    goto icn_54_α
icn_readset_s1_sdrain:
    pop2
    goto icn_54_α
icn_readset_done:
    iconst_0
    putstatic rung36_jcon_mindfa/icn_suspended B
    iconst_0
    putstatic rung36_jcon_mindfa/icn_suspend_id I
    iconst_1
    putstatic rung36_jcon_mindfa/icn_failed B
    return
icn_readset_ret:
    iconst_0
    putstatic rung36_jcon_mindfa/icn_failed B
    return
icn_readset_sret:
    return
.end method

.method public static icn_showdfa()V
    .limit stack 16
    .limit locals 346
    lconst_0
    lstore 0
    lconst_0
    lstore 2
    lconst_0
    lstore 4
    lconst_0
    lstore 6
    lconst_0
    lstore 8
    lconst_0
    lstore 10
    lconst_0
    lstore 12
    lconst_0
    lstore 14
    lconst_0
    lstore 16
    lconst_0
    lstore 18
    lconst_0
    lstore 20
    lconst_0
    lstore 22
    lconst_0
    lstore 24
    lconst_0
    lstore 26
    lconst_0
    lstore 28
    lconst_0
    lstore 30
    lconst_0
    lstore 32
    lconst_0
    lstore 34
    lconst_0
    lstore 36
    lconst_0
    lstore 38
    lconst_0
    lstore 40
    lconst_0
    lstore 42
    lconst_0
    lstore 44
    lconst_0
    lstore 46
    lconst_0
    lstore 48
    lconst_0
    lstore 50
    lconst_0
    lstore 52
    lconst_0
    lstore 54
    lconst_0
    lstore 56
    lconst_0
    lstore 58
    lconst_0
    lstore 60
    lconst_0
    lstore 62
    iconst_0
    istore 84
    iconst_0
    istore 85
    iconst_0
    istore 86
    iconst_0
    istore 87
    aconst_null
    astore 148
    aconst_null
    astore 149
    aconst_null
    astore 150
    aconst_null
    astore 151
    aconst_null
    astore 152
    aconst_null
    astore 153
    aconst_null
    astore 154
    aconst_null
    astore 155
    aconst_null
    astore 156
    aconst_null
    astore 157
    getstatic rung36_jcon_mindfa/icn_arg_str_0 Ljava/lang/String;
    putstatic rung36_jcon_mindfa/icn_pv_showdfa_msg Ljava/lang/String;
    getstatic rung36_jcon_mindfa/icn_arg_1 J
    putstatic rung36_jcon_mindfa/icn_pv_showdfa_D J
    goto icn_91_α
;  VAR
icn_58_α:
    getstatic rung36_jcon_mindfa/icn_pv_showdfa_D J
    goto icn_57_ret_store
icn_58_β:
    goto icn_57_ret_fail
icn_57_α:
    goto icn_58_α
icn_57_β:
    goto icn_showdfa_ret
icn_57_ret_fail:
    iconst_1
    putstatic rung36_jcon_mindfa/icn_failed B
    goto icn_showdfa_done
icn_57_ret_store:
    putstatic rung36_jcon_mindfa/icn_retval J
    iconst_0
    putstatic rung36_jcon_mindfa/icn_failed B
    goto icn_showdfa_ret
icn_62_α:
    goto icn_60_seq_rf_0
icn_62_β:
    goto icn_60_seq_rf_0
icn_61_gdrain:
    pop2
icn_61_pump:
    goto icn_62_β
icn_61_α:
    goto icn_62_α
icn_61_β:
    goto icn_60_seq_rf_0
icn_63_α:
    getstatic java/lang/System/out Ljava/io/PrintStream;
    ldc ""
    invokevirtual java/io/PrintStream/println(Ljava/lang/String;)V
    goto icn_59_bdrain
icn_63_β:
    goto icn_59_pump
    goto icn_60_α
icn_60_seq_rg_0:
    pop2
    goto icn_63_α
icn_60_seq_rf_0:
    goto icn_63_α
icn_60_α:
    goto icn_61_α
icn_60_β:
    goto icn_63_β
icn_66_α:
    goto icn_57_α
icn_66_β:
    goto icn_57_α
icn_65_α:
    goto icn_66_α
icn_65_β:
    goto icn_65_bang_chk
icn_65_bang_adv:
    putstatic rung36_jcon_mindfa/icn_65_bang_str Ljava/lang/String;
    iconst_0
    putstatic rung36_jcon_mindfa/icn_65_bang_pos I
icn_65_bang_chk:
    getstatic rung36_jcon_mindfa/icn_65_bang_str Ljava/lang/String;
    invokevirtual java/lang/String/length()I
    getstatic rung36_jcon_mindfa/icn_65_bang_pos I
    if_icmple icn_57_α
    getstatic rung36_jcon_mindfa/icn_65_bang_str Ljava/lang/String;
    getstatic rung36_jcon_mindfa/icn_65_bang_pos I
    getstatic rung36_jcon_mindfa/icn_65_bang_pos I
    iconst_1
    iadd
    invokevirtual java/lang/String/substring(II)Ljava/lang/String;
    getstatic rung36_jcon_mindfa/icn_65_bang_pos I
    iconst_1
    iadd
    putstatic rung36_jcon_mindfa/icn_65_bang_pos I
    goto icn_64_store
icn_64_α:
    goto icn_65_α
icn_64_β:
    goto icn_65_β
icn_64_store:
    putstatic rung36_jcon_mindfa/icn_pv_showdfa_q Ljava/lang/String;
    getstatic rung36_jcon_mindfa/icn_pv_showdfa_q Ljava/lang/String;
    goto icn_59_gdrain
icn_59_gdrain:
    pop
    goto icn_60_α
icn_59_bdrain:
    pop2
icn_59_pump:
    goto icn_64_β
icn_59_α:
    goto icn_64_α
icn_59_β:
    goto icn_57_α
;  STR
icn_68_α:
    ldc "\tDelta: "
    goto icn_67_waft_0
icn_68_β:
    goto icn_59_α
icn_67_α:
    goto icn_68_α
icn_67_β:
    goto icn_68_β
    goto icn_67_wentry
icn_67_waft_0:
    astore 148
    getstatic java/lang/System/out Ljava/io/PrintStream;
    aload 148
    invokevirtual java/io/PrintStream/print(Ljava/lang/String;)V
    getstatic java/lang/System/out Ljava/io/PrintStream;
    ldc ""
    invokevirtual java/io/PrintStream/println(Ljava/lang/String;)V
    aload 148
    goto icn_showdfa_s12_sdrain
icn_67_wentry:
    goto icn_68_α
icn_showdfa_s12_sdrain:
    pop
    goto icn_59_α
;  STR
icn_70_α:
    ldc "\tStart state is "
    goto icn_69_waft_0
icn_70_β:
    goto icn_67_α
icn_71_α:
    goto icn_67_α
icn_71_β:
    goto icn_67_α
icn_69_α:
    goto icn_70_α
icn_69_β:
    goto icn_70_β
    goto icn_69_wentry
icn_69_waft_0:
    astore 149
    getstatic java/lang/System/out Ljava/io/PrintStream;
    aload 149
    invokevirtual java/io/PrintStream/print(Ljava/lang/String;)V
    goto icn_71_α
icn_69_waft_1:
    lstore 8
    getstatic java/lang/System/out Ljava/io/PrintStream;
    lload 8
    invokevirtual java/io/PrintStream/print(J)V
    getstatic java/lang/System/out Ljava/io/PrintStream;
    ldc ""
    invokevirtual java/io/PrintStream/println(Ljava/lang/String;)V
    lload 8
    goto icn_showdfa_s11_sdrain
icn_69_wentry:
    goto icn_70_α
icn_showdfa_s11_sdrain:
    pop2
    goto icn_67_α
icn_73_α:
    goto icn_69_α
icn_73_β:
    goto icn_69_α
icn_72_arg1:
    putstatic rung36_jcon_mindfa/icn_arg_1 J
    goto icn_72_docall
;  STR
icn_74_α:
    ldc "F"
    goto icn_72_arg0
icn_74_β:
    goto icn_69_α
icn_72_arg0:
    putstatic rung36_jcon_mindfa/icn_arg_str_0 Ljava/lang/String;
    lconst_0
    putstatic rung36_jcon_mindfa/icn_arg_0 J
    goto icn_73_α
icn_72_α:
    goto icn_74_α
icn_72_β:
    goto icn_73_β
icn_72_docall:
    getstatic rung36_jcon_mindfa/icn_7_I J
    lstore 154
    getstatic rung36_jcon_mindfa/icn_7_bound J
    lstore 156
    getstatic rung36_jcon_mindfa/icn_7_e1cur J
    lstore 158
    getstatic rung36_jcon_mindfa/icn_7_e1val J
    lstore 160
    getstatic rung36_jcon_mindfa/icn_7_e2val J
    lstore 162
    getstatic rung36_jcon_mindfa/icn_pv_showdfa_D J
    lstore 164
    invokestatic rung36_jcon_mindfa/icn_writeset()V
    lload 154
    putstatic rung36_jcon_mindfa/icn_7_I J
    lload 156
    putstatic rung36_jcon_mindfa/icn_7_bound J
    lload 158
    putstatic rung36_jcon_mindfa/icn_7_e1cur J
    lload 160
    putstatic rung36_jcon_mindfa/icn_7_e1val J
    lload 162
    putstatic rung36_jcon_mindfa/icn_7_e2val J
    lload 164
    putstatic rung36_jcon_mindfa/icn_pv_showdfa_D J
    getstatic rung36_jcon_mindfa/icn_failed B
    ifne icn_72_after_call
    getstatic rung36_jcon_mindfa/icn_retval J
    goto icn_showdfa_s10_sdrain
icn_72_after_call:
    goto icn_69_α
icn_showdfa_s10_sdrain:
    pop2
    goto icn_69_α
icn_76_α:
    goto icn_72_α
icn_76_β:
    goto icn_72_α
icn_75_arg1:
    putstatic rung36_jcon_mindfa/icn_arg_1 J
    goto icn_75_docall
;  STR
icn_77_α:
    ldc "S"
    goto icn_75_arg0
icn_77_β:
    goto icn_72_α
icn_75_arg0:
    putstatic rung36_jcon_mindfa/icn_arg_str_0 Ljava/lang/String;
    lconst_0
    putstatic rung36_jcon_mindfa/icn_arg_0 J
    goto icn_76_α
icn_75_α:
    goto icn_77_α
icn_75_β:
    goto icn_76_β
icn_75_docall:
    getstatic rung36_jcon_mindfa/icn_7_I J
    lstore 154
    getstatic rung36_jcon_mindfa/icn_7_bound J
    lstore 156
    getstatic rung36_jcon_mindfa/icn_7_e1cur J
    lstore 158
    getstatic rung36_jcon_mindfa/icn_7_e1val J
    lstore 160
    getstatic rung36_jcon_mindfa/icn_7_e2val J
    lstore 162
    getstatic rung36_jcon_mindfa/icn_pv_showdfa_D J
    lstore 164
    invokestatic rung36_jcon_mindfa/icn_writeset()V
    lload 154
    putstatic rung36_jcon_mindfa/icn_7_I J
    lload 156
    putstatic rung36_jcon_mindfa/icn_7_bound J
    lload 158
    putstatic rung36_jcon_mindfa/icn_7_e1cur J
    lload 160
    putstatic rung36_jcon_mindfa/icn_7_e1val J
    lload 162
    putstatic rung36_jcon_mindfa/icn_7_e2val J
    lload 164
    putstatic rung36_jcon_mindfa/icn_pv_showdfa_D J
    getstatic rung36_jcon_mindfa/icn_failed B
    ifne icn_75_after_call
    getstatic rung36_jcon_mindfa/icn_retval J
    goto icn_showdfa_s9_sdrain
icn_75_after_call:
    goto icn_72_α
icn_showdfa_s9_sdrain:
    pop2
    goto icn_72_α
icn_79_α:
    goto icn_75_α
icn_79_β:
    goto icn_75_α
icn_78_arg1:
    putstatic rung36_jcon_mindfa/icn_arg_1 J
    goto icn_78_docall
;  STR
icn_80_α:
    ldc "Q"
    goto icn_78_arg0
icn_80_β:
    goto icn_75_α
icn_78_arg0:
    putstatic rung36_jcon_mindfa/icn_arg_str_0 Ljava/lang/String;
    lconst_0
    putstatic rung36_jcon_mindfa/icn_arg_0 J
    goto icn_79_α
icn_78_α:
    goto icn_80_α
icn_78_β:
    goto icn_79_β
icn_78_docall:
    getstatic rung36_jcon_mindfa/icn_7_I J
    lstore 154
    getstatic rung36_jcon_mindfa/icn_7_bound J
    lstore 156
    getstatic rung36_jcon_mindfa/icn_7_e1cur J
    lstore 158
    getstatic rung36_jcon_mindfa/icn_7_e1val J
    lstore 160
    getstatic rung36_jcon_mindfa/icn_7_e2val J
    lstore 162
    getstatic rung36_jcon_mindfa/icn_pv_showdfa_D J
    lstore 164
    invokestatic rung36_jcon_mindfa/icn_writeset()V
    lload 154
    putstatic rung36_jcon_mindfa/icn_7_I J
    lload 156
    putstatic rung36_jcon_mindfa/icn_7_bound J
    lload 158
    putstatic rung36_jcon_mindfa/icn_7_e1cur J
    lload 160
    putstatic rung36_jcon_mindfa/icn_7_e1val J
    lload 162
    putstatic rung36_jcon_mindfa/icn_7_e2val J
    lload 164
    putstatic rung36_jcon_mindfa/icn_pv_showdfa_D J
    getstatic rung36_jcon_mindfa/icn_failed B
    ifne icn_78_after_call
    getstatic rung36_jcon_mindfa/icn_retval J
    goto icn_showdfa_s8_sdrain
icn_78_after_call:
    goto icn_75_α
icn_showdfa_s8_sdrain:
    pop2
    goto icn_75_α
icn_81_α:
    getstatic java/lang/System/out Ljava/io/PrintStream;
    ldc ""
    invokevirtual java/io/PrintStream/println(Ljava/lang/String;)V
    goto icn_showdfa_s7_sdrain
icn_81_β:
    goto icn_78_α
icn_showdfa_s7_sdrain:
    pop2
    goto icn_78_α
;  STR
icn_83_α:
    ldc "where:"
    goto icn_82_waft_0
icn_83_β:
    goto icn_81_α
icn_82_α:
    goto icn_83_α
icn_82_β:
    goto icn_83_β
    goto icn_82_wentry
icn_82_waft_0:
    astore 150
    getstatic java/lang/System/out Ljava/io/PrintStream;
    aload 150
    invokevirtual java/io/PrintStream/print(Ljava/lang/String;)V
    getstatic java/lang/System/out Ljava/io/PrintStream;
    ldc ""
    invokevirtual java/io/PrintStream/println(Ljava/lang/String;)V
    aload 150
    goto icn_showdfa_s6_sdrain
icn_82_wentry:
    goto icn_83_α
icn_showdfa_s6_sdrain:
    pop
    goto icn_81_α
icn_84_α:
    getstatic java/lang/System/out Ljava/io/PrintStream;
    ldc ""
    invokevirtual java/io/PrintStream/println(Ljava/lang/String;)V
    goto icn_showdfa_s5_sdrain
icn_84_β:
    goto icn_82_α
icn_showdfa_s5_sdrain:
    pop2
    goto icn_82_α
;  STR
icn_86_α:
    ldc "\t(Q,S,delta,q0,F)"
    goto icn_85_waft_0
icn_86_β:
    goto icn_84_α
icn_85_α:
    goto icn_86_α
icn_85_β:
    goto icn_86_β
    goto icn_85_wentry
icn_85_waft_0:
    astore 151
    getstatic java/lang/System/out Ljava/io/PrintStream;
    aload 151
    invokevirtual java/io/PrintStream/print(Ljava/lang/String;)V
    getstatic java/lang/System/out Ljava/io/PrintStream;
    ldc ""
    invokevirtual java/io/PrintStream/println(Ljava/lang/String;)V
    aload 151
    goto icn_showdfa_s4_sdrain
icn_85_wentry:
    goto icn_86_α
icn_showdfa_s4_sdrain:
    pop
    goto icn_84_α
icn_87_α:
    getstatic java/lang/System/out Ljava/io/PrintStream;
    ldc ""
    invokevirtual java/io/PrintStream/println(Ljava/lang/String;)V
    goto icn_showdfa_s3_sdrain
icn_87_β:
    goto icn_85_α
icn_showdfa_s3_sdrain:
    pop2
    goto icn_85_α
;  VAR
icn_89_α:
    getstatic rung36_jcon_mindfa/icn_pv_showdfa_msg Ljava/lang/String;
    goto icn_88_waft_0
icn_89_β:
    goto icn_87_α
;  STR
icn_90_α:
    ldc " Deterministic Finite Automaton is:"
    goto icn_88_waft_1
icn_90_β:
    goto icn_87_α
icn_88_α:
    goto icn_89_α
icn_88_β:
    goto icn_89_β
    goto icn_88_wentry
icn_88_waft_0:
    astore 152
    getstatic java/lang/System/out Ljava/io/PrintStream;
    aload 152
    invokevirtual java/io/PrintStream/print(Ljava/lang/String;)V
    goto icn_90_α
icn_88_waft_1:
    astore 153
    getstatic java/lang/System/out Ljava/io/PrintStream;
    aload 153
    invokevirtual java/io/PrintStream/print(Ljava/lang/String;)V
    getstatic java/lang/System/out Ljava/io/PrintStream;
    ldc ""
    invokevirtual java/io/PrintStream/println(Ljava/lang/String;)V
    aload 153
    goto icn_showdfa_s2_sdrain
icn_88_wentry:
    goto icn_89_α
icn_showdfa_s2_sdrain:
    pop
    goto icn_87_α
icn_92_α:
    getstatic java/lang/System/out Ljava/io/PrintStream;
    ldc ""
    invokevirtual java/io/PrintStream/println(Ljava/lang/String;)V
    goto icn_91_bdrain
icn_92_β:
    goto icn_91_pump
;  INT
icn_94_α:
    ldc2_w 3
    goto icn_93_e2relay
icn_94_β:
    goto icn_93_e1b
;  INT
icn_95_α:
    ldc2_w 1
    goto icn_93_e1relay
icn_95_β:
    goto icn_88_α
icn_93_e1relay:
    putstatic rung36_jcon_mindfa/icn_93_e1val J
    goto icn_94_α
icn_93_e2relay:
    putstatic rung36_jcon_mindfa/icn_93_e2val J
    goto icn_93_init
icn_93_e1b:
    iconst_0
    putstatic rung36_jcon_mindfa/icn_93_e2seen I
    goto icn_95_β
icn_93_e2b:
    goto icn_94_β
icn_93_α:
    iconst_0
    putstatic rung36_jcon_mindfa/icn_93_e2seen I
    goto icn_95_α
icn_93_β:
    getstatic rung36_jcon_mindfa/icn_93_I J
    lconst_1
    ladd
    putstatic rung36_jcon_mindfa/icn_93_I J
    goto icn_93_code
icn_93_init:
    getstatic rung36_jcon_mindfa/icn_93_e2val J
    putstatic rung36_jcon_mindfa/icn_93_bound J
    getstatic rung36_jcon_mindfa/icn_93_e2seen I
    ifne icn_93_init_e2adv
    getstatic rung36_jcon_mindfa/icn_93_e1val J
    putstatic rung36_jcon_mindfa/icn_93_e1cur J
    getstatic rung36_jcon_mindfa/icn_93_e1cur J
    putstatic rung36_jcon_mindfa/icn_93_I J
    iconst_1
    putstatic rung36_jcon_mindfa/icn_93_e2seen I
    goto icn_93_code
icn_93_init_e2adv:
    getstatic rung36_jcon_mindfa/icn_93_e1cur J
    putstatic rung36_jcon_mindfa/icn_93_I J
    goto icn_93_code
icn_93_code:
    getstatic rung36_jcon_mindfa/icn_93_I J
    getstatic rung36_jcon_mindfa/icn_93_bound J
    lcmp
    ifgt icn_93_e2b
    getstatic rung36_jcon_mindfa/icn_93_I J
    goto icn_91_gdrain
icn_91_gdrain:
    pop2
    goto icn_92_α
icn_91_bdrain:
    pop2
icn_91_pump:
    goto icn_93_β
icn_91_α:
    goto icn_93_α
icn_91_β:
    goto icn_88_α
icn_showdfa_done:
    iconst_0
    putstatic rung36_jcon_mindfa/icn_suspended B
    iconst_0
    putstatic rung36_jcon_mindfa/icn_suspend_id I
    iconst_1
    putstatic rung36_jcon_mindfa/icn_failed B
    return
icn_showdfa_ret:
    iconst_0
    putstatic rung36_jcon_mindfa/icn_failed B
    return
icn_showdfa_sret:
    return
.end method

.method public static icn_writeset()V
    .limit stack 16
    .limit locals 363
    lconst_0
    lstore 0
    lconst_0
    lstore 2
    lconst_0
    lstore 4
    lconst_0
    lstore 6
    lconst_0
    lstore 8
    lconst_0
    lstore 10
    lconst_0
    lstore 12
    lconst_0
    lstore 14
    lconst_0
    lstore 16
    lconst_0
    lstore 18
    lconst_0
    lstore 20
    lconst_0
    lstore 22
    lconst_0
    lstore 24
    lconst_0
    lstore 26
    lconst_0
    lstore 28
    lconst_0
    lstore 30
    lconst_0
    lstore 32
    lconst_0
    lstore 34
    lconst_0
    lstore 36
    lconst_0
    lstore 38
    lconst_0
    lstore 40
    lconst_0
    lstore 42
    lconst_0
    lstore 44
    lconst_0
    lstore 46
    lconst_0
    lstore 48
    lconst_0
    lstore 50
    lconst_0
    lstore 52
    lconst_0
    lstore 54
    lconst_0
    lstore 56
    lconst_0
    lstore 58
    lconst_0
    lstore 60
    lconst_0
    lstore 62
    iconst_0
    istore 84
    iconst_0
    istore 85
    iconst_0
    istore 86
    iconst_0
    istore 87
    iconst_0
    istore 88
    iconst_0
    istore 89
    iconst_0
    istore 90
    iconst_0
    istore 91
    aconst_null
    astore 148
    aconst_null
    astore 149
    aconst_null
    astore 150
    aconst_null
    astore 151
    aconst_null
    astore 152
    aconst_null
    astore 153
    aconst_null
    astore 154
    aconst_null
    astore 155
    aconst_null
    astore 156
    getstatic rung36_jcon_mindfa/icn_arg_str_0 Ljava/lang/String;
    putstatic rung36_jcon_mindfa/icn_pv_writeset_msg Ljava/lang/String;
    getstatic rung36_jcon_mindfa/icn_arg_1 J
    putstatic rung36_jcon_mindfa/icn_pv_writeset_s J
    goto icn_113_α
icn_96_α:
    lconst_0
    putstatic rung36_jcon_mindfa/icn_retval J
    iconst_0
    putstatic rung36_jcon_mindfa/icn_failed B
    goto icn_writeset_ret
icn_96_β:
    goto icn_writeset_ret
;  STR
icn_98_α:
    ldc "\t"
    goto icn_97_waft_0
icn_98_β:
    goto icn_96_α
;  VAR
icn_99_α:
    getstatic rung36_jcon_mindfa/icn_pv_writeset_msg Ljava/lang/String;
    goto icn_97_waft_1
icn_99_β:
    goto icn_96_α
;  STR
icn_100_α:
    ldc " = {"
    goto icn_97_waft_2
icn_100_β:
    goto icn_96_α
;  VAR
icn_102_α:
    getstatic rung36_jcon_mindfa/icn_pv_writeset_tmp Ljava/lang/String;
    goto icn_101_sec_sr
icn_102_β:
    goto icn_96_α
;  INT
icn_103_α:
    ldc2_w 1
    goto icn_101_sec_lor
icn_103_β:
    goto icn_96_α
;  INT
icn_105_α:
    ldc2_w 1
    goto icn_104_neg
icn_105_β:
    goto icn_96_α
;  NEG
icn_104_α:
    goto icn_105_α
icn_104_β:
    goto icn_105_β
icn_104_neg:
    lneg
    goto icn_101_sec_hir
icn_101_sec_lor:
    l2i
    istore 84
    iload 84
    ifgt icn_101_sec_lop
    iload 84
    iflt icn_101_sec_lon
icn_101_sec_loz:
    goto icn_96_α
icn_101_sec_lop:
    iload 84
    iconst_1
    isub
    putstatic rung36_jcon_mindfa/icn_101_sec_lo I
    goto icn_104_α
icn_101_sec_lon:
    getstatic rung36_jcon_mindfa/icn_101_sec_s Ljava/lang/String;
    invokevirtual java/lang/String/length()I
    iload 84
    iadd
    putstatic rung36_jcon_mindfa/icn_101_sec_lo I
    goto icn_104_α
icn_101_sec_hir:
    l2i
    istore 85
    iload 85
    ifgt icn_101_sec_hip
    iload 85
    iflt icn_101_sec_hin
icn_101_sec_hiz:
    goto icn_96_α
icn_101_sec_hip:
    iload 85
    iconst_1
    isub
    putstatic rung36_jcon_mindfa/icn_101_sec_hi I
    goto icn_101_sec_cmp
icn_101_sec_hin:
    getstatic rung36_jcon_mindfa/icn_101_sec_s Ljava/lang/String;
    invokevirtual java/lang/String/length()I
    iload 85
    iadd
    putstatic rung36_jcon_mindfa/icn_101_sec_hi I
    goto icn_101_sec_cmp
icn_101_sec_cmp:
    getstatic rung36_jcon_mindfa/icn_101_sec_lo I
    iflt icn_96_α
    getstatic rung36_jcon_mindfa/icn_101_sec_hi I
    iflt icn_96_α
    getstatic rung36_jcon_mindfa/icn_101_sec_s Ljava/lang/String;
    invokevirtual java/lang/String/length()I
    getstatic rung36_jcon_mindfa/icn_101_sec_lo I
    if_icmplt icn_96_α
    getstatic rung36_jcon_mindfa/icn_101_sec_s Ljava/lang/String;
    invokevirtual java/lang/String/length()I
    istore 86
    getstatic rung36_jcon_mindfa/icn_101_sec_hi I
    iload 86
    if_icmple icn_101_sec_hiok
    iload 86
    putstatic rung36_jcon_mindfa/icn_101_sec_hi I
icn_101_sec_hiok:
    getstatic rung36_jcon_mindfa/icn_101_sec_s Ljava/lang/String;
    getstatic rung36_jcon_mindfa/icn_101_sec_lo I
    getstatic rung36_jcon_mindfa/icn_101_sec_hi I
    invokevirtual java/lang/String/substring(II)Ljava/lang/String;
    goto icn_97_waft_3
icn_101_α:
    goto icn_102_α
icn_101_sec_sr:
    putstatic rung36_jcon_mindfa/icn_101_sec_s Ljava/lang/String;
    goto icn_103_α
icn_101_β:
    goto icn_96_α
;  STR
icn_106_α:
    ldc "}"
    goto icn_97_waft_4
icn_106_β:
    goto icn_96_α
icn_97_α:
    goto icn_98_α
icn_97_β:
    goto icn_98_β
    goto icn_97_wentry
icn_97_waft_0:
    astore 148
    getstatic java/lang/System/out Ljava/io/PrintStream;
    aload 148
    invokevirtual java/io/PrintStream/print(Ljava/lang/String;)V
    goto icn_99_α
icn_97_waft_1:
    astore 149
    getstatic java/lang/System/out Ljava/io/PrintStream;
    aload 149
    invokevirtual java/io/PrintStream/print(Ljava/lang/String;)V
    goto icn_100_α
icn_97_waft_2:
    astore 150
    getstatic java/lang/System/out Ljava/io/PrintStream;
    aload 150
    invokevirtual java/io/PrintStream/print(Ljava/lang/String;)V
    goto icn_101_α
icn_97_waft_3:
    astore 151
    getstatic java/lang/System/out Ljava/io/PrintStream;
    aload 151
    invokevirtual java/io/PrintStream/print(Ljava/lang/String;)V
    goto icn_106_α
icn_97_waft_4:
    astore 152
    getstatic java/lang/System/out Ljava/io/PrintStream;
    aload 152
    invokevirtual java/io/PrintStream/print(Ljava/lang/String;)V
    getstatic java/lang/System/out Ljava/io/PrintStream;
    ldc ""
    invokevirtual java/io/PrintStream/println(Ljava/lang/String;)V
    aload 152
    goto icn_writeset_s3_sdrain
icn_97_wentry:
    goto icn_98_α
icn_writeset_s3_sdrain:
    pop
    goto icn_96_α
;  STR
icn_110_α:
    ldc ","
    goto icn_109_rrelay
icn_110_β:
    goto icn_109_lb
;  VAR
icn_112_α:
    getstatic rung36_jcon_mindfa/icn_pv_writeset_s J
    goto icn_111_bang_adv
icn_112_β:
    goto icn_97_α
icn_111_α:
    goto icn_112_α
icn_111_β:
    goto icn_111_bang_chk
icn_111_bang_adv:
    putstatic rung36_jcon_mindfa/icn_111_bang_str Ljava/lang/String;
    iconst_0
    putstatic rung36_jcon_mindfa/icn_111_bang_pos I
icn_111_bang_chk:
    getstatic rung36_jcon_mindfa/icn_111_bang_str Ljava/lang/String;
    invokevirtual java/lang/String/length()I
    getstatic rung36_jcon_mindfa/icn_111_bang_pos I
    if_icmple icn_97_α
    getstatic rung36_jcon_mindfa/icn_111_bang_str Ljava/lang/String;
    getstatic rung36_jcon_mindfa/icn_111_bang_pos I
    getstatic rung36_jcon_mindfa/icn_111_bang_pos I
    iconst_1
    iadd
    invokevirtual java/lang/String/substring(II)Ljava/lang/String;
    getstatic rung36_jcon_mindfa/icn_111_bang_pos I
    iconst_1
    iadd
    putstatic rung36_jcon_mindfa/icn_111_bang_pos I
    goto icn_109_lrelay
icn_109_lrelay:
    putstatic rung36_jcon_mindfa/icn_109_lc Ljava/lang/String;
    goto icn_109_lstore
icn_109_rrelay:
    putstatic rung36_jcon_mindfa/icn_109_rc Ljava/lang/String;
    goto icn_109_compute
icn_109_lb:
    goto icn_111_β
icn_109_α:
    iconst_0
    istore 87
    goto icn_111_α
icn_109_β:
    iconst_1
    istore 87
    goto icn_111_α
icn_109_lstore:
    iload 87
    ifeq icn_110_α
    goto icn_110_β
icn_109_compute:
    getstatic rung36_jcon_mindfa/icn_109_lc Ljava/lang/String;
    getstatic rung36_jcon_mindfa/icn_109_rc Ljava/lang/String;
    invokevirtual java/lang/String/concat(Ljava/lang/String;)Ljava/lang/String;
    goto icn_108_rhsok
icn_108_α:
    goto icn_109_α
icn_108_β:
    goto icn_109_β
icn_108_rhsok:
    putstatic rung36_jcon_mindfa/icn_108_augtemp_s Ljava/lang/String;
    getstatic rung36_jcon_mindfa/icn_pv_writeset_tmp Ljava/lang/String;
    getstatic rung36_jcon_mindfa/icn_108_augtemp_s Ljava/lang/String;
    invokevirtual java/lang/String/concat(Ljava/lang/String;)Ljava/lang/String;
    dup
    putstatic rung36_jcon_mindfa/icn_pv_writeset_tmp Ljava/lang/String;
    goto icn_107_gdrain
icn_107_gdrain:
    pop
icn_107_pump:
    goto icn_108_β
icn_107_α:
    goto icn_108_α
icn_107_β:
    goto icn_97_α
;  STR
icn_114_α:
    ldc ""
    goto icn_113_store
icn_114_β:
    goto icn_107_α
icn_113_α:
    goto icn_114_α
icn_113_β:
    goto icn_114_β
icn_113_store:
    putstatic rung36_jcon_mindfa/icn_pv_writeset_tmp Ljava/lang/String;
    getstatic rung36_jcon_mindfa/icn_pv_writeset_tmp Ljava/lang/String;
    goto icn_writeset_s1_sdrain
icn_writeset_s1_sdrain:
    pop
    goto icn_107_α
icn_writeset_done:
    iconst_0
    putstatic rung36_jcon_mindfa/icn_suspended B
    iconst_0
    putstatic rung36_jcon_mindfa/icn_suspend_id I
    iconst_1
    putstatic rung36_jcon_mindfa/icn_failed B
    return
icn_writeset_ret:
    iconst_0
    putstatic rung36_jcon_mindfa/icn_failed B
    return
icn_writeset_sret:
    return
.end method

.method public static icn_minimize()V
    .limit stack 16
    .limit locals 456
    lconst_0
    lstore 0
    lconst_0
    lstore 2
    lconst_0
    lstore 4
    lconst_0
    lstore 6
    lconst_0
    lstore 8
    lconst_0
    lstore 10
    lconst_0
    lstore 12
    lconst_0
    lstore 14
    lconst_0
    lstore 16
    lconst_0
    lstore 18
    lconst_0
    lstore 20
    lconst_0
    lstore 22
    lconst_0
    lstore 24
    lconst_0
    lstore 26
    lconst_0
    lstore 28
    lconst_0
    lstore 30
    lconst_0
    lstore 32
    lconst_0
    lstore 34
    lconst_0
    lstore 36
    lconst_0
    lstore 38
    lconst_0
    lstore 40
    lconst_0
    lstore 42
    lconst_0
    lstore 44
    lconst_0
    lstore 46
    lconst_0
    lstore 48
    lconst_0
    lstore 50
    lconst_0
    lstore 52
    lconst_0
    lstore 54
    lconst_0
    lstore 56
    lconst_0
    lstore 58
    lconst_0
    lstore 60
    lconst_0
    lstore 62
    iconst_0
    istore 84
    iconst_0
    istore 85
    iconst_0
    istore 86
    iconst_0
    istore 87
    iconst_0
    istore 88
    iconst_0
    istore 89
    iconst_0
    istore 90
    iconst_0
    istore 91
    iconst_0
    istore 92
    iconst_0
    istore 93
    iconst_0
    istore 94
    iconst_0
    istore 95
    iconst_0
    istore 96
    iconst_0
    istore 97
    iconst_0
    istore 98
    iconst_0
    istore 99
    aconst_null
    astore 148
    aconst_null
    astore 149
    aconst_null
    astore 150
    aconst_null
    astore 151
    aconst_null
    astore 152
    aconst_null
    astore 153
    getstatic rung36_jcon_mindfa/icn_arg_str_0 Ljava/lang/String;
    putstatic rung36_jcon_mindfa/icn_pv_minimize_D Ljava/lang/String;
    goto icn_197_α
;  VAR
icn_117_α:
    getstatic rung36_jcon_mindfa/icn_pv_minimize_distab Ljava/util/HashMap;
    goto icn_116_arg1
icn_117_β:
    goto icn_115_ret_fail
icn_116_arg1:
    putstatic rung36_jcon_mindfa/icn_arg_1 J
    goto icn_116_docall
;  VAR
icn_118_α:
    getstatic rung36_jcon_mindfa/icn_pv_minimize_D J
    goto icn_116_arg0
icn_118_β:
    goto icn_115_ret_fail
icn_116_arg0:
    putstatic rung36_jcon_mindfa/icn_arg_0 J
    goto icn_117_α
icn_116_α:
    goto icn_118_α
icn_116_β:
    goto icn_117_β
icn_116_docall:
    getstatic rung36_jcon_mindfa/icn_7_I J
    lstore 152
    getstatic rung36_jcon_mindfa/icn_7_bound J
    lstore 154
    getstatic rung36_jcon_mindfa/icn_7_e1cur J
    lstore 156
    getstatic rung36_jcon_mindfa/icn_7_e1val J
    lstore 158
    getstatic rung36_jcon_mindfa/icn_7_e2val J
    lstore 160
    getstatic rung36_jcon_mindfa/icn_93_I J
    lstore 162
    getstatic rung36_jcon_mindfa/icn_93_bound J
    lstore 164
    getstatic rung36_jcon_mindfa/icn_93_e1cur J
    lstore 166
    getstatic rung36_jcon_mindfa/icn_93_e1val J
    lstore 168
    getstatic rung36_jcon_mindfa/icn_93_e2val J
    lstore 170
    getstatic rung36_jcon_mindfa/icn_pv_minimize_D J
    lstore 172
    invokestatic rung36_jcon_mindfa/icn_makemdfa()V
    lload 152
    putstatic rung36_jcon_mindfa/icn_7_I J
    lload 154
    putstatic rung36_jcon_mindfa/icn_7_bound J
    lload 156
    putstatic rung36_jcon_mindfa/icn_7_e1cur J
    lload 158
    putstatic rung36_jcon_mindfa/icn_7_e1val J
    lload 160
    putstatic rung36_jcon_mindfa/icn_7_e2val J
    lload 162
    putstatic rung36_jcon_mindfa/icn_93_I J
    lload 164
    putstatic rung36_jcon_mindfa/icn_93_bound J
    lload 166
    putstatic rung36_jcon_mindfa/icn_93_e1cur J
    lload 168
    putstatic rung36_jcon_mindfa/icn_93_e1val J
    lload 170
    putstatic rung36_jcon_mindfa/icn_93_e2val J
    lload 172
    putstatic rung36_jcon_mindfa/icn_pv_minimize_D J
    getstatic rung36_jcon_mindfa/icn_failed B
    ifne icn_116_after_call
    getstatic rung36_jcon_mindfa/icn_retval J
    goto icn_115_ret_store
icn_116_after_call:
    goto icn_115_ret_fail
icn_115_α:
    goto icn_116_α
icn_115_β:
    goto icn_minimize_ret
icn_115_ret_fail:
    iconst_1
    putstatic rung36_jcon_mindfa/icn_failed B
    goto icn_minimize_done
icn_115_ret_store:
    putstatic rung36_jcon_mindfa/icn_retval J
    iconst_0
    putstatic rung36_jcon_mindfa/icn_failed B
    goto icn_minimize_ret
;  STR
icn_123_α:
    ldc "X"
    goto icn_122_tsa_vr
icn_123_β:
    goto icn_121_seq_rf_0
icn_124_α:
    goto icn_121_seq_rf_0
icn_124_β:
    goto icn_121_seq_rf_0
icn_122_α:
    goto icn_123_α
icn_122_β:
    goto icn_121_seq_rf_0
icn_122_tsa_vr:
    dup
    putstatic rung36_jcon_mindfa/icn_122_tsa_vl Ljava/lang/String;
    goto icn_124_α
icn_122_tsa_kr:
    invokestatic java/lang/Long/toString(J)Ljava/lang/String;
    putstatic rung36_jcon_mindfa/icn_122_tsa_ks Ljava/lang/String;
    goto icn_122_tsa_put
icn_122_tsa_put:
    getstatic rung36_jcon_mindfa/icn_pv_minimize_distab Ljava/util/HashMap;
    getstatic rung36_jcon_mindfa/icn_122_tsa_ks Ljava/lang/String;
    getstatic rung36_jcon_mindfa/icn_122_tsa_vl Ljava/lang/String;
    invokevirtual java/util/HashMap/put(Ljava/lang/Object;Ljava/lang/Object;)Ljava/lang/Object;
    pop
    getstatic rung36_jcon_mindfa/icn_122_tsa_vl Ljava/lang/String;
    goto icn_121_seq_rg_0
;  VAR
icn_127_α:
    getstatic rung36_jcon_mindfa/icn_pv_minimize_dlists Ljava/util/HashMap;
    goto icn_126_ts_tr
icn_127_β:
    goto icn_119_pump
icn_128_α:
    goto icn_119_pump
icn_128_β:
    goto icn_119_pump
icn_126_α:
    goto icn_127_α
icn_126_β:
    goto icn_128_β
icn_126_ts_tr:
    putstatic rung36_jcon_mindfa/icn_126_ts_tbl Ljava/util/HashMap;
    goto icn_128_α
icn_126_ts_kr:
    dup2
    putstatic rung36_jcon_mindfa/icn_126_ts_kval J
    invokestatic java/lang/Long/toString(J)Ljava/lang/String;
    putstatic rung36_jcon_mindfa/icn_126_ts_key Ljava/lang/String;
    getstatic rung36_jcon_mindfa/icn_126_ts_tbl Ljava/util/HashMap;
    getstatic rung36_jcon_mindfa/icn_126_ts_key Ljava/lang/String;
    invokevirtual java/util/HashMap/get(Ljava/lang/Object;)Ljava/lang/Object;
    dup
    ifnonnull icn_126_ts_got
    pop
    getstatic rung36_jcon_mindfa/icn_pv_minimize_dlists_dflt Ljava/lang/Object;
    checkcast java/lang/Long
    invokevirtual java/lang/Long/longValue()J
    goto icn_125_arg0
icn_126_ts_got:
    checkcast java/lang/Long
    invokevirtual java/lang/Long/longValue()J
    goto icn_125_arg0
icn_125_arg0:
    putstatic rung36_jcon_mindfa/icn_arg_0 J
    goto icn_125_docall
icn_125_α:
    goto icn_126_α
icn_125_β:
    goto icn_126_β
icn_125_docall:
    getstatic rung36_jcon_mindfa/icn_7_I J
    lstore 152
    getstatic rung36_jcon_mindfa/icn_7_bound J
    lstore 154
    getstatic rung36_jcon_mindfa/icn_7_e1cur J
    lstore 156
    getstatic rung36_jcon_mindfa/icn_7_e1val J
    lstore 158
    getstatic rung36_jcon_mindfa/icn_7_e2val J
    lstore 160
    getstatic rung36_jcon_mindfa/icn_93_I J
    lstore 162
    getstatic rung36_jcon_mindfa/icn_93_bound J
    lstore 164
    getstatic rung36_jcon_mindfa/icn_93_e1cur J
    lstore 166
    getstatic rung36_jcon_mindfa/icn_93_e1val J
    lstore 168
    getstatic rung36_jcon_mindfa/icn_93_e2val J
    lstore 170
    getstatic rung36_jcon_mindfa/icn_pv_minimize_D J
    lstore 172
    getstatic rung36_jcon_mindfa/icn_126_ts_kval J
    lstore 174
    invokestatic rung36_jcon_mindfa/icn_marklists()V
    lload 152
    putstatic rung36_jcon_mindfa/icn_7_I J
    lload 154
    putstatic rung36_jcon_mindfa/icn_7_bound J
    lload 156
    putstatic rung36_jcon_mindfa/icn_7_e1cur J
    lload 158
    putstatic rung36_jcon_mindfa/icn_7_e1val J
    lload 160
    putstatic rung36_jcon_mindfa/icn_7_e2val J
    lload 162
    putstatic rung36_jcon_mindfa/icn_93_I J
    lload 164
    putstatic rung36_jcon_mindfa/icn_93_bound J
    lload 166
    putstatic rung36_jcon_mindfa/icn_93_e1cur J
    lload 168
    putstatic rung36_jcon_mindfa/icn_93_e1val J
    lload 170
    putstatic rung36_jcon_mindfa/icn_93_e2val J
    lload 172
    putstatic rung36_jcon_mindfa/icn_pv_minimize_D J
    lload 174
    putstatic rung36_jcon_mindfa/icn_126_ts_kval J
    getstatic rung36_jcon_mindfa/icn_failed B
    ifne icn_125_after_call
    getstatic rung36_jcon_mindfa/icn_retval J
    goto icn_119_bdrain
icn_125_after_call:
    goto icn_119_pump
    goto icn_121_α
icn_121_seq_rg_0:
    pop
    goto icn_125_α
icn_121_seq_rf_0:
    goto icn_125_α
icn_121_α:
    goto icn_122_α
icn_121_β:
    goto icn_125_β
icn_133_α:
    goto icn_131_seq_rf_0
icn_133_β:
    goto icn_131_seq_rf_0
icn_132_α:
    goto icn_133_α
icn_132_β:
    goto icn_133_β
icn_132_store:
    putstatic rung36_jcon_mindfa/icn_pv_minimize_cs J
    getstatic rung36_jcon_mindfa/icn_pv_minimize_cs J
    goto icn_131_seq_rg_0
icn_135_α:
    goto icn_129_pump
icn_135_β:
    goto icn_129_pump
;  VAR
icn_137_α:
    getstatic rung36_jcon_mindfa/icn_pv_minimize_cs J
    goto icn_136_lrelay
icn_137_β:
    goto icn_134_else
icn_138_α:
    goto icn_134_else
icn_138_β:
    goto icn_134_else
;  STRRELOP
icn_136_α:
    goto icn_137_α
icn_136_β:
    goto icn_137_β
icn_136_lrelay:
    astore 84
    goto icn_136_lstore
icn_136_lstore:
    goto icn_138_α
icn_136_rrelay:
    astore 85
    goto icn_136_chk
icn_136_chk:
    aload 84
    aload 85
    invokevirtual java/lang/String/compareTo(Ljava/lang/String;)I
    ifne icn_138_β
    lconst_0
    goto icn_134_then
icn_134_then:
    pop2
    goto icn_135_α
icn_134_else:
    goto icn_131_seq_rf_1
icn_134_α:
    goto icn_136_α
icn_134_β:
    goto icn_136_β
icn_140_α:
    new java/util/ArrayList
    dup
    invokespecial java/util/ArrayList/<init>()V
    putstatic rung36_jcon_mindfa/icn_140_mklist Ljava/util/ArrayList;
    getstatic rung36_jcon_mindfa/icn_140_mklist Ljava/util/ArrayList;
    goto icn_139_store
icn_140_β:
    goto icn_131_seq_rf_2
icn_139_α:
    goto icn_140_α
icn_139_β:
    goto icn_140_β
icn_139_store:
    pop
    aconst_null
    goto icn_131_seq_rg_2
;  VAR
icn_143_α:
    getstatic rung36_jcon_mindfa/icn_pv_minimize_dlists Ljava/util/HashMap;
    goto icn_142_ts_tr
icn_143_β:
    goto icn_129_pump
;  VAR
icn_144_α:
    getstatic rung36_jcon_mindfa/icn_pv_minimize_cs J
    goto icn_142_ts_kr
icn_144_β:
    goto icn_129_pump
icn_142_α:
    goto icn_143_α
icn_142_β:
    goto icn_144_β
icn_142_ts_tr:
    putstatic rung36_jcon_mindfa/icn_142_ts_tbl Ljava/util/HashMap;
    goto icn_144_α
icn_142_ts_kr:
    dup2
    putstatic rung36_jcon_mindfa/icn_142_ts_kval J
    invokestatic java/lang/Long/toString(J)Ljava/lang/String;
    putstatic rung36_jcon_mindfa/icn_142_ts_key Ljava/lang/String;
    getstatic rung36_jcon_mindfa/icn_142_ts_tbl Ljava/util/HashMap;
    getstatic rung36_jcon_mindfa/icn_142_ts_key Ljava/lang/String;
    invokevirtual java/util/HashMap/get(Ljava/lang/Object;)Ljava/lang/Object;
    dup
    ifnonnull icn_142_ts_got
    pop
    getstatic rung36_jcon_mindfa/icn_pv_minimize_dlists_dflt Ljava/lang/Object;
    checkcast java/lang/Long
    invokevirtual java/lang/Long/longValue()J
    goto icn_141_lr
icn_142_ts_got:
    checkcast java/lang/Long
    invokevirtual java/lang/Long/longValue()J
    goto icn_141_lr
icn_145_α:
    goto icn_129_pump
icn_145_β:
    goto icn_129_pump
icn_141_α:
    goto icn_142_α
icn_141_β:
    goto icn_129_pump
icn_141_lr:
    putstatic rung36_jcon_mindfa/icn_141_pushlist Ljava/util/ArrayList;
    goto icn_145_α
icn_141_vr:
    invokestatic java/lang/Long/valueOf(J)Ljava/lang/Long;
    putstatic rung36_jcon_mindfa/icn_141_pushval Ljava/lang/Object;
    getstatic rung36_jcon_mindfa/icn_141_pushlist Ljava/util/ArrayList;
    getstatic rung36_jcon_mindfa/icn_141_pushval Ljava/lang/Object;
    invokevirtual java/util/ArrayList/add(Ljava/lang/Object;)Z
    pop
    getstatic rung36_jcon_mindfa/icn_141_pushlist Ljava/util/ArrayList;
    goto icn_129_bdrain
    goto icn_131_α
icn_131_seq_rg_0:
    pop2
    goto icn_134_α
icn_131_seq_rg_1:
    pop2
    goto icn_139_α
icn_131_seq_rg_2:
    pop2
    goto icn_141_α
icn_131_seq_rf_0:
    goto icn_134_α
icn_131_seq_rf_1:
    goto icn_139_α
icn_131_seq_rf_2:
    goto icn_141_α
icn_131_α:
    goto icn_132_α
icn_131_β:
    goto icn_141_β
;  VAR
icn_149_α:
    getstatic rung36_jcon_mindfa/icn_pv_minimize_a Ljava/lang/String;
    goto icn_148_rrelay
icn_149_β:
    goto icn_148_lb
;  STR
icn_151_α:
    ldc ":"
    goto icn_150_rrelay
icn_151_β:
    goto icn_150_lb
;  VAR
icn_152_α:
    getstatic rung36_jcon_mindfa/icn_pv_minimize_p Ljava/lang/String;
    goto icn_150_lrelay
icn_152_β:
    goto icn_130_else
icn_150_lrelay:
    putstatic rung36_jcon_mindfa/icn_150_lc Ljava/lang/String;
    goto icn_150_lstore
icn_150_rrelay:
    putstatic rung36_jcon_mindfa/icn_150_rc Ljava/lang/String;
    goto icn_150_compute
icn_150_lb:
    goto icn_152_β
icn_150_α:
    iconst_0
    istore 87
    goto icn_152_α
icn_150_β:
    iconst_1
    istore 87
    goto icn_152_α
icn_150_lstore:
    iload 87
    ifeq icn_151_α
    goto icn_151_β
icn_150_compute:
    getstatic rung36_jcon_mindfa/icn_150_lc Ljava/lang/String;
    getstatic rung36_jcon_mindfa/icn_150_rc Ljava/lang/String;
    invokevirtual java/lang/String/concat(Ljava/lang/String;)Ljava/lang/String;
    goto icn_148_lrelay
icn_148_lrelay:
    putstatic rung36_jcon_mindfa/icn_148_lc Ljava/lang/String;
    goto icn_148_lstore
icn_148_rrelay:
    putstatic rung36_jcon_mindfa/icn_148_rc Ljava/lang/String;
    goto icn_148_compute
icn_148_lb:
    goto icn_150_β
icn_148_α:
    iconst_0
    istore 86
    goto icn_150_α
icn_148_β:
    iconst_1
    istore 86
    goto icn_150_α
icn_148_lstore:
    iload 86
    ifeq icn_149_α
    goto icn_149_β
icn_148_compute:
    getstatic rung36_jcon_mindfa/icn_148_lc Ljava/lang/String;
    getstatic rung36_jcon_mindfa/icn_148_rc Ljava/lang/String;
    invokevirtual java/lang/String/concat(Ljava/lang/String;)Ljava/lang/String;
    goto icn_147_sub_irelay
icn_153_α:
    goto icn_130_else
icn_153_β:
    goto icn_130_else
icn_147_sub_srelay:
    putstatic rung36_jcon_mindfa/icn_147_sub_s Ljava/lang/String;
    goto icn_148_α
icn_147_sub_irelay:
    l2i
    istore 88
    iload 88
    ifgt icn_147_sub_pos
    iload 88
    iflt icn_147_sub_neg
icn_147_sub_z:
    goto icn_130_else
icn_147_sub_pos:
    iload 88
    iconst_1
    isub
    putstatic rung36_jcon_mindfa/icn_147_sub_i I
    goto icn_147_sub_check
icn_147_sub_neg:
    getstatic rung36_jcon_mindfa/icn_147_sub_s Ljava/lang/String;
    invokevirtual java/lang/String/length()I
    iload 88
    iadd
    putstatic rung36_jcon_mindfa/icn_147_sub_i I
    goto icn_147_sub_check
icn_147_sub_check:
    getstatic rung36_jcon_mindfa/icn_147_sub_i I
    iflt icn_130_else
    getstatic rung36_jcon_mindfa/icn_147_sub_s Ljava/lang/String;
    invokevirtual java/lang/String/length()I
    getstatic rung36_jcon_mindfa/icn_147_sub_i I
    if_icmple icn_130_else
    getstatic rung36_jcon_mindfa/icn_147_sub_s Ljava/lang/String;
    getstatic rung36_jcon_mindfa/icn_147_sub_i I
    getstatic rung36_jcon_mindfa/icn_147_sub_i I
    iconst_1
    iadd
    invokevirtual java/lang/String/substring(II)Ljava/lang/String;
    goto icn_146_lrelay
icn_147_α:
    goto icn_153_α
icn_147_β:
    goto icn_148_β
;  VAR
icn_156_α:
    getstatic rung36_jcon_mindfa/icn_pv_minimize_a Ljava/lang/String;
    goto icn_155_rrelay
icn_156_β:
    goto icn_155_lb
;  STR
icn_158_α:
    ldc ":"
    goto icn_157_rrelay
icn_158_β:
    goto icn_157_lb
;  VAR
icn_159_α:
    getstatic rung36_jcon_mindfa/icn_gvar_q Ljava/lang/String;
    goto icn_157_lrelay
icn_159_β:
    goto icn_130_else
icn_157_lrelay:
    putstatic rung36_jcon_mindfa/icn_157_lc Ljava/lang/String;
    goto icn_157_lstore
icn_157_rrelay:
    putstatic rung36_jcon_mindfa/icn_157_rc Ljava/lang/String;
    goto icn_157_compute
icn_157_lb:
    goto icn_159_β
icn_157_α:
    iconst_0
    istore 90
    goto icn_159_α
icn_157_β:
    iconst_1
    istore 90
    goto icn_159_α
icn_157_lstore:
    iload 90
    ifeq icn_158_α
    goto icn_158_β
icn_157_compute:
    getstatic rung36_jcon_mindfa/icn_157_lc Ljava/lang/String;
    getstatic rung36_jcon_mindfa/icn_157_rc Ljava/lang/String;
    invokevirtual java/lang/String/concat(Ljava/lang/String;)Ljava/lang/String;
    goto icn_155_lrelay
icn_155_lrelay:
    putstatic rung36_jcon_mindfa/icn_155_lc Ljava/lang/String;
    goto icn_155_lstore
icn_155_rrelay:
    putstatic rung36_jcon_mindfa/icn_155_rc Ljava/lang/String;
    goto icn_155_compute
icn_155_lb:
    goto icn_157_β
icn_155_α:
    iconst_0
    istore 89
    goto icn_157_α
icn_155_β:
    iconst_1
    istore 89
    goto icn_157_α
icn_155_lstore:
    iload 89
    ifeq icn_156_α
    goto icn_156_β
icn_155_compute:
    getstatic rung36_jcon_mindfa/icn_155_lc Ljava/lang/String;
    getstatic rung36_jcon_mindfa/icn_155_rc Ljava/lang/String;
    invokevirtual java/lang/String/concat(Ljava/lang/String;)Ljava/lang/String;
    goto icn_154_sub_irelay
icn_160_α:
    goto icn_130_else
icn_160_β:
    goto icn_130_else
icn_154_sub_srelay:
    putstatic rung36_jcon_mindfa/icn_154_sub_s Ljava/lang/String;
    goto icn_155_α
icn_154_sub_irelay:
    l2i
    istore 91
    iload 91
    ifgt icn_154_sub_pos
    iload 91
    iflt icn_154_sub_neg
icn_154_sub_z:
    goto icn_130_else
icn_154_sub_pos:
    iload 91
    iconst_1
    isub
    putstatic rung36_jcon_mindfa/icn_154_sub_i I
    goto icn_154_sub_check
icn_154_sub_neg:
    getstatic rung36_jcon_mindfa/icn_154_sub_s Ljava/lang/String;
    invokevirtual java/lang/String/length()I
    iload 91
    iadd
    putstatic rung36_jcon_mindfa/icn_154_sub_i I
    goto icn_154_sub_check
icn_154_sub_check:
    getstatic rung36_jcon_mindfa/icn_154_sub_i I
    iflt icn_130_else
    getstatic rung36_jcon_mindfa/icn_154_sub_s Ljava/lang/String;
    invokevirtual java/lang/String/length()I
    getstatic rung36_jcon_mindfa/icn_154_sub_i I
    if_icmple icn_130_else
    getstatic rung36_jcon_mindfa/icn_154_sub_s Ljava/lang/String;
    getstatic rung36_jcon_mindfa/icn_154_sub_i I
    getstatic rung36_jcon_mindfa/icn_154_sub_i I
    iconst_1
    iadd
    invokevirtual java/lang/String/substring(II)Ljava/lang/String;
    goto icn_146_rrelay
icn_154_α:
    goto icn_160_α
icn_154_β:
    goto icn_155_β
;  STRRELOP
icn_146_α:
    goto icn_147_α
icn_146_β:
    goto icn_147_β
icn_146_lrelay:
    astore 92
    goto icn_146_lstore
icn_146_lstore:
    goto icn_154_α
icn_146_rrelay:
    astore 93
    goto icn_146_chk
icn_146_chk:
    aload 92
    aload 93
    invokevirtual java/lang/String/compareTo(Ljava/lang/String;)I
    ifeq icn_154_β
    lconst_0
    goto icn_130_then
icn_130_then:
    pop2
    goto icn_131_α
icn_130_else:
    goto icn_129_pump
icn_130_α:
    goto icn_146_α
icn_130_β:
    goto icn_146_β
icn_163_α:
    goto icn_119_pump
icn_163_β:
    goto icn_119_pump
icn_162_α:
    goto icn_163_α
icn_162_β:
    goto icn_162_bang_chk
icn_162_bang_adv:
    putstatic rung36_jcon_mindfa/icn_162_bang_str Ljava/lang/String;
    iconst_0
    putstatic rung36_jcon_mindfa/icn_162_bang_pos I
icn_162_bang_chk:
    getstatic rung36_jcon_mindfa/icn_162_bang_str Ljava/lang/String;
    invokevirtual java/lang/String/length()I
    getstatic rung36_jcon_mindfa/icn_162_bang_pos I
    if_icmple icn_119_pump
    getstatic rung36_jcon_mindfa/icn_162_bang_str Ljava/lang/String;
    getstatic rung36_jcon_mindfa/icn_162_bang_pos I
    getstatic rung36_jcon_mindfa/icn_162_bang_pos I
    iconst_1
    iadd
    invokevirtual java/lang/String/substring(II)Ljava/lang/String;
    getstatic rung36_jcon_mindfa/icn_162_bang_pos I
    iconst_1
    iadd
    putstatic rung36_jcon_mindfa/icn_162_bang_pos I
    goto icn_161_store
icn_161_α:
    goto icn_162_α
icn_161_β:
    goto icn_162_β
icn_161_store:
    putstatic rung36_jcon_mindfa/icn_pv_minimize_a Ljava/lang/String;
    getstatic rung36_jcon_mindfa/icn_pv_minimize_a Ljava/lang/String;
    goto icn_129_gdrain
icn_129_gdrain:
    pop
    goto icn_130_α
icn_129_bdrain:
    pop2
icn_129_pump:
    goto icn_161_β
icn_129_α:
    goto icn_161_α
icn_129_β:
    goto icn_119_pump
;  VAR
icn_166_α:
    getstatic rung36_jcon_mindfa/icn_pv_minimize_distab Ljava/util/HashMap;
    goto icn_165_ts_tr
icn_166_β:
    goto icn_120_else
icn_167_α:
    goto icn_120_else
icn_167_β:
    goto icn_120_else
icn_165_α:
    goto icn_166_α
icn_165_β:
    goto icn_167_β
icn_165_ts_tr:
    putstatic rung36_jcon_mindfa/icn_165_ts_tbl Ljava/util/HashMap;
    goto icn_167_α
icn_165_ts_kr:
    dup2
    putstatic rung36_jcon_mindfa/icn_165_ts_kval J
    invokestatic java/lang/Long/toString(J)Ljava/lang/String;
    putstatic rung36_jcon_mindfa/icn_165_ts_key Ljava/lang/String;
    getstatic rung36_jcon_mindfa/icn_165_ts_tbl Ljava/util/HashMap;
    getstatic rung36_jcon_mindfa/icn_165_ts_key Ljava/lang/String;
    invokevirtual java/util/HashMap/get(Ljava/lang/Object;)Ljava/lang/Object;
    dup
    ifnonnull icn_165_ts_got
    pop
    getstatic rung36_jcon_mindfa/icn_pv_minimize_distab_dflt Ljava/lang/Object;
    checkcast java/lang/Long
    invokevirtual java/lang/Long/longValue()J
    goto icn_120_then
icn_165_ts_got:
    checkcast java/lang/Long
    invokevirtual java/lang/Long/longValue()J
    goto icn_120_then
;  NONNULL
icn_164_α:
    goto icn_165_α
icn_164_β:
    goto icn_165_β
icn_120_then:
    pop2
    goto icn_121_α
icn_120_else:
    goto icn_129_α
icn_120_α:
    goto icn_164_α
icn_120_β:
    goto icn_164_β
;  VAR
icn_173_α:
    getstatic rung36_jcon_mindfa/icn_pv_minimize_QF J
    goto icn_172_bang_adv
icn_173_β:
    goto icn_115_α
icn_172_α:
    goto icn_173_α
icn_172_β:
    goto icn_172_bang_chk
icn_172_bang_adv:
    putstatic rung36_jcon_mindfa/icn_172_bang_str Ljava/lang/String;
    iconst_0
    putstatic rung36_jcon_mindfa/icn_172_bang_pos I
icn_172_bang_chk:
    getstatic rung36_jcon_mindfa/icn_172_bang_str Ljava/lang/String;
    invokevirtual java/lang/String/length()I
    getstatic rung36_jcon_mindfa/icn_172_bang_pos I
    if_icmple icn_115_α
    getstatic rung36_jcon_mindfa/icn_172_bang_str Ljava/lang/String;
    getstatic rung36_jcon_mindfa/icn_172_bang_pos I
    getstatic rung36_jcon_mindfa/icn_172_bang_pos I
    iconst_1
    iadd
    invokevirtual java/lang/String/substring(II)Ljava/lang/String;
    getstatic rung36_jcon_mindfa/icn_172_bang_pos I
    iconst_1
    iadd
    putstatic rung36_jcon_mindfa/icn_172_bang_pos I
    goto icn_171_store
icn_171_α:
    goto icn_172_α
icn_171_β:
    goto icn_172_β
icn_171_store:
    pop
    aconst_null
    goto icn_170_store
icn_170_α:
    goto icn_171_α
icn_170_β:
    goto icn_171_β
icn_170_store:
    putstatic rung36_jcon_mindfa/icn_pv_minimize_p Ljava/lang/String;
    getstatic rung36_jcon_mindfa/icn_pv_minimize_p Ljava/lang/String;
    goto icn_169_alt_g1
;  VAR
icn_177_α:
    getstatic rung36_jcon_mindfa/icn_pv_minimize_F J
    goto icn_176_bang_adv
icn_177_β:
    goto icn_170_α
icn_176_α:
    goto icn_177_α
icn_176_β:
    goto icn_176_bang_chk
icn_176_bang_adv:
    putstatic rung36_jcon_mindfa/icn_176_bang_str Ljava/lang/String;
    iconst_0
    putstatic rung36_jcon_mindfa/icn_176_bang_pos I
icn_176_bang_chk:
    getstatic rung36_jcon_mindfa/icn_176_bang_str Ljava/lang/String;
    invokevirtual java/lang/String/length()I
    getstatic rung36_jcon_mindfa/icn_176_bang_pos I
    if_icmple icn_170_α
    getstatic rung36_jcon_mindfa/icn_176_bang_str Ljava/lang/String;
    getstatic rung36_jcon_mindfa/icn_176_bang_pos I
    getstatic rung36_jcon_mindfa/icn_176_bang_pos I
    iconst_1
    iadd
    invokevirtual java/lang/String/substring(II)Ljava/lang/String;
    getstatic rung36_jcon_mindfa/icn_176_bang_pos I
    iconst_1
    iadd
    putstatic rung36_jcon_mindfa/icn_176_bang_pos I
    goto icn_175_store
icn_175_α:
    goto icn_176_α
icn_175_β:
    goto icn_176_β
icn_175_store:
    pop
    aconst_null
    goto icn_174_store
icn_174_α:
    goto icn_175_α
icn_174_β:
    goto icn_175_β
icn_174_store:
    putstatic rung36_jcon_mindfa/icn_pv_minimize_p Ljava/lang/String;
    getstatic rung36_jcon_mindfa/icn_pv_minimize_p Ljava/lang/String;
    goto icn_169_alt_g0
icn_169_alt_g0:
    astore 148
    sipush 1
    putstatic rung36_jcon_mindfa/icn_169_alt_gate I
    aload 148
    goto icn_168_and_rg_0
icn_169_alt_g1:
    astore 149
    sipush 2
    putstatic rung36_jcon_mindfa/icn_169_alt_gate I
    aload 149
    goto icn_168_and_rg_0
icn_169_α:
    iconst_0
    putstatic rung36_jcon_mindfa/icn_169_alt_gate I
    goto icn_174_α
icn_169_β:
    getstatic rung36_jcon_mindfa/icn_169_alt_gate I
    tableswitch 1 2
        icn_174_β
        icn_170_β
        default: icn_115_α
;  VAR
icn_179_α:
    getstatic rung36_jcon_mindfa/icn_pv_minimize_p Ljava/lang/String;
    goto icn_178_lrelay
icn_179_β:
    goto icn_169_β
;  VAR
icn_180_α:
    getstatic rung36_jcon_mindfa/icn_gvar_q Ljava/lang/String;
    goto icn_178_rrelay
icn_180_β:
    goto icn_169_β
;  STRRELOP
icn_178_α:
    goto icn_179_α
icn_178_β:
    goto icn_179_β
icn_178_lrelay:
    astore 94
    goto icn_178_lstore
icn_178_lstore:
    goto icn_180_α
icn_178_rrelay:
    astore 95
    goto icn_178_chk
icn_178_chk:
    aload 94
    aload 95
    invokevirtual java/lang/String/compareTo(Ljava/lang/String;)I
    ifeq icn_180_β
    lconst_0
    goto icn_119_gdrain
    goto icn_168_α
icn_168_and_rg_0:
    putstatic rung36_jcon_mindfa/icn_168_and_drain_0 Ljava/lang/String;
    goto icn_178_α
icn_168_α:
    goto icn_169_α
icn_168_β:
    goto icn_178_β
icn_119_gdrain:
    pop2
    goto icn_120_α
icn_119_bdrain:
    pop2
icn_119_pump:
    goto icn_168_β
icn_119_α:
    goto icn_168_α
icn_119_β:
    goto icn_115_α
;  STR
icn_183_α:
    ldc "X"
    goto icn_182_tsa_vr
icn_183_β:
    goto icn_181_pump
icn_184_α:
    goto icn_181_pump
icn_184_β:
    goto icn_181_pump
icn_182_α:
    goto icn_183_α
icn_182_β:
    goto icn_181_pump
icn_182_tsa_vr:
    dup
    putstatic rung36_jcon_mindfa/icn_182_tsa_vl Ljava/lang/String;
    goto icn_184_α
icn_182_tsa_kr:
    invokestatic java/lang/Long/toString(J)Ljava/lang/String;
    putstatic rung36_jcon_mindfa/icn_182_tsa_ks Ljava/lang/String;
    goto icn_182_tsa_put
icn_182_tsa_put:
    getstatic rung36_jcon_mindfa/icn_pv_minimize_distab Ljava/util/HashMap;
    getstatic rung36_jcon_mindfa/icn_182_tsa_ks Ljava/lang/String;
    getstatic rung36_jcon_mindfa/icn_182_tsa_vl Ljava/lang/String;
    invokevirtual java/util/HashMap/put(Ljava/lang/Object;Ljava/lang/Object;)Ljava/lang/Object;
    pop
    getstatic rung36_jcon_mindfa/icn_182_tsa_vl Ljava/lang/String;
    goto icn_181_bdrain
;  VAR
icn_188_α:
    getstatic rung36_jcon_mindfa/icn_pv_minimize_QF J
    goto icn_187_bang_adv
icn_188_β:
    goto icn_119_α
icn_187_α:
    goto icn_188_α
icn_187_β:
    goto icn_187_bang_chk
icn_187_bang_adv:
    putstatic rung36_jcon_mindfa/icn_187_bang_str Ljava/lang/String;
    iconst_0
    putstatic rung36_jcon_mindfa/icn_187_bang_pos I
icn_187_bang_chk:
    getstatic rung36_jcon_mindfa/icn_187_bang_str Ljava/lang/String;
    invokevirtual java/lang/String/length()I
    getstatic rung36_jcon_mindfa/icn_187_bang_pos I
    if_icmple icn_119_α
    getstatic rung36_jcon_mindfa/icn_187_bang_str Ljava/lang/String;
    getstatic rung36_jcon_mindfa/icn_187_bang_pos I
    getstatic rung36_jcon_mindfa/icn_187_bang_pos I
    iconst_1
    iadd
    invokevirtual java/lang/String/substring(II)Ljava/lang/String;
    getstatic rung36_jcon_mindfa/icn_187_bang_pos I
    iconst_1
    iadd
    putstatic rung36_jcon_mindfa/icn_187_bang_pos I
    goto icn_186_store
icn_186_α:
    goto icn_187_α
icn_186_β:
    goto icn_187_β
icn_186_store:
    pop
    aconst_null
    goto icn_185_store
icn_185_α:
    goto icn_186_α
icn_185_β:
    goto icn_186_β
icn_185_store:
    putstatic rung36_jcon_mindfa/icn_pv_minimize_p Ljava/lang/String;
    getstatic rung36_jcon_mindfa/icn_pv_minimize_p Ljava/lang/String;
    goto icn_181_gdrain
icn_181_gdrain:
    pop
    goto icn_182_α
icn_181_bdrain:
    pop
icn_181_pump:
    goto icn_185_β
icn_181_α:
    goto icn_185_α
icn_181_β:
    goto icn_119_α
icn_191_α:
    goto icn_181_α
icn_191_β:
    goto icn_181_α
icn_190_arg1:
    putstatic rung36_jcon_mindfa/icn_arg_1 J
    goto icn_190_docall
icn_192_α:
    goto icn_181_α
icn_192_β:
    goto icn_181_α
icn_190_arg0:
    putstatic rung36_jcon_mindfa/icn_arg_0 J
    goto icn_191_α
icn_190_α:
    goto icn_192_α
icn_190_β:
    goto icn_191_β
icn_190_docall:
    getstatic rung36_jcon_mindfa/icn_7_I J
    lstore 154
    getstatic rung36_jcon_mindfa/icn_7_bound J
    lstore 156
    getstatic rung36_jcon_mindfa/icn_7_e1cur J
    lstore 158
    getstatic rung36_jcon_mindfa/icn_7_e1val J
    lstore 160
    getstatic rung36_jcon_mindfa/icn_7_e2val J
    lstore 162
    getstatic rung36_jcon_mindfa/icn_93_I J
    lstore 164
    getstatic rung36_jcon_mindfa/icn_93_bound J
    lstore 166
    getstatic rung36_jcon_mindfa/icn_93_e1cur J
    lstore 168
    getstatic rung36_jcon_mindfa/icn_93_e1val J
    lstore 170
    getstatic rung36_jcon_mindfa/icn_93_e2val J
    lstore 172
    getstatic rung36_jcon_mindfa/icn_pv_minimize_D J
    lstore 174
    getstatic rung36_jcon_mindfa/icn_126_ts_kval J
    lstore 176
    getstatic rung36_jcon_mindfa/icn_pv_minimize_cs J
    lstore 178
    getstatic rung36_jcon_mindfa/icn_142_ts_kval J
    lstore 180
    getstatic rung36_jcon_mindfa/icn_165_ts_kval J
    lstore 182
    getstatic rung36_jcon_mindfa/icn_pv_minimize_QF J
    lstore 184
    getstatic rung36_jcon_mindfa/icn_pv_minimize_F J
    lstore 186
    invokestatic rung36_jcon_mindfa/icn_diff()V
    lload 154
    putstatic rung36_jcon_mindfa/icn_7_I J
    lload 156
    putstatic rung36_jcon_mindfa/icn_7_bound J
    lload 158
    putstatic rung36_jcon_mindfa/icn_7_e1cur J
    lload 160
    putstatic rung36_jcon_mindfa/icn_7_e1val J
    lload 162
    putstatic rung36_jcon_mindfa/icn_7_e2val J
    lload 164
    putstatic rung36_jcon_mindfa/icn_93_I J
    lload 166
    putstatic rung36_jcon_mindfa/icn_93_bound J
    lload 168
    putstatic rung36_jcon_mindfa/icn_93_e1cur J
    lload 170
    putstatic rung36_jcon_mindfa/icn_93_e1val J
    lload 172
    putstatic rung36_jcon_mindfa/icn_93_e2val J
    lload 174
    putstatic rung36_jcon_mindfa/icn_pv_minimize_D J
    lload 176
    putstatic rung36_jcon_mindfa/icn_126_ts_kval J
    lload 178
    putstatic rung36_jcon_mindfa/icn_pv_minimize_cs J
    lload 180
    putstatic rung36_jcon_mindfa/icn_142_ts_kval J
    lload 182
    putstatic rung36_jcon_mindfa/icn_165_ts_kval J
    lload 184
    putstatic rung36_jcon_mindfa/icn_pv_minimize_QF J
    lload 186
    putstatic rung36_jcon_mindfa/icn_pv_minimize_F J
    getstatic rung36_jcon_mindfa/icn_failed B
    ifne icn_190_after_call
    getstatic rung36_jcon_mindfa/icn_retval J
    goto icn_189_store
icn_190_after_call:
    goto icn_181_α
icn_189_α:
    goto icn_190_α
icn_189_β:
    goto icn_190_β
icn_189_store:
    putstatic rung36_jcon_mindfa/icn_pv_minimize_QF J
    getstatic rung36_jcon_mindfa/icn_pv_minimize_QF J
    goto icn_minimize_s5_sdrain
icn_minimize_s5_sdrain:
    pop2
    goto icn_181_α
icn_194_α:
    goto icn_189_α
icn_194_β:
    goto icn_189_α
icn_193_α:
    goto icn_194_α
icn_193_β:
    goto icn_194_β
icn_193_store:
    putstatic rung36_jcon_mindfa/icn_pv_minimize_F J
    getstatic rung36_jcon_mindfa/icn_pv_minimize_F J
    goto icn_minimize_s4_sdrain
icn_minimize_s4_sdrain:
    pop2
    goto icn_189_α
icn_196_α:
    goto icn_193_α
icn_196_β:
    goto icn_193_α
icn_195_α:
    goto icn_196_α
icn_195_β:
    goto icn_196_β
icn_195_store:
    putstatic rung36_jcon_mindfa/icn_pv_minimize_dlists Ljava/util/HashMap;
    getstatic rung36_jcon_mindfa/icn_pv_minimize_dlists Ljava/util/HashMap;
    goto icn_minimize_s3_sdrain
icn_minimize_s3_sdrain:
    pop
    goto icn_193_α
icn_198_α:
    goto icn_195_α
icn_198_β:
    goto icn_195_α
icn_197_α:
    goto icn_198_α
icn_197_β:
    goto icn_198_β
icn_197_store:
    putstatic rung36_jcon_mindfa/icn_pv_minimize_distab Ljava/util/HashMap;
    getstatic rung36_jcon_mindfa/icn_pv_minimize_distab Ljava/util/HashMap;
    goto icn_minimize_s2_sdrain
icn_minimize_s2_sdrain:
    pop
    goto icn_195_α
icn_minimize_done:
    iconst_0
    putstatic rung36_jcon_mindfa/icn_suspended B
    iconst_0
    putstatic rung36_jcon_mindfa/icn_suspend_id I
    iconst_1
    putstatic rung36_jcon_mindfa/icn_failed B
    return
icn_minimize_ret:
    iconst_0
    putstatic rung36_jcon_mindfa/icn_failed B
    return
icn_minimize_sret:
    return
.end method

.method public static icn_marklists()V
    .limit stack 16
    .limit locals 470
    lconst_0
    lstore 0
    lconst_0
    lstore 2
    lconst_0
    lstore 4
    lconst_0
    lstore 6
    lconst_0
    lstore 8
    lconst_0
    lstore 10
    lconst_0
    lstore 12
    lconst_0
    lstore 14
    lconst_0
    lstore 16
    lconst_0
    lstore 18
    lconst_0
    lstore 20
    lconst_0
    lstore 22
    lconst_0
    lstore 24
    lconst_0
    lstore 26
    lconst_0
    lstore 28
    lconst_0
    lstore 30
    lconst_0
    lstore 32
    lconst_0
    lstore 34
    lconst_0
    lstore 36
    lconst_0
    lstore 38
    lconst_0
    lstore 40
    lconst_0
    lstore 42
    lconst_0
    lstore 44
    lconst_0
    lstore 46
    lconst_0
    lstore 48
    lconst_0
    lstore 50
    lconst_0
    lstore 52
    lconst_0
    lstore 54
    lconst_0
    lstore 56
    lconst_0
    lstore 58
    lconst_0
    lstore 60
    lconst_0
    lstore 62
    iconst_0
    istore 84
    iconst_0
    istore 85
    iconst_0
    istore 86
    iconst_0
    istore 87
    aconst_null
    astore 148
    aconst_null
    astore 149
    aconst_null
    astore 150
    aconst_null
    astore 151
    getstatic rung36_jcon_mindfa/icn_arg_str_0 Ljava/lang/String;
    putstatic rung36_jcon_mindfa/icn_pv_marklists_l Ljava/lang/String;
    goto icn_212_α
icn_199_α:
    lconst_0
    putstatic rung36_jcon_mindfa/icn_retval J
    iconst_0
    putstatic rung36_jcon_mindfa/icn_failed B
    goto icn_marklists_ret
icn_199_β:
    goto icn_marklists_ret
;  STR
icn_203_α:
    ldc "X"
    goto icn_202_tsa_vr
icn_203_β:
    goto icn_201_seq_rf_0
;  VAR
icn_204_α:
    getstatic rung36_jcon_mindfa/icn_pv_marklists_e Ljava/lang/String;
    goto icn_202_tsa_kr
icn_204_β:
    goto icn_201_seq_rf_0
icn_202_α:
    goto icn_203_α
icn_202_β:
    goto icn_201_seq_rf_0
icn_202_tsa_vr:
    dup
    putstatic rung36_jcon_mindfa/icn_202_tsa_vl Ljava/lang/String;
    goto icn_204_α
icn_202_tsa_kr:
    putstatic rung36_jcon_mindfa/icn_202_tsa_ks Ljava/lang/String;
    goto icn_202_tsa_put
icn_202_tsa_put:
    getstatic rung36_jcon_mindfa/icn_pv_marklists_distab Ljava/util/HashMap;
    getstatic rung36_jcon_mindfa/icn_202_tsa_ks Ljava/lang/String;
    getstatic rung36_jcon_mindfa/icn_202_tsa_vl Ljava/lang/String;
    invokevirtual java/util/HashMap/put(Ljava/lang/Object;Ljava/lang/Object;)Ljava/lang/Object;
    pop
    getstatic rung36_jcon_mindfa/icn_202_tsa_vl Ljava/lang/String;
    goto icn_201_seq_rg_0
;  VAR
icn_207_α:
    getstatic rung36_jcon_mindfa/icn_gvar_dlists Ljava/util/HashMap;
    goto icn_206_ts_tr
icn_207_β:
    goto icn_200_pump
;  VAR
icn_208_α:
    getstatic rung36_jcon_mindfa/icn_pv_marklists_e Ljava/lang/String;
    goto icn_206_ts_kr
icn_208_β:
    goto icn_200_pump
icn_206_α:
    goto icn_207_α
icn_206_β:
    goto icn_208_β
icn_206_ts_tr:
    putstatic rung36_jcon_mindfa/icn_206_ts_tbl Ljava/util/HashMap;
    goto icn_208_α
icn_206_ts_kr:
    dup
    putstatic rung36_jcon_mindfa/icn_206_ts_key Ljava/lang/String;
    lconst_0
    putstatic rung36_jcon_mindfa/icn_206_ts_kval J
    getstatic rung36_jcon_mindfa/icn_206_ts_tbl Ljava/util/HashMap;
    getstatic rung36_jcon_mindfa/icn_206_ts_key Ljava/lang/String;
    invokevirtual java/util/HashMap/get(Ljava/lang/Object;)Ljava/lang/Object;
    dup
    ifnonnull icn_206_ts_got
    pop
    lconst_0
    goto icn_205_arg0
icn_206_ts_got:
    checkcast java/lang/Long
    invokevirtual java/lang/Long/longValue()J
    goto icn_205_arg0
icn_205_arg0:
    putstatic rung36_jcon_mindfa/icn_arg_0 J
    goto icn_205_docall
icn_205_α:
    goto icn_206_α
icn_205_β:
    goto icn_206_β
icn_205_docall:
    getstatic rung36_jcon_mindfa/icn_7_I J
    lstore 152
    getstatic rung36_jcon_mindfa/icn_7_bound J
    lstore 154
    getstatic rung36_jcon_mindfa/icn_7_e1cur J
    lstore 156
    getstatic rung36_jcon_mindfa/icn_7_e1val J
    lstore 158
    getstatic rung36_jcon_mindfa/icn_7_e2val J
    lstore 160
    getstatic rung36_jcon_mindfa/icn_93_I J
    lstore 162
    getstatic rung36_jcon_mindfa/icn_93_bound J
    lstore 164
    getstatic rung36_jcon_mindfa/icn_93_e1cur J
    lstore 166
    getstatic rung36_jcon_mindfa/icn_93_e1val J
    lstore 168
    getstatic rung36_jcon_mindfa/icn_93_e2val J
    lstore 170
    getstatic rung36_jcon_mindfa/icn_126_ts_kval J
    lstore 172
    getstatic rung36_jcon_mindfa/icn_142_ts_kval J
    lstore 174
    getstatic rung36_jcon_mindfa/icn_165_ts_kval J
    lstore 176
    getstatic rung36_jcon_mindfa/icn_206_ts_kval J
    lstore 178
    invokestatic rung36_jcon_mindfa/icn_marklists()V
    lload 152
    putstatic rung36_jcon_mindfa/icn_7_I J
    lload 154
    putstatic rung36_jcon_mindfa/icn_7_bound J
    lload 156
    putstatic rung36_jcon_mindfa/icn_7_e1cur J
    lload 158
    putstatic rung36_jcon_mindfa/icn_7_e1val J
    lload 160
    putstatic rung36_jcon_mindfa/icn_7_e2val J
    lload 162
    putstatic rung36_jcon_mindfa/icn_93_I J
    lload 164
    putstatic rung36_jcon_mindfa/icn_93_bound J
    lload 166
    putstatic rung36_jcon_mindfa/icn_93_e1cur J
    lload 168
    putstatic rung36_jcon_mindfa/icn_93_e1val J
    lload 170
    putstatic rung36_jcon_mindfa/icn_93_e2val J
    lload 172
    putstatic rung36_jcon_mindfa/icn_126_ts_kval J
    lload 174
    putstatic rung36_jcon_mindfa/icn_142_ts_kval J
    lload 176
    putstatic rung36_jcon_mindfa/icn_165_ts_kval J
    lload 178
    putstatic rung36_jcon_mindfa/icn_206_ts_kval J
    getstatic rung36_jcon_mindfa/icn_failed B
    ifne icn_205_after_call
    getstatic rung36_jcon_mindfa/icn_retval J
    goto icn_200_bdrain
icn_205_after_call:
    goto icn_200_pump
    goto icn_201_α
icn_201_seq_rg_0:
    pop
    goto icn_205_α
icn_201_seq_rf_0:
    goto icn_205_α
icn_201_α:
    goto icn_202_α
icn_201_β:
    goto icn_205_β
;  VAR
icn_211_α:
    getstatic rung36_jcon_mindfa/icn_pv_marklists_l Ljava/lang/String;
    goto icn_210_bang_st
icn_211_β:
    goto icn_199_α
icn_210_α:
    goto icn_211_α
icn_210_β:
    goto icn_210_bang_chk
icn_210_bang_st:
    putstatic rung36_jcon_mindfa/icn_210_bang_list Ljava/util/ArrayList;
    iconst_0
    putstatic rung36_jcon_mindfa/icn_210_bang_idx I
icn_210_bang_chk:
    getstatic rung36_jcon_mindfa/icn_210_bang_list Ljava/util/ArrayList;
    invokevirtual java/util/ArrayList/size()I
    getstatic rung36_jcon_mindfa/icn_210_bang_idx I
    if_icmple icn_199_α
    getstatic rung36_jcon_mindfa/icn_210_bang_list Ljava/util/ArrayList;
    getstatic rung36_jcon_mindfa/icn_210_bang_idx I
    invokevirtual java/util/ArrayList/get(I)Ljava/lang/Object;
icn_210_bang_ok:
    checkcast java/lang/Long
    invokevirtual java/lang/Long/longValue()J
    getstatic rung36_jcon_mindfa/icn_210_bang_idx I
    iconst_1
    iadd
    putstatic rung36_jcon_mindfa/icn_210_bang_idx I
    goto icn_209_store
icn_209_α:
    goto icn_210_α
icn_209_β:
    goto icn_210_β
icn_209_store:
    putstatic rung36_jcon_mindfa/icn_pv_marklists_e J
    getstatic rung36_jcon_mindfa/icn_pv_marklists_e J
    goto icn_200_gdrain
icn_200_gdrain:
    pop2
    goto icn_201_α
icn_200_bdrain:
    pop2
icn_200_pump:
    goto icn_209_β
icn_200_α:
    goto icn_209_α
icn_200_β:
    goto icn_199_α
icn_213_α:
    lconst_0
    putstatic rung36_jcon_mindfa/icn_retval J
    iconst_0
    putstatic rung36_jcon_mindfa/icn_failed B
    goto icn_marklists_ret
icn_213_β:
    goto icn_marklists_ret
;  VAR
icn_215_α:
    getstatic rung36_jcon_mindfa/icn_pv_marklists_l Ljava/lang/String;
    goto icn_214_cok
icn_215_β:
    goto icn_214_succ
;  NULL
icn_214_α:
    goto icn_215_α
icn_214_β:
    goto icn_215_β
icn_214_cok:
    pop
    goto icn_212_else
icn_214_succ:
    lconst_0
    goto icn_212_then
icn_212_then:
    pop2
    goto icn_213_α
icn_212_else:
    goto icn_200_α
icn_212_α:
    goto icn_214_α
icn_212_β:
    goto icn_214_β
icn_marklists_done:
    iconst_0
    putstatic rung36_jcon_mindfa/icn_suspended B
    iconst_0
    putstatic rung36_jcon_mindfa/icn_suspend_id I
    iconst_1
    putstatic rung36_jcon_mindfa/icn_failed B
    return
icn_marklists_ret:
    iconst_0
    putstatic rung36_jcon_mindfa/icn_failed B
    return
icn_marklists_sret:
    return
.end method

.method public static icn_makemdfa()V
    .limit stack 16
    .limit locals 674
    lconst_0
    lstore 0
    lconst_0
    lstore 2
    lconst_0
    lstore 4
    lconst_0
    lstore 6
    lconst_0
    lstore 8
    lconst_0
    lstore 10
    lconst_0
    lstore 12
    lconst_0
    lstore 14
    lconst_0
    lstore 16
    lconst_0
    lstore 18
    lconst_0
    lstore 20
    lconst_0
    lstore 22
    lconst_0
    lstore 24
    lconst_0
    lstore 26
    lconst_0
    lstore 28
    lconst_0
    lstore 30
    lconst_0
    lstore 32
    lconst_0
    lstore 34
    lconst_0
    lstore 36
    lconst_0
    lstore 38
    lconst_0
    lstore 40
    lconst_0
    lstore 42
    lconst_0
    lstore 44
    lconst_0
    lstore 46
    lconst_0
    lstore 48
    lconst_0
    lstore 50
    lconst_0
    lstore 52
    lconst_0
    lstore 54
    lconst_0
    lstore 56
    lconst_0
    lstore 58
    lconst_0
    lstore 60
    lconst_0
    lstore 62
    iconst_0
    istore 84
    iconst_0
    istore 85
    iconst_0
    istore 86
    iconst_0
    istore 87
    iconst_0
    istore 88
    iconst_0
    istore 89
    iconst_0
    istore 90
    iconst_0
    istore 91
    iconst_0
    istore 92
    iconst_0
    istore 93
    iconst_0
    istore 94
    iconst_0
    istore 95
    iconst_0
    istore 96
    iconst_0
    istore 97
    iconst_0
    istore 98
    iconst_0
    istore 99
    iconst_0
    istore 100
    iconst_0
    istore 101
    aconst_null
    astore 148
    aconst_null
    astore 149
    aconst_null
    astore 150
    aconst_null
    astore 151
    getstatic rung36_jcon_mindfa/icn_arg_str_0 Ljava/lang/String;
    putstatic rung36_jcon_mindfa/icn_pv_makemdfa_D Ljava/lang/String;
    getstatic rung36_jcon_mindfa/icn_arg_str_1 Ljava/lang/String;
    putstatic rung36_jcon_mindfa/icn_pv_makemdfa_DT Ljava/lang/String;
    goto icn_350_α
;  VAR
icn_218_α:
    getstatic rung36_jcon_mindfa/icn_pv_makemdfa_elist Ljava/util/ArrayList;
    goto icn_217_rc_r1
icn_218_β:
    goto icn_216_ret_fail
icn_219_α:
    goto icn_216_ret_fail
icn_219_β:
    goto icn_216_ret_fail
;  VAR
icn_220_α:
    getstatic rung36_jcon_mindfa/icn_pv_makemdfa_Delta Ljava/util/HashMap;
    goto icn_217_rc_r3
icn_220_β:
    goto icn_216_ret_fail
;  VAR
icn_221_α:
    getstatic rung36_jcon_mindfa/icn_pv_makemdfa_q0 J
    goto icn_217_rc_r4
icn_221_β:
    goto icn_216_ret_fail
;  VAR
icn_223_α:
    getstatic rung36_jcon_mindfa/icn_pv_makemdfa_elist Ljava/util/ArrayList;
    goto icn_222_arg1
icn_223_β:
    goto icn_216_ret_fail
icn_222_arg1:
    putstatic rung36_jcon_mindfa/icn_arg_1 J
    goto icn_222_docall
;  VAR
icn_224_α:
    getstatic rung36_jcon_mindfa/icn_pv_makemdfa_D J
    goto icn_222_arg0
icn_224_β:
    goto icn_216_ret_fail
icn_222_arg0:
    putstatic rung36_jcon_mindfa/icn_arg_0 J
    goto icn_223_α
icn_222_α:
    goto icn_224_α
icn_222_β:
    goto icn_223_β
icn_222_docall:
    getstatic rung36_jcon_mindfa/icn_7_I J
    lstore 152
    getstatic rung36_jcon_mindfa/icn_7_bound J
    lstore 154
    getstatic rung36_jcon_mindfa/icn_7_e1cur J
    lstore 156
    getstatic rung36_jcon_mindfa/icn_7_e1val J
    lstore 158
    getstatic rung36_jcon_mindfa/icn_7_e2val J
    lstore 160
    getstatic rung36_jcon_mindfa/icn_93_I J
    lstore 162
    getstatic rung36_jcon_mindfa/icn_93_bound J
    lstore 164
    getstatic rung36_jcon_mindfa/icn_93_e1cur J
    lstore 166
    getstatic rung36_jcon_mindfa/icn_93_e1val J
    lstore 168
    getstatic rung36_jcon_mindfa/icn_93_e2val J
    lstore 170
    getstatic rung36_jcon_mindfa/icn_126_ts_kval J
    lstore 172
    getstatic rung36_jcon_mindfa/icn_142_ts_kval J
    lstore 174
    getstatic rung36_jcon_mindfa/icn_165_ts_kval J
    lstore 176
    getstatic rung36_jcon_mindfa/icn_206_ts_kval J
    lstore 178
    getstatic rung36_jcon_mindfa/icn_pv_makemdfa_q0 J
    lstore 180
    getstatic rung36_jcon_mindfa/icn_pv_makemdfa_D J
    lstore 182
    invokestatic rung36_jcon_mindfa/icn_finalstates()V
    lload 152
    putstatic rung36_jcon_mindfa/icn_7_I J
    lload 154
    putstatic rung36_jcon_mindfa/icn_7_bound J
    lload 156
    putstatic rung36_jcon_mindfa/icn_7_e1cur J
    lload 158
    putstatic rung36_jcon_mindfa/icn_7_e1val J
    lload 160
    putstatic rung36_jcon_mindfa/icn_7_e2val J
    lload 162
    putstatic rung36_jcon_mindfa/icn_93_I J
    lload 164
    putstatic rung36_jcon_mindfa/icn_93_bound J
    lload 166
    putstatic rung36_jcon_mindfa/icn_93_e1cur J
    lload 168
    putstatic rung36_jcon_mindfa/icn_93_e1val J
    lload 170
    putstatic rung36_jcon_mindfa/icn_93_e2val J
    lload 172
    putstatic rung36_jcon_mindfa/icn_126_ts_kval J
    lload 174
    putstatic rung36_jcon_mindfa/icn_142_ts_kval J
    lload 176
    putstatic rung36_jcon_mindfa/icn_165_ts_kval J
    lload 178
    putstatic rung36_jcon_mindfa/icn_206_ts_kval J
    lload 180
    putstatic rung36_jcon_mindfa/icn_pv_makemdfa_q0 J
    lload 182
    putstatic rung36_jcon_mindfa/icn_pv_makemdfa_D J
    getstatic rung36_jcon_mindfa/icn_failed B
    ifne icn_222_after_call
    getstatic rung36_jcon_mindfa/icn_retval J
    goto icn_217_rc_r5
icn_222_after_call:
    goto icn_216_ret_fail
icn_217_α:
    goto icn_218_α
icn_217_β:
    goto icn_216_ret_fail
icn_217_rc_r1:
    invokestatic java/lang/Long/valueOf(J)Ljava/lang/Long;
    putstatic rung36_jcon_mindfa/icn_217_rc_a0 Ljava/lang/Object;
    goto icn_219_α
icn_217_rc_r2:
    invokestatic java/lang/Long/valueOf(J)Ljava/lang/Long;
    putstatic rung36_jcon_mindfa/icn_217_rc_a1 Ljava/lang/Object;
    goto icn_220_α
icn_217_rc_r3:
    invokestatic java/lang/Long/valueOf(J)Ljava/lang/Long;
    putstatic rung36_jcon_mindfa/icn_217_rc_a2 Ljava/lang/Object;
    goto icn_221_α
icn_217_rc_r4:
    invokestatic java/lang/Long/valueOf(J)Ljava/lang/Long;
    putstatic rung36_jcon_mindfa/icn_217_rc_a3 Ljava/lang/Object;
    goto icn_222_α
icn_217_rc_r5:
    invokestatic java/lang/Long/valueOf(J)Ljava/lang/Long;
    putstatic rung36_jcon_mindfa/icn_217_rc_a4 Ljava/lang/Object;
    goto icn_217_rc_build
icn_217_rc_build:
    new rung36_jcon_mindfa$dfa
    dup
    invokespecial rung36_jcon_mindfa$dfa/<init>()V
    putstatic rung36_jcon_mindfa/icn_217_rc_obj Ljava/lang/Object;
    getstatic rung36_jcon_mindfa/icn_217_rc_obj Ljava/lang/Object;
    putstatic rung36_jcon_mindfa/icn_retval_obj Ljava/lang/Object;
    lconst_0
    goto icn_216_ret_store
icn_216_α:
    goto icn_217_α
icn_216_β:
    goto icn_makemdfa_ret
icn_216_ret_fail:
    iconst_1
    putstatic rung36_jcon_mindfa/icn_failed B
    goto icn_makemdfa_done
icn_216_ret_store:
    putstatic rung36_jcon_mindfa/icn_retval J
    iconst_0
    putstatic rung36_jcon_mindfa/icn_failed B
    goto icn_makemdfa_ret
;  VAR
icn_228_α:
    getstatic rung36_jcon_mindfa/icn_pv_makemdfa_tlist Ljava/util/ArrayList;
    goto icn_227_lr
icn_228_β:
    goto icn_216_α
icn_227_α:
    goto icn_228_α
icn_227_β:
    goto icn_216_α
icn_227_lr:
    putstatic rung36_jcon_mindfa/icn_227_glist Ljava/util/ArrayList;
    getstatic rung36_jcon_mindfa/icn_227_glist Ljava/util/ArrayList;
    invokevirtual java/util/ArrayList/size()I
    ifeq icn_216_α
    getstatic rung36_jcon_mindfa/icn_227_glist Ljava/util/ArrayList;
    iconst_0
    invokevirtual java/util/ArrayList/remove(I)Ljava/lang/Object;
    dup
    ifnonnull icn_227_gok
    pop
    goto icn_216_α
icn_227_gok:
    checkcast java/lang/Long
    invokevirtual java/lang/Long/longValue()J
    goto icn_226_store
icn_226_α:
    goto icn_227_α
icn_226_β:
    goto icn_227_β
icn_226_store:
    putstatic rung36_jcon_mindfa/icn_pv_makemdfa_q J
    getstatic rung36_jcon_mindfa/icn_pv_makemdfa_q J
    goto icn_225_condok
icn_225_condok:
    pop2
    goto icn_225_wbstart
;  VAR
icn_233_α:
    getstatic rung36_jcon_mindfa/icn_pv_makemdfa_etab Ljava/util/HashMap;
    goto icn_232_arg3
icn_233_β:
    goto icn_230_seq_rf_0
icn_232_arg3:
    putstatic rung36_jcon_mindfa/icn_arg_3 J
    goto icn_232_docall
;  VAR
icn_234_α:
    getstatic rung36_jcon_mindfa/icn_pv_makemdfa_D J
    goto icn_232_arg2
icn_234_β:
    goto icn_230_seq_rf_0
icn_232_arg2:
    putstatic rung36_jcon_mindfa/icn_arg_2 J
    goto icn_233_α
;  VAR
icn_235_α:
    getstatic rung36_jcon_mindfa/icn_pv_makemdfa_a Ljava/lang/String;
    goto icn_232_arg1
icn_235_β:
    goto icn_230_seq_rf_0
icn_232_arg1:
    putstatic rung36_jcon_mindfa/icn_arg_str_1 Ljava/lang/String;
    lconst_0
    putstatic rung36_jcon_mindfa/icn_arg_1 J
    goto icn_234_α
;  VAR
icn_236_α:
    getstatic rung36_jcon_mindfa/icn_pv_makemdfa_q J
    goto icn_232_arg0
icn_236_β:
    goto icn_230_seq_rf_0
icn_232_arg0:
    putstatic rung36_jcon_mindfa/icn_arg_str_0 Ljava/lang/String;
    lconst_0
    putstatic rung36_jcon_mindfa/icn_arg_0 J
    goto icn_235_α
icn_232_α:
    goto icn_236_α
icn_232_β:
    goto icn_233_β
icn_232_docall:
    getstatic rung36_jcon_mindfa/icn_7_I J
    lstore 152
    getstatic rung36_jcon_mindfa/icn_7_bound J
    lstore 154
    getstatic rung36_jcon_mindfa/icn_7_e1cur J
    lstore 156
    getstatic rung36_jcon_mindfa/icn_7_e1val J
    lstore 158
    getstatic rung36_jcon_mindfa/icn_7_e2val J
    lstore 160
    getstatic rung36_jcon_mindfa/icn_93_I J
    lstore 162
    getstatic rung36_jcon_mindfa/icn_93_bound J
    lstore 164
    getstatic rung36_jcon_mindfa/icn_93_e1cur J
    lstore 166
    getstatic rung36_jcon_mindfa/icn_93_e1val J
    lstore 168
    getstatic rung36_jcon_mindfa/icn_93_e2val J
    lstore 170
    getstatic rung36_jcon_mindfa/icn_126_ts_kval J
    lstore 172
    getstatic rung36_jcon_mindfa/icn_142_ts_kval J
    lstore 174
    getstatic rung36_jcon_mindfa/icn_165_ts_kval J
    lstore 176
    getstatic rung36_jcon_mindfa/icn_206_ts_kval J
    lstore 178
    getstatic rung36_jcon_mindfa/icn_pv_makemdfa_q0 J
    lstore 180
    getstatic rung36_jcon_mindfa/icn_pv_makemdfa_D J
    lstore 182
    getstatic rung36_jcon_mindfa/icn_pv_makemdfa_q J
    lstore 184
    getstatic rung36_jcon_mindfa/icn_231_tsa_vl J
    lstore 186
    invokestatic rung36_jcon_mindfa/icn_equivdelta()V
    lload 152
    putstatic rung36_jcon_mindfa/icn_7_I J
    lload 154
    putstatic rung36_jcon_mindfa/icn_7_bound J
    lload 156
    putstatic rung36_jcon_mindfa/icn_7_e1cur J
    lload 158
    putstatic rung36_jcon_mindfa/icn_7_e1val J
    lload 160
    putstatic rung36_jcon_mindfa/icn_7_e2val J
    lload 162
    putstatic rung36_jcon_mindfa/icn_93_I J
    lload 164
    putstatic rung36_jcon_mindfa/icn_93_bound J
    lload 166
    putstatic rung36_jcon_mindfa/icn_93_e1cur J
    lload 168
    putstatic rung36_jcon_mindfa/icn_93_e1val J
    lload 170
    putstatic rung36_jcon_mindfa/icn_93_e2val J
    lload 172
    putstatic rung36_jcon_mindfa/icn_126_ts_kval J
    lload 174
    putstatic rung36_jcon_mindfa/icn_142_ts_kval J
    lload 176
    putstatic rung36_jcon_mindfa/icn_165_ts_kval J
    lload 178
    putstatic rung36_jcon_mindfa/icn_206_ts_kval J
    lload 180
    putstatic rung36_jcon_mindfa/icn_pv_makemdfa_q0 J
    lload 182
    putstatic rung36_jcon_mindfa/icn_pv_makemdfa_D J
    lload 184
    putstatic rung36_jcon_mindfa/icn_pv_makemdfa_q J
    lload 186
    putstatic rung36_jcon_mindfa/icn_231_tsa_vl J
    getstatic rung36_jcon_mindfa/icn_failed B
    ifne icn_232_after_call
    getstatic rung36_jcon_mindfa/icn_retval J
    goto icn_231_tsa_vr
icn_232_after_call:
    goto icn_230_seq_rf_0
;  VAR
icn_238_α:
    getstatic rung36_jcon_mindfa/icn_pv_makemdfa_a Ljava/lang/String;
    goto icn_237_rrelay
icn_238_β:
    goto icn_237_lb
;  STR
icn_240_α:
    ldc ":"
    goto icn_239_rrelay
icn_240_β:
    goto icn_239_lb
;  VAR
icn_241_α:
    getstatic rung36_jcon_mindfa/icn_pv_makemdfa_q J
    goto icn_239_lrelay
icn_241_β:
    goto icn_230_seq_rf_0
icn_239_lrelay:
    putstatic rung36_jcon_mindfa/icn_239_lc Ljava/lang/String;
    goto icn_239_lstore
icn_239_rrelay:
    putstatic rung36_jcon_mindfa/icn_239_rc Ljava/lang/String;
    goto icn_239_compute
icn_239_lb:
    goto icn_241_β
icn_239_α:
    iconst_0
    istore 85
    goto icn_241_α
icn_239_β:
    iconst_1
    istore 85
    goto icn_241_α
icn_239_lstore:
    iload 85
    ifeq icn_240_α
    goto icn_240_β
icn_239_compute:
    getstatic rung36_jcon_mindfa/icn_239_lc Ljava/lang/String;
    getstatic rung36_jcon_mindfa/icn_239_rc Ljava/lang/String;
    invokevirtual java/lang/String/concat(Ljava/lang/String;)Ljava/lang/String;
    goto icn_237_lrelay
icn_237_lrelay:
    putstatic rung36_jcon_mindfa/icn_237_lc Ljava/lang/String;
    goto icn_237_lstore
icn_237_rrelay:
    putstatic rung36_jcon_mindfa/icn_237_rc Ljava/lang/String;
    goto icn_237_compute
icn_237_lb:
    goto icn_239_β
icn_237_α:
    iconst_0
    istore 84
    goto icn_239_α
icn_237_β:
    iconst_1
    istore 84
    goto icn_239_α
icn_237_lstore:
    iload 84
    ifeq icn_238_α
    goto icn_238_β
icn_237_compute:
    getstatic rung36_jcon_mindfa/icn_237_lc Ljava/lang/String;
    getstatic rung36_jcon_mindfa/icn_237_rc Ljava/lang/String;
    invokevirtual java/lang/String/concat(Ljava/lang/String;)Ljava/lang/String;
    goto icn_231_tsa_kr
icn_231_α:
    goto icn_232_α
icn_231_β:
    goto icn_230_seq_rf_0
icn_231_tsa_vr:
    dup2
    putstatic rung36_jcon_mindfa/icn_231_tsa_vl J
    invokestatic java/lang/Long/valueOf(J)Ljava/lang/Long;
    putstatic rung36_jcon_mindfa/icn_231_tsa_vo Ljava/lang/Object;
    goto icn_237_α
icn_231_tsa_kr:
    putstatic rung36_jcon_mindfa/icn_231_tsa_ks Ljava/lang/String;
    goto icn_231_tsa_put
icn_231_tsa_put:
    getstatic rung36_jcon_mindfa/icn_pv_makemdfa_Delta Ljava/util/HashMap;
    getstatic rung36_jcon_mindfa/icn_231_tsa_ks Ljava/lang/String;
    getstatic rung36_jcon_mindfa/icn_231_tsa_vo Ljava/lang/Object;
    invokevirtual java/util/HashMap/put(Ljava/lang/Object;Ljava/lang/Object;)Ljava/lang/Object;
    pop
    getstatic rung36_jcon_mindfa/icn_231_tsa_vl J
    goto icn_230_seq_rg_0
;  VAR
icn_246_α:
    getstatic rung36_jcon_mindfa/icn_pv_makemdfa_Delta Ljava/util/HashMap;
    goto icn_245_ts_tr
icn_246_β:
    goto icn_243_seq_rf_0
;  VAR
icn_248_α:
    getstatic rung36_jcon_mindfa/icn_pv_makemdfa_a Ljava/lang/String;
    goto icn_247_rrelay
icn_248_β:
    goto icn_247_lb
;  STR
icn_250_α:
    ldc ":"
    goto icn_249_rrelay
icn_250_β:
    goto icn_249_lb
;  VAR
icn_251_α:
    getstatic rung36_jcon_mindfa/icn_pv_makemdfa_q J
    goto icn_249_lrelay
icn_251_β:
    goto icn_243_seq_rf_0
icn_249_lrelay:
    putstatic rung36_jcon_mindfa/icn_249_lc Ljava/lang/String;
    goto icn_249_lstore
icn_249_rrelay:
    putstatic rung36_jcon_mindfa/icn_249_rc Ljava/lang/String;
    goto icn_249_compute
icn_249_lb:
    goto icn_251_β
icn_249_α:
    iconst_0
    istore 87
    goto icn_251_α
icn_249_β:
    iconst_1
    istore 87
    goto icn_251_α
icn_249_lstore:
    iload 87
    ifeq icn_250_α
    goto icn_250_β
icn_249_compute:
    getstatic rung36_jcon_mindfa/icn_249_lc Ljava/lang/String;
    getstatic rung36_jcon_mindfa/icn_249_rc Ljava/lang/String;
    invokevirtual java/lang/String/concat(Ljava/lang/String;)Ljava/lang/String;
    goto icn_247_lrelay
icn_247_lrelay:
    putstatic rung36_jcon_mindfa/icn_247_lc Ljava/lang/String;
    goto icn_247_lstore
icn_247_rrelay:
    putstatic rung36_jcon_mindfa/icn_247_rc Ljava/lang/String;
    goto icn_247_compute
icn_247_lb:
    goto icn_249_β
icn_247_α:
    iconst_0
    istore 86
    goto icn_249_α
icn_247_β:
    iconst_1
    istore 86
    goto icn_249_α
icn_247_lstore:
    iload 86
    ifeq icn_248_α
    goto icn_248_β
icn_247_compute:
    getstatic rung36_jcon_mindfa/icn_247_lc Ljava/lang/String;
    getstatic rung36_jcon_mindfa/icn_247_rc Ljava/lang/String;
    invokevirtual java/lang/String/concat(Ljava/lang/String;)Ljava/lang/String;
    goto icn_245_ts_kr
icn_245_α:
    goto icn_246_α
icn_245_β:
    goto icn_247_β
icn_245_ts_tr:
    putstatic rung36_jcon_mindfa/icn_245_ts_tbl Ljava/util/HashMap;
    goto icn_247_α
icn_245_ts_kr:
    dup
    putstatic rung36_jcon_mindfa/icn_245_ts_key Ljava/lang/String;
    lconst_0
    putstatic rung36_jcon_mindfa/icn_245_ts_kval J
    getstatic rung36_jcon_mindfa/icn_245_ts_tbl Ljava/util/HashMap;
    getstatic rung36_jcon_mindfa/icn_245_ts_key Ljava/lang/String;
    invokevirtual java/util/HashMap/get(Ljava/lang/Object;)Ljava/lang/Object;
    dup
    ifnonnull icn_245_ts_got
    pop
    getstatic rung36_jcon_mindfa/icn_pv_makemdfa_Delta_dflt Ljava/lang/Object;
    checkcast java/lang/Long
    invokevirtual java/lang/Long/longValue()J
    goto icn_244_tsa_vr
icn_245_ts_got:
    checkcast java/lang/Long
    invokevirtual java/lang/Long/longValue()J
    goto icn_244_tsa_vr
;  VAR
icn_253_α:
    getstatic rung36_jcon_mindfa/icn_pv_makemdfa_Delta Ljava/util/HashMap;
    goto icn_252_ts_tr
icn_253_β:
    goto icn_243_seq_rf_0
;  VAR
icn_255_α:
    getstatic rung36_jcon_mindfa/icn_pv_makemdfa_a Ljava/lang/String;
    goto icn_254_rrelay
icn_255_β:
    goto icn_254_lb
;  STR
icn_257_α:
    ldc ":"
    goto icn_256_rrelay
icn_257_β:
    goto icn_256_lb
;  VAR
icn_258_α:
    getstatic rung36_jcon_mindfa/icn_pv_makemdfa_q J
    goto icn_256_lrelay
icn_258_β:
    goto icn_243_seq_rf_0
icn_256_lrelay:
    putstatic rung36_jcon_mindfa/icn_256_lc Ljava/lang/String;
    goto icn_256_lstore
icn_256_rrelay:
    putstatic rung36_jcon_mindfa/icn_256_rc Ljava/lang/String;
    goto icn_256_compute
icn_256_lb:
    goto icn_258_β
icn_256_α:
    iconst_0
    istore 89
    goto icn_258_α
icn_256_β:
    iconst_1
    istore 89
    goto icn_258_α
icn_256_lstore:
    iload 89
    ifeq icn_257_α
    goto icn_257_β
icn_256_compute:
    getstatic rung36_jcon_mindfa/icn_256_lc Ljava/lang/String;
    getstatic rung36_jcon_mindfa/icn_256_rc Ljava/lang/String;
    invokevirtual java/lang/String/concat(Ljava/lang/String;)Ljava/lang/String;
    goto icn_254_lrelay
icn_254_lrelay:
    putstatic rung36_jcon_mindfa/icn_254_lc Ljava/lang/String;
    goto icn_254_lstore
icn_254_rrelay:
    putstatic rung36_jcon_mindfa/icn_254_rc Ljava/lang/String;
    goto icn_254_compute
icn_254_lb:
    goto icn_256_β
icn_254_α:
    iconst_0
    istore 88
    goto icn_256_α
icn_254_β:
    iconst_1
    istore 88
    goto icn_256_α
icn_254_lstore:
    iload 88
    ifeq icn_255_α
    goto icn_255_β
icn_254_compute:
    getstatic rung36_jcon_mindfa/icn_254_lc Ljava/lang/String;
    getstatic rung36_jcon_mindfa/icn_254_rc Ljava/lang/String;
    invokevirtual java/lang/String/concat(Ljava/lang/String;)Ljava/lang/String;
    goto icn_252_ts_kr
icn_252_α:
    goto icn_253_α
icn_252_β:
    goto icn_254_β
icn_252_ts_tr:
    putstatic rung36_jcon_mindfa/icn_252_ts_tbl Ljava/util/HashMap;
    goto icn_254_α
icn_252_ts_kr:
    dup
    putstatic rung36_jcon_mindfa/icn_252_ts_key Ljava/lang/String;
    lconst_0
    putstatic rung36_jcon_mindfa/icn_252_ts_kval J
    getstatic rung36_jcon_mindfa/icn_252_ts_tbl Ljava/util/HashMap;
    getstatic rung36_jcon_mindfa/icn_252_ts_key Ljava/lang/String;
    invokevirtual java/util/HashMap/get(Ljava/lang/Object;)Ljava/lang/Object;
    dup
    ifnonnull icn_252_ts_got
    pop
    getstatic rung36_jcon_mindfa/icn_pv_makemdfa_Delta_dflt Ljava/lang/Object;
    checkcast java/lang/Long
    invokevirtual java/lang/Long/longValue()J
    goto icn_244_tsa_kr
icn_252_ts_got:
    checkcast java/lang/Long
    invokevirtual java/lang/Long/longValue()J
    goto icn_244_tsa_kr
icn_244_α:
    goto icn_245_α
icn_244_β:
    goto icn_243_seq_rf_0
icn_244_tsa_vr:
    dup2
    putstatic rung36_jcon_mindfa/icn_244_tsa_vl J
    invokestatic java/lang/Long/valueOf(J)Ljava/lang/Long;
    putstatic rung36_jcon_mindfa/icn_244_tsa_vo Ljava/lang/Object;
    goto icn_252_α
icn_244_tsa_kr:
    invokestatic java/lang/Long/toString(J)Ljava/lang/String;
    putstatic rung36_jcon_mindfa/icn_244_tsa_ks Ljava/lang/String;
    goto icn_244_tsa_put
icn_244_tsa_put:
    getstatic rung36_jcon_mindfa/icn_pv_makemdfa_echeck Ljava/util/HashMap;
    getstatic rung36_jcon_mindfa/icn_244_tsa_ks Ljava/lang/String;
    getstatic rung36_jcon_mindfa/icn_244_tsa_vo Ljava/lang/Object;
    invokevirtual java/util/HashMap/put(Ljava/lang/Object;Ljava/lang/Object;)Ljava/lang/Object;
    pop
    getstatic rung36_jcon_mindfa/icn_244_tsa_vl J
    goto icn_243_seq_rg_0
;  VAR
icn_260_α:
    getstatic rung36_jcon_mindfa/icn_pv_makemdfa_tlist Ljava/util/ArrayList;
    goto icn_259_lr
icn_260_β:
    goto icn_243_seq_rf_1
;  VAR
icn_262_α:
    getstatic rung36_jcon_mindfa/icn_pv_makemdfa_Delta Ljava/util/HashMap;
    goto icn_261_ts_tr
icn_262_β:
    goto icn_243_seq_rf_1
;  VAR
icn_264_α:
    getstatic rung36_jcon_mindfa/icn_pv_makemdfa_a Ljava/lang/String;
    goto icn_263_rrelay
icn_264_β:
    goto icn_263_lb
;  STR
icn_266_α:
    ldc ":"
    goto icn_265_rrelay
icn_266_β:
    goto icn_265_lb
;  VAR
icn_267_α:
    getstatic rung36_jcon_mindfa/icn_pv_makemdfa_q J
    goto icn_265_lrelay
icn_267_β:
    goto icn_243_seq_rf_1
icn_265_lrelay:
    putstatic rung36_jcon_mindfa/icn_265_lc Ljava/lang/String;
    goto icn_265_lstore
icn_265_rrelay:
    putstatic rung36_jcon_mindfa/icn_265_rc Ljava/lang/String;
    goto icn_265_compute
icn_265_lb:
    goto icn_267_β
icn_265_α:
    iconst_0
    istore 91
    goto icn_267_α
icn_265_β:
    iconst_1
    istore 91
    goto icn_267_α
icn_265_lstore:
    iload 91
    ifeq icn_266_α
    goto icn_266_β
icn_265_compute:
    getstatic rung36_jcon_mindfa/icn_265_lc Ljava/lang/String;
    getstatic rung36_jcon_mindfa/icn_265_rc Ljava/lang/String;
    invokevirtual java/lang/String/concat(Ljava/lang/String;)Ljava/lang/String;
    goto icn_263_lrelay
icn_263_lrelay:
    putstatic rung36_jcon_mindfa/icn_263_lc Ljava/lang/String;
    goto icn_263_lstore
icn_263_rrelay:
    putstatic rung36_jcon_mindfa/icn_263_rc Ljava/lang/String;
    goto icn_263_compute
icn_263_lb:
    goto icn_265_β
icn_263_α:
    iconst_0
    istore 90
    goto icn_265_α
icn_263_β:
    iconst_1
    istore 90
    goto icn_265_α
icn_263_lstore:
    iload 90
    ifeq icn_264_α
    goto icn_264_β
icn_263_compute:
    getstatic rung36_jcon_mindfa/icn_263_lc Ljava/lang/String;
    getstatic rung36_jcon_mindfa/icn_263_rc Ljava/lang/String;
    invokevirtual java/lang/String/concat(Ljava/lang/String;)Ljava/lang/String;
    goto icn_261_ts_kr
icn_261_α:
    goto icn_262_α
icn_261_β:
    goto icn_263_β
icn_261_ts_tr:
    putstatic rung36_jcon_mindfa/icn_261_ts_tbl Ljava/util/HashMap;
    goto icn_263_α
icn_261_ts_kr:
    dup
    putstatic rung36_jcon_mindfa/icn_261_ts_key Ljava/lang/String;
    lconst_0
    putstatic rung36_jcon_mindfa/icn_261_ts_kval J
    getstatic rung36_jcon_mindfa/icn_261_ts_tbl Ljava/util/HashMap;
    getstatic rung36_jcon_mindfa/icn_261_ts_key Ljava/lang/String;
    invokevirtual java/util/HashMap/get(Ljava/lang/Object;)Ljava/lang/Object;
    dup
    ifnonnull icn_261_ts_got
    pop
    getstatic rung36_jcon_mindfa/icn_pv_makemdfa_Delta_dflt Ljava/lang/Object;
    checkcast java/lang/Long
    invokevirtual java/lang/Long/longValue()J
    goto icn_259_vr
icn_261_ts_got:
    checkcast java/lang/Long
    invokevirtual java/lang/Long/longValue()J
    goto icn_259_vr
icn_259_α:
    goto icn_260_α
icn_259_β:
    goto icn_243_seq_rf_1
icn_259_lr:
    putstatic rung36_jcon_mindfa/icn_259_pushlist Ljava/util/ArrayList;
    goto icn_261_α
icn_259_vr:
    invokestatic java/lang/Long/valueOf(J)Ljava/lang/Long;
    putstatic rung36_jcon_mindfa/icn_259_pushval Ljava/lang/Object;
    getstatic rung36_jcon_mindfa/icn_259_pushlist Ljava/util/ArrayList;
    getstatic rung36_jcon_mindfa/icn_259_pushval Ljava/lang/Object;
    invokevirtual java/util/ArrayList/add(Ljava/lang/Object;)Z
    pop
    getstatic rung36_jcon_mindfa/icn_259_pushlist Ljava/util/ArrayList;
    goto icn_243_seq_rg_1
;  VAR
icn_269_α:
    getstatic rung36_jcon_mindfa/icn_pv_makemdfa_elist Ljava/util/ArrayList;
    goto icn_268_lr
icn_269_β:
    goto icn_229_pump
;  VAR
icn_271_α:
    getstatic rung36_jcon_mindfa/icn_pv_makemdfa_Delta Ljava/util/HashMap;
    goto icn_270_ts_tr
icn_271_β:
    goto icn_229_pump
;  VAR
icn_273_α:
    getstatic rung36_jcon_mindfa/icn_pv_makemdfa_a Ljava/lang/String;
    goto icn_272_rrelay
icn_273_β:
    goto icn_272_lb
;  STR
icn_275_α:
    ldc ":"
    goto icn_274_rrelay
icn_275_β:
    goto icn_274_lb
;  VAR
icn_276_α:
    getstatic rung36_jcon_mindfa/icn_pv_makemdfa_q J
    goto icn_274_lrelay
icn_276_β:
    goto icn_229_pump
icn_274_lrelay:
    putstatic rung36_jcon_mindfa/icn_274_lc Ljava/lang/String;
    goto icn_274_lstore
icn_274_rrelay:
    putstatic rung36_jcon_mindfa/icn_274_rc Ljava/lang/String;
    goto icn_274_compute
icn_274_lb:
    goto icn_276_β
icn_274_α:
    iconst_0
    istore 93
    goto icn_276_α
icn_274_β:
    iconst_1
    istore 93
    goto icn_276_α
icn_274_lstore:
    iload 93
    ifeq icn_275_α
    goto icn_275_β
icn_274_compute:
    getstatic rung36_jcon_mindfa/icn_274_lc Ljava/lang/String;
    getstatic rung36_jcon_mindfa/icn_274_rc Ljava/lang/String;
    invokevirtual java/lang/String/concat(Ljava/lang/String;)Ljava/lang/String;
    goto icn_272_lrelay
icn_272_lrelay:
    putstatic rung36_jcon_mindfa/icn_272_lc Ljava/lang/String;
    goto icn_272_lstore
icn_272_rrelay:
    putstatic rung36_jcon_mindfa/icn_272_rc Ljava/lang/String;
    goto icn_272_compute
icn_272_lb:
    goto icn_274_β
icn_272_α:
    iconst_0
    istore 92
    goto icn_274_α
icn_272_β:
    iconst_1
    istore 92
    goto icn_274_α
icn_272_lstore:
    iload 92
    ifeq icn_273_α
    goto icn_273_β
icn_272_compute:
    getstatic rung36_jcon_mindfa/icn_272_lc Ljava/lang/String;
    getstatic rung36_jcon_mindfa/icn_272_rc Ljava/lang/String;
    invokevirtual java/lang/String/concat(Ljava/lang/String;)Ljava/lang/String;
    goto icn_270_ts_kr
icn_270_α:
    goto icn_271_α
icn_270_β:
    goto icn_272_β
icn_270_ts_tr:
    putstatic rung36_jcon_mindfa/icn_270_ts_tbl Ljava/util/HashMap;
    goto icn_272_α
icn_270_ts_kr:
    dup
    putstatic rung36_jcon_mindfa/icn_270_ts_key Ljava/lang/String;
    lconst_0
    putstatic rung36_jcon_mindfa/icn_270_ts_kval J
    getstatic rung36_jcon_mindfa/icn_270_ts_tbl Ljava/util/HashMap;
    getstatic rung36_jcon_mindfa/icn_270_ts_key Ljava/lang/String;
    invokevirtual java/util/HashMap/get(Ljava/lang/Object;)Ljava/lang/Object;
    dup
    ifnonnull icn_270_ts_got
    pop
    getstatic rung36_jcon_mindfa/icn_pv_makemdfa_Delta_dflt Ljava/lang/Object;
    checkcast java/lang/Long
    invokevirtual java/lang/Long/longValue()J
    goto icn_268_vr
icn_270_ts_got:
    checkcast java/lang/Long
    invokevirtual java/lang/Long/longValue()J
    goto icn_268_vr
icn_268_α:
    goto icn_269_α
icn_268_β:
    goto icn_229_pump
icn_268_lr:
    putstatic rung36_jcon_mindfa/icn_268_pushlist Ljava/util/ArrayList;
    goto icn_270_α
icn_268_vr:
    invokestatic java/lang/Long/valueOf(J)Ljava/lang/Long;
    putstatic rung36_jcon_mindfa/icn_268_pushval Ljava/lang/Object;
    getstatic rung36_jcon_mindfa/icn_268_pushlist Ljava/util/ArrayList;
    getstatic rung36_jcon_mindfa/icn_268_pushval Ljava/lang/Object;
    invokevirtual java/util/ArrayList/add(Ljava/lang/Object;)Z
    pop
    getstatic rung36_jcon_mindfa/icn_268_pushlist Ljava/util/ArrayList;
    goto icn_229_bdrain
    goto icn_243_α
icn_243_seq_rg_0:
    pop2
    goto icn_259_α
icn_243_seq_rg_1:
    pop2
    goto icn_268_α
icn_243_seq_rf_0:
    goto icn_259_α
icn_243_seq_rf_1:
    goto icn_268_α
icn_243_α:
    goto icn_244_α
icn_243_β:
    goto icn_268_β
;  VAR
icn_279_α:
    getstatic rung36_jcon_mindfa/icn_pv_makemdfa_echeck Ljava/util/HashMap;
    goto icn_278_ts_tr
icn_279_β:
    goto icn_277_succ
;  VAR
icn_281_α:
    getstatic rung36_jcon_mindfa/icn_pv_makemdfa_Delta Ljava/util/HashMap;
    goto icn_280_ts_tr
icn_281_β:
    goto icn_277_succ
;  VAR
icn_283_α:
    getstatic rung36_jcon_mindfa/icn_pv_makemdfa_a Ljava/lang/String;
    goto icn_282_rrelay
icn_283_β:
    goto icn_282_lb
;  STR
icn_285_α:
    ldc ":"
    goto icn_284_rrelay
icn_285_β:
    goto icn_284_lb
;  VAR
icn_286_α:
    getstatic rung36_jcon_mindfa/icn_pv_makemdfa_q J
    goto icn_284_lrelay
icn_286_β:
    goto icn_277_succ
icn_284_lrelay:
    putstatic rung36_jcon_mindfa/icn_284_lc Ljava/lang/String;
    goto icn_284_lstore
icn_284_rrelay:
    putstatic rung36_jcon_mindfa/icn_284_rc Ljava/lang/String;
    goto icn_284_compute
icn_284_lb:
    goto icn_286_β
icn_284_α:
    iconst_0
    istore 95
    goto icn_286_α
icn_284_β:
    iconst_1
    istore 95
    goto icn_286_α
icn_284_lstore:
    iload 95
    ifeq icn_285_α
    goto icn_285_β
icn_284_compute:
    getstatic rung36_jcon_mindfa/icn_284_lc Ljava/lang/String;
    getstatic rung36_jcon_mindfa/icn_284_rc Ljava/lang/String;
    invokevirtual java/lang/String/concat(Ljava/lang/String;)Ljava/lang/String;
    goto icn_282_lrelay
icn_282_lrelay:
    putstatic rung36_jcon_mindfa/icn_282_lc Ljava/lang/String;
    goto icn_282_lstore
icn_282_rrelay:
    putstatic rung36_jcon_mindfa/icn_282_rc Ljava/lang/String;
    goto icn_282_compute
icn_282_lb:
    goto icn_284_β
icn_282_α:
    iconst_0
    istore 94
    goto icn_284_α
icn_282_β:
    iconst_1
    istore 94
    goto icn_284_α
icn_282_lstore:
    iload 94
    ifeq icn_283_α
    goto icn_283_β
icn_282_compute:
    getstatic rung36_jcon_mindfa/icn_282_lc Ljava/lang/String;
    getstatic rung36_jcon_mindfa/icn_282_rc Ljava/lang/String;
    invokevirtual java/lang/String/concat(Ljava/lang/String;)Ljava/lang/String;
    goto icn_280_ts_kr
icn_280_α:
    goto icn_281_α
icn_280_β:
    goto icn_282_β
icn_280_ts_tr:
    putstatic rung36_jcon_mindfa/icn_280_ts_tbl Ljava/util/HashMap;
    goto icn_282_α
icn_280_ts_kr:
    dup
    putstatic rung36_jcon_mindfa/icn_280_ts_key Ljava/lang/String;
    lconst_0
    putstatic rung36_jcon_mindfa/icn_280_ts_kval J
    getstatic rung36_jcon_mindfa/icn_280_ts_tbl Ljava/util/HashMap;
    getstatic rung36_jcon_mindfa/icn_280_ts_key Ljava/lang/String;
    invokevirtual java/util/HashMap/get(Ljava/lang/Object;)Ljava/lang/Object;
    dup
    ifnonnull icn_280_ts_got
    pop
    getstatic rung36_jcon_mindfa/icn_pv_makemdfa_Delta_dflt Ljava/lang/Object;
    checkcast java/lang/Long
    invokevirtual java/lang/Long/longValue()J
    goto icn_278_ts_kr
icn_280_ts_got:
    checkcast java/lang/Long
    invokevirtual java/lang/Long/longValue()J
    goto icn_278_ts_kr
icn_278_α:
    goto icn_279_α
icn_278_β:
    goto icn_280_β
icn_278_ts_tr:
    putstatic rung36_jcon_mindfa/icn_278_ts_tbl Ljava/util/HashMap;
    goto icn_280_α
icn_278_ts_kr:
    dup2
    putstatic rung36_jcon_mindfa/icn_278_ts_kval J
    invokestatic java/lang/Long/toString(J)Ljava/lang/String;
    putstatic rung36_jcon_mindfa/icn_278_ts_key Ljava/lang/String;
    getstatic rung36_jcon_mindfa/icn_278_ts_tbl Ljava/util/HashMap;
    getstatic rung36_jcon_mindfa/icn_278_ts_key Ljava/lang/String;
    invokevirtual java/util/HashMap/get(Ljava/lang/Object;)Ljava/lang/Object;
    dup
    ifnonnull icn_278_ts_got
    pop
    getstatic rung36_jcon_mindfa/icn_pv_makemdfa_echeck_dflt Ljava/lang/Object;
    checkcast java/lang/Long
    invokevirtual java/lang/Long/longValue()J
    goto icn_277_cok
icn_278_ts_got:
    checkcast java/lang/Long
    invokevirtual java/lang/Long/longValue()J
    goto icn_277_cok
;  NULL
icn_277_α:
    goto icn_278_α
icn_277_β:
    goto icn_278_β
icn_277_cok:
    pop2
    goto icn_242_else
icn_277_succ:
    lconst_0
    goto icn_242_then
icn_242_then:
    pop2
    goto icn_243_α
icn_242_else:
    goto icn_229_pump
icn_242_α:
    goto icn_277_α
icn_242_β:
    goto icn_277_β
    goto icn_230_α
icn_230_seq_rg_0:
    pop2
    goto icn_242_α
icn_230_seq_rf_0:
    goto icn_242_α
icn_230_α:
    goto icn_231_α
icn_230_β:
    goto icn_242_β
icn_289_α:
    goto icn_225_top
icn_289_β:
    goto icn_225_top
icn_288_α:
    goto icn_289_α
icn_288_β:
    goto icn_288_bang_chk
icn_288_bang_adv:
    putstatic rung36_jcon_mindfa/icn_288_bang_str Ljava/lang/String;
    iconst_0
    putstatic rung36_jcon_mindfa/icn_288_bang_pos I
icn_288_bang_chk:
    getstatic rung36_jcon_mindfa/icn_288_bang_str Ljava/lang/String;
    invokevirtual java/lang/String/length()I
    getstatic rung36_jcon_mindfa/icn_288_bang_pos I
    if_icmple icn_225_top
    getstatic rung36_jcon_mindfa/icn_288_bang_str Ljava/lang/String;
    getstatic rung36_jcon_mindfa/icn_288_bang_pos I
    getstatic rung36_jcon_mindfa/icn_288_bang_pos I
    iconst_1
    iadd
    invokevirtual java/lang/String/substring(II)Ljava/lang/String;
    getstatic rung36_jcon_mindfa/icn_288_bang_pos I
    iconst_1
    iadd
    putstatic rung36_jcon_mindfa/icn_288_bang_pos I
    goto icn_287_store
icn_287_α:
    goto icn_288_α
icn_287_β:
    goto icn_288_β
icn_287_store:
    putstatic rung36_jcon_mindfa/icn_pv_makemdfa_a Ljava/lang/String;
    getstatic rung36_jcon_mindfa/icn_pv_makemdfa_a Ljava/lang/String;
    goto icn_229_gdrain
icn_229_gdrain:
    pop
    goto icn_230_α
icn_229_bdrain:
    pop2
icn_229_pump:
    goto icn_287_β
icn_229_α:
    goto icn_287_α
icn_229_β:
    goto icn_225_top
icn_225_wbstart:
    goto icn_229_α
icn_225_wbdrain:
    pop2
icn_225_top:
    goto icn_226_α
icn_225_α:
    goto icn_226_α
icn_225_β:
    goto icn_216_α
;  VAR
icn_291_α:
    getstatic rung36_jcon_mindfa/icn_pv_makemdfa_q0 J
    goto icn_290_tsa_vr
icn_291_β:
    goto icn_225_α
;  VAR
icn_292_α:
    getstatic rung36_jcon_mindfa/icn_pv_makemdfa_q0 J
    goto icn_290_tsa_kr
icn_292_β:
    goto icn_225_α
icn_290_α:
    goto icn_291_α
icn_290_β:
    goto icn_225_α
icn_290_tsa_vr:
    dup
    putstatic rung36_jcon_mindfa/icn_290_tsa_vl Ljava/lang/String;
    goto icn_292_α
icn_290_tsa_kr:
    putstatic rung36_jcon_mindfa/icn_290_tsa_ks Ljava/lang/String;
    goto icn_290_tsa_put
icn_290_tsa_put:
    getstatic rung36_jcon_mindfa/icn_pv_makemdfa_echeck Ljava/util/HashMap;
    getstatic rung36_jcon_mindfa/icn_290_tsa_ks Ljava/lang/String;
    getstatic rung36_jcon_mindfa/icn_290_tsa_vl Ljava/lang/String;
    invokevirtual java/util/HashMap/put(Ljava/lang/Object;Ljava/lang/Object;)Ljava/lang/Object;
    pop
    getstatic rung36_jcon_mindfa/icn_290_tsa_vl Ljava/lang/String;
    goto icn_makemdfa_s12_sdrain
icn_makemdfa_s12_sdrain:
    pop
    goto icn_225_α
icn_294_α:
    goto icn_290_α
icn_294_β:
    goto icn_290_α
icn_293_α:
    goto icn_294_α
icn_293_β:
    goto icn_294_β
icn_293_store:
    putstatic rung36_jcon_mindfa/icn_pv_makemdfa_echeck Ljava/util/HashMap;
    getstatic rung36_jcon_mindfa/icn_pv_makemdfa_echeck Ljava/util/HashMap;
    goto icn_makemdfa_s11_sdrain
icn_makemdfa_s11_sdrain:
    pop
    goto icn_290_α
;  VAR
icn_296_α:
    getstatic rung36_jcon_mindfa/icn_pv_makemdfa_elist Ljava/util/ArrayList;
    goto icn_295_lr
icn_296_β:
    goto icn_293_α
;  VAR
icn_297_α:
    getstatic rung36_jcon_mindfa/icn_pv_makemdfa_q0 J
    goto icn_295_vr
icn_297_β:
    goto icn_293_α
icn_295_α:
    goto icn_296_α
icn_295_β:
    goto icn_293_α
icn_295_lr:
    putstatic rung36_jcon_mindfa/icn_295_pushlist Ljava/util/ArrayList;
    goto icn_297_α
icn_295_vr:
    putstatic rung36_jcon_mindfa/icn_295_pushval Ljava/lang/Object;
    getstatic rung36_jcon_mindfa/icn_295_pushlist Ljava/util/ArrayList;
    getstatic rung36_jcon_mindfa/icn_295_pushval Ljava/lang/Object;
    invokevirtual java/util/ArrayList/add(Ljava/lang/Object;)Z
    pop
    getstatic rung36_jcon_mindfa/icn_295_pushlist Ljava/util/ArrayList;
    goto icn_makemdfa_s10_sdrain
icn_makemdfa_s10_sdrain:
    pop
    goto icn_293_α
;  VAR
icn_299_α:
    getstatic rung36_jcon_mindfa/icn_pv_makemdfa_tlist Ljava/util/ArrayList;
    goto icn_298_lr
icn_299_β:
    goto icn_295_α
;  VAR
icn_300_α:
    getstatic rung36_jcon_mindfa/icn_pv_makemdfa_q0 J
    goto icn_298_vr
icn_300_β:
    goto icn_295_α
icn_298_α:
    goto icn_299_α
icn_298_β:
    goto icn_295_α
icn_298_lr:
    putstatic rung36_jcon_mindfa/icn_298_pushlist Ljava/util/ArrayList;
    goto icn_300_α
icn_298_vr:
    putstatic rung36_jcon_mindfa/icn_298_pushval Ljava/lang/Object;
    getstatic rung36_jcon_mindfa/icn_298_pushlist Ljava/util/ArrayList;
    getstatic rung36_jcon_mindfa/icn_298_pushval Ljava/lang/Object;
    invokevirtual java/util/ArrayList/add(Ljava/lang/Object;)Z
    pop
    getstatic rung36_jcon_mindfa/icn_298_pushlist Ljava/util/ArrayList;
    goto icn_makemdfa_s9_sdrain
icn_makemdfa_s9_sdrain:
    pop
    goto icn_295_α
;  VAR
icn_303_α:
    getstatic rung36_jcon_mindfa/icn_pv_makemdfa_etab Ljava/util/HashMap;
    goto icn_302_arg1
icn_303_β:
    goto icn_298_α
icn_302_arg1:
    putstatic rung36_jcon_mindfa/icn_arg_1 J
    goto icn_302_docall
icn_304_α:
    goto icn_298_α
icn_304_β:
    goto icn_298_α
icn_302_arg0:
    putstatic rung36_jcon_mindfa/icn_arg_0 J
    goto icn_303_α
icn_302_α:
    goto icn_304_α
icn_302_β:
    goto icn_303_β
icn_302_docall:
    getstatic rung36_jcon_mindfa/icn_7_I J
    lstore 152
    getstatic rung36_jcon_mindfa/icn_7_bound J
    lstore 154
    getstatic rung36_jcon_mindfa/icn_7_e1cur J
    lstore 156
    getstatic rung36_jcon_mindfa/icn_7_e1val J
    lstore 158
    getstatic rung36_jcon_mindfa/icn_7_e2val J
    lstore 160
    getstatic rung36_jcon_mindfa/icn_93_I J
    lstore 162
    getstatic rung36_jcon_mindfa/icn_93_bound J
    lstore 164
    getstatic rung36_jcon_mindfa/icn_93_e1cur J
    lstore 166
    getstatic rung36_jcon_mindfa/icn_93_e1val J
    lstore 168
    getstatic rung36_jcon_mindfa/icn_93_e2val J
    lstore 170
    getstatic rung36_jcon_mindfa/icn_126_ts_kval J
    lstore 172
    getstatic rung36_jcon_mindfa/icn_142_ts_kval J
    lstore 174
    getstatic rung36_jcon_mindfa/icn_165_ts_kval J
    lstore 176
    getstatic rung36_jcon_mindfa/icn_206_ts_kval J
    lstore 178
    getstatic rung36_jcon_mindfa/icn_pv_makemdfa_q0 J
    lstore 180
    getstatic rung36_jcon_mindfa/icn_pv_makemdfa_D J
    lstore 182
    getstatic rung36_jcon_mindfa/icn_pv_makemdfa_q J
    lstore 184
    getstatic rung36_jcon_mindfa/icn_231_tsa_vl J
    lstore 186
    getstatic rung36_jcon_mindfa/icn_244_tsa_vl J
    lstore 188
    getstatic rung36_jcon_mindfa/icn_245_ts_kval J
    lstore 190
    getstatic rung36_jcon_mindfa/icn_252_ts_kval J
    lstore 192
    getstatic rung36_jcon_mindfa/icn_261_ts_kval J
    lstore 194
    getstatic rung36_jcon_mindfa/icn_270_ts_kval J
    lstore 196
    getstatic rung36_jcon_mindfa/icn_278_ts_kval J
    lstore 198
    getstatic rung36_jcon_mindfa/icn_280_ts_kval J
    lstore 200
    invokestatic rung36_jcon_mindfa/icn_equiv()V
    lload 152
    putstatic rung36_jcon_mindfa/icn_7_I J
    lload 154
    putstatic rung36_jcon_mindfa/icn_7_bound J
    lload 156
    putstatic rung36_jcon_mindfa/icn_7_e1cur J
    lload 158
    putstatic rung36_jcon_mindfa/icn_7_e1val J
    lload 160
    putstatic rung36_jcon_mindfa/icn_7_e2val J
    lload 162
    putstatic rung36_jcon_mindfa/icn_93_I J
    lload 164
    putstatic rung36_jcon_mindfa/icn_93_bound J
    lload 166
    putstatic rung36_jcon_mindfa/icn_93_e1cur J
    lload 168
    putstatic rung36_jcon_mindfa/icn_93_e1val J
    lload 170
    putstatic rung36_jcon_mindfa/icn_93_e2val J
    lload 172
    putstatic rung36_jcon_mindfa/icn_126_ts_kval J
    lload 174
    putstatic rung36_jcon_mindfa/icn_142_ts_kval J
    lload 176
    putstatic rung36_jcon_mindfa/icn_165_ts_kval J
    lload 178
    putstatic rung36_jcon_mindfa/icn_206_ts_kval J
    lload 180
    putstatic rung36_jcon_mindfa/icn_pv_makemdfa_q0 J
    lload 182
    putstatic rung36_jcon_mindfa/icn_pv_makemdfa_D J
    lload 184
    putstatic rung36_jcon_mindfa/icn_pv_makemdfa_q J
    lload 186
    putstatic rung36_jcon_mindfa/icn_231_tsa_vl J
    lload 188
    putstatic rung36_jcon_mindfa/icn_244_tsa_vl J
    lload 190
    putstatic rung36_jcon_mindfa/icn_245_ts_kval J
    lload 192
    putstatic rung36_jcon_mindfa/icn_252_ts_kval J
    lload 194
    putstatic rung36_jcon_mindfa/icn_261_ts_kval J
    lload 196
    putstatic rung36_jcon_mindfa/icn_270_ts_kval J
    lload 198
    putstatic rung36_jcon_mindfa/icn_278_ts_kval J
    lload 200
    putstatic rung36_jcon_mindfa/icn_280_ts_kval J
    getstatic rung36_jcon_mindfa/icn_failed B
    ifne icn_302_after_call
    getstatic rung36_jcon_mindfa/icn_retval J
    goto icn_301_store
icn_302_after_call:
    goto icn_298_α
icn_301_α:
    goto icn_302_α
icn_301_β:
    goto icn_302_β
icn_301_store:
    putstatic rung36_jcon_mindfa/icn_pv_makemdfa_q0 J
    getstatic rung36_jcon_mindfa/icn_pv_makemdfa_q0 J
    goto icn_makemdfa_s8_sdrain
icn_makemdfa_s8_sdrain:
    pop2
    goto icn_298_α
icn_306_α:
    goto icn_301_α
icn_306_β:
    goto icn_301_α
icn_305_α:
    goto icn_306_α
icn_305_β:
    goto icn_306_β
icn_305_store:
    putstatic rung36_jcon_mindfa/icn_pv_makemdfa_Delta Ljava/util/HashMap;
    getstatic rung36_jcon_mindfa/icn_pv_makemdfa_Delta Ljava/util/HashMap;
    goto icn_makemdfa_s7_sdrain
icn_makemdfa_s7_sdrain:
    pop
    goto icn_301_α
icn_308_α:
    new java/util/ArrayList
    dup
    invokespecial java/util/ArrayList/<init>()V
    putstatic rung36_jcon_mindfa/icn_308_mklist Ljava/util/ArrayList;
    getstatic rung36_jcon_mindfa/icn_308_mklist Ljava/util/ArrayList;
    goto icn_307_store
icn_308_β:
    goto icn_305_α
icn_307_α:
    goto icn_308_α
icn_307_β:
    goto icn_308_β
icn_307_store:
    putstatic rung36_jcon_mindfa/icn_pv_makemdfa_elist Ljava/util/ArrayList;
    getstatic rung36_jcon_mindfa/icn_pv_makemdfa_elist Ljava/util/ArrayList;
    goto icn_makemdfa_s6_sdrain
icn_makemdfa_s6_sdrain:
    pop
    goto icn_305_α
icn_310_α:
    new java/util/ArrayList
    dup
    invokespecial java/util/ArrayList/<init>()V
    putstatic rung36_jcon_mindfa/icn_310_mklist Ljava/util/ArrayList;
    getstatic rung36_jcon_mindfa/icn_310_mklist Ljava/util/ArrayList;
    goto icn_309_store
icn_310_β:
    goto icn_307_α
icn_309_α:
    goto icn_310_α
icn_309_β:
    goto icn_310_β
icn_309_store:
    putstatic rung36_jcon_mindfa/icn_pv_makemdfa_tlist Ljava/util/ArrayList;
    getstatic rung36_jcon_mindfa/icn_pv_makemdfa_tlist Ljava/util/ArrayList;
    goto icn_makemdfa_s5_sdrain
icn_makemdfa_s5_sdrain:
    pop
    goto icn_307_α
;  VAR
icn_314_α:
    getstatic rung36_jcon_mindfa/icn_pv_makemdfa_p Ljava/lang/String;
    goto icn_313_rhsok
icn_314_β:
    goto icn_312_seq_rf_0
icn_313_α:
    goto icn_314_α
icn_313_β:
    goto icn_314_β
icn_313_rhsok:
    putstatic rung36_jcon_mindfa/icn_313_augtemp J
    getstatic rung36_jcon_mindfa/icn_pv_makemdfa_qset J
    getstatic rung36_jcon_mindfa/icn_313_augtemp J
    ladd
    dup2
    putstatic rung36_jcon_mindfa/icn_pv_makemdfa_qset J
    goto icn_312_seq_rg_0
icn_317_α:
    goto icn_312_seq_rf_1
icn_317_β:
    goto icn_312_seq_rf_1
;  VAR
icn_319_α:
    getstatic rung36_jcon_mindfa/icn_pv_makemdfa_etab Ljava/util/HashMap;
    goto icn_318_arg1
icn_319_β:
    goto icn_317_α
icn_318_arg1:
    putstatic rung36_jcon_mindfa/icn_arg_1 J
    goto icn_318_docall
;  VAR
icn_320_α:
    getstatic rung36_jcon_mindfa/icn_pv_makemdfa_p Ljava/lang/String;
    goto icn_318_arg0
icn_320_β:
    goto icn_317_α
icn_318_arg0:
    putstatic rung36_jcon_mindfa/icn_arg_str_0 Ljava/lang/String;
    lconst_0
    putstatic rung36_jcon_mindfa/icn_arg_0 J
    goto icn_319_α
icn_318_α:
    goto icn_320_α
icn_318_β:
    goto icn_319_β
icn_318_docall:
    getstatic rung36_jcon_mindfa/icn_7_I J
    lstore 152
    getstatic rung36_jcon_mindfa/icn_7_bound J
    lstore 154
    getstatic rung36_jcon_mindfa/icn_7_e1cur J
    lstore 156
    getstatic rung36_jcon_mindfa/icn_7_e1val J
    lstore 158
    getstatic rung36_jcon_mindfa/icn_7_e2val J
    lstore 160
    getstatic rung36_jcon_mindfa/icn_93_I J
    lstore 162
    getstatic rung36_jcon_mindfa/icn_93_bound J
    lstore 164
    getstatic rung36_jcon_mindfa/icn_93_e1cur J
    lstore 166
    getstatic rung36_jcon_mindfa/icn_93_e1val J
    lstore 168
    getstatic rung36_jcon_mindfa/icn_93_e2val J
    lstore 170
    getstatic rung36_jcon_mindfa/icn_126_ts_kval J
    lstore 172
    getstatic rung36_jcon_mindfa/icn_142_ts_kval J
    lstore 174
    getstatic rung36_jcon_mindfa/icn_165_ts_kval J
    lstore 176
    getstatic rung36_jcon_mindfa/icn_206_ts_kval J
    lstore 178
    getstatic rung36_jcon_mindfa/icn_pv_makemdfa_q0 J
    lstore 180
    getstatic rung36_jcon_mindfa/icn_pv_makemdfa_D J
    lstore 182
    getstatic rung36_jcon_mindfa/icn_pv_makemdfa_q J
    lstore 184
    getstatic rung36_jcon_mindfa/icn_231_tsa_vl J
    lstore 186
    getstatic rung36_jcon_mindfa/icn_244_tsa_vl J
    lstore 188
    getstatic rung36_jcon_mindfa/icn_245_ts_kval J
    lstore 190
    getstatic rung36_jcon_mindfa/icn_252_ts_kval J
    lstore 192
    getstatic rung36_jcon_mindfa/icn_261_ts_kval J
    lstore 194
    getstatic rung36_jcon_mindfa/icn_270_ts_kval J
    lstore 196
    getstatic rung36_jcon_mindfa/icn_278_ts_kval J
    lstore 198
    getstatic rung36_jcon_mindfa/icn_280_ts_kval J
    lstore 200
    getstatic rung36_jcon_mindfa/icn_313_augtemp J
    lstore 202
    invokestatic rung36_jcon_mindfa/icn_equiv()V
    lload 152
    putstatic rung36_jcon_mindfa/icn_7_I J
    lload 154
    putstatic rung36_jcon_mindfa/icn_7_bound J
    lload 156
    putstatic rung36_jcon_mindfa/icn_7_e1cur J
    lload 158
    putstatic rung36_jcon_mindfa/icn_7_e1val J
    lload 160
    putstatic rung36_jcon_mindfa/icn_7_e2val J
    lload 162
    putstatic rung36_jcon_mindfa/icn_93_I J
    lload 164
    putstatic rung36_jcon_mindfa/icn_93_bound J
    lload 166
    putstatic rung36_jcon_mindfa/icn_93_e1cur J
    lload 168
    putstatic rung36_jcon_mindfa/icn_93_e1val J
    lload 170
    putstatic rung36_jcon_mindfa/icn_93_e2val J
    lload 172
    putstatic rung36_jcon_mindfa/icn_126_ts_kval J
    lload 174
    putstatic rung36_jcon_mindfa/icn_142_ts_kval J
    lload 176
    putstatic rung36_jcon_mindfa/icn_165_ts_kval J
    lload 178
    putstatic rung36_jcon_mindfa/icn_206_ts_kval J
    lload 180
    putstatic rung36_jcon_mindfa/icn_pv_makemdfa_q0 J
    lload 182
    putstatic rung36_jcon_mindfa/icn_pv_makemdfa_D J
    lload 184
    putstatic rung36_jcon_mindfa/icn_pv_makemdfa_q J
    lload 186
    putstatic rung36_jcon_mindfa/icn_231_tsa_vl J
    lload 188
    putstatic rung36_jcon_mindfa/icn_244_tsa_vl J
    lload 190
    putstatic rung36_jcon_mindfa/icn_245_ts_kval J
    lload 192
    putstatic rung36_jcon_mindfa/icn_252_ts_kval J
    lload 194
    putstatic rung36_jcon_mindfa/icn_261_ts_kval J
    lload 196
    putstatic rung36_jcon_mindfa/icn_270_ts_kval J
    lload 198
    putstatic rung36_jcon_mindfa/icn_278_ts_kval J
    lload 200
    putstatic rung36_jcon_mindfa/icn_280_ts_kval J
    lload 202
    putstatic rung36_jcon_mindfa/icn_313_augtemp J
    getstatic rung36_jcon_mindfa/icn_failed B
    ifne icn_318_after_call
    getstatic rung36_jcon_mindfa/icn_retval J
    goto icn_316_alt_g0
icn_318_after_call:
    goto icn_317_α
icn_316_alt_g0:
    putstatic rung36_jcon_mindfa/icn_316_alt_val J
    sipush 1
    putstatic rung36_jcon_mindfa/icn_316_alt_gate I
    getstatic rung36_jcon_mindfa/icn_316_alt_val J
    goto icn_315_store
icn_316_alt_g1:
    putstatic rung36_jcon_mindfa/icn_316_alt_val J
    sipush 2
    putstatic rung36_jcon_mindfa/icn_316_alt_gate I
    getstatic rung36_jcon_mindfa/icn_316_alt_val J
    goto icn_315_store
icn_316_α:
    iconst_0
    putstatic rung36_jcon_mindfa/icn_316_alt_gate I
    goto icn_318_α
icn_316_β:
    getstatic rung36_jcon_mindfa/icn_316_alt_gate I
    tableswitch 1 2
        icn_318_β
        icn_317_β
        default: icn_312_seq_rf_1
icn_315_α:
    goto icn_316_α
icn_315_β:
    goto icn_316_β
icn_315_store:
    putstatic rung36_jcon_mindfa/icn_pv_makemdfa_plike J
    getstatic rung36_jcon_mindfa/icn_pv_makemdfa_plike J
    goto icn_312_seq_rg_1
;  VAR
icn_325_α:
    getstatic rung36_jcon_mindfa/icn_pv_makemdfa_q J
    goto icn_324_alt_g1
icn_325_β:
    goto icn_321_pump
;  VAR
icn_327_α:
    getstatic rung36_jcon_mindfa/icn_pv_makemdfa_etab Ljava/util/HashMap;
    goto icn_326_arg1
icn_327_β:
    goto icn_325_α
icn_326_arg1:
    putstatic rung36_jcon_mindfa/icn_arg_1 J
    goto icn_326_docall
;  VAR
icn_328_α:
    getstatic rung36_jcon_mindfa/icn_pv_makemdfa_q J
    goto icn_326_arg0
icn_328_β:
    goto icn_325_α
icn_326_arg0:
    putstatic rung36_jcon_mindfa/icn_arg_str_0 Ljava/lang/String;
    lconst_0
    putstatic rung36_jcon_mindfa/icn_arg_0 J
    goto icn_327_α
icn_326_α:
    goto icn_328_α
icn_326_β:
    goto icn_327_β
icn_326_docall:
    getstatic rung36_jcon_mindfa/icn_7_I J
    lstore 152
    getstatic rung36_jcon_mindfa/icn_7_bound J
    lstore 154
    getstatic rung36_jcon_mindfa/icn_7_e1cur J
    lstore 156
    getstatic rung36_jcon_mindfa/icn_7_e1val J
    lstore 158
    getstatic rung36_jcon_mindfa/icn_7_e2val J
    lstore 160
    getstatic rung36_jcon_mindfa/icn_93_I J
    lstore 162
    getstatic rung36_jcon_mindfa/icn_93_bound J
    lstore 164
    getstatic rung36_jcon_mindfa/icn_93_e1cur J
    lstore 166
    getstatic rung36_jcon_mindfa/icn_93_e1val J
    lstore 168
    getstatic rung36_jcon_mindfa/icn_93_e2val J
    lstore 170
    getstatic rung36_jcon_mindfa/icn_126_ts_kval J
    lstore 172
    getstatic rung36_jcon_mindfa/icn_142_ts_kval J
    lstore 174
    getstatic rung36_jcon_mindfa/icn_165_ts_kval J
    lstore 176
    getstatic rung36_jcon_mindfa/icn_206_ts_kval J
    lstore 178
    getstatic rung36_jcon_mindfa/icn_pv_makemdfa_q0 J
    lstore 180
    getstatic rung36_jcon_mindfa/icn_pv_makemdfa_D J
    lstore 182
    getstatic rung36_jcon_mindfa/icn_pv_makemdfa_q J
    lstore 184
    getstatic rung36_jcon_mindfa/icn_231_tsa_vl J
    lstore 186
    getstatic rung36_jcon_mindfa/icn_244_tsa_vl J
    lstore 188
    getstatic rung36_jcon_mindfa/icn_245_ts_kval J
    lstore 190
    getstatic rung36_jcon_mindfa/icn_252_ts_kval J
    lstore 192
    getstatic rung36_jcon_mindfa/icn_261_ts_kval J
    lstore 194
    getstatic rung36_jcon_mindfa/icn_270_ts_kval J
    lstore 196
    getstatic rung36_jcon_mindfa/icn_278_ts_kval J
    lstore 198
    getstatic rung36_jcon_mindfa/icn_280_ts_kval J
    lstore 200
    getstatic rung36_jcon_mindfa/icn_313_augtemp J
    lstore 202
    getstatic rung36_jcon_mindfa/icn_316_alt_val J
    lstore 204
    getstatic rung36_jcon_mindfa/icn_pv_makemdfa_plike J
    lstore 206
    invokestatic rung36_jcon_mindfa/icn_equiv()V
    lload 152
    putstatic rung36_jcon_mindfa/icn_7_I J
    lload 154
    putstatic rung36_jcon_mindfa/icn_7_bound J
    lload 156
    putstatic rung36_jcon_mindfa/icn_7_e1cur J
    lload 158
    putstatic rung36_jcon_mindfa/icn_7_e1val J
    lload 160
    putstatic rung36_jcon_mindfa/icn_7_e2val J
    lload 162
    putstatic rung36_jcon_mindfa/icn_93_I J
    lload 164
    putstatic rung36_jcon_mindfa/icn_93_bound J
    lload 166
    putstatic rung36_jcon_mindfa/icn_93_e1cur J
    lload 168
    putstatic rung36_jcon_mindfa/icn_93_e1val J
    lload 170
    putstatic rung36_jcon_mindfa/icn_93_e2val J
    lload 172
    putstatic rung36_jcon_mindfa/icn_126_ts_kval J
    lload 174
    putstatic rung36_jcon_mindfa/icn_142_ts_kval J
    lload 176
    putstatic rung36_jcon_mindfa/icn_165_ts_kval J
    lload 178
    putstatic rung36_jcon_mindfa/icn_206_ts_kval J
    lload 180
    putstatic rung36_jcon_mindfa/icn_pv_makemdfa_q0 J
    lload 182
    putstatic rung36_jcon_mindfa/icn_pv_makemdfa_D J
    lload 184
    putstatic rung36_jcon_mindfa/icn_pv_makemdfa_q J
    lload 186
    putstatic rung36_jcon_mindfa/icn_231_tsa_vl J
    lload 188
    putstatic rung36_jcon_mindfa/icn_244_tsa_vl J
    lload 190
    putstatic rung36_jcon_mindfa/icn_245_ts_kval J
    lload 192
    putstatic rung36_jcon_mindfa/icn_252_ts_kval J
    lload 194
    putstatic rung36_jcon_mindfa/icn_261_ts_kval J
    lload 196
    putstatic rung36_jcon_mindfa/icn_270_ts_kval J
    lload 198
    putstatic rung36_jcon_mindfa/icn_278_ts_kval J
    lload 200
    putstatic rung36_jcon_mindfa/icn_280_ts_kval J
    lload 202
    putstatic rung36_jcon_mindfa/icn_313_augtemp J
    lload 204
    putstatic rung36_jcon_mindfa/icn_316_alt_val J
    lload 206
    putstatic rung36_jcon_mindfa/icn_pv_makemdfa_plike J
    getstatic rung36_jcon_mindfa/icn_failed B
    ifne icn_326_after_call
    getstatic rung36_jcon_mindfa/icn_retval J
    goto icn_324_alt_g0
icn_326_after_call:
    goto icn_325_α
icn_324_alt_g0:
    putstatic rung36_jcon_mindfa/icn_324_alt_val J
    sipush 1
    putstatic rung36_jcon_mindfa/icn_324_alt_gate I
    getstatic rung36_jcon_mindfa/icn_324_alt_val J
    goto icn_323_rhsok
icn_324_alt_g1:
    pop
    lconst_0
    putstatic rung36_jcon_mindfa/icn_324_alt_val J
    sipush 2
    putstatic rung36_jcon_mindfa/icn_324_alt_gate I
    getstatic rung36_jcon_mindfa/icn_324_alt_val J
    goto icn_323_rhsok
icn_324_α:
    iconst_0
    putstatic rung36_jcon_mindfa/icn_324_alt_gate I
    goto icn_326_α
icn_324_β:
    getstatic rung36_jcon_mindfa/icn_324_alt_gate I
    tableswitch 1 2
        icn_326_β
        icn_325_β
        default: icn_321_pump
icn_323_α:
    goto icn_324_α
icn_323_β:
    goto icn_324_β
icn_323_rhsok:
    putstatic rung36_jcon_mindfa/icn_323_augtemp J
    getstatic rung36_jcon_mindfa/icn_pv_makemdfa_plike J
    getstatic rung36_jcon_mindfa/icn_323_augtemp J
    ladd
    dup2
    putstatic rung36_jcon_mindfa/icn_pv_makemdfa_plike J
    goto icn_321_bdrain
;  VAR
icn_331_α:
    getstatic rung36_jcon_mindfa/icn_gvar_distab Ljava/util/HashMap;
    goto icn_330_ts_tr
icn_331_β:
    goto icn_329_succ
icn_332_α:
    goto icn_329_succ
icn_332_β:
    goto icn_329_succ
icn_330_α:
    goto icn_331_α
icn_330_β:
    goto icn_332_β
icn_330_ts_tr:
    putstatic rung36_jcon_mindfa/icn_330_ts_tbl Ljava/util/HashMap;
    goto icn_332_α
icn_330_ts_kr:
    dup2
    putstatic rung36_jcon_mindfa/icn_330_ts_kval J
    invokestatic java/lang/Long/toString(J)Ljava/lang/String;
    putstatic rung36_jcon_mindfa/icn_330_ts_key Ljava/lang/String;
    getstatic rung36_jcon_mindfa/icn_330_ts_tbl Ljava/util/HashMap;
    getstatic rung36_jcon_mindfa/icn_330_ts_key Ljava/lang/String;
    invokevirtual java/util/HashMap/get(Ljava/lang/Object;)Ljava/lang/Object;
    dup
    ifnonnull icn_330_ts_got
    pop
    lconst_0
    goto icn_329_cok
icn_330_ts_got:
    checkcast java/lang/Long
    invokevirtual java/lang/Long/longValue()J
    goto icn_329_cok
;  NULL
icn_329_α:
    goto icn_330_α
icn_329_β:
    goto icn_330_β
icn_329_cok:
    pop2
    goto icn_322_else
icn_329_succ:
    lconst_0
    goto icn_322_then
icn_322_then:
    pop2
    goto icn_323_α
icn_322_else:
    goto icn_321_pump
icn_322_α:
    goto icn_329_α
icn_322_β:
    goto icn_329_β
;  VAR
icn_337_α:
    getstatic rung36_jcon_mindfa/icn_pv_makemdfa_qset Ljava/lang/String;
    goto icn_336_arg1
icn_337_β:
    goto icn_312_seq_rf_2
icn_336_arg1:
    putstatic rung36_jcon_mindfa/icn_arg_str_1 Ljava/lang/String;
    lconst_0
    putstatic rung36_jcon_mindfa/icn_arg_1 J
    goto icn_336_docall
icn_338_α:
    goto icn_312_seq_rf_2
icn_338_β:
    goto icn_312_seq_rf_2
icn_336_arg0:
    putstatic rung36_jcon_mindfa/icn_arg_0 J
    goto icn_337_α
icn_336_α:
    goto icn_338_α
icn_336_β:
    goto icn_337_β
icn_336_docall:
    getstatic rung36_jcon_mindfa/icn_7_I J
    lstore 152
    getstatic rung36_jcon_mindfa/icn_7_bound J
    lstore 154
    getstatic rung36_jcon_mindfa/icn_7_e1cur J
    lstore 156
    getstatic rung36_jcon_mindfa/icn_7_e1val J
    lstore 158
    getstatic rung36_jcon_mindfa/icn_7_e2val J
    lstore 160
    getstatic rung36_jcon_mindfa/icn_93_I J
    lstore 162
    getstatic rung36_jcon_mindfa/icn_93_bound J
    lstore 164
    getstatic rung36_jcon_mindfa/icn_93_e1cur J
    lstore 166
    getstatic rung36_jcon_mindfa/icn_93_e1val J
    lstore 168
    getstatic rung36_jcon_mindfa/icn_93_e2val J
    lstore 170
    getstatic rung36_jcon_mindfa/icn_126_ts_kval J
    lstore 172
    getstatic rung36_jcon_mindfa/icn_142_ts_kval J
    lstore 174
    getstatic rung36_jcon_mindfa/icn_165_ts_kval J
    lstore 176
    getstatic rung36_jcon_mindfa/icn_206_ts_kval J
    lstore 178
    getstatic rung36_jcon_mindfa/icn_pv_makemdfa_q0 J
    lstore 180
    getstatic rung36_jcon_mindfa/icn_pv_makemdfa_D J
    lstore 182
    getstatic rung36_jcon_mindfa/icn_pv_makemdfa_q J
    lstore 184
    getstatic rung36_jcon_mindfa/icn_231_tsa_vl J
    lstore 186
    getstatic rung36_jcon_mindfa/icn_244_tsa_vl J
    lstore 188
    getstatic rung36_jcon_mindfa/icn_245_ts_kval J
    lstore 190
    getstatic rung36_jcon_mindfa/icn_252_ts_kval J
    lstore 192
    getstatic rung36_jcon_mindfa/icn_261_ts_kval J
    lstore 194
    getstatic rung36_jcon_mindfa/icn_270_ts_kval J
    lstore 196
    getstatic rung36_jcon_mindfa/icn_278_ts_kval J
    lstore 198
    getstatic rung36_jcon_mindfa/icn_280_ts_kval J
    lstore 200
    getstatic rung36_jcon_mindfa/icn_313_augtemp J
    lstore 202
    getstatic rung36_jcon_mindfa/icn_316_alt_val J
    lstore 204
    getstatic rung36_jcon_mindfa/icn_pv_makemdfa_plike J
    lstore 206
    getstatic rung36_jcon_mindfa/icn_324_alt_val J
    lstore 208
    getstatic rung36_jcon_mindfa/icn_323_augtemp J
    lstore 210
    getstatic rung36_jcon_mindfa/icn_330_ts_kval J
    lstore 212
    invokestatic rung36_jcon_mindfa/icn_diff()V
    lload 152
    putstatic rung36_jcon_mindfa/icn_7_I J
    lload 154
    putstatic rung36_jcon_mindfa/icn_7_bound J
    lload 156
    putstatic rung36_jcon_mindfa/icn_7_e1cur J
    lload 158
    putstatic rung36_jcon_mindfa/icn_7_e1val J
    lload 160
    putstatic rung36_jcon_mindfa/icn_7_e2val J
    lload 162
    putstatic rung36_jcon_mindfa/icn_93_I J
    lload 164
    putstatic rung36_jcon_mindfa/icn_93_bound J
    lload 166
    putstatic rung36_jcon_mindfa/icn_93_e1cur J
    lload 168
    putstatic rung36_jcon_mindfa/icn_93_e1val J
    lload 170
    putstatic rung36_jcon_mindfa/icn_93_e2val J
    lload 172
    putstatic rung36_jcon_mindfa/icn_126_ts_kval J
    lload 174
    putstatic rung36_jcon_mindfa/icn_142_ts_kval J
    lload 176
    putstatic rung36_jcon_mindfa/icn_165_ts_kval J
    lload 178
    putstatic rung36_jcon_mindfa/icn_206_ts_kval J
    lload 180
    putstatic rung36_jcon_mindfa/icn_pv_makemdfa_q0 J
    lload 182
    putstatic rung36_jcon_mindfa/icn_pv_makemdfa_D J
    lload 184
    putstatic rung36_jcon_mindfa/icn_pv_makemdfa_q J
    lload 186
    putstatic rung36_jcon_mindfa/icn_231_tsa_vl J
    lload 188
    putstatic rung36_jcon_mindfa/icn_244_tsa_vl J
    lload 190
    putstatic rung36_jcon_mindfa/icn_245_ts_kval J
    lload 192
    putstatic rung36_jcon_mindfa/icn_252_ts_kval J
    lload 194
    putstatic rung36_jcon_mindfa/icn_261_ts_kval J
    lload 196
    putstatic rung36_jcon_mindfa/icn_270_ts_kval J
    lload 198
    putstatic rung36_jcon_mindfa/icn_278_ts_kval J
    lload 200
    putstatic rung36_jcon_mindfa/icn_280_ts_kval J
    lload 202
    putstatic rung36_jcon_mindfa/icn_313_augtemp J
    lload 204
    putstatic rung36_jcon_mindfa/icn_316_alt_val J
    lload 206
    putstatic rung36_jcon_mindfa/icn_pv_makemdfa_plike J
    lload 208
    putstatic rung36_jcon_mindfa/icn_324_alt_val J
    lload 210
    putstatic rung36_jcon_mindfa/icn_323_augtemp J
    lload 212
    putstatic rung36_jcon_mindfa/icn_330_ts_kval J
    getstatic rung36_jcon_mindfa/icn_failed B
    ifne icn_336_after_call
    getstatic rung36_jcon_mindfa/icn_retval J
    goto icn_335_bang_adv
icn_336_after_call:
    goto icn_312_seq_rf_2
icn_335_α:
    goto icn_336_α
icn_335_β:
    goto icn_335_bang_chk
icn_335_bang_adv:
    putstatic rung36_jcon_mindfa/icn_335_bang_str Ljava/lang/String;
    iconst_0
    putstatic rung36_jcon_mindfa/icn_335_bang_pos I
icn_335_bang_chk:
    getstatic rung36_jcon_mindfa/icn_335_bang_str Ljava/lang/String;
    invokevirtual java/lang/String/length()I
    getstatic rung36_jcon_mindfa/icn_335_bang_pos I
    if_icmple icn_312_seq_rf_2
    getstatic rung36_jcon_mindfa/icn_335_bang_str Ljava/lang/String;
    getstatic rung36_jcon_mindfa/icn_335_bang_pos I
    getstatic rung36_jcon_mindfa/icn_335_bang_pos I
    iconst_1
    iadd
    invokevirtual java/lang/String/substring(II)Ljava/lang/String;
    getstatic rung36_jcon_mindfa/icn_335_bang_pos I
    iconst_1
    iadd
    putstatic rung36_jcon_mindfa/icn_335_bang_pos I
    goto icn_334_and_rg_0
;  VAR
icn_340_α:
    getstatic rung36_jcon_mindfa/icn_pv_makemdfa_p Ljava/lang/String;
    goto icn_339_lrelay
icn_340_β:
    goto icn_335_β
;  VAR
icn_341_α:
    getstatic rung36_jcon_mindfa/icn_pv_makemdfa_q J
    goto icn_339_rrelay
icn_341_β:
    goto icn_335_β
;  STRRELOP
icn_339_α:
    goto icn_340_α
icn_339_β:
    goto icn_340_β
icn_339_lrelay:
    astore 96
    goto icn_339_lstore
icn_339_lstore:
    goto icn_341_α
icn_339_rrelay:
    astore 97
    goto icn_339_chk
icn_339_chk:
    aload 96
    aload 97
    invokevirtual java/lang/String/compareTo(Ljava/lang/String;)I
    ifeq icn_341_β
    lconst_0
    goto icn_333_store
    goto icn_334_α
icn_334_and_rg_0:
    putstatic rung36_jcon_mindfa/icn_334_and_drain_0 Ljava/lang/String;
    goto icn_339_α
icn_334_α:
    goto icn_335_α
icn_334_β:
    goto icn_339_β
icn_333_α:
    goto icn_334_α
icn_333_β:
    goto icn_334_β
icn_333_store:
    putstatic rung36_jcon_mindfa/icn_pv_makemdfa_q J
    getstatic rung36_jcon_mindfa/icn_pv_makemdfa_q J
    goto icn_321_gdrain
icn_321_gdrain:
    pop2
    goto icn_322_α
icn_321_bdrain:
    pop2
icn_321_pump:
    goto icn_333_β
icn_321_α:
    goto icn_333_α
icn_321_β:
    goto icn_312_seq_rf_2
;  VAR
icn_343_α:
    getstatic rung36_jcon_mindfa/icn_pv_makemdfa_plike J
    goto icn_342_tsa_vr
icn_343_β:
    goto icn_311_pump
;  VAR
icn_344_α:
    getstatic rung36_jcon_mindfa/icn_pv_makemdfa_plike J
    goto icn_342_tsa_kr
icn_344_β:
    goto icn_311_pump
icn_342_α:
    goto icn_343_α
icn_342_β:
    goto icn_311_pump
icn_342_tsa_vr:
    dup2
    putstatic rung36_jcon_mindfa/icn_342_tsa_vl J
    invokestatic java/lang/Long/valueOf(J)Ljava/lang/Long;
    putstatic rung36_jcon_mindfa/icn_342_tsa_vo Ljava/lang/Object;
    goto icn_344_α
icn_342_tsa_kr:
    invokestatic java/lang/Long/toString(J)Ljava/lang/String;
    putstatic rung36_jcon_mindfa/icn_342_tsa_ks Ljava/lang/String;
    goto icn_342_tsa_put
icn_342_tsa_put:
    getstatic rung36_jcon_mindfa/icn_pv_makemdfa_etab Ljava/util/HashMap;
    getstatic rung36_jcon_mindfa/icn_342_tsa_ks Ljava/lang/String;
    getstatic rung36_jcon_mindfa/icn_342_tsa_vo Ljava/lang/Object;
    invokevirtual java/util/HashMap/put(Ljava/lang/Object;Ljava/lang/Object;)Ljava/lang/Object;
    pop
    getstatic rung36_jcon_mindfa/icn_342_tsa_vl J
    goto icn_311_bdrain
    goto icn_312_α
icn_312_seq_rg_0:
    pop2
    goto icn_315_α
icn_312_seq_rg_1:
    pop2
    goto icn_321_α
icn_312_seq_rg_2:
    pop2
    goto icn_342_α
icn_312_seq_rf_0:
    goto icn_315_α
icn_312_seq_rf_1:
    goto icn_321_α
icn_312_seq_rf_2:
    goto icn_342_α
icn_312_α:
    goto icn_313_α
icn_312_β:
    goto icn_342_β
icn_347_α:
    goto icn_309_α
icn_347_β:
    goto icn_309_α
icn_346_α:
    goto icn_347_α
icn_346_β:
    goto icn_346_bang_chk
icn_346_bang_adv:
    putstatic rung36_jcon_mindfa/icn_346_bang_str Ljava/lang/String;
    iconst_0
    putstatic rung36_jcon_mindfa/icn_346_bang_pos I
icn_346_bang_chk:
    getstatic rung36_jcon_mindfa/icn_346_bang_str Ljava/lang/String;
    invokevirtual java/lang/String/length()I
    getstatic rung36_jcon_mindfa/icn_346_bang_pos I
    if_icmple icn_309_α
    getstatic rung36_jcon_mindfa/icn_346_bang_str Ljava/lang/String;
    getstatic rung36_jcon_mindfa/icn_346_bang_pos I
    getstatic rung36_jcon_mindfa/icn_346_bang_pos I
    iconst_1
    iadd
    invokevirtual java/lang/String/substring(II)Ljava/lang/String;
    getstatic rung36_jcon_mindfa/icn_346_bang_pos I
    iconst_1
    iadd
    putstatic rung36_jcon_mindfa/icn_346_bang_pos I
    goto icn_345_store
icn_345_α:
    goto icn_346_α
icn_345_β:
    goto icn_346_β
icn_345_store:
    putstatic rung36_jcon_mindfa/icn_pv_makemdfa_p Ljava/lang/String;
    getstatic rung36_jcon_mindfa/icn_pv_makemdfa_p Ljava/lang/String;
    goto icn_311_gdrain
icn_311_gdrain:
    pop
    goto icn_312_α
icn_311_bdrain:
    pop2
icn_311_pump:
    goto icn_345_β
icn_311_α:
    goto icn_345_α
icn_311_β:
    goto icn_309_α
;  STR
icn_349_α:
    ldc ""
    goto icn_348_store
icn_349_β:
    goto icn_311_α
icn_348_α:
    goto icn_349_α
icn_348_β:
    goto icn_349_β
icn_348_store:
    putstatic rung36_jcon_mindfa/icn_pv_makemdfa_qset Ljava/lang/String;
    getstatic rung36_jcon_mindfa/icn_pv_makemdfa_qset Ljava/lang/String;
    goto icn_makemdfa_s3_sdrain
icn_makemdfa_s3_sdrain:
    pop
    goto icn_311_α
icn_351_α:
    goto icn_348_α
icn_351_β:
    goto icn_348_α
icn_350_α:
    goto icn_351_α
icn_350_β:
    goto icn_351_β
icn_350_store:
    putstatic rung36_jcon_mindfa/icn_pv_makemdfa_etab Ljava/util/HashMap;
    getstatic rung36_jcon_mindfa/icn_pv_makemdfa_etab Ljava/util/HashMap;
    goto icn_makemdfa_s2_sdrain
icn_makemdfa_s2_sdrain:
    pop
    goto icn_348_α
icn_makemdfa_done:
    iconst_0
    putstatic rung36_jcon_mindfa/icn_suspended B
    iconst_0
    putstatic rung36_jcon_mindfa/icn_suspend_id I
    iconst_1
    putstatic rung36_jcon_mindfa/icn_failed B
    return
icn_makemdfa_ret:
    iconst_0
    putstatic rung36_jcon_mindfa/icn_failed B
    return
icn_makemdfa_sret:
    return
.end method

.method public static icn_equiv()V
    .limit stack 16
    .limit locals 688
    lconst_0
    lstore 0
    lconst_0
    lstore 2
    lconst_0
    lstore 4
    lconst_0
    lstore 6
    lconst_0
    lstore 8
    lconst_0
    lstore 10
    lconst_0
    lstore 12
    lconst_0
    lstore 14
    lconst_0
    lstore 16
    lconst_0
    lstore 18
    lconst_0
    lstore 20
    lconst_0
    lstore 22
    lconst_0
    lstore 24
    lconst_0
    lstore 26
    lconst_0
    lstore 28
    lconst_0
    lstore 30
    lconst_0
    lstore 32
    lconst_0
    lstore 34
    lconst_0
    lstore 36
    lconst_0
    lstore 38
    lconst_0
    lstore 40
    lconst_0
    lstore 42
    lconst_0
    lstore 44
    lconst_0
    lstore 46
    lconst_0
    lstore 48
    lconst_0
    lstore 50
    lconst_0
    lstore 52
    lconst_0
    lstore 54
    lconst_0
    lstore 56
    lconst_0
    lstore 58
    lconst_0
    lstore 60
    lconst_0
    lstore 62
    iconst_0
    istore 84
    iconst_0
    istore 85
    iconst_0
    istore 86
    iconst_0
    istore 87
    iconst_0
    istore 88
    iconst_0
    istore 89
    aconst_null
    astore 148
    aconst_null
    astore 149
    aconst_null
    astore 150
    aconst_null
    astore 151
    getstatic rung36_jcon_mindfa/icn_arg_str_0 Ljava/lang/String;
    putstatic rung36_jcon_mindfa/icn_pv_equiv_q Ljava/lang/String;
    getstatic rung36_jcon_mindfa/icn_arg_str_1 Ljava/lang/String;
    putstatic rung36_jcon_mindfa/icn_pv_equiv_el Ljava/lang/String;
    goto icn_352_α
;  VAR
icn_355_α:
    getstatic rung36_jcon_mindfa/icn_pv_equiv_p Ljava/lang/String;
    goto icn_354_ret_store
icn_355_β:
    goto icn_354_ret_fail
icn_354_α:
    goto icn_355_α
icn_354_β:
    goto icn_equiv_ret
icn_354_ret_fail:
    iconst_1
    putstatic rung36_jcon_mindfa/icn_failed B
    goto icn_equiv_done
icn_354_ret_store:
    putstatic rung36_jcon_mindfa/icn_retval_str Ljava/lang/String;
    lconst_0
    putstatic rung36_jcon_mindfa/icn_retval J
    iconst_0
    putstatic rung36_jcon_mindfa/icn_failed B
    goto icn_equiv_ret
;  VAR
icn_358_α:
    getstatic rung36_jcon_mindfa/icn_pv_equiv_q J
    goto icn_357_cbo_cmp
icn_358_β:
    goto icn_357_cbo_lb
;  VAR
icn_359_α:
    getstatic rung36_jcon_mindfa/icn_pv_equiv_p Ljava/lang/String;
    goto icn_357_cbo_ls
icn_359_β:
    goto icn_353_else
icn_357_cbo_lb:
    goto icn_359_β
icn_357_α:
    goto icn_359_α
icn_357_β:
    goto icn_358_β
icn_357_cbo_ls:
    putstatic rung36_jcon_mindfa/icn_cbo357_lcs Ljava/lang/String;
    goto icn_358_α
icn_357_cbo_cmp:
    putstatic rung36_jcon_mindfa/icn_cbo357_rcs Ljava/lang/String;
    getstatic rung36_jcon_mindfa/icn_cbo357_lcs Ljava/lang/String;
    getstatic rung36_jcon_mindfa/icn_cbo357_rcs Ljava/lang/String;
    invokestatic rung36_jcon_mindfa/icn_builtin_cset_union(Ljava/lang/String;Ljava/lang/String;)Ljava/lang/String;
    goto icn_356_lrelay
;  VAR
icn_360_α:
    getstatic rung36_jcon_mindfa/icn_pv_equiv_p Ljava/lang/String;
    goto icn_356_rrelay
icn_360_β:
    goto icn_353_else
;  STRRELOP
icn_356_α:
    goto icn_357_α
icn_356_β:
    goto icn_357_β
icn_356_lrelay:
    astore 84
    goto icn_356_lstore
icn_356_lstore:
    goto icn_360_α
icn_356_rrelay:
    astore 85
    goto icn_356_chk
icn_356_chk:
    aload 84
    aload 85
    invokevirtual java/lang/String/compareTo(Ljava/lang/String;)I
    ifne icn_360_β
    lconst_0
    goto icn_353_then
icn_353_then:
    pop2
    goto icn_354_α
icn_353_else:
    goto icn_352_pump
icn_353_α:
    goto icn_356_α
icn_353_β:
    goto icn_356_β
;  VAR
icn_363_α:
    getstatic rung36_jcon_mindfa/icn_pv_equiv_el J
    goto icn_362_bang_adv
icn_363_β:
    goto icn_equiv_done
icn_362_α:
    goto icn_363_α
icn_362_β:
    goto icn_362_bang_chk
icn_362_bang_adv:
    putstatic rung36_jcon_mindfa/icn_362_bang_str Ljava/lang/String;
    iconst_0
    putstatic rung36_jcon_mindfa/icn_362_bang_pos I
icn_362_bang_chk:
    getstatic rung36_jcon_mindfa/icn_362_bang_str Ljava/lang/String;
    invokevirtual java/lang/String/length()I
    getstatic rung36_jcon_mindfa/icn_362_bang_pos I
    if_icmple icn_equiv_done
    getstatic rung36_jcon_mindfa/icn_362_bang_str Ljava/lang/String;
    getstatic rung36_jcon_mindfa/icn_362_bang_pos I
    getstatic rung36_jcon_mindfa/icn_362_bang_pos I
    iconst_1
    iadd
    invokevirtual java/lang/String/substring(II)Ljava/lang/String;
    getstatic rung36_jcon_mindfa/icn_362_bang_pos I
    iconst_1
    iadd
    putstatic rung36_jcon_mindfa/icn_362_bang_pos I
    goto icn_361_store
icn_361_α:
    goto icn_362_α
icn_361_β:
    goto icn_362_β
icn_361_store:
    putstatic rung36_jcon_mindfa/icn_pv_equiv_p Ljava/lang/String;
    getstatic rung36_jcon_mindfa/icn_pv_equiv_p Ljava/lang/String;
    goto icn_352_gdrain
icn_352_gdrain:
    pop
    goto icn_353_α
icn_352_bdrain:
    pop2
icn_352_pump:
    goto icn_361_β
icn_352_α:
    goto icn_361_α
icn_352_β:
    goto icn_equiv_done
icn_equiv_done:
    iconst_0
    putstatic rung36_jcon_mindfa/icn_suspended B
    iconst_0
    putstatic rung36_jcon_mindfa/icn_suspend_id I
    iconst_1
    putstatic rung36_jcon_mindfa/icn_failed B
    return
icn_equiv_ret:
    iconst_0
    putstatic rung36_jcon_mindfa/icn_failed B
    return
icn_equiv_sret:
    return
.end method

.method public static icn_equivdelta()V
    .limit stack 16
    .limit locals 710
    lconst_0
    lstore 0
    lconst_0
    lstore 2
    lconst_0
    lstore 4
    lconst_0
    lstore 6
    lconst_0
    lstore 8
    lconst_0
    lstore 10
    lconst_0
    lstore 12
    lconst_0
    lstore 14
    lconst_0
    lstore 16
    lconst_0
    lstore 18
    lconst_0
    lstore 20
    lconst_0
    lstore 22
    lconst_0
    lstore 24
    lconst_0
    lstore 26
    lconst_0
    lstore 28
    lconst_0
    lstore 30
    lconst_0
    lstore 32
    lconst_0
    lstore 34
    lconst_0
    lstore 36
    lconst_0
    lstore 38
    lconst_0
    lstore 40
    lconst_0
    lstore 42
    lconst_0
    lstore 44
    lconst_0
    lstore 46
    lconst_0
    lstore 48
    lconst_0
    lstore 50
    lconst_0
    lstore 52
    lconst_0
    lstore 54
    lconst_0
    lstore 56
    lconst_0
    lstore 58
    lconst_0
    lstore 60
    lconst_0
    lstore 62
    iconst_0
    istore 84
    iconst_0
    istore 85
    iconst_0
    istore 86
    iconst_0
    istore 87
    iconst_0
    istore 88
    iconst_0
    istore 89
    iconst_0
    istore 90
    aconst_null
    astore 148
    aconst_null
    astore 149
    aconst_null
    astore 150
    aconst_null
    astore 151
    getstatic rung36_jcon_mindfa/icn_arg_str_0 Ljava/lang/String;
    putstatic rung36_jcon_mindfa/icn_pv_equivdelta_p Ljava/lang/String;
    getstatic rung36_jcon_mindfa/icn_arg_str_1 Ljava/lang/String;
    putstatic rung36_jcon_mindfa/icn_pv_equivdelta_a Ljava/lang/String;
    getstatic rung36_jcon_mindfa/icn_arg_2 J
    putstatic rung36_jcon_mindfa/icn_pv_equivdelta_D J
    getstatic rung36_jcon_mindfa/icn_arg_3 J
    putstatic rung36_jcon_mindfa/icn_pv_equivdelta_el J
    goto icn_376_α
;  VAR
icn_366_α:
    getstatic rung36_jcon_mindfa/icn_pv_equivdelta_el J
    goto icn_365_arg1
icn_366_β:
    goto icn_364_ret_fail
icn_365_arg1:
    putstatic rung36_jcon_mindfa/icn_arg_1 J
    goto icn_365_docall
;  VAR
icn_367_α:
    getstatic rung36_jcon_mindfa/icn_pv_equivdelta_r Ljava/lang/String;
    goto icn_365_arg0
icn_367_β:
    goto icn_364_ret_fail
icn_365_arg0:
    putstatic rung36_jcon_mindfa/icn_arg_str_0 Ljava/lang/String;
    lconst_0
    putstatic rung36_jcon_mindfa/icn_arg_0 J
    goto icn_366_α
icn_365_α:
    goto icn_367_α
icn_365_β:
    goto icn_366_β
icn_365_docall:
    getstatic rung36_jcon_mindfa/icn_7_I J
    lstore 152
    getstatic rung36_jcon_mindfa/icn_7_bound J
    lstore 154
    getstatic rung36_jcon_mindfa/icn_7_e1cur J
    lstore 156
    getstatic rung36_jcon_mindfa/icn_7_e1val J
    lstore 158
    getstatic rung36_jcon_mindfa/icn_7_e2val J
    lstore 160
    getstatic rung36_jcon_mindfa/icn_93_I J
    lstore 162
    getstatic rung36_jcon_mindfa/icn_93_bound J
    lstore 164
    getstatic rung36_jcon_mindfa/icn_93_e1cur J
    lstore 166
    getstatic rung36_jcon_mindfa/icn_93_e1val J
    lstore 168
    getstatic rung36_jcon_mindfa/icn_93_e2val J
    lstore 170
    getstatic rung36_jcon_mindfa/icn_126_ts_kval J
    lstore 172
    getstatic rung36_jcon_mindfa/icn_142_ts_kval J
    lstore 174
    getstatic rung36_jcon_mindfa/icn_165_ts_kval J
    lstore 176
    getstatic rung36_jcon_mindfa/icn_206_ts_kval J
    lstore 178
    getstatic rung36_jcon_mindfa/icn_231_tsa_vl J
    lstore 180
    getstatic rung36_jcon_mindfa/icn_244_tsa_vl J
    lstore 182
    getstatic rung36_jcon_mindfa/icn_245_ts_kval J
    lstore 184
    getstatic rung36_jcon_mindfa/icn_252_ts_kval J
    lstore 186
    getstatic rung36_jcon_mindfa/icn_261_ts_kval J
    lstore 188
    getstatic rung36_jcon_mindfa/icn_270_ts_kval J
    lstore 190
    getstatic rung36_jcon_mindfa/icn_278_ts_kval J
    lstore 192
    getstatic rung36_jcon_mindfa/icn_280_ts_kval J
    lstore 194
    getstatic rung36_jcon_mindfa/icn_313_augtemp J
    lstore 196
    getstatic rung36_jcon_mindfa/icn_316_alt_val J
    lstore 198
    getstatic rung36_jcon_mindfa/icn_324_alt_val J
    lstore 200
    getstatic rung36_jcon_mindfa/icn_323_augtemp J
    lstore 202
    getstatic rung36_jcon_mindfa/icn_330_ts_kval J
    lstore 204
    getstatic rung36_jcon_mindfa/icn_342_tsa_vl J
    lstore 206
    getstatic rung36_jcon_mindfa/icn_pv_equivdelta_el J
    lstore 208
    invokestatic rung36_jcon_mindfa/icn_equiv()V
    lload 152
    putstatic rung36_jcon_mindfa/icn_7_I J
    lload 154
    putstatic rung36_jcon_mindfa/icn_7_bound J
    lload 156
    putstatic rung36_jcon_mindfa/icn_7_e1cur J
    lload 158
    putstatic rung36_jcon_mindfa/icn_7_e1val J
    lload 160
    putstatic rung36_jcon_mindfa/icn_7_e2val J
    lload 162
    putstatic rung36_jcon_mindfa/icn_93_I J
    lload 164
    putstatic rung36_jcon_mindfa/icn_93_bound J
    lload 166
    putstatic rung36_jcon_mindfa/icn_93_e1cur J
    lload 168
    putstatic rung36_jcon_mindfa/icn_93_e1val J
    lload 170
    putstatic rung36_jcon_mindfa/icn_93_e2val J
    lload 172
    putstatic rung36_jcon_mindfa/icn_126_ts_kval J
    lload 174
    putstatic rung36_jcon_mindfa/icn_142_ts_kval J
    lload 176
    putstatic rung36_jcon_mindfa/icn_165_ts_kval J
    lload 178
    putstatic rung36_jcon_mindfa/icn_206_ts_kval J
    lload 180
    putstatic rung36_jcon_mindfa/icn_231_tsa_vl J
    lload 182
    putstatic rung36_jcon_mindfa/icn_244_tsa_vl J
    lload 184
    putstatic rung36_jcon_mindfa/icn_245_ts_kval J
    lload 186
    putstatic rung36_jcon_mindfa/icn_252_ts_kval J
    lload 188
    putstatic rung36_jcon_mindfa/icn_261_ts_kval J
    lload 190
    putstatic rung36_jcon_mindfa/icn_270_ts_kval J
    lload 192
    putstatic rung36_jcon_mindfa/icn_278_ts_kval J
    lload 194
    putstatic rung36_jcon_mindfa/icn_280_ts_kval J
    lload 196
    putstatic rung36_jcon_mindfa/icn_313_augtemp J
    lload 198
    putstatic rung36_jcon_mindfa/icn_316_alt_val J
    lload 200
    putstatic rung36_jcon_mindfa/icn_324_alt_val J
    lload 202
    putstatic rung36_jcon_mindfa/icn_323_augtemp J
    lload 204
    putstatic rung36_jcon_mindfa/icn_330_ts_kval J
    lload 206
    putstatic rung36_jcon_mindfa/icn_342_tsa_vl J
    lload 208
    putstatic rung36_jcon_mindfa/icn_pv_equivdelta_el J
    getstatic rung36_jcon_mindfa/icn_failed B
    ifne icn_365_after_call
    getstatic rung36_jcon_mindfa/icn_retval J
    goto icn_364_ret_store
icn_365_after_call:
    goto icn_364_ret_fail
icn_364_α:
    goto icn_365_α
icn_364_β:
    goto icn_equivdelta_ret
icn_364_ret_fail:
    iconst_1
    putstatic rung36_jcon_mindfa/icn_failed B
    goto icn_equivdelta_done
icn_364_ret_store:
    putstatic rung36_jcon_mindfa/icn_retval J
    iconst_0
    putstatic rung36_jcon_mindfa/icn_failed B
    goto icn_equivdelta_ret
;  VAR
icn_371_α:
    getstatic rung36_jcon_mindfa/icn_pv_equivdelta_a J
    goto icn_370_rrelay
icn_371_β:
    goto icn_370_lb
;  STR
icn_373_α:
    ldc ":"
    goto icn_372_rrelay
icn_373_β:
    goto icn_372_lb
;  VAR
icn_374_α:
    getstatic rung36_jcon_mindfa/icn_pv_equivdelta_q Ljava/lang/String;
    goto icn_372_lrelay
icn_374_β:
    goto icn_364_α
icn_372_lrelay:
    putstatic rung36_jcon_mindfa/icn_372_lc Ljava/lang/String;
    goto icn_372_lstore
icn_372_rrelay:
    putstatic rung36_jcon_mindfa/icn_372_rc Ljava/lang/String;
    goto icn_372_compute
icn_372_lb:
    goto icn_374_β
icn_372_α:
    iconst_0
    istore 85
    goto icn_374_α
icn_372_β:
    iconst_1
    istore 85
    goto icn_374_α
icn_372_lstore:
    iload 85
    ifeq icn_373_α
    goto icn_373_β
icn_372_compute:
    getstatic rung36_jcon_mindfa/icn_372_lc Ljava/lang/String;
    getstatic rung36_jcon_mindfa/icn_372_rc Ljava/lang/String;
    invokevirtual java/lang/String/concat(Ljava/lang/String;)Ljava/lang/String;
    goto icn_370_lrelay
icn_370_lrelay:
    putstatic rung36_jcon_mindfa/icn_370_lc Ljava/lang/String;
    goto icn_370_lstore
icn_370_rrelay:
    putstatic rung36_jcon_mindfa/icn_370_rc Ljava/lang/String;
    goto icn_370_compute
icn_370_lb:
    goto icn_372_β
icn_370_α:
    iconst_0
    istore 84
    goto icn_372_α
icn_370_β:
    iconst_1
    istore 84
    goto icn_372_α
icn_370_lstore:
    iload 84
    ifeq icn_371_α
    goto icn_371_β
icn_370_compute:
    getstatic rung36_jcon_mindfa/icn_370_lc Ljava/lang/String;
    getstatic rung36_jcon_mindfa/icn_370_rc Ljava/lang/String;
    invokevirtual java/lang/String/concat(Ljava/lang/String;)Ljava/lang/String;
    goto icn_369_sub_irelay
icn_375_α:
    goto icn_364_α
icn_375_β:
    goto icn_364_α
icn_369_sub_srelay:
    putstatic rung36_jcon_mindfa/icn_369_sub_s Ljava/lang/String;
    goto icn_370_α
icn_369_sub_irelay:
    l2i
    istore 86
    iload 86
    ifgt icn_369_sub_pos
    iload 86
    iflt icn_369_sub_neg
icn_369_sub_z:
    goto icn_364_α
icn_369_sub_pos:
    iload 86
    iconst_1
    isub
    putstatic rung36_jcon_mindfa/icn_369_sub_i I
    goto icn_369_sub_check
icn_369_sub_neg:
    getstatic rung36_jcon_mindfa/icn_369_sub_s Ljava/lang/String;
    invokevirtual java/lang/String/length()I
    iload 86
    iadd
    putstatic rung36_jcon_mindfa/icn_369_sub_i I
    goto icn_369_sub_check
icn_369_sub_check:
    getstatic rung36_jcon_mindfa/icn_369_sub_i I
    iflt icn_364_α
    getstatic rung36_jcon_mindfa/icn_369_sub_s Ljava/lang/String;
    invokevirtual java/lang/String/length()I
    getstatic rung36_jcon_mindfa/icn_369_sub_i I
    if_icmple icn_364_α
    getstatic rung36_jcon_mindfa/icn_369_sub_s Ljava/lang/String;
    getstatic rung36_jcon_mindfa/icn_369_sub_i I
    getstatic rung36_jcon_mindfa/icn_369_sub_i I
    iconst_1
    iadd
    invokevirtual java/lang/String/substring(II)Ljava/lang/String;
    goto icn_368_store
icn_369_α:
    goto icn_375_α
icn_369_β:
    goto icn_370_β
icn_368_α:
    goto icn_369_α
icn_368_β:
    goto icn_369_β
icn_368_store:
    putstatic rung36_jcon_mindfa/icn_pv_equivdelta_r Ljava/lang/String;
    getstatic rung36_jcon_mindfa/icn_pv_equivdelta_r Ljava/lang/String;
    goto icn_equivdelta_s2_sdrain
icn_equivdelta_s2_sdrain:
    pop
    goto icn_364_α
;  VAR
icn_378_α:
    getstatic rung36_jcon_mindfa/icn_pv_equivdelta_p J
    goto icn_377_bang_adv
icn_378_β:
    goto icn_368_α
icn_377_α:
    goto icn_378_α
icn_377_β:
    goto icn_377_bang_chk
icn_377_bang_adv:
    putstatic rung36_jcon_mindfa/icn_377_bang_str Ljava/lang/String;
    iconst_0
    putstatic rung36_jcon_mindfa/icn_377_bang_pos I
icn_377_bang_chk:
    getstatic rung36_jcon_mindfa/icn_377_bang_str Ljava/lang/String;
    invokevirtual java/lang/String/length()I
    getstatic rung36_jcon_mindfa/icn_377_bang_pos I
    if_icmple icn_368_α
    getstatic rung36_jcon_mindfa/icn_377_bang_str Ljava/lang/String;
    getstatic rung36_jcon_mindfa/icn_377_bang_pos I
    getstatic rung36_jcon_mindfa/icn_377_bang_pos I
    iconst_1
    iadd
    invokevirtual java/lang/String/substring(II)Ljava/lang/String;
    getstatic rung36_jcon_mindfa/icn_377_bang_pos I
    iconst_1
    iadd
    putstatic rung36_jcon_mindfa/icn_377_bang_pos I
    goto icn_376_store
icn_376_α:
    goto icn_377_α
icn_376_β:
    goto icn_377_β
icn_376_store:
    putstatic rung36_jcon_mindfa/icn_pv_equivdelta_q Ljava/lang/String;
    getstatic rung36_jcon_mindfa/icn_pv_equivdelta_q Ljava/lang/String;
    goto icn_equivdelta_s1_sdrain
icn_equivdelta_s1_sdrain:
    pop
    goto icn_368_α
icn_equivdelta_done:
    iconst_0
    putstatic rung36_jcon_mindfa/icn_suspended B
    iconst_0
    putstatic rung36_jcon_mindfa/icn_suspend_id I
    iconst_1
    putstatic rung36_jcon_mindfa/icn_failed B
    return
icn_equivdelta_ret:
    iconst_0
    putstatic rung36_jcon_mindfa/icn_failed B
    return
icn_equivdelta_sret:
    return
.end method

.method public static icn_finalstates()V
    .limit stack 16
    .limit locals 748
    lconst_0
    lstore 0
    lconst_0
    lstore 2
    lconst_0
    lstore 4
    lconst_0
    lstore 6
    lconst_0
    lstore 8
    lconst_0
    lstore 10
    lconst_0
    lstore 12
    lconst_0
    lstore 14
    lconst_0
    lstore 16
    lconst_0
    lstore 18
    lconst_0
    lstore 20
    lconst_0
    lstore 22
    lconst_0
    lstore 24
    lconst_0
    lstore 26
    lconst_0
    lstore 28
    lconst_0
    lstore 30
    lconst_0
    lstore 32
    lconst_0
    lstore 34
    lconst_0
    lstore 36
    lconst_0
    lstore 38
    lconst_0
    lstore 40
    lconst_0
    lstore 42
    lconst_0
    lstore 44
    lconst_0
    lstore 46
    lconst_0
    lstore 48
    lconst_0
    lstore 50
    lconst_0
    lstore 52
    lconst_0
    lstore 54
    lconst_0
    lstore 56
    lconst_0
    lstore 58
    lconst_0
    lstore 60
    lconst_0
    lstore 62
    iconst_0
    istore 84
    iconst_0
    istore 85
    iconst_0
    istore 86
    iconst_0
    istore 87
    iconst_0
    istore 88
    aconst_null
    astore 148
    aconst_null
    astore 149
    aconst_null
    astore 150
    aconst_null
    astore 151
    getstatic rung36_jcon_mindfa/icn_arg_str_0 Ljava/lang/String;
    putstatic rung36_jcon_mindfa/icn_pv_finalstates_D Ljava/lang/String;
    getstatic rung36_jcon_mindfa/icn_arg_str_1 Ljava/lang/String;
    putstatic rung36_jcon_mindfa/icn_pv_finalstates_el Ljava/lang/String;
    goto icn_401_α
;  VAR
icn_380_α:
    getstatic rung36_jcon_mindfa/icn_pv_finalstates_flist Ljava/util/ArrayList;
    goto icn_379_ret_store
icn_380_β:
    goto icn_379_ret_fail
icn_379_α:
    goto icn_380_α
icn_379_β:
    goto icn_finalstates_ret
icn_379_ret_fail:
    iconst_1
    putstatic rung36_jcon_mindfa/icn_failed B
    goto icn_finalstates_done
icn_379_ret_store:
    putstatic rung36_jcon_mindfa/icn_retval J
    iconst_0
    putstatic rung36_jcon_mindfa/icn_failed B
    goto icn_finalstates_ret
;  VAR
icn_383_α:
    getstatic rung36_jcon_mindfa/icn_pv_finalstates_flist Ljava/util/ArrayList;
    goto icn_382_lr
icn_383_β:
    goto icn_379_α
;  INT
icn_385_α:
    ldc2_w 1
    goto icn_384_sub_irelay
icn_385_β:
    goto icn_379_α
;  VAR
icn_388_α:
    getstatic rung36_jcon_mindfa/icn_pv_finalstates_ftab Ljava/util/HashMap;
    goto icn_387_sort_rel
icn_388_β:
    goto icn_379_α
icn_387_α:
    goto icn_388_α
icn_387_β:
    goto icn_379_α
icn_387_sort_rel:
    putstatic rung36_jcon_mindfa/icn_387_sort_list Ljava/util/ArrayList;
    getstatic rung36_jcon_mindfa/icn_387_sort_list Ljava/util/ArrayList;
    invokestatic rung36_jcon_mindfa/icn_builtin_sort(Ljava/util/ArrayList;)Ljava/util/ArrayList;
    goto icn_386_bang_st
icn_386_α:
    goto icn_387_α
icn_386_β:
    goto icn_386_bang_chk
icn_386_bang_st:
    putstatic rung36_jcon_mindfa/icn_386_bang_list Ljava/util/ArrayList;
    iconst_0
    putstatic rung36_jcon_mindfa/icn_386_bang_idx I
icn_386_bang_chk:
    getstatic rung36_jcon_mindfa/icn_386_bang_list Ljava/util/ArrayList;
    invokevirtual java/util/ArrayList/size()I
    getstatic rung36_jcon_mindfa/icn_386_bang_idx I
    if_icmple icn_379_α
    getstatic rung36_jcon_mindfa/icn_386_bang_list Ljava/util/ArrayList;
    getstatic rung36_jcon_mindfa/icn_386_bang_idx I
    invokevirtual java/util/ArrayList/get(I)Ljava/lang/Object;
icn_386_bang_ok:
    checkcast java/lang/Long
    invokevirtual java/lang/Long/longValue()J
    getstatic rung36_jcon_mindfa/icn_386_bang_idx I
    iconst_1
    iadd
    putstatic rung36_jcon_mindfa/icn_386_bang_idx I
    goto icn_384_sub_srelay
icn_384_sub_srelay:
    putstatic rung36_jcon_mindfa/icn_384_sub_s Ljava/lang/String;
    goto icn_385_α
icn_384_sub_irelay:
    l2i
    istore 84
    iload 84
    ifgt icn_384_sub_pos
    iload 84
    iflt icn_384_sub_neg
icn_384_sub_z:
    goto icn_379_α
icn_384_sub_pos:
    iload 84
    iconst_1
    isub
    putstatic rung36_jcon_mindfa/icn_384_sub_i I
    goto icn_384_sub_check
icn_384_sub_neg:
    getstatic rung36_jcon_mindfa/icn_384_sub_s Ljava/lang/String;
    invokevirtual java/lang/String/length()I
    iload 84
    iadd
    putstatic rung36_jcon_mindfa/icn_384_sub_i I
    goto icn_384_sub_check
icn_384_sub_check:
    getstatic rung36_jcon_mindfa/icn_384_sub_i I
    iflt icn_379_α
    getstatic rung36_jcon_mindfa/icn_384_sub_s Ljava/lang/String;
    invokevirtual java/lang/String/length()I
    getstatic rung36_jcon_mindfa/icn_384_sub_i I
    if_icmple icn_379_α
    getstatic rung36_jcon_mindfa/icn_384_sub_s Ljava/lang/String;
    getstatic rung36_jcon_mindfa/icn_384_sub_i I
    getstatic rung36_jcon_mindfa/icn_384_sub_i I
    iconst_1
    iadd
    invokevirtual java/lang/String/substring(II)Ljava/lang/String;
    goto icn_382_vr
icn_384_α:
    goto icn_386_α
icn_384_β:
    goto icn_385_β
icn_382_α:
    goto icn_383_α
icn_382_β:
    goto icn_379_α
icn_382_lr:
    putstatic rung36_jcon_mindfa/icn_382_pushlist Ljava/util/ArrayList;
    goto icn_384_α
icn_382_vr:
    putstatic rung36_jcon_mindfa/icn_382_pushval Ljava/lang/Object;
    getstatic rung36_jcon_mindfa/icn_382_pushlist Ljava/util/ArrayList;
    getstatic rung36_jcon_mindfa/icn_382_pushval Ljava/lang/Object;
    invokevirtual java/util/ArrayList/add(Ljava/lang/Object;)Z
    pop
    getstatic rung36_jcon_mindfa/icn_382_pushlist Ljava/util/ArrayList;
    goto icn_381_gdrain
icn_381_gdrain:
    pop
icn_381_pump:
    goto icn_382_β
icn_381_α:
    goto icn_382_α
icn_381_β:
    goto icn_379_α
icn_390_α:
    new java/util/ArrayList
    dup
    invokespecial java/util/ArrayList/<init>()V
    putstatic rung36_jcon_mindfa/icn_390_mklist Ljava/util/ArrayList;
    getstatic rung36_jcon_mindfa/icn_390_mklist Ljava/util/ArrayList;
    goto icn_389_store
icn_390_β:
    goto icn_381_α
icn_389_α:
    goto icn_390_α
icn_389_β:
    goto icn_390_β
icn_389_store:
    putstatic rung36_jcon_mindfa/icn_pv_finalstates_flist Ljava/util/ArrayList;
    getstatic rung36_jcon_mindfa/icn_pv_finalstates_flist Ljava/util/ArrayList;
    goto icn_finalstates_s3_sdrain
icn_finalstates_s3_sdrain:
    pop
    goto icn_381_α
;  VAR
icn_393_α:
    getstatic rung36_jcon_mindfa/icn_pv_finalstates_q J
    goto icn_392_tsa_vr
icn_393_β:
    goto icn_391_pump
;  VAR
icn_396_α:
    getstatic rung36_jcon_mindfa/icn_pv_finalstates_el J
    goto icn_395_arg1
icn_396_β:
    goto icn_391_pump
icn_395_arg1:
    putstatic rung36_jcon_mindfa/icn_arg_1 J
    goto icn_395_docall
;  VAR
icn_397_α:
    getstatic rung36_jcon_mindfa/icn_pv_finalstates_p Ljava/lang/String;
    goto icn_395_arg0
icn_397_β:
    goto icn_391_pump
icn_395_arg0:
    putstatic rung36_jcon_mindfa/icn_arg_str_0 Ljava/lang/String;
    lconst_0
    putstatic rung36_jcon_mindfa/icn_arg_0 J
    goto icn_396_α
icn_395_α:
    goto icn_397_α
icn_395_β:
    goto icn_396_β
icn_395_docall:
    getstatic rung36_jcon_mindfa/icn_7_I J
    lstore 152
    getstatic rung36_jcon_mindfa/icn_7_bound J
    lstore 154
    getstatic rung36_jcon_mindfa/icn_7_e1cur J
    lstore 156
    getstatic rung36_jcon_mindfa/icn_7_e1val J
    lstore 158
    getstatic rung36_jcon_mindfa/icn_7_e2val J
    lstore 160
    getstatic rung36_jcon_mindfa/icn_93_I J
    lstore 162
    getstatic rung36_jcon_mindfa/icn_93_bound J
    lstore 164
    getstatic rung36_jcon_mindfa/icn_93_e1cur J
    lstore 166
    getstatic rung36_jcon_mindfa/icn_93_e1val J
    lstore 168
    getstatic rung36_jcon_mindfa/icn_93_e2val J
    lstore 170
    getstatic rung36_jcon_mindfa/icn_126_ts_kval J
    lstore 172
    getstatic rung36_jcon_mindfa/icn_142_ts_kval J
    lstore 174
    getstatic rung36_jcon_mindfa/icn_165_ts_kval J
    lstore 176
    getstatic rung36_jcon_mindfa/icn_206_ts_kval J
    lstore 178
    getstatic rung36_jcon_mindfa/icn_231_tsa_vl J
    lstore 180
    getstatic rung36_jcon_mindfa/icn_244_tsa_vl J
    lstore 182
    getstatic rung36_jcon_mindfa/icn_245_ts_kval J
    lstore 184
    getstatic rung36_jcon_mindfa/icn_252_ts_kval J
    lstore 186
    getstatic rung36_jcon_mindfa/icn_261_ts_kval J
    lstore 188
    getstatic rung36_jcon_mindfa/icn_270_ts_kval J
    lstore 190
    getstatic rung36_jcon_mindfa/icn_278_ts_kval J
    lstore 192
    getstatic rung36_jcon_mindfa/icn_280_ts_kval J
    lstore 194
    getstatic rung36_jcon_mindfa/icn_313_augtemp J
    lstore 196
    getstatic rung36_jcon_mindfa/icn_316_alt_val J
    lstore 198
    getstatic rung36_jcon_mindfa/icn_324_alt_val J
    lstore 200
    getstatic rung36_jcon_mindfa/icn_323_augtemp J
    lstore 202
    getstatic rung36_jcon_mindfa/icn_330_ts_kval J
    lstore 204
    getstatic rung36_jcon_mindfa/icn_342_tsa_vl J
    lstore 206
    getstatic rung36_jcon_mindfa/icn_pv_finalstates_q J
    lstore 208
    getstatic rung36_jcon_mindfa/icn_pv_finalstates_el J
    lstore 210
    invokestatic rung36_jcon_mindfa/icn_equiv()V
    lload 152
    putstatic rung36_jcon_mindfa/icn_7_I J
    lload 154
    putstatic rung36_jcon_mindfa/icn_7_bound J
    lload 156
    putstatic rung36_jcon_mindfa/icn_7_e1cur J
    lload 158
    putstatic rung36_jcon_mindfa/icn_7_e1val J
    lload 160
    putstatic rung36_jcon_mindfa/icn_7_e2val J
    lload 162
    putstatic rung36_jcon_mindfa/icn_93_I J
    lload 164
    putstatic rung36_jcon_mindfa/icn_93_bound J
    lload 166
    putstatic rung36_jcon_mindfa/icn_93_e1cur J
    lload 168
    putstatic rung36_jcon_mindfa/icn_93_e1val J
    lload 170
    putstatic rung36_jcon_mindfa/icn_93_e2val J
    lload 172
    putstatic rung36_jcon_mindfa/icn_126_ts_kval J
    lload 174
    putstatic rung36_jcon_mindfa/icn_142_ts_kval J
    lload 176
    putstatic rung36_jcon_mindfa/icn_165_ts_kval J
    lload 178
    putstatic rung36_jcon_mindfa/icn_206_ts_kval J
    lload 180
    putstatic rung36_jcon_mindfa/icn_231_tsa_vl J
    lload 182
    putstatic rung36_jcon_mindfa/icn_244_tsa_vl J
    lload 184
    putstatic rung36_jcon_mindfa/icn_245_ts_kval J
    lload 186
    putstatic rung36_jcon_mindfa/icn_252_ts_kval J
    lload 188
    putstatic rung36_jcon_mindfa/icn_261_ts_kval J
    lload 190
    putstatic rung36_jcon_mindfa/icn_270_ts_kval J
    lload 192
    putstatic rung36_jcon_mindfa/icn_278_ts_kval J
    lload 194
    putstatic rung36_jcon_mindfa/icn_280_ts_kval J
    lload 196
    putstatic rung36_jcon_mindfa/icn_313_augtemp J
    lload 198
    putstatic rung36_jcon_mindfa/icn_316_alt_val J
    lload 200
    putstatic rung36_jcon_mindfa/icn_324_alt_val J
    lload 202
    putstatic rung36_jcon_mindfa/icn_323_augtemp J
    lload 204
    putstatic rung36_jcon_mindfa/icn_330_ts_kval J
    lload 206
    putstatic rung36_jcon_mindfa/icn_342_tsa_vl J
    lload 208
    putstatic rung36_jcon_mindfa/icn_pv_finalstates_q J
    lload 210
    putstatic rung36_jcon_mindfa/icn_pv_finalstates_el J
    getstatic rung36_jcon_mindfa/icn_failed B
    ifne icn_395_after_call
    getstatic rung36_jcon_mindfa/icn_retval J
    goto icn_394_store
icn_395_after_call:
    goto icn_391_pump
icn_394_α:
    goto icn_395_α
icn_394_β:
    goto icn_395_β
icn_394_store:
    putstatic rung36_jcon_mindfa/icn_pv_finalstates_q J
    getstatic rung36_jcon_mindfa/icn_pv_finalstates_q J
    goto icn_392_tsa_kr
icn_392_α:
    goto icn_393_α
icn_392_β:
    goto icn_391_pump
icn_392_tsa_vr:
    dup
    putstatic rung36_jcon_mindfa/icn_392_tsa_vl Ljava/lang/String;
    goto icn_394_α
icn_392_tsa_kr:
    invokestatic java/lang/Long/toString(J)Ljava/lang/String;
    putstatic rung36_jcon_mindfa/icn_392_tsa_ks Ljava/lang/String;
    goto icn_392_tsa_put
icn_392_tsa_put:
    getstatic rung36_jcon_mindfa/icn_pv_finalstates_ftab Ljava/util/HashMap;
    getstatic rung36_jcon_mindfa/icn_392_tsa_ks Ljava/lang/String;
    getstatic rung36_jcon_mindfa/icn_392_tsa_vl Ljava/lang/String;
    invokevirtual java/util/HashMap/put(Ljava/lang/Object;Ljava/lang/Object;)Ljava/lang/Object;
    pop
    getstatic rung36_jcon_mindfa/icn_392_tsa_vl Ljava/lang/String;
    goto icn_391_bdrain
icn_400_α:
    goto icn_389_α
icn_400_β:
    goto icn_389_α
icn_399_α:
    goto icn_400_α
icn_399_β:
    goto icn_399_bang_chk
icn_399_bang_adv:
    putstatic rung36_jcon_mindfa/icn_399_bang_str Ljava/lang/String;
    iconst_0
    putstatic rung36_jcon_mindfa/icn_399_bang_pos I
icn_399_bang_chk:
    getstatic rung36_jcon_mindfa/icn_399_bang_str Ljava/lang/String;
    invokevirtual java/lang/String/length()I
    getstatic rung36_jcon_mindfa/icn_399_bang_pos I
    if_icmple icn_389_α
    getstatic rung36_jcon_mindfa/icn_399_bang_str Ljava/lang/String;
    getstatic rung36_jcon_mindfa/icn_399_bang_pos I
    getstatic rung36_jcon_mindfa/icn_399_bang_pos I
    iconst_1
    iadd
    invokevirtual java/lang/String/substring(II)Ljava/lang/String;
    getstatic rung36_jcon_mindfa/icn_399_bang_pos I
    iconst_1
    iadd
    putstatic rung36_jcon_mindfa/icn_399_bang_pos I
    goto icn_398_store
icn_398_α:
    goto icn_399_α
icn_398_β:
    goto icn_399_β
icn_398_store:
    putstatic rung36_jcon_mindfa/icn_pv_finalstates_p Ljava/lang/String;
    getstatic rung36_jcon_mindfa/icn_pv_finalstates_p Ljava/lang/String;
    goto icn_391_gdrain
icn_391_gdrain:
    pop
    goto icn_392_α
icn_391_bdrain:
    pop
icn_391_pump:
    goto icn_398_β
icn_391_α:
    goto icn_398_α
icn_391_β:
    goto icn_389_α
icn_402_α:
    goto icn_391_α
icn_402_β:
    goto icn_391_α
icn_401_α:
    goto icn_402_α
icn_401_β:
    goto icn_402_β
icn_401_store:
    putstatic rung36_jcon_mindfa/icn_pv_finalstates_ftab Ljava/util/HashMap;
    getstatic rung36_jcon_mindfa/icn_pv_finalstates_ftab Ljava/util/HashMap;
    goto icn_finalstates_s1_sdrain
icn_finalstates_s1_sdrain:
    pop
    goto icn_391_α
icn_finalstates_done:
    iconst_0
    putstatic rung36_jcon_mindfa/icn_suspended B
    iconst_0
    putstatic rung36_jcon_mindfa/icn_suspend_id I
    iconst_1
    putstatic rung36_jcon_mindfa/icn_failed B
    return
icn_finalstates_ret:
    iconst_0
    putstatic rung36_jcon_mindfa/icn_failed B
    return
icn_finalstates_sret:
    return
.end method

.method public static icn_diff()V
    .limit stack 16
    .limit locals 786
    lconst_0
    lstore 0
    lconst_0
    lstore 2
    lconst_0
    lstore 4
    lconst_0
    lstore 6
    lconst_0
    lstore 8
    lconst_0
    lstore 10
    lconst_0
    lstore 12
    lconst_0
    lstore 14
    lconst_0
    lstore 16
    lconst_0
    lstore 18
    lconst_0
    lstore 20
    lconst_0
    lstore 22
    lconst_0
    lstore 24
    lconst_0
    lstore 26
    lconst_0
    lstore 28
    lconst_0
    lstore 30
    lconst_0
    lstore 32
    lconst_0
    lstore 34
    lconst_0
    lstore 36
    lconst_0
    lstore 38
    lconst_0
    lstore 40
    lconst_0
    lstore 42
    lconst_0
    lstore 44
    lconst_0
    lstore 46
    lconst_0
    lstore 48
    lconst_0
    lstore 50
    lconst_0
    lstore 52
    lconst_0
    lstore 54
    lconst_0
    lstore 56
    lconst_0
    lstore 58
    lconst_0
    lstore 60
    lconst_0
    lstore 62
    iconst_0
    istore 84
    iconst_0
    istore 85
    iconst_0
    istore 86
    iconst_0
    istore 87
    aconst_null
    astore 148
    aconst_null
    astore 149
    aconst_null
    astore 150
    aconst_null
    astore 151
    getstatic rung36_jcon_mindfa/icn_arg_str_0 Ljava/lang/String;
    putstatic rung36_jcon_mindfa/icn_pv_diff_l1 Ljava/lang/String;
    getstatic rung36_jcon_mindfa/icn_arg_str_1 Ljava/lang/String;
    putstatic rung36_jcon_mindfa/icn_pv_diff_l2 Ljava/lang/String;
    goto icn_430_α
;  VAR
icn_404_α:
    getstatic rung36_jcon_mindfa/icn_pv_diff_l Ljava/util/ArrayList;
    goto icn_403_ret_store
icn_404_β:
    goto icn_403_ret_fail
icn_403_α:
    goto icn_404_α
icn_403_β:
    goto icn_diff_ret
icn_403_ret_fail:
    iconst_1
    putstatic rung36_jcon_mindfa/icn_failed B
    goto icn_diff_done
icn_403_ret_store:
    putstatic rung36_jcon_mindfa/icn_retval J
    iconst_0
    putstatic rung36_jcon_mindfa/icn_failed B
    goto icn_diff_ret
icn_406_α:
    iconst_1
    putstatic rung36_jcon_mindfa/icn_failed B
    goto icn_diff_done
icn_406_β:
    goto icn_403_α
;  INT
icn_408_α:
    ldc2_w 0
    goto icn_407_rrelay
icn_408_β:
    goto icn_407_lb
;  VAR
icn_410_α:
    getstatic rung36_jcon_mindfa/icn_pv_diff_l Ljava/util/ArrayList;
    goto icn_409_relay
icn_410_β:
    goto icn_405_else
icn_409_α:
    goto icn_410_α
icn_409_β:
    goto icn_410_β
icn_409_relay:
    invokevirtual java/util/ArrayList/size()I
    i2l
    goto icn_407_lrelay
icn_407_lrelay:
    putstatic rung36_jcon_mindfa/icn_407_relop_lc J
    goto icn_407_lstore
icn_407_rrelay:
    putstatic rung36_jcon_mindfa/icn_407_relop_rc J
    goto icn_407_check
icn_407_lb:
    goto icn_409_β
icn_407_α:
    goto icn_409_α
icn_407_β:
    goto icn_408_β
icn_407_lstore:
    goto icn_408_α
icn_407_check:
    getstatic rung36_jcon_mindfa/icn_407_relop_lc J
    getstatic rung36_jcon_mindfa/icn_407_relop_rc J
    lcmp
    ifne icn_408_β
    getstatic rung36_jcon_mindfa/icn_407_relop_rc J
    goto icn_405_then
icn_405_then:
    pop2
    goto icn_406_α
icn_405_else:
    goto icn_403_α
icn_405_α:
    goto icn_407_α
icn_405_β:
    goto icn_407_β
;  VAR
icn_413_α:
    getstatic rung36_jcon_mindfa/icn_pv_diff_l Ljava/util/ArrayList;
    goto icn_412_lr
icn_413_β:
    goto icn_405_α
;  VAR
icn_416_α:
    getstatic rung36_jcon_mindfa/icn_pv_diff_t2 Ljava/lang/String;
    goto icn_415_cbo_cmp
icn_416_β:
    goto icn_415_cbo_lb
;  VAR
icn_417_α:
    getstatic rung36_jcon_mindfa/icn_pv_diff_t1 Ljava/lang/String;
    goto icn_415_cbo_ls
icn_417_β:
    goto icn_405_α
icn_415_cbo_lb:
    goto icn_417_β
icn_415_α:
    goto icn_417_α
icn_415_β:
    goto icn_416_β
icn_415_cbo_ls:
    putstatic rung36_jcon_mindfa/icn_cbo415_lcs Ljava/lang/String;
    goto icn_416_α
icn_415_cbo_cmp:
    putstatic rung36_jcon_mindfa/icn_cbo415_rcs Ljava/lang/String;
    getstatic rung36_jcon_mindfa/icn_cbo415_lcs Ljava/lang/String;
    getstatic rung36_jcon_mindfa/icn_cbo415_rcs Ljava/lang/String;
    invokestatic rung36_jcon_mindfa/icn_builtin_cset_diff(Ljava/lang/String;Ljava/lang/String;)Ljava/lang/String;
    goto icn_414_bang_adv
icn_414_α:
    goto icn_415_α
icn_414_β:
    goto icn_414_bang_chk
icn_414_bang_adv:
    putstatic rung36_jcon_mindfa/icn_414_bang_str Ljava/lang/String;
    iconst_0
    putstatic rung36_jcon_mindfa/icn_414_bang_pos I
icn_414_bang_chk:
    getstatic rung36_jcon_mindfa/icn_414_bang_str Ljava/lang/String;
    invokevirtual java/lang/String/length()I
    getstatic rung36_jcon_mindfa/icn_414_bang_pos I
    if_icmple icn_405_α
    getstatic rung36_jcon_mindfa/icn_414_bang_str Ljava/lang/String;
    getstatic rung36_jcon_mindfa/icn_414_bang_pos I
    getstatic rung36_jcon_mindfa/icn_414_bang_pos I
    iconst_1
    iadd
    invokevirtual java/lang/String/substring(II)Ljava/lang/String;
    getstatic rung36_jcon_mindfa/icn_414_bang_pos I
    iconst_1
    iadd
    putstatic rung36_jcon_mindfa/icn_414_bang_pos I
    goto icn_412_vr
icn_412_α:
    goto icn_413_α
icn_412_β:
    goto icn_405_α
icn_412_lr:
    putstatic rung36_jcon_mindfa/icn_412_pushlist Ljava/util/ArrayList;
    goto icn_414_α
icn_412_vr:
    putstatic rung36_jcon_mindfa/icn_412_pushval Ljava/lang/Object;
    getstatic rung36_jcon_mindfa/icn_412_pushlist Ljava/util/ArrayList;
    getstatic rung36_jcon_mindfa/icn_412_pushval Ljava/lang/Object;
    invokevirtual java/util/ArrayList/add(Ljava/lang/Object;)Z
    pop
    getstatic rung36_jcon_mindfa/icn_412_pushlist Ljava/util/ArrayList;
    goto icn_411_gdrain
icn_411_gdrain:
    pop
icn_411_pump:
    goto icn_412_β
icn_411_α:
    goto icn_412_α
icn_411_β:
    goto icn_405_α
icn_419_α:
    new java/util/ArrayList
    dup
    invokespecial java/util/ArrayList/<init>()V
    putstatic rung36_jcon_mindfa/icn_419_mklist Ljava/util/ArrayList;
    getstatic rung36_jcon_mindfa/icn_419_mklist Ljava/util/ArrayList;
    goto icn_418_store
icn_419_β:
    goto icn_411_α
icn_418_α:
    goto icn_419_α
icn_418_β:
    goto icn_419_β
icn_418_store:
    putstatic rung36_jcon_mindfa/icn_pv_diff_l Ljava/util/ArrayList;
    getstatic rung36_jcon_mindfa/icn_pv_diff_l Ljava/util/ArrayList;
    goto icn_diff_s5_sdrain
icn_diff_s5_sdrain:
    pop
    goto icn_411_α
;  VAR
icn_423_α:
    getstatic rung36_jcon_mindfa/icn_pv_diff_l2 J
    goto icn_422_bang_adv
icn_423_β:
    goto icn_418_α
icn_422_α:
    goto icn_423_α
icn_422_β:
    goto icn_422_bang_chk
icn_422_bang_adv:
    putstatic rung36_jcon_mindfa/icn_422_bang_str Ljava/lang/String;
    iconst_0
    putstatic rung36_jcon_mindfa/icn_422_bang_pos I
icn_422_bang_chk:
    getstatic rung36_jcon_mindfa/icn_422_bang_str Ljava/lang/String;
    invokevirtual java/lang/String/length()I
    getstatic rung36_jcon_mindfa/icn_422_bang_pos I
    if_icmple icn_418_α
    getstatic rung36_jcon_mindfa/icn_422_bang_str Ljava/lang/String;
    getstatic rung36_jcon_mindfa/icn_422_bang_pos I
    getstatic rung36_jcon_mindfa/icn_422_bang_pos I
    iconst_1
    iadd
    invokevirtual java/lang/String/substring(II)Ljava/lang/String;
    getstatic rung36_jcon_mindfa/icn_422_bang_pos I
    iconst_1
    iadd
    putstatic rung36_jcon_mindfa/icn_422_bang_pos I
    goto icn_421_rhsok
icn_421_α:
    goto icn_422_α
icn_421_β:
    goto icn_422_β
icn_421_rhsok:
    putstatic rung36_jcon_mindfa/icn_421_augtemp J
    getstatic rung36_jcon_mindfa/icn_pv_diff_t2 J
    getstatic rung36_jcon_mindfa/icn_421_augtemp J
    ladd
    dup2
    putstatic rung36_jcon_mindfa/icn_pv_diff_t2 J
    goto icn_420_gdrain
icn_420_gdrain:
    pop2
icn_420_pump:
    goto icn_421_β
icn_420_α:
    goto icn_421_α
icn_420_β:
    goto icn_418_α
;  STR
icn_425_α:
    ldc ""
    goto icn_424_store
icn_425_β:
    goto icn_420_α
icn_424_α:
    goto icn_425_α
icn_424_β:
    goto icn_425_β
icn_424_store:
    putstatic rung36_jcon_mindfa/icn_pv_diff_t2 Ljava/lang/String;
    getstatic rung36_jcon_mindfa/icn_pv_diff_t2 Ljava/lang/String;
    goto icn_diff_s3_sdrain
icn_diff_s3_sdrain:
    pop
    goto icn_420_α
;  VAR
icn_429_α:
    getstatic rung36_jcon_mindfa/icn_pv_diff_l1 J
    goto icn_428_bang_adv
icn_429_β:
    goto icn_424_α
icn_428_α:
    goto icn_429_α
icn_428_β:
    goto icn_428_bang_chk
icn_428_bang_adv:
    putstatic rung36_jcon_mindfa/icn_428_bang_str Ljava/lang/String;
    iconst_0
    putstatic rung36_jcon_mindfa/icn_428_bang_pos I
icn_428_bang_chk:
    getstatic rung36_jcon_mindfa/icn_428_bang_str Ljava/lang/String;
    invokevirtual java/lang/String/length()I
    getstatic rung36_jcon_mindfa/icn_428_bang_pos I
    if_icmple icn_424_α
    getstatic rung36_jcon_mindfa/icn_428_bang_str Ljava/lang/String;
    getstatic rung36_jcon_mindfa/icn_428_bang_pos I
    getstatic rung36_jcon_mindfa/icn_428_bang_pos I
    iconst_1
    iadd
    invokevirtual java/lang/String/substring(II)Ljava/lang/String;
    getstatic rung36_jcon_mindfa/icn_428_bang_pos I
    iconst_1
    iadd
    putstatic rung36_jcon_mindfa/icn_428_bang_pos I
    goto icn_427_rhsok
icn_427_α:
    goto icn_428_α
icn_427_β:
    goto icn_428_β
icn_427_rhsok:
    putstatic rung36_jcon_mindfa/icn_427_augtemp J
    getstatic rung36_jcon_mindfa/icn_pv_diff_t1 J
    getstatic rung36_jcon_mindfa/icn_427_augtemp J
    ladd
    dup2
    putstatic rung36_jcon_mindfa/icn_pv_diff_t1 J
    goto icn_426_gdrain
icn_426_gdrain:
    pop2
icn_426_pump:
    goto icn_427_β
icn_426_α:
    goto icn_427_α
icn_426_β:
    goto icn_424_α
;  STR
icn_431_α:
    ldc ""
    goto icn_430_store
icn_431_β:
    goto icn_426_α
icn_430_α:
    goto icn_431_α
icn_430_β:
    goto icn_431_β
icn_430_store:
    putstatic rung36_jcon_mindfa/icn_pv_diff_t1 Ljava/lang/String;
    getstatic rung36_jcon_mindfa/icn_pv_diff_t1 Ljava/lang/String;
    goto icn_diff_s1_sdrain
icn_diff_s1_sdrain:
    pop
    goto icn_426_α
icn_diff_done:
    iconst_0
    putstatic rung36_jcon_mindfa/icn_suspended B
    iconst_0
    putstatic rung36_jcon_mindfa/icn_suspend_id I
    iconst_1
    putstatic rung36_jcon_mindfa/icn_failed B
    return
icn_diff_ret:
    iconst_0
    putstatic rung36_jcon_mindfa/icn_failed B
    return
icn_diff_sret:
    return
.end method

; --- record dfa ---
.class public rung36_jcon_mindfa$dfa
.super java/lang/Object

.method public <init>()V
    .limit stack 1
    .limit locals 1
    aload_0
    invokespecial java/lang/Object/<init>()V
    return
.end method

