; Auto-generated by icon_emit_jvm.c — Tiny-ICON Byrd Box JVM
.bytecode 45.0
.class public rung36_jcon_profsum
.super java/lang/Object

.field public static icn_failed B
.field public static icn_suspended B
.field public static icn_suspend_id I
.field public static icn_retval_obj Ljava/lang/Object;
.field public static icn_retval J
.field public static icn_retval_str Ljava/lang/String;
.field public static icn_gvar_ptab Ljava/util/HashMap;
.field public static icn_gvar_callee Ljava/lang/String;
.field public static icn_pv_accumulate_callee Ljava/lang/String;
.field public static icn_gvar_caller Ljava/lang/String;
.field public static icn_pv_accumulate_caller Ljava/lang/String;
.field public static icn_pv_main_l Ljava/util/ArrayList;
.field public static icn_pv_main_line Ljava/lang/String;
.field public static icn_gvar_line Ljava/lang/String;
.field public static icn_pv_main_p Ljava/lang/String;
.field public static icn_gvar_p Ljava/lang/String;
.field public static icn_2_plist Ljava/util/ArrayList;
.field public static icn_2_psz I
.field public static icn_6_binop_lc J
.field public static icn_6_binop_rc J
.field public static icn_6_binop_bf I
.field public static icn_pv_main_ttotal J
.field public static icn_8_binop_lc J
.field public static icn_8_binop_rc J
.field public static icn_8_binop_bf I
.field public static icn_9_binop_lc J
.field public static icn_9_binop_rc J
.field public static icn_9_binop_bf I
.field public static icn_12_binop_lc J
.field public static icn_12_binop_rc J
.field public static icn_12_binop_bf I
.field public static icn_pv_main_pctlocal J
.field public static icn_16_binop_lc J
.field public static icn_16_binop_rc J
.field public static icn_16_binop_bf I
.field public static icn_18_binop_lc J
.field public static icn_18_binop_rc J
.field public static icn_18_binop_bf I
.field public static icn_19_binop_lc J
.field public static icn_19_binop_rc J
.field public static icn_19_binop_bf I
.field public static icn_22_binop_lc J
.field public static icn_22_binop_rc J
.field public static icn_22_binop_bf I
.field public static icn_25_relop_lc J
.field public static icn_25_relop_rc J
.field public static icn_29_binop_lc J
.field public static icn_29_binop_rc J
.field public static icn_29_binop_bf I
.field public static icn_31_binop_lc J
.field public static icn_31_binop_rc J
.field public static icn_31_binop_bf I
.field public static icn_32_binop_lc J
.field public static icn_32_binop_rc J
.field public static icn_32_binop_bf I
.field public static icn_35_binop_lc J
.field public static icn_35_binop_rc J
.field public static icn_35_binop_bf I
.field public static icn_pv_main_pcttotal J
.field public static icn_arg_1 J
.field public static icn_arg_0 J
.field public static icn_54_relop_lc J
.field public static icn_54_relop_rc J
.field public static icn_69_sortf_list Ljava/util/ArrayList;
.field public static icn_69_sortf_fld J
.field public static icn_73_sortf_list Ljava/util/ArrayList;
.field public static icn_73_sortf_fld J
.field public static icn_pv_main_sorttotal J
.field public static icn_81_binop_lc J
.field public static icn_81_binop_rc J
.field public static icn_81_binop_bf I
.field public static icn_85_augtemp J
.field public static icn_87_relop_lc J
.field public static icn_87_relop_rc J
.field public static icn_90_pushval Ljava/lang/Object;
.field public static icn_90_pushlist Ljava/util/ArrayList;
.field public static icn_94_bang_str Ljava/lang/String;
.field public static icn_94_bang_pos I
.field public static icn_99_mklist Ljava/util/ArrayList;
.field public static icn_scan_oldsubj_103 Ljava/lang/String;
.field public static icn_scan_oldpos_103 I
.field public static icn_subject Ljava/lang/String;
.field public static icn_pos I
.field public static icn_118_alt_gate I
.field public static icn_118_alt_val J
.field public static icn_pv_main_f J
.field public static icn_gvar_&input J
.field public static icn_123_relop_lc J
.field public static icn_123_relop_rc J
.field public static icn_pv_main_args J
.field public static icn_129_glist Ljava/util/ArrayList;
.field public static icn_132_sub_s Ljava/lang/String;
.field public static icn_132_sub_i I
.field public static icn_pv_lookup_ptab Ljava/util/HashMap;
.field public static icn_pv_lookup_p J
.field public static icn_140_tsa_vl J
.field public static icn_140_tsa_vo Ljava/lang/Object;
.field public static icn_140_tsa_ks Ljava/lang/String;
.field public static icn_141_rc_a0 Ljava/lang/Object;
.field public static icn_141_rc_a1 Ljava/lang/Object;
.field public static icn_141_rc_a2 Ljava/lang/Object;
.field public static icn_141_rc_a3 Ljava/lang/Object;
.field public static icn_141_rc_obj Ljava/lang/Object;
.field public static icn_pv_lookup_s J
.field public static icn_149_ts_tbl Ljava/util/HashMap;
.field public static icn_149_ts_key Ljava/lang/String;
.field public static icn_149_ts_kval J
.field public static icn_init_lookup I
.field public static icn_pv_accumulate_time J
.field public static icn_arg_str_0 Ljava/lang/String;
.field public static icn_pv_accumulate_q J
.field public static icn_pv_accumulate_count J
.field public static icn_pv_accumulate_p J
.field public static icn_upto_cs_185 Ljava/lang/String;
.field public static icn_183_augtemp_s Ljava/lang/String;
.field public static icn_187_augtemp_s Ljava/lang/String;
.field public static icn_upto_cs_192 Ljava/lang/String;
.field public static icn_upto_cs_199 Ljava/lang/String;
.field public static icn_scan_oldsubj_209 Ljava/lang/String;
.field public static icn_scan_oldpos_209 I
.field public static icn_pv_fixname_s Ljava/lang/String;
.field public static icn_212_alt_gate I
.field public static icn_upto_cs_217 Ljava/lang/String;
.field public static icn_213_and_drain_0 J
.field public static icn_223_binop_lc J
.field public static icn_223_binop_rc J
.field public static icn_223_binop_bf I
.field public static icn_upto_cs_225 Ljava/lang/String;
.field public static icn_219_and_drain_0 J
.field public static icn_212_alt_val J
.field public static icn_234_right_s Ljava/lang/String;
.field public static icn_pv_pad_s Ljava/lang/String;
.field public static icn_pv_pad_n J
.field public static icn_239_relop_lc J
.field public static icn_239_relop_rc J

.method static <clinit>()V
    .limit stack 2
    .limit locals 0
    ldc ""
    putstatic rung36_jcon_profsum/icn_subject Ljava/lang/String;
    iconst_0
    putstatic rung36_jcon_profsum/icn_pos I
    return
.end method

.method public static main([Ljava/lang/String;)V
    .limit stack 4
    .limit locals 1
    invokestatic rung36_jcon_profsum/icn_main()V
    return
.end method

.method public static icn_builtin_any(Ljava/lang/String;Ljava/lang/String;I)J
    .limit stack 4
    .limit locals 3
    ; if pos >= subj.length() → return -1
    aload_1
    invokevirtual java/lang/String/length()I
    iload_2
    if_icmpgt icn_any_inbounds
    ldc2_w -1
    lreturn
icn_any_inbounds:
    ; cs.indexOf(subj.charAt(pos)) >= 0?
    aload_0
    aload_1
    iload_2
    invokevirtual java/lang/String/charAt(I)C
    invokevirtual java/lang/String/indexOf(I)I
    ifge icn_any_match
    ldc2_w -1
    lreturn
icn_any_match:
    ; return pos+2 (new 1-based pos after consuming one char)
    iload_2
    iconst_2
    iadd
    i2l
    lreturn
.end method

.method public static icn_builtin_many(Ljava/lang/String;Ljava/lang/String;I)J
    .limit stack 4
    .limit locals 4
    ; check first char in cs — must match at least one
    aload_1
    invokevirtual java/lang/String/length()I
    iload_2
    if_icmpgt icn_many_first_ok
    ldc2_w -1
    lreturn
icn_many_first_ok:
    aload_0
    aload_1
    iload_2
    invokevirtual java/lang/String/charAt(I)C
    invokevirtual java/lang/String/indexOf(I)I
    ifge icn_many_loop_init
    ldc2_w -1
    lreturn
icn_many_loop_init:
    ; local 3 = pos (working)
    iload_2
    istore_3
icn_many_loop:
    iinc 3 1
    ; if pos3 >= length → done
    aload_1
    invokevirtual java/lang/String/length()I
    iload_3
    if_icmpgt icn_many_cont
    iload_3
    i2l
    lconst_1
    ladd
    lreturn
icn_many_cont:
    aload_0
    aload_1
    iload_3
    invokevirtual java/lang/String/charAt(I)C
    invokevirtual java/lang/String/indexOf(I)I
    ifge icn_many_loop
    ; stopped — return pos3+1 (1-based)
    iload_3
    iconst_1
    iadd
    i2l
    lreturn
.end method

.method public static icn_builtin_upto_step(Ljava/lang/String;Ljava/lang/String;I)J
    .limit stack 4
    .limit locals 4
    iload_2
    istore_3
icn_upto_scan:
    ; if pos3 >= length → -1
    aload_1
    invokevirtual java/lang/String/length()I
    iload_3
    if_icmpgt icn_upto_inbounds
    ldc2_w -1
    lreturn
icn_upto_inbounds:
    aload_0
    aload_1
    iload_3
    invokevirtual java/lang/String/charAt(I)C
    invokevirtual java/lang/String/indexOf(I)I
    ifge icn_upto_found
    iinc 3 1
    goto icn_upto_scan
icn_upto_found:
    ; return pos3+1 (1-based); caller sets icn_pos=result for next resume
    iload_3
    iconst_1
    iadd
    i2l
    lreturn
.end method

.method public static icn_builtin_find(Ljava/lang/String;Ljava/lang/String;I)J
    .limit stack 4
    .limit locals 3
    aload_1
    aload_0
    iload_2
    invokevirtual java/lang/String/indexOf(Ljava/lang/String;I)I
    dup
    ifge icn_find_ok
    pop
    ldc2_w -1
    lreturn
icn_find_ok:
    iconst_1
    iadd
    i2l
    lreturn
.end method

.method public static icn_builtin_match(Ljava/lang/String;Ljava/lang/String;I)J
    .limit stack 4
    .limit locals 3
    aload_1
    aload_0
    iload_2
    invokevirtual java/lang/String/startsWith(Ljava/lang/String;I)Z
    ifne icn_match_ok
    ldc2_w -1
    lreturn
icn_match_ok:
    iload_2
    aload_0
    invokevirtual java/lang/String/length()I
    iadd
    iconst_1
    iadd
    i2l
    lreturn
.end method

.method public static icn_builtin_tab_str(ILjava/lang/String;I)Ljava/lang/String;
    .limit stack 4
    .limit locals 4
    ; end = n-1 (0-based)
    iload_0
    iconst_1
    isub
    istore_3
    ; fail if end < pos
    iload_3
    iload_2
    if_icmpge icn_tab_posok
    aconst_null
    areturn
icn_tab_posok:
    ; fail if end > subj.length()
    aload_1
    invokevirtual java/lang/String/length()I
    iload_3
    if_icmpge icn_tab_lenok
    aconst_null
    areturn
icn_tab_lenok:
    ; update icn_pos = end (static field)
    iload_3
    putstatic rung36_jcon_profsum/icn_pos I
    ; return subj.substring(pos, end)
    aload_1
    iload_2
    iload_3
    invokevirtual java/lang/String/substring(II)Ljava/lang/String;
    areturn
.end method

.method public static icn_builtin_move_str(ILjava/lang/String;I)Ljava/lang/String;
    .limit stack 4
    .limit locals 4
    ; end = pos+n
    iload_2
    iload_0
    iadd
    istore_3
    ; fail if end > subj.length()
    aload_1
    invokevirtual java/lang/String/length()I
    iload_3
    if_icmpge icn_move_ok
    aconst_null
    areturn
icn_move_ok:
    ; update icn_pos = end
    iload_3
    putstatic rung36_jcon_profsum/icn_pos I
    ; return subj.substring(pos, end)
    aload_1
    iload_2
    iload_3
    invokevirtual java/lang/String/substring(II)Ljava/lang/String;
    areturn
.end method

.method public static icn_builtin_left(Ljava/lang/String;ILjava/lang/String;)Ljava/lang/String;
    .limit stack 4
    .limit locals 5
    aload_0
    invokevirtual java/lang/String/length()I
    iload_1
    if_icmplt icn_left_pad
    aload_0
    iconst_0
    iload_1
    invokevirtual java/lang/String/substring(II)Ljava/lang/String;
    areturn
icn_left_pad:
    new java/lang/StringBuilder
    dup
    aload_0
    invokespecial java/lang/StringBuilder/<init>(Ljava/lang/String;)V
    astore_3
icn_left_loop:
    aload_3
    invokevirtual java/lang/StringBuilder/length()I
    iload_1
    if_icmpge icn_left_done
    aload_3
    aload_2
    iconst_0
    invokevirtual java/lang/String/charAt(I)C
    invokevirtual java/lang/StringBuilder/append(C)Ljava/lang/StringBuilder;
    pop
    goto icn_left_loop
icn_left_done:
    aload_3
    invokevirtual java/lang/StringBuilder/toString()Ljava/lang/String;
    areturn
.end method

.method public static icn_builtin_right(Ljava/lang/String;ILjava/lang/String;)Ljava/lang/String;
    .limit stack 4
    .limit locals 5
    aload_0
    invokevirtual java/lang/String/length()I
    iload_1
    if_icmplt icn_right_pad
    aload_0
    invokevirtual java/lang/String/length()I
    iload_1
    isub
    aload_0
    swap
    invokevirtual java/lang/String/substring(I)Ljava/lang/String;
    areturn
icn_right_pad:
    new java/lang/StringBuilder
    dup
    invokespecial java/lang/StringBuilder/<init>()V
    astore_3
    iload_1
    aload_0
    invokevirtual java/lang/String/length()I
    isub
    istore 4
    iconst_0
icn_right_loop:
    dup
    iload 4
    if_icmpge icn_right_append
    aload_3
    aload_2
    iconst_0
    invokevirtual java/lang/String/charAt(I)C
    invokevirtual java/lang/StringBuilder/append(C)Ljava/lang/StringBuilder;
    pop
    iconst_1
    iadd
    goto icn_right_loop
icn_right_append:
    pop
    aload_3
    aload_0
    invokevirtual java/lang/StringBuilder/append(Ljava/lang/String;)Ljava/lang/StringBuilder;
    pop
    aload_3
    invokevirtual java/lang/StringBuilder/toString()Ljava/lang/String;
    areturn
.end method

.method public static icn_builtin_center(Ljava/lang/String;ILjava/lang/String;)Ljava/lang/String;
    .limit stack 5
    .limit locals 7
    aload_0
    invokevirtual java/lang/String/length()I
    iload_1
    if_icmplt icn_ctr_pad
    aload_0
    iconst_0
    iload_1
    invokevirtual java/lang/String/substring(II)Ljava/lang/String;
    areturn
icn_ctr_pad:
    iload_1
    aload_0
    invokevirtual java/lang/String/length()I
    isub
    istore_3
    iload_3
    iconst_2
    idiv
    istore 4
    iload_3
    iload 4
    isub
    istore 5
    new java/lang/StringBuilder
    dup
    invokespecial java/lang/StringBuilder/<init>()V
    astore 6
    iconst_0
icn_ctr_lloop:
    dup
    iload 4
    if_icmpge icn_ctr_mid
    aload 6
    aload_2
    iconst_0
    invokevirtual java/lang/String/charAt(I)C
    invokevirtual java/lang/StringBuilder/append(C)Ljava/lang/StringBuilder;
    pop
    iconst_1
    iadd
    goto icn_ctr_lloop
icn_ctr_mid:
    pop
    aload 6
    aload_0
    invokevirtual java/lang/StringBuilder/append(Ljava/lang/String;)Ljava/lang/StringBuilder;
    pop
    iconst_0
icn_ctr_rloop:
    dup
    iload 5
    if_icmpge icn_ctr_done
    aload 6
    aload_2
    iconst_0
    invokevirtual java/lang/String/charAt(I)C
    invokevirtual java/lang/StringBuilder/append(C)Ljava/lang/StringBuilder;
    pop
    iconst_1
    iadd
    goto icn_ctr_rloop
icn_ctr_done:
    pop
    aload 6
    invokevirtual java/lang/StringBuilder/toString()Ljava/lang/String;
    areturn
.end method

.method public static icn_builtin_trim(Ljava/lang/String;Ljava/lang/String;)Ljava/lang/String;
    .limit stack 4
    .limit locals 3
    aload_0
    invokevirtual java/lang/String/length()I
    istore_2
icn_trim_loop:
    iload_2
    ifle icn_trim_done
    aload_1
    aload_0
    iload_2
    iconst_1
    isub
    invokevirtual java/lang/String/charAt(I)C
    invokevirtual java/lang/String/indexOf(I)I
    iflt icn_trim_done
    iinc 2 -1
    goto icn_trim_loop
icn_trim_done:
    aload_0
    iconst_0
    iload_2
    invokevirtual java/lang/String/substring(II)Ljava/lang/String;
    areturn
.end method

.method public static icn_builtin_map(Ljava/lang/String;Ljava/lang/String;Ljava/lang/String;)Ljava/lang/String;
    .limit stack 5
    .limit locals 7
    new java/lang/StringBuilder
    dup
    invokespecial java/lang/StringBuilder/<init>()V
    astore_3
    iconst_0
    istore 4
icn_map_loop:
    iload 4
    aload_0
    invokevirtual java/lang/String/length()I
    if_icmpge icn_map_done
    aload_0
    iload 4
    invokevirtual java/lang/String/charAt(I)C
    istore 5
    aload_1
    iload 5
    invokevirtual java/lang/String/indexOf(I)I
    istore 6
    iload 6
    iflt icn_map_notfound
    iload 6
    aload_2
    invokevirtual java/lang/String/length()I
    if_icmpge icn_map_notfound
    aload_3
    aload_2
    iload 6
    invokevirtual java/lang/String/charAt(I)C
    invokevirtual java/lang/StringBuilder/append(C)Ljava/lang/StringBuilder;
    pop
    goto icn_map_next
icn_map_notfound:
    aload_3
    iload 5
    invokevirtual java/lang/StringBuilder/append(C)Ljava/lang/StringBuilder;
    pop
icn_map_next:
    iinc 4 1
    goto icn_map_loop
icn_map_done:
    aload_3
    invokevirtual java/lang/StringBuilder/toString()Ljava/lang/String;
    areturn
.end method

.method public static icn_builtin_parse_long(Ljava/lang/String;)J
    .limit stack 4
    .limit locals 4
    .catch java/lang/Exception from icn_plong_L0 to icn_plong_L1 using icn_plong_catch
icn_plong_L0:
    aload_0
    invokevirtual java/lang/String/trim()Ljava/lang/String;
    astore_1
    aload_1
    ldc "r"
    invokevirtual java/lang/String/contains(Ljava/lang/CharSequence;)Z
    ifeq icn_plong_plain
    aload_1
    ldc "r"
    iconst_2
    invokevirtual java/lang/String/split(Ljava/lang/String;I)[Ljava/lang/String;
    astore_2
    aload_2
    iconst_0
    aaload
    invokestatic java/lang/Integer/parseInt(Ljava/lang/String;)I
    istore_3
    aload_2
    iconst_1
    aaload
    iload_3
    invokestatic java/lang/Long/parseLong(Ljava/lang/String;I)J
    goto icn_plong_L1
icn_plong_plain:
    aload_1
    invokestatic java/lang/Long/parseLong(Ljava/lang/String;)J
icn_plong_L1:
    lreturn
icn_plong_catch:
    pop
    ldc2_w -9223372036854775808
    lreturn
.end method

.method public static icn_builtin_numeric(Ljava/lang/String;)J
    .limit stack 2
    .limit locals 2
    aload_0
    invokestatic rung36_jcon_profsum/icn_builtin_parse_long(Ljava/lang/String;)J
    lreturn
.end method

.method public static icn_builtin_sort(Ljava/util/ArrayList;)Ljava/util/ArrayList;
    .limit stack 6
    .limit locals 8
    new java/util/ArrayList
    dup
    aload_0
    invokespecial java/util/ArrayList/<init>(Ljava/util/Collection;)V
    astore_1
    iconst_1
    istore_2
icn_sort_outer:
    aload_1
    invokevirtual java/util/ArrayList/size()I
    iload_2
    if_icmple icn_sort_done
    aload_1
    iload_2
    invokevirtual java/util/ArrayList/get(I)Ljava/lang/Object;
    checkcast java/lang/Long
    invokevirtual java/lang/Long/longValue()J
    lstore 4
    iload_2
    iconst_1
    isub
    istore_3
icn_sort_inner:
    iload_3
    iflt icn_sort_insert
    aload_1
    iload_3
    invokevirtual java/util/ArrayList/get(I)Ljava/lang/Object;
    checkcast java/lang/Long
    invokevirtual java/lang/Long/longValue()J
    lload 4
    lcmp
    ifle icn_sort_insert
    aload_1
    iload_3
    iconst_1
    iadd
    aload_1
    iload_3
    invokevirtual java/util/ArrayList/get(I)Ljava/lang/Object;
    invokevirtual java/util/ArrayList/set(ILjava/lang/Object;)Ljava/lang/Object;
    pop
    iinc 3 -1
    goto icn_sort_inner
icn_sort_insert:
    aload_1
    iload_3
    iconst_1
    iadd
    lload 4
    invokestatic java/lang/Long/valueOf(J)Ljava/lang/Long;
    invokevirtual java/util/ArrayList/set(ILjava/lang/Object;)Ljava/lang/Object;
    pop
    iinc 2 1
    goto icn_sort_outer
icn_sort_done:
    aload_1
    areturn
.end method

.method public static icn_builtin_sortf(Ljava/util/ArrayList;I)Ljava/util/ArrayList;
    .limit stack 8
    .limit locals 10
    new java/util/ArrayList
    dup
    aload_0
    invokespecial java/util/ArrayList/<init>(Ljava/util/Collection;)V
    astore_2
    iconst_1
    istore_3
icn_sortf_outer:
    aload_2
    invokevirtual java/util/ArrayList/size()I
    iload_3
    if_icmple icn_sortf_done
    aload_2
    iload_3
    invokevirtual java/util/ArrayList/get(I)Ljava/lang/Object;
    astore 5
    iload_3
    iconst_1
    isub
    istore 4
icn_sortf_inner:
    iload 4
    iflt icn_sortf_insert
    aload_2
    iload 4
    invokevirtual java/util/ArrayList/get(I)Ljava/lang/Object;
    astore 6
    aload 6
    invokevirtual java/lang/Object/getClass()Ljava/lang/Class;
    invokevirtual java/lang/Class/getDeclaredFields()[Ljava/lang/reflect/Field;
    iload_1
    iconst_1
    isub
    aaload
    aload 6
    invokevirtual java/lang/reflect/Field/get(Ljava/lang/Object;)Ljava/lang/Object;
    astore 7
    aload 5
    invokevirtual java/lang/Object/getClass()Ljava/lang/Class;
    invokevirtual java/lang/Class/getDeclaredFields()[Ljava/lang/reflect/Field;
    iload_1
    iconst_1
    isub
    aaload
    aload 5
    invokevirtual java/lang/reflect/Field/get(Ljava/lang/Object;)Ljava/lang/Object;
    astore 8
    aload 7
    checkcast java/lang/Long
    aload 8
    checkcast java/lang/Long
    invokevirtual java/lang/Long/compareTo(Ljava/lang/Long;)I
    ifle icn_sortf_insert
    aload_2
    iload 4
    iconst_1
    iadd
    aload_2
    iload 4
    invokevirtual java/util/ArrayList/get(I)Ljava/lang/Object;
    invokevirtual java/util/ArrayList/set(ILjava/lang/Object;)Ljava/lang/Object;
    pop
    iinc 4 -1
    goto icn_sortf_inner
icn_sortf_insert:
    aload_2
    iload 4
    iconst_1
    iadd
    aload 5
    invokevirtual java/util/ArrayList/set(ILjava/lang/Object;)Ljava/lang/Object;
    pop
    iinc 3 1
    goto icn_sortf_outer
icn_sortf_done:
    aload_2
    areturn
.end method

.method public static icn_main()V
    .limit stack 16
    .limit locals 342
    lconst_0
    lstore 0
    lconst_0
    lstore 2
    lconst_0
    lstore 4
    lconst_0
    lstore 6
    lconst_0
    lstore 8
    lconst_0
    lstore 10
    lconst_0
    lstore 12
    lconst_0
    lstore 14
    lconst_0
    lstore 16
    lconst_0
    lstore 18
    lconst_0
    lstore 20
    lconst_0
    lstore 22
    lconst_0
    lstore 24
    lconst_0
    lstore 26
    lconst_0
    lstore 28
    lconst_0
    lstore 30
    lconst_0
    lstore 32
    lconst_0
    lstore 34
    lconst_0
    lstore 36
    lconst_0
    lstore 38
    lconst_0
    lstore 40
    lconst_0
    lstore 42
    lconst_0
    lstore 44
    lconst_0
    lstore 46
    lconst_0
    lstore 48
    lconst_0
    lstore 50
    lconst_0
    lstore 52
    lconst_0
    lstore 54
    lconst_0
    lstore 56
    lconst_0
    lstore 58
    lconst_0
    lstore 60
    lconst_0
    lstore 62
    iconst_0
    istore 84
    iconst_0
    istore 85
    iconst_0
    istore 86
    iconst_0
    istore 87
    iconst_0
    istore 88
    iconst_0
    istore 89
    iconst_0
    istore 90
    aconst_null
    astore 148
    aconst_null
    astore 149
    aconst_null
    astore 150
    aconst_null
    astore 151
    aconst_null
    astore 152
    aconst_null
    astore 153
    aconst_null
    astore 154
    aconst_null
    astore 155
    aconst_null
    astore 156
    aconst_null
    astore 157
    goto icn_127_α
;  VAR
icn_3_α:
    getstatic rung36_jcon_profsum/icn_pv_main_l Ljava/util/ArrayList;
    goto icn_2_lr
icn_3_β:
    goto icn_main_done
icn_2_α:
    goto icn_3_α
icn_2_β:
    goto icn_main_done
icn_2_lr:
    putstatic rung36_jcon_profsum/icn_2_plist Ljava/util/ArrayList;
    getstatic rung36_jcon_profsum/icn_2_plist Ljava/util/ArrayList;
    invokevirtual java/util/ArrayList/size()I
    dup
    ifeq icn_2_pfail
    iconst_1
    isub
    putstatic rung36_jcon_profsum/icn_2_psz I
    getstatic rung36_jcon_profsum/icn_2_plist Ljava/util/ArrayList;
    getstatic rung36_jcon_profsum/icn_2_psz I
    invokevirtual java/util/ArrayList/remove(I)Ljava/lang/Object;
    dup
    ifnonnull icn_2_pok
    pop
    goto icn_main_done
icn_2_pok:
    checkcast java/lang/Long
    invokevirtual java/lang/Long/longValue()J
    goto icn_1_store
icn_2_pfail:
    pop
    goto icn_main_done
icn_1_α:
    goto icn_2_α
icn_1_β:
    goto icn_2_β
icn_1_store:
    putstatic rung36_jcon_profsum/icn_pv_main_p J
    getstatic rung36_jcon_profsum/icn_pv_main_p J
    goto icn_0_condok
icn_0_condok:
    pop2
    goto icn_0_wbstart
;  VAR
icn_7_α:
    getstatic rung36_jcon_profsum/icn_pv_main_ttotal J
    goto icn_6_rrelay
icn_7_β:
    goto icn_6_lb
;  INT
icn_10_α:
    ldc2_w 2
    goto icn_9_rrelay
icn_10_β:
    goto icn_9_lb
;  VAR
icn_11_α:
    getstatic rung36_jcon_profsum/icn_pv_main_ttotal J
    goto icn_9_lrelay
icn_11_β:
    goto icn_8_lb
icn_9_lrelay:
    putstatic rung36_jcon_profsum/icn_9_binop_lc J
    goto icn_9_lstore
icn_9_rrelay:
    putstatic rung36_jcon_profsum/icn_9_binop_rc J
    goto icn_9_compute
icn_9_lb:
    goto icn_11_β
icn_9_α:
    iconst_0
    putstatic rung36_jcon_profsum/icn_9_binop_bf I
    goto icn_11_α
icn_9_β:
    iconst_1
    putstatic rung36_jcon_profsum/icn_9_binop_bf I
    goto icn_11_α
icn_9_lstore:
    getstatic rung36_jcon_profsum/icn_9_binop_bf I
    ifeq icn_10_α
    goto icn_10_β
icn_9_compute:
    getstatic rung36_jcon_profsum/icn_9_binop_lc J
    getstatic rung36_jcon_profsum/icn_9_binop_rc J
    ldiv
    goto icn_8_rrelay
icn_13_α:
    goto icn_12_lb
icn_13_β:
    goto icn_12_lb
;  INT
icn_14_α:
    ldc2_w 100
    goto icn_12_lrelay
icn_14_β:
    goto icn_0_wb_rf_0
icn_12_lrelay:
    putstatic rung36_jcon_profsum/icn_12_binop_lc J
    goto icn_12_lstore
icn_12_rrelay:
    putstatic rung36_jcon_profsum/icn_12_binop_rc J
    goto icn_12_compute
icn_12_lb:
    goto icn_14_β
icn_12_α:
    iconst_0
    putstatic rung36_jcon_profsum/icn_12_binop_bf I
    goto icn_14_α
icn_12_β:
    iconst_1
    putstatic rung36_jcon_profsum/icn_12_binop_bf I
    goto icn_14_α
icn_12_lstore:
    getstatic rung36_jcon_profsum/icn_12_binop_bf I
    ifeq icn_13_α
    goto icn_13_β
icn_12_compute:
    getstatic rung36_jcon_profsum/icn_12_binop_lc J
    getstatic rung36_jcon_profsum/icn_12_binop_rc J
    lmul
    goto icn_8_lrelay
icn_8_lrelay:
    putstatic rung36_jcon_profsum/icn_8_binop_lc J
    goto icn_8_lstore
icn_8_rrelay:
    putstatic rung36_jcon_profsum/icn_8_binop_rc J
    goto icn_8_compute
icn_8_lb:
    goto icn_12_β
icn_8_α:
    iconst_0
    putstatic rung36_jcon_profsum/icn_8_binop_bf I
    goto icn_12_α
icn_8_β:
    goto icn_9_β
icn_8_lstore:
    getstatic rung36_jcon_profsum/icn_8_binop_bf I
    ifeq icn_9_α
    goto icn_9_β
icn_8_compute:
    getstatic rung36_jcon_profsum/icn_8_binop_lc J
    getstatic rung36_jcon_profsum/icn_8_binop_rc J
    ladd
    goto icn_6_lrelay
icn_6_lrelay:
    putstatic rung36_jcon_profsum/icn_6_binop_lc J
    goto icn_6_lstore
icn_6_rrelay:
    putstatic rung36_jcon_profsum/icn_6_binop_rc J
    goto icn_6_compute
icn_6_lb:
    goto icn_8_β
icn_6_α:
    iconst_0
    putstatic rung36_jcon_profsum/icn_6_binop_bf I
    goto icn_8_α
icn_6_β:
    goto icn_7_β
icn_6_lstore:
    getstatic rung36_jcon_profsum/icn_6_binop_bf I
    ifeq icn_7_α
    goto icn_7_β
icn_6_compute:
    getstatic rung36_jcon_profsum/icn_6_binop_lc J
    getstatic rung36_jcon_profsum/icn_6_binop_rc J
    ldiv
    goto icn_5_store
icn_5_α:
    goto icn_6_α
icn_5_β:
    goto icn_6_β
icn_5_store:
    putstatic rung36_jcon_profsum/icn_pv_main_pctlocal J
    getstatic rung36_jcon_profsum/icn_pv_main_pctlocal J
    goto icn_0_wb_rg_0
;  VAR
icn_17_α:
    getstatic rung36_jcon_profsum/icn_pv_main_ttotal J
    goto icn_16_rrelay
icn_17_β:
    goto icn_16_lb
;  INT
icn_20_α:
    ldc2_w 2
    goto icn_19_rrelay
icn_20_β:
    goto icn_19_lb
;  VAR
icn_21_α:
    getstatic rung36_jcon_profsum/icn_pv_main_ttotal J
    goto icn_19_lrelay
icn_21_β:
    goto icn_18_lb
icn_19_lrelay:
    putstatic rung36_jcon_profsum/icn_19_binop_lc J
    goto icn_19_lstore
icn_19_rrelay:
    putstatic rung36_jcon_profsum/icn_19_binop_rc J
    goto icn_19_compute
icn_19_lb:
    goto icn_21_β
icn_19_α:
    iconst_0
    putstatic rung36_jcon_profsum/icn_19_binop_bf I
    goto icn_21_α
icn_19_β:
    iconst_1
    putstatic rung36_jcon_profsum/icn_19_binop_bf I
    goto icn_21_α
icn_19_lstore:
    getstatic rung36_jcon_profsum/icn_19_binop_bf I
    ifeq icn_20_α
    goto icn_20_β
icn_19_compute:
    getstatic rung36_jcon_profsum/icn_19_binop_lc J
    getstatic rung36_jcon_profsum/icn_19_binop_rc J
    ldiv
    goto icn_18_rrelay
icn_23_α:
    goto icn_22_lb
icn_23_β:
    goto icn_22_lb
;  INT
icn_24_α:
    ldc2_w 100
    goto icn_22_lrelay
icn_24_β:
    goto icn_0_wb_rf_0
icn_22_lrelay:
    putstatic rung36_jcon_profsum/icn_22_binop_lc J
    goto icn_22_lstore
icn_22_rrelay:
    putstatic rung36_jcon_profsum/icn_22_binop_rc J
    goto icn_22_compute
icn_22_lb:
    goto icn_24_β
icn_22_α:
    iconst_0
    putstatic rung36_jcon_profsum/icn_22_binop_bf I
    goto icn_24_α
icn_22_β:
    iconst_1
    putstatic rung36_jcon_profsum/icn_22_binop_bf I
    goto icn_24_α
icn_22_lstore:
    getstatic rung36_jcon_profsum/icn_22_binop_bf I
    ifeq icn_23_α
    goto icn_23_β
icn_22_compute:
    getstatic rung36_jcon_profsum/icn_22_binop_lc J
    getstatic rung36_jcon_profsum/icn_22_binop_rc J
    lmul
    goto icn_18_lrelay
icn_18_lrelay:
    putstatic rung36_jcon_profsum/icn_18_binop_lc J
    goto icn_18_lstore
icn_18_rrelay:
    putstatic rung36_jcon_profsum/icn_18_binop_rc J
    goto icn_18_compute
icn_18_lb:
    goto icn_22_β
icn_18_α:
    iconst_0
    putstatic rung36_jcon_profsum/icn_18_binop_bf I
    goto icn_22_α
icn_18_β:
    goto icn_19_β
icn_18_lstore:
    getstatic rung36_jcon_profsum/icn_18_binop_bf I
    ifeq icn_19_α
    goto icn_19_β
icn_18_compute:
    getstatic rung36_jcon_profsum/icn_18_binop_lc J
    getstatic rung36_jcon_profsum/icn_18_binop_rc J
    lsub
    goto icn_16_lrelay
icn_16_lrelay:
    putstatic rung36_jcon_profsum/icn_16_binop_lc J
    goto icn_16_lstore
icn_16_rrelay:
    putstatic rung36_jcon_profsum/icn_16_binop_rc J
    goto icn_16_compute
icn_16_lb:
    goto icn_18_β
icn_16_α:
    iconst_0
    putstatic rung36_jcon_profsum/icn_16_binop_bf I
    goto icn_18_α
icn_16_β:
    goto icn_17_β
icn_16_lstore:
    getstatic rung36_jcon_profsum/icn_16_binop_bf I
    ifeq icn_17_α
    goto icn_17_β
icn_16_compute:
    getstatic rung36_jcon_profsum/icn_16_binop_lc J
    getstatic rung36_jcon_profsum/icn_16_binop_rc J
    ldiv
    goto icn_15_store
icn_15_α:
    goto icn_16_α
icn_15_β:
    goto icn_16_β
icn_15_store:
    putstatic rung36_jcon_profsum/icn_pv_main_pctlocal J
    getstatic rung36_jcon_profsum/icn_pv_main_pctlocal J
    goto icn_0_wb_rg_0
;  INT
icn_26_α:
    ldc2_w 0
    goto icn_25_rrelay
icn_26_β:
    goto icn_25_lb
icn_27_α:
    goto icn_4_else
icn_27_β:
    goto icn_4_else
icn_25_lrelay:
    putstatic rung36_jcon_profsum/icn_25_relop_lc J
    goto icn_25_lstore
icn_25_rrelay:
    putstatic rung36_jcon_profsum/icn_25_relop_rc J
    goto icn_25_check
icn_25_lb:
    goto icn_27_β
icn_25_α:
    goto icn_27_α
icn_25_β:
    goto icn_26_β
icn_25_lstore:
    goto icn_26_α
icn_25_check:
    getstatic rung36_jcon_profsum/icn_25_relop_lc J
    getstatic rung36_jcon_profsum/icn_25_relop_rc J
    lcmp
    ifle icn_26_β
    getstatic rung36_jcon_profsum/icn_25_relop_rc J
    goto icn_4_then
icn_4_then:
    pop2
    goto icn_5_α
icn_4_else:
    goto icn_15_α
icn_4_α:
    goto icn_25_α
icn_4_β:
    goto icn_25_β
;  VAR
icn_30_α:
    getstatic rung36_jcon_profsum/icn_pv_main_ttotal J
    goto icn_29_rrelay
icn_30_β:
    goto icn_29_lb
;  INT
icn_33_α:
    ldc2_w 2
    goto icn_32_rrelay
icn_33_β:
    goto icn_32_lb
;  VAR
icn_34_α:
    getstatic rung36_jcon_profsum/icn_pv_main_ttotal J
    goto icn_32_lrelay
icn_34_β:
    goto icn_31_lb
icn_32_lrelay:
    putstatic rung36_jcon_profsum/icn_32_binop_lc J
    goto icn_32_lstore
icn_32_rrelay:
    putstatic rung36_jcon_profsum/icn_32_binop_rc J
    goto icn_32_compute
icn_32_lb:
    goto icn_34_β
icn_32_α:
    iconst_0
    putstatic rung36_jcon_profsum/icn_32_binop_bf I
    goto icn_34_α
icn_32_β:
    iconst_1
    putstatic rung36_jcon_profsum/icn_32_binop_bf I
    goto icn_34_α
icn_32_lstore:
    getstatic rung36_jcon_profsum/icn_32_binop_bf I
    ifeq icn_33_α
    goto icn_33_β
icn_32_compute:
    getstatic rung36_jcon_profsum/icn_32_binop_lc J
    getstatic rung36_jcon_profsum/icn_32_binop_rc J
    ldiv
    goto icn_31_rrelay
icn_36_α:
    goto icn_35_lb
icn_36_β:
    goto icn_35_lb
;  INT
icn_37_α:
    ldc2_w 100
    goto icn_35_lrelay
icn_37_β:
    goto icn_0_wb_rf_1
icn_35_lrelay:
    putstatic rung36_jcon_profsum/icn_35_binop_lc J
    goto icn_35_lstore
icn_35_rrelay:
    putstatic rung36_jcon_profsum/icn_35_binop_rc J
    goto icn_35_compute
icn_35_lb:
    goto icn_37_β
icn_35_α:
    iconst_0
    putstatic rung36_jcon_profsum/icn_35_binop_bf I
    goto icn_37_α
icn_35_β:
    iconst_1
    putstatic rung36_jcon_profsum/icn_35_binop_bf I
    goto icn_37_α
icn_35_lstore:
    getstatic rung36_jcon_profsum/icn_35_binop_bf I
    ifeq icn_36_α
    goto icn_36_β
icn_35_compute:
    getstatic rung36_jcon_profsum/icn_35_binop_lc J
    getstatic rung36_jcon_profsum/icn_35_binop_rc J
    lmul
    goto icn_31_lrelay
icn_31_lrelay:
    putstatic rung36_jcon_profsum/icn_31_binop_lc J
    goto icn_31_lstore
icn_31_rrelay:
    putstatic rung36_jcon_profsum/icn_31_binop_rc J
    goto icn_31_compute
icn_31_lb:
    goto icn_35_β
icn_31_α:
    iconst_0
    putstatic rung36_jcon_profsum/icn_31_binop_bf I
    goto icn_35_α
icn_31_β:
    goto icn_32_β
icn_31_lstore:
    getstatic rung36_jcon_profsum/icn_31_binop_bf I
    ifeq icn_32_α
    goto icn_32_β
icn_31_compute:
    getstatic rung36_jcon_profsum/icn_31_binop_lc J
    getstatic rung36_jcon_profsum/icn_31_binop_rc J
    ladd
    goto icn_29_lrelay
icn_29_lrelay:
    putstatic rung36_jcon_profsum/icn_29_binop_lc J
    goto icn_29_lstore
icn_29_rrelay:
    putstatic rung36_jcon_profsum/icn_29_binop_rc J
    goto icn_29_compute
icn_29_lb:
    goto icn_31_β
icn_29_α:
    iconst_0
    putstatic rung36_jcon_profsum/icn_29_binop_bf I
    goto icn_31_α
icn_29_β:
    goto icn_30_β
icn_29_lstore:
    getstatic rung36_jcon_profsum/icn_29_binop_bf I
    ifeq icn_30_α
    goto icn_30_β
icn_29_compute:
    getstatic rung36_jcon_profsum/icn_29_binop_lc J
    getstatic rung36_jcon_profsum/icn_29_binop_rc J
    ldiv
    goto icn_28_store
icn_28_α:
    goto icn_29_α
icn_28_β:
    goto icn_29_β
icn_28_store:
    putstatic rung36_jcon_profsum/icn_pv_main_pcttotal J
    getstatic rung36_jcon_profsum/icn_pv_main_pcttotal J
    goto icn_0_wb_rg_1
;  INT
icn_40_α:
    ldc2_w 7
    goto icn_39_arg1
icn_40_β:
    goto icn_0_top
icn_39_arg1:
    putstatic rung36_jcon_profsum/icn_arg_1 J
    goto icn_39_docall
icn_41_α:
    goto icn_0_top
icn_41_β:
    goto icn_0_top
icn_39_arg0:
    putstatic rung36_jcon_profsum/icn_arg_0 J
    goto icn_40_α
icn_39_α:
    goto icn_41_α
icn_39_β:
    goto icn_40_β
icn_39_docall:
    getstatic rung36_jcon_profsum/icn_6_binop_lc J
    lstore 152
    getstatic rung36_jcon_profsum/icn_6_binop_rc J
    lstore 154
    getstatic rung36_jcon_profsum/icn_pv_main_ttotal J
    lstore 156
    getstatic rung36_jcon_profsum/icn_8_binop_lc J
    lstore 158
    getstatic rung36_jcon_profsum/icn_8_binop_rc J
    lstore 160
    getstatic rung36_jcon_profsum/icn_9_binop_lc J
    lstore 162
    getstatic rung36_jcon_profsum/icn_9_binop_rc J
    lstore 164
    getstatic rung36_jcon_profsum/icn_12_binop_lc J
    lstore 166
    getstatic rung36_jcon_profsum/icn_12_binop_rc J
    lstore 168
    getstatic rung36_jcon_profsum/icn_pv_main_pctlocal J
    lstore 170
    getstatic rung36_jcon_profsum/icn_16_binop_lc J
    lstore 172
    getstatic rung36_jcon_profsum/icn_16_binop_rc J
    lstore 174
    getstatic rung36_jcon_profsum/icn_18_binop_lc J
    lstore 176
    getstatic rung36_jcon_profsum/icn_18_binop_rc J
    lstore 178
    getstatic rung36_jcon_profsum/icn_19_binop_lc J
    lstore 180
    getstatic rung36_jcon_profsum/icn_19_binop_rc J
    lstore 182
    getstatic rung36_jcon_profsum/icn_22_binop_lc J
    lstore 184
    getstatic rung36_jcon_profsum/icn_22_binop_rc J
    lstore 186
    getstatic rung36_jcon_profsum/icn_25_relop_lc J
    lstore 188
    getstatic rung36_jcon_profsum/icn_25_relop_rc J
    lstore 190
    getstatic rung36_jcon_profsum/icn_29_binop_lc J
    lstore 192
    getstatic rung36_jcon_profsum/icn_29_binop_rc J
    lstore 194
    getstatic rung36_jcon_profsum/icn_31_binop_lc J
    lstore 196
    getstatic rung36_jcon_profsum/icn_31_binop_rc J
    lstore 198
    getstatic rung36_jcon_profsum/icn_32_binop_lc J
    lstore 200
    getstatic rung36_jcon_profsum/icn_32_binop_rc J
    lstore 202
    getstatic rung36_jcon_profsum/icn_35_binop_lc J
    lstore 204
    getstatic rung36_jcon_profsum/icn_35_binop_rc J
    lstore 206
    getstatic rung36_jcon_profsum/icn_pv_main_pcttotal J
    lstore 208
    invokestatic rung36_jcon_profsum/icn_pad()V
    lload 152
    putstatic rung36_jcon_profsum/icn_6_binop_lc J
    lload 154
    putstatic rung36_jcon_profsum/icn_6_binop_rc J
    lload 156
    putstatic rung36_jcon_profsum/icn_pv_main_ttotal J
    lload 158
    putstatic rung36_jcon_profsum/icn_8_binop_lc J
    lload 160
    putstatic rung36_jcon_profsum/icn_8_binop_rc J
    lload 162
    putstatic rung36_jcon_profsum/icn_9_binop_lc J
    lload 164
    putstatic rung36_jcon_profsum/icn_9_binop_rc J
    lload 166
    putstatic rung36_jcon_profsum/icn_12_binop_lc J
    lload 168
    putstatic rung36_jcon_profsum/icn_12_binop_rc J
    lload 170
    putstatic rung36_jcon_profsum/icn_pv_main_pctlocal J
    lload 172
    putstatic rung36_jcon_profsum/icn_16_binop_lc J
    lload 174
    putstatic rung36_jcon_profsum/icn_16_binop_rc J
    lload 176
    putstatic rung36_jcon_profsum/icn_18_binop_lc J
    lload 178
    putstatic rung36_jcon_profsum/icn_18_binop_rc J
    lload 180
    putstatic rung36_jcon_profsum/icn_19_binop_lc J
    lload 182
    putstatic rung36_jcon_profsum/icn_19_binop_rc J
    lload 184
    putstatic rung36_jcon_profsum/icn_22_binop_lc J
    lload 186
    putstatic rung36_jcon_profsum/icn_22_binop_rc J
    lload 188
    putstatic rung36_jcon_profsum/icn_25_relop_lc J
    lload 190
    putstatic rung36_jcon_profsum/icn_25_relop_rc J
    lload 192
    putstatic rung36_jcon_profsum/icn_29_binop_lc J
    lload 194
    putstatic rung36_jcon_profsum/icn_29_binop_rc J
    lload 196
    putstatic rung36_jcon_profsum/icn_31_binop_lc J
    lload 198
    putstatic rung36_jcon_profsum/icn_31_binop_rc J
    lload 200
    putstatic rung36_jcon_profsum/icn_32_binop_lc J
    lload 202
    putstatic rung36_jcon_profsum/icn_32_binop_rc J
    lload 204
    putstatic rung36_jcon_profsum/icn_35_binop_lc J
    lload 206
    putstatic rung36_jcon_profsum/icn_35_binop_rc J
    lload 208
    putstatic rung36_jcon_profsum/icn_pv_main_pcttotal J
    getstatic rung36_jcon_profsum/icn_failed B
    ifne icn_39_after_call
    getstatic rung36_jcon_profsum/icn_retval J
    goto icn_38_waft_0
icn_39_after_call:
    goto icn_0_top
;  INT
icn_43_α:
    ldc2_w 7
    goto icn_42_arg1
icn_43_β:
    goto icn_0_top
icn_42_arg1:
    putstatic rung36_jcon_profsum/icn_arg_1 J
    goto icn_42_docall
icn_44_α:
    goto icn_0_top
icn_44_β:
    goto icn_0_top
icn_42_arg0:
    putstatic rung36_jcon_profsum/icn_arg_0 J
    goto icn_43_α
icn_42_α:
    goto icn_44_α
icn_42_β:
    goto icn_43_β
icn_42_docall:
    getstatic rung36_jcon_profsum/icn_6_binop_lc J
    lstore 152
    getstatic rung36_jcon_profsum/icn_6_binop_rc J
    lstore 154
    getstatic rung36_jcon_profsum/icn_pv_main_ttotal J
    lstore 156
    getstatic rung36_jcon_profsum/icn_8_binop_lc J
    lstore 158
    getstatic rung36_jcon_profsum/icn_8_binop_rc J
    lstore 160
    getstatic rung36_jcon_profsum/icn_9_binop_lc J
    lstore 162
    getstatic rung36_jcon_profsum/icn_9_binop_rc J
    lstore 164
    getstatic rung36_jcon_profsum/icn_12_binop_lc J
    lstore 166
    getstatic rung36_jcon_profsum/icn_12_binop_rc J
    lstore 168
    getstatic rung36_jcon_profsum/icn_pv_main_pctlocal J
    lstore 170
    getstatic rung36_jcon_profsum/icn_16_binop_lc J
    lstore 172
    getstatic rung36_jcon_profsum/icn_16_binop_rc J
    lstore 174
    getstatic rung36_jcon_profsum/icn_18_binop_lc J
    lstore 176
    getstatic rung36_jcon_profsum/icn_18_binop_rc J
    lstore 178
    getstatic rung36_jcon_profsum/icn_19_binop_lc J
    lstore 180
    getstatic rung36_jcon_profsum/icn_19_binop_rc J
    lstore 182
    getstatic rung36_jcon_profsum/icn_22_binop_lc J
    lstore 184
    getstatic rung36_jcon_profsum/icn_22_binop_rc J
    lstore 186
    getstatic rung36_jcon_profsum/icn_25_relop_lc J
    lstore 188
    getstatic rung36_jcon_profsum/icn_25_relop_rc J
    lstore 190
    getstatic rung36_jcon_profsum/icn_29_binop_lc J
    lstore 192
    getstatic rung36_jcon_profsum/icn_29_binop_rc J
    lstore 194
    getstatic rung36_jcon_profsum/icn_31_binop_lc J
    lstore 196
    getstatic rung36_jcon_profsum/icn_31_binop_rc J
    lstore 198
    getstatic rung36_jcon_profsum/icn_32_binop_lc J
    lstore 200
    getstatic rung36_jcon_profsum/icn_32_binop_rc J
    lstore 202
    getstatic rung36_jcon_profsum/icn_35_binop_lc J
    lstore 204
    getstatic rung36_jcon_profsum/icn_35_binop_rc J
    lstore 206
    getstatic rung36_jcon_profsum/icn_pv_main_pcttotal J
    lstore 208
    invokestatic rung36_jcon_profsum/icn_pad()V
    lload 152
    putstatic rung36_jcon_profsum/icn_6_binop_lc J
    lload 154
    putstatic rung36_jcon_profsum/icn_6_binop_rc J
    lload 156
    putstatic rung36_jcon_profsum/icn_pv_main_ttotal J
    lload 158
    putstatic rung36_jcon_profsum/icn_8_binop_lc J
    lload 160
    putstatic rung36_jcon_profsum/icn_8_binop_rc J
    lload 162
    putstatic rung36_jcon_profsum/icn_9_binop_lc J
    lload 164
    putstatic rung36_jcon_profsum/icn_9_binop_rc J
    lload 166
    putstatic rung36_jcon_profsum/icn_12_binop_lc J
    lload 168
    putstatic rung36_jcon_profsum/icn_12_binop_rc J
    lload 170
    putstatic rung36_jcon_profsum/icn_pv_main_pctlocal J
    lload 172
    putstatic rung36_jcon_profsum/icn_16_binop_lc J
    lload 174
    putstatic rung36_jcon_profsum/icn_16_binop_rc J
    lload 176
    putstatic rung36_jcon_profsum/icn_18_binop_lc J
    lload 178
    putstatic rung36_jcon_profsum/icn_18_binop_rc J
    lload 180
    putstatic rung36_jcon_profsum/icn_19_binop_lc J
    lload 182
    putstatic rung36_jcon_profsum/icn_19_binop_rc J
    lload 184
    putstatic rung36_jcon_profsum/icn_22_binop_lc J
    lload 186
    putstatic rung36_jcon_profsum/icn_22_binop_rc J
    lload 188
    putstatic rung36_jcon_profsum/icn_25_relop_lc J
    lload 190
    putstatic rung36_jcon_profsum/icn_25_relop_rc J
    lload 192
    putstatic rung36_jcon_profsum/icn_29_binop_lc J
    lload 194
    putstatic rung36_jcon_profsum/icn_29_binop_rc J
    lload 196
    putstatic rung36_jcon_profsum/icn_31_binop_lc J
    lload 198
    putstatic rung36_jcon_profsum/icn_31_binop_rc J
    lload 200
    putstatic rung36_jcon_profsum/icn_32_binop_lc J
    lload 202
    putstatic rung36_jcon_profsum/icn_32_binop_rc J
    lload 204
    putstatic rung36_jcon_profsum/icn_35_binop_lc J
    lload 206
    putstatic rung36_jcon_profsum/icn_35_binop_rc J
    lload 208
    putstatic rung36_jcon_profsum/icn_pv_main_pcttotal J
    getstatic rung36_jcon_profsum/icn_failed B
    ifne icn_42_after_call
    getstatic rung36_jcon_profsum/icn_retval J
    goto icn_38_waft_1
icn_42_after_call:
    goto icn_0_top
;  STR
icn_45_α:
    ldc " "
    goto icn_38_waft_2
icn_45_β:
    goto icn_0_top
;  INT
icn_47_α:
    ldc2_w 2
    goto icn_46_arg1
icn_47_β:
    goto icn_0_top
icn_46_arg1:
    putstatic rung36_jcon_profsum/icn_arg_1 J
    goto icn_46_docall
;  VAR
icn_48_α:
    getstatic rung36_jcon_profsum/icn_pv_main_pcttotal J
    goto icn_46_arg0
icn_48_β:
    goto icn_0_top
icn_46_arg0:
    putstatic rung36_jcon_profsum/icn_arg_0 J
    goto icn_47_α
icn_46_α:
    goto icn_48_α
icn_46_β:
    goto icn_47_β
icn_46_docall:
    getstatic rung36_jcon_profsum/icn_6_binop_lc J
    lstore 152
    getstatic rung36_jcon_profsum/icn_6_binop_rc J
    lstore 154
    getstatic rung36_jcon_profsum/icn_pv_main_ttotal J
    lstore 156
    getstatic rung36_jcon_profsum/icn_8_binop_lc J
    lstore 158
    getstatic rung36_jcon_profsum/icn_8_binop_rc J
    lstore 160
    getstatic rung36_jcon_profsum/icn_9_binop_lc J
    lstore 162
    getstatic rung36_jcon_profsum/icn_9_binop_rc J
    lstore 164
    getstatic rung36_jcon_profsum/icn_12_binop_lc J
    lstore 166
    getstatic rung36_jcon_profsum/icn_12_binop_rc J
    lstore 168
    getstatic rung36_jcon_profsum/icn_pv_main_pctlocal J
    lstore 170
    getstatic rung36_jcon_profsum/icn_16_binop_lc J
    lstore 172
    getstatic rung36_jcon_profsum/icn_16_binop_rc J
    lstore 174
    getstatic rung36_jcon_profsum/icn_18_binop_lc J
    lstore 176
    getstatic rung36_jcon_profsum/icn_18_binop_rc J
    lstore 178
    getstatic rung36_jcon_profsum/icn_19_binop_lc J
    lstore 180
    getstatic rung36_jcon_profsum/icn_19_binop_rc J
    lstore 182
    getstatic rung36_jcon_profsum/icn_22_binop_lc J
    lstore 184
    getstatic rung36_jcon_profsum/icn_22_binop_rc J
    lstore 186
    getstatic rung36_jcon_profsum/icn_25_relop_lc J
    lstore 188
    getstatic rung36_jcon_profsum/icn_25_relop_rc J
    lstore 190
    getstatic rung36_jcon_profsum/icn_29_binop_lc J
    lstore 192
    getstatic rung36_jcon_profsum/icn_29_binop_rc J
    lstore 194
    getstatic rung36_jcon_profsum/icn_31_binop_lc J
    lstore 196
    getstatic rung36_jcon_profsum/icn_31_binop_rc J
    lstore 198
    getstatic rung36_jcon_profsum/icn_32_binop_lc J
    lstore 200
    getstatic rung36_jcon_profsum/icn_32_binop_rc J
    lstore 202
    getstatic rung36_jcon_profsum/icn_35_binop_lc J
    lstore 204
    getstatic rung36_jcon_profsum/icn_35_binop_rc J
    lstore 206
    getstatic rung36_jcon_profsum/icn_pv_main_pcttotal J
    lstore 208
    invokestatic rung36_jcon_profsum/icn_pad()V
    lload 152
    putstatic rung36_jcon_profsum/icn_6_binop_lc J
    lload 154
    putstatic rung36_jcon_profsum/icn_6_binop_rc J
    lload 156
    putstatic rung36_jcon_profsum/icn_pv_main_ttotal J
    lload 158
    putstatic rung36_jcon_profsum/icn_8_binop_lc J
    lload 160
    putstatic rung36_jcon_profsum/icn_8_binop_rc J
    lload 162
    putstatic rung36_jcon_profsum/icn_9_binop_lc J
    lload 164
    putstatic rung36_jcon_profsum/icn_9_binop_rc J
    lload 166
    putstatic rung36_jcon_profsum/icn_12_binop_lc J
    lload 168
    putstatic rung36_jcon_profsum/icn_12_binop_rc J
    lload 170
    putstatic rung36_jcon_profsum/icn_pv_main_pctlocal J
    lload 172
    putstatic rung36_jcon_profsum/icn_16_binop_lc J
    lload 174
    putstatic rung36_jcon_profsum/icn_16_binop_rc J
    lload 176
    putstatic rung36_jcon_profsum/icn_18_binop_lc J
    lload 178
    putstatic rung36_jcon_profsum/icn_18_binop_rc J
    lload 180
    putstatic rung36_jcon_profsum/icn_19_binop_lc J
    lload 182
    putstatic rung36_jcon_profsum/icn_19_binop_rc J
    lload 184
    putstatic rung36_jcon_profsum/icn_22_binop_lc J
    lload 186
    putstatic rung36_jcon_profsum/icn_22_binop_rc J
    lload 188
    putstatic rung36_jcon_profsum/icn_25_relop_lc J
    lload 190
    putstatic rung36_jcon_profsum/icn_25_relop_rc J
    lload 192
    putstatic rung36_jcon_profsum/icn_29_binop_lc J
    lload 194
    putstatic rung36_jcon_profsum/icn_29_binop_rc J
    lload 196
    putstatic rung36_jcon_profsum/icn_31_binop_lc J
    lload 198
    putstatic rung36_jcon_profsum/icn_31_binop_rc J
    lload 200
    putstatic rung36_jcon_profsum/icn_32_binop_lc J
    lload 202
    putstatic rung36_jcon_profsum/icn_32_binop_rc J
    lload 204
    putstatic rung36_jcon_profsum/icn_35_binop_lc J
    lload 206
    putstatic rung36_jcon_profsum/icn_35_binop_rc J
    lload 208
    putstatic rung36_jcon_profsum/icn_pv_main_pcttotal J
    getstatic rung36_jcon_profsum/icn_failed B
    ifne icn_46_after_call
    getstatic rung36_jcon_profsum/icn_retval J
    goto icn_38_waft_3
icn_46_after_call:
    goto icn_0_top
;  STR
icn_49_α:
    ldc "%"
    goto icn_38_waft_4
icn_49_β:
    goto icn_0_top
;  INT
icn_52_α:
    ldc2_w 6
    goto icn_50_arg1
icn_52_β:
    goto icn_0_top
;  INT
icn_53_α:
    ldc2_w 7
    goto icn_50_arg1
icn_53_β:
    goto icn_0_top
;  INT
icn_55_α:
    ldc2_w 100
    goto icn_54_rrelay
icn_55_β:
    goto icn_54_lb
;  VAR
icn_56_α:
    getstatic rung36_jcon_profsum/icn_pv_main_pcttotal J
    goto icn_54_lrelay
icn_56_β:
    goto icn_51_else
icn_54_lrelay:
    putstatic rung36_jcon_profsum/icn_54_relop_lc J
    goto icn_54_lstore
icn_54_rrelay:
    putstatic rung36_jcon_profsum/icn_54_relop_rc J
    goto icn_54_check
icn_54_lb:
    goto icn_56_β
icn_54_α:
    goto icn_56_α
icn_54_β:
    goto icn_55_β
icn_54_lstore:
    goto icn_55_α
icn_54_check:
    getstatic rung36_jcon_profsum/icn_54_relop_lc J
    getstatic rung36_jcon_profsum/icn_54_relop_rc J
    lcmp
    ifne icn_55_β
    getstatic rung36_jcon_profsum/icn_54_relop_rc J
    goto icn_51_then
icn_51_then:
    pop2
    goto icn_52_α
icn_51_else:
    goto icn_53_α
icn_51_α:
    goto icn_54_α
icn_51_β:
    goto icn_54_β
icn_50_arg1:
    putstatic rung36_jcon_profsum/icn_arg_1 J
    goto icn_50_docall
icn_57_α:
    goto icn_0_top
icn_57_β:
    goto icn_0_top
icn_50_arg0:
    putstatic rung36_jcon_profsum/icn_arg_0 J
    goto icn_51_α
icn_50_α:
    goto icn_57_α
icn_50_β:
    goto icn_51_β
icn_50_docall:
    getstatic rung36_jcon_profsum/icn_6_binop_lc J
    lstore 152
    getstatic rung36_jcon_profsum/icn_6_binop_rc J
    lstore 154
    getstatic rung36_jcon_profsum/icn_pv_main_ttotal J
    lstore 156
    getstatic rung36_jcon_profsum/icn_8_binop_lc J
    lstore 158
    getstatic rung36_jcon_profsum/icn_8_binop_rc J
    lstore 160
    getstatic rung36_jcon_profsum/icn_9_binop_lc J
    lstore 162
    getstatic rung36_jcon_profsum/icn_9_binop_rc J
    lstore 164
    getstatic rung36_jcon_profsum/icn_12_binop_lc J
    lstore 166
    getstatic rung36_jcon_profsum/icn_12_binop_rc J
    lstore 168
    getstatic rung36_jcon_profsum/icn_pv_main_pctlocal J
    lstore 170
    getstatic rung36_jcon_profsum/icn_16_binop_lc J
    lstore 172
    getstatic rung36_jcon_profsum/icn_16_binop_rc J
    lstore 174
    getstatic rung36_jcon_profsum/icn_18_binop_lc J
    lstore 176
    getstatic rung36_jcon_profsum/icn_18_binop_rc J
    lstore 178
    getstatic rung36_jcon_profsum/icn_19_binop_lc J
    lstore 180
    getstatic rung36_jcon_profsum/icn_19_binop_rc J
    lstore 182
    getstatic rung36_jcon_profsum/icn_22_binop_lc J
    lstore 184
    getstatic rung36_jcon_profsum/icn_22_binop_rc J
    lstore 186
    getstatic rung36_jcon_profsum/icn_25_relop_lc J
    lstore 188
    getstatic rung36_jcon_profsum/icn_25_relop_rc J
    lstore 190
    getstatic rung36_jcon_profsum/icn_29_binop_lc J
    lstore 192
    getstatic rung36_jcon_profsum/icn_29_binop_rc J
    lstore 194
    getstatic rung36_jcon_profsum/icn_31_binop_lc J
    lstore 196
    getstatic rung36_jcon_profsum/icn_31_binop_rc J
    lstore 198
    getstatic rung36_jcon_profsum/icn_32_binop_lc J
    lstore 200
    getstatic rung36_jcon_profsum/icn_32_binop_rc J
    lstore 202
    getstatic rung36_jcon_profsum/icn_35_binop_lc J
    lstore 204
    getstatic rung36_jcon_profsum/icn_35_binop_rc J
    lstore 206
    getstatic rung36_jcon_profsum/icn_pv_main_pcttotal J
    lstore 208
    getstatic rung36_jcon_profsum/icn_54_relop_lc J
    lstore 210
    getstatic rung36_jcon_profsum/icn_54_relop_rc J
    lstore 212
    invokestatic rung36_jcon_profsum/icn_pad()V
    lload 152
    putstatic rung36_jcon_profsum/icn_6_binop_lc J
    lload 154
    putstatic rung36_jcon_profsum/icn_6_binop_rc J
    lload 156
    putstatic rung36_jcon_profsum/icn_pv_main_ttotal J
    lload 158
    putstatic rung36_jcon_profsum/icn_8_binop_lc J
    lload 160
    putstatic rung36_jcon_profsum/icn_8_binop_rc J
    lload 162
    putstatic rung36_jcon_profsum/icn_9_binop_lc J
    lload 164
    putstatic rung36_jcon_profsum/icn_9_binop_rc J
    lload 166
    putstatic rung36_jcon_profsum/icn_12_binop_lc J
    lload 168
    putstatic rung36_jcon_profsum/icn_12_binop_rc J
    lload 170
    putstatic rung36_jcon_profsum/icn_pv_main_pctlocal J
    lload 172
    putstatic rung36_jcon_profsum/icn_16_binop_lc J
    lload 174
    putstatic rung36_jcon_profsum/icn_16_binop_rc J
    lload 176
    putstatic rung36_jcon_profsum/icn_18_binop_lc J
    lload 178
    putstatic rung36_jcon_profsum/icn_18_binop_rc J
    lload 180
    putstatic rung36_jcon_profsum/icn_19_binop_lc J
    lload 182
    putstatic rung36_jcon_profsum/icn_19_binop_rc J
    lload 184
    putstatic rung36_jcon_profsum/icn_22_binop_lc J
    lload 186
    putstatic rung36_jcon_profsum/icn_22_binop_rc J
    lload 188
    putstatic rung36_jcon_profsum/icn_25_relop_lc J
    lload 190
    putstatic rung36_jcon_profsum/icn_25_relop_rc J
    lload 192
    putstatic rung36_jcon_profsum/icn_29_binop_lc J
    lload 194
    putstatic rung36_jcon_profsum/icn_29_binop_rc J
    lload 196
    putstatic rung36_jcon_profsum/icn_31_binop_lc J
    lload 198
    putstatic rung36_jcon_profsum/icn_31_binop_rc J
    lload 200
    putstatic rung36_jcon_profsum/icn_32_binop_lc J
    lload 202
    putstatic rung36_jcon_profsum/icn_32_binop_rc J
    lload 204
    putstatic rung36_jcon_profsum/icn_35_binop_lc J
    lload 206
    putstatic rung36_jcon_profsum/icn_35_binop_rc J
    lload 208
    putstatic rung36_jcon_profsum/icn_pv_main_pcttotal J
    lload 210
    putstatic rung36_jcon_profsum/icn_54_relop_lc J
    lload 212
    putstatic rung36_jcon_profsum/icn_54_relop_rc J
    getstatic rung36_jcon_profsum/icn_failed B
    ifne icn_50_after_call
    getstatic rung36_jcon_profsum/icn_retval J
    goto icn_38_waft_5
icn_50_after_call:
    goto icn_0_top
;  STR
icn_58_α:
    ldc " "
    goto icn_38_waft_6
icn_58_β:
    goto icn_0_top
;  INT
icn_60_α:
    ldc2_w 2
    goto icn_59_arg1
icn_60_β:
    goto icn_0_top
icn_59_arg1:
    putstatic rung36_jcon_profsum/icn_arg_1 J
    goto icn_59_docall
;  VAR
icn_61_α:
    getstatic rung36_jcon_profsum/icn_pv_main_pctlocal J
    goto icn_59_arg0
icn_61_β:
    goto icn_0_top
icn_59_arg0:
    putstatic rung36_jcon_profsum/icn_arg_0 J
    goto icn_60_α
icn_59_α:
    goto icn_61_α
icn_59_β:
    goto icn_60_β
icn_59_docall:
    getstatic rung36_jcon_profsum/icn_6_binop_lc J
    lstore 152
    getstatic rung36_jcon_profsum/icn_6_binop_rc J
    lstore 154
    getstatic rung36_jcon_profsum/icn_pv_main_ttotal J
    lstore 156
    getstatic rung36_jcon_profsum/icn_8_binop_lc J
    lstore 158
    getstatic rung36_jcon_profsum/icn_8_binop_rc J
    lstore 160
    getstatic rung36_jcon_profsum/icn_9_binop_lc J
    lstore 162
    getstatic rung36_jcon_profsum/icn_9_binop_rc J
    lstore 164
    getstatic rung36_jcon_profsum/icn_12_binop_lc J
    lstore 166
    getstatic rung36_jcon_profsum/icn_12_binop_rc J
    lstore 168
    getstatic rung36_jcon_profsum/icn_pv_main_pctlocal J
    lstore 170
    getstatic rung36_jcon_profsum/icn_16_binop_lc J
    lstore 172
    getstatic rung36_jcon_profsum/icn_16_binop_rc J
    lstore 174
    getstatic rung36_jcon_profsum/icn_18_binop_lc J
    lstore 176
    getstatic rung36_jcon_profsum/icn_18_binop_rc J
    lstore 178
    getstatic rung36_jcon_profsum/icn_19_binop_lc J
    lstore 180
    getstatic rung36_jcon_profsum/icn_19_binop_rc J
    lstore 182
    getstatic rung36_jcon_profsum/icn_22_binop_lc J
    lstore 184
    getstatic rung36_jcon_profsum/icn_22_binop_rc J
    lstore 186
    getstatic rung36_jcon_profsum/icn_25_relop_lc J
    lstore 188
    getstatic rung36_jcon_profsum/icn_25_relop_rc J
    lstore 190
    getstatic rung36_jcon_profsum/icn_29_binop_lc J
    lstore 192
    getstatic rung36_jcon_profsum/icn_29_binop_rc J
    lstore 194
    getstatic rung36_jcon_profsum/icn_31_binop_lc J
    lstore 196
    getstatic rung36_jcon_profsum/icn_31_binop_rc J
    lstore 198
    getstatic rung36_jcon_profsum/icn_32_binop_lc J
    lstore 200
    getstatic rung36_jcon_profsum/icn_32_binop_rc J
    lstore 202
    getstatic rung36_jcon_profsum/icn_35_binop_lc J
    lstore 204
    getstatic rung36_jcon_profsum/icn_35_binop_rc J
    lstore 206
    getstatic rung36_jcon_profsum/icn_pv_main_pcttotal J
    lstore 208
    getstatic rung36_jcon_profsum/icn_54_relop_lc J
    lstore 210
    getstatic rung36_jcon_profsum/icn_54_relop_rc J
    lstore 212
    invokestatic rung36_jcon_profsum/icn_pad()V
    lload 152
    putstatic rung36_jcon_profsum/icn_6_binop_lc J
    lload 154
    putstatic rung36_jcon_profsum/icn_6_binop_rc J
    lload 156
    putstatic rung36_jcon_profsum/icn_pv_main_ttotal J
    lload 158
    putstatic rung36_jcon_profsum/icn_8_binop_lc J
    lload 160
    putstatic rung36_jcon_profsum/icn_8_binop_rc J
    lload 162
    putstatic rung36_jcon_profsum/icn_9_binop_lc J
    lload 164
    putstatic rung36_jcon_profsum/icn_9_binop_rc J
    lload 166
    putstatic rung36_jcon_profsum/icn_12_binop_lc J
    lload 168
    putstatic rung36_jcon_profsum/icn_12_binop_rc J
    lload 170
    putstatic rung36_jcon_profsum/icn_pv_main_pctlocal J
    lload 172
    putstatic rung36_jcon_profsum/icn_16_binop_lc J
    lload 174
    putstatic rung36_jcon_profsum/icn_16_binop_rc J
    lload 176
    putstatic rung36_jcon_profsum/icn_18_binop_lc J
    lload 178
    putstatic rung36_jcon_profsum/icn_18_binop_rc J
    lload 180
    putstatic rung36_jcon_profsum/icn_19_binop_lc J
    lload 182
    putstatic rung36_jcon_profsum/icn_19_binop_rc J
    lload 184
    putstatic rung36_jcon_profsum/icn_22_binop_lc J
    lload 186
    putstatic rung36_jcon_profsum/icn_22_binop_rc J
    lload 188
    putstatic rung36_jcon_profsum/icn_25_relop_lc J
    lload 190
    putstatic rung36_jcon_profsum/icn_25_relop_rc J
    lload 192
    putstatic rung36_jcon_profsum/icn_29_binop_lc J
    lload 194
    putstatic rung36_jcon_profsum/icn_29_binop_rc J
    lload 196
    putstatic rung36_jcon_profsum/icn_31_binop_lc J
    lload 198
    putstatic rung36_jcon_profsum/icn_31_binop_rc J
    lload 200
    putstatic rung36_jcon_profsum/icn_32_binop_lc J
    lload 202
    putstatic rung36_jcon_profsum/icn_32_binop_rc J
    lload 204
    putstatic rung36_jcon_profsum/icn_35_binop_lc J
    lload 206
    putstatic rung36_jcon_profsum/icn_35_binop_rc J
    lload 208
    putstatic rung36_jcon_profsum/icn_pv_main_pcttotal J
    lload 210
    putstatic rung36_jcon_profsum/icn_54_relop_lc J
    lload 212
    putstatic rung36_jcon_profsum/icn_54_relop_rc J
    getstatic rung36_jcon_profsum/icn_failed B
    ifne icn_59_after_call
    getstatic rung36_jcon_profsum/icn_retval J
    goto icn_38_waft_7
icn_59_after_call:
    goto icn_0_top
;  STR
icn_62_α:
    ldc "%"
    goto icn_38_waft_8
icn_62_β:
    goto icn_0_top
;  STR
icn_63_α:
    ldc "  "
    goto icn_38_waft_9
icn_63_β:
    goto icn_0_top
icn_64_α:
    goto icn_0_top
icn_64_β:
    goto icn_0_top
icn_38_α:
    goto icn_39_α
icn_38_β:
    goto icn_39_β
    goto icn_38_wentry
icn_38_waft_0:
    lstore 18
    getstatic java/lang/System/out Ljava/io/PrintStream;
    lload 18
    invokevirtual java/io/PrintStream/print(J)V
    goto icn_42_α
icn_38_waft_1:
    lstore 20
    getstatic java/lang/System/out Ljava/io/PrintStream;
    lload 20
    invokevirtual java/io/PrintStream/print(J)V
    goto icn_45_α
icn_38_waft_2:
    astore 148
    getstatic java/lang/System/out Ljava/io/PrintStream;
    aload 148
    invokevirtual java/io/PrintStream/print(Ljava/lang/String;)V
    goto icn_46_α
icn_38_waft_3:
    lstore 22
    getstatic java/lang/System/out Ljava/io/PrintStream;
    lload 22
    invokevirtual java/io/PrintStream/print(J)V
    goto icn_49_α
icn_38_waft_4:
    astore 149
    getstatic java/lang/System/out Ljava/io/PrintStream;
    aload 149
    invokevirtual java/io/PrintStream/print(Ljava/lang/String;)V
    goto icn_50_α
icn_38_waft_5:
    lstore 24
    getstatic java/lang/System/out Ljava/io/PrintStream;
    lload 24
    invokevirtual java/io/PrintStream/print(J)V
    goto icn_58_α
icn_38_waft_6:
    astore 150
    getstatic java/lang/System/out Ljava/io/PrintStream;
    aload 150
    invokevirtual java/io/PrintStream/print(Ljava/lang/String;)V
    goto icn_59_α
icn_38_waft_7:
    lstore 26
    getstatic java/lang/System/out Ljava/io/PrintStream;
    lload 26
    invokevirtual java/io/PrintStream/print(J)V
    goto icn_62_α
icn_38_waft_8:
    astore 151
    getstatic java/lang/System/out Ljava/io/PrintStream;
    aload 151
    invokevirtual java/io/PrintStream/print(Ljava/lang/String;)V
    goto icn_63_α
icn_38_waft_9:
    astore 152
    getstatic java/lang/System/out Ljava/io/PrintStream;
    aload 152
    invokevirtual java/io/PrintStream/print(Ljava/lang/String;)V
    goto icn_64_α
icn_38_waft_10:
    lstore 28
    getstatic java/lang/System/out Ljava/io/PrintStream;
    lload 28
    invokevirtual java/io/PrintStream/print(J)V
    getstatic java/lang/System/out Ljava/io/PrintStream;
    ldc ""
    invokevirtual java/io/PrintStream/println(Ljava/lang/String;)V
    lload 28
    goto icn_0_wbdrain
icn_38_wentry:
    goto icn_39_α
    goto icn_0_wbstart
icn_0_wb_rg_0:
    pop2
    goto icn_28_α
icn_0_wb_rg_1:
    pop2
    goto icn_38_α
icn_0_wb_rf_0:
    goto icn_28_α
icn_0_wb_rf_1:
    goto icn_38_α
icn_0_wbstart:
    goto icn_4_α
icn_0_wbdrain:
    pop2
icn_0_top:
    goto icn_1_α
icn_0_α:
    goto icn_1_α
icn_0_β:
    goto icn_main_done
;  STR
icn_66_α:
    ldc "  calls  totaltime   inmethod  method"
    goto icn_65_waft_0
icn_66_β:
    goto icn_0_α
icn_65_α:
    goto icn_66_α
icn_65_β:
    goto icn_66_β
    goto icn_65_wentry
icn_65_waft_0:
    astore 153
    getstatic java/lang/System/out Ljava/io/PrintStream;
    aload 153
    invokevirtual java/io/PrintStream/print(Ljava/lang/String;)V
    getstatic java/lang/System/out Ljava/io/PrintStream;
    ldc ""
    invokevirtual java/io/PrintStream/println(Ljava/lang/String;)V
    aload 153
    goto icn_main_s8_sdrain
icn_65_wentry:
    goto icn_66_α
icn_main_s8_sdrain:
    pop
    goto icn_0_α
;  VAR
icn_70_α:
    getstatic rung36_jcon_profsum/icn_pv_main_l Ljava/util/ArrayList;
    goto icn_69_sortf_rl
icn_70_β:
    goto icn_65_α
;  INT
icn_71_α:
    ldc2_w 3
    goto icn_69_sortf_rf
icn_71_β:
    goto icn_65_α
icn_69_α:
    goto icn_70_α
icn_69_β:
    goto icn_65_α
icn_69_sortf_rl:
    putstatic rung36_jcon_profsum/icn_69_sortf_list Ljava/util/ArrayList;
    goto icn_71_α
icn_69_sortf_rf:
    putstatic rung36_jcon_profsum/icn_69_sortf_fld J
    getstatic rung36_jcon_profsum/icn_69_sortf_list Ljava/util/ArrayList;
    getstatic rung36_jcon_profsum/icn_69_sortf_fld J
    l2i
    invokestatic rung36_jcon_profsum/icn_builtin_sortf(Ljava/util/ArrayList;I)Ljava/util/ArrayList;
    goto icn_68_store
icn_68_α:
    goto icn_69_α
icn_68_β:
    goto icn_69_β
icn_68_store:
    putstatic rung36_jcon_profsum/icn_pv_main_l Ljava/util/ArrayList;
    getstatic rung36_jcon_profsum/icn_pv_main_l Ljava/util/ArrayList;
    goto icn_main_s7_sdrain
;  VAR
icn_74_α:
    getstatic rung36_jcon_profsum/icn_pv_main_l Ljava/util/ArrayList;
    goto icn_73_sortf_rl
icn_74_β:
    goto icn_65_α
;  INT
icn_75_α:
    ldc2_w 5
    goto icn_73_sortf_rf
icn_75_β:
    goto icn_65_α
icn_73_α:
    goto icn_74_α
icn_73_β:
    goto icn_65_α
icn_73_sortf_rl:
    putstatic rung36_jcon_profsum/icn_73_sortf_list Ljava/util/ArrayList;
    goto icn_75_α
icn_73_sortf_rf:
    putstatic rung36_jcon_profsum/icn_73_sortf_fld J
    getstatic rung36_jcon_profsum/icn_73_sortf_list Ljava/util/ArrayList;
    getstatic rung36_jcon_profsum/icn_73_sortf_fld J
    l2i
    invokestatic rung36_jcon_profsum/icn_builtin_sortf(Ljava/util/ArrayList;I)Ljava/util/ArrayList;
    goto icn_72_store
icn_72_α:
    goto icn_73_α
icn_72_β:
    goto icn_73_β
icn_72_store:
    putstatic rung36_jcon_profsum/icn_pv_main_l Ljava/util/ArrayList;
    getstatic rung36_jcon_profsum/icn_pv_main_l Ljava/util/ArrayList;
    goto icn_main_s7_sdrain
;  VAR
icn_77_α:
    getstatic rung36_jcon_profsum/icn_pv_main_sorttotal J
    goto icn_67_then
icn_77_β:
    goto icn_67_else
;  NONNULL
icn_76_α:
    goto icn_77_α
icn_76_β:
    goto icn_77_β
icn_67_then:
    pop2
    goto icn_68_α
icn_67_else:
    goto icn_72_α
icn_67_α:
    goto icn_76_α
icn_67_β:
    goto icn_76_β
icn_main_s7_sdrain:
    pop2
    goto icn_65_α
icn_82_α:
    goto icn_81_lb
icn_82_β:
    goto icn_81_lb
icn_83_α:
    goto icn_79_seq_rf_0
icn_83_β:
    goto icn_79_seq_rf_0
icn_81_lrelay:
    putstatic rung36_jcon_profsum/icn_81_binop_lc J
    goto icn_81_lstore
icn_81_rrelay:
    putstatic rung36_jcon_profsum/icn_81_binop_rc J
    goto icn_81_compute
icn_81_lb:
    goto icn_83_β
icn_81_α:
    iconst_0
    putstatic rung36_jcon_profsum/icn_81_binop_bf I
    goto icn_83_α
icn_81_β:
    goto icn_82_β
icn_81_lstore:
    getstatic rung36_jcon_profsum/icn_81_binop_bf I
    ifeq icn_82_α
    goto icn_82_β
icn_81_compute:
    getstatic rung36_jcon_profsum/icn_81_binop_lc J
    getstatic rung36_jcon_profsum/icn_81_binop_rc J
    lsub
    goto icn_80_store
icn_80_α:
    goto icn_81_α
icn_80_β:
    goto icn_81_β
icn_80_store:
    pop2
    lconst_0
    goto icn_79_seq_rg_0
icn_86_α:
    goto icn_79_seq_rf_1
icn_86_β:
    goto icn_79_seq_rf_1
icn_85_α:
    goto icn_86_α
icn_85_β:
    goto icn_86_β
icn_85_rhsok:
    putstatic rung36_jcon_profsum/icn_85_augtemp J
    getstatic rung36_jcon_profsum/icn_pv_main_ttotal J
    getstatic rung36_jcon_profsum/icn_85_augtemp J
    ladd
    dup2
    putstatic rung36_jcon_profsum/icn_pv_main_ttotal J
    goto icn_79_seq_rg_1
;  INT
icn_88_α:
    ldc2_w 0
    goto icn_87_rrelay
icn_88_β:
    goto icn_87_lb
icn_89_α:
    goto icn_84_else
icn_89_β:
    goto icn_84_else
icn_87_lrelay:
    putstatic rung36_jcon_profsum/icn_87_relop_lc J
    goto icn_87_lstore
icn_87_rrelay:
    putstatic rung36_jcon_profsum/icn_87_relop_rc J
    goto icn_87_check
icn_87_lb:
    goto icn_89_β
icn_87_α:
    goto icn_89_α
icn_87_β:
    goto icn_88_β
icn_87_lstore:
    goto icn_88_α
icn_87_check:
    getstatic rung36_jcon_profsum/icn_87_relop_lc J
    getstatic rung36_jcon_profsum/icn_87_relop_rc J
    lcmp
    ifle icn_88_β
    getstatic rung36_jcon_profsum/icn_87_relop_rc J
    goto icn_84_then
icn_84_then:
    pop2
    goto icn_85_α
icn_84_else:
    goto icn_79_seq_rf_1
icn_84_α:
    goto icn_87_α
icn_84_β:
    goto icn_87_β
;  VAR
icn_91_α:
    getstatic rung36_jcon_profsum/icn_pv_main_l Ljava/util/ArrayList;
    goto icn_90_lr
icn_91_β:
    goto icn_78_pump
;  VAR
icn_92_α:
    getstatic rung36_jcon_profsum/icn_pv_main_p Ljava/lang/String;
    goto icn_90_vr
icn_92_β:
    goto icn_78_pump
icn_90_α:
    goto icn_91_α
icn_90_β:
    goto icn_78_pump
icn_90_lr:
    putstatic rung36_jcon_profsum/icn_90_pushlist Ljava/util/ArrayList;
    goto icn_92_α
icn_90_vr:
    putstatic rung36_jcon_profsum/icn_90_pushval Ljava/lang/Object;
    getstatic rung36_jcon_profsum/icn_90_pushlist Ljava/util/ArrayList;
    getstatic rung36_jcon_profsum/icn_90_pushval Ljava/lang/Object;
    invokevirtual java/util/ArrayList/add(Ljava/lang/Object;)Z
    pop
    getstatic rung36_jcon_profsum/icn_90_pushlist Ljava/util/ArrayList;
    goto icn_78_bdrain
    goto icn_79_α
icn_79_seq_rg_0:
    pop2
    goto icn_84_α
icn_79_seq_rg_1:
    pop2
    goto icn_90_α
icn_79_seq_rf_0:
    goto icn_84_α
icn_79_seq_rf_1:
    goto icn_90_α
icn_79_α:
    goto icn_80_α
icn_79_β:
    goto icn_90_β
;  VAR
icn_95_α:
    getstatic rung36_jcon_profsum/icn_gvar_ptab Ljava/util/HashMap;
    goto icn_94_bang_adv
icn_95_β:
    goto icn_67_α
icn_94_α:
    goto icn_95_α
icn_94_β:
    goto icn_94_bang_chk
icn_94_bang_adv:
    putstatic rung36_jcon_profsum/icn_94_bang_str Ljava/lang/String;
    iconst_0
    putstatic rung36_jcon_profsum/icn_94_bang_pos I
icn_94_bang_chk:
    getstatic rung36_jcon_profsum/icn_94_bang_str Ljava/lang/String;
    invokevirtual java/lang/String/length()I
    getstatic rung36_jcon_profsum/icn_94_bang_pos I
    if_icmple icn_67_α
    getstatic rung36_jcon_profsum/icn_94_bang_str Ljava/lang/String;
    getstatic rung36_jcon_profsum/icn_94_bang_pos I
    getstatic rung36_jcon_profsum/icn_94_bang_pos I
    iconst_1
    iadd
    invokevirtual java/lang/String/substring(II)Ljava/lang/String;
    getstatic rung36_jcon_profsum/icn_94_bang_pos I
    iconst_1
    iadd
    putstatic rung36_jcon_profsum/icn_94_bang_pos I
    goto icn_93_store
icn_93_α:
    goto icn_94_α
icn_93_β:
    goto icn_94_β
icn_93_store:
    putstatic rung36_jcon_profsum/icn_pv_main_p Ljava/lang/String;
    getstatic rung36_jcon_profsum/icn_pv_main_p Ljava/lang/String;
    goto icn_78_gdrain
icn_78_gdrain:
    pop
    goto icn_79_α
icn_78_bdrain:
    pop2
icn_78_pump:
    goto icn_93_β
icn_78_α:
    goto icn_93_α
icn_78_β:
    goto icn_67_α
;  INT
icn_97_α:
    ldc2_w 0
    goto icn_96_store
icn_97_β:
    goto icn_78_α
icn_96_α:
    goto icn_97_α
icn_96_β:
    goto icn_97_β
icn_96_store:
    putstatic rung36_jcon_profsum/icn_pv_main_ttotal J
    getstatic rung36_jcon_profsum/icn_pv_main_ttotal J
    goto icn_main_s5_sdrain
icn_main_s5_sdrain:
    pop2
    goto icn_78_α
icn_99_α:
    new java/util/ArrayList
    dup
    invokespecial java/util/ArrayList/<init>()V
    putstatic rung36_jcon_profsum/icn_99_mklist Ljava/util/ArrayList;
    getstatic rung36_jcon_profsum/icn_99_mklist Ljava/util/ArrayList;
    goto icn_98_store
icn_99_β:
    goto icn_96_α
icn_98_α:
    goto icn_99_α
icn_98_β:
    goto icn_99_β
icn_98_store:
    putstatic rung36_jcon_profsum/icn_pv_main_l Ljava/util/ArrayList;
    getstatic rung36_jcon_profsum/icn_pv_main_l Ljava/util/ArrayList;
    goto icn_main_s4_sdrain
icn_main_s4_sdrain:
    pop
    goto icn_96_α
icn_102_α:
    goto icn_98_α
icn_102_β:
    goto icn_98_α
icn_101_α:
    goto icn_102_α
icn_101_β:
    goto icn_102_β
icn_101_store:
    putstatic rung36_jcon_profsum/icn_pv_main_line Ljava/lang/String;
    getstatic rung36_jcon_profsum/icn_pv_main_line Ljava/lang/String;
    goto icn_100_condok
icn_100_condok:
    pop
    goto icn_100_wbstart
;  VAR
icn_104_α:
    getstatic rung36_jcon_profsum/icn_pv_main_line Ljava/lang/String;
    goto icn_103_scan_setup
icn_104_β:
    goto icn_100_top
icn_107_α:
    goto icn_101_α
icn_107_β:
    goto icn_101_α
;  STR
icn_109_α:
    ldc "count"
    goto icn_108_ma
icn_109_β:
    goto icn_106_else
icn_108_α:
    goto icn_109_α
icn_108_β:
    goto icn_106_else
icn_108_ma:
;  match: s String on stack
    getstatic rung36_jcon_profsum/icn_subject Ljava/lang/String;
    getstatic rung36_jcon_profsum/icn_pos I
    invokestatic rung36_jcon_profsum/icn_builtin_match(Ljava/lang/String;Ljava/lang/String;I)J
    dup2
    lconst_1
    lneg
    lcmp
    ifne icn_108_mo
    pop2
    goto icn_106_else
icn_108_mo:
;  match ok: icn_pos = result-1 (0-based), push result → γ
    dup2
    l2i
    iconst_1
    isub
    putstatic rung36_jcon_profsum/icn_pos I
    goto icn_106_then
icn_106_then:
    pop2
    goto icn_107_α
icn_106_else:
    goto icn_105_seq_rf_0
icn_106_α:
    goto icn_108_α
icn_106_β:
    goto icn_108_β
icn_111_α:
    goto icn_98_α
icn_111_β:
    goto icn_98_α
;  VAR
icn_114_α:
    ldc "0123456789"
    goto icn_113_after
icn_114_β:
    goto icn_112_succ
icn_113_α:
    goto icn_114_α
icn_113_β:
    goto icn_114_β
icn_113_after:
;  any: cs String on stack
    getstatic rung36_jcon_profsum/icn_subject Ljava/lang/String;
    getstatic rung36_jcon_profsum/icn_pos I
    invokestatic rung36_jcon_profsum/icn_builtin_any(Ljava/lang/String;Ljava/lang/String;I)J
    dup2
    lconst_1
    lneg
    lcmp
    ifne icn_113_chk
    pop2
    goto icn_112_succ
icn_113_chk:
;  any ok: advance icn_pos, push newpos
    dup2
    lconst_1
    lsub
    l2i
    putstatic rung36_jcon_profsum/icn_pos I
    goto icn_112_cok
;  NOT
icn_112_α:
    goto icn_113_α
icn_112_β:
    goto icn_113_β
icn_112_cok:
    pop2
    goto icn_110_else
icn_112_succ:
    lconst_0
    goto icn_110_then
icn_110_then:
    pop2
    goto icn_111_α
icn_110_else:
    goto icn_105_seq_rf_1
icn_110_α:
    goto icn_112_α
icn_110_β:
    goto icn_112_β
icn_115_α:
    goto icn_115_docall
icn_115_β:
    goto icn_103_scan_bfail
icn_115_docall:
    getstatic rung36_jcon_profsum/icn_6_binop_lc J
    lstore 158
    getstatic rung36_jcon_profsum/icn_6_binop_rc J
    lstore 160
    getstatic rung36_jcon_profsum/icn_pv_main_ttotal J
    lstore 162
    getstatic rung36_jcon_profsum/icn_8_binop_lc J
    lstore 164
    getstatic rung36_jcon_profsum/icn_8_binop_rc J
    lstore 166
    getstatic rung36_jcon_profsum/icn_9_binop_lc J
    lstore 168
    getstatic rung36_jcon_profsum/icn_9_binop_rc J
    lstore 170
    getstatic rung36_jcon_profsum/icn_12_binop_lc J
    lstore 172
    getstatic rung36_jcon_profsum/icn_12_binop_rc J
    lstore 174
    getstatic rung36_jcon_profsum/icn_pv_main_pctlocal J
    lstore 176
    getstatic rung36_jcon_profsum/icn_16_binop_lc J
    lstore 178
    getstatic rung36_jcon_profsum/icn_16_binop_rc J
    lstore 180
    getstatic rung36_jcon_profsum/icn_18_binop_lc J
    lstore 182
    getstatic rung36_jcon_profsum/icn_18_binop_rc J
    lstore 184
    getstatic rung36_jcon_profsum/icn_19_binop_lc J
    lstore 186
    getstatic rung36_jcon_profsum/icn_19_binop_rc J
    lstore 188
    getstatic rung36_jcon_profsum/icn_22_binop_lc J
    lstore 190
    getstatic rung36_jcon_profsum/icn_22_binop_rc J
    lstore 192
    getstatic rung36_jcon_profsum/icn_25_relop_lc J
    lstore 194
    getstatic rung36_jcon_profsum/icn_25_relop_rc J
    lstore 196
    getstatic rung36_jcon_profsum/icn_29_binop_lc J
    lstore 198
    getstatic rung36_jcon_profsum/icn_29_binop_rc J
    lstore 200
    getstatic rung36_jcon_profsum/icn_31_binop_lc J
    lstore 202
    getstatic rung36_jcon_profsum/icn_31_binop_rc J
    lstore 204
    getstatic rung36_jcon_profsum/icn_32_binop_lc J
    lstore 206
    getstatic rung36_jcon_profsum/icn_32_binop_rc J
    lstore 208
    getstatic rung36_jcon_profsum/icn_35_binop_lc J
    lstore 210
    getstatic rung36_jcon_profsum/icn_35_binop_rc J
    lstore 212
    getstatic rung36_jcon_profsum/icn_pv_main_pcttotal J
    lstore 214
    getstatic rung36_jcon_profsum/icn_54_relop_lc J
    lstore 216
    getstatic rung36_jcon_profsum/icn_54_relop_rc J
    lstore 218
    getstatic rung36_jcon_profsum/icn_69_sortf_fld J
    lstore 220
    getstatic rung36_jcon_profsum/icn_73_sortf_fld J
    lstore 222
    getstatic rung36_jcon_profsum/icn_pv_main_sorttotal J
    lstore 224
    getstatic rung36_jcon_profsum/icn_81_binop_lc J
    lstore 226
    getstatic rung36_jcon_profsum/icn_81_binop_rc J
    lstore 228
    getstatic rung36_jcon_profsum/icn_85_augtemp J
    lstore 230
    getstatic rung36_jcon_profsum/icn_87_relop_lc J
    lstore 232
    getstatic rung36_jcon_profsum/icn_87_relop_rc J
    lstore 234
    invokestatic rung36_jcon_profsum/icn_accumulate()V
    lload 158
    putstatic rung36_jcon_profsum/icn_6_binop_lc J
    lload 160
    putstatic rung36_jcon_profsum/icn_6_binop_rc J
    lload 162
    putstatic rung36_jcon_profsum/icn_pv_main_ttotal J
    lload 164
    putstatic rung36_jcon_profsum/icn_8_binop_lc J
    lload 166
    putstatic rung36_jcon_profsum/icn_8_binop_rc J
    lload 168
    putstatic rung36_jcon_profsum/icn_9_binop_lc J
    lload 170
    putstatic rung36_jcon_profsum/icn_9_binop_rc J
    lload 172
    putstatic rung36_jcon_profsum/icn_12_binop_lc J
    lload 174
    putstatic rung36_jcon_profsum/icn_12_binop_rc J
    lload 176
    putstatic rung36_jcon_profsum/icn_pv_main_pctlocal J
    lload 178
    putstatic rung36_jcon_profsum/icn_16_binop_lc J
    lload 180
    putstatic rung36_jcon_profsum/icn_16_binop_rc J
    lload 182
    putstatic rung36_jcon_profsum/icn_18_binop_lc J
    lload 184
    putstatic rung36_jcon_profsum/icn_18_binop_rc J
    lload 186
    putstatic rung36_jcon_profsum/icn_19_binop_lc J
    lload 188
    putstatic rung36_jcon_profsum/icn_19_binop_rc J
    lload 190
    putstatic rung36_jcon_profsum/icn_22_binop_lc J
    lload 192
    putstatic rung36_jcon_profsum/icn_22_binop_rc J
    lload 194
    putstatic rung36_jcon_profsum/icn_25_relop_lc J
    lload 196
    putstatic rung36_jcon_profsum/icn_25_relop_rc J
    lload 198
    putstatic rung36_jcon_profsum/icn_29_binop_lc J
    lload 200
    putstatic rung36_jcon_profsum/icn_29_binop_rc J
    lload 202
    putstatic rung36_jcon_profsum/icn_31_binop_lc J
    lload 204
    putstatic rung36_jcon_profsum/icn_31_binop_rc J
    lload 206
    putstatic rung36_jcon_profsum/icn_32_binop_lc J
    lload 208
    putstatic rung36_jcon_profsum/icn_32_binop_rc J
    lload 210
    putstatic rung36_jcon_profsum/icn_35_binop_lc J
    lload 212
    putstatic rung36_jcon_profsum/icn_35_binop_rc J
    lload 214
    putstatic rung36_jcon_profsum/icn_pv_main_pcttotal J
    lload 216
    putstatic rung36_jcon_profsum/icn_54_relop_lc J
    lload 218
    putstatic rung36_jcon_profsum/icn_54_relop_rc J
    lload 220
    putstatic rung36_jcon_profsum/icn_69_sortf_fld J
    lload 222
    putstatic rung36_jcon_profsum/icn_73_sortf_fld J
    lload 224
    putstatic rung36_jcon_profsum/icn_pv_main_sorttotal J
    lload 226
    putstatic rung36_jcon_profsum/icn_81_binop_lc J
    lload 228
    putstatic rung36_jcon_profsum/icn_81_binop_rc J
    lload 230
    putstatic rung36_jcon_profsum/icn_85_augtemp J
    lload 232
    putstatic rung36_jcon_profsum/icn_87_relop_lc J
    lload 234
    putstatic rung36_jcon_profsum/icn_87_relop_rc J
    getstatic rung36_jcon_profsum/icn_failed B
    ifne icn_115_after_call
    getstatic rung36_jcon_profsum/icn_retval J
    goto icn_103_scan_bok
icn_115_after_call:
    goto icn_103_scan_bfail
    goto icn_105_α
icn_105_seq_rg_0:
    pop2
    goto icn_110_α
icn_105_seq_rg_1:
    pop2
    goto icn_115_α
icn_105_seq_rf_0:
    goto icn_110_α
icn_105_seq_rf_1:
    goto icn_115_α
icn_105_α:
    goto icn_106_α
icn_105_β:
    goto icn_115_β
;  SCAN
icn_103_α:
    goto icn_104_α
icn_103_β:
    goto icn_103_scan_beta
icn_103_scan_setup:
;  SCAN save+install
    getstatic rung36_jcon_profsum/icn_subject Ljava/lang/String;
    putstatic rung36_jcon_profsum/icn_scan_oldsubj_103 Ljava/lang/String;
    getstatic rung36_jcon_profsum/icn_pos I
    putstatic rung36_jcon_profsum/icn_scan_oldpos_103 I
    putstatic rung36_jcon_profsum/icn_subject Ljava/lang/String;
    iconst_0
    putstatic rung36_jcon_profsum/icn_pos I
    goto icn_105_α
icn_103_scan_bok:
;  SCAN restore (body ok)
    getstatic rung36_jcon_profsum/icn_scan_oldsubj_103 Ljava/lang/String;
    putstatic rung36_jcon_profsum/icn_subject Ljava/lang/String;
    getstatic rung36_jcon_profsum/icn_scan_oldpos_103 I
    putstatic rung36_jcon_profsum/icn_pos I
    goto icn_100_wbdrain
icn_103_scan_bfail:
;  SCAN restore (body fail)
    getstatic rung36_jcon_profsum/icn_scan_oldsubj_103 Ljava/lang/String;
    putstatic rung36_jcon_profsum/icn_subject Ljava/lang/String;
    getstatic rung36_jcon_profsum/icn_scan_oldpos_103 I
    putstatic rung36_jcon_profsum/icn_pos I
    goto icn_104_β
icn_103_scan_beta:
;  SCAN restore (outer β)
    getstatic rung36_jcon_profsum/icn_scan_oldsubj_103 Ljava/lang/String;
    putstatic rung36_jcon_profsum/icn_subject Ljava/lang/String;
    getstatic rung36_jcon_profsum/icn_scan_oldpos_103 I
    putstatic rung36_jcon_profsum/icn_pos I
    goto icn_105_β
icn_100_wbstart:
    goto icn_103_α
icn_100_wbdrain:
    pop
icn_100_top:
    goto icn_101_α
icn_100_α:
    goto icn_101_α
icn_100_β:
    goto icn_98_α
icn_119_α:
    goto icn_100_α
icn_119_β:
    goto icn_100_α
icn_120_α:
    goto icn_119_α
icn_120_β:
    goto icn_119_α
icn_118_alt_g0:
    pop
    lconst_0
    putstatic rung36_jcon_profsum/icn_118_alt_val J
    sipush 1
    putstatic rung36_jcon_profsum/icn_118_alt_gate I
    getstatic rung36_jcon_profsum/icn_118_alt_val J
    goto icn_117_store
icn_118_alt_g1:
    putstatic rung36_jcon_profsum/icn_118_alt_val J
    sipush 2
    putstatic rung36_jcon_profsum/icn_118_alt_gate I
    getstatic rung36_jcon_profsum/icn_118_alt_val J
    goto icn_117_store
icn_118_α:
    iconst_0
    putstatic rung36_jcon_profsum/icn_118_alt_gate I
    goto icn_120_α
icn_118_β:
    getstatic rung36_jcon_profsum/icn_118_alt_gate I
    tableswitch 1 2
        icn_120_β
        icn_119_β
        default: icn_100_α
icn_117_α:
    goto icn_118_α
icn_117_β:
    goto icn_118_β
icn_117_store:
    putstatic rung36_jcon_profsum/icn_pv_main_f J
    getstatic rung36_jcon_profsum/icn_pv_main_f J
    goto icn_main_s2_sdrain
;  VAR
icn_122_α:
    getstatic rung36_jcon_profsum/icn_gvar_&input J
    goto icn_121_store
icn_122_β:
    goto icn_100_α
icn_121_α:
    goto icn_122_α
icn_121_β:
    goto icn_122_β
icn_121_store:
    putstatic rung36_jcon_profsum/icn_pv_main_f J
    getstatic rung36_jcon_profsum/icn_pv_main_f J
    goto icn_main_s2_sdrain
;  INT
icn_124_α:
    ldc2_w 0
    goto icn_123_rrelay
icn_124_β:
    goto icn_123_lb
;  VAR
icn_126_α:
    getstatic rung36_jcon_profsum/icn_pv_main_args J
    goto icn_125_relay
icn_126_β:
    goto icn_116_else
icn_125_α:
    goto icn_126_α
icn_125_β:
    goto icn_126_β
icn_125_relay:
    invokevirtual java/lang/String/length()I
    i2l
    goto icn_123_lrelay
icn_123_lrelay:
    putstatic rung36_jcon_profsum/icn_123_relop_lc J
    goto icn_123_lstore
icn_123_rrelay:
    putstatic rung36_jcon_profsum/icn_123_relop_rc J
    goto icn_123_check
icn_123_lb:
    goto icn_125_β
icn_123_α:
    goto icn_125_α
icn_123_β:
    goto icn_124_β
icn_123_lstore:
    goto icn_124_α
icn_123_check:
    getstatic rung36_jcon_profsum/icn_123_relop_lc J
    getstatic rung36_jcon_profsum/icn_123_relop_rc J
    lcmp
    ifle icn_124_β
    getstatic rung36_jcon_profsum/icn_123_relop_rc J
    goto icn_116_then
icn_116_then:
    pop2
    goto icn_117_α
icn_116_else:
    goto icn_121_α
icn_116_α:
    goto icn_123_α
icn_116_β:
    goto icn_123_β
icn_main_s2_sdrain:
    pop2
    goto icn_100_α
;  VAR
icn_130_α:
    getstatic rung36_jcon_profsum/icn_pv_main_args J
    goto icn_129_lr
icn_130_β:
    goto icn_116_α
icn_129_α:
    goto icn_130_α
icn_129_β:
    goto icn_116_α
icn_129_lr:
    putstatic rung36_jcon_profsum/icn_129_glist Ljava/util/ArrayList;
    getstatic rung36_jcon_profsum/icn_129_glist Ljava/util/ArrayList;
    invokevirtual java/util/ArrayList/size()I
    ifeq icn_116_α
    getstatic rung36_jcon_profsum/icn_129_glist Ljava/util/ArrayList;
    iconst_0
    invokevirtual java/util/ArrayList/remove(I)Ljava/lang/Object;
    dup
    ifnonnull icn_129_gok
    pop
    goto icn_116_α
icn_129_gok:
    checkcast java/lang/Long
    invokevirtual java/lang/Long/longValue()J
    goto icn_128_store
icn_128_α:
    goto icn_129_α
icn_128_β:
    goto icn_129_β
icn_128_store:
    putstatic rung36_jcon_profsum/icn_pv_main_sorttotal J
    getstatic rung36_jcon_profsum/icn_pv_main_sorttotal J
    goto icn_main_s1_sdrain
;  INT
icn_133_α:
    ldc2_w 1
    goto icn_132_sub_irelay
icn_133_β:
    goto icn_127_else
;  VAR
icn_134_α:
    getstatic rung36_jcon_profsum/icn_pv_main_args J
    goto icn_132_sub_srelay
icn_134_β:
    goto icn_127_else
icn_132_sub_srelay:
    putstatic rung36_jcon_profsum/icn_132_sub_s Ljava/lang/String;
    goto icn_133_α
icn_132_sub_irelay:
    l2i
    istore 84
    iload 84
    ifgt icn_132_sub_pos
    iload 84
    iflt icn_132_sub_neg
icn_132_sub_z:
    goto icn_127_else
icn_132_sub_pos:
    iload 84
    iconst_1
    isub
    putstatic rung36_jcon_profsum/icn_132_sub_i I
    goto icn_132_sub_check
icn_132_sub_neg:
    getstatic rung36_jcon_profsum/icn_132_sub_s Ljava/lang/String;
    invokevirtual java/lang/String/length()I
    iload 84
    iadd
    putstatic rung36_jcon_profsum/icn_132_sub_i I
    goto icn_132_sub_check
icn_132_sub_check:
    getstatic rung36_jcon_profsum/icn_132_sub_i I
    iflt icn_127_else
    getstatic rung36_jcon_profsum/icn_132_sub_s Ljava/lang/String;
    invokevirtual java/lang/String/length()I
    getstatic rung36_jcon_profsum/icn_132_sub_i I
    if_icmple icn_127_else
    getstatic rung36_jcon_profsum/icn_132_sub_s Ljava/lang/String;
    getstatic rung36_jcon_profsum/icn_132_sub_i I
    getstatic rung36_jcon_profsum/icn_132_sub_i I
    iconst_1
    iadd
    invokevirtual java/lang/String/substring(II)Ljava/lang/String;
    goto icn_131_lrelay
icn_132_α:
    goto icn_134_α
icn_132_β:
    goto icn_133_β
;  STR
icn_135_α:
    ldc "-t"
    goto icn_131_rrelay
icn_135_β:
    goto icn_127_else
;  STRRELOP
icn_131_α:
    goto icn_132_α
icn_131_β:
    goto icn_132_β
icn_131_lrelay:
    astore 85
    goto icn_131_lstore
icn_131_lstore:
    goto icn_135_α
icn_131_rrelay:
    astore 86
    goto icn_131_chk
icn_131_chk:
    aload 85
    aload 86
    invokevirtual java/lang/String/compareTo(Ljava/lang/String;)I
    ifne icn_135_β
    lconst_0
    goto icn_127_then
icn_127_then:
    pop2
    goto icn_128_α
icn_127_else:
    goto icn_116_α
icn_127_α:
    goto icn_131_α
icn_127_β:
    goto icn_131_β
icn_main_s1_sdrain:
    pop2
    goto icn_116_α
icn_main_done:
    return
.end method

.method public static icn_lookup()V
    .limit stack 16
    .limit locals 366
    lconst_0
    lstore 0
    lconst_0
    lstore 2
    lconst_0
    lstore 4
    lconst_0
    lstore 6
    lconst_0
    lstore 8
    lconst_0
    lstore 10
    lconst_0
    lstore 12
    lconst_0
    lstore 14
    lconst_0
    lstore 16
    lconst_0
    lstore 18
    lconst_0
    lstore 20
    lconst_0
    lstore 22
    lconst_0
    lstore 24
    lconst_0
    lstore 26
    lconst_0
    lstore 28
    lconst_0
    lstore 30
    lconst_0
    lstore 32
    lconst_0
    lstore 34
    lconst_0
    lstore 36
    lconst_0
    lstore 38
    lconst_0
    lstore 40
    lconst_0
    lstore 42
    lconst_0
    lstore 44
    lconst_0
    lstore 46
    lconst_0
    lstore 48
    lconst_0
    lstore 50
    lconst_0
    lstore 52
    lconst_0
    lstore 54
    lconst_0
    lstore 56
    lconst_0
    lstore 58
    lconst_0
    lstore 60
    lconst_0
    lstore 62
    iconst_0
    istore 84
    iconst_0
    istore 85
    iconst_0
    istore 86
    iconst_0
    istore 87
    aconst_null
    astore 148
    aconst_null
    astore 149
    aconst_null
    astore 150
    aconst_null
    astore 151
    getstatic rung36_jcon_profsum/icn_arg_0 J
    putstatic rung36_jcon_profsum/icn_pv_lookup_s J
    goto icn_152_α
;  VAR
icn_138_α:
    getstatic rung36_jcon_profsum/icn_pv_lookup_p J
    goto icn_137_ret_store
icn_138_β:
    goto icn_137_ret_fail
icn_137_α:
    goto icn_138_α
icn_137_β:
    goto icn_lookup_ret
icn_137_ret_fail:
    iconst_1
    putstatic rung36_jcon_profsum/icn_failed B
    goto icn_lookup_done
icn_137_ret_store:
    putstatic rung36_jcon_profsum/icn_retval_str Ljava/lang/String;
    lconst_0
    putstatic rung36_jcon_profsum/icn_retval J
    iconst_0
    putstatic rung36_jcon_profsum/icn_failed B
    goto icn_lookup_ret
;  VAR
icn_142_α:
    getstatic rung36_jcon_profsum/icn_pv_lookup_s J
    goto icn_141_rc_r1
icn_142_β:
    goto icn_139_ret_fail
;  INT
icn_143_α:
    ldc2_w 0
    goto icn_141_rc_r2
icn_143_β:
    goto icn_139_ret_fail
;  INT
icn_144_α:
    ldc2_w 0
    goto icn_141_rc_r3
icn_144_β:
    goto icn_139_ret_fail
;  INT
icn_145_α:
    ldc2_w 0
    goto icn_141_rc_r4
icn_145_β:
    goto icn_139_ret_fail
icn_141_α:
    goto icn_142_α
icn_141_β:
    goto icn_139_ret_fail
icn_141_rc_r1:
    invokestatic java/lang/Long/valueOf(J)Ljava/lang/Long;
    putstatic rung36_jcon_profsum/icn_141_rc_a0 Ljava/lang/Object;
    goto icn_143_α
icn_141_rc_r2:
    invokestatic java/lang/Long/valueOf(J)Ljava/lang/Long;
    putstatic rung36_jcon_profsum/icn_141_rc_a1 Ljava/lang/Object;
    goto icn_144_α
icn_141_rc_r3:
    invokestatic java/lang/Long/valueOf(J)Ljava/lang/Long;
    putstatic rung36_jcon_profsum/icn_141_rc_a2 Ljava/lang/Object;
    goto icn_145_α
icn_141_rc_r4:
    invokestatic java/lang/Long/valueOf(J)Ljava/lang/Long;
    putstatic rung36_jcon_profsum/icn_141_rc_a3 Ljava/lang/Object;
    goto icn_141_rc_build
icn_141_rc_build:
    new rung36_jcon_profsum$method
    dup
    invokespecial rung36_jcon_profsum$method/<init>()V
    putstatic rung36_jcon_profsum/icn_141_rc_obj Ljava/lang/Object;
    getstatic rung36_jcon_profsum/icn_141_rc_obj Ljava/lang/Object;
    putstatic rung36_jcon_profsum/icn_retval_obj Ljava/lang/Object;
    lconst_0
    goto icn_140_tsa_vr
;  VAR
icn_146_α:
    getstatic rung36_jcon_profsum/icn_pv_lookup_s J
    goto icn_140_tsa_kr
icn_146_β:
    goto icn_139_ret_fail
icn_140_α:
    goto icn_141_α
icn_140_β:
    goto icn_139_ret_fail
icn_140_tsa_vr:
    dup2
    putstatic rung36_jcon_profsum/icn_140_tsa_vl J
    invokestatic java/lang/Long/valueOf(J)Ljava/lang/Long;
    putstatic rung36_jcon_profsum/icn_140_tsa_vo Ljava/lang/Object;
    goto icn_146_α
icn_140_tsa_kr:
    invokestatic java/lang/Long/toString(J)Ljava/lang/String;
    putstatic rung36_jcon_profsum/icn_140_tsa_ks Ljava/lang/String;
    goto icn_140_tsa_put
icn_140_tsa_put:
    getstatic rung36_jcon_profsum/icn_pv_lookup_ptab Ljava/util/HashMap;
    getstatic rung36_jcon_profsum/icn_140_tsa_ks Ljava/lang/String;
    getstatic rung36_jcon_profsum/icn_140_tsa_vo Ljava/lang/Object;
    invokevirtual java/util/HashMap/put(Ljava/lang/Object;Ljava/lang/Object;)Ljava/lang/Object;
    pop
    getstatic rung36_jcon_profsum/icn_140_tsa_vl J
    goto icn_139_ret_store
icn_139_α:
    goto icn_140_α
icn_139_β:
    goto icn_lookup_ret
icn_139_ret_fail:
    iconst_1
    putstatic rung36_jcon_profsum/icn_failed B
    goto icn_lookup_done
icn_139_ret_store:
    putstatic rung36_jcon_profsum/icn_retval J
    iconst_0
    putstatic rung36_jcon_profsum/icn_failed B
    goto icn_lookup_ret
;  VAR
icn_150_α:
    getstatic rung36_jcon_profsum/icn_pv_lookup_ptab Ljava/util/HashMap;
    goto icn_149_ts_tr
icn_150_β:
    goto icn_136_else
;  VAR
icn_151_α:
    getstatic rung36_jcon_profsum/icn_pv_lookup_s J
    goto icn_149_ts_kr
icn_151_β:
    goto icn_136_else
icn_149_α:
    goto icn_150_α
icn_149_β:
    goto icn_151_β
icn_149_ts_tr:
    putstatic rung36_jcon_profsum/icn_149_ts_tbl Ljava/util/HashMap;
    goto icn_151_α
icn_149_ts_kr:
    dup2
    putstatic rung36_jcon_profsum/icn_149_ts_kval J
    invokestatic java/lang/Long/toString(J)Ljava/lang/String;
    putstatic rung36_jcon_profsum/icn_149_ts_key Ljava/lang/String;
    getstatic rung36_jcon_profsum/icn_149_ts_tbl Ljava/util/HashMap;
    getstatic rung36_jcon_profsum/icn_149_ts_key Ljava/lang/String;
    invokevirtual java/util/HashMap/get(Ljava/lang/Object;)Ljava/lang/Object;
    dup
    ifnonnull icn_149_ts_got
    pop
    lconst_0
    goto icn_147_store
icn_149_ts_got:
    checkcast java/lang/Long
    invokevirtual java/lang/Long/longValue()J
    goto icn_147_store
;  NONNULL
icn_148_α:
    goto icn_149_α
icn_148_β:
    goto icn_149_β
icn_147_α:
    goto icn_148_α
icn_147_β:
    goto icn_148_β
icn_147_store:
    putstatic rung36_jcon_profsum/icn_pv_lookup_p J
    getstatic rung36_jcon_profsum/icn_pv_lookup_p J
    goto icn_136_then
icn_136_then:
    pop2
    goto icn_137_α
icn_136_else:
    goto icn_139_α
icn_136_α:
    goto icn_147_α
icn_136_β:
    goto icn_147_β
icn_152_α:
    getstatic rung36_jcon_profsum/icn_init_lookup I
    ifne icn_152_init_skip
    iconst_1
    putstatic rung36_jcon_profsum/icn_init_lookup I
icn_154_α:
    goto icn_152_init_run
icn_154_β:
    goto icn_152_init_run
icn_153_α:
    goto icn_154_α
icn_153_β:
    goto icn_154_β
icn_153_store:
    putstatic rung36_jcon_profsum/icn_pv_lookup_ptab Ljava/util/HashMap;
    getstatic rung36_jcon_profsum/icn_pv_lookup_ptab Ljava/util/HashMap;
    goto icn_152_init_drain
    goto icn_153_α
icn_152_init_drain:
    pop2
icn_152_init_run:
    lconst_0
    goto icn_lookup_s1_sdrain
icn_152_init_skip:
    lconst_0
    goto icn_lookup_s1_sdrain
icn_152_β:
    goto icn_136_α
icn_lookup_s1_sdrain:
    pop2
    goto icn_136_α
icn_lookup_done:
    iconst_0
    putstatic rung36_jcon_profsum/icn_suspended B
    iconst_0
    putstatic rung36_jcon_profsum/icn_suspend_id I
    iconst_1
    putstatic rung36_jcon_profsum/icn_failed B
    return
icn_lookup_ret:
    iconst_0
    putstatic rung36_jcon_profsum/icn_failed B
    return
icn_lookup_sret:
    return
.end method

.method public static icn_accumulate()V
    .limit stack 16
    .limit locals 388
    lconst_0
    lstore 0
    lconst_0
    lstore 2
    lconst_0
    lstore 4
    lconst_0
    lstore 6
    lconst_0
    lstore 8
    lconst_0
    lstore 10
    lconst_0
    lstore 12
    lconst_0
    lstore 14
    lconst_0
    lstore 16
    lconst_0
    lstore 18
    lconst_0
    lstore 20
    lconst_0
    lstore 22
    lconst_0
    lstore 24
    lconst_0
    lstore 26
    lconst_0
    lstore 28
    lconst_0
    lstore 30
    lconst_0
    lstore 32
    lconst_0
    lstore 34
    lconst_0
    lstore 36
    lconst_0
    lstore 38
    lconst_0
    lstore 40
    lconst_0
    lstore 42
    lconst_0
    lstore 44
    lconst_0
    lstore 46
    lconst_0
    lstore 48
    lconst_0
    lstore 50
    lconst_0
    lstore 52
    lconst_0
    lstore 54
    lconst_0
    lstore 56
    lconst_0
    lstore 58
    lconst_0
    lstore 60
    lconst_0
    lstore 62
    iconst_0
    istore 84
    iconst_0
    istore 85
    iconst_0
    istore 86
    iconst_0
    istore 87
    aconst_null
    astore 148
    aconst_null
    astore 149
    aconst_null
    astore 150
    aconst_null
    astore 151
    aconst_null
    astore 152
    aconst_null
    astore 153
    goto icn_204_α
icn_155_α:
    lconst_0
    putstatic rung36_jcon_profsum/icn_retval J
    iconst_0
    putstatic rung36_jcon_profsum/icn_failed B
    goto icn_accumulate_ret
icn_155_β:
    goto icn_accumulate_ret
;  VAR
icn_157_α:
    getstatic rung36_jcon_profsum/icn_pv_accumulate_time J
    goto icn_156_rhsok
icn_157_β:
    goto icn_155_α
icn_156_α:
    goto icn_157_α
icn_156_β:
    goto icn_157_β
icn_156_rhsok:
    goto icn_accumulate_s15_sdrain
icn_accumulate_s15_sdrain:
    pop2
    goto icn_155_α
;  VAR
icn_160_α:
    getstatic rung36_jcon_profsum/icn_pv_accumulate_caller Ljava/lang/String;
    goto icn_159_arg0
icn_160_β:
    goto icn_156_α
icn_159_arg0:
    putstatic rung36_jcon_profsum/icn_arg_str_0 Ljava/lang/String;
    lconst_0
    putstatic rung36_jcon_profsum/icn_arg_0 J
    goto icn_159_docall
icn_159_α:
    goto icn_160_α
icn_159_β:
    goto icn_160_β
icn_159_docall:
    getstatic rung36_jcon_profsum/icn_6_binop_lc J
    lstore 152
    getstatic rung36_jcon_profsum/icn_6_binop_rc J
    lstore 154
    getstatic rung36_jcon_profsum/icn_8_binop_lc J
    lstore 156
    getstatic rung36_jcon_profsum/icn_8_binop_rc J
    lstore 158
    getstatic rung36_jcon_profsum/icn_9_binop_lc J
    lstore 160
    getstatic rung36_jcon_profsum/icn_9_binop_rc J
    lstore 162
    getstatic rung36_jcon_profsum/icn_12_binop_lc J
    lstore 164
    getstatic rung36_jcon_profsum/icn_12_binop_rc J
    lstore 166
    getstatic rung36_jcon_profsum/icn_16_binop_lc J
    lstore 168
    getstatic rung36_jcon_profsum/icn_16_binop_rc J
    lstore 170
    getstatic rung36_jcon_profsum/icn_18_binop_lc J
    lstore 172
    getstatic rung36_jcon_profsum/icn_18_binop_rc J
    lstore 174
    getstatic rung36_jcon_profsum/icn_19_binop_lc J
    lstore 176
    getstatic rung36_jcon_profsum/icn_19_binop_rc J
    lstore 178
    getstatic rung36_jcon_profsum/icn_22_binop_lc J
    lstore 180
    getstatic rung36_jcon_profsum/icn_22_binop_rc J
    lstore 182
    getstatic rung36_jcon_profsum/icn_25_relop_lc J
    lstore 184
    getstatic rung36_jcon_profsum/icn_25_relop_rc J
    lstore 186
    getstatic rung36_jcon_profsum/icn_29_binop_lc J
    lstore 188
    getstatic rung36_jcon_profsum/icn_29_binop_rc J
    lstore 190
    getstatic rung36_jcon_profsum/icn_31_binop_lc J
    lstore 192
    getstatic rung36_jcon_profsum/icn_31_binop_rc J
    lstore 194
    getstatic rung36_jcon_profsum/icn_32_binop_lc J
    lstore 196
    getstatic rung36_jcon_profsum/icn_32_binop_rc J
    lstore 198
    getstatic rung36_jcon_profsum/icn_35_binop_lc J
    lstore 200
    getstatic rung36_jcon_profsum/icn_35_binop_rc J
    lstore 202
    getstatic rung36_jcon_profsum/icn_54_relop_lc J
    lstore 204
    getstatic rung36_jcon_profsum/icn_54_relop_rc J
    lstore 206
    getstatic rung36_jcon_profsum/icn_69_sortf_fld J
    lstore 208
    getstatic rung36_jcon_profsum/icn_73_sortf_fld J
    lstore 210
    getstatic rung36_jcon_profsum/icn_81_binop_lc J
    lstore 212
    getstatic rung36_jcon_profsum/icn_81_binop_rc J
    lstore 214
    getstatic rung36_jcon_profsum/icn_85_augtemp J
    lstore 216
    getstatic rung36_jcon_profsum/icn_87_relop_lc J
    lstore 218
    getstatic rung36_jcon_profsum/icn_87_relop_rc J
    lstore 220
    getstatic rung36_jcon_profsum/icn_118_alt_val J
    lstore 222
    getstatic rung36_jcon_profsum/icn_123_relop_lc J
    lstore 224
    getstatic rung36_jcon_profsum/icn_123_relop_rc J
    lstore 226
    getstatic rung36_jcon_profsum/icn_140_tsa_vl J
    lstore 228
    getstatic rung36_jcon_profsum/icn_149_ts_kval J
    lstore 230
    getstatic rung36_jcon_profsum/icn_pv_accumulate_time J
    lstore 232
    invokestatic rung36_jcon_profsum/icn_lookup()V
    lload 152
    putstatic rung36_jcon_profsum/icn_6_binop_lc J
    lload 154
    putstatic rung36_jcon_profsum/icn_6_binop_rc J
    lload 156
    putstatic rung36_jcon_profsum/icn_8_binop_lc J
    lload 158
    putstatic rung36_jcon_profsum/icn_8_binop_rc J
    lload 160
    putstatic rung36_jcon_profsum/icn_9_binop_lc J
    lload 162
    putstatic rung36_jcon_profsum/icn_9_binop_rc J
    lload 164
    putstatic rung36_jcon_profsum/icn_12_binop_lc J
    lload 166
    putstatic rung36_jcon_profsum/icn_12_binop_rc J
    lload 168
    putstatic rung36_jcon_profsum/icn_16_binop_lc J
    lload 170
    putstatic rung36_jcon_profsum/icn_16_binop_rc J
    lload 172
    putstatic rung36_jcon_profsum/icn_18_binop_lc J
    lload 174
    putstatic rung36_jcon_profsum/icn_18_binop_rc J
    lload 176
    putstatic rung36_jcon_profsum/icn_19_binop_lc J
    lload 178
    putstatic rung36_jcon_profsum/icn_19_binop_rc J
    lload 180
    putstatic rung36_jcon_profsum/icn_22_binop_lc J
    lload 182
    putstatic rung36_jcon_profsum/icn_22_binop_rc J
    lload 184
    putstatic rung36_jcon_profsum/icn_25_relop_lc J
    lload 186
    putstatic rung36_jcon_profsum/icn_25_relop_rc J
    lload 188
    putstatic rung36_jcon_profsum/icn_29_binop_lc J
    lload 190
    putstatic rung36_jcon_profsum/icn_29_binop_rc J
    lload 192
    putstatic rung36_jcon_profsum/icn_31_binop_lc J
    lload 194
    putstatic rung36_jcon_profsum/icn_31_binop_rc J
    lload 196
    putstatic rung36_jcon_profsum/icn_32_binop_lc J
    lload 198
    putstatic rung36_jcon_profsum/icn_32_binop_rc J
    lload 200
    putstatic rung36_jcon_profsum/icn_35_binop_lc J
    lload 202
    putstatic rung36_jcon_profsum/icn_35_binop_rc J
    lload 204
    putstatic rung36_jcon_profsum/icn_54_relop_lc J
    lload 206
    putstatic rung36_jcon_profsum/icn_54_relop_rc J
    lload 208
    putstatic rung36_jcon_profsum/icn_69_sortf_fld J
    lload 210
    putstatic rung36_jcon_profsum/icn_73_sortf_fld J
    lload 212
    putstatic rung36_jcon_profsum/icn_81_binop_lc J
    lload 214
    putstatic rung36_jcon_profsum/icn_81_binop_rc J
    lload 216
    putstatic rung36_jcon_profsum/icn_85_augtemp J
    lload 218
    putstatic rung36_jcon_profsum/icn_87_relop_lc J
    lload 220
    putstatic rung36_jcon_profsum/icn_87_relop_rc J
    lload 222
    putstatic rung36_jcon_profsum/icn_118_alt_val J
    lload 224
    putstatic rung36_jcon_profsum/icn_123_relop_lc J
    lload 226
    putstatic rung36_jcon_profsum/icn_123_relop_rc J
    lload 228
    putstatic rung36_jcon_profsum/icn_140_tsa_vl J
    lload 230
    putstatic rung36_jcon_profsum/icn_149_ts_kval J
    lload 232
    putstatic rung36_jcon_profsum/icn_pv_accumulate_time J
    getstatic rung36_jcon_profsum/icn_failed B
    ifne icn_159_after_call
    getstatic rung36_jcon_profsum/icn_retval J
    goto icn_158_store
icn_159_after_call:
    goto icn_156_α
icn_158_α:
    goto icn_159_α
icn_158_β:
    goto icn_159_β
icn_158_store:
    putstatic rung36_jcon_profsum/icn_pv_accumulate_q J
    getstatic rung36_jcon_profsum/icn_pv_accumulate_q J
    goto icn_accumulate_s14_sdrain
icn_accumulate_s14_sdrain:
    pop2
    goto icn_156_α
;  VAR
icn_162_α:
    getstatic rung36_jcon_profsum/icn_pv_accumulate_count J
    goto icn_161_rhsok
icn_162_β:
    goto icn_158_α
icn_161_α:
    goto icn_162_α
icn_161_β:
    goto icn_162_β
icn_161_rhsok:
    goto icn_accumulate_s13_sdrain
icn_accumulate_s13_sdrain:
    pop2
    goto icn_158_α
;  VAR
icn_164_α:
    getstatic rung36_jcon_profsum/icn_pv_accumulate_time J
    goto icn_163_rhsok
icn_164_β:
    goto icn_161_α
icn_163_α:
    goto icn_164_α
icn_163_β:
    goto icn_164_β
icn_163_rhsok:
    goto icn_accumulate_s12_sdrain
icn_accumulate_s12_sdrain:
    pop2
    goto icn_161_α
;  VAR
icn_167_α:
    getstatic rung36_jcon_profsum/icn_pv_accumulate_callee Ljava/lang/String;
    goto icn_166_arg0
icn_167_β:
    goto icn_163_α
icn_166_arg0:
    putstatic rung36_jcon_profsum/icn_arg_str_0 Ljava/lang/String;
    lconst_0
    putstatic rung36_jcon_profsum/icn_arg_0 J
    goto icn_166_docall
icn_166_α:
    goto icn_167_α
icn_166_β:
    goto icn_167_β
icn_166_docall:
    getstatic rung36_jcon_profsum/icn_6_binop_lc J
    lstore 152
    getstatic rung36_jcon_profsum/icn_6_binop_rc J
    lstore 154
    getstatic rung36_jcon_profsum/icn_8_binop_lc J
    lstore 156
    getstatic rung36_jcon_profsum/icn_8_binop_rc J
    lstore 158
    getstatic rung36_jcon_profsum/icn_9_binop_lc J
    lstore 160
    getstatic rung36_jcon_profsum/icn_9_binop_rc J
    lstore 162
    getstatic rung36_jcon_profsum/icn_12_binop_lc J
    lstore 164
    getstatic rung36_jcon_profsum/icn_12_binop_rc J
    lstore 166
    getstatic rung36_jcon_profsum/icn_16_binop_lc J
    lstore 168
    getstatic rung36_jcon_profsum/icn_16_binop_rc J
    lstore 170
    getstatic rung36_jcon_profsum/icn_18_binop_lc J
    lstore 172
    getstatic rung36_jcon_profsum/icn_18_binop_rc J
    lstore 174
    getstatic rung36_jcon_profsum/icn_19_binop_lc J
    lstore 176
    getstatic rung36_jcon_profsum/icn_19_binop_rc J
    lstore 178
    getstatic rung36_jcon_profsum/icn_22_binop_lc J
    lstore 180
    getstatic rung36_jcon_profsum/icn_22_binop_rc J
    lstore 182
    getstatic rung36_jcon_profsum/icn_25_relop_lc J
    lstore 184
    getstatic rung36_jcon_profsum/icn_25_relop_rc J
    lstore 186
    getstatic rung36_jcon_profsum/icn_29_binop_lc J
    lstore 188
    getstatic rung36_jcon_profsum/icn_29_binop_rc J
    lstore 190
    getstatic rung36_jcon_profsum/icn_31_binop_lc J
    lstore 192
    getstatic rung36_jcon_profsum/icn_31_binop_rc J
    lstore 194
    getstatic rung36_jcon_profsum/icn_32_binop_lc J
    lstore 196
    getstatic rung36_jcon_profsum/icn_32_binop_rc J
    lstore 198
    getstatic rung36_jcon_profsum/icn_35_binop_lc J
    lstore 200
    getstatic rung36_jcon_profsum/icn_35_binop_rc J
    lstore 202
    getstatic rung36_jcon_profsum/icn_54_relop_lc J
    lstore 204
    getstatic rung36_jcon_profsum/icn_54_relop_rc J
    lstore 206
    getstatic rung36_jcon_profsum/icn_69_sortf_fld J
    lstore 208
    getstatic rung36_jcon_profsum/icn_73_sortf_fld J
    lstore 210
    getstatic rung36_jcon_profsum/icn_81_binop_lc J
    lstore 212
    getstatic rung36_jcon_profsum/icn_81_binop_rc J
    lstore 214
    getstatic rung36_jcon_profsum/icn_85_augtemp J
    lstore 216
    getstatic rung36_jcon_profsum/icn_87_relop_lc J
    lstore 218
    getstatic rung36_jcon_profsum/icn_87_relop_rc J
    lstore 220
    getstatic rung36_jcon_profsum/icn_118_alt_val J
    lstore 222
    getstatic rung36_jcon_profsum/icn_123_relop_lc J
    lstore 224
    getstatic rung36_jcon_profsum/icn_123_relop_rc J
    lstore 226
    getstatic rung36_jcon_profsum/icn_140_tsa_vl J
    lstore 228
    getstatic rung36_jcon_profsum/icn_149_ts_kval J
    lstore 230
    getstatic rung36_jcon_profsum/icn_pv_accumulate_time J
    lstore 232
    getstatic rung36_jcon_profsum/icn_pv_accumulate_q J
    lstore 234
    getstatic rung36_jcon_profsum/icn_pv_accumulate_count J
    lstore 236
    invokestatic rung36_jcon_profsum/icn_lookup()V
    lload 152
    putstatic rung36_jcon_profsum/icn_6_binop_lc J
    lload 154
    putstatic rung36_jcon_profsum/icn_6_binop_rc J
    lload 156
    putstatic rung36_jcon_profsum/icn_8_binop_lc J
    lload 158
    putstatic rung36_jcon_profsum/icn_8_binop_rc J
    lload 160
    putstatic rung36_jcon_profsum/icn_9_binop_lc J
    lload 162
    putstatic rung36_jcon_profsum/icn_9_binop_rc J
    lload 164
    putstatic rung36_jcon_profsum/icn_12_binop_lc J
    lload 166
    putstatic rung36_jcon_profsum/icn_12_binop_rc J
    lload 168
    putstatic rung36_jcon_profsum/icn_16_binop_lc J
    lload 170
    putstatic rung36_jcon_profsum/icn_16_binop_rc J
    lload 172
    putstatic rung36_jcon_profsum/icn_18_binop_lc J
    lload 174
    putstatic rung36_jcon_profsum/icn_18_binop_rc J
    lload 176
    putstatic rung36_jcon_profsum/icn_19_binop_lc J
    lload 178
    putstatic rung36_jcon_profsum/icn_19_binop_rc J
    lload 180
    putstatic rung36_jcon_profsum/icn_22_binop_lc J
    lload 182
    putstatic rung36_jcon_profsum/icn_22_binop_rc J
    lload 184
    putstatic rung36_jcon_profsum/icn_25_relop_lc J
    lload 186
    putstatic rung36_jcon_profsum/icn_25_relop_rc J
    lload 188
    putstatic rung36_jcon_profsum/icn_29_binop_lc J
    lload 190
    putstatic rung36_jcon_profsum/icn_29_binop_rc J
    lload 192
    putstatic rung36_jcon_profsum/icn_31_binop_lc J
    lload 194
    putstatic rung36_jcon_profsum/icn_31_binop_rc J
    lload 196
    putstatic rung36_jcon_profsum/icn_32_binop_lc J
    lload 198
    putstatic rung36_jcon_profsum/icn_32_binop_rc J
    lload 200
    putstatic rung36_jcon_profsum/icn_35_binop_lc J
    lload 202
    putstatic rung36_jcon_profsum/icn_35_binop_rc J
    lload 204
    putstatic rung36_jcon_profsum/icn_54_relop_lc J
    lload 206
    putstatic rung36_jcon_profsum/icn_54_relop_rc J
    lload 208
    putstatic rung36_jcon_profsum/icn_69_sortf_fld J
    lload 210
    putstatic rung36_jcon_profsum/icn_73_sortf_fld J
    lload 212
    putstatic rung36_jcon_profsum/icn_81_binop_lc J
    lload 214
    putstatic rung36_jcon_profsum/icn_81_binop_rc J
    lload 216
    putstatic rung36_jcon_profsum/icn_85_augtemp J
    lload 218
    putstatic rung36_jcon_profsum/icn_87_relop_lc J
    lload 220
    putstatic rung36_jcon_profsum/icn_87_relop_rc J
    lload 222
    putstatic rung36_jcon_profsum/icn_118_alt_val J
    lload 224
    putstatic rung36_jcon_profsum/icn_123_relop_lc J
    lload 226
    putstatic rung36_jcon_profsum/icn_123_relop_rc J
    lload 228
    putstatic rung36_jcon_profsum/icn_140_tsa_vl J
    lload 230
    putstatic rung36_jcon_profsum/icn_149_ts_kval J
    lload 232
    putstatic rung36_jcon_profsum/icn_pv_accumulate_time J
    lload 234
    putstatic rung36_jcon_profsum/icn_pv_accumulate_q J
    lload 236
    putstatic rung36_jcon_profsum/icn_pv_accumulate_count J
    getstatic rung36_jcon_profsum/icn_failed B
    ifne icn_166_after_call
    getstatic rung36_jcon_profsum/icn_retval J
    goto icn_165_store
icn_166_after_call:
    goto icn_163_α
icn_165_α:
    goto icn_166_α
icn_165_β:
    goto icn_166_β
icn_165_store:
    putstatic rung36_jcon_profsum/icn_pv_accumulate_p J
    getstatic rung36_jcon_profsum/icn_pv_accumulate_p J
    goto icn_accumulate_s11_sdrain
icn_accumulate_s11_sdrain:
    pop2
    goto icn_163_α
;  VAR
icn_170_α:
    getstatic rung36_jcon_profsum/icn_pv_accumulate_callee Ljava/lang/String;
    goto icn_169_arg0
icn_170_β:
    goto icn_165_α
icn_169_arg0:
    putstatic rung36_jcon_profsum/icn_arg_str_0 Ljava/lang/String;
    lconst_0
    putstatic rung36_jcon_profsum/icn_arg_0 J
    goto icn_169_docall
icn_169_α:
    goto icn_170_α
icn_169_β:
    goto icn_170_β
icn_169_docall:
    getstatic rung36_jcon_profsum/icn_6_binop_lc J
    lstore 152
    getstatic rung36_jcon_profsum/icn_6_binop_rc J
    lstore 154
    getstatic rung36_jcon_profsum/icn_8_binop_lc J
    lstore 156
    getstatic rung36_jcon_profsum/icn_8_binop_rc J
    lstore 158
    getstatic rung36_jcon_profsum/icn_9_binop_lc J
    lstore 160
    getstatic rung36_jcon_profsum/icn_9_binop_rc J
    lstore 162
    getstatic rung36_jcon_profsum/icn_12_binop_lc J
    lstore 164
    getstatic rung36_jcon_profsum/icn_12_binop_rc J
    lstore 166
    getstatic rung36_jcon_profsum/icn_16_binop_lc J
    lstore 168
    getstatic rung36_jcon_profsum/icn_16_binop_rc J
    lstore 170
    getstatic rung36_jcon_profsum/icn_18_binop_lc J
    lstore 172
    getstatic rung36_jcon_profsum/icn_18_binop_rc J
    lstore 174
    getstatic rung36_jcon_profsum/icn_19_binop_lc J
    lstore 176
    getstatic rung36_jcon_profsum/icn_19_binop_rc J
    lstore 178
    getstatic rung36_jcon_profsum/icn_22_binop_lc J
    lstore 180
    getstatic rung36_jcon_profsum/icn_22_binop_rc J
    lstore 182
    getstatic rung36_jcon_profsum/icn_25_relop_lc J
    lstore 184
    getstatic rung36_jcon_profsum/icn_25_relop_rc J
    lstore 186
    getstatic rung36_jcon_profsum/icn_29_binop_lc J
    lstore 188
    getstatic rung36_jcon_profsum/icn_29_binop_rc J
    lstore 190
    getstatic rung36_jcon_profsum/icn_31_binop_lc J
    lstore 192
    getstatic rung36_jcon_profsum/icn_31_binop_rc J
    lstore 194
    getstatic rung36_jcon_profsum/icn_32_binop_lc J
    lstore 196
    getstatic rung36_jcon_profsum/icn_32_binop_rc J
    lstore 198
    getstatic rung36_jcon_profsum/icn_35_binop_lc J
    lstore 200
    getstatic rung36_jcon_profsum/icn_35_binop_rc J
    lstore 202
    getstatic rung36_jcon_profsum/icn_54_relop_lc J
    lstore 204
    getstatic rung36_jcon_profsum/icn_54_relop_rc J
    lstore 206
    getstatic rung36_jcon_profsum/icn_69_sortf_fld J
    lstore 208
    getstatic rung36_jcon_profsum/icn_73_sortf_fld J
    lstore 210
    getstatic rung36_jcon_profsum/icn_81_binop_lc J
    lstore 212
    getstatic rung36_jcon_profsum/icn_81_binop_rc J
    lstore 214
    getstatic rung36_jcon_profsum/icn_85_augtemp J
    lstore 216
    getstatic rung36_jcon_profsum/icn_87_relop_lc J
    lstore 218
    getstatic rung36_jcon_profsum/icn_87_relop_rc J
    lstore 220
    getstatic rung36_jcon_profsum/icn_118_alt_val J
    lstore 222
    getstatic rung36_jcon_profsum/icn_123_relop_lc J
    lstore 224
    getstatic rung36_jcon_profsum/icn_123_relop_rc J
    lstore 226
    getstatic rung36_jcon_profsum/icn_140_tsa_vl J
    lstore 228
    getstatic rung36_jcon_profsum/icn_149_ts_kval J
    lstore 230
    getstatic rung36_jcon_profsum/icn_pv_accumulate_time J
    lstore 232
    getstatic rung36_jcon_profsum/icn_pv_accumulate_q J
    lstore 234
    getstatic rung36_jcon_profsum/icn_pv_accumulate_count J
    lstore 236
    getstatic rung36_jcon_profsum/icn_pv_accumulate_p J
    lstore 238
    invokestatic rung36_jcon_profsum/icn_fixname()V
    lload 152
    putstatic rung36_jcon_profsum/icn_6_binop_lc J
    lload 154
    putstatic rung36_jcon_profsum/icn_6_binop_rc J
    lload 156
    putstatic rung36_jcon_profsum/icn_8_binop_lc J
    lload 158
    putstatic rung36_jcon_profsum/icn_8_binop_rc J
    lload 160
    putstatic rung36_jcon_profsum/icn_9_binop_lc J
    lload 162
    putstatic rung36_jcon_profsum/icn_9_binop_rc J
    lload 164
    putstatic rung36_jcon_profsum/icn_12_binop_lc J
    lload 166
    putstatic rung36_jcon_profsum/icn_12_binop_rc J
    lload 168
    putstatic rung36_jcon_profsum/icn_16_binop_lc J
    lload 170
    putstatic rung36_jcon_profsum/icn_16_binop_rc J
    lload 172
    putstatic rung36_jcon_profsum/icn_18_binop_lc J
    lload 174
    putstatic rung36_jcon_profsum/icn_18_binop_rc J
    lload 176
    putstatic rung36_jcon_profsum/icn_19_binop_lc J
    lload 178
    putstatic rung36_jcon_profsum/icn_19_binop_rc J
    lload 180
    putstatic rung36_jcon_profsum/icn_22_binop_lc J
    lload 182
    putstatic rung36_jcon_profsum/icn_22_binop_rc J
    lload 184
    putstatic rung36_jcon_profsum/icn_25_relop_lc J
    lload 186
    putstatic rung36_jcon_profsum/icn_25_relop_rc J
    lload 188
    putstatic rung36_jcon_profsum/icn_29_binop_lc J
    lload 190
    putstatic rung36_jcon_profsum/icn_29_binop_rc J
    lload 192
    putstatic rung36_jcon_profsum/icn_31_binop_lc J
    lload 194
    putstatic rung36_jcon_profsum/icn_31_binop_rc J
    lload 196
    putstatic rung36_jcon_profsum/icn_32_binop_lc J
    lload 198
    putstatic rung36_jcon_profsum/icn_32_binop_rc J
    lload 200
    putstatic rung36_jcon_profsum/icn_35_binop_lc J
    lload 202
    putstatic rung36_jcon_profsum/icn_35_binop_rc J
    lload 204
    putstatic rung36_jcon_profsum/icn_54_relop_lc J
    lload 206
    putstatic rung36_jcon_profsum/icn_54_relop_rc J
    lload 208
    putstatic rung36_jcon_profsum/icn_69_sortf_fld J
    lload 210
    putstatic rung36_jcon_profsum/icn_73_sortf_fld J
    lload 212
    putstatic rung36_jcon_profsum/icn_81_binop_lc J
    lload 214
    putstatic rung36_jcon_profsum/icn_81_binop_rc J
    lload 216
    putstatic rung36_jcon_profsum/icn_85_augtemp J
    lload 218
    putstatic rung36_jcon_profsum/icn_87_relop_lc J
    lload 220
    putstatic rung36_jcon_profsum/icn_87_relop_rc J
    lload 222
    putstatic rung36_jcon_profsum/icn_118_alt_val J
    lload 224
    putstatic rung36_jcon_profsum/icn_123_relop_lc J
    lload 226
    putstatic rung36_jcon_profsum/icn_123_relop_rc J
    lload 228
    putstatic rung36_jcon_profsum/icn_140_tsa_vl J
    lload 230
    putstatic rung36_jcon_profsum/icn_149_ts_kval J
    lload 232
    putstatic rung36_jcon_profsum/icn_pv_accumulate_time J
    lload 234
    putstatic rung36_jcon_profsum/icn_pv_accumulate_q J
    lload 236
    putstatic rung36_jcon_profsum/icn_pv_accumulate_count J
    lload 238
    putstatic rung36_jcon_profsum/icn_pv_accumulate_p J
    getstatic rung36_jcon_profsum/icn_failed B
    ifne icn_169_after_call
    getstatic rung36_jcon_profsum/icn_retval J
    goto icn_168_store
icn_169_after_call:
    goto icn_165_α
icn_168_α:
    goto icn_169_α
icn_168_β:
    goto icn_169_β
icn_168_store:
    putstatic rung36_jcon_profsum/icn_pv_accumulate_callee J
    getstatic rung36_jcon_profsum/icn_pv_accumulate_callee J
    goto icn_accumulate_s10_sdrain
icn_accumulate_s10_sdrain:
    pop2
    goto icn_165_α
;  VAR
icn_173_α:
    getstatic rung36_jcon_profsum/icn_pv_accumulate_caller Ljava/lang/String;
    goto icn_172_arg0
icn_173_β:
    goto icn_168_α
icn_172_arg0:
    putstatic rung36_jcon_profsum/icn_arg_str_0 Ljava/lang/String;
    lconst_0
    putstatic rung36_jcon_profsum/icn_arg_0 J
    goto icn_172_docall
icn_172_α:
    goto icn_173_α
icn_172_β:
    goto icn_173_β
icn_172_docall:
    getstatic rung36_jcon_profsum/icn_6_binop_lc J
    lstore 152
    getstatic rung36_jcon_profsum/icn_6_binop_rc J
    lstore 154
    getstatic rung36_jcon_profsum/icn_8_binop_lc J
    lstore 156
    getstatic rung36_jcon_profsum/icn_8_binop_rc J
    lstore 158
    getstatic rung36_jcon_profsum/icn_9_binop_lc J
    lstore 160
    getstatic rung36_jcon_profsum/icn_9_binop_rc J
    lstore 162
    getstatic rung36_jcon_profsum/icn_12_binop_lc J
    lstore 164
    getstatic rung36_jcon_profsum/icn_12_binop_rc J
    lstore 166
    getstatic rung36_jcon_profsum/icn_16_binop_lc J
    lstore 168
    getstatic rung36_jcon_profsum/icn_16_binop_rc J
    lstore 170
    getstatic rung36_jcon_profsum/icn_18_binop_lc J
    lstore 172
    getstatic rung36_jcon_profsum/icn_18_binop_rc J
    lstore 174
    getstatic rung36_jcon_profsum/icn_19_binop_lc J
    lstore 176
    getstatic rung36_jcon_profsum/icn_19_binop_rc J
    lstore 178
    getstatic rung36_jcon_profsum/icn_22_binop_lc J
    lstore 180
    getstatic rung36_jcon_profsum/icn_22_binop_rc J
    lstore 182
    getstatic rung36_jcon_profsum/icn_25_relop_lc J
    lstore 184
    getstatic rung36_jcon_profsum/icn_25_relop_rc J
    lstore 186
    getstatic rung36_jcon_profsum/icn_29_binop_lc J
    lstore 188
    getstatic rung36_jcon_profsum/icn_29_binop_rc J
    lstore 190
    getstatic rung36_jcon_profsum/icn_31_binop_lc J
    lstore 192
    getstatic rung36_jcon_profsum/icn_31_binop_rc J
    lstore 194
    getstatic rung36_jcon_profsum/icn_32_binop_lc J
    lstore 196
    getstatic rung36_jcon_profsum/icn_32_binop_rc J
    lstore 198
    getstatic rung36_jcon_profsum/icn_35_binop_lc J
    lstore 200
    getstatic rung36_jcon_profsum/icn_35_binop_rc J
    lstore 202
    getstatic rung36_jcon_profsum/icn_54_relop_lc J
    lstore 204
    getstatic rung36_jcon_profsum/icn_54_relop_rc J
    lstore 206
    getstatic rung36_jcon_profsum/icn_69_sortf_fld J
    lstore 208
    getstatic rung36_jcon_profsum/icn_73_sortf_fld J
    lstore 210
    getstatic rung36_jcon_profsum/icn_81_binop_lc J
    lstore 212
    getstatic rung36_jcon_profsum/icn_81_binop_rc J
    lstore 214
    getstatic rung36_jcon_profsum/icn_85_augtemp J
    lstore 216
    getstatic rung36_jcon_profsum/icn_87_relop_lc J
    lstore 218
    getstatic rung36_jcon_profsum/icn_87_relop_rc J
    lstore 220
    getstatic rung36_jcon_profsum/icn_118_alt_val J
    lstore 222
    getstatic rung36_jcon_profsum/icn_123_relop_lc J
    lstore 224
    getstatic rung36_jcon_profsum/icn_123_relop_rc J
    lstore 226
    getstatic rung36_jcon_profsum/icn_140_tsa_vl J
    lstore 228
    getstatic rung36_jcon_profsum/icn_149_ts_kval J
    lstore 230
    getstatic rung36_jcon_profsum/icn_pv_accumulate_time J
    lstore 232
    getstatic rung36_jcon_profsum/icn_pv_accumulate_q J
    lstore 234
    getstatic rung36_jcon_profsum/icn_pv_accumulate_count J
    lstore 236
    getstatic rung36_jcon_profsum/icn_pv_accumulate_p J
    lstore 238
    invokestatic rung36_jcon_profsum/icn_fixname()V
    lload 152
    putstatic rung36_jcon_profsum/icn_6_binop_lc J
    lload 154
    putstatic rung36_jcon_profsum/icn_6_binop_rc J
    lload 156
    putstatic rung36_jcon_profsum/icn_8_binop_lc J
    lload 158
    putstatic rung36_jcon_profsum/icn_8_binop_rc J
    lload 160
    putstatic rung36_jcon_profsum/icn_9_binop_lc J
    lload 162
    putstatic rung36_jcon_profsum/icn_9_binop_rc J
    lload 164
    putstatic rung36_jcon_profsum/icn_12_binop_lc J
    lload 166
    putstatic rung36_jcon_profsum/icn_12_binop_rc J
    lload 168
    putstatic rung36_jcon_profsum/icn_16_binop_lc J
    lload 170
    putstatic rung36_jcon_profsum/icn_16_binop_rc J
    lload 172
    putstatic rung36_jcon_profsum/icn_18_binop_lc J
    lload 174
    putstatic rung36_jcon_profsum/icn_18_binop_rc J
    lload 176
    putstatic rung36_jcon_profsum/icn_19_binop_lc J
    lload 178
    putstatic rung36_jcon_profsum/icn_19_binop_rc J
    lload 180
    putstatic rung36_jcon_profsum/icn_22_binop_lc J
    lload 182
    putstatic rung36_jcon_profsum/icn_22_binop_rc J
    lload 184
    putstatic rung36_jcon_profsum/icn_25_relop_lc J
    lload 186
    putstatic rung36_jcon_profsum/icn_25_relop_rc J
    lload 188
    putstatic rung36_jcon_profsum/icn_29_binop_lc J
    lload 190
    putstatic rung36_jcon_profsum/icn_29_binop_rc J
    lload 192
    putstatic rung36_jcon_profsum/icn_31_binop_lc J
    lload 194
    putstatic rung36_jcon_profsum/icn_31_binop_rc J
    lload 196
    putstatic rung36_jcon_profsum/icn_32_binop_lc J
    lload 198
    putstatic rung36_jcon_profsum/icn_32_binop_rc J
    lload 200
    putstatic rung36_jcon_profsum/icn_35_binop_lc J
    lload 202
    putstatic rung36_jcon_profsum/icn_35_binop_rc J
    lload 204
    putstatic rung36_jcon_profsum/icn_54_relop_lc J
    lload 206
    putstatic rung36_jcon_profsum/icn_54_relop_rc J
    lload 208
    putstatic rung36_jcon_profsum/icn_69_sortf_fld J
    lload 210
    putstatic rung36_jcon_profsum/icn_73_sortf_fld J
    lload 212
    putstatic rung36_jcon_profsum/icn_81_binop_lc J
    lload 214
    putstatic rung36_jcon_profsum/icn_81_binop_rc J
    lload 216
    putstatic rung36_jcon_profsum/icn_85_augtemp J
    lload 218
    putstatic rung36_jcon_profsum/icn_87_relop_lc J
    lload 220
    putstatic rung36_jcon_profsum/icn_87_relop_rc J
    lload 222
    putstatic rung36_jcon_profsum/icn_118_alt_val J
    lload 224
    putstatic rung36_jcon_profsum/icn_123_relop_lc J
    lload 226
    putstatic rung36_jcon_profsum/icn_123_relop_rc J
    lload 228
    putstatic rung36_jcon_profsum/icn_140_tsa_vl J
    lload 230
    putstatic rung36_jcon_profsum/icn_149_ts_kval J
    lload 232
    putstatic rung36_jcon_profsum/icn_pv_accumulate_time J
    lload 234
    putstatic rung36_jcon_profsum/icn_pv_accumulate_q J
    lload 236
    putstatic rung36_jcon_profsum/icn_pv_accumulate_count J
    lload 238
    putstatic rung36_jcon_profsum/icn_pv_accumulate_p J
    getstatic rung36_jcon_profsum/icn_failed B
    ifne icn_172_after_call
    getstatic rung36_jcon_profsum/icn_retval J
    goto icn_171_store
icn_172_after_call:
    goto icn_168_α
icn_171_α:
    goto icn_172_α
icn_171_β:
    goto icn_172_β
icn_171_store:
    putstatic rung36_jcon_profsum/icn_pv_accumulate_caller J
    getstatic rung36_jcon_profsum/icn_pv_accumulate_caller J
    goto icn_accumulate_s9_sdrain
icn_accumulate_s9_sdrain:
    pop2
    goto icn_168_α
;  VAR
icn_178_α:
    ldc "0123456789"
    goto icn_177_after
icn_178_β:
    goto icn_171_α
icn_177_α:
    goto icn_178_α
icn_177_β:
    goto icn_178_β
icn_177_after:
;  many: cs String on stack
    getstatic rung36_jcon_profsum/icn_subject Ljava/lang/String;
    getstatic rung36_jcon_profsum/icn_pos I
    invokestatic rung36_jcon_profsum/icn_builtin_many(Ljava/lang/String;Ljava/lang/String;I)J
    dup2
    lconst_1
    lneg
    lcmp
    ifne icn_177_chk
    pop2
    goto icn_171_α
icn_177_chk:
;  many ok: advance icn_pos
    dup2
    lconst_1
    lsub
    l2i
    putstatic rung36_jcon_profsum/icn_pos I
    goto icn_176_ta
icn_176_α:
    goto icn_177_α
icn_176_β:
    goto icn_171_α
icn_176_ta:
;  tab: n (long) on stack
    l2i
    getstatic rung36_jcon_profsum/icn_subject Ljava/lang/String;
    getstatic rung36_jcon_profsum/icn_pos I
    invokestatic rung36_jcon_profsum/icn_builtin_tab_str(ILjava/lang/String;I)Ljava/lang/String;
    dup
    ifnonnull icn_176_to
    pop
    goto icn_171_α
icn_176_to:
;  tab ok: advance icn_pos = n-1, push String → γ
    goto icn_175_int_after
icn_175_α:
    goto icn_176_α
icn_175_β:
    goto icn_176_β
icn_175_int_after:
    astore 148
    aload 148
    invokestatic rung36_jcon_profsum/icn_builtin_parse_long(Ljava/lang/String;)J
    lstore 12
    lload 12
    ldc2_w -9223372036854775808
    lcmp
    ifeq icn_175_int_fail
    lload 12
    goto icn_174_store
icn_175_int_fail:
    goto icn_171_α
icn_174_α:
    goto icn_175_α
icn_174_β:
    goto icn_175_β
icn_174_store:
    putstatic rung36_jcon_profsum/icn_pv_accumulate_time J
    getstatic rung36_jcon_profsum/icn_pv_accumulate_time J
    goto icn_accumulate_s8_sdrain
icn_accumulate_s8_sdrain:
    pop2
    goto icn_171_α
;  STR
icn_181_α:
    ldc " "
    goto icn_180_after
icn_181_β:
    goto icn_174_α
icn_180_α:
    goto icn_181_α
icn_180_β:
    goto icn_181_β
icn_180_after:
;  many: cs String on stack
    getstatic rung36_jcon_profsum/icn_subject Ljava/lang/String;
    getstatic rung36_jcon_profsum/icn_pos I
    invokestatic rung36_jcon_profsum/icn_builtin_many(Ljava/lang/String;Ljava/lang/String;I)J
    dup2
    lconst_1
    lneg
    lcmp
    ifne icn_180_chk
    pop2
    goto icn_174_α
icn_180_chk:
;  many ok: advance icn_pos
    dup2
    lconst_1
    lsub
    l2i
    putstatic rung36_jcon_profsum/icn_pos I
    goto icn_179_ta
icn_179_α:
    goto icn_180_α
icn_179_β:
    goto icn_174_α
icn_179_ta:
;  tab: n (long) on stack
    l2i
    getstatic rung36_jcon_profsum/icn_subject Ljava/lang/String;
    getstatic rung36_jcon_profsum/icn_pos I
    invokestatic rung36_jcon_profsum/icn_builtin_tab_str(ILjava/lang/String;I)Ljava/lang/String;
    dup
    ifnonnull icn_179_to
    pop
    goto icn_174_α
icn_179_to:
;  tab ok: advance icn_pos = n-1, push String → γ
    goto icn_accumulate_s7_sdrain
icn_accumulate_s7_sdrain:
    pop
    goto icn_174_α
;  STR
icn_186_α:
    ldc " "
    goto icn_185_after
icn_186_β:
    goto icn_179_α
icn_185_α:
    goto icn_186_α
icn_185_after:
;  upto α: save cs, enter step
    putstatic rung36_jcon_profsum/icn_upto_cs_185 Ljava/lang/String;
    goto icn_185_step
icn_185_β:
    goto icn_185_step
icn_185_step:
;  upto step
    getstatic rung36_jcon_profsum/icn_upto_cs_185 Ljava/lang/String;
    getstatic rung36_jcon_profsum/icn_subject Ljava/lang/String;
    getstatic rung36_jcon_profsum/icn_pos I
    invokestatic rung36_jcon_profsum/icn_builtin_upto_step(Ljava/lang/String;Ljava/lang/String;I)J
    dup2
    lconst_1
    lneg
    lcmp
    ifne icn_185_chk
    pop2
    goto icn_179_α
icn_185_chk:
;  upto: yield 1-based pos (tab advances icn_pos)
    goto icn_184_ta
icn_184_α:
    goto icn_185_α
icn_184_β:
    goto icn_179_α
icn_184_ta:
;  tab: n (long) on stack
    l2i
    getstatic rung36_jcon_profsum/icn_subject Ljava/lang/String;
    getstatic rung36_jcon_profsum/icn_pos I
    invokestatic rung36_jcon_profsum/icn_builtin_tab_str(ILjava/lang/String;I)Ljava/lang/String;
    dup
    ifnonnull icn_184_to
    pop
    goto icn_179_α
icn_184_to:
;  tab ok: advance icn_pos = n-1, push String → γ
    goto icn_183_rhsok
icn_183_α:
    goto icn_184_α
icn_183_β:
    goto icn_184_β
icn_183_rhsok:
    putstatic rung36_jcon_profsum/icn_183_augtemp_s Ljava/lang/String;
    getstatic rung36_jcon_profsum/icn_pv_accumulate_caller Ljava/lang/String;
    getstatic rung36_jcon_profsum/icn_183_augtemp_s Ljava/lang/String;
    invokevirtual java/lang/String/concat(Ljava/lang/String;)Ljava/lang/String;
    dup
    putstatic rung36_jcon_profsum/icn_pv_accumulate_caller Ljava/lang/String;
    goto icn_accumulate_s6_sdrain
;  STR
icn_189_α:
    ldc " caller"
    goto icn_188_ma
icn_189_β:
    goto icn_182_else
icn_188_α:
    goto icn_189_α
icn_188_β:
    goto icn_182_else
icn_188_ma:
;  match: s String on stack
    getstatic rung36_jcon_profsum/icn_subject Ljava/lang/String;
    getstatic rung36_jcon_profsum/icn_pos I
    invokestatic rung36_jcon_profsum/icn_builtin_match(Ljava/lang/String;Ljava/lang/String;I)J
    dup2
    lconst_1
    lneg
    lcmp
    ifne icn_188_mo
    pop2
    goto icn_182_else
icn_188_mo:
;  match ok: icn_pos = result-1 (0-based), push result → γ
    dup2
    l2i
    iconst_1
    isub
    putstatic rung36_jcon_profsum/icn_pos I
    goto icn_187_rhsok
icn_187_α:
    goto icn_188_α
icn_187_β:
    goto icn_188_β
icn_187_rhsok:
    invokestatic java/lang/Long/toString(J)Ljava/lang/String;
    putstatic rung36_jcon_profsum/icn_187_augtemp_s Ljava/lang/String;
    getstatic rung36_jcon_profsum/icn_pv_accumulate_caller Ljava/lang/String;
    getstatic rung36_jcon_profsum/icn_187_augtemp_s Ljava/lang/String;
    invokevirtual java/lang/String/concat(Ljava/lang/String;)Ljava/lang/String;
    dup
    putstatic rung36_jcon_profsum/icn_pv_accumulate_caller Ljava/lang/String;
    goto icn_182_then
icn_182_then:
    pop
    goto icn_183_α
icn_182_else:
    goto icn_179_α
icn_182_α:
    goto icn_187_α
icn_182_β:
    goto icn_187_β
icn_accumulate_s6_sdrain:
    pop
    goto icn_179_α
;  STR
icn_193_α:
    ldc " "
    goto icn_192_after
icn_193_β:
    goto icn_182_α
icn_192_α:
    goto icn_193_α
icn_192_after:
;  upto α: save cs, enter step
    putstatic rung36_jcon_profsum/icn_upto_cs_192 Ljava/lang/String;
    goto icn_192_step
icn_192_β:
    goto icn_192_step
icn_192_step:
;  upto step
    getstatic rung36_jcon_profsum/icn_upto_cs_192 Ljava/lang/String;
    getstatic rung36_jcon_profsum/icn_subject Ljava/lang/String;
    getstatic rung36_jcon_profsum/icn_pos I
    invokestatic rung36_jcon_profsum/icn_builtin_upto_step(Ljava/lang/String;Ljava/lang/String;I)J
    dup2
    lconst_1
    lneg
    lcmp
    ifne icn_192_chk
    pop2
    goto icn_182_α
icn_192_chk:
;  upto: yield 1-based pos (tab advances icn_pos)
    goto icn_191_ta
icn_191_α:
    goto icn_192_α
icn_191_β:
    goto icn_182_α
icn_191_ta:
;  tab: n (long) on stack
    l2i
    getstatic rung36_jcon_profsum/icn_subject Ljava/lang/String;
    getstatic rung36_jcon_profsum/icn_pos I
    invokestatic rung36_jcon_profsum/icn_builtin_tab_str(ILjava/lang/String;I)Ljava/lang/String;
    dup
    ifnonnull icn_191_to
    pop
    goto icn_182_α
icn_191_to:
;  tab ok: advance icn_pos = n-1, push String → γ
    goto icn_190_store
icn_190_α:
    goto icn_191_α
icn_190_β:
    goto icn_191_β
icn_190_store:
    putstatic rung36_jcon_profsum/icn_pv_accumulate_caller Ljava/lang/String;
    getstatic rung36_jcon_profsum/icn_pv_accumulate_caller Ljava/lang/String;
    goto icn_accumulate_s5_sdrain
icn_accumulate_s5_sdrain:
    pop
    goto icn_182_α
;  STR
icn_196_α:
    ldc " "
    goto icn_195_after
icn_196_β:
    goto icn_190_α
icn_195_α:
    goto icn_196_α
icn_195_β:
    goto icn_196_β
icn_195_after:
;  many: cs String on stack
    getstatic rung36_jcon_profsum/icn_subject Ljava/lang/String;
    getstatic rung36_jcon_profsum/icn_pos I
    invokestatic rung36_jcon_profsum/icn_builtin_many(Ljava/lang/String;Ljava/lang/String;I)J
    dup2
    lconst_1
    lneg
    lcmp
    ifne icn_195_chk
    pop2
    goto icn_190_α
icn_195_chk:
;  many ok: advance icn_pos
    dup2
    lconst_1
    lsub
    l2i
    putstatic rung36_jcon_profsum/icn_pos I
    goto icn_194_ta
icn_194_α:
    goto icn_195_α
icn_194_β:
    goto icn_190_α
icn_194_ta:
;  tab: n (long) on stack
    l2i
    getstatic rung36_jcon_profsum/icn_subject Ljava/lang/String;
    getstatic rung36_jcon_profsum/icn_pos I
    invokestatic rung36_jcon_profsum/icn_builtin_tab_str(ILjava/lang/String;I)Ljava/lang/String;
    dup
    ifnonnull icn_194_to
    pop
    goto icn_190_α
icn_194_to:
;  tab ok: advance icn_pos = n-1, push String → γ
    goto icn_accumulate_s4_sdrain
icn_accumulate_s4_sdrain:
    pop
    goto icn_190_α
;  STR
icn_200_α:
    ldc " "
    goto icn_199_after
icn_200_β:
    goto icn_194_α
icn_199_α:
    goto icn_200_α
icn_199_after:
;  upto α: save cs, enter step
    putstatic rung36_jcon_profsum/icn_upto_cs_199 Ljava/lang/String;
    goto icn_199_step
icn_199_β:
    goto icn_199_step
icn_199_step:
;  upto step
    getstatic rung36_jcon_profsum/icn_upto_cs_199 Ljava/lang/String;
    getstatic rung36_jcon_profsum/icn_subject Ljava/lang/String;
    getstatic rung36_jcon_profsum/icn_pos I
    invokestatic rung36_jcon_profsum/icn_builtin_upto_step(Ljava/lang/String;Ljava/lang/String;I)J
    dup2
    lconst_1
    lneg
    lcmp
    ifne icn_199_chk
    pop2
    goto icn_194_α
icn_199_chk:
;  upto: yield 1-based pos (tab advances icn_pos)
    goto icn_198_ta
icn_198_α:
    goto icn_199_α
icn_198_β:
    goto icn_194_α
icn_198_ta:
;  tab: n (long) on stack
    l2i
    getstatic rung36_jcon_profsum/icn_subject Ljava/lang/String;
    getstatic rung36_jcon_profsum/icn_pos I
    invokestatic rung36_jcon_profsum/icn_builtin_tab_str(ILjava/lang/String;I)Ljava/lang/String;
    dup
    ifnonnull icn_198_to
    pop
    goto icn_194_α
icn_198_to:
;  tab ok: advance icn_pos = n-1, push String → γ
    goto icn_197_store
icn_197_α:
    goto icn_198_α
icn_197_β:
    goto icn_198_β
icn_197_store:
    putstatic rung36_jcon_profsum/icn_pv_accumulate_callee Ljava/lang/String;
    getstatic rung36_jcon_profsum/icn_pv_accumulate_callee Ljava/lang/String;
    goto icn_accumulate_s3_sdrain
icn_accumulate_s3_sdrain:
    pop
    goto icn_194_α
;  STR
icn_203_α:
    ldc " "
    goto icn_202_after
icn_203_β:
    goto icn_197_α
icn_202_α:
    goto icn_203_α
icn_202_β:
    goto icn_203_β
icn_202_after:
;  many: cs String on stack
    getstatic rung36_jcon_profsum/icn_subject Ljava/lang/String;
    getstatic rung36_jcon_profsum/icn_pos I
    invokestatic rung36_jcon_profsum/icn_builtin_many(Ljava/lang/String;Ljava/lang/String;I)J
    dup2
    lconst_1
    lneg
    lcmp
    ifne icn_202_chk
    pop2
    goto icn_197_α
icn_202_chk:
;  many ok: advance icn_pos
    dup2
    lconst_1
    lsub
    l2i
    putstatic rung36_jcon_profsum/icn_pos I
    goto icn_201_ta
icn_201_α:
    goto icn_202_α
icn_201_β:
    goto icn_197_α
icn_201_ta:
;  tab: n (long) on stack
    l2i
    getstatic rung36_jcon_profsum/icn_subject Ljava/lang/String;
    getstatic rung36_jcon_profsum/icn_pos I
    invokestatic rung36_jcon_profsum/icn_builtin_tab_str(ILjava/lang/String;I)Ljava/lang/String;
    dup
    ifnonnull icn_201_to
    pop
    goto icn_197_α
icn_201_to:
;  tab ok: advance icn_pos = n-1, push String → γ
    goto icn_accumulate_s2_sdrain
icn_accumulate_s2_sdrain:
    pop
    goto icn_197_α
;  VAR
icn_208_α:
    ldc "0123456789"
    goto icn_207_after
icn_208_β:
    goto icn_201_α
icn_207_α:
    goto icn_208_α
icn_207_β:
    goto icn_208_β
icn_207_after:
;  many: cs String on stack
    getstatic rung36_jcon_profsum/icn_subject Ljava/lang/String;
    getstatic rung36_jcon_profsum/icn_pos I
    invokestatic rung36_jcon_profsum/icn_builtin_many(Ljava/lang/String;Ljava/lang/String;I)J
    dup2
    lconst_1
    lneg
    lcmp
    ifne icn_207_chk
    pop2
    goto icn_201_α
icn_207_chk:
;  many ok: advance icn_pos
    dup2
    lconst_1
    lsub
    l2i
    putstatic rung36_jcon_profsum/icn_pos I
    goto icn_206_ta
icn_206_α:
    goto icn_207_α
icn_206_β:
    goto icn_201_α
icn_206_ta:
;  tab: n (long) on stack
    l2i
    getstatic rung36_jcon_profsum/icn_subject Ljava/lang/String;
    getstatic rung36_jcon_profsum/icn_pos I
    invokestatic rung36_jcon_profsum/icn_builtin_tab_str(ILjava/lang/String;I)Ljava/lang/String;
    dup
    ifnonnull icn_206_to
    pop
    goto icn_201_α
icn_206_to:
;  tab ok: advance icn_pos = n-1, push String → γ
    goto icn_205_int_after
icn_205_α:
    goto icn_206_α
icn_205_β:
    goto icn_206_β
icn_205_int_after:
    astore 149
    aload 149
    invokestatic rung36_jcon_profsum/icn_builtin_parse_long(Ljava/lang/String;)J
    lstore 14
    lload 14
    ldc2_w -9223372036854775808
    lcmp
    ifeq icn_205_int_fail
    lload 14
    goto icn_204_store
icn_205_int_fail:
    goto icn_201_α
icn_204_α:
    goto icn_205_α
icn_204_β:
    goto icn_205_β
icn_204_store:
    putstatic rung36_jcon_profsum/icn_pv_accumulate_count J
    getstatic rung36_jcon_profsum/icn_pv_accumulate_count J
    goto icn_accumulate_s1_sdrain
icn_accumulate_s1_sdrain:
    pop2
    goto icn_201_α
icn_accumulate_done:
    iconst_0
    putstatic rung36_jcon_profsum/icn_suspended B
    iconst_0
    putstatic rung36_jcon_profsum/icn_suspend_id I
    iconst_1
    putstatic rung36_jcon_profsum/icn_failed B
    return
icn_accumulate_ret:
    iconst_0
    putstatic rung36_jcon_profsum/icn_failed B
    return
icn_accumulate_sret:
    return
.end method

.method public static icn_fixname()V
    .limit stack 16
    .limit locals 410
    lconst_0
    lstore 0
    lconst_0
    lstore 2
    lconst_0
    lstore 4
    lconst_0
    lstore 6
    lconst_0
    lstore 8
    lconst_0
    lstore 10
    lconst_0
    lstore 12
    lconst_0
    lstore 14
    lconst_0
    lstore 16
    lconst_0
    lstore 18
    lconst_0
    lstore 20
    lconst_0
    lstore 22
    lconst_0
    lstore 24
    lconst_0
    lstore 26
    lconst_0
    lstore 28
    lconst_0
    lstore 30
    lconst_0
    lstore 32
    lconst_0
    lstore 34
    lconst_0
    lstore 36
    lconst_0
    lstore 38
    lconst_0
    lstore 40
    lconst_0
    lstore 42
    lconst_0
    lstore 44
    lconst_0
    lstore 46
    lconst_0
    lstore 48
    lconst_0
    lstore 50
    lconst_0
    lstore 52
    lconst_0
    lstore 54
    lconst_0
    lstore 56
    lconst_0
    lstore 58
    lconst_0
    lstore 60
    lconst_0
    lstore 62
    iconst_0
    istore 84
    iconst_0
    istore 85
    iconst_0
    istore 86
    iconst_0
    istore 87
    aconst_null
    astore 148
    aconst_null
    astore 149
    aconst_null
    astore 150
    aconst_null
    astore 151
    getstatic rung36_jcon_profsum/icn_arg_str_0 Ljava/lang/String;
    putstatic rung36_jcon_profsum/icn_pv_fixname_s Ljava/lang/String;
    goto icn_209_α
;  VAR
icn_210_α:
    getstatic rung36_jcon_profsum/icn_pv_fixname_s J
    goto icn_209_scan_setup
icn_210_β:
    goto icn_fixname_done
;  STR
icn_215_α:
    ldc "p_l$"
    goto icn_214_ma
icn_215_β:
    goto icn_211_seq_rf_0
icn_214_α:
    goto icn_215_α
icn_214_β:
    goto icn_211_seq_rf_0
icn_214_ma:
;  match: s String on stack
    getstatic rung36_jcon_profsum/icn_subject Ljava/lang/String;
    getstatic rung36_jcon_profsum/icn_pos I
    invokestatic rung36_jcon_profsum/icn_builtin_match(Ljava/lang/String;Ljava/lang/String;I)J
    dup2
    lconst_1
    lneg
    lcmp
    ifne icn_214_mo
    pop2
    goto icn_211_seq_rf_0
icn_214_mo:
;  match ok: icn_pos = result-1 (0-based), push result → γ
    dup2
    l2i
    iconst_1
    isub
    putstatic rung36_jcon_profsum/icn_pos I
    goto icn_213_and_rg_0
;  STR
icn_218_α:
    ldc "$"
    goto icn_217_after
icn_218_β:
    goto icn_214_β
icn_217_α:
    goto icn_218_α
icn_217_after:
;  upto α: save cs, enter step
    putstatic rung36_jcon_profsum/icn_upto_cs_217 Ljava/lang/String;
    goto icn_217_step
icn_217_β:
    goto icn_217_step
icn_217_step:
;  upto step
    getstatic rung36_jcon_profsum/icn_upto_cs_217 Ljava/lang/String;
    getstatic rung36_jcon_profsum/icn_subject Ljava/lang/String;
    getstatic rung36_jcon_profsum/icn_pos I
    invokestatic rung36_jcon_profsum/icn_builtin_upto_step(Ljava/lang/String;Ljava/lang/String;I)J
    dup2
    lconst_1
    lneg
    lcmp
    ifne icn_217_chk
    pop2
    goto icn_214_β
icn_217_chk:
;  upto: yield 1-based pos (tab advances icn_pos)
    goto icn_216_ta
icn_216_α:
    goto icn_217_α
icn_216_β:
    goto icn_214_β
icn_216_ta:
;  tab: n (long) on stack
    l2i
    getstatic rung36_jcon_profsum/icn_subject Ljava/lang/String;
    getstatic rung36_jcon_profsum/icn_pos I
    invokestatic rung36_jcon_profsum/icn_builtin_tab_str(ILjava/lang/String;I)Ljava/lang/String;
    dup
    ifnonnull icn_216_to
    pop
    goto icn_214_β
icn_216_to:
;  tab ok: advance icn_pos = n-1, push String → γ
    goto icn_212_alt_g2
    goto icn_213_α
icn_213_and_rg_0:
    putstatic rung36_jcon_profsum/icn_213_and_drain_0 J
    goto icn_216_α
icn_213_α:
    goto icn_214_α
icn_213_β:
    goto icn_216_β
;  STR
icn_221_α:
    ldc "java/"
    goto icn_220_ma
icn_221_β:
    goto icn_213_α
icn_220_α:
    goto icn_221_α
icn_220_β:
    goto icn_213_α
icn_220_ma:
;  match: s String on stack
    getstatic rung36_jcon_profsum/icn_subject Ljava/lang/String;
    getstatic rung36_jcon_profsum/icn_pos I
    invokestatic rung36_jcon_profsum/icn_builtin_match(Ljava/lang/String;Ljava/lang/String;I)J
    dup2
    lconst_1
    lneg
    lcmp
    ifne icn_220_mo
    pop2
    goto icn_213_α
icn_220_mo:
;  match ok: icn_pos = result-1 (0-based), push result → γ
    dup2
    l2i
    iconst_1
    isub
    putstatic rung36_jcon_profsum/icn_pos I
    goto icn_219_and_rg_0
;  INT
icn_224_α:
    ldc2_w 1
    goto icn_223_rrelay
icn_224_β:
    goto icn_223_lb
;  STR
icn_226_α:
    ldc "/"
    goto icn_225_after
icn_226_β:
    goto icn_220_β
icn_225_α:
    goto icn_226_α
icn_225_after:
;  upto α: save cs, enter step
    putstatic rung36_jcon_profsum/icn_upto_cs_225 Ljava/lang/String;
    goto icn_225_step
icn_225_β:
    goto icn_225_step
icn_225_step:
;  upto step
    getstatic rung36_jcon_profsum/icn_upto_cs_225 Ljava/lang/String;
    getstatic rung36_jcon_profsum/icn_subject Ljava/lang/String;
    getstatic rung36_jcon_profsum/icn_pos I
    invokestatic rung36_jcon_profsum/icn_builtin_upto_step(Ljava/lang/String;Ljava/lang/String;I)J
    dup2
    lconst_1
    lneg
    lcmp
    ifne icn_225_chk
    pop2
    goto icn_220_β
icn_225_chk:
;  upto: yield 1-based pos (tab advances icn_pos)
    goto icn_223_lrelay
icn_223_lrelay:
    putstatic rung36_jcon_profsum/icn_223_binop_lc J
    goto icn_223_lstore
icn_223_rrelay:
    putstatic rung36_jcon_profsum/icn_223_binop_rc J
    goto icn_223_compute
icn_223_lb:
    goto icn_225_β
icn_223_α:
    iconst_0
    putstatic rung36_jcon_profsum/icn_223_binop_bf I
    goto icn_225_α
icn_223_β:
    iconst_1
    putstatic rung36_jcon_profsum/icn_223_binop_bf I
    goto icn_225_α
icn_223_lstore:
    getstatic rung36_jcon_profsum/icn_223_binop_bf I
    ifeq icn_224_α
    goto icn_224_β
icn_223_compute:
    getstatic rung36_jcon_profsum/icn_223_binop_lc J
    getstatic rung36_jcon_profsum/icn_223_binop_rc J
    ladd
    goto icn_222_ta
icn_222_α:
    goto icn_223_α
icn_222_β:
    goto icn_220_β
icn_222_ta:
;  tab: n (long) on stack
    l2i
    getstatic rung36_jcon_profsum/icn_subject Ljava/lang/String;
    getstatic rung36_jcon_profsum/icn_pos I
    invokestatic rung36_jcon_profsum/icn_builtin_tab_str(ILjava/lang/String;I)Ljava/lang/String;
    dup
    ifnonnull icn_222_to
    pop
    goto icn_220_β
icn_222_to:
;  tab ok: advance icn_pos = n-1, push String → γ
    goto icn_212_alt_g1
    goto icn_219_α
icn_219_and_rg_0:
    putstatic rung36_jcon_profsum/icn_219_and_drain_0 J
    goto icn_222_α
icn_219_α:
    goto icn_220_α
icn_219_β:
    goto icn_222_β
;  STR
icn_228_α:
    ldc "jcon/"
    goto icn_227_ma
icn_228_β:
    goto icn_219_α
icn_227_α:
    goto icn_228_α
icn_227_β:
    goto icn_219_α
icn_227_ma:
;  match: s String on stack
    getstatic rung36_jcon_profsum/icn_subject Ljava/lang/String;
    getstatic rung36_jcon_profsum/icn_pos I
    invokestatic rung36_jcon_profsum/icn_builtin_match(Ljava/lang/String;Ljava/lang/String;I)J
    dup2
    lconst_1
    lneg
    lcmp
    ifne icn_227_mo
    pop2
    goto icn_219_α
icn_227_mo:
;  match ok: icn_pos = result-1 (0-based), push result → γ
    dup2
    l2i
    iconst_1
    isub
    putstatic rung36_jcon_profsum/icn_pos I
    goto icn_212_alt_g0
icn_212_alt_g0:
    putstatic rung36_jcon_profsum/icn_212_alt_val J
    sipush 1
    putstatic rung36_jcon_profsum/icn_212_alt_gate I
    getstatic rung36_jcon_profsum/icn_212_alt_val J
    goto icn_211_seq_rg_0
icn_212_alt_g1:
    pop
    lconst_0
    putstatic rung36_jcon_profsum/icn_212_alt_val J
    sipush 2
    putstatic rung36_jcon_profsum/icn_212_alt_gate I
    getstatic rung36_jcon_profsum/icn_212_alt_val J
    goto icn_211_seq_rg_0
icn_212_alt_g2:
    pop
    lconst_0
    putstatic rung36_jcon_profsum/icn_212_alt_val J
    sipush 3
    putstatic rung36_jcon_profsum/icn_212_alt_gate I
    getstatic rung36_jcon_profsum/icn_212_alt_val J
    goto icn_211_seq_rg_0
icn_212_α:
    iconst_0
    putstatic rung36_jcon_profsum/icn_212_alt_gate I
    goto icn_227_α
icn_212_β:
    getstatic rung36_jcon_profsum/icn_212_alt_gate I
    tableswitch 1 3
        icn_227_β
        icn_219_β
        icn_213_β
        default: icn_211_seq_rf_0
;  INT
icn_231_α:
    ldc2_w 0
    goto icn_230_ta
icn_231_β:
    goto icn_229_ret_fail
icn_230_α:
    goto icn_231_α
icn_230_β:
    goto icn_229_ret_fail
icn_230_ta:
;  tab: n (long) on stack
    l2i
    getstatic rung36_jcon_profsum/icn_subject Ljava/lang/String;
    getstatic rung36_jcon_profsum/icn_pos I
    invokestatic rung36_jcon_profsum/icn_builtin_tab_str(ILjava/lang/String;I)Ljava/lang/String;
    dup
    ifnonnull icn_230_to
    pop
    goto icn_229_ret_fail
icn_230_to:
;  tab ok: advance icn_pos = n-1, push String → γ
    goto icn_229_ret_store
icn_229_α:
    goto icn_230_α
icn_229_β:
    goto icn_fixname_ret
icn_229_ret_fail:
    iconst_1
    putstatic rung36_jcon_profsum/icn_failed B
    goto icn_fixname_done
icn_229_ret_store:
    putstatic rung36_jcon_profsum/icn_retval_str Ljava/lang/String;
    lconst_0
    putstatic rung36_jcon_profsum/icn_retval J
    iconst_0
    putstatic rung36_jcon_profsum/icn_failed B
    goto icn_fixname_ret
    goto icn_211_α
icn_211_seq_rg_0:
    pop2
    goto icn_229_α
icn_211_seq_rf_0:
    goto icn_229_α
icn_211_α:
    goto icn_212_α
icn_211_β:
    goto icn_229_β
;  SCAN
icn_209_α:
    goto icn_210_α
icn_209_β:
    goto icn_209_scan_beta
icn_209_scan_setup:
;  SCAN save+install
    getstatic rung36_jcon_profsum/icn_subject Ljava/lang/String;
    putstatic rung36_jcon_profsum/icn_scan_oldsubj_209 Ljava/lang/String;
    getstatic rung36_jcon_profsum/icn_pos I
    putstatic rung36_jcon_profsum/icn_scan_oldpos_209 I
    putstatic rung36_jcon_profsum/icn_subject Ljava/lang/String;
    iconst_0
    putstatic rung36_jcon_profsum/icn_pos I
    goto icn_211_α
icn_209_scan_bok:
;  SCAN restore (body ok)
    getstatic rung36_jcon_profsum/icn_scan_oldsubj_209 Ljava/lang/String;
    putstatic rung36_jcon_profsum/icn_subject Ljava/lang/String;
    getstatic rung36_jcon_profsum/icn_scan_oldpos_209 I
    putstatic rung36_jcon_profsum/icn_pos I
    goto icn_fixname_s0_sdrain
icn_209_scan_bfail:
;  SCAN restore (body fail)
    getstatic rung36_jcon_profsum/icn_scan_oldsubj_209 Ljava/lang/String;
    putstatic rung36_jcon_profsum/icn_subject Ljava/lang/String;
    getstatic rung36_jcon_profsum/icn_scan_oldpos_209 I
    putstatic rung36_jcon_profsum/icn_pos I
    goto icn_210_β
icn_209_scan_beta:
;  SCAN restore (outer β)
    getstatic rung36_jcon_profsum/icn_scan_oldsubj_209 Ljava/lang/String;
    putstatic rung36_jcon_profsum/icn_subject Ljava/lang/String;
    getstatic rung36_jcon_profsum/icn_scan_oldpos_209 I
    putstatic rung36_jcon_profsum/icn_pos I
    goto icn_211_β
icn_fixname_s0_sdrain:
    pop
    goto icn_fixname_done
icn_fixname_done:
    iconst_0
    putstatic rung36_jcon_profsum/icn_suspended B
    iconst_0
    putstatic rung36_jcon_profsum/icn_suspend_id I
    iconst_1
    putstatic rung36_jcon_profsum/icn_failed B
    return
icn_fixname_ret:
    iconst_0
    putstatic rung36_jcon_profsum/icn_failed B
    return
icn_fixname_sret:
    return
.end method

.method public static icn_pad()V
    .limit stack 16
    .limit locals 420
    lconst_0
    lstore 0
    lconst_0
    lstore 2
    lconst_0
    lstore 4
    lconst_0
    lstore 6
    lconst_0
    lstore 8
    lconst_0
    lstore 10
    lconst_0
    lstore 12
    lconst_0
    lstore 14
    lconst_0
    lstore 16
    lconst_0
    lstore 18
    lconst_0
    lstore 20
    lconst_0
    lstore 22
    lconst_0
    lstore 24
    lconst_0
    lstore 26
    lconst_0
    lstore 28
    lconst_0
    lstore 30
    lconst_0
    lstore 32
    lconst_0
    lstore 34
    lconst_0
    lstore 36
    lconst_0
    lstore 38
    lconst_0
    lstore 40
    lconst_0
    lstore 42
    lconst_0
    lstore 44
    lconst_0
    lstore 46
    lconst_0
    lstore 48
    lconst_0
    lstore 50
    lconst_0
    lstore 52
    lconst_0
    lstore 54
    lconst_0
    lstore 56
    lconst_0
    lstore 58
    lconst_0
    lstore 60
    lconst_0
    lstore 62
    iconst_0
    istore 84
    iconst_0
    istore 85
    iconst_0
    istore 86
    iconst_0
    istore 87
    iconst_0
    istore 88
    aconst_null
    astore 148
    aconst_null
    astore 149
    aconst_null
    astore 150
    aconst_null
    astore 151
    getstatic rung36_jcon_profsum/icn_arg_str_0 Ljava/lang/String;
    putstatic rung36_jcon_profsum/icn_pv_pad_s Ljava/lang/String;
    getstatic rung36_jcon_profsum/icn_arg_1 J
    putstatic rung36_jcon_profsum/icn_pv_pad_n J
    goto icn_232_α
;  VAR
icn_235_α:
    getstatic rung36_jcon_profsum/icn_pv_pad_s J
    goto icn_234_right_mid
icn_235_β:
    goto icn_233_ret_fail
;  VAR
icn_236_α:
    getstatic rung36_jcon_profsum/icn_pv_pad_n J
    goto icn_234_right_after
icn_236_β:
    goto icn_233_ret_fail
icn_234_α:
    goto icn_235_α
icn_234_β:
    goto icn_235_β
icn_234_right_mid:
    invokestatic java/lang/Long/toString(J)Ljava/lang/String;
    putstatic rung36_jcon_profsum/icn_234_right_s Ljava/lang/String;
    goto icn_236_α
icn_234_right_after:
    l2i
    istore 84
    getstatic rung36_jcon_profsum/icn_234_right_s Ljava/lang/String;
    iload 84
    ldc " "
    invokestatic rung36_jcon_profsum/icn_builtin_right(Ljava/lang/String;ILjava/lang/String;)Ljava/lang/String;
    goto icn_233_ret_store
icn_233_α:
    goto icn_234_α
icn_233_β:
    goto icn_pad_ret
icn_233_ret_fail:
    iconst_1
    putstatic rung36_jcon_profsum/icn_failed B
    goto icn_pad_done
icn_233_ret_store:
    putstatic rung36_jcon_profsum/icn_retval_str Ljava/lang/String;
    lconst_0
    putstatic rung36_jcon_profsum/icn_retval J
    iconst_0
    putstatic rung36_jcon_profsum/icn_failed B
    goto icn_pad_ret
;  VAR
icn_238_α:
    getstatic rung36_jcon_profsum/icn_pv_pad_s J
    goto icn_237_ret_store
icn_238_β:
    goto icn_237_ret_fail
icn_237_α:
    goto icn_238_α
icn_237_β:
    goto icn_pad_ret
icn_237_ret_fail:
    iconst_1
    putstatic rung36_jcon_profsum/icn_failed B
    goto icn_pad_done
icn_237_ret_store:
    putstatic rung36_jcon_profsum/icn_retval J
    iconst_0
    putstatic rung36_jcon_profsum/icn_failed B
    goto icn_pad_ret
;  VAR
icn_240_α:
    getstatic rung36_jcon_profsum/icn_pv_pad_n J
    goto icn_239_rrelay
icn_240_β:
    goto icn_239_lb
;  VAR
icn_242_α:
    getstatic rung36_jcon_profsum/icn_pv_pad_s J
    goto icn_241_relay
icn_242_β:
    goto icn_232_else
icn_241_α:
    goto icn_242_α
icn_241_β:
    goto icn_242_β
icn_241_relay:
    invokevirtual java/lang/String/length()I
    i2l
    goto icn_239_lrelay
icn_239_lrelay:
    putstatic rung36_jcon_profsum/icn_239_relop_lc J
    goto icn_239_lstore
icn_239_rrelay:
    putstatic rung36_jcon_profsum/icn_239_relop_rc J
    goto icn_239_check
icn_239_lb:
    goto icn_241_β
icn_239_α:
    goto icn_241_α
icn_239_β:
    goto icn_240_β
icn_239_lstore:
    goto icn_240_α
icn_239_check:
    getstatic rung36_jcon_profsum/icn_239_relop_lc J
    getstatic rung36_jcon_profsum/icn_239_relop_rc J
    lcmp
    ifge icn_240_β
    getstatic rung36_jcon_profsum/icn_239_relop_rc J
    goto icn_232_then
icn_232_then:
    pop2
    goto icn_233_α
icn_232_else:
    goto icn_237_α
icn_232_α:
    goto icn_239_α
icn_232_β:
    goto icn_239_β
icn_pad_done:
    iconst_0
    putstatic rung36_jcon_profsum/icn_suspended B
    iconst_0
    putstatic rung36_jcon_profsum/icn_suspend_id I
    iconst_1
    putstatic rung36_jcon_profsum/icn_failed B
    return
icn_pad_ret:
    iconst_0
    putstatic rung36_jcon_profsum/icn_failed B
    return
icn_pad_sret:
    return
.end method

; --- record method ---
.class public rung36_jcon_profsum$method
.super java/lang/Object

.method public <init>()V
    .limit stack 1
    .limit locals 1
    aload_0
    invokespecial java/lang/Object/<init>()V
    return
.end method

