; Auto-generated by icon_emit_jvm.c — Tiny-ICON Byrd Box JVM
.bytecode 45.0
.class public rung36_jcon_args
.super java/lang/Object

.field public static icn_failed B
.field public static icn_suspended B
.field public static icn_suspend_id I
.field public static icn_retval_obj Ljava/lang/Object;
.field public static icn_retval J
.field public static icn_retval_str Ljava/lang/String;
.field public static icn_arg_str_0 Ljava/lang/String;
.field public static icn_pv_note_a Ljava/lang/String;
.field public static icn_gvar_e Ljava/lang/String;
.field public static icn_pv_note_e Ljava/lang/String;
.field public static icn_pv_main_plist Ljava/util/ArrayList;
.field public static icn_pv_main_alist Ljava/util/ArrayList;
.field public static icn_1_relop_lc J
.field public static icn_1_relop_rc J
.field public static icn_8_pushval Ljava/lang/Object;
.field public static icn_8_pushlist Ljava/util/ArrayList;
.field public static icn_10_binop_lc J
.field public static icn_10_binop_rc J
.field public static icn_10_binop_bf I
.field public static icn_15_mklist Ljava/util/ArrayList;
.field public static icn_56_mklist Ljava/util/ArrayList;
.field public static icn_56_elem_0 Ljava/lang/Object;
.field public static icn_56_elem_1 Ljava/lang/Object;
.field public static icn_56_elem_2 Ljava/lang/Object;
.field public static icn_56_elem_3 Ljava/lang/Object;
.field public static icn_56_elem_4 Ljava/lang/Object;
.field public static icn_gvar_p0 J
.field public static icn_56_elem_5 Ljava/lang/Object;
.field public static icn_gvar_p1 J
.field public static icn_56_elem_6 Ljava/lang/Object;
.field public static icn_gvar_p2 J
.field public static icn_56_elem_7 Ljava/lang/Object;
.field public static icn_gvar_p3 J
.field public static icn_56_elem_8 Ljava/lang/Object;
.field public static icn_gvar_p4 J
.field public static icn_56_elem_9 Ljava/lang/Object;
.field public static icn_gvar_p5 J
.field public static icn_56_elem_10 Ljava/lang/Object;
.field public static icn_gvar_p6 J
.field public static icn_56_elem_11 Ljava/lang/Object;
.field public static icn_gvar_p7 J
.field public static icn_56_elem_12 Ljava/lang/Object;
.field public static icn_gvar_p8 J
.field public static icn_56_elem_13 Ljava/lang/Object;
.field public static icn_gvar_p9 J
.field public static icn_56_elem_14 Ljava/lang/Object;
.field public static icn_gvar_p10 J
.field public static icn_56_elem_15 Ljava/lang/Object;
.field public static icn_gvar_p11 J
.field public static icn_56_elem_16 Ljava/lang/Object;
.field public static icn_gvar_p12 J
.field public static icn_arg_0 J
.field public static icn_pv_p1_a Ljava/lang/String;
.field public static icn_arg_1 J
.field public static icn_pv_p2_b J
.field public static icn_arg_2 J
.field public static icn_pv_p2_a Ljava/lang/String;
.field public static icn_pv_p3_c J
.field public static icn_arg_3 J
.field public static icn_pv_p3_b J
.field public static icn_pv_p3_a Ljava/lang/String;
.field public static icn_pv_p4_d J
.field public static icn_arg_4 J
.field public static icn_pv_p4_c J
.field public static icn_pv_p4_b J
.field public static icn_pv_p4_a Ljava/lang/String;
.field public static icn_pv_p5_e J
.field public static icn_arg_str_5 Ljava/lang/String;
.field public static icn_arg_5 J
.field public static icn_pv_p5_d J
.field public static icn_pv_p5_c J
.field public static icn_pv_p5_b J
.field public static icn_pv_p5_a Ljava/lang/String;
.field public static icn_pv_p6_f Ljava/lang/String;
.field public static icn_arg_6 J
.field public static icn_pv_p6_e J
.field public static icn_pv_p6_d J
.field public static icn_pv_p6_c J
.field public static icn_pv_p6_b J
.field public static icn_pv_p6_a Ljava/lang/String;
.field public static icn_pv_p7_g J
.field public static icn_arg_7 J
.field public static icn_pv_p7_f Ljava/lang/String;
.field public static icn_pv_p7_e J
.field public static icn_pv_p7_d J
.field public static icn_pv_p7_c J
.field public static icn_pv_p7_b J
.field public static icn_pv_p7_a Ljava/lang/String;
.field public static icn_pv_p8_h J
.field public static icn_arg_8 J
.field public static icn_pv_p8_g J
.field public static icn_pv_p8_f Ljava/lang/String;
.field public static icn_pv_p8_e J
.field public static icn_pv_p8_d J
.field public static icn_pv_p8_c J
.field public static icn_pv_p8_b J
.field public static icn_pv_p8_a Ljava/lang/String;
.field public static icn_pv_p9_i J
.field public static icn_arg_9 J
.field public static icn_pv_p9_h J
.field public static icn_pv_p9_g J
.field public static icn_pv_p9_f Ljava/lang/String;
.field public static icn_pv_p9_e J
.field public static icn_pv_p9_d J
.field public static icn_pv_p9_c J
.field public static icn_pv_p9_b J
.field public static icn_pv_p9_a Ljava/lang/String;
.field public static icn_pv_p10_j J
.field public static icn_arg_10 J
.field public static icn_pv_p10_i J
.field public static icn_pv_p10_h J
.field public static icn_pv_p10_g J
.field public static icn_pv_p10_f Ljava/lang/String;
.field public static icn_pv_p10_e J
.field public static icn_pv_p10_d J
.field public static icn_pv_p10_c J
.field public static icn_pv_p10_b J
.field public static icn_pv_p10_a Ljava/lang/String;
.field public static icn_pv_p11_k J
.field public static icn_arg_11 J
.field public static icn_pv_p11_j J
.field public static icn_pv_p11_i J
.field public static icn_pv_p11_h J
.field public static icn_pv_p11_g J
.field public static icn_pv_p11_f Ljava/lang/String;
.field public static icn_pv_p11_e J
.field public static icn_pv_p11_d J
.field public static icn_pv_p11_c J
.field public static icn_pv_p11_b J
.field public static icn_pv_p11_a Ljava/lang/String;
.field public static icn_pv_p12_l J
.field public static icn_arg_12 J
.field public static icn_pv_p12_k J
.field public static icn_pv_p12_j J
.field public static icn_pv_p12_i J
.field public static icn_pv_p12_h J
.field public static icn_pv_p12_g J
.field public static icn_pv_p12_f Ljava/lang/String;
.field public static icn_pv_p12_e J
.field public static icn_pv_p12_d J
.field public static icn_pv_p12_c J
.field public static icn_pv_p12_b J
.field public static icn_pv_p12_a Ljava/lang/String;
.field public static icn_184_bang_str Ljava/lang/String;
.field public static icn_184_bang_pos I

.method public static main([Ljava/lang/String;)V
    .limit stack 4
    .limit locals 1
    invokestatic rung36_jcon_args/icn_main()V
    return
.end method

.method public static icn_builtin_left(Ljava/lang/String;ILjava/lang/String;)Ljava/lang/String;
    .limit stack 4
    .limit locals 5
    aload_0
    invokevirtual java/lang/String/length()I
    iload_1
    if_icmplt icn_left_pad
    aload_0
    iconst_0
    iload_1
    invokevirtual java/lang/String/substring(II)Ljava/lang/String;
    areturn
icn_left_pad:
    new java/lang/StringBuilder
    dup
    aload_0
    invokespecial java/lang/StringBuilder/<init>(Ljava/lang/String;)V
    astore_3
icn_left_loop:
    aload_3
    invokevirtual java/lang/StringBuilder/length()I
    iload_1
    if_icmpge icn_left_done
    aload_3
    aload_2
    iconst_0
    invokevirtual java/lang/String/charAt(I)C
    invokevirtual java/lang/StringBuilder/append(C)Ljava/lang/StringBuilder;
    pop
    goto icn_left_loop
icn_left_done:
    aload_3
    invokevirtual java/lang/StringBuilder/toString()Ljava/lang/String;
    areturn
.end method

.method public static icn_builtin_right(Ljava/lang/String;ILjava/lang/String;)Ljava/lang/String;
    .limit stack 4
    .limit locals 5
    aload_0
    invokevirtual java/lang/String/length()I
    iload_1
    if_icmplt icn_right_pad
    aload_0
    invokevirtual java/lang/String/length()I
    iload_1
    isub
    aload_0
    swap
    invokevirtual java/lang/String/substring(I)Ljava/lang/String;
    areturn
icn_right_pad:
    new java/lang/StringBuilder
    dup
    invokespecial java/lang/StringBuilder/<init>()V
    astore_3
    iload_1
    aload_0
    invokevirtual java/lang/String/length()I
    isub
    istore 4
    iconst_0
icn_right_loop:
    dup
    iload 4
    if_icmpge icn_right_append
    aload_3
    aload_2
    iconst_0
    invokevirtual java/lang/String/charAt(I)C
    invokevirtual java/lang/StringBuilder/append(C)Ljava/lang/StringBuilder;
    pop
    iconst_1
    iadd
    goto icn_right_loop
icn_right_append:
    pop
    aload_3
    aload_0
    invokevirtual java/lang/StringBuilder/append(Ljava/lang/String;)Ljava/lang/StringBuilder;
    pop
    aload_3
    invokevirtual java/lang/StringBuilder/toString()Ljava/lang/String;
    areturn
.end method

.method public static icn_builtin_center(Ljava/lang/String;ILjava/lang/String;)Ljava/lang/String;
    .limit stack 5
    .limit locals 7
    aload_0
    invokevirtual java/lang/String/length()I
    iload_1
    if_icmplt icn_ctr_pad
    aload_0
    iconst_0
    iload_1
    invokevirtual java/lang/String/substring(II)Ljava/lang/String;
    areturn
icn_ctr_pad:
    iload_1
    aload_0
    invokevirtual java/lang/String/length()I
    isub
    istore_3
    iload_3
    iconst_2
    idiv
    istore 4
    iload_3
    iload 4
    isub
    istore 5
    new java/lang/StringBuilder
    dup
    invokespecial java/lang/StringBuilder/<init>()V
    astore 6
    iconst_0
icn_ctr_lloop:
    dup
    iload 4
    if_icmpge icn_ctr_mid
    aload 6
    aload_2
    iconst_0
    invokevirtual java/lang/String/charAt(I)C
    invokevirtual java/lang/StringBuilder/append(C)Ljava/lang/StringBuilder;
    pop
    iconst_1
    iadd
    goto icn_ctr_lloop
icn_ctr_mid:
    pop
    aload 6
    aload_0
    invokevirtual java/lang/StringBuilder/append(Ljava/lang/String;)Ljava/lang/StringBuilder;
    pop
    iconst_0
icn_ctr_rloop:
    dup
    iload 5
    if_icmpge icn_ctr_done
    aload 6
    aload_2
    iconst_0
    invokevirtual java/lang/String/charAt(I)C
    invokevirtual java/lang/StringBuilder/append(C)Ljava/lang/StringBuilder;
    pop
    iconst_1
    iadd
    goto icn_ctr_rloop
icn_ctr_done:
    pop
    aload 6
    invokevirtual java/lang/StringBuilder/toString()Ljava/lang/String;
    areturn
.end method

.method public static icn_builtin_trim(Ljava/lang/String;Ljava/lang/String;)Ljava/lang/String;
    .limit stack 4
    .limit locals 3
    aload_0
    invokevirtual java/lang/String/length()I
    istore_2
icn_trim_loop:
    iload_2
    ifle icn_trim_done
    aload_1
    aload_0
    iload_2
    iconst_1
    isub
    invokevirtual java/lang/String/charAt(I)C
    invokevirtual java/lang/String/indexOf(I)I
    iflt icn_trim_done
    iinc 2 -1
    goto icn_trim_loop
icn_trim_done:
    aload_0
    iconst_0
    iload_2
    invokevirtual java/lang/String/substring(II)Ljava/lang/String;
    areturn
.end method

.method public static icn_builtin_map(Ljava/lang/String;Ljava/lang/String;Ljava/lang/String;)Ljava/lang/String;
    .limit stack 5
    .limit locals 7
    new java/lang/StringBuilder
    dup
    invokespecial java/lang/StringBuilder/<init>()V
    astore_3
    iconst_0
    istore 4
icn_map_loop:
    iload 4
    aload_0
    invokevirtual java/lang/String/length()I
    if_icmpge icn_map_done
    aload_0
    iload 4
    invokevirtual java/lang/String/charAt(I)C
    istore 5
    aload_1
    iload 5
    invokevirtual java/lang/String/indexOf(I)I
    istore 6
    iload 6
    iflt icn_map_notfound
    iload 6
    aload_2
    invokevirtual java/lang/String/length()I
    if_icmpge icn_map_notfound
    aload_3
    aload_2
    iload 6
    invokevirtual java/lang/String/charAt(I)C
    invokevirtual java/lang/StringBuilder/append(C)Ljava/lang/StringBuilder;
    pop
    goto icn_map_next
icn_map_notfound:
    aload_3
    iload 5
    invokevirtual java/lang/StringBuilder/append(C)Ljava/lang/StringBuilder;
    pop
icn_map_next:
    iinc 4 1
    goto icn_map_loop
icn_map_done:
    aload_3
    invokevirtual java/lang/StringBuilder/toString()Ljava/lang/String;
    areturn
.end method

.method public static icn_builtin_parse_long(Ljava/lang/String;)J
    .limit stack 4
    .limit locals 4
    .catch java/lang/Exception from icn_plong_L0 to icn_plong_L1 using icn_plong_catch
icn_plong_L0:
    aload_0
    invokevirtual java/lang/String/trim()Ljava/lang/String;
    astore_1
    aload_1
    ldc "r"
    invokevirtual java/lang/String/contains(Ljava/lang/CharSequence;)Z
    ifeq icn_plong_plain
    aload_1
    ldc "r"
    iconst_2
    invokevirtual java/lang/String/split(Ljava/lang/String;I)[Ljava/lang/String;
    astore_2
    aload_2
    iconst_0
    aaload
    invokestatic java/lang/Integer/parseInt(Ljava/lang/String;)I
    istore_3
    aload_2
    iconst_1
    aaload
    iload_3
    invokestatic java/lang/Long/parseLong(Ljava/lang/String;I)J
    goto icn_plong_L1
icn_plong_plain:
    aload_1
    invokestatic java/lang/Long/parseLong(Ljava/lang/String;)J
icn_plong_L1:
    lreturn
icn_plong_catch:
    pop
    ldc2_w -9223372036854775808
    lreturn
.end method

.method public static icn_builtin_numeric(Ljava/lang/String;)J
    .limit stack 2
    .limit locals 2
    aload_0
    invokestatic rung36_jcon_args/icn_builtin_parse_long(Ljava/lang/String;)J
    lreturn
.end method

.method public static icn_builtin_sort(Ljava/util/ArrayList;)Ljava/util/ArrayList;
    .limit stack 6
    .limit locals 8
    new java/util/ArrayList
    dup
    aload_0
    invokespecial java/util/ArrayList/<init>(Ljava/util/Collection;)V
    astore_1
    iconst_1
    istore_2
icn_sort_outer:
    aload_1
    invokevirtual java/util/ArrayList/size()I
    iload_2
    if_icmple icn_sort_done
    aload_1
    iload_2
    invokevirtual java/util/ArrayList/get(I)Ljava/lang/Object;
    checkcast java/lang/Long
    invokevirtual java/lang/Long/longValue()J
    lstore 4
    iload_2
    iconst_1
    isub
    istore_3
icn_sort_inner:
    iload_3
    iflt icn_sort_insert
    aload_1
    iload_3
    invokevirtual java/util/ArrayList/get(I)Ljava/lang/Object;
    checkcast java/lang/Long
    invokevirtual java/lang/Long/longValue()J
    lload 4
    lcmp
    ifle icn_sort_insert
    aload_1
    iload_3
    iconst_1
    iadd
    aload_1
    iload_3
    invokevirtual java/util/ArrayList/get(I)Ljava/lang/Object;
    invokevirtual java/util/ArrayList/set(ILjava/lang/Object;)Ljava/lang/Object;
    pop
    iinc 3 -1
    goto icn_sort_inner
icn_sort_insert:
    aload_1
    iload_3
    iconst_1
    iadd
    lload 4
    invokestatic java/lang/Long/valueOf(J)Ljava/lang/Long;
    invokevirtual java/util/ArrayList/set(ILjava/lang/Object;)Ljava/lang/Object;
    pop
    iinc 2 1
    goto icn_sort_outer
icn_sort_done:
    aload_1
    areturn
.end method

.method public static icn_builtin_sortf(Ljava/util/ArrayList;I)Ljava/util/ArrayList;
    .limit stack 8
    .limit locals 10
    new java/util/ArrayList
    dup
    aload_0
    invokespecial java/util/ArrayList/<init>(Ljava/util/Collection;)V
    astore_2
    iconst_1
    istore_3
icn_sortf_outer:
    aload_2
    invokevirtual java/util/ArrayList/size()I
    iload_3
    if_icmple icn_sortf_done
    aload_2
    iload_3
    invokevirtual java/util/ArrayList/get(I)Ljava/lang/Object;
    astore 5
    iload_3
    iconst_1
    isub
    istore 4
icn_sortf_inner:
    iload 4
    iflt icn_sortf_insert
    aload_2
    iload 4
    invokevirtual java/util/ArrayList/get(I)Ljava/lang/Object;
    astore 6
    aload 6
    invokevirtual java/lang/Object/getClass()Ljava/lang/Class;
    invokevirtual java/lang/Class/getDeclaredFields()[Ljava/lang/reflect/Field;
    iload_1
    iconst_1
    isub
    aaload
    aload 6
    invokevirtual java/lang/reflect/Field/get(Ljava/lang/Object;)Ljava/lang/Object;
    astore 7
    aload 5
    invokevirtual java/lang/Object/getClass()Ljava/lang/Class;
    invokevirtual java/lang/Class/getDeclaredFields()[Ljava/lang/reflect/Field;
    iload_1
    iconst_1
    isub
    aaload
    aload 5
    invokevirtual java/lang/reflect/Field/get(Ljava/lang/Object;)Ljava/lang/Object;
    astore 8
    aload 7
    checkcast java/lang/Long
    aload 8
    checkcast java/lang/Long
    invokevirtual java/lang/Long/compareTo(Ljava/lang/Long;)I
    ifle icn_sortf_insert
    aload_2
    iload 4
    iconst_1
    iadd
    aload_2
    iload 4
    invokevirtual java/util/ArrayList/get(I)Ljava/lang/Object;
    invokevirtual java/util/ArrayList/set(ILjava/lang/Object;)Ljava/lang/Object;
    pop
    iinc 4 -1
    goto icn_sortf_inner
icn_sortf_insert:
    aload_2
    iload 4
    iconst_1
    iadd
    aload 5
    invokevirtual java/util/ArrayList/set(ILjava/lang/Object;)Ljava/lang/Object;
    pop
    iinc 3 1
    goto icn_sortf_outer
icn_sortf_done:
    aload_2
    areturn
.end method

.method public static icn_main()V
    .limit stack 16
    .limit locals 252
    lconst_0
    lstore 0
    lconst_0
    lstore 2
    lconst_0
    lstore 4
    lconst_0
    lstore 6
    lconst_0
    lstore 8
    lconst_0
    lstore 10
    lconst_0
    lstore 12
    lconst_0
    lstore 14
    lconst_0
    lstore 16
    lconst_0
    lstore 18
    lconst_0
    lstore 20
    lconst_0
    lstore 22
    lconst_0
    lstore 24
    lconst_0
    lstore 26
    lconst_0
    lstore 28
    lconst_0
    lstore 30
    lconst_0
    lstore 32
    lconst_0
    lstore 34
    lconst_0
    lstore 36
    lconst_0
    lstore 38
    lconst_0
    lstore 40
    lconst_0
    lstore 42
    lconst_0
    lstore 44
    lconst_0
    lstore 46
    lconst_0
    lstore 48
    lconst_0
    lstore 50
    lconst_0
    lstore 52
    lconst_0
    lstore 54
    lconst_0
    lstore 56
    lconst_0
    lstore 58
    lconst_0
    lstore 60
    lconst_0
    lstore 62
    iconst_0
    istore 84
    iconst_0
    istore 85
    iconst_0
    istore 86
    iconst_0
    istore 87
    aconst_null
    astore 148
    aconst_null
    astore 149
    aconst_null
    astore 150
    aconst_null
    astore 151
    goto icn_55_α
;  INT
icn_2_α:
    ldc2_w 14
    goto icn_1_rrelay
icn_2_β:
    goto icn_1_lb
;  VAR
icn_4_α:
    getstatic rung36_jcon_args/icn_pv_main_alist Ljava/util/ArrayList;
    goto icn_3_relay
icn_4_β:
    goto icn_main_done
icn_3_α:
    goto icn_4_α
icn_3_β:
    goto icn_4_β
icn_3_relay:
    invokevirtual java/util/ArrayList/size()I
    i2l
    goto icn_1_lrelay
icn_1_lrelay:
    putstatic rung36_jcon_args/icn_1_relop_lc J
    goto icn_1_lstore
icn_1_rrelay:
    putstatic rung36_jcon_args/icn_1_relop_rc J
    goto icn_1_check
icn_1_lb:
    goto icn_3_β
icn_1_α:
    goto icn_3_α
icn_1_β:
    goto icn_2_β
icn_1_lstore:
    goto icn_2_α
icn_1_check:
    getstatic rung36_jcon_args/icn_1_relop_lc J
    getstatic rung36_jcon_args/icn_1_relop_rc J
    lcmp
    ifge icn_2_β
    getstatic rung36_jcon_args/icn_1_relop_rc J
    goto icn_0_condok
icn_0_condok:
    pop2
    goto icn_0_wbstart
icn_7_α:
    goto icn_0_wb_rf_0
icn_7_β:
    goto icn_0_wb_rf_0
icn_6_α:
    goto icn_7_α
icn_6_β:
    goto icn_7_β
    goto icn_6_wentry
icn_6_waft_0:
    lstore 4
    getstatic java/lang/System/out Ljava/io/PrintStream;
    lload 4
    invokevirtual java/io/PrintStream/print(J)V
    getstatic java/lang/System/out Ljava/io/PrintStream;
    ldc ""
    invokevirtual java/io/PrintStream/println(Ljava/lang/String;)V
    lload 4
    goto icn_5_gdrain
icn_6_wentry:
    goto icn_7_α
icn_5_gdrain:
    pop2
icn_5_pump:
    goto icn_6_β
icn_5_α:
    goto icn_6_α
icn_5_β:
    goto icn_0_wb_rf_0
;  VAR
icn_9_α:
    getstatic rung36_jcon_args/icn_pv_main_alist Ljava/util/ArrayList;
    goto icn_8_lr
icn_9_β:
    goto icn_0_top
;  INT
icn_11_α:
    ldc2_w 1
    goto icn_10_rrelay
icn_11_β:
    goto icn_10_lb
;  VAR
icn_13_α:
    getstatic rung36_jcon_args/icn_pv_main_alist Ljava/util/ArrayList;
    goto icn_12_relay
icn_13_β:
    goto icn_0_top
icn_12_α:
    goto icn_13_α
icn_12_β:
    goto icn_13_β
icn_12_relay:
    invokevirtual java/util/ArrayList/size()I
    i2l
    goto icn_10_lrelay
icn_10_lrelay:
    putstatic rung36_jcon_args/icn_10_binop_lc J
    goto icn_10_lstore
icn_10_rrelay:
    putstatic rung36_jcon_args/icn_10_binop_rc J
    goto icn_10_compute
icn_10_lb:
    goto icn_12_β
icn_10_α:
    iconst_0
    putstatic rung36_jcon_args/icn_10_binop_bf I
    goto icn_12_α
icn_10_β:
    goto icn_11_β
icn_10_lstore:
    getstatic rung36_jcon_args/icn_10_binop_bf I
    ifeq icn_11_α
    goto icn_11_β
icn_10_compute:
    getstatic rung36_jcon_args/icn_10_binop_lc J
    getstatic rung36_jcon_args/icn_10_binop_rc J
    ladd
    goto icn_8_vr
icn_8_α:
    goto icn_9_α
icn_8_β:
    goto icn_0_top
icn_8_lr:
    putstatic rung36_jcon_args/icn_8_pushlist Ljava/util/ArrayList;
    goto icn_10_α
icn_8_vr:
    invokestatic java/lang/Long/valueOf(J)Ljava/lang/Long;
    putstatic rung36_jcon_args/icn_8_pushval Ljava/lang/Object;
    getstatic rung36_jcon_args/icn_8_pushlist Ljava/util/ArrayList;
    getstatic rung36_jcon_args/icn_8_pushval Ljava/lang/Object;
    invokevirtual java/util/ArrayList/add(Ljava/lang/Object;)Z
    pop
    getstatic rung36_jcon_args/icn_8_pushlist Ljava/util/ArrayList;
    goto icn_0_wbdrain
    goto icn_0_wbstart
icn_0_wb_rg_0:
    pop2
    goto icn_8_α
icn_0_wb_rf_0:
    goto icn_8_α
icn_0_wbstart:
    goto icn_5_α
icn_0_wbdrain:
    pop2
icn_0_top:
    goto icn_1_α
icn_0_α:
    goto icn_1_α
icn_0_β:
    goto icn_main_done
icn_15_α:
    new java/util/ArrayList
    dup
    invokespecial java/util/ArrayList/<init>()V
    putstatic rung36_jcon_args/icn_15_mklist Ljava/util/ArrayList;
    getstatic rung36_jcon_args/icn_15_mklist Ljava/util/ArrayList;
    goto icn_14_store
icn_15_β:
    goto icn_0_α
icn_14_α:
    goto icn_15_α
icn_14_β:
    goto icn_15_β
icn_14_store:
    putstatic rung36_jcon_args/icn_pv_main_alist Ljava/util/ArrayList;
    getstatic rung36_jcon_args/icn_pv_main_alist Ljava/util/ArrayList;
    goto icn_main_s15_sdrain
icn_main_s15_sdrain:
    pop
    goto icn_0_α
icn_18_α:
    goto icn_14_α
icn_18_β:
    goto icn_14_α
icn_17_α:
    goto icn_18_α
icn_17_β:
    goto icn_18_β
    goto icn_17_wentry
icn_17_waft_0:
    lstore 6
    getstatic java/lang/System/out Ljava/io/PrintStream;
    lload 6
    invokevirtual java/io/PrintStream/print(J)V
    getstatic java/lang/System/out Ljava/io/PrintStream;
    ldc ""
    invokevirtual java/io/PrintStream/println(Ljava/lang/String;)V
    lload 6
    goto icn_16_gdrain
icn_17_wentry:
    goto icn_18_α
icn_16_gdrain:
    pop2
icn_16_pump:
    goto icn_17_β
icn_16_α:
    goto icn_17_α
icn_16_β:
    goto icn_14_α
icn_21_α:
    goto icn_16_α
icn_21_β:
    goto icn_16_α
icn_20_α:
    goto icn_21_α
icn_20_β:
    goto icn_21_β
    goto icn_20_wentry
icn_20_waft_0:
    lstore 8
    getstatic java/lang/System/out Ljava/io/PrintStream;
    lload 8
    invokevirtual java/io/PrintStream/print(J)V
    getstatic java/lang/System/out Ljava/io/PrintStream;
    ldc ""
    invokevirtual java/io/PrintStream/println(Ljava/lang/String;)V
    lload 8
    goto icn_19_gdrain
icn_20_wentry:
    goto icn_21_α
icn_19_gdrain:
    pop2
icn_19_pump:
    goto icn_20_β
icn_19_α:
    goto icn_20_α
icn_19_β:
    goto icn_16_α
icn_24_α:
    goto icn_19_α
icn_24_β:
    goto icn_19_α
icn_23_α:
    goto icn_24_α
icn_23_β:
    goto icn_24_β
    goto icn_23_wentry
icn_23_waft_0:
    lstore 10
    getstatic java/lang/System/out Ljava/io/PrintStream;
    lload 10
    invokevirtual java/io/PrintStream/print(J)V
    getstatic java/lang/System/out Ljava/io/PrintStream;
    ldc ""
    invokevirtual java/io/PrintStream/println(Ljava/lang/String;)V
    lload 10
    goto icn_22_gdrain
icn_23_wentry:
    goto icn_24_α
icn_22_gdrain:
    pop2
icn_22_pump:
    goto icn_23_β
icn_22_α:
    goto icn_23_α
icn_22_β:
    goto icn_19_α
icn_27_α:
    goto icn_22_α
icn_27_β:
    goto icn_22_α
icn_26_α:
    goto icn_27_α
icn_26_β:
    goto icn_27_β
    goto icn_26_wentry
icn_26_waft_0:
    lstore 12
    getstatic java/lang/System/out Ljava/io/PrintStream;
    lload 12
    invokevirtual java/io/PrintStream/print(J)V
    getstatic java/lang/System/out Ljava/io/PrintStream;
    ldc ""
    invokevirtual java/io/PrintStream/println(Ljava/lang/String;)V
    lload 12
    goto icn_25_gdrain
icn_26_wentry:
    goto icn_27_α
icn_25_gdrain:
    pop2
icn_25_pump:
    goto icn_26_β
icn_25_α:
    goto icn_26_α
icn_25_β:
    goto icn_22_α
icn_30_α:
    goto icn_25_α
icn_30_β:
    goto icn_25_α
icn_29_α:
    goto icn_30_α
icn_29_β:
    goto icn_30_β
    goto icn_29_wentry
icn_29_waft_0:
    lstore 14
    getstatic java/lang/System/out Ljava/io/PrintStream;
    lload 14
    invokevirtual java/io/PrintStream/print(J)V
    getstatic java/lang/System/out Ljava/io/PrintStream;
    ldc ""
    invokevirtual java/io/PrintStream/println(Ljava/lang/String;)V
    lload 14
    goto icn_28_gdrain
icn_29_wentry:
    goto icn_30_α
icn_28_gdrain:
    pop2
icn_28_pump:
    goto icn_29_β
icn_28_α:
    goto icn_29_α
icn_28_β:
    goto icn_25_α
icn_33_α:
    goto icn_28_α
icn_33_β:
    goto icn_28_α
icn_32_α:
    goto icn_33_α
icn_32_β:
    goto icn_33_β
    goto icn_32_wentry
icn_32_waft_0:
    lstore 16
    getstatic java/lang/System/out Ljava/io/PrintStream;
    lload 16
    invokevirtual java/io/PrintStream/print(J)V
    getstatic java/lang/System/out Ljava/io/PrintStream;
    ldc ""
    invokevirtual java/io/PrintStream/println(Ljava/lang/String;)V
    lload 16
    goto icn_31_gdrain
icn_32_wentry:
    goto icn_33_α
icn_31_gdrain:
    pop2
icn_31_pump:
    goto icn_32_β
icn_31_α:
    goto icn_32_α
icn_31_β:
    goto icn_28_α
icn_36_α:
    goto icn_31_α
icn_36_β:
    goto icn_31_α
icn_35_α:
    goto icn_36_α
icn_35_β:
    goto icn_36_β
    goto icn_35_wentry
icn_35_waft_0:
    lstore 18
    getstatic java/lang/System/out Ljava/io/PrintStream;
    lload 18
    invokevirtual java/io/PrintStream/print(J)V
    getstatic java/lang/System/out Ljava/io/PrintStream;
    ldc ""
    invokevirtual java/io/PrintStream/println(Ljava/lang/String;)V
    lload 18
    goto icn_34_gdrain
icn_35_wentry:
    goto icn_36_α
icn_34_gdrain:
    pop2
icn_34_pump:
    goto icn_35_β
icn_34_α:
    goto icn_35_α
icn_34_β:
    goto icn_31_α
icn_39_α:
    goto icn_34_α
icn_39_β:
    goto icn_34_α
icn_38_α:
    goto icn_39_α
icn_38_β:
    goto icn_39_β
    goto icn_38_wentry
icn_38_waft_0:
    lstore 20
    getstatic java/lang/System/out Ljava/io/PrintStream;
    lload 20
    invokevirtual java/io/PrintStream/print(J)V
    getstatic java/lang/System/out Ljava/io/PrintStream;
    ldc ""
    invokevirtual java/io/PrintStream/println(Ljava/lang/String;)V
    lload 20
    goto icn_37_gdrain
icn_38_wentry:
    goto icn_39_α
icn_37_gdrain:
    pop2
icn_37_pump:
    goto icn_38_β
icn_37_α:
    goto icn_38_α
icn_37_β:
    goto icn_34_α
icn_42_α:
    goto icn_37_α
icn_42_β:
    goto icn_37_α
icn_41_α:
    goto icn_42_α
icn_41_β:
    goto icn_42_β
    goto icn_41_wentry
icn_41_waft_0:
    lstore 22
    getstatic java/lang/System/out Ljava/io/PrintStream;
    lload 22
    invokevirtual java/io/PrintStream/print(J)V
    getstatic java/lang/System/out Ljava/io/PrintStream;
    ldc ""
    invokevirtual java/io/PrintStream/println(Ljava/lang/String;)V
    lload 22
    goto icn_40_gdrain
icn_41_wentry:
    goto icn_42_α
icn_40_gdrain:
    pop2
icn_40_pump:
    goto icn_41_β
icn_40_α:
    goto icn_41_α
icn_40_β:
    goto icn_37_α
icn_45_α:
    goto icn_40_α
icn_45_β:
    goto icn_40_α
icn_44_α:
    goto icn_45_α
icn_44_β:
    goto icn_45_β
    goto icn_44_wentry
icn_44_waft_0:
    lstore 24
    getstatic java/lang/System/out Ljava/io/PrintStream;
    lload 24
    invokevirtual java/io/PrintStream/print(J)V
    getstatic java/lang/System/out Ljava/io/PrintStream;
    ldc ""
    invokevirtual java/io/PrintStream/println(Ljava/lang/String;)V
    lload 24
    goto icn_43_gdrain
icn_44_wentry:
    goto icn_45_α
icn_43_gdrain:
    pop2
icn_43_pump:
    goto icn_44_β
icn_43_α:
    goto icn_44_α
icn_43_β:
    goto icn_40_α
icn_48_α:
    goto icn_43_α
icn_48_β:
    goto icn_43_α
icn_47_α:
    goto icn_48_α
icn_47_β:
    goto icn_48_β
    goto icn_47_wentry
icn_47_waft_0:
    lstore 26
    getstatic java/lang/System/out Ljava/io/PrintStream;
    lload 26
    invokevirtual java/io/PrintStream/print(J)V
    getstatic java/lang/System/out Ljava/io/PrintStream;
    ldc ""
    invokevirtual java/io/PrintStream/println(Ljava/lang/String;)V
    lload 26
    goto icn_46_gdrain
icn_47_wentry:
    goto icn_48_α
icn_46_gdrain:
    pop2
icn_46_pump:
    goto icn_47_β
icn_46_α:
    goto icn_47_α
icn_46_β:
    goto icn_43_α
icn_51_α:
    goto icn_46_α
icn_51_β:
    goto icn_46_α
icn_50_α:
    goto icn_51_α
icn_50_β:
    goto icn_51_β
    goto icn_50_wentry
icn_50_waft_0:
    lstore 28
    getstatic java/lang/System/out Ljava/io/PrintStream;
    lload 28
    invokevirtual java/io/PrintStream/print(J)V
    getstatic java/lang/System/out Ljava/io/PrintStream;
    ldc ""
    invokevirtual java/io/PrintStream/println(Ljava/lang/String;)V
    lload 28
    goto icn_49_gdrain
icn_50_wentry:
    goto icn_51_α
icn_49_gdrain:
    pop2
icn_49_pump:
    goto icn_50_β
icn_49_α:
    goto icn_50_α
icn_49_β:
    goto icn_46_α
icn_54_α:
    goto icn_49_α
icn_54_β:
    goto icn_49_α
icn_53_α:
    goto icn_54_α
icn_53_β:
    goto icn_54_β
    goto icn_53_wentry
icn_53_waft_0:
    lstore 30
    getstatic java/lang/System/out Ljava/io/PrintStream;
    lload 30
    invokevirtual java/io/PrintStream/print(J)V
    getstatic java/lang/System/out Ljava/io/PrintStream;
    ldc ""
    invokevirtual java/io/PrintStream/println(Ljava/lang/String;)V
    lload 30
    goto icn_52_gdrain
icn_53_wentry:
    goto icn_54_α
icn_52_gdrain:
    pop2
icn_52_pump:
    goto icn_53_β
icn_52_α:
    goto icn_53_α
icn_52_β:
    goto icn_49_α
icn_56_α:
    new java/util/ArrayList
    dup
    invokespecial java/util/ArrayList/<init>()V
    putstatic rung36_jcon_args/icn_56_mklist Ljava/util/ArrayList;
;  INT
icn_57_α:
    ldc2_w 3
    goto icn_56_mke_0
icn_57_β:
    goto icn_52_α
    goto icn_57_α
icn_56_mke_0:
    invokestatic java/lang/Long/valueOf(J)Ljava/lang/Long;
    putstatic rung36_jcon_args/icn_56_elem_0 Ljava/lang/Object;
    getstatic rung36_jcon_args/icn_56_mklist Ljava/util/ArrayList;
    getstatic rung36_jcon_args/icn_56_elem_0 Ljava/lang/Object;
    invokevirtual java/util/ArrayList/add(Ljava/lang/Object;)Z
    pop
;  INT
icn_59_α:
    ldc2_w 2
    goto icn_58_neg
icn_59_β:
    goto icn_52_α
;  NEG
icn_58_α:
    goto icn_59_α
icn_58_β:
    goto icn_59_β
icn_58_neg:
    lneg
    goto icn_56_mke_1
    goto icn_58_α
icn_56_mke_1:
    invokestatic java/lang/Long/valueOf(J)Ljava/lang/Long;
    putstatic rung36_jcon_args/icn_56_elem_1 Ljava/lang/Object;
    getstatic rung36_jcon_args/icn_56_mklist Ljava/util/ArrayList;
    getstatic rung36_jcon_args/icn_56_elem_1 Ljava/lang/Object;
    invokevirtual java/util/ArrayList/add(Ljava/lang/Object;)Z
    pop
;  STR
icn_60_α:
    ldc "image"
    goto icn_56_mke_2
icn_60_β:
    goto icn_52_α
    goto icn_60_α
icn_56_mke_2:
    putstatic rung36_jcon_args/icn_56_elem_2 Ljava/lang/Object;
    getstatic rung36_jcon_args/icn_56_mklist Ljava/util/ArrayList;
    getstatic rung36_jcon_args/icn_56_elem_2 Ljava/lang/Object;
    invokevirtual java/util/ArrayList/add(Ljava/lang/Object;)Z
    pop
icn_61_α:
    goto icn_52_α
icn_61_β:
    goto icn_52_α
    goto icn_61_α
icn_56_mke_3:
    invokestatic java/lang/Long/valueOf(J)Ljava/lang/Long;
    putstatic rung36_jcon_args/icn_56_elem_3 Ljava/lang/Object;
    getstatic rung36_jcon_args/icn_56_mklist Ljava/util/ArrayList;
    getstatic rung36_jcon_args/icn_56_elem_3 Ljava/lang/Object;
    invokevirtual java/util/ArrayList/add(Ljava/lang/Object;)Z
    pop
;  VAR
icn_62_α:
    getstatic rung36_jcon_args/icn_gvar_p0 J
    goto icn_56_mke_4
icn_62_β:
    goto icn_52_α
    goto icn_62_α
icn_56_mke_4:
    invokestatic java/lang/Long/valueOf(J)Ljava/lang/Long;
    putstatic rung36_jcon_args/icn_56_elem_4 Ljava/lang/Object;
    getstatic rung36_jcon_args/icn_56_mklist Ljava/util/ArrayList;
    getstatic rung36_jcon_args/icn_56_elem_4 Ljava/lang/Object;
    invokevirtual java/util/ArrayList/add(Ljava/lang/Object;)Z
    pop
;  VAR
icn_63_α:
    getstatic rung36_jcon_args/icn_gvar_p1 J
    goto icn_56_mke_5
icn_63_β:
    goto icn_52_α
    goto icn_63_α
icn_56_mke_5:
    invokestatic java/lang/Long/valueOf(J)Ljava/lang/Long;
    putstatic rung36_jcon_args/icn_56_elem_5 Ljava/lang/Object;
    getstatic rung36_jcon_args/icn_56_mklist Ljava/util/ArrayList;
    getstatic rung36_jcon_args/icn_56_elem_5 Ljava/lang/Object;
    invokevirtual java/util/ArrayList/add(Ljava/lang/Object;)Z
    pop
;  VAR
icn_64_α:
    getstatic rung36_jcon_args/icn_gvar_p2 J
    goto icn_56_mke_6
icn_64_β:
    goto icn_52_α
    goto icn_64_α
icn_56_mke_6:
    invokestatic java/lang/Long/valueOf(J)Ljava/lang/Long;
    putstatic rung36_jcon_args/icn_56_elem_6 Ljava/lang/Object;
    getstatic rung36_jcon_args/icn_56_mklist Ljava/util/ArrayList;
    getstatic rung36_jcon_args/icn_56_elem_6 Ljava/lang/Object;
    invokevirtual java/util/ArrayList/add(Ljava/lang/Object;)Z
    pop
;  VAR
icn_65_α:
    getstatic rung36_jcon_args/icn_gvar_p3 J
    goto icn_56_mke_7
icn_65_β:
    goto icn_52_α
    goto icn_65_α
icn_56_mke_7:
    invokestatic java/lang/Long/valueOf(J)Ljava/lang/Long;
    putstatic rung36_jcon_args/icn_56_elem_7 Ljava/lang/Object;
    getstatic rung36_jcon_args/icn_56_mklist Ljava/util/ArrayList;
    getstatic rung36_jcon_args/icn_56_elem_7 Ljava/lang/Object;
    invokevirtual java/util/ArrayList/add(Ljava/lang/Object;)Z
    pop
;  VAR
icn_66_α:
    getstatic rung36_jcon_args/icn_gvar_p4 J
    goto icn_56_mke_8
icn_66_β:
    goto icn_52_α
    goto icn_66_α
icn_56_mke_8:
    invokestatic java/lang/Long/valueOf(J)Ljava/lang/Long;
    putstatic rung36_jcon_args/icn_56_elem_8 Ljava/lang/Object;
    getstatic rung36_jcon_args/icn_56_mklist Ljava/util/ArrayList;
    getstatic rung36_jcon_args/icn_56_elem_8 Ljava/lang/Object;
    invokevirtual java/util/ArrayList/add(Ljava/lang/Object;)Z
    pop
;  VAR
icn_67_α:
    getstatic rung36_jcon_args/icn_gvar_p5 J
    goto icn_56_mke_9
icn_67_β:
    goto icn_52_α
    goto icn_67_α
icn_56_mke_9:
    invokestatic java/lang/Long/valueOf(J)Ljava/lang/Long;
    putstatic rung36_jcon_args/icn_56_elem_9 Ljava/lang/Object;
    getstatic rung36_jcon_args/icn_56_mklist Ljava/util/ArrayList;
    getstatic rung36_jcon_args/icn_56_elem_9 Ljava/lang/Object;
    invokevirtual java/util/ArrayList/add(Ljava/lang/Object;)Z
    pop
;  VAR
icn_68_α:
    getstatic rung36_jcon_args/icn_gvar_p6 J
    goto icn_56_mke_10
icn_68_β:
    goto icn_52_α
    goto icn_68_α
icn_56_mke_10:
    invokestatic java/lang/Long/valueOf(J)Ljava/lang/Long;
    putstatic rung36_jcon_args/icn_56_elem_10 Ljava/lang/Object;
    getstatic rung36_jcon_args/icn_56_mklist Ljava/util/ArrayList;
    getstatic rung36_jcon_args/icn_56_elem_10 Ljava/lang/Object;
    invokevirtual java/util/ArrayList/add(Ljava/lang/Object;)Z
    pop
;  VAR
icn_69_α:
    getstatic rung36_jcon_args/icn_gvar_p7 J
    goto icn_56_mke_11
icn_69_β:
    goto icn_52_α
    goto icn_69_α
icn_56_mke_11:
    invokestatic java/lang/Long/valueOf(J)Ljava/lang/Long;
    putstatic rung36_jcon_args/icn_56_elem_11 Ljava/lang/Object;
    getstatic rung36_jcon_args/icn_56_mklist Ljava/util/ArrayList;
    getstatic rung36_jcon_args/icn_56_elem_11 Ljava/lang/Object;
    invokevirtual java/util/ArrayList/add(Ljava/lang/Object;)Z
    pop
;  VAR
icn_70_α:
    getstatic rung36_jcon_args/icn_gvar_p8 J
    goto icn_56_mke_12
icn_70_β:
    goto icn_52_α
    goto icn_70_α
icn_56_mke_12:
    invokestatic java/lang/Long/valueOf(J)Ljava/lang/Long;
    putstatic rung36_jcon_args/icn_56_elem_12 Ljava/lang/Object;
    getstatic rung36_jcon_args/icn_56_mklist Ljava/util/ArrayList;
    getstatic rung36_jcon_args/icn_56_elem_12 Ljava/lang/Object;
    invokevirtual java/util/ArrayList/add(Ljava/lang/Object;)Z
    pop
;  VAR
icn_71_α:
    getstatic rung36_jcon_args/icn_gvar_p9 J
    goto icn_56_mke_13
icn_71_β:
    goto icn_52_α
    goto icn_71_α
icn_56_mke_13:
    invokestatic java/lang/Long/valueOf(J)Ljava/lang/Long;
    putstatic rung36_jcon_args/icn_56_elem_13 Ljava/lang/Object;
    getstatic rung36_jcon_args/icn_56_mklist Ljava/util/ArrayList;
    getstatic rung36_jcon_args/icn_56_elem_13 Ljava/lang/Object;
    invokevirtual java/util/ArrayList/add(Ljava/lang/Object;)Z
    pop
;  VAR
icn_72_α:
    getstatic rung36_jcon_args/icn_gvar_p10 J
    goto icn_56_mke_14
icn_72_β:
    goto icn_52_α
    goto icn_72_α
icn_56_mke_14:
    invokestatic java/lang/Long/valueOf(J)Ljava/lang/Long;
    putstatic rung36_jcon_args/icn_56_elem_14 Ljava/lang/Object;
    getstatic rung36_jcon_args/icn_56_mklist Ljava/util/ArrayList;
    getstatic rung36_jcon_args/icn_56_elem_14 Ljava/lang/Object;
    invokevirtual java/util/ArrayList/add(Ljava/lang/Object;)Z
    pop
;  VAR
icn_73_α:
    getstatic rung36_jcon_args/icn_gvar_p11 J
    goto icn_56_mke_15
icn_73_β:
    goto icn_52_α
    goto icn_73_α
icn_56_mke_15:
    invokestatic java/lang/Long/valueOf(J)Ljava/lang/Long;
    putstatic rung36_jcon_args/icn_56_elem_15 Ljava/lang/Object;
    getstatic rung36_jcon_args/icn_56_mklist Ljava/util/ArrayList;
    getstatic rung36_jcon_args/icn_56_elem_15 Ljava/lang/Object;
    invokevirtual java/util/ArrayList/add(Ljava/lang/Object;)Z
    pop
;  VAR
icn_74_α:
    getstatic rung36_jcon_args/icn_gvar_p12 J
    goto icn_56_mke_16
icn_74_β:
    goto icn_52_α
    goto icn_74_α
icn_56_mke_16:
    invokestatic java/lang/Long/valueOf(J)Ljava/lang/Long;
    putstatic rung36_jcon_args/icn_56_elem_16 Ljava/lang/Object;
    getstatic rung36_jcon_args/icn_56_mklist Ljava/util/ArrayList;
    getstatic rung36_jcon_args/icn_56_elem_16 Ljava/lang/Object;
    invokevirtual java/util/ArrayList/add(Ljava/lang/Object;)Z
    pop
    getstatic rung36_jcon_args/icn_56_mklist Ljava/util/ArrayList;
    goto icn_55_store
icn_56_β:
    goto icn_52_α
icn_55_α:
    goto icn_56_α
icn_55_β:
    goto icn_56_β
icn_55_store:
    putstatic rung36_jcon_args/icn_pv_main_plist Ljava/util/ArrayList;
    getstatic rung36_jcon_args/icn_pv_main_plist Ljava/util/ArrayList;
    goto icn_main_s1_sdrain
icn_main_s1_sdrain:
    pop
    goto icn_52_α
icn_main_done:
    return
.end method

.method public static icn_p0()V
    .limit stack 16
    .limit locals 254
    lconst_0
    lstore 0
    lconst_0
    lstore 2
    lconst_0
    lstore 4
    lconst_0
    lstore 6
    lconst_0
    lstore 8
    lconst_0
    lstore 10
    lconst_0
    lstore 12
    lconst_0
    lstore 14
    lconst_0
    lstore 16
    lconst_0
    lstore 18
    lconst_0
    lstore 20
    lconst_0
    lstore 22
    lconst_0
    lstore 24
    lconst_0
    lstore 26
    lconst_0
    lstore 28
    lconst_0
    lstore 30
    lconst_0
    lstore 32
    lconst_0
    lstore 34
    lconst_0
    lstore 36
    lconst_0
    lstore 38
    lconst_0
    lstore 40
    lconst_0
    lstore 42
    lconst_0
    lstore 44
    lconst_0
    lstore 46
    lconst_0
    lstore 48
    lconst_0
    lstore 50
    lconst_0
    lstore 52
    lconst_0
    lstore 54
    lconst_0
    lstore 56
    lconst_0
    lstore 58
    lconst_0
    lstore 60
    lconst_0
    lstore 62
    iconst_0
    istore 84
    iconst_0
    istore 85
    iconst_0
    istore 86
    iconst_0
    istore 87
    aconst_null
    astore 148
    aconst_null
    astore 149
    aconst_null
    astore 150
    aconst_null
    astore 151
    goto icn_75_α
;  STR
icn_76_α:
    ldc "p0"
    goto icn_75_arg0
icn_76_β:
    goto icn_p0_done
icn_75_arg0:
    putstatic rung36_jcon_args/icn_arg_str_0 Ljava/lang/String;
    lconst_0
    putstatic rung36_jcon_args/icn_arg_0 J
    goto icn_75_docall
icn_75_α:
    goto icn_76_α
icn_75_β:
    goto icn_76_β
icn_75_docall:
    getstatic rung36_jcon_args/icn_1_relop_lc J
    lstore 152
    getstatic rung36_jcon_args/icn_1_relop_rc J
    lstore 154
    getstatic rung36_jcon_args/icn_10_binop_lc J
    lstore 156
    getstatic rung36_jcon_args/icn_10_binop_rc J
    lstore 158
    invokestatic rung36_jcon_args/icn_note()V
    lload 152
    putstatic rung36_jcon_args/icn_1_relop_lc J
    lload 154
    putstatic rung36_jcon_args/icn_1_relop_rc J
    lload 156
    putstatic rung36_jcon_args/icn_10_binop_lc J
    lload 158
    putstatic rung36_jcon_args/icn_10_binop_rc J
    getstatic rung36_jcon_args/icn_failed B
    ifne icn_75_after_call
    getstatic rung36_jcon_args/icn_retval J
    goto icn_p0_s0_sdrain
icn_75_after_call:
    goto icn_p0_done
icn_p0_s0_sdrain:
    pop2
    goto icn_p0_done
icn_p0_done:
    iconst_0
    putstatic rung36_jcon_args/icn_suspended B
    iconst_0
    putstatic rung36_jcon_args/icn_suspend_id I
    iconst_1
    putstatic rung36_jcon_args/icn_failed B
    return
icn_p0_ret:
    iconst_0
    putstatic rung36_jcon_args/icn_failed B
    return
icn_p0_sret:
    return
.end method

.method public static icn_p1()V
    .limit stack 16
    .limit locals 258
    lconst_0
    lstore 0
    lconst_0
    lstore 2
    lconst_0
    lstore 4
    lconst_0
    lstore 6
    lconst_0
    lstore 8
    lconst_0
    lstore 10
    lconst_0
    lstore 12
    lconst_0
    lstore 14
    lconst_0
    lstore 16
    lconst_0
    lstore 18
    lconst_0
    lstore 20
    lconst_0
    lstore 22
    lconst_0
    lstore 24
    lconst_0
    lstore 26
    lconst_0
    lstore 28
    lconst_0
    lstore 30
    lconst_0
    lstore 32
    lconst_0
    lstore 34
    lconst_0
    lstore 36
    lconst_0
    lstore 38
    lconst_0
    lstore 40
    lconst_0
    lstore 42
    lconst_0
    lstore 44
    lconst_0
    lstore 46
    lconst_0
    lstore 48
    lconst_0
    lstore 50
    lconst_0
    lstore 52
    lconst_0
    lstore 54
    lconst_0
    lstore 56
    lconst_0
    lstore 58
    lconst_0
    lstore 60
    lconst_0
    lstore 62
    iconst_0
    istore 84
    iconst_0
    istore 85
    iconst_0
    istore 86
    iconst_0
    istore 87
    aconst_null
    astore 148
    aconst_null
    astore 149
    aconst_null
    astore 150
    aconst_null
    astore 151
    getstatic rung36_jcon_args/icn_arg_str_0 Ljava/lang/String;
    putstatic rung36_jcon_args/icn_pv_p1_a Ljava/lang/String;
    goto icn_77_α
;  VAR
icn_78_α:
    getstatic rung36_jcon_args/icn_pv_p1_a J
    goto icn_77_arg1
icn_78_β:
    goto icn_p1_done
icn_77_arg1:
    putstatic rung36_jcon_args/icn_arg_1 J
    goto icn_77_docall
;  STR
icn_79_α:
    ldc "p1"
    goto icn_77_arg0
icn_79_β:
    goto icn_p1_done
icn_77_arg0:
    putstatic rung36_jcon_args/icn_arg_str_0 Ljava/lang/String;
    lconst_0
    putstatic rung36_jcon_args/icn_arg_0 J
    goto icn_78_α
icn_77_α:
    goto icn_79_α
icn_77_β:
    goto icn_78_β
icn_77_docall:
    getstatic rung36_jcon_args/icn_1_relop_lc J
    lstore 152
    getstatic rung36_jcon_args/icn_1_relop_rc J
    lstore 154
    getstatic rung36_jcon_args/icn_10_binop_lc J
    lstore 156
    getstatic rung36_jcon_args/icn_10_binop_rc J
    lstore 158
    getstatic rung36_jcon_args/icn_pv_p1_a J
    lstore 160
    invokestatic rung36_jcon_args/icn_note()V
    lload 152
    putstatic rung36_jcon_args/icn_1_relop_lc J
    lload 154
    putstatic rung36_jcon_args/icn_1_relop_rc J
    lload 156
    putstatic rung36_jcon_args/icn_10_binop_lc J
    lload 158
    putstatic rung36_jcon_args/icn_10_binop_rc J
    lload 160
    putstatic rung36_jcon_args/icn_pv_p1_a J
    getstatic rung36_jcon_args/icn_failed B
    ifne icn_77_after_call
    getstatic rung36_jcon_args/icn_retval J
    goto icn_p1_s0_sdrain
icn_77_after_call:
    goto icn_p1_done
icn_p1_s0_sdrain:
    pop2
    goto icn_p1_done
icn_p1_done:
    iconst_0
    putstatic rung36_jcon_args/icn_suspended B
    iconst_0
    putstatic rung36_jcon_args/icn_suspend_id I
    iconst_1
    putstatic rung36_jcon_args/icn_failed B
    return
icn_p1_ret:
    iconst_0
    putstatic rung36_jcon_args/icn_failed B
    return
icn_p1_sret:
    return
.end method

.method public static icn_p2()V
    .limit stack 16
    .limit locals 264
    lconst_0
    lstore 0
    lconst_0
    lstore 2
    lconst_0
    lstore 4
    lconst_0
    lstore 6
    lconst_0
    lstore 8
    lconst_0
    lstore 10
    lconst_0
    lstore 12
    lconst_0
    lstore 14
    lconst_0
    lstore 16
    lconst_0
    lstore 18
    lconst_0
    lstore 20
    lconst_0
    lstore 22
    lconst_0
    lstore 24
    lconst_0
    lstore 26
    lconst_0
    lstore 28
    lconst_0
    lstore 30
    lconst_0
    lstore 32
    lconst_0
    lstore 34
    lconst_0
    lstore 36
    lconst_0
    lstore 38
    lconst_0
    lstore 40
    lconst_0
    lstore 42
    lconst_0
    lstore 44
    lconst_0
    lstore 46
    lconst_0
    lstore 48
    lconst_0
    lstore 50
    lconst_0
    lstore 52
    lconst_0
    lstore 54
    lconst_0
    lstore 56
    lconst_0
    lstore 58
    lconst_0
    lstore 60
    lconst_0
    lstore 62
    iconst_0
    istore 84
    iconst_0
    istore 85
    iconst_0
    istore 86
    iconst_0
    istore 87
    aconst_null
    astore 148
    aconst_null
    astore 149
    aconst_null
    astore 150
    aconst_null
    astore 151
    getstatic rung36_jcon_args/icn_arg_str_0 Ljava/lang/String;
    putstatic rung36_jcon_args/icn_pv_p2_a Ljava/lang/String;
    getstatic rung36_jcon_args/icn_arg_1 J
    putstatic rung36_jcon_args/icn_pv_p2_b J
    goto icn_80_α
;  VAR
icn_81_α:
    getstatic rung36_jcon_args/icn_pv_p2_b J
    goto icn_80_arg2
icn_81_β:
    goto icn_p2_done
icn_80_arg2:
    putstatic rung36_jcon_args/icn_arg_2 J
    goto icn_80_docall
;  VAR
icn_82_α:
    getstatic rung36_jcon_args/icn_pv_p2_a J
    goto icn_80_arg1
icn_82_β:
    goto icn_p2_done
icn_80_arg1:
    putstatic rung36_jcon_args/icn_arg_1 J
    goto icn_81_α
;  STR
icn_83_α:
    ldc "p2"
    goto icn_80_arg0
icn_83_β:
    goto icn_p2_done
icn_80_arg0:
    putstatic rung36_jcon_args/icn_arg_str_0 Ljava/lang/String;
    lconst_0
    putstatic rung36_jcon_args/icn_arg_0 J
    goto icn_82_α
icn_80_α:
    goto icn_83_α
icn_80_β:
    goto icn_81_β
icn_80_docall:
    getstatic rung36_jcon_args/icn_1_relop_lc J
    lstore 152
    getstatic rung36_jcon_args/icn_1_relop_rc J
    lstore 154
    getstatic rung36_jcon_args/icn_10_binop_lc J
    lstore 156
    getstatic rung36_jcon_args/icn_10_binop_rc J
    lstore 158
    getstatic rung36_jcon_args/icn_pv_p2_b J
    lstore 160
    getstatic rung36_jcon_args/icn_pv_p2_a J
    lstore 162
    invokestatic rung36_jcon_args/icn_note()V
    lload 152
    putstatic rung36_jcon_args/icn_1_relop_lc J
    lload 154
    putstatic rung36_jcon_args/icn_1_relop_rc J
    lload 156
    putstatic rung36_jcon_args/icn_10_binop_lc J
    lload 158
    putstatic rung36_jcon_args/icn_10_binop_rc J
    lload 160
    putstatic rung36_jcon_args/icn_pv_p2_b J
    lload 162
    putstatic rung36_jcon_args/icn_pv_p2_a J
    getstatic rung36_jcon_args/icn_failed B
    ifne icn_80_after_call
    getstatic rung36_jcon_args/icn_retval J
    goto icn_p2_s0_sdrain
icn_80_after_call:
    goto icn_p2_done
icn_p2_s0_sdrain:
    pop2
    goto icn_p2_done
icn_p2_done:
    iconst_0
    putstatic rung36_jcon_args/icn_suspended B
    iconst_0
    putstatic rung36_jcon_args/icn_suspend_id I
    iconst_1
    putstatic rung36_jcon_args/icn_failed B
    return
icn_p2_ret:
    iconst_0
    putstatic rung36_jcon_args/icn_failed B
    return
icn_p2_sret:
    return
.end method

.method public static icn_p3()V
    .limit stack 16
    .limit locals 272
    lconst_0
    lstore 0
    lconst_0
    lstore 2
    lconst_0
    lstore 4
    lconst_0
    lstore 6
    lconst_0
    lstore 8
    lconst_0
    lstore 10
    lconst_0
    lstore 12
    lconst_0
    lstore 14
    lconst_0
    lstore 16
    lconst_0
    lstore 18
    lconst_0
    lstore 20
    lconst_0
    lstore 22
    lconst_0
    lstore 24
    lconst_0
    lstore 26
    lconst_0
    lstore 28
    lconst_0
    lstore 30
    lconst_0
    lstore 32
    lconst_0
    lstore 34
    lconst_0
    lstore 36
    lconst_0
    lstore 38
    lconst_0
    lstore 40
    lconst_0
    lstore 42
    lconst_0
    lstore 44
    lconst_0
    lstore 46
    lconst_0
    lstore 48
    lconst_0
    lstore 50
    lconst_0
    lstore 52
    lconst_0
    lstore 54
    lconst_0
    lstore 56
    lconst_0
    lstore 58
    lconst_0
    lstore 60
    lconst_0
    lstore 62
    iconst_0
    istore 84
    iconst_0
    istore 85
    iconst_0
    istore 86
    iconst_0
    istore 87
    aconst_null
    astore 148
    aconst_null
    astore 149
    aconst_null
    astore 150
    aconst_null
    astore 151
    getstatic rung36_jcon_args/icn_arg_str_0 Ljava/lang/String;
    putstatic rung36_jcon_args/icn_pv_p3_a Ljava/lang/String;
    getstatic rung36_jcon_args/icn_arg_1 J
    putstatic rung36_jcon_args/icn_pv_p3_b J
    getstatic rung36_jcon_args/icn_arg_2 J
    putstatic rung36_jcon_args/icn_pv_p3_c J
    goto icn_84_α
;  VAR
icn_85_α:
    getstatic rung36_jcon_args/icn_pv_p3_c J
    goto icn_84_arg3
icn_85_β:
    goto icn_p3_done
icn_84_arg3:
    putstatic rung36_jcon_args/icn_arg_3 J
    goto icn_84_docall
;  VAR
icn_86_α:
    getstatic rung36_jcon_args/icn_pv_p3_b J
    goto icn_84_arg2
icn_86_β:
    goto icn_p3_done
icn_84_arg2:
    putstatic rung36_jcon_args/icn_arg_2 J
    goto icn_85_α
;  VAR
icn_87_α:
    getstatic rung36_jcon_args/icn_pv_p3_a J
    goto icn_84_arg1
icn_87_β:
    goto icn_p3_done
icn_84_arg1:
    putstatic rung36_jcon_args/icn_arg_1 J
    goto icn_86_α
;  STR
icn_88_α:
    ldc "p3"
    goto icn_84_arg0
icn_88_β:
    goto icn_p3_done
icn_84_arg0:
    putstatic rung36_jcon_args/icn_arg_str_0 Ljava/lang/String;
    lconst_0
    putstatic rung36_jcon_args/icn_arg_0 J
    goto icn_87_α
icn_84_α:
    goto icn_88_α
icn_84_β:
    goto icn_85_β
icn_84_docall:
    getstatic rung36_jcon_args/icn_1_relop_lc J
    lstore 152
    getstatic rung36_jcon_args/icn_1_relop_rc J
    lstore 154
    getstatic rung36_jcon_args/icn_10_binop_lc J
    lstore 156
    getstatic rung36_jcon_args/icn_10_binop_rc J
    lstore 158
    getstatic rung36_jcon_args/icn_pv_p3_c J
    lstore 160
    getstatic rung36_jcon_args/icn_pv_p3_b J
    lstore 162
    getstatic rung36_jcon_args/icn_pv_p3_a J
    lstore 164
    invokestatic rung36_jcon_args/icn_note()V
    lload 152
    putstatic rung36_jcon_args/icn_1_relop_lc J
    lload 154
    putstatic rung36_jcon_args/icn_1_relop_rc J
    lload 156
    putstatic rung36_jcon_args/icn_10_binop_lc J
    lload 158
    putstatic rung36_jcon_args/icn_10_binop_rc J
    lload 160
    putstatic rung36_jcon_args/icn_pv_p3_c J
    lload 162
    putstatic rung36_jcon_args/icn_pv_p3_b J
    lload 164
    putstatic rung36_jcon_args/icn_pv_p3_a J
    getstatic rung36_jcon_args/icn_failed B
    ifne icn_84_after_call
    getstatic rung36_jcon_args/icn_retval J
    goto icn_p3_s0_sdrain
icn_84_after_call:
    goto icn_p3_done
icn_p3_s0_sdrain:
    pop2
    goto icn_p3_done
icn_p3_done:
    iconst_0
    putstatic rung36_jcon_args/icn_suspended B
    iconst_0
    putstatic rung36_jcon_args/icn_suspend_id I
    iconst_1
    putstatic rung36_jcon_args/icn_failed B
    return
icn_p3_ret:
    iconst_0
    putstatic rung36_jcon_args/icn_failed B
    return
icn_p3_sret:
    return
.end method

.method public static icn_p4()V
    .limit stack 16
    .limit locals 282
    lconst_0
    lstore 0
    lconst_0
    lstore 2
    lconst_0
    lstore 4
    lconst_0
    lstore 6
    lconst_0
    lstore 8
    lconst_0
    lstore 10
    lconst_0
    lstore 12
    lconst_0
    lstore 14
    lconst_0
    lstore 16
    lconst_0
    lstore 18
    lconst_0
    lstore 20
    lconst_0
    lstore 22
    lconst_0
    lstore 24
    lconst_0
    lstore 26
    lconst_0
    lstore 28
    lconst_0
    lstore 30
    lconst_0
    lstore 32
    lconst_0
    lstore 34
    lconst_0
    lstore 36
    lconst_0
    lstore 38
    lconst_0
    lstore 40
    lconst_0
    lstore 42
    lconst_0
    lstore 44
    lconst_0
    lstore 46
    lconst_0
    lstore 48
    lconst_0
    lstore 50
    lconst_0
    lstore 52
    lconst_0
    lstore 54
    lconst_0
    lstore 56
    lconst_0
    lstore 58
    lconst_0
    lstore 60
    lconst_0
    lstore 62
    iconst_0
    istore 84
    iconst_0
    istore 85
    iconst_0
    istore 86
    iconst_0
    istore 87
    aconst_null
    astore 148
    aconst_null
    astore 149
    aconst_null
    astore 150
    aconst_null
    astore 151
    getstatic rung36_jcon_args/icn_arg_str_0 Ljava/lang/String;
    putstatic rung36_jcon_args/icn_pv_p4_a Ljava/lang/String;
    getstatic rung36_jcon_args/icn_arg_1 J
    putstatic rung36_jcon_args/icn_pv_p4_b J
    getstatic rung36_jcon_args/icn_arg_2 J
    putstatic rung36_jcon_args/icn_pv_p4_c J
    getstatic rung36_jcon_args/icn_arg_3 J
    putstatic rung36_jcon_args/icn_pv_p4_d J
    goto icn_89_α
;  VAR
icn_90_α:
    getstatic rung36_jcon_args/icn_pv_p4_d J
    goto icn_89_arg4
icn_90_β:
    goto icn_p4_done
icn_89_arg4:
    putstatic rung36_jcon_args/icn_arg_4 J
    goto icn_89_docall
;  VAR
icn_91_α:
    getstatic rung36_jcon_args/icn_pv_p4_c J
    goto icn_89_arg3
icn_91_β:
    goto icn_p4_done
icn_89_arg3:
    putstatic rung36_jcon_args/icn_arg_3 J
    goto icn_90_α
;  VAR
icn_92_α:
    getstatic rung36_jcon_args/icn_pv_p4_b J
    goto icn_89_arg2
icn_92_β:
    goto icn_p4_done
icn_89_arg2:
    putstatic rung36_jcon_args/icn_arg_2 J
    goto icn_91_α
;  VAR
icn_93_α:
    getstatic rung36_jcon_args/icn_pv_p4_a J
    goto icn_89_arg1
icn_93_β:
    goto icn_p4_done
icn_89_arg1:
    putstatic rung36_jcon_args/icn_arg_1 J
    goto icn_92_α
;  STR
icn_94_α:
    ldc "p4"
    goto icn_89_arg0
icn_94_β:
    goto icn_p4_done
icn_89_arg0:
    putstatic rung36_jcon_args/icn_arg_str_0 Ljava/lang/String;
    lconst_0
    putstatic rung36_jcon_args/icn_arg_0 J
    goto icn_93_α
icn_89_α:
    goto icn_94_α
icn_89_β:
    goto icn_90_β
icn_89_docall:
    getstatic rung36_jcon_args/icn_1_relop_lc J
    lstore 152
    getstatic rung36_jcon_args/icn_1_relop_rc J
    lstore 154
    getstatic rung36_jcon_args/icn_10_binop_lc J
    lstore 156
    getstatic rung36_jcon_args/icn_10_binop_rc J
    lstore 158
    getstatic rung36_jcon_args/icn_pv_p4_d J
    lstore 160
    getstatic rung36_jcon_args/icn_pv_p4_c J
    lstore 162
    getstatic rung36_jcon_args/icn_pv_p4_b J
    lstore 164
    getstatic rung36_jcon_args/icn_pv_p4_a J
    lstore 166
    invokestatic rung36_jcon_args/icn_note()V
    lload 152
    putstatic rung36_jcon_args/icn_1_relop_lc J
    lload 154
    putstatic rung36_jcon_args/icn_1_relop_rc J
    lload 156
    putstatic rung36_jcon_args/icn_10_binop_lc J
    lload 158
    putstatic rung36_jcon_args/icn_10_binop_rc J
    lload 160
    putstatic rung36_jcon_args/icn_pv_p4_d J
    lload 162
    putstatic rung36_jcon_args/icn_pv_p4_c J
    lload 164
    putstatic rung36_jcon_args/icn_pv_p4_b J
    lload 166
    putstatic rung36_jcon_args/icn_pv_p4_a J
    getstatic rung36_jcon_args/icn_failed B
    ifne icn_89_after_call
    getstatic rung36_jcon_args/icn_retval J
    goto icn_p4_s0_sdrain
icn_89_after_call:
    goto icn_p4_done
icn_p4_s0_sdrain:
    pop2
    goto icn_p4_done
icn_p4_done:
    iconst_0
    putstatic rung36_jcon_args/icn_suspended B
    iconst_0
    putstatic rung36_jcon_args/icn_suspend_id I
    iconst_1
    putstatic rung36_jcon_args/icn_failed B
    return
icn_p4_ret:
    iconst_0
    putstatic rung36_jcon_args/icn_failed B
    return
icn_p4_sret:
    return
.end method

.method public static icn_p5()V
    .limit stack 16
    .limit locals 296
    lconst_0
    lstore 0
    lconst_0
    lstore 2
    lconst_0
    lstore 4
    lconst_0
    lstore 6
    lconst_0
    lstore 8
    lconst_0
    lstore 10
    lconst_0
    lstore 12
    lconst_0
    lstore 14
    lconst_0
    lstore 16
    lconst_0
    lstore 18
    lconst_0
    lstore 20
    lconst_0
    lstore 22
    lconst_0
    lstore 24
    lconst_0
    lstore 26
    lconst_0
    lstore 28
    lconst_0
    lstore 30
    lconst_0
    lstore 32
    lconst_0
    lstore 34
    lconst_0
    lstore 36
    lconst_0
    lstore 38
    lconst_0
    lstore 40
    lconst_0
    lstore 42
    lconst_0
    lstore 44
    lconst_0
    lstore 46
    lconst_0
    lstore 48
    lconst_0
    lstore 50
    lconst_0
    lstore 52
    lconst_0
    lstore 54
    lconst_0
    lstore 56
    lconst_0
    lstore 58
    lconst_0
    lstore 60
    lconst_0
    lstore 62
    iconst_0
    istore 84
    iconst_0
    istore 85
    iconst_0
    istore 86
    iconst_0
    istore 87
    aconst_null
    astore 148
    aconst_null
    astore 149
    aconst_null
    astore 150
    aconst_null
    astore 151
    getstatic rung36_jcon_args/icn_arg_str_0 Ljava/lang/String;
    putstatic rung36_jcon_args/icn_pv_p5_a Ljava/lang/String;
    getstatic rung36_jcon_args/icn_arg_1 J
    putstatic rung36_jcon_args/icn_pv_p5_b J
    getstatic rung36_jcon_args/icn_arg_2 J
    putstatic rung36_jcon_args/icn_pv_p5_c J
    getstatic rung36_jcon_args/icn_arg_3 J
    putstatic rung36_jcon_args/icn_pv_p5_d J
    getstatic rung36_jcon_args/icn_arg_4 J
    putstatic rung36_jcon_args/icn_pv_p5_e J
    goto icn_95_α
;  VAR
icn_96_α:
    getstatic rung36_jcon_args/icn_pv_p5_e J
    goto icn_95_arg5
icn_96_β:
    goto icn_p5_done
icn_95_arg5:
    putstatic rung36_jcon_args/icn_arg_str_5 Ljava/lang/String;
    lconst_0
    putstatic rung36_jcon_args/icn_arg_5 J
    goto icn_95_docall
;  VAR
icn_97_α:
    getstatic rung36_jcon_args/icn_pv_p5_d J
    goto icn_95_arg4
icn_97_β:
    goto icn_p5_done
icn_95_arg4:
    putstatic rung36_jcon_args/icn_arg_4 J
    goto icn_96_α
;  VAR
icn_98_α:
    getstatic rung36_jcon_args/icn_pv_p5_c J
    goto icn_95_arg3
icn_98_β:
    goto icn_p5_done
icn_95_arg3:
    putstatic rung36_jcon_args/icn_arg_3 J
    goto icn_97_α
;  VAR
icn_99_α:
    getstatic rung36_jcon_args/icn_pv_p5_b J
    goto icn_95_arg2
icn_99_β:
    goto icn_p5_done
icn_95_arg2:
    putstatic rung36_jcon_args/icn_arg_2 J
    goto icn_98_α
;  VAR
icn_100_α:
    getstatic rung36_jcon_args/icn_pv_p5_a J
    goto icn_95_arg1
icn_100_β:
    goto icn_p5_done
icn_95_arg1:
    putstatic rung36_jcon_args/icn_arg_1 J
    goto icn_99_α
;  STR
icn_101_α:
    ldc "p5"
    goto icn_95_arg0
icn_101_β:
    goto icn_p5_done
icn_95_arg0:
    putstatic rung36_jcon_args/icn_arg_str_0 Ljava/lang/String;
    lconst_0
    putstatic rung36_jcon_args/icn_arg_0 J
    goto icn_100_α
icn_95_α:
    goto icn_101_α
icn_95_β:
    goto icn_96_β
icn_95_docall:
    getstatic rung36_jcon_args/icn_1_relop_lc J
    lstore 152
    getstatic rung36_jcon_args/icn_1_relop_rc J
    lstore 154
    getstatic rung36_jcon_args/icn_10_binop_lc J
    lstore 156
    getstatic rung36_jcon_args/icn_10_binop_rc J
    lstore 158
    getstatic rung36_jcon_args/icn_pv_p5_e J
    lstore 160
    getstatic rung36_jcon_args/icn_pv_p5_d J
    lstore 162
    getstatic rung36_jcon_args/icn_pv_p5_c J
    lstore 164
    getstatic rung36_jcon_args/icn_pv_p5_b J
    lstore 166
    getstatic rung36_jcon_args/icn_pv_p5_a J
    lstore 168
    invokestatic rung36_jcon_args/icn_note()V
    lload 152
    putstatic rung36_jcon_args/icn_1_relop_lc J
    lload 154
    putstatic rung36_jcon_args/icn_1_relop_rc J
    lload 156
    putstatic rung36_jcon_args/icn_10_binop_lc J
    lload 158
    putstatic rung36_jcon_args/icn_10_binop_rc J
    lload 160
    putstatic rung36_jcon_args/icn_pv_p5_e J
    lload 162
    putstatic rung36_jcon_args/icn_pv_p5_d J
    lload 164
    putstatic rung36_jcon_args/icn_pv_p5_c J
    lload 166
    putstatic rung36_jcon_args/icn_pv_p5_b J
    lload 168
    putstatic rung36_jcon_args/icn_pv_p5_a J
    getstatic rung36_jcon_args/icn_failed B
    ifne icn_95_after_call
    getstatic rung36_jcon_args/icn_retval J
    goto icn_p5_s0_sdrain
icn_95_after_call:
    goto icn_p5_done
icn_p5_s0_sdrain:
    pop2
    goto icn_p5_done
icn_p5_done:
    iconst_0
    putstatic rung36_jcon_args/icn_suspended B
    iconst_0
    putstatic rung36_jcon_args/icn_suspend_id I
    iconst_1
    putstatic rung36_jcon_args/icn_failed B
    return
icn_p5_ret:
    iconst_0
    putstatic rung36_jcon_args/icn_failed B
    return
icn_p5_sret:
    return
.end method

.method public static icn_p6()V
    .limit stack 16
    .limit locals 310
    lconst_0
    lstore 0
    lconst_0
    lstore 2
    lconst_0
    lstore 4
    lconst_0
    lstore 6
    lconst_0
    lstore 8
    lconst_0
    lstore 10
    lconst_0
    lstore 12
    lconst_0
    lstore 14
    lconst_0
    lstore 16
    lconst_0
    lstore 18
    lconst_0
    lstore 20
    lconst_0
    lstore 22
    lconst_0
    lstore 24
    lconst_0
    lstore 26
    lconst_0
    lstore 28
    lconst_0
    lstore 30
    lconst_0
    lstore 32
    lconst_0
    lstore 34
    lconst_0
    lstore 36
    lconst_0
    lstore 38
    lconst_0
    lstore 40
    lconst_0
    lstore 42
    lconst_0
    lstore 44
    lconst_0
    lstore 46
    lconst_0
    lstore 48
    lconst_0
    lstore 50
    lconst_0
    lstore 52
    lconst_0
    lstore 54
    lconst_0
    lstore 56
    lconst_0
    lstore 58
    lconst_0
    lstore 60
    lconst_0
    lstore 62
    iconst_0
    istore 84
    iconst_0
    istore 85
    iconst_0
    istore 86
    iconst_0
    istore 87
    aconst_null
    astore 148
    aconst_null
    astore 149
    aconst_null
    astore 150
    aconst_null
    astore 151
    getstatic rung36_jcon_args/icn_arg_str_0 Ljava/lang/String;
    putstatic rung36_jcon_args/icn_pv_p6_a Ljava/lang/String;
    getstatic rung36_jcon_args/icn_arg_1 J
    putstatic rung36_jcon_args/icn_pv_p6_b J
    getstatic rung36_jcon_args/icn_arg_2 J
    putstatic rung36_jcon_args/icn_pv_p6_c J
    getstatic rung36_jcon_args/icn_arg_3 J
    putstatic rung36_jcon_args/icn_pv_p6_d J
    getstatic rung36_jcon_args/icn_arg_4 J
    putstatic rung36_jcon_args/icn_pv_p6_e J
    getstatic rung36_jcon_args/icn_arg_str_5 Ljava/lang/String;
    putstatic rung36_jcon_args/icn_pv_p6_f Ljava/lang/String;
    goto icn_102_α
;  VAR
icn_103_α:
    getstatic rung36_jcon_args/icn_pv_p6_f J
    goto icn_102_arg6
icn_103_β:
    goto icn_p6_done
icn_102_arg6:
    putstatic rung36_jcon_args/icn_arg_6 J
    goto icn_102_docall
;  VAR
icn_104_α:
    getstatic rung36_jcon_args/icn_pv_p6_e J
    goto icn_102_arg5
icn_104_β:
    goto icn_p6_done
icn_102_arg5:
    putstatic rung36_jcon_args/icn_arg_str_5 Ljava/lang/String;
    lconst_0
    putstatic rung36_jcon_args/icn_arg_5 J
    goto icn_103_α
;  VAR
icn_105_α:
    getstatic rung36_jcon_args/icn_pv_p6_d J
    goto icn_102_arg4
icn_105_β:
    goto icn_p6_done
icn_102_arg4:
    putstatic rung36_jcon_args/icn_arg_4 J
    goto icn_104_α
;  VAR
icn_106_α:
    getstatic rung36_jcon_args/icn_pv_p6_c J
    goto icn_102_arg3
icn_106_β:
    goto icn_p6_done
icn_102_arg3:
    putstatic rung36_jcon_args/icn_arg_3 J
    goto icn_105_α
;  VAR
icn_107_α:
    getstatic rung36_jcon_args/icn_pv_p6_b J
    goto icn_102_arg2
icn_107_β:
    goto icn_p6_done
icn_102_arg2:
    putstatic rung36_jcon_args/icn_arg_2 J
    goto icn_106_α
;  VAR
icn_108_α:
    getstatic rung36_jcon_args/icn_pv_p6_a J
    goto icn_102_arg1
icn_108_β:
    goto icn_p6_done
icn_102_arg1:
    putstatic rung36_jcon_args/icn_arg_1 J
    goto icn_107_α
;  STR
icn_109_α:
    ldc "p6"
    goto icn_102_arg0
icn_109_β:
    goto icn_p6_done
icn_102_arg0:
    putstatic rung36_jcon_args/icn_arg_str_0 Ljava/lang/String;
    lconst_0
    putstatic rung36_jcon_args/icn_arg_0 J
    goto icn_108_α
icn_102_α:
    goto icn_109_α
icn_102_β:
    goto icn_103_β
icn_102_docall:
    getstatic rung36_jcon_args/icn_1_relop_lc J
    lstore 152
    getstatic rung36_jcon_args/icn_1_relop_rc J
    lstore 154
    getstatic rung36_jcon_args/icn_10_binop_lc J
    lstore 156
    getstatic rung36_jcon_args/icn_10_binop_rc J
    lstore 158
    getstatic rung36_jcon_args/icn_pv_p6_f J
    lstore 160
    getstatic rung36_jcon_args/icn_pv_p6_e J
    lstore 162
    getstatic rung36_jcon_args/icn_pv_p6_d J
    lstore 164
    getstatic rung36_jcon_args/icn_pv_p6_c J
    lstore 166
    getstatic rung36_jcon_args/icn_pv_p6_b J
    lstore 168
    getstatic rung36_jcon_args/icn_pv_p6_a J
    lstore 170
    invokestatic rung36_jcon_args/icn_note()V
    lload 152
    putstatic rung36_jcon_args/icn_1_relop_lc J
    lload 154
    putstatic rung36_jcon_args/icn_1_relop_rc J
    lload 156
    putstatic rung36_jcon_args/icn_10_binop_lc J
    lload 158
    putstatic rung36_jcon_args/icn_10_binop_rc J
    lload 160
    putstatic rung36_jcon_args/icn_pv_p6_f J
    lload 162
    putstatic rung36_jcon_args/icn_pv_p6_e J
    lload 164
    putstatic rung36_jcon_args/icn_pv_p6_d J
    lload 166
    putstatic rung36_jcon_args/icn_pv_p6_c J
    lload 168
    putstatic rung36_jcon_args/icn_pv_p6_b J
    lload 170
    putstatic rung36_jcon_args/icn_pv_p6_a J
    getstatic rung36_jcon_args/icn_failed B
    ifne icn_102_after_call
    getstatic rung36_jcon_args/icn_retval J
    goto icn_p6_s0_sdrain
icn_102_after_call:
    goto icn_p6_done
icn_p6_s0_sdrain:
    pop2
    goto icn_p6_done
icn_p6_done:
    iconst_0
    putstatic rung36_jcon_args/icn_suspended B
    iconst_0
    putstatic rung36_jcon_args/icn_suspend_id I
    iconst_1
    putstatic rung36_jcon_args/icn_failed B
    return
icn_p6_ret:
    iconst_0
    putstatic rung36_jcon_args/icn_failed B
    return
icn_p6_sret:
    return
.end method

.method public static icn_p7()V
    .limit stack 16
    .limit locals 326
    lconst_0
    lstore 0
    lconst_0
    lstore 2
    lconst_0
    lstore 4
    lconst_0
    lstore 6
    lconst_0
    lstore 8
    lconst_0
    lstore 10
    lconst_0
    lstore 12
    lconst_0
    lstore 14
    lconst_0
    lstore 16
    lconst_0
    lstore 18
    lconst_0
    lstore 20
    lconst_0
    lstore 22
    lconst_0
    lstore 24
    lconst_0
    lstore 26
    lconst_0
    lstore 28
    lconst_0
    lstore 30
    lconst_0
    lstore 32
    lconst_0
    lstore 34
    lconst_0
    lstore 36
    lconst_0
    lstore 38
    lconst_0
    lstore 40
    lconst_0
    lstore 42
    lconst_0
    lstore 44
    lconst_0
    lstore 46
    lconst_0
    lstore 48
    lconst_0
    lstore 50
    lconst_0
    lstore 52
    lconst_0
    lstore 54
    lconst_0
    lstore 56
    lconst_0
    lstore 58
    lconst_0
    lstore 60
    lconst_0
    lstore 62
    iconst_0
    istore 84
    iconst_0
    istore 85
    iconst_0
    istore 86
    iconst_0
    istore 87
    aconst_null
    astore 148
    aconst_null
    astore 149
    aconst_null
    astore 150
    aconst_null
    astore 151
    getstatic rung36_jcon_args/icn_arg_str_0 Ljava/lang/String;
    putstatic rung36_jcon_args/icn_pv_p7_a Ljava/lang/String;
    getstatic rung36_jcon_args/icn_arg_1 J
    putstatic rung36_jcon_args/icn_pv_p7_b J
    getstatic rung36_jcon_args/icn_arg_2 J
    putstatic rung36_jcon_args/icn_pv_p7_c J
    getstatic rung36_jcon_args/icn_arg_3 J
    putstatic rung36_jcon_args/icn_pv_p7_d J
    getstatic rung36_jcon_args/icn_arg_4 J
    putstatic rung36_jcon_args/icn_pv_p7_e J
    getstatic rung36_jcon_args/icn_arg_str_5 Ljava/lang/String;
    putstatic rung36_jcon_args/icn_pv_p7_f Ljava/lang/String;
    getstatic rung36_jcon_args/icn_arg_6 J
    putstatic rung36_jcon_args/icn_pv_p7_g J
    goto icn_110_α
;  VAR
icn_111_α:
    getstatic rung36_jcon_args/icn_pv_p7_g J
    goto icn_110_arg7
icn_111_β:
    goto icn_p7_done
icn_110_arg7:
    putstatic rung36_jcon_args/icn_arg_7 J
    goto icn_110_docall
;  VAR
icn_112_α:
    getstatic rung36_jcon_args/icn_pv_p7_f J
    goto icn_110_arg6
icn_112_β:
    goto icn_p7_done
icn_110_arg6:
    putstatic rung36_jcon_args/icn_arg_6 J
    goto icn_111_α
;  VAR
icn_113_α:
    getstatic rung36_jcon_args/icn_pv_p7_e J
    goto icn_110_arg5
icn_113_β:
    goto icn_p7_done
icn_110_arg5:
    putstatic rung36_jcon_args/icn_arg_str_5 Ljava/lang/String;
    lconst_0
    putstatic rung36_jcon_args/icn_arg_5 J
    goto icn_112_α
;  VAR
icn_114_α:
    getstatic rung36_jcon_args/icn_pv_p7_d J
    goto icn_110_arg4
icn_114_β:
    goto icn_p7_done
icn_110_arg4:
    putstatic rung36_jcon_args/icn_arg_4 J
    goto icn_113_α
;  VAR
icn_115_α:
    getstatic rung36_jcon_args/icn_pv_p7_c J
    goto icn_110_arg3
icn_115_β:
    goto icn_p7_done
icn_110_arg3:
    putstatic rung36_jcon_args/icn_arg_3 J
    goto icn_114_α
;  VAR
icn_116_α:
    getstatic rung36_jcon_args/icn_pv_p7_b J
    goto icn_110_arg2
icn_116_β:
    goto icn_p7_done
icn_110_arg2:
    putstatic rung36_jcon_args/icn_arg_2 J
    goto icn_115_α
;  VAR
icn_117_α:
    getstatic rung36_jcon_args/icn_pv_p7_a J
    goto icn_110_arg1
icn_117_β:
    goto icn_p7_done
icn_110_arg1:
    putstatic rung36_jcon_args/icn_arg_1 J
    goto icn_116_α
;  STR
icn_118_α:
    ldc "p7"
    goto icn_110_arg0
icn_118_β:
    goto icn_p7_done
icn_110_arg0:
    putstatic rung36_jcon_args/icn_arg_str_0 Ljava/lang/String;
    lconst_0
    putstatic rung36_jcon_args/icn_arg_0 J
    goto icn_117_α
icn_110_α:
    goto icn_118_α
icn_110_β:
    goto icn_111_β
icn_110_docall:
    getstatic rung36_jcon_args/icn_1_relop_lc J
    lstore 152
    getstatic rung36_jcon_args/icn_1_relop_rc J
    lstore 154
    getstatic rung36_jcon_args/icn_10_binop_lc J
    lstore 156
    getstatic rung36_jcon_args/icn_10_binop_rc J
    lstore 158
    getstatic rung36_jcon_args/icn_pv_p7_g J
    lstore 160
    getstatic rung36_jcon_args/icn_pv_p7_f J
    lstore 162
    getstatic rung36_jcon_args/icn_pv_p7_e J
    lstore 164
    getstatic rung36_jcon_args/icn_pv_p7_d J
    lstore 166
    getstatic rung36_jcon_args/icn_pv_p7_c J
    lstore 168
    getstatic rung36_jcon_args/icn_pv_p7_b J
    lstore 170
    getstatic rung36_jcon_args/icn_pv_p7_a J
    lstore 172
    invokestatic rung36_jcon_args/icn_note()V
    lload 152
    putstatic rung36_jcon_args/icn_1_relop_lc J
    lload 154
    putstatic rung36_jcon_args/icn_1_relop_rc J
    lload 156
    putstatic rung36_jcon_args/icn_10_binop_lc J
    lload 158
    putstatic rung36_jcon_args/icn_10_binop_rc J
    lload 160
    putstatic rung36_jcon_args/icn_pv_p7_g J
    lload 162
    putstatic rung36_jcon_args/icn_pv_p7_f J
    lload 164
    putstatic rung36_jcon_args/icn_pv_p7_e J
    lload 166
    putstatic rung36_jcon_args/icn_pv_p7_d J
    lload 168
    putstatic rung36_jcon_args/icn_pv_p7_c J
    lload 170
    putstatic rung36_jcon_args/icn_pv_p7_b J
    lload 172
    putstatic rung36_jcon_args/icn_pv_p7_a J
    getstatic rung36_jcon_args/icn_failed B
    ifne icn_110_after_call
    getstatic rung36_jcon_args/icn_retval J
    goto icn_p7_s0_sdrain
icn_110_after_call:
    goto icn_p7_done
icn_p7_s0_sdrain:
    pop2
    goto icn_p7_done
icn_p7_done:
    iconst_0
    putstatic rung36_jcon_args/icn_suspended B
    iconst_0
    putstatic rung36_jcon_args/icn_suspend_id I
    iconst_1
    putstatic rung36_jcon_args/icn_failed B
    return
icn_p7_ret:
    iconst_0
    putstatic rung36_jcon_args/icn_failed B
    return
icn_p7_sret:
    return
.end method

.method public static icn_p8()V
    .limit stack 16
    .limit locals 344
    lconst_0
    lstore 0
    lconst_0
    lstore 2
    lconst_0
    lstore 4
    lconst_0
    lstore 6
    lconst_0
    lstore 8
    lconst_0
    lstore 10
    lconst_0
    lstore 12
    lconst_0
    lstore 14
    lconst_0
    lstore 16
    lconst_0
    lstore 18
    lconst_0
    lstore 20
    lconst_0
    lstore 22
    lconst_0
    lstore 24
    lconst_0
    lstore 26
    lconst_0
    lstore 28
    lconst_0
    lstore 30
    lconst_0
    lstore 32
    lconst_0
    lstore 34
    lconst_0
    lstore 36
    lconst_0
    lstore 38
    lconst_0
    lstore 40
    lconst_0
    lstore 42
    lconst_0
    lstore 44
    lconst_0
    lstore 46
    lconst_0
    lstore 48
    lconst_0
    lstore 50
    lconst_0
    lstore 52
    lconst_0
    lstore 54
    lconst_0
    lstore 56
    lconst_0
    lstore 58
    lconst_0
    lstore 60
    lconst_0
    lstore 62
    iconst_0
    istore 84
    iconst_0
    istore 85
    iconst_0
    istore 86
    iconst_0
    istore 87
    aconst_null
    astore 148
    aconst_null
    astore 149
    aconst_null
    astore 150
    aconst_null
    astore 151
    getstatic rung36_jcon_args/icn_arg_str_0 Ljava/lang/String;
    putstatic rung36_jcon_args/icn_pv_p8_a Ljava/lang/String;
    getstatic rung36_jcon_args/icn_arg_1 J
    putstatic rung36_jcon_args/icn_pv_p8_b J
    getstatic rung36_jcon_args/icn_arg_2 J
    putstatic rung36_jcon_args/icn_pv_p8_c J
    getstatic rung36_jcon_args/icn_arg_3 J
    putstatic rung36_jcon_args/icn_pv_p8_d J
    getstatic rung36_jcon_args/icn_arg_4 J
    putstatic rung36_jcon_args/icn_pv_p8_e J
    getstatic rung36_jcon_args/icn_arg_str_5 Ljava/lang/String;
    putstatic rung36_jcon_args/icn_pv_p8_f Ljava/lang/String;
    getstatic rung36_jcon_args/icn_arg_6 J
    putstatic rung36_jcon_args/icn_pv_p8_g J
    getstatic rung36_jcon_args/icn_arg_7 J
    putstatic rung36_jcon_args/icn_pv_p8_h J
    goto icn_119_α
;  VAR
icn_120_α:
    getstatic rung36_jcon_args/icn_pv_p8_h J
    goto icn_119_arg8
icn_120_β:
    goto icn_p8_done
icn_119_arg8:
    putstatic rung36_jcon_args/icn_arg_8 J
    goto icn_119_docall
;  VAR
icn_121_α:
    getstatic rung36_jcon_args/icn_pv_p8_g J
    goto icn_119_arg7
icn_121_β:
    goto icn_p8_done
icn_119_arg7:
    putstatic rung36_jcon_args/icn_arg_7 J
    goto icn_120_α
;  VAR
icn_122_α:
    getstatic rung36_jcon_args/icn_pv_p8_f J
    goto icn_119_arg6
icn_122_β:
    goto icn_p8_done
icn_119_arg6:
    putstatic rung36_jcon_args/icn_arg_6 J
    goto icn_121_α
;  VAR
icn_123_α:
    getstatic rung36_jcon_args/icn_pv_p8_e J
    goto icn_119_arg5
icn_123_β:
    goto icn_p8_done
icn_119_arg5:
    putstatic rung36_jcon_args/icn_arg_str_5 Ljava/lang/String;
    lconst_0
    putstatic rung36_jcon_args/icn_arg_5 J
    goto icn_122_α
;  VAR
icn_124_α:
    getstatic rung36_jcon_args/icn_pv_p8_d J
    goto icn_119_arg4
icn_124_β:
    goto icn_p8_done
icn_119_arg4:
    putstatic rung36_jcon_args/icn_arg_4 J
    goto icn_123_α
;  VAR
icn_125_α:
    getstatic rung36_jcon_args/icn_pv_p8_c J
    goto icn_119_arg3
icn_125_β:
    goto icn_p8_done
icn_119_arg3:
    putstatic rung36_jcon_args/icn_arg_3 J
    goto icn_124_α
;  VAR
icn_126_α:
    getstatic rung36_jcon_args/icn_pv_p8_b J
    goto icn_119_arg2
icn_126_β:
    goto icn_p8_done
icn_119_arg2:
    putstatic rung36_jcon_args/icn_arg_2 J
    goto icn_125_α
;  VAR
icn_127_α:
    getstatic rung36_jcon_args/icn_pv_p8_a J
    goto icn_119_arg1
icn_127_β:
    goto icn_p8_done
icn_119_arg1:
    putstatic rung36_jcon_args/icn_arg_1 J
    goto icn_126_α
;  STR
icn_128_α:
    ldc "p8"
    goto icn_119_arg0
icn_128_β:
    goto icn_p8_done
icn_119_arg0:
    putstatic rung36_jcon_args/icn_arg_str_0 Ljava/lang/String;
    lconst_0
    putstatic rung36_jcon_args/icn_arg_0 J
    goto icn_127_α
icn_119_α:
    goto icn_128_α
icn_119_β:
    goto icn_120_β
icn_119_docall:
    getstatic rung36_jcon_args/icn_1_relop_lc J
    lstore 152
    getstatic rung36_jcon_args/icn_1_relop_rc J
    lstore 154
    getstatic rung36_jcon_args/icn_10_binop_lc J
    lstore 156
    getstatic rung36_jcon_args/icn_10_binop_rc J
    lstore 158
    getstatic rung36_jcon_args/icn_pv_p8_h J
    lstore 160
    getstatic rung36_jcon_args/icn_pv_p8_g J
    lstore 162
    getstatic rung36_jcon_args/icn_pv_p8_f J
    lstore 164
    getstatic rung36_jcon_args/icn_pv_p8_e J
    lstore 166
    getstatic rung36_jcon_args/icn_pv_p8_d J
    lstore 168
    getstatic rung36_jcon_args/icn_pv_p8_c J
    lstore 170
    getstatic rung36_jcon_args/icn_pv_p8_b J
    lstore 172
    getstatic rung36_jcon_args/icn_pv_p8_a J
    lstore 174
    invokestatic rung36_jcon_args/icn_note()V
    lload 152
    putstatic rung36_jcon_args/icn_1_relop_lc J
    lload 154
    putstatic rung36_jcon_args/icn_1_relop_rc J
    lload 156
    putstatic rung36_jcon_args/icn_10_binop_lc J
    lload 158
    putstatic rung36_jcon_args/icn_10_binop_rc J
    lload 160
    putstatic rung36_jcon_args/icn_pv_p8_h J
    lload 162
    putstatic rung36_jcon_args/icn_pv_p8_g J
    lload 164
    putstatic rung36_jcon_args/icn_pv_p8_f J
    lload 166
    putstatic rung36_jcon_args/icn_pv_p8_e J
    lload 168
    putstatic rung36_jcon_args/icn_pv_p8_d J
    lload 170
    putstatic rung36_jcon_args/icn_pv_p8_c J
    lload 172
    putstatic rung36_jcon_args/icn_pv_p8_b J
    lload 174
    putstatic rung36_jcon_args/icn_pv_p8_a J
    getstatic rung36_jcon_args/icn_failed B
    ifne icn_119_after_call
    getstatic rung36_jcon_args/icn_retval J
    goto icn_p8_s0_sdrain
icn_119_after_call:
    goto icn_p8_done
icn_p8_s0_sdrain:
    pop2
    goto icn_p8_done
icn_p8_done:
    iconst_0
    putstatic rung36_jcon_args/icn_suspended B
    iconst_0
    putstatic rung36_jcon_args/icn_suspend_id I
    iconst_1
    putstatic rung36_jcon_args/icn_failed B
    return
icn_p8_ret:
    iconst_0
    putstatic rung36_jcon_args/icn_failed B
    return
icn_p8_sret:
    return
.end method

.method public static icn_p9()V
    .limit stack 16
    .limit locals 364
    lconst_0
    lstore 0
    lconst_0
    lstore 2
    lconst_0
    lstore 4
    lconst_0
    lstore 6
    lconst_0
    lstore 8
    lconst_0
    lstore 10
    lconst_0
    lstore 12
    lconst_0
    lstore 14
    lconst_0
    lstore 16
    lconst_0
    lstore 18
    lconst_0
    lstore 20
    lconst_0
    lstore 22
    lconst_0
    lstore 24
    lconst_0
    lstore 26
    lconst_0
    lstore 28
    lconst_0
    lstore 30
    lconst_0
    lstore 32
    lconst_0
    lstore 34
    lconst_0
    lstore 36
    lconst_0
    lstore 38
    lconst_0
    lstore 40
    lconst_0
    lstore 42
    lconst_0
    lstore 44
    lconst_0
    lstore 46
    lconst_0
    lstore 48
    lconst_0
    lstore 50
    lconst_0
    lstore 52
    lconst_0
    lstore 54
    lconst_0
    lstore 56
    lconst_0
    lstore 58
    lconst_0
    lstore 60
    lconst_0
    lstore 62
    iconst_0
    istore 84
    iconst_0
    istore 85
    iconst_0
    istore 86
    iconst_0
    istore 87
    aconst_null
    astore 148
    aconst_null
    astore 149
    aconst_null
    astore 150
    aconst_null
    astore 151
    getstatic rung36_jcon_args/icn_arg_str_0 Ljava/lang/String;
    putstatic rung36_jcon_args/icn_pv_p9_a Ljava/lang/String;
    getstatic rung36_jcon_args/icn_arg_1 J
    putstatic rung36_jcon_args/icn_pv_p9_b J
    getstatic rung36_jcon_args/icn_arg_2 J
    putstatic rung36_jcon_args/icn_pv_p9_c J
    getstatic rung36_jcon_args/icn_arg_3 J
    putstatic rung36_jcon_args/icn_pv_p9_d J
    getstatic rung36_jcon_args/icn_arg_4 J
    putstatic rung36_jcon_args/icn_pv_p9_e J
    getstatic rung36_jcon_args/icn_arg_str_5 Ljava/lang/String;
    putstatic rung36_jcon_args/icn_pv_p9_f Ljava/lang/String;
    getstatic rung36_jcon_args/icn_arg_6 J
    putstatic rung36_jcon_args/icn_pv_p9_g J
    getstatic rung36_jcon_args/icn_arg_7 J
    putstatic rung36_jcon_args/icn_pv_p9_h J
    getstatic rung36_jcon_args/icn_arg_8 J
    putstatic rung36_jcon_args/icn_pv_p9_i J
    goto icn_129_α
;  VAR
icn_130_α:
    getstatic rung36_jcon_args/icn_pv_p9_i J
    goto icn_129_arg9
icn_130_β:
    goto icn_p9_done
icn_129_arg9:
    putstatic rung36_jcon_args/icn_arg_9 J
    goto icn_129_docall
;  VAR
icn_131_α:
    getstatic rung36_jcon_args/icn_pv_p9_h J
    goto icn_129_arg8
icn_131_β:
    goto icn_p9_done
icn_129_arg8:
    putstatic rung36_jcon_args/icn_arg_8 J
    goto icn_130_α
;  VAR
icn_132_α:
    getstatic rung36_jcon_args/icn_pv_p9_g J
    goto icn_129_arg7
icn_132_β:
    goto icn_p9_done
icn_129_arg7:
    putstatic rung36_jcon_args/icn_arg_7 J
    goto icn_131_α
;  VAR
icn_133_α:
    getstatic rung36_jcon_args/icn_pv_p9_f J
    goto icn_129_arg6
icn_133_β:
    goto icn_p9_done
icn_129_arg6:
    putstatic rung36_jcon_args/icn_arg_6 J
    goto icn_132_α
;  VAR
icn_134_α:
    getstatic rung36_jcon_args/icn_pv_p9_e J
    goto icn_129_arg5
icn_134_β:
    goto icn_p9_done
icn_129_arg5:
    putstatic rung36_jcon_args/icn_arg_str_5 Ljava/lang/String;
    lconst_0
    putstatic rung36_jcon_args/icn_arg_5 J
    goto icn_133_α
;  VAR
icn_135_α:
    getstatic rung36_jcon_args/icn_pv_p9_d J
    goto icn_129_arg4
icn_135_β:
    goto icn_p9_done
icn_129_arg4:
    putstatic rung36_jcon_args/icn_arg_4 J
    goto icn_134_α
;  VAR
icn_136_α:
    getstatic rung36_jcon_args/icn_pv_p9_c J
    goto icn_129_arg3
icn_136_β:
    goto icn_p9_done
icn_129_arg3:
    putstatic rung36_jcon_args/icn_arg_3 J
    goto icn_135_α
;  VAR
icn_137_α:
    getstatic rung36_jcon_args/icn_pv_p9_b J
    goto icn_129_arg2
icn_137_β:
    goto icn_p9_done
icn_129_arg2:
    putstatic rung36_jcon_args/icn_arg_2 J
    goto icn_136_α
;  VAR
icn_138_α:
    getstatic rung36_jcon_args/icn_pv_p9_a J
    goto icn_129_arg1
icn_138_β:
    goto icn_p9_done
icn_129_arg1:
    putstatic rung36_jcon_args/icn_arg_1 J
    goto icn_137_α
;  STR
icn_139_α:
    ldc "p9"
    goto icn_129_arg0
icn_139_β:
    goto icn_p9_done
icn_129_arg0:
    putstatic rung36_jcon_args/icn_arg_str_0 Ljava/lang/String;
    lconst_0
    putstatic rung36_jcon_args/icn_arg_0 J
    goto icn_138_α
icn_129_α:
    goto icn_139_α
icn_129_β:
    goto icn_130_β
icn_129_docall:
    getstatic rung36_jcon_args/icn_1_relop_lc J
    lstore 152
    getstatic rung36_jcon_args/icn_1_relop_rc J
    lstore 154
    getstatic rung36_jcon_args/icn_10_binop_lc J
    lstore 156
    getstatic rung36_jcon_args/icn_10_binop_rc J
    lstore 158
    getstatic rung36_jcon_args/icn_pv_p9_i J
    lstore 160
    getstatic rung36_jcon_args/icn_pv_p9_h J
    lstore 162
    getstatic rung36_jcon_args/icn_pv_p9_g J
    lstore 164
    getstatic rung36_jcon_args/icn_pv_p9_f J
    lstore 166
    getstatic rung36_jcon_args/icn_pv_p9_e J
    lstore 168
    getstatic rung36_jcon_args/icn_pv_p9_d J
    lstore 170
    getstatic rung36_jcon_args/icn_pv_p9_c J
    lstore 172
    getstatic rung36_jcon_args/icn_pv_p9_b J
    lstore 174
    getstatic rung36_jcon_args/icn_pv_p9_a J
    lstore 176
    invokestatic rung36_jcon_args/icn_note()V
    lload 152
    putstatic rung36_jcon_args/icn_1_relop_lc J
    lload 154
    putstatic rung36_jcon_args/icn_1_relop_rc J
    lload 156
    putstatic rung36_jcon_args/icn_10_binop_lc J
    lload 158
    putstatic rung36_jcon_args/icn_10_binop_rc J
    lload 160
    putstatic rung36_jcon_args/icn_pv_p9_i J
    lload 162
    putstatic rung36_jcon_args/icn_pv_p9_h J
    lload 164
    putstatic rung36_jcon_args/icn_pv_p9_g J
    lload 166
    putstatic rung36_jcon_args/icn_pv_p9_f J
    lload 168
    putstatic rung36_jcon_args/icn_pv_p9_e J
    lload 170
    putstatic rung36_jcon_args/icn_pv_p9_d J
    lload 172
    putstatic rung36_jcon_args/icn_pv_p9_c J
    lload 174
    putstatic rung36_jcon_args/icn_pv_p9_b J
    lload 176
    putstatic rung36_jcon_args/icn_pv_p9_a J
    getstatic rung36_jcon_args/icn_failed B
    ifne icn_129_after_call
    getstatic rung36_jcon_args/icn_retval J
    goto icn_p9_s0_sdrain
icn_129_after_call:
    goto icn_p9_done
icn_p9_s0_sdrain:
    pop2
    goto icn_p9_done
icn_p9_done:
    iconst_0
    putstatic rung36_jcon_args/icn_suspended B
    iconst_0
    putstatic rung36_jcon_args/icn_suspend_id I
    iconst_1
    putstatic rung36_jcon_args/icn_failed B
    return
icn_p9_ret:
    iconst_0
    putstatic rung36_jcon_args/icn_failed B
    return
icn_p9_sret:
    return
.end method

.method public static icn_p10()V
    .limit stack 16
    .limit locals 386
    lconst_0
    lstore 0
    lconst_0
    lstore 2
    lconst_0
    lstore 4
    lconst_0
    lstore 6
    lconst_0
    lstore 8
    lconst_0
    lstore 10
    lconst_0
    lstore 12
    lconst_0
    lstore 14
    lconst_0
    lstore 16
    lconst_0
    lstore 18
    lconst_0
    lstore 20
    lconst_0
    lstore 22
    lconst_0
    lstore 24
    lconst_0
    lstore 26
    lconst_0
    lstore 28
    lconst_0
    lstore 30
    lconst_0
    lstore 32
    lconst_0
    lstore 34
    lconst_0
    lstore 36
    lconst_0
    lstore 38
    lconst_0
    lstore 40
    lconst_0
    lstore 42
    lconst_0
    lstore 44
    lconst_0
    lstore 46
    lconst_0
    lstore 48
    lconst_0
    lstore 50
    lconst_0
    lstore 52
    lconst_0
    lstore 54
    lconst_0
    lstore 56
    lconst_0
    lstore 58
    lconst_0
    lstore 60
    lconst_0
    lstore 62
    iconst_0
    istore 84
    iconst_0
    istore 85
    iconst_0
    istore 86
    iconst_0
    istore 87
    aconst_null
    astore 148
    aconst_null
    astore 149
    aconst_null
    astore 150
    aconst_null
    astore 151
    getstatic rung36_jcon_args/icn_arg_str_0 Ljava/lang/String;
    putstatic rung36_jcon_args/icn_pv_p10_a Ljava/lang/String;
    getstatic rung36_jcon_args/icn_arg_1 J
    putstatic rung36_jcon_args/icn_pv_p10_b J
    getstatic rung36_jcon_args/icn_arg_2 J
    putstatic rung36_jcon_args/icn_pv_p10_c J
    getstatic rung36_jcon_args/icn_arg_3 J
    putstatic rung36_jcon_args/icn_pv_p10_d J
    getstatic rung36_jcon_args/icn_arg_4 J
    putstatic rung36_jcon_args/icn_pv_p10_e J
    getstatic rung36_jcon_args/icn_arg_str_5 Ljava/lang/String;
    putstatic rung36_jcon_args/icn_pv_p10_f Ljava/lang/String;
    getstatic rung36_jcon_args/icn_arg_6 J
    putstatic rung36_jcon_args/icn_pv_p10_g J
    getstatic rung36_jcon_args/icn_arg_7 J
    putstatic rung36_jcon_args/icn_pv_p10_h J
    getstatic rung36_jcon_args/icn_arg_8 J
    putstatic rung36_jcon_args/icn_pv_p10_i J
    getstatic rung36_jcon_args/icn_arg_9 J
    putstatic rung36_jcon_args/icn_pv_p10_j J
    goto icn_140_α
;  VAR
icn_141_α:
    getstatic rung36_jcon_args/icn_pv_p10_j J
    goto icn_140_arg10
icn_141_β:
    goto icn_p10_done
icn_140_arg10:
    putstatic rung36_jcon_args/icn_arg_10 J
    goto icn_140_docall
;  VAR
icn_142_α:
    getstatic rung36_jcon_args/icn_pv_p10_i J
    goto icn_140_arg9
icn_142_β:
    goto icn_p10_done
icn_140_arg9:
    putstatic rung36_jcon_args/icn_arg_9 J
    goto icn_141_α
;  VAR
icn_143_α:
    getstatic rung36_jcon_args/icn_pv_p10_h J
    goto icn_140_arg8
icn_143_β:
    goto icn_p10_done
icn_140_arg8:
    putstatic rung36_jcon_args/icn_arg_8 J
    goto icn_142_α
;  VAR
icn_144_α:
    getstatic rung36_jcon_args/icn_pv_p10_g J
    goto icn_140_arg7
icn_144_β:
    goto icn_p10_done
icn_140_arg7:
    putstatic rung36_jcon_args/icn_arg_7 J
    goto icn_143_α
;  VAR
icn_145_α:
    getstatic rung36_jcon_args/icn_pv_p10_f J
    goto icn_140_arg6
icn_145_β:
    goto icn_p10_done
icn_140_arg6:
    putstatic rung36_jcon_args/icn_arg_6 J
    goto icn_144_α
;  VAR
icn_146_α:
    getstatic rung36_jcon_args/icn_pv_p10_e J
    goto icn_140_arg5
icn_146_β:
    goto icn_p10_done
icn_140_arg5:
    putstatic rung36_jcon_args/icn_arg_str_5 Ljava/lang/String;
    lconst_0
    putstatic rung36_jcon_args/icn_arg_5 J
    goto icn_145_α
;  VAR
icn_147_α:
    getstatic rung36_jcon_args/icn_pv_p10_d J
    goto icn_140_arg4
icn_147_β:
    goto icn_p10_done
icn_140_arg4:
    putstatic rung36_jcon_args/icn_arg_4 J
    goto icn_146_α
;  VAR
icn_148_α:
    getstatic rung36_jcon_args/icn_pv_p10_c J
    goto icn_140_arg3
icn_148_β:
    goto icn_p10_done
icn_140_arg3:
    putstatic rung36_jcon_args/icn_arg_3 J
    goto icn_147_α
;  VAR
icn_149_α:
    getstatic rung36_jcon_args/icn_pv_p10_b J
    goto icn_140_arg2
icn_149_β:
    goto icn_p10_done
icn_140_arg2:
    putstatic rung36_jcon_args/icn_arg_2 J
    goto icn_148_α
;  VAR
icn_150_α:
    getstatic rung36_jcon_args/icn_pv_p10_a J
    goto icn_140_arg1
icn_150_β:
    goto icn_p10_done
icn_140_arg1:
    putstatic rung36_jcon_args/icn_arg_1 J
    goto icn_149_α
;  STR
icn_151_α:
    ldc "p10"
    goto icn_140_arg0
icn_151_β:
    goto icn_p10_done
icn_140_arg0:
    putstatic rung36_jcon_args/icn_arg_str_0 Ljava/lang/String;
    lconst_0
    putstatic rung36_jcon_args/icn_arg_0 J
    goto icn_150_α
icn_140_α:
    goto icn_151_α
icn_140_β:
    goto icn_141_β
icn_140_docall:
    getstatic rung36_jcon_args/icn_1_relop_lc J
    lstore 152
    getstatic rung36_jcon_args/icn_1_relop_rc J
    lstore 154
    getstatic rung36_jcon_args/icn_10_binop_lc J
    lstore 156
    getstatic rung36_jcon_args/icn_10_binop_rc J
    lstore 158
    getstatic rung36_jcon_args/icn_pv_p10_j J
    lstore 160
    getstatic rung36_jcon_args/icn_pv_p10_i J
    lstore 162
    getstatic rung36_jcon_args/icn_pv_p10_h J
    lstore 164
    getstatic rung36_jcon_args/icn_pv_p10_g J
    lstore 166
    getstatic rung36_jcon_args/icn_pv_p10_f J
    lstore 168
    getstatic rung36_jcon_args/icn_pv_p10_e J
    lstore 170
    getstatic rung36_jcon_args/icn_pv_p10_d J
    lstore 172
    getstatic rung36_jcon_args/icn_pv_p10_c J
    lstore 174
    getstatic rung36_jcon_args/icn_pv_p10_b J
    lstore 176
    getstatic rung36_jcon_args/icn_pv_p10_a J
    lstore 178
    invokestatic rung36_jcon_args/icn_note()V
    lload 152
    putstatic rung36_jcon_args/icn_1_relop_lc J
    lload 154
    putstatic rung36_jcon_args/icn_1_relop_rc J
    lload 156
    putstatic rung36_jcon_args/icn_10_binop_lc J
    lload 158
    putstatic rung36_jcon_args/icn_10_binop_rc J
    lload 160
    putstatic rung36_jcon_args/icn_pv_p10_j J
    lload 162
    putstatic rung36_jcon_args/icn_pv_p10_i J
    lload 164
    putstatic rung36_jcon_args/icn_pv_p10_h J
    lload 166
    putstatic rung36_jcon_args/icn_pv_p10_g J
    lload 168
    putstatic rung36_jcon_args/icn_pv_p10_f J
    lload 170
    putstatic rung36_jcon_args/icn_pv_p10_e J
    lload 172
    putstatic rung36_jcon_args/icn_pv_p10_d J
    lload 174
    putstatic rung36_jcon_args/icn_pv_p10_c J
    lload 176
    putstatic rung36_jcon_args/icn_pv_p10_b J
    lload 178
    putstatic rung36_jcon_args/icn_pv_p10_a J
    getstatic rung36_jcon_args/icn_failed B
    ifne icn_140_after_call
    getstatic rung36_jcon_args/icn_retval J
    goto icn_p10_s0_sdrain
icn_140_after_call:
    goto icn_p10_done
icn_p10_s0_sdrain:
    pop2
    goto icn_p10_done
icn_p10_done:
    iconst_0
    putstatic rung36_jcon_args/icn_suspended B
    iconst_0
    putstatic rung36_jcon_args/icn_suspend_id I
    iconst_1
    putstatic rung36_jcon_args/icn_failed B
    return
icn_p10_ret:
    iconst_0
    putstatic rung36_jcon_args/icn_failed B
    return
icn_p10_sret:
    return
.end method

.method public static icn_p11()V
    .limit stack 16
    .limit locals 410
    lconst_0
    lstore 0
    lconst_0
    lstore 2
    lconst_0
    lstore 4
    lconst_0
    lstore 6
    lconst_0
    lstore 8
    lconst_0
    lstore 10
    lconst_0
    lstore 12
    lconst_0
    lstore 14
    lconst_0
    lstore 16
    lconst_0
    lstore 18
    lconst_0
    lstore 20
    lconst_0
    lstore 22
    lconst_0
    lstore 24
    lconst_0
    lstore 26
    lconst_0
    lstore 28
    lconst_0
    lstore 30
    lconst_0
    lstore 32
    lconst_0
    lstore 34
    lconst_0
    lstore 36
    lconst_0
    lstore 38
    lconst_0
    lstore 40
    lconst_0
    lstore 42
    lconst_0
    lstore 44
    lconst_0
    lstore 46
    lconst_0
    lstore 48
    lconst_0
    lstore 50
    lconst_0
    lstore 52
    lconst_0
    lstore 54
    lconst_0
    lstore 56
    lconst_0
    lstore 58
    lconst_0
    lstore 60
    lconst_0
    lstore 62
    iconst_0
    istore 84
    iconst_0
    istore 85
    iconst_0
    istore 86
    iconst_0
    istore 87
    aconst_null
    astore 148
    aconst_null
    astore 149
    aconst_null
    astore 150
    aconst_null
    astore 151
    getstatic rung36_jcon_args/icn_arg_str_0 Ljava/lang/String;
    putstatic rung36_jcon_args/icn_pv_p11_a Ljava/lang/String;
    getstatic rung36_jcon_args/icn_arg_1 J
    putstatic rung36_jcon_args/icn_pv_p11_b J
    getstatic rung36_jcon_args/icn_arg_2 J
    putstatic rung36_jcon_args/icn_pv_p11_c J
    getstatic rung36_jcon_args/icn_arg_3 J
    putstatic rung36_jcon_args/icn_pv_p11_d J
    getstatic rung36_jcon_args/icn_arg_4 J
    putstatic rung36_jcon_args/icn_pv_p11_e J
    getstatic rung36_jcon_args/icn_arg_str_5 Ljava/lang/String;
    putstatic rung36_jcon_args/icn_pv_p11_f Ljava/lang/String;
    getstatic rung36_jcon_args/icn_arg_6 J
    putstatic rung36_jcon_args/icn_pv_p11_g J
    getstatic rung36_jcon_args/icn_arg_7 J
    putstatic rung36_jcon_args/icn_pv_p11_h J
    getstatic rung36_jcon_args/icn_arg_8 J
    putstatic rung36_jcon_args/icn_pv_p11_i J
    getstatic rung36_jcon_args/icn_arg_9 J
    putstatic rung36_jcon_args/icn_pv_p11_j J
    getstatic rung36_jcon_args/icn_arg_10 J
    putstatic rung36_jcon_args/icn_pv_p11_k J
    goto icn_152_α
;  VAR
icn_153_α:
    getstatic rung36_jcon_args/icn_pv_p11_k J
    goto icn_152_arg11
icn_153_β:
    goto icn_p11_done
icn_152_arg11:
    putstatic rung36_jcon_args/icn_arg_11 J
    goto icn_152_docall
;  VAR
icn_154_α:
    getstatic rung36_jcon_args/icn_pv_p11_j J
    goto icn_152_arg10
icn_154_β:
    goto icn_p11_done
icn_152_arg10:
    putstatic rung36_jcon_args/icn_arg_10 J
    goto icn_153_α
;  VAR
icn_155_α:
    getstatic rung36_jcon_args/icn_pv_p11_i J
    goto icn_152_arg9
icn_155_β:
    goto icn_p11_done
icn_152_arg9:
    putstatic rung36_jcon_args/icn_arg_9 J
    goto icn_154_α
;  VAR
icn_156_α:
    getstatic rung36_jcon_args/icn_pv_p11_h J
    goto icn_152_arg8
icn_156_β:
    goto icn_p11_done
icn_152_arg8:
    putstatic rung36_jcon_args/icn_arg_8 J
    goto icn_155_α
;  VAR
icn_157_α:
    getstatic rung36_jcon_args/icn_pv_p11_g J
    goto icn_152_arg7
icn_157_β:
    goto icn_p11_done
icn_152_arg7:
    putstatic rung36_jcon_args/icn_arg_7 J
    goto icn_156_α
;  VAR
icn_158_α:
    getstatic rung36_jcon_args/icn_pv_p11_f J
    goto icn_152_arg6
icn_158_β:
    goto icn_p11_done
icn_152_arg6:
    putstatic rung36_jcon_args/icn_arg_6 J
    goto icn_157_α
;  VAR
icn_159_α:
    getstatic rung36_jcon_args/icn_pv_p11_e J
    goto icn_152_arg5
icn_159_β:
    goto icn_p11_done
icn_152_arg5:
    putstatic rung36_jcon_args/icn_arg_str_5 Ljava/lang/String;
    lconst_0
    putstatic rung36_jcon_args/icn_arg_5 J
    goto icn_158_α
;  VAR
icn_160_α:
    getstatic rung36_jcon_args/icn_pv_p11_d J
    goto icn_152_arg4
icn_160_β:
    goto icn_p11_done
icn_152_arg4:
    putstatic rung36_jcon_args/icn_arg_4 J
    goto icn_159_α
;  VAR
icn_161_α:
    getstatic rung36_jcon_args/icn_pv_p11_c J
    goto icn_152_arg3
icn_161_β:
    goto icn_p11_done
icn_152_arg3:
    putstatic rung36_jcon_args/icn_arg_3 J
    goto icn_160_α
;  VAR
icn_162_α:
    getstatic rung36_jcon_args/icn_pv_p11_b J
    goto icn_152_arg2
icn_162_β:
    goto icn_p11_done
icn_152_arg2:
    putstatic rung36_jcon_args/icn_arg_2 J
    goto icn_161_α
;  VAR
icn_163_α:
    getstatic rung36_jcon_args/icn_pv_p11_a J
    goto icn_152_arg1
icn_163_β:
    goto icn_p11_done
icn_152_arg1:
    putstatic rung36_jcon_args/icn_arg_1 J
    goto icn_162_α
;  STR
icn_164_α:
    ldc "p11"
    goto icn_152_arg0
icn_164_β:
    goto icn_p11_done
icn_152_arg0:
    putstatic rung36_jcon_args/icn_arg_str_0 Ljava/lang/String;
    lconst_0
    putstatic rung36_jcon_args/icn_arg_0 J
    goto icn_163_α
icn_152_α:
    goto icn_164_α
icn_152_β:
    goto icn_153_β
icn_152_docall:
    getstatic rung36_jcon_args/icn_1_relop_lc J
    lstore 152
    getstatic rung36_jcon_args/icn_1_relop_rc J
    lstore 154
    getstatic rung36_jcon_args/icn_10_binop_lc J
    lstore 156
    getstatic rung36_jcon_args/icn_10_binop_rc J
    lstore 158
    getstatic rung36_jcon_args/icn_pv_p11_k J
    lstore 160
    getstatic rung36_jcon_args/icn_pv_p11_j J
    lstore 162
    getstatic rung36_jcon_args/icn_pv_p11_i J
    lstore 164
    getstatic rung36_jcon_args/icn_pv_p11_h J
    lstore 166
    getstatic rung36_jcon_args/icn_pv_p11_g J
    lstore 168
    getstatic rung36_jcon_args/icn_pv_p11_f J
    lstore 170
    getstatic rung36_jcon_args/icn_pv_p11_e J
    lstore 172
    getstatic rung36_jcon_args/icn_pv_p11_d J
    lstore 174
    getstatic rung36_jcon_args/icn_pv_p11_c J
    lstore 176
    getstatic rung36_jcon_args/icn_pv_p11_b J
    lstore 178
    getstatic rung36_jcon_args/icn_pv_p11_a J
    lstore 180
    invokestatic rung36_jcon_args/icn_note()V
    lload 152
    putstatic rung36_jcon_args/icn_1_relop_lc J
    lload 154
    putstatic rung36_jcon_args/icn_1_relop_rc J
    lload 156
    putstatic rung36_jcon_args/icn_10_binop_lc J
    lload 158
    putstatic rung36_jcon_args/icn_10_binop_rc J
    lload 160
    putstatic rung36_jcon_args/icn_pv_p11_k J
    lload 162
    putstatic rung36_jcon_args/icn_pv_p11_j J
    lload 164
    putstatic rung36_jcon_args/icn_pv_p11_i J
    lload 166
    putstatic rung36_jcon_args/icn_pv_p11_h J
    lload 168
    putstatic rung36_jcon_args/icn_pv_p11_g J
    lload 170
    putstatic rung36_jcon_args/icn_pv_p11_f J
    lload 172
    putstatic rung36_jcon_args/icn_pv_p11_e J
    lload 174
    putstatic rung36_jcon_args/icn_pv_p11_d J
    lload 176
    putstatic rung36_jcon_args/icn_pv_p11_c J
    lload 178
    putstatic rung36_jcon_args/icn_pv_p11_b J
    lload 180
    putstatic rung36_jcon_args/icn_pv_p11_a J
    getstatic rung36_jcon_args/icn_failed B
    ifne icn_152_after_call
    getstatic rung36_jcon_args/icn_retval J
    goto icn_p11_s0_sdrain
icn_152_after_call:
    goto icn_p11_done
icn_p11_s0_sdrain:
    pop2
    goto icn_p11_done
icn_p11_done:
    iconst_0
    putstatic rung36_jcon_args/icn_suspended B
    iconst_0
    putstatic rung36_jcon_args/icn_suspend_id I
    iconst_1
    putstatic rung36_jcon_args/icn_failed B
    return
icn_p11_ret:
    iconst_0
    putstatic rung36_jcon_args/icn_failed B
    return
icn_p11_sret:
    return
.end method

.method public static icn_p12()V
    .limit stack 16
    .limit locals 436
    lconst_0
    lstore 0
    lconst_0
    lstore 2
    lconst_0
    lstore 4
    lconst_0
    lstore 6
    lconst_0
    lstore 8
    lconst_0
    lstore 10
    lconst_0
    lstore 12
    lconst_0
    lstore 14
    lconst_0
    lstore 16
    lconst_0
    lstore 18
    lconst_0
    lstore 20
    lconst_0
    lstore 22
    lconst_0
    lstore 24
    lconst_0
    lstore 26
    lconst_0
    lstore 28
    lconst_0
    lstore 30
    lconst_0
    lstore 32
    lconst_0
    lstore 34
    lconst_0
    lstore 36
    lconst_0
    lstore 38
    lconst_0
    lstore 40
    lconst_0
    lstore 42
    lconst_0
    lstore 44
    lconst_0
    lstore 46
    lconst_0
    lstore 48
    lconst_0
    lstore 50
    lconst_0
    lstore 52
    lconst_0
    lstore 54
    lconst_0
    lstore 56
    lconst_0
    lstore 58
    lconst_0
    lstore 60
    lconst_0
    lstore 62
    iconst_0
    istore 84
    iconst_0
    istore 85
    iconst_0
    istore 86
    iconst_0
    istore 87
    aconst_null
    astore 148
    aconst_null
    astore 149
    aconst_null
    astore 150
    aconst_null
    astore 151
    getstatic rung36_jcon_args/icn_arg_str_0 Ljava/lang/String;
    putstatic rung36_jcon_args/icn_pv_p12_a Ljava/lang/String;
    getstatic rung36_jcon_args/icn_arg_1 J
    putstatic rung36_jcon_args/icn_pv_p12_b J
    getstatic rung36_jcon_args/icn_arg_2 J
    putstatic rung36_jcon_args/icn_pv_p12_c J
    getstatic rung36_jcon_args/icn_arg_3 J
    putstatic rung36_jcon_args/icn_pv_p12_d J
    getstatic rung36_jcon_args/icn_arg_4 J
    putstatic rung36_jcon_args/icn_pv_p12_e J
    getstatic rung36_jcon_args/icn_arg_str_5 Ljava/lang/String;
    putstatic rung36_jcon_args/icn_pv_p12_f Ljava/lang/String;
    getstatic rung36_jcon_args/icn_arg_6 J
    putstatic rung36_jcon_args/icn_pv_p12_g J
    getstatic rung36_jcon_args/icn_arg_7 J
    putstatic rung36_jcon_args/icn_pv_p12_h J
    getstatic rung36_jcon_args/icn_arg_8 J
    putstatic rung36_jcon_args/icn_pv_p12_i J
    getstatic rung36_jcon_args/icn_arg_9 J
    putstatic rung36_jcon_args/icn_pv_p12_j J
    getstatic rung36_jcon_args/icn_arg_10 J
    putstatic rung36_jcon_args/icn_pv_p12_k J
    getstatic rung36_jcon_args/icn_arg_11 J
    putstatic rung36_jcon_args/icn_pv_p12_l J
    goto icn_165_α
;  VAR
icn_166_α:
    getstatic rung36_jcon_args/icn_pv_p12_l J
    goto icn_165_arg12
icn_166_β:
    goto icn_p12_done
icn_165_arg12:
    putstatic rung36_jcon_args/icn_arg_12 J
    goto icn_165_docall
;  VAR
icn_167_α:
    getstatic rung36_jcon_args/icn_pv_p12_k J
    goto icn_165_arg11
icn_167_β:
    goto icn_p12_done
icn_165_arg11:
    putstatic rung36_jcon_args/icn_arg_11 J
    goto icn_166_α
;  VAR
icn_168_α:
    getstatic rung36_jcon_args/icn_pv_p12_j J
    goto icn_165_arg10
icn_168_β:
    goto icn_p12_done
icn_165_arg10:
    putstatic rung36_jcon_args/icn_arg_10 J
    goto icn_167_α
;  VAR
icn_169_α:
    getstatic rung36_jcon_args/icn_pv_p12_i J
    goto icn_165_arg9
icn_169_β:
    goto icn_p12_done
icn_165_arg9:
    putstatic rung36_jcon_args/icn_arg_9 J
    goto icn_168_α
;  VAR
icn_170_α:
    getstatic rung36_jcon_args/icn_pv_p12_h J
    goto icn_165_arg8
icn_170_β:
    goto icn_p12_done
icn_165_arg8:
    putstatic rung36_jcon_args/icn_arg_8 J
    goto icn_169_α
;  VAR
icn_171_α:
    getstatic rung36_jcon_args/icn_pv_p12_g J
    goto icn_165_arg7
icn_171_β:
    goto icn_p12_done
icn_165_arg7:
    putstatic rung36_jcon_args/icn_arg_7 J
    goto icn_170_α
;  VAR
icn_172_α:
    getstatic rung36_jcon_args/icn_pv_p12_f J
    goto icn_165_arg6
icn_172_β:
    goto icn_p12_done
icn_165_arg6:
    putstatic rung36_jcon_args/icn_arg_6 J
    goto icn_171_α
;  VAR
icn_173_α:
    getstatic rung36_jcon_args/icn_pv_p12_e J
    goto icn_165_arg5
icn_173_β:
    goto icn_p12_done
icn_165_arg5:
    putstatic rung36_jcon_args/icn_arg_str_5 Ljava/lang/String;
    lconst_0
    putstatic rung36_jcon_args/icn_arg_5 J
    goto icn_172_α
;  VAR
icn_174_α:
    getstatic rung36_jcon_args/icn_pv_p12_d J
    goto icn_165_arg4
icn_174_β:
    goto icn_p12_done
icn_165_arg4:
    putstatic rung36_jcon_args/icn_arg_4 J
    goto icn_173_α
;  VAR
icn_175_α:
    getstatic rung36_jcon_args/icn_pv_p12_c J
    goto icn_165_arg3
icn_175_β:
    goto icn_p12_done
icn_165_arg3:
    putstatic rung36_jcon_args/icn_arg_3 J
    goto icn_174_α
;  VAR
icn_176_α:
    getstatic rung36_jcon_args/icn_pv_p12_b J
    goto icn_165_arg2
icn_176_β:
    goto icn_p12_done
icn_165_arg2:
    putstatic rung36_jcon_args/icn_arg_2 J
    goto icn_175_α
;  VAR
icn_177_α:
    getstatic rung36_jcon_args/icn_pv_p12_a J
    goto icn_165_arg1
icn_177_β:
    goto icn_p12_done
icn_165_arg1:
    putstatic rung36_jcon_args/icn_arg_1 J
    goto icn_176_α
;  STR
icn_178_α:
    ldc "p12"
    goto icn_165_arg0
icn_178_β:
    goto icn_p12_done
icn_165_arg0:
    putstatic rung36_jcon_args/icn_arg_str_0 Ljava/lang/String;
    lconst_0
    putstatic rung36_jcon_args/icn_arg_0 J
    goto icn_177_α
icn_165_α:
    goto icn_178_α
icn_165_β:
    goto icn_166_β
icn_165_docall:
    getstatic rung36_jcon_args/icn_1_relop_lc J
    lstore 152
    getstatic rung36_jcon_args/icn_1_relop_rc J
    lstore 154
    getstatic rung36_jcon_args/icn_10_binop_lc J
    lstore 156
    getstatic rung36_jcon_args/icn_10_binop_rc J
    lstore 158
    getstatic rung36_jcon_args/icn_pv_p12_l J
    lstore 160
    getstatic rung36_jcon_args/icn_pv_p12_k J
    lstore 162
    getstatic rung36_jcon_args/icn_pv_p12_j J
    lstore 164
    getstatic rung36_jcon_args/icn_pv_p12_i J
    lstore 166
    getstatic rung36_jcon_args/icn_pv_p12_h J
    lstore 168
    getstatic rung36_jcon_args/icn_pv_p12_g J
    lstore 170
    getstatic rung36_jcon_args/icn_pv_p12_f J
    lstore 172
    getstatic rung36_jcon_args/icn_pv_p12_e J
    lstore 174
    getstatic rung36_jcon_args/icn_pv_p12_d J
    lstore 176
    getstatic rung36_jcon_args/icn_pv_p12_c J
    lstore 178
    getstatic rung36_jcon_args/icn_pv_p12_b J
    lstore 180
    getstatic rung36_jcon_args/icn_pv_p12_a J
    lstore 182
    invokestatic rung36_jcon_args/icn_note()V
    lload 152
    putstatic rung36_jcon_args/icn_1_relop_lc J
    lload 154
    putstatic rung36_jcon_args/icn_1_relop_rc J
    lload 156
    putstatic rung36_jcon_args/icn_10_binop_lc J
    lload 158
    putstatic rung36_jcon_args/icn_10_binop_rc J
    lload 160
    putstatic rung36_jcon_args/icn_pv_p12_l J
    lload 162
    putstatic rung36_jcon_args/icn_pv_p12_k J
    lload 164
    putstatic rung36_jcon_args/icn_pv_p12_j J
    lload 166
    putstatic rung36_jcon_args/icn_pv_p12_i J
    lload 168
    putstatic rung36_jcon_args/icn_pv_p12_h J
    lload 170
    putstatic rung36_jcon_args/icn_pv_p12_g J
    lload 172
    putstatic rung36_jcon_args/icn_pv_p12_f J
    lload 174
    putstatic rung36_jcon_args/icn_pv_p12_e J
    lload 176
    putstatic rung36_jcon_args/icn_pv_p12_d J
    lload 178
    putstatic rung36_jcon_args/icn_pv_p12_c J
    lload 180
    putstatic rung36_jcon_args/icn_pv_p12_b J
    lload 182
    putstatic rung36_jcon_args/icn_pv_p12_a J
    getstatic rung36_jcon_args/icn_failed B
    ifne icn_165_after_call
    getstatic rung36_jcon_args/icn_retval J
    goto icn_p12_s0_sdrain
icn_165_after_call:
    goto icn_p12_done
icn_p12_s0_sdrain:
    pop2
    goto icn_p12_done
icn_p12_done:
    iconst_0
    putstatic rung36_jcon_args/icn_suspended B
    iconst_0
    putstatic rung36_jcon_args/icn_suspend_id I
    iconst_1
    putstatic rung36_jcon_args/icn_failed B
    return
icn_p12_ret:
    iconst_0
    putstatic rung36_jcon_args/icn_failed B
    return
icn_p12_sret:
    return
.end method

.method public static icn_note()V
    .limit stack 16
    .limit locals 440
    lconst_0
    lstore 0
    lconst_0
    lstore 2
    lconst_0
    lstore 4
    lconst_0
    lstore 6
    lconst_0
    lstore 8
    lconst_0
    lstore 10
    lconst_0
    lstore 12
    lconst_0
    lstore 14
    lconst_0
    lstore 16
    lconst_0
    lstore 18
    lconst_0
    lstore 20
    lconst_0
    lstore 22
    lconst_0
    lstore 24
    lconst_0
    lstore 26
    lconst_0
    lstore 28
    lconst_0
    lstore 30
    lconst_0
    lstore 32
    lconst_0
    lstore 34
    lconst_0
    lstore 36
    lconst_0
    lstore 38
    lconst_0
    lstore 40
    lconst_0
    lstore 42
    lconst_0
    lstore 44
    lconst_0
    lstore 46
    lconst_0
    lstore 48
    lconst_0
    lstore 50
    lconst_0
    lstore 52
    lconst_0
    lstore 54
    lconst_0
    lstore 56
    lconst_0
    lstore 58
    lconst_0
    lstore 60
    lconst_0
    lstore 62
    iconst_0
    istore 84
    iconst_0
    istore 85
    iconst_0
    istore 86
    iconst_0
    istore 87
    aconst_null
    astore 148
    aconst_null
    astore 149
    aconst_null
    astore 150
    aconst_null
    astore 151
    getstatic rung36_jcon_args/icn_arg_str_0 Ljava/lang/String;
    putstatic rung36_jcon_args/icn_pv_note_a Ljava/lang/String;
    goto icn_181_α
icn_179_α:
    lconst_0
    putstatic rung36_jcon_args/icn_retval J
    iconst_0
    putstatic rung36_jcon_args/icn_failed B
    goto icn_note_ret
icn_179_β:
    goto icn_note_ret
icn_180_α:
    getstatic java/lang/System/out Ljava/io/PrintStream;
    ldc ""
    invokevirtual java/io/PrintStream/println(Ljava/lang/String;)V
    goto icn_note_s2_sdrain
icn_180_β:
    goto icn_179_α
icn_note_s2_sdrain:
    pop2
    goto icn_179_α
icn_182_α:
    goto icn_181_pump
icn_182_β:
    goto icn_181_pump
;  VAR
icn_185_α:
    getstatic rung36_jcon_args/icn_pv_note_a Ljava/lang/String;
    goto icn_184_bang_adv
icn_185_β:
    goto icn_180_α
icn_184_α:
    goto icn_185_α
icn_184_β:
    goto icn_184_bang_chk
icn_184_bang_adv:
    putstatic rung36_jcon_args/icn_184_bang_str Ljava/lang/String;
    iconst_0
    putstatic rung36_jcon_args/icn_184_bang_pos I
icn_184_bang_chk:
    getstatic rung36_jcon_args/icn_184_bang_str Ljava/lang/String;
    invokevirtual java/lang/String/length()I
    getstatic rung36_jcon_args/icn_184_bang_pos I
    if_icmple icn_180_α
    getstatic rung36_jcon_args/icn_184_bang_str Ljava/lang/String;
    getstatic rung36_jcon_args/icn_184_bang_pos I
    getstatic rung36_jcon_args/icn_184_bang_pos I
    iconst_1
    iadd
    invokevirtual java/lang/String/substring(II)Ljava/lang/String;
    getstatic rung36_jcon_args/icn_184_bang_pos I
    iconst_1
    iadd
    putstatic rung36_jcon_args/icn_184_bang_pos I
    goto icn_183_store
icn_183_α:
    goto icn_184_α
icn_183_β:
    goto icn_184_β
icn_183_store:
    putstatic rung36_jcon_args/icn_pv_note_e Ljava/lang/String;
    getstatic rung36_jcon_args/icn_pv_note_e Ljava/lang/String;
    goto icn_181_gdrain
icn_181_gdrain:
    pop
    goto icn_182_α
icn_181_bdrain:
    pop2
icn_181_pump:
    goto icn_183_β
icn_181_α:
    goto icn_183_α
icn_181_β:
    goto icn_180_α
icn_note_done:
    iconst_0
    putstatic rung36_jcon_args/icn_suspended B
    iconst_0
    putstatic rung36_jcon_args/icn_suspend_id I
    iconst_1
    putstatic rung36_jcon_args/icn_failed B
    return
icn_note_ret:
    iconst_0
    putstatic rung36_jcon_args/icn_failed B
    return
icn_note_sret:
    return
.end method

