; Auto-generated by icon_emit_jvm.c — Tiny-ICON Byrd Box JVM
.bytecode 45.0
.class public rung36_jcon_table
.super java/lang/Object

.field public static icn_failed B
.field public static icn_suspended B
.field public static icn_suspend_id I
.field public static icn_retval_obj Ljava/lang/Object;
.field public static icn_retval J
.field public static icn_retval_str Ljava/lang/String;
.field public static icn_arg_str_0 Ljava/lang/String;
.field public static icn_pv_tdump_label Ljava/lang/String;
.field public static icn_pv_main_x Ljava/util/HashMap;
.field public static icn_pv_main_x_dflt Ljava/lang/Object;
.field public static icn_pv_main_y J
.field public static icn_arg_1 J
.field public static icn_arg_0 J
.field public static icn_16_tsa_vl J
.field public static icn_16_tsa_vo Ljava/lang/Object;
.field public static icn_16_tsa_ks Ljava/lang/String;
.field public static icn_17_binop_lc J
.field public static icn_17_binop_rc J
.field public static icn_17_binop_bf I
.field public static icn_pv_main_k J
.field public static icn_22_I J
.field public static icn_22_bound J
.field public static icn_22_e1cur J
.field public static icn_22_e2seen I
.field public static icn_22_e1val J
.field public static icn_22_e2val J
.field public static icn_30_bang_str Ljava/lang/String;
.field public static icn_30_bang_pos I
.field public static icn_35_ktbl Ljava/util/HashMap;
.field public static icn_35_karr [Ljava/lang/Object;
.field public static icn_35_kidx I
.field public static icn_35_kinit I
.field public static icn_38_tsa_vl J
.field public static icn_38_tsa_vo Ljava/lang/Object;
.field public static icn_38_tsa_ks Ljava/lang/String;
.field public static icn_42_tbl Ljava/util/HashMap;
.field public static icn_42_tdflt Ljava/lang/Object;
.field public static icn_48_alt_gate I
.field public static icn_51_dtbl Ljava/util/HashMap;
.field public static icn_51_dkey Ljava/lang/String;
.field public static icn_52_dtbl Ljava/util/HashMap;
.field public static icn_52_dkey Ljava/lang/String;
.field public static icn_48_alt_val J
.field public static icn_56_alt_gate I
.field public static icn_59_dtbl Ljava/util/HashMap;
.field public static icn_59_dkey Ljava/lang/String;
.field public static icn_56_alt_val J
.field public static icn_62_alt_gate I
.field public static icn_62_alt_val J
.field public static icn_69_alt_gate I
.field public static icn_72_itbl2 Ljava/util/HashMap;
.field public static icn_72_ikey2 Ljava/lang/String;
.field public static icn_72_ival2 Ljava/lang/Object;
.field public static icn_69_alt_val J
.field public static icn_76_alt_gate I
.field public static icn_79_itbl2 Ljava/util/HashMap;
.field public static icn_79_ikey2 Ljava/lang/String;
.field public static icn_79_ival2 Ljava/lang/Object;
.field public static icn_80_itbl2 Ljava/util/HashMap;
.field public static icn_80_ikey2 Ljava/lang/String;
.field public static icn_80_ival2 Ljava/lang/Object;
.field public static icn_76_alt_val J
.field public static icn_86_alt_gate I
.field public static icn_89_itbl2 Ljava/util/HashMap;
.field public static icn_89_ikey2 Ljava/lang/String;
.field public static icn_89_ival2 Ljava/lang/Object;
.field public static icn_86_alt_val J
.field public static icn_93_alt_gate I
.field public static icn_96_itbl2 Ljava/util/HashMap;
.field public static icn_96_ikey2 Ljava/lang/String;
.field public static icn_96_ival2 Ljava/lang/Object;
.field public static icn_93_alt_val J
.field public static icn_100_alt_gate I
.field public static icn_100_alt_val J
.field public static icn_104_alt_gate I
.field public static icn_104_alt_val J
.field public static icn_112_ts_tbl Ljava/util/HashMap;
.field public static icn_112_ts_key Ljava/lang/String;
.field public static icn_112_ts_kval J
.field public static icn_116_tbl Ljava/util/HashMap;
.field public static icn_116_tdflt Ljava/lang/Object;
.field public static icn_121_alt_gate I
.field public static icn_124_dtbl Ljava/util/HashMap;
.field public static icn_124_dkey Ljava/lang/String;
.field public static icn_125_dtbl Ljava/util/HashMap;
.field public static icn_125_dkey Ljava/lang/String;
.field public static icn_121_alt_val J
.field public static icn_129_alt_gate I
.field public static icn_132_dtbl Ljava/util/HashMap;
.field public static icn_132_dkey Ljava/lang/String;
.field public static icn_129_alt_val J
.field public static icn_135_alt_gate I
.field public static icn_135_alt_val J
.field public static icn_147_alt_gate I
.field public static icn_150_itbl2 Ljava/util/HashMap;
.field public static icn_150_ikey2 Ljava/lang/String;
.field public static icn_150_ival2 Ljava/lang/Object;
.field public static icn_147_alt_val J
.field public static icn_154_alt_gate I
.field public static icn_157_itbl2 Ljava/util/HashMap;
.field public static icn_157_ikey2 Ljava/lang/String;
.field public static icn_157_ival2 Ljava/lang/Object;
.field public static icn_158_itbl2 Ljava/util/HashMap;
.field public static icn_158_ikey2 Ljava/lang/String;
.field public static icn_158_ival2 Ljava/lang/Object;
.field public static icn_154_alt_val J
.field public static icn_164_alt_gate I
.field public static icn_167_itbl2 Ljava/util/HashMap;
.field public static icn_167_ikey2 Ljava/lang/String;
.field public static icn_167_ival2 Ljava/lang/Object;
.field public static icn_164_alt_val J
.field public static icn_171_alt_gate I
.field public static icn_174_itbl2 Ljava/util/HashMap;
.field public static icn_174_ikey2 Ljava/lang/String;
.field public static icn_174_ival2 Ljava/lang/Object;
.field public static icn_171_alt_val J
.field public static icn_178_alt_gate I
.field public static icn_178_alt_val J
.field public static icn_182_alt_gate I
.field public static icn_182_alt_val J
.field public static icn_192_alt_gate I
.field public static icn_196_ts_tbl Ljava/util/HashMap;
.field public static icn_196_ts_key Ljava/lang/String;
.field public static icn_196_ts_kval J
.field public static icn_192_alt_val J
.field public static icn_199_alt_gate I
.field public static icn_203_ts_tbl Ljava/util/HashMap;
.field public static icn_203_ts_key Ljava/lang/String;
.field public static icn_203_ts_kval J
.field public static icn_199_alt_val J
.field public static icn_210_tsa_vl J
.field public static icn_210_tsa_vo Ljava/lang/Object;
.field public static icn_210_tsa_ks Ljava/lang/String;
.field public static icn_214_ktbl Ljava/util/HashMap;
.field public static icn_214_karr [Ljava/lang/Object;
.field public static icn_214_kidx I
.field public static icn_214_kinit I
.field public static icn_220_tsa_vl J
.field public static icn_220_tsa_vo Ljava/lang/Object;
.field public static icn_220_tsa_ks Ljava/lang/String;
.field public static icn_222_ktbl Ljava/util/HashMap;
.field public static icn_222_karr [Ljava/lang/Object;
.field public static icn_222_kidx I
.field public static icn_222_kinit I
.field public static icn_233_tsa_vl Ljava/lang/String;
.field public static icn_233_tsa_vo Ljava/lang/Object;
.field public static icn_233_tsa_ks Ljava/lang/String;
.field public static icn_236_tsa_vl J
.field public static icn_236_tsa_vo Ljava/lang/Object;
.field public static icn_236_tsa_ks Ljava/lang/String;
.field public static icn_241_tsa_vl J
.field public static icn_241_tsa_vo Ljava/lang/Object;
.field public static icn_241_tsa_ks Ljava/lang/String;
.field public static icn_258_alt_gate I
.field public static icn_260_mtbl Ljava/util/HashMap;
.field public static icn_260_mkey Ljava/lang/String;
.field public static icn_260_mkeyv J
.field public static icn_pv_tdump_T J
.field public static icn_pv_tdump_x J
.field public static icn_258_alt_val J
.field public static icn_264_mtbl Ljava/util/HashMap;
.field public static icn_264_mkey Ljava/lang/String;
.field public static icn_264_mkeyv J
.field public static icn_263_and_drain_0 J
.field public static icn_268_id_lc J
.field public static icn_268_id_rc J
.field public static icn_269_ktbl Ljava/util/HashMap;
.field public static icn_269_karr [Ljava/lang/Object;
.field public static icn_269_kidx I
.field public static icn_269_kinit I
.field public static icn_273_alt_gate I
.field public static icn_274_bang_str Ljava/lang/String;
.field public static icn_274_bang_pos I
.field public static icn_276_I J
.field public static icn_276_bound J
.field public static icn_276_e1cur J
.field public static icn_276_e2seen I
.field public static icn_276_e1val J
.field public static icn_276_e2val J
.field public static icn_273_alt_val J

.method public static main([Ljava/lang/String;)V
    .limit stack 4
    .limit locals 1
    invokestatic rung36_jcon_table/icn_main()V
    return
.end method

.method public static icn_builtin_left(Ljava/lang/String;ILjava/lang/String;)Ljava/lang/String;
    .limit stack 4
    .limit locals 5
    aload_0
    invokevirtual java/lang/String/length()I
    iload_1
    if_icmplt icn_left_pad
    aload_0
    iconst_0
    iload_1
    invokevirtual java/lang/String/substring(II)Ljava/lang/String;
    areturn
icn_left_pad:
    new java/lang/StringBuilder
    dup
    aload_0
    invokespecial java/lang/StringBuilder/<init>(Ljava/lang/String;)V
    astore_3
icn_left_loop:
    aload_3
    invokevirtual java/lang/StringBuilder/length()I
    iload_1
    if_icmpge icn_left_done
    aload_3
    aload_2
    iconst_0
    invokevirtual java/lang/String/charAt(I)C
    invokevirtual java/lang/StringBuilder/append(C)Ljava/lang/StringBuilder;
    pop
    goto icn_left_loop
icn_left_done:
    aload_3
    invokevirtual java/lang/StringBuilder/toString()Ljava/lang/String;
    areturn
.end method

.method public static icn_builtin_right(Ljava/lang/String;ILjava/lang/String;)Ljava/lang/String;
    .limit stack 4
    .limit locals 5
    aload_0
    invokevirtual java/lang/String/length()I
    iload_1
    if_icmplt icn_right_pad
    aload_0
    invokevirtual java/lang/String/length()I
    iload_1
    isub
    aload_0
    swap
    invokevirtual java/lang/String/substring(I)Ljava/lang/String;
    areturn
icn_right_pad:
    new java/lang/StringBuilder
    dup
    invokespecial java/lang/StringBuilder/<init>()V
    astore_3
    iload_1
    aload_0
    invokevirtual java/lang/String/length()I
    isub
    istore 4
    iconst_0
icn_right_loop:
    dup
    iload 4
    if_icmpge icn_right_append
    aload_3
    aload_2
    iconst_0
    invokevirtual java/lang/String/charAt(I)C
    invokevirtual java/lang/StringBuilder/append(C)Ljava/lang/StringBuilder;
    pop
    iconst_1
    iadd
    goto icn_right_loop
icn_right_append:
    pop
    aload_3
    aload_0
    invokevirtual java/lang/StringBuilder/append(Ljava/lang/String;)Ljava/lang/StringBuilder;
    pop
    aload_3
    invokevirtual java/lang/StringBuilder/toString()Ljava/lang/String;
    areturn
.end method

.method public static icn_builtin_center(Ljava/lang/String;ILjava/lang/String;)Ljava/lang/String;
    .limit stack 5
    .limit locals 7
    aload_0
    invokevirtual java/lang/String/length()I
    iload_1
    if_icmplt icn_ctr_pad
    aload_0
    iconst_0
    iload_1
    invokevirtual java/lang/String/substring(II)Ljava/lang/String;
    areturn
icn_ctr_pad:
    iload_1
    aload_0
    invokevirtual java/lang/String/length()I
    isub
    istore_3
    iload_3
    iconst_2
    idiv
    istore 4
    iload_3
    iload 4
    isub
    istore 5
    new java/lang/StringBuilder
    dup
    invokespecial java/lang/StringBuilder/<init>()V
    astore 6
    iconst_0
icn_ctr_lloop:
    dup
    iload 4
    if_icmpge icn_ctr_mid
    aload 6
    aload_2
    iconst_0
    invokevirtual java/lang/String/charAt(I)C
    invokevirtual java/lang/StringBuilder/append(C)Ljava/lang/StringBuilder;
    pop
    iconst_1
    iadd
    goto icn_ctr_lloop
icn_ctr_mid:
    pop
    aload 6
    aload_0
    invokevirtual java/lang/StringBuilder/append(Ljava/lang/String;)Ljava/lang/StringBuilder;
    pop
    iconst_0
icn_ctr_rloop:
    dup
    iload 5
    if_icmpge icn_ctr_done
    aload 6
    aload_2
    iconst_0
    invokevirtual java/lang/String/charAt(I)C
    invokevirtual java/lang/StringBuilder/append(C)Ljava/lang/StringBuilder;
    pop
    iconst_1
    iadd
    goto icn_ctr_rloop
icn_ctr_done:
    pop
    aload 6
    invokevirtual java/lang/StringBuilder/toString()Ljava/lang/String;
    areturn
.end method

.method public static icn_builtin_trim(Ljava/lang/String;Ljava/lang/String;)Ljava/lang/String;
    .limit stack 4
    .limit locals 3
    aload_0
    invokevirtual java/lang/String/length()I
    istore_2
icn_trim_loop:
    iload_2
    ifle icn_trim_done
    aload_1
    aload_0
    iload_2
    iconst_1
    isub
    invokevirtual java/lang/String/charAt(I)C
    invokevirtual java/lang/String/indexOf(I)I
    iflt icn_trim_done
    iinc 2 -1
    goto icn_trim_loop
icn_trim_done:
    aload_0
    iconst_0
    iload_2
    invokevirtual java/lang/String/substring(II)Ljava/lang/String;
    areturn
.end method

.method public static icn_builtin_map(Ljava/lang/String;Ljava/lang/String;Ljava/lang/String;)Ljava/lang/String;
    .limit stack 5
    .limit locals 7
    new java/lang/StringBuilder
    dup
    invokespecial java/lang/StringBuilder/<init>()V
    astore_3
    iconst_0
    istore 4
icn_map_loop:
    iload 4
    aload_0
    invokevirtual java/lang/String/length()I
    if_icmpge icn_map_done
    aload_0
    iload 4
    invokevirtual java/lang/String/charAt(I)C
    istore 5
    aload_1
    iload 5
    invokevirtual java/lang/String/indexOf(I)I
    istore 6
    iload 6
    iflt icn_map_notfound
    iload 6
    aload_2
    invokevirtual java/lang/String/length()I
    if_icmpge icn_map_notfound
    aload_3
    aload_2
    iload 6
    invokevirtual java/lang/String/charAt(I)C
    invokevirtual java/lang/StringBuilder/append(C)Ljava/lang/StringBuilder;
    pop
    goto icn_map_next
icn_map_notfound:
    aload_3
    iload 5
    invokevirtual java/lang/StringBuilder/append(C)Ljava/lang/StringBuilder;
    pop
icn_map_next:
    iinc 4 1
    goto icn_map_loop
icn_map_done:
    aload_3
    invokevirtual java/lang/StringBuilder/toString()Ljava/lang/String;
    areturn
.end method

.method public static icn_builtin_parse_long(Ljava/lang/String;)J
    .limit stack 4
    .limit locals 4
    .catch java/lang/Exception from icn_plong_L0 to icn_plong_L1 using icn_plong_catch
icn_plong_L0:
    aload_0
    invokevirtual java/lang/String/trim()Ljava/lang/String;
    astore_1
    aload_1
    ldc "r"
    invokevirtual java/lang/String/contains(Ljava/lang/CharSequence;)Z
    ifeq icn_plong_plain
    aload_1
    ldc "r"
    iconst_2
    invokevirtual java/lang/String/split(Ljava/lang/String;I)[Ljava/lang/String;
    astore_2
    aload_2
    iconst_0
    aaload
    invokestatic java/lang/Integer/parseInt(Ljava/lang/String;)I
    istore_3
    aload_2
    iconst_1
    aaload
    iload_3
    invokestatic java/lang/Long/parseLong(Ljava/lang/String;I)J
    goto icn_plong_L1
icn_plong_plain:
    aload_1
    invokestatic java/lang/Long/parseLong(Ljava/lang/String;)J
icn_plong_L1:
    lreturn
icn_plong_catch:
    pop
    ldc2_w -9223372036854775808
    lreturn
.end method

.method public static icn_builtin_numeric(Ljava/lang/String;)J
    .limit stack 2
    .limit locals 2
    aload_0
    invokestatic rung36_jcon_table/icn_builtin_parse_long(Ljava/lang/String;)J
    lreturn
.end method

.method public static icn_builtin_sort(Ljava/util/ArrayList;)Ljava/util/ArrayList;
    .limit stack 6
    .limit locals 8
    new java/util/ArrayList
    dup
    aload_0
    invokespecial java/util/ArrayList/<init>(Ljava/util/Collection;)V
    astore_1
    iconst_1
    istore_2
icn_sort_outer:
    aload_1
    invokevirtual java/util/ArrayList/size()I
    iload_2
    if_icmple icn_sort_done
    aload_1
    iload_2
    invokevirtual java/util/ArrayList/get(I)Ljava/lang/Object;
    checkcast java/lang/Long
    invokevirtual java/lang/Long/longValue()J
    lstore 4
    iload_2
    iconst_1
    isub
    istore_3
icn_sort_inner:
    iload_3
    iflt icn_sort_insert
    aload_1
    iload_3
    invokevirtual java/util/ArrayList/get(I)Ljava/lang/Object;
    checkcast java/lang/Long
    invokevirtual java/lang/Long/longValue()J
    lload 4
    lcmp
    ifle icn_sort_insert
    aload_1
    iload_3
    iconst_1
    iadd
    aload_1
    iload_3
    invokevirtual java/util/ArrayList/get(I)Ljava/lang/Object;
    invokevirtual java/util/ArrayList/set(ILjava/lang/Object;)Ljava/lang/Object;
    pop
    iinc 3 -1
    goto icn_sort_inner
icn_sort_insert:
    aload_1
    iload_3
    iconst_1
    iadd
    lload 4
    invokestatic java/lang/Long/valueOf(J)Ljava/lang/Long;
    invokevirtual java/util/ArrayList/set(ILjava/lang/Object;)Ljava/lang/Object;
    pop
    iinc 2 1
    goto icn_sort_outer
icn_sort_done:
    aload_1
    areturn
.end method

.method public static icn_builtin_sortf(Ljava/util/ArrayList;I)Ljava/util/ArrayList;
    .limit stack 8
    .limit locals 10
    new java/util/ArrayList
    dup
    aload_0
    invokespecial java/util/ArrayList/<init>(Ljava/util/Collection;)V
    astore_2
    iconst_1
    istore_3
icn_sortf_outer:
    aload_2
    invokevirtual java/util/ArrayList/size()I
    iload_3
    if_icmple icn_sortf_done
    aload_2
    iload_3
    invokevirtual java/util/ArrayList/get(I)Ljava/lang/Object;
    astore 5
    iload_3
    iconst_1
    isub
    istore 4
icn_sortf_inner:
    iload 4
    iflt icn_sortf_insert
    aload_2
    iload 4
    invokevirtual java/util/ArrayList/get(I)Ljava/lang/Object;
    astore 6
    aload 6
    invokevirtual java/lang/Object/getClass()Ljava/lang/Class;
    invokevirtual java/lang/Class/getDeclaredFields()[Ljava/lang/reflect/Field;
    iload_1
    iconst_1
    isub
    aaload
    aload 6
    invokevirtual java/lang/reflect/Field/get(Ljava/lang/Object;)Ljava/lang/Object;
    astore 7
    aload 5
    invokevirtual java/lang/Object/getClass()Ljava/lang/Class;
    invokevirtual java/lang/Class/getDeclaredFields()[Ljava/lang/reflect/Field;
    iload_1
    iconst_1
    isub
    aaload
    aload 5
    invokevirtual java/lang/reflect/Field/get(Ljava/lang/Object;)Ljava/lang/Object;
    astore 8
    aload 7
    checkcast java/lang/Long
    aload 8
    checkcast java/lang/Long
    invokevirtual java/lang/Long/compareTo(Ljava/lang/Long;)I
    ifle icn_sortf_insert
    aload_2
    iload 4
    iconst_1
    iadd
    aload_2
    iload 4
    invokevirtual java/util/ArrayList/get(I)Ljava/lang/Object;
    invokevirtual java/util/ArrayList/set(ILjava/lang/Object;)Ljava/lang/Object;
    pop
    iinc 4 -1
    goto icn_sortf_inner
icn_sortf_insert:
    aload_2
    iload 4
    iconst_1
    iadd
    aload 5
    invokevirtual java/util/ArrayList/set(ILjava/lang/Object;)Ljava/lang/Object;
    pop
    iinc 3 1
    goto icn_sortf_outer
icn_sortf_done:
    aload_2
    areturn
.end method

.method public static icn_main()V
    .limit stack 16
    .limit locals 481
    lconst_0
    lstore 0
    lconst_0
    lstore 2
    lconst_0
    lstore 4
    lconst_0
    lstore 6
    lconst_0
    lstore 8
    lconst_0
    lstore 10
    lconst_0
    lstore 12
    lconst_0
    lstore 14
    lconst_0
    lstore 16
    lconst_0
    lstore 18
    lconst_0
    lstore 20
    lconst_0
    lstore 22
    lconst_0
    lstore 24
    lconst_0
    lstore 26
    lconst_0
    lstore 28
    lconst_0
    lstore 30
    lconst_0
    lstore 32
    lconst_0
    lstore 34
    lconst_0
    lstore 36
    lconst_0
    lstore 38
    lconst_0
    lstore 40
    lconst_0
    lstore 42
    lconst_0
    lstore 44
    lconst_0
    lstore 46
    lconst_0
    lstore 48
    lconst_0
    lstore 50
    lconst_0
    lstore 52
    lconst_0
    lstore 54
    lconst_0
    lstore 56
    lconst_0
    lstore 58
    lconst_0
    lstore 60
    lconst_0
    lstore 62
    iconst_0
    istore 84
    iconst_0
    istore 85
    iconst_0
    istore 86
    iconst_0
    istore 87
    aconst_null
    astore 148
    aconst_null
    astore 149
    aconst_null
    astore 150
    aconst_null
    astore 151
    aconst_null
    astore 152
    aconst_null
    astore 153
    aconst_null
    astore 154
    aconst_null
    astore 155
    aconst_null
    astore 156
    aconst_null
    astore 157
    aconst_null
    astore 158
    aconst_null
    astore 159
    aconst_null
    astore 160
    aconst_null
    astore 161
    aconst_null
    astore 162
    aconst_null
    astore 163
    aconst_null
    astore 164
    aconst_null
    astore 165
    aconst_null
    astore 166
    aconst_null
    astore 167
    aconst_null
    astore 168
    aconst_null
    astore 169
    aconst_null
    astore 170
    aconst_null
    astore 171
    aconst_null
    astore 172
    aconst_null
    astore 173
    aconst_null
    astore 174
    aconst_null
    astore 175
    aconst_null
    astore 176
    goto icn_250_α
;  VAR
icn_1_α:
    getstatic rung36_jcon_table/icn_pv_main_y J
    goto icn_0_arg1
icn_1_β:
    goto icn_main_done
icn_0_arg1:
    putstatic rung36_jcon_table/icn_arg_1 J
    goto icn_0_docall
;  STR
icn_2_α:
    ldc "50s"
    goto icn_0_arg0
icn_2_β:
    goto icn_main_done
icn_0_arg0:
    putstatic rung36_jcon_table/icn_arg_str_0 Ljava/lang/String;
    lconst_0
    putstatic rung36_jcon_table/icn_arg_0 J
    goto icn_1_α
icn_0_α:
    goto icn_2_α
icn_0_β:
    goto icn_1_β
icn_0_docall:
    getstatic rung36_jcon_table/icn_pv_main_y J
    lstore 152
    invokestatic rung36_jcon_table/icn_tdump()V
    lload 152
    putstatic rung36_jcon_table/icn_pv_main_y J
    getstatic rung36_jcon_table/icn_failed B
    ifne icn_0_after_call
    getstatic rung36_jcon_table/icn_retval J
    goto icn_main_s57_sdrain
icn_0_after_call:
    goto icn_main_done
icn_main_s57_sdrain:
    pop2
    goto icn_main_done
;  VAR
icn_4_α:
    getstatic rung36_jcon_table/icn_pv_main_x Ljava/util/HashMap;
    goto icn_3_arg1
icn_4_β:
    goto icn_0_α
icn_3_arg1:
    putstatic rung36_jcon_table/icn_arg_1 J
    goto icn_3_docall
;  STR
icn_5_α:
    ldc "30s"
    goto icn_3_arg0
icn_5_β:
    goto icn_0_α
icn_3_arg0:
    putstatic rung36_jcon_table/icn_arg_str_0 Ljava/lang/String;
    lconst_0
    putstatic rung36_jcon_table/icn_arg_0 J
    goto icn_4_α
icn_3_α:
    goto icn_5_α
icn_3_β:
    goto icn_4_β
icn_3_docall:
    getstatic rung36_jcon_table/icn_pv_main_y J
    lstore 152
    invokestatic rung36_jcon_table/icn_tdump()V
    lload 152
    putstatic rung36_jcon_table/icn_pv_main_y J
    getstatic rung36_jcon_table/icn_failed B
    ifne icn_3_after_call
    getstatic rung36_jcon_table/icn_retval J
    goto icn_main_s56_sdrain
icn_3_after_call:
    goto icn_0_α
icn_main_s56_sdrain:
    pop2
    goto icn_0_α
;  INT
icn_8_α:
    ldc2_w 40
    goto icn_7_rhsok
icn_8_β:
    goto icn_3_α
icn_7_α:
    goto icn_8_α
icn_7_β:
    goto icn_8_β
icn_7_rhsok:
    goto icn_6_gdrain
icn_6_gdrain:
    pop2
icn_6_pump:
    goto icn_7_β
icn_6_α:
    goto icn_7_α
icn_6_β:
    goto icn_3_α
;  INT
icn_11_α:
    ldc2_w 20
    goto icn_10_rhsok
icn_11_β:
    goto icn_6_α
icn_10_α:
    goto icn_11_α
icn_10_β:
    goto icn_11_β
icn_10_rhsok:
    goto icn_9_gdrain
icn_9_gdrain:
    pop2
icn_9_pump:
    goto icn_10_β
icn_9_α:
    goto icn_10_α
icn_9_β:
    goto icn_6_α
;  VAR
icn_14_α:
    getstatic rung36_jcon_table/icn_pv_main_x Ljava/util/HashMap;
    goto icn_13_copy_after
icn_14_β:
    goto icn_9_α
icn_13_α:
    goto icn_14_α
icn_13_β:
    goto icn_14_β
icn_13_copy_after:
    goto icn_12_store
icn_12_α:
    goto icn_13_α
icn_12_β:
    goto icn_13_β
icn_12_store:
    putstatic rung36_jcon_table/icn_pv_main_y J
    getstatic rung36_jcon_table/icn_pv_main_y J
    goto icn_main_s53_sdrain
icn_main_s53_sdrain:
    pop2
    goto icn_9_α
;  INT
icn_18_α:
    ldc2_w 10
    goto icn_17_rrelay
icn_18_β:
    goto icn_17_lb
;  VAR
icn_19_α:
    getstatic rung36_jcon_table/icn_pv_main_k J
    goto icn_17_lrelay
icn_19_β:
    goto icn_15_pump
icn_17_lrelay:
    putstatic rung36_jcon_table/icn_17_binop_lc J
    goto icn_17_lstore
icn_17_rrelay:
    putstatic rung36_jcon_table/icn_17_binop_rc J
    goto icn_17_compute
icn_17_lb:
    goto icn_19_β
icn_17_α:
    iconst_0
    putstatic rung36_jcon_table/icn_17_binop_bf I
    goto icn_19_α
icn_17_β:
    iconst_1
    putstatic rung36_jcon_table/icn_17_binop_bf I
    goto icn_19_α
icn_17_lstore:
    getstatic rung36_jcon_table/icn_17_binop_bf I
    ifeq icn_18_α
    goto icn_18_β
icn_17_compute:
    getstatic rung36_jcon_table/icn_17_binop_lc J
    getstatic rung36_jcon_table/icn_17_binop_rc J
    ladd
    goto icn_16_tsa_vr
;  VAR
icn_20_α:
    getstatic rung36_jcon_table/icn_pv_main_k J
    goto icn_16_tsa_kr
icn_20_β:
    goto icn_15_pump
icn_16_α:
    goto icn_17_α
icn_16_β:
    goto icn_15_pump
icn_16_tsa_vr:
    dup2
    putstatic rung36_jcon_table/icn_16_tsa_vl J
    invokestatic java/lang/Long/valueOf(J)Ljava/lang/Long;
    putstatic rung36_jcon_table/icn_16_tsa_vo Ljava/lang/Object;
    goto icn_20_α
icn_16_tsa_kr:
    invokestatic java/lang/Long/toString(J)Ljava/lang/String;
    putstatic rung36_jcon_table/icn_16_tsa_ks Ljava/lang/String;
    goto icn_16_tsa_put
icn_16_tsa_put:
    getstatic rung36_jcon_table/icn_pv_main_x Ljava/util/HashMap;
    getstatic rung36_jcon_table/icn_16_tsa_ks Ljava/lang/String;
    getstatic rung36_jcon_table/icn_16_tsa_vo Ljava/lang/Object;
    invokevirtual java/util/HashMap/put(Ljava/lang/Object;Ljava/lang/Object;)Ljava/lang/Object;
    pop
    getstatic rung36_jcon_table/icn_16_tsa_vl J
    goto icn_15_bdrain
;  INT
icn_23_α:
    ldc2_w 4
    goto icn_22_e2relay
icn_23_β:
    goto icn_22_e1b
;  INT
icn_24_α:
    ldc2_w 0
    goto icn_22_e1relay
icn_24_β:
    goto icn_12_α
icn_22_e1relay:
    putstatic rung36_jcon_table/icn_22_e1val J
    goto icn_23_α
icn_22_e2relay:
    putstatic rung36_jcon_table/icn_22_e2val J
    goto icn_22_init
icn_22_e1b:
    iconst_0
    putstatic rung36_jcon_table/icn_22_e2seen I
    goto icn_24_β
icn_22_e2b:
    goto icn_23_β
icn_22_α:
    iconst_0
    putstatic rung36_jcon_table/icn_22_e2seen I
    goto icn_24_α
icn_22_β:
    getstatic rung36_jcon_table/icn_22_I J
    lconst_1
    ladd
    putstatic rung36_jcon_table/icn_22_I J
    goto icn_22_code
icn_22_init:
    getstatic rung36_jcon_table/icn_22_e2val J
    putstatic rung36_jcon_table/icn_22_bound J
    getstatic rung36_jcon_table/icn_22_e2seen I
    ifne icn_22_init_e2adv
    getstatic rung36_jcon_table/icn_22_e1val J
    putstatic rung36_jcon_table/icn_22_e1cur J
    getstatic rung36_jcon_table/icn_22_e1cur J
    putstatic rung36_jcon_table/icn_22_I J
    iconst_1
    putstatic rung36_jcon_table/icn_22_e2seen I
    goto icn_22_code
icn_22_init_e2adv:
    getstatic rung36_jcon_table/icn_22_e1cur J
    putstatic rung36_jcon_table/icn_22_I J
    goto icn_22_code
icn_22_code:
    getstatic rung36_jcon_table/icn_22_I J
    getstatic rung36_jcon_table/icn_22_bound J
    lcmp
    ifgt icn_22_e2b
    getstatic rung36_jcon_table/icn_22_I J
    goto icn_21_store
icn_21_α:
    goto icn_22_α
icn_21_β:
    goto icn_22_β
icn_21_store:
    putstatic rung36_jcon_table/icn_pv_main_k J
    getstatic rung36_jcon_table/icn_pv_main_k J
    goto icn_15_gdrain
icn_15_gdrain:
    pop2
    goto icn_16_α
icn_15_bdrain:
    pop2
icn_15_pump:
    goto icn_21_β
icn_15_α:
    goto icn_21_α
icn_15_β:
    goto icn_12_α
icn_26_α:
    goto icn_15_α
icn_26_β:
    goto icn_15_α
icn_25_α:
    goto icn_26_α
icn_25_β:
    goto icn_26_β
icn_25_store:
    putstatic rung36_jcon_table/icn_pv_main_x Ljava/util/HashMap;
    getstatic rung36_jcon_table/icn_pv_main_x Ljava/util/HashMap;
    goto icn_main_s51_sdrain
icn_main_s51_sdrain:
    pop
    goto icn_15_α
;  STR
icn_29_α:
    ldc "v "
    goto icn_28_waft_0
icn_29_β:
    goto icn_25_α
;  VAR
icn_31_α:
    getstatic rung36_jcon_table/icn_pv_main_x Ljava/util/HashMap;
    goto icn_30_bang_adv
icn_31_β:
    goto icn_25_α
icn_30_α:
    goto icn_31_α
icn_30_β:
    goto icn_30_bang_chk
icn_30_bang_adv:
    putstatic rung36_jcon_table/icn_30_bang_str Ljava/lang/String;
    iconst_0
    putstatic rung36_jcon_table/icn_30_bang_pos I
icn_30_bang_chk:
    getstatic rung36_jcon_table/icn_30_bang_str Ljava/lang/String;
    invokevirtual java/lang/String/length()I
    getstatic rung36_jcon_table/icn_30_bang_pos I
    if_icmple icn_25_α
    getstatic rung36_jcon_table/icn_30_bang_str Ljava/lang/String;
    getstatic rung36_jcon_table/icn_30_bang_pos I
    getstatic rung36_jcon_table/icn_30_bang_pos I
    iconst_1
    iadd
    invokevirtual java/lang/String/substring(II)Ljava/lang/String;
    getstatic rung36_jcon_table/icn_30_bang_pos I
    iconst_1
    iadd
    putstatic rung36_jcon_table/icn_30_bang_pos I
    goto icn_28_waft_1
icn_28_α:
    goto icn_29_α
icn_28_β:
    goto icn_29_β
    goto icn_28_wentry
icn_28_waft_0:
    astore 148
    getstatic java/lang/System/out Ljava/io/PrintStream;
    aload 148
    invokevirtual java/io/PrintStream/print(Ljava/lang/String;)V
    goto icn_30_α
icn_28_waft_1:
    astore 149
    getstatic java/lang/System/out Ljava/io/PrintStream;
    aload 149
    invokevirtual java/io/PrintStream/print(Ljava/lang/String;)V
    getstatic java/lang/System/out Ljava/io/PrintStream;
    ldc ""
    invokevirtual java/io/PrintStream/println(Ljava/lang/String;)V
    aload 149
    goto icn_27_gdrain
icn_28_wentry:
    goto icn_29_α
icn_27_gdrain:
    pop
icn_27_pump:
    goto icn_28_β
icn_27_α:
    goto icn_28_α
icn_27_β:
    goto icn_25_α
;  STR
icn_34_α:
    ldc "k "
    goto icn_33_waft_0
icn_34_β:
    goto icn_27_α
;  VAR
icn_36_α:
    getstatic rung36_jcon_table/icn_pv_main_x Ljava/util/HashMap;
    goto icn_35_ktr
icn_36_β:
    goto icn_27_α
icn_35_α:
    getstatic rung36_jcon_table/icn_35_kinit I
    ifne icn_35_kchk
    goto icn_36_α
icn_35_ktr:
    putstatic rung36_jcon_table/icn_35_ktbl Ljava/util/HashMap;
    getstatic rung36_jcon_table/icn_35_ktbl Ljava/util/HashMap;
    invokevirtual java/util/HashMap/keySet()Ljava/util/Set;
    invokeinterface java/util/Set/toArray()[Ljava/lang/Object; 1
    putstatic rung36_jcon_table/icn_35_karr [Ljava/lang/Object;
    iconst_0
    putstatic rung36_jcon_table/icn_35_kidx I
    iconst_1
    putstatic rung36_jcon_table/icn_35_kinit I
    goto icn_35_kchk
icn_35_β:
    getstatic rung36_jcon_table/icn_35_kidx I
    iconst_1
    iadd
    putstatic rung36_jcon_table/icn_35_kidx I
icn_35_kchk:
    getstatic rung36_jcon_table/icn_35_karr [Ljava/lang/Object;
    checkcast [Ljava/lang/Object;
    arraylength
    getstatic rung36_jcon_table/icn_35_kidx I
    if_icmple icn_27_α
    getstatic rung36_jcon_table/icn_35_karr [Ljava/lang/Object;
    checkcast [Ljava/lang/Object;
    getstatic rung36_jcon_table/icn_35_kidx I
    aaload
    checkcast java/lang/String
    invokestatic java/lang/Long/parseLong(Ljava/lang/String;)J
    goto icn_33_waft_1
icn_33_α:
    goto icn_34_α
icn_33_β:
    goto icn_34_β
    goto icn_33_wentry
icn_33_waft_0:
    astore 150
    getstatic java/lang/System/out Ljava/io/PrintStream;
    aload 150
    invokevirtual java/io/PrintStream/print(Ljava/lang/String;)V
    goto icn_35_α
icn_33_waft_1:
    lstore 6
    getstatic java/lang/System/out Ljava/io/PrintStream;
    lload 6
    invokevirtual java/io/PrintStream/print(J)V
    getstatic java/lang/System/out Ljava/io/PrintStream;
    ldc ""
    invokevirtual java/io/PrintStream/println(Ljava/lang/String;)V
    lload 6
    goto icn_32_gdrain
icn_33_wentry:
    goto icn_34_α
icn_32_gdrain:
    pop2
icn_32_pump:
    goto icn_33_β
icn_32_α:
    goto icn_33_α
icn_32_β:
    goto icn_27_α
;  INT
icn_39_α:
    ldc2_w 19
    goto icn_38_tsa_vr
icn_39_β:
    goto icn_32_α
;  INT
icn_40_α:
    ldc2_w 3
    goto icn_38_tsa_kr
icn_40_β:
    goto icn_32_α
icn_38_α:
    goto icn_39_α
icn_38_β:
    goto icn_32_α
icn_38_tsa_vr:
    dup2
    putstatic rung36_jcon_table/icn_38_tsa_vl J
    invokestatic java/lang/Long/valueOf(J)Ljava/lang/Long;
    putstatic rung36_jcon_table/icn_38_tsa_vo Ljava/lang/Object;
    goto icn_40_α
icn_38_tsa_kr:
    invokestatic java/lang/Long/toString(J)Ljava/lang/String;
    putstatic rung36_jcon_table/icn_38_tsa_ks Ljava/lang/String;
    goto icn_38_tsa_put
icn_38_tsa_put:
    getstatic rung36_jcon_table/icn_pv_main_x Ljava/util/HashMap;
    getstatic rung36_jcon_table/icn_38_tsa_ks Ljava/lang/String;
    getstatic rung36_jcon_table/icn_38_tsa_vo Ljava/lang/Object;
    invokevirtual java/util/HashMap/put(Ljava/lang/Object;Ljava/lang/Object;)Ljava/lang/Object;
    pop
    getstatic rung36_jcon_table/icn_38_tsa_vl J
    goto icn_37_gdrain
icn_37_gdrain:
    pop2
icn_37_pump:
    goto icn_38_β
icn_37_α:
    goto icn_38_α
icn_37_β:
    goto icn_32_α
;  INT
icn_43_α:
    ldc2_w 7
    goto icn_42_tdr
icn_43_β:
    goto icn_37_α
icn_42_α:
    goto icn_43_α
icn_42_β:
    goto icn_37_α
icn_42_tdr:
    invokestatic java/lang/Long/valueOf(J)Ljava/lang/Long;
    putstatic rung36_jcon_table/icn_42_tdflt Ljava/lang/Object;
    new java/util/HashMap
    dup
    invokespecial java/util/HashMap/<init>()V
    putstatic rung36_jcon_table/icn_42_tbl Ljava/util/HashMap;
    getstatic rung36_jcon_table/icn_42_tbl Ljava/util/HashMap;
    goto icn_41_store
icn_41_α:
    goto icn_42_α
icn_41_β:
    goto icn_42_β
icn_41_store:
    putstatic rung36_jcon_table/icn_pv_main_x Ljava/util/HashMap;
    getstatic rung36_jcon_table/icn_42_tdflt Ljava/lang/Object;
    putstatic rung36_jcon_table/icn_pv_main_x_dflt Ljava/lang/Object;
    getstatic rung36_jcon_table/icn_pv_main_x Ljava/util/HashMap;
    goto icn_main_s47_sdrain
icn_main_s47_sdrain:
    pop
    goto icn_37_α
icn_44_α:
    getstatic java/lang/System/out Ljava/io/PrintStream;
    ldc ""
    invokevirtual java/io/PrintStream/println(Ljava/lang/String;)V
    goto icn_main_s46_sdrain
icn_44_β:
    goto icn_41_α
icn_main_s46_sdrain:
    pop2
    goto icn_41_α
;  VAR
icn_46_α:
    getstatic rung36_jcon_table/icn_pv_main_x Ljava/util/HashMap;
    goto icn_45_arg1
icn_46_β:
    goto icn_44_α
icn_45_arg1:
    putstatic rung36_jcon_table/icn_arg_1 J
    goto icn_45_docall
;  STR
icn_47_α:
    ldc "t0d"
    goto icn_45_arg0
icn_47_β:
    goto icn_44_α
icn_45_arg0:
    putstatic rung36_jcon_table/icn_arg_str_0 Ljava/lang/String;
    lconst_0
    putstatic rung36_jcon_table/icn_arg_0 J
    goto icn_46_α
icn_45_α:
    goto icn_47_α
icn_45_β:
    goto icn_46_β
icn_45_docall:
    getstatic rung36_jcon_table/icn_pv_main_y J
    lstore 155
    getstatic rung36_jcon_table/icn_16_tsa_vl J
    lstore 157
    getstatic rung36_jcon_table/icn_17_binop_lc J
    lstore 159
    getstatic rung36_jcon_table/icn_17_binop_rc J
    lstore 161
    getstatic rung36_jcon_table/icn_pv_main_k J
    lstore 163
    getstatic rung36_jcon_table/icn_22_I J
    lstore 165
    getstatic rung36_jcon_table/icn_22_bound J
    lstore 167
    getstatic rung36_jcon_table/icn_22_e1cur J
    lstore 169
    getstatic rung36_jcon_table/icn_22_e1val J
    lstore 171
    getstatic rung36_jcon_table/icn_22_e2val J
    lstore 173
    getstatic rung36_jcon_table/icn_38_tsa_vl J
    lstore 175
    invokestatic rung36_jcon_table/icn_tdump()V
    lload 155
    putstatic rung36_jcon_table/icn_pv_main_y J
    lload 157
    putstatic rung36_jcon_table/icn_16_tsa_vl J
    lload 159
    putstatic rung36_jcon_table/icn_17_binop_lc J
    lload 161
    putstatic rung36_jcon_table/icn_17_binop_rc J
    lload 163
    putstatic rung36_jcon_table/icn_pv_main_k J
    lload 165
    putstatic rung36_jcon_table/icn_22_I J
    lload 167
    putstatic rung36_jcon_table/icn_22_bound J
    lload 169
    putstatic rung36_jcon_table/icn_22_e1cur J
    lload 171
    putstatic rung36_jcon_table/icn_22_e1val J
    lload 173
    putstatic rung36_jcon_table/icn_22_e2val J
    lload 175
    putstatic rung36_jcon_table/icn_38_tsa_vl J
    getstatic rung36_jcon_table/icn_failed B
    ifne icn_45_after_call
    getstatic rung36_jcon_table/icn_retval J
    goto icn_main_s45_sdrain
icn_45_after_call:
    goto icn_44_α
icn_main_s45_sdrain:
    pop2
    goto icn_44_α
;  STR
icn_50_α:
    ldc "failed d71"
    goto icn_49_waft_0
icn_50_β:
    goto icn_45_α
icn_49_α:
    goto icn_50_α
icn_49_β:
    goto icn_50_β
    goto icn_49_wentry
icn_49_waft_0:
    astore 151
    getstatic java/lang/System/out Ljava/io/PrintStream;
    aload 151
    invokevirtual java/io/PrintStream/print(Ljava/lang/String;)V
    getstatic java/lang/System/out Ljava/io/PrintStream;
    ldc ""
    invokevirtual java/io/PrintStream/println(Ljava/lang/String;)V
    aload 151
    goto icn_48_alt_g1
icn_49_wentry:
    goto icn_50_α
;  VAR
icn_53_α:
    getstatic rung36_jcon_table/icn_pv_main_x Ljava/util/HashMap;
    goto icn_52_dtr
icn_53_β:
    goto icn_49_α
;  INT
icn_54_α:
    ldc2_w 7
    goto icn_52_dkr
icn_54_β:
    goto icn_49_α
icn_52_α:
    goto icn_53_α
icn_52_β:
    goto icn_49_α
icn_52_dtr:
    putstatic rung36_jcon_table/icn_52_dtbl Ljava/util/HashMap;
    goto icn_54_α
icn_52_dkr:
    invokestatic java/lang/Long/toString(J)Ljava/lang/String;
    putstatic rung36_jcon_table/icn_52_dkey Ljava/lang/String;
    getstatic rung36_jcon_table/icn_52_dtbl Ljava/util/HashMap;
    getstatic rung36_jcon_table/icn_52_dkey Ljava/lang/String;
    invokevirtual java/util/HashMap/remove(Ljava/lang/Object;)Ljava/lang/Object;
    pop
    getstatic rung36_jcon_table/icn_52_dtbl Ljava/util/HashMap;
    goto icn_51_dtr
;  INT
icn_55_α:
    ldc2_w 1
    goto icn_51_dkr
icn_55_β:
    goto icn_49_α
icn_51_α:
    goto icn_52_α
icn_51_β:
    goto icn_49_α
icn_51_dtr:
    putstatic rung36_jcon_table/icn_51_dtbl Ljava/util/HashMap;
    goto icn_55_α
icn_51_dkr:
    invokestatic java/lang/Long/toString(J)Ljava/lang/String;
    putstatic rung36_jcon_table/icn_51_dkey Ljava/lang/String;
    getstatic rung36_jcon_table/icn_51_dtbl Ljava/util/HashMap;
    getstatic rung36_jcon_table/icn_51_dkey Ljava/lang/String;
    invokevirtual java/util/HashMap/remove(Ljava/lang/Object;)Ljava/lang/Object;
    pop
    getstatic rung36_jcon_table/icn_51_dtbl Ljava/util/HashMap;
    goto icn_48_alt_g0
icn_48_alt_g0:
    pop
    lconst_0
    putstatic rung36_jcon_table/icn_48_alt_val J
    sipush 1
    putstatic rung36_jcon_table/icn_48_alt_gate I
    getstatic rung36_jcon_table/icn_48_alt_val J
    goto icn_main_s44_sdrain
icn_48_alt_g1:
    pop
    lconst_0
    putstatic rung36_jcon_table/icn_48_alt_val J
    sipush 2
    putstatic rung36_jcon_table/icn_48_alt_gate I
    getstatic rung36_jcon_table/icn_48_alt_val J
    goto icn_main_s44_sdrain
icn_48_α:
    iconst_0
    putstatic rung36_jcon_table/icn_48_alt_gate I
    goto icn_51_α
icn_48_β:
    getstatic rung36_jcon_table/icn_48_alt_gate I
    tableswitch 1 2
        icn_51_β
        icn_49_β
        default: icn_45_α
icn_main_s44_sdrain:
    pop2
    goto icn_45_α
;  STR
icn_58_α:
    ldc "failed d36"
    goto icn_57_waft_0
icn_58_β:
    goto icn_48_α
icn_57_α:
    goto icn_58_α
icn_57_β:
    goto icn_58_β
    goto icn_57_wentry
icn_57_waft_0:
    astore 152
    getstatic java/lang/System/out Ljava/io/PrintStream;
    aload 152
    invokevirtual java/io/PrintStream/print(Ljava/lang/String;)V
    getstatic java/lang/System/out Ljava/io/PrintStream;
    ldc ""
    invokevirtual java/io/PrintStream/println(Ljava/lang/String;)V
    aload 152
    goto icn_56_alt_g1
icn_57_wentry:
    goto icn_58_α
;  VAR
icn_60_α:
    getstatic rung36_jcon_table/icn_pv_main_x Ljava/util/HashMap;
    goto icn_59_dtr
icn_60_β:
    goto icn_57_α
;  INT
icn_61_α:
    ldc2_w 3
    goto icn_59_dkr
icn_61_β:
    goto icn_57_α
icn_59_α:
    goto icn_60_α
icn_59_β:
    goto icn_57_α
icn_59_dtr:
    putstatic rung36_jcon_table/icn_59_dtbl Ljava/util/HashMap;
    goto icn_61_α
icn_59_dkr:
    invokestatic java/lang/Long/toString(J)Ljava/lang/String;
    putstatic rung36_jcon_table/icn_59_dkey Ljava/lang/String;
    getstatic rung36_jcon_table/icn_59_dtbl Ljava/util/HashMap;
    getstatic rung36_jcon_table/icn_59_dkey Ljava/lang/String;
    invokevirtual java/util/HashMap/remove(Ljava/lang/Object;)Ljava/lang/Object;
    pop
    getstatic rung36_jcon_table/icn_59_dtbl Ljava/util/HashMap;
    goto icn_56_alt_g0
icn_56_alt_g0:
    pop
    lconst_0
    putstatic rung36_jcon_table/icn_56_alt_val J
    sipush 1
    putstatic rung36_jcon_table/icn_56_alt_gate I
    getstatic rung36_jcon_table/icn_56_alt_val J
    goto icn_main_s43_sdrain
icn_56_alt_g1:
    pop
    lconst_0
    putstatic rung36_jcon_table/icn_56_alt_val J
    sipush 2
    putstatic rung36_jcon_table/icn_56_alt_gate I
    getstatic rung36_jcon_table/icn_56_alt_val J
    goto icn_main_s43_sdrain
icn_56_α:
    iconst_0
    putstatic rung36_jcon_table/icn_56_alt_gate I
    goto icn_59_α
icn_56_β:
    getstatic rung36_jcon_table/icn_56_alt_gate I
    tableswitch 1 2
        icn_59_β
        icn_57_β
        default: icn_48_α
icn_main_s43_sdrain:
    pop2
    goto icn_48_α
;  STR
icn_64_α:
    ldc "failed dn"
    goto icn_63_waft_0
icn_64_β:
    goto icn_56_α
icn_63_α:
    goto icn_64_α
icn_63_β:
    goto icn_64_β
    goto icn_63_wentry
icn_63_waft_0:
    astore 153
    getstatic java/lang/System/out Ljava/io/PrintStream;
    aload 153
    invokevirtual java/io/PrintStream/print(Ljava/lang/String;)V
    getstatic java/lang/System/out Ljava/io/PrintStream;
    ldc ""
    invokevirtual java/io/PrintStream/println(Ljava/lang/String;)V
    aload 153
    goto icn_62_alt_g1
icn_63_wentry:
    goto icn_64_α
icn_65_α:
    goto icn_63_α
icn_65_β:
    goto icn_63_α
icn_62_alt_g0:
    pop
    lconst_0
    putstatic rung36_jcon_table/icn_62_alt_val J
    sipush 1
    putstatic rung36_jcon_table/icn_62_alt_gate I
    getstatic rung36_jcon_table/icn_62_alt_val J
    goto icn_main_s42_sdrain
icn_62_alt_g1:
    pop
    lconst_0
    putstatic rung36_jcon_table/icn_62_alt_val J
    sipush 2
    putstatic rung36_jcon_table/icn_62_alt_gate I
    getstatic rung36_jcon_table/icn_62_alt_val J
    goto icn_main_s42_sdrain
icn_62_α:
    iconst_0
    putstatic rung36_jcon_table/icn_62_alt_gate I
    goto icn_65_α
icn_62_β:
    getstatic rung36_jcon_table/icn_62_alt_gate I
    tableswitch 1 2
        icn_65_β
        icn_63_β
        default: icn_56_α
icn_main_s42_sdrain:
    pop2
    goto icn_56_α
;  VAR
icn_67_α:
    getstatic rung36_jcon_table/icn_pv_main_x Ljava/util/HashMap;
    goto icn_66_arg1
icn_67_β:
    goto icn_62_α
icn_66_arg1:
    putstatic rung36_jcon_table/icn_arg_1 J
    goto icn_66_docall
;  STR
icn_68_α:
    ldc "t0i"
    goto icn_66_arg0
icn_68_β:
    goto icn_62_α
icn_66_arg0:
    putstatic rung36_jcon_table/icn_arg_str_0 Ljava/lang/String;
    lconst_0
    putstatic rung36_jcon_table/icn_arg_0 J
    goto icn_67_α
icn_66_α:
    goto icn_68_α
icn_66_β:
    goto icn_67_β
icn_66_docall:
    getstatic rung36_jcon_table/icn_pv_main_y J
    lstore 158
    getstatic rung36_jcon_table/icn_16_tsa_vl J
    lstore 160
    getstatic rung36_jcon_table/icn_17_binop_lc J
    lstore 162
    getstatic rung36_jcon_table/icn_17_binop_rc J
    lstore 164
    getstatic rung36_jcon_table/icn_pv_main_k J
    lstore 166
    getstatic rung36_jcon_table/icn_22_I J
    lstore 168
    getstatic rung36_jcon_table/icn_22_bound J
    lstore 170
    getstatic rung36_jcon_table/icn_22_e1cur J
    lstore 172
    getstatic rung36_jcon_table/icn_22_e1val J
    lstore 174
    getstatic rung36_jcon_table/icn_22_e2val J
    lstore 176
    getstatic rung36_jcon_table/icn_38_tsa_vl J
    lstore 178
    getstatic rung36_jcon_table/icn_48_alt_val J
    lstore 180
    getstatic rung36_jcon_table/icn_56_alt_val J
    lstore 182
    getstatic rung36_jcon_table/icn_62_alt_val J
    lstore 184
    invokestatic rung36_jcon_table/icn_tdump()V
    lload 158
    putstatic rung36_jcon_table/icn_pv_main_y J
    lload 160
    putstatic rung36_jcon_table/icn_16_tsa_vl J
    lload 162
    putstatic rung36_jcon_table/icn_17_binop_lc J
    lload 164
    putstatic rung36_jcon_table/icn_17_binop_rc J
    lload 166
    putstatic rung36_jcon_table/icn_pv_main_k J
    lload 168
    putstatic rung36_jcon_table/icn_22_I J
    lload 170
    putstatic rung36_jcon_table/icn_22_bound J
    lload 172
    putstatic rung36_jcon_table/icn_22_e1cur J
    lload 174
    putstatic rung36_jcon_table/icn_22_e1val J
    lload 176
    putstatic rung36_jcon_table/icn_22_e2val J
    lload 178
    putstatic rung36_jcon_table/icn_38_tsa_vl J
    lload 180
    putstatic rung36_jcon_table/icn_48_alt_val J
    lload 182
    putstatic rung36_jcon_table/icn_56_alt_val J
    lload 184
    putstatic rung36_jcon_table/icn_62_alt_val J
    getstatic rung36_jcon_table/icn_failed B
    ifne icn_66_after_call
    getstatic rung36_jcon_table/icn_retval J
    goto icn_main_s41_sdrain
icn_66_after_call:
    goto icn_62_α
icn_main_s41_sdrain:
    pop2
    goto icn_62_α
;  STR
icn_71_α:
    ldc "failed n"
    goto icn_70_waft_0
icn_71_β:
    goto icn_66_α
icn_70_α:
    goto icn_71_α
icn_70_β:
    goto icn_71_β
    goto icn_70_wentry
icn_70_waft_0:
    astore 154
    getstatic java/lang/System/out Ljava/io/PrintStream;
    aload 154
    invokevirtual java/io/PrintStream/print(Ljava/lang/String;)V
    getstatic java/lang/System/out Ljava/io/PrintStream;
    ldc ""
    invokevirtual java/io/PrintStream/println(Ljava/lang/String;)V
    aload 154
    goto icn_69_alt_g1
icn_70_wentry:
    goto icn_71_α
;  VAR
icn_73_α:
    getstatic rung36_jcon_table/icn_pv_main_x Ljava/util/HashMap;
    goto icn_72_itr2
icn_73_β:
    goto icn_70_α
;  VAR
icn_74_α:
    lconst_0
    goto icn_72_ikr2
icn_74_β:
    goto icn_70_α
;  STR
icn_75_α:
    ldc "null"
    goto icn_72_ivr2
icn_75_β:
    goto icn_70_α
icn_72_α:
    goto icn_73_α
icn_72_β:
    goto icn_70_α
icn_72_itr2:
    putstatic rung36_jcon_table/icn_72_itbl2 Ljava/util/HashMap;
    goto icn_74_α
icn_72_ikr2:
    invokestatic java/lang/Long/toString(J)Ljava/lang/String;
    putstatic rung36_jcon_table/icn_72_ikey2 Ljava/lang/String;
    goto icn_75_α
icn_72_ivr2:
    invokestatic java/lang/Long/valueOf(J)Ljava/lang/Long;
    putstatic rung36_jcon_table/icn_72_ival2 Ljava/lang/Object;
    getstatic rung36_jcon_table/icn_72_itbl2 Ljava/util/HashMap;
    getstatic rung36_jcon_table/icn_72_ikey2 Ljava/lang/String;
    getstatic rung36_jcon_table/icn_72_ival2 Ljava/lang/Object;
    invokevirtual java/util/HashMap/put(Ljava/lang/Object;Ljava/lang/Object;)Ljava/lang/Object;
    pop
    getstatic rung36_jcon_table/icn_72_itbl2 Ljava/util/HashMap;
    goto icn_69_alt_g0
icn_69_alt_g0:
    pop
    lconst_0
    putstatic rung36_jcon_table/icn_69_alt_val J
    sipush 1
    putstatic rung36_jcon_table/icn_69_alt_gate I
    getstatic rung36_jcon_table/icn_69_alt_val J
    goto icn_main_s40_sdrain
icn_69_alt_g1:
    pop
    lconst_0
    putstatic rung36_jcon_table/icn_69_alt_val J
    sipush 2
    putstatic rung36_jcon_table/icn_69_alt_gate I
    getstatic rung36_jcon_table/icn_69_alt_val J
    goto icn_main_s40_sdrain
icn_69_α:
    iconst_0
    putstatic rung36_jcon_table/icn_69_alt_gate I
    goto icn_72_α
icn_69_β:
    getstatic rung36_jcon_table/icn_69_alt_gate I
    tableswitch 1 2
        icn_72_β
        icn_70_β
        default: icn_66_α
icn_main_s40_sdrain:
    pop2
    goto icn_66_α
;  STR
icn_78_α:
    ldc "failed 67"
    goto icn_77_waft_0
icn_78_β:
    goto icn_69_α
icn_77_α:
    goto icn_78_α
icn_77_β:
    goto icn_78_β
    goto icn_77_wentry
icn_77_waft_0:
    astore 155
    getstatic java/lang/System/out Ljava/io/PrintStream;
    aload 155
    invokevirtual java/io/PrintStream/print(Ljava/lang/String;)V
    getstatic java/lang/System/out Ljava/io/PrintStream;
    ldc ""
    invokevirtual java/io/PrintStream/println(Ljava/lang/String;)V
    aload 155
    goto icn_76_alt_g1
icn_77_wentry:
    goto icn_78_α
;  VAR
icn_81_α:
    getstatic rung36_jcon_table/icn_pv_main_x Ljava/util/HashMap;
    goto icn_80_itr2
icn_81_β:
    goto icn_77_α
;  INT
icn_82_α:
    ldc2_w 6
    goto icn_80_ikr2
icn_82_β:
    goto icn_77_α
;  INT
icn_83_α:
    ldc2_w 66
    goto icn_80_ivr2
icn_83_β:
    goto icn_77_α
icn_80_α:
    goto icn_81_α
icn_80_β:
    goto icn_77_α
icn_80_itr2:
    putstatic rung36_jcon_table/icn_80_itbl2 Ljava/util/HashMap;
    goto icn_82_α
icn_80_ikr2:
    invokestatic java/lang/Long/toString(J)Ljava/lang/String;
    putstatic rung36_jcon_table/icn_80_ikey2 Ljava/lang/String;
    goto icn_83_α
icn_80_ivr2:
    invokestatic java/lang/Long/valueOf(J)Ljava/lang/Long;
    putstatic rung36_jcon_table/icn_80_ival2 Ljava/lang/Object;
    getstatic rung36_jcon_table/icn_80_itbl2 Ljava/util/HashMap;
    getstatic rung36_jcon_table/icn_80_ikey2 Ljava/lang/String;
    getstatic rung36_jcon_table/icn_80_ival2 Ljava/lang/Object;
    invokevirtual java/util/HashMap/put(Ljava/lang/Object;Ljava/lang/Object;)Ljava/lang/Object;
    pop
    getstatic rung36_jcon_table/icn_80_itbl2 Ljava/util/HashMap;
    goto icn_79_itr2
;  INT
icn_84_α:
    ldc2_w 7
    goto icn_79_ikr2
icn_84_β:
    goto icn_77_α
;  INT
icn_85_α:
    ldc2_w 77
    goto icn_79_ivr2
icn_85_β:
    goto icn_77_α
icn_79_α:
    goto icn_80_α
icn_79_β:
    goto icn_77_α
icn_79_itr2:
    putstatic rung36_jcon_table/icn_79_itbl2 Ljava/util/HashMap;
    goto icn_84_α
icn_79_ikr2:
    invokestatic java/lang/Long/toString(J)Ljava/lang/String;
    putstatic rung36_jcon_table/icn_79_ikey2 Ljava/lang/String;
    goto icn_85_α
icn_79_ivr2:
    invokestatic java/lang/Long/valueOf(J)Ljava/lang/Long;
    putstatic rung36_jcon_table/icn_79_ival2 Ljava/lang/Object;
    getstatic rung36_jcon_table/icn_79_itbl2 Ljava/util/HashMap;
    getstatic rung36_jcon_table/icn_79_ikey2 Ljava/lang/String;
    getstatic rung36_jcon_table/icn_79_ival2 Ljava/lang/Object;
    invokevirtual java/util/HashMap/put(Ljava/lang/Object;Ljava/lang/Object;)Ljava/lang/Object;
    pop
    getstatic rung36_jcon_table/icn_79_itbl2 Ljava/util/HashMap;
    goto icn_76_alt_g0
icn_76_alt_g0:
    pop
    lconst_0
    putstatic rung36_jcon_table/icn_76_alt_val J
    sipush 1
    putstatic rung36_jcon_table/icn_76_alt_gate I
    getstatic rung36_jcon_table/icn_76_alt_val J
    goto icn_main_s39_sdrain
icn_76_alt_g1:
    pop
    lconst_0
    putstatic rung36_jcon_table/icn_76_alt_val J
    sipush 2
    putstatic rung36_jcon_table/icn_76_alt_gate I
    getstatic rung36_jcon_table/icn_76_alt_val J
    goto icn_main_s39_sdrain
icn_76_α:
    iconst_0
    putstatic rung36_jcon_table/icn_76_alt_gate I
    goto icn_79_α
icn_76_β:
    getstatic rung36_jcon_table/icn_76_alt_gate I
    tableswitch 1 2
        icn_79_β
        icn_77_β
        default: icn_69_α
icn_main_s39_sdrain:
    pop2
    goto icn_69_α
;  STR
icn_88_α:
    ldc "failed 5"
    goto icn_87_waft_0
icn_88_β:
    goto icn_76_α
icn_87_α:
    goto icn_88_α
icn_87_β:
    goto icn_88_β
    goto icn_87_wentry
icn_87_waft_0:
    astore 156
    getstatic java/lang/System/out Ljava/io/PrintStream;
    aload 156
    invokevirtual java/io/PrintStream/print(Ljava/lang/String;)V
    getstatic java/lang/System/out Ljava/io/PrintStream;
    ldc ""
    invokevirtual java/io/PrintStream/println(Ljava/lang/String;)V
    aload 156
    goto icn_86_alt_g1
icn_87_wentry:
    goto icn_88_α
;  VAR
icn_90_α:
    getstatic rung36_jcon_table/icn_pv_main_x Ljava/util/HashMap;
    goto icn_89_itr2
icn_90_β:
    goto icn_87_α
;  INT
icn_91_α:
    ldc2_w 5
    goto icn_89_ikr2
icn_91_β:
    goto icn_87_α
;  INT
icn_92_α:
    ldc2_w 55
    goto icn_89_ivr2
icn_92_β:
    goto icn_87_α
icn_89_α:
    goto icn_90_α
icn_89_β:
    goto icn_87_α
icn_89_itr2:
    putstatic rung36_jcon_table/icn_89_itbl2 Ljava/util/HashMap;
    goto icn_91_α
icn_89_ikr2:
    invokestatic java/lang/Long/toString(J)Ljava/lang/String;
    putstatic rung36_jcon_table/icn_89_ikey2 Ljava/lang/String;
    goto icn_92_α
icn_89_ivr2:
    invokestatic java/lang/Long/valueOf(J)Ljava/lang/Long;
    putstatic rung36_jcon_table/icn_89_ival2 Ljava/lang/Object;
    getstatic rung36_jcon_table/icn_89_itbl2 Ljava/util/HashMap;
    getstatic rung36_jcon_table/icn_89_ikey2 Ljava/lang/String;
    getstatic rung36_jcon_table/icn_89_ival2 Ljava/lang/Object;
    invokevirtual java/util/HashMap/put(Ljava/lang/Object;Ljava/lang/Object;)Ljava/lang/Object;
    pop
    getstatic rung36_jcon_table/icn_89_itbl2 Ljava/util/HashMap;
    goto icn_86_alt_g0
icn_86_alt_g0:
    pop
    lconst_0
    putstatic rung36_jcon_table/icn_86_alt_val J
    sipush 1
    putstatic rung36_jcon_table/icn_86_alt_gate I
    getstatic rung36_jcon_table/icn_86_alt_val J
    goto icn_main_s38_sdrain
icn_86_alt_g1:
    pop
    lconst_0
    putstatic rung36_jcon_table/icn_86_alt_val J
    sipush 2
    putstatic rung36_jcon_table/icn_86_alt_gate I
    getstatic rung36_jcon_table/icn_86_alt_val J
    goto icn_main_s38_sdrain
icn_86_α:
    iconst_0
    putstatic rung36_jcon_table/icn_86_alt_gate I
    goto icn_89_α
icn_86_β:
    getstatic rung36_jcon_table/icn_86_alt_gate I
    tableswitch 1 2
        icn_89_β
        icn_87_β
        default: icn_76_α
icn_main_s38_sdrain:
    pop2
    goto icn_76_α
;  STR
icn_95_α:
    ldc "failed 3"
    goto icn_94_waft_0
icn_95_β:
    goto icn_86_α
icn_94_α:
    goto icn_95_α
icn_94_β:
    goto icn_95_β
    goto icn_94_wentry
icn_94_waft_0:
    astore 157
    getstatic java/lang/System/out Ljava/io/PrintStream;
    aload 157
    invokevirtual java/io/PrintStream/print(Ljava/lang/String;)V
    getstatic java/lang/System/out Ljava/io/PrintStream;
    ldc ""
    invokevirtual java/io/PrintStream/println(Ljava/lang/String;)V
    aload 157
    goto icn_93_alt_g1
icn_94_wentry:
    goto icn_95_α
;  VAR
icn_97_α:
    getstatic rung36_jcon_table/icn_pv_main_x Ljava/util/HashMap;
    goto icn_96_itr2
icn_97_β:
    goto icn_94_α
;  INT
icn_98_α:
    ldc2_w 3
    goto icn_96_ikr2
icn_98_β:
    goto icn_94_α
;  VAR
icn_99_α:
    lconst_0
    goto icn_96_ivr2
icn_99_β:
    goto icn_94_α
icn_96_α:
    goto icn_97_α
icn_96_β:
    goto icn_94_α
icn_96_itr2:
    putstatic rung36_jcon_table/icn_96_itbl2 Ljava/util/HashMap;
    goto icn_98_α
icn_96_ikr2:
    invokestatic java/lang/Long/toString(J)Ljava/lang/String;
    putstatic rung36_jcon_table/icn_96_ikey2 Ljava/lang/String;
    goto icn_99_α
icn_96_ivr2:
    invokestatic java/lang/Long/valueOf(J)Ljava/lang/Long;
    putstatic rung36_jcon_table/icn_96_ival2 Ljava/lang/Object;
    getstatic rung36_jcon_table/icn_96_itbl2 Ljava/util/HashMap;
    getstatic rung36_jcon_table/icn_96_ikey2 Ljava/lang/String;
    getstatic rung36_jcon_table/icn_96_ival2 Ljava/lang/Object;
    invokevirtual java/util/HashMap/put(Ljava/lang/Object;Ljava/lang/Object;)Ljava/lang/Object;
    pop
    getstatic rung36_jcon_table/icn_96_itbl2 Ljava/util/HashMap;
    goto icn_93_alt_g0
icn_93_alt_g0:
    pop
    lconst_0
    putstatic rung36_jcon_table/icn_93_alt_val J
    sipush 1
    putstatic rung36_jcon_table/icn_93_alt_gate I
    getstatic rung36_jcon_table/icn_93_alt_val J
    goto icn_main_s37_sdrain
icn_93_alt_g1:
    pop
    lconst_0
    putstatic rung36_jcon_table/icn_93_alt_val J
    sipush 2
    putstatic rung36_jcon_table/icn_93_alt_gate I
    getstatic rung36_jcon_table/icn_93_alt_val J
    goto icn_main_s37_sdrain
icn_93_α:
    iconst_0
    putstatic rung36_jcon_table/icn_93_alt_gate I
    goto icn_96_α
icn_93_β:
    getstatic rung36_jcon_table/icn_93_alt_gate I
    tableswitch 1 2
        icn_96_β
        icn_94_β
        default: icn_86_α
icn_main_s37_sdrain:
    pop2
    goto icn_86_α
;  STR
icn_102_α:
    ldc "failed 1"
    goto icn_101_waft_0
icn_102_β:
    goto icn_93_α
icn_101_α:
    goto icn_102_α
icn_101_β:
    goto icn_102_β
    goto icn_101_wentry
icn_101_waft_0:
    astore 158
    getstatic java/lang/System/out Ljava/io/PrintStream;
    aload 158
    invokevirtual java/io/PrintStream/print(Ljava/lang/String;)V
    getstatic java/lang/System/out Ljava/io/PrintStream;
    ldc ""
    invokevirtual java/io/PrintStream/println(Ljava/lang/String;)V
    aload 158
    goto icn_100_alt_g1
icn_101_wentry:
    goto icn_102_α
icn_103_α:
    goto icn_101_α
icn_103_β:
    goto icn_101_α
icn_100_alt_g0:
    pop
    lconst_0
    putstatic rung36_jcon_table/icn_100_alt_val J
    sipush 1
    putstatic rung36_jcon_table/icn_100_alt_gate I
    getstatic rung36_jcon_table/icn_100_alt_val J
    goto icn_main_s36_sdrain
icn_100_alt_g1:
    pop
    lconst_0
    putstatic rung36_jcon_table/icn_100_alt_val J
    sipush 2
    putstatic rung36_jcon_table/icn_100_alt_gate I
    getstatic rung36_jcon_table/icn_100_alt_val J
    goto icn_main_s36_sdrain
icn_100_α:
    iconst_0
    putstatic rung36_jcon_table/icn_100_alt_gate I
    goto icn_103_α
icn_100_β:
    getstatic rung36_jcon_table/icn_100_alt_gate I
    tableswitch 1 2
        icn_103_β
        icn_101_β
        default: icn_93_α
icn_main_s36_sdrain:
    pop2
    goto icn_93_α
;  STR
icn_106_α:
    ldc "failed 0"
    goto icn_105_waft_0
icn_106_β:
    goto icn_100_α
icn_105_α:
    goto icn_106_α
icn_105_β:
    goto icn_106_β
    goto icn_105_wentry
icn_105_waft_0:
    astore 159
    getstatic java/lang/System/out Ljava/io/PrintStream;
    aload 159
    invokevirtual java/io/PrintStream/print(Ljava/lang/String;)V
    getstatic java/lang/System/out Ljava/io/PrintStream;
    ldc ""
    invokevirtual java/io/PrintStream/println(Ljava/lang/String;)V
    aload 159
    goto icn_104_alt_g1
icn_105_wentry:
    goto icn_106_α
icn_107_α:
    goto icn_105_α
icn_107_β:
    goto icn_105_α
icn_104_alt_g0:
    pop
    lconst_0
    putstatic rung36_jcon_table/icn_104_alt_val J
    sipush 1
    putstatic rung36_jcon_table/icn_104_alt_gate I
    getstatic rung36_jcon_table/icn_104_alt_val J
    goto icn_main_s35_sdrain
icn_104_alt_g1:
    pop
    lconst_0
    putstatic rung36_jcon_table/icn_104_alt_val J
    sipush 2
    putstatic rung36_jcon_table/icn_104_alt_gate I
    getstatic rung36_jcon_table/icn_104_alt_val J
    goto icn_main_s35_sdrain
icn_104_α:
    iconst_0
    putstatic rung36_jcon_table/icn_104_alt_gate I
    goto icn_107_α
icn_104_β:
    getstatic rung36_jcon_table/icn_104_alt_gate I
    tableswitch 1 2
        icn_107_β
        icn_105_β
        default: icn_100_α
icn_main_s35_sdrain:
    pop2
    goto icn_100_α
;  VAR
icn_109_α:
    getstatic rung36_jcon_table/icn_pv_main_x Ljava/util/HashMap;
    goto icn_108_arg1
icn_109_β:
    goto icn_104_α
icn_108_arg1:
    putstatic rung36_jcon_table/icn_arg_1 J
    goto icn_108_docall
;  STR
icn_110_α:
    ldc "t0"
    goto icn_108_arg0
icn_110_β:
    goto icn_104_α
icn_108_arg0:
    putstatic rung36_jcon_table/icn_arg_str_0 Ljava/lang/String;
    lconst_0
    putstatic rung36_jcon_table/icn_arg_0 J
    goto icn_109_α
icn_108_α:
    goto icn_110_α
icn_108_β:
    goto icn_109_β
icn_108_docall:
    getstatic rung36_jcon_table/icn_pv_main_y J
    lstore 164
    getstatic rung36_jcon_table/icn_16_tsa_vl J
    lstore 166
    getstatic rung36_jcon_table/icn_17_binop_lc J
    lstore 168
    getstatic rung36_jcon_table/icn_17_binop_rc J
    lstore 170
    getstatic rung36_jcon_table/icn_pv_main_k J
    lstore 172
    getstatic rung36_jcon_table/icn_22_I J
    lstore 174
    getstatic rung36_jcon_table/icn_22_bound J
    lstore 176
    getstatic rung36_jcon_table/icn_22_e1cur J
    lstore 178
    getstatic rung36_jcon_table/icn_22_e1val J
    lstore 180
    getstatic rung36_jcon_table/icn_22_e2val J
    lstore 182
    getstatic rung36_jcon_table/icn_38_tsa_vl J
    lstore 184
    getstatic rung36_jcon_table/icn_48_alt_val J
    lstore 186
    getstatic rung36_jcon_table/icn_56_alt_val J
    lstore 188
    getstatic rung36_jcon_table/icn_62_alt_val J
    lstore 190
    getstatic rung36_jcon_table/icn_69_alt_val J
    lstore 192
    getstatic rung36_jcon_table/icn_76_alt_val J
    lstore 194
    getstatic rung36_jcon_table/icn_86_alt_val J
    lstore 196
    getstatic rung36_jcon_table/icn_93_alt_val J
    lstore 198
    getstatic rung36_jcon_table/icn_100_alt_val J
    lstore 200
    getstatic rung36_jcon_table/icn_104_alt_val J
    lstore 202
    invokestatic rung36_jcon_table/icn_tdump()V
    lload 164
    putstatic rung36_jcon_table/icn_pv_main_y J
    lload 166
    putstatic rung36_jcon_table/icn_16_tsa_vl J
    lload 168
    putstatic rung36_jcon_table/icn_17_binop_lc J
    lload 170
    putstatic rung36_jcon_table/icn_17_binop_rc J
    lload 172
    putstatic rung36_jcon_table/icn_pv_main_k J
    lload 174
    putstatic rung36_jcon_table/icn_22_I J
    lload 176
    putstatic rung36_jcon_table/icn_22_bound J
    lload 178
    putstatic rung36_jcon_table/icn_22_e1cur J
    lload 180
    putstatic rung36_jcon_table/icn_22_e1val J
    lload 182
    putstatic rung36_jcon_table/icn_22_e2val J
    lload 184
    putstatic rung36_jcon_table/icn_38_tsa_vl J
    lload 186
    putstatic rung36_jcon_table/icn_48_alt_val J
    lload 188
    putstatic rung36_jcon_table/icn_56_alt_val J
    lload 190
    putstatic rung36_jcon_table/icn_62_alt_val J
    lload 192
    putstatic rung36_jcon_table/icn_69_alt_val J
    lload 194
    putstatic rung36_jcon_table/icn_76_alt_val J
    lload 196
    putstatic rung36_jcon_table/icn_86_alt_val J
    lload 198
    putstatic rung36_jcon_table/icn_93_alt_val J
    lload 200
    putstatic rung36_jcon_table/icn_100_alt_val J
    lload 202
    putstatic rung36_jcon_table/icn_104_alt_val J
    getstatic rung36_jcon_table/icn_failed B
    ifne icn_108_after_call
    getstatic rung36_jcon_table/icn_retval J
    goto icn_main_s34_sdrain
icn_108_after_call:
    goto icn_104_α
icn_main_s34_sdrain:
    pop2
    goto icn_104_α
;  VAR
icn_113_α:
    getstatic rung36_jcon_table/icn_pv_main_x Ljava/util/HashMap;
    goto icn_112_ts_tr
icn_113_β:
    goto icn_108_α
;  INT
icn_114_α:
    ldc2_w 47
    goto icn_112_ts_kr
icn_114_β:
    goto icn_108_α
icn_112_α:
    goto icn_113_α
icn_112_β:
    goto icn_114_β
icn_112_ts_tr:
    putstatic rung36_jcon_table/icn_112_ts_tbl Ljava/util/HashMap;
    goto icn_114_α
icn_112_ts_kr:
    dup2
    putstatic rung36_jcon_table/icn_112_ts_kval J
    invokestatic java/lang/Long/toString(J)Ljava/lang/String;
    putstatic rung36_jcon_table/icn_112_ts_key Ljava/lang/String;
    getstatic rung36_jcon_table/icn_112_ts_tbl Ljava/util/HashMap;
    getstatic rung36_jcon_table/icn_112_ts_key Ljava/lang/String;
    invokevirtual java/util/HashMap/get(Ljava/lang/Object;)Ljava/lang/Object;
    dup
    ifnonnull icn_112_ts_got
    pop
    getstatic rung36_jcon_table/icn_pv_main_x_dflt Ljava/lang/Object;
    checkcast java/lang/Long
    invokevirtual java/lang/Long/longValue()J
    goto icn_111_waft_0
icn_112_ts_got:
    checkcast java/lang/Long
    invokevirtual java/lang/Long/longValue()J
    goto icn_111_waft_0
icn_111_α:
    goto icn_112_α
icn_111_β:
    goto icn_112_β
    goto icn_111_wentry
icn_111_waft_0:
    lstore 8
    getstatic java/lang/System/out Ljava/io/PrintStream;
    lload 8
    invokevirtual java/io/PrintStream/print(J)V
    getstatic java/lang/System/out Ljava/io/PrintStream;
    ldc ""
    invokevirtual java/io/PrintStream/println(Ljava/lang/String;)V
    lload 8
    goto icn_main_s33_sdrain
icn_111_wentry:
    goto icn_112_α
icn_main_s33_sdrain:
    pop2
    goto icn_108_α
;  INT
icn_117_α:
    ldc2_w 0
    goto icn_116_tdr
icn_117_β:
    goto icn_111_α
icn_116_α:
    goto icn_117_α
icn_116_β:
    goto icn_111_α
icn_116_tdr:
    invokestatic java/lang/Long/valueOf(J)Ljava/lang/Long;
    putstatic rung36_jcon_table/icn_116_tdflt Ljava/lang/Object;
    new java/util/HashMap
    dup
    invokespecial java/util/HashMap/<init>()V
    putstatic rung36_jcon_table/icn_116_tbl Ljava/util/HashMap;
    getstatic rung36_jcon_table/icn_116_tbl Ljava/util/HashMap;
    goto icn_115_store
icn_115_α:
    goto icn_116_α
icn_115_β:
    goto icn_116_β
icn_115_store:
    putstatic rung36_jcon_table/icn_pv_main_x Ljava/util/HashMap;
    getstatic rung36_jcon_table/icn_116_tdflt Ljava/lang/Object;
    putstatic rung36_jcon_table/icn_pv_main_x_dflt Ljava/lang/Object;
    getstatic rung36_jcon_table/icn_pv_main_x Ljava/util/HashMap;
    goto icn_main_s32_sdrain
icn_main_s32_sdrain:
    pop
    goto icn_111_α
;  VAR
icn_119_α:
    getstatic rung36_jcon_table/icn_pv_main_x Ljava/util/HashMap;
    goto icn_118_arg1
icn_119_β:
    goto icn_115_α
icn_118_arg1:
    putstatic rung36_jcon_table/icn_arg_1 J
    goto icn_118_docall
;  STR
icn_120_α:
    ldc "delete"
    goto icn_118_arg0
icn_120_β:
    goto icn_115_α
icn_118_arg0:
    putstatic rung36_jcon_table/icn_arg_str_0 Ljava/lang/String;
    lconst_0
    putstatic rung36_jcon_table/icn_arg_0 J
    goto icn_119_α
icn_118_α:
    goto icn_120_α
icn_118_β:
    goto icn_119_β
icn_118_docall:
    getstatic rung36_jcon_table/icn_pv_main_y J
    lstore 164
    getstatic rung36_jcon_table/icn_16_tsa_vl J
    lstore 166
    getstatic rung36_jcon_table/icn_17_binop_lc J
    lstore 168
    getstatic rung36_jcon_table/icn_17_binop_rc J
    lstore 170
    getstatic rung36_jcon_table/icn_pv_main_k J
    lstore 172
    getstatic rung36_jcon_table/icn_22_I J
    lstore 174
    getstatic rung36_jcon_table/icn_22_bound J
    lstore 176
    getstatic rung36_jcon_table/icn_22_e1cur J
    lstore 178
    getstatic rung36_jcon_table/icn_22_e1val J
    lstore 180
    getstatic rung36_jcon_table/icn_22_e2val J
    lstore 182
    getstatic rung36_jcon_table/icn_38_tsa_vl J
    lstore 184
    getstatic rung36_jcon_table/icn_48_alt_val J
    lstore 186
    getstatic rung36_jcon_table/icn_56_alt_val J
    lstore 188
    getstatic rung36_jcon_table/icn_62_alt_val J
    lstore 190
    getstatic rung36_jcon_table/icn_69_alt_val J
    lstore 192
    getstatic rung36_jcon_table/icn_76_alt_val J
    lstore 194
    getstatic rung36_jcon_table/icn_86_alt_val J
    lstore 196
    getstatic rung36_jcon_table/icn_93_alt_val J
    lstore 198
    getstatic rung36_jcon_table/icn_100_alt_val J
    lstore 200
    getstatic rung36_jcon_table/icn_104_alt_val J
    lstore 202
    getstatic rung36_jcon_table/icn_112_ts_kval J
    lstore 204
    invokestatic rung36_jcon_table/icn_tdump()V
    lload 164
    putstatic rung36_jcon_table/icn_pv_main_y J
    lload 166
    putstatic rung36_jcon_table/icn_16_tsa_vl J
    lload 168
    putstatic rung36_jcon_table/icn_17_binop_lc J
    lload 170
    putstatic rung36_jcon_table/icn_17_binop_rc J
    lload 172
    putstatic rung36_jcon_table/icn_pv_main_k J
    lload 174
    putstatic rung36_jcon_table/icn_22_I J
    lload 176
    putstatic rung36_jcon_table/icn_22_bound J
    lload 178
    putstatic rung36_jcon_table/icn_22_e1cur J
    lload 180
    putstatic rung36_jcon_table/icn_22_e1val J
    lload 182
    putstatic rung36_jcon_table/icn_22_e2val J
    lload 184
    putstatic rung36_jcon_table/icn_38_tsa_vl J
    lload 186
    putstatic rung36_jcon_table/icn_48_alt_val J
    lload 188
    putstatic rung36_jcon_table/icn_56_alt_val J
    lload 190
    putstatic rung36_jcon_table/icn_62_alt_val J
    lload 192
    putstatic rung36_jcon_table/icn_69_alt_val J
    lload 194
    putstatic rung36_jcon_table/icn_76_alt_val J
    lload 196
    putstatic rung36_jcon_table/icn_86_alt_val J
    lload 198
    putstatic rung36_jcon_table/icn_93_alt_val J
    lload 200
    putstatic rung36_jcon_table/icn_100_alt_val J
    lload 202
    putstatic rung36_jcon_table/icn_104_alt_val J
    lload 204
    putstatic rung36_jcon_table/icn_112_ts_kval J
    getstatic rung36_jcon_table/icn_failed B
    ifne icn_118_after_call
    getstatic rung36_jcon_table/icn_retval J
    goto icn_main_s31_sdrain
icn_118_after_call:
    goto icn_115_α
icn_main_s31_sdrain:
    pop2
    goto icn_115_α
;  STR
icn_123_α:
    ldc "failed d71"
    goto icn_122_waft_0
icn_123_β:
    goto icn_118_α
icn_122_α:
    goto icn_123_α
icn_122_β:
    goto icn_123_β
    goto icn_122_wentry
icn_122_waft_0:
    astore 160
    getstatic java/lang/System/out Ljava/io/PrintStream;
    aload 160
    invokevirtual java/io/PrintStream/print(Ljava/lang/String;)V
    getstatic java/lang/System/out Ljava/io/PrintStream;
    ldc ""
    invokevirtual java/io/PrintStream/println(Ljava/lang/String;)V
    aload 160
    goto icn_121_alt_g1
icn_122_wentry:
    goto icn_123_α
;  VAR
icn_126_α:
    getstatic rung36_jcon_table/icn_pv_main_x Ljava/util/HashMap;
    goto icn_125_dtr
icn_126_β:
    goto icn_122_α
;  INT
icn_127_α:
    ldc2_w 7
    goto icn_125_dkr
icn_127_β:
    goto icn_122_α
icn_125_α:
    goto icn_126_α
icn_125_β:
    goto icn_122_α
icn_125_dtr:
    putstatic rung36_jcon_table/icn_125_dtbl Ljava/util/HashMap;
    goto icn_127_α
icn_125_dkr:
    invokestatic java/lang/Long/toString(J)Ljava/lang/String;
    putstatic rung36_jcon_table/icn_125_dkey Ljava/lang/String;
    getstatic rung36_jcon_table/icn_125_dtbl Ljava/util/HashMap;
    getstatic rung36_jcon_table/icn_125_dkey Ljava/lang/String;
    invokevirtual java/util/HashMap/remove(Ljava/lang/Object;)Ljava/lang/Object;
    pop
    getstatic rung36_jcon_table/icn_125_dtbl Ljava/util/HashMap;
    goto icn_124_dtr
;  INT
icn_128_α:
    ldc2_w 1
    goto icn_124_dkr
icn_128_β:
    goto icn_122_α
icn_124_α:
    goto icn_125_α
icn_124_β:
    goto icn_122_α
icn_124_dtr:
    putstatic rung36_jcon_table/icn_124_dtbl Ljava/util/HashMap;
    goto icn_128_α
icn_124_dkr:
    invokestatic java/lang/Long/toString(J)Ljava/lang/String;
    putstatic rung36_jcon_table/icn_124_dkey Ljava/lang/String;
    getstatic rung36_jcon_table/icn_124_dtbl Ljava/util/HashMap;
    getstatic rung36_jcon_table/icn_124_dkey Ljava/lang/String;
    invokevirtual java/util/HashMap/remove(Ljava/lang/Object;)Ljava/lang/Object;
    pop
    getstatic rung36_jcon_table/icn_124_dtbl Ljava/util/HashMap;
    goto icn_121_alt_g0
icn_121_alt_g0:
    pop
    lconst_0
    putstatic rung36_jcon_table/icn_121_alt_val J
    sipush 1
    putstatic rung36_jcon_table/icn_121_alt_gate I
    getstatic rung36_jcon_table/icn_121_alt_val J
    goto icn_main_s30_sdrain
icn_121_alt_g1:
    pop
    lconst_0
    putstatic rung36_jcon_table/icn_121_alt_val J
    sipush 2
    putstatic rung36_jcon_table/icn_121_alt_gate I
    getstatic rung36_jcon_table/icn_121_alt_val J
    goto icn_main_s30_sdrain
icn_121_α:
    iconst_0
    putstatic rung36_jcon_table/icn_121_alt_gate I
    goto icn_124_α
icn_121_β:
    getstatic rung36_jcon_table/icn_121_alt_gate I
    tableswitch 1 2
        icn_124_β
        icn_122_β
        default: icn_118_α
icn_main_s30_sdrain:
    pop2
    goto icn_118_α
;  STR
icn_131_α:
    ldc "failed d36"
    goto icn_130_waft_0
icn_131_β:
    goto icn_121_α
icn_130_α:
    goto icn_131_α
icn_130_β:
    goto icn_131_β
    goto icn_130_wentry
icn_130_waft_0:
    astore 161
    getstatic java/lang/System/out Ljava/io/PrintStream;
    aload 161
    invokevirtual java/io/PrintStream/print(Ljava/lang/String;)V
    getstatic java/lang/System/out Ljava/io/PrintStream;
    ldc ""
    invokevirtual java/io/PrintStream/println(Ljava/lang/String;)V
    aload 161
    goto icn_129_alt_g1
icn_130_wentry:
    goto icn_131_α
;  VAR
icn_133_α:
    getstatic rung36_jcon_table/icn_pv_main_x Ljava/util/HashMap;
    goto icn_132_dtr
icn_133_β:
    goto icn_130_α
;  INT
icn_134_α:
    ldc2_w 3
    goto icn_132_dkr
icn_134_β:
    goto icn_130_α
icn_132_α:
    goto icn_133_α
icn_132_β:
    goto icn_130_α
icn_132_dtr:
    putstatic rung36_jcon_table/icn_132_dtbl Ljava/util/HashMap;
    goto icn_134_α
icn_132_dkr:
    invokestatic java/lang/Long/toString(J)Ljava/lang/String;
    putstatic rung36_jcon_table/icn_132_dkey Ljava/lang/String;
    getstatic rung36_jcon_table/icn_132_dtbl Ljava/util/HashMap;
    getstatic rung36_jcon_table/icn_132_dkey Ljava/lang/String;
    invokevirtual java/util/HashMap/remove(Ljava/lang/Object;)Ljava/lang/Object;
    pop
    getstatic rung36_jcon_table/icn_132_dtbl Ljava/util/HashMap;
    goto icn_129_alt_g0
icn_129_alt_g0:
    pop
    lconst_0
    putstatic rung36_jcon_table/icn_129_alt_val J
    sipush 1
    putstatic rung36_jcon_table/icn_129_alt_gate I
    getstatic rung36_jcon_table/icn_129_alt_val J
    goto icn_main_s29_sdrain
icn_129_alt_g1:
    pop
    lconst_0
    putstatic rung36_jcon_table/icn_129_alt_val J
    sipush 2
    putstatic rung36_jcon_table/icn_129_alt_gate I
    getstatic rung36_jcon_table/icn_129_alt_val J
    goto icn_main_s29_sdrain
icn_129_α:
    iconst_0
    putstatic rung36_jcon_table/icn_129_alt_gate I
    goto icn_132_α
icn_129_β:
    getstatic rung36_jcon_table/icn_129_alt_gate I
    tableswitch 1 2
        icn_132_β
        icn_130_β
        default: icn_121_α
icn_main_s29_sdrain:
    pop2
    goto icn_121_α
;  STR
icn_137_α:
    ldc "failed dn"
    goto icn_136_waft_0
icn_137_β:
    goto icn_129_α
icn_136_α:
    goto icn_137_α
icn_136_β:
    goto icn_137_β
    goto icn_136_wentry
icn_136_waft_0:
    astore 162
    getstatic java/lang/System/out Ljava/io/PrintStream;
    aload 162
    invokevirtual java/io/PrintStream/print(Ljava/lang/String;)V
    getstatic java/lang/System/out Ljava/io/PrintStream;
    ldc ""
    invokevirtual java/io/PrintStream/println(Ljava/lang/String;)V
    aload 162
    goto icn_135_alt_g1
icn_136_wentry:
    goto icn_137_α
icn_138_α:
    goto icn_136_α
icn_138_β:
    goto icn_136_α
icn_135_alt_g0:
    pop
    lconst_0
    putstatic rung36_jcon_table/icn_135_alt_val J
    sipush 1
    putstatic rung36_jcon_table/icn_135_alt_gate I
    getstatic rung36_jcon_table/icn_135_alt_val J
    goto icn_main_s28_sdrain
icn_135_alt_g1:
    pop
    lconst_0
    putstatic rung36_jcon_table/icn_135_alt_val J
    sipush 2
    putstatic rung36_jcon_table/icn_135_alt_gate I
    getstatic rung36_jcon_table/icn_135_alt_val J
    goto icn_main_s28_sdrain
icn_135_α:
    iconst_0
    putstatic rung36_jcon_table/icn_135_alt_gate I
    goto icn_138_α
icn_135_β:
    getstatic rung36_jcon_table/icn_135_alt_gate I
    tableswitch 1 2
        icn_138_β
        icn_136_β
        default: icn_129_α
icn_main_s28_sdrain:
    pop2
    goto icn_129_α
;  VAR
icn_140_α:
    getstatic rung36_jcon_table/icn_pv_main_x Ljava/util/HashMap;
    goto icn_139_arg1
icn_140_β:
    goto icn_135_α
icn_139_arg1:
    putstatic rung36_jcon_table/icn_arg_1 J
    goto icn_139_docall
;  STR
icn_141_α:
    ldc "insert"
    goto icn_139_arg0
icn_141_β:
    goto icn_135_α
icn_139_arg0:
    putstatic rung36_jcon_table/icn_arg_str_0 Ljava/lang/String;
    lconst_0
    putstatic rung36_jcon_table/icn_arg_0 J
    goto icn_140_α
icn_139_α:
    goto icn_141_α
icn_139_β:
    goto icn_140_β
icn_139_docall:
    getstatic rung36_jcon_table/icn_pv_main_y J
    lstore 167
    getstatic rung36_jcon_table/icn_16_tsa_vl J
    lstore 169
    getstatic rung36_jcon_table/icn_17_binop_lc J
    lstore 171
    getstatic rung36_jcon_table/icn_17_binop_rc J
    lstore 173
    getstatic rung36_jcon_table/icn_pv_main_k J
    lstore 175
    getstatic rung36_jcon_table/icn_22_I J
    lstore 177
    getstatic rung36_jcon_table/icn_22_bound J
    lstore 179
    getstatic rung36_jcon_table/icn_22_e1cur J
    lstore 181
    getstatic rung36_jcon_table/icn_22_e1val J
    lstore 183
    getstatic rung36_jcon_table/icn_22_e2val J
    lstore 185
    getstatic rung36_jcon_table/icn_38_tsa_vl J
    lstore 187
    getstatic rung36_jcon_table/icn_48_alt_val J
    lstore 189
    getstatic rung36_jcon_table/icn_56_alt_val J
    lstore 191
    getstatic rung36_jcon_table/icn_62_alt_val J
    lstore 193
    getstatic rung36_jcon_table/icn_69_alt_val J
    lstore 195
    getstatic rung36_jcon_table/icn_76_alt_val J
    lstore 197
    getstatic rung36_jcon_table/icn_86_alt_val J
    lstore 199
    getstatic rung36_jcon_table/icn_93_alt_val J
    lstore 201
    getstatic rung36_jcon_table/icn_100_alt_val J
    lstore 203
    getstatic rung36_jcon_table/icn_104_alt_val J
    lstore 205
    getstatic rung36_jcon_table/icn_112_ts_kval J
    lstore 207
    getstatic rung36_jcon_table/icn_121_alt_val J
    lstore 209
    getstatic rung36_jcon_table/icn_129_alt_val J
    lstore 211
    getstatic rung36_jcon_table/icn_135_alt_val J
    lstore 213
    invokestatic rung36_jcon_table/icn_tdump()V
    lload 167
    putstatic rung36_jcon_table/icn_pv_main_y J
    lload 169
    putstatic rung36_jcon_table/icn_16_tsa_vl J
    lload 171
    putstatic rung36_jcon_table/icn_17_binop_lc J
    lload 173
    putstatic rung36_jcon_table/icn_17_binop_rc J
    lload 175
    putstatic rung36_jcon_table/icn_pv_main_k J
    lload 177
    putstatic rung36_jcon_table/icn_22_I J
    lload 179
    putstatic rung36_jcon_table/icn_22_bound J
    lload 181
    putstatic rung36_jcon_table/icn_22_e1cur J
    lload 183
    putstatic rung36_jcon_table/icn_22_e1val J
    lload 185
    putstatic rung36_jcon_table/icn_22_e2val J
    lload 187
    putstatic rung36_jcon_table/icn_38_tsa_vl J
    lload 189
    putstatic rung36_jcon_table/icn_48_alt_val J
    lload 191
    putstatic rung36_jcon_table/icn_56_alt_val J
    lload 193
    putstatic rung36_jcon_table/icn_62_alt_val J
    lload 195
    putstatic rung36_jcon_table/icn_69_alt_val J
    lload 197
    putstatic rung36_jcon_table/icn_76_alt_val J
    lload 199
    putstatic rung36_jcon_table/icn_86_alt_val J
    lload 201
    putstatic rung36_jcon_table/icn_93_alt_val J
    lload 203
    putstatic rung36_jcon_table/icn_100_alt_val J
    lload 205
    putstatic rung36_jcon_table/icn_104_alt_val J
    lload 207
    putstatic rung36_jcon_table/icn_112_ts_kval J
    lload 209
    putstatic rung36_jcon_table/icn_121_alt_val J
    lload 211
    putstatic rung36_jcon_table/icn_129_alt_val J
    lload 213
    putstatic rung36_jcon_table/icn_135_alt_val J
    getstatic rung36_jcon_table/icn_failed B
    ifne icn_139_after_call
    getstatic rung36_jcon_table/icn_retval J
    goto icn_main_s27_sdrain
icn_139_after_call:
    goto icn_135_α
icn_main_s27_sdrain:
    pop2
    goto icn_135_α
;  STR
icn_144_α:
    ldc "NULL IS NOT MEMBER"
    goto icn_143_waft_0
icn_144_β:
    goto icn_139_α
icn_143_α:
    goto icn_144_α
icn_143_β:
    goto icn_144_β
    goto icn_143_wentry
icn_143_waft_0:
    astore 163
    getstatic java/lang/System/out Ljava/io/PrintStream;
    aload 163
    invokevirtual java/io/PrintStream/print(Ljava/lang/String;)V
    getstatic java/lang/System/out Ljava/io/PrintStream;
    ldc ""
    invokevirtual java/io/PrintStream/println(Ljava/lang/String;)V
    aload 163
    goto icn_main_s26_sdrain
icn_143_wentry:
    goto icn_144_α
icn_146_α:
    goto icn_145_succ
icn_146_β:
    goto icn_145_succ
;  NOT
icn_145_α:
    goto icn_146_α
icn_145_β:
    goto icn_146_β
icn_145_cok:
    pop2
    goto icn_142_else
icn_145_succ:
    lconst_0
    goto icn_142_then
icn_142_then:
    pop2
    goto icn_143_α
icn_142_else:
    goto icn_139_α
icn_142_α:
    goto icn_145_α
icn_142_β:
    goto icn_145_β
icn_main_s26_sdrain:
    pop
    goto icn_139_α
;  STR
icn_149_α:
    ldc "failed n"
    goto icn_148_waft_0
icn_149_β:
    goto icn_142_α
icn_148_α:
    goto icn_149_α
icn_148_β:
    goto icn_149_β
    goto icn_148_wentry
icn_148_waft_0:
    astore 164
    getstatic java/lang/System/out Ljava/io/PrintStream;
    aload 164
    invokevirtual java/io/PrintStream/print(Ljava/lang/String;)V
    getstatic java/lang/System/out Ljava/io/PrintStream;
    ldc ""
    invokevirtual java/io/PrintStream/println(Ljava/lang/String;)V
    aload 164
    goto icn_147_alt_g1
icn_148_wentry:
    goto icn_149_α
;  VAR
icn_151_α:
    getstatic rung36_jcon_table/icn_pv_main_x Ljava/util/HashMap;
    goto icn_150_itr2
icn_151_β:
    goto icn_148_α
;  VAR
icn_152_α:
    lconst_0
    goto icn_150_ikr2
icn_152_β:
    goto icn_148_α
;  STR
icn_153_α:
    ldc "null"
    goto icn_150_ivr2
icn_153_β:
    goto icn_148_α
icn_150_α:
    goto icn_151_α
icn_150_β:
    goto icn_148_α
icn_150_itr2:
    putstatic rung36_jcon_table/icn_150_itbl2 Ljava/util/HashMap;
    goto icn_152_α
icn_150_ikr2:
    invokestatic java/lang/Long/toString(J)Ljava/lang/String;
    putstatic rung36_jcon_table/icn_150_ikey2 Ljava/lang/String;
    goto icn_153_α
icn_150_ivr2:
    invokestatic java/lang/Long/valueOf(J)Ljava/lang/Long;
    putstatic rung36_jcon_table/icn_150_ival2 Ljava/lang/Object;
    getstatic rung36_jcon_table/icn_150_itbl2 Ljava/util/HashMap;
    getstatic rung36_jcon_table/icn_150_ikey2 Ljava/lang/String;
    getstatic rung36_jcon_table/icn_150_ival2 Ljava/lang/Object;
    invokevirtual java/util/HashMap/put(Ljava/lang/Object;Ljava/lang/Object;)Ljava/lang/Object;
    pop
    getstatic rung36_jcon_table/icn_150_itbl2 Ljava/util/HashMap;
    goto icn_147_alt_g0
icn_147_alt_g0:
    pop
    lconst_0
    putstatic rung36_jcon_table/icn_147_alt_val J
    sipush 1
    putstatic rung36_jcon_table/icn_147_alt_gate I
    getstatic rung36_jcon_table/icn_147_alt_val J
    goto icn_main_s25_sdrain
icn_147_alt_g1:
    pop
    lconst_0
    putstatic rung36_jcon_table/icn_147_alt_val J
    sipush 2
    putstatic rung36_jcon_table/icn_147_alt_gate I
    getstatic rung36_jcon_table/icn_147_alt_val J
    goto icn_main_s25_sdrain
icn_147_α:
    iconst_0
    putstatic rung36_jcon_table/icn_147_alt_gate I
    goto icn_150_α
icn_147_β:
    getstatic rung36_jcon_table/icn_147_alt_gate I
    tableswitch 1 2
        icn_150_β
        icn_148_β
        default: icn_142_α
icn_main_s25_sdrain:
    pop2
    goto icn_142_α
;  STR
icn_156_α:
    ldc "failed 67"
    goto icn_155_waft_0
icn_156_β:
    goto icn_147_α
icn_155_α:
    goto icn_156_α
icn_155_β:
    goto icn_156_β
    goto icn_155_wentry
icn_155_waft_0:
    astore 165
    getstatic java/lang/System/out Ljava/io/PrintStream;
    aload 165
    invokevirtual java/io/PrintStream/print(Ljava/lang/String;)V
    getstatic java/lang/System/out Ljava/io/PrintStream;
    ldc ""
    invokevirtual java/io/PrintStream/println(Ljava/lang/String;)V
    aload 165
    goto icn_154_alt_g1
icn_155_wentry:
    goto icn_156_α
;  VAR
icn_159_α:
    getstatic rung36_jcon_table/icn_pv_main_x Ljava/util/HashMap;
    goto icn_158_itr2
icn_159_β:
    goto icn_155_α
;  INT
icn_160_α:
    ldc2_w 6
    goto icn_158_ikr2
icn_160_β:
    goto icn_155_α
;  INT
icn_161_α:
    ldc2_w 66
    goto icn_158_ivr2
icn_161_β:
    goto icn_155_α
icn_158_α:
    goto icn_159_α
icn_158_β:
    goto icn_155_α
icn_158_itr2:
    putstatic rung36_jcon_table/icn_158_itbl2 Ljava/util/HashMap;
    goto icn_160_α
icn_158_ikr2:
    invokestatic java/lang/Long/toString(J)Ljava/lang/String;
    putstatic rung36_jcon_table/icn_158_ikey2 Ljava/lang/String;
    goto icn_161_α
icn_158_ivr2:
    invokestatic java/lang/Long/valueOf(J)Ljava/lang/Long;
    putstatic rung36_jcon_table/icn_158_ival2 Ljava/lang/Object;
    getstatic rung36_jcon_table/icn_158_itbl2 Ljava/util/HashMap;
    getstatic rung36_jcon_table/icn_158_ikey2 Ljava/lang/String;
    getstatic rung36_jcon_table/icn_158_ival2 Ljava/lang/Object;
    invokevirtual java/util/HashMap/put(Ljava/lang/Object;Ljava/lang/Object;)Ljava/lang/Object;
    pop
    getstatic rung36_jcon_table/icn_158_itbl2 Ljava/util/HashMap;
    goto icn_157_itr2
;  INT
icn_162_α:
    ldc2_w 7
    goto icn_157_ikr2
icn_162_β:
    goto icn_155_α
;  INT
icn_163_α:
    ldc2_w 77
    goto icn_157_ivr2
icn_163_β:
    goto icn_155_α
icn_157_α:
    goto icn_158_α
icn_157_β:
    goto icn_155_α
icn_157_itr2:
    putstatic rung36_jcon_table/icn_157_itbl2 Ljava/util/HashMap;
    goto icn_162_α
icn_157_ikr2:
    invokestatic java/lang/Long/toString(J)Ljava/lang/String;
    putstatic rung36_jcon_table/icn_157_ikey2 Ljava/lang/String;
    goto icn_163_α
icn_157_ivr2:
    invokestatic java/lang/Long/valueOf(J)Ljava/lang/Long;
    putstatic rung36_jcon_table/icn_157_ival2 Ljava/lang/Object;
    getstatic rung36_jcon_table/icn_157_itbl2 Ljava/util/HashMap;
    getstatic rung36_jcon_table/icn_157_ikey2 Ljava/lang/String;
    getstatic rung36_jcon_table/icn_157_ival2 Ljava/lang/Object;
    invokevirtual java/util/HashMap/put(Ljava/lang/Object;Ljava/lang/Object;)Ljava/lang/Object;
    pop
    getstatic rung36_jcon_table/icn_157_itbl2 Ljava/util/HashMap;
    goto icn_154_alt_g0
icn_154_alt_g0:
    pop
    lconst_0
    putstatic rung36_jcon_table/icn_154_alt_val J
    sipush 1
    putstatic rung36_jcon_table/icn_154_alt_gate I
    getstatic rung36_jcon_table/icn_154_alt_val J
    goto icn_main_s24_sdrain
icn_154_alt_g1:
    pop
    lconst_0
    putstatic rung36_jcon_table/icn_154_alt_val J
    sipush 2
    putstatic rung36_jcon_table/icn_154_alt_gate I
    getstatic rung36_jcon_table/icn_154_alt_val J
    goto icn_main_s24_sdrain
icn_154_α:
    iconst_0
    putstatic rung36_jcon_table/icn_154_alt_gate I
    goto icn_157_α
icn_154_β:
    getstatic rung36_jcon_table/icn_154_alt_gate I
    tableswitch 1 2
        icn_157_β
        icn_155_β
        default: icn_147_α
icn_main_s24_sdrain:
    pop2
    goto icn_147_α
;  STR
icn_166_α:
    ldc "failed 5"
    goto icn_165_waft_0
icn_166_β:
    goto icn_154_α
icn_165_α:
    goto icn_166_α
icn_165_β:
    goto icn_166_β
    goto icn_165_wentry
icn_165_waft_0:
    astore 166
    getstatic java/lang/System/out Ljava/io/PrintStream;
    aload 166
    invokevirtual java/io/PrintStream/print(Ljava/lang/String;)V
    getstatic java/lang/System/out Ljava/io/PrintStream;
    ldc ""
    invokevirtual java/io/PrintStream/println(Ljava/lang/String;)V
    aload 166
    goto icn_164_alt_g1
icn_165_wentry:
    goto icn_166_α
;  VAR
icn_168_α:
    getstatic rung36_jcon_table/icn_pv_main_x Ljava/util/HashMap;
    goto icn_167_itr2
icn_168_β:
    goto icn_165_α
;  INT
icn_169_α:
    ldc2_w 5
    goto icn_167_ikr2
icn_169_β:
    goto icn_165_α
;  INT
icn_170_α:
    ldc2_w 55
    goto icn_167_ivr2
icn_170_β:
    goto icn_165_α
icn_167_α:
    goto icn_168_α
icn_167_β:
    goto icn_165_α
icn_167_itr2:
    putstatic rung36_jcon_table/icn_167_itbl2 Ljava/util/HashMap;
    goto icn_169_α
icn_167_ikr2:
    invokestatic java/lang/Long/toString(J)Ljava/lang/String;
    putstatic rung36_jcon_table/icn_167_ikey2 Ljava/lang/String;
    goto icn_170_α
icn_167_ivr2:
    invokestatic java/lang/Long/valueOf(J)Ljava/lang/Long;
    putstatic rung36_jcon_table/icn_167_ival2 Ljava/lang/Object;
    getstatic rung36_jcon_table/icn_167_itbl2 Ljava/util/HashMap;
    getstatic rung36_jcon_table/icn_167_ikey2 Ljava/lang/String;
    getstatic rung36_jcon_table/icn_167_ival2 Ljava/lang/Object;
    invokevirtual java/util/HashMap/put(Ljava/lang/Object;Ljava/lang/Object;)Ljava/lang/Object;
    pop
    getstatic rung36_jcon_table/icn_167_itbl2 Ljava/util/HashMap;
    goto icn_164_alt_g0
icn_164_alt_g0:
    pop
    lconst_0
    putstatic rung36_jcon_table/icn_164_alt_val J
    sipush 1
    putstatic rung36_jcon_table/icn_164_alt_gate I
    getstatic rung36_jcon_table/icn_164_alt_val J
    goto icn_main_s23_sdrain
icn_164_alt_g1:
    pop
    lconst_0
    putstatic rung36_jcon_table/icn_164_alt_val J
    sipush 2
    putstatic rung36_jcon_table/icn_164_alt_gate I
    getstatic rung36_jcon_table/icn_164_alt_val J
    goto icn_main_s23_sdrain
icn_164_α:
    iconst_0
    putstatic rung36_jcon_table/icn_164_alt_gate I
    goto icn_167_α
icn_164_β:
    getstatic rung36_jcon_table/icn_164_alt_gate I
    tableswitch 1 2
        icn_167_β
        icn_165_β
        default: icn_154_α
icn_main_s23_sdrain:
    pop2
    goto icn_154_α
;  STR
icn_173_α:
    ldc "failed 3"
    goto icn_172_waft_0
icn_173_β:
    goto icn_164_α
icn_172_α:
    goto icn_173_α
icn_172_β:
    goto icn_173_β
    goto icn_172_wentry
icn_172_waft_0:
    astore 167
    getstatic java/lang/System/out Ljava/io/PrintStream;
    aload 167
    invokevirtual java/io/PrintStream/print(Ljava/lang/String;)V
    getstatic java/lang/System/out Ljava/io/PrintStream;
    ldc ""
    invokevirtual java/io/PrintStream/println(Ljava/lang/String;)V
    aload 167
    goto icn_171_alt_g1
icn_172_wentry:
    goto icn_173_α
;  VAR
icn_175_α:
    getstatic rung36_jcon_table/icn_pv_main_x Ljava/util/HashMap;
    goto icn_174_itr2
icn_175_β:
    goto icn_172_α
;  INT
icn_176_α:
    ldc2_w 3
    goto icn_174_ikr2
icn_176_β:
    goto icn_172_α
;  VAR
icn_177_α:
    lconst_0
    goto icn_174_ivr2
icn_177_β:
    goto icn_172_α
icn_174_α:
    goto icn_175_α
icn_174_β:
    goto icn_172_α
icn_174_itr2:
    putstatic rung36_jcon_table/icn_174_itbl2 Ljava/util/HashMap;
    goto icn_176_α
icn_174_ikr2:
    invokestatic java/lang/Long/toString(J)Ljava/lang/String;
    putstatic rung36_jcon_table/icn_174_ikey2 Ljava/lang/String;
    goto icn_177_α
icn_174_ivr2:
    invokestatic java/lang/Long/valueOf(J)Ljava/lang/Long;
    putstatic rung36_jcon_table/icn_174_ival2 Ljava/lang/Object;
    getstatic rung36_jcon_table/icn_174_itbl2 Ljava/util/HashMap;
    getstatic rung36_jcon_table/icn_174_ikey2 Ljava/lang/String;
    getstatic rung36_jcon_table/icn_174_ival2 Ljava/lang/Object;
    invokevirtual java/util/HashMap/put(Ljava/lang/Object;Ljava/lang/Object;)Ljava/lang/Object;
    pop
    getstatic rung36_jcon_table/icn_174_itbl2 Ljava/util/HashMap;
    goto icn_171_alt_g0
icn_171_alt_g0:
    pop
    lconst_0
    putstatic rung36_jcon_table/icn_171_alt_val J
    sipush 1
    putstatic rung36_jcon_table/icn_171_alt_gate I
    getstatic rung36_jcon_table/icn_171_alt_val J
    goto icn_main_s22_sdrain
icn_171_alt_g1:
    pop
    lconst_0
    putstatic rung36_jcon_table/icn_171_alt_val J
    sipush 2
    putstatic rung36_jcon_table/icn_171_alt_gate I
    getstatic rung36_jcon_table/icn_171_alt_val J
    goto icn_main_s22_sdrain
icn_171_α:
    iconst_0
    putstatic rung36_jcon_table/icn_171_alt_gate I
    goto icn_174_α
icn_171_β:
    getstatic rung36_jcon_table/icn_171_alt_gate I
    tableswitch 1 2
        icn_174_β
        icn_172_β
        default: icn_164_α
icn_main_s22_sdrain:
    pop2
    goto icn_164_α
;  STR
icn_180_α:
    ldc "failed 1"
    goto icn_179_waft_0
icn_180_β:
    goto icn_171_α
icn_179_α:
    goto icn_180_α
icn_179_β:
    goto icn_180_β
    goto icn_179_wentry
icn_179_waft_0:
    astore 168
    getstatic java/lang/System/out Ljava/io/PrintStream;
    aload 168
    invokevirtual java/io/PrintStream/print(Ljava/lang/String;)V
    getstatic java/lang/System/out Ljava/io/PrintStream;
    ldc ""
    invokevirtual java/io/PrintStream/println(Ljava/lang/String;)V
    aload 168
    goto icn_178_alt_g1
icn_179_wentry:
    goto icn_180_α
icn_181_α:
    goto icn_179_α
icn_181_β:
    goto icn_179_α
icn_178_alt_g0:
    pop
    lconst_0
    putstatic rung36_jcon_table/icn_178_alt_val J
    sipush 1
    putstatic rung36_jcon_table/icn_178_alt_gate I
    getstatic rung36_jcon_table/icn_178_alt_val J
    goto icn_main_s21_sdrain
icn_178_alt_g1:
    pop
    lconst_0
    putstatic rung36_jcon_table/icn_178_alt_val J
    sipush 2
    putstatic rung36_jcon_table/icn_178_alt_gate I
    getstatic rung36_jcon_table/icn_178_alt_val J
    goto icn_main_s21_sdrain
icn_178_α:
    iconst_0
    putstatic rung36_jcon_table/icn_178_alt_gate I
    goto icn_181_α
icn_178_β:
    getstatic rung36_jcon_table/icn_178_alt_gate I
    tableswitch 1 2
        icn_181_β
        icn_179_β
        default: icn_171_α
icn_main_s21_sdrain:
    pop2
    goto icn_171_α
;  STR
icn_184_α:
    ldc "failed 0"
    goto icn_183_waft_0
icn_184_β:
    goto icn_178_α
icn_183_α:
    goto icn_184_α
icn_183_β:
    goto icn_184_β
    goto icn_183_wentry
icn_183_waft_0:
    astore 169
    getstatic java/lang/System/out Ljava/io/PrintStream;
    aload 169
    invokevirtual java/io/PrintStream/print(Ljava/lang/String;)V
    getstatic java/lang/System/out Ljava/io/PrintStream;
    ldc ""
    invokevirtual java/io/PrintStream/println(Ljava/lang/String;)V
    aload 169
    goto icn_182_alt_g1
icn_183_wentry:
    goto icn_184_α
icn_185_α:
    goto icn_183_α
icn_185_β:
    goto icn_183_α
icn_182_alt_g0:
    pop
    lconst_0
    putstatic rung36_jcon_table/icn_182_alt_val J
    sipush 1
    putstatic rung36_jcon_table/icn_182_alt_gate I
    getstatic rung36_jcon_table/icn_182_alt_val J
    goto icn_main_s20_sdrain
icn_182_alt_g1:
    pop
    lconst_0
    putstatic rung36_jcon_table/icn_182_alt_val J
    sipush 2
    putstatic rung36_jcon_table/icn_182_alt_gate I
    getstatic rung36_jcon_table/icn_182_alt_val J
    goto icn_main_s20_sdrain
icn_182_α:
    iconst_0
    putstatic rung36_jcon_table/icn_182_alt_gate I
    goto icn_185_α
icn_182_β:
    getstatic rung36_jcon_table/icn_182_alt_gate I
    tableswitch 1 2
        icn_185_β
        icn_183_β
        default: icn_178_α
icn_main_s20_sdrain:
    pop2
    goto icn_178_α
;  STR
icn_188_α:
    ldc "NULL IS MEMBER"
    goto icn_187_waft_0
icn_188_β:
    goto icn_182_α
icn_187_α:
    goto icn_188_α
icn_187_β:
    goto icn_188_β
    goto icn_187_wentry
icn_187_waft_0:
    astore 170
    getstatic java/lang/System/out Ljava/io/PrintStream;
    aload 170
    invokevirtual java/io/PrintStream/print(Ljava/lang/String;)V
    getstatic java/lang/System/out Ljava/io/PrintStream;
    ldc ""
    invokevirtual java/io/PrintStream/println(Ljava/lang/String;)V
    aload 170
    goto icn_main_s19_sdrain
icn_187_wentry:
    goto icn_188_α
icn_189_α:
    goto icn_186_else
icn_189_β:
    goto icn_186_else
icn_186_then:
    pop2
    goto icn_187_α
icn_186_else:
    goto icn_182_α
icn_186_α:
    goto icn_189_α
icn_186_β:
    goto icn_189_β
icn_main_s19_sdrain:
    pop
    goto icn_182_α
icn_191_α:
    goto icn_186_α
icn_191_β:
    goto icn_186_α
icn_190_α:
    goto icn_191_α
icn_190_β:
    goto icn_191_β
icn_190_store:
    putstatic rung36_jcon_table/icn_pv_main_x Ljava/util/HashMap;
    getstatic rung36_jcon_table/icn_pv_main_x Ljava/util/HashMap;
    goto icn_main_s18_sdrain
icn_main_s18_sdrain:
    pop
    goto icn_186_α
;  STR
icn_194_α:
    ldc "\\2"
    goto icn_193_waft_0
icn_194_β:
    goto icn_190_α
icn_193_α:
    goto icn_194_α
icn_193_β:
    goto icn_194_β
    goto icn_193_wentry
icn_193_waft_0:
    astore 171
    getstatic java/lang/System/out Ljava/io/PrintStream;
    aload 171
    invokevirtual java/io/PrintStream/print(Ljava/lang/String;)V
    getstatic java/lang/System/out Ljava/io/PrintStream;
    ldc ""
    invokevirtual java/io/PrintStream/println(Ljava/lang/String;)V
    aload 171
    goto icn_192_alt_g1
icn_193_wentry:
    goto icn_194_α
;  VAR
icn_197_α:
    getstatic rung36_jcon_table/icn_pv_main_x Ljava/util/HashMap;
    goto icn_196_ts_tr
icn_197_β:
    goto icn_193_α
;  INT
icn_198_α:
    ldc2_w 2
    goto icn_196_ts_kr
icn_198_β:
    goto icn_193_α
icn_196_α:
    goto icn_197_α
icn_196_β:
    goto icn_198_β
icn_196_ts_tr:
    putstatic rung36_jcon_table/icn_196_ts_tbl Ljava/util/HashMap;
    goto icn_198_α
icn_196_ts_kr:
    dup2
    putstatic rung36_jcon_table/icn_196_ts_kval J
    invokestatic java/lang/Long/toString(J)Ljava/lang/String;
    putstatic rung36_jcon_table/icn_196_ts_key Ljava/lang/String;
    getstatic rung36_jcon_table/icn_196_ts_tbl Ljava/util/HashMap;
    getstatic rung36_jcon_table/icn_196_ts_key Ljava/lang/String;
    invokevirtual java/util/HashMap/get(Ljava/lang/Object;)Ljava/lang/Object;
    dup
    ifnonnull icn_196_ts_got
    pop
    getstatic rung36_jcon_table/icn_pv_main_x_dflt Ljava/lang/Object;
    checkcast java/lang/Long
    invokevirtual java/lang/Long/longValue()J
    goto icn_192_alt_g0
icn_196_ts_got:
    checkcast java/lang/Long
    invokevirtual java/lang/Long/longValue()J
    goto icn_192_alt_g0
;  NONNULL
icn_195_α:
    goto icn_196_α
icn_195_β:
    goto icn_196_β
icn_192_alt_g0:
    putstatic rung36_jcon_table/icn_192_alt_val J
    sipush 1
    putstatic rung36_jcon_table/icn_192_alt_gate I
    getstatic rung36_jcon_table/icn_192_alt_val J
    goto icn_main_s17_sdrain
icn_192_alt_g1:
    pop
    lconst_0
    putstatic rung36_jcon_table/icn_192_alt_val J
    sipush 2
    putstatic rung36_jcon_table/icn_192_alt_gate I
    getstatic rung36_jcon_table/icn_192_alt_val J
    goto icn_main_s17_sdrain
icn_192_α:
    iconst_0
    putstatic rung36_jcon_table/icn_192_alt_gate I
    goto icn_195_α
icn_192_β:
    getstatic rung36_jcon_table/icn_192_alt_gate I
    tableswitch 1 2
        icn_195_β
        icn_193_β
        default: icn_190_α
icn_main_s17_sdrain:
    pop2
    goto icn_190_α
;  STR
icn_201_α:
    ldc "/1"
    goto icn_200_waft_0
icn_201_β:
    goto icn_192_α
icn_200_α:
    goto icn_201_α
icn_200_β:
    goto icn_201_β
    goto icn_200_wentry
icn_200_waft_0:
    astore 172
    getstatic java/lang/System/out Ljava/io/PrintStream;
    aload 172
    invokevirtual java/io/PrintStream/print(Ljava/lang/String;)V
    getstatic java/lang/System/out Ljava/io/PrintStream;
    ldc ""
    invokevirtual java/io/PrintStream/println(Ljava/lang/String;)V
    aload 172
    goto icn_199_alt_g1
icn_200_wentry:
    goto icn_201_α
;  VAR
icn_204_α:
    getstatic rung36_jcon_table/icn_pv_main_x Ljava/util/HashMap;
    goto icn_203_ts_tr
icn_204_β:
    goto icn_202_succ
;  INT
icn_205_α:
    ldc2_w 1
    goto icn_203_ts_kr
icn_205_β:
    goto icn_202_succ
icn_203_α:
    goto icn_204_α
icn_203_β:
    goto icn_205_β
icn_203_ts_tr:
    putstatic rung36_jcon_table/icn_203_ts_tbl Ljava/util/HashMap;
    goto icn_205_α
icn_203_ts_kr:
    dup2
    putstatic rung36_jcon_table/icn_203_ts_kval J
    invokestatic java/lang/Long/toString(J)Ljava/lang/String;
    putstatic rung36_jcon_table/icn_203_ts_key Ljava/lang/String;
    getstatic rung36_jcon_table/icn_203_ts_tbl Ljava/util/HashMap;
    getstatic rung36_jcon_table/icn_203_ts_key Ljava/lang/String;
    invokevirtual java/util/HashMap/get(Ljava/lang/Object;)Ljava/lang/Object;
    dup
    ifnonnull icn_203_ts_got
    pop
    getstatic rung36_jcon_table/icn_pv_main_x_dflt Ljava/lang/Object;
    checkcast java/lang/Long
    invokevirtual java/lang/Long/longValue()J
    goto icn_202_cok
icn_203_ts_got:
    checkcast java/lang/Long
    invokevirtual java/lang/Long/longValue()J
    goto icn_202_cok
;  NULL
icn_202_α:
    goto icn_203_α
icn_202_β:
    goto icn_203_β
icn_202_cok:
    pop2
    goto icn_200_α
icn_202_succ:
    lconst_0
    goto icn_199_alt_g0
icn_199_alt_g0:
    putstatic rung36_jcon_table/icn_199_alt_val J
    sipush 1
    putstatic rung36_jcon_table/icn_199_alt_gate I
    getstatic rung36_jcon_table/icn_199_alt_val J
    goto icn_main_s16_sdrain
icn_199_alt_g1:
    pop
    lconst_0
    putstatic rung36_jcon_table/icn_199_alt_val J
    sipush 2
    putstatic rung36_jcon_table/icn_199_alt_gate I
    getstatic rung36_jcon_table/icn_199_alt_val J
    goto icn_main_s16_sdrain
icn_199_α:
    iconst_0
    putstatic rung36_jcon_table/icn_199_alt_gate I
    goto icn_202_α
icn_199_β:
    getstatic rung36_jcon_table/icn_199_alt_gate I
    tableswitch 1 2
        icn_202_β
        icn_200_β
        default: icn_192_α
icn_main_s16_sdrain:
    pop2
    goto icn_192_α
;  VAR
icn_207_α:
    getstatic rung36_jcon_table/icn_pv_main_x Ljava/util/HashMap;
    goto icn_206_arg1
icn_207_β:
    goto icn_199_α
icn_206_arg1:
    putstatic rung36_jcon_table/icn_arg_1 J
    goto icn_206_docall
;  STR
icn_208_α:
    ldc "x[k]=k"
    goto icn_206_arg0
icn_208_β:
    goto icn_199_α
icn_206_arg0:
    putstatic rung36_jcon_table/icn_arg_str_0 Ljava/lang/String;
    lconst_0
    putstatic rung36_jcon_table/icn_arg_0 J
    goto icn_207_α
icn_206_α:
    goto icn_208_α
icn_206_β:
    goto icn_207_β
icn_206_docall:
    getstatic rung36_jcon_table/icn_pv_main_y J
    lstore 177
    getstatic rung36_jcon_table/icn_16_tsa_vl J
    lstore 179
    getstatic rung36_jcon_table/icn_17_binop_lc J
    lstore 181
    getstatic rung36_jcon_table/icn_17_binop_rc J
    lstore 183
    getstatic rung36_jcon_table/icn_pv_main_k J
    lstore 185
    getstatic rung36_jcon_table/icn_22_I J
    lstore 187
    getstatic rung36_jcon_table/icn_22_bound J
    lstore 189
    getstatic rung36_jcon_table/icn_22_e1cur J
    lstore 191
    getstatic rung36_jcon_table/icn_22_e1val J
    lstore 193
    getstatic rung36_jcon_table/icn_22_e2val J
    lstore 195
    getstatic rung36_jcon_table/icn_38_tsa_vl J
    lstore 197
    getstatic rung36_jcon_table/icn_48_alt_val J
    lstore 199
    getstatic rung36_jcon_table/icn_56_alt_val J
    lstore 201
    getstatic rung36_jcon_table/icn_62_alt_val J
    lstore 203
    getstatic rung36_jcon_table/icn_69_alt_val J
    lstore 205
    getstatic rung36_jcon_table/icn_76_alt_val J
    lstore 207
    getstatic rung36_jcon_table/icn_86_alt_val J
    lstore 209
    getstatic rung36_jcon_table/icn_93_alt_val J
    lstore 211
    getstatic rung36_jcon_table/icn_100_alt_val J
    lstore 213
    getstatic rung36_jcon_table/icn_104_alt_val J
    lstore 215
    getstatic rung36_jcon_table/icn_112_ts_kval J
    lstore 217
    getstatic rung36_jcon_table/icn_121_alt_val J
    lstore 219
    getstatic rung36_jcon_table/icn_129_alt_val J
    lstore 221
    getstatic rung36_jcon_table/icn_135_alt_val J
    lstore 223
    getstatic rung36_jcon_table/icn_147_alt_val J
    lstore 225
    getstatic rung36_jcon_table/icn_154_alt_val J
    lstore 227
    getstatic rung36_jcon_table/icn_164_alt_val J
    lstore 229
    getstatic rung36_jcon_table/icn_171_alt_val J
    lstore 231
    getstatic rung36_jcon_table/icn_178_alt_val J
    lstore 233
    getstatic rung36_jcon_table/icn_182_alt_val J
    lstore 235
    getstatic rung36_jcon_table/icn_196_ts_kval J
    lstore 237
    getstatic rung36_jcon_table/icn_192_alt_val J
    lstore 239
    getstatic rung36_jcon_table/icn_203_ts_kval J
    lstore 241
    getstatic rung36_jcon_table/icn_199_alt_val J
    lstore 243
    invokestatic rung36_jcon_table/icn_tdump()V
    lload 177
    putstatic rung36_jcon_table/icn_pv_main_y J
    lload 179
    putstatic rung36_jcon_table/icn_16_tsa_vl J
    lload 181
    putstatic rung36_jcon_table/icn_17_binop_lc J
    lload 183
    putstatic rung36_jcon_table/icn_17_binop_rc J
    lload 185
    putstatic rung36_jcon_table/icn_pv_main_k J
    lload 187
    putstatic rung36_jcon_table/icn_22_I J
    lload 189
    putstatic rung36_jcon_table/icn_22_bound J
    lload 191
    putstatic rung36_jcon_table/icn_22_e1cur J
    lload 193
    putstatic rung36_jcon_table/icn_22_e1val J
    lload 195
    putstatic rung36_jcon_table/icn_22_e2val J
    lload 197
    putstatic rung36_jcon_table/icn_38_tsa_vl J
    lload 199
    putstatic rung36_jcon_table/icn_48_alt_val J
    lload 201
    putstatic rung36_jcon_table/icn_56_alt_val J
    lload 203
    putstatic rung36_jcon_table/icn_62_alt_val J
    lload 205
    putstatic rung36_jcon_table/icn_69_alt_val J
    lload 207
    putstatic rung36_jcon_table/icn_76_alt_val J
    lload 209
    putstatic rung36_jcon_table/icn_86_alt_val J
    lload 211
    putstatic rung36_jcon_table/icn_93_alt_val J
    lload 213
    putstatic rung36_jcon_table/icn_100_alt_val J
    lload 215
    putstatic rung36_jcon_table/icn_104_alt_val J
    lload 217
    putstatic rung36_jcon_table/icn_112_ts_kval J
    lload 219
    putstatic rung36_jcon_table/icn_121_alt_val J
    lload 221
    putstatic rung36_jcon_table/icn_129_alt_val J
    lload 223
    putstatic rung36_jcon_table/icn_135_alt_val J
    lload 225
    putstatic rung36_jcon_table/icn_147_alt_val J
    lload 227
    putstatic rung36_jcon_table/icn_154_alt_val J
    lload 229
    putstatic rung36_jcon_table/icn_164_alt_val J
    lload 231
    putstatic rung36_jcon_table/icn_171_alt_val J
    lload 233
    putstatic rung36_jcon_table/icn_178_alt_val J
    lload 235
    putstatic rung36_jcon_table/icn_182_alt_val J
    lload 237
    putstatic rung36_jcon_table/icn_196_ts_kval J
    lload 239
    putstatic rung36_jcon_table/icn_192_alt_val J
    lload 241
    putstatic rung36_jcon_table/icn_203_ts_kval J
    lload 243
    putstatic rung36_jcon_table/icn_199_alt_val J
    getstatic rung36_jcon_table/icn_failed B
    ifne icn_206_after_call
    getstatic rung36_jcon_table/icn_retval J
    goto icn_main_s15_sdrain
icn_206_after_call:
    goto icn_199_α
icn_main_s15_sdrain:
    pop2
    goto icn_199_α
;  VAR
icn_211_α:
    getstatic rung36_jcon_table/icn_pv_main_k J
    goto icn_210_tsa_vr
icn_211_β:
    goto icn_209_pump
;  VAR
icn_212_α:
    getstatic rung36_jcon_table/icn_pv_main_k J
    goto icn_210_tsa_kr
icn_212_β:
    goto icn_209_pump
icn_210_α:
    goto icn_211_α
icn_210_β:
    goto icn_209_pump
icn_210_tsa_vr:
    dup2
    putstatic rung36_jcon_table/icn_210_tsa_vl J
    invokestatic java/lang/Long/valueOf(J)Ljava/lang/Long;
    putstatic rung36_jcon_table/icn_210_tsa_vo Ljava/lang/Object;
    goto icn_212_α
icn_210_tsa_kr:
    invokestatic java/lang/Long/toString(J)Ljava/lang/String;
    putstatic rung36_jcon_table/icn_210_tsa_ks Ljava/lang/String;
    goto icn_210_tsa_put
icn_210_tsa_put:
    getstatic rung36_jcon_table/icn_pv_main_x Ljava/util/HashMap;
    getstatic rung36_jcon_table/icn_210_tsa_ks Ljava/lang/String;
    getstatic rung36_jcon_table/icn_210_tsa_vo Ljava/lang/Object;
    invokevirtual java/util/HashMap/put(Ljava/lang/Object;Ljava/lang/Object;)Ljava/lang/Object;
    pop
    getstatic rung36_jcon_table/icn_210_tsa_vl J
    goto icn_209_bdrain
;  VAR
icn_215_α:
    getstatic rung36_jcon_table/icn_pv_main_x Ljava/util/HashMap;
    goto icn_214_ktr
icn_215_β:
    goto icn_206_α
icn_214_α:
    getstatic rung36_jcon_table/icn_214_kinit I
    ifne icn_214_kchk
    goto icn_215_α
icn_214_ktr:
    putstatic rung36_jcon_table/icn_214_ktbl Ljava/util/HashMap;
    getstatic rung36_jcon_table/icn_214_ktbl Ljava/util/HashMap;
    invokevirtual java/util/HashMap/keySet()Ljava/util/Set;
    invokeinterface java/util/Set/toArray()[Ljava/lang/Object; 1
    putstatic rung36_jcon_table/icn_214_karr [Ljava/lang/Object;
    iconst_0
    putstatic rung36_jcon_table/icn_214_kidx I
    iconst_1
    putstatic rung36_jcon_table/icn_214_kinit I
    goto icn_214_kchk
icn_214_β:
    getstatic rung36_jcon_table/icn_214_kidx I
    iconst_1
    iadd
    putstatic rung36_jcon_table/icn_214_kidx I
icn_214_kchk:
    getstatic rung36_jcon_table/icn_214_karr [Ljava/lang/Object;
    checkcast [Ljava/lang/Object;
    arraylength
    getstatic rung36_jcon_table/icn_214_kidx I
    if_icmple icn_206_α
    getstatic rung36_jcon_table/icn_214_karr [Ljava/lang/Object;
    checkcast [Ljava/lang/Object;
    getstatic rung36_jcon_table/icn_214_kidx I
    aaload
    checkcast java/lang/String
    invokestatic java/lang/Long/parseLong(Ljava/lang/String;)J
    goto icn_213_store
icn_213_α:
    goto icn_214_α
icn_213_β:
    goto icn_214_β
icn_213_store:
    putstatic rung36_jcon_table/icn_pv_main_k J
    getstatic rung36_jcon_table/icn_pv_main_k J
    goto icn_209_gdrain
icn_209_gdrain:
    pop2
    goto icn_210_α
icn_209_bdrain:
    pop2
icn_209_pump:
    goto icn_213_β
icn_209_α:
    goto icn_213_α
icn_209_β:
    goto icn_206_α
;  VAR
icn_217_α:
    getstatic rung36_jcon_table/icn_pv_main_x Ljava/util/HashMap;
    goto icn_216_arg1
icn_217_β:
    goto icn_209_α
icn_216_arg1:
    putstatic rung36_jcon_table/icn_arg_1 J
    goto icn_216_docall
;  STR
icn_218_α:
    ldc "[all]=99"
    goto icn_216_arg0
icn_218_β:
    goto icn_209_α
icn_216_arg0:
    putstatic rung36_jcon_table/icn_arg_str_0 Ljava/lang/String;
    lconst_0
    putstatic rung36_jcon_table/icn_arg_0 J
    goto icn_217_α
icn_216_α:
    goto icn_218_α
icn_216_β:
    goto icn_217_β
icn_216_docall:
    getstatic rung36_jcon_table/icn_pv_main_y J
    lstore 177
    getstatic rung36_jcon_table/icn_16_tsa_vl J
    lstore 179
    getstatic rung36_jcon_table/icn_17_binop_lc J
    lstore 181
    getstatic rung36_jcon_table/icn_17_binop_rc J
    lstore 183
    getstatic rung36_jcon_table/icn_pv_main_k J
    lstore 185
    getstatic rung36_jcon_table/icn_22_I J
    lstore 187
    getstatic rung36_jcon_table/icn_22_bound J
    lstore 189
    getstatic rung36_jcon_table/icn_22_e1cur J
    lstore 191
    getstatic rung36_jcon_table/icn_22_e1val J
    lstore 193
    getstatic rung36_jcon_table/icn_22_e2val J
    lstore 195
    getstatic rung36_jcon_table/icn_38_tsa_vl J
    lstore 197
    getstatic rung36_jcon_table/icn_48_alt_val J
    lstore 199
    getstatic rung36_jcon_table/icn_56_alt_val J
    lstore 201
    getstatic rung36_jcon_table/icn_62_alt_val J
    lstore 203
    getstatic rung36_jcon_table/icn_69_alt_val J
    lstore 205
    getstatic rung36_jcon_table/icn_76_alt_val J
    lstore 207
    getstatic rung36_jcon_table/icn_86_alt_val J
    lstore 209
    getstatic rung36_jcon_table/icn_93_alt_val J
    lstore 211
    getstatic rung36_jcon_table/icn_100_alt_val J
    lstore 213
    getstatic rung36_jcon_table/icn_104_alt_val J
    lstore 215
    getstatic rung36_jcon_table/icn_112_ts_kval J
    lstore 217
    getstatic rung36_jcon_table/icn_121_alt_val J
    lstore 219
    getstatic rung36_jcon_table/icn_129_alt_val J
    lstore 221
    getstatic rung36_jcon_table/icn_135_alt_val J
    lstore 223
    getstatic rung36_jcon_table/icn_147_alt_val J
    lstore 225
    getstatic rung36_jcon_table/icn_154_alt_val J
    lstore 227
    getstatic rung36_jcon_table/icn_164_alt_val J
    lstore 229
    getstatic rung36_jcon_table/icn_171_alt_val J
    lstore 231
    getstatic rung36_jcon_table/icn_178_alt_val J
    lstore 233
    getstatic rung36_jcon_table/icn_182_alt_val J
    lstore 235
    getstatic rung36_jcon_table/icn_196_ts_kval J
    lstore 237
    getstatic rung36_jcon_table/icn_192_alt_val J
    lstore 239
    getstatic rung36_jcon_table/icn_203_ts_kval J
    lstore 241
    getstatic rung36_jcon_table/icn_199_alt_val J
    lstore 243
    getstatic rung36_jcon_table/icn_210_tsa_vl J
    lstore 245
    invokestatic rung36_jcon_table/icn_tdump()V
    lload 177
    putstatic rung36_jcon_table/icn_pv_main_y J
    lload 179
    putstatic rung36_jcon_table/icn_16_tsa_vl J
    lload 181
    putstatic rung36_jcon_table/icn_17_binop_lc J
    lload 183
    putstatic rung36_jcon_table/icn_17_binop_rc J
    lload 185
    putstatic rung36_jcon_table/icn_pv_main_k J
    lload 187
    putstatic rung36_jcon_table/icn_22_I J
    lload 189
    putstatic rung36_jcon_table/icn_22_bound J
    lload 191
    putstatic rung36_jcon_table/icn_22_e1cur J
    lload 193
    putstatic rung36_jcon_table/icn_22_e1val J
    lload 195
    putstatic rung36_jcon_table/icn_22_e2val J
    lload 197
    putstatic rung36_jcon_table/icn_38_tsa_vl J
    lload 199
    putstatic rung36_jcon_table/icn_48_alt_val J
    lload 201
    putstatic rung36_jcon_table/icn_56_alt_val J
    lload 203
    putstatic rung36_jcon_table/icn_62_alt_val J
    lload 205
    putstatic rung36_jcon_table/icn_69_alt_val J
    lload 207
    putstatic rung36_jcon_table/icn_76_alt_val J
    lload 209
    putstatic rung36_jcon_table/icn_86_alt_val J
    lload 211
    putstatic rung36_jcon_table/icn_93_alt_val J
    lload 213
    putstatic rung36_jcon_table/icn_100_alt_val J
    lload 215
    putstatic rung36_jcon_table/icn_104_alt_val J
    lload 217
    putstatic rung36_jcon_table/icn_112_ts_kval J
    lload 219
    putstatic rung36_jcon_table/icn_121_alt_val J
    lload 221
    putstatic rung36_jcon_table/icn_129_alt_val J
    lload 223
    putstatic rung36_jcon_table/icn_135_alt_val J
    lload 225
    putstatic rung36_jcon_table/icn_147_alt_val J
    lload 227
    putstatic rung36_jcon_table/icn_154_alt_val J
    lload 229
    putstatic rung36_jcon_table/icn_164_alt_val J
    lload 231
    putstatic rung36_jcon_table/icn_171_alt_val J
    lload 233
    putstatic rung36_jcon_table/icn_178_alt_val J
    lload 235
    putstatic rung36_jcon_table/icn_182_alt_val J
    lload 237
    putstatic rung36_jcon_table/icn_196_ts_kval J
    lload 239
    putstatic rung36_jcon_table/icn_192_alt_val J
    lload 241
    putstatic rung36_jcon_table/icn_203_ts_kval J
    lload 243
    putstatic rung36_jcon_table/icn_199_alt_val J
    lload 245
    putstatic rung36_jcon_table/icn_210_tsa_vl J
    getstatic rung36_jcon_table/icn_failed B
    ifne icn_216_after_call
    getstatic rung36_jcon_table/icn_retval J
    goto icn_main_s13_sdrain
icn_216_after_call:
    goto icn_209_α
icn_main_s13_sdrain:
    pop2
    goto icn_209_α
;  INT
icn_221_α:
    ldc2_w 99
    goto icn_220_tsa_vr
icn_221_β:
    goto icn_216_α
;  VAR
icn_223_α:
    getstatic rung36_jcon_table/icn_pv_main_x Ljava/util/HashMap;
    goto icn_222_ktr
icn_223_β:
    goto icn_216_α
icn_222_α:
    getstatic rung36_jcon_table/icn_222_kinit I
    ifne icn_222_kchk
    goto icn_223_α
icn_222_ktr:
    putstatic rung36_jcon_table/icn_222_ktbl Ljava/util/HashMap;
    getstatic rung36_jcon_table/icn_222_ktbl Ljava/util/HashMap;
    invokevirtual java/util/HashMap/keySet()Ljava/util/Set;
    invokeinterface java/util/Set/toArray()[Ljava/lang/Object; 1
    putstatic rung36_jcon_table/icn_222_karr [Ljava/lang/Object;
    iconst_0
    putstatic rung36_jcon_table/icn_222_kidx I
    iconst_1
    putstatic rung36_jcon_table/icn_222_kinit I
    goto icn_222_kchk
icn_222_β:
    getstatic rung36_jcon_table/icn_222_kidx I
    iconst_1
    iadd
    putstatic rung36_jcon_table/icn_222_kidx I
icn_222_kchk:
    getstatic rung36_jcon_table/icn_222_karr [Ljava/lang/Object;
    checkcast [Ljava/lang/Object;
    arraylength
    getstatic rung36_jcon_table/icn_222_kidx I
    if_icmple icn_216_α
    getstatic rung36_jcon_table/icn_222_karr [Ljava/lang/Object;
    checkcast [Ljava/lang/Object;
    getstatic rung36_jcon_table/icn_222_kidx I
    aaload
    checkcast java/lang/String
    invokestatic java/lang/Long/parseLong(Ljava/lang/String;)J
    goto icn_220_tsa_kr
icn_220_α:
    goto icn_221_α
icn_220_β:
    goto icn_216_α
icn_220_tsa_vr:
    dup2
    putstatic rung36_jcon_table/icn_220_tsa_vl J
    invokestatic java/lang/Long/valueOf(J)Ljava/lang/Long;
    putstatic rung36_jcon_table/icn_220_tsa_vo Ljava/lang/Object;
    goto icn_222_α
icn_220_tsa_kr:
    invokestatic java/lang/Long/toString(J)Ljava/lang/String;
    putstatic rung36_jcon_table/icn_220_tsa_ks Ljava/lang/String;
    goto icn_220_tsa_put
icn_220_tsa_put:
    getstatic rung36_jcon_table/icn_pv_main_x Ljava/util/HashMap;
    getstatic rung36_jcon_table/icn_220_tsa_ks Ljava/lang/String;
    getstatic rung36_jcon_table/icn_220_tsa_vo Ljava/lang/Object;
    invokevirtual java/util/HashMap/put(Ljava/lang/Object;Ljava/lang/Object;)Ljava/lang/Object;
    pop
    getstatic rung36_jcon_table/icn_220_tsa_vl J
    goto icn_219_gdrain
icn_219_gdrain:
    pop2
icn_219_pump:
    goto icn_220_β
icn_219_α:
    goto icn_220_α
icn_219_β:
    goto icn_216_α
;  VAR
icn_225_α:
    getstatic rung36_jcon_table/icn_pv_main_x Ljava/util/HashMap;
    goto icn_224_arg1
icn_225_β:
    goto icn_219_α
icn_224_arg1:
    putstatic rung36_jcon_table/icn_arg_1 J
    goto icn_224_docall
;  STR
icn_226_α:
    ldc "!x=88"
    goto icn_224_arg0
icn_226_β:
    goto icn_219_α
icn_224_arg0:
    putstatic rung36_jcon_table/icn_arg_str_0 Ljava/lang/String;
    lconst_0
    putstatic rung36_jcon_table/icn_arg_0 J
    goto icn_225_α
icn_224_α:
    goto icn_226_α
icn_224_β:
    goto icn_225_β
icn_224_docall:
    getstatic rung36_jcon_table/icn_pv_main_y J
    lstore 177
    getstatic rung36_jcon_table/icn_16_tsa_vl J
    lstore 179
    getstatic rung36_jcon_table/icn_17_binop_lc J
    lstore 181
    getstatic rung36_jcon_table/icn_17_binop_rc J
    lstore 183
    getstatic rung36_jcon_table/icn_pv_main_k J
    lstore 185
    getstatic rung36_jcon_table/icn_22_I J
    lstore 187
    getstatic rung36_jcon_table/icn_22_bound J
    lstore 189
    getstatic rung36_jcon_table/icn_22_e1cur J
    lstore 191
    getstatic rung36_jcon_table/icn_22_e1val J
    lstore 193
    getstatic rung36_jcon_table/icn_22_e2val J
    lstore 195
    getstatic rung36_jcon_table/icn_38_tsa_vl J
    lstore 197
    getstatic rung36_jcon_table/icn_48_alt_val J
    lstore 199
    getstatic rung36_jcon_table/icn_56_alt_val J
    lstore 201
    getstatic rung36_jcon_table/icn_62_alt_val J
    lstore 203
    getstatic rung36_jcon_table/icn_69_alt_val J
    lstore 205
    getstatic rung36_jcon_table/icn_76_alt_val J
    lstore 207
    getstatic rung36_jcon_table/icn_86_alt_val J
    lstore 209
    getstatic rung36_jcon_table/icn_93_alt_val J
    lstore 211
    getstatic rung36_jcon_table/icn_100_alt_val J
    lstore 213
    getstatic rung36_jcon_table/icn_104_alt_val J
    lstore 215
    getstatic rung36_jcon_table/icn_112_ts_kval J
    lstore 217
    getstatic rung36_jcon_table/icn_121_alt_val J
    lstore 219
    getstatic rung36_jcon_table/icn_129_alt_val J
    lstore 221
    getstatic rung36_jcon_table/icn_135_alt_val J
    lstore 223
    getstatic rung36_jcon_table/icn_147_alt_val J
    lstore 225
    getstatic rung36_jcon_table/icn_154_alt_val J
    lstore 227
    getstatic rung36_jcon_table/icn_164_alt_val J
    lstore 229
    getstatic rung36_jcon_table/icn_171_alt_val J
    lstore 231
    getstatic rung36_jcon_table/icn_178_alt_val J
    lstore 233
    getstatic rung36_jcon_table/icn_182_alt_val J
    lstore 235
    getstatic rung36_jcon_table/icn_196_ts_kval J
    lstore 237
    getstatic rung36_jcon_table/icn_192_alt_val J
    lstore 239
    getstatic rung36_jcon_table/icn_203_ts_kval J
    lstore 241
    getstatic rung36_jcon_table/icn_199_alt_val J
    lstore 243
    getstatic rung36_jcon_table/icn_210_tsa_vl J
    lstore 245
    getstatic rung36_jcon_table/icn_220_tsa_vl J
    lstore 247
    invokestatic rung36_jcon_table/icn_tdump()V
    lload 177
    putstatic rung36_jcon_table/icn_pv_main_y J
    lload 179
    putstatic rung36_jcon_table/icn_16_tsa_vl J
    lload 181
    putstatic rung36_jcon_table/icn_17_binop_lc J
    lload 183
    putstatic rung36_jcon_table/icn_17_binop_rc J
    lload 185
    putstatic rung36_jcon_table/icn_pv_main_k J
    lload 187
    putstatic rung36_jcon_table/icn_22_I J
    lload 189
    putstatic rung36_jcon_table/icn_22_bound J
    lload 191
    putstatic rung36_jcon_table/icn_22_e1cur J
    lload 193
    putstatic rung36_jcon_table/icn_22_e1val J
    lload 195
    putstatic rung36_jcon_table/icn_22_e2val J
    lload 197
    putstatic rung36_jcon_table/icn_38_tsa_vl J
    lload 199
    putstatic rung36_jcon_table/icn_48_alt_val J
    lload 201
    putstatic rung36_jcon_table/icn_56_alt_val J
    lload 203
    putstatic rung36_jcon_table/icn_62_alt_val J
    lload 205
    putstatic rung36_jcon_table/icn_69_alt_val J
    lload 207
    putstatic rung36_jcon_table/icn_76_alt_val J
    lload 209
    putstatic rung36_jcon_table/icn_86_alt_val J
    lload 211
    putstatic rung36_jcon_table/icn_93_alt_val J
    lload 213
    putstatic rung36_jcon_table/icn_100_alt_val J
    lload 215
    putstatic rung36_jcon_table/icn_104_alt_val J
    lload 217
    putstatic rung36_jcon_table/icn_112_ts_kval J
    lload 219
    putstatic rung36_jcon_table/icn_121_alt_val J
    lload 221
    putstatic rung36_jcon_table/icn_129_alt_val J
    lload 223
    putstatic rung36_jcon_table/icn_135_alt_val J
    lload 225
    putstatic rung36_jcon_table/icn_147_alt_val J
    lload 227
    putstatic rung36_jcon_table/icn_154_alt_val J
    lload 229
    putstatic rung36_jcon_table/icn_164_alt_val J
    lload 231
    putstatic rung36_jcon_table/icn_171_alt_val J
    lload 233
    putstatic rung36_jcon_table/icn_178_alt_val J
    lload 235
    putstatic rung36_jcon_table/icn_182_alt_val J
    lload 237
    putstatic rung36_jcon_table/icn_196_ts_kval J
    lload 239
    putstatic rung36_jcon_table/icn_192_alt_val J
    lload 241
    putstatic rung36_jcon_table/icn_203_ts_kval J
    lload 243
    putstatic rung36_jcon_table/icn_199_alt_val J
    lload 245
    putstatic rung36_jcon_table/icn_210_tsa_vl J
    lload 247
    putstatic rung36_jcon_table/icn_220_tsa_vl J
    getstatic rung36_jcon_table/icn_failed B
    ifne icn_224_after_call
    getstatic rung36_jcon_table/icn_retval J
    goto icn_main_s11_sdrain
icn_224_after_call:
    goto icn_219_α
icn_main_s11_sdrain:
    pop2
    goto icn_219_α
;  INT
icn_229_α:
    ldc2_w 88
    goto icn_228_store
icn_229_β:
    goto icn_224_α
icn_228_α:
    goto icn_229_α
icn_228_β:
    goto icn_229_β
icn_228_store:
    pop2
    lconst_0
    goto icn_227_gdrain
icn_227_gdrain:
    pop2
icn_227_pump:
    goto icn_228_β
icn_227_α:
    goto icn_228_α
icn_227_β:
    goto icn_224_α
;  VAR
icn_231_α:
    getstatic rung36_jcon_table/icn_pv_main_x Ljava/util/HashMap;
    goto icn_230_arg1
icn_231_β:
    goto icn_227_α
icn_230_arg1:
    putstatic rung36_jcon_table/icn_arg_1 J
    goto icn_230_docall
;  STR
icn_232_α:
    ldc "+2+4+a"
    goto icn_230_arg0
icn_232_β:
    goto icn_227_α
icn_230_arg0:
    putstatic rung36_jcon_table/icn_arg_str_0 Ljava/lang/String;
    lconst_0
    putstatic rung36_jcon_table/icn_arg_0 J
    goto icn_231_α
icn_230_α:
    goto icn_232_α
icn_230_β:
    goto icn_231_β
icn_230_docall:
    getstatic rung36_jcon_table/icn_pv_main_y J
    lstore 177
    getstatic rung36_jcon_table/icn_16_tsa_vl J
    lstore 179
    getstatic rung36_jcon_table/icn_17_binop_lc J
    lstore 181
    getstatic rung36_jcon_table/icn_17_binop_rc J
    lstore 183
    getstatic rung36_jcon_table/icn_pv_main_k J
    lstore 185
    getstatic rung36_jcon_table/icn_22_I J
    lstore 187
    getstatic rung36_jcon_table/icn_22_bound J
    lstore 189
    getstatic rung36_jcon_table/icn_22_e1cur J
    lstore 191
    getstatic rung36_jcon_table/icn_22_e1val J
    lstore 193
    getstatic rung36_jcon_table/icn_22_e2val J
    lstore 195
    getstatic rung36_jcon_table/icn_38_tsa_vl J
    lstore 197
    getstatic rung36_jcon_table/icn_48_alt_val J
    lstore 199
    getstatic rung36_jcon_table/icn_56_alt_val J
    lstore 201
    getstatic rung36_jcon_table/icn_62_alt_val J
    lstore 203
    getstatic rung36_jcon_table/icn_69_alt_val J
    lstore 205
    getstatic rung36_jcon_table/icn_76_alt_val J
    lstore 207
    getstatic rung36_jcon_table/icn_86_alt_val J
    lstore 209
    getstatic rung36_jcon_table/icn_93_alt_val J
    lstore 211
    getstatic rung36_jcon_table/icn_100_alt_val J
    lstore 213
    getstatic rung36_jcon_table/icn_104_alt_val J
    lstore 215
    getstatic rung36_jcon_table/icn_112_ts_kval J
    lstore 217
    getstatic rung36_jcon_table/icn_121_alt_val J
    lstore 219
    getstatic rung36_jcon_table/icn_129_alt_val J
    lstore 221
    getstatic rung36_jcon_table/icn_135_alt_val J
    lstore 223
    getstatic rung36_jcon_table/icn_147_alt_val J
    lstore 225
    getstatic rung36_jcon_table/icn_154_alt_val J
    lstore 227
    getstatic rung36_jcon_table/icn_164_alt_val J
    lstore 229
    getstatic rung36_jcon_table/icn_171_alt_val J
    lstore 231
    getstatic rung36_jcon_table/icn_178_alt_val J
    lstore 233
    getstatic rung36_jcon_table/icn_182_alt_val J
    lstore 235
    getstatic rung36_jcon_table/icn_196_ts_kval J
    lstore 237
    getstatic rung36_jcon_table/icn_192_alt_val J
    lstore 239
    getstatic rung36_jcon_table/icn_203_ts_kval J
    lstore 241
    getstatic rung36_jcon_table/icn_199_alt_val J
    lstore 243
    getstatic rung36_jcon_table/icn_210_tsa_vl J
    lstore 245
    getstatic rung36_jcon_table/icn_220_tsa_vl J
    lstore 247
    invokestatic rung36_jcon_table/icn_tdump()V
    lload 177
    putstatic rung36_jcon_table/icn_pv_main_y J
    lload 179
    putstatic rung36_jcon_table/icn_16_tsa_vl J
    lload 181
    putstatic rung36_jcon_table/icn_17_binop_lc J
    lload 183
    putstatic rung36_jcon_table/icn_17_binop_rc J
    lload 185
    putstatic rung36_jcon_table/icn_pv_main_k J
    lload 187
    putstatic rung36_jcon_table/icn_22_I J
    lload 189
    putstatic rung36_jcon_table/icn_22_bound J
    lload 191
    putstatic rung36_jcon_table/icn_22_e1cur J
    lload 193
    putstatic rung36_jcon_table/icn_22_e1val J
    lload 195
    putstatic rung36_jcon_table/icn_22_e2val J
    lload 197
    putstatic rung36_jcon_table/icn_38_tsa_vl J
    lload 199
    putstatic rung36_jcon_table/icn_48_alt_val J
    lload 201
    putstatic rung36_jcon_table/icn_56_alt_val J
    lload 203
    putstatic rung36_jcon_table/icn_62_alt_val J
    lload 205
    putstatic rung36_jcon_table/icn_69_alt_val J
    lload 207
    putstatic rung36_jcon_table/icn_76_alt_val J
    lload 209
    putstatic rung36_jcon_table/icn_86_alt_val J
    lload 211
    putstatic rung36_jcon_table/icn_93_alt_val J
    lload 213
    putstatic rung36_jcon_table/icn_100_alt_val J
    lload 215
    putstatic rung36_jcon_table/icn_104_alt_val J
    lload 217
    putstatic rung36_jcon_table/icn_112_ts_kval J
    lload 219
    putstatic rung36_jcon_table/icn_121_alt_val J
    lload 221
    putstatic rung36_jcon_table/icn_129_alt_val J
    lload 223
    putstatic rung36_jcon_table/icn_135_alt_val J
    lload 225
    putstatic rung36_jcon_table/icn_147_alt_val J
    lload 227
    putstatic rung36_jcon_table/icn_154_alt_val J
    lload 229
    putstatic rung36_jcon_table/icn_164_alt_val J
    lload 231
    putstatic rung36_jcon_table/icn_171_alt_val J
    lload 233
    putstatic rung36_jcon_table/icn_178_alt_val J
    lload 235
    putstatic rung36_jcon_table/icn_182_alt_val J
    lload 237
    putstatic rung36_jcon_table/icn_196_ts_kval J
    lload 239
    putstatic rung36_jcon_table/icn_192_alt_val J
    lload 241
    putstatic rung36_jcon_table/icn_203_ts_kval J
    lload 243
    putstatic rung36_jcon_table/icn_199_alt_val J
    lload 245
    putstatic rung36_jcon_table/icn_210_tsa_vl J
    lload 247
    putstatic rung36_jcon_table/icn_220_tsa_vl J
    getstatic rung36_jcon_table/icn_failed B
    ifne icn_230_after_call
    getstatic rung36_jcon_table/icn_retval J
    goto icn_main_s9_sdrain
icn_230_after_call:
    goto icn_227_α
icn_main_s9_sdrain:
    pop2
    goto icn_227_α
;  STR
icn_234_α:
    ldc "A"
    goto icn_233_tsa_vr
icn_234_β:
    goto icn_230_α
;  STR
icn_235_α:
    ldc "a"
    goto icn_233_tsa_kr
icn_235_β:
    goto icn_230_α
icn_233_α:
    goto icn_234_α
icn_233_β:
    goto icn_230_α
icn_233_tsa_vr:
    dup
    putstatic rung36_jcon_table/icn_233_tsa_vl Ljava/lang/String;
    goto icn_235_α
icn_233_tsa_kr:
    putstatic rung36_jcon_table/icn_233_tsa_ks Ljava/lang/String;
    goto icn_233_tsa_put
icn_233_tsa_put:
    getstatic rung36_jcon_table/icn_pv_main_x Ljava/util/HashMap;
    getstatic rung36_jcon_table/icn_233_tsa_ks Ljava/lang/String;
    getstatic rung36_jcon_table/icn_233_tsa_vl Ljava/lang/String;
    invokevirtual java/util/HashMap/put(Ljava/lang/Object;Ljava/lang/Object;)Ljava/lang/Object;
    pop
    getstatic rung36_jcon_table/icn_233_tsa_vl Ljava/lang/String;
    goto icn_main_s8_sdrain
icn_main_s8_sdrain:
    pop
    goto icn_230_α
;  INT
icn_237_α:
    ldc2_w 7
    goto icn_236_tsa_vr
icn_237_β:
    goto icn_233_α
;  INT
icn_238_α:
    ldc2_w 4
    goto icn_236_tsa_kr
icn_238_β:
    goto icn_233_α
icn_236_α:
    goto icn_237_α
icn_236_β:
    goto icn_233_α
icn_236_tsa_vr:
    dup2
    putstatic rung36_jcon_table/icn_236_tsa_vl J
    invokestatic java/lang/Long/valueOf(J)Ljava/lang/Long;
    putstatic rung36_jcon_table/icn_236_tsa_vo Ljava/lang/Object;
    goto icn_238_α
icn_236_tsa_kr:
    invokestatic java/lang/Long/toString(J)Ljava/lang/String;
    putstatic rung36_jcon_table/icn_236_tsa_ks Ljava/lang/String;
    goto icn_236_tsa_put
icn_236_tsa_put:
    getstatic rung36_jcon_table/icn_pv_main_x Ljava/util/HashMap;
    getstatic rung36_jcon_table/icn_236_tsa_ks Ljava/lang/String;
    getstatic rung36_jcon_table/icn_236_tsa_vo Ljava/lang/Object;
    invokevirtual java/util/HashMap/put(Ljava/lang/Object;Ljava/lang/Object;)Ljava/lang/Object;
    pop
    getstatic rung36_jcon_table/icn_236_tsa_vl J
    goto icn_main_s7_sdrain
icn_main_s7_sdrain:
    pop2
    goto icn_233_α
icn_240_α:
    goto icn_236_α
icn_240_β:
    goto icn_236_α
icn_239_gdrain:
    pop2
icn_239_pump:
    goto icn_240_β
icn_239_α:
    goto icn_240_α
icn_239_β:
    goto icn_236_α
;  INT
icn_242_α:
    ldc2_w 3
    goto icn_241_tsa_vr
icn_242_β:
    goto icn_239_α
;  INT
icn_243_α:
    ldc2_w 2
    goto icn_241_tsa_kr
icn_243_β:
    goto icn_239_α
icn_241_α:
    goto icn_242_α
icn_241_β:
    goto icn_239_α
icn_241_tsa_vr:
    dup2
    putstatic rung36_jcon_table/icn_241_tsa_vl J
    invokestatic java/lang/Long/valueOf(J)Ljava/lang/Long;
    putstatic rung36_jcon_table/icn_241_tsa_vo Ljava/lang/Object;
    goto icn_243_α
icn_241_tsa_kr:
    invokestatic java/lang/Long/toString(J)Ljava/lang/String;
    putstatic rung36_jcon_table/icn_241_tsa_ks Ljava/lang/String;
    goto icn_241_tsa_put
icn_241_tsa_put:
    getstatic rung36_jcon_table/icn_pv_main_x Ljava/util/HashMap;
    getstatic rung36_jcon_table/icn_241_tsa_ks Ljava/lang/String;
    getstatic rung36_jcon_table/icn_241_tsa_vo Ljava/lang/Object;
    invokevirtual java/util/HashMap/put(Ljava/lang/Object;Ljava/lang/Object;)Ljava/lang/Object;
    pop
    getstatic rung36_jcon_table/icn_241_tsa_vl J
    goto icn_main_s5_sdrain
icn_main_s5_sdrain:
    pop2
    goto icn_239_α
icn_245_α:
    goto icn_241_α
icn_245_β:
    goto icn_241_α
icn_244_gdrain:
    pop2
icn_244_pump:
    goto icn_245_β
icn_244_α:
    goto icn_245_α
icn_244_β:
    goto icn_241_α
icn_246_α:
    goto icn_244_α
icn_246_β:
    goto icn_244_α
icn_main_s3_sdrain:
    pop2
    goto icn_244_α
;  VAR
icn_248_α:
    getstatic rung36_jcon_table/icn_pv_main_x Ljava/util/HashMap;
    goto icn_247_arg1
icn_248_β:
    goto icn_246_α
icn_247_arg1:
    putstatic rung36_jcon_table/icn_arg_1 J
    goto icn_247_docall
;  STR
icn_249_α:
    ldc "initial"
    goto icn_247_arg0
icn_249_β:
    goto icn_246_α
icn_247_arg0:
    putstatic rung36_jcon_table/icn_arg_str_0 Ljava/lang/String;
    lconst_0
    putstatic rung36_jcon_table/icn_arg_0 J
    goto icn_248_α
icn_247_α:
    goto icn_249_α
icn_247_β:
    goto icn_248_β
icn_247_docall:
    getstatic rung36_jcon_table/icn_pv_main_y J
    lstore 177
    getstatic rung36_jcon_table/icn_16_tsa_vl J
    lstore 179
    getstatic rung36_jcon_table/icn_17_binop_lc J
    lstore 181
    getstatic rung36_jcon_table/icn_17_binop_rc J
    lstore 183
    getstatic rung36_jcon_table/icn_pv_main_k J
    lstore 185
    getstatic rung36_jcon_table/icn_22_I J
    lstore 187
    getstatic rung36_jcon_table/icn_22_bound J
    lstore 189
    getstatic rung36_jcon_table/icn_22_e1cur J
    lstore 191
    getstatic rung36_jcon_table/icn_22_e1val J
    lstore 193
    getstatic rung36_jcon_table/icn_22_e2val J
    lstore 195
    getstatic rung36_jcon_table/icn_38_tsa_vl J
    lstore 197
    getstatic rung36_jcon_table/icn_48_alt_val J
    lstore 199
    getstatic rung36_jcon_table/icn_56_alt_val J
    lstore 201
    getstatic rung36_jcon_table/icn_62_alt_val J
    lstore 203
    getstatic rung36_jcon_table/icn_69_alt_val J
    lstore 205
    getstatic rung36_jcon_table/icn_76_alt_val J
    lstore 207
    getstatic rung36_jcon_table/icn_86_alt_val J
    lstore 209
    getstatic rung36_jcon_table/icn_93_alt_val J
    lstore 211
    getstatic rung36_jcon_table/icn_100_alt_val J
    lstore 213
    getstatic rung36_jcon_table/icn_104_alt_val J
    lstore 215
    getstatic rung36_jcon_table/icn_112_ts_kval J
    lstore 217
    getstatic rung36_jcon_table/icn_121_alt_val J
    lstore 219
    getstatic rung36_jcon_table/icn_129_alt_val J
    lstore 221
    getstatic rung36_jcon_table/icn_135_alt_val J
    lstore 223
    getstatic rung36_jcon_table/icn_147_alt_val J
    lstore 225
    getstatic rung36_jcon_table/icn_154_alt_val J
    lstore 227
    getstatic rung36_jcon_table/icn_164_alt_val J
    lstore 229
    getstatic rung36_jcon_table/icn_171_alt_val J
    lstore 231
    getstatic rung36_jcon_table/icn_178_alt_val J
    lstore 233
    getstatic rung36_jcon_table/icn_182_alt_val J
    lstore 235
    getstatic rung36_jcon_table/icn_196_ts_kval J
    lstore 237
    getstatic rung36_jcon_table/icn_192_alt_val J
    lstore 239
    getstatic rung36_jcon_table/icn_203_ts_kval J
    lstore 241
    getstatic rung36_jcon_table/icn_199_alt_val J
    lstore 243
    getstatic rung36_jcon_table/icn_210_tsa_vl J
    lstore 245
    getstatic rung36_jcon_table/icn_220_tsa_vl J
    lstore 247
    getstatic rung36_jcon_table/icn_236_tsa_vl J
    lstore 249
    getstatic rung36_jcon_table/icn_241_tsa_vl J
    lstore 251
    invokestatic rung36_jcon_table/icn_tdump()V
    lload 177
    putstatic rung36_jcon_table/icn_pv_main_y J
    lload 179
    putstatic rung36_jcon_table/icn_16_tsa_vl J
    lload 181
    putstatic rung36_jcon_table/icn_17_binop_lc J
    lload 183
    putstatic rung36_jcon_table/icn_17_binop_rc J
    lload 185
    putstatic rung36_jcon_table/icn_pv_main_k J
    lload 187
    putstatic rung36_jcon_table/icn_22_I J
    lload 189
    putstatic rung36_jcon_table/icn_22_bound J
    lload 191
    putstatic rung36_jcon_table/icn_22_e1cur J
    lload 193
    putstatic rung36_jcon_table/icn_22_e1val J
    lload 195
    putstatic rung36_jcon_table/icn_22_e2val J
    lload 197
    putstatic rung36_jcon_table/icn_38_tsa_vl J
    lload 199
    putstatic rung36_jcon_table/icn_48_alt_val J
    lload 201
    putstatic rung36_jcon_table/icn_56_alt_val J
    lload 203
    putstatic rung36_jcon_table/icn_62_alt_val J
    lload 205
    putstatic rung36_jcon_table/icn_69_alt_val J
    lload 207
    putstatic rung36_jcon_table/icn_76_alt_val J
    lload 209
    putstatic rung36_jcon_table/icn_86_alt_val J
    lload 211
    putstatic rung36_jcon_table/icn_93_alt_val J
    lload 213
    putstatic rung36_jcon_table/icn_100_alt_val J
    lload 215
    putstatic rung36_jcon_table/icn_104_alt_val J
    lload 217
    putstatic rung36_jcon_table/icn_112_ts_kval J
    lload 219
    putstatic rung36_jcon_table/icn_121_alt_val J
    lload 221
    putstatic rung36_jcon_table/icn_129_alt_val J
    lload 223
    putstatic rung36_jcon_table/icn_135_alt_val J
    lload 225
    putstatic rung36_jcon_table/icn_147_alt_val J
    lload 227
    putstatic rung36_jcon_table/icn_154_alt_val J
    lload 229
    putstatic rung36_jcon_table/icn_164_alt_val J
    lload 231
    putstatic rung36_jcon_table/icn_171_alt_val J
    lload 233
    putstatic rung36_jcon_table/icn_178_alt_val J
    lload 235
    putstatic rung36_jcon_table/icn_182_alt_val J
    lload 237
    putstatic rung36_jcon_table/icn_196_ts_kval J
    lload 239
    putstatic rung36_jcon_table/icn_192_alt_val J
    lload 241
    putstatic rung36_jcon_table/icn_203_ts_kval J
    lload 243
    putstatic rung36_jcon_table/icn_199_alt_val J
    lload 245
    putstatic rung36_jcon_table/icn_210_tsa_vl J
    lload 247
    putstatic rung36_jcon_table/icn_220_tsa_vl J
    lload 249
    putstatic rung36_jcon_table/icn_236_tsa_vl J
    lload 251
    putstatic rung36_jcon_table/icn_241_tsa_vl J
    getstatic rung36_jcon_table/icn_failed B
    ifne icn_247_after_call
    getstatic rung36_jcon_table/icn_retval J
    goto icn_main_s2_sdrain
icn_247_after_call:
    goto icn_246_α
icn_main_s2_sdrain:
    pop2
    goto icn_246_α
icn_251_α:
    goto icn_247_α
icn_251_β:
    goto icn_247_α
icn_250_α:
    goto icn_251_α
icn_250_β:
    goto icn_251_β
icn_250_store:
    putstatic rung36_jcon_table/icn_pv_main_x Ljava/util/HashMap;
    getstatic rung36_jcon_table/icn_pv_main_x Ljava/util/HashMap;
    goto icn_main_s1_sdrain
icn_main_s1_sdrain:
    pop
    goto icn_247_α
icn_main_done:
    return
.end method

.method public static icn_tdump()V
    .limit stack 16
    .limit locals 510
    lconst_0
    lstore 0
    lconst_0
    lstore 2
    lconst_0
    lstore 4
    lconst_0
    lstore 6
    lconst_0
    lstore 8
    lconst_0
    lstore 10
    lconst_0
    lstore 12
    lconst_0
    lstore 14
    lconst_0
    lstore 16
    lconst_0
    lstore 18
    lconst_0
    lstore 20
    lconst_0
    lstore 22
    lconst_0
    lstore 24
    lconst_0
    lstore 26
    lconst_0
    lstore 28
    lconst_0
    lstore 30
    lconst_0
    lstore 32
    lconst_0
    lstore 34
    lconst_0
    lstore 36
    lconst_0
    lstore 38
    lconst_0
    lstore 40
    lconst_0
    lstore 42
    lconst_0
    lstore 44
    lconst_0
    lstore 46
    lconst_0
    lstore 48
    lconst_0
    lstore 50
    lconst_0
    lstore 52
    lconst_0
    lstore 54
    lconst_0
    lstore 56
    lconst_0
    lstore 58
    lconst_0
    lstore 60
    lconst_0
    lstore 62
    iconst_0
    istore 84
    iconst_0
    istore 85
    iconst_0
    istore 86
    iconst_0
    istore 87
    aconst_null
    astore 148
    aconst_null
    astore 149
    aconst_null
    astore 150
    aconst_null
    astore 151
    getstatic rung36_jcon_table/icn_arg_str_0 Ljava/lang/String;
    putstatic rung36_jcon_table/icn_pv_tdump_label Ljava/lang/String;
    getstatic rung36_jcon_table/icn_arg_1 J
    putstatic rung36_jcon_table/icn_pv_tdump_T J
    goto icn_280_α
icn_252_α:
    lconst_0
    putstatic rung36_jcon_table/icn_retval J
    iconst_0
    putstatic rung36_jcon_table/icn_failed B
    goto icn_tdump_ret
icn_252_β:
    goto icn_tdump_ret
icn_253_α:
    getstatic java/lang/System/out Ljava/io/PrintStream;
    ldc ""
    invokevirtual java/io/PrintStream/println(Ljava/lang/String;)V
    goto icn_tdump_s3_sdrain
icn_253_β:
    goto icn_252_α
icn_tdump_s3_sdrain:
    pop2
    goto icn_252_α
icn_257_α:
    goto icn_256_seq_rf_0
icn_257_β:
    goto icn_256_seq_rf_0
icn_259_α:
    goto icn_254_pump
icn_259_β:
    goto icn_254_pump
;  VAR
icn_261_α:
    getstatic rung36_jcon_table/icn_pv_tdump_T J
    goto icn_260_mtr
icn_261_β:
    goto icn_259_α
;  VAR
icn_262_α:
    getstatic rung36_jcon_table/icn_pv_tdump_x J
    goto icn_260_mkr
icn_262_β:
    goto icn_259_α
icn_260_α:
    goto icn_261_α
icn_260_β:
    goto icn_259_α
icn_260_mtr:
    putstatic rung36_jcon_table/icn_260_mtbl Ljava/util/HashMap;
    goto icn_262_α
icn_260_mkr:
    dup2
    putstatic rung36_jcon_table/icn_260_mkeyv J
    invokestatic java/lang/Long/toString(J)Ljava/lang/String;
    putstatic rung36_jcon_table/icn_260_mkey Ljava/lang/String;
    getstatic rung36_jcon_table/icn_260_mtbl Ljava/util/HashMap;
    getstatic rung36_jcon_table/icn_260_mkey Ljava/lang/String;
    invokevirtual java/util/HashMap/containsKey(Ljava/lang/Object;)Z
    ifeq icn_259_α
    getstatic rung36_jcon_table/icn_260_mkeyv J
    goto icn_258_alt_g0
icn_258_alt_g0:
    putstatic rung36_jcon_table/icn_258_alt_val J
    sipush 1
    putstatic rung36_jcon_table/icn_258_alt_gate I
    getstatic rung36_jcon_table/icn_258_alt_val J
    goto icn_254_bdrain
icn_258_alt_g1:
    putstatic rung36_jcon_table/icn_258_alt_val J
    sipush 2
    putstatic rung36_jcon_table/icn_258_alt_gate I
    getstatic rung36_jcon_table/icn_258_alt_val J
    goto icn_254_bdrain
icn_258_α:
    iconst_0
    putstatic rung36_jcon_table/icn_258_alt_gate I
    goto icn_260_α
icn_258_β:
    getstatic rung36_jcon_table/icn_258_alt_gate I
    tableswitch 1 2
        icn_260_β
        icn_259_β
        default: icn_254_pump
    goto icn_256_α
icn_256_seq_rg_0:
    pop2
    goto icn_258_α
icn_256_seq_rf_0:
    goto icn_258_α
icn_256_α:
    goto icn_257_α
icn_256_β:
    goto icn_258_β
;  VAR
icn_265_α:
    getstatic rung36_jcon_table/icn_pv_tdump_T J
    goto icn_264_mtr
icn_265_β:
    goto icn_254_pump
;  VAR
icn_266_α:
    getstatic rung36_jcon_table/icn_pv_tdump_x J
    goto icn_264_mkr
icn_266_β:
    goto icn_254_pump
icn_264_α:
    goto icn_265_α
icn_264_β:
    goto icn_254_pump
icn_264_mtr:
    putstatic rung36_jcon_table/icn_264_mtbl Ljava/util/HashMap;
    goto icn_266_α
icn_264_mkr:
    dup2
    putstatic rung36_jcon_table/icn_264_mkeyv J
    invokestatic java/lang/Long/toString(J)Ljava/lang/String;
    putstatic rung36_jcon_table/icn_264_mkey Ljava/lang/String;
    getstatic rung36_jcon_table/icn_264_mtbl Ljava/util/HashMap;
    getstatic rung36_jcon_table/icn_264_mkey Ljava/lang/String;
    invokevirtual java/util/HashMap/containsKey(Ljava/lang/Object;)Z
    ifeq icn_254_pump
    getstatic rung36_jcon_table/icn_264_mkeyv J
    goto icn_263_and_rg_0
icn_267_α:
    goto icn_264_β
icn_267_β:
    goto icn_264_β
    goto icn_263_α
icn_263_and_rg_0:
    putstatic rung36_jcon_table/icn_263_and_drain_0 J
    goto icn_267_α
icn_263_α:
    goto icn_264_α
icn_263_β:
    goto icn_267_β
;  VAR
icn_270_α:
    getstatic rung36_jcon_table/icn_pv_tdump_T J
    goto icn_269_ktr
icn_270_β:
    goto icn_255_else
icn_269_α:
    getstatic rung36_jcon_table/icn_269_kinit I
    ifne icn_269_kchk
    goto icn_270_α
icn_269_ktr:
    putstatic rung36_jcon_table/icn_269_ktbl Ljava/util/HashMap;
    getstatic rung36_jcon_table/icn_269_ktbl Ljava/util/HashMap;
    invokevirtual java/util/HashMap/keySet()Ljava/util/Set;
    invokeinterface java/util/Set/toArray()[Ljava/lang/Object; 1
    putstatic rung36_jcon_table/icn_269_karr [Ljava/lang/Object;
    iconst_0
    putstatic rung36_jcon_table/icn_269_kidx I
    iconst_1
    putstatic rung36_jcon_table/icn_269_kinit I
    goto icn_269_kchk
icn_269_β:
    getstatic rung36_jcon_table/icn_269_kidx I
    iconst_1
    iadd
    putstatic rung36_jcon_table/icn_269_kidx I
icn_269_kchk:
    getstatic rung36_jcon_table/icn_269_karr [Ljava/lang/Object;
    checkcast [Ljava/lang/Object;
    arraylength
    getstatic rung36_jcon_table/icn_269_kidx I
    if_icmple icn_255_else
    getstatic rung36_jcon_table/icn_269_karr [Ljava/lang/Object;
    checkcast [Ljava/lang/Object;
    getstatic rung36_jcon_table/icn_269_kidx I
    aaload
    checkcast java/lang/String
    invokestatic java/lang/Long/parseLong(Ljava/lang/String;)J
    goto icn_268_id_rr
;  VAR
icn_271_α:
    getstatic rung36_jcon_table/icn_pv_tdump_x J
    goto icn_268_id_lr
icn_271_β:
    goto icn_255_else
icn_268_id_lr:
    putstatic rung36_jcon_table/icn_268_id_lc J
icn_268_id_rr:
    putstatic rung36_jcon_table/icn_268_id_rc J
icn_268_α:
    goto icn_271_α
icn_268_id_chk:
    getstatic rung36_jcon_table/icn_268_id_lc J
    getstatic rung36_jcon_table/icn_268_id_rc J
    lcmp
    ifne icn_255_else
    getstatic rung36_jcon_table/icn_268_id_lc J
    goto icn_255_then
icn_268_β:
    goto icn_255_else
icn_255_then:
    pop2
    goto icn_256_α
icn_255_else:
    goto icn_263_α
icn_255_α:
    goto icn_268_α
icn_255_β:
    goto icn_268_β
;  STR
icn_275_α:
    ldc "abcde"
    goto icn_274_bang_adv
icn_275_β:
    goto icn_253_α
icn_274_α:
    goto icn_275_α
icn_274_β:
    goto icn_274_bang_chk
icn_274_bang_adv:
    putstatic rung36_jcon_table/icn_274_bang_str Ljava/lang/String;
    iconst_0
    putstatic rung36_jcon_table/icn_274_bang_pos I
icn_274_bang_chk:
    getstatic rung36_jcon_table/icn_274_bang_str Ljava/lang/String;
    invokevirtual java/lang/String/length()I
    getstatic rung36_jcon_table/icn_274_bang_pos I
    if_icmple icn_253_α
    getstatic rung36_jcon_table/icn_274_bang_str Ljava/lang/String;
    getstatic rung36_jcon_table/icn_274_bang_pos I
    getstatic rung36_jcon_table/icn_274_bang_pos I
    iconst_1
    iadd
    invokevirtual java/lang/String/substring(II)Ljava/lang/String;
    getstatic rung36_jcon_table/icn_274_bang_pos I
    iconst_1
    iadd
    putstatic rung36_jcon_table/icn_274_bang_pos I
    goto icn_273_alt_g2
;  INT
icn_277_α:
    ldc2_w 9
    goto icn_276_e2relay
icn_277_β:
    goto icn_276_e1b
;  INT
icn_278_α:
    ldc2_w 0
    goto icn_276_e1relay
icn_278_β:
    goto icn_274_α
icn_276_e1relay:
    putstatic rung36_jcon_table/icn_276_e1val J
    goto icn_277_α
icn_276_e2relay:
    putstatic rung36_jcon_table/icn_276_e2val J
    goto icn_276_init
icn_276_e1b:
    iconst_0
    putstatic rung36_jcon_table/icn_276_e2seen I
    goto icn_278_β
icn_276_e2b:
    goto icn_277_β
icn_276_α:
    iconst_0
    putstatic rung36_jcon_table/icn_276_e2seen I
    goto icn_278_α
icn_276_β:
    getstatic rung36_jcon_table/icn_276_I J
    lconst_1
    ladd
    putstatic rung36_jcon_table/icn_276_I J
    goto icn_276_code
icn_276_init:
    getstatic rung36_jcon_table/icn_276_e2val J
    putstatic rung36_jcon_table/icn_276_bound J
    getstatic rung36_jcon_table/icn_276_e2seen I
    ifne icn_276_init_e2adv
    getstatic rung36_jcon_table/icn_276_e1val J
    putstatic rung36_jcon_table/icn_276_e1cur J
    getstatic rung36_jcon_table/icn_276_e1cur J
    putstatic rung36_jcon_table/icn_276_I J
    iconst_1
    putstatic rung36_jcon_table/icn_276_e2seen I
    goto icn_276_code
icn_276_init_e2adv:
    getstatic rung36_jcon_table/icn_276_e1cur J
    putstatic rung36_jcon_table/icn_276_I J
    goto icn_276_code
icn_276_code:
    getstatic rung36_jcon_table/icn_276_I J
    getstatic rung36_jcon_table/icn_276_bound J
    lcmp
    ifgt icn_276_e2b
    getstatic rung36_jcon_table/icn_276_I J
    goto icn_273_alt_g1
;  VAR
icn_279_α:
    lconst_0
    goto icn_273_alt_g0
icn_279_β:
    goto icn_276_α
icn_273_alt_g0:
    putstatic rung36_jcon_table/icn_273_alt_val J
    sipush 1
    putstatic rung36_jcon_table/icn_273_alt_gate I
    getstatic rung36_jcon_table/icn_273_alt_val J
    goto icn_272_store
icn_273_alt_g1:
    putstatic rung36_jcon_table/icn_273_alt_val J
    sipush 2
    putstatic rung36_jcon_table/icn_273_alt_gate I
    getstatic rung36_jcon_table/icn_273_alt_val J
    goto icn_272_store
icn_273_alt_g2:
    pop
    lconst_0
    putstatic rung36_jcon_table/icn_273_alt_val J
    sipush 3
    putstatic rung36_jcon_table/icn_273_alt_gate I
    getstatic rung36_jcon_table/icn_273_alt_val J
    goto icn_272_store
icn_273_α:
    iconst_0
    putstatic rung36_jcon_table/icn_273_alt_gate I
    goto icn_279_α
icn_273_β:
    getstatic rung36_jcon_table/icn_273_alt_gate I
    tableswitch 1 3
        icn_279_β
        icn_276_β
        icn_274_β
        default: icn_253_α
icn_272_α:
    goto icn_273_α
icn_272_β:
    goto icn_273_β
icn_272_store:
    putstatic rung36_jcon_table/icn_pv_tdump_x J
    getstatic rung36_jcon_table/icn_pv_tdump_x J
    goto icn_254_gdrain
icn_254_gdrain:
    pop2
    goto icn_255_α
icn_254_bdrain:
    pop2
icn_254_pump:
    goto icn_272_β
icn_254_α:
    goto icn_272_α
icn_254_β:
    goto icn_253_α
icn_280_α:
    goto icn_254_α
icn_280_β:
    goto icn_254_α
icn_tdump_s1_sdrain:
    pop2
    goto icn_254_α
icn_tdump_done:
    iconst_0
    putstatic rung36_jcon_table/icn_suspended B
    iconst_0
    putstatic rung36_jcon_table/icn_suspend_id I
    iconst_1
    putstatic rung36_jcon_table/icn_failed B
    return
icn_tdump_ret:
    iconst_0
    putstatic rung36_jcon_table/icn_failed B
    return
icn_tdump_sret:
    return
.end method

